Workbook

Sheet Ficha
A1: FICHA DE COSTO DE PRODUCCIÓN
A2: Elige el molde y, si quieres, otra tela para cada pieza. Vacío = tela por defecto. Todo neto, sin IVA y sin gastos generales.
B3: Al cambiar de molde, borra las telas elegidas (columna azul) para volver a las de siempre.
B4: MOLDE ▶ | C4: 14 · FUTHOMU01PRO | F4: =IFERROR(INDEX(Moldes!$B$5:$B$154,MATCH($C$4,Moldes!$A$5:$A$154,0))&" · "&INDEX(Moldes!$C$5:$C$154,MATCH($C$4,Moldes!$A$5:$A$154,0))&" "&INDEX(Moldes!$D$5:$D$154,MATCH($C$4,Moldes!$A$5:$A$154,0)),"← elige un molde") -> Fútbol, pro, cuello redondo · Camiseta Masculino
B5: =IFERROR("Consumo: despiece + "&TEXT(IF(ISNUMBER(INDEX(Moldes!$K$5:$K$154,MATCH($C$4,Moldes!$A$5:$A$154,0))),INDEX(Moldes!$K$5:$K$154,MATCH($C$4,Moldes!$A$5:$A$154,0)),Precios!$Q$12),"0%")&IF(ISNUMBER(INDEX(Moldes!$K$5:$K$154,MATCH($C$4,Moldes!$A$5:$A$154,0)))," (ajuste por consumo real de este molde)"," (merma general)"),"") -> Consumo: despiece + 0% (merma general)
A7: # | B7: Pieza | C7: Cant. | D7: Metros por prenda | E7: TELA (elige) vacío = por defecto | F7: Tela usada | G7: $ por metro | H7: $ Tela | I7: $ Impresión | J7: TOTAL PIEZA | K7: Aviso
A8: =IF(B8="","",1) -> 1 | B8: =IFERROR(INDEX(Despiece!$B$5:$B$1004,MATCH($C$4&"|"&1,Despiece!$H$5:$H$1004,0)),"") -> Delantero | C8: =IF(B8="","",INDEX(Despiece!$C$5:$C$1004,MATCH($C$4&"|"&1,Despiece!$H$5:$H$1004,0))) -> 1 | D8: =IF(B8="","",IF(N(INDEX(Despiece!$D$5:$D$1004,MATCH($C$4&"|"&1,Despiece!$H$5:$H$1004,0)))>0,INDEX(Despiece!$D$5:$D$1004,MATCH($C$4&"|"&1,Despiece!$H$5:$H$1004,0))*(1+IFERROR(IF(ISNUMBER(INDEX(Moldes!$K$5:$K$154,MATCH($C$4,Moldes!$A$5:$A$154,0))),INDEX(Moldes!$K$5:$K$154,MATCH($C$4,Moldes!$A$5:$A$154,0)),Precios!$Q$12),Precios!$Q$12)),"")) | F8: =IF(B8="","",IF(E8<>"",E8,INDEX(Despiece!$E$5:$E$1004,MATCH($C$4&"|"&1,Despiece!$H$5:$H$1004,0))&"")) -> MONTESIMONE TRAINING (fut pro) | G8: =IF(OR(B8="",F8=""),"",IFERROR(INDEX(Precios!$F$5:$F$124,MATCH(F8,Precios!$A$5:$A$124,0))*1,"")) -> 695.607 | H8: =IF(AND(ISNUMBER(D8),ISNUMBER(G8)),D8*G8,"") | I8: =IF(OR(B8="",NOT(ISNUMBER(D8))),"",IF(INDEX(Despiece!$F$5:$F$1004,MATCH($C$4&"|"&1,Despiece!$H$5:$H$1004,0))="Sí",D8*Precios!$Q$10,0)) | J8: =IF(AND(ISNUMBER(H8),ISNUMBER(I8)),H8+I8,"") | K8: =IF(B8="","",IF(ISNUMBER(J8),IF(INDEX(Despiece!$F$5:$F$1004,MATCH($C$4&"|"&1,Despiece!$H$5:$H$1004,0))="Sí","Sublimada",""),IF(NOT(ISNUMBER(D8)),"Faltan metros (Despiece). ","")&IF(F8="","Elige tela. ",IF(NOT(ISNUMBER(G8)),"Falta precio o peso de 1 m (Precios). ","")))) -> Faltan metros (Despiece).
A9: =IF(B9="","",2) -> 2 | B9: =IFERROR(INDEX(Despiece!$B$5:$B$1004,MATCH($C$4&"|"&2,Despiece!$H$5:$H$1004,0)),"") -> Espalda | C9: =IF(B9="","",INDEX(Despiece!$C$5:$C$1004,MATCH($C$4&"|"&2,Despiece!$H$5:$H$1004,0))) -> 1 | D9: =IF(B9="","",IF(N(INDEX(Despiece!$D$5:$D$1004,MATCH($C$4&"|"&2,Despiece!$H$5:$H$1004,0)))>0,INDEX(Despiece!$D$5:$D$1004,MATCH($C$4&"|"&2,Despiece!$H$5:$H$1004,0))*(1+IFERROR(IF(ISNUMBER(INDEX(Moldes!$K$5:$K$154,MATCH($C$4,Moldes!$A$5:$A$154,0))),INDEX(Moldes!$K$5:$K$154,MATCH($C$4,Moldes!$A$5:$A$154,0)),Precios!$Q$12),Precios!$Q$12)),"")) | F9: =IF(B9="","",IF(E9<>"",E9,INDEX(Despiece!$E$5:$E$1004,MATCH($C$4&"|"&2,Despiece!$H$5:$H$1004,0))&"")) -> MONTESIMONE TRAINING (fut pro) | G9: =IF(OR(B9="",F9=""),"",IFERROR(INDEX(Precios!$F$5:$F$124,MATCH(F9,Precios!$A$5:$A$124,0))*1,"")) -> 695.607 | H9: =IF(AND(ISNUMBER(D9),ISNUMBER(G9)),D9*G9,"") | I9: =IF(OR(B9="",NOT(ISNUMBER(D9))),"",IF(INDEX(Despiece!$F$5:$F$1004,MATCH($C$4&"|"&2,Despiece!$H$5:$H$1004,0))="Sí",D9*Precios!$Q$10,0)) | J9: =IF(AND(ISNUMBER(H9),ISNUMBER(I9)),H9+I9,"") | K9: =IF(B9="","",IF(ISNUMBER(J9),IF(INDEX(Despiece!$F$5:$F$1004,MATCH($C$4&"|"&2,Despiece!$H$5:$H$1004,0))="Sí","Sublimada",""),IF(NOT(ISNUMBER(D9)),"Faltan metros (Despiece). ","")&IF(F9="","Elige tela. ",IF(NOT(ISNUMBER(G9)),"Falta precio o peso de 1 m (Precios). ","")))) -> Faltan metros (Despiece).
A10: =IF(B10="","",3) -> 3 | B10: =IFERROR(INDEX(Despiece!$B$5:$B$1004,MATCH($C$4&"|"&3,Despiece!$H$5:$H$1004,0)),"") -> Manga | C10: =IF(B10="","",INDEX(Despiece!$C$5:$C$1004,MATCH($C$4&"|"&3,Despiece!$H$5:$H$1004,0))) -> 2 | D10: =IF(B10="","",IF(N(INDEX(Despiece!$D$5:$D$1004,MATCH($C$4&"|"&3,Despiece!$H$5:$H$1004,0)))>0,INDEX(Despiece!$D$5:$D$1004,MATCH($C$4&"|"&3,Despiece!$H$5:$H$1004,0))*(1+IFERROR(IF(ISNUMBER(INDEX(Moldes!$K$5:$K$154,MATCH($C$4,Moldes!$A$5:$A$154,0))),INDEX(Moldes!$K$5:$K$154,MATCH($C$4,Moldes!$A$5:$A$154,0)),Precios!$Q$12),Precios!$Q$12)),"")) | F10: =IF(B10="","",IF(E10<>"",E10,INDEX(Despiece!$E$5:$E$1004,MATCH($C$4&"|"&3,Despiece!$H$5:$H$1004,0))&"")) -> MONTESIMONE TRAINING (fut pro) | G10: =IF(OR(B10="",F10=""),"",IFERROR(INDEX(Precios!$F$5:$F$124,MATCH(F10,Precios!$A$5:$A$124,0))*1,"")) -> 695.607 | H10: =IF(AND(ISNUMBER(D10),ISNUMBER(G10)),D10*G10,"") | I10: =IF(OR(B10="",NOT(ISNUMBER(D10))),"",IF(INDEX(Despiece!$F$5:$F$1004,MATCH($C$4&"|"&3,Despiece!$H$5:$H$1004,0))="Sí",D10*Precios!$Q$10,0)) | J10: =IF(AND(ISNUMBER(H10),ISNUMBER(I10)),H10+I10,"") | K10: =IF(B10="","",IF(ISNUMBER(J10),IF(INDEX(Despiece!$F$5:$F$1004,MATCH($C$4&"|"&3,Despiece!$H$5:$H$1004,0))="Sí","Sublimada",""),IF(NOT(ISNUMBER(D10)),"Faltan metros (Despiece). ","")&IF(F10="","Elige tela. ",IF(NOT(ISNUMBER(G10)),"Falta precio o peso de 1 m (Precios). ","")))) -> Faltan metros (Despiece).
A11: =IF(B11="","",4) -> 4 | B11: =IFERROR(INDEX(Despiece!$B$5:$B$1004,MATCH($C$4&"|"&4,Despiece!$H$5:$H$1004,0)),"") -> Tira de cuello | C11: =IF(B11="","",INDEX(Despiece!$C$5:$C$1004,MATCH($C$4&"|"&4,Despiece!$H$5:$H$1004,0))) -> 1 | D11: =IF(B11="","",IF(N(INDEX(Despiece!$D$5:$D$1004,MATCH($C$4&"|"&4,Despiece!$H$5:$H$1004,0)))>0,INDEX(Despiece!$D$5:$D$1004,MATCH($C$4&"|"&4,Despiece!$H$5:$H$1004,0))*(1+IFERROR(IF(ISNUMBER(INDEX(Moldes!$K$5:$K$154,MATCH($C$4,Moldes!$A$5:$A$154,0))),INDEX(Moldes!$K$5:$K$154,MATCH($C$4,Moldes!$A$5:$A$154,0)),Precios!$Q$12),Precios!$Q$12)),"")) | F11: =IF(B11="","",IF(E11<>"",E11,INDEX(Despiece!$E$5:$E$1004,MATCH($C$4&"|"&4,Despiece!$H$5:$H$1004,0))&"")) -> MONTESIMONE TRAINING (fut pro) | G11: =IF(OR(B11="",F11=""),"",IFERROR(INDEX(Precios!$F$5:$F$124,MATCH(F11,Precios!$A$5:$A$124,0))*1,"")) -> 695.607 | H11: =IF(AND(ISNUMBER(D11),ISNUMBER(G11)),D11*G11,"") | I11: =IF(OR(B11="",NOT(ISNUMBER(D11))),"",IF(INDEX(Despiece!$F$5:$F$1004,MATCH($C$4&"|"&4,Despiece!$H$5:$H$1004,0))="Sí",D11*Precios!$Q$10,0)) | J11: =IF(AND(ISNUMBER(H11),ISNUMBER(I11)),H11+I11,"") | K11: =IF(B11="","",IF(ISNUMBER(J11),IF(INDEX(Despiece!$F$5:$F$1004,MATCH($C$4&"|"&4,Despiece!$H$5:$H$1004,0))="Sí","Sublimada",""),IF(NOT(ISNUMBER(D11)),"Faltan metros (Despiece). ","")&IF(F11="","Elige tela. ",IF(NOT(ISNUMBER(G11)),"Falta precio o peso de 1 m (Precios). ","")))) -> Faltan metros (Despiece).
A12: =IF(B12="","",5) -> 5 | B12: =IFERROR(INDEX(Despiece!$B$5:$B$1004,MATCH($C$4&"|"&5,Despiece!$H$5:$H$1004,0)),"") -> Paneles laterales | C12: =IF(B12="","",INDEX(Despiece!$C$5:$C$1004,MATCH($C$4&"|"&5,Despiece!$H$5:$H$1004,0))) -> 2 | D12: =IF(B12="","",IF(N(INDEX(Despiece!$D$5:$D$1004,MATCH($C$4&"|"&5,Despiece!$H$5:$H$1004,0)))>0,INDEX(Despiece!$D$5:$D$1004,MATCH($C$4&"|"&5,Despiece!$H$5:$H$1004,0))*(1+IFERROR(IF(ISNUMBER(INDEX(Moldes!$K$5:$K$154,MATCH($C$4,Moldes!$A$5:$A$154,0))),INDEX(Moldes!$K$5:$K$154,MATCH($C$4,Moldes!$A$5:$A$154,0)),Precios!$Q$12),Precios!$Q$12)),"")) | F12: =IF(B12="","",IF(E12<>"",E12,INDEX(Despiece!$E$5:$E$1004,MATCH($C$4&"|"&5,Despiece!$H$5:$H$1004,0))&"")) -> MESH | G12: =IF(OR(B12="",F12=""),"",IFERROR(INDEX(Precios!$F$5:$F$124,MATCH(F12,Precios!$A$5:$A$124,0))*1,"")) | H12: =IF(AND(ISNUMBER(D12),ISNUMBER(G12)),D12*G12,"") | I12: =IF(OR(B12="",NOT(ISNUMBER(D12))),"",IF(INDEX(Despiece!$F$5:$F$1004,MATCH($C$4&"|"&5,Despiece!$H$5:$H$1004,0))="Sí",D12*Precios!$Q$10,0)) | J12: =IF(AND(ISNUMBER(H12),ISNUMBER(I12)),H12+I12,"") | K12: =IF(B12="","",IF(ISNUMBER(J12),IF(INDEX(Despiece!$F$5:$F$1004,MATCH($C$4&"|"&5,Despiece!$H$5:$H$1004,0))="Sí","Sublimada",""),IF(NOT(ISNUMBER(D12)),"Faltan metros (Despiece). ","")&IF(F12="","Elige tela. ",IF(NOT(ISNUMBER(G12)),"Falta precio o peso de 1 m (Precios). ","")))) -> Faltan metros (Despiece). Falta precio o peso de 1 m (Precios).
A13: =IF(B13="","",6) | B13: =IFERROR(INDEX(Despiece!$B$5:$B$1004,MATCH($C$4&"|"&6,Despiece!$H$5:$H$1004,0)),"") | C13: =IF(B13="","",INDEX(Despiece!$C$5:$C$1004,MATCH($C$4&"|"&6,Despiece!$H$5:$H$1004,0))) | D13: =IF(B13="","",IF(N(INDEX(Despiece!$D$5:$D$1004,MATCH($C$4&"|"&6,Despiece!$H$5:$H$1004,0)))>0,INDEX(Despiece!$D$5:$D$1004,MATCH($C$4&"|"&6,Despiece!$H$5:$H$1004,0))*(1+IFERROR(IF(ISNUMBER(INDEX(Moldes!$K$5:$K$154,MATCH($C$4,Moldes!$A$5:$A$154,0))),INDEX(Moldes!$K$5:$K$154,MATCH($C$4,Moldes!$A$5:$A$154,0)),Precios!$Q$12),Precios!$Q$12)),"")) | F13: =IF(B13="","",IF(E13<>"",E13,INDEX(Despiece!$E$5:$E$1004,MATCH($C$4&"|"&6,Despiece!$H$5:$H$1004,0))&"")) | G13: =IF(OR(B13="",F13=""),"",IFERROR(INDEX(Precios!$F$5:$F$124,MATCH(F13,Precios!$A$5:$A$124,0))*1,"")) | H13: =IF(AND(ISNUMBER(D13),ISNUMBER(G13)),D13*G13,"") | I13: =IF(OR(B13="",NOT(ISNUMBER(D13))),"",IF(INDEX(Despiece!$F$5:$F$1004,MATCH($C$4&"|"&6,Despiece!$H$5:$H$1004,0))="Sí",D13*Precios!$Q$10,0)) | J13: =IF(AND(ISNUMBER(H13),ISNUMBER(I13)),H13+I13,"") | K13: =IF(B13="","",IF(ISNUMBER(J13),IF(INDEX(Despiece!$F$5:$F$1004,MATCH($C$4&"|"&6,Despiece!$H$5:$H$1004,0))="Sí","Sublimada",""),IF(NOT(ISNUMBER(D13)),"Faltan metros (Despiece). ","")&IF(F13="","Elige tela. ",IF(NOT(ISNUMBER(G13)),"Falta precio o peso de 1 m (Precios). ",""))))
A14: =IF(B14="","",7) | B14: =IFERROR(INDEX(Despiece!$B$5:$B$1004,MATCH($C$4&"|"&7,Despiece!$H$5:$H$1004,0)),"") | C14: =IF(B14="","",INDEX(Despiece!$C$5:$C$1004,MATCH($C$4&"|"&7,Despiece!$H$5:$H$1004,0))) | D14: =IF(B14="","",IF(N(INDEX(Despiece!$D$5:$D$1004,MATCH($C$4&"|"&7,Despiece!$H$5:$H$1004,0)))>0,INDEX(Despiece!$D$5:$D$1004,MATCH($C$4&"|"&7,Despiece!$H$5:$H$1004,0))*(1+IFERROR(IF(ISNUMBER(INDEX(Moldes!$K$5:$K$154,MATCH($C$4,Moldes!$A$5:$A$154,0))),INDEX(Moldes!$K$5:$K$154,MATCH($C$4,Moldes!$A$5:$A$154,0)),Precios!$Q$12),Precios!$Q$12)),"")) | F14: =IF(B14="","",IF(E14<>"",E14,INDEX(Despiece!$E$5:$E$1004,MATCH($C$4&"|"&7,Despiece!$H$5:$H$1004,0))&"")) | G14: =IF(OR(B14="",F14=""),"",IFERROR(INDEX(Precios!$F$5:$F$124,MATCH(F14,Precios!$A$5:$A$124,0))*1,"")) | H14: =IF(AND(ISNUMBER(D14),ISNUMBER(G14)),D14*G14,"") | I14: =IF(OR(B14="",NOT(ISNUMBER(D14))),"",IF(INDEX(Despiece!$F$5:$F$1004,MATCH($C$4&"|"&7,Despiece!$H$5:$H$1004,0))="Sí",D14*Precios!$Q$10,0)) | J14: =IF(AND(ISNUMBER(H14),ISNUMBER(I14)),H14+I14,"") | K14: =IF(B14="","",IF(ISNUMBER(J14),IF(INDEX(Despiece!$F$5:$F$1004,MATCH($C$4&"|"&7,Despiece!$H$5:$H$1004,0))="Sí","Sublimada",""),IF(NOT(ISNUMBER(D14)),"Faltan metros (Despiece). ","")&IF(F14="","Elige tela. ",IF(NOT(ISNUMBER(G14)),"Falta precio o peso de 1 m (Precios). ",""))))
A15: =IF(B15="","",8) | B15: =IFERROR(INDEX(Despiece!$B$5:$B$1004,MATCH($C$4&"|"&8,Despiece!$H$5:$H$1004,0)),"") | C15: =IF(B15="","",INDEX(Despiece!$C$5:$C$1004,MATCH($C$4&"|"&8,Despiece!$H$5:$H$1004,0))) | D15: =IF(B15="","",IF(N(INDEX(Despiece!$D$5:$D$1004,MATCH($C$4&"|"&8,Despiece!$H$5:$H$1004,0)))>0,INDEX(Despiece!$D$5:$D$1004,MATCH($C$4&"|"&8,Despiece!$H$5:$H$1004,0))*(1+IFERROR(IF(ISNUMBER(INDEX(Moldes!$K$5:$K$154,MATCH($C$4,Moldes!$A$5:$A$154,0))),INDEX(Moldes!$K$5:$K$154,MATCH($C$4,Moldes!$A$5:$A$154,0)),Precios!$Q$12),Precios!$Q$12)),"")) | F15: =IF(B15="","",IF(E15<>"",E15,INDEX(Despiece!$E$5:$E$1004,MATCH($C$4&"|"&8,Despiece!$H$5:$H$1004,0))&"")) | G15: =IF(OR(B15="",F15=""),"",IFERROR(INDEX(Precios!$F$5:$F$124,MATCH(F15,Precios!$A$5:$A$124,0))*1,"")) | H15: =IF(AND(ISNUMBER(D15),ISNUMBER(G15)),D15*G15,"") | I15: =IF(OR(B15="",NOT(ISNUMBER(D15))),"",IF(INDEX(Despiece!$F$5:$F$1004,MATCH($C$4&"|"&8,Despiece!$H$5:$H$1004,0))="Sí",D15*Precios!$Q$10,0)) | J15: =IF(AND(ISNUMBER(H15),ISNUMBER(I15)),H15+I15,"") | K15: =IF(B15="","",IF(ISNUMBER(J15),IF(INDEX(Despiece!$F$5:$F$1004,MATCH($C$4&"|"&8,Despiece!$H$5:$H$1004,0))="Sí","Sublimada",""),IF(NOT(ISNUMBER(D15)),"Faltan metros (Despiece). ","")&IF(F15="","Elige tela. ",IF(NOT(ISNUMBER(G15)),"Falta precio o peso de 1 m (Precios). ",""))))
A16: =IF(B16="","",9) | B16: =IFERROR(INDEX(Despiece!$B$5:$B$1004,MATCH($C$4&"|"&9,Despiece!$H$5:$H$1004,0)),"") | C16: =IF(B16="","",INDEX(Despiece!$C$5:$C$1004,MATCH($C$4&"|"&9,Despiece!$H$5:$H$1004,0))) | D16: =IF(B16="","",IF(N(INDEX(Despiece!$D$5:$D$1004,MATCH($C$4&"|"&9,Despiece!$H$5:$H$1004,0)))>0,INDEX(Despiece!$D$5:$D$1004,MATCH($C$4&"|"&9,Despiece!$H$5:$H$1004,0))*(1+IFERROR(IF(ISNUMBER(INDEX(Moldes!$K$5:$K$154,MATCH($C$4,Moldes!$A$5:$A$154,0))),INDEX(Moldes!$K$5:$K$154,MATCH($C$4,Moldes!$A$5:$A$154,0)),Precios!$Q$12),Precios!$Q$12)),"")) | F16: =IF(B16="","",IF(E16<>"",E16,INDEX(Despiece!$E$5:$E$1004,MATCH($C$4&"|"&9,Despiece!$H$5:$H$1004,0))&"")) | G16: =IF(OR(B16="",F16=""),"",IFERROR(INDEX(Precios!$F$5:$F$124,MATCH(F16,Precios!$A$5:$A$124,0))*1,"")) | H16: =IF(AND(ISNUMBER(D16),ISNUMBER(G16)),D16*G16,"") | I16: =IF(OR(B16="",NOT(ISNUMBER(D16))),"",IF(INDEX(Despiece!$F$5:$F$1004,MATCH($C$4&"|"&9,Despiece!$H$5:$H$1004,0))="Sí",D16*Precios!$Q$10,0)) | J16: =IF(AND(ISNUMBER(H16),ISNUMBER(I16)),H16+I16,"") | K16: =IF(B16="","",IF(ISNUMBER(J16),IF(INDEX(Despiece!$F$5:$F$1004,MATCH($C$4&"|"&9,Despiece!$H$5:$H$1004,0))="Sí","Sublimada",""),IF(NOT(ISNUMBER(D16)),"Faltan metros (Despiece). ","")&IF(F16="","Elige tela. ",IF(NOT(ISNUMBER(G16)),"Falta precio o peso de 1 m (Precios). ",""))))
A17: =IF(B17="","",10) | B17: =IFERROR(INDEX(Despiece!$B$5:$B$1004,MATCH($C$4&"|"&10,Despiece!$H$5:$H$1004,0)),"") | C17: =IF(B17="","",INDEX(Despiece!$C$5:$C$1004,MATCH($C$4&"|"&10,Despiece!$H$5:$H$1004,0))) | D17: =IF(B17="","",IF(N(INDEX(Despiece!$D$5:$D$1004,MATCH($C$4&"|"&10,Despiece!$H$5:$H$1004,0)))>0,INDEX(Despiece!$D$5:$D$1004,MATCH($C$4&"|"&10,Despiece!$H$5:$H$1004,0))*(1+IFERROR(IF(ISNUMBER(INDEX(Moldes!$K$5:$K$154,MATCH($C$4,Moldes!$A$5:$A$154,0))),INDEX(Moldes!$K$5:$K$154,MATCH($C$4,Moldes!$A$5:$A$154,0)),Precios!$Q$12),Precios!$Q$12)),"")) | F17: =IF(B17="","",IF(E17<>"",E17,INDEX(Despiece!$E$5:$E$1004,MATCH($C$4&"|"&10,Despiece!$H$5:$H$1004,0))&"")) | G17: =IF(OR(B17="",F17=""),"",IFERROR(INDEX(Precios!$F$5:$F$124,MATCH(F17,Precios!$A$5:$A$124,0))*1,"")) | H17: =IF(AND(ISNUMBER(D17),ISNUMBER(G17)),D17*G17,"") | I17: =IF(OR(B17="",NOT(ISNUMBER(D17))),"",IF(INDEX(Despiece!$F$5:$F$1004,MATCH($C$4&"|"&10,Despiece!$H$5:$H$1004,0))="Sí",D17*Precios!$Q$10,0)) | J17: =IF(AND(ISNUMBER(H17),ISNUMBER(I17)),H17+I17,"") | K17: =IF(B17="","",IF(ISNUMBER(J17),IF(INDEX(Despiece!$F$5:$F$1004,MATCH($C$4&"|"&10,Despiece!$H$5:$H$1004,0))="Sí","Sublimada",""),IF(NOT(ISNUMBER(D17)),"Faltan metros (Despiece). ","")&IF(F17="","Elige tela. ",IF(NOT(ISNUMBER(G17)),"Falta precio o peso de 1 m (Precios). ",""))))
A18: =IF(B18="","",11) | B18: =IFERROR(INDEX(Despiece!$B$5:$B$1004,MATCH($C$4&"|"&11,Despiece!$H$5:$H$1004,0)),"") | C18: =IF(B18="","",INDEX(Despiece!$C$5:$C$1004,MATCH($C$4&"|"&11,Despiece!$H$5:$H$1004,0))) | D18: =IF(B18="","",IF(N(INDEX(Despiece!$D$5:$D$1004,MATCH($C$4&"|"&11,Despiece!$H$5:$H$1004,0)))>0,INDEX(Despiece!$D$5:$D$1004,MATCH($C$4&"|"&11,Despiece!$H$5:$H$1004,0))*(1+IFERROR(IF(ISNUMBER(INDEX(Moldes!$K$5:$K$154,MATCH($C$4,Moldes!$A$5:$A$154,0))),INDEX(Moldes!$K$5:$K$154,MATCH($C$4,Moldes!$A$5:$A$154,0)),Precios!$Q$12),Precios!$Q$12)),"")) | F18: =IF(B18="","",IF(E18<>"",E18,INDEX(Despiece!$E$5:$E$1004,MATCH($C$4&"|"&11,Despiece!$H$5:$H$1004,0))&"")) | G18: =IF(OR(B18="",F18=""),"",IFERROR(INDEX(Precios!$F$5:$F$124,MATCH(F18,Precios!$A$5:$A$124,0))*1,"")) | H18: =IF(AND(ISNUMBER(D18),ISNUMBER(G18)),D18*G18,"") | I18: =IF(OR(B18="",NOT(ISNUMBER(D18))),"",IF(INDEX(Despiece!$F$5:$F$1004,MATCH($C$4&"|"&11,Despiece!$H$5:$H$1004,0))="Sí",D18*Precios!$Q$10,0)) | J18: =IF(AND(ISNUMBER(H18),ISNUMBER(I18)),H18+I18,"") | K18: =IF(B18="","",IF(ISNUMBER(J18),IF(INDEX(Despiece!$F$5:$F$1004,MATCH($C$4&"|"&11,Despiece!$H$5:$H$1004,0))="Sí","Sublimada",""),IF(NOT(ISNUMBER(D18)),"Faltan metros (Despiece). ","")&IF(F18="","Elige tela. ",IF(NOT(ISNUMBER(G18)),"Falta precio o peso de 1 m (Precios). ",""))))
A19: =IF(B19="","",12) | B19: =IFERROR(INDEX(Despiece!$B$5:$B$1004,MATCH($C$4&"|"&12,Despiece!$H$5:$H$1004,0)),"") | C19: =IF(B19="","",INDEX(Despiece!$C$5:$C$1004,MATCH($C$4&"|"&12,Despiece!$H$5:$H$1004,0))) | D19: =IF(B19="","",IF(N(INDEX(Despiece!$D$5:$D$1004,MATCH($C$4&"|"&12,Despiece!$H$5:$H$1004,0)))>0,INDEX(Despiece!$D$5:$D$1004,MATCH($C$4&"|"&12,Despiece!$H$5:$H$1004,0))*(1+IFERROR(IF(ISNUMBER(INDEX(Moldes!$K$5:$K$154,MATCH($C$4,Moldes!$A$5:$A$154,0))),INDEX(Moldes!$K$5:$K$154,MATCH($C$4,Moldes!$A$5:$A$154,0)),Precios!$Q$12),Precios!$Q$12)),"")) | F19: =IF(B19="","",IF(E19<>"",E19,INDEX(Despiece!$E$5:$E$1004,MATCH($C$4&"|"&12,Despiece!$H$5:$H$1004,0))&"")) | G19: =IF(OR(B19="",F19=""),"",IFERROR(INDEX(Precios!$F$5:$F$124,MATCH(F19,Precios!$A$5:$A$124,0))*1,"")) | H19: =IF(AND(ISNUMBER(D19),ISNUMBER(G19)),D19*G19,"") | I19: =IF(OR(B19="",NOT(ISNUMBER(D19))),"",IF(INDEX(Despiece!$F$5:$F$1004,MATCH($C$4&"|"&12,Despiece!$H$5:$H$1004,0))="Sí",D19*Precios!$Q$10,0)) | J19: =IF(AND(ISNUMBER(H19),ISNUMBER(I19)),H19+I19,"") | K19: =IF(B19="","",IF(ISNUMBER(J19),IF(INDEX(Despiece!$F$5:$F$1004,MATCH($C$4&"|"&12,Despiece!$H$5:$H$1004,0))="Sí","Sublimada",""),IF(NOT(ISNUMBER(D19)),"Faltan metros (Despiece). ","")&IF(F19="","Elige tela. ",IF(NOT(ISNUMBER(G19)),"Falta precio o peso de 1 m (Precios). ",""))))
A20: =IF(B20="","",13) | B20: =IFERROR(INDEX(Despiece!$B$5:$B$1004,MATCH($C$4&"|"&13,Despiece!$H$5:$H$1004,0)),"") | C20: =IF(B20="","",INDEX(Despiece!$C$5:$C$1004,MATCH($C$4&"|"&13,Despiece!$H$5:$H$1004,0))) | D20: =IF(B20="","",IF(N(INDEX(Despiece!$D$5:$D$1004,MATCH($C$4&"|"&13,Despiece!$H$5:$H$1004,0)))>0,INDEX(Despiece!$D$5:$D$1004,MATCH($C$4&"|"&13,Despiece!$H$5:$H$1004,0))*(1+IFERROR(IF(ISNUMBER(INDEX(Moldes!$K$5:$K$154,MATCH($C$4,Moldes!$A$5:$A$154,0))),INDEX(Moldes!$K$5:$K$154,MATCH($C$4,Moldes!$A$5:$A$154,0)),Precios!$Q$12),Precios!$Q$12)),"")) | F20: =IF(B20="","",IF(E20<>"",E20,INDEX(Despiece!$E$5:$E$1004,MATCH($C$4&"|"&13,Despiece!$H$5:$H$1004,0))&"")) | G20: =IF(OR(B20="",F20=""),"",IFERROR(INDEX(Precios!$F$5:$F$124,MATCH(F20,Precios!$A$5:$A$124,0))*1,"")) | H20: =IF(AND(ISNUMBER(D20),ISNUMBER(G20)),D20*G20,"") | I20: =IF(OR(B20="",NOT(ISNUMBER(D20))),"",IF(INDEX(Despiece!$F$5:$F$1004,MATCH($C$4&"|"&13,Despiece!$H$5:$H$1004,0))="Sí",D20*Precios!$Q$10,0)) | J20: =IF(AND(ISNUMBER(H20),ISNUMBER(I20)),H20+I20,"") | K20: =IF(B20="","",IF(ISNUMBER(J20),IF(INDEX(Despiece!$F$5:$F$1004,MATCH($C$4&"|"&13,Despiece!$H$5:$H$1004,0))="Sí","Sublimada",""),IF(NOT(ISNUMBER(D20)),"Faltan metros (Despiece). ","")&IF(F20="","Elige tela. ",IF(NOT(ISNUMBER(G20)),"Falta precio o peso de 1 m (Precios). ",""))))
A21: =IF(B21="","",14) | B21: =IFERROR(INDEX(Despiece!$B$5:$B$1004,MATCH($C$4&"|"&14,Despiece!$H$5:$H$1004,0)),"") | C21: =IF(B21="","",INDEX(Despiece!$C$5:$C$1004,MATCH($C$4&"|"&14,Despiece!$H$5:$H$1004,0))) | D21: =IF(B21="","",IF(N(INDEX(Despiece!$D$5:$D$1004,MATCH($C$4&"|"&14,Despiece!$H$5:$H$1004,0)))>0,INDEX(Despiece!$D$5:$D$1004,MATCH($C$4&"|"&14,Despiece!$H$5:$H$1004,0))*(1+IFERROR(IF(ISNUMBER(INDEX(Moldes!$K$5:$K$154,MATCH($C$4,Moldes!$A$5:$A$154,0))),INDEX(Moldes!$K$5:$K$154,MATCH($C$4,Moldes!$A$5:$A$154,0)),Precios!$Q$12),Precios!$Q$12)),"")) | F21: =IF(B21="","",IF(E21<>"",E21,INDEX(Despiece!$E$5:$E$1004,MATCH($C$4&"|"&14,Despiece!$H$5:$H$1004,0))&"")) | G21: =IF(OR(B21="",F21=""),"",IFERROR(INDEX(Precios!$F$5:$F$124,MATCH(F21,Precios!$A$5:$A$124,0))*1,"")) | H21: =IF(AND(ISNUMBER(D21),ISNUMBER(G21)),D21*G21,"") | I21: =IF(OR(B21="",NOT(ISNUMBER(D21))),"",IF(INDEX(Despiece!$F$5:$F$1004,MATCH($C$4&"|"&14,Despiece!$H$5:$H$1004,0))="Sí",D21*Precios!$Q$10,0)) | J21: =IF(AND(ISNUMBER(H21),ISNUMBER(I21)),H21+I21,"") | K21: =IF(B21="","",IF(ISNUMBER(J21),IF(INDEX(Despiece!$F$5:$F$1004,MATCH($C$4&"|"&14,Despiece!$H$5:$H$1004,0))="Sí","Sublimada",""),IF(NOT(ISNUMBER(D21)),"Faltan metros (Despiece). ","")&IF(F21="","Elige tela. ",IF(NOT(ISNUMBER(G21)),"Falta precio o peso de 1 m (Precios). ",""))))
A22: =IF(B22="","",15) | B22: =IFERROR(INDEX(Despiece!$B$5:$B$1004,MATCH($C$4&"|"&15,Despiece!$H$5:$H$1004,0)),"") | C22: =IF(B22="","",INDEX(Despiece!$C$5:$C$1004,MATCH($C$4&"|"&15,Despiece!$H$5:$H$1004,0))) | D22: =IF(B22="","",IF(N(INDEX(Despiece!$D$5:$D$1004,MATCH($C$4&"|"&15,Despiece!$H$5:$H$1004,0)))>0,INDEX(Despiece!$D$5:$D$1004,MATCH($C$4&"|"&15,Despiece!$H$5:$H$1004,0))*(1+IFERROR(IF(ISNUMBER(INDEX(Moldes!$K$5:$K$154,MATCH($C$4,Moldes!$A$5:$A$154,0))),INDEX(Moldes!$K$5:$K$154,MATCH($C$4,Moldes!$A$5:$A$154,0)),Precios!$Q$12),Precios!$Q$12)),"")) | F22: =IF(B22="","",IF(E22<>"",E22,INDEX(Despiece!$E$5:$E$1004,MATCH($C$4&"|"&15,Despiece!$H$5:$H$1004,0))&"")) | G22: =IF(OR(B22="",F22=""),"",IFERROR(INDEX(Precios!$F$5:$F$124,MATCH(F22,Precios!$A$5:$A$124,0))*1,"")) | H22: =IF(AND(ISNUMBER(D22),ISNUMBER(G22)),D22*G22,"") | I22: =IF(OR(B22="",NOT(ISNUMBER(D22))),"",IF(INDEX(Despiece!$F$5:$F$1004,MATCH($C$4&"|"&15,Despiece!$H$5:$H$1004,0))="Sí",D22*Precios!$Q$10,0)) | J22: =IF(AND(ISNUMBER(H22),ISNUMBER(I22)),H22+I22,"") | K22: =IF(B22="","",IF(ISNUMBER(J22),IF(INDEX(Despiece!$F$5:$F$1004,MATCH($C$4&"|"&15,Despiece!$H$5:$H$1004,0))="Sí","Sublimada",""),IF(NOT(ISNUMBER(D22)),"Faltan metros (Despiece). ","")&IF(F22="","Elige tela. ",IF(NOT(ISNUMBER(G22)),"Falta precio o peso de 1 m (Precios). ",""))))
A23: =IF(B23="","",16) | B23: =IFERROR(INDEX(Despiece!$B$5:$B$1004,MATCH($C$4&"|"&16,Despiece!$H$5:$H$1004,0)),"") | C23: =IF(B23="","",INDEX(Despiece!$C$5:$C$1004,MATCH($C$4&"|"&16,Despiece!$H$5:$H$1004,0))) | D23: =IF(B23="","",IF(N(INDEX(Despiece!$D$5:$D$1004,MATCH($C$4&"|"&16,Despiece!$H$5:$H$1004,0)))>0,INDEX(Despiece!$D$5:$D$1004,MATCH($C$4&"|"&16,Despiece!$H$5:$H$1004,0))*(1+IFERROR(IF(ISNUMBER(INDEX(Moldes!$K$5:$K$154,MATCH($C$4,Moldes!$A$5:$A$154,0))),INDEX(Moldes!$K$5:$K$154,MATCH($C$4,Moldes!$A$5:$A$154,0)),Precios!$Q$12),Precios!$Q$12)),"")) | F23: =IF(B23="","",IF(E23<>"",E23,INDEX(Despiece!$E$5:$E$1004,MATCH($C$4&"|"&16,Despiece!$H$5:$H$1004,0))&"")) | G23: =IF(OR(B23="",F23=""),"",IFERROR(INDEX(Precios!$F$5:$F$124,MATCH(F23,Precios!$A$5:$A$124,0))*1,"")) | H23: =IF(AND(ISNUMBER(D23),ISNUMBER(G23)),D23*G23,"") | I23: =IF(OR(B23="",NOT(ISNUMBER(D23))),"",IF(INDEX(Despiece!$F$5:$F$1004,MATCH($C$4&"|"&16,Despiece!$H$5:$H$1004,0))="Sí",D23*Precios!$Q$10,0)) | J23: =IF(AND(ISNUMBER(H23),ISNUMBER(I23)),H23+I23,"") | K23: =IF(B23="","",IF(ISNUMBER(J23),IF(INDEX(Despiece!$F$5:$F$1004,MATCH($C$4&"|"&16,Despiece!$H$5:$H$1004,0))="Sí","Sublimada",""),IF(NOT(ISNUMBER(D23)),"Faltan metros (Despiece). ","")&IF(F23="","Elige tela. ",IF(NOT(ISNUMBER(G23)),"Falta precio o peso de 1 m (Precios). ",""))))
B25: RESUMEN POR PRENDA
B26: Tela | J26: =IF(SUMPRODUCT((B8:B23<>"")*NOT(ISNUMBER(J8:J23)))=0,SUM(H8:H23),"Faltan datos ↑") -> Faltan datos ↑ | K26: Suma de las piezas
B27: Papel y tinta de sublimación | J27: =IF(SUMPRODUCT((B8:B23<>"")*NOT(ISNUMBER(J8:J23)))=0,SUM(I8:I23),"Faltan datos ↑") -> Faltan datos ↑ | K27: =IF(N(Precios!$Q$10)=0,"OJO: costo de impresión en $0 (hoja Precios)",TEXT(SUMIF(I8:I23,">0",D8:D23),"0.00")&" m impresos × "&TEXT(Precios!$Q$10,"$#,##0")) -> OJO: costo de impresión en $0 (hoja Precios)
B28: Confección (taller) | J28: =IFERROR(INDEX(Moldes!$M$5:$M$154,MATCH($C$4,Moldes!$A$5:$A$154,0))*1,"Falta tipo de confección (Moldes)") -> 2000 | K28: =IFERROR(INDEX(Moldes!$E$5:$E$154,MATCH($C$4,Moldes!$A$5:$A$154,0))&"","") -> Camiseta De Futbol
B29: Avíos | J29: =IFERROR(INDEX(Moldes!$N$5:$N$154,MATCH($C$4,Moldes!$A$5:$A$154,0))*1,0) -> 0 | K29: =IFERROR(IF(INDEX(Moldes!$F$5:$F$154,MATCH($C$4,Moldes!$A$5:$A$154,0))&""="","Sin avíos",INDEX(Moldes!$F$5:$F$154,MATCH($C$4,Moldes!$A$5:$A$154,0))&" × "&INDEX(Moldes!$G$5:$G$154,MATCH($C$4,Moldes!$A$5:$A$154,0))&IF(INDEX(Moldes!$H$5:$H$154,MATCH($C$4,Moldes!$A$5:$A$154,0))&""="",""," + "&INDEX(Moldes!$H$5:$H$154,MATCH($C$4,Moldes!$A$5:$A$154,0))&" × "&INDEX(Moldes!$I$5:$I$154,MATCH($C$4,Moldes!$A$5:$A$154,0)))),"") -> Sin avíos
B30: Extras (bordado, DTF, escudo…) — escribe | K30: Por prenda
B31: COSTO DE PRODUCCIÓN | J31: =IFERROR(J26+J27+J28+J29+N(J30),"Completa los datos ↑") -> Completa los datos ↑
B33: ="Precio mínimo de venta (neto) = costo × "&TEXT(Precios!$Q$16,"0.00")&" (gastos generales "&TEXT(Precios!$Q$14,"0.0%")&" + ganancia "&TEXT(Precios!$Q$15,"0%")&")" -> Precio mínimo de venta (neto) = costo × 2.40 (gastos generales 43.4% + ganancia 15%) | J33: =IF(ISNUMBER(J31),J31*Precios!$Q$16,"")
B34: Tu precio de venta actual, neto — escribe
B35: Ganancia por prenda (después de costo y gastos generales) | J35: =IF(AND(ISNUMBER(J31),N(J34)>0),J34-J31-J34*Precios!$Q$14,"") | K35: =IF(ISNUMBER(J35),TEXT(J35/J34,"0.0%")&" del precio"&IF(J35<0," ← PIERDE PLATA",IF(J35/J34<Precios!$Q$15," ← bajo la meta","")),"")
B37: AJUSTAR CON UN CORTE REAL (opcional)
B38: Después de cortar este molde: qué tela, cuántas prendas y cuántos kg se usaron. Te dice el % de ajuste para anotar en Moldes.
B39: Tela cortada
B40: Prendas cortadas
B41: Kg usados
B42: Metros reales por prenda | J42: =IFERROR(J41/INDEX(Precios!$E$5:$E$124,MATCH(J39,Precios!$A$5:$A$124,0))/J40,"")
B43: Metros del despiece en esa tela (sin merma) | J43: =IF(J39="","",SUMIF(F8:F23,J39,D8:D23)/(1+IFERROR(IF(ISNUMBER(INDEX(Moldes!$K$5:$K$154,MATCH($C$4,Moldes!$A$5:$A$154,0))),INDEX(Moldes!$K$5:$K$154,MATCH($C$4,Moldes!$A$5:$A$154,0)),Precios!$Q$12),Precios!$Q$12)))
B44: AJUSTE A ANOTAR EN MOLDES (columna K) | J44: =IF(AND(ISNUMBER(J42),N(J43)>0),J42/J43-1,"")
B45: Si da error: falta el peso de 1 metro de esa tela, o los metros de las piezas en el Despiece.
B47: No van aquí (están en los gastos generales del sistema de ventas): sueldos de corte, ploteo, sublimación, estampado y diseño, arriendo, luz, ventas y administración.

Sheet Moldes
A1: MOLDES — catálogo con su costo de producción (telas por defecto)
A2: Una fila por molde. Lo que va por prenda y no depende de la tela: confección y avíos. Para probar otras telas, usa la Ficha.
A3: ="Moldes con costo completo: "&COUNTIF(P5:P154,"Lista*")&" de "&COUNTA(A5:A154) -> Moldes con costo completo: 0 de 58
A4: Molde | B4: Descripción | C4: Prenda | D4: Calce | E4: Tipo de confección | F4: Avío 1 | G4: Cant. | H4: Avío 2 | I4: Cant. | J4: Piezas en despiece | K4: Ajuste por consumo real (%) — vacío = merma general | L4: $ Tela + impresión | M4: $ Confección | N4: $ Avíos | O4: COSTO DE PRODUCCIÓN | P4: Qué falta | Q4: Notas
A5: 01 · FUTMUJU01 | B5: Fútbol, cuello redondo | C5: Camiseta | D5: Femenino | E5: Camiseta De Futbol | J5: =IF(A5="","",COUNTIF(Despiece!$A$5:$A$1004,A5)) -> 4 | L5: =IF(A5="","",IF(COUNTIFS(Despiece!$A$5:$A$1004,A5,Despiece!$D$5:$D$1004,">0")<J5,"",IF(COUNTIFS(Despiece!$A$5:$A$1004,A5,Despiece!$G$5:$G$1004,"falta*")>0,"",SUMIFS(Despiece!$G$5:$G$1004,Despiece!$A$5:$A$1004,A5)))) | M5: =IF(OR(A5="",E5=""),"",IFERROR(INDEX(Precios!$K$5:$K$84,MATCH(E5,Precios!$J$5:$J$84,0)),"")) -> 2000 | N5: =IF(A5="","",IFERROR(N(G5)*IF(F5="",0,INDEX(Precios!$N$5:$N$64,MATCH(F5,Precios!$M$5:$M$64,0)))+N(I5)*IF(H5="",0,INDEX(Precios!$N$5:$N$64,MATCH(H5,Precios!$M$5:$M$64,0))),"")) -> 0 | O5: =IF(A5="","",IFERROR(L5+M5+N5,"")) | P5: =IF(A5="","",IF(ISNUMBER(O5),"Lista"&IF(N(Precios!$Q$10)=0," (impresión en $0)",""),IF(J5=0,"Agregar piezas en Despiece. ",IF(COUNTIFS(Despiece!$A$5:$A$1004,A5,Despiece!$D$5:$D$1004,">0")<J5,"Metros de "&(J5-COUNTIFS(Despiece!$A$5:$A$1004,A5,Despiece!$D$5:$D$1004,">0"))&" pieza(s). ",""))&IF(COUNTIFS(Despiece!$A$5:$A$1004,A5,Despiece!$G$5:$G$1004,"falta*")>0,"Precio o peso de 1 m de alguna tela. ","")&IF(M5="","Tipo/precio de confección. ",""))) -> Metros de 4 pieza(s).
A6: 02 · FUTHOMU01 | B6: Fútbol, cuello redondo | C6: Camiseta | D6: Masculino | E6: Camiseta De Futbol | J6: =IF(A6="","",COUNTIF(Despiece!$A$5:$A$1004,A6)) -> 4 | L6: =IF(A6="","",IF(COUNTIFS(Despiece!$A$5:$A$1004,A6,Despiece!$D$5:$D$1004,">0")<J6,"",IF(COUNTIFS(Despiece!$A$5:$A$1004,A6,Despiece!$G$5:$G$1004,"falta*")>0,"",SUMIFS(Despiece!$G$5:$G$1004,Despiece!$A$5:$A$1004,A6)))) | M6: =IF(OR(A6="",E6=""),"",IFERROR(INDEX(Precios!$K$5:$K$84,MATCH(E6,Precios!$J$5:$J$84,0)),"")) -> 2000 | N6: =IF(A6="","",IFERROR(N(G6)*IF(F6="",0,INDEX(Precios!$N$5:$N$64,MATCH(F6,Precios!$M$5:$M$64,0)))+N(I6)*IF(H6="",0,INDEX(Precios!$N$5:$N$64,MATCH(H6,Precios!$M$5:$M$64,0))),"")) -> 0 | O6: =IF(A6="","",IFERROR(L6+M6+N6,"")) | P6: =IF(A6="","",IF(ISNUMBER(O6),"Lista"&IF(N(Precios!$Q$10)=0," (impresión en $0)",""),IF(J6=0,"Agregar piezas en Despiece. ",IF(COUNTIFS(Despiece!$A$5:$A$1004,A6,Despiece!$D$5:$D$1004,">0")<J6,"Metros de "&(J6-COUNTIFS(Despiece!$A$5:$A$1004,A6,Despiece!$D$5:$D$1004,">0"))&" pieza(s). ",""))&IF(COUNTIFS(Despiece!$A$5:$A$1004,A6,Despiece!$G$5:$G$1004,"falta*")>0,"Precio o peso de 1 m de alguna tela. ","")&IF(M6="","Tipo/precio de confección. ",""))) -> Metros de 4 pieza(s).
A7: 03 · FUTINMUJU01 | B7: Fútbol infantil, cuello redondo | C7: Camiseta | D7: Infantil Femenino | E7: Camiseta De Futbol | J7: =IF(A7="","",COUNTIF(Despiece!$A$5:$A$1004,A7)) -> 4 | L7: =IF(A7="","",IF(COUNTIFS(Despiece!$A$5:$A$1004,A7,Despiece!$D$5:$D$1004,">0")<J7,"",IF(COUNTIFS(Despiece!$A$5:$A$1004,A7,Despiece!$G$5:$G$1004,"falta*")>0,"",SUMIFS(Despiece!$G$5:$G$1004,Despiece!$A$5:$A$1004,A7)))) | M7: =IF(OR(A7="",E7=""),"",IFERROR(INDEX(Precios!$K$5:$K$84,MATCH(E7,Precios!$J$5:$J$84,0)),"")) -> 2000 | N7: =IF(A7="","",IFERROR(N(G7)*IF(F7="",0,INDEX(Precios!$N$5:$N$64,MATCH(F7,Precios!$M$5:$M$64,0)))+N(I7)*IF(H7="",0,INDEX(Precios!$N$5:$N$64,MATCH(H7,Precios!$M$5:$M$64,0))),"")) -> 0 | O7: =IF(A7="","",IFERROR(L7+M7+N7,"")) | P7: =IF(A7="","",IF(ISNUMBER(O7),"Lista"&IF(N(Precios!$Q$10)=0," (impresión en $0)",""),IF(J7=0,"Agregar piezas en Despiece. ",IF(COUNTIFS(Despiece!$A$5:$A$1004,A7,Despiece!$D$5:$D$1004,">0")<J7,"Metros de "&(J7-COUNTIFS(Despiece!$A$5:$A$1004,A7,Despiece!$D$5:$D$1004,">0"))&" pieza(s). ",""))&IF(COUNTIFS(Despiece!$A$5:$A$1004,A7,Despiece!$G$5:$G$1004,"falta*")>0,"Precio o peso de 1 m de alguna tela. ","")&IF(M7="","Tipo/precio de confección. ",""))) -> Metros de 4 pieza(s).
A8: 04 · FUTINHOMU01 | B8: Fútbol infantil, cuello redondo | C8: Camiseta | D8: Infantil Masculino | E8: Camiseta De Futbol | J8: =IF(A8="","",COUNTIF(Despiece!$A$5:$A$1004,A8)) -> 4 | L8: =IF(A8="","",IF(COUNTIFS(Despiece!$A$5:$A$1004,A8,Despiece!$D$5:$D$1004,">0")<J8,"",IF(COUNTIFS(Despiece!$A$5:$A$1004,A8,Despiece!$G$5:$G$1004,"falta*")>0,"",SUMIFS(Despiece!$G$5:$G$1004,Despiece!$A$5:$A$1004,A8)))) | M8: =IF(OR(A8="",E8=""),"",IFERROR(INDEX(Precios!$K$5:$K$84,MATCH(E8,Precios!$J$5:$J$84,0)),"")) -> 2000 | N8: =IF(A8="","",IFERROR(N(G8)*IF(F8="",0,INDEX(Precios!$N$5:$N$64,MATCH(F8,Precios!$M$5:$M$64,0)))+N(I8)*IF(H8="",0,INDEX(Precios!$N$5:$N$64,MATCH(H8,Precios!$M$5:$M$64,0))),"")) -> 0 | O8: =IF(A8="","",IFERROR(L8+M8+N8,"")) | P8: =IF(A8="","",IF(ISNUMBER(O8),"Lista"&IF(N(Precios!$Q$10)=0," (impresión en $0)",""),IF(J8=0,"Agregar piezas en Despiece. ",IF(COUNTIFS(Despiece!$A$5:$A$1004,A8,Despiece!$D$5:$D$1004,">0")<J8,"Metros de "&(J8-COUNTIFS(Despiece!$A$5:$A$1004,A8,Despiece!$D$5:$D$1004,">0"))&" pieza(s). ",""))&IF(COUNTIFS(Despiece!$A$5:$A$1004,A8,Despiece!$G$5:$G$1004,"falta*")>0,"Precio o peso de 1 m de alguna tela. ","")&IF(M8="","Tipo/precio de confección. ",""))) -> Metros de 4 pieza(s). | Q8: Corte OT 2369: 0,0375 kg Cire + 0,024 kg Mesh por prenda.
A9: 05 · FUTMUJV01 | B9: Fútbol, cuello v | C9: Camiseta | D9: Femenino | E9: Camiseta De Futbol | J9: =IF(A9="","",COUNTIF(Despiece!$A$5:$A$1004,A9)) -> 4 | L9: =IF(A9="","",IF(COUNTIFS(Despiece!$A$5:$A$1004,A9,Despiece!$D$5:$D$1004,">0")<J9,"",IF(COUNTIFS(Despiece!$A$5:$A$1004,A9,Despiece!$G$5:$G$1004,"falta*")>0,"",SUMIFS(Despiece!$G$5:$G$1004,Despiece!$A$5:$A$1004,A9)))) | M9: =IF(OR(A9="",E9=""),"",IFERROR(INDEX(Precios!$K$5:$K$84,MATCH(E9,Precios!$J$5:$J$84,0)),"")) -> 2000 | N9: =IF(A9="","",IFERROR(N(G9)*IF(F9="",0,INDEX(Precios!$N$5:$N$64,MATCH(F9,Precios!$M$5:$M$64,0)))+N(I9)*IF(H9="",0,INDEX(Precios!$N$5:$N$64,MATCH(H9,Precios!$M$5:$M$64,0))),"")) -> 0 | O9: =IF(A9="","",IFERROR(L9+M9+N9,"")) | P9: =IF(A9="","",IF(ISNUMBER(O9),"Lista"&IF(N(Precios!$Q$10)=0," (impresión en $0)",""),IF(J9=0,"Agregar piezas en Despiece. ",IF(COUNTIFS(Despiece!$A$5:$A$1004,A9,Despiece!$D$5:$D$1004,">0")<J9,"Metros de "&(J9-COUNTIFS(Despiece!$A$5:$A$1004,A9,Despiece!$D$5:$D$1004,">0"))&" pieza(s). ",""))&IF(COUNTIFS(Despiece!$A$5:$A$1004,A9,Despiece!$G$5:$G$1004,"falta*")>0,"Precio o peso de 1 m de alguna tela. ","")&IF(M9="","Tipo/precio de confección. ",""))) -> Metros de 4 pieza(s).
A10: 06 · FUTHOMV01 | B10: Fútbol, cuello v | C10: Camiseta | D10: Masculino | E10: Camiseta De Futbol | J10: =IF(A10="","",COUNTIF(Despiece!$A$5:$A$1004,A10)) -> 4 | L10: =IF(A10="","",IF(COUNTIFS(Despiece!$A$5:$A$1004,A10,Despiece!$D$5:$D$1004,">0")<J10,"",IF(COUNTIFS(Despiece!$A$5:$A$1004,A10,Despiece!$G$5:$G$1004,"falta*")>0,"",SUMIFS(Despiece!$G$5:$G$1004,Despiece!$A$5:$A$1004,A10)))) | M10: =IF(OR(A10="",E10=""),"",IFERROR(INDEX(Precios!$K$5:$K$84,MATCH(E10,Precios!$J$5:$J$84,0)),"")) -> 2000 | N10: =IF(A10="","",IFERROR(N(G10)*IF(F10="",0,INDEX(Precios!$N$5:$N$64,MATCH(F10,Precios!$M$5:$M$64,0)))+N(I10)*IF(H10="",0,INDEX(Precios!$N$5:$N$64,MATCH(H10,Precios!$M$5:$M$64,0))),"")) -> 0 | O10: =IF(A10="","",IFERROR(L10+M10+N10,"")) | P10: =IF(A10="","",IF(ISNUMBER(O10),"Lista"&IF(N(Precios!$Q$10)=0," (impresión en $0)",""),IF(J10=0,"Agregar piezas en Despiece. ",IF(COUNTIFS(Despiece!$A$5:$A$1004,A10,Despiece!$D$5:$D$1004,">0")<J10,"Metros de "&(J10-COUNTIFS(Despiece!$A$5:$A$1004,A10,Despiece!$D$5:$D$1004,">0"))&" pieza(s). ",""))&IF(COUNTIFS(Despiece!$A$5:$A$1004,A10,Despiece!$G$5:$G$1004,"falta*")>0,"Precio o peso de 1 m de alguna tela. ","")&IF(M10="","Tipo/precio de confección. ",""))) -> Metros de 4 pieza(s).
A11: 07 · FUTINMUJV01 | B11: Fútbol infantil, cuello v | C11: Camiseta | D11: Infantil Femenino | E11: Camiseta De Futbol | J11: =IF(A11="","",COUNTIF(Despiece!$A$5:$A$1004,A11)) -> 4 | L11: =IF(A11="","",IF(COUNTIFS(Despiece!$A$5:$A$1004,A11,Despiece!$D$5:$D$1004,">0")<J11,"",IF(COUNTIFS(Despiece!$A$5:$A$1004,A11,Despiece!$G$5:$G$1004,"falta*")>0,"",SUMIFS(Despiece!$G$5:$G$1004,Despiece!$A$5:$A$1004,A11)))) | M11: =IF(OR(A11="",E11=""),"",IFERROR(INDEX(Precios!$K$5:$K$84,MATCH(E11,Precios!$J$5:$J$84,0)),"")) -> 2000 | N11: =IF(A11="","",IFERROR(N(G11)*IF(F11="",0,INDEX(Precios!$N$5:$N$64,MATCH(F11,Precios!$M$5:$M$64,0)))+N(I11)*IF(H11="",0,INDEX(Precios!$N$5:$N$64,MATCH(H11,Precios!$M$5:$M$64,0))),"")) -> 0 | O11: =IF(A11="","",IFERROR(L11+M11+N11,"")) | P11: =IF(A11="","",IF(ISNUMBER(O11),"Lista"&IF(N(Precios!$Q$10)=0," (impresión en $0)",""),IF(J11=0,"Agregar piezas en Despiece. ",IF(COUNTIFS(Despiece!$A$5:$A$1004,A11,Despiece!$D$5:$D$1004,">0")<J11,"Metros de "&(J11-COUNTIFS(Despiece!$A$5:$A$1004,A11,Despiece!$D$5:$D$1004,">0"))&" pieza(s). ",""))&IF(COUNTIFS(Despiece!$A$5:$A$1004,A11,Despiece!$G$5:$G$1004,"falta*")>0,"Precio o peso de 1 m de alguna tela. ","")&IF(M11="","Tipo/precio de confección. ",""))) -> Metros de 4 pieza(s).
A12: 08 · FUTINHOMV01 | B12: Fútbol infantil, cuello v | C12: Camiseta | D12: Infantil Masculino | E12: Camiseta De Futbol | J12: =IF(A12="","",COUNTIF(Despiece!$A$5:$A$1004,A12)) -> 4 | L12: =IF(A12="","",IF(COUNTIFS(Despiece!$A$5:$A$1004,A12,Despiece!$D$5:$D$1004,">0")<J12,"",IF(COUNTIFS(Despiece!$A$5:$A$1004,A12,Despiece!$G$5:$G$1004,"falta*")>0,"",SUMIFS(Despiece!$G$5:$G$1004,Despiece!$A$5:$A$1004,A12)))) | M12: =IF(OR(A12="",E12=""),"",IFERROR(INDEX(Precios!$K$5:$K$84,MATCH(E12,Precios!$J$5:$J$84,0)),"")) -> 2000 | N12: =IF(A12="","",IFERROR(N(G12)*IF(F12="",0,INDEX(Precios!$N$5:$N$64,MATCH(F12,Precios!$M$5:$M$64,0)))+N(I12)*IF(H12="",0,INDEX(Precios!$N$5:$N$64,MATCH(H12,Precios!$M$5:$M$64,0))),"")) -> 0 | O12: =IF(A12="","",IFERROR(L12+M12+N12,"")) | P12: =IF(A12="","",IF(ISNUMBER(O12),"Lista"&IF(N(Precios!$Q$10)=0," (impresión en $0)",""),IF(J12=0,"Agregar piezas en Despiece. ",IF(COUNTIFS(Despiece!$A$5:$A$1004,A12,Despiece!$D$5:$D$1004,">0")<J12,"Metros de "&(J12-COUNTIFS(Despiece!$A$5:$A$1004,A12,Despiece!$D$5:$D$1004,">0"))&" pieza(s). ",""))&IF(COUNTIFS(Despiece!$A$5:$A$1004,A12,Despiece!$G$5:$G$1004,"falta*")>0,"Precio o peso de 1 m de alguna tela. ","")&IF(M12="","Tipo/precio de confección. ",""))) -> Metros de 4 pieza(s).
A13: 09 · FUTMUJCC01 | B13: Fútbol, cuello camisero | C13: Camiseta | D13: Femenino | E13: Camiseta De Futbol | J13: =IF(A13="","",COUNTIF(Despiece!$A$5:$A$1004,A13)) -> 4 | L13: =IF(A13="","",IF(COUNTIFS(Despiece!$A$5:$A$1004,A13,Despiece!$D$5:$D$1004,">0")<J13,"",IF(COUNTIFS(Despiece!$A$5:$A$1004,A13,Despiece!$G$5:$G$1004,"falta*")>0,"",SUMIFS(Despiece!$G$5:$G$1004,Despiece!$A$5:$A$1004,A13)))) | M13: =IF(OR(A13="",E13=""),"",IFERROR(INDEX(Precios!$K$5:$K$84,MATCH(E13,Precios!$J$5:$J$84,0)),"")) -> 2000 | N13: =IF(A13="","",IFERROR(N(G13)*IF(F13="",0,INDEX(Precios!$N$5:$N$64,MATCH(F13,Precios!$M$5:$M$64,0)))+N(I13)*IF(H13="",0,INDEX(Precios!$N$5:$N$64,MATCH(H13,Precios!$M$5:$M$64,0))),"")) -> 0 | O13: =IF(A13="","",IFERROR(L13+M13+N13,"")) | P13: =IF(A13="","",IF(ISNUMBER(O13),"Lista"&IF(N(Precios!$Q$10)=0," (impresión en $0)",""),IF(J13=0,"Agregar piezas en Despiece. ",IF(COUNTIFS(Despiece!$A$5:$A$1004,A13,Despiece!$D$5:$D$1004,">0")<J13,"Metros de "&(J13-COUNTIFS(Despiece!$A$5:$A$1004,A13,Despiece!$D$5:$D$1004,">0"))&" pieza(s). ",""))&IF(COUNTIFS(Despiece!$A$5:$A$1004,A13,Despiece!$G$5:$G$1004,"falta*")>0,"Precio o peso de 1 m de alguna tela. ","")&IF(M13="","Tipo/precio de confección. ",""))) -> Metros de 4 pieza(s).
A14: 10 · FUTHOMCC01 | B14: Fútbol, cuello camisero | C14: Camiseta | D14: Masculino | E14: Camiseta De Futbol | J14: =IF(A14="","",COUNTIF(Despiece!$A$5:$A$1004,A14)) -> 4 | L14: =IF(A14="","",IF(COUNTIFS(Despiece!$A$5:$A$1004,A14,Despiece!$D$5:$D$1004,">0")<J14,"",IF(COUNTIFS(Despiece!$A$5:$A$1004,A14,Despiece!$G$5:$G$1004,"falta*")>0,"",SUMIFS(Despiece!$G$5:$G$1004,Despiece!$A$5:$A$1004,A14)))) | M14: =IF(OR(A14="",E14=""),"",IFERROR(INDEX(Precios!$K$5:$K$84,MATCH(E14,Precios!$J$5:$J$84,0)),"")) -> 2000 | N14: =IF(A14="","",IFERROR(N(G14)*IF(F14="",0,INDEX(Precios!$N$5:$N$64,MATCH(F14,Precios!$M$5:$M$64,0)))+N(I14)*IF(H14="",0,INDEX(Precios!$N$5:$N$64,MATCH(H14,Precios!$M$5:$M$64,0))),"")) -> 0 | O14: =IF(A14="","",IFERROR(L14+M14+N14,"")) | P14: =IF(A14="","",IF(ISNUMBER(O14),"Lista"&IF(N(Precios!$Q$10)=0," (impresión en $0)",""),IF(J14=0,"Agregar piezas en Despiece. ",IF(COUNTIFS(Despiece!$A$5:$A$1004,A14,Despiece!$D$5:$D$1004,">0")<J14,"Metros de "&(J14-COUNTIFS(Despiece!$A$5:$A$1004,A14,Despiece!$D$5:$D$1004,">0"))&" pieza(s). ",""))&IF(COUNTIFS(Despiece!$A$5:$A$1004,A14,Despiece!$G$5:$G$1004,"falta*")>0,"Precio o peso de 1 m de alguna tela. ","")&IF(M14="","Tipo/precio de confección. ",""))) -> Metros de 4 pieza(s).
A15: 11 · FUTINMUJCC01 | B15: Fútbol infantil, cuello camisero | C15: Camiseta | D15: Infantil Femenino | E15: Camiseta De Futbol | J15: =IF(A15="","",COUNTIF(Despiece!$A$5:$A$1004,A15)) -> 4 | L15: =IF(A15="","",IF(COUNTIFS(Despiece!$A$5:$A$1004,A15,Despiece!$D$5:$D$1004,">0")<J15,"",IF(COUNTIFS(Despiece!$A$5:$A$1004,A15,Despiece!$G$5:$G$1004,"falta*")>0,"",SUMIFS(Despiece!$G$5:$G$1004,Despiece!$A$5:$A$1004,A15)))) | M15: =IF(OR(A15="",E15=""),"",IFERROR(INDEX(Precios!$K$5:$K$84,MATCH(E15,Precios!$J$5:$J$84,0)),"")) -> 2000 | N15: =IF(A15="","",IFERROR(N(G15)*IF(F15="",0,INDEX(Precios!$N$5:$N$64,MATCH(F15,Precios!$M$5:$M$64,0)))+N(I15)*IF(H15="",0,INDEX(Precios!$N$5:$N$64,MATCH(H15,Precios!$M$5:$M$64,0))),"")) -> 0 | O15: =IF(A15="","",IFERROR(L15+M15+N15,"")) | P15: =IF(A15="","",IF(ISNUMBER(O15),"Lista"&IF(N(Precios!$Q$10)=0," (impresión en $0)",""),IF(J15=0,"Agregar piezas en Despiece. ",IF(COUNTIFS(Despiece!$A$5:$A$1004,A15,Despiece!$D$5:$D$1004,">0")<J15,"Metros de "&(J15-COUNTIFS(Despiece!$A$5:$A$1004,A15,Despiece!$D$5:$D$1004,">0"))&" pieza(s). ",""))&IF(COUNTIFS(Despiece!$A$5:$A$1004,A15,Despiece!$G$5:$G$1004,"falta*")>0,"Precio o peso de 1 m de alguna tela. ","")&IF(M15="","Tipo/precio de confección. ",""))) -> Metros de 4 pieza(s).
A16: 12 · FUTINHOMCC01 | B16: Fútbol infantil, cuello camisero | C16: Camiseta | D16: Infantil Masculino | E16: Camiseta De Futbol | J16: =IF(A16="","",COUNTIF(Despiece!$A$5:$A$1004,A16)) -> 4 | L16: =IF(A16="","",IF(COUNTIFS(Despiece!$A$5:$A$1004,A16,Despiece!$D$5:$D$1004,">0")<J16,"",IF(COUNTIFS(Despiece!$A$5:$A$1004,A16,Despiece!$G$5:$G$1004,"falta*")>0,"",SUMIFS(Despiece!$G$5:$G$1004,Despiece!$A$5:$A$1004,A16)))) | M16: =IF(OR(A16="",E16=""),"",IFERROR(INDEX(Precios!$K$5:$K$84,MATCH(E16,Precios!$J$5:$J$84,0)),"")) -> 2000 | N16: =IF(A16="","",IFERROR(N(G16)*IF(F16="",0,INDEX(Precios!$N$5:$N$64,MATCH(F16,Precios!$M$5:$M$64,0)))+N(I16)*IF(H16="",0,INDEX(Precios!$N$5:$N$64,MATCH(H16,Precios!$M$5:$M$64,0))),"")) -> 0 | O16: =IF(A16="","",IFERROR(L16+M16+N16,"")) | P16: =IF(A16="","",IF(ISNUMBER(O16),"Lista"&IF(N(Precios!$Q$10)=0," (impresión en $0)",""),IF(J16=0,"Agregar piezas en Despiece. ",IF(COUNTIFS(Despiece!$A$5:$A$1004,A16,Despiece!$D$5:$D$1004,">0")<J16,"Metros de "&(J16-COUNTIFS(Despiece!$A$5:$A$1004,A16,Despiece!$D$5:$D$1004,">0"))&" pieza(s). ",""))&IF(COUNTIFS(Despiece!$A$5:$A$1004,A16,Despiece!$G$5:$G$1004,"falta*")>0,"Precio o peso de 1 m de alguna tela. ","")&IF(M16="","Tipo/precio de confección. ",""))) -> Metros de 4 pieza(s).
A17: 13 · FUTMUJU01PRO | B17: Fútbol, pro, cuello redondo | C17: Camiseta | D17: Femenino | E17: Camiseta De Futbol | J17: =IF(A17="","",COUNTIF(Despiece!$A$5:$A$1004,A17)) -> 5 | L17: =IF(A17="","",IF(COUNTIFS(Despiece!$A$5:$A$1004,A17,Despiece!$D$5:$D$1004,">0")<J17,"",IF(COUNTIFS(Despiece!$A$5:$A$1004,A17,Despiece!$G$5:$G$1004,"falta*")>0,"",SUMIFS(Despiece!$G$5:$G$1004,Despiece!$A$5:$A$1004,A17)))) | M17: =IF(OR(A17="",E17=""),"",IFERROR(INDEX(Precios!$K$5:$K$84,MATCH(E17,Precios!$J$5:$J$84,0)),"")) -> 2000 | N17: =IF(A17="","",IFERROR(N(G17)*IF(F17="",0,INDEX(Precios!$N$5:$N$64,MATCH(F17,Precios!$M$5:$M$64,0)))+N(I17)*IF(H17="",0,INDEX(Precios!$N$5:$N$64,MATCH(H17,Precios!$M$5:$M$64,0))),"")) -> 0 | O17: =IF(A17="","",IFERROR(L17+M17+N17,"")) | P17: =IF(A17="","",IF(ISNUMBER(O17),"Lista"&IF(N(Precios!$Q$10)=0," (impresión en $0)",""),IF(J17=0,"Agregar piezas en Despiece. ",IF(COUNTIFS(Despiece!$A$5:$A$1004,A17,Despiece!$D$5:$D$1004,">0")<J17,"Metros de "&(J17-COUNTIFS(Despiece!$A$5:$A$1004,A17,Despiece!$D$5:$D$1004,">0"))&" pieza(s). ",""))&IF(COUNTIFS(Despiece!$A$5:$A$1004,A17,Despiece!$G$5:$G$1004,"falta*")>0,"Precio o peso de 1 m de alguna tela. ","")&IF(M17="","Tipo/precio de confección. ",""))) -> Metros de 5 pieza(s). | Q17: Corte OT 2257: 0,1225 kg Montesimone por prenda.
A18: 14 · FUTHOMU01PRO | B18: Fútbol, pro, cuello redondo | C18: Camiseta | D18: Masculino | E18: Camiseta De Futbol | J18: =IF(A18="","",COUNTIF(Despiece!$A$5:$A$1004,A18)) -> 5 | L18: =IF(A18="","",IF(COUNTIFS(Despiece!$A$5:$A$1004,A18,Despiece!$D$5:$D$1004,">0")<J18,"",IF(COUNTIFS(Despiece!$A$5:$A$1004,A18,Despiece!$G$5:$G$1004,"falta*")>0,"",SUMIFS(Despiece!$G$5:$G$1004,Despiece!$A$5:$A$1004,A18)))) | M18: =IF(OR(A18="",E18=""),"",IFERROR(INDEX(Precios!$K$5:$K$84,MATCH(E18,Precios!$J$5:$J$84,0)),"")) -> 2000 | N18: =IF(A18="","",IFERROR(N(G18)*IF(F18="",0,INDEX(Precios!$N$5:$N$64,MATCH(F18,Precios!$M$5:$M$64,0)))+N(I18)*IF(H18="",0,INDEX(Precios!$N$5:$N$64,MATCH(H18,Precios!$M$5:$M$64,0))),"")) -> 0 | O18: =IF(A18="","",IFERROR(L18+M18+N18,"")) | P18: =IF(A18="","",IF(ISNUMBER(O18),"Lista"&IF(N(Precios!$Q$10)=0," (impresión en $0)",""),IF(J18=0,"Agregar piezas en Despiece. ",IF(COUNTIFS(Despiece!$A$5:$A$1004,A18,Despiece!$D$5:$D$1004,">0")<J18,"Metros de "&(J18-COUNTIFS(Despiece!$A$5:$A$1004,A18,Despiece!$D$5:$D$1004,">0"))&" pieza(s). ",""))&IF(COUNTIFS(Despiece!$A$5:$A$1004,A18,Despiece!$G$5:$G$1004,"falta*")>0,"Precio o peso de 1 m de alguna tela. ","")&IF(M18="","Tipo/precio de confección. ",""))) -> Metros de 5 pieza(s). | Q18: Corte OT 2547: 0,12 kg Montesimone + 0,0775 kg Mesh por prenda.
A19: 15 · FUTMUJV01PRO | B19: Fútbol, pro, cuello v | C19: Camiseta | D19: Femenino | E19: Camiseta De Futbol | J19: =IF(A19="","",COUNTIF(Despiece!$A$5:$A$1004,A19)) -> 5 | L19: =IF(A19="","",IF(COUNTIFS(Despiece!$A$5:$A$1004,A19,Despiece!$D$5:$D$1004,">0")<J19,"",IF(COUNTIFS(Despiece!$A$5:$A$1004,A19,Despiece!$G$5:$G$1004,"falta*")>0,"",SUMIFS(Despiece!$G$5:$G$1004,Despiece!$A$5:$A$1004,A19)))) | M19: =IF(OR(A19="",E19=""),"",IFERROR(INDEX(Precios!$K$5:$K$84,MATCH(E19,Precios!$J$5:$J$84,0)),"")) -> 2000 | N19: =IF(A19="","",IFERROR(N(G19)*IF(F19="",0,INDEX(Precios!$N$5:$N$64,MATCH(F19,Precios!$M$5:$M$64,0)))+N(I19)*IF(H19="",0,INDEX(Precios!$N$5:$N$64,MATCH(H19,Precios!$M$5:$M$64,0))),"")) -> 0 | O19: =IF(A19="","",IFERROR(L19+M19+N19,"")) | P19: =IF(A19="","",IF(ISNUMBER(O19),"Lista"&IF(N(Precios!$Q$10)=0," (impresión en $0)",""),IF(J19=0,"Agregar piezas en Despiece. ",IF(COUNTIFS(Despiece!$A$5:$A$1004,A19,Despiece!$D$5:$D$1004,">0")<J19,"Metros de "&(J19-COUNTIFS(Despiece!$A$5:$A$1004,A19,Despiece!$D$5:$D$1004,">0"))&" pieza(s). ",""))&IF(COUNTIFS(Despiece!$A$5:$A$1004,A19,Despiece!$G$5:$G$1004,"falta*")>0,"Precio o peso de 1 m de alguna tela. ","")&IF(M19="","Tipo/precio de confección. ",""))) -> Metros de 5 pieza(s).
A20: 16 · FUTHOMV01PRO | B20: Fútbol, pro, cuello v | C20: Camiseta | D20: Masculino | E20: Camiseta De Futbol | J20: =IF(A20="","",COUNTIF(Despiece!$A$5:$A$1004,A20)) -> 5 | L20: =IF(A20="","",IF(COUNTIFS(Despiece!$A$5:$A$1004,A20,Despiece!$D$5:$D$1004,">0")<J20,"",IF(COUNTIFS(Despiece!$A$5:$A$1004,A20,Despiece!$G$5:$G$1004,"falta*")>0,"",SUMIFS(Despiece!$G$5:$G$1004,Despiece!$A$5:$A$1004,A20)))) | M20: =IF(OR(A20="",E20=""),"",IFERROR(INDEX(Precios!$K$5:$K$84,MATCH(E20,Precios!$J$5:$J$84,0)),"")) -> 2000 | N20: =IF(A20="","",IFERROR(N(G20)*IF(F20="",0,INDEX(Precios!$N$5:$N$64,MATCH(F20,Precios!$M$5:$M$64,0)))+N(I20)*IF(H20="",0,INDEX(Precios!$N$5:$N$64,MATCH(H20,Precios!$M$5:$M$64,0))),"")) -> 0 | O20: =IF(A20="","",IFERROR(L20+M20+N20,"")) | P20: =IF(A20="","",IF(ISNUMBER(O20),"Lista"&IF(N(Precios!$Q$10)=0," (impresión en $0)",""),IF(J20=0,"Agregar piezas en Despiece. ",IF(COUNTIFS(Despiece!$A$5:$A$1004,A20,Despiece!$D$5:$D$1004,">0")<J20,"Metros de "&(J20-COUNTIFS(Despiece!$A$5:$A$1004,A20,Despiece!$D$5:$D$1004,">0"))&" pieza(s). ",""))&IF(COUNTIFS(Despiece!$A$5:$A$1004,A20,Despiece!$G$5:$G$1004,"falta*")>0,"Precio o peso de 1 m de alguna tela. ","")&IF(M20="","Tipo/precio de confección. ",""))) -> Metros de 5 pieza(s).
A21: 17 · FUTMUJU02 | B21: Fútbol, raglán, cuello redondo | C21: Camiseta | D21: Femenino | E21: Camiseta Futbol Molde 2026 (Raglan) | J21: =IF(A21="","",COUNTIF(Despiece!$A$5:$A$1004,A21)) -> 4 | L21: =IF(A21="","",IF(COUNTIFS(Despiece!$A$5:$A$1004,A21,Despiece!$D$5:$D$1004,">0")<J21,"",IF(COUNTIFS(Despiece!$A$5:$A$1004,A21,Despiece!$G$5:$G$1004,"falta*")>0,"",SUMIFS(Despiece!$G$5:$G$1004,Despiece!$A$5:$A$1004,A21)))) | M21: =IF(OR(A21="",E21=""),"",IFERROR(INDEX(Precios!$K$5:$K$84,MATCH(E21,Precios!$J$5:$J$84,0)),"")) -> 2300 | N21: =IF(A21="","",IFERROR(N(G21)*IF(F21="",0,INDEX(Precios!$N$5:$N$64,MATCH(F21,Precios!$M$5:$M$64,0)))+N(I21)*IF(H21="",0,INDEX(Precios!$N$5:$N$64,MATCH(H21,Precios!$M$5:$M$64,0))),"")) -> 0 | O21: =IF(A21="","",IFERROR(L21+M21+N21,"")) | P21: =IF(A21="","",IF(ISNUMBER(O21),"Lista"&IF(N(Precios!$Q$10)=0," (impresión en $0)",""),IF(J21=0,"Agregar piezas en Despiece. ",IF(COUNTIFS(Despiece!$A$5:$A$1004,A21,Despiece!$D$5:$D$1004,">0")<J21,"Metros de "&(J21-COUNTIFS(Despiece!$A$5:$A$1004,A21,Despiece!$D$5:$D$1004,">0"))&" pieza(s). ",""))&IF(COUNTIFS(Despiece!$A$5:$A$1004,A21,Despiece!$G$5:$G$1004,"falta*")>0,"Precio o peso de 1 m de alguna tela. ","")&IF(M21="","Tipo/precio de confección. ",""))) -> Metros de 4 pieza(s).
A22: 18 · FUTHOMU02 | B22: Fútbol, raglán, cuello redondo | C22: Camiseta | D22: Masculino | E22: Camiseta Futbol Molde 2026 (Raglan) | J22: =IF(A22="","",COUNTIF(Despiece!$A$5:$A$1004,A22)) -> 4 | L22: =IF(A22="","",IF(COUNTIFS(Despiece!$A$5:$A$1004,A22,Despiece!$D$5:$D$1004,">0")<J22,"",IF(COUNTIFS(Despiece!$A$5:$A$1004,A22,Despiece!$G$5:$G$1004,"falta*")>0,"",SUMIFS(Despiece!$G$5:$G$1004,Despiece!$A$5:$A$1004,A22)))) | M22: =IF(OR(A22="",E22=""),"",IFERROR(INDEX(Precios!$K$5:$K$84,MATCH(E22,Precios!$J$5:$J$84,0)),"")) -> 2300 | N22: =IF(A22="","",IFERROR(N(G22)*IF(F22="",0,INDEX(Precios!$N$5:$N$64,MATCH(F22,Precios!$M$5:$M$64,0)))+N(I22)*IF(H22="",0,INDEX(Precios!$N$5:$N$64,MATCH(H22,Precios!$M$5:$M$64,0))),"")) -> 0 | O22: =IF(A22="","",IFERROR(L22+M22+N22,"")) | P22: =IF(A22="","",IF(ISNUMBER(O22),"Lista"&IF(N(Precios!$Q$10)=0," (impresión en $0)",""),IF(J22=0,"Agregar piezas en Despiece. ",IF(COUNTIFS(Despiece!$A$5:$A$1004,A22,Despiece!$D$5:$D$1004,">0")<J22,"Metros de "&(J22-COUNTIFS(Despiece!$A$5:$A$1004,A22,Despiece!$D$5:$D$1004,">0"))&" pieza(s). ",""))&IF(COUNTIFS(Despiece!$A$5:$A$1004,A22,Despiece!$G$5:$G$1004,"falta*")>0,"Precio o peso de 1 m de alguna tela. ","")&IF(M22="","Tipo/precio de confección. ",""))) -> Metros de 4 pieza(s).
A23: 19 · FUTINMUJU02 | B23: Fútbol infantil, raglán, cuello redondo | C23: Camiseta | D23: Infantil Femenino | E23: Camiseta Futbol Molde 2026 (Raglan) | J23: =IF(A23="","",COUNTIF(Despiece!$A$5:$A$1004,A23)) -> 4 | L23: =IF(A23="","",IF(COUNTIFS(Despiece!$A$5:$A$1004,A23,Despiece!$D$5:$D$1004,">0")<J23,"",IF(COUNTIFS(Despiece!$A$5:$A$1004,A23,Despiece!$G$5:$G$1004,"falta*")>0,"",SUMIFS(Despiece!$G$5:$G$1004,Despiece!$A$5:$A$1004,A23)))) | M23: =IF(OR(A23="",E23=""),"",IFERROR(INDEX(Precios!$K$5:$K$84,MATCH(E23,Precios!$J$5:$J$84,0)),"")) -> 2300 | N23: =IF(A23="","",IFERROR(N(G23)*IF(F23="",0,INDEX(Precios!$N$5:$N$64,MATCH(F23,Precios!$M$5:$M$64,0)))+N(I23)*IF(H23="",0,INDEX(Precios!$N$5:$N$64,MATCH(H23,Precios!$M$5:$M$64,0))),"")) -> 0 | O23: =IF(A23="","",IFERROR(L23+M23+N23,"")) | P23: =IF(A23="","",IF(ISNUMBER(O23),"Lista"&IF(N(Precios!$Q$10)=0," (impresión en $0)",""),IF(J23=0,"Agregar piezas en Despiece. ",IF(COUNTIFS(Despiece!$A$5:$A$1004,A23,Despiece!$D$5:$D$1004,">0")<J23,"Metros de "&(J23-COUNTIFS(Despiece!$A$5:$A$1004,A23,Despiece!$D$5:$D$1004,">0"))&" pieza(s). ",""))&IF(COUNTIFS(Despiece!$A$5:$A$1004,A23,Despiece!$G$5:$G$1004,"falta*")>0,"Precio o peso de 1 m de alguna tela. ","")&IF(M23="","Tipo/precio de confección. ",""))) -> Metros de 4 pieza(s).
A24: 20 · FUTINHOMU02 | B24: Fútbol infantil, raglán, cuello redondo | C24: Camiseta | D24: Infantil Masculino | E24: Camiseta Futbol Molde 2026 (Raglan) | J24: =IF(A24="","",COUNTIF(Despiece!$A$5:$A$1004,A24)) -> 4 | L24: =IF(A24="","",IF(COUNTIFS(Despiece!$A$5:$A$1004,A24,Despiece!$D$5:$D$1004,">0")<J24,"",IF(COUNTIFS(Despiece!$A$5:$A$1004,A24,Despiece!$G$5:$G$1004,"falta*")>0,"",SUMIFS(Despiece!$G$5:$G$1004,Despiece!$A$5:$A$1004,A24)))) | M24: =IF(OR(A24="",E24=""),"",IFERROR(INDEX(Precios!$K$5:$K$84,MATCH(E24,Precios!$J$5:$J$84,0)),"")) -> 2300 | N24: =IF(A24="","",IFERROR(N(G24)*IF(F24="",0,INDEX(Precios!$N$5:$N$64,MATCH(F24,Precios!$M$5:$M$64,0)))+N(I24)*IF(H24="",0,INDEX(Precios!$N$5:$N$64,MATCH(H24,Precios!$M$5:$M$64,0))),"")) -> 0 | O24: =IF(A24="","",IFERROR(L24+M24+N24,"")) | P24: =IF(A24="","",IF(ISNUMBER(O24),"Lista"&IF(N(Precios!$Q$10)=0," (impresión en $0)",""),IF(J24=0,"Agregar piezas en Despiece. ",IF(COUNTIFS(Despiece!$A$5:$A$1004,A24,Despiece!$D$5:$D$1004,">0")<J24,"Metros de "&(J24-COUNTIFS(Despiece!$A$5:$A$1004,A24,Despiece!$D$5:$D$1004,">0"))&" pieza(s). ",""))&IF(COUNTIFS(Despiece!$A$5:$A$1004,A24,Despiece!$G$5:$G$1004,"falta*")>0,"Precio o peso de 1 m de alguna tela. ","")&IF(M24="","Tipo/precio de confección. ",""))) -> Metros de 4 pieza(s).
A25: 21 · FUTMUJV02 | B25: Fútbol, raglán, cuello v | C25: Camiseta | D25: Femenino | E25: Camiseta Futbol Molde 2026 (Raglan) | J25: =IF(A25="","",COUNTIF(Despiece!$A$5:$A$1004,A25)) -> 4 | L25: =IF(A25="","",IF(COUNTIFS(Despiece!$A$5:$A$1004,A25,Despiece!$D$5:$D$1004,">0")<J25,"",IF(COUNTIFS(Despiece!$A$5:$A$1004,A25,Despiece!$G$5:$G$1004,"falta*")>0,"",SUMIFS(Despiece!$G$5:$G$1004,Despiece!$A$5:$A$1004,A25)))) | M25: =IF(OR(A25="",E25=""),"",IFERROR(INDEX(Precios!$K$5:$K$84,MATCH(E25,Precios!$J$5:$J$84,0)),"")) -> 2300 | N25: =IF(A25="","",IFERROR(N(G25)*IF(F25="",0,INDEX(Precios!$N$5:$N$64,MATCH(F25,Precios!$M$5:$M$64,0)))+N(I25)*IF(H25="",0,INDEX(Precios!$N$5:$N$64,MATCH(H25,Precios!$M$5:$M$64,0))),"")) -> 0 | O25: =IF(A25="","",IFERROR(L25+M25+N25,"")) | P25: =IF(A25="","",IF(ISNUMBER(O25),"Lista"&IF(N(Precios!$Q$10)=0," (impresión en $0)",""),IF(J25=0,"Agregar piezas en Despiece. ",IF(COUNTIFS(Despiece!$A$5:$A$1004,A25,Despiece!$D$5:$D$1004,">0")<J25,"Metros de "&(J25-COUNTIFS(Despiece!$A$5:$A$1004,A25,Despiece!$D$5:$D$1004,">0"))&" pieza(s). ",""))&IF(COUNTIFS(Despiece!$A$5:$A$1004,A25,Despiece!$G$5:$G$1004,"falta*")>0,"Precio o peso de 1 m de alguna tela. ","")&IF(M25="","Tipo/precio de confección. ",""))) -> Metros de 4 pieza(s).
A26: 22 · FUTHOMV02 | B26: Fútbol, raglán, cuello v | C26: Camiseta | D26: Masculino | E26: Camiseta Futbol Molde 2026 (Raglan) | J26: =IF(A26="","",COUNTIF(Despiece!$A$5:$A$1004,A26)) -> 4 | L26: =IF(A26="","",IF(COUNTIFS(Despiece!$A$5:$A$1004,A26,Despiece!$D$5:$D$1004,">0")<J26,"",IF(COUNTIFS(Despiece!$A$5:$A$1004,A26,Despiece!$G$5:$G$1004,"falta*")>0,"",SUMIFS(Despiece!$G$5:$G$1004,Despiece!$A$5:$A$1004,A26)))) | M26: =IF(OR(A26="",E26=""),"",IFERROR(INDEX(Precios!$K$5:$K$84,MATCH(E26,Precios!$J$5:$J$84,0)),"")) -> 2300 | N26: =IF(A26="","",IFERROR(N(G26)*IF(F26="",0,INDEX(Precios!$N$5:$N$64,MATCH(F26,Precios!$M$5:$M$64,0)))+N(I26)*IF(H26="",0,INDEX(Precios!$N$5:$N$64,MATCH(H26,Precios!$M$5:$M$64,0))),"")) -> 0 | O26: =IF(A26="","",IFERROR(L26+M26+N26,"")) | P26: =IF(A26="","",IF(ISNUMBER(O26),"Lista"&IF(N(Precios!$Q$10)=0," (impresión en $0)",""),IF(J26=0,"Agregar piezas en Despiece. ",IF(COUNTIFS(Despiece!$A$5:$A$1004,A26,Despiece!$D$5:$D$1004,">0")<J26,"Metros de "&(J26-COUNTIFS(Despiece!$A$5:$A$1004,A26,Despiece!$D$5:$D$1004,">0"))&" pieza(s). ",""))&IF(COUNTIFS(Despiece!$A$5:$A$1004,A26,Despiece!$G$5:$G$1004,"falta*")>0,"Precio o peso de 1 m de alguna tela. ","")&IF(M26="","Tipo/precio de confección. ",""))) -> Metros de 4 pieza(s).
A27: 23 · FUTINMUJV02 | B27: Fútbol infantil, raglán, cuello v | C27: Camiseta | D27: Infantil Femenino | E27: Camiseta Futbol Molde 2026 (Raglan) | J27: =IF(A27="","",COUNTIF(Despiece!$A$5:$A$1004,A27)) -> 4 | L27: =IF(A27="","",IF(COUNTIFS(Despiece!$A$5:$A$1004,A27,Despiece!$D$5:$D$1004,">0")<J27,"",IF(COUNTIFS(Despiece!$A$5:$A$1004,A27,Despiece!$G$5:$G$1004,"falta*")>0,"",SUMIFS(Despiece!$G$5:$G$1004,Despiece!$A$5:$A$1004,A27)))) | M27: =IF(OR(A27="",E27=""),"",IFERROR(INDEX(Precios!$K$5:$K$84,MATCH(E27,Precios!$J$5:$J$84,0)),"")) -> 2300 | N27: =IF(A27="","",IFERROR(N(G27)*IF(F27="",0,INDEX(Precios!$N$5:$N$64,MATCH(F27,Precios!$M$5:$M$64,0)))+N(I27)*IF(H27="",0,INDEX(Precios!$N$5:$N$64,MATCH(H27,Precios!$M$5:$M$64,0))),"")) -> 0 | O27: =IF(A27="","",IFERROR(L27+M27+N27,"")) | P27: =IF(A27="","",IF(ISNUMBER(O27),"Lista"&IF(N(Precios!$Q$10)=0," (impresión en $0)",""),IF(J27=0,"Agregar piezas en Despiece. ",IF(COUNTIFS(Despiece!$A$5:$A$1004,A27,Despiece!$D$5:$D$1004,">0")<J27,"Metros de "&(J27-COUNTIFS(Despiece!$A$5:$A$1004,A27,Despiece!$D$5:$D$1004,">0"))&" pieza(s). ",""))&IF(COUNTIFS(Despiece!$A$5:$A$1004,A27,Despiece!$G$5:$G$1004,"falta*")>0,"Precio o peso de 1 m de alguna tela. ","")&IF(M27="","Tipo/precio de confección. ",""))) -> Metros de 4 pieza(s).
A28: 24 · FUTINHOMV02 | B28: Fútbol infantil, raglán, cuello v | C28: Camiseta | D28: Infantil Masculino | E28: Camiseta Futbol Molde 2026 (Raglan) | J28: =IF(A28="","",COUNTIF(Despiece!$A$5:$A$1004,A28)) -> 4 | L28: =IF(A28="","",IF(COUNTIFS(Despiece!$A$5:$A$1004,A28,Despiece!$D$5:$D$1004,">0")<J28,"",IF(COUNTIFS(Despiece!$A$5:$A$1004,A28,Despiece!$G$5:$G$1004,"falta*")>0,"",SUMIFS(Despiece!$G$5:$G$1004,Despiece!$A$5:$A$1004,A28)))) | M28: =IF(OR(A28="",E28=""),"",IFERROR(INDEX(Precios!$K$5:$K$84,MATCH(E28,Precios!$J$5:$J$84,0)),"")) -> 2300 | N28: =IF(A28="","",IFERROR(N(G28)*IF(F28="",0,INDEX(Precios!$N$5:$N$64,MATCH(F28,Precios!$M$5:$M$64,0)))+N(I28)*IF(H28="",0,INDEX(Precios!$N$5:$N$64,MATCH(H28,Precios!$M$5:$M$64,0))),"")) -> 0 | O28: =IF(A28="","",IFERROR(L28+M28+N28,"")) | P28: =IF(A28="","",IF(ISNUMBER(O28),"Lista"&IF(N(Precios!$Q$10)=0," (impresión en $0)",""),IF(J28=0,"Agregar piezas en Despiece. ",IF(COUNTIFS(Despiece!$A$5:$A$1004,A28,Despiece!$D$5:$D$1004,">0")<J28,"Metros de "&(J28-COUNTIFS(Despiece!$A$5:$A$1004,A28,Despiece!$D$5:$D$1004,">0"))&" pieza(s). ",""))&IF(COUNTIFS(Despiece!$A$5:$A$1004,A28,Despiece!$G$5:$G$1004,"falta*")>0,"Precio o peso de 1 m de alguna tela. ","")&IF(M28="","Tipo/precio de confección. ",""))) -> Metros de 4 pieza(s).
A29: 25 · FUTMUJU02PRO | B29: Fútbol, raglán, pro, cuello redondo | C29: Camiseta | D29: Femenino | E29: Camiseta Futbol Molde 2026 (Raglan) | J29: =IF(A29="","",COUNTIF(Despiece!$A$5:$A$1004,A29)) -> 5 | L29: =IF(A29="","",IF(COUNTIFS(Despiece!$A$5:$A$1004,A29,Despiece!$D$5:$D$1004,">0")<J29,"",IF(COUNTIFS(Despiece!$A$5:$A$1004,A29,Despiece!$G$5:$G$1004,"falta*")>0,"",SUMIFS(Despiece!$G$5:$G$1004,Despiece!$A$5:$A$1004,A29)))) | M29: =IF(OR(A29="",E29=""),"",IFERROR(INDEX(Precios!$K$5:$K$84,MATCH(E29,Precios!$J$5:$J$84,0)),"")) -> 2300 | N29: =IF(A29="","",IFERROR(N(G29)*IF(F29="",0,INDEX(Precios!$N$5:$N$64,MATCH(F29,Precios!$M$5:$M$64,0)))+N(I29)*IF(H29="",0,INDEX(Precios!$N$5:$N$64,MATCH(H29,Precios!$M$5:$M$64,0))),"")) -> 0 | O29: =IF(A29="","",IFERROR(L29+M29+N29,"")) | P29: =IF(A29="","",IF(ISNUMBER(O29),"Lista"&IF(N(Precios!$Q$10)=0," (impresión en $0)",""),IF(J29=0,"Agregar piezas en Despiece. ",IF(COUNTIFS(Despiece!$A$5:$A$1004,A29,Despiece!$D$5:$D$1004,">0")<J29,"Metros de "&(J29-COUNTIFS(Despiece!$A$5:$A$1004,A29,Despiece!$D$5:$D$1004,">0"))&" pieza(s). ",""))&IF(COUNTIFS(Despiece!$A$5:$A$1004,A29,Despiece!$G$5:$G$1004,"falta*")>0,"Precio o peso de 1 m de alguna tela. ","")&IF(M29="","Tipo/precio de confección. ",""))) -> Metros de 5 pieza(s).
A30: 26 · FUTHOMU02PRO | B30: Fútbol, raglán, pro, cuello redondo | C30: Camiseta | D30: Masculino | E30: Camiseta Futbol Molde 2026 (Raglan) | J30: =IF(A30="","",COUNTIF(Despiece!$A$5:$A$1004,A30)) -> 5 | L30: =IF(A30="","",IF(COUNTIFS(Despiece!$A$5:$A$1004,A30,Despiece!$D$5:$D$1004,">0")<J30,"",IF(COUNTIFS(Despiece!$A$5:$A$1004,A30,Despiece!$G$5:$G$1004,"falta*")>0,"",SUMIFS(Despiece!$G$5:$G$1004,Despiece!$A$5:$A$1004,A30)))) | M30: =IF(OR(A30="",E30=""),"",IFERROR(INDEX(Precios!$K$5:$K$84,MATCH(E30,Precios!$J$5:$J$84,0)),"")) -> 2300 | N30: =IF(A30="","",IFERROR(N(G30)*IF(F30="",0,INDEX(Precios!$N$5:$N$64,MATCH(F30,Precios!$M$5:$M$64,0)))+N(I30)*IF(H30="",0,INDEX(Precios!$N$5:$N$64,MATCH(H30,Precios!$M$5:$M$64,0))),"")) -> 0 | O30: =IF(A30="","",IFERROR(L30+M30+N30,"")) | P30: =IF(A30="","",IF(ISNUMBER(O30),"Lista"&IF(N(Precios!$Q$10)=0," (impresión en $0)",""),IF(J30=0,"Agregar piezas en Despiece. ",IF(COUNTIFS(Despiece!$A$5:$A$1004,A30,Despiece!$D$5:$D$1004,">0")<J30,"Metros de "&(J30-COUNTIFS(Despiece!$A$5:$A$1004,A30,Despiece!$D$5:$D$1004,">0"))&" pieza(s). ",""))&IF(COUNTIFS(Despiece!$A$5:$A$1004,A30,Despiece!$G$5:$G$1004,"falta*")>0,"Precio o peso de 1 m de alguna tela. ","")&IF(M30="","Tipo/precio de confección. ",""))) -> Metros de 5 pieza(s).
... A33: 29 · BKMUJU03 | B33: Básquetbol, cuello redondo | C33: Camiseta | D33: Femenino | E33: Camiseta De Basket | J33: =IF(A33="","",COUNTIF(Despiece!$A$5:$A$1004,A33)) -> 3 | L33: =IF(A33="","",IF(COUNTIFS(Despiece!$A$5:$A$1004,A33,Despiece!$D$5:$D$1004,">0")<J33,"",IF(COUNTIFS(Despiece!$A$5:$A$1004,A33,Despiece!$G$5:$G$1004,"falta*")>0,"",SUMIFS(Despiece!$G$5:$G$1004,Despiece!$A$5:$A$1004,A33)))) | M33: =IF(OR(A33="",E33=""),"",IFERROR(INDEX(Precios!$K$5:$K$84,MATCH(E33,Precios!$J$5:$J$84,0)),"")) -> 1900 | N33: =IF(A33="","",IFERROR(N(G33)*IF(F33="",0,INDEX(Precios!$N$5:$N$64,MATCH(F33,Precios!$M$5:$M$64,0)))+N(I33)*IF(H33="",0,INDEX(Precios!$N$5:$N$64,MATCH(H33,Precios!$M$5:$M$64,0))),"")) -> 0 | O33: =IF(A33="","",IFERROR(L33+M33+N33,"")) | P33: =IF(A33="","",IF(ISNUMBER(O33),"Lista"&IF(N(Precios!$Q$10)=0," (impresión en $0)",""),IF(J33=0,"Agregar piezas en Despiece. ",IF(COUNTIFS(Despiece!$A$5:$A$1004,A33,Despiece!$D$5:$D$1004,">0")<J33,"Metros de "&(J33-COUNTIFS(Despiece!$A$5:$A$1004,A33,Despiece!$D$5:$D$1004,">0"))&" pieza(s). ",""))&IF(COUNTIFS(Despiece!$A$5:$A$1004,A33,Despiece!$G$5:$G$1004,"falta*")>0,"Precio o peso de 1 m de alguna tela. ","")&IF(M33="","Tipo/precio de confección. ",""))) -> Metros de 3 pieza(s).
A34: 30 · BKHOMU03 | B34: Básquetbol, cuello redondo | C34: Camiseta | D34: Masculino | E34: Camiseta De Basket | J34: =IF(A34="","",COUNTIF(Despiece!$A$5:$A$1004,A34)) -> 3 | L34: =IF(A34="","",IF(COUNTIFS(Despiece!$A$5:$A$1004,A34,Despiece!$D$5:$D$1004,">0")<J34,"",IF(COUNTIFS(Despiece!$A$5:$A$1004,A34,Despiece!$G$5:$G$1004,"falta*")>0,"",SUMIFS(Despiece!$G$5:$G$1004,Despiece!$A$5:$A$1004,A34)))) | M34: =IF(OR(A34="",E34=""),"",IFERROR(INDEX(Precios!$K$5:$K$84,MATCH(E34,Precios!$J$5:$J$84,0)),"")) -> 1900 | N34: =IF(A34="","",IFERROR(N(G34)*IF(F34="",0,INDEX(Precios!$N$5:$N$64,MATCH(F34,Precios!$M$5:$M$64,0)))+N(I34)*IF(H34="",0,INDEX(Precios!$N$5:$N$64,MATCH(H34,Precios!$M$5:$M$64,0))),"")) -> 0 | O34: =IF(A34="","",IFERROR(L34+M34+N34,"")) | P34: =IF(A34="","",IF(ISNUMBER(O34),"Lista"&IF(N(Precios!$Q$10)=0," (impresión en $0)",""),IF(J34=0,"Agregar piezas en Despiece. ",IF(COUNTIFS(Despiece!$A$5:$A$1004,A34,Despiece!$D$5:$D$1004,">0")<J34,"Metros de "&(J34-COUNTIFS(Despiece!$A$5:$A$1004,A34,Despiece!$D$5:$D$1004,">0"))&" pieza(s). ",""))&IF(COUNTIFS(Despiece!$A$5:$A$1004,A34,Despiece!$G$5:$G$1004,"falta*")>0,"Precio o peso de 1 m de alguna tela. ","")&IF(M34="","Tipo/precio de confección. ",""))) -> Metros de 3 pieza(s). | Q34: Corte OT 2425: 0,2029 kg Quickdry por prenda.
A35: 31 · BKINMUJU03 | B35: Básquetbol infantil, cuello redondo | C35: Camiseta | D35: Infantil Femenino | E35: Camiseta De Basket | J35: =IF(A35="","",COUNTIF(Despiece!$A$5:$A$1004,A35)) -> 3 | L35: =IF(A35="","",IF(COUNTIFS(Despiece!$A$5:$A$1004,A35,Despiece!$D$5:$D$1004,">0")<J35,"",IF(COUNTIFS(Despiece!$A$5:$A$1004,A35,Despiece!$G$5:$G$1004,"falta*")>0,"",SUMIFS(Despiece!$G$5:$G$1004,Despiece!$A$5:$A$1004,A35)))) | M35: =IF(OR(A35="",E35=""),"",IFERROR(INDEX(Precios!$K$5:$K$84,MATCH(E35,Precios!$J$5:$J$84,0)),"")) -> 1900 | N35: =IF(A35="","",IFERROR(N(G35)*IF(F35="",0,INDEX(Precios!$N$5:$N$64,MATCH(F35,Precios!$M$5:$M$64,0)))+N(I35)*IF(H35="",0,INDEX(Precios!$N$5:$N$64,MATCH(H35,Precios!$M$5:$M$64,0))),"")) -> 0 | O35: =IF(A35="","",IFERROR(L35+M35+N35,"")) | P35: =IF(A35="","",IF(ISNUMBER(O35),"Lista"&IF(N(Precios!$Q$10)=0," (impresión en $0)",""),IF(J35=0,"Agregar piezas en Despiece. ",IF(COUNTIFS(Despiece!$A$5:$A$1004,A35,Despiece!$D$5:$D$1004,">0")<J35,"Metros de "&(J35-COUNTIFS(Despiece!$A$5:$A$1004,A35,Despiece!$D$5:$D$1004,">0"))&" pieza(s). ",""))&IF(COUNTIFS(Despiece!$A$5:$A$1004,A35,Despiece!$G$5:$G$1004,"falta*")>0,"Precio o peso de 1 m de alguna tela. ","")&IF(M35="","Tipo/precio de confección. ",""))) -> Metros de 3 pieza(s).
A36: 32 · BKINHOMU03 | B36: Básquetbol infantil, cuello redondo | C36: Camiseta | D36: Infantil Masculino | E36: Camiseta De Basket | J36: =IF(A36="","",COUNTIF(Despiece!$A$5:$A$1004,A36)) -> 3 | L36: =IF(A36="","",IF(COUNTIFS(Despiece!$A$5:$A$1004,A36,Despiece!$D$5:$D$1004,">0")<J36,"",IF(COUNTIFS(Despiece!$A$5:$A$1004,A36,Despiece!$G$5:$G$1004,"falta*")>0,"",SUMIFS(Despiece!$G$5:$G$1004,Despiece!$A$5:$A$1004,A36)))) | M36: =IF(OR(A36="",E36=""),"",IFERROR(INDEX(Precios!$K$5:$K$84,MATCH(E36,Precios!$J$5:$J$84,0)),"")) -> 1900 | N36: =IF(A36="","",IFERROR(N(G36)*IF(F36="",0,INDEX(Precios!$N$5:$N$64,MATCH(F36,Precios!$M$5:$M$64,0)))+N(I36)*IF(H36="",0,INDEX(Precios!$N$5:$N$64,MATCH(H36,Precios!$M$5:$M$64,0))),"")) -> 0 | O36: =IF(A36="","",IFERROR(L36+M36+N36,"")) | P36: =IF(A36="","",IF(ISNUMBER(O36),"Lista"&IF(N(Precios!$Q$10)=0," (impresión en $0)",""),IF(J36=0,"Agregar piezas en Despiece. ",IF(COUNTIFS(Despiece!$A$5:$A$1004,A36,Despiece!$D$5:$D$1004,">0")<J36,"Metros de "&(J36-COUNTIFS(Despiece!$A$5:$A$1004,A36,Despiece!$D$5:$D$1004,">0"))&" pieza(s). ",""))&IF(COUNTIFS(Despiece!$A$5:$A$1004,A36,Despiece!$G$5:$G$1004,"falta*")>0,"Precio o peso de 1 m de alguna tela. ","")&IF(M36="","Tipo/precio de confección. ",""))) -> Metros de 3 pieza(s).
A37: 33 · BKMUJV03 | B37: Básquetbol, cuello v | C37: Camiseta | D37: Femenino | E37: Camiseta De Basket | J37: =IF(A37="","",COUNTIF(Despiece!$A$5:$A$1004,A37)) -> 3 | L37: =IF(A37="","",IF(COUNTIFS(Despiece!$A$5:$A$1004,A37,Despiece!$D$5:$D$1004,">0")<J37,"",IF(COUNTIFS(Despiece!$A$5:$A$1004,A37,Despiece!$G$5:$G$1004,"falta*")>0,"",SUMIFS(Despiece!$G$5:$G$1004,Despiece!$A$5:$A$1004,A37)))) | M37: =IF(OR(A37="",E37=""),"",IFERROR(INDEX(Precios!$K$5:$K$84,MATCH(E37,Precios!$J$5:$J$84,0)),"")) -> 1900 | N37: =IF(A37="","",IFERROR(N(G37)*IF(F37="",0,INDEX(Precios!$N$5:$N$64,MATCH(F37,Precios!$M$5:$M$64,0)))+N(I37)*IF(H37="",0,INDEX(Precios!$N$5:$N$64,MATCH(H37,Precios!$M$5:$M$64,0))),"")) -> 0 | O37: =IF(A37="","",IFERROR(L37+M37+N37,"")) | P37: =IF(A37="","",IF(ISNUMBER(O37),"Lista"&IF(N(Precios!$Q$10)=0," (impresión en $0)",""),IF(J37=0,"Agregar piezas en Despiece. ",IF(COUNTIFS(Despiece!$A$5:$A$1004,A37,Despiece!$D$5:$D$1004,">0")<J37,"Metros de "&(J37-COUNTIFS(Despiece!$A$5:$A$1004,A37,Despiece!$D$5:$D$1004,">0"))&" pieza(s). ",""))&IF(COUNTIFS(Despiece!$A$5:$A$1004,A37,Despiece!$G$5:$G$1004,"falta*")>0,"Precio o peso de 1 m de alguna tela. ","")&IF(M37="","Tipo/precio de confección. ",""))) -> Metros de 3 pieza(s).
A38: 34 · BKHOMV03 | B38: Básquetbol, cuello v | C38: Camiseta | D38: Masculino | E38: Camiseta De Basket | J38: =IF(A38="","",COUNTIF(Despiece!$A$5:$A$1004,A38)) -> 3 | L38: =IF(A38="","",IF(COUNTIFS(Despiece!$A$5:$A$1004,A38,Despiece!$D$5:$D$1004,">0")<J38,"",IF(COUNTIFS(Despiece!$A$5:$A$1004,A38,Despiece!$G$5:$G$1004,"falta*")>0,"",SUMIFS(Despiece!$G$5:$G$1004,Despiece!$A$5:$A$1004,A38)))) | M38: =IF(OR(A38="",E38=""),"",IFERROR(INDEX(Precios!$K$5:$K$84,MATCH(E38,Precios!$J$5:$J$84,0)),"")) -> 1900 | N38: =IF(A38="","",IFERROR(N(G38)*IF(F38="",0,INDEX(Precios!$N$5:$N$64,MATCH(F38,Precios!$M$5:$M$64,0)))+N(I38)*IF(H38="",0,INDEX(Precios!$N$5:$N$64,MATCH(H38,Precios!$M$5:$M$64,0))),"")) -> 0 | O38: =IF(A38="","",IFERROR(L38+M38+N38,"")) | P38: =IF(A38="","",IF(ISNUMBER(O38),"Lista"&IF(N(Precios!$Q$10)=0," (impresión en $0)",""),IF(J38=0,"Agregar piezas en Despiece. ",IF(COUNTIFS(Despiece!$A$5:$A$1004,A38,Despiece!$D$5:$D$1004,">0")<J38,"Metros de "&(J38-COUNTIFS(Despiece!$A$5:$A$1004,A38,Despiece!$D$5:$D$1004,">0"))&" pieza(s). ",""))&IF(COUNTIFS(Despiece!$A$5:$A$1004,A38,Despiece!$G$5:$G$1004,"falta*")>0,"Precio o peso de 1 m de alguna tela. ","")&IF(M38="","Tipo/precio de confección. ",""))) -> Metros de 3 pieza(s).
A39: 35 · BKINMUJV03 | B39: Básquetbol infantil, cuello v | C39: Camiseta | D39: Infantil Femenino | E39: Camiseta De Basket | J39: =IF(A39="","",COUNTIF(Despiece!$A$5:$A$1004,A39)) -> 3 | L39: =IF(A39="","",IF(COUNTIFS(Despiece!$A$5:$A$1004,A39,Despiece!$D$5:$D$1004,">0")<J39,"",IF(COUNTIFS(Despiece!$A$5:$A$1004,A39,Despiece!$G$5:$G$1004,"falta*")>0,"",SUMIFS(Despiece!$G$5:$G$1004,Despiece!$A$5:$A$1004,A39)))) | M39: =IF(OR(A39="",E39=""),"",IFERROR(INDEX(Precios!$K$5:$K$84,MATCH(E39,Precios!$J$5:$J$84,0)),"")) -> 1900 | N39: =IF(A39="","",IFERROR(N(G39)*IF(F39="",0,INDEX(Precios!$N$5:$N$64,MATCH(F39,Precios!$M$5:$M$64,0)))+N(I39)*IF(H39="",0,INDEX(Precios!$N$5:$N$64,MATCH(H39,Precios!$M$5:$M$64,0))),"")) -> 0 | O39: =IF(A39="","",IFERROR(L39+M39+N39,"")) | P39: =IF(A39="","",IF(ISNUMBER(O39),"Lista"&IF(N(Precios!$Q$10)=0," (impresión en $0)",""),IF(J39=0,"Agregar piezas en Despiece. ",IF(COUNTIFS(Despiece!$A$5:$A$1004,A39,Despiece!$D$5:$D$1004,">0")<J39,"Metros de "&(J39-COUNTIFS(Despiece!$A$5:$A$1004,A39,Despiece!$D$5:$D$1004,">0"))&" pieza(s). ",""))&IF(COUNTIFS(Despiece!$A$5:$A$1004,A39,Despiece!$G$5:$G$1004,"falta*")>0,"Precio o peso de 1 m de alguna tela. ","")&IF(M39="","Tipo/precio de confección. ",""))) -> Metros de 3 pieza(s).
A40: 36 · BKINHOMV03 | B40: Básquetbol infantil, cuello v | C40: Camiseta | D40: Infantil Masculino | E40: Camiseta De Basket | J40: =IF(A40="","",COUNTIF(Despiece!$A$5:$A$1004,A40)) -> 3 | L40: =IF(A40="","",IF(COUNTIFS(Despiece!$A$5:$A$1004,A40,Despiece!$D$5:$D$1004,">0")<J40,"",IF(COUNTIFS(Despiece!$A$5:$A$1004,A40,Despiece!$G$5:$G$1004,"falta*")>0,"",SUMIFS(Despiece!$G$5:$G$1004,Despiece!$A$5:$A$1004,A40)))) | M40: =IF(OR(A40="",E40=""),"",IFERROR(INDEX(Precios!$K$5:$K$84,MATCH(E40,Precios!$J$5:$J$84,0)),"")) -> 1900 | N40: =IF(A40="","",IFERROR(N(G40)*IF(F40="",0,INDEX(Precios!$N$5:$N$64,MATCH(F40,Precios!$M$5:$M$64,0)))+N(I40)*IF(H40="",0,INDEX(Precios!$N$5:$N$64,MATCH(H40,Precios!$M$5:$M$64,0))),"")) -> 0 | O40: =IF(A40="","",IFERROR(L40+M40+N40,"")) | P40: =IF(A40="","",IF(ISNUMBER(O40),"Lista"&IF(N(Precios!$Q$10)=0," (impresión en $0)",""),IF(J40=0,"Agregar piezas en Despiece. ",IF(COUNTIFS(Despiece!$A$5:$A$1004,A40,Despiece!$D$5:$D$1004,">0")<J40,"Metros de "&(J40-COUNTIFS(Despiece!$A$5:$A$1004,A40,Despiece!$D$5:$D$1004,">0"))&" pieza(s). ",""))&IF(COUNTIFS(Despiece!$A$5:$A$1004,A40,Despiece!$G$5:$G$1004,"falta*")>0,"Precio o peso de 1 m de alguna tela. ","")&IF(M40="","Tipo/precio de confección. ",""))) -> Metros de 3 pieza(s).
A41: 37 · BKMUJU03RE | B41: Básquetbol, reversible, cuello redondo | C41: Camiseta | D41: Femenino | E41: Camiseta De Basket Reversible | J41: =IF(A41="","",COUNTIF(Despiece!$A$5:$A$1004,A41)) -> 5 | L41: =IF(A41="","",IF(COUNTIFS(Despiece!$A$5:$A$1004,A41,Despiece!$D$5:$D$1004,">0")<J41,"",IF(COUNTIFS(Despiece!$A$5:$A$1004,A41,Despiece!$G$5:$G$1004,"falta*")>0,"",SUMIFS(Despiece!$G$5:$G$1004,Despiece!$A$5:$A$1004,A41)))) | M41: =IF(OR(A41="",E41=""),"",IFERROR(INDEX(Precios!$K$5:$K$84,MATCH(E41,Precios!$J$5:$J$84,0)),"")) -> 2400 | N41: =IF(A41="","",IFERROR(N(G41)*IF(F41="",0,INDEX(Precios!$N$5:$N$64,MATCH(F41,Precios!$M$5:$M$64,0)))+N(I41)*IF(H41="",0,INDEX(Precios!$N$5:$N$64,MATCH(H41,Precios!$M$5:$M$64,0))),"")) -> 0 | O41: =IF(A41="","",IFERROR(L41+M41+N41,"")) | P41: =IF(A41="","",IF(ISNUMBER(O41),"Lista"&IF(N(Precios!$Q$10)=0," (impresión en $0)",""),IF(J41=0,"Agregar piezas en Despiece. ",IF(COUNTIFS(Despiece!$A$5:$A$1004,A41,Despiece!$D$5:$D$1004,">0")<J41,"Metros de "&(J41-COUNTIFS(Despiece!$A$5:$A$1004,A41,Despiece!$D$5:$D$1004,">0"))&" pieza(s). ",""))&IF(COUNTIFS(Despiece!$A$5:$A$1004,A41,Despiece!$G$5:$G$1004,"falta*")>0,"Precio o peso de 1 m de alguna tela. ","")&IF(M41="","Tipo/precio de confección. ",""))) -> Metros de 5 pieza(s).
A42: 38 · BKHOMU03RE | B42: Básquetbol, reversible, cuello redondo | C42: Camiseta | D42: Masculino | E42: Camiseta De Basket Reversible | J42: =IF(A42="","",COUNTIF(Despiece!$A$5:$A$1004,A42)) -> 5 | L42: =IF(A42="","",IF(COUNTIFS(Despiece!$A$5:$A$1004,A42,Despiece!$D$5:$D$1004,">0")<J42,"",IF(COUNTIFS(Despiece!$A$5:$A$1004,A42,Despiece!$G$5:$G$1004,"falta*")>0,"",SUMIFS(Despiece!$G$5:$G$1004,Despiece!$A$5:$A$1004,A42)))) | M42: =IF(OR(A42="",E42=""),"",IFERROR(INDEX(Precios!$K$5:$K$84,MATCH(E42,Precios!$J$5:$J$84,0)),"")) -> 2400 | N42: =IF(A42="","",IFERROR(N(G42)*IF(F42="",0,INDEX(Precios!$N$5:$N$64,MATCH(F42,Precios!$M$5:$M$64,0)))+N(I42)*IF(H42="",0,INDEX(Precios!$N$5:$N$64,MATCH(H42,Precios!$M$5:$M$64,0))),"")) -> 0 | O42: =IF(A42="","",IFERROR(L42+M42+N42,"")) | P42: =IF(A42="","",IF(ISNUMBER(O42),"Lista"&IF(N(Precios!$Q$10)=0," (impresión en $0)",""),IF(J42=0,"Agregar piezas en Despiece. ",IF(COUNTIFS(Despiece!$A$5:$A$1004,A42,Despiece!$D$5:$D$1004,">0")<J42,"Metros de "&(J42-COUNTIFS(Despiece!$A$5:$A$1004,A42,Despiece!$D$5:$D$1004,">0"))&" pieza(s). ",""))&IF(COUNTIFS(Despiece!$A$5:$A$1004,A42,Despiece!$G$5:$G$1004,"falta*")>0,"Precio o peso de 1 m de alguna tela. ","")&IF(M42="","Tipo/precio de confección. ",""))) -> Metros de 5 pieza(s).
A43: 39 · BKINMUJU03 | B43: Básquetbol infantil, reversible, cuello redondo | C43: Camiseta | D43: Infantil Femenino | E43: Camiseta De Basket Reversible | J43: =IF(A43="","",COUNTIF(Despiece!$A$5:$A$1004,A43)) -> 5 | L43: =IF(A43="","",IF(COUNTIFS(Despiece!$A$5:$A$1004,A43,Despiece!$D$5:$D$1004,">0")<J43,"",IF(COUNTIFS(Despiece!$A$5:$A$1004,A43,Despiece!$G$5:$G$1004,"falta*")>0,"",SUMIFS(Despiece!$G$5:$G$1004,Despiece!$A$5:$A$1004,A43)))) | M43: =IF(OR(A43="",E43=""),"",IFERROR(INDEX(Precios!$K$5:$K$84,MATCH(E43,Precios!$J$5:$J$84,0)),"")) -> 2400 | N43: =IF(A43="","",IFERROR(N(G43)*IF(F43="",0,INDEX(Precios!$N$5:$N$64,MATCH(F43,Precios!$M$5:$M$64,0)))+N(I43)*IF(H43="",0,INDEX(Precios!$N$5:$N$64,MATCH(H43,Precios!$M$5:$M$64,0))),"")) -> 0 | O43: =IF(A43="","",IFERROR(L43+M43+N43,"")) | P43: =IF(A43="","",IF(ISNUMBER(O43),"Lista"&IF(N(Precios!$Q$10)=0," (impresión en $0)",""),IF(J43=0,"Agregar piezas en Despiece. ",IF(COUNTIFS(Despiece!$A$5:$A$1004,A43,Despiece!$D$5:$D$1004,">0")<J43,"Metros de "&(J43-COUNTIFS(Despiece!$A$5:$A$1004,A43,Despiece!$D$5:$D$1004,">0"))&" pieza(s). ",""))&IF(COUNTIFS(Despiece!$A$5:$A$1004,A43,Despiece!$G$5:$G$1004,"falta*")>0,"Precio o peso de 1 m de alguna tela. ","")&IF(M43="","Tipo/precio de confección. ",""))) -> Metros de 5 pieza(s).
A44: 40 · BKINHOMU03RE | B44: Básquetbol infantil, reversible, cuello redondo | C44: Camiseta | D44: Infantil Masculino | E44: Camiseta De Basket Reversible | J44: =IF(A44="","",COUNTIF(Despiece!$A$5:$A$1004,A44)) -> 5 | L44: =IF(A44="","",IF(COUNTIFS(Despiece!$A$5:$A$1004,A44,Despiece!$D$5:$D$1004,">0")<J44,"",IF(COUNTIFS(Despiece!$A$5:$A$1004,A44,Despiece!$G$5:$G$1004,"falta*")>0,"",SUMIFS(Despiece!$G$5:$G$1004,Despiece!$A$5:$A$1004,A44)))) | M44: =IF(OR(A44="",E44=""),"",IFERROR(INDEX(Precios!$K$5:$K$84,MATCH(E44,Precios!$J$5:$J$84,0)),"")) -> 2400 | N44: =IF(A44="","",IFERROR(N(G44)*IF(F44="",0,INDEX(Precios!$N$5:$N$64,MATCH(F44,Precios!$M$5:$M$64,0)))+N(I44)*IF(H44="",0,INDEX(Precios!$N$5:$N$64,MATCH(H44,Precios!$M$5:$M$64,0))),"")) -> 0 | O44: =IF(A44="","",IFERROR(L44+M44+N44,"")) | P44: =IF(A44="","",IF(ISNUMBER(O44),"Lista"&IF(N(Precios!$Q$10)=0," (impresión en $0)",""),IF(J44=0,"Agregar piezas en Despiece. ",IF(COUNTIFS(Despiece!$A$5:$A$1004,A44,Despiece!$D$5:$D$1004,">0")<J44,"Metros de "&(J44-COUNTIFS(Despiece!$A$5:$A$1004,A44,Despiece!$D$5:$D$1004,">0"))&" pieza(s). ",""))&IF(COUNTIFS(Despiece!$A$5:$A$1004,A44,Despiece!$G$5:$G$1004,"falta*")>0,"Precio o peso de 1 m de alguna tela. ","")&IF(M44="","Tipo/precio de confección. ",""))) -> Metros de 5 pieza(s).
A45: 41 · BKMUJU03PRO | B45: Básquetbol, pro, cuello redondo | C45: Camiseta | D45: Femenino | E45: Camiseta De Basket Pro | J45: =IF(A45="","",COUNTIF(Despiece!$A$5:$A$1004,A45)) -> 4 | L45: =IF(A45="","",IF(COUNTIFS(Despiece!$A$5:$A$1004,A45,Despiece!$D$5:$D$1004,">0")<J45,"",IF(COUNTIFS(Despiece!$A$5:$A$1004,A45,Despiece!$G$5:$G$1004,"falta*")>0,"",SUMIFS(Despiece!$G$5:$G$1004,Despiece!$A$5:$A$1004,A45)))) | M45: =IF(OR(A45="",E45=""),"",IFERROR(INDEX(Precios!$K$5:$K$84,MATCH(E45,Precios!$J$5:$J$84,0)),"")) -> 2000 | N45: =IF(A45="","",IFERROR(N(G45)*IF(F45="",0,INDEX(Precios!$N$5:$N$64,MATCH(F45,Precios!$M$5:$M$64,0)))+N(I45)*IF(H45="",0,INDEX(Precios!$N$5:$N$64,MATCH(H45,Precios!$M$5:$M$64,0))),"")) -> 0 | O45: =IF(A45="","",IFERROR(L45+M45+N45,"")) | P45: =IF(A45="","",IF(ISNUMBER(O45),"Lista"&IF(N(Precios!$Q$10)=0," (impresión en $0)",""),IF(J45=0,"Agregar piezas en Despiece. ",IF(COUNTIFS(Despiece!$A$5:$A$1004,A45,Despiece!$D$5:$D$1004,">0")<J45,"Metros de "&(J45-COUNTIFS(Despiece!$A$5:$A$1004,A45,Despiece!$D$5:$D$1004,">0"))&" pieza(s). ",""))&IF(COUNTIFS(Despiece!$A$5:$A$1004,A45,Despiece!$G$5:$G$1004,"falta*")>0,"Precio o peso de 1 m de alguna tela. ","")&IF(M45="","Tipo/precio de confección. ",""))) -> Metros de 4 pieza(s).
A46: 42 · BKHOMU03PRO | B46: Básquetbol, pro, cuello redondo | C46: Camiseta | D46: Masculino | E46: Camiseta De Basket Pro | J46: =IF(A46="","",COUNTIF(Despiece!$A$5:$A$1004,A46)) -> 4 | L46: =IF(A46="","",IF(COUNTIFS(Despiece!$A$5:$A$1004,A46,Despiece!$D$5:$D$1004,">0")<J46,"",IF(COUNTIFS(Despiece!$A$5:$A$1004,A46,Despiece!$G$5:$G$1004,"falta*")>0,"",SUMIFS(Despiece!$G$5:$G$1004,Despiece!$A$5:$A$1004,A46)))) | M46: =IF(OR(A46="",E46=""),"",IFERROR(INDEX(Precios!$K$5:$K$84,MATCH(E46,Precios!$J$5:$J$84,0)),"")) -> 2000 | N46: =IF(A46="","",IFERROR(N(G46)*IF(F46="",0,INDEX(Precios!$N$5:$N$64,MATCH(F46,Precios!$M$5:$M$64,0)))+N(I46)*IF(H46="",0,INDEX(Precios!$N$5:$N$64,MATCH(H46,Precios!$M$5:$M$64,0))),"")) -> 0 | O46: =IF(A46="","",IFERROR(L46+M46+N46,"")) | P46: =IF(A46="","",IF(ISNUMBER(O46),"Lista"&IF(N(Precios!$Q$10)=0," (impresión en $0)",""),IF(J46=0,"Agregar piezas en Despiece. ",IF(COUNTIFS(Despiece!$A$5:$A$1004,A46,Despiece!$D$5:$D$1004,">0")<J46,"Metros de "&(J46-COUNTIFS(Despiece!$A$5:$A$1004,A46,Despiece!$D$5:$D$1004,">0"))&" pieza(s). ",""))&IF(COUNTIFS(Despiece!$A$5:$A$1004,A46,Despiece!$G$5:$G$1004,"falta*")>0,"Precio o peso de 1 m de alguna tela. ","")&IF(M46="","Tipo/precio de confección. ",""))) -> Metros de 4 pieza(s).
... A49: 45 · BKSHMUJ | B49: Básquetbol | C49: Short | D49: Femenino | E49: Short De Basket | J49: =IF(A49="","",COUNTIF(Despiece!$A$5:$A$1004,A49)) -> 3 | L49: =IF(A49="","",IF(COUNTIFS(Despiece!$A$5:$A$1004,A49,Despiece!$D$5:$D$1004,">0")<J49,"",IF(COUNTIFS(Despiece!$A$5:$A$1004,A49,Despiece!$G$5:$G$1004,"falta*")>0,"",SUMIFS(Despiece!$G$5:$G$1004,Despiece!$A$5:$A$1004,A49)))) | M49: =IF(OR(A49="",E49=""),"",IFERROR(INDEX(Precios!$K$5:$K$84,MATCH(E49,Precios!$J$5:$J$84,0)),"")) -> 1900 | N49: =IF(A49="","",IFERROR(N(G49)*IF(F49="",0,INDEX(Precios!$N$5:$N$64,MATCH(F49,Precios!$M$5:$M$64,0)))+N(I49)*IF(H49="",0,INDEX(Precios!$N$5:$N$64,MATCH(H49,Precios!$M$5:$M$64,0))),"")) -> 0 | O49: =IF(A49="","",IFERROR(L49+M49+N49,"")) | P49: =IF(A49="","",IF(ISNUMBER(O49),"Lista"&IF(N(Precios!$Q$10)=0," (impresión en $0)",""),IF(J49=0,"Agregar piezas en Despiece. ",IF(COUNTIFS(Despiece!$A$5:$A$1004,A49,Despiece!$D$5:$D$1004,">0")<J49,"Metros de "&(J49-COUNTIFS(Despiece!$A$5:$A$1004,A49,Despiece!$D$5:$D$1004,">0"))&" pieza(s). ",""))&IF(COUNTIFS(Despiece!$A$5:$A$1004,A49,Despiece!$G$5:$G$1004,"falta*")>0,"Precio o peso de 1 m de alguna tela. ","")&IF(M49="","Tipo/precio de confección. ",""))) -> Metros de 3 pieza(s).
A50: 46 · BK-SH | B50: Básquetbol | C50: Short | D50: Masculino | E50: Short De Basket | J50: =IF(A50="","",COUNTIF(Despiece!$A$5:$A$1004,A50)) -> 3 | L50: =IF(A50="","",IF(COUNTIFS(Despiece!$A$5:$A$1004,A50,Despiece!$D$5:$D$1004,">0")<J50,"",IF(COUNTIFS(Despiece!$A$5:$A$1004,A50,Despiece!$G$5:$G$1004,"falta*")>0,"",SUMIFS(Despiece!$G$5:$G$1004,Despiece!$A$5:$A$1004,A50)))) | M50: =IF(OR(A50="",E50=""),"",IFERROR(INDEX(Precios!$K$5:$K$84,MATCH(E50,Precios!$J$5:$J$84,0)),"")) -> 1900 | N50: =IF(A50="","",IFERROR(N(G50)*IF(F50="",0,INDEX(Precios!$N$5:$N$64,MATCH(F50,Precios!$M$5:$M$64,0)))+N(I50)*IF(H50="",0,INDEX(Precios!$N$5:$N$64,MATCH(H50,Precios!$M$5:$M$64,0))),"")) -> 0 | O50: =IF(A50="","",IFERROR(L50+M50+N50,"")) | P50: =IF(A50="","",IF(ISNUMBER(O50),"Lista"&IF(N(Precios!$Q$10)=0," (impresión en $0)",""),IF(J50=0,"Agregar piezas en Despiece. ",IF(COUNTIFS(Despiece!$A$5:$A$1004,A50,Despiece!$D$5:$D$1004,">0")<J50,"Metros de "&(J50-COUNTIFS(Despiece!$A$5:$A$1004,A50,Despiece!$D$5:$D$1004,">0"))&" pieza(s). ",""))&IF(COUNTIFS(Despiece!$A$5:$A$1004,A50,Despiece!$G$5:$G$1004,"falta*")>0,"Precio o peso de 1 m de alguna tela. ","")&IF(M50="","Tipo/precio de confección. ",""))) -> Metros de 3 pieza(s). | Q50: Corte OT 2425: 0,1529 kg Quickdry por prenda.
A51: 47 · BKINSHMUJ | B51: Básquetbol infantil | C51: Short | D51: Infantil Femenino | E51: Short De Basket | J51: =IF(A51="","",COUNTIF(Despiece!$A$5:$A$1004,A51)) -> 3 | L51: =IF(A51="","",IF(COUNTIFS(Despiece!$A$5:$A$1004,A51,Despiece!$D$5:$D$1004,">0")<J51,"",IF(COUNTIFS(Despiece!$A$5:$A$1004,A51,Despiece!$G$5:$G$1004,"falta*")>0,"",SUMIFS(Despiece!$G$5:$G$1004,Despiece!$A$5:$A$1004,A51)))) | M51: =IF(OR(A51="",E51=""),"",IFERROR(INDEX(Precios!$K$5:$K$84,MATCH(E51,Precios!$J$5:$J$84,0)),"")) -> 1900 | N51: =IF(A51="","",IFERROR(N(G51)*IF(F51="",0,INDEX(Precios!$N$5:$N$64,MATCH(F51,Precios!$M$5:$M$64,0)))+N(I51)*IF(H51="",0,INDEX(Precios!$N$5:$N$64,MATCH(H51,Precios!$M$5:$M$64,0))),"")) -> 0 | O51: =IF(A51="","",IFERROR(L51+M51+N51,"")) | P51: =IF(A51="","",IF(ISNUMBER(O51),"Lista"&IF(N(Precios!$Q$10)=0," (impresión en $0)",""),IF(J51=0,"Agregar piezas en Despiece. ",IF(COUNTIFS(Despiece!$A$5:$A$1004,A51,Despiece!$D$5:$D$1004,">0")<J51,"Metros de "&(J51-COUNTIFS(Despiece!$A$5:$A$1004,A51,Despiece!$D$5:$D$1004,">0"))&" pieza(s). ",""))&IF(COUNTIFS(Despiece!$A$5:$A$1004,A51,Despiece!$G$5:$G$1004,"falta*")>0,"Precio o peso de 1 m de alguna tela. ","")&IF(M51="","Tipo/precio de confección. ",""))) -> Metros de 3 pieza(s).
A52: 48 · BKINSHHOM | B52: Básquetbol infantil | C52: Short | D52: Infantil Masculino | E52: Short De Basket | J52: =IF(A52="","",COUNTIF(Despiece!$A$5:$A$1004,A52)) -> 3 | L52: =IF(A52="","",IF(COUNTIFS(Despiece!$A$5:$A$1004,A52,Despiece!$D$5:$D$1004,">0")<J52,"",IF(COUNTIFS(Despiece!$A$5:$A$1004,A52,Despiece!$G$5:$G$1004,"falta*")>0,"",SUMIFS(Despiece!$G$5:$G$1004,Despiece!$A$5:$A$1004,A52)))) | M52: =IF(OR(A52="",E52=""),"",IFERROR(INDEX(Precios!$K$5:$K$84,MATCH(E52,Precios!$J$5:$J$84,0)),"")) -> 1900 | N52: =IF(A52="","",IFERROR(N(G52)*IF(F52="",0,INDEX(Precios!$N$5:$N$64,MATCH(F52,Precios!$M$5:$M$64,0)))+N(I52)*IF(H52="",0,INDEX(Precios!$N$5:$N$64,MATCH(H52,Precios!$M$5:$M$64,0))),"")) -> 0 | O52: =IF(A52="","",IFERROR(L52+M52+N52,"")) | P52: =IF(A52="","",IF(ISNUMBER(O52),"Lista"&IF(N(Precios!$Q$10)=0," (impresión en $0)",""),IF(J52=0,"Agregar piezas en Despiece. ",IF(COUNTIFS(Despiece!$A$5:$A$1004,A52,Despiece!$D$5:$D$1004,">0")<J52,"Metros de "&(J52-COUNTIFS(Despiece!$A$5:$A$1004,A52,Despiece!$D$5:$D$1004,">0"))&" pieza(s). ",""))&IF(COUNTIFS(Despiece!$A$5:$A$1004,A52,Despiece!$G$5:$G$1004,"falta*")>0,"Precio o peso de 1 m de alguna tela. ","")&IF(M52="","Tipo/precio de confección. ",""))) -> Metros de 3 pieza(s).
A53: 49 · BKSHMUJRE | B53: Básquetbol, reversible | C53: Short | D53: Femenino | E53: Short De Basket Reversible | J53: =IF(A53="","",COUNTIF(Despiece!$A$5:$A$1004,A53)) -> 6 | L53: =IF(A53="","",IF(COUNTIFS(Despiece!$A$5:$A$1004,A53,Despiece!$D$5:$D$1004,">0")<J53,"",IF(COUNTIFS(Despiece!$A$5:$A$1004,A53,Despiece!$G$5:$G$1004,"falta*")>0,"",SUMIFS(Despiece!$G$5:$G$1004,Despiece!$A$5:$A$1004,A53)))) | M53: =IF(OR(A53="",E53=""),"",IFERROR(INDEX(Precios!$K$5:$K$84,MATCH(E53,Precios!$J$5:$J$84,0)),"")) -> 2400 | N53: =IF(A53="","",IFERROR(N(G53)*IF(F53="",0,INDEX(Precios!$N$5:$N$64,MATCH(F53,Precios!$M$5:$M$64,0)))+N(I53)*IF(H53="",0,INDEX(Precios!$N$5:$N$64,MATCH(H53,Precios!$M$5:$M$64,0))),"")) -> 0 | O53: =IF(A53="","",IFERROR(L53+M53+N53,"")) | P53: =IF(A53="","",IF(ISNUMBER(O53),"Lista"&IF(N(Precios!$Q$10)=0," (impresión en $0)",""),IF(J53=0,"Agregar piezas en Despiece. ",IF(COUNTIFS(Despiece!$A$5:$A$1004,A53,Despiece!$D$5:$D$1004,">0")<J53,"Metros de "&(J53-COUNTIFS(Despiece!$A$5:$A$1004,A53,Despiece!$D$5:$D$1004,">0"))&" pieza(s). ",""))&IF(COUNTIFS(Despiece!$A$5:$A$1004,A53,Despiece!$G$5:$G$1004,"falta*")>0,"Precio o peso de 1 m de alguna tela. ","")&IF(M53="","Tipo/precio de confección. ",""))) -> Metros de 6 pieza(s).
A54: 50 · BK-SH | B54: Básquetbol, reversible | C54: Short | D54: Masculino | E54: Short De Basket Reversible | J54: =IF(A54="","",COUNTIF(Despiece!$A$5:$A$1004,A54)) -> 6 | L54: =IF(A54="","",IF(COUNTIFS(Despiece!$A$5:$A$1004,A54,Despiece!$D$5:$D$1004,">0")<J54,"",IF(COUNTIFS(Despiece!$A$5:$A$1004,A54,Despiece!$G$5:$G$1004,"falta*")>0,"",SUMIFS(Despiece!$G$5:$G$1004,Despiece!$A$5:$A$1004,A54)))) | M54: =IF(OR(A54="",E54=""),"",IFERROR(INDEX(Precios!$K$5:$K$84,MATCH(E54,Precios!$J$5:$J$84,0)),"")) -> 2400 | N54: =IF(A54="","",IFERROR(N(G54)*IF(F54="",0,INDEX(Precios!$N$5:$N$64,MATCH(F54,Precios!$M$5:$M$64,0)))+N(I54)*IF(H54="",0,INDEX(Precios!$N$5:$N$64,MATCH(H54,Precios!$M$5:$M$64,0))),"")) -> 0 | O54: =IF(A54="","",IFERROR(L54+M54+N54,"")) | P54: =IF(A54="","",IF(ISNUMBER(O54),"Lista"&IF(N(Precios!$Q$10)=0," (impresión en $0)",""),IF(J54=0,"Agregar piezas en Despiece. ",IF(COUNTIFS(Despiece!$A$5:$A$1004,A54,Despiece!$D$5:$D$1004,">0")<J54,"Metros de "&(J54-COUNTIFS(Despiece!$A$5:$A$1004,A54,Despiece!$D$5:$D$1004,">0"))&" pieza(s). ",""))&IF(COUNTIFS(Despiece!$A$5:$A$1004,A54,Despiece!$G$5:$G$1004,"falta*")>0,"Precio o peso de 1 m de alguna tela. ","")&IF(M54="","Tipo/precio de confección. ",""))) -> Metros de 6 pieza(s).
A55: 51 · BKINSHMUJRE | B55: Básquetbol infantil, reversible | C55: Short | D55: Infantil Femenino | E55: Short De Basket Reversible | J55: =IF(A55="","",COUNTIF(Despiece!$A$5:$A$1004,A55)) -> 6 | L55: =IF(A55="","",IF(COUNTIFS(Despiece!$A$5:$A$1004,A55,Despiece!$D$5:$D$1004,">0")<J55,"",IF(COUNTIFS(Despiece!$A$5:$A$1004,A55,Despiece!$G$5:$G$1004,"falta*")>0,"",SUMIFS(Despiece!$G$5:$G$1004,Despiece!$A$5:$A$1004,A55)))) | M55: =IF(OR(A55="",E55=""),"",IFERROR(INDEX(Precios!$K$5:$K$84,MATCH(E55,Precios!$J$5:$J$84,0)),"")) -> 2400 | N55: =IF(A55="","",IFERROR(N(G55)*IF(F55="",0,INDEX(Precios!$N$5:$N$64,MATCH(F55,Precios!$M$5:$M$64,0)))+N(I55)*IF(H55="",0,INDEX(Precios!$N$5:$N$64,MATCH(H55,Precios!$M$5:$M$64,0))),"")) -> 0 | O55: =IF(A55="","",IFERROR(L55+M55+N55,"")) | P55: =IF(A55="","",IF(ISNUMBER(O55),"Lista"&IF(N(Precios!$Q$10)=0," (impresión en $0)",""),IF(J55=0,"Agregar piezas en Despiece. ",IF(COUNTIFS(Despiece!$A$5:$A$1004,A55,Despiece!$D$5:$D$1004,">0")<J55,"Metros de "&(J55-COUNTIFS(Despiece!$A$5:$A$1004,A55,Despiece!$D$5:$D$1004,">0"))&" pieza(s). ",""))&IF(COUNTIFS(Despiece!$A$5:$A$1004,A55,Despiece!$G$5:$G$1004,"falta*")>0,"Precio o peso de 1 m de alguna tela. ","")&IF(M55="","Tipo/precio de confección. ",""))) -> Metros de 6 pieza(s).
A56: 52 · BKINSHHOMRE | B56: Básquetbol infantil, reversible | C56: Short | D56: Infantil Masculino | E56: Short De Basket Reversible | J56: =IF(A56="","",COUNTIF(Despiece!$A$5:$A$1004,A56)) -> 6 | L56: =IF(A56="","",IF(COUNTIFS(Despiece!$A$5:$A$1004,A56,Despiece!$D$5:$D$1004,">0")<J56,"",IF(COUNTIFS(Despiece!$A$5:$A$1004,A56,Despiece!$G$5:$G$1004,"falta*")>0,"",SUMIFS(Despiece!$G$5:$G$1004,Despiece!$A$5:$A$1004,A56)))) | M56: =IF(OR(A56="",E56=""),"",IFERROR(INDEX(Precios!$K$5:$K$84,MATCH(E56,Precios!$J$5:$J$84,0)),"")) -> 2400 | N56: =IF(A56="","",IFERROR(N(G56)*IF(F56="",0,INDEX(Precios!$N$5:$N$64,MATCH(F56,Precios!$M$5:$M$64,0)))+N(I56)*IF(H56="",0,INDEX(Precios!$N$5:$N$64,MATCH(H56,Precios!$M$5:$M$64,0))),"")) -> 0 | O56: =IF(A56="","",IFERROR(L56+M56+N56,"")) | P56: =IF(A56="","",IF(ISNUMBER(O56),"Lista"&IF(N(Precios!$Q$10)=0," (impresión en $0)",""),IF(J56=0,"Agregar piezas en Despiece. ",IF(COUNTIFS(Despiece!$A$5:$A$1004,A56,Despiece!$D$5:$D$1004,">0")<J56,"Metros de "&(J56-COUNTIFS(Despiece!$A$5:$A$1004,A56,Despiece!$D$5:$D$1004,">0"))&" pieza(s). ",""))&IF(COUNTIFS(Despiece!$A$5:$A$1004,A56,Despiece!$G$5:$G$1004,"falta*")>0,"Precio o peso de 1 m de alguna tela. ","")&IF(M56="","Tipo/precio de confección. ",""))) -> Metros de 6 pieza(s).
A57: 53 · BKSHMUJPRO | B57: Básquetbol, pro | C57: Short | D57: Femenino | E57: Short De Basket Pro | J57: =IF(A57="","",COUNTIF(Despiece!$A$5:$A$1004,A57)) -> 4 | L57: =IF(A57="","",IF(COUNTIFS(Despiece!$A$5:$A$1004,A57,Despiece!$D$5:$D$1004,">0")<J57,"",IF(COUNTIFS(Despiece!$A$5:$A$1004,A57,Despiece!$G$5:$G$1004,"falta*")>0,"",SUMIFS(Despiece!$G$5:$G$1004,Despiece!$A$5:$A$1004,A57)))) | M57: =IF(OR(A57="",E57=""),"",IFERROR(INDEX(Precios!$K$5:$K$84,MATCH(E57,Precios!$J$5:$J$84,0)),"")) -> 2200 | N57: =IF(A57="","",IFERROR(N(G57)*IF(F57="",0,INDEX(Precios!$N$5:$N$64,MATCH(F57,Precios!$M$5:$M$64,0)))+N(I57)*IF(H57="",0,INDEX(Precios!$N$5:$N$64,MATCH(H57,Precios!$M$5:$M$64,0))),"")) -> 0 | O57: =IF(A57="","",IFERROR(L57+M57+N57,"")) | P57: =IF(A57="","",IF(ISNUMBER(O57),"Lista"&IF(N(Precios!$Q$10)=0," (impresión en $0)",""),IF(J57=0,"Agregar piezas en Despiece. ",IF(COUNTIFS(Despiece!$A$5:$A$1004,A57,Despiece!$D$5:$D$1004,">0")<J57,"Metros de "&(J57-COUNTIFS(Despiece!$A$5:$A$1004,A57,Despiece!$D$5:$D$1004,">0"))&" pieza(s). ",""))&IF(COUNTIFS(Despiece!$A$5:$A$1004,A57,Despiece!$G$5:$G$1004,"falta*")>0,"Precio o peso de 1 m de alguna tela. ","")&IF(M57="","Tipo/precio de confección. ",""))) -> Metros de 4 pieza(s).
A58: 54 · BK-SH PRO | B58: Básquetbol, pro | C58: Short | D58: Masculino | E58: Short De Basket Pro | J58: =IF(A58="","",COUNTIF(Despiece!$A$5:$A$1004,A58)) -> 4 | L58: =IF(A58="","",IF(COUNTIFS(Despiece!$A$5:$A$1004,A58,Despiece!$D$5:$D$1004,">0")<J58,"",IF(COUNTIFS(Despiece!$A$5:$A$1004,A58,Despiece!$G$5:$G$1004,"falta*")>0,"",SUMIFS(Despiece!$G$5:$G$1004,Despiece!$A$5:$A$1004,A58)))) | M58: =IF(OR(A58="",E58=""),"",IFERROR(INDEX(Precios!$K$5:$K$84,MATCH(E58,Precios!$J$5:$J$84,0)),"")) -> 2200 | N58: =IF(A58="","",IFERROR(N(G58)*IF(F58="",0,INDEX(Precios!$N$5:$N$64,MATCH(F58,Precios!$M$5:$M$64,0)))+N(I58)*IF(H58="",0,INDEX(Precios!$N$5:$N$64,MATCH(H58,Precios!$M$5:$M$64,0))),"")) -> 0 | O58: =IF(A58="","",IFERROR(L58+M58+N58,"")) | P58: =IF(A58="","",IF(ISNUMBER(O58),"Lista"&IF(N(Precios!$Q$10)=0," (impresión en $0)",""),IF(J58=0,"Agregar piezas en Despiece. ",IF(COUNTIFS(Despiece!$A$5:$A$1004,A58,Despiece!$D$5:$D$1004,">0")<J58,"Metros de "&(J58-COUNTIFS(Despiece!$A$5:$A$1004,A58,Despiece!$D$5:$D$1004,">0"))&" pieza(s). ",""))&IF(COUNTIFS(Despiece!$A$5:$A$1004,A58,Despiece!$G$5:$G$1004,"falta*")>0,"Precio o peso de 1 m de alguna tela. ","")&IF(M58="","Tipo/precio de confección. ",""))) -> Metros de 4 pieza(s).
A59: SM-01 · Short Fútbol | B59: Short de fútbol (sin molde en catálogo) | C59: Short | D59: Masculino | E59: Short De Futbol | J59: =IF(A59="","",COUNTIF(Despiece!$A$5:$A$1004,A59)) -> 3 | L59: =IF(A59="","",IF(COUNTIFS(Despiece!$A$5:$A$1004,A59,Despiece!$D$5:$D$1004,">0")<J59,"",IF(COUNTIFS(Despiece!$A$5:$A$1004,A59,Despiece!$G$5:$G$1004,"falta*")>0,"",SUMIFS(Despiece!$G$5:$G$1004,Despiece!$A$5:$A$1004,A59)))) | M59: =IF(OR(A59="",E59=""),"",IFERROR(INDEX(Precios!$K$5:$K$84,MATCH(E59,Precios!$J$5:$J$84,0)),"")) -> 1700 | N59: =IF(A59="","",IFERROR(N(G59)*IF(F59="",0,INDEX(Precios!$N$5:$N$64,MATCH(F59,Precios!$M$5:$M$64,0)))+N(I59)*IF(H59="",0,INDEX(Precios!$N$5:$N$64,MATCH(H59,Precios!$M$5:$M$64,0))),"")) -> 0 | O59: =IF(A59="","",IFERROR(L59+M59+N59,"")) | P59: =IF(A59="","",IF(ISNUMBER(O59),"Lista"&IF(N(Precios!$Q$10)=0," (impresión en $0)",""),IF(J59=0,"Agregar piezas en Despiece. ",IF(COUNTIFS(Despiece!$A$5:$A$1004,A59,Despiece!$D$5:$D$1004,">0")<J59,"Metros de "&(J59-COUNTIFS(Despiece!$A$5:$A$1004,A59,Despiece!$D$5:$D$1004,">0"))&" pieza(s). ",""))&IF(COUNTIFS(Despiece!$A$5:$A$1004,A59,Despiece!$G$5:$G$1004,"falta*")>0,"Precio o peso de 1 m de alguna tela. ","")&IF(M59="","Tipo/precio de confección. ",""))) -> Metros de 3 pieza(s). | Q59: Cortes OT 2547 y 2588: 0,175 y 0,138 kg Cire por prenda.
A60: SM-02 · Short Rugby | B60: Short de rugby (sin molde en catálogo) | C60: Short | D60: Masculino | E60: Short De Rugby | J60: =IF(A60="","",COUNTIF(Despiece!$A$5:$A$1004,A60)) -> 3 | L60: =IF(A60="","",IF(COUNTIFS(Despiece!$A$5:$A$1004,A60,Despiece!$D$5:$D$1004,">0")<J60,"",IF(COUNTIFS(Despiece!$A$5:$A$1004,A60,Despiece!$G$5:$G$1004,"falta*")>0,"",SUMIFS(Despiece!$G$5:$G$1004,Despiece!$A$5:$A$1004,A60)))) | M60: =IF(OR(A60="",E60=""),"",IFERROR(INDEX(Precios!$K$5:$K$84,MATCH(E60,Precios!$J$5:$J$84,0)),"")) -> 2200 | N60: =IF(A60="","",IFERROR(N(G60)*IF(F60="",0,INDEX(Precios!$N$5:$N$64,MATCH(F60,Precios!$M$5:$M$64,0)))+N(I60)*IF(H60="",0,INDEX(Precios!$N$5:$N$64,MATCH(H60,Precios!$M$5:$M$64,0))),"")) -> 0 | O60: =IF(A60="","",IFERROR(L60+M60+N60,"")) | P60: =IF(A60="","",IF(ISNUMBER(O60),"Lista"&IF(N(Precios!$Q$10)=0," (impresión en $0)",""),IF(J60=0,"Agregar piezas en Despiece. ",IF(COUNTIFS(Despiece!$A$5:$A$1004,A60,Despiece!$D$5:$D$1004,">0")<J60,"Metros de "&(J60-COUNTIFS(Despiece!$A$5:$A$1004,A60,Despiece!$D$5:$D$1004,">0"))&" pieza(s). ",""))&IF(COUNTIFS(Despiece!$A$5:$A$1004,A60,Despiece!$G$5:$G$1004,"falta*")>0,"Precio o peso de 1 m de alguna tela. ","")&IF(M60="","Tipo/precio de confección. ",""))) -> Metros de 3 pieza(s). | Q60: Corte OT 205: 0,1842 kg Gabardina por prenda.
A61: SM-03 · Camiseta Running s/m | B61: Camiseta running sin mangas (sin molde) | C61: Camiseta | D61: Masculino | E61: Camiseta De Running | J61: =IF(A61="","",COUNTIF(Despiece!$A$5:$A$1004,A61)) -> 3 | L61: =IF(A61="","",IF(COUNTIFS(Despiece!$A$5:$A$1004,A61,Despiece!$D$5:$D$1004,">0")<J61,"",IF(COUNTIFS(Despiece!$A$5:$A$1004,A61,Despiece!$G$5:$G$1004,"falta*")>0,"",SUMIFS(Despiece!$G$5:$G$1004,Despiece!$A$5:$A$1004,A61)))) | M61: =IF(OR(A61="",E61=""),"",IFERROR(INDEX(Precios!$K$5:$K$84,MATCH(E61,Precios!$J$5:$J$84,0)),"")) -> 1800 | N61: =IF(A61="","",IFERROR(N(G61)*IF(F61="",0,INDEX(Precios!$N$5:$N$64,MATCH(F61,Precios!$M$5:$M$64,0)))+N(I61)*IF(H61="",0,INDEX(Precios!$N$5:$N$64,MATCH(H61,Precios!$M$5:$M$64,0))),"")) -> 0 | O61: =IF(A61="","",IFERROR(L61+M61+N61,"")) | P61: =IF(A61="","",IF(ISNUMBER(O61),"Lista"&IF(N(Precios!$Q$10)=0," (impresión en $0)",""),IF(J61=0,"Agregar piezas en Despiece. ",IF(COUNTIFS(Despiece!$A$5:$A$1004,A61,Despiece!$D$5:$D$1004,">0")<J61,"Metros de "&(J61-COUNTIFS(Despiece!$A$5:$A$1004,A61,Despiece!$D$5:$D$1004,">0"))&" pieza(s). ",""))&IF(COUNTIFS(Despiece!$A$5:$A$1004,A61,Despiece!$G$5:$G$1004,"falta*")>0,"Precio o peso de 1 m de alguna tela. ","")&IF(M61="","Tipo/precio de confección. ",""))) -> Metros de 3 pieza(s). | Q61: Corte OT 2223: 0,082 kg 5K por prenda.
A62: SM-04 · Calza Vóley | B62: Calza vóley (sin molde) | C62: Calza | D62: Masculino | E62: Calza | J62: =IF(A62="","",COUNTIF(Despiece!$A$5:$A$1004,A62)) -> 2 | L62: =IF(A62="","",IF(COUNTIFS(Despiece!$A$5:$A$1004,A62,Despiece!$D$5:$D$1004,">0")<J62,"",IF(COUNTIFS(Despiece!$A$5:$A$1004,A62,Despiece!$G$5:$G$1004,"falta*")>0,"",SUMIFS(Despiece!$G$5:$G$1004,Despiece!$A$5:$A$1004,A62)))) | M62: =IF(OR(A62="",E62=""),"",IFERROR(INDEX(Precios!$K$5:$K$84,MATCH(E62,Precios!$J$5:$J$84,0)),"")) -> 1200 | N62: =IF(A62="","",IFERROR(N(G62)*IF(F62="",0,INDEX(Precios!$N$5:$N$64,MATCH(F62,Precios!$M$5:$M$64,0)))+N(I62)*IF(H62="",0,INDEX(Precios!$N$5:$N$64,MATCH(H62,Precios!$M$5:$M$64,0))),"")) -> 0 | O62: =IF(A62="","",IFERROR(L62+M62+N62,"")) | P62: =IF(A62="","",IF(ISNUMBER(O62),"Lista"&IF(N(Precios!$Q$10)=0," (impresión en $0)",""),IF(J62=0,"Agregar piezas en Despiece. ",IF(COUNTIFS(Despiece!$A$5:$A$1004,A62,Despiece!$D$5:$D$1004,">0")<J62,"Metros de "&(J62-COUNTIFS(Despiece!$A$5:$A$1004,A62,Despiece!$D$5:$D$1004,">0"))&" pieza(s). ",""))&IF(COUNTIFS(Despiece!$A$5:$A$1004,A62,Despiece!$G$5:$G$1004,"falta*")>0,"Precio o peso de 1 m de alguna tela. ","")&IF(M62="","Tipo/precio de confección. ",""))) -> Metros de 2 pieza(s). | Q62: Corte OT 2642: 0,074 kg Lycra por prenda.
J63: =IF(A63="","",COUNTIF(Despiece!$A$5:$A$1004,A63)) | L63: =IF(A63="","",IF(COUNTIFS(Despiece!$A$5:$A$1004,A63,Despiece!$D$5:$D$1004,">0")<J63,"",IF(COUNTIFS(Despiece!$A$5:$A$1004,A63,Despiece!$G$5:$G$1004,"falta*")>0,"",SUMIFS(Despiece!$G$5:$G$1004,Despiece!$A$5:$A$1004,A63)))) | M63: =IF(OR(A63="",E63=""),"",IFERROR(INDEX(Precios!$K$5:$K$84,MATCH(E63,Precios!$J$5:$J$84,0)),"")) | N63: =IF(A63="","",IFERROR(N(G63)*IF(F63="",0,INDEX(Precios!$N$5:$N$64,MATCH(F63,Precios!$M$5:$M$64,0)))+N(I63)*IF(H63="",0,INDEX(Precios!$N$5:$N$64,MATCH(H63,Precios!$M$5:$M$64,0))),"")) | O63: =IF(A63="","",IFERROR(L63+M63+N63,"")) | P63: =IF(A63="","",IF(ISNUMBER(O63),"Lista"&IF(N(Precios!$Q$10)=0," (impresión en $0)",""),IF(J63=0,"Agregar piezas en Despiece. ",IF(COUNTIFS(Despiece!$A$5:$A$1004,A63,Despiece!$D$5:$D$1004,">0")<J63,"Metros de "&(J63-COUNTIFS(Despiece!$A$5:$A$1004,A63,Despiece!$D$5:$D$1004,">0"))&" pieza(s). ",""))&IF(COUNTIFS(Despiece!$A$5:$A$1004,A63,Despiece!$G$5:$G$1004,"falta*")>0,"Precio o peso de 1 m de alguna tela. ","")&IF(M63="","Tipo/precio de confección. ","")))
J64: =IF(A64="","",COUNTIF(Despiece!$A$5:$A$1004,A64)) | L64: =IF(A64="","",IF(COUNTIFS(Despiece!$A$5:$A$1004,A64,Despiece!$D$5:$D$1004,">0")<J64,"",IF(COUNTIFS(Despiece!$A$5:$A$1004,A64,Despiece!$G$5:$G$1004,"falta*")>0,"",SUMIFS(Despiece!$G$5:$G$1004,Despiece!$A$5:$A$1004,A64)))) | M64: =IF(OR(A64="",E64=""),"",IFERROR(INDEX(Precios!$K$5:$K$84,MATCH(E64,Precios!$J$5:$J$84,0)),"")) | N64: =IF(A64="","",IFERROR(N(G64)*IF(F64="",0,INDEX(Precios!$N$5:$N$64,MATCH(F64,Precios!$M$5:$M$64,0)))+N(I64)*IF(H64="",0,INDEX(Precios!$N$5:$N$64,MATCH(H64,Precios!$M$5:$M$64,0))),"")) | O64: =IF(A64="","",IFERROR(L64+M64+N64,"")) | P64: =IF(A64="","",IF(ISNUMBER(O64),"Lista"&IF(N(Precios!$Q$10)=0," (impresión en $0)",""),IF(J64=0,"Agregar piezas en Despiece. ",IF(COUNTIFS(Despiece!$A$5:$A$1004,A64,Despiece!$D$5:$D$1004,">0")<J64,"Metros de "&(J64-COUNTIFS(Despiece!$A$5:$A$1004,A64,Despiece!$D$5:$D$1004,">0"))&" pieza(s). ",""))&IF(COUNTIFS(Despiece!$A$5:$A$1004,A64,Despiece!$G$5:$G$1004,"falta*")>0,"Precio o peso de 1 m de alguna tela. ","")&IF(M64="","Tipo/precio de confección. ","")))
J65: =IF(A65="","",COUNTIF(Despiece!$A$5:$A$1004,A65)) | L65: =IF(A65="","",IF(COUNTIFS(Despiece!$A$5:$A$1004,A65,Despiece!$D$5:$D$1004,">0")<J65,"",IF(COUNTIFS(Despiece!$A$5:$A$1004,A65,Despiece!$G$5:$G$1004,"falta*")>0,"",SUMIFS(Despiece!$G$5:$G$1004,Despiece!$A$5:$A$1004,A65)))) | M65: =IF(OR(A65="",E65=""),"",IFERROR(INDEX(Precios!$K$5:$K$84,MATCH(E65,Precios!$J$5:$J$84,0)),"")) | N65: =IF(A65="","",IFERROR(N(G65)*IF(F65="",0,INDEX(Precios!$N$5:$N$64,MATCH(F65,Precios!$M$5:$M$64,0)))+N(I65)*IF(H65="",0,INDEX(Precios!$N$5:$N$64,MATCH(H65,Precios!$M$5:$M$64,0))),"")) | O65: =IF(A65="","",IFERROR(L65+M65+N65,"")) | P65: =IF(A65="","",IF(ISNUMBER(O65),"Lista"&IF(N(Precios!$Q$10)=0," (impresión en $0)",""),IF(J65=0,"Agregar piezas en Despiece. ",IF(COUNTIFS(Despiece!$A$5:$A$1004,A65,Despiece!$D$5:$D$1004,">0")<J65,"Metros de "&(J65-COUNTIFS(Despiece!$A$5:$A$1004,A65,Despiece!$D$5:$D$1004,">0"))&" pieza(s). ",""))&IF(COUNTIFS(Despiece!$A$5:$A$1004,A65,Despiece!$G$5:$G$1004,"falta*")>0,"Precio o peso de 1 m de alguna tela. ","")&IF(M65="","Tipo/precio de confección. ","")))
J66: =IF(A66="","",COUNTIF(Despiece!$A$5:$A$1004,A66)) | L66: =IF(A66="","",IF(COUNTIFS(Despiece!$A$5:$A$1004,A66,Despiece!$D$5:$D$1004,">0")<J66,"",IF(COUNTIFS(Despiece!$A$5:$A$1004,A66,Despiece!$G$5:$G$1004,"falta*")>0,"",SUMIFS(Despiece!$G$5:$G$1004,Despiece!$A$5:$A$1004,A66)))) | M66: =IF(OR(A66="",E66=""),"",IFERROR(INDEX(Precios!$K$5:$K$84,MATCH(E66,Precios!$J$5:$J$84,0)),"")) | N66: =IF(A66="","",IFERROR(N(G66)*IF(F66="",0,INDEX(Precios!$N$5:$N$64,MATCH(F66,Precios!$M$5:$M$64,0)))+N(I66)*IF(H66="",0,INDEX(Precios!$N$5:$N$64,MATCH(H66,Precios!$M$5:$M$64,0))),"")) | O66: =IF(A66="","",IFERROR(L66+M66+N66,"")) | P66: =IF(A66="","",IF(ISNUMBER(O66),"Lista"&IF(N(Precios!$Q$10)=0," (impresión en $0)",""),IF(J66=0,"Agregar piezas en Despiece. ",IF(COUNTIFS(Despiece!$A$5:$A$1004,A66,Despiece!$D$5:$D$1004,">0")<J66,"Metros de "&(J66-COUNTIFS(Despiece!$A$5:$A$1004,A66,Despiece!$D$5:$D$1004,">0"))&" pieza(s). ",""))&IF(COUNTIFS(Despiece!$A$5:$A$1004,A66,Despiece!$G$5:$G$1004,"falta*")>0,"Precio o peso de 1 m de alguna tela. ","")&IF(M66="","Tipo/precio de confección. ","")))
J67: =IF(A67="","",COUNTIF(Despiece!$A$5:$A$1004,A67)) | L67: =IF(A67="","",IF(COUNTIFS(Despiece!$A$5:$A$1004,A67,Despiece!$D$5:$D$1004,">0")<J67,"",IF(COUNTIFS(Despiece!$A$5:$A$1004,A67,Despiece!$G$5:$G$1004,"falta*")>0,"",SUMIFS(Despiece!$G$5:$G$1004,Despiece!$A$5:$A$1004,A67)))) | M67: =IF(OR(A67="",E67=""),"",IFERROR(INDEX(Precios!$K$5:$K$84,MATCH(E67,Precios!$J$5:$J$84,0)),"")) | N67: =IF(A67="","",IFERROR(N(G67)*IF(F67="",0,INDEX(Precios!$N$5:$N$64,MATCH(F67,Precios!$M$5:$M$64,0)))+N(I67)*IF(H67="",0,INDEX(Precios!$N$5:$N$64,MATCH(H67,Precios!$M$5:$M$64,0))),"")) | O67: =IF(A67="","",IFERROR(L67+M67+N67,"")) | P67: =IF(A67="","",IF(ISNUMBER(O67),"Lista"&IF(N(Precios!$Q$10)=0," (impresión en $0)",""),IF(J67=0,"Agregar piezas en Despiece. ",IF(COUNTIFS(Despiece!$A$5:$A$1004,A67,Despiece!$D$5:$D$1004,">0")<J67,"Metros de "&(J67-COUNTIFS(Despiece!$A$5:$A$1004,A67,Despiece!$D$5:$D$1004,">0"))&" pieza(s). ",""))&IF(COUNTIFS(Despiece!$A$5:$A$1004,A67,Despiece!$G$5:$G$1004,"falta*")>0,"Precio o peso de 1 m de alguna tela. ","")&IF(M67="","Tipo/precio de confección. ","")))
J68: =IF(A68="","",COUNTIF(Despiece!$A$5:$A$1004,A68)) | L68: =IF(A68="","",IF(COUNTIFS(Despiece!$A$5:$A$1004,A68,Despiece!$D$5:$D$1004,">0")<J68,"",IF(COUNTIFS(Despiece!$A$5:$A$1004,A68,Despiece!$G$5:$G$1004,"falta*")>0,"",SUMIFS(Despiece!$G$5:$G$1004,Despiece!$A$5:$A$1004,A68)))) | M68: =IF(OR(A68="",E68=""),"",IFERROR(INDEX(Precios!$K$5:$K$84,MATCH(E68,Precios!$J$5:$J$84,0)),"")) | N68: =IF(A68="","",IFERROR(N(G68)*IF(F68="",0,INDEX(Precios!$N$5:$N$64,MATCH(F68,Precios!$M$5:$M$64,0)))+N(I68)*IF(H68="",0,INDEX(Precios!$N$5:$N$64,MATCH(H68,Precios!$M$5:$M$64,0))),"")) | O68: =IF(A68="","",IFERROR(L68+M68+N68,"")) | P68: =IF(A68="","",IF(ISNUMBER(O68),"Lista"&IF(N(Precios!$Q$10)=0," (impresión en $0)",""),IF(J68=0,"Agregar piezas en Despiece. ",IF(COUNTIFS(Despiece!$A$5:$A$1004,A68,Despiece!$D$5:$D$1004,">0")<J68,"Metros de "&(J68-COUNTIFS(Despiece!$A$5:$A$1004,A68,Despiece!$D$5:$D$1004,">0"))&" pieza(s). ",""))&IF(COUNTIFS(Despiece!$A$5:$A$1004,A68,Despiece!$G$5:$G$1004,"falta*")>0,"Precio o peso de 1 m de alguna tela. ","")&IF(M68="","Tipo/precio de confección. ","")))
J69: =IF(A69="","",COUNTIF(Despiece!$A$5:$A$1004,A69)) | L69: =IF(A69="","",IF(COUNTIFS(Despiece!$A$5:$A$1004,A69,Despiece!$D$5:$D$1004,">0")<J69,"",IF(COUNTIFS(Despiece!$A$5:$A$1004,A69,Despiece!$G$5:$G$1004,"falta*")>0,"",SUMIFS(Despiece!$G$5:$G$1004,Despiece!$A$5:$A$1004,A69)))) | M69: =IF(OR(A69="",E69=""),"",IFERROR(INDEX(Precios!$K$5:$K$84,MATCH(E69,Precios!$J$5:$J$84,0)),"")) | N69: =IF(A69="","",IFERROR(N(G69)*IF(F69="",0,INDEX(Precios!$N$5:$N$64,MATCH(F69,Precios!$M$5:$M$64,0)))+N(I69)*IF(H69="",0,INDEX(Precios!$N$5:$N$64,MATCH(H69,Precios!$M$5:$M$64,0))),"")) | O69: =IF(A69="","",IFERROR(L69+M69+N69,"")) | P69: =IF(A69="","",IF(ISNUMBER(O69),"Lista"&IF(N(Precios!$Q$10)=0," (impresión en $0)",""),IF(J69=0,"Agregar piezas en Despiece. ",IF(COUNTIFS(Despiece!$A$5:$A$1004,A69,Despiece!$D$5:$D$1004,">0")<J69,"Metros de "&(J69-COUNTIFS(Despiece!$A$5:$A$1004,A69,Despiece!$D$5:$D$1004,">0"))&" pieza(s). ",""))&IF(COUNTIFS(Despiece!$A$5:$A$1004,A69,Despiece!$G$5:$G$1004,"falta*")>0,"Precio o peso de 1 m de alguna tela. ","")&IF(M69="","Tipo/precio de confección. ","")))
J70: =IF(A70="","",COUNTIF(Despiece!$A$5:$A$1004,A70)) | L70: =IF(A70="","",IF(COUNTIFS(Despiece!$A$5:$A$1004,A70,Despiece!$D$5:$D$1004,">0")<J70,"",IF(COUNTIFS(Despiece!$A$5:$A$1004,A70,Despiece!$G$5:$G$1004,"falta*")>0,"",SUMIFS(Despiece!$G$5:$G$1004,Despiece!$A$5:$A$1004,A70)))) | M70: =IF(OR(A70="",E70=""),"",IFERROR(INDEX(Precios!$K$5:$K$84,MATCH(E70,Precios!$J$5:$J$84,0)),"")) | N70: =IF(A70="","",IFERROR(N(G70)*IF(F70="",0,INDEX(Precios!$N$5:$N$64,MATCH(F70,Precios!$M$5:$M$64,0)))+N(I70)*IF(H70="",0,INDEX(Precios!$N$5:$N$64,MATCH(H70,Precios!$M$5:$M$64,0))),"")) | O70: =IF(A70="","",IFERROR(L70+M70+N70,"")) | P70: =IF(A70="","",IF(ISNUMBER(O70),"Lista"&IF(N(Precios!$Q$10)=0," (impresión en $0)",""),IF(J70=0,"Agregar piezas en Despiece. ",IF(COUNTIFS(Despiece!$A$5:$A$1004,A70,Despiece!$D$5:$D$1004,">0")<J70,"Metros de "&(J70-COUNTIFS(Despiece!$A$5:$A$1004,A70,Despiece!$D$5:$D$1004,">0"))&" pieza(s). ",""))&IF(COUNTIFS(Despiece!$A$5:$A$1004,A70,Despiece!$G$5:$G$1004,"falta*")>0,"Precio o peso de 1 m de alguna tela. ","")&IF(M70="","Tipo/precio de confección. ","")))
J71: =IF(A71="","",COUNTIF(Despiece!$A$5:$A$1004,A71)) | L71: =IF(A71="","",IF(COUNTIFS(Despiece!$A$5:$A$1004,A71,Despiece!$D$5:$D$1004,">0")<J71,"",IF(COUNTIFS(Despiece!$A$5:$A$1004,A71,Despiece!$G$5:$G$1004,"falta*")>0,"",SUMIFS(Despiece!$G$5:$G$1004,Despiece!$A$5:$A$1004,A71)))) | M71: =IF(OR(A71="",E71=""),"",IFERROR(INDEX(Precios!$K$5:$K$84,MATCH(E71,Precios!$J$5:$J$84,0)),"")) | N71: =IF(A71="","",IFERROR(N(G71)*IF(F71="",0,INDEX(Precios!$N$5:$N$64,MATCH(F71,Precios!$M$5:$M$64,0)))+N(I71)*IF(H71="",0,INDEX(Precios!$N$5:$N$64,MATCH(H71,Precios!$M$5:$M$64,0))),"")) | O71: =IF(A71="","",IFERROR(L71+M71+N71,"")) | P71: =IF(A71="","",IF(ISNUMBER(O71),"Lista"&IF(N(Precios!$Q$10)=0," (impresión en $0)",""),IF(J71=0,"Agregar piezas en Despiece. ",IF(COUNTIFS(Despiece!$A$5:$A$1004,A71,Despiece!$D$5:$D$1004,">0")<J71,"Metros de "&(J71-COUNTIFS(Despiece!$A$5:$A$1004,A71,Despiece!$D$5:$D$1004,">0"))&" pieza(s). ",""))&IF(COUNTIFS(Despiece!$A$5:$A$1004,A71,Despiece!$G$5:$G$1004,"falta*")>0,"Precio o peso de 1 m de alguna tela. ","")&IF(M71="","Tipo/precio de confección. ","")))
J72: =IF(A72="","",COUNTIF(Despiece!$A$5:$A$1004,A72)) | L72: =IF(A72="","",IF(COUNTIFS(Despiece!$A$5:$A$1004,A72,Despiece!$D$5:$D$1004,">0")<J72,"",IF(COUNTIFS(Despiece!$A$5:$A$1004,A72,Despiece!$G$5:$G$1004,"falta*")>0,"",SUMIFS(Despiece!$G$5:$G$1004,Despiece!$A$5:$A$1004,A72)))) | M72: =IF(OR(A72="",E72=""),"",IFERROR(INDEX(Precios!$K$5:$K$84,MATCH(E72,Precios!$J$5:$J$84,0)),"")) | N72: =IF(A72="","",IFERROR(N(G72)*IF(F72="",0,INDEX(Precios!$N$5:$N$64,MATCH(F72,Precios!$M$5:$M$64,0)))+N(I72)*IF(H72="",0,INDEX(Precios!$N$5:$N$64,MATCH(H72,Precios!$M$5:$M$64,0))),"")) | O72: =IF(A72="","",IFERROR(L72+M72+N72,"")) | P72: =IF(A72="","",IF(ISNUMBER(O72),"Lista"&IF(N(Precios!$Q$10)=0," (impresión en $0)",""),IF(J72=0,"Agregar piezas en Despiece. ",IF(COUNTIFS(Despiece!$A$5:$A$1004,A72,Despiece!$D$5:$D$1004,">0")<J72,"Metros de "&(J72-COUNTIFS(Despiece!$A$5:$A$1004,A72,Despiece!$D$5:$D$1004,">0"))&" pieza(s). ",""))&IF(COUNTIFS(Despiece!$A$5:$A$1004,A72,Despiece!$G$5:$G$1004,"falta*")>0,"Precio o peso de 1 m de alguna tela. ","")&IF(M72="","Tipo/precio de confección. ","")))
J73: =IF(A73="","",COUNTIF(Despiece!$A$5:$A$1004,A73)) | L73: =IF(A73="","",IF(COUNTIFS(Despiece!$A$5:$A$1004,A73,Despiece!$D$5:$D$1004,">0")<J73,"",IF(COUNTIFS(Despiece!$A$5:$A$1004,A73,Despiece!$G$5:$G$1004,"falta*")>0,"",SUMIFS(Despiece!$G$5:$G$1004,Despiece!$A$5:$A$1004,A73)))) | M73: =IF(OR(A73="",E73=""),"",IFERROR(INDEX(Precios!$K$5:$K$84,MATCH(E73,Precios!$J$5:$J$84,0)),"")) | N73: =IF(A73="","",IFERROR(N(G73)*IF(F73="",0,INDEX(Precios!$N$5:$N$64,MATCH(F73,Precios!$M$5:$M$64,0)))+N(I73)*IF(H73="",0,INDEX(Precios!$N$5:$N$64,MATCH(H73,Precios!$M$5:$M$64,0))),"")) | O73: =IF(A73="","",IFERROR(L73+M73+N73,"")) | P73: =IF(A73="","",IF(ISNUMBER(O73),"Lista"&IF(N(Precios!$Q$10)=0," (impresión en $0)",""),IF(J73=0,"Agregar piezas en Despiece. ",IF(COUNTIFS(Despiece!$A$5:$A$1004,A73,Despiece!$D$5:$D$1004,">0")<J73,"Metros de "&(J73-COUNTIFS(Despiece!$A$5:$A$1004,A73,Despiece!$D$5:$D$1004,">0"))&" pieza(s). ",""))&IF(COUNTIFS(Despiece!$A$5:$A$1004,A73,Despiece!$G$5:$G$1004,"falta*")>0,"Precio o peso de 1 m de alguna tela. ","")&IF(M73="","Tipo/precio de confección. ","")))
J74: =IF(A74="","",COUNTIF(Despiece!$A$5:$A$1004,A74)) | L74: =IF(A74="","",IF(COUNTIFS(Despiece!$A$5:$A$1004,A74,Despiece!$D$5:$D$1004,">0")<J74,"",IF(COUNTIFS(Despiece!$A$5:$A$1004,A74,Despiece!$G$5:$G$1004,"falta*")>0,"",SUMIFS(Despiece!$G$5:$G$1004,Despiece!$A$5:$A$1004,A74)))) | M74: =IF(OR(A74="",E74=""),"",IFERROR(INDEX(Precios!$K$5:$K$84,MATCH(E74,Precios!$J$5:$J$84,0)),"")) | N74: =IF(A74="","",IFERROR(N(G74)*IF(F74="",0,INDEX(Precios!$N$5:$N$64,MATCH(F74,Precios!$M$5:$M$64,0)))+N(I74)*IF(H74="",0,INDEX(Precios!$N$5:$N$64,MATCH(H74,Precios!$M$5:$M$64,0))),"")) | O74: =IF(A74="","",IFERROR(L74+M74+N74,"")) | P74: =IF(A74="","",IF(ISNUMBER(O74),"Lista"&IF(N(Precios!$Q$10)=0," (impresión en $0)",""),IF(J74=0,"Agregar piezas en Despiece. ",IF(COUNTIFS(Despiece!$A$5:$A$1004,A74,Despiece!$D$5:$D$1004,">0")<J74,"Metros de "&(J74-COUNTIFS(Despiece!$A$5:$A$1004,A74,Despiece!$D$5:$D$1004,">0"))&" pieza(s). ",""))&IF(COUNTIFS(Despiece!$A$5:$A$1004,A74,Despiece!$G$5:$G$1004,"falta*")>0,"Precio o peso de 1 m de alguna tela. ","")&IF(M74="","Tipo/precio de confección. ","")))
... J154: =IF(A154="","",COUNTIF(Despiece!$A$5:$A$1004,A154)) | L154: =IF(A154="","",IF(COUNTIFS(Despiece!$A$5:$A$1004,A154,Despiece!$D$5:$D$1004,">0")<J154,"",IF(COUNTIFS(Despiece!$A$5:$A$1004,A154,Despiece!$G$5:$G$1004,"falta*")>0,"",SUMIFS(Despiece!$G$5:$G$1004,Despiece!$A$5:$A$1004,A154)))) | M154: =IF(OR(A154="",E154=""),"",IFERROR(INDEX(Precios!$K$5:$K$84,MATCH(E154,Precios!$J$5:$J$84,0)),"")) | N154: =IF(A154="","",IFERROR(N(G154)*IF(F154="",0,INDEX(Precios!$N$5:$N$64,MATCH(F154,Precios!$M$5:$M$64,0)))+N(I154)*IF(H154="",0,INDEX(Precios!$N$5:$N$64,MATCH(H154,Precios!$M$5:$M$64,0))),"")) | O154: =IF(A154="","",IFERROR(L154+M154+N154,"")) | P154: =IF(A154="","",IF(ISNUMBER(O154),"Lista"&IF(N(Precios!$Q$10)=0," (impresión en $0)",""),IF(J154=0,"Agregar piezas en Despiece. ",IF(COUNTIFS(Despiece!$A$5:$A$1004,A154,Despiece!$D$5:$D$1004,">0")<J154,"Metros de "&(J154-COUNTIFS(Despiece!$A$5:$A$1004,A154,Despiece!$D$5:$D$1004,">0"))&" pieza(s). ",""))&IF(COUNTIFS(Despiece!$A$5:$A$1004,A154,Despiece!$G$5:$G$1004,"falta*")>0,"Precio o peso de 1 m de alguna tela. ","")&IF(M154="","Tipo/precio de confección. ","")))

Sheet Despiece
A1: DESPIECE — piezas de cada molde
A2: Metros por prenda de cada pieza (de la marcada del plotter). Los metros NO cambian con la tela. "Tela por defecto" es la que usa la Ficha si no eliges otra.
A4: Molde | B4: Pieza | C4: Cant. | D4: METROS por prenda | E4: Tela por defecto | F4: ¿Se sublima? | G4: $ tela + impresión (con tela por defecto) | H4: clave
A5: 01 · FUTMUJU01 | B5: Delantero | C5: 1 | F5: Sí | G5: =IF(OR(A5="",N(D5)=0),"",IFERROR(D5*(1+IFERROR(IF(ISNUMBER(INDEX(Moldes!$K$5:$K$154,MATCH(A5,Moldes!$A$5:$A$154,0))),INDEX(Moldes!$K$5:$K$154,MATCH(A5,Moldes!$A$5:$A$154,0)),Precios!$Q$12),Precios!$Q$12))*(INDEX(Precios!$F$5:$F$124,MATCH(E5,Precios!$A$5:$A$124,0))+IF(F5="Sí",Precios!$Q$10,0)),"falta $ tela")) | H5: =IF(A5="","",A5&"|"&COUNTIF($A$5:A5,A5)) -> 01 · FUTMUJU01|1
A6: 01 · FUTMUJU01 | B6: Espalda | C6: 1 | F6: Sí | G6: =IF(OR(A6="",N(D6)=0),"",IFERROR(D6*(1+IFERROR(IF(ISNUMBER(INDEX(Moldes!$K$5:$K$154,MATCH(A6,Moldes!$A$5:$A$154,0))),INDEX(Moldes!$K$5:$K$154,MATCH(A6,Moldes!$A$5:$A$154,0)),Precios!$Q$12),Precios!$Q$12))*(INDEX(Precios!$F$5:$F$124,MATCH(E6,Precios!$A$5:$A$124,0))+IF(F6="Sí",Precios!$Q$10,0)),"falta $ tela")) | H6: =IF(A6="","",A6&"|"&COUNTIF($A$5:A6,A6)) -> 01 · FUTMUJU01|2
A7: 01 · FUTMUJU01 | B7: Manga | C7: 2 | F7: Sí | G7: =IF(OR(A7="",N(D7)=0),"",IFERROR(D7*(1+IFERROR(IF(ISNUMBER(INDEX(Moldes!$K$5:$K$154,MATCH(A7,Moldes!$A$5:$A$154,0))),INDEX(Moldes!$K$5:$K$154,MATCH(A7,Moldes!$A$5:$A$154,0)),Precios!$Q$12),Precios!$Q$12))*(INDEX(Precios!$F$5:$F$124,MATCH(E7,Precios!$A$5:$A$124,0))+IF(F7="Sí",Precios!$Q$10,0)),"falta $ tela")) | H7: =IF(A7="","",A7&"|"&COUNTIF($A$5:A7,A7)) -> 01 · FUTMUJU01|3
A8: 01 · FUTMUJU01 | B8: Tira de cuello | C8: 1 | F8: Sí | G8: =IF(OR(A8="",N(D8)=0),"",IFERROR(D8*(1+IFERROR(IF(ISNUMBER(INDEX(Moldes!$K$5:$K$154,MATCH(A8,Moldes!$A$5:$A$154,0))),INDEX(Moldes!$K$5:$K$154,MATCH(A8,Moldes!$A$5:$A$154,0)),Precios!$Q$12),Precios!$Q$12))*(INDEX(Precios!$F$5:$F$124,MATCH(E8,Precios!$A$5:$A$124,0))+IF(F8="Sí",Precios!$Q$10,0)),"falta $ tela")) | H8: =IF(A8="","",A8&"|"&COUNTIF($A$5:A8,A8)) -> 01 · FUTMUJU01|4
A9: 02 · FUTHOMU01 | B9: Delantero | C9: 1 | F9: Sí | G9: =IF(OR(A9="",N(D9)=0),"",IFERROR(D9*(1+IFERROR(IF(ISNUMBER(INDEX(Moldes!$K$5:$K$154,MATCH(A9,Moldes!$A$5:$A$154,0))),INDEX(Moldes!$K$5:$K$154,MATCH(A9,Moldes!$A$5:$A$154,0)),Precios!$Q$12),Precios!$Q$12))*(INDEX(Precios!$F$5:$F$124,MATCH(E9,Precios!$A$5:$A$124,0))+IF(F9="Sí",Precios!$Q$10,0)),"falta $ tela")) | H9: =IF(A9="","",A9&"|"&COUNTIF($A$5:A9,A9)) -> 02 · FUTHOMU01|1
A10: 02 · FUTHOMU01 | B10: Espalda | C10: 1 | F10: Sí | G10: =IF(OR(A10="",N(D10)=0),"",IFERROR(D10*(1+IFERROR(IF(ISNUMBER(INDEX(Moldes!$K$5:$K$154,MATCH(A10,Moldes!$A$5:$A$154,0))),INDEX(Moldes!$K$5:$K$154,MATCH(A10,Moldes!$A$5:$A$154,0)),Precios!$Q$12),Precios!$Q$12))*(INDEX(Precios!$F$5:$F$124,MATCH(E10,Precios!$A$5:$A$124,0))+IF(F10="Sí",Precios!$Q$10,0)),"falta $ tela")) | H10: =IF(A10="","",A10&"|"&COUNTIF($A$5:A10,A10)) -> 02 · FUTHOMU01|2
A11: 02 · FUTHOMU01 | B11: Manga | C11: 2 | F11: Sí | G11: =IF(OR(A11="",N(D11)=0),"",IFERROR(D11*(1+IFERROR(IF(ISNUMBER(INDEX(Moldes!$K$5:$K$154,MATCH(A11,Moldes!$A$5:$A$154,0))),INDEX(Moldes!$K$5:$K$154,MATCH(A11,Moldes!$A$5:$A$154,0)),Precios!$Q$12),Precios!$Q$12))*(INDEX(Precios!$F$5:$F$124,MATCH(E11,Precios!$A$5:$A$124,0))+IF(F11="Sí",Precios!$Q$10,0)),"falta $ tela")) | H11: =IF(A11="","",A11&"|"&COUNTIF($A$5:A11,A11)) -> 02 · FUTHOMU01|3
A12: 02 · FUTHOMU01 | B12: Tira de cuello | C12: 1 | F12: Sí | G12: =IF(OR(A12="",N(D12)=0),"",IFERROR(D12*(1+IFERROR(IF(ISNUMBER(INDEX(Moldes!$K$5:$K$154,MATCH(A12,Moldes!$A$5:$A$154,0))),INDEX(Moldes!$K$5:$K$154,MATCH(A12,Moldes!$A$5:$A$154,0)),Precios!$Q$12),Precios!$Q$12))*(INDEX(Precios!$F$5:$F$124,MATCH(E12,Precios!$A$5:$A$124,0))+IF(F12="Sí",Precios!$Q$10,0)),"falta $ tela")) | H12: =IF(A12="","",A12&"|"&COUNTIF($A$5:A12,A12)) -> 02 · FUTHOMU01|4
A13: 03 · FUTINMUJU01 | B13: Delantero | C13: 1 | F13: Sí | G13: =IF(OR(A13="",N(D13)=0),"",IFERROR(D13*(1+IFERROR(IF(ISNUMBER(INDEX(Moldes!$K$5:$K$154,MATCH(A13,Moldes!$A$5:$A$154,0))),INDEX(Moldes!$K$5:$K$154,MATCH(A13,Moldes!$A$5:$A$154,0)),Precios!$Q$12),Precios!$Q$12))*(INDEX(Precios!$F$5:$F$124,MATCH(E13,Precios!$A$5:$A$124,0))+IF(F13="Sí",Precios!$Q$10,0)),"falta $ tela")) | H13: =IF(A13="","",A13&"|"&COUNTIF($A$5:A13,A13)) -> 03 · FUTINMUJU01|1
A14: 03 · FUTINMUJU01 | B14: Espalda | C14: 1 | F14: Sí | G14: =IF(OR(A14="",N(D14)=0),"",IFERROR(D14*(1+IFERROR(IF(ISNUMBER(INDEX(Moldes!$K$5:$K$154,MATCH(A14,Moldes!$A$5:$A$154,0))),INDEX(Moldes!$K$5:$K$154,MATCH(A14,Moldes!$A$5:$A$154,0)),Precios!$Q$12),Precios!$Q$12))*(INDEX(Precios!$F$5:$F$124,MATCH(E14,Precios!$A$5:$A$124,0))+IF(F14="Sí",Precios!$Q$10,0)),"falta $ tela")) | H14: =IF(A14="","",A14&"|"&COUNTIF($A$5:A14,A14)) -> 03 · FUTINMUJU01|2
A15: 03 · FUTINMUJU01 | B15: Manga | C15: 2 | F15: Sí | G15: =IF(OR(A15="",N(D15)=0),"",IFERROR(D15*(1+IFERROR(IF(ISNUMBER(INDEX(Moldes!$K$5:$K$154,MATCH(A15,Moldes!$A$5:$A$154,0))),INDEX(Moldes!$K$5:$K$154,MATCH(A15,Moldes!$A$5:$A$154,0)),Precios!$Q$12),Precios!$Q$12))*(INDEX(Precios!$F$5:$F$124,MATCH(E15,Precios!$A$5:$A$124,0))+IF(F15="Sí",Precios!$Q$10,0)),"falta $ tela")) | H15: =IF(A15="","",A15&"|"&COUNTIF($A$5:A15,A15)) -> 03 · FUTINMUJU01|3
A16: 03 · FUTINMUJU01 | B16: Tira de cuello | C16: 1 | F16: Sí | G16: =IF(OR(A16="",N(D16)=0),"",IFERROR(D16*(1+IFERROR(IF(ISNUMBER(INDEX(Moldes!$K$5:$K$154,MATCH(A16,Moldes!$A$5:$A$154,0))),INDEX(Moldes!$K$5:$K$154,MATCH(A16,Moldes!$A$5:$A$154,0)),Precios!$Q$12),Precios!$Q$12))*(INDEX(Precios!$F$5:$F$124,MATCH(E16,Precios!$A$5:$A$124,0))+IF(F16="Sí",Precios!$Q$10,0)),"falta $ tela")) | H16: =IF(A16="","",A16&"|"&COUNTIF($A$5:A16,A16)) -> 03 · FUTINMUJU01|4
A17: 04 · FUTINHOMU01 | B17: Delantero | C17: 1 | E17: CIRE BLANCO | F17: Sí | G17: =IF(OR(A17="",N(D17)=0),"",IFERROR(D17*(1+IFERROR(IF(ISNUMBER(INDEX(Moldes!$K$5:$K$154,MATCH(A17,Moldes!$A$5:$A$154,0))),INDEX(Moldes!$K$5:$K$154,MATCH(A17,Moldes!$A$5:$A$154,0)),Precios!$Q$12),Precios!$Q$12))*(INDEX(Precios!$F$5:$F$124,MATCH(E17,Precios!$A$5:$A$124,0))+IF(F17="Sí",Precios!$Q$10,0)),"falta $ tela")) | H17: =IF(A17="","",A17&"|"&COUNTIF($A$5:A17,A17)) -> 04 · FUTINHOMU01|1
A18: 04 · FUTINHOMU01 | B18: Espalda | C18: 1 | E18: CIRE BLANCO | F18: Sí | G18: =IF(OR(A18="",N(D18)=0),"",IFERROR(D18*(1+IFERROR(IF(ISNUMBER(INDEX(Moldes!$K$5:$K$154,MATCH(A18,Moldes!$A$5:$A$154,0))),INDEX(Moldes!$K$5:$K$154,MATCH(A18,Moldes!$A$5:$A$154,0)),Precios!$Q$12),Precios!$Q$12))*(INDEX(Precios!$F$5:$F$124,MATCH(E18,Precios!$A$5:$A$124,0))+IF(F18="Sí",Precios!$Q$10,0)),"falta $ tela")) | H18: =IF(A18="","",A18&"|"&COUNTIF($A$5:A18,A18)) -> 04 · FUTINHOMU01|2
A19: 04 · FUTINHOMU01 | B19: Manga | C19: 2 | E19: CIRE BLANCO | F19: Sí | G19: =IF(OR(A19="",N(D19)=0),"",IFERROR(D19*(1+IFERROR(IF(ISNUMBER(INDEX(Moldes!$K$5:$K$154,MATCH(A19,Moldes!$A$5:$A$154,0))),INDEX(Moldes!$K$5:$K$154,MATCH(A19,Moldes!$A$5:$A$154,0)),Precios!$Q$12),Precios!$Q$12))*(INDEX(Precios!$F$5:$F$124,MATCH(E19,Precios!$A$5:$A$124,0))+IF(F19="Sí",Precios!$Q$10,0)),"falta $ tela")) | H19: =IF(A19="","",A19&"|"&COUNTIF($A$5:A19,A19)) -> 04 · FUTINHOMU01|3
A20: 04 · FUTINHOMU01 | B20: Tira de cuello | C20: 1 | E20: CIRE BLANCO | F20: Sí | G20: =IF(OR(A20="",N(D20)=0),"",IFERROR(D20*(1+IFERROR(IF(ISNUMBER(INDEX(Moldes!$K$5:$K$154,MATCH(A20,Moldes!$A$5:$A$154,0))),INDEX(Moldes!$K$5:$K$154,MATCH(A20,Moldes!$A$5:$A$154,0)),Precios!$Q$12),Precios!$Q$12))*(INDEX(Precios!$F$5:$F$124,MATCH(E20,Precios!$A$5:$A$124,0))+IF(F20="Sí",Precios!$Q$10,0)),"falta $ tela")) | H20: =IF(A20="","",A20&"|"&COUNTIF($A$5:A20,A20)) -> 04 · FUTINHOMU01|4
A21: 05 · FUTMUJV01 | B21: Delantero | C21: 1 | F21: Sí | G21: =IF(OR(A21="",N(D21)=0),"",IFERROR(D21*(1+IFERROR(IF(ISNUMBER(INDEX(Moldes!$K$5:$K$154,MATCH(A21,Moldes!$A$5:$A$154,0))),INDEX(Moldes!$K$5:$K$154,MATCH(A21,Moldes!$A$5:$A$154,0)),Precios!$Q$12),Precios!$Q$12))*(INDEX(Precios!$F$5:$F$124,MATCH(E21,Precios!$A$5:$A$124,0))+IF(F21="Sí",Precios!$Q$10,0)),"falta $ tela")) | H21: =IF(A21="","",A21&"|"&COUNTIF($A$5:A21,A21)) -> 05 · FUTMUJV01|1
A22: 05 · FUTMUJV01 | B22: Espalda | C22: 1 | F22: Sí | G22: =IF(OR(A22="",N(D22)=0),"",IFERROR(D22*(1+IFERROR(IF(ISNUMBER(INDEX(Moldes!$K$5:$K$154,MATCH(A22,Moldes!$A$5:$A$154,0))),INDEX(Moldes!$K$5:$K$154,MATCH(A22,Moldes!$A$5:$A$154,0)),Precios!$Q$12),Precios!$Q$12))*(INDEX(Precios!$F$5:$F$124,MATCH(E22,Precios!$A$5:$A$124,0))+IF(F22="Sí",Precios!$Q$10,0)),"falta $ tela")) | H22: =IF(A22="","",A22&"|"&COUNTIF($A$5:A22,A22)) -> 05 · FUTMUJV01|2
A23: 05 · FUTMUJV01 | B23: Manga | C23: 2 | F23: Sí | G23: =IF(OR(A23="",N(D23)=0),"",IFERROR(D23*(1+IFERROR(IF(ISNUMBER(INDEX(Moldes!$K$5:$K$154,MATCH(A23,Moldes!$A$5:$A$154,0))),INDEX(Moldes!$K$5:$K$154,MATCH(A23,Moldes!$A$5:$A$154,0)),Precios!$Q$12),Precios!$Q$12))*(INDEX(Precios!$F$5:$F$124,MATCH(E23,Precios!$A$5:$A$124,0))+IF(F23="Sí",Precios!$Q$10,0)),"falta $ tela")) | H23: =IF(A23="","",A23&"|"&COUNTIF($A$5:A23,A23)) -> 05 · FUTMUJV01|3
A24: 05 · FUTMUJV01 | B24: Tira de cuello | C24: 1 | F24: Sí | G24: =IF(OR(A24="",N(D24)=0),"",IFERROR(D24*(1+IFERROR(IF(ISNUMBER(INDEX(Moldes!$K$5:$K$154,MATCH(A24,Moldes!$A$5:$A$154,0))),INDEX(Moldes!$K$5:$K$154,MATCH(A24,Moldes!$A$5:$A$154,0)),Precios!$Q$12),Precios!$Q$12))*(INDEX(Precios!$F$5:$F$124,MATCH(E24,Precios!$A$5:$A$124,0))+IF(F24="Sí",Precios!$Q$10,0)),"falta $ tela")) | H24: =IF(A24="","",A24&"|"&COUNTIF($A$5:A24,A24)) -> 05 · FUTMUJV01|4
A25: 06 · FUTHOMV01 | B25: Delantero | C25: 1 | F25: Sí | G25: =IF(OR(A25="",N(D25)=0),"",IFERROR(D25*(1+IFERROR(IF(ISNUMBER(INDEX(Moldes!$K$5:$K$154,MATCH(A25,Moldes!$A$5:$A$154,0))),INDEX(Moldes!$K$5:$K$154,MATCH(A25,Moldes!$A$5:$A$154,0)),Precios!$Q$12),Precios!$Q$12))*(INDEX(Precios!$F$5:$F$124,MATCH(E25,Precios!$A$5:$A$124,0))+IF(F25="Sí",Precios!$Q$10,0)),"falta $ tela")) | H25: =IF(A25="","",A25&"|"&COUNTIF($A$5:A25,A25)) -> 06 · FUTHOMV01|1
A26: 06 · FUTHOMV01 | B26: Espalda | C26: 1 | F26: Sí | G26: =IF(OR(A26="",N(D26)=0),"",IFERROR(D26*(1+IFERROR(IF(ISNUMBER(INDEX(Moldes!$K$5:$K$154,MATCH(A26,Moldes!$A$5:$A$154,0))),INDEX(Moldes!$K$5:$K$154,MATCH(A26,Moldes!$A$5:$A$154,0)),Precios!$Q$12),Precios!$Q$12))*(INDEX(Precios!$F$5:$F$124,MATCH(E26,Precios!$A$5:$A$124,0))+IF(F26="Sí",Precios!$Q$10,0)),"falta $ tela")) | H26: =IF(A26="","",A26&"|"&COUNTIF($A$5:A26,A26)) -> 06 · FUTHOMV01|2
A27: 06 · FUTHOMV01 | B27: Manga | C27: 2 | F27: Sí | G27: =IF(OR(A27="",N(D27)=0),"",IFERROR(D27*(1+IFERROR(IF(ISNUMBER(INDEX(Moldes!$K$5:$K$154,MATCH(A27,Moldes!$A$5:$A$154,0))),INDEX(Moldes!$K$5:$K$154,MATCH(A27,Moldes!$A$5:$A$154,0)),Precios!$Q$12),Precios!$Q$12))*(INDEX(Precios!$F$5:$F$124,MATCH(E27,Precios!$A$5:$A$124,0))+IF(F27="Sí",Precios!$Q$10,0)),"falta $ tela")) | H27: =IF(A27="","",A27&"|"&COUNTIF($A$5:A27,A27)) -> 06 · FUTHOMV01|3
A28: 06 · FUTHOMV01 | B28: Tira de cuello | C28: 1 | F28: Sí | G28: =IF(OR(A28="",N(D28)=0),"",IFERROR(D28*(1+IFERROR(IF(ISNUMBER(INDEX(Moldes!$K$5:$K$154,MATCH(A28,Moldes!$A$5:$A$154,0))),INDEX(Moldes!$K$5:$K$154,MATCH(A28,Moldes!$A$5:$A$154,0)),Precios!$Q$12),Precios!$Q$12))*(INDEX(Precios!$F$5:$F$124,MATCH(E28,Precios!$A$5:$A$124,0))+IF(F28="Sí",Precios!$Q$10,0)),"falta $ tela")) | H28: =IF(A28="","",A28&"|"&COUNTIF($A$5:A28,A28)) -> 06 · FUTHOMV01|4
A29: 07 · FUTINMUJV01 | B29: Delantero | C29: 1 | F29: Sí | G29: =IF(OR(A29="",N(D29)=0),"",IFERROR(D29*(1+IFERROR(IF(ISNUMBER(INDEX(Moldes!$K$5:$K$154,MATCH(A29,Moldes!$A$5:$A$154,0))),INDEX(Moldes!$K$5:$K$154,MATCH(A29,Moldes!$A$5:$A$154,0)),Precios!$Q$12),Precios!$Q$12))*(INDEX(Precios!$F$5:$F$124,MATCH(E29,Precios!$A$5:$A$124,0))+IF(F29="Sí",Precios!$Q$10,0)),"falta $ tela")) | H29: =IF(A29="","",A29&"|"&COUNTIF($A$5:A29,A29)) -> 07 · FUTINMUJV01|1
A30: 07 · FUTINMUJV01 | B30: Espalda | C30: 1 | F30: Sí | G30: =IF(OR(A30="",N(D30)=0),"",IFERROR(D30*(1+IFERROR(IF(ISNUMBER(INDEX(Moldes!$K$5:$K$154,MATCH(A30,Moldes!$A$5:$A$154,0))),INDEX(Moldes!$K$5:$K$154,MATCH(A30,Moldes!$A$5:$A$154,0)),Precios!$Q$12),Precios!$Q$12))*(INDEX(Precios!$F$5:$F$124,MATCH(E30,Precios!$A$5:$A$124,0))+IF(F30="Sí",Precios!$Q$10,0)),"falta $ tela")) | H30: =IF(A30="","",A30&"|"&COUNTIF($A$5:A30,A30)) -> 07 · FUTINMUJV01|2
A31: 07 · FUTINMUJV01 | B31: Manga | C31: 2 | F31: Sí | G31: =IF(OR(A31="",N(D31)=0),"",IFERROR(D31*(1+IFERROR(IF(ISNUMBER(INDEX(Moldes!$K$5:$K$154,MATCH(A31,Moldes!$A$5:$A$154,0))),INDEX(Moldes!$K$5:$K$154,MATCH(A31,Moldes!$A$5:$A$154,0)),Precios!$Q$12),Precios!$Q$12))*(INDEX(Precios!$F$5:$F$124,MATCH(E31,Precios!$A$5:$A$124,0))+IF(F31="Sí",Precios!$Q$10,0)),"falta $ tela")) | H31: =IF(A31="","",A31&"|"&COUNTIF($A$5:A31,A31)) -> 07 · FUTINMUJV01|3
A32: 07 · FUTINMUJV01 | B32: Tira de cuello | C32: 1 | F32: Sí | G32: =IF(OR(A32="",N(D32)=0),"",IFERROR(D32*(1+IFERROR(IF(ISNUMBER(INDEX(Moldes!$K$5:$K$154,MATCH(A32,Moldes!$A$5:$A$154,0))),INDEX(Moldes!$K$5:$K$154,MATCH(A32,Moldes!$A$5:$A$154,0)),Precios!$Q$12),Precios!$Q$12))*(INDEX(Precios!$F$5:$F$124,MATCH(E32,Precios!$A$5:$A$124,0))+IF(F32="Sí",Precios!$Q$10,0)),"falta $ tela")) | H32: =IF(A32="","",A32&"|"&COUNTIF($A$5:A32,A32)) -> 07 · FUTINMUJV01|4
... A52: 12 · FUTINHOMCC01 | B52: Tapeta | C52: 1 | F52: Sí | G52: =IF(OR(A52="",N(D52)=0),"",IFERROR(D52*(1+IFERROR(IF(ISNUMBER(INDEX(Moldes!$K$5:$K$154,MATCH(A52,Moldes!$A$5:$A$154,0))),INDEX(Moldes!$K$5:$K$154,MATCH(A52,Moldes!$A$5:$A$154,0)),Precios!$Q$12),Precios!$Q$12))*(INDEX(Precios!$F$5:$F$124,MATCH(E52,Precios!$A$5:$A$124,0))+IF(F52="Sí",Precios!$Q$10,0)),"falta $ tela")) | H52: =IF(A52="","",A52&"|"&COUNTIF($A$5:A52,A52)) -> 12 · FUTINHOMCC01|4
A53: 13 · FUTMUJU01PRO | B53: Delantero | C53: 1 | E53: MONTESIMONE TRAINING (fut pro) | F53: Sí | G53: =IF(OR(A53="",N(D53)=0),"",IFERROR(D53*(1+IFERROR(IF(ISNUMBER(INDEX(Moldes!$K$5:$K$154,MATCH(A53,Moldes!$A$5:$A$154,0))),INDEX(Moldes!$K$5:$K$154,MATCH(A53,Moldes!$A$5:$A$154,0)),Precios!$Q$12),Precios!$Q$12))*(INDEX(Precios!$F$5:$F$124,MATCH(E53,Precios!$A$5:$A$124,0))+IF(F53="Sí",Precios!$Q$10,0)),"falta $ tela")) | H53: =IF(A53="","",A53&"|"&COUNTIF($A$5:A53,A53)) -> 13 · FUTMUJU01PRO|1
A54: 13 · FUTMUJU01PRO | B54: Espalda | C54: 1 | E54: MONTESIMONE TRAINING (fut pro) | F54: Sí | G54: =IF(OR(A54="",N(D54)=0),"",IFERROR(D54*(1+IFERROR(IF(ISNUMBER(INDEX(Moldes!$K$5:$K$154,MATCH(A54,Moldes!$A$5:$A$154,0))),INDEX(Moldes!$K$5:$K$154,MATCH(A54,Moldes!$A$5:$A$154,0)),Precios!$Q$12),Precios!$Q$12))*(INDEX(Precios!$F$5:$F$124,MATCH(E54,Precios!$A$5:$A$124,0))+IF(F54="Sí",Precios!$Q$10,0)),"falta $ tela")) | H54: =IF(A54="","",A54&"|"&COUNTIF($A$5:A54,A54)) -> 13 · FUTMUJU01PRO|2
A55: 13 · FUTMUJU01PRO | B55: Manga | C55: 2 | E55: MONTESIMONE TRAINING (fut pro) | F55: Sí | G55: =IF(OR(A55="",N(D55)=0),"",IFERROR(D55*(1+IFERROR(IF(ISNUMBER(INDEX(Moldes!$K$5:$K$154,MATCH(A55,Moldes!$A$5:$A$154,0))),INDEX(Moldes!$K$5:$K$154,MATCH(A55,Moldes!$A$5:$A$154,0)),Precios!$Q$12),Precios!$Q$12))*(INDEX(Precios!$F$5:$F$124,MATCH(E55,Precios!$A$5:$A$124,0))+IF(F55="Sí",Precios!$Q$10,0)),"falta $ tela")) | H55: =IF(A55="","",A55&"|"&COUNTIF($A$5:A55,A55)) -> 13 · FUTMUJU01PRO|3
A56: 13 · FUTMUJU01PRO | B56: Tira de cuello | C56: 1 | E56: MONTESIMONE TRAINING (fut pro) | F56: Sí | G56: =IF(OR(A56="",N(D56)=0),"",IFERROR(D56*(1+IFERROR(IF(ISNUMBER(INDEX(Moldes!$K$5:$K$154,MATCH(A56,Moldes!$A$5:$A$154,0))),INDEX(Moldes!$K$5:$K$154,MATCH(A56,Moldes!$A$5:$A$154,0)),Precios!$Q$12),Precios!$Q$12))*(INDEX(Precios!$F$5:$F$124,MATCH(E56,Precios!$A$5:$A$124,0))+IF(F56="Sí",Precios!$Q$10,0)),"falta $ tela")) | H56: =IF(A56="","",A56&"|"&COUNTIF($A$5:A56,A56)) -> 13 · FUTMUJU01PRO|4
A57: 13 · FUTMUJU01PRO | B57: Paneles laterales | C57: 2 | E57: MONTESIMONE TRAINING (fut pro) | F57: Sí | G57: =IF(OR(A57="",N(D57)=0),"",IFERROR(D57*(1+IFERROR(IF(ISNUMBER(INDEX(Moldes!$K$5:$K$154,MATCH(A57,Moldes!$A$5:$A$154,0))),INDEX(Moldes!$K$5:$K$154,MATCH(A57,Moldes!$A$5:$A$154,0)),Precios!$Q$12),Precios!$Q$12))*(INDEX(Precios!$F$5:$F$124,MATCH(E57,Precios!$A$5:$A$124,0))+IF(F57="Sí",Precios!$Q$10,0)),"falta $ tela")) | H57: =IF(A57="","",A57&"|"&COUNTIF($A$5:A57,A57)) -> 13 · FUTMUJU01PRO|5
A58: 14 · FUTHOMU01PRO | B58: Delantero | C58: 1 | E58: MONTESIMONE TRAINING (fut pro) | F58: Sí | G58: =IF(OR(A58="",N(D58)=0),"",IFERROR(D58*(1+IFERROR(IF(ISNUMBER(INDEX(Moldes!$K$5:$K$154,MATCH(A58,Moldes!$A$5:$A$154,0))),INDEX(Moldes!$K$5:$K$154,MATCH(A58,Moldes!$A$5:$A$154,0)),Precios!$Q$12),Precios!$Q$12))*(INDEX(Precios!$F$5:$F$124,MATCH(E58,Precios!$A$5:$A$124,0))+IF(F58="Sí",Precios!$Q$10,0)),"falta $ tela")) | H58: =IF(A58="","",A58&"|"&COUNTIF($A$5:A58,A58)) -> 14 · FUTHOMU01PRO|1
A59: 14 · FUTHOMU01PRO | B59: Espalda | C59: 1 | E59: MONTESIMONE TRAINING (fut pro) | F59: Sí | G59: =IF(OR(A59="",N(D59)=0),"",IFERROR(D59*(1+IFERROR(IF(ISNUMBER(INDEX(Moldes!$K$5:$K$154,MATCH(A59,Moldes!$A$5:$A$154,0))),INDEX(Moldes!$K$5:$K$154,MATCH(A59,Moldes!$A$5:$A$154,0)),Precios!$Q$12),Precios!$Q$12))*(INDEX(Precios!$F$5:$F$124,MATCH(E59,Precios!$A$5:$A$124,0))+IF(F59="Sí",Precios!$Q$10,0)),"falta $ tela")) | H59: =IF(A59="","",A59&"|"&COUNTIF($A$5:A59,A59)) -> 14 · FUTHOMU01PRO|2
A60: 14 · FUTHOMU01PRO | B60: Manga | C60: 2 | E60: MONTESIMONE TRAINING (fut pro) | F60: Sí | G60: =IF(OR(A60="",N(D60)=0),"",IFERROR(D60*(1+IFERROR(IF(ISNUMBER(INDEX(Moldes!$K$5:$K$154,MATCH(A60,Moldes!$A$5:$A$154,0))),INDEX(Moldes!$K$5:$K$154,MATCH(A60,Moldes!$A$5:$A$154,0)),Precios!$Q$12),Precios!$Q$12))*(INDEX(Precios!$F$5:$F$124,MATCH(E60,Precios!$A$5:$A$124,0))+IF(F60="Sí",Precios!$Q$10,0)),"falta $ tela")) | H60: =IF(A60="","",A60&"|"&COUNTIF($A$5:A60,A60)) -> 14 · FUTHOMU01PRO|3
A61: 14 · FUTHOMU01PRO | B61: Tira de cuello | C61: 1 | E61: MONTESIMONE TRAINING (fut pro) | F61: Sí | G61: =IF(OR(A61="",N(D61)=0),"",IFERROR(D61*(1+IFERROR(IF(ISNUMBER(INDEX(Moldes!$K$5:$K$154,MATCH(A61,Moldes!$A$5:$A$154,0))),INDEX(Moldes!$K$5:$K$154,MATCH(A61,Moldes!$A$5:$A$154,0)),Precios!$Q$12),Precios!$Q$12))*(INDEX(Precios!$F$5:$F$124,MATCH(E61,Precios!$A$5:$A$124,0))+IF(F61="Sí",Precios!$Q$10,0)),"falta $ tela")) | H61: =IF(A61="","",A61&"|"&COUNTIF($A$5:A61,A61)) -> 14 · FUTHOMU01PRO|4
A62: 14 · FUTHOMU01PRO | B62: Paneles laterales | C62: 2 | E62: MESH | F62: Sí | G62: =IF(OR(A62="",N(D62)=0),"",IFERROR(D62*(1+IFERROR(IF(ISNUMBER(INDEX(Moldes!$K$5:$K$154,MATCH(A62,Moldes!$A$5:$A$154,0))),INDEX(Moldes!$K$5:$K$154,MATCH(A62,Moldes!$A$5:$A$154,0)),Precios!$Q$12),Precios!$Q$12))*(INDEX(Precios!$F$5:$F$124,MATCH(E62,Precios!$A$5:$A$124,0))+IF(F62="Sí",Precios!$Q$10,0)),"falta $ tela")) | H62: =IF(A62="","",A62&"|"&COUNTIF($A$5:A62,A62)) -> 14 · FUTHOMU01PRO|5
A63: 15 · FUTMUJV01PRO | B63: Delantero | C63: 1 | F63: Sí | G63: =IF(OR(A63="",N(D63)=0),"",IFERROR(D63*(1+IFERROR(IF(ISNUMBER(INDEX(Moldes!$K$5:$K$154,MATCH(A63,Moldes!$A$5:$A$154,0))),INDEX(Moldes!$K$5:$K$154,MATCH(A63,Moldes!$A$5:$A$154,0)),Precios!$Q$12),Precios!$Q$12))*(INDEX(Precios!$F$5:$F$124,MATCH(E63,Precios!$A$5:$A$124,0))+IF(F63="Sí",Precios!$Q$10,0)),"falta $ tela")) | H63: =IF(A63="","",A63&"|"&COUNTIF($A$5:A63,A63)) -> 15 · FUTMUJV01PRO|1
A64: 15 · FUTMUJV01PRO | B64: Espalda | C64: 1 | F64: Sí | G64: =IF(OR(A64="",N(D64)=0),"",IFERROR(D64*(1+IFERROR(IF(ISNUMBER(INDEX(Moldes!$K$5:$K$154,MATCH(A64,Moldes!$A$5:$A$154,0))),INDEX(Moldes!$K$5:$K$154,MATCH(A64,Moldes!$A$5:$A$154,0)),Precios!$Q$12),Precios!$Q$12))*(INDEX(Precios!$F$5:$F$124,MATCH(E64,Precios!$A$5:$A$124,0))+IF(F64="Sí",Precios!$Q$10,0)),"falta $ tela")) | H64: =IF(A64="","",A64&"|"&COUNTIF($A$5:A64,A64)) -> 15 · FUTMUJV01PRO|2
A65: 15 · FUTMUJV01PRO | B65: Manga | C65: 2 | F65: Sí | G65: =IF(OR(A65="",N(D65)=0),"",IFERROR(D65*(1+IFERROR(IF(ISNUMBER(INDEX(Moldes!$K$5:$K$154,MATCH(A65,Moldes!$A$5:$A$154,0))),INDEX(Moldes!$K$5:$K$154,MATCH(A65,Moldes!$A$5:$A$154,0)),Precios!$Q$12),Precios!$Q$12))*(INDEX(Precios!$F$5:$F$124,MATCH(E65,Precios!$A$5:$A$124,0))+IF(F65="Sí",Precios!$Q$10,0)),"falta $ tela")) | H65: =IF(A65="","",A65&"|"&COUNTIF($A$5:A65,A65)) -> 15 · FUTMUJV01PRO|3
A66: 15 · FUTMUJV01PRO | B66: Tira de cuello | C66: 1 | F66: Sí | G66: =IF(OR(A66="",N(D66)=0),"",IFERROR(D66*(1+IFERROR(IF(ISNUMBER(INDEX(Moldes!$K$5:$K$154,MATCH(A66,Moldes!$A$5:$A$154,0))),INDEX(Moldes!$K$5:$K$154,MATCH(A66,Moldes!$A$5:$A$154,0)),Precios!$Q$12),Precios!$Q$12))*(INDEX(Precios!$F$5:$F$124,MATCH(E66,Precios!$A$5:$A$124,0))+IF(F66="Sí",Precios!$Q$10,0)),"falta $ tela")) | H66: =IF(A66="","",A66&"|"&COUNTIF($A$5:A66,A66)) -> 15 · FUTMUJV01PRO|4
A67: 15 · FUTMUJV01PRO | B67: Paneles laterales | C67: 2 | F67: Sí | G67: =IF(OR(A67="",N(D67)=0),"",IFERROR(D67*(1+IFERROR(IF(ISNUMBER(INDEX(Moldes!$K$5:$K$154,MATCH(A67,Moldes!$A$5:$A$154,0))),INDEX(Moldes!$K$5:$K$154,MATCH(A67,Moldes!$A$5:$A$154,0)),Precios!$Q$12),Precios!$Q$12))*(INDEX(Precios!$F$5:$F$124,MATCH(E67,Precios!$A$5:$A$124,0))+IF(F67="Sí",Precios!$Q$10,0)),"falta $ tela")) | H67: =IF(A67="","",A67&"|"&COUNTIF($A$5:A67,A67)) -> 15 · FUTMUJV01PRO|5
A68: 16 · FUTHOMV01PRO | B68: Delantero | C68: 1 | F68: Sí | G68: =IF(OR(A68="",N(D68)=0),"",IFERROR(D68*(1+IFERROR(IF(ISNUMBER(INDEX(Moldes!$K$5:$K$154,MATCH(A68,Moldes!$A$5:$A$154,0))),INDEX(Moldes!$K$5:$K$154,MATCH(A68,Moldes!$A$5:$A$154,0)),Precios!$Q$12),Precios!$Q$12))*(INDEX(Precios!$F$5:$F$124,MATCH(E68,Precios!$A$5:$A$124,0))+IF(F68="Sí",Precios!$Q$10,0)),"falta $ tela")) | H68: =IF(A68="","",A68&"|"&COUNTIF($A$5:A68,A68)) -> 16 · FUTHOMV01PRO|1
A69: 16 · FUTHOMV01PRO | B69: Espalda | C69: 1 | F69: Sí | G69: =IF(OR(A69="",N(D69)=0),"",IFERROR(D69*(1+IFERROR(IF(ISNUMBER(INDEX(Moldes!$K$5:$K$154,MATCH(A69,Moldes!$A$5:$A$154,0))),INDEX(Moldes!$K$5:$K$154,MATCH(A69,Moldes!$A$5:$A$154,0)),Precios!$Q$12),Precios!$Q$12))*(INDEX(Precios!$F$5:$F$124,MATCH(E69,Precios!$A$5:$A$124,0))+IF(F69="Sí",Precios!$Q$10,0)),"falta $ tela")) | H69: =IF(A69="","",A69&"|"&COUNTIF($A$5:A69,A69)) -> 16 · FUTHOMV01PRO|2
A70: 16 · FUTHOMV01PRO | B70: Manga | C70: 2 | F70: Sí | G70: =IF(OR(A70="",N(D70)=0),"",IFERROR(D70*(1+IFERROR(IF(ISNUMBER(INDEX(Moldes!$K$5:$K$154,MATCH(A70,Moldes!$A$5:$A$154,0))),INDEX(Moldes!$K$5:$K$154,MATCH(A70,Moldes!$A$5:$A$154,0)),Precios!$Q$12),Precios!$Q$12))*(INDEX(Precios!$F$5:$F$124,MATCH(E70,Precios!$A$5:$A$124,0))+IF(F70="Sí",Precios!$Q$10,0)),"falta $ tela")) | H70: =IF(A70="","",A70&"|"&COUNTIF($A$5:A70,A70)) -> 16 · FUTHOMV01PRO|3
A71: 16 · FUTHOMV01PRO | B71: Tira de cuello | C71: 1 | F71: Sí | G71: =IF(OR(A71="",N(D71)=0),"",IFERROR(D71*(1+IFERROR(IF(ISNUMBER(INDEX(Moldes!$K$5:$K$154,MATCH(A71,Moldes!$A$5:$A$154,0))),INDEX(Moldes!$K$5:$K$154,MATCH(A71,Moldes!$A$5:$A$154,0)),Precios!$Q$12),Precios!$Q$12))*(INDEX(Precios!$F$5:$F$124,MATCH(E71,Precios!$A$5:$A$124,0))+IF(F71="Sí",Precios!$Q$10,0)),"falta $ tela")) | H71: =IF(A71="","",A71&"|"&COUNTIF($A$5:A71,A71)) -> 16 · FUTHOMV01PRO|4
A72: 16 · FUTHOMV01PRO | B72: Paneles laterales | C72: 2 | F72: Sí | G72: =IF(OR(A72="",N(D72)=0),"",IFERROR(D72*(1+IFERROR(IF(ISNUMBER(INDEX(Moldes!$K$5:$K$154,MATCH(A72,Moldes!$A$5:$A$154,0))),INDEX(Moldes!$K$5:$K$154,MATCH(A72,Moldes!$A$5:$A$154,0)),Precios!$Q$12),Precios!$Q$12))*(INDEX(Precios!$F$5:$F$124,MATCH(E72,Precios!$A$5:$A$124,0))+IF(F72="Sí",Precios!$Q$10,0)),"falta $ tela")) | H72: =IF(A72="","",A72&"|"&COUNTIF($A$5:A72,A72)) -> 16 · FUTHOMV01PRO|5
A73: 17 · FUTMUJU02 | B73: Delantero | C73: 1 | F73: Sí | G73: =IF(OR(A73="",N(D73)=0),"",IFERROR(D73*(1+IFERROR(IF(ISNUMBER(INDEX(Moldes!$K$5:$K$154,MATCH(A73,Moldes!$A$5:$A$154,0))),INDEX(Moldes!$K$5:$K$154,MATCH(A73,Moldes!$A$5:$A$154,0)),Precios!$Q$12),Precios!$Q$12))*(INDEX(Precios!$F$5:$F$124,MATCH(E73,Precios!$A$5:$A$124,0))+IF(F73="Sí",Precios!$Q$10,0)),"falta $ tela")) | H73: =IF(A73="","",A73&"|"&COUNTIF($A$5:A73,A73)) -> 17 · FUTMUJU02|1
A74: 17 · FUTMUJU02 | B74: Espalda | C74: 1 | F74: Sí | G74: =IF(OR(A74="",N(D74)=0),"",IFERROR(D74*(1+IFERROR(IF(ISNUMBER(INDEX(Moldes!$K$5:$K$154,MATCH(A74,Moldes!$A$5:$A$154,0))),INDEX(Moldes!$K$5:$K$154,MATCH(A74,Moldes!$A$5:$A$154,0)),Precios!$Q$12),Precios!$Q$12))*(INDEX(Precios!$F$5:$F$124,MATCH(E74,Precios!$A$5:$A$124,0))+IF(F74="Sí",Precios!$Q$10,0)),"falta $ tela")) | H74: =IF(A74="","",A74&"|"&COUNTIF($A$5:A74,A74)) -> 17 · FUTMUJU02|2
... A127: 29 · BKMUJU03 | B127: Ribete cuello y sisas | C127: 1 | F127: Sí | G127: =IF(OR(A127="",N(D127)=0),"",IFERROR(D127*(1+IFERROR(IF(ISNUMBER(INDEX(Moldes!$K$5:$K$154,MATCH(A127,Moldes!$A$5:$A$154,0))),INDEX(Moldes!$K$5:$K$154,MATCH(A127,Moldes!$A$5:$A$154,0)),Precios!$Q$12),Precios!$Q$12))*(INDEX(Precios!$F$5:$F$124,MATCH(E127,Precios!$A$5:$A$124,0))+IF(F127="Sí",Precios!$Q$10,0)),"falta $ tela")) | H127: =IF(A127="","",A127&"|"&COUNTIF($A$5:A127,A127)) -> 29 · BKMUJU03|3
A128: 30 · BKHOMU03 | B128: Delantero | C128: 1 | E128: QUICKDRY | F128: Sí | G128: =IF(OR(A128="",N(D128)=0),"",IFERROR(D128*(1+IFERROR(IF(ISNUMBER(INDEX(Moldes!$K$5:$K$154,MATCH(A128,Moldes!$A$5:$A$154,0))),INDEX(Moldes!$K$5:$K$154,MATCH(A128,Moldes!$A$5:$A$154,0)),Precios!$Q$12),Precios!$Q$12))*(INDEX(Precios!$F$5:$F$124,MATCH(E128,Precios!$A$5:$A$124,0))+IF(F128="Sí",Precios!$Q$10,0)),"falta $ tela")) | H128: =IF(A128="","",A128&"|"&COUNTIF($A$5:A128,A128)) -> 30 · BKHOMU03|1
A129: 30 · BKHOMU03 | B129: Espalda | C129: 1 | E129: QUICKDRY | F129: Sí | G129: =IF(OR(A129="",N(D129)=0),"",IFERROR(D129*(1+IFERROR(IF(ISNUMBER(INDEX(Moldes!$K$5:$K$154,MATCH(A129,Moldes!$A$5:$A$154,0))),INDEX(Moldes!$K$5:$K$154,MATCH(A129,Moldes!$A$5:$A$154,0)),Precios!$Q$12),Precios!$Q$12))*(INDEX(Precios!$F$5:$F$124,MATCH(E129,Precios!$A$5:$A$124,0))+IF(F129="Sí",Precios!$Q$10,0)),"falta $ tela")) | H129: =IF(A129="","",A129&"|"&COUNTIF($A$5:A129,A129)) -> 30 · BKHOMU03|2
A130: 30 · BKHOMU03 | B130: Ribete cuello y sisas | C130: 1 | E130: QUICKDRY | F130: Sí | G130: =IF(OR(A130="",N(D130)=0),"",IFERROR(D130*(1+IFERROR(IF(ISNUMBER(INDEX(Moldes!$K$5:$K$154,MATCH(A130,Moldes!$A$5:$A$154,0))),INDEX(Moldes!$K$5:$K$154,MATCH(A130,Moldes!$A$5:$A$154,0)),Precios!$Q$12),Precios!$Q$12))*(INDEX(Precios!$F$5:$F$124,MATCH(E130,Precios!$A$5:$A$124,0))+IF(F130="Sí",Precios!$Q$10,0)),"falta $ tela")) | H130: =IF(A130="","",A130&"|"&COUNTIF($A$5:A130,A130)) -> 30 · BKHOMU03|3
A131: 31 · BKINMUJU03 | B131: Delantero | C131: 1 | F131: Sí | G131: =IF(OR(A131="",N(D131)=0),"",IFERROR(D131*(1+IFERROR(IF(ISNUMBER(INDEX(Moldes!$K$5:$K$154,MATCH(A131,Moldes!$A$5:$A$154,0))),INDEX(Moldes!$K$5:$K$154,MATCH(A131,Moldes!$A$5:$A$154,0)),Precios!$Q$12),Precios!$Q$12))*(INDEX(Precios!$F$5:$F$124,MATCH(E131,Precios!$A$5:$A$124,0))+IF(F131="Sí",Precios!$Q$10,0)),"falta $ tela")) | H131: =IF(A131="","",A131&"|"&COUNTIF($A$5:A131,A131)) -> 31 · BKINMUJU03|1
A132: 31 · BKINMUJU03 | B132: Espalda | C132: 1 | F132: Sí | G132: =IF(OR(A132="",N(D132)=0),"",IFERROR(D132*(1+IFERROR(IF(ISNUMBER(INDEX(Moldes!$K$5:$K$154,MATCH(A132,Moldes!$A$5:$A$154,0))),INDEX(Moldes!$K$5:$K$154,MATCH(A132,Moldes!$A$5:$A$154,0)),Precios!$Q$12),Precios!$Q$12))*(INDEX(Precios!$F$5:$F$124,MATCH(E132,Precios!$A$5:$A$124,0))+IF(F132="Sí",Precios!$Q$10,0)),"falta $ tela")) | H132: =IF(A132="","",A132&"|"&COUNTIF($A$5:A132,A132)) -> 31 · BKINMUJU03|2
A133: 31 · BKINMUJU03 | B133: Ribete cuello y sisas | C133: 1 | F133: Sí | G133: =IF(OR(A133="",N(D133)=0),"",IFERROR(D133*(1+IFERROR(IF(ISNUMBER(INDEX(Moldes!$K$5:$K$154,MATCH(A133,Moldes!$A$5:$A$154,0))),INDEX(Moldes!$K$5:$K$154,MATCH(A133,Moldes!$A$5:$A$154,0)),Precios!$Q$12),Precios!$Q$12))*(INDEX(Precios!$F$5:$F$124,MATCH(E133,Precios!$A$5:$A$124,0))+IF(F133="Sí",Precios!$Q$10,0)),"falta $ tela")) | H133: =IF(A133="","",A133&"|"&COUNTIF($A$5:A133,A133)) -> 31 · BKINMUJU03|3
A134: 32 · BKINHOMU03 | B134: Delantero | C134: 1 | F134: Sí | G134: =IF(OR(A134="",N(D134)=0),"",IFERROR(D134*(1+IFERROR(IF(ISNUMBER(INDEX(Moldes!$K$5:$K$154,MATCH(A134,Moldes!$A$5:$A$154,0))),INDEX(Moldes!$K$5:$K$154,MATCH(A134,Moldes!$A$5:$A$154,0)),Precios!$Q$12),Precios!$Q$12))*(INDEX(Precios!$F$5:$F$124,MATCH(E134,Precios!$A$5:$A$124,0))+IF(F134="Sí",Precios!$Q$10,0)),"falta $ tela")) | H134: =IF(A134="","",A134&"|"&COUNTIF($A$5:A134,A134)) -> 32 · BKINHOMU03|1
A135: 32 · BKINHOMU03 | B135: Espalda | C135: 1 | F135: Sí | G135: =IF(OR(A135="",N(D135)=0),"",IFERROR(D135*(1+IFERROR(IF(ISNUMBER(INDEX(Moldes!$K$5:$K$154,MATCH(A135,Moldes!$A$5:$A$154,0))),INDEX(Moldes!$K$5:$K$154,MATCH(A135,Moldes!$A$5:$A$154,0)),Precios!$Q$12),Precios!$Q$12))*(INDEX(Precios!$F$5:$F$124,MATCH(E135,Precios!$A$5:$A$124,0))+IF(F135="Sí",Precios!$Q$10,0)),"falta $ tela")) | H135: =IF(A135="","",A135&"|"&COUNTIF($A$5:A135,A135)) -> 32 · BKINHOMU03|2
A136: 32 · BKINHOMU03 | B136: Ribete cuello y sisas | C136: 1 | F136: Sí | G136: =IF(OR(A136="",N(D136)=0),"",IFERROR(D136*(1+IFERROR(IF(ISNUMBER(INDEX(Moldes!$K$5:$K$154,MATCH(A136,Moldes!$A$5:$A$154,0))),INDEX(Moldes!$K$5:$K$154,MATCH(A136,Moldes!$A$5:$A$154,0)),Precios!$Q$12),Precios!$Q$12))*(INDEX(Precios!$F$5:$F$124,MATCH(E136,Precios!$A$5:$A$124,0))+IF(F136="Sí",Precios!$Q$10,0)),"falta $ tela")) | H136: =IF(A136="","",A136&"|"&COUNTIF($A$5:A136,A136)) -> 32 · BKINHOMU03|3
A137: 33 · BKMUJV03 | B137: Delantero | C137: 1 | F137: Sí | G137: =IF(OR(A137="",N(D137)=0),"",IFERROR(D137*(1+IFERROR(IF(ISNUMBER(INDEX(Moldes!$K$5:$K$154,MATCH(A137,Moldes!$A$5:$A$154,0))),INDEX(Moldes!$K$5:$K$154,MATCH(A137,Moldes!$A$5:$A$154,0)),Precios!$Q$12),Precios!$Q$12))*(INDEX(Precios!$F$5:$F$124,MATCH(E137,Precios!$A$5:$A$124,0))+IF(F137="Sí",Precios!$Q$10,0)),"falta $ tela")) | H137: =IF(A137="","",A137&"|"&COUNTIF($A$5:A137,A137)) -> 33 · BKMUJV03|1
A138: 33 · BKMUJV03 | B138: Espalda | C138: 1 | F138: Sí | G138: =IF(OR(A138="",N(D138)=0),"",IFERROR(D138*(1+IFERROR(IF(ISNUMBER(INDEX(Moldes!$K$5:$K$154,MATCH(A138,Moldes!$A$5:$A$154,0))),INDEX(Moldes!$K$5:$K$154,MATCH(A138,Moldes!$A$5:$A$154,0)),Precios!$Q$12),Precios!$Q$12))*(INDEX(Precios!$F$5:$F$124,MATCH(E138,Precios!$A$5:$A$124,0))+IF(F138="Sí",Precios!$Q$10,0)),"falta $ tela")) | H138: =IF(A138="","",A138&"|"&COUNTIF($A$5:A138,A138)) -> 33 · BKMUJV03|2
A139: 33 · BKMUJV03 | B139: Ribete cuello y sisas | C139: 1 | F139: Sí | G139: =IF(OR(A139="",N(D139)=0),"",IFERROR(D139*(1+IFERROR(IF(ISNUMBER(INDEX(Moldes!$K$5:$K$154,MATCH(A139,Moldes!$A$5:$A$154,0))),INDEX(Moldes!$K$5:$K$154,MATCH(A139,Moldes!$A$5:$A$154,0)),Precios!$Q$12),Precios!$Q$12))*(INDEX(Precios!$F$5:$F$124,MATCH(E139,Precios!$A$5:$A$124,0))+IF(F139="Sí",Precios!$Q$10,0)),"falta $ tela")) | H139: =IF(A139="","",A139&"|"&COUNTIF($A$5:A139,A139)) -> 33 · BKMUJV03|3
A140: 34 · BKHOMV03 | B140: Delantero | C140: 1 | F140: Sí | G140: =IF(OR(A140="",N(D140)=0),"",IFERROR(D140*(1+IFERROR(IF(ISNUMBER(INDEX(Moldes!$K$5:$K$154,MATCH(A140,Moldes!$A$5:$A$154,0))),INDEX(Moldes!$K$5:$K$154,MATCH(A140,Moldes!$A$5:$A$154,0)),Precios!$Q$12),Precios!$Q$12))*(INDEX(Precios!$F$5:$F$124,MATCH(E140,Precios!$A$5:$A$124,0))+IF(F140="Sí",Precios!$Q$10,0)),"falta $ tela")) | H140: =IF(A140="","",A140&"|"&COUNTIF($A$5:A140,A140)) -> 34 · BKHOMV03|1
A141: 34 · BKHOMV03 | B141: Espalda | C141: 1 | F141: Sí | G141: =IF(OR(A141="",N(D141)=0),"",IFERROR(D141*(1+IFERROR(IF(ISNUMBER(INDEX(Moldes!$K$5:$K$154,MATCH(A141,Moldes!$A$5:$A$154,0))),INDEX(Moldes!$K$5:$K$154,MATCH(A141,Moldes!$A$5:$A$154,0)),Precios!$Q$12),Precios!$Q$12))*(INDEX(Precios!$F$5:$F$124,MATCH(E141,Precios!$A$5:$A$124,0))+IF(F141="Sí",Precios!$Q$10,0)),"falta $ tela")) | H141: =IF(A141="","",A141&"|"&COUNTIF($A$5:A141,A141)) -> 34 · BKHOMV03|2
A142: 34 · BKHOMV03 | B142: Ribete cuello y sisas | C142: 1 | F142: Sí | G142: =IF(OR(A142="",N(D142)=0),"",IFERROR(D142*(1+IFERROR(IF(ISNUMBER(INDEX(Moldes!$K$5:$K$154,MATCH(A142,Moldes!$A$5:$A$154,0))),INDEX(Moldes!$K$5:$K$154,MATCH(A142,Moldes!$A$5:$A$154,0)),Precios!$Q$12),Precios!$Q$12))*(INDEX(Precios!$F$5:$F$124,MATCH(E142,Precios!$A$5:$A$124,0))+IF(F142="Sí",Precios!$Q$10,0)),"falta $ tela")) | H142: =IF(A142="","",A142&"|"&COUNTIF($A$5:A142,A142)) -> 34 · BKHOMV03|3
... A187: 45 · BKSHMUJ | B187: Pretina | C187: 1 | F187: Sí | G187: =IF(OR(A187="",N(D187)=0),"",IFERROR(D187*(1+IFERROR(IF(ISNUMBER(INDEX(Moldes!$K$5:$K$154,MATCH(A187,Moldes!$A$5:$A$154,0))),INDEX(Moldes!$K$5:$K$154,MATCH(A187,Moldes!$A$5:$A$154,0)),Precios!$Q$12),Precios!$Q$12))*(INDEX(Precios!$F$5:$F$124,MATCH(E187,Precios!$A$5:$A$124,0))+IF(F187="Sí",Precios!$Q$10,0)),"falta $ tela")) | H187: =IF(A187="","",A187&"|"&COUNTIF($A$5:A187,A187)) -> 45 · BKSHMUJ|3
A188: 46 · BK-SH | B188: Delantero | C188: 2 | E188: QUICKDRY | F188: Sí | G188: =IF(OR(A188="",N(D188)=0),"",IFERROR(D188*(1+IFERROR(IF(ISNUMBER(INDEX(Moldes!$K$5:$K$154,MATCH(A188,Moldes!$A$5:$A$154,0))),INDEX(Moldes!$K$5:$K$154,MATCH(A188,Moldes!$A$5:$A$154,0)),Precios!$Q$12),Precios!$Q$12))*(INDEX(Precios!$F$5:$F$124,MATCH(E188,Precios!$A$5:$A$124,0))+IF(F188="Sí",Precios!$Q$10,0)),"falta $ tela")) | H188: =IF(A188="","",A188&"|"&COUNTIF($A$5:A188,A188)) -> 46 · BK-SH|1
A189: 46 · BK-SH | B189: Trasero | C189: 2 | E189: QUICKDRY | F189: Sí | G189: =IF(OR(A189="",N(D189)=0),"",IFERROR(D189*(1+IFERROR(IF(ISNUMBER(INDEX(Moldes!$K$5:$K$154,MATCH(A189,Moldes!$A$5:$A$154,0))),INDEX(Moldes!$K$5:$K$154,MATCH(A189,Moldes!$A$5:$A$154,0)),Precios!$Q$12),Precios!$Q$12))*(INDEX(Precios!$F$5:$F$124,MATCH(E189,Precios!$A$5:$A$124,0))+IF(F189="Sí",Precios!$Q$10,0)),"falta $ tela")) | H189: =IF(A189="","",A189&"|"&COUNTIF($A$5:A189,A189)) -> 46 · BK-SH|2
A190: 46 · BK-SH | B190: Pretina | C190: 1 | E190: QUICKDRY | F190: Sí | G190: =IF(OR(A190="",N(D190)=0),"",IFERROR(D190*(1+IFERROR(IF(ISNUMBER(INDEX(Moldes!$K$5:$K$154,MATCH(A190,Moldes!$A$5:$A$154,0))),INDEX(Moldes!$K$5:$K$154,MATCH(A190,Moldes!$A$5:$A$154,0)),Precios!$Q$12),Precios!$Q$12))*(INDEX(Precios!$F$5:$F$124,MATCH(E190,Precios!$A$5:$A$124,0))+IF(F190="Sí",Precios!$Q$10,0)),"falta $ tela")) | H190: =IF(A190="","",A190&"|"&COUNTIF($A$5:A190,A190)) -> 46 · BK-SH|3
A191: 47 · BKINSHMUJ | B191: Delantero | C191: 2 | F191: Sí | G191: =IF(OR(A191="",N(D191)=0),"",IFERROR(D191*(1+IFERROR(IF(ISNUMBER(INDEX(Moldes!$K$5:$K$154,MATCH(A191,Moldes!$A$5:$A$154,0))),INDEX(Moldes!$K$5:$K$154,MATCH(A191,Moldes!$A$5:$A$154,0)),Precios!$Q$12),Precios!$Q$12))*(INDEX(Precios!$F$5:$F$124,MATCH(E191,Precios!$A$5:$A$124,0))+IF(F191="Sí",Precios!$Q$10,0)),"falta $ tela")) | H191: =IF(A191="","",A191&"|"&COUNTIF($A$5:A191,A191)) -> 47 · BKINSHMUJ|1
A192: 47 · BKINSHMUJ | B192: Trasero | C192: 2 | F192: Sí | G192: =IF(OR(A192="",N(D192)=0),"",IFERROR(D192*(1+IFERROR(IF(ISNUMBER(INDEX(Moldes!$K$5:$K$154,MATCH(A192,Moldes!$A$5:$A$154,0))),INDEX(Moldes!$K$5:$K$154,MATCH(A192,Moldes!$A$5:$A$154,0)),Precios!$Q$12),Precios!$Q$12))*(INDEX(Precios!$F$5:$F$124,MATCH(E192,Precios!$A$5:$A$124,0))+IF(F192="Sí",Precios!$Q$10,0)),"falta $ tela")) | H192: =IF(A192="","",A192&"|"&COUNTIF($A$5:A192,A192)) -> 47 · BKINSHMUJ|2
A193: 47 · BKINSHMUJ | B193: Pretina | C193: 1 | F193: Sí | G193: =IF(OR(A193="",N(D193)=0),"",IFERROR(D193*(1+IFERROR(IF(ISNUMBER(INDEX(Moldes!$K$5:$K$154,MATCH(A193,Moldes!$A$5:$A$154,0))),INDEX(Moldes!$K$5:$K$154,MATCH(A193,Moldes!$A$5:$A$154,0)),Precios!$Q$12),Precios!$Q$12))*(INDEX(Precios!$F$5:$F$124,MATCH(E193,Precios!$A$5:$A$124,0))+IF(F193="Sí",Precios!$Q$10,0)),"falta $ tela")) | H193: =IF(A193="","",A193&"|"&COUNTIF($A$5:A193,A193)) -> 47 · BKINSHMUJ|3
A194: 48 · BKINSHHOM | B194: Delantero | C194: 2 | F194: Sí | G194: =IF(OR(A194="",N(D194)=0),"",IFERROR(D194*(1+IFERROR(IF(ISNUMBER(INDEX(Moldes!$K$5:$K$154,MATCH(A194,Moldes!$A$5:$A$154,0))),INDEX(Moldes!$K$5:$K$154,MATCH(A194,Moldes!$A$5:$A$154,0)),Precios!$Q$12),Precios!$Q$12))*(INDEX(Precios!$F$5:$F$124,MATCH(E194,Precios!$A$5:$A$124,0))+IF(F194="Sí",Precios!$Q$10,0)),"falta $ tela")) | H194: =IF(A194="","",A194&"|"&COUNTIF($A$5:A194,A194)) -> 48 · BKINSHHOM|1
A195: 48 · BKINSHHOM | B195: Trasero | C195: 2 | F195: Sí | G195: =IF(OR(A195="",N(D195)=0),"",IFERROR(D195*(1+IFERROR(IF(ISNUMBER(INDEX(Moldes!$K$5:$K$154,MATCH(A195,Moldes!$A$5:$A$154,0))),INDEX(Moldes!$K$5:$K$154,MATCH(A195,Moldes!$A$5:$A$154,0)),Precios!$Q$12),Precios!$Q$12))*(INDEX(Precios!$F$5:$F$124,MATCH(E195,Precios!$A$5:$A$124,0))+IF(F195="Sí",Precios!$Q$10,0)),"falta $ tela")) | H195: =IF(A195="","",A195&"|"&COUNTIF($A$5:A195,A195)) -> 48 · BKINSHHOM|2
A196: 48 · BKINSHHOM | B196: Pretina | C196: 1 | F196: Sí | G196: =IF(OR(A196="",N(D196)=0),"",IFERROR(D196*(1+IFERROR(IF(ISNUMBER(INDEX(Moldes!$K$5:$K$154,MATCH(A196,Moldes!$A$5:$A$154,0))),INDEX(Moldes!$K$5:$K$154,MATCH(A196,Moldes!$A$5:$A$154,0)),Precios!$Q$12),Precios!$Q$12))*(INDEX(Precios!$F$5:$F$124,MATCH(E196,Precios!$A$5:$A$124,0))+IF(F196="Sí",Precios!$Q$10,0)),"falta $ tela")) | H196: =IF(A196="","",A196&"|"&COUNTIF($A$5:A196,A196)) -> 48 · BKINSHHOM|3
A197: 49 · BKSHMUJRE | B197: Delantero cara A | C197: 2 | F197: Sí | G197: =IF(OR(A197="",N(D197)=0),"",IFERROR(D197*(1+IFERROR(IF(ISNUMBER(INDEX(Moldes!$K$5:$K$154,MATCH(A197,Moldes!$A$5:$A$154,0))),INDEX(Moldes!$K$5:$K$154,MATCH(A197,Moldes!$A$5:$A$154,0)),Precios!$Q$12),Precios!$Q$12))*(INDEX(Precios!$F$5:$F$124,MATCH(E197,Precios!$A$5:$A$124,0))+IF(F197="Sí",Precios!$Q$10,0)),"falta $ tela")) | H197: =IF(A197="","",A197&"|"&COUNTIF($A$5:A197,A197)) -> 49 · BKSHMUJRE|1
A198: 49 · BKSHMUJRE | B198: Trasero cara A | C198: 2 | F198: Sí | G198: =IF(OR(A198="",N(D198)=0),"",IFERROR(D198*(1+IFERROR(IF(ISNUMBER(INDEX(Moldes!$K$5:$K$154,MATCH(A198,Moldes!$A$5:$A$154,0))),INDEX(Moldes!$K$5:$K$154,MATCH(A198,Moldes!$A$5:$A$154,0)),Precios!$Q$12),Precios!$Q$12))*(INDEX(Precios!$F$5:$F$124,MATCH(E198,Precios!$A$5:$A$124,0))+IF(F198="Sí",Precios!$Q$10,0)),"falta $ tela")) | H198: =IF(A198="","",A198&"|"&COUNTIF($A$5:A198,A198)) -> 49 · BKSHMUJRE|2
A199: 49 · BKSHMUJRE | B199: Pretina cara A | C199: 1 | F199: Sí | G199: =IF(OR(A199="",N(D199)=0),"",IFERROR(D199*(1+IFERROR(IF(ISNUMBER(INDEX(Moldes!$K$5:$K$154,MATCH(A199,Moldes!$A$5:$A$154,0))),INDEX(Moldes!$K$5:$K$154,MATCH(A199,Moldes!$A$5:$A$154,0)),Precios!$Q$12),Precios!$Q$12))*(INDEX(Precios!$F$5:$F$124,MATCH(E199,Precios!$A$5:$A$124,0))+IF(F199="Sí",Precios!$Q$10,0)),"falta $ tela")) | H199: =IF(A199="","",A199&"|"&COUNTIF($A$5:A199,A199)) -> 49 · BKSHMUJRE|3
A200: 49 · BKSHMUJRE | B200: Delantero cara B | C200: 2 | F200: Sí | G200: =IF(OR(A200="",N(D200)=0),"",IFERROR(D200*(1+IFERROR(IF(ISNUMBER(INDEX(Moldes!$K$5:$K$154,MATCH(A200,Moldes!$A$5:$A$154,0))),INDEX(Moldes!$K$5:$K$154,MATCH(A200,Moldes!$A$5:$A$154,0)),Precios!$Q$12),Precios!$Q$12))*(INDEX(Precios!$F$5:$F$124,MATCH(E200,Precios!$A$5:$A$124,0))+IF(F200="Sí",Precios!$Q$10,0)),"falta $ tela")) | H200: =IF(A200="","",A200&"|"&COUNTIF($A$5:A200,A200)) -> 49 · BKSHMUJRE|4
A201: 49 · BKSHMUJRE | B201: Trasero cara B | C201: 2 | F201: Sí | G201: =IF(OR(A201="",N(D201)=0),"",IFERROR(D201*(1+IFERROR(IF(ISNUMBER(INDEX(Moldes!$K$5:$K$154,MATCH(A201,Moldes!$A$5:$A$154,0))),INDEX(Moldes!$K$5:$K$154,MATCH(A201,Moldes!$A$5:$A$154,0)),Precios!$Q$12),Precios!$Q$12))*(INDEX(Precios!$F$5:$F$124,MATCH(E201,Precios!$A$5:$A$124,0))+IF(F201="Sí",Precios!$Q$10,0)),"falta $ tela")) | H201: =IF(A201="","",A201&"|"&COUNTIF($A$5:A201,A201)) -> 49 · BKSHMUJRE|5
A202: 49 · BKSHMUJRE | B202: Pretina cara B | C202: 1 | F202: Sí | G202: =IF(OR(A202="",N(D202)=0),"",IFERROR(D202*(1+IFERROR(IF(ISNUMBER(INDEX(Moldes!$K$5:$K$154,MATCH(A202,Moldes!$A$5:$A$154,0))),INDEX(Moldes!$K$5:$K$154,MATCH(A202,Moldes!$A$5:$A$154,0)),Precios!$Q$12),Precios!$Q$12))*(INDEX(Precios!$F$5:$F$124,MATCH(E202,Precios!$A$5:$A$124,0))+IF(F202="Sí",Precios!$Q$10,0)),"falta $ tela")) | H202: =IF(A202="","",A202&"|"&COUNTIF($A$5:A202,A202)) -> 49 · BKSHMUJRE|6
... A228: 54 · BK-SH PRO | B228: Paneles laterales | C228: 2 | F228: Sí | G228: =IF(OR(A228="",N(D228)=0),"",IFERROR(D228*(1+IFERROR(IF(ISNUMBER(INDEX(Moldes!$K$5:$K$154,MATCH(A228,Moldes!$A$5:$A$154,0))),INDEX(Moldes!$K$5:$K$154,MATCH(A228,Moldes!$A$5:$A$154,0)),Precios!$Q$12),Precios!$Q$12))*(INDEX(Precios!$F$5:$F$124,MATCH(E228,Precios!$A$5:$A$124,0))+IF(F228="Sí",Precios!$Q$10,0)),"falta $ tela")) | H228: =IF(A228="","",A228&"|"&COUNTIF($A$5:A228,A228)) -> 54 · BK-SH PRO|4
A229: SM-01 · Short Fútbol | B229: Delantero | C229: 2 | E229: CIRE BLANCO | F229: Sí | G229: =IF(OR(A229="",N(D229)=0),"",IFERROR(D229*(1+IFERROR(IF(ISNUMBER(INDEX(Moldes!$K$5:$K$154,MATCH(A229,Moldes!$A$5:$A$154,0))),INDEX(Moldes!$K$5:$K$154,MATCH(A229,Moldes!$A$5:$A$154,0)),Precios!$Q$12),Precios!$Q$12))*(INDEX(Precios!$F$5:$F$124,MATCH(E229,Precios!$A$5:$A$124,0))+IF(F229="Sí",Precios!$Q$10,0)),"falta $ tela")) | H229: =IF(A229="","",A229&"|"&COUNTIF($A$5:A229,A229)) -> SM-01 · Short Fútbol|1
A230: SM-01 · Short Fútbol | B230: Trasero | C230: 2 | E230: CIRE BLANCO | F230: Sí | G230: =IF(OR(A230="",N(D230)=0),"",IFERROR(D230*(1+IFERROR(IF(ISNUMBER(INDEX(Moldes!$K$5:$K$154,MATCH(A230,Moldes!$A$5:$A$154,0))),INDEX(Moldes!$K$5:$K$154,MATCH(A230,Moldes!$A$5:$A$154,0)),Precios!$Q$12),Precios!$Q$12))*(INDEX(Precios!$F$5:$F$124,MATCH(E230,Precios!$A$5:$A$124,0))+IF(F230="Sí",Precios!$Q$10,0)),"falta $ tela")) | H230: =IF(A230="","",A230&"|"&COUNTIF($A$5:A230,A230)) -> SM-01 · Short Fútbol|2
A231: SM-01 · Short Fútbol | B231: Pretina | C231: 1 | E231: CIRE BLANCO | F231: Sí | G231: =IF(OR(A231="",N(D231)=0),"",IFERROR(D231*(1+IFERROR(IF(ISNUMBER(INDEX(Moldes!$K$5:$K$154,MATCH(A231,Moldes!$A$5:$A$154,0))),INDEX(Moldes!$K$5:$K$154,MATCH(A231,Moldes!$A$5:$A$154,0)),Precios!$Q$12),Precios!$Q$12))*(INDEX(Precios!$F$5:$F$124,MATCH(E231,Precios!$A$5:$A$124,0))+IF(F231="Sí",Precios!$Q$10,0)),"falta $ tela")) | H231: =IF(A231="","",A231&"|"&COUNTIF($A$5:A231,A231)) -> SM-01 · Short Fútbol|3
A232: SM-02 · Short Rugby | B232: Delantero | C232: 2 | E232: GABARDINA | F232: No | G232: =IF(OR(A232="",N(D232)=0),"",IFERROR(D232*(1+IFERROR(IF(ISNUMBER(INDEX(Moldes!$K$5:$K$154,MATCH(A232,Moldes!$A$5:$A$154,0))),INDEX(Moldes!$K$5:$K$154,MATCH(A232,Moldes!$A$5:$A$154,0)),Precios!$Q$12),Precios!$Q$12))*(INDEX(Precios!$F$5:$F$124,MATCH(E232,Precios!$A$5:$A$124,0))+IF(F232="Sí",Precios!$Q$10,0)),"falta $ tela")) | H232: =IF(A232="","",A232&"|"&COUNTIF($A$5:A232,A232)) -> SM-02 · Short Rugby|1
A233: SM-02 · Short Rugby | B233: Trasero | C233: 2 | E233: GABARDINA | F233: No | G233: =IF(OR(A233="",N(D233)=0),"",IFERROR(D233*(1+IFERROR(IF(ISNUMBER(INDEX(Moldes!$K$5:$K$154,MATCH(A233,Moldes!$A$5:$A$154,0))),INDEX(Moldes!$K$5:$K$154,MATCH(A233,Moldes!$A$5:$A$154,0)),Precios!$Q$12),Precios!$Q$12))*(INDEX(Precios!$F$5:$F$124,MATCH(E233,Precios!$A$5:$A$124,0))+IF(F233="Sí",Precios!$Q$10,0)),"falta $ tela")) | H233: =IF(A233="","",A233&"|"&COUNTIF($A$5:A233,A233)) -> SM-02 · Short Rugby|2
A234: SM-02 · Short Rugby | B234: Pretina | C234: 1 | E234: GABARDINA | F234: No | G234: =IF(OR(A234="",N(D234)=0),"",IFERROR(D234*(1+IFERROR(IF(ISNUMBER(INDEX(Moldes!$K$5:$K$154,MATCH(A234,Moldes!$A$5:$A$154,0))),INDEX(Moldes!$K$5:$K$154,MATCH(A234,Moldes!$A$5:$A$154,0)),Precios!$Q$12),Precios!$Q$12))*(INDEX(Precios!$F$5:$F$124,MATCH(E234,Precios!$A$5:$A$124,0))+IF(F234="Sí",Precios!$Q$10,0)),"falta $ tela")) | H234: =IF(A234="","",A234&"|"&COUNTIF($A$5:A234,A234)) -> SM-02 · Short Rugby|3
A235: SM-03 · Camiseta Running s/m | B235: Delantero | C235: 1 | E235: 5K NACIONAL (running pro) | F235: Sí | G235: =IF(OR(A235="",N(D235)=0),"",IFERROR(D235*(1+IFERROR(IF(ISNUMBER(INDEX(Moldes!$K$5:$K$154,MATCH(A235,Moldes!$A$5:$A$154,0))),INDEX(Moldes!$K$5:$K$154,MATCH(A235,Moldes!$A$5:$A$154,0)),Precios!$Q$12),Precios!$Q$12))*(INDEX(Precios!$F$5:$F$124,MATCH(E235,Precios!$A$5:$A$124,0))+IF(F235="Sí",Precios!$Q$10,0)),"falta $ tela")) | H235: =IF(A235="","",A235&"|"&COUNTIF($A$5:A235,A235)) -> SM-03 · Camiseta Running s/m|1
A236: SM-03 · Camiseta Running s/m | B236: Espalda | C236: 1 | E236: 5K NACIONAL (running pro) | F236: Sí | G236: =IF(OR(A236="",N(D236)=0),"",IFERROR(D236*(1+IFERROR(IF(ISNUMBER(INDEX(Moldes!$K$5:$K$154,MATCH(A236,Moldes!$A$5:$A$154,0))),INDEX(Moldes!$K$5:$K$154,MATCH(A236,Moldes!$A$5:$A$154,0)),Precios!$Q$12),Precios!$Q$12))*(INDEX(Precios!$F$5:$F$124,MATCH(E236,Precios!$A$5:$A$124,0))+IF(F236="Sí",Precios!$Q$10,0)),"falta $ tela")) | H236: =IF(A236="","",A236&"|"&COUNTIF($A$5:A236,A236)) -> SM-03 · Camiseta Running s/m|2
A237: SM-03 · Camiseta Running s/m | B237: Ribete cuello y sisas | C237: 1 | E237: 5K NACIONAL (running pro) | F237: Sí | G237: =IF(OR(A237="",N(D237)=0),"",IFERROR(D237*(1+IFERROR(IF(ISNUMBER(INDEX(Moldes!$K$5:$K$154,MATCH(A237,Moldes!$A$5:$A$154,0))),INDEX(Moldes!$K$5:$K$154,MATCH(A237,Moldes!$A$5:$A$154,0)),Precios!$Q$12),Precios!$Q$12))*(INDEX(Precios!$F$5:$F$124,MATCH(E237,Precios!$A$5:$A$124,0))+IF(F237="Sí",Precios!$Q$10,0)),"falta $ tela")) | H237: =IF(A237="","",A237&"|"&COUNTIF($A$5:A237,A237)) -> SM-03 · Camiseta Running s/m|3
A238: SM-04 · Calza Vóley | B238: Pierna | C238: 2 | E238: LYCRA | F238: No | G238: =IF(OR(A238="",N(D238)=0),"",IFERROR(D238*(1+IFERROR(IF(ISNUMBER(INDEX(Moldes!$K$5:$K$154,MATCH(A238,Moldes!$A$5:$A$154,0))),INDEX(Moldes!$K$5:$K$154,MATCH(A238,Moldes!$A$5:$A$154,0)),Precios!$Q$12),Precios!$Q$12))*(INDEX(Precios!$F$5:$F$124,MATCH(E238,Precios!$A$5:$A$124,0))+IF(F238="Sí",Precios!$Q$10,0)),"falta $ tela")) | H238: =IF(A238="","",A238&"|"&COUNTIF($A$5:A238,A238)) -> SM-04 · Calza Vóley|1
A239: SM-04 · Calza Vóley | B239: Pretina | C239: 1 | E239: LYCRA | F239: No | G239: =IF(OR(A239="",N(D239)=0),"",IFERROR(D239*(1+IFERROR(IF(ISNUMBER(INDEX(Moldes!$K$5:$K$154,MATCH(A239,Moldes!$A$5:$A$154,0))),INDEX(Moldes!$K$5:$K$154,MATCH(A239,Moldes!$A$5:$A$154,0)),Precios!$Q$12),Precios!$Q$12))*(INDEX(Precios!$F$5:$F$124,MATCH(E239,Precios!$A$5:$A$124,0))+IF(F239="Sí",Precios!$Q$10,0)),"falta $ tela")) | H239: =IF(A239="","",A239&"|"&COUNTIF($A$5:A239,A239)) -> SM-04 · Calza Vóley|2
G240: =IF(OR(A240="",N(D240)=0),"",IFERROR(D240*(1+IFERROR(IF(ISNUMBER(INDEX(Moldes!$K$5:$K$154,MATCH(A240,Moldes!$A$5:$A$154,0))),INDEX(Moldes!$K$5:$K$154,MATCH(A240,Moldes!$A$5:$A$154,0)),Precios!$Q$12),Precios!$Q$12))*(INDEX(Precios!$F$5:$F$124,MATCH(E240,Precios!$A$5:$A$124,0))+IF(F240="Sí",Precios!$Q$10,0)),"falta $ tela")) | H240: =IF(A240="","",A240&"|"&COUNTIF($A$5:A240,A240))
G241: =IF(OR(A241="",N(D241)=0),"",IFERROR(D241*(1+IFERROR(IF(ISNUMBER(INDEX(Moldes!$K$5:$K$154,MATCH(A241,Moldes!$A$5:$A$154,0))),INDEX(Moldes!$K$5:$K$154,MATCH(A241,Moldes!$A$5:$A$154,0)),Precios!$Q$12),Precios!$Q$12))*(INDEX(Precios!$F$5:$F$124,MATCH(E241,Precios!$A$5:$A$124,0))+IF(F241="Sí",Precios!$Q$10,0)),"falta $ tela")) | H241: =IF(A241="","",A241&"|"&COUNTIF($A$5:A241,A241))
...

Sheet Precios
A1: PRECIOS — todo NETO (sin IVA)
A2: Azul = lo escribes tú. Gris = se calcula solo. Si solo tienes el precio de la factura (con IVA), escríbelo en esa columna y se descuenta solo.
A4: TELA | B4: Tipo | C4: $ por kg NETO | D4: o $ por kg CON IVA | E4: Peso de 1 metro (kg) | F4: $ POR METRO | G4: Rinde (m por kg) | H4: Nota | J4: CONFECCIÓN (tipo) | K4: $ por prenda (taller) | M4: AVÍO | N4: $ por unidad | P4: IMPRESIÓN Y PARÁMETROS | Q4: Valor | R4: Nota
A5: MONTESIMONE TRAINING (fut pro) | B5: Pro | C5: 3531 | E5: 0.197 | F5: =IF(N(E5)=0,"",IF(ISNUMBER(C5),C5,IF(ISNUMBER(D5),D5/1.19,""))*E5) -> 695.607 | G5: =IF(N(E5)>0,1/E5,"") -> 5.0761421 | J5: Short De Futbol | K5: 1700 | M5: Cuello | N5: 350 | P5: Papel sublimación: precio del rollo | Q5: 50420 | R5: POR CONFIRMAR: ¿$50.420 es el rollo?
A6: LONDRES BLANCO | C6: 5600 | F6: =IF(N(E6)=0,"",IF(ISNUMBER(C6),C6,IF(ISNUMBER(D6),D6/1.19,""))*E6) | G6: =IF(N(E6)>0,1/E6,"") | H6: Falta pesar 1 metro | J6: Camiseta De Futbol | K6: 2000 | M6: Puño | N6: 8500 | P6: Papel sublimación: metros del rollo | R6: PENDIENTE
A7: CIRE BLANCO | C7: 5600 | F7: =IF(N(E7)=0,"",IF(ISNUMBER(C7),C7,IF(ISNUMBER(D7),D7/1.19,""))*E7) | G7: =IF(N(E7)>0,1/E7,"") | H7: Falta pesar 1 metro | J7: Camiseta De Futbol Retro | K7: 2200 | M7: Tapacuello | N7: 150 | P7: Tinta: precio por litro | Q7: 72119 | R7: POR CONFIRMAR
A8: CIRE AZUL | C8: 7500 | F8: =IF(N(E8)=0,"",IF(ISNUMBER(C8),C8,IF(ISNUMBER(D8),D8/1.19,""))*E8) | G8: =IF(N(E8)>0,1/E8,"") | H8: Falta pesar 1 metro | J8: Camiseta De Basket | K8: 1900 | M8: Hilo | N8: 80 | P8: Tinta: ml por metro impreso | R8: PENDIENTE: litros del mes ÷ metros impresos × 1000
A9: MESH | C9: 7700 | F9: =IF(N(E9)=0,"",IF(ISNUMBER(C9),C9,IF(ISNUMBER(D9),D9/1.19,""))*E9) | G9: =IF(N(E9)>0,1/E9,"") | H9: Falta pesar 1 metro | J9: Camiseta De Basket Pro | K9: 2000 | M9: Etiqueta | N9: 65 | P9: Papel protección (kraft): $ por metro | R9: Opcional
A10: FRANELA | C10: 8000 | F10: =IF(N(E10)=0,"",IF(ISNUMBER(C10),C10,IF(ISNUMBER(D10),D10/1.19,""))*E10) | G10: =IF(N(E10)>0,1/E10,"") | H10: Falta pesar 1 metro | J10: Short De Basket Pro | K10: 2200 | M10: Cierre | N10: 600 | P10: COSTO DE IMPRESIÓN POR METRO | Q10: =IFERROR(Q5/Q6,0)+N(Q8)*N(Q7)/1000+N(Q9) -> 0 | R10: Papel + tinta + protección
A11: PIQUE SELECCION | C11: 7800 | F11: =IF(N(E11)=0,"",IF(ISNUMBER(C11),C11,IF(ISNUMBER(D11),D11/1.19,""))*E11) | G11: =IF(N(E11)>0,1/E11,"") | H11: Falta pesar 1 metro | J11: Short De Basket | K11: 1900 | M11: Cordón | N11: 200
A12: MICROFIBRA | C12: 6900 | F12: =IF(N(E12)=0,"",IF(ISNUMBER(C12),C12,IF(ISNUMBER(D12),D12/1.19,""))*E12) | G12: =IF(N(E12)>0,1/E12,"") | H12: Falta pesar 1 metro | J12: Short De Basket Reversible | K12: 2400 | M12: Elástico | N12: 5454 | P12: Merma general sobre el despiece | Q12: 0 | R12: Tela que se pierde (cabezales, fallas). Se usa si el molde no tiene ajuste propio.
A13: CIRE MICROFIBRA AZUL REY | C13: 7200 | F13: =IF(N(E13)=0,"",IF(ISNUMBER(C13),C13,IF(ISNUMBER(D13),D13/1.19,""))*E13) | G13: =IF(N(E13)>0,1/E13,"") | H13: Falta pesar 1 metro | J13: Camiseta De Basket Reversible | K13: 2400 | M13: Forro | N13: 900
A14: SCUBA | C14: 7900 | F14: =IF(N(E14)=0,"",IF(ISNUMBER(C14),C14,IF(ISNUMBER(D14),D14/1.19,""))*E14) | G14: =IF(N(E14)>0,1/E14,"") | H14: Falta pesar 1 metro | J14: Camiseta De Rugby Básica | K14: 2200 | M14: Cremallera bolsillo | N14: 400 | P14: Gastos generales (% del precio) | Q14: 0.434 | R14: Del sistema de ventas (jul–sep 2026). Solo para el precio mínimo.
A15: GLOBAL | C15: 6800 | F15: =IF(N(E15)=0,"",IF(ISNUMBER(C15),C15,IF(ISNUMBER(D15),D15/1.19,""))*E15) | G15: =IF(N(E15)>0,1/E15,"") | H15: Falta pesar 1 metro | J15: Camiseta De Rugby Lycra | K15: 2600 | P15: Meta de ganancia (% del precio) | Q15: 0.15 | R15: POR CONFIRMAR
A16: PIQUE RUGBY | C16: 5600 | F16: =IF(N(E16)=0,"",IF(ISNUMBER(C16),C16,IF(ISNUMBER(D16),D16/1.19,""))*E16) | G16: =IF(N(E16)>0,1/E16,"") | H16: Falta pesar 1 metro | J16: Short De Rugby | K16: 2200 | P16: Multiplicador: precio mínimo = costo × | Q16: =IFERROR(1/(1-Q14-Q15),"") -> 2.4038462 | R16: Costo ÷ (1 − gastos generales − meta)
A17: CORDERITO | C17: 5800 | F17: =IF(N(E17)=0,"",IF(ISNUMBER(C17),C17,IF(ISNUMBER(D17),D17/1.19,""))*E17) | G17: =IF(N(E17)>0,1/E17,"") | H17: Falta pesar 1 metro | J17: Camiseta Futbol Molde 2026 (Raglan) | K17: 2300
A18: MICROFIBRA CIRE COLORES | C18: 7800 | F18: =IF(N(E18)=0,"",IF(ISNUMBER(C18),C18,IF(ISNUMBER(D18),D18/1.19,""))*E18) | G18: =IF(N(E18)>0,1/E18,"") | H18: Falta pesar 1 metro | J18: Camiseta Futbol Fem Santiago Morning | K18: 2400
A19: BASQUET BLANCO | C19: 5600 | F19: =IF(N(E19)=0,"",IF(ISNUMBER(C19),C19,IF(ISNUMBER(D19),D19/1.19,""))*E19) | G19: =IF(N(E19)>0,1/E19,"") | H19: Falta pesar 1 metro | J19: Short Fem Con Tajali | K19: 1800
A20: PIQUE TENIS BLANCO | C20: 5600 | F20: =IF(N(E20)=0,"",IF(ISNUMBER(C20),C20,IF(ISNUMBER(D20),D20/1.19,""))*E20) | G20: =IF(N(E20)>0,1/E20,"") | H20: Falta pesar 1 metro | J20: Camiseta De Hockey | K20: 1800
A21: DEPORTIVO COLOR | C21: 6200 | F21: =IF(N(E21)=0,"",IF(ISNUMBER(C21),C21,IF(ISNUMBER(D21),D21/1.19,""))*E21) | G21: =IF(N(E21)>0,1/E21,"") | H21: Falta pesar 1 metro | J21: Camiseta De Hockey Franja | K21: 2000
A22: GABARDINA 8Z | C22: 2630 | F22: =IF(N(E22)=0,"",IF(ISNUMBER(C22),C22,IF(ISNUMBER(D22),D22/1.19,""))*E22) | G22: =IF(N(E22)>0,1/E22,"") | H22: Falta pesar 1 metro | J22: Calza-Falda | K22: 2600
A23: GABARDINA | C23: 2750 | F23: =IF(N(E23)=0,"",IF(ISNUMBER(C23),C23,IF(ISNUMBER(D23),D23/1.19,""))*E23) | G23: =IF(N(E23)>0,1/E23,"") | H23: Falta pesar 1 metro | J23: Calza | K23: 1200
A24: FRANELA POLIESTER | C24: 2790 | F24: =IF(N(E24)=0,"",IF(ISNUMBER(C24),C24,IF(ISNUMBER(D24),D24/1.19,""))*E24) | G24: =IF(N(E24)>0,1/E24,"") | H24: Falta pesar 1 metro | J24: Pantalon Pitillo | K24: 3500
A25: GABARDINA 7Z | C25: 2390 | F25: =IF(N(E25)=0,"",IF(ISNUMBER(C25),C25,IF(ISNUMBER(D25),D25/1.19,""))*E25) | G25: =IF(N(E25)>0,1/E25,"") | H25: Falta pesar 1 metro | J25: Poleron Entrenamiento Raglan | K25: 3200
A26: FALCAO | C26: 2380 | F26: =IF(N(E26)=0,"",IF(ISNUMBER(C26),C26,IF(ISNUMBER(D26),D26/1.19,""))*E26) | G26: =IF(N(E26)>0,1/E26,"") | H26: Falta pesar 1 metro | J26: Short De Salida | K26: 2200
A27: RUGBY IRLANDA | C27: 5900 | F27: =IF(N(E27)=0,"",IF(ISNUMBER(C27),C27,IF(ISNUMBER(D27),D27/1.19,""))*E27) | G27: =IF(N(E27)>0,1/E27,"") | H27: Falta pesar 1 metro | J27: Peto Entrenamiento | K27: 1000
A28: LYCRA GRIS OSCURA | C28: 4300 | F28: =IF(N(E28)=0,"",IF(ISNUMBER(C28),C28,IF(ISNUMBER(D28),D28/1.19,""))*E28) | G28: =IF(N(E28)>0,1/E28,"") | H28: Falta pesar 1 metro | J28: Pantalon No Pitillo | K28: 3200
... A30: COTTON | C30: 2302 | F30: =IF(N(E30)=0,"",IF(ISNUMBER(C30),C30,IF(ISNUMBER(D30),D30/1.19,""))*E30) | G30: =IF(N(E30)>0,1/E30,"") | H30: Falta pesar 1 metro | J30: Camiseta Running Con Manga | K30: 2000
A31: 5K NACIONAL (running pro) | B31: Pro | C31: 4244 | E31: 0.198 | F31: =IF(N(E31)=0,"",IF(ISNUMBER(C31),C31,IF(ISNUMBER(D31),D31/1.19,""))*E31) -> 840.312 | G31: =IF(N(E31)>0,1/E31,"") -> 5.0505051 | J31: Camiseta De Salida Con Hojal Y Boton | K31: 2500
A32: JACQUARD TECH | C32: 4408 | E32: 0.233 | F32: =IF(N(E32)=0,"",IF(ISNUMBER(C32),C32,IF(ISNUMBER(D32),D32/1.19,""))*E32) -> 1027.064 | G32: =IF(N(E32)>0,1/E32,"") -> 4.2918455 | J32: Camiseta De Salida Sin Hojal Ni Boton | K32: 2200
A33: JACQUARD BYTES | C33: 4408 | E33: 0.254 | F33: =IF(N(E33)=0,"",IF(ISNUMBER(C33),C33,IF(ISNUMBER(D33),D33/1.19,""))*E33) -> 1119.632 | G33: =IF(N(E33)>0,1/E33,"") -> 3.9370079 | J33: Camiseta De Salida Con Cuello Y Puño Tejido Con Boton | K33: 2200
A34: LYCRA | F34: =IF(N(E34)=0,"",IF(ISNUMBER(C34),C34,IF(ISNUMBER(D34),D34/1.19,""))*E34) | G34: =IF(N(E34)>0,1/E34,"") | H34: Falta pesar 1 metro | J34: Camiseta De Salida Con Cuello Y Puño Tejido Sin Boton | K34: 1900
A35: MALLA DEPORTIVA BLANCO | C35: 6400 | F35: =IF(N(E35)=0,"",IF(ISNUMBER(C35),C35,IF(ISNUMBER(D35),D35/1.19,""))*E35) | G35: =IF(N(E35)>0,1/E35,"") | H35: Falta pesar 1 metro | J35: Camiseta Kimono | K35: 2400
A36: NOVAK | C36: 2975 | F36: =IF(N(E36)=0,"",IF(ISNUMBER(C36),C36,IF(ISNUMBER(D36),D36/1.19,""))*E36) | G36: =IF(N(E36)>0,1/E36,"") | H36: Falta pesar 1 metro | J36: Camiseta Voley | K36: 1700
A37: THERMAFLEECE | C37: 8590 | F37: =IF(N(E37)=0,"",IF(ISNUMBER(C37),C37,IF(ISNUMBER(D37),D37/1.19,""))*E37) | G37: =IF(N(E37)>0,1/E37,"") | H37: Falta pesar 1 metro | J37: Calza Larga | K37: 1800
F38: =IF(N(E38)=0,"",IF(ISNUMBER(C38),C38,IF(ISNUMBER(D38),D38/1.19,""))*E38) | G38: =IF(N(E38)>0,1/E38,"") | J38: Lienzo | K38: 650
F39: =IF(N(E39)=0,"",IF(ISNUMBER(C39),C39,IF(ISNUMBER(D39),D39/1.19,""))*E39) | G39: =IF(N(E39)>0,1/E39,"") | J39: Camiseta Retro | K39: 2400
F40: =IF(N(E40)=0,"",IF(ISNUMBER(C40),C40,IF(ISNUMBER(D40),D40/1.19,""))*E40) | G40: =IF(N(E40)>0,1/E40,"") | J40: Multideporte | K40: 1700
F41: =IF(N(E41)=0,"",IF(ISNUMBER(C41),C41,IF(ISNUMBER(D41),D41/1.19,""))*E41) | G41: =IF(N(E41)>0,1/E41,"") | J41: Poleron Polo | K41: 2000
F42: =IF(N(E42)=0,"",IF(ISNUMBER(C42),C42,IF(ISNUMBER(D42),D42/1.19,""))*E42) | G42: =IF(N(E42)>0,1/E42,"") | J42: Parka Larga 2025 | K42: 8000
F43: =IF(N(E43)=0,"",IF(ISNUMBER(C43),C43,IF(ISNUMBER(D43),D43/1.19,""))*E43) | G43: =IF(N(E43)>0,1/E43,"") | J43: Camiseta Rugby Con Cuello | K43: 2500
F44: =IF(N(E44)=0,"",IF(ISNUMBER(C44),C44,IF(ISNUMBER(D44),D44/1.19,""))*E44) | G44: =IF(N(E44)>0,1/E44,"") | J44: Poleron Oversize 3C | K44: 5500
F45: =IF(N(E45)=0,"",IF(ISNUMBER(C45),C45,IF(ISNUMBER(D45),D45/1.19,""))*E45) | G45: =IF(N(E45)>0,1/E45,"") | J45: Cortaviento Con Capucha | K45: 6000
F46: =IF(N(E46)=0,"",IF(ISNUMBER(C46),C46,IF(ISNUMBER(D46),D46/1.19,""))*E46) | G46: =IF(N(E46)>0,1/E46,"") | J46: Cortaviento Sin Capucha | K46: 5500
F47: =IF(N(E47)=0,"",IF(ISNUMBER(C47),C47,IF(ISNUMBER(D47),D47/1.19,""))*E47) | G47: =IF(N(E47)>0,1/E47,"") | J47: Poleron Hoodie | K47: 3000
F48: =IF(N(E48)=0,"",IF(ISNUMBER(C48),C48,IF(ISNUMBER(D48),D48/1.19,""))*E48) | G48: =IF(N(E48)>0,1/E48,"") | J48: Poleron Hoodie Corte Mangas | K48: 3300
F49: =IF(N(E49)=0,"",IF(ISNUMBER(C49),C49,IF(ISNUMBER(D49),D49/1.19,""))*E49) | G49: =IF(N(E49)>0,1/E49,"") | J49: Bolso | K49: 1000
F50: =IF(N(E50)=0,"",IF(ISNUMBER(C50),C50,IF(ISNUMBER(D50),D50/1.19,""))*E50) | G50: =IF(N(E50)>0,1/E50,"") | J50: Colett | K50: 500
F51: =IF(N(E51)=0,"",IF(ISNUMBER(C51),C51,IF(ISNUMBER(D51),D51/1.19,""))*E51) | G51: =IF(N(E51)>0,1/E51,"")
F52: =IF(N(E52)=0,"",IF(ISNUMBER(C52),C52,IF(ISNUMBER(D52),D52/1.19,""))*E52) | G52: =IF(N(E52)>0,1/E52,"")
F53: =IF(N(E53)=0,"",IF(ISNUMBER(C53),C53,IF(ISNUMBER(D53),D53/1.19,""))*E53) | G53: =IF(N(E53)>0,1/E53,"")
F54: =IF(N(E54)=0,"",IF(ISNUMBER(C54),C54,IF(ISNUMBER(D54),D54/1.19,""))*E54) | G54: =IF(N(E54)>0,1/E54,"")
F55: =IF(N(E55)=0,"",IF(ISNUMBER(C55),C55,IF(ISNUMBER(D55),D55/1.19,""))*E55) | G55: =IF(N(E55)>0,1/E55,"")
F56: =IF(N(E56)=0,"",IF(ISNUMBER(C56),C56,IF(ISNUMBER(D56),D56/1.19,""))*E56) | G56: =IF(N(E56)>0,1/E56,"")
F57: =IF(N(E57)=0,"",IF(ISNUMBER(C57),C57,IF(ISNUMBER(D57),D57/1.19,""))*E57) | G57: =IF(N(E57)>0,1/E57,"")
F58: =IF(N(E58)=0,"",IF(ISNUMBER(C58),C58,IF(ISNUMBER(D58),D58/1.19,""))*E58) | G58: =IF(N(E58)>0,1/E58,"")
F59: =IF(N(E59)=0,"",IF(ISNUMBER(C59),C59,IF(ISNUMBER(D59),D59/1.19,""))*E59) | G59: =IF(N(E59)>0,1/E59,"")
F60: =IF(N(E60)=0,"",IF(ISNUMBER(C60),C60,IF(ISNUMBER(D60),D60/1.19,""))*E60) | G60: =IF(N(E60)>0,1/E60,"")
F61: =IF(N(E61)=0,"",IF(ISNUMBER(C61),C61,IF(ISNUMBER(D61),D61/1.19,""))*E61) | G61: =IF(N(E61)>0,1/E61,"")
F62: =IF(N(E62)=0,"",IF(ISNUMBER(C62),C62,IF(ISNUMBER(D62),D62/1.19,""))*E62) | G62: =IF(N(E62)>0,1/E62,"")
... F124: =IF(N(E124)=0,"",IF(ISNUMBER(C124),C124,IF(ISNUMBER(D124),D124/1.19,""))*E124) | G124: =IF(N(E124)>0,1/E124,"")
