Workbook

Sheet Como_usar
A1: RECETAS DE COSTO — PLAYMAKER (v3, por molde del catálogo)
A2: Armado desde el Sistema de Costeo v2 y el catálogo de moldes vigente. Todo dato dice "Por confirmar" hasta que lo valides.
A4: CÓMO ESTÁ ORDENADO
B5: RECETAS: una por cada MOLDE del catálogo (los 54 de Fútbol y Básquetbol, los mismos de Fichas y Planificación). Es el costo de producir UNA prenda con ese molde.
B6: PRODUCTOS: lo que vendes. Cada producto elige la receta de su molde (columna E) y suma extras (cuello piqué, manga larga). Ahí ves ganancia, precio mínimo y semáforo.
B7: Así, si cambia una tela o un consumo, se actualizan solos todos los productos que usan ese molde.
A8: COLORES
B9: AZUL = lo escribes tú. GRIS = se calcula solo. Semáforo: PIERDE (rojo) · BAJO META (amarillo) · OK (verde) · gris = faltan datos.
A10: PASOS PARA COMPLETAR
B11: 1) En Recetas, completa el molde: tela (lista), kg por prenda (kg de la ficha de corte ÷ prendas cortadas), tela 2 si lleva malla, metros impresos y confección.
B12: 2) En Productos, revisa que cada producto tenga elegida la receta de su molde. Los marcados "sugerido" hay que confirmarlos.
B13: 3) Las prendas que aún no tienen molde (short de fútbol, short de rugby, running, calza) están al final de Recetas como "SM-…". Agrega más en las filas libres.
A14: CADA TRIMESTRE (próximo: diciembre 2026)
B15: En Gastos_Ventas escribe los gastos y ventas de los 3 meses más recientes. El recargo y todos los productos se actualizan solos.
A16: PENDIENTES QUE AFECTAN LOS RESULTADOS
B17: ="• Papel y tinta: "&IF(Parametros!$B$27=0,"SIN DATO → las prendas sublimadas salen más baratas de lo real.","ingresado ("&TEXT(Parametros!$B$27,"$#,##0")&" por metro).") -> • Papel y tinta: SIN DATO → las prendas sublimadas salen más baratas de lo real.
B18: ="• Recetas (moldes) completas: "&COUNTIF(Recetas!T5:T84,"Lista*")&" de "&COUNTA(Recetas!A5:A84) -> • Recetas (moldes) completas: 4 de 59
B19: ="• Productos con costo completo: "&COUNTIF(Catalogo!F6:F200,"Completa")&" · con datos faltantes: "&COUNTIF(Catalogo!F6:F200,"Faltan datos") -> • Productos con costo completo: 7 · con datos faltantes: 67
B20: • Faltan fichas de corte de casi todos los moldes: cada ficha nueva completa la receta de su molde para todos los productos que lo usan.
B21: • El short de fútbol no tiene molde en el catálogo: cuando se agregue, cambia su receta "SM-01" por el molde nuevo.
B22: • Gastos: el archivo original trae un solo mes; se repitió en los 3 meses. Reemplazar con el gasto real.

Sheet Productos
A1: PRODUCTOS — ganancia y precio mínimo de lo que vendes
A2: Cada producto usa la receta de su molde (hoja Recetas). Elige la receta en la columna E y suma los extras (cuello piqué, manga larga…). Fuente de productos y precios: 2_Catálogo (jun–sep 2026).
A3: ="Recargo usado: "&TEXT(Parametros!$B$14,"0.0%")&" del precio (fábrica "&TEXT(Parametros!$B$12,"0.0%")&" + comercial "&TEXT(Parametros!$B$13,"0.0%")&") · Meta de ganancia: "&TEXT(Parametros!$B$18,"0%")&" · Impresión: "&IF(Parametros!$B$27=0,"SIN COSTO (pendiente)",TEXT(Parametros!$B$27,"$#,##0")&" por metro") -> Recargo usado: 48.0% del precio (fábrica 35.3% + comercial 12.7%) · Meta de ganancia: 10% · Impresión: SIN COSTO (pendiente)
A4: PRODUCTO | E4: LO LLENAS TÚ | J4: RESULTADO AL PRECIO ACTUAL
A5: Código | B5: Producto | C5: Tipo | D5: Unid. vendidas jun–sep | E5: Receta (molde) | F5: Extras ($ por prenda) | G5: Precio venta neto ($) | H5: Estado | I5: Notas | J5: COSTO DE PRODUCCIÓN | K5: Gastos de fábrica | L5: Gastos comerciales | M5: GANANCIA ($) | N5: GANANCIA (%) | O5: Precio mínimo (sin perder) | P5: Precio mínimo (con meta) | Q5: Semáforo | R5: Qué falta
A6: FUTCSUBMC | B6: Camiseta Fútbol Playmaker, m/c | C6: Juego | D6: 198 | E6: 02 · FUTHOMU01 | G6: 15994 | H6: Por confirmar | I6: Molde sugerido: fútbol masculino cuello redondo. Confirmar. | J6: =IF(OR(B6="",E6=""),"",IF(IFERROR(INDEX(Recetas!$S$5:$S$84,MATCH(E6,Recetas!$A$5:$A$84,0)),"")="","",IFERROR(INDEX(Recetas!$S$5:$S$84,MATCH(E6,Recetas!$A$5:$A$84,0)),"")+N(F6))) | K6: =IF(AND(J6<>"",ISNUMBER(G6)),G6*Parametros!$B$12,"") | L6: =IF(AND(J6<>"",ISNUMBER(G6)),G6*Parametros!$B$13,"") | M6: =IF(AND(J6<>"",ISNUMBER(G6)),G6-J6-K6-L6,"") | N6: =IF(AND(J6<>"",ISNUMBER(G6)),M6/G6,"") | O6: =IF(OR(J6="",Parametros!$B$14>=1),"",J6/(1-Parametros!$B$14)) | P6: =IF(OR(J6="",Parametros!$B$14+Parametros!$B$18>=1),"",J6/(1-Parametros!$B$14-Parametros!$B$18)) | Q6: =IF(B6="","",IF(E6="","SIN RECETA",IF(J6="","FALTAN DATOS",IF(NOT(ISNUMBER(G6)),"FALTA PRECIO",IF(M6<0,"PIERDE",IF(N6<Parametros!$B$18,"BAJO META","OK")))))) -> FALTAN DATOS | R6: =IF(B6="","",IF(E6="","Elegir receta (molde).",IF(ISNA(MATCH(E6,Recetas!$A$5:$A$84,0)),"La receta no existe en Recetas.",IF(J6="","Completar la receta "&E6&": "&INDEX(Recetas!$T$5:$T$84,MATCH(E6,Recetas!$A$5:$A$84,0)),IF(NOT(ISNUMBER(G6)),"Precio de venta.",""))))) -> Completar la receta 02 · FUTHOMU01: Tela. Kg de tela. Metros impresos.
A7: FUTCSUBREDMC | B7: Camiseta Fútbol Playmaker Cuello Redondo m/c | C7: Juego | D7: 190 | E7: 02 · FUTHOMU01 | G7: 16073 | H7: Por confirmar | I7: Molde sugerido. Confirmar. | J7: =IF(OR(B7="",E7=""),"",IF(IFERROR(INDEX(Recetas!$S$5:$S$84,MATCH(E7,Recetas!$A$5:$A$84,0)),"")="","",IFERROR(INDEX(Recetas!$S$5:$S$84,MATCH(E7,Recetas!$A$5:$A$84,0)),"")+N(F7))) | K7: =IF(AND(J7<>"",ISNUMBER(G7)),G7*Parametros!$B$12,"") | L7: =IF(AND(J7<>"",ISNUMBER(G7)),G7*Parametros!$B$13,"") | M7: =IF(AND(J7<>"",ISNUMBER(G7)),G7-J7-K7-L7,"") | N7: =IF(AND(J7<>"",ISNUMBER(G7)),M7/G7,"") | O7: =IF(OR(J7="",Parametros!$B$14>=1),"",J7/(1-Parametros!$B$14)) | P7: =IF(OR(J7="",Parametros!$B$14+Parametros!$B$18>=1),"",J7/(1-Parametros!$B$14-Parametros!$B$18)) | Q7: =IF(B7="","",IF(E7="","SIN RECETA",IF(J7="","FALTAN DATOS",IF(NOT(ISNUMBER(G7)),"FALTA PRECIO",IF(M7<0,"PIERDE",IF(N7<Parametros!$B$18,"BAJO META","OK")))))) -> FALTAN DATOS | R7: =IF(B7="","",IF(E7="","Elegir receta (molde).",IF(ISNA(MATCH(E7,Recetas!$A$5:$A$84,0)),"La receta no existe en Recetas.",IF(J7="","Completar la receta "&E7&": "&INDEX(Recetas!$T$5:$T$84,MATCH(E7,Recetas!$A$5:$A$84,0)),IF(NOT(ISNUMBER(G7)),"Precio de venta.",""))))) -> Completar la receta 02 · FUTHOMU01: Tela. Kg de tela. Metros impresos.
A8: FUTCSUBPROREDMC | B8: Camiseta Fútbol Pro Playmaker Cuello Redondo m/c | C8: Juego | D8: 160 | E8: 14 · FUTHOMU01PRO | G8: 18403 | H8: Por confirmar | I8: Molde Pro cuello redondo. | J8: =IF(OR(B8="",E8=""),"",IF(IFERROR(INDEX(Recetas!$S$5:$S$84,MATCH(E8,Recetas!$A$5:$A$84,0)),"")="","",IFERROR(INDEX(Recetas!$S$5:$S$84,MATCH(E8,Recetas!$A$5:$A$84,0)),"")+N(F8))) -> 3020.47 | K8: =IF(AND(J8<>"",ISNUMBER(G8)),G8*Parametros!$B$12,"") -> 6495.2752 | L8: =IF(AND(J8<>"",ISNUMBER(G8)),G8*Parametros!$B$13,"") -> 2331.5946 | M8: =IF(AND(J8<>"",ISNUMBER(G8)),G8-J8-K8-L8,"") -> 6555.6601 | N8: =IF(AND(J8<>"",ISNUMBER(G8)),M8/G8,"") -> 0.3562278 | O8: =IF(OR(J8="",Parametros!$B$14>=1),"",J8/(1-Parametros!$B$14)) -> 5804.6109 | P8: =IF(OR(J8="",Parametros!$B$14+Parametros!$B$18>=1),"",J8/(1-Parametros!$B$14-Parametros!$B$18)) -> 7185.4873 | Q8: =IF(B8="","",IF(E8="","SIN RECETA",IF(J8="","FALTAN DATOS",IF(NOT(ISNUMBER(G8)),"FALTA PRECIO",IF(M8<0,"PIERDE",IF(N8<Parametros!$B$18,"BAJO META","OK")))))) -> OK | R8: =IF(B8="","",IF(E8="","Elegir receta (molde).",IF(ISNA(MATCH(E8,Recetas!$A$5:$A$84,0)),"La receta no existe en Recetas.",IF(J8="","Completar la receta "&E8&": "&INDEX(Recetas!$T$5:$T$84,MATCH(E8,Recetas!$A$5:$A$84,0)),IF(NOT(ISNUMBER(G8)),"Precio de venta.","")))))
A9: VOLMASC-CSUB-V-MC | B9: Camiseta Voley fem Playmaker, V m/c | C9: Juego | D9: 139 | G9: 17563 | H9: Por confirmar | I9: Sin receta: elige el molde que usa, o crea la receta en "Recetas" si aún no tiene molde. | J9: =IF(OR(B9="",E9=""),"",IF(IFERROR(INDEX(Recetas!$S$5:$S$84,MATCH(E9,Recetas!$A$5:$A$84,0)),"")="","",IFERROR(INDEX(Recetas!$S$5:$S$84,MATCH(E9,Recetas!$A$5:$A$84,0)),"")+N(F9))) | K9: =IF(AND(J9<>"",ISNUMBER(G9)),G9*Parametros!$B$12,"") | L9: =IF(AND(J9<>"",ISNUMBER(G9)),G9*Parametros!$B$13,"") | M9: =IF(AND(J9<>"",ISNUMBER(G9)),G9-J9-K9-L9,"") | N9: =IF(AND(J9<>"",ISNUMBER(G9)),M9/G9,"") | O9: =IF(OR(J9="",Parametros!$B$14>=1),"",J9/(1-Parametros!$B$14)) | P9: =IF(OR(J9="",Parametros!$B$14+Parametros!$B$18>=1),"",J9/(1-Parametros!$B$14-Parametros!$B$18)) | Q9: =IF(B9="","",IF(E9="","SIN RECETA",IF(J9="","FALTAN DATOS",IF(NOT(ISNUMBER(G9)),"FALTA PRECIO",IF(M9<0,"PIERDE",IF(N9<Parametros!$B$18,"BAJO META","OK")))))) -> SIN RECETA | R9: =IF(B9="","",IF(E9="","Elegir receta (molde).",IF(ISNA(MATCH(E9,Recetas!$A$5:$A$84,0)),"La receta no existe en Recetas.",IF(J9="","Completar la receta "&E9&": "&INDEX(Recetas!$T$5:$T$84,MATCH(E9,Recetas!$A$5:$A$84,0)),IF(NOT(ISNUMBER(G9)),"Precio de venta.",""))))) -> Elegir receta (molde).
A10: FUTCSUBPROMC | B10: Camiseta Fútbol Pro Playmaker, m/c | C10: Juego | D10: 109 | E10: 14 · FUTHOMU01PRO | G10: 18403 | H10: Por confirmar | I10: Molde Pro sugerido. Confirmar. | J10: =IF(OR(B10="",E10=""),"",IF(IFERROR(INDEX(Recetas!$S$5:$S$84,MATCH(E10,Recetas!$A$5:$A$84,0)),"")="","",IFERROR(INDEX(Recetas!$S$5:$S$84,MATCH(E10,Recetas!$A$5:$A$84,0)),"")+N(F10))) -> 3020.47 | K10: =IF(AND(J10<>"",ISNUMBER(G10)),G10*Parametros!$B$12,"") -> 6495.2752 | L10: =IF(AND(J10<>"",ISNUMBER(G10)),G10*Parametros!$B$13,"") -> 2331.5946 | M10: =IF(AND(J10<>"",ISNUMBER(G10)),G10-J10-K10-L10,"") -> 6555.6601 | N10: =IF(AND(J10<>"",ISNUMBER(G10)),M10/G10,"") -> 0.3562278 | O10: =IF(OR(J10="",Parametros!$B$14>=1),"",J10/(1-Parametros!$B$14)) -> 5804.6109 | P10: =IF(OR(J10="",Parametros!$B$14+Parametros!$B$18>=1),"",J10/(1-Parametros!$B$14-Parametros!$B$18)) -> 7185.4873 | Q10: =IF(B10="","",IF(E10="","SIN RECETA",IF(J10="","FALTAN DATOS",IF(NOT(ISNUMBER(G10)),"FALTA PRECIO",IF(M10<0,"PIERDE",IF(N10<Parametros!$B$18,"BAJO META","OK")))))) -> OK | R10: =IF(B10="","",IF(E10="","Elegir receta (molde).",IF(ISNA(MATCH(E10,Recetas!$A$5:$A$84,0)),"La receta no existe en Recetas.",IF(J10="","Completar la receta "&E10&": "&INDEX(Recetas!$T$5:$T$84,MATCH(E10,Recetas!$A$5:$A$84,0)),IF(NOT(ISNUMBER(G10)),"Precio de venta.","")))))
A11: FUTCSUBMC-V | B11: Camiseta Fútbol Playmaker, V m/c | C11: Juego | D11: 109 | E11: 06 · FUTHOMV01 | G11: 16589 | H11: Por confirmar | I11: Molde sugerido: cuello V. Confirmar. | J11: =IF(OR(B11="",E11=""),"",IF(IFERROR(INDEX(Recetas!$S$5:$S$84,MATCH(E11,Recetas!$A$5:$A$84,0)),"")="","",IFERROR(INDEX(Recetas!$S$5:$S$84,MATCH(E11,Recetas!$A$5:$A$84,0)),"")+N(F11))) | K11: =IF(AND(J11<>"",ISNUMBER(G11)),G11*Parametros!$B$12,"") | L11: =IF(AND(J11<>"",ISNUMBER(G11)),G11*Parametros!$B$13,"") | M11: =IF(AND(J11<>"",ISNUMBER(G11)),G11-J11-K11-L11,"") | N11: =IF(AND(J11<>"",ISNUMBER(G11)),M11/G11,"") | O11: =IF(OR(J11="",Parametros!$B$14>=1),"",J11/(1-Parametros!$B$14)) | P11: =IF(OR(J11="",Parametros!$B$14+Parametros!$B$18>=1),"",J11/(1-Parametros!$B$14-Parametros!$B$18)) | Q11: =IF(B11="","",IF(E11="","SIN RECETA",IF(J11="","FALTAN DATOS",IF(NOT(ISNUMBER(G11)),"FALTA PRECIO",IF(M11<0,"PIERDE",IF(N11<Parametros!$B$18,"BAJO META","OK")))))) -> FALTAN DATOS | R11: =IF(B11="","",IF(E11="","Elegir receta (molde).",IF(ISNA(MATCH(E11,Recetas!$A$5:$A$84,0)),"La receta no existe en Recetas.",IF(J11="","Completar la receta "&E11&": "&INDEX(Recetas!$T$5:$T$84,MATCH(E11,Recetas!$A$5:$A$84,0)),IF(NOT(ISNUMBER(G11)),"Precio de venta.",""))))) -> Completar la receta 06 · FUTHOMV01: Tela. Kg de tela. Metros impresos.
A12: SALPOLPRESLISA | B12: Polera de Presentación Lisa | C12: Salida | D12: 109 | G12: 17004 | H12: Por confirmar | I12: Sin receta: elige el molde que usa, o crea la receta en "Recetas" si aún no tiene molde. | J12: =IF(OR(B12="",E12=""),"",IF(IFERROR(INDEX(Recetas!$S$5:$S$84,MATCH(E12,Recetas!$A$5:$A$84,0)),"")="","",IFERROR(INDEX(Recetas!$S$5:$S$84,MATCH(E12,Recetas!$A$5:$A$84,0)),"")+N(F12))) | K12: =IF(AND(J12<>"",ISNUMBER(G12)),G12*Parametros!$B$12,"") | L12: =IF(AND(J12<>"",ISNUMBER(G12)),G12*Parametros!$B$13,"") | M12: =IF(AND(J12<>"",ISNUMBER(G12)),G12-J12-K12-L12,"") | N12: =IF(AND(J12<>"",ISNUMBER(G12)),M12/G12,"") | O12: =IF(OR(J12="",Parametros!$B$14>=1),"",J12/(1-Parametros!$B$14)) | P12: =IF(OR(J12="",Parametros!$B$14+Parametros!$B$18>=1),"",J12/(1-Parametros!$B$14-Parametros!$B$18)) | Q12: =IF(B12="","",IF(E12="","SIN RECETA",IF(J12="","FALTAN DATOS",IF(NOT(ISNUMBER(G12)),"FALTA PRECIO",IF(M12<0,"PIERDE",IF(N12<Parametros!$B$18,"BAJO META","OK")))))) -> SIN RECETA | R12: =IF(B12="","",IF(E12="","Elegir receta (molde).",IF(ISNA(MATCH(E12,Recetas!$A$5:$A$84,0)),"La receta no existe en Recetas.",IF(J12="","Completar la receta "&E12&": "&INDEX(Recetas!$T$5:$T$84,MATCH(E12,Recetas!$A$5:$A$84,0)),IF(NOT(ISNUMBER(G12)),"Precio de venta.",""))))) -> Elegir receta (molde).
A13: CSUBRUGSFROSA | B13: CAMISETA DE RUGBY STADE FRANCAIS ANIVERSARIO (ROSADA) | C13: Juego | D13: 100 | G13: 25714 | H13: Por confirmar | I13: Sin receta: elige el molde que usa, o crea la receta en "Recetas" si aún no tiene molde. | J13: =IF(OR(B13="",E13=""),"",IF(IFERROR(INDEX(Recetas!$S$5:$S$84,MATCH(E13,Recetas!$A$5:$A$84,0)),"")="","",IFERROR(INDEX(Recetas!$S$5:$S$84,MATCH(E13,Recetas!$A$5:$A$84,0)),"")+N(F13))) | K13: =IF(AND(J13<>"",ISNUMBER(G13)),G13*Parametros!$B$12,"") | L13: =IF(AND(J13<>"",ISNUMBER(G13)),G13*Parametros!$B$13,"") | M13: =IF(AND(J13<>"",ISNUMBER(G13)),G13-J13-K13-L13,"") | N13: =IF(AND(J13<>"",ISNUMBER(G13)),M13/G13,"") | O13: =IF(OR(J13="",Parametros!$B$14>=1),"",J13/(1-Parametros!$B$14)) | P13: =IF(OR(J13="",Parametros!$B$14+Parametros!$B$18>=1),"",J13/(1-Parametros!$B$14-Parametros!$B$18)) | Q13: =IF(B13="","",IF(E13="","SIN RECETA",IF(J13="","FALTAN DATOS",IF(NOT(ISNUMBER(G13)),"FALTA PRECIO",IF(M13<0,"PIERDE",IF(N13<Parametros!$B$18,"BAJO META","OK")))))) -> SIN RECETA | R13: =IF(B13="","",IF(E13="","Elegir receta (molde).",IF(ISNA(MATCH(E13,Recetas!$A$5:$A$84,0)),"La receta no existe en Recetas.",IF(J13="","Completar la receta "&E13&": "&INDEX(Recetas!$T$5:$T$84,MATCH(E13,Recetas!$A$5:$A$84,0)),IF(NOT(ISNUMBER(G13)),"Precio de venta.",""))))) -> Elegir receta (molde).
A14: SAL-PLA-SUB-MC | B14: Polera de presentación Sublim m/c | C14: Salida | D14: 99 | G14: 18729 | H14: Por confirmar | I14: Sin receta: elige el molde que usa, o crea la receta en "Recetas" si aún no tiene molde. | J14: =IF(OR(B14="",E14=""),"",IF(IFERROR(INDEX(Recetas!$S$5:$S$84,MATCH(E14,Recetas!$A$5:$A$84,0)),"")="","",IFERROR(INDEX(Recetas!$S$5:$S$84,MATCH(E14,Recetas!$A$5:$A$84,0)),"")+N(F14))) | K14: =IF(AND(J14<>"",ISNUMBER(G14)),G14*Parametros!$B$12,"") | L14: =IF(AND(J14<>"",ISNUMBER(G14)),G14*Parametros!$B$13,"") | M14: =IF(AND(J14<>"",ISNUMBER(G14)),G14-J14-K14-L14,"") | N14: =IF(AND(J14<>"",ISNUMBER(G14)),M14/G14,"") | O14: =IF(OR(J14="",Parametros!$B$14>=1),"",J14/(1-Parametros!$B$14)) | P14: =IF(OR(J14="",Parametros!$B$14+Parametros!$B$18>=1),"",J14/(1-Parametros!$B$14-Parametros!$B$18)) | Q14: =IF(B14="","",IF(E14="","SIN RECETA",IF(J14="","FALTAN DATOS",IF(NOT(ISNUMBER(G14)),"FALTA PRECIO",IF(M14<0,"PIERDE",IF(N14<Parametros!$B$18,"BAJO META","OK")))))) -> SIN RECETA | R14: =IF(B14="","",IF(E14="","Elegir receta (molde).",IF(ISNA(MATCH(E14,Recetas!$A$5:$A$84,0)),"La receta no existe en Recetas.",IF(J14="","Completar la receta "&E14&": "&INDEX(Recetas!$T$5:$T$84,MATCH(E14,Recetas!$A$5:$A$84,0)),IF(NOT(ISNUMBER(G14)),"Precio de venta.",""))))) -> Elegir receta (molde).
A15: POL-CSUB-POL-MC | B15: Polera Playmaker, Cuello Redondo m/c | C15: Juego | D15: 96 | G15: 15588 | H15: Por confirmar | I15: Sin receta: elige el molde que usa, o crea la receta en "Recetas" si aún no tiene molde. | J15: =IF(OR(B15="",E15=""),"",IF(IFERROR(INDEX(Recetas!$S$5:$S$84,MATCH(E15,Recetas!$A$5:$A$84,0)),"")="","",IFERROR(INDEX(Recetas!$S$5:$S$84,MATCH(E15,Recetas!$A$5:$A$84,0)),"")+N(F15))) | K15: =IF(AND(J15<>"",ISNUMBER(G15)),G15*Parametros!$B$12,"") | L15: =IF(AND(J15<>"",ISNUMBER(G15)),G15*Parametros!$B$13,"") | M15: =IF(AND(J15<>"",ISNUMBER(G15)),G15-J15-K15-L15,"") | N15: =IF(AND(J15<>"",ISNUMBER(G15)),M15/G15,"") | O15: =IF(OR(J15="",Parametros!$B$14>=1),"",J15/(1-Parametros!$B$14)) | P15: =IF(OR(J15="",Parametros!$B$14+Parametros!$B$18>=1),"",J15/(1-Parametros!$B$14-Parametros!$B$18)) | Q15: =IF(B15="","",IF(E15="","SIN RECETA",IF(J15="","FALTAN DATOS",IF(NOT(ISNUMBER(G15)),"FALTA PRECIO",IF(M15<0,"PIERDE",IF(N15<Parametros!$B$18,"BAJO META","OK")))))) -> SIN RECETA | R15: =IF(B15="","",IF(E15="","Elegir receta (molde).",IF(ISNA(MATCH(E15,Recetas!$A$5:$A$84,0)),"La receta no existe en Recetas.",IF(J15="","Completar la receta "&E15&": "&INDEX(Recetas!$T$5:$T$84,MATCH(E15,Recetas!$A$5:$A$84,0)),IF(NOT(ISNUMBER(G15)),"Precio de venta.",""))))) -> Elegir receta (molde).
A16: RUGCSUBPRO | B16: Camiseta Rugby Pro Pmk | C16: Juego | D16: 93 | G16: 21765 | H16: Por confirmar | I16: Sin receta: elige el molde que usa, o crea la receta en "Recetas" si aún no tiene molde. | J16: =IF(OR(B16="",E16=""),"",IF(IFERROR(INDEX(Recetas!$S$5:$S$84,MATCH(E16,Recetas!$A$5:$A$84,0)),"")="","",IFERROR(INDEX(Recetas!$S$5:$S$84,MATCH(E16,Recetas!$A$5:$A$84,0)),"")+N(F16))) | K16: =IF(AND(J16<>"",ISNUMBER(G16)),G16*Parametros!$B$12,"") | L16: =IF(AND(J16<>"",ISNUMBER(G16)),G16*Parametros!$B$13,"") | M16: =IF(AND(J16<>"",ISNUMBER(G16)),G16-J16-K16-L16,"") | N16: =IF(AND(J16<>"",ISNUMBER(G16)),M16/G16,"") | O16: =IF(OR(J16="",Parametros!$B$14>=1),"",J16/(1-Parametros!$B$14)) | P16: =IF(OR(J16="",Parametros!$B$14+Parametros!$B$18>=1),"",J16/(1-Parametros!$B$14-Parametros!$B$18)) | Q16: =IF(B16="","",IF(E16="","SIN RECETA",IF(J16="","FALTAN DATOS",IF(NOT(ISNUMBER(G16)),"FALTA PRECIO",IF(M16<0,"PIERDE",IF(N16<Parametros!$B$18,"BAJO META","OK")))))) -> SIN RECETA | R16: =IF(B16="","",IF(E16="","Elegir receta (molde).",IF(ISNA(MATCH(E16,Recetas!$A$5:$A$84,0)),"La receta no existe en Recetas.",IF(J16="","Completar la receta "&E16&": "&INDEX(Recetas!$T$5:$T$84,MATCH(E16,Recetas!$A$5:$A$84,0)),IF(NOT(ISNUMBER(G16)),"Precio de venta.",""))))) -> Elegir receta (molde).
A17: MDBZCOMENTPITSUB | B17: Conjunto Polerón de Entrenamiento + Buzo Pitillo Subl | C17: Salida | D17: 76 | G17: 44010 | H17: Por confirmar | I17: Sin receta: elige el molde que usa, o crea la receta en "Recetas" si aún no tiene molde. | J17: =IF(OR(B17="",E17=""),"",IF(IFERROR(INDEX(Recetas!$S$5:$S$84,MATCH(E17,Recetas!$A$5:$A$84,0)),"")="","",IFERROR(INDEX(Recetas!$S$5:$S$84,MATCH(E17,Recetas!$A$5:$A$84,0)),"")+N(F17))) | K17: =IF(AND(J17<>"",ISNUMBER(G17)),G17*Parametros!$B$12,"") | L17: =IF(AND(J17<>"",ISNUMBER(G17)),G17*Parametros!$B$13,"") | M17: =IF(AND(J17<>"",ISNUMBER(G17)),G17-J17-K17-L17,"") | N17: =IF(AND(J17<>"",ISNUMBER(G17)),M17/G17,"") | O17: =IF(OR(J17="",Parametros!$B$14>=1),"",J17/(1-Parametros!$B$14)) | P17: =IF(OR(J17="",Parametros!$B$14+Parametros!$B$18>=1),"",J17/(1-Parametros!$B$14-Parametros!$B$18)) | Q17: =IF(B17="","",IF(E17="","SIN RECETA",IF(J17="","FALTAN DATOS",IF(NOT(ISNUMBER(G17)),"FALTA PRECIO",IF(M17<0,"PIERDE",IF(N17<Parametros!$B$18,"BAJO META","OK")))))) -> SIN RECETA | R17: =IF(B17="","",IF(E17="","Elegir receta (molde).",IF(ISNA(MATCH(E17,Recetas!$A$5:$A$84,0)),"La receta no existe en Recetas.",IF(J17="","Completar la receta "&E17&": "&INDEX(Recetas!$T$5:$T$84,MATCH(E17,Recetas!$A$5:$A$84,0)),IF(NOT(ISNUMBER(G17)),"Precio de venta.",""))))) -> Elegir receta (molde).
A18: FUTCSUBPROPIQMC | B18: Camiseta Fútbol Pro Playmaker, Piqué m/c | C18: Juego | D18: 66 | G18: 21554 | H18: Por confirmar | I18: Sin receta: elige el molde que usa, o crea la receta en "Recetas" si aún no tiene molde. | J18: =IF(OR(B18="",E18=""),"",IF(IFERROR(INDEX(Recetas!$S$5:$S$84,MATCH(E18,Recetas!$A$5:$A$84,0)),"")="","",IFERROR(INDEX(Recetas!$S$5:$S$84,MATCH(E18,Recetas!$A$5:$A$84,0)),"")+N(F18))) | K18: =IF(AND(J18<>"",ISNUMBER(G18)),G18*Parametros!$B$12,"") | L18: =IF(AND(J18<>"",ISNUMBER(G18)),G18*Parametros!$B$13,"") | M18: =IF(AND(J18<>"",ISNUMBER(G18)),G18-J18-K18-L18,"") | N18: =IF(AND(J18<>"",ISNUMBER(G18)),M18/G18,"") | O18: =IF(OR(J18="",Parametros!$B$14>=1),"",J18/(1-Parametros!$B$14)) | P18: =IF(OR(J18="",Parametros!$B$14+Parametros!$B$18>=1),"",J18/(1-Parametros!$B$14-Parametros!$B$18)) | Q18: =IF(B18="","",IF(E18="","SIN RECETA",IF(J18="","FALTAN DATOS",IF(NOT(ISNUMBER(G18)),"FALTA PRECIO",IF(M18<0,"PIERDE",IF(N18<Parametros!$B$18,"BAJO META","OK")))))) -> SIN RECETA | R18: =IF(B18="","",IF(E18="","Elegir receta (molde).",IF(ISNA(MATCH(E18,Recetas!$A$5:$A$84,0)),"La receta no existe en Recetas.",IF(J18="","Completar la receta "&E18&": "&INDEX(Recetas!$T$5:$T$84,MATCH(E18,Recetas!$A$5:$A$84,0)),IF(NOT(ISNUMBER(G18)),"Precio de venta.",""))))) -> Elegir receta (molde).
A19: RUNCSUBPROSM | B19: Camiseta Running Pro s/m | C19: Juego | D19: 65 | E19: SM-03 · Camiseta Running s/m | G19: 19244 | H19: Por confirmar | J19: =IF(OR(B19="",E19=""),"",IF(IFERROR(INDEX(Recetas!$S$5:$S$84,MATCH(E19,Recetas!$A$5:$A$84,0)),"")="","",IFERROR(INDEX(Recetas!$S$5:$S$84,MATCH(E19,Recetas!$A$5:$A$84,0)),"")+N(F19))) -> 2148.008 | K19: =IF(AND(J19<>"",ISNUMBER(G19)),G19*Parametros!$B$12,"") -> 6792.1033 | L19: =IF(AND(J19<>"",ISNUMBER(G19)),G19*Parametros!$B$13,"") -> 2438.1464 | M19: =IF(AND(J19<>"",ISNUMBER(G19)),G19-J19-K19-L19,"") -> 7865.7424 | N19: =IF(AND(J19<>"",ISNUMBER(G19)),M19/G19,"") -> 0.40873739 | O19: =IF(OR(J19="",Parametros!$B$14>=1),"",J19/(1-Parametros!$B$14)) -> 4127.9505 | P19: =IF(OR(J19="",Parametros!$B$14+Parametros!$B$18>=1),"",J19/(1-Parametros!$B$14-Parametros!$B$18)) -> 5109.9611 | Q19: =IF(B19="","",IF(E19="","SIN RECETA",IF(J19="","FALTAN DATOS",IF(NOT(ISNUMBER(G19)),"FALTA PRECIO",IF(M19<0,"PIERDE",IF(N19<Parametros!$B$18,"BAJO META","OK")))))) -> OK | R19: =IF(B19="","",IF(E19="","Elegir receta (molde).",IF(ISNA(MATCH(E19,Recetas!$A$5:$A$84,0)),"La receta no existe en Recetas.",IF(J19="","Completar la receta "&E19&": "&INDEX(Recetas!$T$5:$T$84,MATCH(E19,Recetas!$A$5:$A$84,0)),IF(NOT(ISNUMBER(G19)),"Precio de venta.","")))))
A20: SAL-CTV-SUB-SG | B20: CORTAVIENTO SUBLIMADO | C20: Salida | D20: 62 | G20: 36050 | H20: Por confirmar | I20: Sin receta: elige el molde que usa, o crea la receta en "Recetas" si aún no tiene molde. | J20: =IF(OR(B20="",E20=""),"",IF(IFERROR(INDEX(Recetas!$S$5:$S$84,MATCH(E20,Recetas!$A$5:$A$84,0)),"")="","",IFERROR(INDEX(Recetas!$S$5:$S$84,MATCH(E20,Recetas!$A$5:$A$84,0)),"")+N(F20))) | K20: =IF(AND(J20<>"",ISNUMBER(G20)),G20*Parametros!$B$12,"") | L20: =IF(AND(J20<>"",ISNUMBER(G20)),G20*Parametros!$B$13,"") | M20: =IF(AND(J20<>"",ISNUMBER(G20)),G20-J20-K20-L20,"") | N20: =IF(AND(J20<>"",ISNUMBER(G20)),M20/G20,"") | O20: =IF(OR(J20="",Parametros!$B$14>=1),"",J20/(1-Parametros!$B$14)) | P20: =IF(OR(J20="",Parametros!$B$14+Parametros!$B$18>=1),"",J20/(1-Parametros!$B$14-Parametros!$B$18)) | Q20: =IF(B20="","",IF(E20="","SIN RECETA",IF(J20="","FALTAN DATOS",IF(NOT(ISNUMBER(G20)),"FALTA PRECIO",IF(M20<0,"PIERDE",IF(N20<Parametros!$B$18,"BAJO META","OK")))))) -> SIN RECETA | R20: =IF(B20="","",IF(E20="","Elegir receta (molde).",IF(ISNA(MATCH(E20,Recetas!$A$5:$A$84,0)),"La receta no existe en Recetas.",IF(J20="","Completar la receta "&E20&": "&INDEX(Recetas!$T$5:$T$84,MATCH(E20,Recetas!$A$5:$A$84,0)),IF(NOT(ISNUMBER(G20)),"Precio de venta.",""))))) -> Elegir receta (molde).
A21: RUG-SHO-BAS | B21: Short Rugby Basic | C21: Juego | D21: 61 | E21: SM-02 · Short Rugby | G21: 12507 | H21: Por confirmar | J21: =IF(OR(B21="",E21=""),"",IF(IFERROR(INDEX(Recetas!$S$5:$S$84,MATCH(E21,Recetas!$A$5:$A$84,0)),"")="","",IFERROR(INDEX(Recetas!$S$5:$S$84,MATCH(E21,Recetas!$A$5:$A$84,0)),"")+N(F21))) -> 2706.55 | K21: =IF(AND(J21<>"",ISNUMBER(G21)),G21*Parametros!$B$12,"") -> 4414.3024 | L21: =IF(AND(J21<>"",ISNUMBER(G21)),G21*Parametros!$B$13,"") -> 1584.5924 | M21: =IF(AND(J21<>"",ISNUMBER(G21)),G21-J21-K21-L21,"") -> 3801.5552 | N21: =IF(AND(J21<>"",ISNUMBER(G21)),M21/G21,"") -> 0.3039542 | O21: =IF(OR(J21="",Parametros!$B$14>=1),"",J21/(1-Parametros!$B$14)) -> 5201.3328 | P21: =IF(OR(J21="",Parametros!$B$14+Parametros!$B$18>=1),"",J21/(1-Parametros!$B$14-Parametros!$B$18)) -> 6438.6936 | Q21: =IF(B21="","",IF(E21="","SIN RECETA",IF(J21="","FALTAN DATOS",IF(NOT(ISNUMBER(G21)),"FALTA PRECIO",IF(M21<0,"PIERDE",IF(N21<Parametros!$B$18,"BAJO META","OK")))))) -> OK | R21: =IF(B21="","",IF(E21="","Elegir receta (molde).",IF(ISNA(MATCH(E21,Recetas!$A$5:$A$84,0)),"La receta no existe en Recetas.",IF(J21="","Completar la receta "&E21&": "&INDEX(Recetas!$T$5:$T$84,MATCH(E21,Recetas!$A$5:$A$84,0)),IF(NOT(ISNUMBER(G21)),"Precio de venta.","")))))
A22: SALPTPESUB | B22: Conjunto Polerón de Entrenamiento + Pitillo | C22: Salida | D22: 60 | G22: 41933 | H22: Por confirmar | I22: Sin receta: elige el molde que usa, o crea la receta en "Recetas" si aún no tiene molde. | J22: =IF(OR(B22="",E22=""),"",IF(IFERROR(INDEX(Recetas!$S$5:$S$84,MATCH(E22,Recetas!$A$5:$A$84,0)),"")="","",IFERROR(INDEX(Recetas!$S$5:$S$84,MATCH(E22,Recetas!$A$5:$A$84,0)),"")+N(F22))) | K22: =IF(AND(J22<>"",ISNUMBER(G22)),G22*Parametros!$B$12,"") | L22: =IF(AND(J22<>"",ISNUMBER(G22)),G22*Parametros!$B$13,"") | M22: =IF(AND(J22<>"",ISNUMBER(G22)),G22-J22-K22-L22,"") | N22: =IF(AND(J22<>"",ISNUMBER(G22)),M22/G22,"") | O22: =IF(OR(J22="",Parametros!$B$14>=1),"",J22/(1-Parametros!$B$14)) | P22: =IF(OR(J22="",Parametros!$B$14+Parametros!$B$18>=1),"",J22/(1-Parametros!$B$14-Parametros!$B$18)) | Q22: =IF(B22="","",IF(E22="","SIN RECETA",IF(J22="","FALTAN DATOS",IF(NOT(ISNUMBER(G22)),"FALTA PRECIO",IF(M22<0,"PIERDE",IF(N22<Parametros!$B$18,"BAJO META","OK")))))) -> SIN RECETA | R22: =IF(B22="","",IF(E22="","Elegir receta (molde).",IF(ISNA(MATCH(E22,Recetas!$A$5:$A$84,0)),"La receta no existe en Recetas.",IF(J22="","Completar la receta "&E22&": "&INDEX(Recetas!$T$5:$T$84,MATCH(E22,Recetas!$A$5:$A$84,0)),IF(NOT(ISNUMBER(G22)),"Precio de venta.",""))))) -> Elegir receta (molde).
A23: FUTSHOLIS | B23: Short Fútbol Playmaker Liso | C23: Juego | D23: 55 | E23: SM-01 · Short Fútbol | G23: 8059 | H23: Por confirmar | I23: El short de fútbol aún no tiene molde en el catálogo. | J23: =IF(OR(B23="",E23=""),"",IF(IFERROR(INDEX(Recetas!$S$5:$S$84,MATCH(E23,Recetas!$A$5:$A$84,0)),"")="","",IFERROR(INDEX(Recetas!$S$5:$S$84,MATCH(E23,Recetas!$A$5:$A$84,0)),"")+N(F23))) -> 2601.04 | K23: =IF(AND(J23<>"",ISNUMBER(G23)),G23*Parametros!$B$12,"") -> 2844.3962 | L23: =IF(AND(J23<>"",ISNUMBER(G23)),G23*Parametros!$B$13,"") -> 1021.0466 | M23: =IF(AND(J23<>"",ISNUMBER(G23)),G23-J23-K23-L23,"") -> 1592.5172 | N23: =IF(AND(J23<>"",ISNUMBER(G23)),M23/G23,"") -> 0.19760729 | O23: =IF(OR(J23="",Parametros!$B$14>=1),"",J23/(1-Parametros!$B$14)) -> 4998.5682 | P23: =IF(OR(J23="",Parametros!$B$14+Parametros!$B$18>=1),"",J23/(1-Parametros!$B$14-Parametros!$B$18)) -> 6187.6926 | Q23: =IF(B23="","",IF(E23="","SIN RECETA",IF(J23="","FALTAN DATOS",IF(NOT(ISNUMBER(G23)),"FALTA PRECIO",IF(M23<0,"PIERDE",IF(N23<Parametros!$B$18,"BAJO META","OK")))))) -> OK | R23: =IF(B23="","",IF(E23="","Elegir receta (molde).",IF(ISNA(MATCH(E23,Recetas!$A$5:$A$84,0)),"La receta no existe en Recetas.",IF(J23="","Completar la receta "&E23&": "&INDEX(Recetas!$T$5:$T$84,MATCH(E23,Recetas!$A$5:$A$84,0)),IF(NOT(ISNUMBER(G23)),"Precio de venta.","")))))
A24: VOLFEMCSUBPROV | B24: Camiseta Voley fem Pro Playmaker, V | C24: Juego | D24: 50 | G24: 19244 | H24: Por confirmar | I24: Sin receta: elige el molde que usa, o crea la receta en "Recetas" si aún no tiene molde. | J24: =IF(OR(B24="",E24=""),"",IF(IFERROR(INDEX(Recetas!$S$5:$S$84,MATCH(E24,Recetas!$A$5:$A$84,0)),"")="","",IFERROR(INDEX(Recetas!$S$5:$S$84,MATCH(E24,Recetas!$A$5:$A$84,0)),"")+N(F24))) | K24: =IF(AND(J24<>"",ISNUMBER(G24)),G24*Parametros!$B$12,"") | L24: =IF(AND(J24<>"",ISNUMBER(G24)),G24*Parametros!$B$13,"") | M24: =IF(AND(J24<>"",ISNUMBER(G24)),G24-J24-K24-L24,"") | N24: =IF(AND(J24<>"",ISNUMBER(G24)),M24/G24,"") | O24: =IF(OR(J24="",Parametros!$B$14>=1),"",J24/(1-Parametros!$B$14)) | P24: =IF(OR(J24="",Parametros!$B$14+Parametros!$B$18>=1),"",J24/(1-Parametros!$B$14-Parametros!$B$18)) | Q24: =IF(B24="","",IF(E24="","SIN RECETA",IF(J24="","FALTAN DATOS",IF(NOT(ISNUMBER(G24)),"FALTA PRECIO",IF(M24<0,"PIERDE",IF(N24<Parametros!$B$18,"BAJO META","OK")))))) -> SIN RECETA | R24: =IF(B24="","",IF(E24="","Elegir receta (molde).",IF(ISNA(MATCH(E24,Recetas!$A$5:$A$84,0)),"La receta no existe en Recetas.",IF(J24="","Completar la receta "&E24&": "&INDEX(Recetas!$T$5:$T$84,MATCH(E24,Recetas!$A$5:$A$84,0)),IF(NOT(ISNUMBER(G24)),"Precio de venta.",""))))) -> Elegir receta (molde).
A25: MDPTSUB | B25: PETO ENTRENAMIENTO SUB | C25: Juego | D25: 48 | G25: 8319 | H25: Por confirmar | I25: Sin receta: elige el molde que usa, o crea la receta en "Recetas" si aún no tiene molde. | J25: =IF(OR(B25="",E25=""),"",IF(IFERROR(INDEX(Recetas!$S$5:$S$84,MATCH(E25,Recetas!$A$5:$A$84,0)),"")="","",IFERROR(INDEX(Recetas!$S$5:$S$84,MATCH(E25,Recetas!$A$5:$A$84,0)),"")+N(F25))) | K25: =IF(AND(J25<>"",ISNUMBER(G25)),G25*Parametros!$B$12,"") | L25: =IF(AND(J25<>"",ISNUMBER(G25)),G25*Parametros!$B$13,"") | M25: =IF(AND(J25<>"",ISNUMBER(G25)),G25-J25-K25-L25,"") | N25: =IF(AND(J25<>"",ISNUMBER(G25)),M25/G25,"") | O25: =IF(OR(J25="",Parametros!$B$14>=1),"",J25/(1-Parametros!$B$14)) | P25: =IF(OR(J25="",Parametros!$B$14+Parametros!$B$18>=1),"",J25/(1-Parametros!$B$14-Parametros!$B$18)) | Q25: =IF(B25="","",IF(E25="","SIN RECETA",IF(J25="","FALTAN DATOS",IF(NOT(ISNUMBER(G25)),"FALTA PRECIO",IF(M25<0,"PIERDE",IF(N25<Parametros!$B$18,"BAJO META","OK")))))) -> SIN RECETA | R25: =IF(B25="","",IF(E25="","Elegir receta (molde).",IF(ISNA(MATCH(E25,Recetas!$A$5:$A$84,0)),"La receta no existe en Recetas.",IF(J25="","Completar la receta "&E25&": "&INDEX(Recetas!$T$5:$T$84,MATCH(E25,Recetas!$A$5:$A$84,0)),IF(NOT(ISNUMBER(G25)),"Precio de venta.",""))))) -> Elegir receta (molde).
A26: MDCSUBOVA | B26: Polera Playmaker, Cuello Oval s/mangas | C26: Juego | D26: 48 | G26: 16723 | H26: Por confirmar | I26: Sin receta: elige el molde que usa, o crea la receta en "Recetas" si aún no tiene molde. | J26: =IF(OR(B26="",E26=""),"",IF(IFERROR(INDEX(Recetas!$S$5:$S$84,MATCH(E26,Recetas!$A$5:$A$84,0)),"")="","",IFERROR(INDEX(Recetas!$S$5:$S$84,MATCH(E26,Recetas!$A$5:$A$84,0)),"")+N(F26))) | K26: =IF(AND(J26<>"",ISNUMBER(G26)),G26*Parametros!$B$12,"") | L26: =IF(AND(J26<>"",ISNUMBER(G26)),G26*Parametros!$B$13,"") | M26: =IF(AND(J26<>"",ISNUMBER(G26)),G26-J26-K26-L26,"") | N26: =IF(AND(J26<>"",ISNUMBER(G26)),M26/G26,"") | O26: =IF(OR(J26="",Parametros!$B$14>=1),"",J26/(1-Parametros!$B$14)) | P26: =IF(OR(J26="",Parametros!$B$14+Parametros!$B$18>=1),"",J26/(1-Parametros!$B$14-Parametros!$B$18)) | Q26: =IF(B26="","",IF(E26="","SIN RECETA",IF(J26="","FALTAN DATOS",IF(NOT(ISNUMBER(G26)),"FALTA PRECIO",IF(M26<0,"PIERDE",IF(N26<Parametros!$B$18,"BAJO META","OK")))))) -> SIN RECETA | R26: =IF(B26="","",IF(E26="","Elegir receta (molde).",IF(ISNA(MATCH(E26,Recetas!$A$5:$A$84,0)),"La receta no existe en Recetas.",IF(J26="","Completar la receta "&E26&": "&INDEX(Recetas!$T$5:$T$84,MATCH(E26,Recetas!$A$5:$A$84,0)),IF(NOT(ISNUMBER(G26)),"Precio de venta.",""))))) -> Elegir receta (molde).
A27: SALHOOLIS | B27: Polerón Hoodie Playmaker liso | C27: Salida | D27: 47 | G27: 26134 | H27: Por confirmar | I27: Sin receta: elige el molde que usa, o crea la receta en "Recetas" si aún no tiene molde. | J27: =IF(OR(B27="",E27=""),"",IF(IFERROR(INDEX(Recetas!$S$5:$S$84,MATCH(E27,Recetas!$A$5:$A$84,0)),"")="","",IFERROR(INDEX(Recetas!$S$5:$S$84,MATCH(E27,Recetas!$A$5:$A$84,0)),"")+N(F27))) | K27: =IF(AND(J27<>"",ISNUMBER(G27)),G27*Parametros!$B$12,"") | L27: =IF(AND(J27<>"",ISNUMBER(G27)),G27*Parametros!$B$13,"") | M27: =IF(AND(J27<>"",ISNUMBER(G27)),G27-J27-K27-L27,"") | N27: =IF(AND(J27<>"",ISNUMBER(G27)),M27/G27,"") | O27: =IF(OR(J27="",Parametros!$B$14>=1),"",J27/(1-Parametros!$B$14)) | P27: =IF(OR(J27="",Parametros!$B$14+Parametros!$B$18>=1),"",J27/(1-Parametros!$B$14-Parametros!$B$18)) | Q27: =IF(B27="","",IF(E27="","SIN RECETA",IF(J27="","FALTAN DATOS",IF(NOT(ISNUMBER(G27)),"FALTA PRECIO",IF(M27<0,"PIERDE",IF(N27<Parametros!$B$18,"BAJO META","OK")))))) -> SIN RECETA | R27: =IF(B27="","",IF(E27="","Elegir receta (molde).",IF(ISNA(MATCH(E27,Recetas!$A$5:$A$84,0)),"La receta no existe en Recetas.",IF(J27="","Completar la receta "&E27&": "&INDEX(Recetas!$T$5:$T$84,MATCH(E27,Recetas!$A$5:$A$84,0)),IF(NOT(ISNUMBER(G27)),"Precio de venta.",""))))) -> Elegir receta (molde).
A28: CSUBRUGSFBLANCA | B28: CAMISETA DE RUGBY STADE FRANCAIS ANIVERSARIO (BLANCA) | C28: Juego | D28: 44 | G28: 27605 | H28: Por confirmar | I28: Sin receta: elige el molde que usa, o crea la receta en "Recetas" si aún no tiene molde. | J28: =IF(OR(B28="",E28=""),"",IF(IFERROR(INDEX(Recetas!$S$5:$S$84,MATCH(E28,Recetas!$A$5:$A$84,0)),"")="","",IFERROR(INDEX(Recetas!$S$5:$S$84,MATCH(E28,Recetas!$A$5:$A$84,0)),"")+N(F28))) | K28: =IF(AND(J28<>"",ISNUMBER(G28)),G28*Parametros!$B$12,"") | L28: =IF(AND(J28<>"",ISNUMBER(G28)),G28*Parametros!$B$13,"") | M28: =IF(AND(J28<>"",ISNUMBER(G28)),G28-J28-K28-L28,"") | N28: =IF(AND(J28<>"",ISNUMBER(G28)),M28/G28,"") | O28: =IF(OR(J28="",Parametros!$B$14>=1),"",J28/(1-Parametros!$B$14)) | P28: =IF(OR(J28="",Parametros!$B$14+Parametros!$B$18>=1),"",J28/(1-Parametros!$B$14-Parametros!$B$18)) | Q28: =IF(B28="","",IF(E28="","SIN RECETA",IF(J28="","FALTAN DATOS",IF(NOT(ISNUMBER(G28)),"FALTA PRECIO",IF(M28<0,"PIERDE",IF(N28<Parametros!$B$18,"BAJO META","OK")))))) -> SIN RECETA | R28: =IF(B28="","",IF(E28="","Elegir receta (molde).",IF(ISNA(MATCH(E28,Recetas!$A$5:$A$84,0)),"La receta no existe en Recetas.",IF(J28="","Completar la receta "&E28&": "&INDEX(Recetas!$T$5:$T$84,MATCH(E28,Recetas!$A$5:$A$84,0)),IF(NOT(ISNUMBER(G28)),"Precio de venta.",""))))) -> Elegir receta (molde).
A29: SAL-POL-3C | B29: Polerón 3C Playmaker Algodón Cierre | C29: Salida | D29: 40 | G29: 32689 | H29: Por confirmar | I29: Sin receta: elige el molde que usa, o crea la receta en "Recetas" si aún no tiene molde. | J29: =IF(OR(B29="",E29=""),"",IF(IFERROR(INDEX(Recetas!$S$5:$S$84,MATCH(E29,Recetas!$A$5:$A$84,0)),"")="","",IFERROR(INDEX(Recetas!$S$5:$S$84,MATCH(E29,Recetas!$A$5:$A$84,0)),"")+N(F29))) | K29: =IF(AND(J29<>"",ISNUMBER(G29)),G29*Parametros!$B$12,"") | L29: =IF(AND(J29<>"",ISNUMBER(G29)),G29*Parametros!$B$13,"") | M29: =IF(AND(J29<>"",ISNUMBER(G29)),G29-J29-K29-L29,"") | N29: =IF(AND(J29<>"",ISNUMBER(G29)),M29/G29,"") | O29: =IF(OR(J29="",Parametros!$B$14>=1),"",J29/(1-Parametros!$B$14)) | P29: =IF(OR(J29="",Parametros!$B$14+Parametros!$B$18>=1),"",J29/(1-Parametros!$B$14-Parametros!$B$18)) | Q29: =IF(B29="","",IF(E29="","SIN RECETA",IF(J29="","FALTAN DATOS",IF(NOT(ISNUMBER(G29)),"FALTA PRECIO",IF(M29<0,"PIERDE",IF(N29<Parametros!$B$18,"BAJO META","OK")))))) -> SIN RECETA | R29: =IF(B29="","",IF(E29="","Elegir receta (molde).",IF(ISNA(MATCH(E29,Recetas!$A$5:$A$84,0)),"La receta no existe en Recetas.",IF(J29="","Completar la receta "&E29&": "&INDEX(Recetas!$T$5:$T$84,MATCH(E29,Recetas!$A$5:$A$84,0)),IF(NOT(ISNUMBER(G29)),"Precio de venta.",""))))) -> Elegir receta (molde).
A30: VOLMASC-CSUB-POL-CER | B30: Camiseta Voley masc Playmaker, Polo m/cero | C30: Juego | D30: 37 | G30: 17563 | H30: Por confirmar | I30: Sin receta: elige el molde que usa, o crea la receta en "Recetas" si aún no tiene molde. | J30: =IF(OR(B30="",E30=""),"",IF(IFERROR(INDEX(Recetas!$S$5:$S$84,MATCH(E30,Recetas!$A$5:$A$84,0)),"")="","",IFERROR(INDEX(Recetas!$S$5:$S$84,MATCH(E30,Recetas!$A$5:$A$84,0)),"")+N(F30))) | K30: =IF(AND(J30<>"",ISNUMBER(G30)),G30*Parametros!$B$12,"") | L30: =IF(AND(J30<>"",ISNUMBER(G30)),G30*Parametros!$B$13,"") | M30: =IF(AND(J30<>"",ISNUMBER(G30)),G30-J30-K30-L30,"") | N30: =IF(AND(J30<>"",ISNUMBER(G30)),M30/G30,"") | O30: =IF(OR(J30="",Parametros!$B$14>=1),"",J30/(1-Parametros!$B$14)) | P30: =IF(OR(J30="",Parametros!$B$14+Parametros!$B$18>=1),"",J30/(1-Parametros!$B$14-Parametros!$B$18)) | Q30: =IF(B30="","",IF(E30="","SIN RECETA",IF(J30="","FALTAN DATOS",IF(NOT(ISNUMBER(G30)),"FALTA PRECIO",IF(M30<0,"PIERDE",IF(N30<Parametros!$B$18,"BAJO META","OK")))))) -> SIN RECETA | R30: =IF(B30="","",IF(E30="","Elegir receta (molde).",IF(ISNA(MATCH(E30,Recetas!$A$5:$A$84,0)),"La receta no existe en Recetas.",IF(J30="","Completar la receta "&E30&": "&INDEX(Recetas!$T$5:$T$84,MATCH(E30,Recetas!$A$5:$A$84,0)),IF(NOT(ISNUMBER(G30)),"Precio de venta.",""))))) -> Elegir receta (molde).
A31: SALPRKLIS | B31: Parka Lisa Playmaker | C31: Salida | D31: 37 | G31: 54022 | H31: Por confirmar | I31: Sin receta: elige el molde que usa, o crea la receta en "Recetas" si aún no tiene molde. | J31: =IF(OR(B31="",E31=""),"",IF(IFERROR(INDEX(Recetas!$S$5:$S$84,MATCH(E31,Recetas!$A$5:$A$84,0)),"")="","",IFERROR(INDEX(Recetas!$S$5:$S$84,MATCH(E31,Recetas!$A$5:$A$84,0)),"")+N(F31))) | K31: =IF(AND(J31<>"",ISNUMBER(G31)),G31*Parametros!$B$12,"") | L31: =IF(AND(J31<>"",ISNUMBER(G31)),G31*Parametros!$B$13,"") | M31: =IF(AND(J31<>"",ISNUMBER(G31)),G31-J31-K31-L31,"") | N31: =IF(AND(J31<>"",ISNUMBER(G31)),M31/G31,"") | O31: =IF(OR(J31="",Parametros!$B$14>=1),"",J31/(1-Parametros!$B$14)) | P31: =IF(OR(J31="",Parametros!$B$14+Parametros!$B$18>=1),"",J31/(1-Parametros!$B$14-Parametros!$B$18)) | Q31: =IF(B31="","",IF(E31="","SIN RECETA",IF(J31="","FALTAN DATOS",IF(NOT(ISNUMBER(G31)),"FALTA PRECIO",IF(M31<0,"PIERDE",IF(N31<Parametros!$B$18,"BAJO META","OK")))))) -> SIN RECETA | R31: =IF(B31="","",IF(E31="","Elegir receta (molde).",IF(ISNA(MATCH(E31,Recetas!$A$5:$A$84,0)),"La receta no existe en Recetas.",IF(J31="","Completar la receta "&E31&": "&INDEX(Recetas!$T$5:$T$84,MATCH(E31,Recetas!$A$5:$A$84,0)),IF(NOT(ISNUMBER(G31)),"Precio de venta.",""))))) -> Elegir receta (molde).
A32: RUG-SHO-PRO | B32: Short Rugby Pro | C32: Juego | D32: 35 | E32: SM-02 · Short Rugby | G32: 14202 | H32: Por confirmar | I32: Pro puede gastar distinto: confirmar. | J32: =IF(OR(B32="",E32=""),"",IF(IFERROR(INDEX(Recetas!$S$5:$S$84,MATCH(E32,Recetas!$A$5:$A$84,0)),"")="","",IFERROR(INDEX(Recetas!$S$5:$S$84,MATCH(E32,Recetas!$A$5:$A$84,0)),"")+N(F32))) -> 2706.55 | K32: =IF(AND(J32<>"",ISNUMBER(G32)),G32*Parametros!$B$12,"") -> 5012.5468 | L32: =IF(AND(J32<>"",ISNUMBER(G32)),G32*Parametros!$B$13,"") -> 1799.3429 | M32: =IF(AND(J32<>"",ISNUMBER(G32)),G32-J32-K32-L32,"") -> 4683.5603 | N32: =IF(AND(J32<>"",ISNUMBER(G32)),M32/G32,"") -> 0.32978174 | O32: =IF(OR(J32="",Parametros!$B$14>=1),"",J32/(1-Parametros!$B$14)) -> 5201.3328 | P32: =IF(OR(J32="",Parametros!$B$14+Parametros!$B$18>=1),"",J32/(1-Parametros!$B$14-Parametros!$B$18)) -> 6438.6936 | Q32: =IF(B32="","",IF(E32="","SIN RECETA",IF(J32="","FALTAN DATOS",IF(NOT(ISNUMBER(G32)),"FALTA PRECIO",IF(M32<0,"PIERDE",IF(N32<Parametros!$B$18,"BAJO META","OK")))))) -> OK | R32: =IF(B32="","",IF(E32="","Elegir receta (molde).",IF(ISNA(MATCH(E32,Recetas!$A$5:$A$84,0)),"La receta no existe en Recetas.",IF(J32="","Completar la receta "&E32&": "&INDEX(Recetas!$T$5:$T$84,MATCH(E32,Recetas!$A$5:$A$84,0)),IF(NOT(ISNUMBER(G32)),"Precio de venta.","")))))
A33: SAL-POL-SUB | B33: Polerón Entrenamiento Sublim | C33: Salida | D33: 35 | G33: 27647 | H33: Por confirmar | I33: Sin receta: elige el molde que usa, o crea la receta en "Recetas" si aún no tiene molde. | J33: =IF(OR(B33="",E33=""),"",IF(IFERROR(INDEX(Recetas!$S$5:$S$84,MATCH(E33,Recetas!$A$5:$A$84,0)),"")="","",IFERROR(INDEX(Recetas!$S$5:$S$84,MATCH(E33,Recetas!$A$5:$A$84,0)),"")+N(F33))) | K33: =IF(AND(J33<>"",ISNUMBER(G33)),G33*Parametros!$B$12,"") | L33: =IF(AND(J33<>"",ISNUMBER(G33)),G33*Parametros!$B$13,"") | M33: =IF(AND(J33<>"",ISNUMBER(G33)),G33-J33-K33-L33,"") | N33: =IF(AND(J33<>"",ISNUMBER(G33)),M33/G33,"") | O33: =IF(OR(J33="",Parametros!$B$14>=1),"",J33/(1-Parametros!$B$14)) | P33: =IF(OR(J33="",Parametros!$B$14+Parametros!$B$18>=1),"",J33/(1-Parametros!$B$14-Parametros!$B$18)) | Q33: =IF(B33="","",IF(E33="","SIN RECETA",IF(J33="","FALTAN DATOS",IF(NOT(ISNUMBER(G33)),"FALTA PRECIO",IF(M33<0,"PIERDE",IF(N33<Parametros!$B$18,"BAJO META","OK")))))) -> SIN RECETA | R33: =IF(B33="","",IF(E33="","Elegir receta (molde).",IF(ISNA(MATCH(E33,Recetas!$A$5:$A$84,0)),"La receta no existe en Recetas.",IF(J33="","Completar la receta "&E33&": "&INDEX(Recetas!$T$5:$T$84,MATCH(E33,Recetas!$A$5:$A$84,0)),IF(NOT(ISNUMBER(G33)),"Precio de venta.",""))))) -> Elegir receta (molde).
A34: RUGCSUBPER | B34: Camiseta Rugby Performance Pmk | C34: Juego | D34: 34 | G34: 19664 | H34: Por confirmar | I34: Sin receta: elige el molde que usa, o crea la receta en "Recetas" si aún no tiene molde. | J34: =IF(OR(B34="",E34=""),"",IF(IFERROR(INDEX(Recetas!$S$5:$S$84,MATCH(E34,Recetas!$A$5:$A$84,0)),"")="","",IFERROR(INDEX(Recetas!$S$5:$S$84,MATCH(E34,Recetas!$A$5:$A$84,0)),"")+N(F34))) | K34: =IF(AND(J34<>"",ISNUMBER(G34)),G34*Parametros!$B$12,"") | L34: =IF(AND(J34<>"",ISNUMBER(G34)),G34*Parametros!$B$13,"") | M34: =IF(AND(J34<>"",ISNUMBER(G34)),G34-J34-K34-L34,"") | N34: =IF(AND(J34<>"",ISNUMBER(G34)),M34/G34,"") | O34: =IF(OR(J34="",Parametros!$B$14>=1),"",J34/(1-Parametros!$B$14)) | P34: =IF(OR(J34="",Parametros!$B$14+Parametros!$B$18>=1),"",J34/(1-Parametros!$B$14-Parametros!$B$18)) | Q34: =IF(B34="","",IF(E34="","SIN RECETA",IF(J34="","FALTAN DATOS",IF(NOT(ISNUMBER(G34)),"FALTA PRECIO",IF(M34<0,"PIERDE",IF(N34<Parametros!$B$18,"BAJO META","OK")))))) -> SIN RECETA | R34: =IF(B34="","",IF(E34="","Elegir receta (molde).",IF(ISNA(MATCH(E34,Recetas!$A$5:$A$84,0)),"La receta no existe en Recetas.",IF(J34="","Completar la receta "&E34&": "&INDEX(Recetas!$T$5:$T$84,MATCH(E34,Recetas!$A$5:$A$84,0)),IF(NOT(ISNUMBER(G34)),"Precio de venta.",""))))) -> Elegir receta (molde).
A35: FUTCSUBML | B35: Camiseta Fútbol Playmaker, m/l | C35: Juego | D35: 34 | E35: 02 · FUTHOMU01 | G35: 17563 | H35: Por confirmar | I35: Manga larga: suma su costo extra en "Extras". | J35: =IF(OR(B35="",E35=""),"",IF(IFERROR(INDEX(Recetas!$S$5:$S$84,MATCH(E35,Recetas!$A$5:$A$84,0)),"")="","",IFERROR(INDEX(Recetas!$S$5:$S$84,MATCH(E35,Recetas!$A$5:$A$84,0)),"")+N(F35))) | K35: =IF(AND(J35<>"",ISNUMBER(G35)),G35*Parametros!$B$12,"") | L35: =IF(AND(J35<>"",ISNUMBER(G35)),G35*Parametros!$B$13,"") | M35: =IF(AND(J35<>"",ISNUMBER(G35)),G35-J35-K35-L35,"") | N35: =IF(AND(J35<>"",ISNUMBER(G35)),M35/G35,"") | O35: =IF(OR(J35="",Parametros!$B$14>=1),"",J35/(1-Parametros!$B$14)) | P35: =IF(OR(J35="",Parametros!$B$14+Parametros!$B$18>=1),"",J35/(1-Parametros!$B$14-Parametros!$B$18)) | Q35: =IF(B35="","",IF(E35="","SIN RECETA",IF(J35="","FALTAN DATOS",IF(NOT(ISNUMBER(G35)),"FALTA PRECIO",IF(M35<0,"PIERDE",IF(N35<Parametros!$B$18,"BAJO META","OK")))))) -> FALTAN DATOS | R35: =IF(B35="","",IF(E35="","Elegir receta (molde).",IF(ISNA(MATCH(E35,Recetas!$A$5:$A$84,0)),"La receta no existe en Recetas.",IF(J35="","Completar la receta "&E35&": "&INDEX(Recetas!$T$5:$T$84,MATCH(E35,Recetas!$A$5:$A$84,0)),IF(NOT(ISNUMBER(G35)),"Precio de venta.",""))))) -> Completar la receta 02 · FUTHOMU01: Tela. Kg de tela. Metros impresos.
A36: SALALMLLISA | B36: Camiseta Algodón Manga Larga Lisa | C36: Juego | D36: 31 | G36: 12521 | H36: Por confirmar | I36: Sin receta: elige el molde que usa, o crea la receta en "Recetas" si aún no tiene molde. | J36: =IF(OR(B36="",E36=""),"",IF(IFERROR(INDEX(Recetas!$S$5:$S$84,MATCH(E36,Recetas!$A$5:$A$84,0)),"")="","",IFERROR(INDEX(Recetas!$S$5:$S$84,MATCH(E36,Recetas!$A$5:$A$84,0)),"")+N(F36))) | K36: =IF(AND(J36<>"",ISNUMBER(G36)),G36*Parametros!$B$12,"") | L36: =IF(AND(J36<>"",ISNUMBER(G36)),G36*Parametros!$B$13,"") | M36: =IF(AND(J36<>"",ISNUMBER(G36)),G36-J36-K36-L36,"") | N36: =IF(AND(J36<>"",ISNUMBER(G36)),M36/G36,"") | O36: =IF(OR(J36="",Parametros!$B$14>=1),"",J36/(1-Parametros!$B$14)) | P36: =IF(OR(J36="",Parametros!$B$14+Parametros!$B$18>=1),"",J36/(1-Parametros!$B$14-Parametros!$B$18)) | Q36: =IF(B36="","",IF(E36="","SIN RECETA",IF(J36="","FALTAN DATOS",IF(NOT(ISNUMBER(G36)),"FALTA PRECIO",IF(M36<0,"PIERDE",IF(N36<Parametros!$B$18,"BAJO META","OK")))))) -> SIN RECETA | R36: =IF(B36="","",IF(E36="","Elegir receta (molde).",IF(ISNA(MATCH(E36,Recetas!$A$5:$A$84,0)),"La receta no existe en Recetas.",IF(J36="","Completar la receta "&E36&": "&INDEX(Recetas!$T$5:$T$84,MATCH(E36,Recetas!$A$5:$A$84,0)),IF(NOT(ISNUMBER(G36)),"Precio de venta.",""))))) -> Elegir receta (molde).
A37: RUG-CSUB-PIQ | B37: Camiseta Rugby Playmaker, Vintage | C37: Juego | D37: 29 | G37: 21204 | H37: Por confirmar | I37: Sin receta: elige el molde que usa, o crea la receta en "Recetas" si aún no tiene molde. | J37: =IF(OR(B37="",E37=""),"",IF(IFERROR(INDEX(Recetas!$S$5:$S$84,MATCH(E37,Recetas!$A$5:$A$84,0)),"")="","",IFERROR(INDEX(Recetas!$S$5:$S$84,MATCH(E37,Recetas!$A$5:$A$84,0)),"")+N(F37))) | K37: =IF(AND(J37<>"",ISNUMBER(G37)),G37*Parametros!$B$12,"") | L37: =IF(AND(J37<>"",ISNUMBER(G37)),G37*Parametros!$B$13,"") | M37: =IF(AND(J37<>"",ISNUMBER(G37)),G37-J37-K37-L37,"") | N37: =IF(AND(J37<>"",ISNUMBER(G37)),M37/G37,"") | O37: =IF(OR(J37="",Parametros!$B$14>=1),"",J37/(1-Parametros!$B$14)) | P37: =IF(OR(J37="",Parametros!$B$14+Parametros!$B$18>=1),"",J37/(1-Parametros!$B$14-Parametros!$B$18)) | Q37: =IF(B37="","",IF(E37="","SIN RECETA",IF(J37="","FALTAN DATOS",IF(NOT(ISNUMBER(G37)),"FALTA PRECIO",IF(M37<0,"PIERDE",IF(N37<Parametros!$B$18,"BAJO META","OK")))))) -> SIN RECETA | R37: =IF(B37="","",IF(E37="","Elegir receta (molde).",IF(ISNA(MATCH(E37,Recetas!$A$5:$A$84,0)),"La receta no existe en Recetas.",IF(J37="","Completar la receta "&E37&": "&INDEX(Recetas!$T$5:$T$84,MATCH(E37,Recetas!$A$5:$A$84,0)),IF(NOT(ISNUMBER(G37)),"Precio de venta.",""))))) -> Elegir receta (molde).
A38: VOL-CSUB-SAL-MC | B38: Camiseta Salida de Cancha Voley m/c | C38: Salida | D38: 29 | G38: 22605 | H38: Por confirmar | I38: Sin receta: elige el molde que usa, o crea la receta en "Recetas" si aún no tiene molde. | J38: =IF(OR(B38="",E38=""),"",IF(IFERROR(INDEX(Recetas!$S$5:$S$84,MATCH(E38,Recetas!$A$5:$A$84,0)),"")="","",IFERROR(INDEX(Recetas!$S$5:$S$84,MATCH(E38,Recetas!$A$5:$A$84,0)),"")+N(F38))) | K38: =IF(AND(J38<>"",ISNUMBER(G38)),G38*Parametros!$B$12,"") | L38: =IF(AND(J38<>"",ISNUMBER(G38)),G38*Parametros!$B$13,"") | M38: =IF(AND(J38<>"",ISNUMBER(G38)),G38-J38-K38-L38,"") | N38: =IF(AND(J38<>"",ISNUMBER(G38)),M38/G38,"") | O38: =IF(OR(J38="",Parametros!$B$14>=1),"",J38/(1-Parametros!$B$14)) | P38: =IF(OR(J38="",Parametros!$B$14+Parametros!$B$18>=1),"",J38/(1-Parametros!$B$14-Parametros!$B$18)) | Q38: =IF(B38="","",IF(E38="","SIN RECETA",IF(J38="","FALTAN DATOS",IF(NOT(ISNUMBER(G38)),"FALTA PRECIO",IF(M38<0,"PIERDE",IF(N38<Parametros!$B$18,"BAJO META","OK")))))) -> SIN RECETA | R38: =IF(B38="","",IF(E38="","Elegir receta (molde).",IF(ISNA(MATCH(E38,Recetas!$A$5:$A$84,0)),"La receta no existe en Recetas.",IF(J38="","Completar la receta "&E38&": "&INDEX(Recetas!$T$5:$T$84,MATCH(E38,Recetas!$A$5:$A$84,0)),IF(NOT(ISNUMBER(G38)),"Precio de venta.",""))))) -> Elegir receta (molde).
A39: CSUBVOLFEMVSM | B39: CAMISETA VOLEY FEM V S/M PLAYMAKER | C39: Juego | D39: 29 | G39: 16723 | H39: Por confirmar | I39: Sin receta: elige el molde que usa, o crea la receta en "Recetas" si aún no tiene molde. | J39: =IF(OR(B39="",E39=""),"",IF(IFERROR(INDEX(Recetas!$S$5:$S$84,MATCH(E39,Recetas!$A$5:$A$84,0)),"")="","",IFERROR(INDEX(Recetas!$S$5:$S$84,MATCH(E39,Recetas!$A$5:$A$84,0)),"")+N(F39))) | K39: =IF(AND(J39<>"",ISNUMBER(G39)),G39*Parametros!$B$12,"") | L39: =IF(AND(J39<>"",ISNUMBER(G39)),G39*Parametros!$B$13,"") | M39: =IF(AND(J39<>"",ISNUMBER(G39)),G39-J39-K39-L39,"") | N39: =IF(AND(J39<>"",ISNUMBER(G39)),M39/G39,"") | O39: =IF(OR(J39="",Parametros!$B$14>=1),"",J39/(1-Parametros!$B$14)) | P39: =IF(OR(J39="",Parametros!$B$14+Parametros!$B$18>=1),"",J39/(1-Parametros!$B$14-Parametros!$B$18)) | Q39: =IF(B39="","",IF(E39="","SIN RECETA",IF(J39="","FALTAN DATOS",IF(NOT(ISNUMBER(G39)),"FALTA PRECIO",IF(M39<0,"PIERDE",IF(N39<Parametros!$B$18,"BAJO META","OK")))))) -> SIN RECETA | R39: =IF(B39="","",IF(E39="","Elegir receta (molde).",IF(ISNA(MATCH(E39,Recetas!$A$5:$A$84,0)),"La receta no existe en Recetas.",IF(J39="","Completar la receta "&E39&": "&INDEX(Recetas!$T$5:$T$84,MATCH(E39,Recetas!$A$5:$A$84,0)),IF(NOT(ISNUMBER(G39)),"Precio de venta.",""))))) -> Elegir receta (molde).
A40: RUG-CSUB-LIC | B40: Camiseta Rugby Playmaker, Low Profile | C40: Juego | D40: 26 | G40: 23488 | H40: Por confirmar | I40: Sin receta: elige el molde que usa, o crea la receta en "Recetas" si aún no tiene molde. | J40: =IF(OR(B40="",E40=""),"",IF(IFERROR(INDEX(Recetas!$S$5:$S$84,MATCH(E40,Recetas!$A$5:$A$84,0)),"")="","",IFERROR(INDEX(Recetas!$S$5:$S$84,MATCH(E40,Recetas!$A$5:$A$84,0)),"")+N(F40))) | K40: =IF(AND(J40<>"",ISNUMBER(G40)),G40*Parametros!$B$12,"") | L40: =IF(AND(J40<>"",ISNUMBER(G40)),G40*Parametros!$B$13,"") | M40: =IF(AND(J40<>"",ISNUMBER(G40)),G40-J40-K40-L40,"") | N40: =IF(AND(J40<>"",ISNUMBER(G40)),M40/G40,"") | O40: =IF(OR(J40="",Parametros!$B$14>=1),"",J40/(1-Parametros!$B$14)) | P40: =IF(OR(J40="",Parametros!$B$14+Parametros!$B$18>=1),"",J40/(1-Parametros!$B$14-Parametros!$B$18)) | Q40: =IF(B40="","",IF(E40="","SIN RECETA",IF(J40="","FALTAN DATOS",IF(NOT(ISNUMBER(G40)),"FALTA PRECIO",IF(M40<0,"PIERDE",IF(N40<Parametros!$B$18,"BAJO META","OK")))))) -> SIN RECETA | R40: =IF(B40="","",IF(E40="","Elegir receta (molde).",IF(ISNA(MATCH(E40,Recetas!$A$5:$A$84,0)),"La receta no existe en Recetas.",IF(J40="","Completar la receta "&E40&": "&INDEX(Recetas!$T$5:$T$84,MATCH(E40,Recetas!$A$5:$A$84,0)),IF(NOT(ISNUMBER(G40)),"Precio de venta.",""))))) -> Elegir receta (molde).
A41: RUNCSUBPROMC | B41: Camiseta Running Pro m/c | C41: Juego | D41: 25 | G41: 19244 | H41: Por confirmar | I41: Sin receta: elige el molde que usa, o crea la receta en "Recetas" si aún no tiene molde. | J41: =IF(OR(B41="",E41=""),"",IF(IFERROR(INDEX(Recetas!$S$5:$S$84,MATCH(E41,Recetas!$A$5:$A$84,0)),"")="","",IFERROR(INDEX(Recetas!$S$5:$S$84,MATCH(E41,Recetas!$A$5:$A$84,0)),"")+N(F41))) | K41: =IF(AND(J41<>"",ISNUMBER(G41)),G41*Parametros!$B$12,"") | L41: =IF(AND(J41<>"",ISNUMBER(G41)),G41*Parametros!$B$13,"") | M41: =IF(AND(J41<>"",ISNUMBER(G41)),G41-J41-K41-L41,"") | N41: =IF(AND(J41<>"",ISNUMBER(G41)),M41/G41,"") | O41: =IF(OR(J41="",Parametros!$B$14>=1),"",J41/(1-Parametros!$B$14)) | P41: =IF(OR(J41="",Parametros!$B$14+Parametros!$B$18>=1),"",J41/(1-Parametros!$B$14-Parametros!$B$18)) | Q41: =IF(B41="","",IF(E41="","SIN RECETA",IF(J41="","FALTAN DATOS",IF(NOT(ISNUMBER(G41)),"FALTA PRECIO",IF(M41<0,"PIERDE",IF(N41<Parametros!$B$18,"BAJO META","OK")))))) -> SIN RECETA | R41: =IF(B41="","",IF(E41="","Elegir receta (molde).",IF(ISNA(MATCH(E41,Recetas!$A$5:$A$84,0)),"La receta no existe en Recetas.",IF(J41="","Completar la receta "&E41&": "&INDEX(Recetas!$T$5:$T$84,MATCH(E41,Recetas!$A$5:$A$84,0)),IF(NOT(ISNUMBER(G41)),"Precio de venta.",""))))) -> Elegir receta (molde).
A42: SAL-SHO-SUB | B42: SHORT SALIDA SUB | C42: Salida | D42: 25 | G42: 15882 | H42: Por confirmar | I42: Sin receta: elige el molde que usa, o crea la receta en "Recetas" si aún no tiene molde. | J42: =IF(OR(B42="",E42=""),"",IF(IFERROR(INDEX(Recetas!$S$5:$S$84,MATCH(E42,Recetas!$A$5:$A$84,0)),"")="","",IFERROR(INDEX(Recetas!$S$5:$S$84,MATCH(E42,Recetas!$A$5:$A$84,0)),"")+N(F42))) | K42: =IF(AND(J42<>"",ISNUMBER(G42)),G42*Parametros!$B$12,"") | L42: =IF(AND(J42<>"",ISNUMBER(G42)),G42*Parametros!$B$13,"") | M42: =IF(AND(J42<>"",ISNUMBER(G42)),G42-J42-K42-L42,"") | N42: =IF(AND(J42<>"",ISNUMBER(G42)),M42/G42,"") | O42: =IF(OR(J42="",Parametros!$B$14>=1),"",J42/(1-Parametros!$B$14)) | P42: =IF(OR(J42="",Parametros!$B$14+Parametros!$B$18>=1),"",J42/(1-Parametros!$B$14-Parametros!$B$18)) | Q42: =IF(B42="","",IF(E42="","SIN RECETA",IF(J42="","FALTAN DATOS",IF(NOT(ISNUMBER(G42)),"FALTA PRECIO",IF(M42<0,"PIERDE",IF(N42<Parametros!$B$18,"BAJO META","OK")))))) -> SIN RECETA | R42: =IF(B42="","",IF(E42="","Elegir receta (molde).",IF(ISNA(MATCH(E42,Recetas!$A$5:$A$84,0)),"La receta no existe en Recetas.",IF(J42="","Completar la receta "&E42&": "&INDEX(Recetas!$T$5:$T$84,MATCH(E42,Recetas!$A$5:$A$84,0)),IF(NOT(ISNUMBER(G42)),"Precio de venta.",""))))) -> Elegir receta (molde).
A43: FUTCSUBPIQMC | B43: Camiseta Fútbol Playmaker, Piqué m/c | C43: Juego | D43: 24 | E43: 10 · FUTHOMCC01 | G43: 18403 | H43: Por confirmar | I43: ¿Piqué = cuello camisero? Confirmar. | J43: =IF(OR(B43="",E43=""),"",IF(IFERROR(INDEX(Recetas!$S$5:$S$84,MATCH(E43,Recetas!$A$5:$A$84,0)),"")="","",IFERROR(INDEX(Recetas!$S$5:$S$84,MATCH(E43,Recetas!$A$5:$A$84,0)),"")+N(F43))) | K43: =IF(AND(J43<>"",ISNUMBER(G43)),G43*Parametros!$B$12,"") | L43: =IF(AND(J43<>"",ISNUMBER(G43)),G43*Parametros!$B$13,"") | M43: =IF(AND(J43<>"",ISNUMBER(G43)),G43-J43-K43-L43,"") | N43: =IF(AND(J43<>"",ISNUMBER(G43)),M43/G43,"") | O43: =IF(OR(J43="",Parametros!$B$14>=1),"",J43/(1-Parametros!$B$14)) | P43: =IF(OR(J43="",Parametros!$B$14+Parametros!$B$18>=1),"",J43/(1-Parametros!$B$14-Parametros!$B$18)) | Q43: =IF(B43="","",IF(E43="","SIN RECETA",IF(J43="","FALTAN DATOS",IF(NOT(ISNUMBER(G43)),"FALTA PRECIO",IF(M43<0,"PIERDE",IF(N43<Parametros!$B$18,"BAJO META","OK")))))) -> FALTAN DATOS | R43: =IF(B43="","",IF(E43="","Elegir receta (molde).",IF(ISNA(MATCH(E43,Recetas!$A$5:$A$84,0)),"La receta no existe en Recetas.",IF(J43="","Completar la receta "&E43&": "&INDEX(Recetas!$T$5:$T$84,MATCH(E43,Recetas!$A$5:$A$84,0)),IF(NOT(ISNUMBER(G43)),"Precio de venta.",""))))) -> Completar la receta 10 · FUTHOMCC01: Tela. Kg de tela. Metros impresos.
A44: FUTCSUBPROMC-V | B44: Camiseta Fútbol Pro Playmaker, V m/c | C44: Juego | D44: 23 | E44: 16 · FUTHOMV01PRO | G44: 19244 | H44: Por confirmar | I44: Molde Pro cuello V. | J44: =IF(OR(B44="",E44=""),"",IF(IFERROR(INDEX(Recetas!$S$5:$S$84,MATCH(E44,Recetas!$A$5:$A$84,0)),"")="","",IFERROR(INDEX(Recetas!$S$5:$S$84,MATCH(E44,Recetas!$A$5:$A$84,0)),"")+N(F44))) | K44: =IF(AND(J44<>"",ISNUMBER(G44)),G44*Parametros!$B$12,"") | L44: =IF(AND(J44<>"",ISNUMBER(G44)),G44*Parametros!$B$13,"") | M44: =IF(AND(J44<>"",ISNUMBER(G44)),G44-J44-K44-L44,"") | N44: =IF(AND(J44<>"",ISNUMBER(G44)),M44/G44,"") | O44: =IF(OR(J44="",Parametros!$B$14>=1),"",J44/(1-Parametros!$B$14)) | P44: =IF(OR(J44="",Parametros!$B$14+Parametros!$B$18>=1),"",J44/(1-Parametros!$B$14-Parametros!$B$18)) | Q44: =IF(B44="","",IF(E44="","SIN RECETA",IF(J44="","FALTAN DATOS",IF(NOT(ISNUMBER(G44)),"FALTA PRECIO",IF(M44<0,"PIERDE",IF(N44<Parametros!$B$18,"BAJO META","OK")))))) -> FALTAN DATOS | R44: =IF(B44="","",IF(E44="","Elegir receta (molde).",IF(ISNA(MATCH(E44,Recetas!$A$5:$A$84,0)),"La receta no existe en Recetas.",IF(J44="","Completar la receta "&E44&": "&INDEX(Recetas!$T$5:$T$84,MATCH(E44,Recetas!$A$5:$A$84,0)),IF(NOT(ISNUMBER(G44)),"Precio de venta.",""))))) -> Completar la receta 16 · FUTHOMV01PRO: Tela. Kg de tela. Metros impresos.
A45: BASCSUBPER | B45: Camiseta Básquetbol Performance | C45: Juego | D45: 21 | E45: 30 · BKHOMU03 | G45: 17563 | H45: Por confirmar | I45: Molde sugerido: básquet masculino cuello redondo. Confirmar. | J45: =IF(OR(B45="",E45=""),"",IF(IFERROR(INDEX(Recetas!$S$5:$S$84,MATCH(E45,Recetas!$A$5:$A$84,0)),"")="","",IFERROR(INDEX(Recetas!$S$5:$S$84,MATCH(E45,Recetas!$A$5:$A$84,0)),"")+N(F45))) | K45: =IF(AND(J45<>"",ISNUMBER(G45)),G45*Parametros!$B$12,"") | L45: =IF(AND(J45<>"",ISNUMBER(G45)),G45*Parametros!$B$13,"") | M45: =IF(AND(J45<>"",ISNUMBER(G45)),G45-J45-K45-L45,"") | N45: =IF(AND(J45<>"",ISNUMBER(G45)),M45/G45,"") | O45: =IF(OR(J45="",Parametros!$B$14>=1),"",J45/(1-Parametros!$B$14)) | P45: =IF(OR(J45="",Parametros!$B$14+Parametros!$B$18>=1),"",J45/(1-Parametros!$B$14-Parametros!$B$18)) | Q45: =IF(B45="","",IF(E45="","SIN RECETA",IF(J45="","FALTAN DATOS",IF(NOT(ISNUMBER(G45)),"FALTA PRECIO",IF(M45<0,"PIERDE",IF(N45<Parametros!$B$18,"BAJO META","OK")))))) -> FALTAN DATOS | R45: =IF(B45="","",IF(E45="","Elegir receta (molde).",IF(ISNA(MATCH(E45,Recetas!$A$5:$A$84,0)),"La receta no existe en Recetas.",IF(J45="","Completar la receta "&E45&": "&INDEX(Recetas!$T$5:$T$84,MATCH(E45,Recetas!$A$5:$A$84,0)),IF(NOT(ISNUMBER(G45)),"Precio de venta.",""))))) -> Completar la receta 30 · BKHOMU03: Metros impresos.
A46: VOL-SHO-SUB | B46: Short Fútbol Playmaker Sublimado | C46: Juego | D46: 20 | E46: SM-01 · Short Fútbol | G46: 12521 | H46: Por confirmar | I46: Short sublimado: completar metros impresos en su receta. | J46: =IF(OR(B46="",E46=""),"",IF(IFERROR(INDEX(Recetas!$S$5:$S$84,MATCH(E46,Recetas!$A$5:$A$84,0)),"")="","",IFERROR(INDEX(Recetas!$S$5:$S$84,MATCH(E46,Recetas!$A$5:$A$84,0)),"")+N(F46))) -> 2601.04 | K46: =IF(AND(J46<>"",ISNUMBER(G46)),G46*Parametros!$B$12,"") -> 4419.2437 | L46: =IF(AND(J46<>"",ISNUMBER(G46)),G46*Parametros!$B$13,"") -> 1586.3662 | M46: =IF(AND(J46<>"",ISNUMBER(G46)),G46-J46-K46-L46,"") -> 3914.3502 | N46: =IF(AND(J46<>"",ISNUMBER(G46)),M46/G46,"") -> 0.31262281 | O46: =IF(OR(J46="",Parametros!$B$14>=1),"",J46/(1-Parametros!$B$14)) -> 4998.5682 | P46: =IF(OR(J46="",Parametros!$B$14+Parametros!$B$18>=1),"",J46/(1-Parametros!$B$14-Parametros!$B$18)) -> 6187.6926 | Q46: =IF(B46="","",IF(E46="","SIN RECETA",IF(J46="","FALTAN DATOS",IF(NOT(ISNUMBER(G46)),"FALTA PRECIO",IF(M46<0,"PIERDE",IF(N46<Parametros!$B$18,"BAJO META","OK")))))) -> OK | R46: =IF(B46="","",IF(E46="","Elegir receta (molde).",IF(ISNA(MATCH(E46,Recetas!$A$5:$A$84,0)),"La receta no existe en Recetas.",IF(J46="","Completar la receta "&E46&": "&INDEX(Recetas!$T$5:$T$84,MATCH(E46,Recetas!$A$5:$A$84,0)),IF(NOT(ISNUMBER(G46)),"Precio de venta.","")))))
A47: VOLFEM-CSUBPRO-POL | B47: Camiseta Voley fem Pro Playmaker, Polo | C47: Juego | D47: 20 | G47: 18403 | H47: Por confirmar | I47: Sin receta: elige el molde que usa, o crea la receta en "Recetas" si aún no tiene molde. | J47: =IF(OR(B47="",E47=""),"",IF(IFERROR(INDEX(Recetas!$S$5:$S$84,MATCH(E47,Recetas!$A$5:$A$84,0)),"")="","",IFERROR(INDEX(Recetas!$S$5:$S$84,MATCH(E47,Recetas!$A$5:$A$84,0)),"")+N(F47))) | K47: =IF(AND(J47<>"",ISNUMBER(G47)),G47*Parametros!$B$12,"") | L47: =IF(AND(J47<>"",ISNUMBER(G47)),G47*Parametros!$B$13,"") | M47: =IF(AND(J47<>"",ISNUMBER(G47)),G47-J47-K47-L47,"") | N47: =IF(AND(J47<>"",ISNUMBER(G47)),M47/G47,"") | O47: =IF(OR(J47="",Parametros!$B$14>=1),"",J47/(1-Parametros!$B$14)) | P47: =IF(OR(J47="",Parametros!$B$14+Parametros!$B$18>=1),"",J47/(1-Parametros!$B$14-Parametros!$B$18)) | Q47: =IF(B47="","",IF(E47="","SIN RECETA",IF(J47="","FALTAN DATOS",IF(NOT(ISNUMBER(G47)),"FALTA PRECIO",IF(M47<0,"PIERDE",IF(N47<Parametros!$B$18,"BAJO META","OK")))))) -> SIN RECETA | R47: =IF(B47="","",IF(E47="","Elegir receta (molde).",IF(ISNA(MATCH(E47,Recetas!$A$5:$A$84,0)),"La receta no existe en Recetas.",IF(J47="","Completar la receta "&E47&": "&INDEX(Recetas!$T$5:$T$84,MATCH(E47,Recetas!$A$5:$A$84,0)),IF(NOT(ISNUMBER(G47)),"Precio de venta.",""))))) -> Elegir receta (molde).
A48: CSUBRUGSFBLAZUL | B48: CAMISETA DE RUGBY STADE FRANCAIS ANIVERSARIO (AZUL) | C48: Juego | D48: 20 | G48: 30000 | H48: Por confirmar | I48: Sin receta: elige el molde que usa, o crea la receta en "Recetas" si aún no tiene molde. | J48: =IF(OR(B48="",E48=""),"",IF(IFERROR(INDEX(Recetas!$S$5:$S$84,MATCH(E48,Recetas!$A$5:$A$84,0)),"")="","",IFERROR(INDEX(Recetas!$S$5:$S$84,MATCH(E48,Recetas!$A$5:$A$84,0)),"")+N(F48))) | K48: =IF(AND(J48<>"",ISNUMBER(G48)),G48*Parametros!$B$12,"") | L48: =IF(AND(J48<>"",ISNUMBER(G48)),G48*Parametros!$B$13,"") | M48: =IF(AND(J48<>"",ISNUMBER(G48)),G48-J48-K48-L48,"") | N48: =IF(AND(J48<>"",ISNUMBER(G48)),M48/G48,"") | O48: =IF(OR(J48="",Parametros!$B$14>=1),"",J48/(1-Parametros!$B$14)) | P48: =IF(OR(J48="",Parametros!$B$14+Parametros!$B$18>=1),"",J48/(1-Parametros!$B$14-Parametros!$B$18)) | Q48: =IF(B48="","",IF(E48="","SIN RECETA",IF(J48="","FALTAN DATOS",IF(NOT(ISNUMBER(G48)),"FALTA PRECIO",IF(M48<0,"PIERDE",IF(N48<Parametros!$B$18,"BAJO META","OK")))))) -> SIN RECETA | R48: =IF(B48="","",IF(E48="","Elegir receta (molde).",IF(ISNA(MATCH(E48,Recetas!$A$5:$A$84,0)),"La receta no existe en Recetas.",IF(J48="","Completar la receta "&E48&": "&INDEX(Recetas!$T$5:$T$84,MATCH(E48,Recetas!$A$5:$A$84,0)),IF(NOT(ISNUMBER(G48)),"Precio de venta.",""))))) -> Elegir receta (molde).
A49: MDPTLIS | B49: PETO ENTRENAMIENTO LISO | C49: Juego | D49: 20 | G49: 6000 | H49: Por confirmar | I49: Sin receta: elige el molde que usa, o crea la receta en "Recetas" si aún no tiene molde. | J49: =IF(OR(B49="",E49=""),"",IF(IFERROR(INDEX(Recetas!$S$5:$S$84,MATCH(E49,Recetas!$A$5:$A$84,0)),"")="","",IFERROR(INDEX(Recetas!$S$5:$S$84,MATCH(E49,Recetas!$A$5:$A$84,0)),"")+N(F49))) | K49: =IF(AND(J49<>"",ISNUMBER(G49)),G49*Parametros!$B$12,"") | L49: =IF(AND(J49<>"",ISNUMBER(G49)),G49*Parametros!$B$13,"") | M49: =IF(AND(J49<>"",ISNUMBER(G49)),G49-J49-K49-L49,"") | N49: =IF(AND(J49<>"",ISNUMBER(G49)),M49/G49,"") | O49: =IF(OR(J49="",Parametros!$B$14>=1),"",J49/(1-Parametros!$B$14)) | P49: =IF(OR(J49="",Parametros!$B$14+Parametros!$B$18>=1),"",J49/(1-Parametros!$B$14-Parametros!$B$18)) | Q49: =IF(B49="","",IF(E49="","SIN RECETA",IF(J49="","FALTAN DATOS",IF(NOT(ISNUMBER(G49)),"FALTA PRECIO",IF(M49<0,"PIERDE",IF(N49<Parametros!$B$18,"BAJO META","OK")))))) -> SIN RECETA | R49: =IF(B49="","",IF(E49="","Elegir receta (molde).",IF(ISNA(MATCH(E49,Recetas!$A$5:$A$84,0)),"La receta no existe en Recetas.",IF(J49="","Completar la receta "&E49&": "&INDEX(Recetas!$T$5:$T$84,MATCH(E49,Recetas!$A$5:$A$84,0)),IF(NOT(ISNUMBER(G49)),"Precio de venta.",""))))) -> Elegir receta (molde).
A50: RUNCSUBPERSM | B50: Camiseta Running Performance s/m | C50: Juego | D50: 19 | G50: 15882 | H50: Por confirmar | I50: Sin receta: elige el molde que usa, o crea la receta en "Recetas" si aún no tiene molde. | J50: =IF(OR(B50="",E50=""),"",IF(IFERROR(INDEX(Recetas!$S$5:$S$84,MATCH(E50,Recetas!$A$5:$A$84,0)),"")="","",IFERROR(INDEX(Recetas!$S$5:$S$84,MATCH(E50,Recetas!$A$5:$A$84,0)),"")+N(F50))) | K50: =IF(AND(J50<>"",ISNUMBER(G50)),G50*Parametros!$B$12,"") | L50: =IF(AND(J50<>"",ISNUMBER(G50)),G50*Parametros!$B$13,"") | M50: =IF(AND(J50<>"",ISNUMBER(G50)),G50-J50-K50-L50,"") | N50: =IF(AND(J50<>"",ISNUMBER(G50)),M50/G50,"") | O50: =IF(OR(J50="",Parametros!$B$14>=1),"",J50/(1-Parametros!$B$14)) | P50: =IF(OR(J50="",Parametros!$B$14+Parametros!$B$18>=1),"",J50/(1-Parametros!$B$14-Parametros!$B$18)) | Q50: =IF(B50="","",IF(E50="","SIN RECETA",IF(J50="","FALTAN DATOS",IF(NOT(ISNUMBER(G50)),"FALTA PRECIO",IF(M50<0,"PIERDE",IF(N50<Parametros!$B$18,"BAJO META","OK")))))) -> SIN RECETA | R50: =IF(B50="","",IF(E50="","Elegir receta (molde).",IF(ISNA(MATCH(E50,Recetas!$A$5:$A$84,0)),"La receta no existe en Recetas.",IF(J50="","Completar la receta "&E50&": "&INDEX(Recetas!$T$5:$T$84,MATCH(E50,Recetas!$A$5:$A$84,0)),IF(NOT(ISNUMBER(G50)),"Precio de venta.",""))))) -> Elegir receta (molde).
A51: SAL-BUZ-LIS-RT | B51: Pantalón Buzo Playmaker Liso Recto | C51: Salida | D51: 19 | G51: 15042 | H51: Por confirmar | I51: Sin receta: elige el molde que usa, o crea la receta en "Recetas" si aún no tiene molde. | J51: =IF(OR(B51="",E51=""),"",IF(IFERROR(INDEX(Recetas!$S$5:$S$84,MATCH(E51,Recetas!$A$5:$A$84,0)),"")="","",IFERROR(INDEX(Recetas!$S$5:$S$84,MATCH(E51,Recetas!$A$5:$A$84,0)),"")+N(F51))) | K51: =IF(AND(J51<>"",ISNUMBER(G51)),G51*Parametros!$B$12,"") | L51: =IF(AND(J51<>"",ISNUMBER(G51)),G51*Parametros!$B$13,"") | M51: =IF(AND(J51<>"",ISNUMBER(G51)),G51-J51-K51-L51,"") | N51: =IF(AND(J51<>"",ISNUMBER(G51)),M51/G51,"") | O51: =IF(OR(J51="",Parametros!$B$14>=1),"",J51/(1-Parametros!$B$14)) | P51: =IF(OR(J51="",Parametros!$B$14+Parametros!$B$18>=1),"",J51/(1-Parametros!$B$14-Parametros!$B$18)) | Q51: =IF(B51="","",IF(E51="","SIN RECETA",IF(J51="","FALTAN DATOS",IF(NOT(ISNUMBER(G51)),"FALTA PRECIO",IF(M51<0,"PIERDE",IF(N51<Parametros!$B$18,"BAJO META","OK")))))) -> SIN RECETA | R51: =IF(B51="","",IF(E51="","Elegir receta (molde).",IF(ISNA(MATCH(E51,Recetas!$A$5:$A$84,0)),"La receta no existe en Recetas.",IF(J51="","Completar la receta "&E51&": "&INDEX(Recetas!$T$5:$T$84,MATCH(E51,Recetas!$A$5:$A$84,0)),IF(NOT(ISNUMBER(G51)),"Precio de venta.",""))))) -> Elegir receta (molde).
A52: SAL-BUZ-LIS | B52: Pantalón Buzo Playmaker Liso Pitillo | C52: Salida | D52: 17 | G52: 24328 | H52: Por confirmar | I52: Sin receta: elige el molde que usa, o crea la receta en "Recetas" si aún no tiene molde. | J52: =IF(OR(B52="",E52=""),"",IF(IFERROR(INDEX(Recetas!$S$5:$S$84,MATCH(E52,Recetas!$A$5:$A$84,0)),"")="","",IFERROR(INDEX(Recetas!$S$5:$S$84,MATCH(E52,Recetas!$A$5:$A$84,0)),"")+N(F52))) | K52: =IF(AND(J52<>"",ISNUMBER(G52)),G52*Parametros!$B$12,"") | L52: =IF(AND(J52<>"",ISNUMBER(G52)),G52*Parametros!$B$13,"") | M52: =IF(AND(J52<>"",ISNUMBER(G52)),G52-J52-K52-L52,"") | N52: =IF(AND(J52<>"",ISNUMBER(G52)),M52/G52,"") | O52: =IF(OR(J52="",Parametros!$B$14>=1),"",J52/(1-Parametros!$B$14)) | P52: =IF(OR(J52="",Parametros!$B$14+Parametros!$B$18>=1),"",J52/(1-Parametros!$B$14-Parametros!$B$18)) | Q52: =IF(B52="","",IF(E52="","SIN RECETA",IF(J52="","FALTAN DATOS",IF(NOT(ISNUMBER(G52)),"FALTA PRECIO",IF(M52<0,"PIERDE",IF(N52<Parametros!$B$18,"BAJO META","OK")))))) -> SIN RECETA | R52: =IF(B52="","",IF(E52="","Elegir receta (molde).",IF(ISNA(MATCH(E52,Recetas!$A$5:$A$84,0)),"La receta no existe en Recetas.",IF(J52="","Completar la receta "&E52&": "&INDEX(Recetas!$T$5:$T$84,MATCH(E52,Recetas!$A$5:$A$84,0)),IF(NOT(ISNUMBER(G52)),"Precio de venta.",""))))) -> Elegir receta (molde).
A53: RUNCSUBPERMC | B53: Camiseta Running Performance m/c | C53: Juego | D53: 16 | G53: 15882 | H53: Por confirmar | I53: Sin receta: elige el molde que usa, o crea la receta en "Recetas" si aún no tiene molde. | J53: =IF(OR(B53="",E53=""),"",IF(IFERROR(INDEX(Recetas!$S$5:$S$84,MATCH(E53,Recetas!$A$5:$A$84,0)),"")="","",IFERROR(INDEX(Recetas!$S$5:$S$84,MATCH(E53,Recetas!$A$5:$A$84,0)),"")+N(F53))) | K53: =IF(AND(J53<>"",ISNUMBER(G53)),G53*Parametros!$B$12,"") | L53: =IF(AND(J53<>"",ISNUMBER(G53)),G53*Parametros!$B$13,"") | M53: =IF(AND(J53<>"",ISNUMBER(G53)),G53-J53-K53-L53,"") | N53: =IF(AND(J53<>"",ISNUMBER(G53)),M53/G53,"") | O53: =IF(OR(J53="",Parametros!$B$14>=1),"",J53/(1-Parametros!$B$14)) | P53: =IF(OR(J53="",Parametros!$B$14+Parametros!$B$18>=1),"",J53/(1-Parametros!$B$14-Parametros!$B$18)) | Q53: =IF(B53="","",IF(E53="","SIN RECETA",IF(J53="","FALTAN DATOS",IF(NOT(ISNUMBER(G53)),"FALTA PRECIO",IF(M53<0,"PIERDE",IF(N53<Parametros!$B$18,"BAJO META","OK")))))) -> SIN RECETA | R53: =IF(B53="","",IF(E53="","Elegir receta (molde).",IF(ISNA(MATCH(E53,Recetas!$A$5:$A$84,0)),"La receta no existe en Recetas.",IF(J53="","Completar la receta "&E53&": "&INDEX(Recetas!$T$5:$T$84,MATCH(E53,Recetas!$A$5:$A$84,0)),IF(NOT(ISNUMBER(G53)),"Precio de venta.",""))))) -> Elegir receta (molde).
A54: HCKCSUBOVA | B54: Camiseta Hockey Playmaker, Cuello Ova s/mangas | C54: Juego | D54: 15 | G54: 17563 | H54: Por confirmar | I54: Sin receta: elige el molde que usa, o crea la receta en "Recetas" si aún no tiene molde. | J54: =IF(OR(B54="",E54=""),"",IF(IFERROR(INDEX(Recetas!$S$5:$S$84,MATCH(E54,Recetas!$A$5:$A$84,0)),"")="","",IFERROR(INDEX(Recetas!$S$5:$S$84,MATCH(E54,Recetas!$A$5:$A$84,0)),"")+N(F54))) | K54: =IF(AND(J54<>"",ISNUMBER(G54)),G54*Parametros!$B$12,"") | L54: =IF(AND(J54<>"",ISNUMBER(G54)),G54*Parametros!$B$13,"") | M54: =IF(AND(J54<>"",ISNUMBER(G54)),G54-J54-K54-L54,"") | N54: =IF(AND(J54<>"",ISNUMBER(G54)),M54/G54,"") | O54: =IF(OR(J54="",Parametros!$B$14>=1),"",J54/(1-Parametros!$B$14)) | P54: =IF(OR(J54="",Parametros!$B$14+Parametros!$B$18>=1),"",J54/(1-Parametros!$B$14-Parametros!$B$18)) | Q54: =IF(B54="","",IF(E54="","SIN RECETA",IF(J54="","FALTAN DATOS",IF(NOT(ISNUMBER(G54)),"FALTA PRECIO",IF(M54<0,"PIERDE",IF(N54<Parametros!$B$18,"BAJO META","OK")))))) -> SIN RECETA | R54: =IF(B54="","",IF(E54="","Elegir receta (molde).",IF(ISNA(MATCH(E54,Recetas!$A$5:$A$84,0)),"La receta no existe en Recetas.",IF(J54="","Completar la receta "&E54&": "&INDEX(Recetas!$T$5:$T$84,MATCH(E54,Recetas!$A$5:$A$84,0)),IF(NOT(ISNUMBER(G54)),"Precio de venta.",""))))) -> Elegir receta (molde).
A55: HCK-FAL-LIS | B55: Falda Short Hockey Playmaker lisa | C55: Juego | D55: 15 | G55: 14202 | H55: Por confirmar | I55: Sin receta: elige el molde que usa, o crea la receta en "Recetas" si aún no tiene molde. | J55: =IF(OR(B55="",E55=""),"",IF(IFERROR(INDEX(Recetas!$S$5:$S$84,MATCH(E55,Recetas!$A$5:$A$84,0)),"")="","",IFERROR(INDEX(Recetas!$S$5:$S$84,MATCH(E55,Recetas!$A$5:$A$84,0)),"")+N(F55))) | K55: =IF(AND(J55<>"",ISNUMBER(G55)),G55*Parametros!$B$12,"") | L55: =IF(AND(J55<>"",ISNUMBER(G55)),G55*Parametros!$B$13,"") | M55: =IF(AND(J55<>"",ISNUMBER(G55)),G55-J55-K55-L55,"") | N55: =IF(AND(J55<>"",ISNUMBER(G55)),M55/G55,"") | O55: =IF(OR(J55="",Parametros!$B$14>=1),"",J55/(1-Parametros!$B$14)) | P55: =IF(OR(J55="",Parametros!$B$14+Parametros!$B$18>=1),"",J55/(1-Parametros!$B$14-Parametros!$B$18)) | Q55: =IF(B55="","",IF(E55="","SIN RECETA",IF(J55="","FALTAN DATOS",IF(NOT(ISNUMBER(G55)),"FALTA PRECIO",IF(M55<0,"PIERDE",IF(N55<Parametros!$B$18,"BAJO META","OK")))))) -> SIN RECETA | R55: =IF(B55="","",IF(E55="","Elegir receta (molde).",IF(ISNA(MATCH(E55,Recetas!$A$5:$A$84,0)),"La receta no existe en Recetas.",IF(J55="","Completar la receta "&E55&": "&INDEX(Recetas!$T$5:$T$84,MATCH(E55,Recetas!$A$5:$A$84,0)),IF(NOT(ISNUMBER(G55)),"Precio de venta.",""))))) -> Elegir receta (molde).
A56: MDCALLARPMK | B56: Calza larga fem Playmaker | C56: Juego | D56: 14 | G56: 11681 | H56: Por confirmar | I56: Sin receta: elige el molde que usa, o crea la receta en "Recetas" si aún no tiene molde. | J56: =IF(OR(B56="",E56=""),"",IF(IFERROR(INDEX(Recetas!$S$5:$S$84,MATCH(E56,Recetas!$A$5:$A$84,0)),"")="","",IFERROR(INDEX(Recetas!$S$5:$S$84,MATCH(E56,Recetas!$A$5:$A$84,0)),"")+N(F56))) | K56: =IF(AND(J56<>"",ISNUMBER(G56)),G56*Parametros!$B$12,"") | L56: =IF(AND(J56<>"",ISNUMBER(G56)),G56*Parametros!$B$13,"") | M56: =IF(AND(J56<>"",ISNUMBER(G56)),G56-J56-K56-L56,"") | N56: =IF(AND(J56<>"",ISNUMBER(G56)),M56/G56,"") | O56: =IF(OR(J56="",Parametros!$B$14>=1),"",J56/(1-Parametros!$B$14)) | P56: =IF(OR(J56="",Parametros!$B$14+Parametros!$B$18>=1),"",J56/(1-Parametros!$B$14-Parametros!$B$18)) | Q56: =IF(B56="","",IF(E56="","SIN RECETA",IF(J56="","FALTAN DATOS",IF(NOT(ISNUMBER(G56)),"FALTA PRECIO",IF(M56<0,"PIERDE",IF(N56<Parametros!$B$18,"BAJO META","OK")))))) -> SIN RECETA | R56: =IF(B56="","",IF(E56="","Elegir receta (molde).",IF(ISNA(MATCH(E56,Recetas!$A$5:$A$84,0)),"La receta no existe en Recetas.",IF(J56="","Completar la receta "&E56&": "&INDEX(Recetas!$T$5:$T$84,MATCH(E56,Recetas!$A$5:$A$84,0)),IF(NOT(ISNUMBER(G56)),"Precio de venta.",""))))) -> Elegir receta (molde).
A57: SAL-HOO-APSUB | B57: Polerón Hoodie Aplicación Sublim | C57: Salida | D57: 14 | G57: 31092 | H57: Por confirmar | I57: Sin receta: elige el molde que usa, o crea la receta en "Recetas" si aún no tiene molde. | J57: =IF(OR(B57="",E57=""),"",IF(IFERROR(INDEX(Recetas!$S$5:$S$84,MATCH(E57,Recetas!$A$5:$A$84,0)),"")="","",IFERROR(INDEX(Recetas!$S$5:$S$84,MATCH(E57,Recetas!$A$5:$A$84,0)),"")+N(F57))) | K57: =IF(AND(J57<>"",ISNUMBER(G57)),G57*Parametros!$B$12,"") | L57: =IF(AND(J57<>"",ISNUMBER(G57)),G57*Parametros!$B$13,"") | M57: =IF(AND(J57<>"",ISNUMBER(G57)),G57-J57-K57-L57,"") | N57: =IF(AND(J57<>"",ISNUMBER(G57)),M57/G57,"") | O57: =IF(OR(J57="",Parametros!$B$14>=1),"",J57/(1-Parametros!$B$14)) | P57: =IF(OR(J57="",Parametros!$B$14+Parametros!$B$18>=1),"",J57/(1-Parametros!$B$14-Parametros!$B$18)) | Q57: =IF(B57="","",IF(E57="","SIN RECETA",IF(J57="","FALTAN DATOS",IF(NOT(ISNUMBER(G57)),"FALTA PRECIO",IF(M57<0,"PIERDE",IF(N57<Parametros!$B$18,"BAJO META","OK")))))) -> SIN RECETA | R57: =IF(B57="","",IF(E57="","Elegir receta (molde).",IF(ISNA(MATCH(E57,Recetas!$A$5:$A$84,0)),"La receta no existe en Recetas.",IF(J57="","Completar la receta "&E57&": "&INDEX(Recetas!$T$5:$T$84,MATCH(E57,Recetas!$A$5:$A$84,0)),IF(NOT(ISNUMBER(G57)),"Precio de venta.",""))))) -> Elegir receta (molde).
A58: SAL-POL-BAS | B58: POLERON BASIC | C58: Salida | D58: 13 | G58: 17646 | H58: Por confirmar | I58: Sin receta: elige el molde que usa, o crea la receta en "Recetas" si aún no tiene molde. | J58: =IF(OR(B58="",E58=""),"",IF(IFERROR(INDEX(Recetas!$S$5:$S$84,MATCH(E58,Recetas!$A$5:$A$84,0)),"")="","",IFERROR(INDEX(Recetas!$S$5:$S$84,MATCH(E58,Recetas!$A$5:$A$84,0)),"")+N(F58))) | K58: =IF(AND(J58<>"",ISNUMBER(G58)),G58*Parametros!$B$12,"") | L58: =IF(AND(J58<>"",ISNUMBER(G58)),G58*Parametros!$B$13,"") | M58: =IF(AND(J58<>"",ISNUMBER(G58)),G58-J58-K58-L58,"") | N58: =IF(AND(J58<>"",ISNUMBER(G58)),M58/G58,"") | O58: =IF(OR(J58="",Parametros!$B$14>=1),"",J58/(1-Parametros!$B$14)) | P58: =IF(OR(J58="",Parametros!$B$14+Parametros!$B$18>=1),"",J58/(1-Parametros!$B$14-Parametros!$B$18)) | Q58: =IF(B58="","",IF(E58="","SIN RECETA",IF(J58="","FALTAN DATOS",IF(NOT(ISNUMBER(G58)),"FALTA PRECIO",IF(M58<0,"PIERDE",IF(N58<Parametros!$B$18,"BAJO META","OK")))))) -> SIN RECETA | R58: =IF(B58="","",IF(E58="","Elegir receta (molde).",IF(ISNA(MATCH(E58,Recetas!$A$5:$A$84,0)),"La receta no existe en Recetas.",IF(J58="","Completar la receta "&E58&": "&INDEX(Recetas!$T$5:$T$84,MATCH(E58,Recetas!$A$5:$A$84,0)),IF(NOT(ISNUMBER(G58)),"Precio de venta.",""))))) -> Elegir receta (molde).
... A69: RUGCSUBENTMC | B69: Camiseta de entrenamiento Rugby,m/c | C69: Juego | D69: 5 | G69: 15882 | H69: Por confirmar | I69: Sin receta: elige el molde que usa, o crea la receta en "Recetas" si aún no tiene molde. | J69: =IF(OR(B69="",E69=""),"",IF(IFERROR(INDEX(Recetas!$S$5:$S$84,MATCH(E69,Recetas!$A$5:$A$84,0)),"")="","",IFERROR(INDEX(Recetas!$S$5:$S$84,MATCH(E69,Recetas!$A$5:$A$84,0)),"")+N(F69))) | K69: =IF(AND(J69<>"",ISNUMBER(G69)),G69*Parametros!$B$12,"") | L69: =IF(AND(J69<>"",ISNUMBER(G69)),G69*Parametros!$B$13,"") | M69: =IF(AND(J69<>"",ISNUMBER(G69)),G69-J69-K69-L69,"") | N69: =IF(AND(J69<>"",ISNUMBER(G69)),M69/G69,"") | O69: =IF(OR(J69="",Parametros!$B$14>=1),"",J69/(1-Parametros!$B$14)) | P69: =IF(OR(J69="",Parametros!$B$14+Parametros!$B$18>=1),"",J69/(1-Parametros!$B$14-Parametros!$B$18)) | Q69: =IF(B69="","",IF(E69="","SIN RECETA",IF(J69="","FALTAN DATOS",IF(NOT(ISNUMBER(G69)),"FALTA PRECIO",IF(M69<0,"PIERDE",IF(N69<Parametros!$B$18,"BAJO META","OK")))))) -> SIN RECETA | R69: =IF(B69="","",IF(E69="","Elegir receta (molde).",IF(ISNA(MATCH(E69,Recetas!$A$5:$A$84,0)),"La receta no existe en Recetas.",IF(J69="","Completar la receta "&E69&": "&INDEX(Recetas!$T$5:$T$84,MATCH(E69,Recetas!$A$5:$A$84,0)),IF(NOT(ISNUMBER(G69)),"Precio de venta.",""))))) -> Elegir receta (molde).
A70: MDCALCORPMK | B70: Calza corta fem Playmaker | C70: Juego | D70: 4 | E70: SM-04 · Calza Vóley | G70: 12689 | H70: Por confirmar | J70: =IF(OR(B70="",E70=""),"",IF(IFERROR(INDEX(Recetas!$S$5:$S$84,MATCH(E70,Recetas!$A$5:$A$84,0)),"")="","",IFERROR(INDEX(Recetas!$S$5:$S$84,MATCH(E70,Recetas!$A$5:$A$84,0)),"")+N(F70))) | K70: =IF(AND(J70<>"",ISNUMBER(G70)),G70*Parametros!$B$12,"") | L70: =IF(AND(J70<>"",ISNUMBER(G70)),G70*Parametros!$B$13,"") | M70: =IF(AND(J70<>"",ISNUMBER(G70)),G70-J70-K70-L70,"") | N70: =IF(AND(J70<>"",ISNUMBER(G70)),M70/G70,"") | O70: =IF(OR(J70="",Parametros!$B$14>=1),"",J70/(1-Parametros!$B$14)) | P70: =IF(OR(J70="",Parametros!$B$14+Parametros!$B$18>=1),"",J70/(1-Parametros!$B$14-Parametros!$B$18)) | Q70: =IF(B70="","",IF(E70="","SIN RECETA",IF(J70="","FALTAN DATOS",IF(NOT(ISNUMBER(G70)),"FALTA PRECIO",IF(M70<0,"PIERDE",IF(N70<Parametros!$B$18,"BAJO META","OK")))))) -> FALTAN DATOS | R70: =IF(B70="","",IF(E70="","Elegir receta (molde).",IF(ISNA(MATCH(E70,Recetas!$A$5:$A$84,0)),"La receta no existe en Recetas.",IF(J70="","Completar la receta "&E70&": "&INDEX(Recetas!$T$5:$T$84,MATCH(E70,Recetas!$A$5:$A$84,0)),IF(NOT(ISNUMBER(G70)),"Precio de venta.",""))))) -> Completar la receta SM-04 · Calza Vóley: Tela sin precio.
A71: SAL-SHO-LIS | B71: Short Salida con bolsillos | C71: Salida | D71: 4 | G71: 13445 | H71: Por confirmar | I71: Sin receta: elige el molde que usa, o crea la receta en "Recetas" si aún no tiene molde. | J71: =IF(OR(B71="",E71=""),"",IF(IFERROR(INDEX(Recetas!$S$5:$S$84,MATCH(E71,Recetas!$A$5:$A$84,0)),"")="","",IFERROR(INDEX(Recetas!$S$5:$S$84,MATCH(E71,Recetas!$A$5:$A$84,0)),"")+N(F71))) | K71: =IF(AND(J71<>"",ISNUMBER(G71)),G71*Parametros!$B$12,"") | L71: =IF(AND(J71<>"",ISNUMBER(G71)),G71*Parametros!$B$13,"") | M71: =IF(AND(J71<>"",ISNUMBER(G71)),G71-J71-K71-L71,"") | N71: =IF(AND(J71<>"",ISNUMBER(G71)),M71/G71,"") | O71: =IF(OR(J71="",Parametros!$B$14>=1),"",J71/(1-Parametros!$B$14)) | P71: =IF(OR(J71="",Parametros!$B$14+Parametros!$B$18>=1),"",J71/(1-Parametros!$B$14-Parametros!$B$18)) | Q71: =IF(B71="","",IF(E71="","SIN RECETA",IF(J71="","FALTAN DATOS",IF(NOT(ISNUMBER(G71)),"FALTA PRECIO",IF(M71<0,"PIERDE",IF(N71<Parametros!$B$18,"BAJO META","OK")))))) -> SIN RECETA | R71: =IF(B71="","",IF(E71="","Elegir receta (molde).",IF(ISNA(MATCH(E71,Recetas!$A$5:$A$84,0)),"La receta no existe en Recetas.",IF(J71="","Completar la receta "&E71&": "&INDEX(Recetas!$T$5:$T$84,MATCH(E71,Recetas!$A$5:$A$84,0)),IF(NOT(ISNUMBER(G71)),"Precio de venta.",""))))) -> Elegir receta (molde).
A72: ENT-POL-MANSUBL | B72: POLERON DE ENTRENAMIENTO MANGAS SUBLIMADAS MASC | C72: Salida | D72: 4 | G72: 30168 | H72: Por confirmar | I72: Sin receta: elige el molde que usa, o crea la receta en "Recetas" si aún no tiene molde. | J72: =IF(OR(B72="",E72=""),"",IF(IFERROR(INDEX(Recetas!$S$5:$S$84,MATCH(E72,Recetas!$A$5:$A$84,0)),"")="","",IFERROR(INDEX(Recetas!$S$5:$S$84,MATCH(E72,Recetas!$A$5:$A$84,0)),"")+N(F72))) | K72: =IF(AND(J72<>"",ISNUMBER(G72)),G72*Parametros!$B$12,"") | L72: =IF(AND(J72<>"",ISNUMBER(G72)),G72*Parametros!$B$13,"") | M72: =IF(AND(J72<>"",ISNUMBER(G72)),G72-J72-K72-L72,"") | N72: =IF(AND(J72<>"",ISNUMBER(G72)),M72/G72,"") | O72: =IF(OR(J72="",Parametros!$B$14>=1),"",J72/(1-Parametros!$B$14)) | P72: =IF(OR(J72="",Parametros!$B$14+Parametros!$B$18>=1),"",J72/(1-Parametros!$B$14-Parametros!$B$18)) | Q72: =IF(B72="","",IF(E72="","SIN RECETA",IF(J72="","FALTAN DATOS",IF(NOT(ISNUMBER(G72)),"FALTA PRECIO",IF(M72<0,"PIERDE",IF(N72<Parametros!$B$18,"BAJO META","OK")))))) -> SIN RECETA | R72: =IF(B72="","",IF(E72="","Elegir receta (molde).",IF(ISNA(MATCH(E72,Recetas!$A$5:$A$84,0)),"La receta no existe en Recetas.",IF(J72="","Completar la receta "&E72&": "&INDEX(Recetas!$T$5:$T$84,MATCH(E72,Recetas!$A$5:$A$84,0)),IF(NOT(ISNUMBER(G72)),"Precio de venta.",""))))) -> Elegir receta (molde).
A73: VOLMASC-CSUB-V-CER | B73: Camiseta Voley masc Playmaker, V m/cero | C73: Juego | D73: 3 | G73: 16723 | H73: Por confirmar | I73: Sin receta: elige el molde que usa, o crea la receta en "Recetas" si aún no tiene molde. | J73: =IF(OR(B73="",E73=""),"",IF(IFERROR(INDEX(Recetas!$S$5:$S$84,MATCH(E73,Recetas!$A$5:$A$84,0)),"")="","",IFERROR(INDEX(Recetas!$S$5:$S$84,MATCH(E73,Recetas!$A$5:$A$84,0)),"")+N(F73))) | K73: =IF(AND(J73<>"",ISNUMBER(G73)),G73*Parametros!$B$12,"") | L73: =IF(AND(J73<>"",ISNUMBER(G73)),G73*Parametros!$B$13,"") | M73: =IF(AND(J73<>"",ISNUMBER(G73)),G73-J73-K73-L73,"") | N73: =IF(AND(J73<>"",ISNUMBER(G73)),M73/G73,"") | O73: =IF(OR(J73="",Parametros!$B$14>=1),"",J73/(1-Parametros!$B$14)) | P73: =IF(OR(J73="",Parametros!$B$14+Parametros!$B$18>=1),"",J73/(1-Parametros!$B$14-Parametros!$B$18)) | Q73: =IF(B73="","",IF(E73="","SIN RECETA",IF(J73="","FALTAN DATOS",IF(NOT(ISNUMBER(G73)),"FALTA PRECIO",IF(M73<0,"PIERDE",IF(N73<Parametros!$B$18,"BAJO META","OK")))))) -> SIN RECETA | R73: =IF(B73="","",IF(E73="","Elegir receta (molde).",IF(ISNA(MATCH(E73,Recetas!$A$5:$A$84,0)),"La receta no existe en Recetas.",IF(J73="","Completar la receta "&E73&": "&INDEX(Recetas!$T$5:$T$84,MATCH(E73,Recetas!$A$5:$A$84,0)),IF(NOT(ISNUMBER(G73)),"Precio de venta.",""))))) -> Elegir receta (molde).
A74: SAL-POL-MGSUB | B74: Polerón Entrenamiento liso con mangas Sublim | C74: Salida | D74: 2 | G74: 27647 | H74: Por confirmar | I74: Sin receta: elige el molde que usa, o crea la receta en "Recetas" si aún no tiene molde. | J74: =IF(OR(B74="",E74=""),"",IF(IFERROR(INDEX(Recetas!$S$5:$S$84,MATCH(E74,Recetas!$A$5:$A$84,0)),"")="","",IFERROR(INDEX(Recetas!$S$5:$S$84,MATCH(E74,Recetas!$A$5:$A$84,0)),"")+N(F74))) | K74: =IF(AND(J74<>"",ISNUMBER(G74)),G74*Parametros!$B$12,"") | L74: =IF(AND(J74<>"",ISNUMBER(G74)),G74*Parametros!$B$13,"") | M74: =IF(AND(J74<>"",ISNUMBER(G74)),G74-J74-K74-L74,"") | N74: =IF(AND(J74<>"",ISNUMBER(G74)),M74/G74,"") | O74: =IF(OR(J74="",Parametros!$B$14>=1),"",J74/(1-Parametros!$B$14)) | P74: =IF(OR(J74="",Parametros!$B$14+Parametros!$B$18>=1),"",J74/(1-Parametros!$B$14-Parametros!$B$18)) | Q74: =IF(B74="","",IF(E74="","SIN RECETA",IF(J74="","FALTAN DATOS",IF(NOT(ISNUMBER(G74)),"FALTA PRECIO",IF(M74<0,"PIERDE",IF(N74<Parametros!$B$18,"BAJO META","OK")))))) -> SIN RECETA | R74: =IF(B74="","",IF(E74="","Elegir receta (molde).",IF(ISNA(MATCH(E74,Recetas!$A$5:$A$84,0)),"La receta no existe en Recetas.",IF(J74="","Completar la receta "&E74&": "&INDEX(Recetas!$T$5:$T$84,MATCH(E74,Recetas!$A$5:$A$84,0)),IF(NOT(ISNUMBER(G74)),"Precio de venta.",""))))) -> Elegir receta (molde).
A75: VOLMASC-CSUBPRO-V-MC | B75: Camiseta Voley masc Pro Playmaker, V m/c | C75: Juego | D75: 1 | G75: 19244 | H75: Por confirmar | I75: Sin receta: elige el molde que usa, o crea la receta en "Recetas" si aún no tiene molde. | J75: =IF(OR(B75="",E75=""),"",IF(IFERROR(INDEX(Recetas!$S$5:$S$84,MATCH(E75,Recetas!$A$5:$A$84,0)),"")="","",IFERROR(INDEX(Recetas!$S$5:$S$84,MATCH(E75,Recetas!$A$5:$A$84,0)),"")+N(F75))) | K75: =IF(AND(J75<>"",ISNUMBER(G75)),G75*Parametros!$B$12,"") | L75: =IF(AND(J75<>"",ISNUMBER(G75)),G75*Parametros!$B$13,"") | M75: =IF(AND(J75<>"",ISNUMBER(G75)),G75-J75-K75-L75,"") | N75: =IF(AND(J75<>"",ISNUMBER(G75)),M75/G75,"") | O75: =IF(OR(J75="",Parametros!$B$14>=1),"",J75/(1-Parametros!$B$14)) | P75: =IF(OR(J75="",Parametros!$B$14+Parametros!$B$18>=1),"",J75/(1-Parametros!$B$14-Parametros!$B$18)) | Q75: =IF(B75="","",IF(E75="","SIN RECETA",IF(J75="","FALTAN DATOS",IF(NOT(ISNUMBER(G75)),"FALTA PRECIO",IF(M75<0,"PIERDE",IF(N75<Parametros!$B$18,"BAJO META","OK")))))) -> SIN RECETA | R75: =IF(B75="","",IF(E75="","Elegir receta (molde).",IF(ISNA(MATCH(E75,Recetas!$A$5:$A$84,0)),"La receta no existe en Recetas.",IF(J75="","Completar la receta "&E75&": "&INDEX(Recetas!$T$5:$T$84,MATCH(E75,Recetas!$A$5:$A$84,0)),IF(NOT(ISNUMBER(G75)),"Precio de venta.",""))))) -> Elegir receta (molde).
A76: RUG-CSUB-POL | B76: Camiseta Rugby Playmaker, Polo | C76: Juego | D76: 1 | G76: 20084 | H76: Por confirmar | I76: Sin receta: elige el molde que usa, o crea la receta en "Recetas" si aún no tiene molde. | J76: =IF(OR(B76="",E76=""),"",IF(IFERROR(INDEX(Recetas!$S$5:$S$84,MATCH(E76,Recetas!$A$5:$A$84,0)),"")="","",IFERROR(INDEX(Recetas!$S$5:$S$84,MATCH(E76,Recetas!$A$5:$A$84,0)),"")+N(F76))) | K76: =IF(AND(J76<>"",ISNUMBER(G76)),G76*Parametros!$B$12,"") | L76: =IF(AND(J76<>"",ISNUMBER(G76)),G76*Parametros!$B$13,"") | M76: =IF(AND(J76<>"",ISNUMBER(G76)),G76-J76-K76-L76,"") | N76: =IF(AND(J76<>"",ISNUMBER(G76)),M76/G76,"") | O76: =IF(OR(J76="",Parametros!$B$14>=1),"",J76/(1-Parametros!$B$14)) | P76: =IF(OR(J76="",Parametros!$B$14+Parametros!$B$18>=1),"",J76/(1-Parametros!$B$14-Parametros!$B$18)) | Q76: =IF(B76="","",IF(E76="","SIN RECETA",IF(J76="","FALTAN DATOS",IF(NOT(ISNUMBER(G76)),"FALTA PRECIO",IF(M76<0,"PIERDE",IF(N76<Parametros!$B$18,"BAJO META","OK")))))) -> SIN RECETA | R76: =IF(B76="","",IF(E76="","Elegir receta (molde).",IF(ISNA(MATCH(E76,Recetas!$A$5:$A$84,0)),"La receta no existe en Recetas.",IF(J76="","Completar la receta "&E76&": "&INDEX(Recetas!$T$5:$T$84,MATCH(E76,Recetas!$A$5:$A$84,0)),IF(NOT(ISNUMBER(G76)),"Precio de venta.",""))))) -> Elegir receta (molde).
A77: LZO-2 | B77: Lienzo 1.5x2 | C77: Juego | D77: 1 | G77: 21765 | H77: Por confirmar | I77: Sin receta: elige el molde que usa, o crea la receta en "Recetas" si aún no tiene molde. | J77: =IF(OR(B77="",E77=""),"",IF(IFERROR(INDEX(Recetas!$S$5:$S$84,MATCH(E77,Recetas!$A$5:$A$84,0)),"")="","",IFERROR(INDEX(Recetas!$S$5:$S$84,MATCH(E77,Recetas!$A$5:$A$84,0)),"")+N(F77))) | K77: =IF(AND(J77<>"",ISNUMBER(G77)),G77*Parametros!$B$12,"") | L77: =IF(AND(J77<>"",ISNUMBER(G77)),G77*Parametros!$B$13,"") | M77: =IF(AND(J77<>"",ISNUMBER(G77)),G77-J77-K77-L77,"") | N77: =IF(AND(J77<>"",ISNUMBER(G77)),M77/G77,"") | O77: =IF(OR(J77="",Parametros!$B$14>=1),"",J77/(1-Parametros!$B$14)) | P77: =IF(OR(J77="",Parametros!$B$14+Parametros!$B$18>=1),"",J77/(1-Parametros!$B$14-Parametros!$B$18)) | Q77: =IF(B77="","",IF(E77="","SIN RECETA",IF(J77="","FALTAN DATOS",IF(NOT(ISNUMBER(G77)),"FALTA PRECIO",IF(M77<0,"PIERDE",IF(N77<Parametros!$B$18,"BAJO META","OK")))))) -> SIN RECETA | R77: =IF(B77="","",IF(E77="","Elegir receta (molde).",IF(ISNA(MATCH(E77,Recetas!$A$5:$A$84,0)),"La receta no existe en Recetas.",IF(J77="","Completar la receta "&E77&": "&INDEX(Recetas!$T$5:$T$84,MATCH(E77,Recetas!$A$5:$A$84,0)),IF(NOT(ISNUMBER(G77)),"Precio de venta.",""))))) -> Elegir receta (molde).
A78: FUTJINSUB | B78: Jineta de Capitán Subl | C78: Juego | D78: 1 | G78: 11681 | H78: Por confirmar | I78: Sin receta: elige el molde que usa, o crea la receta en "Recetas" si aún no tiene molde. | J78: =IF(OR(B78="",E78=""),"",IF(IFERROR(INDEX(Recetas!$S$5:$S$84,MATCH(E78,Recetas!$A$5:$A$84,0)),"")="","",IFERROR(INDEX(Recetas!$S$5:$S$84,MATCH(E78,Recetas!$A$5:$A$84,0)),"")+N(F78))) | K78: =IF(AND(J78<>"",ISNUMBER(G78)),G78*Parametros!$B$12,"") | L78: =IF(AND(J78<>"",ISNUMBER(G78)),G78*Parametros!$B$13,"") | M78: =IF(AND(J78<>"",ISNUMBER(G78)),G78-J78-K78-L78,"") | N78: =IF(AND(J78<>"",ISNUMBER(G78)),M78/G78,"") | O78: =IF(OR(J78="",Parametros!$B$14>=1),"",J78/(1-Parametros!$B$14)) | P78: =IF(OR(J78="",Parametros!$B$14+Parametros!$B$18>=1),"",J78/(1-Parametros!$B$14-Parametros!$B$18)) | Q78: =IF(B78="","",IF(E78="","SIN RECETA",IF(J78="","FALTAN DATOS",IF(NOT(ISNUMBER(G78)),"FALTA PRECIO",IF(M78<0,"PIERDE",IF(N78<Parametros!$B$18,"BAJO META","OK")))))) -> SIN RECETA | R78: =IF(B78="","",IF(E78="","Elegir receta (molde).",IF(ISNA(MATCH(E78,Recetas!$A$5:$A$84,0)),"La receta no existe en Recetas.",IF(J78="","Completar la receta "&E78&": "&INDEX(Recetas!$T$5:$T$84,MATCH(E78,Recetas!$A$5:$A$84,0)),IF(NOT(ISNUMBER(G78)),"Precio de venta.",""))))) -> Elegir receta (molde).
A79: SAL-POL-ALG-LIS | B79: POLERÓN ALGODÓN CON CAPUCHA PMK | C79: Salida | D79: 1 | G79: 21765 | H79: Por confirmar | I79: Sin receta: elige el molde que usa, o crea la receta en "Recetas" si aún no tiene molde. | J79: =IF(OR(B79="",E79=""),"",IF(IFERROR(INDEX(Recetas!$S$5:$S$84,MATCH(E79,Recetas!$A$5:$A$84,0)),"")="","",IFERROR(INDEX(Recetas!$S$5:$S$84,MATCH(E79,Recetas!$A$5:$A$84,0)),"")+N(F79))) | K79: =IF(AND(J79<>"",ISNUMBER(G79)),G79*Parametros!$B$12,"") | L79: =IF(AND(J79<>"",ISNUMBER(G79)),G79*Parametros!$B$13,"") | M79: =IF(AND(J79<>"",ISNUMBER(G79)),G79-J79-K79-L79,"") | N79: =IF(AND(J79<>"",ISNUMBER(G79)),M79/G79,"") | O79: =IF(OR(J79="",Parametros!$B$14>=1),"",J79/(1-Parametros!$B$14)) | P79: =IF(OR(J79="",Parametros!$B$14+Parametros!$B$18>=1),"",J79/(1-Parametros!$B$14-Parametros!$B$18)) | Q79: =IF(B79="","",IF(E79="","SIN RECETA",IF(J79="","FALTAN DATOS",IF(NOT(ISNUMBER(G79)),"FALTA PRECIO",IF(M79<0,"PIERDE",IF(N79<Parametros!$B$18,"BAJO META","OK")))))) -> SIN RECETA | R79: =IF(B79="","",IF(E79="","Elegir receta (molde).",IF(ISNA(MATCH(E79,Recetas!$A$5:$A$84,0)),"La receta no existe en Recetas.",IF(J79="","Completar la receta "&E79&": "&INDEX(Recetas!$T$5:$T$84,MATCH(E79,Recetas!$A$5:$A$84,0)),IF(NOT(ISNUMBER(G79)),"Precio de venta.",""))))) -> Elegir receta (molde).
J80: =IF(OR(B80="",E80=""),"",IF(IFERROR(INDEX(Recetas!$S$5:$S$84,MATCH(E80,Recetas!$A$5:$A$84,0)),"")="","",IFERROR(INDEX(Recetas!$S$5:$S$84,MATCH(E80,Recetas!$A$5:$A$84,0)),"")+N(F80))) | K80: =IF(AND(J80<>"",ISNUMBER(G80)),G80*Parametros!$B$12,"") | L80: =IF(AND(J80<>"",ISNUMBER(G80)),G80*Parametros!$B$13,"") | M80: =IF(AND(J80<>"",ISNUMBER(G80)),G80-J80-K80-L80,"") | N80: =IF(AND(J80<>"",ISNUMBER(G80)),M80/G80,"") | O80: =IF(OR(J80="",Parametros!$B$14>=1),"",J80/(1-Parametros!$B$14)) | P80: =IF(OR(J80="",Parametros!$B$14+Parametros!$B$18>=1),"",J80/(1-Parametros!$B$14-Parametros!$B$18)) | Q80: =IF(B80="","",IF(E80="","SIN RECETA",IF(J80="","FALTAN DATOS",IF(NOT(ISNUMBER(G80)),"FALTA PRECIO",IF(M80<0,"PIERDE",IF(N80<Parametros!$B$18,"BAJO META","OK")))))) | R80: =IF(B80="","",IF(E80="","Elegir receta (molde).",IF(ISNA(MATCH(E80,Recetas!$A$5:$A$84,0)),"La receta no existe en Recetas.",IF(J80="","Completar la receta "&E80&": "&INDEX(Recetas!$T$5:$T$84,MATCH(E80,Recetas!$A$5:$A$84,0)),IF(NOT(ISNUMBER(G80)),"Precio de venta.","")))))
J81: =IF(OR(B81="",E81=""),"",IF(IFERROR(INDEX(Recetas!$S$5:$S$84,MATCH(E81,Recetas!$A$5:$A$84,0)),"")="","",IFERROR(INDEX(Recetas!$S$5:$S$84,MATCH(E81,Recetas!$A$5:$A$84,0)),"")+N(F81))) | K81: =IF(AND(J81<>"",ISNUMBER(G81)),G81*Parametros!$B$12,"") | L81: =IF(AND(J81<>"",ISNUMBER(G81)),G81*Parametros!$B$13,"") | M81: =IF(AND(J81<>"",ISNUMBER(G81)),G81-J81-K81-L81,"") | N81: =IF(AND(J81<>"",ISNUMBER(G81)),M81/G81,"") | O81: =IF(OR(J81="",Parametros!$B$14>=1),"",J81/(1-Parametros!$B$14)) | P81: =IF(OR(J81="",Parametros!$B$14+Parametros!$B$18>=1),"",J81/(1-Parametros!$B$14-Parametros!$B$18)) | Q81: =IF(B81="","",IF(E81="","SIN RECETA",IF(J81="","FALTAN DATOS",IF(NOT(ISNUMBER(G81)),"FALTA PRECIO",IF(M81<0,"PIERDE",IF(N81<Parametros!$B$18,"BAJO META","OK")))))) | R81: =IF(B81="","",IF(E81="","Elegir receta (molde).",IF(ISNA(MATCH(E81,Recetas!$A$5:$A$84,0)),"La receta no existe en Recetas.",IF(J81="","Completar la receta "&E81&": "&INDEX(Recetas!$T$5:$T$84,MATCH(E81,Recetas!$A$5:$A$84,0)),IF(NOT(ISNUMBER(G81)),"Precio de venta.","")))))
J82: =IF(OR(B82="",E82=""),"",IF(IFERROR(INDEX(Recetas!$S$5:$S$84,MATCH(E82,Recetas!$A$5:$A$84,0)),"")="","",IFERROR(INDEX(Recetas!$S$5:$S$84,MATCH(E82,Recetas!$A$5:$A$84,0)),"")+N(F82))) | K82: =IF(AND(J82<>"",ISNUMBER(G82)),G82*Parametros!$B$12,"") | L82: =IF(AND(J82<>"",ISNUMBER(G82)),G82*Parametros!$B$13,"") | M82: =IF(AND(J82<>"",ISNUMBER(G82)),G82-J82-K82-L82,"") | N82: =IF(AND(J82<>"",ISNUMBER(G82)),M82/G82,"") | O82: =IF(OR(J82="",Parametros!$B$14>=1),"",J82/(1-Parametros!$B$14)) | P82: =IF(OR(J82="",Parametros!$B$14+Parametros!$B$18>=1),"",J82/(1-Parametros!$B$14-Parametros!$B$18)) | Q82: =IF(B82="","",IF(E82="","SIN RECETA",IF(J82="","FALTAN DATOS",IF(NOT(ISNUMBER(G82)),"FALTA PRECIO",IF(M82<0,"PIERDE",IF(N82<Parametros!$B$18,"BAJO META","OK")))))) | R82: =IF(B82="","",IF(E82="","Elegir receta (molde).",IF(ISNA(MATCH(E82,Recetas!$A$5:$A$84,0)),"La receta no existe en Recetas.",IF(J82="","Completar la receta "&E82&": "&INDEX(Recetas!$T$5:$T$84,MATCH(E82,Recetas!$A$5:$A$84,0)),IF(NOT(ISNUMBER(G82)),"Precio de venta.","")))))
J83: =IF(OR(B83="",E83=""),"",IF(IFERROR(INDEX(Recetas!$S$5:$S$84,MATCH(E83,Recetas!$A$5:$A$84,0)),"")="","",IFERROR(INDEX(Recetas!$S$5:$S$84,MATCH(E83,Recetas!$A$5:$A$84,0)),"")+N(F83))) | K83: =IF(AND(J83<>"",ISNUMBER(G83)),G83*Parametros!$B$12,"") | L83: =IF(AND(J83<>"",ISNUMBER(G83)),G83*Parametros!$B$13,"") | M83: =IF(AND(J83<>"",ISNUMBER(G83)),G83-J83-K83-L83,"") | N83: =IF(AND(J83<>"",ISNUMBER(G83)),M83/G83,"") | O83: =IF(OR(J83="",Parametros!$B$14>=1),"",J83/(1-Parametros!$B$14)) | P83: =IF(OR(J83="",Parametros!$B$14+Parametros!$B$18>=1),"",J83/(1-Parametros!$B$14-Parametros!$B$18)) | Q83: =IF(B83="","",IF(E83="","SIN RECETA",IF(J83="","FALTAN DATOS",IF(NOT(ISNUMBER(G83)),"FALTA PRECIO",IF(M83<0,"PIERDE",IF(N83<Parametros!$B$18,"BAJO META","OK")))))) | R83: =IF(B83="","",IF(E83="","Elegir receta (molde).",IF(ISNA(MATCH(E83,Recetas!$A$5:$A$84,0)),"La receta no existe en Recetas.",IF(J83="","Completar la receta "&E83&": "&INDEX(Recetas!$T$5:$T$84,MATCH(E83,Recetas!$A$5:$A$84,0)),IF(NOT(ISNUMBER(G83)),"Precio de venta.","")))))
J84: =IF(OR(B84="",E84=""),"",IF(IFERROR(INDEX(Recetas!$S$5:$S$84,MATCH(E84,Recetas!$A$5:$A$84,0)),"")="","",IFERROR(INDEX(Recetas!$S$5:$S$84,MATCH(E84,Recetas!$A$5:$A$84,0)),"")+N(F84))) | K84: =IF(AND(J84<>"",ISNUMBER(G84)),G84*Parametros!$B$12,"") | L84: =IF(AND(J84<>"",ISNUMBER(G84)),G84*Parametros!$B$13,"") | M84: =IF(AND(J84<>"",ISNUMBER(G84)),G84-J84-K84-L84,"") | N84: =IF(AND(J84<>"",ISNUMBER(G84)),M84/G84,"") | O84: =IF(OR(J84="",Parametros!$B$14>=1),"",J84/(1-Parametros!$B$14)) | P84: =IF(OR(J84="",Parametros!$B$14+Parametros!$B$18>=1),"",J84/(1-Parametros!$B$14-Parametros!$B$18)) | Q84: =IF(B84="","",IF(E84="","SIN RECETA",IF(J84="","FALTAN DATOS",IF(NOT(ISNUMBER(G84)),"FALTA PRECIO",IF(M84<0,"PIERDE",IF(N84<Parametros!$B$18,"BAJO META","OK")))))) | R84: =IF(B84="","",IF(E84="","Elegir receta (molde).",IF(ISNA(MATCH(E84,Recetas!$A$5:$A$84,0)),"La receta no existe en Recetas.",IF(J84="","Completar la receta "&E84&": "&INDEX(Recetas!$T$5:$T$84,MATCH(E84,Recetas!$A$5:$A$84,0)),IF(NOT(ISNUMBER(G84)),"Precio de venta.","")))))
J85: =IF(OR(B85="",E85=""),"",IF(IFERROR(INDEX(Recetas!$S$5:$S$84,MATCH(E85,Recetas!$A$5:$A$84,0)),"")="","",IFERROR(INDEX(Recetas!$S$5:$S$84,MATCH(E85,Recetas!$A$5:$A$84,0)),"")+N(F85))) | K85: =IF(AND(J85<>"",ISNUMBER(G85)),G85*Parametros!$B$12,"") | L85: =IF(AND(J85<>"",ISNUMBER(G85)),G85*Parametros!$B$13,"") | M85: =IF(AND(J85<>"",ISNUMBER(G85)),G85-J85-K85-L85,"") | N85: =IF(AND(J85<>"",ISNUMBER(G85)),M85/G85,"") | O85: =IF(OR(J85="",Parametros!$B$14>=1),"",J85/(1-Parametros!$B$14)) | P85: =IF(OR(J85="",Parametros!$B$14+Parametros!$B$18>=1),"",J85/(1-Parametros!$B$14-Parametros!$B$18)) | Q85: =IF(B85="","",IF(E85="","SIN RECETA",IF(J85="","FALTAN DATOS",IF(NOT(ISNUMBER(G85)),"FALTA PRECIO",IF(M85<0,"PIERDE",IF(N85<Parametros!$B$18,"BAJO META","OK")))))) | R85: =IF(B85="","",IF(E85="","Elegir receta (molde).",IF(ISNA(MATCH(E85,Recetas!$A$5:$A$84,0)),"La receta no existe en Recetas.",IF(J85="","Completar la receta "&E85&": "&INDEX(Recetas!$T$5:$T$84,MATCH(E85,Recetas!$A$5:$A$84,0)),IF(NOT(ISNUMBER(G85)),"Precio de venta.","")))))
J86: =IF(OR(B86="",E86=""),"",IF(IFERROR(INDEX(Recetas!$S$5:$S$84,MATCH(E86,Recetas!$A$5:$A$84,0)),"")="","",IFERROR(INDEX(Recetas!$S$5:$S$84,MATCH(E86,Recetas!$A$5:$A$84,0)),"")+N(F86))) | K86: =IF(AND(J86<>"",ISNUMBER(G86)),G86*Parametros!$B$12,"") | L86: =IF(AND(J86<>"",ISNUMBER(G86)),G86*Parametros!$B$13,"") | M86: =IF(AND(J86<>"",ISNUMBER(G86)),G86-J86-K86-L86,"") | N86: =IF(AND(J86<>"",ISNUMBER(G86)),M86/G86,"") | O86: =IF(OR(J86="",Parametros!$B$14>=1),"",J86/(1-Parametros!$B$14)) | P86: =IF(OR(J86="",Parametros!$B$14+Parametros!$B$18>=1),"",J86/(1-Parametros!$B$14-Parametros!$B$18)) | Q86: =IF(B86="","",IF(E86="","SIN RECETA",IF(J86="","FALTAN DATOS",IF(NOT(ISNUMBER(G86)),"FALTA PRECIO",IF(M86<0,"PIERDE",IF(N86<Parametros!$B$18,"BAJO META","OK")))))) | R86: =IF(B86="","",IF(E86="","Elegir receta (molde).",IF(ISNA(MATCH(E86,Recetas!$A$5:$A$84,0)),"La receta no existe en Recetas.",IF(J86="","Completar la receta "&E86&": "&INDEX(Recetas!$T$5:$T$84,MATCH(E86,Recetas!$A$5:$A$84,0)),IF(NOT(ISNUMBER(G86)),"Precio de venta.","")))))
J87: =IF(OR(B87="",E87=""),"",IF(IFERROR(INDEX(Recetas!$S$5:$S$84,MATCH(E87,Recetas!$A$5:$A$84,0)),"")="","",IFERROR(INDEX(Recetas!$S$5:$S$84,MATCH(E87,Recetas!$A$5:$A$84,0)),"")+N(F87))) | K87: =IF(AND(J87<>"",ISNUMBER(G87)),G87*Parametros!$B$12,"") | L87: =IF(AND(J87<>"",ISNUMBER(G87)),G87*Parametros!$B$13,"") | M87: =IF(AND(J87<>"",ISNUMBER(G87)),G87-J87-K87-L87,"") | N87: =IF(AND(J87<>"",ISNUMBER(G87)),M87/G87,"") | O87: =IF(OR(J87="",Parametros!$B$14>=1),"",J87/(1-Parametros!$B$14)) | P87: =IF(OR(J87="",Parametros!$B$14+Parametros!$B$18>=1),"",J87/(1-Parametros!$B$14-Parametros!$B$18)) | Q87: =IF(B87="","",IF(E87="","SIN RECETA",IF(J87="","FALTAN DATOS",IF(NOT(ISNUMBER(G87)),"FALTA PRECIO",IF(M87<0,"PIERDE",IF(N87<Parametros!$B$18,"BAJO META","OK")))))) | R87: =IF(B87="","",IF(E87="","Elegir receta (molde).",IF(ISNA(MATCH(E87,Recetas!$A$5:$A$84,0)),"La receta no existe en Recetas.",IF(J87="","Completar la receta "&E87&": "&INDEX(Recetas!$T$5:$T$84,MATCH(E87,Recetas!$A$5:$A$84,0)),IF(NOT(ISNUMBER(G87)),"Precio de venta.","")))))
J88: =IF(OR(B88="",E88=""),"",IF(IFERROR(INDEX(Recetas!$S$5:$S$84,MATCH(E88,Recetas!$A$5:$A$84,0)),"")="","",IFERROR(INDEX(Recetas!$S$5:$S$84,MATCH(E88,Recetas!$A$5:$A$84,0)),"")+N(F88))) | K88: =IF(AND(J88<>"",ISNUMBER(G88)),G88*Parametros!$B$12,"") | L88: =IF(AND(J88<>"",ISNUMBER(G88)),G88*Parametros!$B$13,"") | M88: =IF(AND(J88<>"",ISNUMBER(G88)),G88-J88-K88-L88,"") | N88: =IF(AND(J88<>"",ISNUMBER(G88)),M88/G88,"") | O88: =IF(OR(J88="",Parametros!$B$14>=1),"",J88/(1-Parametros!$B$14)) | P88: =IF(OR(J88="",Parametros!$B$14+Parametros!$B$18>=1),"",J88/(1-Parametros!$B$14-Parametros!$B$18)) | Q88: =IF(B88="","",IF(E88="","SIN RECETA",IF(J88="","FALTAN DATOS",IF(NOT(ISNUMBER(G88)),"FALTA PRECIO",IF(M88<0,"PIERDE",IF(N88<Parametros!$B$18,"BAJO META","OK")))))) | R88: =IF(B88="","",IF(E88="","Elegir receta (molde).",IF(ISNA(MATCH(E88,Recetas!$A$5:$A$84,0)),"La receta no existe en Recetas.",IF(J88="","Completar la receta "&E88&": "&INDEX(Recetas!$T$5:$T$84,MATCH(E88,Recetas!$A$5:$A$84,0)),IF(NOT(ISNUMBER(G88)),"Precio de venta.","")))))
J89: =IF(OR(B89="",E89=""),"",IF(IFERROR(INDEX(Recetas!$S$5:$S$84,MATCH(E89,Recetas!$A$5:$A$84,0)),"")="","",IFERROR(INDEX(Recetas!$S$5:$S$84,MATCH(E89,Recetas!$A$5:$A$84,0)),"")+N(F89))) | K89: =IF(AND(J89<>"",ISNUMBER(G89)),G89*Parametros!$B$12,"") | L89: =IF(AND(J89<>"",ISNUMBER(G89)),G89*Parametros!$B$13,"") | M89: =IF(AND(J89<>"",ISNUMBER(G89)),G89-J89-K89-L89,"") | N89: =IF(AND(J89<>"",ISNUMBER(G89)),M89/G89,"") | O89: =IF(OR(J89="",Parametros!$B$14>=1),"",J89/(1-Parametros!$B$14)) | P89: =IF(OR(J89="",Parametros!$B$14+Parametros!$B$18>=1),"",J89/(1-Parametros!$B$14-Parametros!$B$18)) | Q89: =IF(B89="","",IF(E89="","SIN RECETA",IF(J89="","FALTAN DATOS",IF(NOT(ISNUMBER(G89)),"FALTA PRECIO",IF(M89<0,"PIERDE",IF(N89<Parametros!$B$18,"BAJO META","OK")))))) | R89: =IF(B89="","",IF(E89="","Elegir receta (molde).",IF(ISNA(MATCH(E89,Recetas!$A$5:$A$84,0)),"La receta no existe en Recetas.",IF(J89="","Completar la receta "&E89&": "&INDEX(Recetas!$T$5:$T$84,MATCH(E89,Recetas!$A$5:$A$84,0)),IF(NOT(ISNUMBER(G89)),"Precio de venta.","")))))
J90: =IF(OR(B90="",E90=""),"",IF(IFERROR(INDEX(Recetas!$S$5:$S$84,MATCH(E90,Recetas!$A$5:$A$84,0)),"")="","",IFERROR(INDEX(Recetas!$S$5:$S$84,MATCH(E90,Recetas!$A$5:$A$84,0)),"")+N(F90))) | K90: =IF(AND(J90<>"",ISNUMBER(G90)),G90*Parametros!$B$12,"") | L90: =IF(AND(J90<>"",ISNUMBER(G90)),G90*Parametros!$B$13,"") | M90: =IF(AND(J90<>"",ISNUMBER(G90)),G90-J90-K90-L90,"") | N90: =IF(AND(J90<>"",ISNUMBER(G90)),M90/G90,"") | O90: =IF(OR(J90="",Parametros!$B$14>=1),"",J90/(1-Parametros!$B$14)) | P90: =IF(OR(J90="",Parametros!$B$14+Parametros!$B$18>=1),"",J90/(1-Parametros!$B$14-Parametros!$B$18)) | Q90: =IF(B90="","",IF(E90="","SIN RECETA",IF(J90="","FALTAN DATOS",IF(NOT(ISNUMBER(G90)),"FALTA PRECIO",IF(M90<0,"PIERDE",IF(N90<Parametros!$B$18,"BAJO META","OK")))))) | R90: =IF(B90="","",IF(E90="","Elegir receta (molde).",IF(ISNA(MATCH(E90,Recetas!$A$5:$A$84,0)),"La receta no existe en Recetas.",IF(J90="","Completar la receta "&E90&": "&INDEX(Recetas!$T$5:$T$84,MATCH(E90,Recetas!$A$5:$A$84,0)),IF(NOT(ISNUMBER(G90)),"Precio de venta.","")))))
J91: =IF(OR(B91="",E91=""),"",IF(IFERROR(INDEX(Recetas!$S$5:$S$84,MATCH(E91,Recetas!$A$5:$A$84,0)),"")="","",IFERROR(INDEX(Recetas!$S$5:$S$84,MATCH(E91,Recetas!$A$5:$A$84,0)),"")+N(F91))) | K91: =IF(AND(J91<>"",ISNUMBER(G91)),G91*Parametros!$B$12,"") | L91: =IF(AND(J91<>"",ISNUMBER(G91)),G91*Parametros!$B$13,"") | M91: =IF(AND(J91<>"",ISNUMBER(G91)),G91-J91-K91-L91,"") | N91: =IF(AND(J91<>"",ISNUMBER(G91)),M91/G91,"") | O91: =IF(OR(J91="",Parametros!$B$14>=1),"",J91/(1-Parametros!$B$14)) | P91: =IF(OR(J91="",Parametros!$B$14+Parametros!$B$18>=1),"",J91/(1-Parametros!$B$14-Parametros!$B$18)) | Q91: =IF(B91="","",IF(E91="","SIN RECETA",IF(J91="","FALTAN DATOS",IF(NOT(ISNUMBER(G91)),"FALTA PRECIO",IF(M91<0,"PIERDE",IF(N91<Parametros!$B$18,"BAJO META","OK")))))) | R91: =IF(B91="","",IF(E91="","Elegir receta (molde).",IF(ISNA(MATCH(E91,Recetas!$A$5:$A$84,0)),"La receta no existe en Recetas.",IF(J91="","Completar la receta "&E91&": "&INDEX(Recetas!$T$5:$T$84,MATCH(E91,Recetas!$A$5:$A$84,0)),IF(NOT(ISNUMBER(G91)),"Precio de venta.","")))))
... J110: =IF(OR(B110="",E110=""),"",IF(IFERROR(INDEX(Recetas!$S$5:$S$84,MATCH(E110,Recetas!$A$5:$A$84,0)),"")="","",IFERROR(INDEX(Recetas!$S$5:$S$84,MATCH(E110,Recetas!$A$5:$A$84,0)),"")+N(F110))) | K110: =IF(AND(J110<>"",ISNUMBER(G110)),G110*Parametros!$B$12,"") | L110: =IF(AND(J110<>"",ISNUMBER(G110)),G110*Parametros!$B$13,"") | M110: =IF(AND(J110<>"",ISNUMBER(G110)),G110-J110-K110-L110,"") | N110: =IF(AND(J110<>"",ISNUMBER(G110)),M110/G110,"") | O110: =IF(OR(J110="",Parametros!$B$14>=1),"",J110/(1-Parametros!$B$14)) | P110: =IF(OR(J110="",Parametros!$B$14+Parametros!$B$18>=1),"",J110/(1-Parametros!$B$14-Parametros!$B$18)) | Q110: =IF(B110="","",IF(E110="","SIN RECETA",IF(J110="","FALTAN DATOS",IF(NOT(ISNUMBER(G110)),"FALTA PRECIO",IF(M110<0,"PIERDE",IF(N110<Parametros!$B$18,"BAJO META","OK")))))) | R110: =IF(B110="","",IF(E110="","Elegir receta (molde).",IF(ISNA(MATCH(E110,Recetas!$A$5:$A$84,0)),"La receta no existe en Recetas.",IF(J110="","Completar la receta "&E110&": "&INDEX(Recetas!$T$5:$T$84,MATCH(E110,Recetas!$A$5:$A$84,0)),IF(NOT(ISNUMBER(G110)),"Precio de venta.","")))))

Sheet Recetas
A1: RECETAS POR MOLDE — costo de producción de una prenda
A2: Una fila = un molde del catálogo (los mismos del panel de Fichas y de Planificación). Llena las columnas azules. Abajo: prendas que aún no tienen molde.
A4: Receta (molde) | B4: Descripción | C4: Deporte | D4: Prenda | E4: Calce | F4: Tela principal | G4: Kg tela por prenda | H4: Tela 2 (malla, etc.) | I4: Kg tela 2 por prenda | J4: Metros impresos por prenda | K4: Confección (tipo) | L4: Avíos ($ por prenda) | M4: Estado del dato | N4: Notas | O4: $ Telas | P4: $ Papel y tinta | Q4: $ Confección | R4: $ Avíos | S4: COSTO DE PRODUCCIÓN | T4: Qué falta
A5: 01 · FUTMUJU01 | B5: Fútbol, cuello redondo | C5: Fútbol | D5: Camiseta | E5: Femenino | K5: Camiseta De Futbol | M5: Por confirmar | N5: Confección sugerida por el tipo de molde: confirmar. | O5: =IF(A5="","",IFERROR(G5*INDEX(Precios!$D$5:$D$120,MATCH(F5,Precios!$A$5:$A$120,0)),0)+IF(H5="",0,IFERROR(I5*INDEX(Precios!$D$5:$D$120,MATCH(H5,Precios!$A$5:$A$120,0)),0))) -> 0 | P5: =IF(A5="","",N(J5)*Parametros!$B$27) -> 0 | Q5: =IF(A5="","",IFERROR(INDEX(Confeccion!$B$5:$B$100,MATCH(K5,Confeccion!$A$5:$A$100,0)),0)) -> 2000 | R5: =IF(A5="","",N(L5)) -> 0 | S5: =IF(A5="","",IF(AND(F5<>"",ISNUMBER(G5),ISNUMBER(IFERROR(INDEX(Precios!$D$5:$D$120,MATCH(F5,Precios!$A$5:$A$120,0)),"x")),OR(H5="",ISNUMBER(IFERROR(INDEX(Precios!$D$5:$D$120,MATCH(H5,Precios!$A$5:$A$120,0)),"x"))),J5<>"",K5<>"",Q5>0),SUM(O5:R5),"")) | T5: =IF(A5="","",IF(S5<>"",IF(AND(N(J5)>0,Parametros!$B$27=0),"Lista (sin costo de impresión)","Lista"),IF(F5="","Tela. ","")&IF(NOT(ISNUMBER(G5)),"Kg de tela. ","")&IF(AND(F5<>"",NOT(ISNUMBER(IFERROR(INDEX(Precios!$D$5:$D$120,MATCH(F5,Precios!$A$5:$A$120,0)),"x")))),"Tela sin precio. ","")&IF(J5="","Metros impresos. ","")&IF(K5="","Confección. ",IF(Q5=0,"Confección sin valor. ","")))) -> Tela. Kg de tela. Metros impresos.
A6: 02 · FUTHOMU01 | B6: Fútbol, cuello redondo | C6: Fútbol | D6: Camiseta | E6: Masculino | K6: Camiseta De Futbol | M6: Por confirmar | N6: Confección sugerida por el tipo de molde: confirmar. | O6: =IF(A6="","",IFERROR(G6*INDEX(Precios!$D$5:$D$120,MATCH(F6,Precios!$A$5:$A$120,0)),0)+IF(H6="",0,IFERROR(I6*INDEX(Precios!$D$5:$D$120,MATCH(H6,Precios!$A$5:$A$120,0)),0))) -> 0 | P6: =IF(A6="","",N(J6)*Parametros!$B$27) -> 0 | Q6: =IF(A6="","",IFERROR(INDEX(Confeccion!$B$5:$B$100,MATCH(K6,Confeccion!$A$5:$A$100,0)),0)) -> 2000 | R6: =IF(A6="","",N(L6)) -> 0 | S6: =IF(A6="","",IF(AND(F6<>"",ISNUMBER(G6),ISNUMBER(IFERROR(INDEX(Precios!$D$5:$D$120,MATCH(F6,Precios!$A$5:$A$120,0)),"x")),OR(H6="",ISNUMBER(IFERROR(INDEX(Precios!$D$5:$D$120,MATCH(H6,Precios!$A$5:$A$120,0)),"x"))),J6<>"",K6<>"",Q6>0),SUM(O6:R6),"")) | T6: =IF(A6="","",IF(S6<>"",IF(AND(N(J6)>0,Parametros!$B$27=0),"Lista (sin costo de impresión)","Lista"),IF(F6="","Tela. ","")&IF(NOT(ISNUMBER(G6)),"Kg de tela. ","")&IF(AND(F6<>"",NOT(ISNUMBER(IFERROR(INDEX(Precios!$D$5:$D$120,MATCH(F6,Precios!$A$5:$A$120,0)),"x")))),"Tela sin precio. ","")&IF(J6="","Metros impresos. ","")&IF(K6="","Confección. ",IF(Q6=0,"Confección sin valor. ","")))) -> Tela. Kg de tela. Metros impresos.
A7: 03 · FUTINMUJU01 | B7: Fútbol infantil, cuello redondo | C7: Fútbol | D7: Camiseta | E7: Infantil Femenino | K7: Camiseta De Futbol | M7: Por confirmar | N7: Confección sugerida por el tipo de molde: confirmar. | O7: =IF(A7="","",IFERROR(G7*INDEX(Precios!$D$5:$D$120,MATCH(F7,Precios!$A$5:$A$120,0)),0)+IF(H7="",0,IFERROR(I7*INDEX(Precios!$D$5:$D$120,MATCH(H7,Precios!$A$5:$A$120,0)),0))) -> 0 | P7: =IF(A7="","",N(J7)*Parametros!$B$27) -> 0 | Q7: =IF(A7="","",IFERROR(INDEX(Confeccion!$B$5:$B$100,MATCH(K7,Confeccion!$A$5:$A$100,0)),0)) -> 2000 | R7: =IF(A7="","",N(L7)) -> 0 | S7: =IF(A7="","",IF(AND(F7<>"",ISNUMBER(G7),ISNUMBER(IFERROR(INDEX(Precios!$D$5:$D$120,MATCH(F7,Precios!$A$5:$A$120,0)),"x")),OR(H7="",ISNUMBER(IFERROR(INDEX(Precios!$D$5:$D$120,MATCH(H7,Precios!$A$5:$A$120,0)),"x"))),J7<>"",K7<>"",Q7>0),SUM(O7:R7),"")) | T7: =IF(A7="","",IF(S7<>"",IF(AND(N(J7)>0,Parametros!$B$27=0),"Lista (sin costo de impresión)","Lista"),IF(F7="","Tela. ","")&IF(NOT(ISNUMBER(G7)),"Kg de tela. ","")&IF(AND(F7<>"",NOT(ISNUMBER(IFERROR(INDEX(Precios!$D$5:$D$120,MATCH(F7,Precios!$A$5:$A$120,0)),"x")))),"Tela sin precio. ","")&IF(J7="","Metros impresos. ","")&IF(K7="","Confección. ",IF(Q7=0,"Confección sin valor. ","")))) -> Tela. Kg de tela. Metros impresos.
A8: 04 · FUTINHOMU01 | B8: Fútbol infantil, cuello redondo | C8: Fútbol | D8: Camiseta | E8: Infantil Masculino | F8: CIRE BLANCO | G8: 0.0375 | H8: MESH | I8: 0.024 | K8: Camiseta De Futbol | M8: Por confirmar | N8: Ficha OT 2369 (48 camisetas infantiles). Falta metros impresos. | O8: =IF(A8="","",IFERROR(G8*INDEX(Precios!$D$5:$D$120,MATCH(F8,Precios!$A$5:$A$120,0)),0)+IF(H8="",0,IFERROR(I8*INDEX(Precios!$D$5:$D$120,MATCH(H8,Precios!$A$5:$A$120,0)),0))) -> 394.8 | P8: =IF(A8="","",N(J8)*Parametros!$B$27) -> 0 | Q8: =IF(A8="","",IFERROR(INDEX(Confeccion!$B$5:$B$100,MATCH(K8,Confeccion!$A$5:$A$100,0)),0)) -> 2000 | R8: =IF(A8="","",N(L8)) -> 0 | S8: =IF(A8="","",IF(AND(F8<>"",ISNUMBER(G8),ISNUMBER(IFERROR(INDEX(Precios!$D$5:$D$120,MATCH(F8,Precios!$A$5:$A$120,0)),"x")),OR(H8="",ISNUMBER(IFERROR(INDEX(Precios!$D$5:$D$120,MATCH(H8,Precios!$A$5:$A$120,0)),"x"))),J8<>"",K8<>"",Q8>0),SUM(O8:R8),"")) | T8: =IF(A8="","",IF(S8<>"",IF(AND(N(J8)>0,Parametros!$B$27=0),"Lista (sin costo de impresión)","Lista"),IF(F8="","Tela. ","")&IF(NOT(ISNUMBER(G8)),"Kg de tela. ","")&IF(AND(F8<>"",NOT(ISNUMBER(IFERROR(INDEX(Precios!$D$5:$D$120,MATCH(F8,Precios!$A$5:$A$120,0)),"x")))),"Tela sin precio. ","")&IF(J8="","Metros impresos. ","")&IF(K8="","Confección. ",IF(Q8=0,"Confección sin valor. ","")))) -> Metros impresos.
A9: 05 · FUTMUJV01 | B9: Fútbol, cuello v | C9: Fútbol | D9: Camiseta | E9: Femenino | K9: Camiseta De Futbol | M9: Por confirmar | N9: Confección sugerida por el tipo de molde: confirmar. | O9: =IF(A9="","",IFERROR(G9*INDEX(Precios!$D$5:$D$120,MATCH(F9,Precios!$A$5:$A$120,0)),0)+IF(H9="",0,IFERROR(I9*INDEX(Precios!$D$5:$D$120,MATCH(H9,Precios!$A$5:$A$120,0)),0))) -> 0 | P9: =IF(A9="","",N(J9)*Parametros!$B$27) -> 0 | Q9: =IF(A9="","",IFERROR(INDEX(Confeccion!$B$5:$B$100,MATCH(K9,Confeccion!$A$5:$A$100,0)),0)) -> 2000 | R9: =IF(A9="","",N(L9)) -> 0 | S9: =IF(A9="","",IF(AND(F9<>"",ISNUMBER(G9),ISNUMBER(IFERROR(INDEX(Precios!$D$5:$D$120,MATCH(F9,Precios!$A$5:$A$120,0)),"x")),OR(H9="",ISNUMBER(IFERROR(INDEX(Precios!$D$5:$D$120,MATCH(H9,Precios!$A$5:$A$120,0)),"x"))),J9<>"",K9<>"",Q9>0),SUM(O9:R9),"")) | T9: =IF(A9="","",IF(S9<>"",IF(AND(N(J9)>0,Parametros!$B$27=0),"Lista (sin costo de impresión)","Lista"),IF(F9="","Tela. ","")&IF(NOT(ISNUMBER(G9)),"Kg de tela. ","")&IF(AND(F9<>"",NOT(ISNUMBER(IFERROR(INDEX(Precios!$D$5:$D$120,MATCH(F9,Precios!$A$5:$A$120,0)),"x")))),"Tela sin precio. ","")&IF(J9="","Metros impresos. ","")&IF(K9="","Confección. ",IF(Q9=0,"Confección sin valor. ","")))) -> Tela. Kg de tela. Metros impresos.
A10: 06 · FUTHOMV01 | B10: Fútbol, cuello v | C10: Fútbol | D10: Camiseta | E10: Masculino | K10: Camiseta De Futbol | M10: Por confirmar | N10: Confección sugerida por el tipo de molde: confirmar. | O10: =IF(A10="","",IFERROR(G10*INDEX(Precios!$D$5:$D$120,MATCH(F10,Precios!$A$5:$A$120,0)),0)+IF(H10="",0,IFERROR(I10*INDEX(Precios!$D$5:$D$120,MATCH(H10,Precios!$A$5:$A$120,0)),0))) -> 0 | P10: =IF(A10="","",N(J10)*Parametros!$B$27) -> 0 | Q10: =IF(A10="","",IFERROR(INDEX(Confeccion!$B$5:$B$100,MATCH(K10,Confeccion!$A$5:$A$100,0)),0)) -> 2000 | R10: =IF(A10="","",N(L10)) -> 0 | S10: =IF(A10="","",IF(AND(F10<>"",ISNUMBER(G10),ISNUMBER(IFERROR(INDEX(Precios!$D$5:$D$120,MATCH(F10,Precios!$A$5:$A$120,0)),"x")),OR(H10="",ISNUMBER(IFERROR(INDEX(Precios!$D$5:$D$120,MATCH(H10,Precios!$A$5:$A$120,0)),"x"))),J10<>"",K10<>"",Q10>0),SUM(O10:R10),"")) | T10: =IF(A10="","",IF(S10<>"",IF(AND(N(J10)>0,Parametros!$B$27=0),"Lista (sin costo de impresión)","Lista"),IF(F10="","Tela. ","")&IF(NOT(ISNUMBER(G10)),"Kg de tela. ","")&IF(AND(F10<>"",NOT(ISNUMBER(IFERROR(INDEX(Precios!$D$5:$D$120,MATCH(F10,Precios!$A$5:$A$120,0)),"x")))),"Tela sin precio. ","")&IF(J10="","Metros impresos. ","")&IF(K10="","Confección. ",IF(Q10=0,"Confección sin valor. ","")))) -> Tela. Kg de tela. Metros impresos.
A11: 07 · FUTINMUJV01 | B11: Fútbol infantil, cuello v | C11: Fútbol | D11: Camiseta | E11: Infantil Femenino | K11: Camiseta De Futbol | M11: Por confirmar | N11: Confección sugerida por el tipo de molde: confirmar. | O11: =IF(A11="","",IFERROR(G11*INDEX(Precios!$D$5:$D$120,MATCH(F11,Precios!$A$5:$A$120,0)),0)+IF(H11="",0,IFERROR(I11*INDEX(Precios!$D$5:$D$120,MATCH(H11,Precios!$A$5:$A$120,0)),0))) -> 0 | P11: =IF(A11="","",N(J11)*Parametros!$B$27) -> 0 | Q11: =IF(A11="","",IFERROR(INDEX(Confeccion!$B$5:$B$100,MATCH(K11,Confeccion!$A$5:$A$100,0)),0)) -> 2000 | R11: =IF(A11="","",N(L11)) -> 0 | S11: =IF(A11="","",IF(AND(F11<>"",ISNUMBER(G11),ISNUMBER(IFERROR(INDEX(Precios!$D$5:$D$120,MATCH(F11,Precios!$A$5:$A$120,0)),"x")),OR(H11="",ISNUMBER(IFERROR(INDEX(Precios!$D$5:$D$120,MATCH(H11,Precios!$A$5:$A$120,0)),"x"))),J11<>"",K11<>"",Q11>0),SUM(O11:R11),"")) | T11: =IF(A11="","",IF(S11<>"",IF(AND(N(J11)>0,Parametros!$B$27=0),"Lista (sin costo de impresión)","Lista"),IF(F11="","Tela. ","")&IF(NOT(ISNUMBER(G11)),"Kg de tela. ","")&IF(AND(F11<>"",NOT(ISNUMBER(IFERROR(INDEX(Precios!$D$5:$D$120,MATCH(F11,Precios!$A$5:$A$120,0)),"x")))),"Tela sin precio. ","")&IF(J11="","Metros impresos. ","")&IF(K11="","Confección. ",IF(Q11=0,"Confección sin valor. ","")))) -> Tela. Kg de tela. Metros impresos.
A12: 08 · FUTINHOMV01 | B12: Fútbol infantil, cuello v | C12: Fútbol | D12: Camiseta | E12: Infantil Masculino | K12: Camiseta De Futbol | M12: Por confirmar | N12: Confección sugerida por el tipo de molde: confirmar. | O12: =IF(A12="","",IFERROR(G12*INDEX(Precios!$D$5:$D$120,MATCH(F12,Precios!$A$5:$A$120,0)),0)+IF(H12="",0,IFERROR(I12*INDEX(Precios!$D$5:$D$120,MATCH(H12,Precios!$A$5:$A$120,0)),0))) -> 0 | P12: =IF(A12="","",N(J12)*Parametros!$B$27) -> 0 | Q12: =IF(A12="","",IFERROR(INDEX(Confeccion!$B$5:$B$100,MATCH(K12,Confeccion!$A$5:$A$100,0)),0)) -> 2000 | R12: =IF(A12="","",N(L12)) -> 0 | S12: =IF(A12="","",IF(AND(F12<>"",ISNUMBER(G12),ISNUMBER(IFERROR(INDEX(Precios!$D$5:$D$120,MATCH(F12,Precios!$A$5:$A$120,0)),"x")),OR(H12="",ISNUMBER(IFERROR(INDEX(Precios!$D$5:$D$120,MATCH(H12,Precios!$A$5:$A$120,0)),"x"))),J12<>"",K12<>"",Q12>0),SUM(O12:R12),"")) | T12: =IF(A12="","",IF(S12<>"",IF(AND(N(J12)>0,Parametros!$B$27=0),"Lista (sin costo de impresión)","Lista"),IF(F12="","Tela. ","")&IF(NOT(ISNUMBER(G12)),"Kg de tela. ","")&IF(AND(F12<>"",NOT(ISNUMBER(IFERROR(INDEX(Precios!$D$5:$D$120,MATCH(F12,Precios!$A$5:$A$120,0)),"x")))),"Tela sin precio. ","")&IF(J12="","Metros impresos. ","")&IF(K12="","Confección. ",IF(Q12=0,"Confección sin valor. ","")))) -> Tela. Kg de tela. Metros impresos.
A13: 09 · FUTMUJCC01 | B13: Fútbol, cuello camisero | C13: Fútbol | D13: Camiseta | E13: Femenino | K13: Camiseta De Futbol | M13: Por confirmar | N13: Confección sugerida por el tipo de molde: confirmar. | O13: =IF(A13="","",IFERROR(G13*INDEX(Precios!$D$5:$D$120,MATCH(F13,Precios!$A$5:$A$120,0)),0)+IF(H13="",0,IFERROR(I13*INDEX(Precios!$D$5:$D$120,MATCH(H13,Precios!$A$5:$A$120,0)),0))) -> 0 | P13: =IF(A13="","",N(J13)*Parametros!$B$27) -> 0 | Q13: =IF(A13="","",IFERROR(INDEX(Confeccion!$B$5:$B$100,MATCH(K13,Confeccion!$A$5:$A$100,0)),0)) -> 2000 | R13: =IF(A13="","",N(L13)) -> 0 | S13: =IF(A13="","",IF(AND(F13<>"",ISNUMBER(G13),ISNUMBER(IFERROR(INDEX(Precios!$D$5:$D$120,MATCH(F13,Precios!$A$5:$A$120,0)),"x")),OR(H13="",ISNUMBER(IFERROR(INDEX(Precios!$D$5:$D$120,MATCH(H13,Precios!$A$5:$A$120,0)),"x"))),J13<>"",K13<>"",Q13>0),SUM(O13:R13),"")) | T13: =IF(A13="","",IF(S13<>"",IF(AND(N(J13)>0,Parametros!$B$27=0),"Lista (sin costo de impresión)","Lista"),IF(F13="","Tela. ","")&IF(NOT(ISNUMBER(G13)),"Kg de tela. ","")&IF(AND(F13<>"",NOT(ISNUMBER(IFERROR(INDEX(Precios!$D$5:$D$120,MATCH(F13,Precios!$A$5:$A$120,0)),"x")))),"Tela sin precio. ","")&IF(J13="","Metros impresos. ","")&IF(K13="","Confección. ",IF(Q13=0,"Confección sin valor. ","")))) -> Tela. Kg de tela. Metros impresos.
A14: 10 · FUTHOMCC01 | B14: Fútbol, cuello camisero | C14: Fútbol | D14: Camiseta | E14: Masculino | K14: Camiseta De Futbol | M14: Por confirmar | N14: Confección sugerida por el tipo de molde: confirmar. | O14: =IF(A14="","",IFERROR(G14*INDEX(Precios!$D$5:$D$120,MATCH(F14,Precios!$A$5:$A$120,0)),0)+IF(H14="",0,IFERROR(I14*INDEX(Precios!$D$5:$D$120,MATCH(H14,Precios!$A$5:$A$120,0)),0))) -> 0 | P14: =IF(A14="","",N(J14)*Parametros!$B$27) -> 0 | Q14: =IF(A14="","",IFERROR(INDEX(Confeccion!$B$5:$B$100,MATCH(K14,Confeccion!$A$5:$A$100,0)),0)) -> 2000 | R14: =IF(A14="","",N(L14)) -> 0 | S14: =IF(A14="","",IF(AND(F14<>"",ISNUMBER(G14),ISNUMBER(IFERROR(INDEX(Precios!$D$5:$D$120,MATCH(F14,Precios!$A$5:$A$120,0)),"x")),OR(H14="",ISNUMBER(IFERROR(INDEX(Precios!$D$5:$D$120,MATCH(H14,Precios!$A$5:$A$120,0)),"x"))),J14<>"",K14<>"",Q14>0),SUM(O14:R14),"")) | T14: =IF(A14="","",IF(S14<>"",IF(AND(N(J14)>0,Parametros!$B$27=0),"Lista (sin costo de impresión)","Lista"),IF(F14="","Tela. ","")&IF(NOT(ISNUMBER(G14)),"Kg de tela. ","")&IF(AND(F14<>"",NOT(ISNUMBER(IFERROR(INDEX(Precios!$D$5:$D$120,MATCH(F14,Precios!$A$5:$A$120,0)),"x")))),"Tela sin precio. ","")&IF(J14="","Metros impresos. ","")&IF(K14="","Confección. ",IF(Q14=0,"Confección sin valor. ","")))) -> Tela. Kg de tela. Metros impresos.
A15: 11 · FUTINMUJCC01 | B15: Fútbol infantil, cuello camisero | C15: Fútbol | D15: Camiseta | E15: Infantil Femenino | K15: Camiseta De Futbol | M15: Por confirmar | N15: Confección sugerida por el tipo de molde: confirmar. | O15: =IF(A15="","",IFERROR(G15*INDEX(Precios!$D$5:$D$120,MATCH(F15,Precios!$A$5:$A$120,0)),0)+IF(H15="",0,IFERROR(I15*INDEX(Precios!$D$5:$D$120,MATCH(H15,Precios!$A$5:$A$120,0)),0))) -> 0 | P15: =IF(A15="","",N(J15)*Parametros!$B$27) -> 0 | Q15: =IF(A15="","",IFERROR(INDEX(Confeccion!$B$5:$B$100,MATCH(K15,Confeccion!$A$5:$A$100,0)),0)) -> 2000 | R15: =IF(A15="","",N(L15)) -> 0 | S15: =IF(A15="","",IF(AND(F15<>"",ISNUMBER(G15),ISNUMBER(IFERROR(INDEX(Precios!$D$5:$D$120,MATCH(F15,Precios!$A$5:$A$120,0)),"x")),OR(H15="",ISNUMBER(IFERROR(INDEX(Precios!$D$5:$D$120,MATCH(H15,Precios!$A$5:$A$120,0)),"x"))),J15<>"",K15<>"",Q15>0),SUM(O15:R15),"")) | T15: =IF(A15="","",IF(S15<>"",IF(AND(N(J15)>0,Parametros!$B$27=0),"Lista (sin costo de impresión)","Lista"),IF(F15="","Tela. ","")&IF(NOT(ISNUMBER(G15)),"Kg de tela. ","")&IF(AND(F15<>"",NOT(ISNUMBER(IFERROR(INDEX(Precios!$D$5:$D$120,MATCH(F15,Precios!$A$5:$A$120,0)),"x")))),"Tela sin precio. ","")&IF(J15="","Metros impresos. ","")&IF(K15="","Confección. ",IF(Q15=0,"Confección sin valor. ","")))) -> Tela. Kg de tela. Metros impresos.
A16: 12 · FUTINHOMCC01 | B16: Fútbol infantil, cuello camisero | C16: Fútbol | D16: Camiseta | E16: Infantil Masculino | K16: Camiseta De Futbol | M16: Por confirmar | N16: Confección sugerida por el tipo de molde: confirmar. | O16: =IF(A16="","",IFERROR(G16*INDEX(Precios!$D$5:$D$120,MATCH(F16,Precios!$A$5:$A$120,0)),0)+IF(H16="",0,IFERROR(I16*INDEX(Precios!$D$5:$D$120,MATCH(H16,Precios!$A$5:$A$120,0)),0))) -> 0 | P16: =IF(A16="","",N(J16)*Parametros!$B$27) -> 0 | Q16: =IF(A16="","",IFERROR(INDEX(Confeccion!$B$5:$B$100,MATCH(K16,Confeccion!$A$5:$A$100,0)),0)) -> 2000 | R16: =IF(A16="","",N(L16)) -> 0 | S16: =IF(A16="","",IF(AND(F16<>"",ISNUMBER(G16),ISNUMBER(IFERROR(INDEX(Precios!$D$5:$D$120,MATCH(F16,Precios!$A$5:$A$120,0)),"x")),OR(H16="",ISNUMBER(IFERROR(INDEX(Precios!$D$5:$D$120,MATCH(H16,Precios!$A$5:$A$120,0)),"x"))),J16<>"",K16<>"",Q16>0),SUM(O16:R16),"")) | T16: =IF(A16="","",IF(S16<>"",IF(AND(N(J16)>0,Parametros!$B$27=0),"Lista (sin costo de impresión)","Lista"),IF(F16="","Tela. ","")&IF(NOT(ISNUMBER(G16)),"Kg de tela. ","")&IF(AND(F16<>"",NOT(ISNUMBER(IFERROR(INDEX(Precios!$D$5:$D$120,MATCH(F16,Precios!$A$5:$A$120,0)),"x")))),"Tela sin precio. ","")&IF(J16="","Metros impresos. ","")&IF(K16="","Confección. ",IF(Q16=0,"Confección sin valor. ","")))) -> Tela. Kg de tela. Metros impresos.
A17: 13 · FUTMUJU01PRO | B17: Fútbol, pro, cuello redondo | C17: Fútbol | D17: Camiseta | E17: Femenino | F17: MONTESIMONE TRAINING (fut pro) | G17: 0.1225 | K17: Camiseta De Futbol | M17: Por confirmar | N17: Ficha OT 2257 (20 camisetas Pro femeninas). Falta metros impresos. | O17: =IF(A17="","",IFERROR(G17*INDEX(Precios!$D$5:$D$120,MATCH(F17,Precios!$A$5:$A$120,0)),0)+IF(H17="",0,IFERROR(I17*INDEX(Precios!$D$5:$D$120,MATCH(H17,Precios!$A$5:$A$120,0)),0))) -> 432.5475 | P17: =IF(A17="","",N(J17)*Parametros!$B$27) -> 0 | Q17: =IF(A17="","",IFERROR(INDEX(Confeccion!$B$5:$B$100,MATCH(K17,Confeccion!$A$5:$A$100,0)),0)) -> 2000 | R17: =IF(A17="","",N(L17)) -> 0 | S17: =IF(A17="","",IF(AND(F17<>"",ISNUMBER(G17),ISNUMBER(IFERROR(INDEX(Precios!$D$5:$D$120,MATCH(F17,Precios!$A$5:$A$120,0)),"x")),OR(H17="",ISNUMBER(IFERROR(INDEX(Precios!$D$5:$D$120,MATCH(H17,Precios!$A$5:$A$120,0)),"x"))),J17<>"",K17<>"",Q17>0),SUM(O17:R17),"")) | T17: =IF(A17="","",IF(S17<>"",IF(AND(N(J17)>0,Parametros!$B$27=0),"Lista (sin costo de impresión)","Lista"),IF(F17="","Tela. ","")&IF(NOT(ISNUMBER(G17)),"Kg de tela. ","")&IF(AND(F17<>"",NOT(ISNUMBER(IFERROR(INDEX(Precios!$D$5:$D$120,MATCH(F17,Precios!$A$5:$A$120,0)),"x")))),"Tela sin precio. ","")&IF(J17="","Metros impresos. ","")&IF(K17="","Confección. ",IF(Q17=0,"Confección sin valor. ","")))) -> Metros impresos.
A18: 14 · FUTHOMU01PRO | B18: Fútbol, pro, cuello redondo | C18: Fútbol | D18: Camiseta | E18: Masculino | F18: MONTESIMONE TRAINING (fut pro) | G18: 0.12 | H18: MESH | I18: 0.0775 | J18: 1.9 | K18: Camiseta De Futbol | M18: Por confirmar | N18: Ficha OT 2547 (20 camisetas Pro masculinas). Metros: la ficha dice 1,9; la receta anterior 1,2 → confirmar. | O18: =IF(A18="","",IFERROR(G18*INDEX(Precios!$D$5:$D$120,MATCH(F18,Precios!$A$5:$A$120,0)),0)+IF(H18="",0,IFERROR(I18*INDEX(Precios!$D$5:$D$120,MATCH(H18,Precios!$A$5:$A$120,0)),0))) -> 1020.47 | P18: =IF(A18="","",N(J18)*Parametros!$B$27) -> 0 | Q18: =IF(A18="","",IFERROR(INDEX(Confeccion!$B$5:$B$100,MATCH(K18,Confeccion!$A$5:$A$100,0)),0)) -> 2000 | R18: =IF(A18="","",N(L18)) -> 0 | S18: =IF(A18="","",IF(AND(F18<>"",ISNUMBER(G18),ISNUMBER(IFERROR(INDEX(Precios!$D$5:$D$120,MATCH(F18,Precios!$A$5:$A$120,0)),"x")),OR(H18="",ISNUMBER(IFERROR(INDEX(Precios!$D$5:$D$120,MATCH(H18,Precios!$A$5:$A$120,0)),"x"))),J18<>"",K18<>"",Q18>0),SUM(O18:R18),"")) -> 3020.47 | T18: =IF(A18="","",IF(S18<>"",IF(AND(N(J18)>0,Parametros!$B$27=0),"Lista (sin costo de impresión)","Lista"),IF(F18="","Tela. ","")&IF(NOT(ISNUMBER(G18)),"Kg de tela. ","")&IF(AND(F18<>"",NOT(ISNUMBER(IFERROR(INDEX(Precios!$D$5:$D$120,MATCH(F18,Precios!$A$5:$A$120,0)),"x")))),"Tela sin precio. ","")&IF(J18="","Metros impresos. ","")&IF(K18="","Confección. ",IF(Q18=0,"Confección sin valor. ","")))) -> Lista (sin costo de impresión)
A19: 15 · FUTMUJV01PRO | B19: Fútbol, pro, cuello v | C19: Fútbol | D19: Camiseta | E19: Femenino | K19: Camiseta De Futbol | M19: Por confirmar | N19: Confección sugerida por el tipo de molde: confirmar. | O19: =IF(A19="","",IFERROR(G19*INDEX(Precios!$D$5:$D$120,MATCH(F19,Precios!$A$5:$A$120,0)),0)+IF(H19="",0,IFERROR(I19*INDEX(Precios!$D$5:$D$120,MATCH(H19,Precios!$A$5:$A$120,0)),0))) -> 0 | P19: =IF(A19="","",N(J19)*Parametros!$B$27) -> 0 | Q19: =IF(A19="","",IFERROR(INDEX(Confeccion!$B$5:$B$100,MATCH(K19,Confeccion!$A$5:$A$100,0)),0)) -> 2000 | R19: =IF(A19="","",N(L19)) -> 0 | S19: =IF(A19="","",IF(AND(F19<>"",ISNUMBER(G19),ISNUMBER(IFERROR(INDEX(Precios!$D$5:$D$120,MATCH(F19,Precios!$A$5:$A$120,0)),"x")),OR(H19="",ISNUMBER(IFERROR(INDEX(Precios!$D$5:$D$120,MATCH(H19,Precios!$A$5:$A$120,0)),"x"))),J19<>"",K19<>"",Q19>0),SUM(O19:R19),"")) | T19: =IF(A19="","",IF(S19<>"",IF(AND(N(J19)>0,Parametros!$B$27=0),"Lista (sin costo de impresión)","Lista"),IF(F19="","Tela. ","")&IF(NOT(ISNUMBER(G19)),"Kg de tela. ","")&IF(AND(F19<>"",NOT(ISNUMBER(IFERROR(INDEX(Precios!$D$5:$D$120,MATCH(F19,Precios!$A$5:$A$120,0)),"x")))),"Tela sin precio. ","")&IF(J19="","Metros impresos. ","")&IF(K19="","Confección. ",IF(Q19=0,"Confección sin valor. ","")))) -> Tela. Kg de tela. Metros impresos.
A20: 16 · FUTHOMV01PRO | B20: Fútbol, pro, cuello v | C20: Fútbol | D20: Camiseta | E20: Masculino | K20: Camiseta De Futbol | M20: Por confirmar | N20: Confección sugerida por el tipo de molde: confirmar. | O20: =IF(A20="","",IFERROR(G20*INDEX(Precios!$D$5:$D$120,MATCH(F20,Precios!$A$5:$A$120,0)),0)+IF(H20="",0,IFERROR(I20*INDEX(Precios!$D$5:$D$120,MATCH(H20,Precios!$A$5:$A$120,0)),0))) -> 0 | P20: =IF(A20="","",N(J20)*Parametros!$B$27) -> 0 | Q20: =IF(A20="","",IFERROR(INDEX(Confeccion!$B$5:$B$100,MATCH(K20,Confeccion!$A$5:$A$100,0)),0)) -> 2000 | R20: =IF(A20="","",N(L20)) -> 0 | S20: =IF(A20="","",IF(AND(F20<>"",ISNUMBER(G20),ISNUMBER(IFERROR(INDEX(Precios!$D$5:$D$120,MATCH(F20,Precios!$A$5:$A$120,0)),"x")),OR(H20="",ISNUMBER(IFERROR(INDEX(Precios!$D$5:$D$120,MATCH(H20,Precios!$A$5:$A$120,0)),"x"))),J20<>"",K20<>"",Q20>0),SUM(O20:R20),"")) | T20: =IF(A20="","",IF(S20<>"",IF(AND(N(J20)>0,Parametros!$B$27=0),"Lista (sin costo de impresión)","Lista"),IF(F20="","Tela. ","")&IF(NOT(ISNUMBER(G20)),"Kg de tela. ","")&IF(AND(F20<>"",NOT(ISNUMBER(IFERROR(INDEX(Precios!$D$5:$D$120,MATCH(F20,Precios!$A$5:$A$120,0)),"x")))),"Tela sin precio. ","")&IF(J20="","Metros impresos. ","")&IF(K20="","Confección. ",IF(Q20=0,"Confección sin valor. ","")))) -> Tela. Kg de tela. Metros impresos.
A21: 17 · FUTMUJU02 | B21: Fútbol, raglán, cuello redondo | C21: Fútbol | D21: Camiseta | E21: Femenino | K21: Camiseta Futbol Molde 2026 (Raglan) | M21: Por confirmar | N21: Confección sugerida por el tipo de molde: confirmar. | O21: =IF(A21="","",IFERROR(G21*INDEX(Precios!$D$5:$D$120,MATCH(F21,Precios!$A$5:$A$120,0)),0)+IF(H21="",0,IFERROR(I21*INDEX(Precios!$D$5:$D$120,MATCH(H21,Precios!$A$5:$A$120,0)),0))) -> 0 | P21: =IF(A21="","",N(J21)*Parametros!$B$27) -> 0 | Q21: =IF(A21="","",IFERROR(INDEX(Confeccion!$B$5:$B$100,MATCH(K21,Confeccion!$A$5:$A$100,0)),0)) -> 2300 | R21: =IF(A21="","",N(L21)) -> 0 | S21: =IF(A21="","",IF(AND(F21<>"",ISNUMBER(G21),ISNUMBER(IFERROR(INDEX(Precios!$D$5:$D$120,MATCH(F21,Precios!$A$5:$A$120,0)),"x")),OR(H21="",ISNUMBER(IFERROR(INDEX(Precios!$D$5:$D$120,MATCH(H21,Precios!$A$5:$A$120,0)),"x"))),J21<>"",K21<>"",Q21>0),SUM(O21:R21),"")) | T21: =IF(A21="","",IF(S21<>"",IF(AND(N(J21)>0,Parametros!$B$27=0),"Lista (sin costo de impresión)","Lista"),IF(F21="","Tela. ","")&IF(NOT(ISNUMBER(G21)),"Kg de tela. ","")&IF(AND(F21<>"",NOT(ISNUMBER(IFERROR(INDEX(Precios!$D$5:$D$120,MATCH(F21,Precios!$A$5:$A$120,0)),"x")))),"Tela sin precio. ","")&IF(J21="","Metros impresos. ","")&IF(K21="","Confección. ",IF(Q21=0,"Confección sin valor. ","")))) -> Tela. Kg de tela. Metros impresos.
A22: 18 · FUTHOMU02 | B22: Fútbol, raglán, cuello redondo | C22: Fútbol | D22: Camiseta | E22: Masculino | K22: Camiseta Futbol Molde 2026 (Raglan) | M22: Por confirmar | N22: Confección sugerida por el tipo de molde: confirmar. | O22: =IF(A22="","",IFERROR(G22*INDEX(Precios!$D$5:$D$120,MATCH(F22,Precios!$A$5:$A$120,0)),0)+IF(H22="",0,IFERROR(I22*INDEX(Precios!$D$5:$D$120,MATCH(H22,Precios!$A$5:$A$120,0)),0))) -> 0 | P22: =IF(A22="","",N(J22)*Parametros!$B$27) -> 0 | Q22: =IF(A22="","",IFERROR(INDEX(Confeccion!$B$5:$B$100,MATCH(K22,Confeccion!$A$5:$A$100,0)),0)) -> 2300 | R22: =IF(A22="","",N(L22)) -> 0 | S22: =IF(A22="","",IF(AND(F22<>"",ISNUMBER(G22),ISNUMBER(IFERROR(INDEX(Precios!$D$5:$D$120,MATCH(F22,Precios!$A$5:$A$120,0)),"x")),OR(H22="",ISNUMBER(IFERROR(INDEX(Precios!$D$5:$D$120,MATCH(H22,Precios!$A$5:$A$120,0)),"x"))),J22<>"",K22<>"",Q22>0),SUM(O22:R22),"")) | T22: =IF(A22="","",IF(S22<>"",IF(AND(N(J22)>0,Parametros!$B$27=0),"Lista (sin costo de impresión)","Lista"),IF(F22="","Tela. ","")&IF(NOT(ISNUMBER(G22)),"Kg de tela. ","")&IF(AND(F22<>"",NOT(ISNUMBER(IFERROR(INDEX(Precios!$D$5:$D$120,MATCH(F22,Precios!$A$5:$A$120,0)),"x")))),"Tela sin precio. ","")&IF(J22="","Metros impresos. ","")&IF(K22="","Confección. ",IF(Q22=0,"Confección sin valor. ","")))) -> Tela. Kg de tela. Metros impresos.
A23: 19 · FUTINMUJU02 | B23: Fútbol infantil, raglán, cuello redondo | C23: Fútbol | D23: Camiseta | E23: Infantil Femenino | K23: Camiseta Futbol Molde 2026 (Raglan) | M23: Por confirmar | N23: Confección sugerida por el tipo de molde: confirmar. | O23: =IF(A23="","",IFERROR(G23*INDEX(Precios!$D$5:$D$120,MATCH(F23,Precios!$A$5:$A$120,0)),0)+IF(H23="",0,IFERROR(I23*INDEX(Precios!$D$5:$D$120,MATCH(H23,Precios!$A$5:$A$120,0)),0))) -> 0 | P23: =IF(A23="","",N(J23)*Parametros!$B$27) -> 0 | Q23: =IF(A23="","",IFERROR(INDEX(Confeccion!$B$5:$B$100,MATCH(K23,Confeccion!$A$5:$A$100,0)),0)) -> 2300 | R23: =IF(A23="","",N(L23)) -> 0 | S23: =IF(A23="","",IF(AND(F23<>"",ISNUMBER(G23),ISNUMBER(IFERROR(INDEX(Precios!$D$5:$D$120,MATCH(F23,Precios!$A$5:$A$120,0)),"x")),OR(H23="",ISNUMBER(IFERROR(INDEX(Precios!$D$5:$D$120,MATCH(H23,Precios!$A$5:$A$120,0)),"x"))),J23<>"",K23<>"",Q23>0),SUM(O23:R23),"")) | T23: =IF(A23="","",IF(S23<>"",IF(AND(N(J23)>0,Parametros!$B$27=0),"Lista (sin costo de impresión)","Lista"),IF(F23="","Tela. ","")&IF(NOT(ISNUMBER(G23)),"Kg de tela. ","")&IF(AND(F23<>"",NOT(ISNUMBER(IFERROR(INDEX(Precios!$D$5:$D$120,MATCH(F23,Precios!$A$5:$A$120,0)),"x")))),"Tela sin precio. ","")&IF(J23="","Metros impresos. ","")&IF(K23="","Confección. ",IF(Q23=0,"Confección sin valor. ","")))) -> Tela. Kg de tela. Metros impresos.
A24: 20 · FUTINHOMU02 | B24: Fútbol infantil, raglán, cuello redondo | C24: Fútbol | D24: Camiseta | E24: Infantil Masculino | K24: Camiseta Futbol Molde 2026 (Raglan) | M24: Por confirmar | N24: Confección sugerida por el tipo de molde: confirmar. | O24: =IF(A24="","",IFERROR(G24*INDEX(Precios!$D$5:$D$120,MATCH(F24,Precios!$A$5:$A$120,0)),0)+IF(H24="",0,IFERROR(I24*INDEX(Precios!$D$5:$D$120,MATCH(H24,Precios!$A$5:$A$120,0)),0))) -> 0 | P24: =IF(A24="","",N(J24)*Parametros!$B$27) -> 0 | Q24: =IF(A24="","",IFERROR(INDEX(Confeccion!$B$5:$B$100,MATCH(K24,Confeccion!$A$5:$A$100,0)),0)) -> 2300 | R24: =IF(A24="","",N(L24)) -> 0 | S24: =IF(A24="","",IF(AND(F24<>"",ISNUMBER(G24),ISNUMBER(IFERROR(INDEX(Precios!$D$5:$D$120,MATCH(F24,Precios!$A$5:$A$120,0)),"x")),OR(H24="",ISNUMBER(IFERROR(INDEX(Precios!$D$5:$D$120,MATCH(H24,Precios!$A$5:$A$120,0)),"x"))),J24<>"",K24<>"",Q24>0),SUM(O24:R24),"")) | T24: =IF(A24="","",IF(S24<>"",IF(AND(N(J24)>0,Parametros!$B$27=0),"Lista (sin costo de impresión)","Lista"),IF(F24="","Tela. ","")&IF(NOT(ISNUMBER(G24)),"Kg de tela. ","")&IF(AND(F24<>"",NOT(ISNUMBER(IFERROR(INDEX(Precios!$D$5:$D$120,MATCH(F24,Precios!$A$5:$A$120,0)),"x")))),"Tela sin precio. ","")&IF(J24="","Metros impresos. ","")&IF(K24="","Confección. ",IF(Q24=0,"Confección sin valor. ","")))) -> Tela. Kg de tela. Metros impresos.
A25: 21 · FUTMUJV02 | B25: Fútbol, raglán, cuello v | C25: Fútbol | D25: Camiseta | E25: Femenino | K25: Camiseta Futbol Molde 2026 (Raglan) | M25: Por confirmar | N25: Confección sugerida por el tipo de molde: confirmar. | O25: =IF(A25="","",IFERROR(G25*INDEX(Precios!$D$5:$D$120,MATCH(F25,Precios!$A$5:$A$120,0)),0)+IF(H25="",0,IFERROR(I25*INDEX(Precios!$D$5:$D$120,MATCH(H25,Precios!$A$5:$A$120,0)),0))) -> 0 | P25: =IF(A25="","",N(J25)*Parametros!$B$27) -> 0 | Q25: =IF(A25="","",IFERROR(INDEX(Confeccion!$B$5:$B$100,MATCH(K25,Confeccion!$A$5:$A$100,0)),0)) -> 2300 | R25: =IF(A25="","",N(L25)) -> 0 | S25: =IF(A25="","",IF(AND(F25<>"",ISNUMBER(G25),ISNUMBER(IFERROR(INDEX(Precios!$D$5:$D$120,MATCH(F25,Precios!$A$5:$A$120,0)),"x")),OR(H25="",ISNUMBER(IFERROR(INDEX(Precios!$D$5:$D$120,MATCH(H25,Precios!$A$5:$A$120,0)),"x"))),J25<>"",K25<>"",Q25>0),SUM(O25:R25),"")) | T25: =IF(A25="","",IF(S25<>"",IF(AND(N(J25)>0,Parametros!$B$27=0),"Lista (sin costo de impresión)","Lista"),IF(F25="","Tela. ","")&IF(NOT(ISNUMBER(G25)),"Kg de tela. ","")&IF(AND(F25<>"",NOT(ISNUMBER(IFERROR(INDEX(Precios!$D$5:$D$120,MATCH(F25,Precios!$A$5:$A$120,0)),"x")))),"Tela sin precio. ","")&IF(J25="","Metros impresos. ","")&IF(K25="","Confección. ",IF(Q25=0,"Confección sin valor. ","")))) -> Tela. Kg de tela. Metros impresos.
A26: 22 · FUTHOMV02 | B26: Fútbol, raglán, cuello v | C26: Fútbol | D26: Camiseta | E26: Masculino | K26: Camiseta Futbol Molde 2026 (Raglan) | M26: Por confirmar | N26: Confección sugerida por el tipo de molde: confirmar. | O26: =IF(A26="","",IFERROR(G26*INDEX(Precios!$D$5:$D$120,MATCH(F26,Precios!$A$5:$A$120,0)),0)+IF(H26="",0,IFERROR(I26*INDEX(Precios!$D$5:$D$120,MATCH(H26,Precios!$A$5:$A$120,0)),0))) -> 0 | P26: =IF(A26="","",N(J26)*Parametros!$B$27) -> 0 | Q26: =IF(A26="","",IFERROR(INDEX(Confeccion!$B$5:$B$100,MATCH(K26,Confeccion!$A$5:$A$100,0)),0)) -> 2300 | R26: =IF(A26="","",N(L26)) -> 0 | S26: =IF(A26="","",IF(AND(F26<>"",ISNUMBER(G26),ISNUMBER(IFERROR(INDEX(Precios!$D$5:$D$120,MATCH(F26,Precios!$A$5:$A$120,0)),"x")),OR(H26="",ISNUMBER(IFERROR(INDEX(Precios!$D$5:$D$120,MATCH(H26,Precios!$A$5:$A$120,0)),"x"))),J26<>"",K26<>"",Q26>0),SUM(O26:R26),"")) | T26: =IF(A26="","",IF(S26<>"",IF(AND(N(J26)>0,Parametros!$B$27=0),"Lista (sin costo de impresión)","Lista"),IF(F26="","Tela. ","")&IF(NOT(ISNUMBER(G26)),"Kg de tela. ","")&IF(AND(F26<>"",NOT(ISNUMBER(IFERROR(INDEX(Precios!$D$5:$D$120,MATCH(F26,Precios!$A$5:$A$120,0)),"x")))),"Tela sin precio. ","")&IF(J26="","Metros impresos. ","")&IF(K26="","Confección. ",IF(Q26=0,"Confección sin valor. ","")))) -> Tela. Kg de tela. Metros impresos.
A27: 23 · FUTINMUJV02 | B27: Fútbol infantil, raglán, cuello v | C27: Fútbol | D27: Camiseta | E27: Infantil Femenino | K27: Camiseta Futbol Molde 2026 (Raglan) | M27: Por confirmar | N27: Confección sugerida por el tipo de molde: confirmar. | O27: =IF(A27="","",IFERROR(G27*INDEX(Precios!$D$5:$D$120,MATCH(F27,Precios!$A$5:$A$120,0)),0)+IF(H27="",0,IFERROR(I27*INDEX(Precios!$D$5:$D$120,MATCH(H27,Precios!$A$5:$A$120,0)),0))) -> 0 | P27: =IF(A27="","",N(J27)*Parametros!$B$27) -> 0 | Q27: =IF(A27="","",IFERROR(INDEX(Confeccion!$B$5:$B$100,MATCH(K27,Confeccion!$A$5:$A$100,0)),0)) -> 2300 | R27: =IF(A27="","",N(L27)) -> 0 | S27: =IF(A27="","",IF(AND(F27<>"",ISNUMBER(G27),ISNUMBER(IFERROR(INDEX(Precios!$D$5:$D$120,MATCH(F27,Precios!$A$5:$A$120,0)),"x")),OR(H27="",ISNUMBER(IFERROR(INDEX(Precios!$D$5:$D$120,MATCH(H27,Precios!$A$5:$A$120,0)),"x"))),J27<>"",K27<>"",Q27>0),SUM(O27:R27),"")) | T27: =IF(A27="","",IF(S27<>"",IF(AND(N(J27)>0,Parametros!$B$27=0),"Lista (sin costo de impresión)","Lista"),IF(F27="","Tela. ","")&IF(NOT(ISNUMBER(G27)),"Kg de tela. ","")&IF(AND(F27<>"",NOT(ISNUMBER(IFERROR(INDEX(Precios!$D$5:$D$120,MATCH(F27,Precios!$A$5:$A$120,0)),"x")))),"Tela sin precio. ","")&IF(J27="","Metros impresos. ","")&IF(K27="","Confección. ",IF(Q27=0,"Confección sin valor. ","")))) -> Tela. Kg de tela. Metros impresos.
A28: 24 · FUTINHOMV02 | B28: Fútbol infantil, raglán, cuello v | C28: Fútbol | D28: Camiseta | E28: Infantil Masculino | K28: Camiseta Futbol Molde 2026 (Raglan) | M28: Por confirmar | N28: Confección sugerida por el tipo de molde: confirmar. | O28: =IF(A28="","",IFERROR(G28*INDEX(Precios!$D$5:$D$120,MATCH(F28,Precios!$A$5:$A$120,0)),0)+IF(H28="",0,IFERROR(I28*INDEX(Precios!$D$5:$D$120,MATCH(H28,Precios!$A$5:$A$120,0)),0))) -> 0 | P28: =IF(A28="","",N(J28)*Parametros!$B$27) -> 0 | Q28: =IF(A28="","",IFERROR(INDEX(Confeccion!$B$5:$B$100,MATCH(K28,Confeccion!$A$5:$A$100,0)),0)) -> 2300 | R28: =IF(A28="","",N(L28)) -> 0 | S28: =IF(A28="","",IF(AND(F28<>"",ISNUMBER(G28),ISNUMBER(IFERROR(INDEX(Precios!$D$5:$D$120,MATCH(F28,Precios!$A$5:$A$120,0)),"x")),OR(H28="",ISNUMBER(IFERROR(INDEX(Precios!$D$5:$D$120,MATCH(H28,Precios!$A$5:$A$120,0)),"x"))),J28<>"",K28<>"",Q28>0),SUM(O28:R28),"")) | T28: =IF(A28="","",IF(S28<>"",IF(AND(N(J28)>0,Parametros!$B$27=0),"Lista (sin costo de impresión)","Lista"),IF(F28="","Tela. ","")&IF(NOT(ISNUMBER(G28)),"Kg de tela. ","")&IF(AND(F28<>"",NOT(ISNUMBER(IFERROR(INDEX(Precios!$D$5:$D$120,MATCH(F28,Precios!$A$5:$A$120,0)),"x")))),"Tela sin precio. ","")&IF(J28="","Metros impresos. ","")&IF(K28="","Confección. ",IF(Q28=0,"Confección sin valor. ","")))) -> Tela. Kg de tela. Metros impresos.
A29: 25 · FUTMUJU02PRO | B29: Fútbol, raglán, pro, cuello redondo | C29: Fútbol | D29: Camiseta | E29: Femenino | K29: Camiseta Futbol Molde 2026 (Raglan) | M29: Por confirmar | N29: Confección sugerida por el tipo de molde: confirmar. | O29: =IF(A29="","",IFERROR(G29*INDEX(Precios!$D$5:$D$120,MATCH(F29,Precios!$A$5:$A$120,0)),0)+IF(H29="",0,IFERROR(I29*INDEX(Precios!$D$5:$D$120,MATCH(H29,Precios!$A$5:$A$120,0)),0))) -> 0 | P29: =IF(A29="","",N(J29)*Parametros!$B$27) -> 0 | Q29: =IF(A29="","",IFERROR(INDEX(Confeccion!$B$5:$B$100,MATCH(K29,Confeccion!$A$5:$A$100,0)),0)) -> 2300 | R29: =IF(A29="","",N(L29)) -> 0 | S29: =IF(A29="","",IF(AND(F29<>"",ISNUMBER(G29),ISNUMBER(IFERROR(INDEX(Precios!$D$5:$D$120,MATCH(F29,Precios!$A$5:$A$120,0)),"x")),OR(H29="",ISNUMBER(IFERROR(INDEX(Precios!$D$5:$D$120,MATCH(H29,Precios!$A$5:$A$120,0)),"x"))),J29<>"",K29<>"",Q29>0),SUM(O29:R29),"")) | T29: =IF(A29="","",IF(S29<>"",IF(AND(N(J29)>0,Parametros!$B$27=0),"Lista (sin costo de impresión)","Lista"),IF(F29="","Tela. ","")&IF(NOT(ISNUMBER(G29)),"Kg de tela. ","")&IF(AND(F29<>"",NOT(ISNUMBER(IFERROR(INDEX(Precios!$D$5:$D$120,MATCH(F29,Precios!$A$5:$A$120,0)),"x")))),"Tela sin precio. ","")&IF(J29="","Metros impresos. ","")&IF(K29="","Confección. ",IF(Q29=0,"Confección sin valor. ","")))) -> Tela. Kg de tela. Metros impresos.
A30: 26 · FUTHOMU02PRO | B30: Fútbol, raglán, pro, cuello redondo | C30: Fútbol | D30: Camiseta | E30: Masculino | K30: Camiseta Futbol Molde 2026 (Raglan) | M30: Por confirmar | N30: Confección sugerida por el tipo de molde: confirmar. | O30: =IF(A30="","",IFERROR(G30*INDEX(Precios!$D$5:$D$120,MATCH(F30,Precios!$A$5:$A$120,0)),0)+IF(H30="",0,IFERROR(I30*INDEX(Precios!$D$5:$D$120,MATCH(H30,Precios!$A$5:$A$120,0)),0))) -> 0 | P30: =IF(A30="","",N(J30)*Parametros!$B$27) -> 0 | Q30: =IF(A30="","",IFERROR(INDEX(Confeccion!$B$5:$B$100,MATCH(K30,Confeccion!$A$5:$A$100,0)),0)) -> 2300 | R30: =IF(A30="","",N(L30)) -> 0 | S30: =IF(A30="","",IF(AND(F30<>"",ISNUMBER(G30),ISNUMBER(IFERROR(INDEX(Precios!$D$5:$D$120,MATCH(F30,Precios!$A$5:$A$120,0)),"x")),OR(H30="",ISNUMBER(IFERROR(INDEX(Precios!$D$5:$D$120,MATCH(H30,Precios!$A$5:$A$120,0)),"x"))),J30<>"",K30<>"",Q30>0),SUM(O30:R30),"")) | T30: =IF(A30="","",IF(S30<>"",IF(AND(N(J30)>0,Parametros!$B$27=0),"Lista (sin costo de impresión)","Lista"),IF(F30="","Tela. ","")&IF(NOT(ISNUMBER(G30)),"Kg de tela. ","")&IF(AND(F30<>"",NOT(ISNUMBER(IFERROR(INDEX(Precios!$D$5:$D$120,MATCH(F30,Precios!$A$5:$A$120,0)),"x")))),"Tela sin precio. ","")&IF(J30="","Metros impresos. ","")&IF(K30="","Confección. ",IF(Q30=0,"Confección sin valor. ","")))) -> Tela. Kg de tela. Metros impresos.
... A33: 29 · BKMUJU03 | B33: Básquetbol, cuello redondo | C33: Básquetbol | D33: Camiseta | E33: Femenino | K33: Camiseta De Basket | M33: Por confirmar | N33: Confección sugerida por el tipo de molde: confirmar. | O33: =IF(A33="","",IFERROR(G33*INDEX(Precios!$D$5:$D$120,MATCH(F33,Precios!$A$5:$A$120,0)),0)+IF(H33="",0,IFERROR(I33*INDEX(Precios!$D$5:$D$120,MATCH(H33,Precios!$A$5:$A$120,0)),0))) -> 0 | P33: =IF(A33="","",N(J33)*Parametros!$B$27) -> 0 | Q33: =IF(A33="","",IFERROR(INDEX(Confeccion!$B$5:$B$100,MATCH(K33,Confeccion!$A$5:$A$100,0)),0)) -> 1900 | R33: =IF(A33="","",N(L33)) -> 0 | S33: =IF(A33="","",IF(AND(F33<>"",ISNUMBER(G33),ISNUMBER(IFERROR(INDEX(Precios!$D$5:$D$120,MATCH(F33,Precios!$A$5:$A$120,0)),"x")),OR(H33="",ISNUMBER(IFERROR(INDEX(Precios!$D$5:$D$120,MATCH(H33,Precios!$A$5:$A$120,0)),"x"))),J33<>"",K33<>"",Q33>0),SUM(O33:R33),"")) | T33: =IF(A33="","",IF(S33<>"",IF(AND(N(J33)>0,Parametros!$B$27=0),"Lista (sin costo de impresión)","Lista"),IF(F33="","Tela. ","")&IF(NOT(ISNUMBER(G33)),"Kg de tela. ","")&IF(AND(F33<>"",NOT(ISNUMBER(IFERROR(INDEX(Precios!$D$5:$D$120,MATCH(F33,Precios!$A$5:$A$120,0)),"x")))),"Tela sin precio. ","")&IF(J33="","Metros impresos. ","")&IF(K33="","Confección. ",IF(Q33=0,"Confección sin valor. ","")))) -> Tela. Kg de tela. Metros impresos.
A34: 30 · BKHOMU03 | B34: Básquetbol, cuello redondo | C34: Básquetbol | D34: Camiseta | E34: Masculino | F34: QUICKDRY | G34: 0.2029 | K34: Camiseta De Basket | M34: Por confirmar | N34: Ficha OT 2425 (17 camisetas básquet). Falta metros impresos. | O34: =IF(A34="","",IFERROR(G34*INDEX(Precios!$D$5:$D$120,MATCH(F34,Precios!$A$5:$A$120,0)),0)+IF(H34="",0,IFERROR(I34*INDEX(Precios!$D$5:$D$120,MATCH(H34,Precios!$A$5:$A$120,0)),0))) -> 1419.4884 | P34: =IF(A34="","",N(J34)*Parametros!$B$27) -> 0 | Q34: =IF(A34="","",IFERROR(INDEX(Confeccion!$B$5:$B$100,MATCH(K34,Confeccion!$A$5:$A$100,0)),0)) -> 1900 | R34: =IF(A34="","",N(L34)) -> 0 | S34: =IF(A34="","",IF(AND(F34<>"",ISNUMBER(G34),ISNUMBER(IFERROR(INDEX(Precios!$D$5:$D$120,MATCH(F34,Precios!$A$5:$A$120,0)),"x")),OR(H34="",ISNUMBER(IFERROR(INDEX(Precios!$D$5:$D$120,MATCH(H34,Precios!$A$5:$A$120,0)),"x"))),J34<>"",K34<>"",Q34>0),SUM(O34:R34),"")) | T34: =IF(A34="","",IF(S34<>"",IF(AND(N(J34)>0,Parametros!$B$27=0),"Lista (sin costo de impresión)","Lista"),IF(F34="","Tela. ","")&IF(NOT(ISNUMBER(G34)),"Kg de tela. ","")&IF(AND(F34<>"",NOT(ISNUMBER(IFERROR(INDEX(Precios!$D$5:$D$120,MATCH(F34,Precios!$A$5:$A$120,0)),"x")))),"Tela sin precio. ","")&IF(J34="","Metros impresos. ","")&IF(K34="","Confección. ",IF(Q34=0,"Confección sin valor. ","")))) -> Metros impresos.
A35: 31 · BKINMUJU03 | B35: Básquetbol infantil, cuello redondo | C35: Básquetbol | D35: Camiseta | E35: Infantil Femenino | K35: Camiseta De Basket | M35: Por confirmar | N35: Confección sugerida por el tipo de molde: confirmar. | O35: =IF(A35="","",IFERROR(G35*INDEX(Precios!$D$5:$D$120,MATCH(F35,Precios!$A$5:$A$120,0)),0)+IF(H35="",0,IFERROR(I35*INDEX(Precios!$D$5:$D$120,MATCH(H35,Precios!$A$5:$A$120,0)),0))) -> 0 | P35: =IF(A35="","",N(J35)*Parametros!$B$27) -> 0 | Q35: =IF(A35="","",IFERROR(INDEX(Confeccion!$B$5:$B$100,MATCH(K35,Confeccion!$A$5:$A$100,0)),0)) -> 1900 | R35: =IF(A35="","",N(L35)) -> 0 | S35: =IF(A35="","",IF(AND(F35<>"",ISNUMBER(G35),ISNUMBER(IFERROR(INDEX(Precios!$D$5:$D$120,MATCH(F35,Precios!$A$5:$A$120,0)),"x")),OR(H35="",ISNUMBER(IFERROR(INDEX(Precios!$D$5:$D$120,MATCH(H35,Precios!$A$5:$A$120,0)),"x"))),J35<>"",K35<>"",Q35>0),SUM(O35:R35),"")) | T35: =IF(A35="","",IF(S35<>"",IF(AND(N(J35)>0,Parametros!$B$27=0),"Lista (sin costo de impresión)","Lista"),IF(F35="","Tela. ","")&IF(NOT(ISNUMBER(G35)),"Kg de tela. ","")&IF(AND(F35<>"",NOT(ISNUMBER(IFERROR(INDEX(Precios!$D$5:$D$120,MATCH(F35,Precios!$A$5:$A$120,0)),"x")))),"Tela sin precio. ","")&IF(J35="","Metros impresos. ","")&IF(K35="","Confección. ",IF(Q35=0,"Confección sin valor. ","")))) -> Tela. Kg de tela. Metros impresos.
A36: 32 · BKINHOMU03 | B36: Básquetbol infantil, cuello redondo | C36: Básquetbol | D36: Camiseta | E36: Infantil Masculino | K36: Camiseta De Basket | M36: Por confirmar | N36: Confección sugerida por el tipo de molde: confirmar. | O36: =IF(A36="","",IFERROR(G36*INDEX(Precios!$D$5:$D$120,MATCH(F36,Precios!$A$5:$A$120,0)),0)+IF(H36="",0,IFERROR(I36*INDEX(Precios!$D$5:$D$120,MATCH(H36,Precios!$A$5:$A$120,0)),0))) -> 0 | P36: =IF(A36="","",N(J36)*Parametros!$B$27) -> 0 | Q36: =IF(A36="","",IFERROR(INDEX(Confeccion!$B$5:$B$100,MATCH(K36,Confeccion!$A$5:$A$100,0)),0)) -> 1900 | R36: =IF(A36="","",N(L36)) -> 0 | S36: =IF(A36="","",IF(AND(F36<>"",ISNUMBER(G36),ISNUMBER(IFERROR(INDEX(Precios!$D$5:$D$120,MATCH(F36,Precios!$A$5:$A$120,0)),"x")),OR(H36="",ISNUMBER(IFERROR(INDEX(Precios!$D$5:$D$120,MATCH(H36,Precios!$A$5:$A$120,0)),"x"))),J36<>"",K36<>"",Q36>0),SUM(O36:R36),"")) | T36: =IF(A36="","",IF(S36<>"",IF(AND(N(J36)>0,Parametros!$B$27=0),"Lista (sin costo de impresión)","Lista"),IF(F36="","Tela. ","")&IF(NOT(ISNUMBER(G36)),"Kg de tela. ","")&IF(AND(F36<>"",NOT(ISNUMBER(IFERROR(INDEX(Precios!$D$5:$D$120,MATCH(F36,Precios!$A$5:$A$120,0)),"x")))),"Tela sin precio. ","")&IF(J36="","Metros impresos. ","")&IF(K36="","Confección. ",IF(Q36=0,"Confección sin valor. ","")))) -> Tela. Kg de tela. Metros impresos.
A37: 33 · BKMUJV03 | B37: Básquetbol, cuello v | C37: Básquetbol | D37: Camiseta | E37: Femenino | K37: Camiseta De Basket | M37: Por confirmar | N37: Confección sugerida por el tipo de molde: confirmar. | O37: =IF(A37="","",IFERROR(G37*INDEX(Precios!$D$5:$D$120,MATCH(F37,Precios!$A$5:$A$120,0)),0)+IF(H37="",0,IFERROR(I37*INDEX(Precios!$D$5:$D$120,MATCH(H37,Precios!$A$5:$A$120,0)),0))) -> 0 | P37: =IF(A37="","",N(J37)*Parametros!$B$27) -> 0 | Q37: =IF(A37="","",IFERROR(INDEX(Confeccion!$B$5:$B$100,MATCH(K37,Confeccion!$A$5:$A$100,0)),0)) -> 1900 | R37: =IF(A37="","",N(L37)) -> 0 | S37: =IF(A37="","",IF(AND(F37<>"",ISNUMBER(G37),ISNUMBER(IFERROR(INDEX(Precios!$D$5:$D$120,MATCH(F37,Precios!$A$5:$A$120,0)),"x")),OR(H37="",ISNUMBER(IFERROR(INDEX(Precios!$D$5:$D$120,MATCH(H37,Precios!$A$5:$A$120,0)),"x"))),J37<>"",K37<>"",Q37>0),SUM(O37:R37),"")) | T37: =IF(A37="","",IF(S37<>"",IF(AND(N(J37)>0,Parametros!$B$27=0),"Lista (sin costo de impresión)","Lista"),IF(F37="","Tela. ","")&IF(NOT(ISNUMBER(G37)),"Kg de tela. ","")&IF(AND(F37<>"",NOT(ISNUMBER(IFERROR(INDEX(Precios!$D$5:$D$120,MATCH(F37,Precios!$A$5:$A$120,0)),"x")))),"Tela sin precio. ","")&IF(J37="","Metros impresos. ","")&IF(K37="","Confección. ",IF(Q37=0,"Confección sin valor. ","")))) -> Tela. Kg de tela. Metros impresos.
A38: 34 · BKHOMV03 | B38: Básquetbol, cuello v | C38: Básquetbol | D38: Camiseta | E38: Masculino | K38: Camiseta De Basket | M38: Por confirmar | N38: Confección sugerida por el tipo de molde: confirmar. | O38: =IF(A38="","",IFERROR(G38*INDEX(Precios!$D$5:$D$120,MATCH(F38,Precios!$A$5:$A$120,0)),0)+IF(H38="",0,IFERROR(I38*INDEX(Precios!$D$5:$D$120,MATCH(H38,Precios!$A$5:$A$120,0)),0))) -> 0 | P38: =IF(A38="","",N(J38)*Parametros!$B$27) -> 0 | Q38: =IF(A38="","",IFERROR(INDEX(Confeccion!$B$5:$B$100,MATCH(K38,Confeccion!$A$5:$A$100,0)),0)) -> 1900 | R38: =IF(A38="","",N(L38)) -> 0 | S38: =IF(A38="","",IF(AND(F38<>"",ISNUMBER(G38),ISNUMBER(IFERROR(INDEX(Precios!$D$5:$D$120,MATCH(F38,Precios!$A$5:$A$120,0)),"x")),OR(H38="",ISNUMBER(IFERROR(INDEX(Precios!$D$5:$D$120,MATCH(H38,Precios!$A$5:$A$120,0)),"x"))),J38<>"",K38<>"",Q38>0),SUM(O38:R38),"")) | T38: =IF(A38="","",IF(S38<>"",IF(AND(N(J38)>0,Parametros!$B$27=0),"Lista (sin costo de impresión)","Lista"),IF(F38="","Tela. ","")&IF(NOT(ISNUMBER(G38)),"Kg de tela. ","")&IF(AND(F38<>"",NOT(ISNUMBER(IFERROR(INDEX(Precios!$D$5:$D$120,MATCH(F38,Precios!$A$5:$A$120,0)),"x")))),"Tela sin precio. ","")&IF(J38="","Metros impresos. ","")&IF(K38="","Confección. ",IF(Q38=0,"Confección sin valor. ","")))) -> Tela. Kg de tela. Metros impresos.
A39: 35 · BKINMUJV03 | B39: Básquetbol infantil, cuello v | C39: Básquetbol | D39: Camiseta | E39: Infantil Femenino | K39: Camiseta De Basket | M39: Por confirmar | N39: Confección sugerida por el tipo de molde: confirmar. | O39: =IF(A39="","",IFERROR(G39*INDEX(Precios!$D$5:$D$120,MATCH(F39,Precios!$A$5:$A$120,0)),0)+IF(H39="",0,IFERROR(I39*INDEX(Precios!$D$5:$D$120,MATCH(H39,Precios!$A$5:$A$120,0)),0))) -> 0 | P39: =IF(A39="","",N(J39)*Parametros!$B$27) -> 0 | Q39: =IF(A39="","",IFERROR(INDEX(Confeccion!$B$5:$B$100,MATCH(K39,Confeccion!$A$5:$A$100,0)),0)) -> 1900 | R39: =IF(A39="","",N(L39)) -> 0 | S39: =IF(A39="","",IF(AND(F39<>"",ISNUMBER(G39),ISNUMBER(IFERROR(INDEX(Precios!$D$5:$D$120,MATCH(F39,Precios!$A$5:$A$120,0)),"x")),OR(H39="",ISNUMBER(IFERROR(INDEX(Precios!$D$5:$D$120,MATCH(H39,Precios!$A$5:$A$120,0)),"x"))),J39<>"",K39<>"",Q39>0),SUM(O39:R39),"")) | T39: =IF(A39="","",IF(S39<>"",IF(AND(N(J39)>0,Parametros!$B$27=0),"Lista (sin costo de impresión)","Lista"),IF(F39="","Tela. ","")&IF(NOT(ISNUMBER(G39)),"Kg de tela. ","")&IF(AND(F39<>"",NOT(ISNUMBER(IFERROR(INDEX(Precios!$D$5:$D$120,MATCH(F39,Precios!$A$5:$A$120,0)),"x")))),"Tela sin precio. ","")&IF(J39="","Metros impresos. ","")&IF(K39="","Confección. ",IF(Q39=0,"Confección sin valor. ","")))) -> Tela. Kg de tela. Metros impresos.
A40: 36 · BKINHOMV03 | B40: Básquetbol infantil, cuello v | C40: Básquetbol | D40: Camiseta | E40: Infantil Masculino | K40: Camiseta De Basket | M40: Por confirmar | N40: Confección sugerida por el tipo de molde: confirmar. | O40: =IF(A40="","",IFERROR(G40*INDEX(Precios!$D$5:$D$120,MATCH(F40,Precios!$A$5:$A$120,0)),0)+IF(H40="",0,IFERROR(I40*INDEX(Precios!$D$5:$D$120,MATCH(H40,Precios!$A$5:$A$120,0)),0))) -> 0 | P40: =IF(A40="","",N(J40)*Parametros!$B$27) -> 0 | Q40: =IF(A40="","",IFERROR(INDEX(Confeccion!$B$5:$B$100,MATCH(K40,Confeccion!$A$5:$A$100,0)),0)) -> 1900 | R40: =IF(A40="","",N(L40)) -> 0 | S40: =IF(A40="","",IF(AND(F40<>"",ISNUMBER(G40),ISNUMBER(IFERROR(INDEX(Precios!$D$5:$D$120,MATCH(F40,Precios!$A$5:$A$120,0)),"x")),OR(H40="",ISNUMBER(IFERROR(INDEX(Precios!$D$5:$D$120,MATCH(H40,Precios!$A$5:$A$120,0)),"x"))),J40<>"",K40<>"",Q40>0),SUM(O40:R40),"")) | T40: =IF(A40="","",IF(S40<>"",IF(AND(N(J40)>0,Parametros!$B$27=0),"Lista (sin costo de impresión)","Lista"),IF(F40="","Tela. ","")&IF(NOT(ISNUMBER(G40)),"Kg de tela. ","")&IF(AND(F40<>"",NOT(ISNUMBER(IFERROR(INDEX(Precios!$D$5:$D$120,MATCH(F40,Precios!$A$5:$A$120,0)),"x")))),"Tela sin precio. ","")&IF(J40="","Metros impresos. ","")&IF(K40="","Confección. ",IF(Q40=0,"Confección sin valor. ","")))) -> Tela. Kg de tela. Metros impresos.
A41: 37 · BKMUJU03RE | B41: Básquetbol, reversible, cuello redondo | C41: Básquetbol | D41: Camiseta | E41: Femenino | K41: Camiseta De Basket Reversible | M41: Por confirmar | N41: Confección sugerida por el tipo de molde: confirmar. | O41: =IF(A41="","",IFERROR(G41*INDEX(Precios!$D$5:$D$120,MATCH(F41,Precios!$A$5:$A$120,0)),0)+IF(H41="",0,IFERROR(I41*INDEX(Precios!$D$5:$D$120,MATCH(H41,Precios!$A$5:$A$120,0)),0))) -> 0 | P41: =IF(A41="","",N(J41)*Parametros!$B$27) -> 0 | Q41: =IF(A41="","",IFERROR(INDEX(Confeccion!$B$5:$B$100,MATCH(K41,Confeccion!$A$5:$A$100,0)),0)) -> 2400 | R41: =IF(A41="","",N(L41)) -> 0 | S41: =IF(A41="","",IF(AND(F41<>"",ISNUMBER(G41),ISNUMBER(IFERROR(INDEX(Precios!$D$5:$D$120,MATCH(F41,Precios!$A$5:$A$120,0)),"x")),OR(H41="",ISNUMBER(IFERROR(INDEX(Precios!$D$5:$D$120,MATCH(H41,Precios!$A$5:$A$120,0)),"x"))),J41<>"",K41<>"",Q41>0),SUM(O41:R41),"")) | T41: =IF(A41="","",IF(S41<>"",IF(AND(N(J41)>0,Parametros!$B$27=0),"Lista (sin costo de impresión)","Lista"),IF(F41="","Tela. ","")&IF(NOT(ISNUMBER(G41)),"Kg de tela. ","")&IF(AND(F41<>"",NOT(ISNUMBER(IFERROR(INDEX(Precios!$D$5:$D$120,MATCH(F41,Precios!$A$5:$A$120,0)),"x")))),"Tela sin precio. ","")&IF(J41="","Metros impresos. ","")&IF(K41="","Confección. ",IF(Q41=0,"Confección sin valor. ","")))) -> Tela. Kg de tela. Metros impresos.
A42: 38 · BKHOMU03RE | B42: Básquetbol, reversible, cuello redondo | C42: Básquetbol | D42: Camiseta | E42: Masculino | K42: Camiseta De Basket Reversible | M42: Por confirmar | N42: Confección sugerida por el tipo de molde: confirmar. | O42: =IF(A42="","",IFERROR(G42*INDEX(Precios!$D$5:$D$120,MATCH(F42,Precios!$A$5:$A$120,0)),0)+IF(H42="",0,IFERROR(I42*INDEX(Precios!$D$5:$D$120,MATCH(H42,Precios!$A$5:$A$120,0)),0))) -> 0 | P42: =IF(A42="","",N(J42)*Parametros!$B$27) -> 0 | Q42: =IF(A42="","",IFERROR(INDEX(Confeccion!$B$5:$B$100,MATCH(K42,Confeccion!$A$5:$A$100,0)),0)) -> 2400 | R42: =IF(A42="","",N(L42)) -> 0 | S42: =IF(A42="","",IF(AND(F42<>"",ISNUMBER(G42),ISNUMBER(IFERROR(INDEX(Precios!$D$5:$D$120,MATCH(F42,Precios!$A$5:$A$120,0)),"x")),OR(H42="",ISNUMBER(IFERROR(INDEX(Precios!$D$5:$D$120,MATCH(H42,Precios!$A$5:$A$120,0)),"x"))),J42<>"",K42<>"",Q42>0),SUM(O42:R42),"")) | T42: =IF(A42="","",IF(S42<>"",IF(AND(N(J42)>0,Parametros!$B$27=0),"Lista (sin costo de impresión)","Lista"),IF(F42="","Tela. ","")&IF(NOT(ISNUMBER(G42)),"Kg de tela. ","")&IF(AND(F42<>"",NOT(ISNUMBER(IFERROR(INDEX(Precios!$D$5:$D$120,MATCH(F42,Precios!$A$5:$A$120,0)),"x")))),"Tela sin precio. ","")&IF(J42="","Metros impresos. ","")&IF(K42="","Confección. ",IF(Q42=0,"Confección sin valor. ","")))) -> Tela. Kg de tela. Metros impresos.
A43: 39 · BKINMUJU03 | B43: Básquetbol infantil, reversible, cuello redondo | C43: Básquetbol | D43: Camiseta | E43: Infantil Femenino | K43: Camiseta De Basket Reversible | M43: Por confirmar | N43: Confección sugerida por el tipo de molde: confirmar. | O43: =IF(A43="","",IFERROR(G43*INDEX(Precios!$D$5:$D$120,MATCH(F43,Precios!$A$5:$A$120,0)),0)+IF(H43="",0,IFERROR(I43*INDEX(Precios!$D$5:$D$120,MATCH(H43,Precios!$A$5:$A$120,0)),0))) -> 0 | P43: =IF(A43="","",N(J43)*Parametros!$B$27) -> 0 | Q43: =IF(A43="","",IFERROR(INDEX(Confeccion!$B$5:$B$100,MATCH(K43,Confeccion!$A$5:$A$100,0)),0)) -> 2400 | R43: =IF(A43="","",N(L43)) -> 0 | S43: =IF(A43="","",IF(AND(F43<>"",ISNUMBER(G43),ISNUMBER(IFERROR(INDEX(Precios!$D$5:$D$120,MATCH(F43,Precios!$A$5:$A$120,0)),"x")),OR(H43="",ISNUMBER(IFERROR(INDEX(Precios!$D$5:$D$120,MATCH(H43,Precios!$A$5:$A$120,0)),"x"))),J43<>"",K43<>"",Q43>0),SUM(O43:R43),"")) | T43: =IF(A43="","",IF(S43<>"",IF(AND(N(J43)>0,Parametros!$B$27=0),"Lista (sin costo de impresión)","Lista"),IF(F43="","Tela. ","")&IF(NOT(ISNUMBER(G43)),"Kg de tela. ","")&IF(AND(F43<>"",NOT(ISNUMBER(IFERROR(INDEX(Precios!$D$5:$D$120,MATCH(F43,Precios!$A$5:$A$120,0)),"x")))),"Tela sin precio. ","")&IF(J43="","Metros impresos. ","")&IF(K43="","Confección. ",IF(Q43=0,"Confección sin valor. ","")))) -> Tela. Kg de tela. Metros impresos.
A44: 40 · BKINHOMU03RE | B44: Básquetbol infantil, reversible, cuello redondo | C44: Básquetbol | D44: Camiseta | E44: Infantil Masculino | K44: Camiseta De Basket Reversible | M44: Por confirmar | N44: Confección sugerida por el tipo de molde: confirmar. | O44: =IF(A44="","",IFERROR(G44*INDEX(Precios!$D$5:$D$120,MATCH(F44,Precios!$A$5:$A$120,0)),0)+IF(H44="",0,IFERROR(I44*INDEX(Precios!$D$5:$D$120,MATCH(H44,Precios!$A$5:$A$120,0)),0))) -> 0 | P44: =IF(A44="","",N(J44)*Parametros!$B$27) -> 0 | Q44: =IF(A44="","",IFERROR(INDEX(Confeccion!$B$5:$B$100,MATCH(K44,Confeccion!$A$5:$A$100,0)),0)) -> 2400 | R44: =IF(A44="","",N(L44)) -> 0 | S44: =IF(A44="","",IF(AND(F44<>"",ISNUMBER(G44),ISNUMBER(IFERROR(INDEX(Precios!$D$5:$D$120,MATCH(F44,Precios!$A$5:$A$120,0)),"x")),OR(H44="",ISNUMBER(IFERROR(INDEX(Precios!$D$5:$D$120,MATCH(H44,Precios!$A$5:$A$120,0)),"x"))),J44<>"",K44<>"",Q44>0),SUM(O44:R44),"")) | T44: =IF(A44="","",IF(S44<>"",IF(AND(N(J44)>0,Parametros!$B$27=0),"Lista (sin costo de impresión)","Lista"),IF(F44="","Tela. ","")&IF(NOT(ISNUMBER(G44)),"Kg de tela. ","")&IF(AND(F44<>"",NOT(ISNUMBER(IFERROR(INDEX(Precios!$D$5:$D$120,MATCH(F44,Precios!$A$5:$A$120,0)),"x")))),"Tela sin precio. ","")&IF(J44="","Metros impresos. ","")&IF(K44="","Confección. ",IF(Q44=0,"Confección sin valor. ","")))) -> Tela. Kg de tela. Metros impresos.
A45: 41 · BKMUJU03PRO | B45: Básquetbol, pro, cuello redondo | C45: Básquetbol | D45: Camiseta | E45: Femenino | K45: Camiseta De Basket Pro | M45: Por confirmar | N45: Confección sugerida por el tipo de molde: confirmar. | O45: =IF(A45="","",IFERROR(G45*INDEX(Precios!$D$5:$D$120,MATCH(F45,Precios!$A$5:$A$120,0)),0)+IF(H45="",0,IFERROR(I45*INDEX(Precios!$D$5:$D$120,MATCH(H45,Precios!$A$5:$A$120,0)),0))) -> 0 | P45: =IF(A45="","",N(J45)*Parametros!$B$27) -> 0 | Q45: =IF(A45="","",IFERROR(INDEX(Confeccion!$B$5:$B$100,MATCH(K45,Confeccion!$A$5:$A$100,0)),0)) -> 2000 | R45: =IF(A45="","",N(L45)) -> 0 | S45: =IF(A45="","",IF(AND(F45<>"",ISNUMBER(G45),ISNUMBER(IFERROR(INDEX(Precios!$D$5:$D$120,MATCH(F45,Precios!$A$5:$A$120,0)),"x")),OR(H45="",ISNUMBER(IFERROR(INDEX(Precios!$D$5:$D$120,MATCH(H45,Precios!$A$5:$A$120,0)),"x"))),J45<>"",K45<>"",Q45>0),SUM(O45:R45),"")) | T45: =IF(A45="","",IF(S45<>"",IF(AND(N(J45)>0,Parametros!$B$27=0),"Lista (sin costo de impresión)","Lista"),IF(F45="","Tela. ","")&IF(NOT(ISNUMBER(G45)),"Kg de tela. ","")&IF(AND(F45<>"",NOT(ISNUMBER(IFERROR(INDEX(Precios!$D$5:$D$120,MATCH(F45,Precios!$A$5:$A$120,0)),"x")))),"Tela sin precio. ","")&IF(J45="","Metros impresos. ","")&IF(K45="","Confección. ",IF(Q45=0,"Confección sin valor. ","")))) -> Tela. Kg de tela. Metros impresos.
A46: 42 · BKHOMU03PRO | B46: Básquetbol, pro, cuello redondo | C46: Básquetbol | D46: Camiseta | E46: Masculino | K46: Camiseta De Basket Pro | M46: Por confirmar | N46: Confección sugerida por el tipo de molde: confirmar. | O46: =IF(A46="","",IFERROR(G46*INDEX(Precios!$D$5:$D$120,MATCH(F46,Precios!$A$5:$A$120,0)),0)+IF(H46="",0,IFERROR(I46*INDEX(Precios!$D$5:$D$120,MATCH(H46,Precios!$A$5:$A$120,0)),0))) -> 0 | P46: =IF(A46="","",N(J46)*Parametros!$B$27) -> 0 | Q46: =IF(A46="","",IFERROR(INDEX(Confeccion!$B$5:$B$100,MATCH(K46,Confeccion!$A$5:$A$100,0)),0)) -> 2000 | R46: =IF(A46="","",N(L46)) -> 0 | S46: =IF(A46="","",IF(AND(F46<>"",ISNUMBER(G46),ISNUMBER(IFERROR(INDEX(Precios!$D$5:$D$120,MATCH(F46,Precios!$A$5:$A$120,0)),"x")),OR(H46="",ISNUMBER(IFERROR(INDEX(Precios!$D$5:$D$120,MATCH(H46,Precios!$A$5:$A$120,0)),"x"))),J46<>"",K46<>"",Q46>0),SUM(O46:R46),"")) | T46: =IF(A46="","",IF(S46<>"",IF(AND(N(J46)>0,Parametros!$B$27=0),"Lista (sin costo de impresión)","Lista"),IF(F46="","Tela. ","")&IF(NOT(ISNUMBER(G46)),"Kg de tela. ","")&IF(AND(F46<>"",NOT(ISNUMBER(IFERROR(INDEX(Precios!$D$5:$D$120,MATCH(F46,Precios!$A$5:$A$120,0)),"x")))),"Tela sin precio. ","")&IF(J46="","Metros impresos. ","")&IF(K46="","Confección. ",IF(Q46=0,"Confección sin valor. ","")))) -> Tela. Kg de tela. Metros impresos.
... A49: 45 · BKSHMUJ | B49: Básquetbol | C49: Básquetbol | D49: Short | E49: Femenino | K49: Short De Basket | M49: Por confirmar | N49: Confección sugerida por el tipo de molde: confirmar. | O49: =IF(A49="","",IFERROR(G49*INDEX(Precios!$D$5:$D$120,MATCH(F49,Precios!$A$5:$A$120,0)),0)+IF(H49="",0,IFERROR(I49*INDEX(Precios!$D$5:$D$120,MATCH(H49,Precios!$A$5:$A$120,0)),0))) -> 0 | P49: =IF(A49="","",N(J49)*Parametros!$B$27) -> 0 | Q49: =IF(A49="","",IFERROR(INDEX(Confeccion!$B$5:$B$100,MATCH(K49,Confeccion!$A$5:$A$100,0)),0)) -> 1900 | R49: =IF(A49="","",N(L49)) -> 0 | S49: =IF(A49="","",IF(AND(F49<>"",ISNUMBER(G49),ISNUMBER(IFERROR(INDEX(Precios!$D$5:$D$120,MATCH(F49,Precios!$A$5:$A$120,0)),"x")),OR(H49="",ISNUMBER(IFERROR(INDEX(Precios!$D$5:$D$120,MATCH(H49,Precios!$A$5:$A$120,0)),"x"))),J49<>"",K49<>"",Q49>0),SUM(O49:R49),"")) | T49: =IF(A49="","",IF(S49<>"",IF(AND(N(J49)>0,Parametros!$B$27=0),"Lista (sin costo de impresión)","Lista"),IF(F49="","Tela. ","")&IF(NOT(ISNUMBER(G49)),"Kg de tela. ","")&IF(AND(F49<>"",NOT(ISNUMBER(IFERROR(INDEX(Precios!$D$5:$D$120,MATCH(F49,Precios!$A$5:$A$120,0)),"x")))),"Tela sin precio. ","")&IF(J49="","Metros impresos. ","")&IF(K49="","Confección. ",IF(Q49=0,"Confección sin valor. ","")))) -> Tela. Kg de tela. Metros impresos.
A50: 46 · BK-SH | B50: Básquetbol | C50: Básquetbol | D50: Short | E50: Masculino | F50: QUICKDRY | G50: 0.1529 | K50: Short De Basket | M50: Por confirmar | N50: Ficha OT 2425 (17 shorts básquet: 2,6 kg). Falta metros impresos. | O50: =IF(A50="","",IFERROR(G50*INDEX(Precios!$D$5:$D$120,MATCH(F50,Precios!$A$5:$A$120,0)),0)+IF(H50="",0,IFERROR(I50*INDEX(Precios!$D$5:$D$120,MATCH(H50,Precios!$A$5:$A$120,0)),0))) -> 1069.6884 | P50: =IF(A50="","",N(J50)*Parametros!$B$27) -> 0 | Q50: =IF(A50="","",IFERROR(INDEX(Confeccion!$B$5:$B$100,MATCH(K50,Confeccion!$A$5:$A$100,0)),0)) -> 1900 | R50: =IF(A50="","",N(L50)) -> 0 | S50: =IF(A50="","",IF(AND(F50<>"",ISNUMBER(G50),ISNUMBER(IFERROR(INDEX(Precios!$D$5:$D$120,MATCH(F50,Precios!$A$5:$A$120,0)),"x")),OR(H50="",ISNUMBER(IFERROR(INDEX(Precios!$D$5:$D$120,MATCH(H50,Precios!$A$5:$A$120,0)),"x"))),J50<>"",K50<>"",Q50>0),SUM(O50:R50),"")) | T50: =IF(A50="","",IF(S50<>"",IF(AND(N(J50)>0,Parametros!$B$27=0),"Lista (sin costo de impresión)","Lista"),IF(F50="","Tela. ","")&IF(NOT(ISNUMBER(G50)),"Kg de tela. ","")&IF(AND(F50<>"",NOT(ISNUMBER(IFERROR(INDEX(Precios!$D$5:$D$120,MATCH(F50,Precios!$A$5:$A$120,0)),"x")))),"Tela sin precio. ","")&IF(J50="","Metros impresos. ","")&IF(K50="","Confección. ",IF(Q50=0,"Confección sin valor. ","")))) -> Metros impresos.
A51: 47 · BKINSHMUJ | B51: Básquetbol infantil | C51: Básquetbol | D51: Short | E51: Infantil Femenino | K51: Short De Basket | M51: Por confirmar | N51: Confección sugerida por el tipo de molde: confirmar. | O51: =IF(A51="","",IFERROR(G51*INDEX(Precios!$D$5:$D$120,MATCH(F51,Precios!$A$5:$A$120,0)),0)+IF(H51="",0,IFERROR(I51*INDEX(Precios!$D$5:$D$120,MATCH(H51,Precios!$A$5:$A$120,0)),0))) -> 0 | P51: =IF(A51="","",N(J51)*Parametros!$B$27) -> 0 | Q51: =IF(A51="","",IFERROR(INDEX(Confeccion!$B$5:$B$100,MATCH(K51,Confeccion!$A$5:$A$100,0)),0)) -> 1900 | R51: =IF(A51="","",N(L51)) -> 0 | S51: =IF(A51="","",IF(AND(F51<>"",ISNUMBER(G51),ISNUMBER(IFERROR(INDEX(Precios!$D$5:$D$120,MATCH(F51,Precios!$A$5:$A$120,0)),"x")),OR(H51="",ISNUMBER(IFERROR(INDEX(Precios!$D$5:$D$120,MATCH(H51,Precios!$A$5:$A$120,0)),"x"))),J51<>"",K51<>"",Q51>0),SUM(O51:R51),"")) | T51: =IF(A51="","",IF(S51<>"",IF(AND(N(J51)>0,Parametros!$B$27=0),"Lista (sin costo de impresión)","Lista"),IF(F51="","Tela. ","")&IF(NOT(ISNUMBER(G51)),"Kg de tela. ","")&IF(AND(F51<>"",NOT(ISNUMBER(IFERROR(INDEX(Precios!$D$5:$D$120,MATCH(F51,Precios!$A$5:$A$120,0)),"x")))),"Tela sin precio. ","")&IF(J51="","Metros impresos. ","")&IF(K51="","Confección. ",IF(Q51=0,"Confección sin valor. ","")))) -> Tela. Kg de tela. Metros impresos.
A52: 48 · BKINSHHOM | B52: Básquetbol infantil | C52: Básquetbol | D52: Short | E52: Infantil Masculino | K52: Short De Basket | M52: Por confirmar | N52: Confección sugerida por el tipo de molde: confirmar. | O52: =IF(A52="","",IFERROR(G52*INDEX(Precios!$D$5:$D$120,MATCH(F52,Precios!$A$5:$A$120,0)),0)+IF(H52="",0,IFERROR(I52*INDEX(Precios!$D$5:$D$120,MATCH(H52,Precios!$A$5:$A$120,0)),0))) -> 0 | P52: =IF(A52="","",N(J52)*Parametros!$B$27) -> 0 | Q52: =IF(A52="","",IFERROR(INDEX(Confeccion!$B$5:$B$100,MATCH(K52,Confeccion!$A$5:$A$100,0)),0)) -> 1900 | R52: =IF(A52="","",N(L52)) -> 0 | S52: =IF(A52="","",IF(AND(F52<>"",ISNUMBER(G52),ISNUMBER(IFERROR(INDEX(Precios!$D$5:$D$120,MATCH(F52,Precios!$A$5:$A$120,0)),"x")),OR(H52="",ISNUMBER(IFERROR(INDEX(Precios!$D$5:$D$120,MATCH(H52,Precios!$A$5:$A$120,0)),"x"))),J52<>"",K52<>"",Q52>0),SUM(O52:R52),"")) | T52: =IF(A52="","",IF(S52<>"",IF(AND(N(J52)>0,Parametros!$B$27=0),"Lista (sin costo de impresión)","Lista"),IF(F52="","Tela. ","")&IF(NOT(ISNUMBER(G52)),"Kg de tela. ","")&IF(AND(F52<>"",NOT(ISNUMBER(IFERROR(INDEX(Precios!$D$5:$D$120,MATCH(F52,Precios!$A$5:$A$120,0)),"x")))),"Tela sin precio. ","")&IF(J52="","Metros impresos. ","")&IF(K52="","Confección. ",IF(Q52=0,"Confección sin valor. ","")))) -> Tela. Kg de tela. Metros impresos.
A53: 49 · BKSHMUJRE | B53: Básquetbol, reversible | C53: Básquetbol | D53: Short | E53: Femenino | K53: Short De Basket Reversible | M53: Por confirmar | N53: Confección sugerida por el tipo de molde: confirmar. | O53: =IF(A53="","",IFERROR(G53*INDEX(Precios!$D$5:$D$120,MATCH(F53,Precios!$A$5:$A$120,0)),0)+IF(H53="",0,IFERROR(I53*INDEX(Precios!$D$5:$D$120,MATCH(H53,Precios!$A$5:$A$120,0)),0))) -> 0 | P53: =IF(A53="","",N(J53)*Parametros!$B$27) -> 0 | Q53: =IF(A53="","",IFERROR(INDEX(Confeccion!$B$5:$B$100,MATCH(K53,Confeccion!$A$5:$A$100,0)),0)) -> 2400 | R53: =IF(A53="","",N(L53)) -> 0 | S53: =IF(A53="","",IF(AND(F53<>"",ISNUMBER(G53),ISNUMBER(IFERROR(INDEX(Precios!$D$5:$D$120,MATCH(F53,Precios!$A$5:$A$120,0)),"x")),OR(H53="",ISNUMBER(IFERROR(INDEX(Precios!$D$5:$D$120,MATCH(H53,Precios!$A$5:$A$120,0)),"x"))),J53<>"",K53<>"",Q53>0),SUM(O53:R53),"")) | T53: =IF(A53="","",IF(S53<>"",IF(AND(N(J53)>0,Parametros!$B$27=0),"Lista (sin costo de impresión)","Lista"),IF(F53="","Tela. ","")&IF(NOT(ISNUMBER(G53)),"Kg de tela. ","")&IF(AND(F53<>"",NOT(ISNUMBER(IFERROR(INDEX(Precios!$D$5:$D$120,MATCH(F53,Precios!$A$5:$A$120,0)),"x")))),"Tela sin precio. ","")&IF(J53="","Metros impresos. ","")&IF(K53="","Confección. ",IF(Q53=0,"Confección sin valor. ","")))) -> Tela. Kg de tela. Metros impresos.
A54: 50 · BK-SH | B54: Básquetbol, reversible | C54: Básquetbol | D54: Short | E54: Masculino | K54: Short De Basket Reversible | M54: Por confirmar | N54: Confección sugerida por el tipo de molde: confirmar. | O54: =IF(A54="","",IFERROR(G54*INDEX(Precios!$D$5:$D$120,MATCH(F54,Precios!$A$5:$A$120,0)),0)+IF(H54="",0,IFERROR(I54*INDEX(Precios!$D$5:$D$120,MATCH(H54,Precios!$A$5:$A$120,0)),0))) -> 0 | P54: =IF(A54="","",N(J54)*Parametros!$B$27) -> 0 | Q54: =IF(A54="","",IFERROR(INDEX(Confeccion!$B$5:$B$100,MATCH(K54,Confeccion!$A$5:$A$100,0)),0)) -> 2400 | R54: =IF(A54="","",N(L54)) -> 0 | S54: =IF(A54="","",IF(AND(F54<>"",ISNUMBER(G54),ISNUMBER(IFERROR(INDEX(Precios!$D$5:$D$120,MATCH(F54,Precios!$A$5:$A$120,0)),"x")),OR(H54="",ISNUMBER(IFERROR(INDEX(Precios!$D$5:$D$120,MATCH(H54,Precios!$A$5:$A$120,0)),"x"))),J54<>"",K54<>"",Q54>0),SUM(O54:R54),"")) | T54: =IF(A54="","",IF(S54<>"",IF(AND(N(J54)>0,Parametros!$B$27=0),"Lista (sin costo de impresión)","Lista"),IF(F54="","Tela. ","")&IF(NOT(ISNUMBER(G54)),"Kg de tela. ","")&IF(AND(F54<>"",NOT(ISNUMBER(IFERROR(INDEX(Precios!$D$5:$D$120,MATCH(F54,Precios!$A$5:$A$120,0)),"x")))),"Tela sin precio. ","")&IF(J54="","Metros impresos. ","")&IF(K54="","Confección. ",IF(Q54=0,"Confección sin valor. ","")))) -> Tela. Kg de tela. Metros impresos.
A55: 51 · BKINSHMUJRE | B55: Básquetbol infantil, reversible | C55: Básquetbol | D55: Short | E55: Infantil Femenino | K55: Short De Basket Reversible | M55: Por confirmar | N55: Confección sugerida por el tipo de molde: confirmar. | O55: =IF(A55="","",IFERROR(G55*INDEX(Precios!$D$5:$D$120,MATCH(F55,Precios!$A$5:$A$120,0)),0)+IF(H55="",0,IFERROR(I55*INDEX(Precios!$D$5:$D$120,MATCH(H55,Precios!$A$5:$A$120,0)),0))) -> 0 | P55: =IF(A55="","",N(J55)*Parametros!$B$27) -> 0 | Q55: =IF(A55="","",IFERROR(INDEX(Confeccion!$B$5:$B$100,MATCH(K55,Confeccion!$A$5:$A$100,0)),0)) -> 2400 | R55: =IF(A55="","",N(L55)) -> 0 | S55: =IF(A55="","",IF(AND(F55<>"",ISNUMBER(G55),ISNUMBER(IFERROR(INDEX(Precios!$D$5:$D$120,MATCH(F55,Precios!$A$5:$A$120,0)),"x")),OR(H55="",ISNUMBER(IFERROR(INDEX(Precios!$D$5:$D$120,MATCH(H55,Precios!$A$5:$A$120,0)),"x"))),J55<>"",K55<>"",Q55>0),SUM(O55:R55),"")) | T55: =IF(A55="","",IF(S55<>"",IF(AND(N(J55)>0,Parametros!$B$27=0),"Lista (sin costo de impresión)","Lista"),IF(F55="","Tela. ","")&IF(NOT(ISNUMBER(G55)),"Kg de tela. ","")&IF(AND(F55<>"",NOT(ISNUMBER(IFERROR(INDEX(Precios!$D$5:$D$120,MATCH(F55,Precios!$A$5:$A$120,0)),"x")))),"Tela sin precio. ","")&IF(J55="","Metros impresos. ","")&IF(K55="","Confección. ",IF(Q55=0,"Confección sin valor. ","")))) -> Tela. Kg de tela. Metros impresos.
A56: 52 · BKINSHHOMRE | B56: Básquetbol infantil, reversible | C56: Básquetbol | D56: Short | E56: Infantil Masculino | K56: Short De Basket Reversible | M56: Por confirmar | N56: Confección sugerida por el tipo de molde: confirmar. | O56: =IF(A56="","",IFERROR(G56*INDEX(Precios!$D$5:$D$120,MATCH(F56,Precios!$A$5:$A$120,0)),0)+IF(H56="",0,IFERROR(I56*INDEX(Precios!$D$5:$D$120,MATCH(H56,Precios!$A$5:$A$120,0)),0))) -> 0 | P56: =IF(A56="","",N(J56)*Parametros!$B$27) -> 0 | Q56: =IF(A56="","",IFERROR(INDEX(Confeccion!$B$5:$B$100,MATCH(K56,Confeccion!$A$5:$A$100,0)),0)) -> 2400 | R56: =IF(A56="","",N(L56)) -> 0 | S56: =IF(A56="","",IF(AND(F56<>"",ISNUMBER(G56),ISNUMBER(IFERROR(INDEX(Precios!$D$5:$D$120,MATCH(F56,Precios!$A$5:$A$120,0)),"x")),OR(H56="",ISNUMBER(IFERROR(INDEX(Precios!$D$5:$D$120,MATCH(H56,Precios!$A$5:$A$120,0)),"x"))),J56<>"",K56<>"",Q56>0),SUM(O56:R56),"")) | T56: =IF(A56="","",IF(S56<>"",IF(AND(N(J56)>0,Parametros!$B$27=0),"Lista (sin costo de impresión)","Lista"),IF(F56="","Tela. ","")&IF(NOT(ISNUMBER(G56)),"Kg de tela. ","")&IF(AND(F56<>"",NOT(ISNUMBER(IFERROR(INDEX(Precios!$D$5:$D$120,MATCH(F56,Precios!$A$5:$A$120,0)),"x")))),"Tela sin precio. ","")&IF(J56="","Metros impresos. ","")&IF(K56="","Confección. ",IF(Q56=0,"Confección sin valor. ","")))) -> Tela. Kg de tela. Metros impresos.
A57: 53 · BKSHMUJPRO | B57: Básquetbol, pro | C57: Básquetbol | D57: Short | E57: Femenino | K57: Short De Basket Pro | M57: Por confirmar | N57: Confección sugerida por el tipo de molde: confirmar. | O57: =IF(A57="","",IFERROR(G57*INDEX(Precios!$D$5:$D$120,MATCH(F57,Precios!$A$5:$A$120,0)),0)+IF(H57="",0,IFERROR(I57*INDEX(Precios!$D$5:$D$120,MATCH(H57,Precios!$A$5:$A$120,0)),0))) -> 0 | P57: =IF(A57="","",N(J57)*Parametros!$B$27) -> 0 | Q57: =IF(A57="","",IFERROR(INDEX(Confeccion!$B$5:$B$100,MATCH(K57,Confeccion!$A$5:$A$100,0)),0)) -> 2200 | R57: =IF(A57="","",N(L57)) -> 0 | S57: =IF(A57="","",IF(AND(F57<>"",ISNUMBER(G57),ISNUMBER(IFERROR(INDEX(Precios!$D$5:$D$120,MATCH(F57,Precios!$A$5:$A$120,0)),"x")),OR(H57="",ISNUMBER(IFERROR(INDEX(Precios!$D$5:$D$120,MATCH(H57,Precios!$A$5:$A$120,0)),"x"))),J57<>"",K57<>"",Q57>0),SUM(O57:R57),"")) | T57: =IF(A57="","",IF(S57<>"",IF(AND(N(J57)>0,Parametros!$B$27=0),"Lista (sin costo de impresión)","Lista"),IF(F57="","Tela. ","")&IF(NOT(ISNUMBER(G57)),"Kg de tela. ","")&IF(AND(F57<>"",NOT(ISNUMBER(IFERROR(INDEX(Precios!$D$5:$D$120,MATCH(F57,Precios!$A$5:$A$120,0)),"x")))),"Tela sin precio. ","")&IF(J57="","Metros impresos. ","")&IF(K57="","Confección. ",IF(Q57=0,"Confección sin valor. ","")))) -> Tela. Kg de tela. Metros impresos.
A58: 54 · BK-SH PRO | B58: Básquetbol, pro | C58: Básquetbol | D58: Short | E58: Masculino | K58: Short De Basket Pro | M58: Por confirmar | N58: Confección sugerida por el tipo de molde: confirmar. | O58: =IF(A58="","",IFERROR(G58*INDEX(Precios!$D$5:$D$120,MATCH(F58,Precios!$A$5:$A$120,0)),0)+IF(H58="",0,IFERROR(I58*INDEX(Precios!$D$5:$D$120,MATCH(H58,Precios!$A$5:$A$120,0)),0))) -> 0 | P58: =IF(A58="","",N(J58)*Parametros!$B$27) -> 0 | Q58: =IF(A58="","",IFERROR(INDEX(Confeccion!$B$5:$B$100,MATCH(K58,Confeccion!$A$5:$A$100,0)),0)) -> 2200 | R58: =IF(A58="","",N(L58)) -> 0 | S58: =IF(A58="","",IF(AND(F58<>"",ISNUMBER(G58),ISNUMBER(IFERROR(INDEX(Precios!$D$5:$D$120,MATCH(F58,Precios!$A$5:$A$120,0)),"x")),OR(H58="",ISNUMBER(IFERROR(INDEX(Precios!$D$5:$D$120,MATCH(H58,Precios!$A$5:$A$120,0)),"x"))),J58<>"",K58<>"",Q58>0),SUM(O58:R58),"")) | T58: =IF(A58="","",IF(S58<>"",IF(AND(N(J58)>0,Parametros!$B$27=0),"Lista (sin costo de impresión)","Lista"),IF(F58="","Tela. ","")&IF(NOT(ISNUMBER(G58)),"Kg de tela. ","")&IF(AND(F58<>"",NOT(ISNUMBER(IFERROR(INDEX(Precios!$D$5:$D$120,MATCH(F58,Precios!$A$5:$A$120,0)),"x")))),"Tela sin precio. ","")&IF(J58="","Metros impresos. ","")&IF(K58="","Confección. ",IF(Q58=0,"Confección sin valor. ","")))) -> Tela. Kg de tela. Metros impresos.
A59: PRENDAS SIN MOLDE EN EL CATÁLOGO (agrega aquí las que falten)
A60: SM-01 · Short Fútbol | B60: Short de fútbol (sin molde en catálogo) | C60: Fútbol | D60: Short | E60: Masculino | F60: CIRE BLANCO | G60: 0.1609 | J60: 0 | K60: Short De Futbol | M60: Por confirmar | N60: Promedio OT 2547 (0,175) y OT 2588 (0,138). Liso = 0 m impresos: confirmar. | O60: =IF(A60="","",IFERROR(G60*INDEX(Precios!$D$5:$D$120,MATCH(F60,Precios!$A$5:$A$120,0)),0)+IF(H60="",0,IFERROR(I60*INDEX(Precios!$D$5:$D$120,MATCH(H60,Precios!$A$5:$A$120,0)),0))) -> 901.04 | P60: =IF(A60="","",N(J60)*Parametros!$B$27) -> 0 | Q60: =IF(A60="","",IFERROR(INDEX(Confeccion!$B$5:$B$100,MATCH(K60,Confeccion!$A$5:$A$100,0)),0)) -> 1700 | R60: =IF(A60="","",N(L60)) -> 0 | S60: =IF(A60="","",IF(AND(F60<>"",ISNUMBER(G60),ISNUMBER(IFERROR(INDEX(Precios!$D$5:$D$120,MATCH(F60,Precios!$A$5:$A$120,0)),"x")),OR(H60="",ISNUMBER(IFERROR(INDEX(Precios!$D$5:$D$120,MATCH(H60,Precios!$A$5:$A$120,0)),"x"))),J60<>"",K60<>"",Q60>0),SUM(O60:R60),"")) -> 2601.04 | T60: =IF(A60="","",IF(S60<>"",IF(AND(N(J60)>0,Parametros!$B$27=0),"Lista (sin costo de impresión)","Lista"),IF(F60="","Tela. ","")&IF(NOT(ISNUMBER(G60)),"Kg de tela. ","")&IF(AND(F60<>"",NOT(ISNUMBER(IFERROR(INDEX(Precios!$D$5:$D$120,MATCH(F60,Precios!$A$5:$A$120,0)),"x")))),"Tela sin precio. ","")&IF(J60="","Metros impresos. ","")&IF(K60="","Confección. ",IF(Q60=0,"Confección sin valor. ","")))) -> Lista
A61: SM-02 · Short Rugby | B61: Short de rugby (sin molde en catálogo) | C61: Rugby | D61: Short | E61: Masculino | F61: GABARDINA | G61: 0.1842 | J61: 0 | K61: Short De Rugby | M61: Por confirmar | N61: Ficha OT 205 (19 shorts). | O61: =IF(A61="","",IFERROR(G61*INDEX(Precios!$D$5:$D$120,MATCH(F61,Precios!$A$5:$A$120,0)),0)+IF(H61="",0,IFERROR(I61*INDEX(Precios!$D$5:$D$120,MATCH(H61,Precios!$A$5:$A$120,0)),0))) -> 506.55 | P61: =IF(A61="","",N(J61)*Parametros!$B$27) -> 0 | Q61: =IF(A61="","",IFERROR(INDEX(Confeccion!$B$5:$B$100,MATCH(K61,Confeccion!$A$5:$A$100,0)),0)) -> 2200 | R61: =IF(A61="","",N(L61)) -> 0 | S61: =IF(A61="","",IF(AND(F61<>"",ISNUMBER(G61),ISNUMBER(IFERROR(INDEX(Precios!$D$5:$D$120,MATCH(F61,Precios!$A$5:$A$120,0)),"x")),OR(H61="",ISNUMBER(IFERROR(INDEX(Precios!$D$5:$D$120,MATCH(H61,Precios!$A$5:$A$120,0)),"x"))),J61<>"",K61<>"",Q61>0),SUM(O61:R61),"")) -> 2706.55 | T61: =IF(A61="","",IF(S61<>"",IF(AND(N(J61)>0,Parametros!$B$27=0),"Lista (sin costo de impresión)","Lista"),IF(F61="","Tela. ","")&IF(NOT(ISNUMBER(G61)),"Kg de tela. ","")&IF(AND(F61<>"",NOT(ISNUMBER(IFERROR(INDEX(Precios!$D$5:$D$120,MATCH(F61,Precios!$A$5:$A$120,0)),"x")))),"Tela sin precio. ","")&IF(J61="","Metros impresos. ","")&IF(K61="","Confección. ",IF(Q61=0,"Confección sin valor. ","")))) -> Lista
A62: SM-03 · Camiseta Running s/m | B62: Camiseta running sin mangas (sin molde) | C62: Running | D62: Camiseta | E62: Masculino | F62: 5K NACIONAL (running pro) | G62: 0.082 | J62: 1.2 | K62: Camiseta De Running | M62: Por confirmar | N62: Ficha OT 2223 (25 prendas). Metros 1,2 de la receta anterior: confirmar. | O62: =IF(A62="","",IFERROR(G62*INDEX(Precios!$D$5:$D$120,MATCH(F62,Precios!$A$5:$A$120,0)),0)+IF(H62="",0,IFERROR(I62*INDEX(Precios!$D$5:$D$120,MATCH(H62,Precios!$A$5:$A$120,0)),0))) -> 348.008 | P62: =IF(A62="","",N(J62)*Parametros!$B$27) -> 0 | Q62: =IF(A62="","",IFERROR(INDEX(Confeccion!$B$5:$B$100,MATCH(K62,Confeccion!$A$5:$A$100,0)),0)) -> 1800 | R62: =IF(A62="","",N(L62)) -> 0 | S62: =IF(A62="","",IF(AND(F62<>"",ISNUMBER(G62),ISNUMBER(IFERROR(INDEX(Precios!$D$5:$D$120,MATCH(F62,Precios!$A$5:$A$120,0)),"x")),OR(H62="",ISNUMBER(IFERROR(INDEX(Precios!$D$5:$D$120,MATCH(H62,Precios!$A$5:$A$120,0)),"x"))),J62<>"",K62<>"",Q62>0),SUM(O62:R62),"")) -> 2148.008 | T62: =IF(A62="","",IF(S62<>"",IF(AND(N(J62)>0,Parametros!$B$27=0),"Lista (sin costo de impresión)","Lista"),IF(F62="","Tela. ","")&IF(NOT(ISNUMBER(G62)),"Kg de tela. ","")&IF(AND(F62<>"",NOT(ISNUMBER(IFERROR(INDEX(Precios!$D$5:$D$120,MATCH(F62,Precios!$A$5:$A$120,0)),"x")))),"Tela sin precio. ","")&IF(J62="","Metros impresos. ","")&IF(K62="","Confección. ",IF(Q62=0,"Confección sin valor. ","")))) -> Lista (sin costo de impresión)
A63: SM-04 · Calza Vóley | B63: Calza vóley (sin molde) | C63: Vóley | D63: Calza | E63: Masculino | F63: LYCRA | G63: 0.074 | J63: 0 | K63: Calza | M63: Por confirmar | N63: Ficha OT 2642 (5 calzas). La Lycra no tiene precio. | O63: =IF(A63="","",IFERROR(G63*INDEX(Precios!$D$5:$D$120,MATCH(F63,Precios!$A$5:$A$120,0)),0)+IF(H63="",0,IFERROR(I63*INDEX(Precios!$D$5:$D$120,MATCH(H63,Precios!$A$5:$A$120,0)),0))) -> 0 | P63: =IF(A63="","",N(J63)*Parametros!$B$27) -> 0 | Q63: =IF(A63="","",IFERROR(INDEX(Confeccion!$B$5:$B$100,MATCH(K63,Confeccion!$A$5:$A$100,0)),0)) -> 1200 | R63: =IF(A63="","",N(L63)) -> 0 | S63: =IF(A63="","",IF(AND(F63<>"",ISNUMBER(G63),ISNUMBER(IFERROR(INDEX(Precios!$D$5:$D$120,MATCH(F63,Precios!$A$5:$A$120,0)),"x")),OR(H63="",ISNUMBER(IFERROR(INDEX(Precios!$D$5:$D$120,MATCH(H63,Precios!$A$5:$A$120,0)),"x"))),J63<>"",K63<>"",Q63>0),SUM(O63:R63),"")) | T63: =IF(A63="","",IF(S63<>"",IF(AND(N(J63)>0,Parametros!$B$27=0),"Lista (sin costo de impresión)","Lista"),IF(F63="","Tela. ","")&IF(NOT(ISNUMBER(G63)),"Kg de tela. ","")&IF(AND(F63<>"",NOT(ISNUMBER(IFERROR(INDEX(Precios!$D$5:$D$120,MATCH(F63,Precios!$A$5:$A$120,0)),"x")))),"Tela sin precio. ","")&IF(J63="","Metros impresos. ","")&IF(K63="","Confección. ",IF(Q63=0,"Confección sin valor. ","")))) -> Tela sin precio.
N64: ← filas libres: escribe un código (ej: SM-05 · Polerón) y completa la receta | O64: =IF(A64="","",IFERROR(G64*INDEX(Precios!$D$5:$D$120,MATCH(F64,Precios!$A$5:$A$120,0)),0)+IF(H64="",0,IFERROR(I64*INDEX(Precios!$D$5:$D$120,MATCH(H64,Precios!$A$5:$A$120,0)),0))) | P64: =IF(A64="","",N(J64)*Parametros!$B$27) | Q64: =IF(A64="","",IFERROR(INDEX(Confeccion!$B$5:$B$100,MATCH(K64,Confeccion!$A$5:$A$100,0)),0)) | R64: =IF(A64="","",N(L64)) | S64: =IF(A64="","",IF(AND(F64<>"",ISNUMBER(G64),ISNUMBER(IFERROR(INDEX(Precios!$D$5:$D$120,MATCH(F64,Precios!$A$5:$A$120,0)),"x")),OR(H64="",ISNUMBER(IFERROR(INDEX(Precios!$D$5:$D$120,MATCH(H64,Precios!$A$5:$A$120,0)),"x"))),J64<>"",K64<>"",Q64>0),SUM(O64:R64),"")) | T64: =IF(A64="","",IF(S64<>"",IF(AND(N(J64)>0,Parametros!$B$27=0),"Lista (sin costo de impresión)","Lista"),IF(F64="","Tela. ","")&IF(NOT(ISNUMBER(G64)),"Kg de tela. ","")&IF(AND(F64<>"",NOT(ISNUMBER(IFERROR(INDEX(Precios!$D$5:$D$120,MATCH(F64,Precios!$A$5:$A$120,0)),"x")))),"Tela sin precio. ","")&IF(J64="","Metros impresos. ","")&IF(K64="","Confección. ",IF(Q64=0,"Confección sin valor. ",""))))
O65: =IF(A65="","",IFERROR(G65*INDEX(Precios!$D$5:$D$120,MATCH(F65,Precios!$A$5:$A$120,0)),0)+IF(H65="",0,IFERROR(I65*INDEX(Precios!$D$5:$D$120,MATCH(H65,Precios!$A$5:$A$120,0)),0))) | P65: =IF(A65="","",N(J65)*Parametros!$B$27) | Q65: =IF(A65="","",IFERROR(INDEX(Confeccion!$B$5:$B$100,MATCH(K65,Confeccion!$A$5:$A$100,0)),0)) | R65: =IF(A65="","",N(L65)) | S65: =IF(A65="","",IF(AND(F65<>"",ISNUMBER(G65),ISNUMBER(IFERROR(INDEX(Precios!$D$5:$D$120,MATCH(F65,Precios!$A$5:$A$120,0)),"x")),OR(H65="",ISNUMBER(IFERROR(INDEX(Precios!$D$5:$D$120,MATCH(H65,Precios!$A$5:$A$120,0)),"x"))),J65<>"",K65<>"",Q65>0),SUM(O65:R65),"")) | T65: =IF(A65="","",IF(S65<>"",IF(AND(N(J65)>0,Parametros!$B$27=0),"Lista (sin costo de impresión)","Lista"),IF(F65="","Tela. ","")&IF(NOT(ISNUMBER(G65)),"Kg de tela. ","")&IF(AND(F65<>"",NOT(ISNUMBER(IFERROR(INDEX(Precios!$D$5:$D$120,MATCH(F65,Precios!$A$5:$A$120,0)),"x")))),"Tela sin precio. ","")&IF(J65="","Metros impresos. ","")&IF(K65="","Confección. ",IF(Q65=0,"Confección sin valor. ",""))))
O66: =IF(A66="","",IFERROR(G66*INDEX(Precios!$D$5:$D$120,MATCH(F66,Precios!$A$5:$A$120,0)),0)+IF(H66="",0,IFERROR(I66*INDEX(Precios!$D$5:$D$120,MATCH(H66,Precios!$A$5:$A$120,0)),0))) | P66: =IF(A66="","",N(J66)*Parametros!$B$27) | Q66: =IF(A66="","",IFERROR(INDEX(Confeccion!$B$5:$B$100,MATCH(K66,Confeccion!$A$5:$A$100,0)),0)) | R66: =IF(A66="","",N(L66)) | S66: =IF(A66="","",IF(AND(F66<>"",ISNUMBER(G66),ISNUMBER(IFERROR(INDEX(Precios!$D$5:$D$120,MATCH(F66,Precios!$A$5:$A$120,0)),"x")),OR(H66="",ISNUMBER(IFERROR(INDEX(Precios!$D$5:$D$120,MATCH(H66,Precios!$A$5:$A$120,0)),"x"))),J66<>"",K66<>"",Q66>0),SUM(O66:R66),"")) | T66: =IF(A66="","",IF(S66<>"",IF(AND(N(J66)>0,Parametros!$B$27=0),"Lista (sin costo de impresión)","Lista"),IF(F66="","Tela. ","")&IF(NOT(ISNUMBER(G66)),"Kg de tela. ","")&IF(AND(F66<>"",NOT(ISNUMBER(IFERROR(INDEX(Precios!$D$5:$D$120,MATCH(F66,Precios!$A$5:$A$120,0)),"x")))),"Tela sin precio. ","")&IF(J66="","Metros impresos. ","")&IF(K66="","Confección. ",IF(Q66=0,"Confección sin valor. ",""))))
O67: =IF(A67="","",IFERROR(G67*INDEX(Precios!$D$5:$D$120,MATCH(F67,Precios!$A$5:$A$120,0)),0)+IF(H67="",0,IFERROR(I67*INDEX(Precios!$D$5:$D$120,MATCH(H67,Precios!$A$5:$A$120,0)),0))) | P67: =IF(A67="","",N(J67)*Parametros!$B$27) | Q67: =IF(A67="","",IFERROR(INDEX(Confeccion!$B$5:$B$100,MATCH(K67,Confeccion!$A$5:$A$100,0)),0)) | R67: =IF(A67="","",N(L67)) | S67: =IF(A67="","",IF(AND(F67<>"",ISNUMBER(G67),ISNUMBER(IFERROR(INDEX(Precios!$D$5:$D$120,MATCH(F67,Precios!$A$5:$A$120,0)),"x")),OR(H67="",ISNUMBER(IFERROR(INDEX(Precios!$D$5:$D$120,MATCH(H67,Precios!$A$5:$A$120,0)),"x"))),J67<>"",K67<>"",Q67>0),SUM(O67:R67),"")) | T67: =IF(A67="","",IF(S67<>"",IF(AND(N(J67)>0,Parametros!$B$27=0),"Lista (sin costo de impresión)","Lista"),IF(F67="","Tela. ","")&IF(NOT(ISNUMBER(G67)),"Kg de tela. ","")&IF(AND(F67<>"",NOT(ISNUMBER(IFERROR(INDEX(Precios!$D$5:$D$120,MATCH(F67,Precios!$A$5:$A$120,0)),"x")))),"Tela sin precio. ","")&IF(J67="","Metros impresos. ","")&IF(K67="","Confección. ",IF(Q67=0,"Confección sin valor. ",""))))
O68: =IF(A68="","",IFERROR(G68*INDEX(Precios!$D$5:$D$120,MATCH(F68,Precios!$A$5:$A$120,0)),0)+IF(H68="",0,IFERROR(I68*INDEX(Precios!$D$5:$D$120,MATCH(H68,Precios!$A$5:$A$120,0)),0))) | P68: =IF(A68="","",N(J68)*Parametros!$B$27) | Q68: =IF(A68="","",IFERROR(INDEX(Confeccion!$B$5:$B$100,MATCH(K68,Confeccion!$A$5:$A$100,0)),0)) | R68: =IF(A68="","",N(L68)) | S68: =IF(A68="","",IF(AND(F68<>"",ISNUMBER(G68),ISNUMBER(IFERROR(INDEX(Precios!$D$5:$D$120,MATCH(F68,Precios!$A$5:$A$120,0)),"x")),OR(H68="",ISNUMBER(IFERROR(INDEX(Precios!$D$5:$D$120,MATCH(H68,Precios!$A$5:$A$120,0)),"x"))),J68<>"",K68<>"",Q68>0),SUM(O68:R68),"")) | T68: =IF(A68="","",IF(S68<>"",IF(AND(N(J68)>0,Parametros!$B$27=0),"Lista (sin costo de impresión)","Lista"),IF(F68="","Tela. ","")&IF(NOT(ISNUMBER(G68)),"Kg de tela. ","")&IF(AND(F68<>"",NOT(ISNUMBER(IFERROR(INDEX(Precios!$D$5:$D$120,MATCH(F68,Precios!$A$5:$A$120,0)),"x")))),"Tela sin precio. ","")&IF(J68="","Metros impresos. ","")&IF(K68="","Confección. ",IF(Q68=0,"Confección sin valor. ",""))))
O69: =IF(A69="","",IFERROR(G69*INDEX(Precios!$D$5:$D$120,MATCH(F69,Precios!$A$5:$A$120,0)),0)+IF(H69="",0,IFERROR(I69*INDEX(Precios!$D$5:$D$120,MATCH(H69,Precios!$A$5:$A$120,0)),0))) | P69: =IF(A69="","",N(J69)*Parametros!$B$27) | Q69: =IF(A69="","",IFERROR(INDEX(Confeccion!$B$5:$B$100,MATCH(K69,Confeccion!$A$5:$A$100,0)),0)) | R69: =IF(A69="","",N(L69)) | S69: =IF(A69="","",IF(AND(F69<>"",ISNUMBER(G69),ISNUMBER(IFERROR(INDEX(Precios!$D$5:$D$120,MATCH(F69,Precios!$A$5:$A$120,0)),"x")),OR(H69="",ISNUMBER(IFERROR(INDEX(Precios!$D$5:$D$120,MATCH(H69,Precios!$A$5:$A$120,0)),"x"))),J69<>"",K69<>"",Q69>0),SUM(O69:R69),"")) | T69: =IF(A69="","",IF(S69<>"",IF(AND(N(J69)>0,Parametros!$B$27=0),"Lista (sin costo de impresión)","Lista"),IF(F69="","Tela. ","")&IF(NOT(ISNUMBER(G69)),"Kg de tela. ","")&IF(AND(F69<>"",NOT(ISNUMBER(IFERROR(INDEX(Precios!$D$5:$D$120,MATCH(F69,Precios!$A$5:$A$120,0)),"x")))),"Tela sin precio. ","")&IF(J69="","Metros impresos. ","")&IF(K69="","Confección. ",IF(Q69=0,"Confección sin valor. ",""))))
O70: =IF(A70="","",IFERROR(G70*INDEX(Precios!$D$5:$D$120,MATCH(F70,Precios!$A$5:$A$120,0)),0)+IF(H70="",0,IFERROR(I70*INDEX(Precios!$D$5:$D$120,MATCH(H70,Precios!$A$5:$A$120,0)),0))) | P70: =IF(A70="","",N(J70)*Parametros!$B$27) | Q70: =IF(A70="","",IFERROR(INDEX(Confeccion!$B$5:$B$100,MATCH(K70,Confeccion!$A$5:$A$100,0)),0)) | R70: =IF(A70="","",N(L70)) | S70: =IF(A70="","",IF(AND(F70<>"",ISNUMBER(G70),ISNUMBER(IFERROR(INDEX(Precios!$D$5:$D$120,MATCH(F70,Precios!$A$5:$A$120,0)),"x")),OR(H70="",ISNUMBER(IFERROR(INDEX(Precios!$D$5:$D$120,MATCH(H70,Precios!$A$5:$A$120,0)),"x"))),J70<>"",K70<>"",Q70>0),SUM(O70:R70),"")) | T70: =IF(A70="","",IF(S70<>"",IF(AND(N(J70)>0,Parametros!$B$27=0),"Lista (sin costo de impresión)","Lista"),IF(F70="","Tela. ","")&IF(NOT(ISNUMBER(G70)),"Kg de tela. ","")&IF(AND(F70<>"",NOT(ISNUMBER(IFERROR(INDEX(Precios!$D$5:$D$120,MATCH(F70,Precios!$A$5:$A$120,0)),"x")))),"Tela sin precio. ","")&IF(J70="","Metros impresos. ","")&IF(K70="","Confección. ",IF(Q70=0,"Confección sin valor. ",""))))
O71: =IF(A71="","",IFERROR(G71*INDEX(Precios!$D$5:$D$120,MATCH(F71,Precios!$A$5:$A$120,0)),0)+IF(H71="",0,IFERROR(I71*INDEX(Precios!$D$5:$D$120,MATCH(H71,Precios!$A$5:$A$120,0)),0))) | P71: =IF(A71="","",N(J71)*Parametros!$B$27) | Q71: =IF(A71="","",IFERROR(INDEX(Confeccion!$B$5:$B$100,MATCH(K71,Confeccion!$A$5:$A$100,0)),0)) | R71: =IF(A71="","",N(L71)) | S71: =IF(A71="","",IF(AND(F71<>"",ISNUMBER(G71),ISNUMBER(IFERROR(INDEX(Precios!$D$5:$D$120,MATCH(F71,Precios!$A$5:$A$120,0)),"x")),OR(H71="",ISNUMBER(IFERROR(INDEX(Precios!$D$5:$D$120,MATCH(H71,Precios!$A$5:$A$120,0)),"x"))),J71<>"",K71<>"",Q71>0),SUM(O71:R71),"")) | T71: =IF(A71="","",IF(S71<>"",IF(AND(N(J71)>0,Parametros!$B$27=0),"Lista (sin costo de impresión)","Lista"),IF(F71="","Tela. ","")&IF(NOT(ISNUMBER(G71)),"Kg de tela. ","")&IF(AND(F71<>"",NOT(ISNUMBER(IFERROR(INDEX(Precios!$D$5:$D$120,MATCH(F71,Precios!$A$5:$A$120,0)),"x")))),"Tela sin precio. ","")&IF(J71="","Metros impresos. ","")&IF(K71="","Confección. ",IF(Q71=0,"Confección sin valor. ",""))))
O72: =IF(A72="","",IFERROR(G72*INDEX(Precios!$D$5:$D$120,MATCH(F72,Precios!$A$5:$A$120,0)),0)+IF(H72="",0,IFERROR(I72*INDEX(Precios!$D$5:$D$120,MATCH(H72,Precios!$A$5:$A$120,0)),0))) | P72: =IF(A72="","",N(J72)*Parametros!$B$27) | Q72: =IF(A72="","",IFERROR(INDEX(Confeccion!$B$5:$B$100,MATCH(K72,Confeccion!$A$5:$A$100,0)),0)) | R72: =IF(A72="","",N(L72)) | S72: =IF(A72="","",IF(AND(F72<>"",ISNUMBER(G72),ISNUMBER(IFERROR(INDEX(Precios!$D$5:$D$120,MATCH(F72,Precios!$A$5:$A$120,0)),"x")),OR(H72="",ISNUMBER(IFERROR(INDEX(Precios!$D$5:$D$120,MATCH(H72,Precios!$A$5:$A$120,0)),"x"))),J72<>"",K72<>"",Q72>0),SUM(O72:R72),"")) | T72: =IF(A72="","",IF(S72<>"",IF(AND(N(J72)>0,Parametros!$B$27=0),"Lista (sin costo de impresión)","Lista"),IF(F72="","Tela. ","")&IF(NOT(ISNUMBER(G72)),"Kg de tela. ","")&IF(AND(F72<>"",NOT(ISNUMBER(IFERROR(INDEX(Precios!$D$5:$D$120,MATCH(F72,Precios!$A$5:$A$120,0)),"x")))),"Tela sin precio. ","")&IF(J72="","Metros impresos. ","")&IF(K72="","Confección. ",IF(Q72=0,"Confección sin valor. ",""))))
O73: =IF(A73="","",IFERROR(G73*INDEX(Precios!$D$5:$D$120,MATCH(F73,Precios!$A$5:$A$120,0)),0)+IF(H73="",0,IFERROR(I73*INDEX(Precios!$D$5:$D$120,MATCH(H73,Precios!$A$5:$A$120,0)),0))) | P73: =IF(A73="","",N(J73)*Parametros!$B$27) | Q73: =IF(A73="","",IFERROR(INDEX(Confeccion!$B$5:$B$100,MATCH(K73,Confeccion!$A$5:$A$100,0)),0)) | R73: =IF(A73="","",N(L73)) | S73: =IF(A73="","",IF(AND(F73<>"",ISNUMBER(G73),ISNUMBER(IFERROR(INDEX(Precios!$D$5:$D$120,MATCH(F73,Precios!$A$5:$A$120,0)),"x")),OR(H73="",ISNUMBER(IFERROR(INDEX(Precios!$D$5:$D$120,MATCH(H73,Precios!$A$5:$A$120,0)),"x"))),J73<>"",K73<>"",Q73>0),SUM(O73:R73),"")) | T73: =IF(A73="","",IF(S73<>"",IF(AND(N(J73)>0,Parametros!$B$27=0),"Lista (sin costo de impresión)","Lista"),IF(F73="","Tela. ","")&IF(NOT(ISNUMBER(G73)),"Kg de tela. ","")&IF(AND(F73<>"",NOT(ISNUMBER(IFERROR(INDEX(Precios!$D$5:$D$120,MATCH(F73,Precios!$A$5:$A$120,0)),"x")))),"Tela sin precio. ","")&IF(J73="","Metros impresos. ","")&IF(K73="","Confección. ",IF(Q73=0,"Confección sin valor. ",""))))
O74: =IF(A74="","",IFERROR(G74*INDEX(Precios!$D$5:$D$120,MATCH(F74,Precios!$A$5:$A$120,0)),0)+IF(H74="",0,IFERROR(I74*INDEX(Precios!$D$5:$D$120,MATCH(H74,Precios!$A$5:$A$120,0)),0))) | P74: =IF(A74="","",N(J74)*Parametros!$B$27) | Q74: =IF(A74="","",IFERROR(INDEX(Confeccion!$B$5:$B$100,MATCH(K74,Confeccion!$A$5:$A$100,0)),0)) | R74: =IF(A74="","",N(L74)) | S74: =IF(A74="","",IF(AND(F74<>"",ISNUMBER(G74),ISNUMBER(IFERROR(INDEX(Precios!$D$5:$D$120,MATCH(F74,Precios!$A$5:$A$120,0)),"x")),OR(H74="",ISNUMBER(IFERROR(INDEX(Precios!$D$5:$D$120,MATCH(H74,Precios!$A$5:$A$120,0)),"x"))),J74<>"",K74<>"",Q74>0),SUM(O74:R74),"")) | T74: =IF(A74="","",IF(S74<>"",IF(AND(N(J74)>0,Parametros!$B$27=0),"Lista (sin costo de impresión)","Lista"),IF(F74="","Tela. ","")&IF(NOT(ISNUMBER(G74)),"Kg de tela. ","")&IF(AND(F74<>"",NOT(ISNUMBER(IFERROR(INDEX(Precios!$D$5:$D$120,MATCH(F74,Precios!$A$5:$A$120,0)),"x")))),"Tela sin precio. ","")&IF(J74="","Metros impresos. ","")&IF(K74="","Confección. ",IF(Q74=0,"Confección sin valor. ",""))))
O75: =IF(A75="","",IFERROR(G75*INDEX(Precios!$D$5:$D$120,MATCH(F75,Precios!$A$5:$A$120,0)),0)+IF(H75="",0,IFERROR(I75*INDEX(Precios!$D$5:$D$120,MATCH(H75,Precios!$A$5:$A$120,0)),0))) | P75: =IF(A75="","",N(J75)*Parametros!$B$27) | Q75: =IF(A75="","",IFERROR(INDEX(Confeccion!$B$5:$B$100,MATCH(K75,Confeccion!$A$5:$A$100,0)),0)) | R75: =IF(A75="","",N(L75)) | S75: =IF(A75="","",IF(AND(F75<>"",ISNUMBER(G75),ISNUMBER(IFERROR(INDEX(Precios!$D$5:$D$120,MATCH(F75,Precios!$A$5:$A$120,0)),"x")),OR(H75="",ISNUMBER(IFERROR(INDEX(Precios!$D$5:$D$120,MATCH(H75,Precios!$A$5:$A$120,0)),"x"))),J75<>"",K75<>"",Q75>0),SUM(O75:R75),"")) | T75: =IF(A75="","",IF(S75<>"",IF(AND(N(J75)>0,Parametros!$B$27=0),"Lista (sin costo de impresión)","Lista"),IF(F75="","Tela. ","")&IF(NOT(ISNUMBER(G75)),"Kg de tela. ","")&IF(AND(F75<>"",NOT(ISNUMBER(IFERROR(INDEX(Precios!$D$5:$D$120,MATCH(F75,Precios!$A$5:$A$120,0)),"x")))),"Tela sin precio. ","")&IF(J75="","Metros impresos. ","")&IF(K75="","Confección. ",IF(Q75=0,"Confección sin valor. ",""))))
O76: =IF(A76="","",IFERROR(G76*INDEX(Precios!$D$5:$D$120,MATCH(F76,Precios!$A$5:$A$120,0)),0)+IF(H76="",0,IFERROR(I76*INDEX(Precios!$D$5:$D$120,MATCH(H76,Precios!$A$5:$A$120,0)),0))) | P76: =IF(A76="","",N(J76)*Parametros!$B$27) | Q76: =IF(A76="","",IFERROR(INDEX(Confeccion!$B$5:$B$100,MATCH(K76,Confeccion!$A$5:$A$100,0)),0)) | R76: =IF(A76="","",N(L76)) | S76: =IF(A76="","",IF(AND(F76<>"",ISNUMBER(G76),ISNUMBER(IFERROR(INDEX(Precios!$D$5:$D$120,MATCH(F76,Precios!$A$5:$A$120,0)),"x")),OR(H76="",ISNUMBER(IFERROR(INDEX(Precios!$D$5:$D$120,MATCH(H76,Precios!$A$5:$A$120,0)),"x"))),J76<>"",K76<>"",Q76>0),SUM(O76:R76),"")) | T76: =IF(A76="","",IF(S76<>"",IF(AND(N(J76)>0,Parametros!$B$27=0),"Lista (sin costo de impresión)","Lista"),IF(F76="","Tela. ","")&IF(NOT(ISNUMBER(G76)),"Kg de tela. ","")&IF(AND(F76<>"",NOT(ISNUMBER(IFERROR(INDEX(Precios!$D$5:$D$120,MATCH(F76,Precios!$A$5:$A$120,0)),"x")))),"Tela sin precio. ","")&IF(J76="","Metros impresos. ","")&IF(K76="","Confección. ",IF(Q76=0,"Confección sin valor. ",""))))
... O84: =IF(A84="","",IFERROR(G84*INDEX(Precios!$D$5:$D$120,MATCH(F84,Precios!$A$5:$A$120,0)),0)+IF(H84="",0,IFERROR(I84*INDEX(Precios!$D$5:$D$120,MATCH(H84,Precios!$A$5:$A$120,0)),0))) | P84: =IF(A84="","",N(J84)*Parametros!$B$27) | Q84: =IF(A84="","",IFERROR(INDEX(Confeccion!$B$5:$B$100,MATCH(K84,Confeccion!$A$5:$A$100,0)),0)) | R84: =IF(A84="","",N(L84)) | S84: =IF(A84="","",IF(AND(F84<>"",ISNUMBER(G84),ISNUMBER(IFERROR(INDEX(Precios!$D$5:$D$120,MATCH(F84,Precios!$A$5:$A$120,0)),"x")),OR(H84="",ISNUMBER(IFERROR(INDEX(Precios!$D$5:$D$120,MATCH(H84,Precios!$A$5:$A$120,0)),"x"))),J84<>"",K84<>"",Q84>0),SUM(O84:R84),"")) | T84: =IF(A84="","",IF(S84<>"",IF(AND(N(J84)>0,Parametros!$B$27=0),"Lista (sin costo de impresión)","Lista"),IF(F84="","Tela. ","")&IF(NOT(ISNUMBER(G84)),"Kg de tela. ","")&IF(AND(F84<>"",NOT(ISNUMBER(IFERROR(INDEX(Precios!$D$5:$D$120,MATCH(F84,Precios!$A$5:$A$120,0)),"x")))),"Tela sin precio. ","")&IF(J84="","Metros impresos. ","")&IF(K84="","Confección. ",IF(Q84=0,"Confección sin valor. ",""))))

Sheet Parametros
A1: PARÁMETROS — recargo, meta de ganancia y costo de impresión
A2: Azul = lo editas tú. Gris = se calcula solo.
A4: 1) RECARGO POR GASTOS FIJOS (promedio de los últimos 3 meses, se revisa cada trimestre)
A5: Gastos de fábrica — promedio mensual | B5: =Gastos_Ventas!F41 -> 12421897 | C5: Desde Gastos_Ventas
A6: Gastos comerciales — promedio mensual | B6: =Gastos_Ventas!F42 -> 4459061 | C6: Desde Gastos_Ventas
A7: Ventas netas — promedio mensual | B7: =Gastos_Ventas!F45 -> 35194840 | C7: Desde Gastos_Ventas
A8: Recargo de fábrica calculado | B8: =IFERROR(B5/B7,0) -> 0.35294654 | C8: Gastos de fábrica ÷ ventas
A9: Recargo comercial calculado | B9: =IFERROR(B6/B7,0) -> 0.12669644 | C9: Gastos comerciales ÷ ventas
A10: Recargo de fábrica fijado a mano (opcional) | C10: Vacío = usa el calculado. Escribe un % solo si quieres fijarlo.
A11: Recargo comercial fijado a mano (opcional) | C11: Vacío = usa el calculado.
A12: RECARGO DE FÁBRICA USADO | B12: =IF(ISNUMBER(B10),B10,B8) -> 0.35294654 | C12: Lo usan todas las recetas
A13: RECARGO COMERCIAL USADO | B13: =IF(ISNUMBER(B11),B11,B9) -> 0.12669644 | C13: Lo usan todas las recetas
A14: RECARGO TOTAL | B14: =B12+B13 -> 0.47964299 | C14: De cada $100 que vendes, este monto se va en pagar gastos fijos.
A15: Próxima revisión del recargo | B15: Diciembre 2026 | C15: Usar septiembre, octubre y noviembre.
A17: 2) META DE GANANCIA
A18: Ganancia deseada (% del precio de venta) | B18: 0.1 | C18: POR CONFIRMAR: 10% es solo un ejemplo. Define tu meta.
A20: 3) COSTO DE IMPRESIÓN (papel + tinta) por metro impreso
A21: Papel sublimación — precio del rollo ($) | B21: 50420 | C21: POR CONFIRMAR: en tu archivo dice $50.420 "por kg". ¿Es el precio del rollo?
A22: Papel — metros que rinde el rollo | C22: PENDIENTE: ¿cuántos metros trae el rollo?
A23: Tinta — precio por litro ($) | B23: 72119 | C23: POR CONFIRMAR: precio de la tinta magenta. ¿Los otros colores cuestan lo mismo?
A24: Tinta — ml que gasta 1 metro impreso | C24: PENDIENTE: litros gastados en el mes ÷ metros impresos (Control de Ploteo) × 1000.
A25: Papel por metro | B25: =IFERROR(B21/B22,0) -> 0 | C25: Se calcula solo
A26: Tinta por metro | B26: =B24*B23/1000 -> 0 | C26: Se calcula solo
A27: COSTO DE IMPRESIÓN POR METRO | B27: =B25+B26 -> 0 | C27: Mientras esté en $0, las prendas sublimadas salen más baratas de lo real.
A29: 4) POR QUÉ LOS SUELDOS NO VAN EN LA RECETA
A30: Los sueldos de ploteo, sublimación, corte y estampado se pagan completos cada mes, se produzca mucho o poco. Por eso van en "Gastos de fábrica" y llegan a cada prenda a través del recargo. Si además se cobraran dentro de la receta (como hacía el sistema anterior), se contarían dos veces. La receta solo lleva lo que se gasta por cada prenda: tela, papel y tinta, taller de confección y avíos.

Sheet Gastos_Ventas
A1: GASTOS FIJOS Y VENTAS — últimos 3 meses
A2: Cada trimestre escribe los 3 meses más recientes. El promedio y el recargo se recalculan solos.
A4: Concepto | B4: Grupo | C4: Jun-2026 | D4: Jul-2026 | E4: Ago-2026 | F4: Promedio 3 meses | G4: Nota
A5: Ploteo | B5: Fábrica | C5: 2400000 | D5: 2400000 | E5: 2400000 | F5: =AVERAGE(C5:E5) -> 2400000 | G5: Sueldo: se paga igual haya o no producción → va en gastos, no en la receta.
A6: Sublimación | B6: Fábrica | C6: 833000 | D6: 833000 | E6: 833000 | F6: =AVERAGE(C6:E6) -> 833000 | G6: Sueldo: se paga igual haya o no producción → va en gastos, no en la receta.
A7: Corte | B7: Fábrica | C7: 1666000 | D7: 1666000 | E7: 1666000 | F7: =AVERAGE(C7:E7) -> 1666000 | G7: Sueldo: se paga igual haya o no producción → va en gastos, no en la receta.
A8: Confección interna | B8: Fábrica | C8: 1105374 | D8: 1105374 | E8: 1105374 | F8: =AVERAGE(C8:E8) -> 1105374 | G8: Sueldo: se paga igual haya o no producción → va en gastos, no en la receta.
A9: Estampado | B9: Fábrica | C9: 720000 | D9: 720000 | E9: 720000 | F9: =AVERAGE(C9:E9) -> 720000 | G9: Sueldo: se paga igual haya o no producción → va en gastos, no en la receta.
A10: Luz | B10: Fábrica | C10: 638049 | D10: 638049 | E10: 638049 | F10: =AVERAGE(C10:E10) -> 638049
A11: Agua | B11: Fábrica | C11: 10630 | D11: 10630 | E11: 10630 | F11: =AVERAGE(C11:E11) -> 10630
A12: Telefonía | B12: Fábrica | C12: 95000 | D12: 95000 | E12: 95000 | F12: =AVERAGE(C12:E12) -> 95000
A13: Arriendo | B13: Fábrica | C13: 2163844 | D13: 2163844 | E13: 2163844 | F13: =AVERAGE(C13:E13) -> 2163844
A14: Internet | B14: Fábrica | C14: 49000 | D14: 49000 | E14: 49000 | F14: =AVERAGE(C14:E14) -> 49000
A15: Mantención de máquinas | B15: Fábrica | C15: 300000 | D15: 300000 | E15: 300000 | F15: =AVERAGE(C15:E15) -> 300000
A16: Seguridad | B16: Fábrica | C16: 50000 | D16: 50000 | E16: 50000 | F16: =AVERAGE(C16:E16) -> 50000
A17: Insumos de limpieza (aseo) | B17: Fábrica | C17: 100000 | D17: 100000 | E17: 100000 | F17: =AVERAGE(C17:E17) -> 100000
A18: Insumos de oficina | B18: Fábrica | C18: 100000 | D18: 100000 | E18: 100000 | F18: =AVERAGE(C18:E18) -> 100000
A19: Bencina | B19: Fábrica | C19: 300000 | D19: 300000 | E19: 300000 | F19: =AVERAGE(C19:E19) -> 300000
A20: Jefe de producción (sueldo) | B20: Fábrica | C20: 1071000 | D20: 1071000 | E20: 1071000 | F20: =AVERAGE(C20:E20) -> 1071000 | G20: Sueldo: se paga igual haya o no producción → va en gastos, no en la receta.
A21: Fichas técnicas (sueldo) | B21: Fábrica | C21: 400000 | D21: 400000 | E21: 400000 | F21: =AVERAGE(C21:E21) -> 400000 | G21: Sueldo: se paga igual haya o no producción → va en gastos, no en la receta.
A22: Apoyo producción (sueldo) | B22: Fábrica | C22: 120000 | D22: 120000 | E22: 120000 | F22: =AVERAGE(C22:E22) -> 120000 | G22: Sueldo: se paga igual haya o no producción → va en gastos, no en la receta.
A23: Personal aseo (sueldo) | B23: Fábrica | C23: 300000 | D23: 300000 | E23: 300000 | F23: =AVERAGE(C23:E23) -> 300000 | G23: Sueldo: se paga igual haya o no producción → va en gastos, no en la receta.
A24: CEO (sueldo) | B24: Comercial | C24: 0 | D24: 0 | E24: 0 | F24: =AVERAGE(C24:E24) -> 0 | G24: Sueldo: se paga igual haya o no producción → va en gastos, no en la receta.
A25: Administración (sueldo) | B25: Comercial | C25: 0 | D25: 0 | E25: 0 | F25: =AVERAGE(C25:E25) -> 0 | G25: Sueldo: se paga igual haya o no producción → va en gastos, no en la receta.
A26: Ventas (sueldo) | B26: Comercial | C26: 1680000 | D26: 1680000 | E26: 1680000 | F26: =AVERAGE(C26:E26) -> 1680000 | G26: Sueldo: se paga igual haya o no producción → va en gastos, no en la receta.
A27: Marketing (sueldo) | B27: Comercial | C27: 680000 | D27: 680000 | E27: 680000 | F27: =AVERAGE(C27:E27) -> 680000 | G27: Sueldo: se paga igual haya o no producción → va en gastos, no en la receta.
A28: Audiovisual / contenido (sueldo) | B28: Comercial | C28: 397000 | D28: 397000 | E28: 397000 | F28: =AVERAGE(C28:E28) -> 397000 | G28: Sueldo: se paga igual haya o no producción → va en gastos, no en la receta.
A29: Facebook / Instagram Ads | B29: Comercial | C29: 447861 | D29: 447861 | E29: 447861 | F29: =AVERAGE(C29:E29) -> 447861
A30: Google Ads | B30: Comercial | C30: 450000 | D30: 450000 | E30: 450000 | F30: =AVERAGE(C30:E30) -> 450000
A31: Agencia de marketing | B31: Comercial | C31: 214200 | D31: 214200 | E31: 214200 | F31: =AVERAGE(C31:E31) -> 214200
A32: Herramientas de IA | B32: Comercial | C32: 450000 | D32: 450000 | E32: 450000 | F32: =AVERAGE(C32:E32) -> 450000
A33: Software (Canva, Adobe, etc.) | B33: Comercial | C33: 60000 | D33: 60000 | E33: 60000 | F33: =AVERAGE(C33:E33) -> 60000
A34: Uber | B34: Comercial | C34: 80000 | D34: 80000 | E34: 80000 | F34: =AVERAGE(C34:E34) -> 80000
F35: =IF(COUNT(C35:E35)=0,0,AVERAGE(C35:E35)) -> 0 | G35: ← filas libres para agregar gastos
F36: =IF(COUNT(C36:E36)=0,0,AVERAGE(C36:E36)) -> 0
F37: =IF(COUNT(C37:E37)=0,0,AVERAGE(C37:E37)) -> 0
F38: =IF(COUNT(C38:E38)=0,0,AVERAGE(C38:E38)) -> 0
F39: =IF(COUNT(C39:E39)=0,0,AVERAGE(C39:E39)) -> 0
A41: TOTAL GASTOS DE FÁBRICA | C41: =SUMIF($B$5:$B$39,"Fábrica",C$5:C$39) -> 12421897 | D41: =SUMIF($B$5:$B$39,"Fábrica",D$5:D$39) -> 12421897 | E41: =SUMIF($B$5:$B$39,"Fábrica",E$5:E$39) -> 12421897 | F41: =SUMIF($B$5:$B$39,"Fábrica",F$5:F$39) -> 12421897
A42: TOTAL GASTOS COMERCIALES | C42: =SUMIF($B$5:$B$39,"Comercial",C$5:C$39) -> 4459061 | D42: =SUMIF($B$5:$B$39,"Comercial",D$5:D$39) -> 4459061 | E42: =SUMIF($B$5:$B$39,"Comercial",E$5:E$39) -> 4459061 | F42: =SUMIF($B$5:$B$39,"Comercial",F$5:F$39) -> 4459061
A43: TOTAL GASTOS FIJOS | C43: =C41+C42 -> 16880958 | D43: =D41+D42 -> 16880958 | E43: =E41+E42 -> 16880958 | F43: =F41+F42 -> 16880958
A45: VENTAS NETAS DEL MES ($) | C45: 32768213 | D45: 38874120 | E45: 33942186 | F45: =AVERAGE(C45:E45) -> 35194840 | G45: Fuente: hoja Proyectos_PMK (export Parrotfy), suma de Neto $ por mes. Septiembre no se usa: el export llega solo hasta el 5-sep.
A47: POR CONFIRMAR: el archivo original trae un solo mes de gastos; se repitió en los 3 meses. Reemplazar con el gasto real de cada mes.
A48: Fábrica = lo que cuesta tener la fábrica funcionando (arriendo, luz, todos los sueldos de producción). Comercial = vender (sueldos de ventas y marketing, publicidad). Puedes cambiar el grupo de cualquier línea.

Sheet Precios
A1: PRECIOS DE TELAS Y AVÍOS — neto, sin IVA
A2: Fuente: hoja 3_Insumos del Sistema de Costeo v2. Al cambiar un precio se actualizan todas las recetas. Cuando lo verifiques, cambia el estado a "Confirmado".
A4: Insumo | B4: Tipo | C4: Unidad | D4: Precio neto ($) | E4: Estado | F4: Nota
A5: MONTESIMONE TRAINING (fut pro) | B5: Tela | C5: kg | D5: 3531 | E5: Por confirmar
A6: LONDRES BLANCO | B6: Tela | C6: kg | D6: 5600 | E6: Por confirmar
A7: CIRE BLANCO | B7: Tela | C7: kg | D7: 5600 | E7: Por confirmar
A8: CIRE AZUL | B8: Tela | C8: kg | D8: 7500 | E8: Por confirmar
A9: MESH | B9: Tela | C9: kg | D9: 7700 | E9: Por confirmar
A10: FRANELA | B10: Tela | C10: kg | D10: 8000 | E10: Por confirmar
A11: PIQUE SELECCION | B11: Tela | C11: kg | D11: 7800 | E11: Por confirmar
A12: MICROFIBRA | B12: Tela | C12: kg | D12: 6900 | E12: Por confirmar
A13: CIRE MICROFIBRA AZUL REY | B13: Tela | C13: kg | D13: 7200 | E13: Por confirmar
A14: SCUBA | B14: Tela | C14: kg | D14: 7900 | E14: Por confirmar
A15: GLOBAL | B15: Tela | C15: kg | D15: 6800 | E15: Por confirmar
A16: PIQUE RUGBY | B16: Tela | C16: kg | D16: 5600 | E16: Por confirmar
... A33: JACQUARD BYTES | B33: Tela | C33: kg | D33: 4408 | E33: Por confirmar
A34: LYCRA | B34: Tela | C34: kg | E34: SIN PRECIO
A35: MALLA DEPORTIVA BLANCO | B35: Tela | C35: kg | D35: 6400 | E35: Por confirmar | F35: Estaba en avíos, pero se compra por kg como tela.
A36: NOVAK | B36: Tela | C36: kg | D36: 2975 | E36: Por confirmar | F36: Estaba en avíos, pero se compra por kg como tela.
A37: THERMAFLEECE | B37: Tela | C37: kg | D37: 8590 | E37: Por confirmar | F37: Estaba en avíos, pero se compra por kg como tela.
A38: Cuello | B38: Avío | C38: unidad | D38: 350 | E38: Por confirmar | F38: Precio marcado "estimado" en el archivo original.
A39: Puño | B39: Avío | C39: unidad | D39: 8500 | E39: Por confirmar | F39: $8.500 por unidad parece alto: ¿es por kg?
A40: Tapacuello | B40: Avío | C40: unidad | D40: 150 | E40: Por confirmar | F40: Precio marcado "estimado" en el archivo original.
A41: Hilo | B41: Avío | C41: unidad | D41: 80 | E41: Por confirmar | F41: Precio marcado "estimado" en el archivo original.
A42: Etiqueta | B42: Avío | C42: unidad | D42: 65 | E42: Por confirmar
A43: Cierre | B43: Avío | C43: unidad | D43: 600 | E43: Por confirmar | F43: Precio marcado "estimado" en el archivo original.
A44: Cordón | B44: Avío | C44: unidad | D44: 200 | E44: Por confirmar | F44: Precio marcado "estimado" en el archivo original.
A45: Elástico | B45: Avío | C45: unidad | D45: 5454 | E45: Por confirmar
A46: Forro | B46: Avío | C46: unidad | D46: 900 | E46: Por confirmar | F46: Precio marcado "estimado" en el archivo original.
A47: Cremallera bolsillo | B47: Avío | C47: unidad | D47: 400 | E47: Por confirmar | F47: Precio marcado "estimado" en el archivo original.

Sheet Confeccion
A1: CONFECCIÓN — valor que se paga al taller por prenda (neto, con planchado)
A2: Fuente: hoja Talleres_Confección del Sistema de Costeo v2. Agrega tipos nuevos al final.
A4: Tipo de prenda | B4: Valor con planchado ($) | C4: Sin planchado (ref.) | D4: Estado | E4: Nota
A5: Short De Futbol | B5: 1700 | C5: 1500 | D5: Por confirmar
A6: Camiseta De Futbol | B6: 2000 | C6: 1800 | D6: Por confirmar
A7: Camiseta De Futbol Retro | B7: 2200 | C7: 1900 | D7: Por confirmar
A8: Camiseta De Basket | B8: 1900 | C8: 1700 | D8: Por confirmar
A9: Camiseta De Basket Pro | B9: 2000 | C9: 1800 | D9: Por confirmar
A10: Short De Basket Pro | B10: 2200 | C10: 1700 | D10: Por confirmar
A11: Short De Basket | B11: 1900 | C11: 1700 | D11: Por confirmar
A12: Short De Basket Reversible | B12: 2400 | C12: 2000 | D12: Por confirmar
A13: Camiseta De Basket Reversible | B13: 2400 | C13: 2200 | D13: Por confirmar
A14: Camiseta De Rugby Básica | B14: 2200 | C14: 2000 | D14: Por confirmar
A15: Camiseta De Rugby Lycra | B15: 2600 | C15: 2300 | D15: Por confirmar
