Workbook

Sheet Ficha_costo
A1: FICHA DE COSTO — elige el molde y la tela de cada pieza
A2: Celdas azules = eliges tú. La tela vacía usa la de siempre del molde. El costo de cada pieza aparece al lado y el resumen abajo.
A3: Al cambiar de molde, borra las telas que elegiste en la columna "TELA (elige)" para partir con las de siempre.
A4: MOLDE ▶ | B4: 14 · FUTHOMU01PRO | F4: =IFERROR(INDEX(Recetas!$B$6:$B$115,MATCH($B$4,Recetas!$A$6:$A$115,0))&" · "&INDEX(Recetas!$D$6:$D$115,MATCH($B$4,Recetas!$A$6:$A$115,0))&" "&INDEX(Recetas!$E$6:$E$115,MATCH($B$4,Recetas!$A$6:$A$115,0)),"Elige un molde de la lista") -> Fútbol, pro, cuello redondo · Camiseta Masculino
A5: Consumo según: | B5: =IFERROR(IF(COUNTIFS(Mediciones!$C$6:$C$305,$B$4)>0,"Promedio de "&COUNTIFS(Mediciones!$C$6:$C$305,$B$4)&" medición(es) real(es) de corte, repartido por pieza según el despiece","Despiece"&IF(N(Parametros!$B$22)>0," + "&TEXT(Parametros!$B$22,"0%")&" de merma","")),"") -> Promedio de 2 medición(es) real(es) de corte, repartido por pieza según el despiece
A7: Pieza | B7: Cant. | C7: Grupo de tela | D7: Proceso | E7: TELA (elige) vacío = la de siempre | F7: Tela usada | G7: Metros por prenda | H7: $ por metro | I7: $ COSTO TELA de la pieza | J7: Aviso
A8: =IFERROR(INDEX(Despiece!$B$6:$B$705,MATCH($B$4&"|"&1,Despiece!$H$6:$H$705,0)),"") -> Delantero | B8: =IF(A8="","",INDEX(Despiece!$C$6:$C$705,MATCH($B$4&"|"&1,Despiece!$H$6:$H$705,0))) -> 1 | C8: =IF(A8="","",INDEX(Despiece!$D$6:$D$705,MATCH($B$4&"|"&1,Despiece!$H$6:$H$705,0))) -> Tela principal | D8: =IF(A8="","",INDEX(Despiece!$E$6:$E$705,MATCH($B$4&"|"&1,Despiece!$H$6:$H$705,0))) -> Sublimada | F8: =IF(A8="","",IF(E8<>"",E8,IFERROR(IF($C8="Tela principal",INDEX(Recetas!$K$6:$K$115,MATCH($B$4,Recetas!$A$6:$A$115,0))&"",IF($C8="Tela 2",INDEX(Recetas!$L$6:$L$115,MATCH($B$4,Recetas!$A$6:$A$115,0))&"",IF(INDEX(Recetas!$M$6:$M$115,MATCH($B$4,Recetas!$A$6:$A$115,0))&""="",INDEX(Recetas!$K$6:$K$115,MATCH($B$4,Recetas!$A$6:$A$115,0))&"",INDEX(Recetas!$M$6:$M$115,MATCH($B$4,Recetas!$A$6:$A$115,0))&""))),""))) -> MONTESIMONE TRAINING (fut pro) | G8: =IF(A8="","",IF(N(INDEX(Despiece!$F$6:$F$705,MATCH($B$4&"|"&1,Despiece!$H$6:$H$705,0)))>0,INDEX(Despiece!$F$6:$F$705,MATCH($B$4&"|"&1,Despiece!$H$6:$H$705,0))*IFERROR(IF($C8="Tela principal",INDEX(Recetas!$Q$6:$Q$115,MATCH($B$4,Recetas!$A$6:$A$115,0)),IF($C8="Tela 2",INDEX(Recetas!$T$6:$T$115,MATCH($B$4,Recetas!$A$6:$A$115,0)),INDEX(Recetas!$W$6:$W$115,MATCH($B$4,Recetas!$A$6:$A$115,0))))/IF($C8="Tela principal",INDEX(Recetas!$O$6:$O$115,MATCH($B$4,Recetas!$A$6:$A$115,0)),IF($C8="Tela 2",INDEX(Recetas!$R$6:$R$115,MATCH($B$4,Recetas!$A$6:$A$115,0)),INDEX(Recetas!$U$6:$U$115,MATCH($B$4,Recetas!$A$6:$A$115,0)))),1+Parametros!$B$22),"")) | H8: =IF(OR(A8="",F8=""),"",IFERROR(IF(N(INDEX(Telas!$I$6:$I$105,MATCH(F8,Telas!$A$6:$A$105,0)))>0,INDEX(Telas!$I$6:$I$105,MATCH(F8,Telas!$A$6:$A$105,0)),""),"")) -> 695.607 | I8: =IF(AND(ISNUMBER(G8),ISNUMBER(H8)),G8*H8,"") | J8: =IF(A8="","",IF(ISNUMBER(I8),"",IF(NOT(ISNUMBER(G8)),"Faltan los metros de esta pieza (hoja Despiece). ","")&IF(F8="","Elige la tela. ",IF(NOT(ISNUMBER(H8)),"Falta precio o peso de 1 m de "&F8&" (hoja Telas). ","")))) -> Faltan los metros de esta pieza (hoja Despiece).
A9: =IFERROR(INDEX(Despiece!$B$6:$B$705,MATCH($B$4&"|"&2,Despiece!$H$6:$H$705,0)),"") -> Espalda | B9: =IF(A9="","",INDEX(Despiece!$C$6:$C$705,MATCH($B$4&"|"&2,Despiece!$H$6:$H$705,0))) -> 1 | C9: =IF(A9="","",INDEX(Despiece!$D$6:$D$705,MATCH($B$4&"|"&2,Despiece!$H$6:$H$705,0))) -> Tela principal | D9: =IF(A9="","",INDEX(Despiece!$E$6:$E$705,MATCH($B$4&"|"&2,Despiece!$H$6:$H$705,0))) -> Sublimada | F9: =IF(A9="","",IF(E9<>"",E9,IFERROR(IF($C9="Tela principal",INDEX(Recetas!$K$6:$K$115,MATCH($B$4,Recetas!$A$6:$A$115,0))&"",IF($C9="Tela 2",INDEX(Recetas!$L$6:$L$115,MATCH($B$4,Recetas!$A$6:$A$115,0))&"",IF(INDEX(Recetas!$M$6:$M$115,MATCH($B$4,Recetas!$A$6:$A$115,0))&""="",INDEX(Recetas!$K$6:$K$115,MATCH($B$4,Recetas!$A$6:$A$115,0))&"",INDEX(Recetas!$M$6:$M$115,MATCH($B$4,Recetas!$A$6:$A$115,0))&""))),""))) -> MONTESIMONE TRAINING (fut pro) | G9: =IF(A9="","",IF(N(INDEX(Despiece!$F$6:$F$705,MATCH($B$4&"|"&2,Despiece!$H$6:$H$705,0)))>0,INDEX(Despiece!$F$6:$F$705,MATCH($B$4&"|"&2,Despiece!$H$6:$H$705,0))*IFERROR(IF($C9="Tela principal",INDEX(Recetas!$Q$6:$Q$115,MATCH($B$4,Recetas!$A$6:$A$115,0)),IF($C9="Tela 2",INDEX(Recetas!$T$6:$T$115,MATCH($B$4,Recetas!$A$6:$A$115,0)),INDEX(Recetas!$W$6:$W$115,MATCH($B$4,Recetas!$A$6:$A$115,0))))/IF($C9="Tela principal",INDEX(Recetas!$O$6:$O$115,MATCH($B$4,Recetas!$A$6:$A$115,0)),IF($C9="Tela 2",INDEX(Recetas!$R$6:$R$115,MATCH($B$4,Recetas!$A$6:$A$115,0)),INDEX(Recetas!$U$6:$U$115,MATCH($B$4,Recetas!$A$6:$A$115,0)))),1+Parametros!$B$22),"")) | H9: =IF(OR(A9="",F9=""),"",IFERROR(IF(N(INDEX(Telas!$I$6:$I$105,MATCH(F9,Telas!$A$6:$A$105,0)))>0,INDEX(Telas!$I$6:$I$105,MATCH(F9,Telas!$A$6:$A$105,0)),""),"")) -> 695.607 | I9: =IF(AND(ISNUMBER(G9),ISNUMBER(H9)),G9*H9,"") | J9: =IF(A9="","",IF(ISNUMBER(I9),"",IF(NOT(ISNUMBER(G9)),"Faltan los metros de esta pieza (hoja Despiece). ","")&IF(F9="","Elige la tela. ",IF(NOT(ISNUMBER(H9)),"Falta precio o peso de 1 m de "&F9&" (hoja Telas). ","")))) -> Faltan los metros de esta pieza (hoja Despiece).
A10: =IFERROR(INDEX(Despiece!$B$6:$B$705,MATCH($B$4&"|"&3,Despiece!$H$6:$H$705,0)),"") -> Manga | B10: =IF(A10="","",INDEX(Despiece!$C$6:$C$705,MATCH($B$4&"|"&3,Despiece!$H$6:$H$705,0))) -> 2 | C10: =IF(A10="","",INDEX(Despiece!$D$6:$D$705,MATCH($B$4&"|"&3,Despiece!$H$6:$H$705,0))) -> Tela principal | D10: =IF(A10="","",INDEX(Despiece!$E$6:$E$705,MATCH($B$4&"|"&3,Despiece!$H$6:$H$705,0))) -> Sublimada | F10: =IF(A10="","",IF(E10<>"",E10,IFERROR(IF($C10="Tela principal",INDEX(Recetas!$K$6:$K$115,MATCH($B$4,Recetas!$A$6:$A$115,0))&"",IF($C10="Tela 2",INDEX(Recetas!$L$6:$L$115,MATCH($B$4,Recetas!$A$6:$A$115,0))&"",IF(INDEX(Recetas!$M$6:$M$115,MATCH($B$4,Recetas!$A$6:$A$115,0))&""="",INDEX(Recetas!$K$6:$K$115,MATCH($B$4,Recetas!$A$6:$A$115,0))&"",INDEX(Recetas!$M$6:$M$115,MATCH($B$4,Recetas!$A$6:$A$115,0))&""))),""))) -> MONTESIMONE TRAINING (fut pro) | G10: =IF(A10="","",IF(N(INDEX(Despiece!$F$6:$F$705,MATCH($B$4&"|"&3,Despiece!$H$6:$H$705,0)))>0,INDEX(Despiece!$F$6:$F$705,MATCH($B$4&"|"&3,Despiece!$H$6:$H$705,0))*IFERROR(IF($C10="Tela principal",INDEX(Recetas!$Q$6:$Q$115,MATCH($B$4,Recetas!$A$6:$A$115,0)),IF($C10="Tela 2",INDEX(Recetas!$T$6:$T$115,MATCH($B$4,Recetas!$A$6:$A$115,0)),INDEX(Recetas!$W$6:$W$115,MATCH($B$4,Recetas!$A$6:$A$115,0))))/IF($C10="Tela principal",INDEX(Recetas!$O$6:$O$115,MATCH($B$4,Recetas!$A$6:$A$115,0)),IF($C10="Tela 2",INDEX(Recetas!$R$6:$R$115,MATCH($B$4,Recetas!$A$6:$A$115,0)),INDEX(Recetas!$U$6:$U$115,MATCH($B$4,Recetas!$A$6:$A$115,0)))),1+Parametros!$B$22),"")) | H10: =IF(OR(A10="",F10=""),"",IFERROR(IF(N(INDEX(Telas!$I$6:$I$105,MATCH(F10,Telas!$A$6:$A$105,0)))>0,INDEX(Telas!$I$6:$I$105,MATCH(F10,Telas!$A$6:$A$105,0)),""),"")) -> 695.607 | I10: =IF(AND(ISNUMBER(G10),ISNUMBER(H10)),G10*H10,"") | J10: =IF(A10="","",IF(ISNUMBER(I10),"",IF(NOT(ISNUMBER(G10)),"Faltan los metros de esta pieza (hoja Despiece). ","")&IF(F10="","Elige la tela. ",IF(NOT(ISNUMBER(H10)),"Falta precio o peso de 1 m de "&F10&" (hoja Telas). ","")))) -> Faltan los metros de esta pieza (hoja Despiece).
A11: =IFERROR(INDEX(Despiece!$B$6:$B$705,MATCH($B$4&"|"&4,Despiece!$H$6:$H$705,0)),"") -> Tira de cuello | B11: =IF(A11="","",INDEX(Despiece!$C$6:$C$705,MATCH($B$4&"|"&4,Despiece!$H$6:$H$705,0))) -> 1 | C11: =IF(A11="","",INDEX(Despiece!$D$6:$D$705,MATCH($B$4&"|"&4,Despiece!$H$6:$H$705,0))) -> Tela principal | D11: =IF(A11="","",INDEX(Despiece!$E$6:$E$705,MATCH($B$4&"|"&4,Despiece!$H$6:$H$705,0))) -> Sublimada | F11: =IF(A11="","",IF(E11<>"",E11,IFERROR(IF($C11="Tela principal",INDEX(Recetas!$K$6:$K$115,MATCH($B$4,Recetas!$A$6:$A$115,0))&"",IF($C11="Tela 2",INDEX(Recetas!$L$6:$L$115,MATCH($B$4,Recetas!$A$6:$A$115,0))&"",IF(INDEX(Recetas!$M$6:$M$115,MATCH($B$4,Recetas!$A$6:$A$115,0))&""="",INDEX(Recetas!$K$6:$K$115,MATCH($B$4,Recetas!$A$6:$A$115,0))&"",INDEX(Recetas!$M$6:$M$115,MATCH($B$4,Recetas!$A$6:$A$115,0))&""))),""))) -> MONTESIMONE TRAINING (fut pro) | G11: =IF(A11="","",IF(N(INDEX(Despiece!$F$6:$F$705,MATCH($B$4&"|"&4,Despiece!$H$6:$H$705,0)))>0,INDEX(Despiece!$F$6:$F$705,MATCH($B$4&"|"&4,Despiece!$H$6:$H$705,0))*IFERROR(IF($C11="Tela principal",INDEX(Recetas!$Q$6:$Q$115,MATCH($B$4,Recetas!$A$6:$A$115,0)),IF($C11="Tela 2",INDEX(Recetas!$T$6:$T$115,MATCH($B$4,Recetas!$A$6:$A$115,0)),INDEX(Recetas!$W$6:$W$115,MATCH($B$4,Recetas!$A$6:$A$115,0))))/IF($C11="Tela principal",INDEX(Recetas!$O$6:$O$115,MATCH($B$4,Recetas!$A$6:$A$115,0)),IF($C11="Tela 2",INDEX(Recetas!$R$6:$R$115,MATCH($B$4,Recetas!$A$6:$A$115,0)),INDEX(Recetas!$U$6:$U$115,MATCH($B$4,Recetas!$A$6:$A$115,0)))),1+Parametros!$B$22),"")) | H11: =IF(OR(A11="",F11=""),"",IFERROR(IF(N(INDEX(Telas!$I$6:$I$105,MATCH(F11,Telas!$A$6:$A$105,0)))>0,INDEX(Telas!$I$6:$I$105,MATCH(F11,Telas!$A$6:$A$105,0)),""),"")) -> 695.607 | I11: =IF(AND(ISNUMBER(G11),ISNUMBER(H11)),G11*H11,"") | J11: =IF(A11="","",IF(ISNUMBER(I11),"",IF(NOT(ISNUMBER(G11)),"Faltan los metros de esta pieza (hoja Despiece). ","")&IF(F11="","Elige la tela. ",IF(NOT(ISNUMBER(H11)),"Falta precio o peso de 1 m de "&F11&" (hoja Telas). ","")))) -> Faltan los metros de esta pieza (hoja Despiece).
A12: =IFERROR(INDEX(Despiece!$B$6:$B$705,MATCH($B$4&"|"&5,Despiece!$H$6:$H$705,0)),"") -> Paneles laterales | B12: =IF(A12="","",INDEX(Despiece!$C$6:$C$705,MATCH($B$4&"|"&5,Despiece!$H$6:$H$705,0))) -> 2 | C12: =IF(A12="","",INDEX(Despiece!$D$6:$D$705,MATCH($B$4&"|"&5,Despiece!$H$6:$H$705,0))) -> Tela 2 | D12: =IF(A12="","",INDEX(Despiece!$E$6:$E$705,MATCH($B$4&"|"&5,Despiece!$H$6:$H$705,0))) -> Sublimada | F12: =IF(A12="","",IF(E12<>"",E12,IFERROR(IF($C12="Tela principal",INDEX(Recetas!$K$6:$K$115,MATCH($B$4,Recetas!$A$6:$A$115,0))&"",IF($C12="Tela 2",INDEX(Recetas!$L$6:$L$115,MATCH($B$4,Recetas!$A$6:$A$115,0))&"",IF(INDEX(Recetas!$M$6:$M$115,MATCH($B$4,Recetas!$A$6:$A$115,0))&""="",INDEX(Recetas!$K$6:$K$115,MATCH($B$4,Recetas!$A$6:$A$115,0))&"",INDEX(Recetas!$M$6:$M$115,MATCH($B$4,Recetas!$A$6:$A$115,0))&""))),""))) -> MESH | G12: =IF(A12="","",IF(N(INDEX(Despiece!$F$6:$F$705,MATCH($B$4&"|"&5,Despiece!$H$6:$H$705,0)))>0,INDEX(Despiece!$F$6:$F$705,MATCH($B$4&"|"&5,Despiece!$H$6:$H$705,0))*IFERROR(IF($C12="Tela principal",INDEX(Recetas!$Q$6:$Q$115,MATCH($B$4,Recetas!$A$6:$A$115,0)),IF($C12="Tela 2",INDEX(Recetas!$T$6:$T$115,MATCH($B$4,Recetas!$A$6:$A$115,0)),INDEX(Recetas!$W$6:$W$115,MATCH($B$4,Recetas!$A$6:$A$115,0))))/IF($C12="Tela principal",INDEX(Recetas!$O$6:$O$115,MATCH($B$4,Recetas!$A$6:$A$115,0)),IF($C12="Tela 2",INDEX(Recetas!$R$6:$R$115,MATCH($B$4,Recetas!$A$6:$A$115,0)),INDEX(Recetas!$U$6:$U$115,MATCH($B$4,Recetas!$A$6:$A$115,0)))),1+Parametros!$B$22),"")) | H12: =IF(OR(A12="",F12=""),"",IFERROR(IF(N(INDEX(Telas!$I$6:$I$105,MATCH(F12,Telas!$A$6:$A$105,0)))>0,INDEX(Telas!$I$6:$I$105,MATCH(F12,Telas!$A$6:$A$105,0)),""),"")) | I12: =IF(AND(ISNUMBER(G12),ISNUMBER(H12)),G12*H12,"") | J12: =IF(A12="","",IF(ISNUMBER(I12),"",IF(NOT(ISNUMBER(G12)),"Faltan los metros de esta pieza (hoja Despiece). ","")&IF(F12="","Elige la tela. ",IF(NOT(ISNUMBER(H12)),"Falta precio o peso de 1 m de "&F12&" (hoja Telas). ","")))) -> Faltan los metros de esta pieza (hoja Despiece). Falta precio o peso de 1 m de MESH (hoja Telas).
A13: =IFERROR(INDEX(Despiece!$B$6:$B$705,MATCH($B$4&"|"&6,Despiece!$H$6:$H$705,0)),"") | B13: =IF(A13="","",INDEX(Despiece!$C$6:$C$705,MATCH($B$4&"|"&6,Despiece!$H$6:$H$705,0))) | C13: =IF(A13="","",INDEX(Despiece!$D$6:$D$705,MATCH($B$4&"|"&6,Despiece!$H$6:$H$705,0))) | D13: =IF(A13="","",INDEX(Despiece!$E$6:$E$705,MATCH($B$4&"|"&6,Despiece!$H$6:$H$705,0))) | F13: =IF(A13="","",IF(E13<>"",E13,IFERROR(IF($C13="Tela principal",INDEX(Recetas!$K$6:$K$115,MATCH($B$4,Recetas!$A$6:$A$115,0))&"",IF($C13="Tela 2",INDEX(Recetas!$L$6:$L$115,MATCH($B$4,Recetas!$A$6:$A$115,0))&"",IF(INDEX(Recetas!$M$6:$M$115,MATCH($B$4,Recetas!$A$6:$A$115,0))&""="",INDEX(Recetas!$K$6:$K$115,MATCH($B$4,Recetas!$A$6:$A$115,0))&"",INDEX(Recetas!$M$6:$M$115,MATCH($B$4,Recetas!$A$6:$A$115,0))&""))),""))) | G13: =IF(A13="","",IF(N(INDEX(Despiece!$F$6:$F$705,MATCH($B$4&"|"&6,Despiece!$H$6:$H$705,0)))>0,INDEX(Despiece!$F$6:$F$705,MATCH($B$4&"|"&6,Despiece!$H$6:$H$705,0))*IFERROR(IF($C13="Tela principal",INDEX(Recetas!$Q$6:$Q$115,MATCH($B$4,Recetas!$A$6:$A$115,0)),IF($C13="Tela 2",INDEX(Recetas!$T$6:$T$115,MATCH($B$4,Recetas!$A$6:$A$115,0)),INDEX(Recetas!$W$6:$W$115,MATCH($B$4,Recetas!$A$6:$A$115,0))))/IF($C13="Tela principal",INDEX(Recetas!$O$6:$O$115,MATCH($B$4,Recetas!$A$6:$A$115,0)),IF($C13="Tela 2",INDEX(Recetas!$R$6:$R$115,MATCH($B$4,Recetas!$A$6:$A$115,0)),INDEX(Recetas!$U$6:$U$115,MATCH($B$4,Recetas!$A$6:$A$115,0)))),1+Parametros!$B$22),"")) | H13: =IF(OR(A13="",F13=""),"",IFERROR(IF(N(INDEX(Telas!$I$6:$I$105,MATCH(F13,Telas!$A$6:$A$105,0)))>0,INDEX(Telas!$I$6:$I$105,MATCH(F13,Telas!$A$6:$A$105,0)),""),"")) | I13: =IF(AND(ISNUMBER(G13),ISNUMBER(H13)),G13*H13,"") | J13: =IF(A13="","",IF(ISNUMBER(I13),"",IF(NOT(ISNUMBER(G13)),"Faltan los metros de esta pieza (hoja Despiece). ","")&IF(F13="","Elige la tela. ",IF(NOT(ISNUMBER(H13)),"Falta precio o peso de 1 m de "&F13&" (hoja Telas). ",""))))
A14: =IFERROR(INDEX(Despiece!$B$6:$B$705,MATCH($B$4&"|"&7,Despiece!$H$6:$H$705,0)),"") | B14: =IF(A14="","",INDEX(Despiece!$C$6:$C$705,MATCH($B$4&"|"&7,Despiece!$H$6:$H$705,0))) | C14: =IF(A14="","",INDEX(Despiece!$D$6:$D$705,MATCH($B$4&"|"&7,Despiece!$H$6:$H$705,0))) | D14: =IF(A14="","",INDEX(Despiece!$E$6:$E$705,MATCH($B$4&"|"&7,Despiece!$H$6:$H$705,0))) | F14: =IF(A14="","",IF(E14<>"",E14,IFERROR(IF($C14="Tela principal",INDEX(Recetas!$K$6:$K$115,MATCH($B$4,Recetas!$A$6:$A$115,0))&"",IF($C14="Tela 2",INDEX(Recetas!$L$6:$L$115,MATCH($B$4,Recetas!$A$6:$A$115,0))&"",IF(INDEX(Recetas!$M$6:$M$115,MATCH($B$4,Recetas!$A$6:$A$115,0))&""="",INDEX(Recetas!$K$6:$K$115,MATCH($B$4,Recetas!$A$6:$A$115,0))&"",INDEX(Recetas!$M$6:$M$115,MATCH($B$4,Recetas!$A$6:$A$115,0))&""))),""))) | G14: =IF(A14="","",IF(N(INDEX(Despiece!$F$6:$F$705,MATCH($B$4&"|"&7,Despiece!$H$6:$H$705,0)))>0,INDEX(Despiece!$F$6:$F$705,MATCH($B$4&"|"&7,Despiece!$H$6:$H$705,0))*IFERROR(IF($C14="Tela principal",INDEX(Recetas!$Q$6:$Q$115,MATCH($B$4,Recetas!$A$6:$A$115,0)),IF($C14="Tela 2",INDEX(Recetas!$T$6:$T$115,MATCH($B$4,Recetas!$A$6:$A$115,0)),INDEX(Recetas!$W$6:$W$115,MATCH($B$4,Recetas!$A$6:$A$115,0))))/IF($C14="Tela principal",INDEX(Recetas!$O$6:$O$115,MATCH($B$4,Recetas!$A$6:$A$115,0)),IF($C14="Tela 2",INDEX(Recetas!$R$6:$R$115,MATCH($B$4,Recetas!$A$6:$A$115,0)),INDEX(Recetas!$U$6:$U$115,MATCH($B$4,Recetas!$A$6:$A$115,0)))),1+Parametros!$B$22),"")) | H14: =IF(OR(A14="",F14=""),"",IFERROR(IF(N(INDEX(Telas!$I$6:$I$105,MATCH(F14,Telas!$A$6:$A$105,0)))>0,INDEX(Telas!$I$6:$I$105,MATCH(F14,Telas!$A$6:$A$105,0)),""),"")) | I14: =IF(AND(ISNUMBER(G14),ISNUMBER(H14)),G14*H14,"") | J14: =IF(A14="","",IF(ISNUMBER(I14),"",IF(NOT(ISNUMBER(G14)),"Faltan los metros de esta pieza (hoja Despiece). ","")&IF(F14="","Elige la tela. ",IF(NOT(ISNUMBER(H14)),"Falta precio o peso de 1 m de "&F14&" (hoja Telas). ",""))))
A15: =IFERROR(INDEX(Despiece!$B$6:$B$705,MATCH($B$4&"|"&8,Despiece!$H$6:$H$705,0)),"") | B15: =IF(A15="","",INDEX(Despiece!$C$6:$C$705,MATCH($B$4&"|"&8,Despiece!$H$6:$H$705,0))) | C15: =IF(A15="","",INDEX(Despiece!$D$6:$D$705,MATCH($B$4&"|"&8,Despiece!$H$6:$H$705,0))) | D15: =IF(A15="","",INDEX(Despiece!$E$6:$E$705,MATCH($B$4&"|"&8,Despiece!$H$6:$H$705,0))) | F15: =IF(A15="","",IF(E15<>"",E15,IFERROR(IF($C15="Tela principal",INDEX(Recetas!$K$6:$K$115,MATCH($B$4,Recetas!$A$6:$A$115,0))&"",IF($C15="Tela 2",INDEX(Recetas!$L$6:$L$115,MATCH($B$4,Recetas!$A$6:$A$115,0))&"",IF(INDEX(Recetas!$M$6:$M$115,MATCH($B$4,Recetas!$A$6:$A$115,0))&""="",INDEX(Recetas!$K$6:$K$115,MATCH($B$4,Recetas!$A$6:$A$115,0))&"",INDEX(Recetas!$M$6:$M$115,MATCH($B$4,Recetas!$A$6:$A$115,0))&""))),""))) | G15: =IF(A15="","",IF(N(INDEX(Despiece!$F$6:$F$705,MATCH($B$4&"|"&8,Despiece!$H$6:$H$705,0)))>0,INDEX(Despiece!$F$6:$F$705,MATCH($B$4&"|"&8,Despiece!$H$6:$H$705,0))*IFERROR(IF($C15="Tela principal",INDEX(Recetas!$Q$6:$Q$115,MATCH($B$4,Recetas!$A$6:$A$115,0)),IF($C15="Tela 2",INDEX(Recetas!$T$6:$T$115,MATCH($B$4,Recetas!$A$6:$A$115,0)),INDEX(Recetas!$W$6:$W$115,MATCH($B$4,Recetas!$A$6:$A$115,0))))/IF($C15="Tela principal",INDEX(Recetas!$O$6:$O$115,MATCH($B$4,Recetas!$A$6:$A$115,0)),IF($C15="Tela 2",INDEX(Recetas!$R$6:$R$115,MATCH($B$4,Recetas!$A$6:$A$115,0)),INDEX(Recetas!$U$6:$U$115,MATCH($B$4,Recetas!$A$6:$A$115,0)))),1+Parametros!$B$22),"")) | H15: =IF(OR(A15="",F15=""),"",IFERROR(IF(N(INDEX(Telas!$I$6:$I$105,MATCH(F15,Telas!$A$6:$A$105,0)))>0,INDEX(Telas!$I$6:$I$105,MATCH(F15,Telas!$A$6:$A$105,0)),""),"")) | I15: =IF(AND(ISNUMBER(G15),ISNUMBER(H15)),G15*H15,"") | J15: =IF(A15="","",IF(ISNUMBER(I15),"",IF(NOT(ISNUMBER(G15)),"Faltan los metros de esta pieza (hoja Despiece). ","")&IF(F15="","Elige la tela. ",IF(NOT(ISNUMBER(H15)),"Falta precio o peso de 1 m de "&F15&" (hoja Telas). ",""))))
A16: =IFERROR(INDEX(Despiece!$B$6:$B$705,MATCH($B$4&"|"&9,Despiece!$H$6:$H$705,0)),"") | B16: =IF(A16="","",INDEX(Despiece!$C$6:$C$705,MATCH($B$4&"|"&9,Despiece!$H$6:$H$705,0))) | C16: =IF(A16="","",INDEX(Despiece!$D$6:$D$705,MATCH($B$4&"|"&9,Despiece!$H$6:$H$705,0))) | D16: =IF(A16="","",INDEX(Despiece!$E$6:$E$705,MATCH($B$4&"|"&9,Despiece!$H$6:$H$705,0))) | F16: =IF(A16="","",IF(E16<>"",E16,IFERROR(IF($C16="Tela principal",INDEX(Recetas!$K$6:$K$115,MATCH($B$4,Recetas!$A$6:$A$115,0))&"",IF($C16="Tela 2",INDEX(Recetas!$L$6:$L$115,MATCH($B$4,Recetas!$A$6:$A$115,0))&"",IF(INDEX(Recetas!$M$6:$M$115,MATCH($B$4,Recetas!$A$6:$A$115,0))&""="",INDEX(Recetas!$K$6:$K$115,MATCH($B$4,Recetas!$A$6:$A$115,0))&"",INDEX(Recetas!$M$6:$M$115,MATCH($B$4,Recetas!$A$6:$A$115,0))&""))),""))) | G16: =IF(A16="","",IF(N(INDEX(Despiece!$F$6:$F$705,MATCH($B$4&"|"&9,Despiece!$H$6:$H$705,0)))>0,INDEX(Despiece!$F$6:$F$705,MATCH($B$4&"|"&9,Despiece!$H$6:$H$705,0))*IFERROR(IF($C16="Tela principal",INDEX(Recetas!$Q$6:$Q$115,MATCH($B$4,Recetas!$A$6:$A$115,0)),IF($C16="Tela 2",INDEX(Recetas!$T$6:$T$115,MATCH($B$4,Recetas!$A$6:$A$115,0)),INDEX(Recetas!$W$6:$W$115,MATCH($B$4,Recetas!$A$6:$A$115,0))))/IF($C16="Tela principal",INDEX(Recetas!$O$6:$O$115,MATCH($B$4,Recetas!$A$6:$A$115,0)),IF($C16="Tela 2",INDEX(Recetas!$R$6:$R$115,MATCH($B$4,Recetas!$A$6:$A$115,0)),INDEX(Recetas!$U$6:$U$115,MATCH($B$4,Recetas!$A$6:$A$115,0)))),1+Parametros!$B$22),"")) | H16: =IF(OR(A16="",F16=""),"",IFERROR(IF(N(INDEX(Telas!$I$6:$I$105,MATCH(F16,Telas!$A$6:$A$105,0)))>0,INDEX(Telas!$I$6:$I$105,MATCH(F16,Telas!$A$6:$A$105,0)),""),"")) | I16: =IF(AND(ISNUMBER(G16),ISNUMBER(H16)),G16*H16,"") | J16: =IF(A16="","",IF(ISNUMBER(I16),"",IF(NOT(ISNUMBER(G16)),"Faltan los metros de esta pieza (hoja Despiece). ","")&IF(F16="","Elige la tela. ",IF(NOT(ISNUMBER(H16)),"Falta precio o peso de 1 m de "&F16&" (hoja Telas). ",""))))
A17: =IFERROR(INDEX(Despiece!$B$6:$B$705,MATCH($B$4&"|"&10,Despiece!$H$6:$H$705,0)),"") | B17: =IF(A17="","",INDEX(Despiece!$C$6:$C$705,MATCH($B$4&"|"&10,Despiece!$H$6:$H$705,0))) | C17: =IF(A17="","",INDEX(Despiece!$D$6:$D$705,MATCH($B$4&"|"&10,Despiece!$H$6:$H$705,0))) | D17: =IF(A17="","",INDEX(Despiece!$E$6:$E$705,MATCH($B$4&"|"&10,Despiece!$H$6:$H$705,0))) | F17: =IF(A17="","",IF(E17<>"",E17,IFERROR(IF($C17="Tela principal",INDEX(Recetas!$K$6:$K$115,MATCH($B$4,Recetas!$A$6:$A$115,0))&"",IF($C17="Tela 2",INDEX(Recetas!$L$6:$L$115,MATCH($B$4,Recetas!$A$6:$A$115,0))&"",IF(INDEX(Recetas!$M$6:$M$115,MATCH($B$4,Recetas!$A$6:$A$115,0))&""="",INDEX(Recetas!$K$6:$K$115,MATCH($B$4,Recetas!$A$6:$A$115,0))&"",INDEX(Recetas!$M$6:$M$115,MATCH($B$4,Recetas!$A$6:$A$115,0))&""))),""))) | G17: =IF(A17="","",IF(N(INDEX(Despiece!$F$6:$F$705,MATCH($B$4&"|"&10,Despiece!$H$6:$H$705,0)))>0,INDEX(Despiece!$F$6:$F$705,MATCH($B$4&"|"&10,Despiece!$H$6:$H$705,0))*IFERROR(IF($C17="Tela principal",INDEX(Recetas!$Q$6:$Q$115,MATCH($B$4,Recetas!$A$6:$A$115,0)),IF($C17="Tela 2",INDEX(Recetas!$T$6:$T$115,MATCH($B$4,Recetas!$A$6:$A$115,0)),INDEX(Recetas!$W$6:$W$115,MATCH($B$4,Recetas!$A$6:$A$115,0))))/IF($C17="Tela principal",INDEX(Recetas!$O$6:$O$115,MATCH($B$4,Recetas!$A$6:$A$115,0)),IF($C17="Tela 2",INDEX(Recetas!$R$6:$R$115,MATCH($B$4,Recetas!$A$6:$A$115,0)),INDEX(Recetas!$U$6:$U$115,MATCH($B$4,Recetas!$A$6:$A$115,0)))),1+Parametros!$B$22),"")) | H17: =IF(OR(A17="",F17=""),"",IFERROR(IF(N(INDEX(Telas!$I$6:$I$105,MATCH(F17,Telas!$A$6:$A$105,0)))>0,INDEX(Telas!$I$6:$I$105,MATCH(F17,Telas!$A$6:$A$105,0)),""),"")) | I17: =IF(AND(ISNUMBER(G17),ISNUMBER(H17)),G17*H17,"") | J17: =IF(A17="","",IF(ISNUMBER(I17),"",IF(NOT(ISNUMBER(G17)),"Faltan los metros de esta pieza (hoja Despiece). ","")&IF(F17="","Elige la tela. ",IF(NOT(ISNUMBER(H17)),"Falta precio o peso de 1 m de "&F17&" (hoja Telas). ",""))))
A18: =IFERROR(INDEX(Despiece!$B$6:$B$705,MATCH($B$4&"|"&11,Despiece!$H$6:$H$705,0)),"") | B18: =IF(A18="","",INDEX(Despiece!$C$6:$C$705,MATCH($B$4&"|"&11,Despiece!$H$6:$H$705,0))) | C18: =IF(A18="","",INDEX(Despiece!$D$6:$D$705,MATCH($B$4&"|"&11,Despiece!$H$6:$H$705,0))) | D18: =IF(A18="","",INDEX(Despiece!$E$6:$E$705,MATCH($B$4&"|"&11,Despiece!$H$6:$H$705,0))) | F18: =IF(A18="","",IF(E18<>"",E18,IFERROR(IF($C18="Tela principal",INDEX(Recetas!$K$6:$K$115,MATCH($B$4,Recetas!$A$6:$A$115,0))&"",IF($C18="Tela 2",INDEX(Recetas!$L$6:$L$115,MATCH($B$4,Recetas!$A$6:$A$115,0))&"",IF(INDEX(Recetas!$M$6:$M$115,MATCH($B$4,Recetas!$A$6:$A$115,0))&""="",INDEX(Recetas!$K$6:$K$115,MATCH($B$4,Recetas!$A$6:$A$115,0))&"",INDEX(Recetas!$M$6:$M$115,MATCH($B$4,Recetas!$A$6:$A$115,0))&""))),""))) | G18: =IF(A18="","",IF(N(INDEX(Despiece!$F$6:$F$705,MATCH($B$4&"|"&11,Despiece!$H$6:$H$705,0)))>0,INDEX(Despiece!$F$6:$F$705,MATCH($B$4&"|"&11,Despiece!$H$6:$H$705,0))*IFERROR(IF($C18="Tela principal",INDEX(Recetas!$Q$6:$Q$115,MATCH($B$4,Recetas!$A$6:$A$115,0)),IF($C18="Tela 2",INDEX(Recetas!$T$6:$T$115,MATCH($B$4,Recetas!$A$6:$A$115,0)),INDEX(Recetas!$W$6:$W$115,MATCH($B$4,Recetas!$A$6:$A$115,0))))/IF($C18="Tela principal",INDEX(Recetas!$O$6:$O$115,MATCH($B$4,Recetas!$A$6:$A$115,0)),IF($C18="Tela 2",INDEX(Recetas!$R$6:$R$115,MATCH($B$4,Recetas!$A$6:$A$115,0)),INDEX(Recetas!$U$6:$U$115,MATCH($B$4,Recetas!$A$6:$A$115,0)))),1+Parametros!$B$22),"")) | H18: =IF(OR(A18="",F18=""),"",IFERROR(IF(N(INDEX(Telas!$I$6:$I$105,MATCH(F18,Telas!$A$6:$A$105,0)))>0,INDEX(Telas!$I$6:$I$105,MATCH(F18,Telas!$A$6:$A$105,0)),""),"")) | I18: =IF(AND(ISNUMBER(G18),ISNUMBER(H18)),G18*H18,"") | J18: =IF(A18="","",IF(ISNUMBER(I18),"",IF(NOT(ISNUMBER(G18)),"Faltan los metros de esta pieza (hoja Despiece). ","")&IF(F18="","Elige la tela. ",IF(NOT(ISNUMBER(H18)),"Falta precio o peso de 1 m de "&F18&" (hoja Telas). ",""))))
A19: =IFERROR(INDEX(Despiece!$B$6:$B$705,MATCH($B$4&"|"&12,Despiece!$H$6:$H$705,0)),"") | B19: =IF(A19="","",INDEX(Despiece!$C$6:$C$705,MATCH($B$4&"|"&12,Despiece!$H$6:$H$705,0))) | C19: =IF(A19="","",INDEX(Despiece!$D$6:$D$705,MATCH($B$4&"|"&12,Despiece!$H$6:$H$705,0))) | D19: =IF(A19="","",INDEX(Despiece!$E$6:$E$705,MATCH($B$4&"|"&12,Despiece!$H$6:$H$705,0))) | F19: =IF(A19="","",IF(E19<>"",E19,IFERROR(IF($C19="Tela principal",INDEX(Recetas!$K$6:$K$115,MATCH($B$4,Recetas!$A$6:$A$115,0))&"",IF($C19="Tela 2",INDEX(Recetas!$L$6:$L$115,MATCH($B$4,Recetas!$A$6:$A$115,0))&"",IF(INDEX(Recetas!$M$6:$M$115,MATCH($B$4,Recetas!$A$6:$A$115,0))&""="",INDEX(Recetas!$K$6:$K$115,MATCH($B$4,Recetas!$A$6:$A$115,0))&"",INDEX(Recetas!$M$6:$M$115,MATCH($B$4,Recetas!$A$6:$A$115,0))&""))),""))) | G19: =IF(A19="","",IF(N(INDEX(Despiece!$F$6:$F$705,MATCH($B$4&"|"&12,Despiece!$H$6:$H$705,0)))>0,INDEX(Despiece!$F$6:$F$705,MATCH($B$4&"|"&12,Despiece!$H$6:$H$705,0))*IFERROR(IF($C19="Tela principal",INDEX(Recetas!$Q$6:$Q$115,MATCH($B$4,Recetas!$A$6:$A$115,0)),IF($C19="Tela 2",INDEX(Recetas!$T$6:$T$115,MATCH($B$4,Recetas!$A$6:$A$115,0)),INDEX(Recetas!$W$6:$W$115,MATCH($B$4,Recetas!$A$6:$A$115,0))))/IF($C19="Tela principal",INDEX(Recetas!$O$6:$O$115,MATCH($B$4,Recetas!$A$6:$A$115,0)),IF($C19="Tela 2",INDEX(Recetas!$R$6:$R$115,MATCH($B$4,Recetas!$A$6:$A$115,0)),INDEX(Recetas!$U$6:$U$115,MATCH($B$4,Recetas!$A$6:$A$115,0)))),1+Parametros!$B$22),"")) | H19: =IF(OR(A19="",F19=""),"",IFERROR(IF(N(INDEX(Telas!$I$6:$I$105,MATCH(F19,Telas!$A$6:$A$105,0)))>0,INDEX(Telas!$I$6:$I$105,MATCH(F19,Telas!$A$6:$A$105,0)),""),"")) | I19: =IF(AND(ISNUMBER(G19),ISNUMBER(H19)),G19*H19,"") | J19: =IF(A19="","",IF(ISNUMBER(I19),"",IF(NOT(ISNUMBER(G19)),"Faltan los metros de esta pieza (hoja Despiece). ","")&IF(F19="","Elige la tela. ",IF(NOT(ISNUMBER(H19)),"Falta precio o peso de 1 m de "&F19&" (hoja Telas). ",""))))
A20: =IFERROR(INDEX(Despiece!$B$6:$B$705,MATCH($B$4&"|"&13,Despiece!$H$6:$H$705,0)),"") | B20: =IF(A20="","",INDEX(Despiece!$C$6:$C$705,MATCH($B$4&"|"&13,Despiece!$H$6:$H$705,0))) | C20: =IF(A20="","",INDEX(Despiece!$D$6:$D$705,MATCH($B$4&"|"&13,Despiece!$H$6:$H$705,0))) | D20: =IF(A20="","",INDEX(Despiece!$E$6:$E$705,MATCH($B$4&"|"&13,Despiece!$H$6:$H$705,0))) | F20: =IF(A20="","",IF(E20<>"",E20,IFERROR(IF($C20="Tela principal",INDEX(Recetas!$K$6:$K$115,MATCH($B$4,Recetas!$A$6:$A$115,0))&"",IF($C20="Tela 2",INDEX(Recetas!$L$6:$L$115,MATCH($B$4,Recetas!$A$6:$A$115,0))&"",IF(INDEX(Recetas!$M$6:$M$115,MATCH($B$4,Recetas!$A$6:$A$115,0))&""="",INDEX(Recetas!$K$6:$K$115,MATCH($B$4,Recetas!$A$6:$A$115,0))&"",INDEX(Recetas!$M$6:$M$115,MATCH($B$4,Recetas!$A$6:$A$115,0))&""))),""))) | G20: =IF(A20="","",IF(N(INDEX(Despiece!$F$6:$F$705,MATCH($B$4&"|"&13,Despiece!$H$6:$H$705,0)))>0,INDEX(Despiece!$F$6:$F$705,MATCH($B$4&"|"&13,Despiece!$H$6:$H$705,0))*IFERROR(IF($C20="Tela principal",INDEX(Recetas!$Q$6:$Q$115,MATCH($B$4,Recetas!$A$6:$A$115,0)),IF($C20="Tela 2",INDEX(Recetas!$T$6:$T$115,MATCH($B$4,Recetas!$A$6:$A$115,0)),INDEX(Recetas!$W$6:$W$115,MATCH($B$4,Recetas!$A$6:$A$115,0))))/IF($C20="Tela principal",INDEX(Recetas!$O$6:$O$115,MATCH($B$4,Recetas!$A$6:$A$115,0)),IF($C20="Tela 2",INDEX(Recetas!$R$6:$R$115,MATCH($B$4,Recetas!$A$6:$A$115,0)),INDEX(Recetas!$U$6:$U$115,MATCH($B$4,Recetas!$A$6:$A$115,0)))),1+Parametros!$B$22),"")) | H20: =IF(OR(A20="",F20=""),"",IFERROR(IF(N(INDEX(Telas!$I$6:$I$105,MATCH(F20,Telas!$A$6:$A$105,0)))>0,INDEX(Telas!$I$6:$I$105,MATCH(F20,Telas!$A$6:$A$105,0)),""),"")) | I20: =IF(AND(ISNUMBER(G20),ISNUMBER(H20)),G20*H20,"") | J20: =IF(A20="","",IF(ISNUMBER(I20),"",IF(NOT(ISNUMBER(G20)),"Faltan los metros de esta pieza (hoja Despiece). ","")&IF(F20="","Elige la tela. ",IF(NOT(ISNUMBER(H20)),"Falta precio o peso de 1 m de "&F20&" (hoja Telas). ",""))))
A21: =IFERROR(INDEX(Despiece!$B$6:$B$705,MATCH($B$4&"|"&14,Despiece!$H$6:$H$705,0)),"") | B21: =IF(A21="","",INDEX(Despiece!$C$6:$C$705,MATCH($B$4&"|"&14,Despiece!$H$6:$H$705,0))) | C21: =IF(A21="","",INDEX(Despiece!$D$6:$D$705,MATCH($B$4&"|"&14,Despiece!$H$6:$H$705,0))) | D21: =IF(A21="","",INDEX(Despiece!$E$6:$E$705,MATCH($B$4&"|"&14,Despiece!$H$6:$H$705,0))) | F21: =IF(A21="","",IF(E21<>"",E21,IFERROR(IF($C21="Tela principal",INDEX(Recetas!$K$6:$K$115,MATCH($B$4,Recetas!$A$6:$A$115,0))&"",IF($C21="Tela 2",INDEX(Recetas!$L$6:$L$115,MATCH($B$4,Recetas!$A$6:$A$115,0))&"",IF(INDEX(Recetas!$M$6:$M$115,MATCH($B$4,Recetas!$A$6:$A$115,0))&""="",INDEX(Recetas!$K$6:$K$115,MATCH($B$4,Recetas!$A$6:$A$115,0))&"",INDEX(Recetas!$M$6:$M$115,MATCH($B$4,Recetas!$A$6:$A$115,0))&""))),""))) | G21: =IF(A21="","",IF(N(INDEX(Despiece!$F$6:$F$705,MATCH($B$4&"|"&14,Despiece!$H$6:$H$705,0)))>0,INDEX(Despiece!$F$6:$F$705,MATCH($B$4&"|"&14,Despiece!$H$6:$H$705,0))*IFERROR(IF($C21="Tela principal",INDEX(Recetas!$Q$6:$Q$115,MATCH($B$4,Recetas!$A$6:$A$115,0)),IF($C21="Tela 2",INDEX(Recetas!$T$6:$T$115,MATCH($B$4,Recetas!$A$6:$A$115,0)),INDEX(Recetas!$W$6:$W$115,MATCH($B$4,Recetas!$A$6:$A$115,0))))/IF($C21="Tela principal",INDEX(Recetas!$O$6:$O$115,MATCH($B$4,Recetas!$A$6:$A$115,0)),IF($C21="Tela 2",INDEX(Recetas!$R$6:$R$115,MATCH($B$4,Recetas!$A$6:$A$115,0)),INDEX(Recetas!$U$6:$U$115,MATCH($B$4,Recetas!$A$6:$A$115,0)))),1+Parametros!$B$22),"")) | H21: =IF(OR(A21="",F21=""),"",IFERROR(IF(N(INDEX(Telas!$I$6:$I$105,MATCH(F21,Telas!$A$6:$A$105,0)))>0,INDEX(Telas!$I$6:$I$105,MATCH(F21,Telas!$A$6:$A$105,0)),""),"")) | I21: =IF(AND(ISNUMBER(G21),ISNUMBER(H21)),G21*H21,"") | J21: =IF(A21="","",IF(ISNUMBER(I21),"",IF(NOT(ISNUMBER(G21)),"Faltan los metros de esta pieza (hoja Despiece). ","")&IF(F21="","Elige la tela. ",IF(NOT(ISNUMBER(H21)),"Falta precio o peso de 1 m de "&F21&" (hoja Telas). ",""))))
A22: =IFERROR(INDEX(Despiece!$B$6:$B$705,MATCH($B$4&"|"&15,Despiece!$H$6:$H$705,0)),"") | B22: =IF(A22="","",INDEX(Despiece!$C$6:$C$705,MATCH($B$4&"|"&15,Despiece!$H$6:$H$705,0))) | C22: =IF(A22="","",INDEX(Despiece!$D$6:$D$705,MATCH($B$4&"|"&15,Despiece!$H$6:$H$705,0))) | D22: =IF(A22="","",INDEX(Despiece!$E$6:$E$705,MATCH($B$4&"|"&15,Despiece!$H$6:$H$705,0))) | F22: =IF(A22="","",IF(E22<>"",E22,IFERROR(IF($C22="Tela principal",INDEX(Recetas!$K$6:$K$115,MATCH($B$4,Recetas!$A$6:$A$115,0))&"",IF($C22="Tela 2",INDEX(Recetas!$L$6:$L$115,MATCH($B$4,Recetas!$A$6:$A$115,0))&"",IF(INDEX(Recetas!$M$6:$M$115,MATCH($B$4,Recetas!$A$6:$A$115,0))&""="",INDEX(Recetas!$K$6:$K$115,MATCH($B$4,Recetas!$A$6:$A$115,0))&"",INDEX(Recetas!$M$6:$M$115,MATCH($B$4,Recetas!$A$6:$A$115,0))&""))),""))) | G22: =IF(A22="","",IF(N(INDEX(Despiece!$F$6:$F$705,MATCH($B$4&"|"&15,Despiece!$H$6:$H$705,0)))>0,INDEX(Despiece!$F$6:$F$705,MATCH($B$4&"|"&15,Despiece!$H$6:$H$705,0))*IFERROR(IF($C22="Tela principal",INDEX(Recetas!$Q$6:$Q$115,MATCH($B$4,Recetas!$A$6:$A$115,0)),IF($C22="Tela 2",INDEX(Recetas!$T$6:$T$115,MATCH($B$4,Recetas!$A$6:$A$115,0)),INDEX(Recetas!$W$6:$W$115,MATCH($B$4,Recetas!$A$6:$A$115,0))))/IF($C22="Tela principal",INDEX(Recetas!$O$6:$O$115,MATCH($B$4,Recetas!$A$6:$A$115,0)),IF($C22="Tela 2",INDEX(Recetas!$R$6:$R$115,MATCH($B$4,Recetas!$A$6:$A$115,0)),INDEX(Recetas!$U$6:$U$115,MATCH($B$4,Recetas!$A$6:$A$115,0)))),1+Parametros!$B$22),"")) | H22: =IF(OR(A22="",F22=""),"",IFERROR(IF(N(INDEX(Telas!$I$6:$I$105,MATCH(F22,Telas!$A$6:$A$105,0)))>0,INDEX(Telas!$I$6:$I$105,MATCH(F22,Telas!$A$6:$A$105,0)),""),"")) | I22: =IF(AND(ISNUMBER(G22),ISNUMBER(H22)),G22*H22,"") | J22: =IF(A22="","",IF(ISNUMBER(I22),"",IF(NOT(ISNUMBER(G22)),"Faltan los metros de esta pieza (hoja Despiece). ","")&IF(F22="","Elige la tela. ",IF(NOT(ISNUMBER(H22)),"Falta precio o peso de 1 m de "&F22&" (hoja Telas). ",""))))
A24: RESUMEN — COSTO DE PRODUCCIÓN DE UNA PRENDA (neto, sin IVA)
A25: Tela (suma de las piezas) | I25: =IF(COUNTA(A8:A22)-COUNTBLANK(A8:A22)=0,"",IF(SUMPRODUCT((A8:A22<>"")*NOT(ISNUMBER(I8:I22)))>0,"Faltan datos ↑",SUM(I8:I22))) -> Faltan datos ↑
A26: Papel y tinta de sublimación | I26: =IFERROR(INDEX(Recetas!$AA$6:$AA$115,MATCH($B$4,Recetas!$A$6:$A$115,0))*1,"Faltan metros impresos") -> 0 | J26: =IFERROR(TEXT(INDEX(Recetas!$Y$6:$Y$115,MATCH($B$4,Recetas!$A$6:$A$115,0)),"0.00")&" m impresos × "&TEXT(Parametros!$B$19,"$#,##0")&" por metro"&IF(N(Parametros!$B$19)=0," ← OJO: costo de impresión en $0 (Parametros)",""),"") -> 1.90 m impresos × $0 por metro ← OJO: costo de impresión en $0 (Parametros)
A27: Confección (taller, a trato) | I27: =IFERROR(INDEX(Recetas!$AB$6:$AB$115,MATCH($B$4,Recetas!$A$6:$A$115,0))*1,"Falta tipo/precio de confección") -> 2000 | J27: =IFERROR(INDEX(Recetas!$F$6:$F$115,MATCH($B$4,Recetas!$A$6:$A$115,0))&"","") -> Camiseta De Futbol
A28: Avíos | I28: =IFERROR(INDEX(Recetas!$AC$6:$AC$115,MATCH($B$4,Recetas!$A$6:$A$115,0))*1,0) -> 0 | J28: =IFERROR(IF(INDEX(Recetas!$G$6:$G$115,MATCH($B$4,Recetas!$A$6:$A$115,0))&""="","Sin avíos",INDEX(Recetas!$G$6:$G$115,MATCH($B$4,Recetas!$A$6:$A$115,0))&" × "&INDEX(Recetas!$H$6:$H$115,MATCH($B$4,Recetas!$A$6:$A$115,0))&IF(INDEX(Recetas!$I$6:$I$115,MATCH($B$4,Recetas!$A$6:$A$115,0))&""="",""," + "&INDEX(Recetas!$I$6:$I$115,MATCH($B$4,Recetas!$A$6:$A$115,0))&" × "&INDEX(Recetas!$J$6:$J$115,MATCH($B$4,Recetas!$A$6:$A$115,0)))),"") -> Sin avíos
A29: Extras (escribe: bordado, DTF, escudo…) | J29: Por prenda
A30: COSTO DE PRODUCCIÓN | I30: =IFERROR(I25+I26+I27+I28+N(I29),"Completa los datos ↑") -> Completa los datos ↑
A32: PRECIO Y GANANCIA
A33: ="Precio mínimo de venta (neto): costo × "&TEXT(Parametros!$B$12,"0.00")&" (gastos generales "&TEXT(Parametros!$B$8,"0.0%")&" + ganancia "&TEXT(Parametros!$B$11,"0%")&")" -> Precio mínimo de venta (neto): costo × 2.40 (gastos generales 43.4% + ganancia 15%) | I33: =IF(ISNUMBER(I30),I30*Parametros!$B$12,"")
A34: Precio de venta actual, neto (escribe)
A35: Gastos generales que paga esta prenda | I35: =IF(N(I34)>0,I34*Parametros!$B$8,"")
A36: GANANCIA POR PRENDA | I36: =IF(AND(ISNUMBER(I30),N(I34)>0),I34-I30-I35,"") | J36: =IF(ISNUMBER(I36),TEXT(I36/I34,"0.0%")&" del precio"&IF(I36<0," ← PIERDE PLATA",IF(I36/I34<Parametros!$B$11," ← bajo la meta","")),"")
A38: Corte, ploteo, sublimado y estampado (mano de obra con sueldo) NO van aquí: están en los gastos generales que cobra el sistema de ventas. Si se sumaran, se cobrarían dos veces.

Sheet Como_usar
A1: RECETAS DE COSTO — PLAYMAKER v8
B3: QUÉ ES
B4: El COSTO DE PRODUCCIÓN de cada prenda: tela + papel y tinta + confección + avíos, todo neto (sin IVA). No lleva gastos generales: esos los aplica el sistema de ventas como % del precio.
B5: IDEA CLAVE
B6: Un molde gasta los MISMOS METROS con cualquier tela, y el taller cobra lo MISMO con cualquier tela. Lo único que cambia al cambiar de tela es el $ por metro. Por eso el consumo se guarda por molde, en metros, y la tela se elige aparte.
B7: EMPIEZA AQUÍ
B8: Hoja "Ficha_costo": eliges el molde, ves sus piezas, eliges la tela de cada pieza y al lado sale el costo de esa pieza. Abajo, el costo de producción completo y el precio mínimo.
B9: 1. Telas
B10: Una fila por tela: precio por kg (neto, o el de la factura con IVA) y el PESO DE 1 METRO (cortar 1 m de ancho completo y pesarlo). Sin el peso por metro no se puede pasar de kg a metros.
B11: 2. Despiece
B12: Las piezas de cada molde y en qué grupo de tela va cada una (Tela principal / Tela 2 / Tela 3). Para poner las mangas en otra tela, cambia su grupo a "Tela 2". Metros por prenda: de la marcada (tizado) del plotter.
B13: 3. Mediciones
B14: El consumo REAL: después de cada corte, anota tela, prendas cortadas y kg usados. Se pasa solo a metros por prenda y la receta usa el promedio. Mientras más cortes anotes, más exacto. Ya incluye la merma real.
... B26: Pesar 1 metro de cada tela · metros por pieza del despiece (tizado) · papel: metros por rollo · tinta: ml por metro · confirmar precios de confección · meta de ganancia.

Sheet Recetas
A1: RECETAS POR MOLDE — costo de producción de UNA prenda (neto, sin gastos generales)
A2: Consumo en metros: sale del promedio de las Mediciones reales; si no hay, del Despiece (+ merma). Las telas de aquí son las de siempre: para probar otras, usa "Comparar telas" o "Productos".
A3: ="Recetas listas: "&COUNTIF(AG6:AG115,"Lista*")&" de "&COUNTA(A6:A115)&" · Precio mínimo = costo × "&TEXT(Parametros!B12,"0.00")&" (gastos generales "&TEXT(Parametros!B8,"0.0%")&" + meta "&TEXT(Parametros!B11,"0%")&")" -> Recetas listas: 1 de 58 · Precio mínimo = costo × 2.40 (gastos generales 43.4% + meta 15%)
A4: MOLDE | F4: LO ESCRIBES TÚ | O4: CONSUMO TELA PRINCIPAL | R4: CONSUMO TELA 2 | U4: CONSUMO TELA 3 | X4: IMPRESIÓN | Z4: COSTO DE PRODUCCIÓN POR PRENDA ($, neto)
A5: Molde | B5: Descripción | C5: Deporte | D5: Prenda | E5: Calce | F5: Confección (tipo) | G5: Avío 1 | H5: Cant. | I5: Avío 2 | J5: Cant. | K5: Tela principal (la de siempre) | L5: Tela 2 | M5: Tela 3 | N5: Consumo según (vacío = automático) | O5: Despiece (m) | P5: Real medido (m) | Q5: USADO (m) | R5: Despiece (m) | S5: Real medido (m) | T5: USADO (m) | U5: Despiece (m) | V5: Real medido (m) | W5: USADO (m) | X5: Metros impresos (si lo mides) | Y5: METROS IMPRESOS | Z5: $ Tela | AA5: $ Papel y tinta | AB5: $ Confección | AC5: $ Avíos | AD5: COSTO DE PRODUCCIÓN | AE5: Precio mínimo (referencia) | AF5: Prendas por kg (tela principal) | AG5: Qué falta | AH5: Notas
A6: 01 · FUTMUJU01 | B6: Fútbol, cuello redondo | C6: Fútbol | D6: Camiseta | E6: Femenino | F6: Camiseta De Futbol | O6: =IF($A6="","",IF(COUNTIFS(Despiece!$A$6:$A$705,$A6,Despiece!$D$6:$D$705,"Tela principal",Despiece!$F$6:$F$705,">0")=0,"",SUMIFS(Despiece!$F$6:$F$705,Despiece!$A$6:$A$705,$A6,Despiece!$D$6:$D$705,"Tela principal"))) | P6: =IF($A6="","",IFERROR(AVERAGEIFS(Mediciones!$K$6:$K$305,Mediciones!$C$6:$C$305,$A6,Mediciones!$D$6:$D$305,"Tela principal"),"")) | Q6: =IF($A6="","",IF(N(IF($N6="Despiece",IF(ISNUMBER(O6),O6*(1+Parametros!$B$22),IF(COUNTIFS(Despiece!$A$6:$A$705,$A6,Despiece!$D$6:$D$705,"Tela principal")>0,"",0)),IF($N6="Medición real",IF(ISNUMBER(P6),P6,IF(COUNTIFS(Mediciones!$C$6:$C$305,$A6,Mediciones!$D$6:$D$305,"Tela principal")>0,"",0)),IF(ISNUMBER(P6),P6,IF(ISNUMBER(O6),O6*(1+Parametros!$B$22),IF(OR(COUNTIFS(Despiece!$A$6:$A$705,$A6,Despiece!$D$6:$D$705,"Tela principal")>0,COUNTIFS(Mediciones!$C$6:$C$305,$A6,Mediciones!$D$6:$D$305,"Tela principal")>0),"",0))))))=0,"",IF($N6="Despiece",IF(ISNUMBER(O6),O6*(1+Parametros!$B$22),IF(COUNTIFS(Despiece!$A$6:$A$705,$A6,Despiece!$D$6:$D$705,"Tela principal")>0,"",0)),IF($N6="Medición real",IF(ISNUMBER(P6),P6,IF(COUNTIFS(Mediciones!$C$6:$C$305,$A6,Mediciones!$D$6:$D$305,"Tela principal")>0,"",0)),IF(ISNUMBER(P6),P6,IF(ISNUMBER(O6),O6*(1+Parametros!$B$22),IF(OR(COUNTIFS(Despiece!$A$6:$A$705,$A6,Despiece!$D$6:$D$705,"Tela principal")>0,COUNTIFS(Mediciones!$C$6:$C$305,$A6,Mediciones!$D$6:$D$305,"Tela principal")>0),"",0))))))) | R6: =IF($A6="","",IF(COUNTIFS(Despiece!$A$6:$A$705,$A6,Despiece!$D$6:$D$705,"Tela 2",Despiece!$F$6:$F$705,">0")=0,"",SUMIFS(Despiece!$F$6:$F$705,Despiece!$A$6:$A$705,$A6,Despiece!$D$6:$D$705,"Tela 2"))) | S6: =IF($A6="","",IFERROR(AVERAGEIFS(Mediciones!$K$6:$K$305,Mediciones!$C$6:$C$305,$A6,Mediciones!$D$6:$D$305,"Tela 2"),"")) | T6: =IF($A6="","",IF($N6="Despiece",IF(ISNUMBER(R6),R6*(1+Parametros!$B$22),IF(COUNTIFS(Despiece!$A$6:$A$705,$A6,Despiece!$D$6:$D$705,"Tela 2")>0,"",0)),IF($N6="Medición real",IF(ISNUMBER(S6),S6,IF(COUNTIFS(Mediciones!$C$6:$C$305,$A6,Mediciones!$D$6:$D$305,"Tela 2")>0,"",0)),IF(ISNUMBER(S6),S6,IF(ISNUMBER(R6),R6*(1+Parametros!$B$22),IF(OR(COUNTIFS(Despiece!$A$6:$A$705,$A6,Despiece!$D$6:$D$705,"Tela 2")>0,COUNTIFS(Mediciones!$C$6:$C$305,$A6,Mediciones!$D$6:$D$305,"Tela 2")>0),"",0)))))) -> 0 | U6: =IF($A6="","",IF(COUNTIFS(Despiece!$A$6:$A$705,$A6,Despiece!$D$6:$D$705,"Tela 3",Despiece!$F$6:$F$705,">0")=0,"",SUMIFS(Despiece!$F$6:$F$705,Despiece!$A$6:$A$705,$A6,Despiece!$D$6:$D$705,"Tela 3"))) | V6: =IF($A6="","",IFERROR(AVERAGEIFS(Mediciones!$K$6:$K$305,Mediciones!$C$6:$C$305,$A6,Mediciones!$D$6:$D$305,"Tela 3"),"")) | W6: =IF($A6="","",IF($N6="Despiece",IF(ISNUMBER(U6),U6*(1+Parametros!$B$22),IF(COUNTIFS(Despiece!$A$6:$A$705,$A6,Despiece!$D$6:$D$705,"Tela 3")>0,"",0)),IF($N6="Medición real",IF(ISNUMBER(V6),V6,IF(COUNTIFS(Mediciones!$C$6:$C$305,$A6,Mediciones!$D$6:$D$305,"Tela 3")>0,"",0)),IF(ISNUMBER(V6),V6,IF(ISNUMBER(U6),U6*(1+Parametros!$B$22),IF(OR(COUNTIFS(Despiece!$A$6:$A$705,$A6,Despiece!$D$6:$D$705,"Tela 3")>0,COUNTIFS(Mediciones!$C$6:$C$305,$A6,Mediciones!$D$6:$D$305,"Tela 3")>0),"",0)))))) -> 0 | Y6: =IF($A6="","",IF(ISNUMBER(X6),X6,IF(COUNTIFS(Despiece!$A$6:$A$705,$A6,Despiece!$E$6:$E$705,"Sublimada",Despiece!$F$6:$F$705,">0")>0,SUMIFS(Despiece!$F$6:$F$705,Despiece!$A$6:$A$705,$A6,Despiece!$E$6:$E$705,"Sublimada")*(1+Parametros!$B$22),IF(COUNTIFS(Despiece!$A$6:$A$705,$A6,Despiece!$E$6:$E$705,"Sublimada")=0,0,"")))) | Z6: =IF($A6="","",IFERROR(IF(ISNUMBER(Q6),IF(Q6=0,0,Q6*INDEX(Telas!$I$6:$I$105,MATCH(K6,Telas!$A$6:$A$105,0))),NA())+IF(ISNUMBER(T6),IF(T6=0,0,T6*INDEX(Telas!$I$6:$I$105,MATCH(L6,Telas!$A$6:$A$105,0))),NA())+IF(ISNUMBER(W6),IF(W6=0,0,W6*INDEX(Telas!$I$6:$I$105,MATCH(IF(M6="",K6,M6),Telas!$A$6:$A$105,0))),NA()),"")) | AA6: =IF($A6="","",IF(ISNUMBER(Y6),Y6*Parametros!$B$19,"")) | AB6: =IF(OR($A6="",F6=""),"",IFERROR(INDEX(Confeccion!$B$6:$B$125,MATCH(F6,Confeccion!$A$6:$A$125,0)),"")) -> 2000 | AC6: =IF($A6="","",IFERROR(N(H6)*IF(G6="",0,INDEX(Avios!$C$6:$C$65,MATCH(G6,Avios!$A$6:$A$65,0)))+N(J6)*IF(I6="",0,INDEX(Avios!$C$6:$C$65,MATCH(I6,Avios!$A$6:$A$65,0))),"")) -> 0 | AD6: =IF($A6="","",IFERROR(Z6+AA6+AB6+AC6,"")) | AE6: =IF(ISNUMBER(AD6),AD6*Parametros!$B$12,"") | AF6: =IF(AND(ISNUMBER(Q6),K6<>""),IFERROR(1/(Q6*INDEX(Telas!$G$6:$G$105,MATCH(K6,Telas!$A$6:$A$105,0))),""),"") | AG6: =IF($A6="","",IF(ISNUMBER(AD6),IF(AND(N(Y6)>0,N(Parametros!$B$19)=0),"Lista, pero sin costo de impresión (Parametros)","Lista"),IF(Q6="","Consumo tela principal (Despiece o Mediciones). ","")&IF(COUNTIFS(Mediciones!$C$6:$C$305,$A6,Mediciones!$K$6:$K$305,"")>0,"Pesar 1 m de la tela medida (Telas, kg por metro). ","")&IF(T6="","Consumo Tela 2. ","")&IF(W6="","Consumo Tela 3. ","")&IF(K6="","Elegir tela principal. ",IF(ISERROR(INDEX(Telas!$I$6:$I$105,MATCH(K6,Telas!$A$6:$A$105,0))*1),"Precio o peso por metro de "&K6&". ",""))&IF(AND(N(T6)>0,L6=""),"Elegir Tela 2. ",IF(AND(N(T6)>0,ISERROR(INDEX(Telas!$I$6:$I$105,MATCH(L6,Telas!$A$6:$A$105,0))*1)),"Precio o peso por metro de "&L6&". ",""))&IF(Y6="","Metros impresos. ","")&IF(F6="","Tipo de confección. ",IF(AB6="","Precio de confección. ","")))) -> Consumo tela principal (Despiece o Mediciones). Elegir tela principal. Metros impresos. | AH6: Confección sugerida por el tipo de molde: confirmar. Falta ficha de corte.
A7: 02 · FUTHOMU01 | B7: Fútbol, cuello redondo | C7: Fútbol | D7: Camiseta | E7: Masculino | F7: Camiseta De Futbol | O7: =IF($A7="","",IF(COUNTIFS(Despiece!$A$6:$A$705,$A7,Despiece!$D$6:$D$705,"Tela principal",Despiece!$F$6:$F$705,">0")=0,"",SUMIFS(Despiece!$F$6:$F$705,Despiece!$A$6:$A$705,$A7,Despiece!$D$6:$D$705,"Tela principal"))) | P7: =IF($A7="","",IFERROR(AVERAGEIFS(Mediciones!$K$6:$K$305,Mediciones!$C$6:$C$305,$A7,Mediciones!$D$6:$D$305,"Tela principal"),"")) | Q7: =IF($A7="","",IF(N(IF($N7="Despiece",IF(ISNUMBER(O7),O7*(1+Parametros!$B$22),IF(COUNTIFS(Despiece!$A$6:$A$705,$A7,Despiece!$D$6:$D$705,"Tela principal")>0,"",0)),IF($N7="Medición real",IF(ISNUMBER(P7),P7,IF(COUNTIFS(Mediciones!$C$6:$C$305,$A7,Mediciones!$D$6:$D$305,"Tela principal")>0,"",0)),IF(ISNUMBER(P7),P7,IF(ISNUMBER(O7),O7*(1+Parametros!$B$22),IF(OR(COUNTIFS(Despiece!$A$6:$A$705,$A7,Despiece!$D$6:$D$705,"Tela principal")>0,COUNTIFS(Mediciones!$C$6:$C$305,$A7,Mediciones!$D$6:$D$305,"Tela principal")>0),"",0))))))=0,"",IF($N7="Despiece",IF(ISNUMBER(O7),O7*(1+Parametros!$B$22),IF(COUNTIFS(Despiece!$A$6:$A$705,$A7,Despiece!$D$6:$D$705,"Tela principal")>0,"",0)),IF($N7="Medición real",IF(ISNUMBER(P7),P7,IF(COUNTIFS(Mediciones!$C$6:$C$305,$A7,Mediciones!$D$6:$D$305,"Tela principal")>0,"",0)),IF(ISNUMBER(P7),P7,IF(ISNUMBER(O7),O7*(1+Parametros!$B$22),IF(OR(COUNTIFS(Despiece!$A$6:$A$705,$A7,Despiece!$D$6:$D$705,"Tela principal")>0,COUNTIFS(Mediciones!$C$6:$C$305,$A7,Mediciones!$D$6:$D$305,"Tela principal")>0),"",0))))))) | R7: =IF($A7="","",IF(COUNTIFS(Despiece!$A$6:$A$705,$A7,Despiece!$D$6:$D$705,"Tela 2",Despiece!$F$6:$F$705,">0")=0,"",SUMIFS(Despiece!$F$6:$F$705,Despiece!$A$6:$A$705,$A7,Despiece!$D$6:$D$705,"Tela 2"))) | S7: =IF($A7="","",IFERROR(AVERAGEIFS(Mediciones!$K$6:$K$305,Mediciones!$C$6:$C$305,$A7,Mediciones!$D$6:$D$305,"Tela 2"),"")) | T7: =IF($A7="","",IF($N7="Despiece",IF(ISNUMBER(R7),R7*(1+Parametros!$B$22),IF(COUNTIFS(Despiece!$A$6:$A$705,$A7,Despiece!$D$6:$D$705,"Tela 2")>0,"",0)),IF($N7="Medición real",IF(ISNUMBER(S7),S7,IF(COUNTIFS(Mediciones!$C$6:$C$305,$A7,Mediciones!$D$6:$D$305,"Tela 2")>0,"",0)),IF(ISNUMBER(S7),S7,IF(ISNUMBER(R7),R7*(1+Parametros!$B$22),IF(OR(COUNTIFS(Despiece!$A$6:$A$705,$A7,Despiece!$D$6:$D$705,"Tela 2")>0,COUNTIFS(Mediciones!$C$6:$C$305,$A7,Mediciones!$D$6:$D$305,"Tela 2")>0),"",0)))))) -> 0 | U7: =IF($A7="","",IF(COUNTIFS(Despiece!$A$6:$A$705,$A7,Despiece!$D$6:$D$705,"Tela 3",Despiece!$F$6:$F$705,">0")=0,"",SUMIFS(Despiece!$F$6:$F$705,Despiece!$A$6:$A$705,$A7,Despiece!$D$6:$D$705,"Tela 3"))) | V7: =IF($A7="","",IFERROR(AVERAGEIFS(Mediciones!$K$6:$K$305,Mediciones!$C$6:$C$305,$A7,Mediciones!$D$6:$D$305,"Tela 3"),"")) | W7: =IF($A7="","",IF($N7="Despiece",IF(ISNUMBER(U7),U7*(1+Parametros!$B$22),IF(COUNTIFS(Despiece!$A$6:$A$705,$A7,Despiece!$D$6:$D$705,"Tela 3")>0,"",0)),IF($N7="Medición real",IF(ISNUMBER(V7),V7,IF(COUNTIFS(Mediciones!$C$6:$C$305,$A7,Mediciones!$D$6:$D$305,"Tela 3")>0,"",0)),IF(ISNUMBER(V7),V7,IF(ISNUMBER(U7),U7*(1+Parametros!$B$22),IF(OR(COUNTIFS(Despiece!$A$6:$A$705,$A7,Despiece!$D$6:$D$705,"Tela 3")>0,COUNTIFS(Mediciones!$C$6:$C$305,$A7,Mediciones!$D$6:$D$305,"Tela 3")>0),"",0)))))) -> 0 | Y7: =IF($A7="","",IF(ISNUMBER(X7),X7,IF(COUNTIFS(Despiece!$A$6:$A$705,$A7,Despiece!$E$6:$E$705,"Sublimada",Despiece!$F$6:$F$705,">0")>0,SUMIFS(Despiece!$F$6:$F$705,Despiece!$A$6:$A$705,$A7,Despiece!$E$6:$E$705,"Sublimada")*(1+Parametros!$B$22),IF(COUNTIFS(Despiece!$A$6:$A$705,$A7,Despiece!$E$6:$E$705,"Sublimada")=0,0,"")))) | Z7: =IF($A7="","",IFERROR(IF(ISNUMBER(Q7),IF(Q7=0,0,Q7*INDEX(Telas!$I$6:$I$105,MATCH(K7,Telas!$A$6:$A$105,0))),NA())+IF(ISNUMBER(T7),IF(T7=0,0,T7*INDEX(Telas!$I$6:$I$105,MATCH(L7,Telas!$A$6:$A$105,0))),NA())+IF(ISNUMBER(W7),IF(W7=0,0,W7*INDEX(Telas!$I$6:$I$105,MATCH(IF(M7="",K7,M7),Telas!$A$6:$A$105,0))),NA()),"")) | AA7: =IF($A7="","",IF(ISNUMBER(Y7),Y7*Parametros!$B$19,"")) | AB7: =IF(OR($A7="",F7=""),"",IFERROR(INDEX(Confeccion!$B$6:$B$125,MATCH(F7,Confeccion!$A$6:$A$125,0)),"")) -> 2000 | AC7: =IF($A7="","",IFERROR(N(H7)*IF(G7="",0,INDEX(Avios!$C$6:$C$65,MATCH(G7,Avios!$A$6:$A$65,0)))+N(J7)*IF(I7="",0,INDEX(Avios!$C$6:$C$65,MATCH(I7,Avios!$A$6:$A$65,0))),"")) -> 0 | AD7: =IF($A7="","",IFERROR(Z7+AA7+AB7+AC7,"")) | AE7: =IF(ISNUMBER(AD7),AD7*Parametros!$B$12,"") | AF7: =IF(AND(ISNUMBER(Q7),K7<>""),IFERROR(1/(Q7*INDEX(Telas!$G$6:$G$105,MATCH(K7,Telas!$A$6:$A$105,0))),""),"") | AG7: =IF($A7="","",IF(ISNUMBER(AD7),IF(AND(N(Y7)>0,N(Parametros!$B$19)=0),"Lista, pero sin costo de impresión (Parametros)","Lista"),IF(Q7="","Consumo tela principal (Despiece o Mediciones). ","")&IF(COUNTIFS(Mediciones!$C$6:$C$305,$A7,Mediciones!$K$6:$K$305,"")>0,"Pesar 1 m de la tela medida (Telas, kg por metro). ","")&IF(T7="","Consumo Tela 2. ","")&IF(W7="","Consumo Tela 3. ","")&IF(K7="","Elegir tela principal. ",IF(ISERROR(INDEX(Telas!$I$6:$I$105,MATCH(K7,Telas!$A$6:$A$105,0))*1),"Precio o peso por metro de "&K7&". ",""))&IF(AND(N(T7)>0,L7=""),"Elegir Tela 2. ",IF(AND(N(T7)>0,ISERROR(INDEX(Telas!$I$6:$I$105,MATCH(L7,Telas!$A$6:$A$105,0))*1)),"Precio o peso por metro de "&L7&". ",""))&IF(Y7="","Metros impresos. ","")&IF(F7="","Tipo de confección. ",IF(AB7="","Precio de confección. ","")))) -> Consumo tela principal (Despiece o Mediciones). Elegir tela principal. Metros impresos. | AH7: Confección sugerida por el tipo de molde: confirmar. Falta ficha de corte.
A8: 03 · FUTINMUJU01 | B8: Fútbol infantil, cuello redondo | C8: Fútbol | D8: Camiseta | E8: Infantil Femenino | F8: Camiseta De Futbol | O8: =IF($A8="","",IF(COUNTIFS(Despiece!$A$6:$A$705,$A8,Despiece!$D$6:$D$705,"Tela principal",Despiece!$F$6:$F$705,">0")=0,"",SUMIFS(Despiece!$F$6:$F$705,Despiece!$A$6:$A$705,$A8,Despiece!$D$6:$D$705,"Tela principal"))) | P8: =IF($A8="","",IFERROR(AVERAGEIFS(Mediciones!$K$6:$K$305,Mediciones!$C$6:$C$305,$A8,Mediciones!$D$6:$D$305,"Tela principal"),"")) | Q8: =IF($A8="","",IF(N(IF($N8="Despiece",IF(ISNUMBER(O8),O8*(1+Parametros!$B$22),IF(COUNTIFS(Despiece!$A$6:$A$705,$A8,Despiece!$D$6:$D$705,"Tela principal")>0,"",0)),IF($N8="Medición real",IF(ISNUMBER(P8),P8,IF(COUNTIFS(Mediciones!$C$6:$C$305,$A8,Mediciones!$D$6:$D$305,"Tela principal")>0,"",0)),IF(ISNUMBER(P8),P8,IF(ISNUMBER(O8),O8*(1+Parametros!$B$22),IF(OR(COUNTIFS(Despiece!$A$6:$A$705,$A8,Despiece!$D$6:$D$705,"Tela principal")>0,COUNTIFS(Mediciones!$C$6:$C$305,$A8,Mediciones!$D$6:$D$305,"Tela principal")>0),"",0))))))=0,"",IF($N8="Despiece",IF(ISNUMBER(O8),O8*(1+Parametros!$B$22),IF(COUNTIFS(Despiece!$A$6:$A$705,$A8,Despiece!$D$6:$D$705,"Tela principal")>0,"",0)),IF($N8="Medición real",IF(ISNUMBER(P8),P8,IF(COUNTIFS(Mediciones!$C$6:$C$305,$A8,Mediciones!$D$6:$D$305,"Tela principal")>0,"",0)),IF(ISNUMBER(P8),P8,IF(ISNUMBER(O8),O8*(1+Parametros!$B$22),IF(OR(COUNTIFS(Despiece!$A$6:$A$705,$A8,Despiece!$D$6:$D$705,"Tela principal")>0,COUNTIFS(Mediciones!$C$6:$C$305,$A8,Mediciones!$D$6:$D$305,"Tela principal")>0),"",0))))))) | R8: =IF($A8="","",IF(COUNTIFS(Despiece!$A$6:$A$705,$A8,Despiece!$D$6:$D$705,"Tela 2",Despiece!$F$6:$F$705,">0")=0,"",SUMIFS(Despiece!$F$6:$F$705,Despiece!$A$6:$A$705,$A8,Despiece!$D$6:$D$705,"Tela 2"))) | S8: =IF($A8="","",IFERROR(AVERAGEIFS(Mediciones!$K$6:$K$305,Mediciones!$C$6:$C$305,$A8,Mediciones!$D$6:$D$305,"Tela 2"),"")) | T8: =IF($A8="","",IF($N8="Despiece",IF(ISNUMBER(R8),R8*(1+Parametros!$B$22),IF(COUNTIFS(Despiece!$A$6:$A$705,$A8,Despiece!$D$6:$D$705,"Tela 2")>0,"",0)),IF($N8="Medición real",IF(ISNUMBER(S8),S8,IF(COUNTIFS(Mediciones!$C$6:$C$305,$A8,Mediciones!$D$6:$D$305,"Tela 2")>0,"",0)),IF(ISNUMBER(S8),S8,IF(ISNUMBER(R8),R8*(1+Parametros!$B$22),IF(OR(COUNTIFS(Despiece!$A$6:$A$705,$A8,Despiece!$D$6:$D$705,"Tela 2")>0,COUNTIFS(Mediciones!$C$6:$C$305,$A8,Mediciones!$D$6:$D$305,"Tela 2")>0),"",0)))))) -> 0 | U8: =IF($A8="","",IF(COUNTIFS(Despiece!$A$6:$A$705,$A8,Despiece!$D$6:$D$705,"Tela 3",Despiece!$F$6:$F$705,">0")=0,"",SUMIFS(Despiece!$F$6:$F$705,Despiece!$A$6:$A$705,$A8,Despiece!$D$6:$D$705,"Tela 3"))) | V8: =IF($A8="","",IFERROR(AVERAGEIFS(Mediciones!$K$6:$K$305,Mediciones!$C$6:$C$305,$A8,Mediciones!$D$6:$D$305,"Tela 3"),"")) | W8: =IF($A8="","",IF($N8="Despiece",IF(ISNUMBER(U8),U8*(1+Parametros!$B$22),IF(COUNTIFS(Despiece!$A$6:$A$705,$A8,Despiece!$D$6:$D$705,"Tela 3")>0,"",0)),IF($N8="Medición real",IF(ISNUMBER(V8),V8,IF(COUNTIFS(Mediciones!$C$6:$C$305,$A8,Mediciones!$D$6:$D$305,"Tela 3")>0,"",0)),IF(ISNUMBER(V8),V8,IF(ISNUMBER(U8),U8*(1+Parametros!$B$22),IF(OR(COUNTIFS(Despiece!$A$6:$A$705,$A8,Despiece!$D$6:$D$705,"Tela 3")>0,COUNTIFS(Mediciones!$C$6:$C$305,$A8,Mediciones!$D$6:$D$305,"Tela 3")>0),"",0)))))) -> 0 | Y8: =IF($A8="","",IF(ISNUMBER(X8),X8,IF(COUNTIFS(Despiece!$A$6:$A$705,$A8,Despiece!$E$6:$E$705,"Sublimada",Despiece!$F$6:$F$705,">0")>0,SUMIFS(Despiece!$F$6:$F$705,Despiece!$A$6:$A$705,$A8,Despiece!$E$6:$E$705,"Sublimada")*(1+Parametros!$B$22),IF(COUNTIFS(Despiece!$A$6:$A$705,$A8,Despiece!$E$6:$E$705,"Sublimada")=0,0,"")))) | Z8: =IF($A8="","",IFERROR(IF(ISNUMBER(Q8),IF(Q8=0,0,Q8*INDEX(Telas!$I$6:$I$105,MATCH(K8,Telas!$A$6:$A$105,0))),NA())+IF(ISNUMBER(T8),IF(T8=0,0,T8*INDEX(Telas!$I$6:$I$105,MATCH(L8,Telas!$A$6:$A$105,0))),NA())+IF(ISNUMBER(W8),IF(W8=0,0,W8*INDEX(Telas!$I$6:$I$105,MATCH(IF(M8="",K8,M8),Telas!$A$6:$A$105,0))),NA()),"")) | AA8: =IF($A8="","",IF(ISNUMBER(Y8),Y8*Parametros!$B$19,"")) | AB8: =IF(OR($A8="",F8=""),"",IFERROR(INDEX(Confeccion!$B$6:$B$125,MATCH(F8,Confeccion!$A$6:$A$125,0)),"")) -> 2000 | AC8: =IF($A8="","",IFERROR(N(H8)*IF(G8="",0,INDEX(Avios!$C$6:$C$65,MATCH(G8,Avios!$A$6:$A$65,0)))+N(J8)*IF(I8="",0,INDEX(Avios!$C$6:$C$65,MATCH(I8,Avios!$A$6:$A$65,0))),"")) -> 0 | AD8: =IF($A8="","",IFERROR(Z8+AA8+AB8+AC8,"")) | AE8: =IF(ISNUMBER(AD8),AD8*Parametros!$B$12,"") | AF8: =IF(AND(ISNUMBER(Q8),K8<>""),IFERROR(1/(Q8*INDEX(Telas!$G$6:$G$105,MATCH(K8,Telas!$A$6:$A$105,0))),""),"") | AG8: =IF($A8="","",IF(ISNUMBER(AD8),IF(AND(N(Y8)>0,N(Parametros!$B$19)=0),"Lista, pero sin costo de impresión (Parametros)","Lista"),IF(Q8="","Consumo tela principal (Despiece o Mediciones). ","")&IF(COUNTIFS(Mediciones!$C$6:$C$305,$A8,Mediciones!$K$6:$K$305,"")>0,"Pesar 1 m de la tela medida (Telas, kg por metro). ","")&IF(T8="","Consumo Tela 2. ","")&IF(W8="","Consumo Tela 3. ","")&IF(K8="","Elegir tela principal. ",IF(ISERROR(INDEX(Telas!$I$6:$I$105,MATCH(K8,Telas!$A$6:$A$105,0))*1),"Precio o peso por metro de "&K8&". ",""))&IF(AND(N(T8)>0,L8=""),"Elegir Tela 2. ",IF(AND(N(T8)>0,ISERROR(INDEX(Telas!$I$6:$I$105,MATCH(L8,Telas!$A$6:$A$105,0))*1)),"Precio o peso por metro de "&L8&". ",""))&IF(Y8="","Metros impresos. ","")&IF(F8="","Tipo de confección. ",IF(AB8="","Precio de confección. ","")))) -> Consumo tela principal (Despiece o Mediciones). Elegir tela principal. Metros impresos. | AH8: Confección sugerida por el tipo de molde: confirmar. Falta ficha de corte.
A9: 04 · FUTINHOMU01 | B9: Fútbol infantil, cuello redondo | C9: Fútbol | D9: Camiseta | E9: Infantil Masculino | F9: Camiseta De Futbol | K9: CIRE BLANCO | L9: MESH | O9: =IF($A9="","",IF(COUNTIFS(Despiece!$A$6:$A$705,$A9,Despiece!$D$6:$D$705,"Tela principal",Despiece!$F$6:$F$705,">0")=0,"",SUMIFS(Despiece!$F$6:$F$705,Despiece!$A$6:$A$705,$A9,Despiece!$D$6:$D$705,"Tela principal"))) | P9: =IF($A9="","",IFERROR(AVERAGEIFS(Mediciones!$K$6:$K$305,Mediciones!$C$6:$C$305,$A9,Mediciones!$D$6:$D$305,"Tela principal"),"")) | Q9: =IF($A9="","",IF(N(IF($N9="Despiece",IF(ISNUMBER(O9),O9*(1+Parametros!$B$22),IF(COUNTIFS(Despiece!$A$6:$A$705,$A9,Despiece!$D$6:$D$705,"Tela principal")>0,"",0)),IF($N9="Medición real",IF(ISNUMBER(P9),P9,IF(COUNTIFS(Mediciones!$C$6:$C$305,$A9,Mediciones!$D$6:$D$305,"Tela principal")>0,"",0)),IF(ISNUMBER(P9),P9,IF(ISNUMBER(O9),O9*(1+Parametros!$B$22),IF(OR(COUNTIFS(Despiece!$A$6:$A$705,$A9,Despiece!$D$6:$D$705,"Tela principal")>0,COUNTIFS(Mediciones!$C$6:$C$305,$A9,Mediciones!$D$6:$D$305,"Tela principal")>0),"",0))))))=0,"",IF($N9="Despiece",IF(ISNUMBER(O9),O9*(1+Parametros!$B$22),IF(COUNTIFS(Despiece!$A$6:$A$705,$A9,Despiece!$D$6:$D$705,"Tela principal")>0,"",0)),IF($N9="Medición real",IF(ISNUMBER(P9),P9,IF(COUNTIFS(Mediciones!$C$6:$C$305,$A9,Mediciones!$D$6:$D$305,"Tela principal")>0,"",0)),IF(ISNUMBER(P9),P9,IF(ISNUMBER(O9),O9*(1+Parametros!$B$22),IF(OR(COUNTIFS(Despiece!$A$6:$A$705,$A9,Despiece!$D$6:$D$705,"Tela principal")>0,COUNTIFS(Mediciones!$C$6:$C$305,$A9,Mediciones!$D$6:$D$305,"Tela principal")>0),"",0))))))) | R9: =IF($A9="","",IF(COUNTIFS(Despiece!$A$6:$A$705,$A9,Despiece!$D$6:$D$705,"Tela 2",Despiece!$F$6:$F$705,">0")=0,"",SUMIFS(Despiece!$F$6:$F$705,Despiece!$A$6:$A$705,$A9,Despiece!$D$6:$D$705,"Tela 2"))) | S9: =IF($A9="","",IFERROR(AVERAGEIFS(Mediciones!$K$6:$K$305,Mediciones!$C$6:$C$305,$A9,Mediciones!$D$6:$D$305,"Tela 2"),"")) | T9: =IF($A9="","",IF($N9="Despiece",IF(ISNUMBER(R9),R9*(1+Parametros!$B$22),IF(COUNTIFS(Despiece!$A$6:$A$705,$A9,Despiece!$D$6:$D$705,"Tela 2")>0,"",0)),IF($N9="Medición real",IF(ISNUMBER(S9),S9,IF(COUNTIFS(Mediciones!$C$6:$C$305,$A9,Mediciones!$D$6:$D$305,"Tela 2")>0,"",0)),IF(ISNUMBER(S9),S9,IF(ISNUMBER(R9),R9*(1+Parametros!$B$22),IF(OR(COUNTIFS(Despiece!$A$6:$A$705,$A9,Despiece!$D$6:$D$705,"Tela 2")>0,COUNTIFS(Mediciones!$C$6:$C$305,$A9,Mediciones!$D$6:$D$305,"Tela 2")>0),"",0)))))) | U9: =IF($A9="","",IF(COUNTIFS(Despiece!$A$6:$A$705,$A9,Despiece!$D$6:$D$705,"Tela 3",Despiece!$F$6:$F$705,">0")=0,"",SUMIFS(Despiece!$F$6:$F$705,Despiece!$A$6:$A$705,$A9,Despiece!$D$6:$D$705,"Tela 3"))) | V9: =IF($A9="","",IFERROR(AVERAGEIFS(Mediciones!$K$6:$K$305,Mediciones!$C$6:$C$305,$A9,Mediciones!$D$6:$D$305,"Tela 3"),"")) | W9: =IF($A9="","",IF($N9="Despiece",IF(ISNUMBER(U9),U9*(1+Parametros!$B$22),IF(COUNTIFS(Despiece!$A$6:$A$705,$A9,Despiece!$D$6:$D$705,"Tela 3")>0,"",0)),IF($N9="Medición real",IF(ISNUMBER(V9),V9,IF(COUNTIFS(Mediciones!$C$6:$C$305,$A9,Mediciones!$D$6:$D$305,"Tela 3")>0,"",0)),IF(ISNUMBER(V9),V9,IF(ISNUMBER(U9),U9*(1+Parametros!$B$22),IF(OR(COUNTIFS(Despiece!$A$6:$A$705,$A9,Despiece!$D$6:$D$705,"Tela 3")>0,COUNTIFS(Mediciones!$C$6:$C$305,$A9,Mediciones!$D$6:$D$305,"Tela 3")>0),"",0)))))) -> 0 | Y9: =IF($A9="","",IF(ISNUMBER(X9),X9,IF(COUNTIFS(Despiece!$A$6:$A$705,$A9,Despiece!$E$6:$E$705,"Sublimada",Despiece!$F$6:$F$705,">0")>0,SUMIFS(Despiece!$F$6:$F$705,Despiece!$A$6:$A$705,$A9,Despiece!$E$6:$E$705,"Sublimada")*(1+Parametros!$B$22),IF(COUNTIFS(Despiece!$A$6:$A$705,$A9,Despiece!$E$6:$E$705,"Sublimada")=0,0,"")))) | Z9: =IF($A9="","",IFERROR(IF(ISNUMBER(Q9),IF(Q9=0,0,Q9*INDEX(Telas!$I$6:$I$105,MATCH(K9,Telas!$A$6:$A$105,0))),NA())+IF(ISNUMBER(T9),IF(T9=0,0,T9*INDEX(Telas!$I$6:$I$105,MATCH(L9,Telas!$A$6:$A$105,0))),NA())+IF(ISNUMBER(W9),IF(W9=0,0,W9*INDEX(Telas!$I$6:$I$105,MATCH(IF(M9="",K9,M9),Telas!$A$6:$A$105,0))),NA()),"")) | AA9: =IF($A9="","",IF(ISNUMBER(Y9),Y9*Parametros!$B$19,"")) | AB9: =IF(OR($A9="",F9=""),"",IFERROR(INDEX(Confeccion!$B$6:$B$125,MATCH(F9,Confeccion!$A$6:$A$125,0)),"")) -> 2000 | AC9: =IF($A9="","",IFERROR(N(H9)*IF(G9="",0,INDEX(Avios!$C$6:$C$65,MATCH(G9,Avios!$A$6:$A$65,0)))+N(J9)*IF(I9="",0,INDEX(Avios!$C$6:$C$65,MATCH(I9,Avios!$A$6:$A$65,0))),"")) -> 0 | AD9: =IF($A9="","",IFERROR(Z9+AA9+AB9+AC9,"")) | AE9: =IF(ISNUMBER(AD9),AD9*Parametros!$B$12,"") | AF9: =IF(AND(ISNUMBER(Q9),K9<>""),IFERROR(1/(Q9*INDEX(Telas!$G$6:$G$105,MATCH(K9,Telas!$A$6:$A$105,0))),""),"") | AG9: =IF($A9="","",IF(ISNUMBER(AD9),IF(AND(N(Y9)>0,N(Parametros!$B$19)=0),"Lista, pero sin costo de impresión (Parametros)","Lista"),IF(Q9="","Consumo tela principal (Despiece o Mediciones). ","")&IF(COUNTIFS(Mediciones!$C$6:$C$305,$A9,Mediciones!$K$6:$K$305,"")>0,"Pesar 1 m de la tela medida (Telas, kg por metro). ","")&IF(T9="","Consumo Tela 2. ","")&IF(W9="","Consumo Tela 3. ","")&IF(K9="","Elegir tela principal. ",IF(ISERROR(INDEX(Telas!$I$6:$I$105,MATCH(K9,Telas!$A$6:$A$105,0))*1),"Precio o peso por metro de "&K9&". ",""))&IF(AND(N(T9)>0,L9=""),"Elegir Tela 2. ",IF(AND(N(T9)>0,ISERROR(INDEX(Telas!$I$6:$I$105,MATCH(L9,Telas!$A$6:$A$105,0))*1)),"Precio o peso por metro de "&L9&". ",""))&IF(Y9="","Metros impresos. ","")&IF(F9="","Tipo de confección. ",IF(AB9="","Precio de confección. ","")))) -> Consumo tela principal (Despiece o Mediciones). Pesar 1 m de la tela medida (Telas, kg por metro). Consumo Tela 2. Precio o peso por metro de CIRE BLANCO. Metros impresos. | AH9: Ficha OT 2369 (48 camisetas infantiles). Falta metros impresos.
A10: 05 · FUTMUJV01 | B10: Fútbol, cuello v | C10: Fútbol | D10: Camiseta | E10: Femenino | F10: Camiseta De Futbol | O10: =IF($A10="","",IF(COUNTIFS(Despiece!$A$6:$A$705,$A10,Despiece!$D$6:$D$705,"Tela principal",Despiece!$F$6:$F$705,">0")=0,"",SUMIFS(Despiece!$F$6:$F$705,Despiece!$A$6:$A$705,$A10,Despiece!$D$6:$D$705,"Tela principal"))) | P10: =IF($A10="","",IFERROR(AVERAGEIFS(Mediciones!$K$6:$K$305,Mediciones!$C$6:$C$305,$A10,Mediciones!$D$6:$D$305,"Tela principal"),"")) | Q10: =IF($A10="","",IF(N(IF($N10="Despiece",IF(ISNUMBER(O10),O10*(1+Parametros!$B$22),IF(COUNTIFS(Despiece!$A$6:$A$705,$A10,Despiece!$D$6:$D$705,"Tela principal")>0,"",0)),IF($N10="Medición real",IF(ISNUMBER(P10),P10,IF(COUNTIFS(Mediciones!$C$6:$C$305,$A10,Mediciones!$D$6:$D$305,"Tela principal")>0,"",0)),IF(ISNUMBER(P10),P10,IF(ISNUMBER(O10),O10*(1+Parametros!$B$22),IF(OR(COUNTIFS(Despiece!$A$6:$A$705,$A10,Despiece!$D$6:$D$705,"Tela principal")>0,COUNTIFS(Mediciones!$C$6:$C$305,$A10,Mediciones!$D$6:$D$305,"Tela principal")>0),"",0))))))=0,"",IF($N10="Despiece",IF(ISNUMBER(O10),O10*(1+Parametros!$B$22),IF(COUNTIFS(Despiece!$A$6:$A$705,$A10,Despiece!$D$6:$D$705,"Tela principal")>0,"",0)),IF($N10="Medición real",IF(ISNUMBER(P10),P10,IF(COUNTIFS(Mediciones!$C$6:$C$305,$A10,Mediciones!$D$6:$D$305,"Tela principal")>0,"",0)),IF(ISNUMBER(P10),P10,IF(ISNUMBER(O10),O10*(1+Parametros!$B$22),IF(OR(COUNTIFS(Despiece!$A$6:$A$705,$A10,Despiece!$D$6:$D$705,"Tela principal")>0,COUNTIFS(Mediciones!$C$6:$C$305,$A10,Mediciones!$D$6:$D$305,"Tela principal")>0),"",0))))))) | R10: =IF($A10="","",IF(COUNTIFS(Despiece!$A$6:$A$705,$A10,Despiece!$D$6:$D$705,"Tela 2",Despiece!$F$6:$F$705,">0")=0,"",SUMIFS(Despiece!$F$6:$F$705,Despiece!$A$6:$A$705,$A10,Despiece!$D$6:$D$705,"Tela 2"))) | S10: =IF($A10="","",IFERROR(AVERAGEIFS(Mediciones!$K$6:$K$305,Mediciones!$C$6:$C$305,$A10,Mediciones!$D$6:$D$305,"Tela 2"),"")) | T10: =IF($A10="","",IF($N10="Despiece",IF(ISNUMBER(R10),R10*(1+Parametros!$B$22),IF(COUNTIFS(Despiece!$A$6:$A$705,$A10,Despiece!$D$6:$D$705,"Tela 2")>0,"",0)),IF($N10="Medición real",IF(ISNUMBER(S10),S10,IF(COUNTIFS(Mediciones!$C$6:$C$305,$A10,Mediciones!$D$6:$D$305,"Tela 2")>0,"",0)),IF(ISNUMBER(S10),S10,IF(ISNUMBER(R10),R10*(1+Parametros!$B$22),IF(OR(COUNTIFS(Despiece!$A$6:$A$705,$A10,Despiece!$D$6:$D$705,"Tela 2")>0,COUNTIFS(Mediciones!$C$6:$C$305,$A10,Mediciones!$D$6:$D$305,"Tela 2")>0),"",0)))))) -> 0 | U10: =IF($A10="","",IF(COUNTIFS(Despiece!$A$6:$A$705,$A10,Despiece!$D$6:$D$705,"Tela 3",Despiece!$F$6:$F$705,">0")=0,"",SUMIFS(Despiece!$F$6:$F$705,Despiece!$A$6:$A$705,$A10,Despiece!$D$6:$D$705,"Tela 3"))) | V10: =IF($A10="","",IFERROR(AVERAGEIFS(Mediciones!$K$6:$K$305,Mediciones!$C$6:$C$305,$A10,Mediciones!$D$6:$D$305,"Tela 3"),"")) | W10: =IF($A10="","",IF($N10="Despiece",IF(ISNUMBER(U10),U10*(1+Parametros!$B$22),IF(COUNTIFS(Despiece!$A$6:$A$705,$A10,Despiece!$D$6:$D$705,"Tela 3")>0,"",0)),IF($N10="Medición real",IF(ISNUMBER(V10),V10,IF(COUNTIFS(Mediciones!$C$6:$C$305,$A10,Mediciones!$D$6:$D$305,"Tela 3")>0,"",0)),IF(ISNUMBER(V10),V10,IF(ISNUMBER(U10),U10*(1+Parametros!$B$22),IF(OR(COUNTIFS(Despiece!$A$6:$A$705,$A10,Despiece!$D$6:$D$705,"Tela 3")>0,COUNTIFS(Mediciones!$C$6:$C$305,$A10,Mediciones!$D$6:$D$305,"Tela 3")>0),"",0)))))) -> 0 | Y10: =IF($A10="","",IF(ISNUMBER(X10),X10,IF(COUNTIFS(Despiece!$A$6:$A$705,$A10,Despiece!$E$6:$E$705,"Sublimada",Despiece!$F$6:$F$705,">0")>0,SUMIFS(Despiece!$F$6:$F$705,Despiece!$A$6:$A$705,$A10,Despiece!$E$6:$E$705,"Sublimada")*(1+Parametros!$B$22),IF(COUNTIFS(Despiece!$A$6:$A$705,$A10,Despiece!$E$6:$E$705,"Sublimada")=0,0,"")))) | Z10: =IF($A10="","",IFERROR(IF(ISNUMBER(Q10),IF(Q10=0,0,Q10*INDEX(Telas!$I$6:$I$105,MATCH(K10,Telas!$A$6:$A$105,0))),NA())+IF(ISNUMBER(T10),IF(T10=0,0,T10*INDEX(Telas!$I$6:$I$105,MATCH(L10,Telas!$A$6:$A$105,0))),NA())+IF(ISNUMBER(W10),IF(W10=0,0,W10*INDEX(Telas!$I$6:$I$105,MATCH(IF(M10="",K10,M10),Telas!$A$6:$A$105,0))),NA()),"")) | AA10: =IF($A10="","",IF(ISNUMBER(Y10),Y10*Parametros!$B$19,"")) | AB10: =IF(OR($A10="",F10=""),"",IFERROR(INDEX(Confeccion!$B$6:$B$125,MATCH(F10,Confeccion!$A$6:$A$125,0)),"")) -> 2000 | AC10: =IF($A10="","",IFERROR(N(H10)*IF(G10="",0,INDEX(Avios!$C$6:$C$65,MATCH(G10,Avios!$A$6:$A$65,0)))+N(J10)*IF(I10="",0,INDEX(Avios!$C$6:$C$65,MATCH(I10,Avios!$A$6:$A$65,0))),"")) -> 0 | AD10: =IF($A10="","",IFERROR(Z10+AA10+AB10+AC10,"")) | AE10: =IF(ISNUMBER(AD10),AD10*Parametros!$B$12,"") | AF10: =IF(AND(ISNUMBER(Q10),K10<>""),IFERROR(1/(Q10*INDEX(Telas!$G$6:$G$105,MATCH(K10,Telas!$A$6:$A$105,0))),""),"") | AG10: =IF($A10="","",IF(ISNUMBER(AD10),IF(AND(N(Y10)>0,N(Parametros!$B$19)=0),"Lista, pero sin costo de impresión (Parametros)","Lista"),IF(Q10="","Consumo tela principal (Despiece o Mediciones). ","")&IF(COUNTIFS(Mediciones!$C$6:$C$305,$A10,Mediciones!$K$6:$K$305,"")>0,"Pesar 1 m de la tela medida (Telas, kg por metro). ","")&IF(T10="","Consumo Tela 2. ","")&IF(W10="","Consumo Tela 3. ","")&IF(K10="","Elegir tela principal. ",IF(ISERROR(INDEX(Telas!$I$6:$I$105,MATCH(K10,Telas!$A$6:$A$105,0))*1),"Precio o peso por metro de "&K10&". ",""))&IF(AND(N(T10)>0,L10=""),"Elegir Tela 2. ",IF(AND(N(T10)>0,ISERROR(INDEX(Telas!$I$6:$I$105,MATCH(L10,Telas!$A$6:$A$105,0))*1)),"Precio o peso por metro de "&L10&". ",""))&IF(Y10="","Metros impresos. ","")&IF(F10="","Tipo de confección. ",IF(AB10="","Precio de confección. ","")))) -> Consumo tela principal (Despiece o Mediciones). Elegir tela principal. Metros impresos. | AH10: Confección sugerida por el tipo de molde: confirmar. Falta ficha de corte.
A11: 06 · FUTHOMV01 | B11: Fútbol, cuello v | C11: Fútbol | D11: Camiseta | E11: Masculino | F11: Camiseta De Futbol | O11: =IF($A11="","",IF(COUNTIFS(Despiece!$A$6:$A$705,$A11,Despiece!$D$6:$D$705,"Tela principal",Despiece!$F$6:$F$705,">0")=0,"",SUMIFS(Despiece!$F$6:$F$705,Despiece!$A$6:$A$705,$A11,Despiece!$D$6:$D$705,"Tela principal"))) | P11: =IF($A11="","",IFERROR(AVERAGEIFS(Mediciones!$K$6:$K$305,Mediciones!$C$6:$C$305,$A11,Mediciones!$D$6:$D$305,"Tela principal"),"")) | Q11: =IF($A11="","",IF(N(IF($N11="Despiece",IF(ISNUMBER(O11),O11*(1+Parametros!$B$22),IF(COUNTIFS(Despiece!$A$6:$A$705,$A11,Despiece!$D$6:$D$705,"Tela principal")>0,"",0)),IF($N11="Medición real",IF(ISNUMBER(P11),P11,IF(COUNTIFS(Mediciones!$C$6:$C$305,$A11,Mediciones!$D$6:$D$305,"Tela principal")>0,"",0)),IF(ISNUMBER(P11),P11,IF(ISNUMBER(O11),O11*(1+Parametros!$B$22),IF(OR(COUNTIFS(Despiece!$A$6:$A$705,$A11,Despiece!$D$6:$D$705,"Tela principal")>0,COUNTIFS(Mediciones!$C$6:$C$305,$A11,Mediciones!$D$6:$D$305,"Tela principal")>0),"",0))))))=0,"",IF($N11="Despiece",IF(ISNUMBER(O11),O11*(1+Parametros!$B$22),IF(COUNTIFS(Despiece!$A$6:$A$705,$A11,Despiece!$D$6:$D$705,"Tela principal")>0,"",0)),IF($N11="Medición real",IF(ISNUMBER(P11),P11,IF(COUNTIFS(Mediciones!$C$6:$C$305,$A11,Mediciones!$D$6:$D$305,"Tela principal")>0,"",0)),IF(ISNUMBER(P11),P11,IF(ISNUMBER(O11),O11*(1+Parametros!$B$22),IF(OR(COUNTIFS(Despiece!$A$6:$A$705,$A11,Despiece!$D$6:$D$705,"Tela principal")>0,COUNTIFS(Mediciones!$C$6:$C$305,$A11,Mediciones!$D$6:$D$305,"Tela principal")>0),"",0))))))) | R11: =IF($A11="","",IF(COUNTIFS(Despiece!$A$6:$A$705,$A11,Despiece!$D$6:$D$705,"Tela 2",Despiece!$F$6:$F$705,">0")=0,"",SUMIFS(Despiece!$F$6:$F$705,Despiece!$A$6:$A$705,$A11,Despiece!$D$6:$D$705,"Tela 2"))) | S11: =IF($A11="","",IFERROR(AVERAGEIFS(Mediciones!$K$6:$K$305,Mediciones!$C$6:$C$305,$A11,Mediciones!$D$6:$D$305,"Tela 2"),"")) | T11: =IF($A11="","",IF($N11="Despiece",IF(ISNUMBER(R11),R11*(1+Parametros!$B$22),IF(COUNTIFS(Despiece!$A$6:$A$705,$A11,Despiece!$D$6:$D$705,"Tela 2")>0,"",0)),IF($N11="Medición real",IF(ISNUMBER(S11),S11,IF(COUNTIFS(Mediciones!$C$6:$C$305,$A11,Mediciones!$D$6:$D$305,"Tela 2")>0,"",0)),IF(ISNUMBER(S11),S11,IF(ISNUMBER(R11),R11*(1+Parametros!$B$22),IF(OR(COUNTIFS(Despiece!$A$6:$A$705,$A11,Despiece!$D$6:$D$705,"Tela 2")>0,COUNTIFS(Mediciones!$C$6:$C$305,$A11,Mediciones!$D$6:$D$305,"Tela 2")>0),"",0)))))) -> 0 | U11: =IF($A11="","",IF(COUNTIFS(Despiece!$A$6:$A$705,$A11,Despiece!$D$6:$D$705,"Tela 3",Despiece!$F$6:$F$705,">0")=0,"",SUMIFS(Despiece!$F$6:$F$705,Despiece!$A$6:$A$705,$A11,Despiece!$D$6:$D$705,"Tela 3"))) | V11: =IF($A11="","",IFERROR(AVERAGEIFS(Mediciones!$K$6:$K$305,Mediciones!$C$6:$C$305,$A11,Mediciones!$D$6:$D$305,"Tela 3"),"")) | W11: =IF($A11="","",IF($N11="Despiece",IF(ISNUMBER(U11),U11*(1+Parametros!$B$22),IF(COUNTIFS(Despiece!$A$6:$A$705,$A11,Despiece!$D$6:$D$705,"Tela 3")>0,"",0)),IF($N11="Medición real",IF(ISNUMBER(V11),V11,IF(COUNTIFS(Mediciones!$C$6:$C$305,$A11,Mediciones!$D$6:$D$305,"Tela 3")>0,"",0)),IF(ISNUMBER(V11),V11,IF(ISNUMBER(U11),U11*(1+Parametros!$B$22),IF(OR(COUNTIFS(Despiece!$A$6:$A$705,$A11,Despiece!$D$6:$D$705,"Tela 3")>0,COUNTIFS(Mediciones!$C$6:$C$305,$A11,Mediciones!$D$6:$D$305,"Tela 3")>0),"",0)))))) -> 0 | Y11: =IF($A11="","",IF(ISNUMBER(X11),X11,IF(COUNTIFS(Despiece!$A$6:$A$705,$A11,Despiece!$E$6:$E$705,"Sublimada",Despiece!$F$6:$F$705,">0")>0,SUMIFS(Despiece!$F$6:$F$705,Despiece!$A$6:$A$705,$A11,Despiece!$E$6:$E$705,"Sublimada")*(1+Parametros!$B$22),IF(COUNTIFS(Despiece!$A$6:$A$705,$A11,Despiece!$E$6:$E$705,"Sublimada")=0,0,"")))) | Z11: =IF($A11="","",IFERROR(IF(ISNUMBER(Q11),IF(Q11=0,0,Q11*INDEX(Telas!$I$6:$I$105,MATCH(K11,Telas!$A$6:$A$105,0))),NA())+IF(ISNUMBER(T11),IF(T11=0,0,T11*INDEX(Telas!$I$6:$I$105,MATCH(L11,Telas!$A$6:$A$105,0))),NA())+IF(ISNUMBER(W11),IF(W11=0,0,W11*INDEX(Telas!$I$6:$I$105,MATCH(IF(M11="",K11,M11),Telas!$A$6:$A$105,0))),NA()),"")) | AA11: =IF($A11="","",IF(ISNUMBER(Y11),Y11*Parametros!$B$19,"")) | AB11: =IF(OR($A11="",F11=""),"",IFERROR(INDEX(Confeccion!$B$6:$B$125,MATCH(F11,Confeccion!$A$6:$A$125,0)),"")) -> 2000 | AC11: =IF($A11="","",IFERROR(N(H11)*IF(G11="",0,INDEX(Avios!$C$6:$C$65,MATCH(G11,Avios!$A$6:$A$65,0)))+N(J11)*IF(I11="",0,INDEX(Avios!$C$6:$C$65,MATCH(I11,Avios!$A$6:$A$65,0))),"")) -> 0 | AD11: =IF($A11="","",IFERROR(Z11+AA11+AB11+AC11,"")) | AE11: =IF(ISNUMBER(AD11),AD11*Parametros!$B$12,"") | AF11: =IF(AND(ISNUMBER(Q11),K11<>""),IFERROR(1/(Q11*INDEX(Telas!$G$6:$G$105,MATCH(K11,Telas!$A$6:$A$105,0))),""),"") | AG11: =IF($A11="","",IF(ISNUMBER(AD11),IF(AND(N(Y11)>0,N(Parametros!$B$19)=0),"Lista, pero sin costo de impresión (Parametros)","Lista"),IF(Q11="","Consumo tela principal (Despiece o Mediciones). ","")&IF(COUNTIFS(Mediciones!$C$6:$C$305,$A11,Mediciones!$K$6:$K$305,"")>0,"Pesar 1 m de la tela medida (Telas, kg por metro). ","")&IF(T11="","Consumo Tela 2. ","")&IF(W11="","Consumo Tela 3. ","")&IF(K11="","Elegir tela principal. ",IF(ISERROR(INDEX(Telas!$I$6:$I$105,MATCH(K11,Telas!$A$6:$A$105,0))*1),"Precio o peso por metro de "&K11&". ",""))&IF(AND(N(T11)>0,L11=""),"Elegir Tela 2. ",IF(AND(N(T11)>0,ISERROR(INDEX(Telas!$I$6:$I$105,MATCH(L11,Telas!$A$6:$A$105,0))*1)),"Precio o peso por metro de "&L11&". ",""))&IF(Y11="","Metros impresos. ","")&IF(F11="","Tipo de confección. ",IF(AB11="","Precio de confección. ","")))) -> Consumo tela principal (Despiece o Mediciones). Elegir tela principal. Metros impresos. | AH11: Confección sugerida por el tipo de molde: confirmar. Falta ficha de corte.
A12: 07 · FUTINMUJV01 | B12: Fútbol infantil, cuello v | C12: Fútbol | D12: Camiseta | E12: Infantil Femenino | F12: Camiseta De Futbol | O12: =IF($A12="","",IF(COUNTIFS(Despiece!$A$6:$A$705,$A12,Despiece!$D$6:$D$705,"Tela principal",Despiece!$F$6:$F$705,">0")=0,"",SUMIFS(Despiece!$F$6:$F$705,Despiece!$A$6:$A$705,$A12,Despiece!$D$6:$D$705,"Tela principal"))) | P12: =IF($A12="","",IFERROR(AVERAGEIFS(Mediciones!$K$6:$K$305,Mediciones!$C$6:$C$305,$A12,Mediciones!$D$6:$D$305,"Tela principal"),"")) | Q12: =IF($A12="","",IF(N(IF($N12="Despiece",IF(ISNUMBER(O12),O12*(1+Parametros!$B$22),IF(COUNTIFS(Despiece!$A$6:$A$705,$A12,Despiece!$D$6:$D$705,"Tela principal")>0,"",0)),IF($N12="Medición real",IF(ISNUMBER(P12),P12,IF(COUNTIFS(Mediciones!$C$6:$C$305,$A12,Mediciones!$D$6:$D$305,"Tela principal")>0,"",0)),IF(ISNUMBER(P12),P12,IF(ISNUMBER(O12),O12*(1+Parametros!$B$22),IF(OR(COUNTIFS(Despiece!$A$6:$A$705,$A12,Despiece!$D$6:$D$705,"Tela principal")>0,COUNTIFS(Mediciones!$C$6:$C$305,$A12,Mediciones!$D$6:$D$305,"Tela principal")>0),"",0))))))=0,"",IF($N12="Despiece",IF(ISNUMBER(O12),O12*(1+Parametros!$B$22),IF(COUNTIFS(Despiece!$A$6:$A$705,$A12,Despiece!$D$6:$D$705,"Tela principal")>0,"",0)),IF($N12="Medición real",IF(ISNUMBER(P12),P12,IF(COUNTIFS(Mediciones!$C$6:$C$305,$A12,Mediciones!$D$6:$D$305,"Tela principal")>0,"",0)),IF(ISNUMBER(P12),P12,IF(ISNUMBER(O12),O12*(1+Parametros!$B$22),IF(OR(COUNTIFS(Despiece!$A$6:$A$705,$A12,Despiece!$D$6:$D$705,"Tela principal")>0,COUNTIFS(Mediciones!$C$6:$C$305,$A12,Mediciones!$D$6:$D$305,"Tela principal")>0),"",0))))))) | R12: =IF($A12="","",IF(COUNTIFS(Despiece!$A$6:$A$705,$A12,Despiece!$D$6:$D$705,"Tela 2",Despiece!$F$6:$F$705,">0")=0,"",SUMIFS(Despiece!$F$6:$F$705,Despiece!$A$6:$A$705,$A12,Despiece!$D$6:$D$705,"Tela 2"))) | S12: =IF($A12="","",IFERROR(AVERAGEIFS(Mediciones!$K$6:$K$305,Mediciones!$C$6:$C$305,$A12,Mediciones!$D$6:$D$305,"Tela 2"),"")) | T12: =IF($A12="","",IF($N12="Despiece",IF(ISNUMBER(R12),R12*(1+Parametros!$B$22),IF(COUNTIFS(Despiece!$A$6:$A$705,$A12,Despiece!$D$6:$D$705,"Tela 2")>0,"",0)),IF($N12="Medición real",IF(ISNUMBER(S12),S12,IF(COUNTIFS(Mediciones!$C$6:$C$305,$A12,Mediciones!$D$6:$D$305,"Tela 2")>0,"",0)),IF(ISNUMBER(S12),S12,IF(ISNUMBER(R12),R12*(1+Parametros!$B$22),IF(OR(COUNTIFS(Despiece!$A$6:$A$705,$A12,Despiece!$D$6:$D$705,"Tela 2")>0,COUNTIFS(Mediciones!$C$6:$C$305,$A12,Mediciones!$D$6:$D$305,"Tela 2")>0),"",0)))))) -> 0 | U12: =IF($A12="","",IF(COUNTIFS(Despiece!$A$6:$A$705,$A12,Despiece!$D$6:$D$705,"Tela 3",Despiece!$F$6:$F$705,">0")=0,"",SUMIFS(Despiece!$F$6:$F$705,Despiece!$A$6:$A$705,$A12,Despiece!$D$6:$D$705,"Tela 3"))) | V12: =IF($A12="","",IFERROR(AVERAGEIFS(Mediciones!$K$6:$K$305,Mediciones!$C$6:$C$305,$A12,Mediciones!$D$6:$D$305,"Tela 3"),"")) | W12: =IF($A12="","",IF($N12="Despiece",IF(ISNUMBER(U12),U12*(1+Parametros!$B$22),IF(COUNTIFS(Despiece!$A$6:$A$705,$A12,Despiece!$D$6:$D$705,"Tela 3")>0,"",0)),IF($N12="Medición real",IF(ISNUMBER(V12),V12,IF(COUNTIFS(Mediciones!$C$6:$C$305,$A12,Mediciones!$D$6:$D$305,"Tela 3")>0,"",0)),IF(ISNUMBER(V12),V12,IF(ISNUMBER(U12),U12*(1+Parametros!$B$22),IF(OR(COUNTIFS(Despiece!$A$6:$A$705,$A12,Despiece!$D$6:$D$705,"Tela 3")>0,COUNTIFS(Mediciones!$C$6:$C$305,$A12,Mediciones!$D$6:$D$305,"Tela 3")>0),"",0)))))) -> 0 | Y12: =IF($A12="","",IF(ISNUMBER(X12),X12,IF(COUNTIFS(Despiece!$A$6:$A$705,$A12,Despiece!$E$6:$E$705,"Sublimada",Despiece!$F$6:$F$705,">0")>0,SUMIFS(Despiece!$F$6:$F$705,Despiece!$A$6:$A$705,$A12,Despiece!$E$6:$E$705,"Sublimada")*(1+Parametros!$B$22),IF(COUNTIFS(Despiece!$A$6:$A$705,$A12,Despiece!$E$6:$E$705,"Sublimada")=0,0,"")))) | Z12: =IF($A12="","",IFERROR(IF(ISNUMBER(Q12),IF(Q12=0,0,Q12*INDEX(Telas!$I$6:$I$105,MATCH(K12,Telas!$A$6:$A$105,0))),NA())+IF(ISNUMBER(T12),IF(T12=0,0,T12*INDEX(Telas!$I$6:$I$105,MATCH(L12,Telas!$A$6:$A$105,0))),NA())+IF(ISNUMBER(W12),IF(W12=0,0,W12*INDEX(Telas!$I$6:$I$105,MATCH(IF(M12="",K12,M12),Telas!$A$6:$A$105,0))),NA()),"")) | AA12: =IF($A12="","",IF(ISNUMBER(Y12),Y12*Parametros!$B$19,"")) | AB12: =IF(OR($A12="",F12=""),"",IFERROR(INDEX(Confeccion!$B$6:$B$125,MATCH(F12,Confeccion!$A$6:$A$125,0)),"")) -> 2000 | AC12: =IF($A12="","",IFERROR(N(H12)*IF(G12="",0,INDEX(Avios!$C$6:$C$65,MATCH(G12,Avios!$A$6:$A$65,0)))+N(J12)*IF(I12="",0,INDEX(Avios!$C$6:$C$65,MATCH(I12,Avios!$A$6:$A$65,0))),"")) -> 0 | AD12: =IF($A12="","",IFERROR(Z12+AA12+AB12+AC12,"")) | AE12: =IF(ISNUMBER(AD12),AD12*Parametros!$B$12,"") | AF12: =IF(AND(ISNUMBER(Q12),K12<>""),IFERROR(1/(Q12*INDEX(Telas!$G$6:$G$105,MATCH(K12,Telas!$A$6:$A$105,0))),""),"") | AG12: =IF($A12="","",IF(ISNUMBER(AD12),IF(AND(N(Y12)>0,N(Parametros!$B$19)=0),"Lista, pero sin costo de impresión (Parametros)","Lista"),IF(Q12="","Consumo tela principal (Despiece o Mediciones). ","")&IF(COUNTIFS(Mediciones!$C$6:$C$305,$A12,Mediciones!$K$6:$K$305,"")>0,"Pesar 1 m de la tela medida (Telas, kg por metro). ","")&IF(T12="","Consumo Tela 2. ","")&IF(W12="","Consumo Tela 3. ","")&IF(K12="","Elegir tela principal. ",IF(ISERROR(INDEX(Telas!$I$6:$I$105,MATCH(K12,Telas!$A$6:$A$105,0))*1),"Precio o peso por metro de "&K12&". ",""))&IF(AND(N(T12)>0,L12=""),"Elegir Tela 2. ",IF(AND(N(T12)>0,ISERROR(INDEX(Telas!$I$6:$I$105,MATCH(L12,Telas!$A$6:$A$105,0))*1)),"Precio o peso por metro de "&L12&". ",""))&IF(Y12="","Metros impresos. ","")&IF(F12="","Tipo de confección. ",IF(AB12="","Precio de confección. ","")))) -> Consumo tela principal (Despiece o Mediciones). Elegir tela principal. Metros impresos. | AH12: Confección sugerida por el tipo de molde: confirmar. Falta ficha de corte.
A13: 08 · FUTINHOMV01 | B13: Fútbol infantil, cuello v | C13: Fútbol | D13: Camiseta | E13: Infantil Masculino | F13: Camiseta De Futbol | O13: =IF($A13="","",IF(COUNTIFS(Despiece!$A$6:$A$705,$A13,Despiece!$D$6:$D$705,"Tela principal",Despiece!$F$6:$F$705,">0")=0,"",SUMIFS(Despiece!$F$6:$F$705,Despiece!$A$6:$A$705,$A13,Despiece!$D$6:$D$705,"Tela principal"))) | P13: =IF($A13="","",IFERROR(AVERAGEIFS(Mediciones!$K$6:$K$305,Mediciones!$C$6:$C$305,$A13,Mediciones!$D$6:$D$305,"Tela principal"),"")) | Q13: =IF($A13="","",IF(N(IF($N13="Despiece",IF(ISNUMBER(O13),O13*(1+Parametros!$B$22),IF(COUNTIFS(Despiece!$A$6:$A$705,$A13,Despiece!$D$6:$D$705,"Tela principal")>0,"",0)),IF($N13="Medición real",IF(ISNUMBER(P13),P13,IF(COUNTIFS(Mediciones!$C$6:$C$305,$A13,Mediciones!$D$6:$D$305,"Tela principal")>0,"",0)),IF(ISNUMBER(P13),P13,IF(ISNUMBER(O13),O13*(1+Parametros!$B$22),IF(OR(COUNTIFS(Despiece!$A$6:$A$705,$A13,Despiece!$D$6:$D$705,"Tela principal")>0,COUNTIFS(Mediciones!$C$6:$C$305,$A13,Mediciones!$D$6:$D$305,"Tela principal")>0),"",0))))))=0,"",IF($N13="Despiece",IF(ISNUMBER(O13),O13*(1+Parametros!$B$22),IF(COUNTIFS(Despiece!$A$6:$A$705,$A13,Despiece!$D$6:$D$705,"Tela principal")>0,"",0)),IF($N13="Medición real",IF(ISNUMBER(P13),P13,IF(COUNTIFS(Mediciones!$C$6:$C$305,$A13,Mediciones!$D$6:$D$305,"Tela principal")>0,"",0)),IF(ISNUMBER(P13),P13,IF(ISNUMBER(O13),O13*(1+Parametros!$B$22),IF(OR(COUNTIFS(Despiece!$A$6:$A$705,$A13,Despiece!$D$6:$D$705,"Tela principal")>0,COUNTIFS(Mediciones!$C$6:$C$305,$A13,Mediciones!$D$6:$D$305,"Tela principal")>0),"",0))))))) | R13: =IF($A13="","",IF(COUNTIFS(Despiece!$A$6:$A$705,$A13,Despiece!$D$6:$D$705,"Tela 2",Despiece!$F$6:$F$705,">0")=0,"",SUMIFS(Despiece!$F$6:$F$705,Despiece!$A$6:$A$705,$A13,Despiece!$D$6:$D$705,"Tela 2"))) | S13: =IF($A13="","",IFERROR(AVERAGEIFS(Mediciones!$K$6:$K$305,Mediciones!$C$6:$C$305,$A13,Mediciones!$D$6:$D$305,"Tela 2"),"")) | T13: =IF($A13="","",IF($N13="Despiece",IF(ISNUMBER(R13),R13*(1+Parametros!$B$22),IF(COUNTIFS(Despiece!$A$6:$A$705,$A13,Despiece!$D$6:$D$705,"Tela 2")>0,"",0)),IF($N13="Medición real",IF(ISNUMBER(S13),S13,IF(COUNTIFS(Mediciones!$C$6:$C$305,$A13,Mediciones!$D$6:$D$305,"Tela 2")>0,"",0)),IF(ISNUMBER(S13),S13,IF(ISNUMBER(R13),R13*(1+Parametros!$B$22),IF(OR(COUNTIFS(Despiece!$A$6:$A$705,$A13,Despiece!$D$6:$D$705,"Tela 2")>0,COUNTIFS(Mediciones!$C$6:$C$305,$A13,Mediciones!$D$6:$D$305,"Tela 2")>0),"",0)))))) -> 0 | U13: =IF($A13="","",IF(COUNTIFS(Despiece!$A$6:$A$705,$A13,Despiece!$D$6:$D$705,"Tela 3",Despiece!$F$6:$F$705,">0")=0,"",SUMIFS(Despiece!$F$6:$F$705,Despiece!$A$6:$A$705,$A13,Despiece!$D$6:$D$705,"Tela 3"))) | V13: =IF($A13="","",IFERROR(AVERAGEIFS(Mediciones!$K$6:$K$305,Mediciones!$C$6:$C$305,$A13,Mediciones!$D$6:$D$305,"Tela 3"),"")) | W13: =IF($A13="","",IF($N13="Despiece",IF(ISNUMBER(U13),U13*(1+Parametros!$B$22),IF(COUNTIFS(Despiece!$A$6:$A$705,$A13,Despiece!$D$6:$D$705,"Tela 3")>0,"",0)),IF($N13="Medición real",IF(ISNUMBER(V13),V13,IF(COUNTIFS(Mediciones!$C$6:$C$305,$A13,Mediciones!$D$6:$D$305,"Tela 3")>0,"",0)),IF(ISNUMBER(V13),V13,IF(ISNUMBER(U13),U13*(1+Parametros!$B$22),IF(OR(COUNTIFS(Despiece!$A$6:$A$705,$A13,Despiece!$D$6:$D$705,"Tela 3")>0,COUNTIFS(Mediciones!$C$6:$C$305,$A13,Mediciones!$D$6:$D$305,"Tela 3")>0),"",0)))))) -> 0 | Y13: =IF($A13="","",IF(ISNUMBER(X13),X13,IF(COUNTIFS(Despiece!$A$6:$A$705,$A13,Despiece!$E$6:$E$705,"Sublimada",Despiece!$F$6:$F$705,">0")>0,SUMIFS(Despiece!$F$6:$F$705,Despiece!$A$6:$A$705,$A13,Despiece!$E$6:$E$705,"Sublimada")*(1+Parametros!$B$22),IF(COUNTIFS(Despiece!$A$6:$A$705,$A13,Despiece!$E$6:$E$705,"Sublimada")=0,0,"")))) | Z13: =IF($A13="","",IFERROR(IF(ISNUMBER(Q13),IF(Q13=0,0,Q13*INDEX(Telas!$I$6:$I$105,MATCH(K13,Telas!$A$6:$A$105,0))),NA())+IF(ISNUMBER(T13),IF(T13=0,0,T13*INDEX(Telas!$I$6:$I$105,MATCH(L13,Telas!$A$6:$A$105,0))),NA())+IF(ISNUMBER(W13),IF(W13=0,0,W13*INDEX(Telas!$I$6:$I$105,MATCH(IF(M13="",K13,M13),Telas!$A$6:$A$105,0))),NA()),"")) | AA13: =IF($A13="","",IF(ISNUMBER(Y13),Y13*Parametros!$B$19,"")) | AB13: =IF(OR($A13="",F13=""),"",IFERROR(INDEX(Confeccion!$B$6:$B$125,MATCH(F13,Confeccion!$A$6:$A$125,0)),"")) -> 2000 | AC13: =IF($A13="","",IFERROR(N(H13)*IF(G13="",0,INDEX(Avios!$C$6:$C$65,MATCH(G13,Avios!$A$6:$A$65,0)))+N(J13)*IF(I13="",0,INDEX(Avios!$C$6:$C$65,MATCH(I13,Avios!$A$6:$A$65,0))),"")) -> 0 | AD13: =IF($A13="","",IFERROR(Z13+AA13+AB13+AC13,"")) | AE13: =IF(ISNUMBER(AD13),AD13*Parametros!$B$12,"") | AF13: =IF(AND(ISNUMBER(Q13),K13<>""),IFERROR(1/(Q13*INDEX(Telas!$G$6:$G$105,MATCH(K13,Telas!$A$6:$A$105,0))),""),"") | AG13: =IF($A13="","",IF(ISNUMBER(AD13),IF(AND(N(Y13)>0,N(Parametros!$B$19)=0),"Lista, pero sin costo de impresión (Parametros)","Lista"),IF(Q13="","Consumo tela principal (Despiece o Mediciones). ","")&IF(COUNTIFS(Mediciones!$C$6:$C$305,$A13,Mediciones!$K$6:$K$305,"")>0,"Pesar 1 m de la tela medida (Telas, kg por metro). ","")&IF(T13="","Consumo Tela 2. ","")&IF(W13="","Consumo Tela 3. ","")&IF(K13="","Elegir tela principal. ",IF(ISERROR(INDEX(Telas!$I$6:$I$105,MATCH(K13,Telas!$A$6:$A$105,0))*1),"Precio o peso por metro de "&K13&". ",""))&IF(AND(N(T13)>0,L13=""),"Elegir Tela 2. ",IF(AND(N(T13)>0,ISERROR(INDEX(Telas!$I$6:$I$105,MATCH(L13,Telas!$A$6:$A$105,0))*1)),"Precio o peso por metro de "&L13&". ",""))&IF(Y13="","Metros impresos. ","")&IF(F13="","Tipo de confección. ",IF(AB13="","Precio de confección. ","")))) -> Consumo tela principal (Despiece o Mediciones). Elegir tela principal. Metros impresos. | AH13: Confección sugerida por el tipo de molde: confirmar. Falta ficha de corte.
A14: 09 · FUTMUJCC01 | B14: Fútbol, cuello camisero | C14: Fútbol | D14: Camiseta | E14: Femenino | F14: Camiseta De Futbol | O14: =IF($A14="","",IF(COUNTIFS(Despiece!$A$6:$A$705,$A14,Despiece!$D$6:$D$705,"Tela principal",Despiece!$F$6:$F$705,">0")=0,"",SUMIFS(Despiece!$F$6:$F$705,Despiece!$A$6:$A$705,$A14,Despiece!$D$6:$D$705,"Tela principal"))) | P14: =IF($A14="","",IFERROR(AVERAGEIFS(Mediciones!$K$6:$K$305,Mediciones!$C$6:$C$305,$A14,Mediciones!$D$6:$D$305,"Tela principal"),"")) | Q14: =IF($A14="","",IF(N(IF($N14="Despiece",IF(ISNUMBER(O14),O14*(1+Parametros!$B$22),IF(COUNTIFS(Despiece!$A$6:$A$705,$A14,Despiece!$D$6:$D$705,"Tela principal")>0,"",0)),IF($N14="Medición real",IF(ISNUMBER(P14),P14,IF(COUNTIFS(Mediciones!$C$6:$C$305,$A14,Mediciones!$D$6:$D$305,"Tela principal")>0,"",0)),IF(ISNUMBER(P14),P14,IF(ISNUMBER(O14),O14*(1+Parametros!$B$22),IF(OR(COUNTIFS(Despiece!$A$6:$A$705,$A14,Despiece!$D$6:$D$705,"Tela principal")>0,COUNTIFS(Mediciones!$C$6:$C$305,$A14,Mediciones!$D$6:$D$305,"Tela principal")>0),"",0))))))=0,"",IF($N14="Despiece",IF(ISNUMBER(O14),O14*(1+Parametros!$B$22),IF(COUNTIFS(Despiece!$A$6:$A$705,$A14,Despiece!$D$6:$D$705,"Tela principal")>0,"",0)),IF($N14="Medición real",IF(ISNUMBER(P14),P14,IF(COUNTIFS(Mediciones!$C$6:$C$305,$A14,Mediciones!$D$6:$D$305,"Tela principal")>0,"",0)),IF(ISNUMBER(P14),P14,IF(ISNUMBER(O14),O14*(1+Parametros!$B$22),IF(OR(COUNTIFS(Despiece!$A$6:$A$705,$A14,Despiece!$D$6:$D$705,"Tela principal")>0,COUNTIFS(Mediciones!$C$6:$C$305,$A14,Mediciones!$D$6:$D$305,"Tela principal")>0),"",0))))))) | R14: =IF($A14="","",IF(COUNTIFS(Despiece!$A$6:$A$705,$A14,Despiece!$D$6:$D$705,"Tela 2",Despiece!$F$6:$F$705,">0")=0,"",SUMIFS(Despiece!$F$6:$F$705,Despiece!$A$6:$A$705,$A14,Despiece!$D$6:$D$705,"Tela 2"))) | S14: =IF($A14="","",IFERROR(AVERAGEIFS(Mediciones!$K$6:$K$305,Mediciones!$C$6:$C$305,$A14,Mediciones!$D$6:$D$305,"Tela 2"),"")) | T14: =IF($A14="","",IF($N14="Despiece",IF(ISNUMBER(R14),R14*(1+Parametros!$B$22),IF(COUNTIFS(Despiece!$A$6:$A$705,$A14,Despiece!$D$6:$D$705,"Tela 2")>0,"",0)),IF($N14="Medición real",IF(ISNUMBER(S14),S14,IF(COUNTIFS(Mediciones!$C$6:$C$305,$A14,Mediciones!$D$6:$D$305,"Tela 2")>0,"",0)),IF(ISNUMBER(S14),S14,IF(ISNUMBER(R14),R14*(1+Parametros!$B$22),IF(OR(COUNTIFS(Despiece!$A$6:$A$705,$A14,Despiece!$D$6:$D$705,"Tela 2")>0,COUNTIFS(Mediciones!$C$6:$C$305,$A14,Mediciones!$D$6:$D$305,"Tela 2")>0),"",0)))))) -> 0 | U14: =IF($A14="","",IF(COUNTIFS(Despiece!$A$6:$A$705,$A14,Despiece!$D$6:$D$705,"Tela 3",Despiece!$F$6:$F$705,">0")=0,"",SUMIFS(Despiece!$F$6:$F$705,Despiece!$A$6:$A$705,$A14,Despiece!$D$6:$D$705,"Tela 3"))) | V14: =IF($A14="","",IFERROR(AVERAGEIFS(Mediciones!$K$6:$K$305,Mediciones!$C$6:$C$305,$A14,Mediciones!$D$6:$D$305,"Tela 3"),"")) | W14: =IF($A14="","",IF($N14="Despiece",IF(ISNUMBER(U14),U14*(1+Parametros!$B$22),IF(COUNTIFS(Despiece!$A$6:$A$705,$A14,Despiece!$D$6:$D$705,"Tela 3")>0,"",0)),IF($N14="Medición real",IF(ISNUMBER(V14),V14,IF(COUNTIFS(Mediciones!$C$6:$C$305,$A14,Mediciones!$D$6:$D$305,"Tela 3")>0,"",0)),IF(ISNUMBER(V14),V14,IF(ISNUMBER(U14),U14*(1+Parametros!$B$22),IF(OR(COUNTIFS(Despiece!$A$6:$A$705,$A14,Despiece!$D$6:$D$705,"Tela 3")>0,COUNTIFS(Mediciones!$C$6:$C$305,$A14,Mediciones!$D$6:$D$305,"Tela 3")>0),"",0)))))) -> 0 | Y14: =IF($A14="","",IF(ISNUMBER(X14),X14,IF(COUNTIFS(Despiece!$A$6:$A$705,$A14,Despiece!$E$6:$E$705,"Sublimada",Despiece!$F$6:$F$705,">0")>0,SUMIFS(Despiece!$F$6:$F$705,Despiece!$A$6:$A$705,$A14,Despiece!$E$6:$E$705,"Sublimada")*(1+Parametros!$B$22),IF(COUNTIFS(Despiece!$A$6:$A$705,$A14,Despiece!$E$6:$E$705,"Sublimada")=0,0,"")))) | Z14: =IF($A14="","",IFERROR(IF(ISNUMBER(Q14),IF(Q14=0,0,Q14*INDEX(Telas!$I$6:$I$105,MATCH(K14,Telas!$A$6:$A$105,0))),NA())+IF(ISNUMBER(T14),IF(T14=0,0,T14*INDEX(Telas!$I$6:$I$105,MATCH(L14,Telas!$A$6:$A$105,0))),NA())+IF(ISNUMBER(W14),IF(W14=0,0,W14*INDEX(Telas!$I$6:$I$105,MATCH(IF(M14="",K14,M14),Telas!$A$6:$A$105,0))),NA()),"")) | AA14: =IF($A14="","",IF(ISNUMBER(Y14),Y14*Parametros!$B$19,"")) | AB14: =IF(OR($A14="",F14=""),"",IFERROR(INDEX(Confeccion!$B$6:$B$125,MATCH(F14,Confeccion!$A$6:$A$125,0)),"")) -> 2000 | AC14: =IF($A14="","",IFERROR(N(H14)*IF(G14="",0,INDEX(Avios!$C$6:$C$65,MATCH(G14,Avios!$A$6:$A$65,0)))+N(J14)*IF(I14="",0,INDEX(Avios!$C$6:$C$65,MATCH(I14,Avios!$A$6:$A$65,0))),"")) -> 0 | AD14: =IF($A14="","",IFERROR(Z14+AA14+AB14+AC14,"")) | AE14: =IF(ISNUMBER(AD14),AD14*Parametros!$B$12,"") | AF14: =IF(AND(ISNUMBER(Q14),K14<>""),IFERROR(1/(Q14*INDEX(Telas!$G$6:$G$105,MATCH(K14,Telas!$A$6:$A$105,0))),""),"") | AG14: =IF($A14="","",IF(ISNUMBER(AD14),IF(AND(N(Y14)>0,N(Parametros!$B$19)=0),"Lista, pero sin costo de impresión (Parametros)","Lista"),IF(Q14="","Consumo tela principal (Despiece o Mediciones). ","")&IF(COUNTIFS(Mediciones!$C$6:$C$305,$A14,Mediciones!$K$6:$K$305,"")>0,"Pesar 1 m de la tela medida (Telas, kg por metro). ","")&IF(T14="","Consumo Tela 2. ","")&IF(W14="","Consumo Tela 3. ","")&IF(K14="","Elegir tela principal. ",IF(ISERROR(INDEX(Telas!$I$6:$I$105,MATCH(K14,Telas!$A$6:$A$105,0))*1),"Precio o peso por metro de "&K14&". ",""))&IF(AND(N(T14)>0,L14=""),"Elegir Tela 2. ",IF(AND(N(T14)>0,ISERROR(INDEX(Telas!$I$6:$I$105,MATCH(L14,Telas!$A$6:$A$105,0))*1)),"Precio o peso por metro de "&L14&". ",""))&IF(Y14="","Metros impresos. ","")&IF(F14="","Tipo de confección. ",IF(AB14="","Precio de confección. ","")))) -> Consumo tela principal (Despiece o Mediciones). Elegir tela principal. Metros impresos. | AH14: Confección sugerida por el tipo de molde: confirmar. Falta ficha de corte.
A15: 10 · FUTHOMCC01 | B15: Fútbol, cuello camisero | C15: Fútbol | D15: Camiseta | E15: Masculino | F15: Camiseta De Futbol | O15: =IF($A15="","",IF(COUNTIFS(Despiece!$A$6:$A$705,$A15,Despiece!$D$6:$D$705,"Tela principal",Despiece!$F$6:$F$705,">0")=0,"",SUMIFS(Despiece!$F$6:$F$705,Despiece!$A$6:$A$705,$A15,Despiece!$D$6:$D$705,"Tela principal"))) | P15: =IF($A15="","",IFERROR(AVERAGEIFS(Mediciones!$K$6:$K$305,Mediciones!$C$6:$C$305,$A15,Mediciones!$D$6:$D$305,"Tela principal"),"")) | Q15: =IF($A15="","",IF(N(IF($N15="Despiece",IF(ISNUMBER(O15),O15*(1+Parametros!$B$22),IF(COUNTIFS(Despiece!$A$6:$A$705,$A15,Despiece!$D$6:$D$705,"Tela principal")>0,"",0)),IF($N15="Medición real",IF(ISNUMBER(P15),P15,IF(COUNTIFS(Mediciones!$C$6:$C$305,$A15,Mediciones!$D$6:$D$305,"Tela principal")>0,"",0)),IF(ISNUMBER(P15),P15,IF(ISNUMBER(O15),O15*(1+Parametros!$B$22),IF(OR(COUNTIFS(Despiece!$A$6:$A$705,$A15,Despiece!$D$6:$D$705,"Tela principal")>0,COUNTIFS(Mediciones!$C$6:$C$305,$A15,Mediciones!$D$6:$D$305,"Tela principal")>0),"",0))))))=0,"",IF($N15="Despiece",IF(ISNUMBER(O15),O15*(1+Parametros!$B$22),IF(COUNTIFS(Despiece!$A$6:$A$705,$A15,Despiece!$D$6:$D$705,"Tela principal")>0,"",0)),IF($N15="Medición real",IF(ISNUMBER(P15),P15,IF(COUNTIFS(Mediciones!$C$6:$C$305,$A15,Mediciones!$D$6:$D$305,"Tela principal")>0,"",0)),IF(ISNUMBER(P15),P15,IF(ISNUMBER(O15),O15*(1+Parametros!$B$22),IF(OR(COUNTIFS(Despiece!$A$6:$A$705,$A15,Despiece!$D$6:$D$705,"Tela principal")>0,COUNTIFS(Mediciones!$C$6:$C$305,$A15,Mediciones!$D$6:$D$305,"Tela principal")>0),"",0))))))) | R15: =IF($A15="","",IF(COUNTIFS(Despiece!$A$6:$A$705,$A15,Despiece!$D$6:$D$705,"Tela 2",Despiece!$F$6:$F$705,">0")=0,"",SUMIFS(Despiece!$F$6:$F$705,Despiece!$A$6:$A$705,$A15,Despiece!$D$6:$D$705,"Tela 2"))) | S15: =IF($A15="","",IFERROR(AVERAGEIFS(Mediciones!$K$6:$K$305,Mediciones!$C$6:$C$305,$A15,Mediciones!$D$6:$D$305,"Tela 2"),"")) | T15: =IF($A15="","",IF($N15="Despiece",IF(ISNUMBER(R15),R15*(1+Parametros!$B$22),IF(COUNTIFS(Despiece!$A$6:$A$705,$A15,Despiece!$D$6:$D$705,"Tela 2")>0,"",0)),IF($N15="Medición real",IF(ISNUMBER(S15),S15,IF(COUNTIFS(Mediciones!$C$6:$C$305,$A15,Mediciones!$D$6:$D$305,"Tela 2")>0,"",0)),IF(ISNUMBER(S15),S15,IF(ISNUMBER(R15),R15*(1+Parametros!$B$22),IF(OR(COUNTIFS(Despiece!$A$6:$A$705,$A15,Despiece!$D$6:$D$705,"Tela 2")>0,COUNTIFS(Mediciones!$C$6:$C$305,$A15,Mediciones!$D$6:$D$305,"Tela 2")>0),"",0)))))) -> 0 | U15: =IF($A15="","",IF(COUNTIFS(Despiece!$A$6:$A$705,$A15,Despiece!$D$6:$D$705,"Tela 3",Despiece!$F$6:$F$705,">0")=0,"",SUMIFS(Despiece!$F$6:$F$705,Despiece!$A$6:$A$705,$A15,Despiece!$D$6:$D$705,"Tela 3"))) | V15: =IF($A15="","",IFERROR(AVERAGEIFS(Mediciones!$K$6:$K$305,Mediciones!$C$6:$C$305,$A15,Mediciones!$D$6:$D$305,"Tela 3"),"")) | W15: =IF($A15="","",IF($N15="Despiece",IF(ISNUMBER(U15),U15*(1+Parametros!$B$22),IF(COUNTIFS(Despiece!$A$6:$A$705,$A15,Despiece!$D$6:$D$705,"Tela 3")>0,"",0)),IF($N15="Medición real",IF(ISNUMBER(V15),V15,IF(COUNTIFS(Mediciones!$C$6:$C$305,$A15,Mediciones!$D$6:$D$305,"Tela 3")>0,"",0)),IF(ISNUMBER(V15),V15,IF(ISNUMBER(U15),U15*(1+Parametros!$B$22),IF(OR(COUNTIFS(Despiece!$A$6:$A$705,$A15,Despiece!$D$6:$D$705,"Tela 3")>0,COUNTIFS(Mediciones!$C$6:$C$305,$A15,Mediciones!$D$6:$D$305,"Tela 3")>0),"",0)))))) -> 0 | Y15: =IF($A15="","",IF(ISNUMBER(X15),X15,IF(COUNTIFS(Despiece!$A$6:$A$705,$A15,Despiece!$E$6:$E$705,"Sublimada",Despiece!$F$6:$F$705,">0")>0,SUMIFS(Despiece!$F$6:$F$705,Despiece!$A$6:$A$705,$A15,Despiece!$E$6:$E$705,"Sublimada")*(1+Parametros!$B$22),IF(COUNTIFS(Despiece!$A$6:$A$705,$A15,Despiece!$E$6:$E$705,"Sublimada")=0,0,"")))) | Z15: =IF($A15="","",IFERROR(IF(ISNUMBER(Q15),IF(Q15=0,0,Q15*INDEX(Telas!$I$6:$I$105,MATCH(K15,Telas!$A$6:$A$105,0))),NA())+IF(ISNUMBER(T15),IF(T15=0,0,T15*INDEX(Telas!$I$6:$I$105,MATCH(L15,Telas!$A$6:$A$105,0))),NA())+IF(ISNUMBER(W15),IF(W15=0,0,W15*INDEX(Telas!$I$6:$I$105,MATCH(IF(M15="",K15,M15),Telas!$A$6:$A$105,0))),NA()),"")) | AA15: =IF($A15="","",IF(ISNUMBER(Y15),Y15*Parametros!$B$19,"")) | AB15: =IF(OR($A15="",F15=""),"",IFERROR(INDEX(Confeccion!$B$6:$B$125,MATCH(F15,Confeccion!$A$6:$A$125,0)),"")) -> 2000 | AC15: =IF($A15="","",IFERROR(N(H15)*IF(G15="",0,INDEX(Avios!$C$6:$C$65,MATCH(G15,Avios!$A$6:$A$65,0)))+N(J15)*IF(I15="",0,INDEX(Avios!$C$6:$C$65,MATCH(I15,Avios!$A$6:$A$65,0))),"")) -> 0 | AD15: =IF($A15="","",IFERROR(Z15+AA15+AB15+AC15,"")) | AE15: =IF(ISNUMBER(AD15),AD15*Parametros!$B$12,"") | AF15: =IF(AND(ISNUMBER(Q15),K15<>""),IFERROR(1/(Q15*INDEX(Telas!$G$6:$G$105,MATCH(K15,Telas!$A$6:$A$105,0))),""),"") | AG15: =IF($A15="","",IF(ISNUMBER(AD15),IF(AND(N(Y15)>0,N(Parametros!$B$19)=0),"Lista, pero sin costo de impresión (Parametros)","Lista"),IF(Q15="","Consumo tela principal (Despiece o Mediciones). ","")&IF(COUNTIFS(Mediciones!$C$6:$C$305,$A15,Mediciones!$K$6:$K$305,"")>0,"Pesar 1 m de la tela medida (Telas, kg por metro). ","")&IF(T15="","Consumo Tela 2. ","")&IF(W15="","Consumo Tela 3. ","")&IF(K15="","Elegir tela principal. ",IF(ISERROR(INDEX(Telas!$I$6:$I$105,MATCH(K15,Telas!$A$6:$A$105,0))*1),"Precio o peso por metro de "&K15&". ",""))&IF(AND(N(T15)>0,L15=""),"Elegir Tela 2. ",IF(AND(N(T15)>0,ISERROR(INDEX(Telas!$I$6:$I$105,MATCH(L15,Telas!$A$6:$A$105,0))*1)),"Precio o peso por metro de "&L15&". ",""))&IF(Y15="","Metros impresos. ","")&IF(F15="","Tipo de confección. ",IF(AB15="","Precio de confección. ","")))) -> Consumo tela principal (Despiece o Mediciones). Elegir tela principal. Metros impresos. | AH15: Confección sugerida por el tipo de molde: confirmar. Falta ficha de corte.
A16: 11 · FUTINMUJCC01 | B16: Fútbol infantil, cuello camisero | C16: Fútbol | D16: Camiseta | E16: Infantil Femenino | F16: Camiseta De Futbol | O16: =IF($A16="","",IF(COUNTIFS(Despiece!$A$6:$A$705,$A16,Despiece!$D$6:$D$705,"Tela principal",Despiece!$F$6:$F$705,">0")=0,"",SUMIFS(Despiece!$F$6:$F$705,Despiece!$A$6:$A$705,$A16,Despiece!$D$6:$D$705,"Tela principal"))) | P16: =IF($A16="","",IFERROR(AVERAGEIFS(Mediciones!$K$6:$K$305,Mediciones!$C$6:$C$305,$A16,Mediciones!$D$6:$D$305,"Tela principal"),"")) | Q16: =IF($A16="","",IF(N(IF($N16="Despiece",IF(ISNUMBER(O16),O16*(1+Parametros!$B$22),IF(COUNTIFS(Despiece!$A$6:$A$705,$A16,Despiece!$D$6:$D$705,"Tela principal")>0,"",0)),IF($N16="Medición real",IF(ISNUMBER(P16),P16,IF(COUNTIFS(Mediciones!$C$6:$C$305,$A16,Mediciones!$D$6:$D$305,"Tela principal")>0,"",0)),IF(ISNUMBER(P16),P16,IF(ISNUMBER(O16),O16*(1+Parametros!$B$22),IF(OR(COUNTIFS(Despiece!$A$6:$A$705,$A16,Despiece!$D$6:$D$705,"Tela principal")>0,COUNTIFS(Mediciones!$C$6:$C$305,$A16,Mediciones!$D$6:$D$305,"Tela principal")>0),"",0))))))=0,"",IF($N16="Despiece",IF(ISNUMBER(O16),O16*(1+Parametros!$B$22),IF(COUNTIFS(Despiece!$A$6:$A$705,$A16,Despiece!$D$6:$D$705,"Tela principal")>0,"",0)),IF($N16="Medición real",IF(ISNUMBER(P16),P16,IF(COUNTIFS(Mediciones!$C$6:$C$305,$A16,Mediciones!$D$6:$D$305,"Tela principal")>0,"",0)),IF(ISNUMBER(P16),P16,IF(ISNUMBER(O16),O16*(1+Parametros!$B$22),IF(OR(COUNTIFS(Despiece!$A$6:$A$705,$A16,Despiece!$D$6:$D$705,"Tela principal")>0,COUNTIFS(Mediciones!$C$6:$C$305,$A16,Mediciones!$D$6:$D$305,"Tela principal")>0),"",0))))))) | R16: =IF($A16="","",IF(COUNTIFS(Despiece!$A$6:$A$705,$A16,Despiece!$D$6:$D$705,"Tela 2",Despiece!$F$6:$F$705,">0")=0,"",SUMIFS(Despiece!$F$6:$F$705,Despiece!$A$6:$A$705,$A16,Despiece!$D$6:$D$705,"Tela 2"))) | S16: =IF($A16="","",IFERROR(AVERAGEIFS(Mediciones!$K$6:$K$305,Mediciones!$C$6:$C$305,$A16,Mediciones!$D$6:$D$305,"Tela 2"),"")) | T16: =IF($A16="","",IF($N16="Despiece",IF(ISNUMBER(R16),R16*(1+Parametros!$B$22),IF(COUNTIFS(Despiece!$A$6:$A$705,$A16,Despiece!$D$6:$D$705,"Tela 2")>0,"",0)),IF($N16="Medición real",IF(ISNUMBER(S16),S16,IF(COUNTIFS(Mediciones!$C$6:$C$305,$A16,Mediciones!$D$6:$D$305,"Tela 2")>0,"",0)),IF(ISNUMBER(S16),S16,IF(ISNUMBER(R16),R16*(1+Parametros!$B$22),IF(OR(COUNTIFS(Despiece!$A$6:$A$705,$A16,Despiece!$D$6:$D$705,"Tela 2")>0,COUNTIFS(Mediciones!$C$6:$C$305,$A16,Mediciones!$D$6:$D$305,"Tela 2")>0),"",0)))))) -> 0 | U16: =IF($A16="","",IF(COUNTIFS(Despiece!$A$6:$A$705,$A16,Despiece!$D$6:$D$705,"Tela 3",Despiece!$F$6:$F$705,">0")=0,"",SUMIFS(Despiece!$F$6:$F$705,Despiece!$A$6:$A$705,$A16,Despiece!$D$6:$D$705,"Tela 3"))) | V16: =IF($A16="","",IFERROR(AVERAGEIFS(Mediciones!$K$6:$K$305,Mediciones!$C$6:$C$305,$A16,Mediciones!$D$6:$D$305,"Tela 3"),"")) | W16: =IF($A16="","",IF($N16="Despiece",IF(ISNUMBER(U16),U16*(1+Parametros!$B$22),IF(COUNTIFS(Despiece!$A$6:$A$705,$A16,Despiece!$D$6:$D$705,"Tela 3")>0,"",0)),IF($N16="Medición real",IF(ISNUMBER(V16),V16,IF(COUNTIFS(Mediciones!$C$6:$C$305,$A16,Mediciones!$D$6:$D$305,"Tela 3")>0,"",0)),IF(ISNUMBER(V16),V16,IF(ISNUMBER(U16),U16*(1+Parametros!$B$22),IF(OR(COUNTIFS(Despiece!$A$6:$A$705,$A16,Despiece!$D$6:$D$705,"Tela 3")>0,COUNTIFS(Mediciones!$C$6:$C$305,$A16,Mediciones!$D$6:$D$305,"Tela 3")>0),"",0)))))) -> 0 | Y16: =IF($A16="","",IF(ISNUMBER(X16),X16,IF(COUNTIFS(Despiece!$A$6:$A$705,$A16,Despiece!$E$6:$E$705,"Sublimada",Despiece!$F$6:$F$705,">0")>0,SUMIFS(Despiece!$F$6:$F$705,Despiece!$A$6:$A$705,$A16,Despiece!$E$6:$E$705,"Sublimada")*(1+Parametros!$B$22),IF(COUNTIFS(Despiece!$A$6:$A$705,$A16,Despiece!$E$6:$E$705,"Sublimada")=0,0,"")))) | Z16: =IF($A16="","",IFERROR(IF(ISNUMBER(Q16),IF(Q16=0,0,Q16*INDEX(Telas!$I$6:$I$105,MATCH(K16,Telas!$A$6:$A$105,0))),NA())+IF(ISNUMBER(T16),IF(T16=0,0,T16*INDEX(Telas!$I$6:$I$105,MATCH(L16,Telas!$A$6:$A$105,0))),NA())+IF(ISNUMBER(W16),IF(W16=0,0,W16*INDEX(Telas!$I$6:$I$105,MATCH(IF(M16="",K16,M16),Telas!$A$6:$A$105,0))),NA()),"")) | AA16: =IF($A16="","",IF(ISNUMBER(Y16),Y16*Parametros!$B$19,"")) | AB16: =IF(OR($A16="",F16=""),"",IFERROR(INDEX(Confeccion!$B$6:$B$125,MATCH(F16,Confeccion!$A$6:$A$125,0)),"")) -> 2000 | AC16: =IF($A16="","",IFERROR(N(H16)*IF(G16="",0,INDEX(Avios!$C$6:$C$65,MATCH(G16,Avios!$A$6:$A$65,0)))+N(J16)*IF(I16="",0,INDEX(Avios!$C$6:$C$65,MATCH(I16,Avios!$A$6:$A$65,0))),"")) -> 0 | AD16: =IF($A16="","",IFERROR(Z16+AA16+AB16+AC16,"")) | AE16: =IF(ISNUMBER(AD16),AD16*Parametros!$B$12,"") | AF16: =IF(AND(ISNUMBER(Q16),K16<>""),IFERROR(1/(Q16*INDEX(Telas!$G$6:$G$105,MATCH(K16,Telas!$A$6:$A$105,0))),""),"") | AG16: =IF($A16="","",IF(ISNUMBER(AD16),IF(AND(N(Y16)>0,N(Parametros!$B$19)=0),"Lista, pero sin costo de impresión (Parametros)","Lista"),IF(Q16="","Consumo tela principal (Despiece o Mediciones). ","")&IF(COUNTIFS(Mediciones!$C$6:$C$305,$A16,Mediciones!$K$6:$K$305,"")>0,"Pesar 1 m de la tela medida (Telas, kg por metro). ","")&IF(T16="","Consumo Tela 2. ","")&IF(W16="","Consumo Tela 3. ","")&IF(K16="","Elegir tela principal. ",IF(ISERROR(INDEX(Telas!$I$6:$I$105,MATCH(K16,Telas!$A$6:$A$105,0))*1),"Precio o peso por metro de "&K16&". ",""))&IF(AND(N(T16)>0,L16=""),"Elegir Tela 2. ",IF(AND(N(T16)>0,ISERROR(INDEX(Telas!$I$6:$I$105,MATCH(L16,Telas!$A$6:$A$105,0))*1)),"Precio o peso por metro de "&L16&". ",""))&IF(Y16="","Metros impresos. ","")&IF(F16="","Tipo de confección. ",IF(AB16="","Precio de confección. ","")))) -> Consumo tela principal (Despiece o Mediciones). Elegir tela principal. Metros impresos. | AH16: Confección sugerida por el tipo de molde: confirmar. Falta ficha de corte.
A17: 12 · FUTINHOMCC01 | B17: Fútbol infantil, cuello camisero | C17: Fútbol | D17: Camiseta | E17: Infantil Masculino | F17: Camiseta De Futbol | O17: =IF($A17="","",IF(COUNTIFS(Despiece!$A$6:$A$705,$A17,Despiece!$D$6:$D$705,"Tela principal",Despiece!$F$6:$F$705,">0")=0,"",SUMIFS(Despiece!$F$6:$F$705,Despiece!$A$6:$A$705,$A17,Despiece!$D$6:$D$705,"Tela principal"))) | P17: =IF($A17="","",IFERROR(AVERAGEIFS(Mediciones!$K$6:$K$305,Mediciones!$C$6:$C$305,$A17,Mediciones!$D$6:$D$305,"Tela principal"),"")) | Q17: =IF($A17="","",IF(N(IF($N17="Despiece",IF(ISNUMBER(O17),O17*(1+Parametros!$B$22),IF(COUNTIFS(Despiece!$A$6:$A$705,$A17,Despiece!$D$6:$D$705,"Tela principal")>0,"",0)),IF($N17="Medición real",IF(ISNUMBER(P17),P17,IF(COUNTIFS(Mediciones!$C$6:$C$305,$A17,Mediciones!$D$6:$D$305,"Tela principal")>0,"",0)),IF(ISNUMBER(P17),P17,IF(ISNUMBER(O17),O17*(1+Parametros!$B$22),IF(OR(COUNTIFS(Despiece!$A$6:$A$705,$A17,Despiece!$D$6:$D$705,"Tela principal")>0,COUNTIFS(Mediciones!$C$6:$C$305,$A17,Mediciones!$D$6:$D$305,"Tela principal")>0),"",0))))))=0,"",IF($N17="Despiece",IF(ISNUMBER(O17),O17*(1+Parametros!$B$22),IF(COUNTIFS(Despiece!$A$6:$A$705,$A17,Despiece!$D$6:$D$705,"Tela principal")>0,"",0)),IF($N17="Medición real",IF(ISNUMBER(P17),P17,IF(COUNTIFS(Mediciones!$C$6:$C$305,$A17,Mediciones!$D$6:$D$305,"Tela principal")>0,"",0)),IF(ISNUMBER(P17),P17,IF(ISNUMBER(O17),O17*(1+Parametros!$B$22),IF(OR(COUNTIFS(Despiece!$A$6:$A$705,$A17,Despiece!$D$6:$D$705,"Tela principal")>0,COUNTIFS(Mediciones!$C$6:$C$305,$A17,Mediciones!$D$6:$D$305,"Tela principal")>0),"",0))))))) | R17: =IF($A17="","",IF(COUNTIFS(Despiece!$A$6:$A$705,$A17,Despiece!$D$6:$D$705,"Tela 2",Despiece!$F$6:$F$705,">0")=0,"",SUMIFS(Despiece!$F$6:$F$705,Despiece!$A$6:$A$705,$A17,Despiece!$D$6:$D$705,"Tela 2"))) | S17: =IF($A17="","",IFERROR(AVERAGEIFS(Mediciones!$K$6:$K$305,Mediciones!$C$6:$C$305,$A17,Mediciones!$D$6:$D$305,"Tela 2"),"")) | T17: =IF($A17="","",IF($N17="Despiece",IF(ISNUMBER(R17),R17*(1+Parametros!$B$22),IF(COUNTIFS(Despiece!$A$6:$A$705,$A17,Despiece!$D$6:$D$705,"Tela 2")>0,"",0)),IF($N17="Medición real",IF(ISNUMBER(S17),S17,IF(COUNTIFS(Mediciones!$C$6:$C$305,$A17,Mediciones!$D$6:$D$305,"Tela 2")>0,"",0)),IF(ISNUMBER(S17),S17,IF(ISNUMBER(R17),R17*(1+Parametros!$B$22),IF(OR(COUNTIFS(Despiece!$A$6:$A$705,$A17,Despiece!$D$6:$D$705,"Tela 2")>0,COUNTIFS(Mediciones!$C$6:$C$305,$A17,Mediciones!$D$6:$D$305,"Tela 2")>0),"",0)))))) -> 0 | U17: =IF($A17="","",IF(COUNTIFS(Despiece!$A$6:$A$705,$A17,Despiece!$D$6:$D$705,"Tela 3",Despiece!$F$6:$F$705,">0")=0,"",SUMIFS(Despiece!$F$6:$F$705,Despiece!$A$6:$A$705,$A17,Despiece!$D$6:$D$705,"Tela 3"))) | V17: =IF($A17="","",IFERROR(AVERAGEIFS(Mediciones!$K$6:$K$305,Mediciones!$C$6:$C$305,$A17,Mediciones!$D$6:$D$305,"Tela 3"),"")) | W17: =IF($A17="","",IF($N17="Despiece",IF(ISNUMBER(U17),U17*(1+Parametros!$B$22),IF(COUNTIFS(Despiece!$A$6:$A$705,$A17,Despiece!$D$6:$D$705,"Tela 3")>0,"",0)),IF($N17="Medición real",IF(ISNUMBER(V17),V17,IF(COUNTIFS(Mediciones!$C$6:$C$305,$A17,Mediciones!$D$6:$D$305,"Tela 3")>0,"",0)),IF(ISNUMBER(V17),V17,IF(ISNUMBER(U17),U17*(1+Parametros!$B$22),IF(OR(COUNTIFS(Despiece!$A$6:$A$705,$A17,Despiece!$D$6:$D$705,"Tela 3")>0,COUNTIFS(Mediciones!$C$6:$C$305,$A17,Mediciones!$D$6:$D$305,"Tela 3")>0),"",0)))))) -> 0 | Y17: =IF($A17="","",IF(ISNUMBER(X17),X17,IF(COUNTIFS(Despiece!$A$6:$A$705,$A17,Despiece!$E$6:$E$705,"Sublimada",Despiece!$F$6:$F$705,">0")>0,SUMIFS(Despiece!$F$6:$F$705,Despiece!$A$6:$A$705,$A17,Despiece!$E$6:$E$705,"Sublimada")*(1+Parametros!$B$22),IF(COUNTIFS(Despiece!$A$6:$A$705,$A17,Despiece!$E$6:$E$705,"Sublimada")=0,0,"")))) | Z17: =IF($A17="","",IFERROR(IF(ISNUMBER(Q17),IF(Q17=0,0,Q17*INDEX(Telas!$I$6:$I$105,MATCH(K17,Telas!$A$6:$A$105,0))),NA())+IF(ISNUMBER(T17),IF(T17=0,0,T17*INDEX(Telas!$I$6:$I$105,MATCH(L17,Telas!$A$6:$A$105,0))),NA())+IF(ISNUMBER(W17),IF(W17=0,0,W17*INDEX(Telas!$I$6:$I$105,MATCH(IF(M17="",K17,M17),Telas!$A$6:$A$105,0))),NA()),"")) | AA17: =IF($A17="","",IF(ISNUMBER(Y17),Y17*Parametros!$B$19,"")) | AB17: =IF(OR($A17="",F17=""),"",IFERROR(INDEX(Confeccion!$B$6:$B$125,MATCH(F17,Confeccion!$A$6:$A$125,0)),"")) -> 2000 | AC17: =IF($A17="","",IFERROR(N(H17)*IF(G17="",0,INDEX(Avios!$C$6:$C$65,MATCH(G17,Avios!$A$6:$A$65,0)))+N(J17)*IF(I17="",0,INDEX(Avios!$C$6:$C$65,MATCH(I17,Avios!$A$6:$A$65,0))),"")) -> 0 | AD17: =IF($A17="","",IFERROR(Z17+AA17+AB17+AC17,"")) | AE17: =IF(ISNUMBER(AD17),AD17*Parametros!$B$12,"") | AF17: =IF(AND(ISNUMBER(Q17),K17<>""),IFERROR(1/(Q17*INDEX(Telas!$G$6:$G$105,MATCH(K17,Telas!$A$6:$A$105,0))),""),"") | AG17: =IF($A17="","",IF(ISNUMBER(AD17),IF(AND(N(Y17)>0,N(Parametros!$B$19)=0),"Lista, pero sin costo de impresión (Parametros)","Lista"),IF(Q17="","Consumo tela principal (Despiece o Mediciones). ","")&IF(COUNTIFS(Mediciones!$C$6:$C$305,$A17,Mediciones!$K$6:$K$305,"")>0,"Pesar 1 m de la tela medida (Telas, kg por metro). ","")&IF(T17="","Consumo Tela 2. ","")&IF(W17="","Consumo Tela 3. ","")&IF(K17="","Elegir tela principal. ",IF(ISERROR(INDEX(Telas!$I$6:$I$105,MATCH(K17,Telas!$A$6:$A$105,0))*1),"Precio o peso por metro de "&K17&". ",""))&IF(AND(N(T17)>0,L17=""),"Elegir Tela 2. ",IF(AND(N(T17)>0,ISERROR(INDEX(Telas!$I$6:$I$105,MATCH(L17,Telas!$A$6:$A$105,0))*1)),"Precio o peso por metro de "&L17&". ",""))&IF(Y17="","Metros impresos. ","")&IF(F17="","Tipo de confección. ",IF(AB17="","Precio de confección. ","")))) -> Consumo tela principal (Despiece o Mediciones). Elegir tela principal. Metros impresos. | AH17: Confección sugerida por el tipo de molde: confirmar. Falta ficha de corte.
A18: 13 · FUTMUJU01PRO | B18: Fútbol, pro, cuello redondo | C18: Fútbol | D18: Camiseta | E18: Femenino | F18: Camiseta De Futbol | K18: MONTESIMONE TRAINING (fut pro) | O18: =IF($A18="","",IF(COUNTIFS(Despiece!$A$6:$A$705,$A18,Despiece!$D$6:$D$705,"Tela principal",Despiece!$F$6:$F$705,">0")=0,"",SUMIFS(Despiece!$F$6:$F$705,Despiece!$A$6:$A$705,$A18,Despiece!$D$6:$D$705,"Tela principal"))) | P18: =IF($A18="","",IFERROR(AVERAGEIFS(Mediciones!$K$6:$K$305,Mediciones!$C$6:$C$305,$A18,Mediciones!$D$6:$D$305,"Tela principal"),"")) -> 0.62182741 | Q18: =IF($A18="","",IF(N(IF($N18="Despiece",IF(ISNUMBER(O18),O18*(1+Parametros!$B$22),IF(COUNTIFS(Despiece!$A$6:$A$705,$A18,Despiece!$D$6:$D$705,"Tela principal")>0,"",0)),IF($N18="Medición real",IF(ISNUMBER(P18),P18,IF(COUNTIFS(Mediciones!$C$6:$C$305,$A18,Mediciones!$D$6:$D$305,"Tela principal")>0,"",0)),IF(ISNUMBER(P18),P18,IF(ISNUMBER(O18),O18*(1+Parametros!$B$22),IF(OR(COUNTIFS(Despiece!$A$6:$A$705,$A18,Despiece!$D$6:$D$705,"Tela principal")>0,COUNTIFS(Mediciones!$C$6:$C$305,$A18,Mediciones!$D$6:$D$305,"Tela principal")>0),"",0))))))=0,"",IF($N18="Despiece",IF(ISNUMBER(O18),O18*(1+Parametros!$B$22),IF(COUNTIFS(Despiece!$A$6:$A$705,$A18,Despiece!$D$6:$D$705,"Tela principal")>0,"",0)),IF($N18="Medición real",IF(ISNUMBER(P18),P18,IF(COUNTIFS(Mediciones!$C$6:$C$305,$A18,Mediciones!$D$6:$D$305,"Tela principal")>0,"",0)),IF(ISNUMBER(P18),P18,IF(ISNUMBER(O18),O18*(1+Parametros!$B$22),IF(OR(COUNTIFS(Despiece!$A$6:$A$705,$A18,Despiece!$D$6:$D$705,"Tela principal")>0,COUNTIFS(Mediciones!$C$6:$C$305,$A18,Mediciones!$D$6:$D$305,"Tela principal")>0),"",0))))))) -> 0.62182741 | R18: =IF($A18="","",IF(COUNTIFS(Despiece!$A$6:$A$705,$A18,Despiece!$D$6:$D$705,"Tela 2",Despiece!$F$6:$F$705,">0")=0,"",SUMIFS(Despiece!$F$6:$F$705,Despiece!$A$6:$A$705,$A18,Despiece!$D$6:$D$705,"Tela 2"))) | S18: =IF($A18="","",IFERROR(AVERAGEIFS(Mediciones!$K$6:$K$305,Mediciones!$C$6:$C$305,$A18,Mediciones!$D$6:$D$305,"Tela 2"),"")) | T18: =IF($A18="","",IF($N18="Despiece",IF(ISNUMBER(R18),R18*(1+Parametros!$B$22),IF(COUNTIFS(Despiece!$A$6:$A$705,$A18,Despiece!$D$6:$D$705,"Tela 2")>0,"",0)),IF($N18="Medición real",IF(ISNUMBER(S18),S18,IF(COUNTIFS(Mediciones!$C$6:$C$305,$A18,Mediciones!$D$6:$D$305,"Tela 2")>0,"",0)),IF(ISNUMBER(S18),S18,IF(ISNUMBER(R18),R18*(1+Parametros!$B$22),IF(OR(COUNTIFS(Despiece!$A$6:$A$705,$A18,Despiece!$D$6:$D$705,"Tela 2")>0,COUNTIFS(Mediciones!$C$6:$C$305,$A18,Mediciones!$D$6:$D$305,"Tela 2")>0),"",0)))))) | U18: =IF($A18="","",IF(COUNTIFS(Despiece!$A$6:$A$705,$A18,Despiece!$D$6:$D$705,"Tela 3",Despiece!$F$6:$F$705,">0")=0,"",SUMIFS(Despiece!$F$6:$F$705,Despiece!$A$6:$A$705,$A18,Despiece!$D$6:$D$705,"Tela 3"))) | V18: =IF($A18="","",IFERROR(AVERAGEIFS(Mediciones!$K$6:$K$305,Mediciones!$C$6:$C$305,$A18,Mediciones!$D$6:$D$305,"Tela 3"),"")) | W18: =IF($A18="","",IF($N18="Despiece",IF(ISNUMBER(U18),U18*(1+Parametros!$B$22),IF(COUNTIFS(Despiece!$A$6:$A$705,$A18,Despiece!$D$6:$D$705,"Tela 3")>0,"",0)),IF($N18="Medición real",IF(ISNUMBER(V18),V18,IF(COUNTIFS(Mediciones!$C$6:$C$305,$A18,Mediciones!$D$6:$D$305,"Tela 3")>0,"",0)),IF(ISNUMBER(V18),V18,IF(ISNUMBER(U18),U18*(1+Parametros!$B$22),IF(OR(COUNTIFS(Despiece!$A$6:$A$705,$A18,Despiece!$D$6:$D$705,"Tela 3")>0,COUNTIFS(Mediciones!$C$6:$C$305,$A18,Mediciones!$D$6:$D$305,"Tela 3")>0),"",0)))))) -> 0 | Y18: =IF($A18="","",IF(ISNUMBER(X18),X18,IF(COUNTIFS(Despiece!$A$6:$A$705,$A18,Despiece!$E$6:$E$705,"Sublimada",Despiece!$F$6:$F$705,">0")>0,SUMIFS(Despiece!$F$6:$F$705,Despiece!$A$6:$A$705,$A18,Despiece!$E$6:$E$705,"Sublimada")*(1+Parametros!$B$22),IF(COUNTIFS(Despiece!$A$6:$A$705,$A18,Despiece!$E$6:$E$705,"Sublimada")=0,0,"")))) | Z18: =IF($A18="","",IFERROR(IF(ISNUMBER(Q18),IF(Q18=0,0,Q18*INDEX(Telas!$I$6:$I$105,MATCH(K18,Telas!$A$6:$A$105,0))),NA())+IF(ISNUMBER(T18),IF(T18=0,0,T18*INDEX(Telas!$I$6:$I$105,MATCH(L18,Telas!$A$6:$A$105,0))),NA())+IF(ISNUMBER(W18),IF(W18=0,0,W18*INDEX(Telas!$I$6:$I$105,MATCH(IF(M18="",K18,M18),Telas!$A$6:$A$105,0))),NA()),"")) | AA18: =IF($A18="","",IF(ISNUMBER(Y18),Y18*Parametros!$B$19,"")) | AB18: =IF(OR($A18="",F18=""),"",IFERROR(INDEX(Confeccion!$B$6:$B$125,MATCH(F18,Confeccion!$A$6:$A$125,0)),"")) -> 2000 | AC18: =IF($A18="","",IFERROR(N(H18)*IF(G18="",0,INDEX(Avios!$C$6:$C$65,MATCH(G18,Avios!$A$6:$A$65,0)))+N(J18)*IF(I18="",0,INDEX(Avios!$C$6:$C$65,MATCH(I18,Avios!$A$6:$A$65,0))),"")) -> 0 | AD18: =IF($A18="","",IFERROR(Z18+AA18+AB18+AC18,"")) | AE18: =IF(ISNUMBER(AD18),AD18*Parametros!$B$12,"") | AF18: =IF(AND(ISNUMBER(Q18),K18<>""),IFERROR(1/(Q18*INDEX(Telas!$G$6:$G$105,MATCH(K18,Telas!$A$6:$A$105,0))),""),"") -> 8.1632653 | AG18: =IF($A18="","",IF(ISNUMBER(AD18),IF(AND(N(Y18)>0,N(Parametros!$B$19)=0),"Lista, pero sin costo de impresión (Parametros)","Lista"),IF(Q18="","Consumo tela principal (Despiece o Mediciones). ","")&IF(COUNTIFS(Mediciones!$C$6:$C$305,$A18,Mediciones!$K$6:$K$305,"")>0,"Pesar 1 m de la tela medida (Telas, kg por metro). ","")&IF(T18="","Consumo Tela 2. ","")&IF(W18="","Consumo Tela 3. ","")&IF(K18="","Elegir tela principal. ",IF(ISERROR(INDEX(Telas!$I$6:$I$105,MATCH(K18,Telas!$A$6:$A$105,0))*1),"Precio o peso por metro de "&K18&". ",""))&IF(AND(N(T18)>0,L18=""),"Elegir Tela 2. ",IF(AND(N(T18)>0,ISERROR(INDEX(Telas!$I$6:$I$105,MATCH(L18,Telas!$A$6:$A$105,0))*1)),"Precio o peso por metro de "&L18&". ",""))&IF(Y18="","Metros impresos. ","")&IF(F18="","Tipo de confección. ",IF(AB18="","Precio de confección. ","")))) -> Consumo Tela 2. Metros impresos. | AH18: Ficha OT 2257 (20 camisetas Pro femeninas). Falta metros impresos.
A19: 14 · FUTHOMU01PRO | B19: Fútbol, pro, cuello redondo | C19: Fútbol | D19: Camiseta | E19: Masculino | F19: Camiseta De Futbol | K19: MONTESIMONE TRAINING (fut pro) | L19: MESH | O19: =IF($A19="","",IF(COUNTIFS(Despiece!$A$6:$A$705,$A19,Despiece!$D$6:$D$705,"Tela principal",Despiece!$F$6:$F$705,">0")=0,"",SUMIFS(Despiece!$F$6:$F$705,Despiece!$A$6:$A$705,$A19,Despiece!$D$6:$D$705,"Tela principal"))) | P19: =IF($A19="","",IFERROR(AVERAGEIFS(Mediciones!$K$6:$K$305,Mediciones!$C$6:$C$305,$A19,Mediciones!$D$6:$D$305,"Tela principal"),"")) -> 0.60913706 | Q19: =IF($A19="","",IF(N(IF($N19="Despiece",IF(ISNUMBER(O19),O19*(1+Parametros!$B$22),IF(COUNTIFS(Despiece!$A$6:$A$705,$A19,Despiece!$D$6:$D$705,"Tela principal")>0,"",0)),IF($N19="Medición real",IF(ISNUMBER(P19),P19,IF(COUNTIFS(Mediciones!$C$6:$C$305,$A19,Mediciones!$D$6:$D$305,"Tela principal")>0,"",0)),IF(ISNUMBER(P19),P19,IF(ISNUMBER(O19),O19*(1+Parametros!$B$22),IF(OR(COUNTIFS(Despiece!$A$6:$A$705,$A19,Despiece!$D$6:$D$705,"Tela principal")>0,COUNTIFS(Mediciones!$C$6:$C$305,$A19,Mediciones!$D$6:$D$305,"Tela principal")>0),"",0))))))=0,"",IF($N19="Despiece",IF(ISNUMBER(O19),O19*(1+Parametros!$B$22),IF(COUNTIFS(Despiece!$A$6:$A$705,$A19,Despiece!$D$6:$D$705,"Tela principal")>0,"",0)),IF($N19="Medición real",IF(ISNUMBER(P19),P19,IF(COUNTIFS(Mediciones!$C$6:$C$305,$A19,Mediciones!$D$6:$D$305,"Tela principal")>0,"",0)),IF(ISNUMBER(P19),P19,IF(ISNUMBER(O19),O19*(1+Parametros!$B$22),IF(OR(COUNTIFS(Despiece!$A$6:$A$705,$A19,Despiece!$D$6:$D$705,"Tela principal")>0,COUNTIFS(Mediciones!$C$6:$C$305,$A19,Mediciones!$D$6:$D$305,"Tela principal")>0),"",0))))))) -> 0.60913706 | R19: =IF($A19="","",IF(COUNTIFS(Despiece!$A$6:$A$705,$A19,Despiece!$D$6:$D$705,"Tela 2",Despiece!$F$6:$F$705,">0")=0,"",SUMIFS(Despiece!$F$6:$F$705,Despiece!$A$6:$A$705,$A19,Despiece!$D$6:$D$705,"Tela 2"))) | S19: =IF($A19="","",IFERROR(AVERAGEIFS(Mediciones!$K$6:$K$305,Mediciones!$C$6:$C$305,$A19,Mediciones!$D$6:$D$305,"Tela 2"),"")) | T19: =IF($A19="","",IF($N19="Despiece",IF(ISNUMBER(R19),R19*(1+Parametros!$B$22),IF(COUNTIFS(Despiece!$A$6:$A$705,$A19,Despiece!$D$6:$D$705,"Tela 2")>0,"",0)),IF($N19="Medición real",IF(ISNUMBER(S19),S19,IF(COUNTIFS(Mediciones!$C$6:$C$305,$A19,Mediciones!$D$6:$D$305,"Tela 2")>0,"",0)),IF(ISNUMBER(S19),S19,IF(ISNUMBER(R19),R19*(1+Parametros!$B$22),IF(OR(COUNTIFS(Despiece!$A$6:$A$705,$A19,Despiece!$D$6:$D$705,"Tela 2")>0,COUNTIFS(Mediciones!$C$6:$C$305,$A19,Mediciones!$D$6:$D$305,"Tela 2")>0),"",0)))))) | U19: =IF($A19="","",IF(COUNTIFS(Despiece!$A$6:$A$705,$A19,Despiece!$D$6:$D$705,"Tela 3",Despiece!$F$6:$F$705,">0")=0,"",SUMIFS(Despiece!$F$6:$F$705,Despiece!$A$6:$A$705,$A19,Despiece!$D$6:$D$705,"Tela 3"))) | V19: =IF($A19="","",IFERROR(AVERAGEIFS(Mediciones!$K$6:$K$305,Mediciones!$C$6:$C$305,$A19,Mediciones!$D$6:$D$305,"Tela 3"),"")) | W19: =IF($A19="","",IF($N19="Despiece",IF(ISNUMBER(U19),U19*(1+Parametros!$B$22),IF(COUNTIFS(Despiece!$A$6:$A$705,$A19,Despiece!$D$6:$D$705,"Tela 3")>0,"",0)),IF($N19="Medición real",IF(ISNUMBER(V19),V19,IF(COUNTIFS(Mediciones!$C$6:$C$305,$A19,Mediciones!$D$6:$D$305,"Tela 3")>0,"",0)),IF(ISNUMBER(V19),V19,IF(ISNUMBER(U19),U19*(1+Parametros!$B$22),IF(OR(COUNTIFS(Despiece!$A$6:$A$705,$A19,Despiece!$D$6:$D$705,"Tela 3")>0,COUNTIFS(Mediciones!$C$6:$C$305,$A19,Mediciones!$D$6:$D$305,"Tela 3")>0),"",0)))))) -> 0 | X19: 1.9 | Y19: =IF($A19="","",IF(ISNUMBER(X19),X19,IF(COUNTIFS(Despiece!$A$6:$A$705,$A19,Despiece!$E$6:$E$705,"Sublimada",Despiece!$F$6:$F$705,">0")>0,SUMIFS(Despiece!$F$6:$F$705,Despiece!$A$6:$A$705,$A19,Despiece!$E$6:$E$705,"Sublimada")*(1+Parametros!$B$22),IF(COUNTIFS(Despiece!$A$6:$A$705,$A19,Despiece!$E$6:$E$705,"Sublimada")=0,0,"")))) -> 1.9 | Z19: =IF($A19="","",IFERROR(IF(ISNUMBER(Q19),IF(Q19=0,0,Q19*INDEX(Telas!$I$6:$I$105,MATCH(K19,Telas!$A$6:$A$105,0))),NA())+IF(ISNUMBER(T19),IF(T19=0,0,T19*INDEX(Telas!$I$6:$I$105,MATCH(L19,Telas!$A$6:$A$105,0))),NA())+IF(ISNUMBER(W19),IF(W19=0,0,W19*INDEX(Telas!$I$6:$I$105,MATCH(IF(M19="",K19,M19),Telas!$A$6:$A$105,0))),NA()),"")) | AA19: =IF($A19="","",IF(ISNUMBER(Y19),Y19*Parametros!$B$19,"")) -> 0 | AB19: =IF(OR($A19="",F19=""),"",IFERROR(INDEX(Confeccion!$B$6:$B$125,MATCH(F19,Confeccion!$A$6:$A$125,0)),"")) -> 2000 | AC19: =IF($A19="","",IFERROR(N(H19)*IF(G19="",0,INDEX(Avios!$C$6:$C$65,MATCH(G19,Avios!$A$6:$A$65,0)))+N(J19)*IF(I19="",0,INDEX(Avios!$C$6:$C$65,MATCH(I19,Avios!$A$6:$A$65,0))),"")) -> 0 | AD19: =IF($A19="","",IFERROR(Z19+AA19+AB19+AC19,"")) | AE19: =IF(ISNUMBER(AD19),AD19*Parametros!$B$12,"") | AF19: =IF(AND(ISNUMBER(Q19),K19<>""),IFERROR(1/(Q19*INDEX(Telas!$G$6:$G$105,MATCH(K19,Telas!$A$6:$A$105,0))),""),"") -> 8.3333333 | AG19: =IF($A19="","",IF(ISNUMBER(AD19),IF(AND(N(Y19)>0,N(Parametros!$B$19)=0),"Lista, pero sin costo de impresión (Parametros)","Lista"),IF(Q19="","Consumo tela principal (Despiece o Mediciones). ","")&IF(COUNTIFS(Mediciones!$C$6:$C$305,$A19,Mediciones!$K$6:$K$305,"")>0,"Pesar 1 m de la tela medida (Telas, kg por metro). ","")&IF(T19="","Consumo Tela 2. ","")&IF(W19="","Consumo Tela 3. ","")&IF(K19="","Elegir tela principal. ",IF(ISERROR(INDEX(Telas!$I$6:$I$105,MATCH(K19,Telas!$A$6:$A$105,0))*1),"Precio o peso por metro de "&K19&". ",""))&IF(AND(N(T19)>0,L19=""),"Elegir Tela 2. ",IF(AND(N(T19)>0,ISERROR(INDEX(Telas!$I$6:$I$105,MATCH(L19,Telas!$A$6:$A$105,0))*1)),"Precio o peso por metro de "&L19&". ",""))&IF(Y19="","Metros impresos. ","")&IF(F19="","Tipo de confección. ",IF(AB19="","Precio de confección. ","")))) -> Pesar 1 m de la tela medida (Telas, kg por metro). Consumo Tela 2. | AH19: Ficha OT 2547 (20 camisetas Pro masculinas). Metros: la ficha dice 1,9; la receta anterior 1,2 → confirmar.
A20: 15 · FUTMUJV01PRO | B20: Fútbol, pro, cuello v | C20: Fútbol | D20: Camiseta | E20: Femenino | F20: Camiseta De Futbol | O20: =IF($A20="","",IF(COUNTIFS(Despiece!$A$6:$A$705,$A20,Despiece!$D$6:$D$705,"Tela principal",Despiece!$F$6:$F$705,">0")=0,"",SUMIFS(Despiece!$F$6:$F$705,Despiece!$A$6:$A$705,$A20,Despiece!$D$6:$D$705,"Tela principal"))) | P20: =IF($A20="","",IFERROR(AVERAGEIFS(Mediciones!$K$6:$K$305,Mediciones!$C$6:$C$305,$A20,Mediciones!$D$6:$D$305,"Tela principal"),"")) | Q20: =IF($A20="","",IF(N(IF($N20="Despiece",IF(ISNUMBER(O20),O20*(1+Parametros!$B$22),IF(COUNTIFS(Despiece!$A$6:$A$705,$A20,Despiece!$D$6:$D$705,"Tela principal")>0,"",0)),IF($N20="Medición real",IF(ISNUMBER(P20),P20,IF(COUNTIFS(Mediciones!$C$6:$C$305,$A20,Mediciones!$D$6:$D$305,"Tela principal")>0,"",0)),IF(ISNUMBER(P20),P20,IF(ISNUMBER(O20),O20*(1+Parametros!$B$22),IF(OR(COUNTIFS(Despiece!$A$6:$A$705,$A20,Despiece!$D$6:$D$705,"Tela principal")>0,COUNTIFS(Mediciones!$C$6:$C$305,$A20,Mediciones!$D$6:$D$305,"Tela principal")>0),"",0))))))=0,"",IF($N20="Despiece",IF(ISNUMBER(O20),O20*(1+Parametros!$B$22),IF(COUNTIFS(Despiece!$A$6:$A$705,$A20,Despiece!$D$6:$D$705,"Tela principal")>0,"",0)),IF($N20="Medición real",IF(ISNUMBER(P20),P20,IF(COUNTIFS(Mediciones!$C$6:$C$305,$A20,Mediciones!$D$6:$D$305,"Tela principal")>0,"",0)),IF(ISNUMBER(P20),P20,IF(ISNUMBER(O20),O20*(1+Parametros!$B$22),IF(OR(COUNTIFS(Despiece!$A$6:$A$705,$A20,Despiece!$D$6:$D$705,"Tela principal")>0,COUNTIFS(Mediciones!$C$6:$C$305,$A20,Mediciones!$D$6:$D$305,"Tela principal")>0),"",0))))))) | R20: =IF($A20="","",IF(COUNTIFS(Despiece!$A$6:$A$705,$A20,Despiece!$D$6:$D$705,"Tela 2",Despiece!$F$6:$F$705,">0")=0,"",SUMIFS(Despiece!$F$6:$F$705,Despiece!$A$6:$A$705,$A20,Despiece!$D$6:$D$705,"Tela 2"))) | S20: =IF($A20="","",IFERROR(AVERAGEIFS(Mediciones!$K$6:$K$305,Mediciones!$C$6:$C$305,$A20,Mediciones!$D$6:$D$305,"Tela 2"),"")) | T20: =IF($A20="","",IF($N20="Despiece",IF(ISNUMBER(R20),R20*(1+Parametros!$B$22),IF(COUNTIFS(Despiece!$A$6:$A$705,$A20,Despiece!$D$6:$D$705,"Tela 2")>0,"",0)),IF($N20="Medición real",IF(ISNUMBER(S20),S20,IF(COUNTIFS(Mediciones!$C$6:$C$305,$A20,Mediciones!$D$6:$D$305,"Tela 2")>0,"",0)),IF(ISNUMBER(S20),S20,IF(ISNUMBER(R20),R20*(1+Parametros!$B$22),IF(OR(COUNTIFS(Despiece!$A$6:$A$705,$A20,Despiece!$D$6:$D$705,"Tela 2")>0,COUNTIFS(Mediciones!$C$6:$C$305,$A20,Mediciones!$D$6:$D$305,"Tela 2")>0),"",0)))))) | U20: =IF($A20="","",IF(COUNTIFS(Despiece!$A$6:$A$705,$A20,Despiece!$D$6:$D$705,"Tela 3",Despiece!$F$6:$F$705,">0")=0,"",SUMIFS(Despiece!$F$6:$F$705,Despiece!$A$6:$A$705,$A20,Despiece!$D$6:$D$705,"Tela 3"))) | V20: =IF($A20="","",IFERROR(AVERAGEIFS(Mediciones!$K$6:$K$305,Mediciones!$C$6:$C$305,$A20,Mediciones!$D$6:$D$305,"Tela 3"),"")) | W20: =IF($A20="","",IF($N20="Despiece",IF(ISNUMBER(U20),U20*(1+Parametros!$B$22),IF(COUNTIFS(Despiece!$A$6:$A$705,$A20,Despiece!$D$6:$D$705,"Tela 3")>0,"",0)),IF($N20="Medición real",IF(ISNUMBER(V20),V20,IF(COUNTIFS(Mediciones!$C$6:$C$305,$A20,Mediciones!$D$6:$D$305,"Tela 3")>0,"",0)),IF(ISNUMBER(V20),V20,IF(ISNUMBER(U20),U20*(1+Parametros!$B$22),IF(OR(COUNTIFS(Despiece!$A$6:$A$705,$A20,Despiece!$D$6:$D$705,"Tela 3")>0,COUNTIFS(Mediciones!$C$6:$C$305,$A20,Mediciones!$D$6:$D$305,"Tela 3")>0),"",0)))))) -> 0 | Y20: =IF($A20="","",IF(ISNUMBER(X20),X20,IF(COUNTIFS(Despiece!$A$6:$A$705,$A20,Despiece!$E$6:$E$705,"Sublimada",Despiece!$F$6:$F$705,">0")>0,SUMIFS(Despiece!$F$6:$F$705,Despiece!$A$6:$A$705,$A20,Despiece!$E$6:$E$705,"Sublimada")*(1+Parametros!$B$22),IF(COUNTIFS(Despiece!$A$6:$A$705,$A20,Despiece!$E$6:$E$705,"Sublimada")=0,0,"")))) | Z20: =IF($A20="","",IFERROR(IF(ISNUMBER(Q20),IF(Q20=0,0,Q20*INDEX(Telas!$I$6:$I$105,MATCH(K20,Telas!$A$6:$A$105,0))),NA())+IF(ISNUMBER(T20),IF(T20=0,0,T20*INDEX(Telas!$I$6:$I$105,MATCH(L20,Telas!$A$6:$A$105,0))),NA())+IF(ISNUMBER(W20),IF(W20=0,0,W20*INDEX(Telas!$I$6:$I$105,MATCH(IF(M20="",K20,M20),Telas!$A$6:$A$105,0))),NA()),"")) | AA20: =IF($A20="","",IF(ISNUMBER(Y20),Y20*Parametros!$B$19,"")) | AB20: =IF(OR($A20="",F20=""),"",IFERROR(INDEX(Confeccion!$B$6:$B$125,MATCH(F20,Confeccion!$A$6:$A$125,0)),"")) -> 2000 | AC20: =IF($A20="","",IFERROR(N(H20)*IF(G20="",0,INDEX(Avios!$C$6:$C$65,MATCH(G20,Avios!$A$6:$A$65,0)))+N(J20)*IF(I20="",0,INDEX(Avios!$C$6:$C$65,MATCH(I20,Avios!$A$6:$A$65,0))),"")) -> 0 | AD20: =IF($A20="","",IFERROR(Z20+AA20+AB20+AC20,"")) | AE20: =IF(ISNUMBER(AD20),AD20*Parametros!$B$12,"") | AF20: =IF(AND(ISNUMBER(Q20),K20<>""),IFERROR(1/(Q20*INDEX(Telas!$G$6:$G$105,MATCH(K20,Telas!$A$6:$A$105,0))),""),"") | AG20: =IF($A20="","",IF(ISNUMBER(AD20),IF(AND(N(Y20)>0,N(Parametros!$B$19)=0),"Lista, pero sin costo de impresión (Parametros)","Lista"),IF(Q20="","Consumo tela principal (Despiece o Mediciones). ","")&IF(COUNTIFS(Mediciones!$C$6:$C$305,$A20,Mediciones!$K$6:$K$305,"")>0,"Pesar 1 m de la tela medida (Telas, kg por metro). ","")&IF(T20="","Consumo Tela 2. ","")&IF(W20="","Consumo Tela 3. ","")&IF(K20="","Elegir tela principal. ",IF(ISERROR(INDEX(Telas!$I$6:$I$105,MATCH(K20,Telas!$A$6:$A$105,0))*1),"Precio o peso por metro de "&K20&". ",""))&IF(AND(N(T20)>0,L20=""),"Elegir Tela 2. ",IF(AND(N(T20)>0,ISERROR(INDEX(Telas!$I$6:$I$105,MATCH(L20,Telas!$A$6:$A$105,0))*1)),"Precio o peso por metro de "&L20&". ",""))&IF(Y20="","Metros impresos. ","")&IF(F20="","Tipo de confección. ",IF(AB20="","Precio de confección. ","")))) -> Consumo tela principal (Despiece o Mediciones). Consumo Tela 2. Elegir tela principal. Metros impresos. | AH20: Confección sugerida por el tipo de molde: confirmar. Falta ficha de corte.
A21: 16 · FUTHOMV01PRO | B21: Fútbol, pro, cuello v | C21: Fútbol | D21: Camiseta | E21: Masculino | F21: Camiseta De Futbol | O21: =IF($A21="","",IF(COUNTIFS(Despiece!$A$6:$A$705,$A21,Despiece!$D$6:$D$705,"Tela principal",Despiece!$F$6:$F$705,">0")=0,"",SUMIFS(Despiece!$F$6:$F$705,Despiece!$A$6:$A$705,$A21,Despiece!$D$6:$D$705,"Tela principal"))) | P21: =IF($A21="","",IFERROR(AVERAGEIFS(Mediciones!$K$6:$K$305,Mediciones!$C$6:$C$305,$A21,Mediciones!$D$6:$D$305,"Tela principal"),"")) | Q21: =IF($A21="","",IF(N(IF($N21="Despiece",IF(ISNUMBER(O21),O21*(1+Parametros!$B$22),IF(COUNTIFS(Despiece!$A$6:$A$705,$A21,Despiece!$D$6:$D$705,"Tela principal")>0,"",0)),IF($N21="Medición real",IF(ISNUMBER(P21),P21,IF(COUNTIFS(Mediciones!$C$6:$C$305,$A21,Mediciones!$D$6:$D$305,"Tela principal")>0,"",0)),IF(ISNUMBER(P21),P21,IF(ISNUMBER(O21),O21*(1+Parametros!$B$22),IF(OR(COUNTIFS(Despiece!$A$6:$A$705,$A21,Despiece!$D$6:$D$705,"Tela principal")>0,COUNTIFS(Mediciones!$C$6:$C$305,$A21,Mediciones!$D$6:$D$305,"Tela principal")>0),"",0))))))=0,"",IF($N21="Despiece",IF(ISNUMBER(O21),O21*(1+Parametros!$B$22),IF(COUNTIFS(Despiece!$A$6:$A$705,$A21,Despiece!$D$6:$D$705,"Tela principal")>0,"",0)),IF($N21="Medición real",IF(ISNUMBER(P21),P21,IF(COUNTIFS(Mediciones!$C$6:$C$305,$A21,Mediciones!$D$6:$D$305,"Tela principal")>0,"",0)),IF(ISNUMBER(P21),P21,IF(ISNUMBER(O21),O21*(1+Parametros!$B$22),IF(OR(COUNTIFS(Despiece!$A$6:$A$705,$A21,Despiece!$D$6:$D$705,"Tela principal")>0,COUNTIFS(Mediciones!$C$6:$C$305,$A21,Mediciones!$D$6:$D$305,"Tela principal")>0),"",0))))))) | R21: =IF($A21="","",IF(COUNTIFS(Despiece!$A$6:$A$705,$A21,Despiece!$D$6:$D$705,"Tela 2",Despiece!$F$6:$F$705,">0")=0,"",SUMIFS(Despiece!$F$6:$F$705,Despiece!$A$6:$A$705,$A21,Despiece!$D$6:$D$705,"Tela 2"))) | S21: =IF($A21="","",IFERROR(AVERAGEIFS(Mediciones!$K$6:$K$305,Mediciones!$C$6:$C$305,$A21,Mediciones!$D$6:$D$305,"Tela 2"),"")) | T21: =IF($A21="","",IF($N21="Despiece",IF(ISNUMBER(R21),R21*(1+Parametros!$B$22),IF(COUNTIFS(Despiece!$A$6:$A$705,$A21,Despiece!$D$6:$D$705,"Tela 2")>0,"",0)),IF($N21="Medición real",IF(ISNUMBER(S21),S21,IF(COUNTIFS(Mediciones!$C$6:$C$305,$A21,Mediciones!$D$6:$D$305,"Tela 2")>0,"",0)),IF(ISNUMBER(S21),S21,IF(ISNUMBER(R21),R21*(1+Parametros!$B$22),IF(OR(COUNTIFS(Despiece!$A$6:$A$705,$A21,Despiece!$D$6:$D$705,"Tela 2")>0,COUNTIFS(Mediciones!$C$6:$C$305,$A21,Mediciones!$D$6:$D$305,"Tela 2")>0),"",0)))))) | U21: =IF($A21="","",IF(COUNTIFS(Despiece!$A$6:$A$705,$A21,Despiece!$D$6:$D$705,"Tela 3",Despiece!$F$6:$F$705,">0")=0,"",SUMIFS(Despiece!$F$6:$F$705,Despiece!$A$6:$A$705,$A21,Despiece!$D$6:$D$705,"Tela 3"))) | V21: =IF($A21="","",IFERROR(AVERAGEIFS(Mediciones!$K$6:$K$305,Mediciones!$C$6:$C$305,$A21,Mediciones!$D$6:$D$305,"Tela 3"),"")) | W21: =IF($A21="","",IF($N21="Despiece",IF(ISNUMBER(U21),U21*(1+Parametros!$B$22),IF(COUNTIFS(Despiece!$A$6:$A$705,$A21,Despiece!$D$6:$D$705,"Tela 3")>0,"",0)),IF($N21="Medición real",IF(ISNUMBER(V21),V21,IF(COUNTIFS(Mediciones!$C$6:$C$305,$A21,Mediciones!$D$6:$D$305,"Tela 3")>0,"",0)),IF(ISNUMBER(V21),V21,IF(ISNUMBER(U21),U21*(1+Parametros!$B$22),IF(OR(COUNTIFS(Despiece!$A$6:$A$705,$A21,Despiece!$D$6:$D$705,"Tela 3")>0,COUNTIFS(Mediciones!$C$6:$C$305,$A21,Mediciones!$D$6:$D$305,"Tela 3")>0),"",0)))))) -> 0 | Y21: =IF($A21="","",IF(ISNUMBER(X21),X21,IF(COUNTIFS(Despiece!$A$6:$A$705,$A21,Despiece!$E$6:$E$705,"Sublimada",Despiece!$F$6:$F$705,">0")>0,SUMIFS(Despiece!$F$6:$F$705,Despiece!$A$6:$A$705,$A21,Despiece!$E$6:$E$705,"Sublimada")*(1+Parametros!$B$22),IF(COUNTIFS(Despiece!$A$6:$A$705,$A21,Despiece!$E$6:$E$705,"Sublimada")=0,0,"")))) | Z21: =IF($A21="","",IFERROR(IF(ISNUMBER(Q21),IF(Q21=0,0,Q21*INDEX(Telas!$I$6:$I$105,MATCH(K21,Telas!$A$6:$A$105,0))),NA())+IF(ISNUMBER(T21),IF(T21=0,0,T21*INDEX(Telas!$I$6:$I$105,MATCH(L21,Telas!$A$6:$A$105,0))),NA())+IF(ISNUMBER(W21),IF(W21=0,0,W21*INDEX(Telas!$I$6:$I$105,MATCH(IF(M21="",K21,M21),Telas!$A$6:$A$105,0))),NA()),"")) | AA21: =IF($A21="","",IF(ISNUMBER(Y21),Y21*Parametros!$B$19,"")) | AB21: =IF(OR($A21="",F21=""),"",IFERROR(INDEX(Confeccion!$B$6:$B$125,MATCH(F21,Confeccion!$A$6:$A$125,0)),"")) -> 2000 | AC21: =IF($A21="","",IFERROR(N(H21)*IF(G21="",0,INDEX(Avios!$C$6:$C$65,MATCH(G21,Avios!$A$6:$A$65,0)))+N(J21)*IF(I21="",0,INDEX(Avios!$C$6:$C$65,MATCH(I21,Avios!$A$6:$A$65,0))),"")) -> 0 | AD21: =IF($A21="","",IFERROR(Z21+AA21+AB21+AC21,"")) | AE21: =IF(ISNUMBER(AD21),AD21*Parametros!$B$12,"") | AF21: =IF(AND(ISNUMBER(Q21),K21<>""),IFERROR(1/(Q21*INDEX(Telas!$G$6:$G$105,MATCH(K21,Telas!$A$6:$A$105,0))),""),"") | AG21: =IF($A21="","",IF(ISNUMBER(AD21),IF(AND(N(Y21)>0,N(Parametros!$B$19)=0),"Lista, pero sin costo de impresión (Parametros)","Lista"),IF(Q21="","Consumo tela principal (Despiece o Mediciones). ","")&IF(COUNTIFS(Mediciones!$C$6:$C$305,$A21,Mediciones!$K$6:$K$305,"")>0,"Pesar 1 m de la tela medida (Telas, kg por metro). ","")&IF(T21="","Consumo Tela 2. ","")&IF(W21="","Consumo Tela 3. ","")&IF(K21="","Elegir tela principal. ",IF(ISERROR(INDEX(Telas!$I$6:$I$105,MATCH(K21,Telas!$A$6:$A$105,0))*1),"Precio o peso por metro de "&K21&". ",""))&IF(AND(N(T21)>0,L21=""),"Elegir Tela 2. ",IF(AND(N(T21)>0,ISERROR(INDEX(Telas!$I$6:$I$105,MATCH(L21,Telas!$A$6:$A$105,0))*1)),"Precio o peso por metro de "&L21&". ",""))&IF(Y21="","Metros impresos. ","")&IF(F21="","Tipo de confección. ",IF(AB21="","Precio de confección. ","")))) -> Consumo tela principal (Despiece o Mediciones). Consumo Tela 2. Elegir tela principal. Metros impresos. | AH21: Confección sugerida por el tipo de molde: confirmar. Falta ficha de corte.
A22: 17 · FUTMUJU02 | B22: Fútbol, raglán, cuello redondo | C22: Fútbol | D22: Camiseta | E22: Femenino | F22: Camiseta Futbol Molde 2026 (Raglan) | O22: =IF($A22="","",IF(COUNTIFS(Despiece!$A$6:$A$705,$A22,Despiece!$D$6:$D$705,"Tela principal",Despiece!$F$6:$F$705,">0")=0,"",SUMIFS(Despiece!$F$6:$F$705,Despiece!$A$6:$A$705,$A22,Despiece!$D$6:$D$705,"Tela principal"))) | P22: =IF($A22="","",IFERROR(AVERAGEIFS(Mediciones!$K$6:$K$305,Mediciones!$C$6:$C$305,$A22,Mediciones!$D$6:$D$305,"Tela principal"),"")) | Q22: =IF($A22="","",IF(N(IF($N22="Despiece",IF(ISNUMBER(O22),O22*(1+Parametros!$B$22),IF(COUNTIFS(Despiece!$A$6:$A$705,$A22,Despiece!$D$6:$D$705,"Tela principal")>0,"",0)),IF($N22="Medición real",IF(ISNUMBER(P22),P22,IF(COUNTIFS(Mediciones!$C$6:$C$305,$A22,Mediciones!$D$6:$D$305,"Tela principal")>0,"",0)),IF(ISNUMBER(P22),P22,IF(ISNUMBER(O22),O22*(1+Parametros!$B$22),IF(OR(COUNTIFS(Despiece!$A$6:$A$705,$A22,Despiece!$D$6:$D$705,"Tela principal")>0,COUNTIFS(Mediciones!$C$6:$C$305,$A22,Mediciones!$D$6:$D$305,"Tela principal")>0),"",0))))))=0,"",IF($N22="Despiece",IF(ISNUMBER(O22),O22*(1+Parametros!$B$22),IF(COUNTIFS(Despiece!$A$6:$A$705,$A22,Despiece!$D$6:$D$705,"Tela principal")>0,"",0)),IF($N22="Medición real",IF(ISNUMBER(P22),P22,IF(COUNTIFS(Mediciones!$C$6:$C$305,$A22,Mediciones!$D$6:$D$305,"Tela principal")>0,"",0)),IF(ISNUMBER(P22),P22,IF(ISNUMBER(O22),O22*(1+Parametros!$B$22),IF(OR(COUNTIFS(Despiece!$A$6:$A$705,$A22,Despiece!$D$6:$D$705,"Tela principal")>0,COUNTIFS(Mediciones!$C$6:$C$305,$A22,Mediciones!$D$6:$D$305,"Tela principal")>0),"",0))))))) | R22: =IF($A22="","",IF(COUNTIFS(Despiece!$A$6:$A$705,$A22,Despiece!$D$6:$D$705,"Tela 2",Despiece!$F$6:$F$705,">0")=0,"",SUMIFS(Despiece!$F$6:$F$705,Despiece!$A$6:$A$705,$A22,Despiece!$D$6:$D$705,"Tela 2"))) | S22: =IF($A22="","",IFERROR(AVERAGEIFS(Mediciones!$K$6:$K$305,Mediciones!$C$6:$C$305,$A22,Mediciones!$D$6:$D$305,"Tela 2"),"")) | T22: =IF($A22="","",IF($N22="Despiece",IF(ISNUMBER(R22),R22*(1+Parametros!$B$22),IF(COUNTIFS(Despiece!$A$6:$A$705,$A22,Despiece!$D$6:$D$705,"Tela 2")>0,"",0)),IF($N22="Medición real",IF(ISNUMBER(S22),S22,IF(COUNTIFS(Mediciones!$C$6:$C$305,$A22,Mediciones!$D$6:$D$305,"Tela 2")>0,"",0)),IF(ISNUMBER(S22),S22,IF(ISNUMBER(R22),R22*(1+Parametros!$B$22),IF(OR(COUNTIFS(Despiece!$A$6:$A$705,$A22,Despiece!$D$6:$D$705,"Tela 2")>0,COUNTIFS(Mediciones!$C$6:$C$305,$A22,Mediciones!$D$6:$D$305,"Tela 2")>0),"",0)))))) -> 0 | U22: =IF($A22="","",IF(COUNTIFS(Despiece!$A$6:$A$705,$A22,Despiece!$D$6:$D$705,"Tela 3",Despiece!$F$6:$F$705,">0")=0,"",SUMIFS(Despiece!$F$6:$F$705,Despiece!$A$6:$A$705,$A22,Despiece!$D$6:$D$705,"Tela 3"))) | V22: =IF($A22="","",IFERROR(AVERAGEIFS(Mediciones!$K$6:$K$305,Mediciones!$C$6:$C$305,$A22,Mediciones!$D$6:$D$305,"Tela 3"),"")) | W22: =IF($A22="","",IF($N22="Despiece",IF(ISNUMBER(U22),U22*(1+Parametros!$B$22),IF(COUNTIFS(Despiece!$A$6:$A$705,$A22,Despiece!$D$6:$D$705,"Tela 3")>0,"",0)),IF($N22="Medición real",IF(ISNUMBER(V22),V22,IF(COUNTIFS(Mediciones!$C$6:$C$305,$A22,Mediciones!$D$6:$D$305,"Tela 3")>0,"",0)),IF(ISNUMBER(V22),V22,IF(ISNUMBER(U22),U22*(1+Parametros!$B$22),IF(OR(COUNTIFS(Despiece!$A$6:$A$705,$A22,Despiece!$D$6:$D$705,"Tela 3")>0,COUNTIFS(Mediciones!$C$6:$C$305,$A22,Mediciones!$D$6:$D$305,"Tela 3")>0),"",0)))))) -> 0 | Y22: =IF($A22="","",IF(ISNUMBER(X22),X22,IF(COUNTIFS(Despiece!$A$6:$A$705,$A22,Despiece!$E$6:$E$705,"Sublimada",Despiece!$F$6:$F$705,">0")>0,SUMIFS(Despiece!$F$6:$F$705,Despiece!$A$6:$A$705,$A22,Despiece!$E$6:$E$705,"Sublimada")*(1+Parametros!$B$22),IF(COUNTIFS(Despiece!$A$6:$A$705,$A22,Despiece!$E$6:$E$705,"Sublimada")=0,0,"")))) | Z22: =IF($A22="","",IFERROR(IF(ISNUMBER(Q22),IF(Q22=0,0,Q22*INDEX(Telas!$I$6:$I$105,MATCH(K22,Telas!$A$6:$A$105,0))),NA())+IF(ISNUMBER(T22),IF(T22=0,0,T22*INDEX(Telas!$I$6:$I$105,MATCH(L22,Telas!$A$6:$A$105,0))),NA())+IF(ISNUMBER(W22),IF(W22=0,0,W22*INDEX(Telas!$I$6:$I$105,MATCH(IF(M22="",K22,M22),Telas!$A$6:$A$105,0))),NA()),"")) | AA22: =IF($A22="","",IF(ISNUMBER(Y22),Y22*Parametros!$B$19,"")) | AB22: =IF(OR($A22="",F22=""),"",IFERROR(INDEX(Confeccion!$B$6:$B$125,MATCH(F22,Confeccion!$A$6:$A$125,0)),"")) -> 2300 | AC22: =IF($A22="","",IFERROR(N(H22)*IF(G22="",0,INDEX(Avios!$C$6:$C$65,MATCH(G22,Avios!$A$6:$A$65,0)))+N(J22)*IF(I22="",0,INDEX(Avios!$C$6:$C$65,MATCH(I22,Avios!$A$6:$A$65,0))),"")) -> 0 | AD22: =IF($A22="","",IFERROR(Z22+AA22+AB22+AC22,"")) | AE22: =IF(ISNUMBER(AD22),AD22*Parametros!$B$12,"") | AF22: =IF(AND(ISNUMBER(Q22),K22<>""),IFERROR(1/(Q22*INDEX(Telas!$G$6:$G$105,MATCH(K22,Telas!$A$6:$A$105,0))),""),"") | AG22: =IF($A22="","",IF(ISNUMBER(AD22),IF(AND(N(Y22)>0,N(Parametros!$B$19)=0),"Lista, pero sin costo de impresión (Parametros)","Lista"),IF(Q22="","Consumo tela principal (Despiece o Mediciones). ","")&IF(COUNTIFS(Mediciones!$C$6:$C$305,$A22,Mediciones!$K$6:$K$305,"")>0,"Pesar 1 m de la tela medida (Telas, kg por metro). ","")&IF(T22="","Consumo Tela 2. ","")&IF(W22="","Consumo Tela 3. ","")&IF(K22="","Elegir tela principal. ",IF(ISERROR(INDEX(Telas!$I$6:$I$105,MATCH(K22,Telas!$A$6:$A$105,0))*1),"Precio o peso por metro de "&K22&". ",""))&IF(AND(N(T22)>0,L22=""),"Elegir Tela 2. ",IF(AND(N(T22)>0,ISERROR(INDEX(Telas!$I$6:$I$105,MATCH(L22,Telas!$A$6:$A$105,0))*1)),"Precio o peso por metro de "&L22&". ",""))&IF(Y22="","Metros impresos. ","")&IF(F22="","Tipo de confección. ",IF(AB22="","Precio de confección. ","")))) -> Consumo tela principal (Despiece o Mediciones). Elegir tela principal. Metros impresos. | AH22: Confección sugerida por el tipo de molde: confirmar. Falta ficha de corte.
A23: 18 · FUTHOMU02 | B23: Fútbol, raglán, cuello redondo | C23: Fútbol | D23: Camiseta | E23: Masculino | F23: Camiseta Futbol Molde 2026 (Raglan) | O23: =IF($A23="","",IF(COUNTIFS(Despiece!$A$6:$A$705,$A23,Despiece!$D$6:$D$705,"Tela principal",Despiece!$F$6:$F$705,">0")=0,"",SUMIFS(Despiece!$F$6:$F$705,Despiece!$A$6:$A$705,$A23,Despiece!$D$6:$D$705,"Tela principal"))) | P23: =IF($A23="","",IFERROR(AVERAGEIFS(Mediciones!$K$6:$K$305,Mediciones!$C$6:$C$305,$A23,Mediciones!$D$6:$D$305,"Tela principal"),"")) | Q23: =IF($A23="","",IF(N(IF($N23="Despiece",IF(ISNUMBER(O23),O23*(1+Parametros!$B$22),IF(COUNTIFS(Despiece!$A$6:$A$705,$A23,Despiece!$D$6:$D$705,"Tela principal")>0,"",0)),IF($N23="Medición real",IF(ISNUMBER(P23),P23,IF(COUNTIFS(Mediciones!$C$6:$C$305,$A23,Mediciones!$D$6:$D$305,"Tela principal")>0,"",0)),IF(ISNUMBER(P23),P23,IF(ISNUMBER(O23),O23*(1+Parametros!$B$22),IF(OR(COUNTIFS(Despiece!$A$6:$A$705,$A23,Despiece!$D$6:$D$705,"Tela principal")>0,COUNTIFS(Mediciones!$C$6:$C$305,$A23,Mediciones!$D$6:$D$305,"Tela principal")>0),"",0))))))=0,"",IF($N23="Despiece",IF(ISNUMBER(O23),O23*(1+Parametros!$B$22),IF(COUNTIFS(Despiece!$A$6:$A$705,$A23,Despiece!$D$6:$D$705,"Tela principal")>0,"",0)),IF($N23="Medición real",IF(ISNUMBER(P23),P23,IF(COUNTIFS(Mediciones!$C$6:$C$305,$A23,Mediciones!$D$6:$D$305,"Tela principal")>0,"",0)),IF(ISNUMBER(P23),P23,IF(ISNUMBER(O23),O23*(1+Parametros!$B$22),IF(OR(COUNTIFS(Despiece!$A$6:$A$705,$A23,Despiece!$D$6:$D$705,"Tela principal")>0,COUNTIFS(Mediciones!$C$6:$C$305,$A23,Mediciones!$D$6:$D$305,"Tela principal")>0),"",0))))))) | R23: =IF($A23="","",IF(COUNTIFS(Despiece!$A$6:$A$705,$A23,Despiece!$D$6:$D$705,"Tela 2",Despiece!$F$6:$F$705,">0")=0,"",SUMIFS(Despiece!$F$6:$F$705,Despiece!$A$6:$A$705,$A23,Despiece!$D$6:$D$705,"Tela 2"))) | S23: =IF($A23="","",IFERROR(AVERAGEIFS(Mediciones!$K$6:$K$305,Mediciones!$C$6:$C$305,$A23,Mediciones!$D$6:$D$305,"Tela 2"),"")) | T23: =IF($A23="","",IF($N23="Despiece",IF(ISNUMBER(R23),R23*(1+Parametros!$B$22),IF(COUNTIFS(Despiece!$A$6:$A$705,$A23,Despiece!$D$6:$D$705,"Tela 2")>0,"",0)),IF($N23="Medición real",IF(ISNUMBER(S23),S23,IF(COUNTIFS(Mediciones!$C$6:$C$305,$A23,Mediciones!$D$6:$D$305,"Tela 2")>0,"",0)),IF(ISNUMBER(S23),S23,IF(ISNUMBER(R23),R23*(1+Parametros!$B$22),IF(OR(COUNTIFS(Despiece!$A$6:$A$705,$A23,Despiece!$D$6:$D$705,"Tela 2")>0,COUNTIFS(Mediciones!$C$6:$C$305,$A23,Mediciones!$D$6:$D$305,"Tela 2")>0),"",0)))))) -> 0 | U23: =IF($A23="","",IF(COUNTIFS(Despiece!$A$6:$A$705,$A23,Despiece!$D$6:$D$705,"Tela 3",Despiece!$F$6:$F$705,">0")=0,"",SUMIFS(Despiece!$F$6:$F$705,Despiece!$A$6:$A$705,$A23,Despiece!$D$6:$D$705,"Tela 3"))) | V23: =IF($A23="","",IFERROR(AVERAGEIFS(Mediciones!$K$6:$K$305,Mediciones!$C$6:$C$305,$A23,Mediciones!$D$6:$D$305,"Tela 3"),"")) | W23: =IF($A23="","",IF($N23="Despiece",IF(ISNUMBER(U23),U23*(1+Parametros!$B$22),IF(COUNTIFS(Despiece!$A$6:$A$705,$A23,Despiece!$D$6:$D$705,"Tela 3")>0,"",0)),IF($N23="Medición real",IF(ISNUMBER(V23),V23,IF(COUNTIFS(Mediciones!$C$6:$C$305,$A23,Mediciones!$D$6:$D$305,"Tela 3")>0,"",0)),IF(ISNUMBER(V23),V23,IF(ISNUMBER(U23),U23*(1+Parametros!$B$22),IF(OR(COUNTIFS(Despiece!$A$6:$A$705,$A23,Despiece!$D$6:$D$705,"Tela 3")>0,COUNTIFS(Mediciones!$C$6:$C$305,$A23,Mediciones!$D$6:$D$305,"Tela 3")>0),"",0)))))) -> 0 | Y23: =IF($A23="","",IF(ISNUMBER(X23),X23,IF(COUNTIFS(Despiece!$A$6:$A$705,$A23,Despiece!$E$6:$E$705,"Sublimada",Despiece!$F$6:$F$705,">0")>0,SUMIFS(Despiece!$F$6:$F$705,Despiece!$A$6:$A$705,$A23,Despiece!$E$6:$E$705,"Sublimada")*(1+Parametros!$B$22),IF(COUNTIFS(Despiece!$A$6:$A$705,$A23,Despiece!$E$6:$E$705,"Sublimada")=0,0,"")))) | Z23: =IF($A23="","",IFERROR(IF(ISNUMBER(Q23),IF(Q23=0,0,Q23*INDEX(Telas!$I$6:$I$105,MATCH(K23,Telas!$A$6:$A$105,0))),NA())+IF(ISNUMBER(T23),IF(T23=0,0,T23*INDEX(Telas!$I$6:$I$105,MATCH(L23,Telas!$A$6:$A$105,0))),NA())+IF(ISNUMBER(W23),IF(W23=0,0,W23*INDEX(Telas!$I$6:$I$105,MATCH(IF(M23="",K23,M23),Telas!$A$6:$A$105,0))),NA()),"")) | AA23: =IF($A23="","",IF(ISNUMBER(Y23),Y23*Parametros!$B$19,"")) | AB23: =IF(OR($A23="",F23=""),"",IFERROR(INDEX(Confeccion!$B$6:$B$125,MATCH(F23,Confeccion!$A$6:$A$125,0)),"")) -> 2300 | AC23: =IF($A23="","",IFERROR(N(H23)*IF(G23="",0,INDEX(Avios!$C$6:$C$65,MATCH(G23,Avios!$A$6:$A$65,0)))+N(J23)*IF(I23="",0,INDEX(Avios!$C$6:$C$65,MATCH(I23,Avios!$A$6:$A$65,0))),"")) -> 0 | AD23: =IF($A23="","",IFERROR(Z23+AA23+AB23+AC23,"")) | AE23: =IF(ISNUMBER(AD23),AD23*Parametros!$B$12,"") | AF23: =IF(AND(ISNUMBER(Q23),K23<>""),IFERROR(1/(Q23*INDEX(Telas!$G$6:$G$105,MATCH(K23,Telas!$A$6:$A$105,0))),""),"") | AG23: =IF($A23="","",IF(ISNUMBER(AD23),IF(AND(N(Y23)>0,N(Parametros!$B$19)=0),"Lista, pero sin costo de impresión (Parametros)","Lista"),IF(Q23="","Consumo tela principal (Despiece o Mediciones). ","")&IF(COUNTIFS(Mediciones!$C$6:$C$305,$A23,Mediciones!$K$6:$K$305,"")>0,"Pesar 1 m de la tela medida (Telas, kg por metro). ","")&IF(T23="","Consumo Tela 2. ","")&IF(W23="","Consumo Tela 3. ","")&IF(K23="","Elegir tela principal. ",IF(ISERROR(INDEX(Telas!$I$6:$I$105,MATCH(K23,Telas!$A$6:$A$105,0))*1),"Precio o peso por metro de "&K23&". ",""))&IF(AND(N(T23)>0,L23=""),"Elegir Tela 2. ",IF(AND(N(T23)>0,ISERROR(INDEX(Telas!$I$6:$I$105,MATCH(L23,Telas!$A$6:$A$105,0))*1)),"Precio o peso por metro de "&L23&". ",""))&IF(Y23="","Metros impresos. ","")&IF(F23="","Tipo de confección. ",IF(AB23="","Precio de confección. ","")))) -> Consumo tela principal (Despiece o Mediciones). Elegir tela principal. Metros impresos. | AH23: Confección sugerida por el tipo de molde: confirmar. Falta ficha de corte.
A24: 19 · FUTINMUJU02 | B24: Fútbol infantil, raglán, cuello redondo | C24: Fútbol | D24: Camiseta | E24: Infantil Femenino | F24: Camiseta Futbol Molde 2026 (Raglan) | O24: =IF($A24="","",IF(COUNTIFS(Despiece!$A$6:$A$705,$A24,Despiece!$D$6:$D$705,"Tela principal",Despiece!$F$6:$F$705,">0")=0,"",SUMIFS(Despiece!$F$6:$F$705,Despiece!$A$6:$A$705,$A24,Despiece!$D$6:$D$705,"Tela principal"))) | P24: =IF($A24="","",IFERROR(AVERAGEIFS(Mediciones!$K$6:$K$305,Mediciones!$C$6:$C$305,$A24,Mediciones!$D$6:$D$305,"Tela principal"),"")) | Q24: =IF($A24="","",IF(N(IF($N24="Despiece",IF(ISNUMBER(O24),O24*(1+Parametros!$B$22),IF(COUNTIFS(Despiece!$A$6:$A$705,$A24,Despiece!$D$6:$D$705,"Tela principal")>0,"",0)),IF($N24="Medición real",IF(ISNUMBER(P24),P24,IF(COUNTIFS(Mediciones!$C$6:$C$305,$A24,Mediciones!$D$6:$D$305,"Tela principal")>0,"",0)),IF(ISNUMBER(P24),P24,IF(ISNUMBER(O24),O24*(1+Parametros!$B$22),IF(OR(COUNTIFS(Despiece!$A$6:$A$705,$A24,Despiece!$D$6:$D$705,"Tela principal")>0,COUNTIFS(Mediciones!$C$6:$C$305,$A24,Mediciones!$D$6:$D$305,"Tela principal")>0),"",0))))))=0,"",IF($N24="Despiece",IF(ISNUMBER(O24),O24*(1+Parametros!$B$22),IF(COUNTIFS(Despiece!$A$6:$A$705,$A24,Despiece!$D$6:$D$705,"Tela principal")>0,"",0)),IF($N24="Medición real",IF(ISNUMBER(P24),P24,IF(COUNTIFS(Mediciones!$C$6:$C$305,$A24,Mediciones!$D$6:$D$305,"Tela principal")>0,"",0)),IF(ISNUMBER(P24),P24,IF(ISNUMBER(O24),O24*(1+Parametros!$B$22),IF(OR(COUNTIFS(Despiece!$A$6:$A$705,$A24,Despiece!$D$6:$D$705,"Tela principal")>0,COUNTIFS(Mediciones!$C$6:$C$305,$A24,Mediciones!$D$6:$D$305,"Tela principal")>0),"",0))))))) | R24: =IF($A24="","",IF(COUNTIFS(Despiece!$A$6:$A$705,$A24,Despiece!$D$6:$D$705,"Tela 2",Despiece!$F$6:$F$705,">0")=0,"",SUMIFS(Despiece!$F$6:$F$705,Despiece!$A$6:$A$705,$A24,Despiece!$D$6:$D$705,"Tela 2"))) | S24: =IF($A24="","",IFERROR(AVERAGEIFS(Mediciones!$K$6:$K$305,Mediciones!$C$6:$C$305,$A24,Mediciones!$D$6:$D$305,"Tela 2"),"")) | T24: =IF($A24="","",IF($N24="Despiece",IF(ISNUMBER(R24),R24*(1+Parametros!$B$22),IF(COUNTIFS(Despiece!$A$6:$A$705,$A24,Despiece!$D$6:$D$705,"Tela 2")>0,"",0)),IF($N24="Medición real",IF(ISNUMBER(S24),S24,IF(COUNTIFS(Mediciones!$C$6:$C$305,$A24,Mediciones!$D$6:$D$305,"Tela 2")>0,"",0)),IF(ISNUMBER(S24),S24,IF(ISNUMBER(R24),R24*(1+Parametros!$B$22),IF(OR(COUNTIFS(Despiece!$A$6:$A$705,$A24,Despiece!$D$6:$D$705,"Tela 2")>0,COUNTIFS(Mediciones!$C$6:$C$305,$A24,Mediciones!$D$6:$D$305,"Tela 2")>0),"",0)))))) -> 0 | U24: =IF($A24="","",IF(COUNTIFS(Despiece!$A$6:$A$705,$A24,Despiece!$D$6:$D$705,"Tela 3",Despiece!$F$6:$F$705,">0")=0,"",SUMIFS(Despiece!$F$6:$F$705,Despiece!$A$6:$A$705,$A24,Despiece!$D$6:$D$705,"Tela 3"))) | V24: =IF($A24="","",IFERROR(AVERAGEIFS(Mediciones!$K$6:$K$305,Mediciones!$C$6:$C$305,$A24,Mediciones!$D$6:$D$305,"Tela 3"),"")) | W24: =IF($A24="","",IF($N24="Despiece",IF(ISNUMBER(U24),U24*(1+Parametros!$B$22),IF(COUNTIFS(Despiece!$A$6:$A$705,$A24,Despiece!$D$6:$D$705,"Tela 3")>0,"",0)),IF($N24="Medición real",IF(ISNUMBER(V24),V24,IF(COUNTIFS(Mediciones!$C$6:$C$305,$A24,Mediciones!$D$6:$D$305,"Tela 3")>0,"",0)),IF(ISNUMBER(V24),V24,IF(ISNUMBER(U24),U24*(1+Parametros!$B$22),IF(OR(COUNTIFS(Despiece!$A$6:$A$705,$A24,Despiece!$D$6:$D$705,"Tela 3")>0,COUNTIFS(Mediciones!$C$6:$C$305,$A24,Mediciones!$D$6:$D$305,"Tela 3")>0),"",0)))))) -> 0 | Y24: =IF($A24="","",IF(ISNUMBER(X24),X24,IF(COUNTIFS(Despiece!$A$6:$A$705,$A24,Despiece!$E$6:$E$705,"Sublimada",Despiece!$F$6:$F$705,">0")>0,SUMIFS(Despiece!$F$6:$F$705,Despiece!$A$6:$A$705,$A24,Despiece!$E$6:$E$705,"Sublimada")*(1+Parametros!$B$22),IF(COUNTIFS(Despiece!$A$6:$A$705,$A24,Despiece!$E$6:$E$705,"Sublimada")=0,0,"")))) | Z24: =IF($A24="","",IFERROR(IF(ISNUMBER(Q24),IF(Q24=0,0,Q24*INDEX(Telas!$I$6:$I$105,MATCH(K24,Telas!$A$6:$A$105,0))),NA())+IF(ISNUMBER(T24),IF(T24=0,0,T24*INDEX(Telas!$I$6:$I$105,MATCH(L24,Telas!$A$6:$A$105,0))),NA())+IF(ISNUMBER(W24),IF(W24=0,0,W24*INDEX(Telas!$I$6:$I$105,MATCH(IF(M24="",K24,M24),Telas!$A$6:$A$105,0))),NA()),"")) | AA24: =IF($A24="","",IF(ISNUMBER(Y24),Y24*Parametros!$B$19,"")) | AB24: =IF(OR($A24="",F24=""),"",IFERROR(INDEX(Confeccion!$B$6:$B$125,MATCH(F24,Confeccion!$A$6:$A$125,0)),"")) -> 2300 | AC24: =IF($A24="","",IFERROR(N(H24)*IF(G24="",0,INDEX(Avios!$C$6:$C$65,MATCH(G24,Avios!$A$6:$A$65,0)))+N(J24)*IF(I24="",0,INDEX(Avios!$C$6:$C$65,MATCH(I24,Avios!$A$6:$A$65,0))),"")) -> 0 | AD24: =IF($A24="","",IFERROR(Z24+AA24+AB24+AC24,"")) | AE24: =IF(ISNUMBER(AD24),AD24*Parametros!$B$12,"") | AF24: =IF(AND(ISNUMBER(Q24),K24<>""),IFERROR(1/(Q24*INDEX(Telas!$G$6:$G$105,MATCH(K24,Telas!$A$6:$A$105,0))),""),"") | AG24: =IF($A24="","",IF(ISNUMBER(AD24),IF(AND(N(Y24)>0,N(Parametros!$B$19)=0),"Lista, pero sin costo de impresión (Parametros)","Lista"),IF(Q24="","Consumo tela principal (Despiece o Mediciones). ","")&IF(COUNTIFS(Mediciones!$C$6:$C$305,$A24,Mediciones!$K$6:$K$305,"")>0,"Pesar 1 m de la tela medida (Telas, kg por metro). ","")&IF(T24="","Consumo Tela 2. ","")&IF(W24="","Consumo Tela 3. ","")&IF(K24="","Elegir tela principal. ",IF(ISERROR(INDEX(Telas!$I$6:$I$105,MATCH(K24,Telas!$A$6:$A$105,0))*1),"Precio o peso por metro de "&K24&". ",""))&IF(AND(N(T24)>0,L24=""),"Elegir Tela 2. ",IF(AND(N(T24)>0,ISERROR(INDEX(Telas!$I$6:$I$105,MATCH(L24,Telas!$A$6:$A$105,0))*1)),"Precio o peso por metro de "&L24&". ",""))&IF(Y24="","Metros impresos. ","")&IF(F24="","Tipo de confección. ",IF(AB24="","Precio de confección. ","")))) -> Consumo tela principal (Despiece o Mediciones). Elegir tela principal. Metros impresos. | AH24: Confección sugerida por el tipo de molde: confirmar. Falta ficha de corte.
A25: 20 · FUTINHOMU02 | B25: Fútbol infantil, raglán, cuello redondo | C25: Fútbol | D25: Camiseta | E25: Infantil Masculino | F25: Camiseta Futbol Molde 2026 (Raglan) | O25: =IF($A25="","",IF(COUNTIFS(Despiece!$A$6:$A$705,$A25,Despiece!$D$6:$D$705,"Tela principal",Despiece!$F$6:$F$705,">0")=0,"",SUMIFS(Despiece!$F$6:$F$705,Despiece!$A$6:$A$705,$A25,Despiece!$D$6:$D$705,"Tela principal"))) | P25: =IF($A25="","",IFERROR(AVERAGEIFS(Mediciones!$K$6:$K$305,Mediciones!$C$6:$C$305,$A25,Mediciones!$D$6:$D$305,"Tela principal"),"")) | Q25: =IF($A25="","",IF(N(IF($N25="Despiece",IF(ISNUMBER(O25),O25*(1+Parametros!$B$22),IF(COUNTIFS(Despiece!$A$6:$A$705,$A25,Despiece!$D$6:$D$705,"Tela principal")>0,"",0)),IF($N25="Medición real",IF(ISNUMBER(P25),P25,IF(COUNTIFS(Mediciones!$C$6:$C$305,$A25,Mediciones!$D$6:$D$305,"Tela principal")>0,"",0)),IF(ISNUMBER(P25),P25,IF(ISNUMBER(O25),O25*(1+Parametros!$B$22),IF(OR(COUNTIFS(Despiece!$A$6:$A$705,$A25,Despiece!$D$6:$D$705,"Tela principal")>0,COUNTIFS(Mediciones!$C$6:$C$305,$A25,Mediciones!$D$6:$D$305,"Tela principal")>0),"",0))))))=0,"",IF($N25="Despiece",IF(ISNUMBER(O25),O25*(1+Parametros!$B$22),IF(COUNTIFS(Despiece!$A$6:$A$705,$A25,Despiece!$D$6:$D$705,"Tela principal")>0,"",0)),IF($N25="Medición real",IF(ISNUMBER(P25),P25,IF(COUNTIFS(Mediciones!$C$6:$C$305,$A25,Mediciones!$D$6:$D$305,"Tela principal")>0,"",0)),IF(ISNUMBER(P25),P25,IF(ISNUMBER(O25),O25*(1+Parametros!$B$22),IF(OR(COUNTIFS(Despiece!$A$6:$A$705,$A25,Despiece!$D$6:$D$705,"Tela principal")>0,COUNTIFS(Mediciones!$C$6:$C$305,$A25,Mediciones!$D$6:$D$305,"Tela principal")>0),"",0))))))) | R25: =IF($A25="","",IF(COUNTIFS(Despiece!$A$6:$A$705,$A25,Despiece!$D$6:$D$705,"Tela 2",Despiece!$F$6:$F$705,">0")=0,"",SUMIFS(Despiece!$F$6:$F$705,Despiece!$A$6:$A$705,$A25,Despiece!$D$6:$D$705,"Tela 2"))) | S25: =IF($A25="","",IFERROR(AVERAGEIFS(Mediciones!$K$6:$K$305,Mediciones!$C$6:$C$305,$A25,Mediciones!$D$6:$D$305,"Tela 2"),"")) | T25: =IF($A25="","",IF($N25="Despiece",IF(ISNUMBER(R25),R25*(1+Parametros!$B$22),IF(COUNTIFS(Despiece!$A$6:$A$705,$A25,Despiece!$D$6:$D$705,"Tela 2")>0,"",0)),IF($N25="Medición real",IF(ISNUMBER(S25),S25,IF(COUNTIFS(Mediciones!$C$6:$C$305,$A25,Mediciones!$D$6:$D$305,"Tela 2")>0,"",0)),IF(ISNUMBER(S25),S25,IF(ISNUMBER(R25),R25*(1+Parametros!$B$22),IF(OR(COUNTIFS(Despiece!$A$6:$A$705,$A25,Despiece!$D$6:$D$705,"Tela 2")>0,COUNTIFS(Mediciones!$C$6:$C$305,$A25,Mediciones!$D$6:$D$305,"Tela 2")>0),"",0)))))) -> 0 | U25: =IF($A25="","",IF(COUNTIFS(Despiece!$A$6:$A$705,$A25,Despiece!$D$6:$D$705,"Tela 3",Despiece!$F$6:$F$705,">0")=0,"",SUMIFS(Despiece!$F$6:$F$705,Despiece!$A$6:$A$705,$A25,Despiece!$D$6:$D$705,"Tela 3"))) | V25: =IF($A25="","",IFERROR(AVERAGEIFS(Mediciones!$K$6:$K$305,Mediciones!$C$6:$C$305,$A25,Mediciones!$D$6:$D$305,"Tela 3"),"")) | W25: =IF($A25="","",IF($N25="Despiece",IF(ISNUMBER(U25),U25*(1+Parametros!$B$22),IF(COUNTIFS(Despiece!$A$6:$A$705,$A25,Despiece!$D$6:$D$705,"Tela 3")>0,"",0)),IF($N25="Medición real",IF(ISNUMBER(V25),V25,IF(COUNTIFS(Mediciones!$C$6:$C$305,$A25,Mediciones!$D$6:$D$305,"Tela 3")>0,"",0)),IF(ISNUMBER(V25),V25,IF(ISNUMBER(U25),U25*(1+Parametros!$B$22),IF(OR(COUNTIFS(Despiece!$A$6:$A$705,$A25,Despiece!$D$6:$D$705,"Tela 3")>0,COUNTIFS(Mediciones!$C$6:$C$305,$A25,Mediciones!$D$6:$D$305,"Tela 3")>0),"",0)))))) -> 0 | Y25: =IF($A25="","",IF(ISNUMBER(X25),X25,IF(COUNTIFS(Despiece!$A$6:$A$705,$A25,Despiece!$E$6:$E$705,"Sublimada",Despiece!$F$6:$F$705,">0")>0,SUMIFS(Despiece!$F$6:$F$705,Despiece!$A$6:$A$705,$A25,Despiece!$E$6:$E$705,"Sublimada")*(1+Parametros!$B$22),IF(COUNTIFS(Despiece!$A$6:$A$705,$A25,Despiece!$E$6:$E$705,"Sublimada")=0,0,"")))) | Z25: =IF($A25="","",IFERROR(IF(ISNUMBER(Q25),IF(Q25=0,0,Q25*INDEX(Telas!$I$6:$I$105,MATCH(K25,Telas!$A$6:$A$105,0))),NA())+IF(ISNUMBER(T25),IF(T25=0,0,T25*INDEX(Telas!$I$6:$I$105,MATCH(L25,Telas!$A$6:$A$105,0))),NA())+IF(ISNUMBER(W25),IF(W25=0,0,W25*INDEX(Telas!$I$6:$I$105,MATCH(IF(M25="",K25,M25),Telas!$A$6:$A$105,0))),NA()),"")) | AA25: =IF($A25="","",IF(ISNUMBER(Y25),Y25*Parametros!$B$19,"")) | AB25: =IF(OR($A25="",F25=""),"",IFERROR(INDEX(Confeccion!$B$6:$B$125,MATCH(F25,Confeccion!$A$6:$A$125,0)),"")) -> 2300 | AC25: =IF($A25="","",IFERROR(N(H25)*IF(G25="",0,INDEX(Avios!$C$6:$C$65,MATCH(G25,Avios!$A$6:$A$65,0)))+N(J25)*IF(I25="",0,INDEX(Avios!$C$6:$C$65,MATCH(I25,Avios!$A$6:$A$65,0))),"")) -> 0 | AD25: =IF($A25="","",IFERROR(Z25+AA25+AB25+AC25,"")) | AE25: =IF(ISNUMBER(AD25),AD25*Parametros!$B$12,"") | AF25: =IF(AND(ISNUMBER(Q25),K25<>""),IFERROR(1/(Q25*INDEX(Telas!$G$6:$G$105,MATCH(K25,Telas!$A$6:$A$105,0))),""),"") | AG25: =IF($A25="","",IF(ISNUMBER(AD25),IF(AND(N(Y25)>0,N(Parametros!$B$19)=0),"Lista, pero sin costo de impresión (Parametros)","Lista"),IF(Q25="","Consumo tela principal (Despiece o Mediciones). ","")&IF(COUNTIFS(Mediciones!$C$6:$C$305,$A25,Mediciones!$K$6:$K$305,"")>0,"Pesar 1 m de la tela medida (Telas, kg por metro). ","")&IF(T25="","Consumo Tela 2. ","")&IF(W25="","Consumo Tela 3. ","")&IF(K25="","Elegir tela principal. ",IF(ISERROR(INDEX(Telas!$I$6:$I$105,MATCH(K25,Telas!$A$6:$A$105,0))*1),"Precio o peso por metro de "&K25&". ",""))&IF(AND(N(T25)>0,L25=""),"Elegir Tela 2. ",IF(AND(N(T25)>0,ISERROR(INDEX(Telas!$I$6:$I$105,MATCH(L25,Telas!$A$6:$A$105,0))*1)),"Precio o peso por metro de "&L25&". ",""))&IF(Y25="","Metros impresos. ","")&IF(F25="","Tipo de confección. ",IF(AB25="","Precio de confección. ","")))) -> Consumo tela principal (Despiece o Mediciones). Elegir tela principal. Metros impresos. | AH25: Confección sugerida por el tipo de molde: confirmar. Falta ficha de corte.
A26: 21 · FUTMUJV02 | B26: Fútbol, raglán, cuello v | C26: Fútbol | D26: Camiseta | E26: Femenino | F26: Camiseta Futbol Molde 2026 (Raglan) | O26: =IF($A26="","",IF(COUNTIFS(Despiece!$A$6:$A$705,$A26,Despiece!$D$6:$D$705,"Tela principal",Despiece!$F$6:$F$705,">0")=0,"",SUMIFS(Despiece!$F$6:$F$705,Despiece!$A$6:$A$705,$A26,Despiece!$D$6:$D$705,"Tela principal"))) | P26: =IF($A26="","",IFERROR(AVERAGEIFS(Mediciones!$K$6:$K$305,Mediciones!$C$6:$C$305,$A26,Mediciones!$D$6:$D$305,"Tela principal"),"")) | Q26: =IF($A26="","",IF(N(IF($N26="Despiece",IF(ISNUMBER(O26),O26*(1+Parametros!$B$22),IF(COUNTIFS(Despiece!$A$6:$A$705,$A26,Despiece!$D$6:$D$705,"Tela principal")>0,"",0)),IF($N26="Medición real",IF(ISNUMBER(P26),P26,IF(COUNTIFS(Mediciones!$C$6:$C$305,$A26,Mediciones!$D$6:$D$305,"Tela principal")>0,"",0)),IF(ISNUMBER(P26),P26,IF(ISNUMBER(O26),O26*(1+Parametros!$B$22),IF(OR(COUNTIFS(Despiece!$A$6:$A$705,$A26,Despiece!$D$6:$D$705,"Tela principal")>0,COUNTIFS(Mediciones!$C$6:$C$305,$A26,Mediciones!$D$6:$D$305,"Tela principal")>0),"",0))))))=0,"",IF($N26="Despiece",IF(ISNUMBER(O26),O26*(1+Parametros!$B$22),IF(COUNTIFS(Despiece!$A$6:$A$705,$A26,Despiece!$D$6:$D$705,"Tela principal")>0,"",0)),IF($N26="Medición real",IF(ISNUMBER(P26),P26,IF(COUNTIFS(Mediciones!$C$6:$C$305,$A26,Mediciones!$D$6:$D$305,"Tela principal")>0,"",0)),IF(ISNUMBER(P26),P26,IF(ISNUMBER(O26),O26*(1+Parametros!$B$22),IF(OR(COUNTIFS(Despiece!$A$6:$A$705,$A26,Despiece!$D$6:$D$705,"Tela principal")>0,COUNTIFS(Mediciones!$C$6:$C$305,$A26,Mediciones!$D$6:$D$305,"Tela principal")>0),"",0))))))) | R26: =IF($A26="","",IF(COUNTIFS(Despiece!$A$6:$A$705,$A26,Despiece!$D$6:$D$705,"Tela 2",Despiece!$F$6:$F$705,">0")=0,"",SUMIFS(Despiece!$F$6:$F$705,Despiece!$A$6:$A$705,$A26,Despiece!$D$6:$D$705,"Tela 2"))) | S26: =IF($A26="","",IFERROR(AVERAGEIFS(Mediciones!$K$6:$K$305,Mediciones!$C$6:$C$305,$A26,Mediciones!$D$6:$D$305,"Tela 2"),"")) | T26: =IF($A26="","",IF($N26="Despiece",IF(ISNUMBER(R26),R26*(1+Parametros!$B$22),IF(COUNTIFS(Despiece!$A$6:$A$705,$A26,Despiece!$D$6:$D$705,"Tela 2")>0,"",0)),IF($N26="Medición real",IF(ISNUMBER(S26),S26,IF(COUNTIFS(Mediciones!$C$6:$C$305,$A26,Mediciones!$D$6:$D$305,"Tela 2")>0,"",0)),IF(ISNUMBER(S26),S26,IF(ISNUMBER(R26),R26*(1+Parametros!$B$22),IF(OR(COUNTIFS(Despiece!$A$6:$A$705,$A26,Despiece!$D$6:$D$705,"Tela 2")>0,COUNTIFS(Mediciones!$C$6:$C$305,$A26,Mediciones!$D$6:$D$305,"Tela 2")>0),"",0)))))) -> 0 | U26: =IF($A26="","",IF(COUNTIFS(Despiece!$A$6:$A$705,$A26,Despiece!$D$6:$D$705,"Tela 3",Despiece!$F$6:$F$705,">0")=0,"",SUMIFS(Despiece!$F$6:$F$705,Despiece!$A$6:$A$705,$A26,Despiece!$D$6:$D$705,"Tela 3"))) | V26: =IF($A26="","",IFERROR(AVERAGEIFS(Mediciones!$K$6:$K$305,Mediciones!$C$6:$C$305,$A26,Mediciones!$D$6:$D$305,"Tela 3"),"")) | W26: =IF($A26="","",IF($N26="Despiece",IF(ISNUMBER(U26),U26*(1+Parametros!$B$22),IF(COUNTIFS(Despiece!$A$6:$A$705,$A26,Despiece!$D$6:$D$705,"Tela 3")>0,"",0)),IF($N26="Medición real",IF(ISNUMBER(V26),V26,IF(COUNTIFS(Mediciones!$C$6:$C$305,$A26,Mediciones!$D$6:$D$305,"Tela 3")>0,"",0)),IF(ISNUMBER(V26),V26,IF(ISNUMBER(U26),U26*(1+Parametros!$B$22),IF(OR(COUNTIFS(Despiece!$A$6:$A$705,$A26,Despiece!$D$6:$D$705,"Tela 3")>0,COUNTIFS(Mediciones!$C$6:$C$305,$A26,Mediciones!$D$6:$D$305,"Tela 3")>0),"",0)))))) -> 0 | Y26: =IF($A26="","",IF(ISNUMBER(X26),X26,IF(COUNTIFS(Despiece!$A$6:$A$705,$A26,Despiece!$E$6:$E$705,"Sublimada",Despiece!$F$6:$F$705,">0")>0,SUMIFS(Despiece!$F$6:$F$705,Despiece!$A$6:$A$705,$A26,Despiece!$E$6:$E$705,"Sublimada")*(1+Parametros!$B$22),IF(COUNTIFS(Despiece!$A$6:$A$705,$A26,Despiece!$E$6:$E$705,"Sublimada")=0,0,"")))) | Z26: =IF($A26="","",IFERROR(IF(ISNUMBER(Q26),IF(Q26=0,0,Q26*INDEX(Telas!$I$6:$I$105,MATCH(K26,Telas!$A$6:$A$105,0))),NA())+IF(ISNUMBER(T26),IF(T26=0,0,T26*INDEX(Telas!$I$6:$I$105,MATCH(L26,Telas!$A$6:$A$105,0))),NA())+IF(ISNUMBER(W26),IF(W26=0,0,W26*INDEX(Telas!$I$6:$I$105,MATCH(IF(M26="",K26,M26),Telas!$A$6:$A$105,0))),NA()),"")) | AA26: =IF($A26="","",IF(ISNUMBER(Y26),Y26*Parametros!$B$19,"")) | AB26: =IF(OR($A26="",F26=""),"",IFERROR(INDEX(Confeccion!$B$6:$B$125,MATCH(F26,Confeccion!$A$6:$A$125,0)),"")) -> 2300 | AC26: =IF($A26="","",IFERROR(N(H26)*IF(G26="",0,INDEX(Avios!$C$6:$C$65,MATCH(G26,Avios!$A$6:$A$65,0)))+N(J26)*IF(I26="",0,INDEX(Avios!$C$6:$C$65,MATCH(I26,Avios!$A$6:$A$65,0))),"")) -> 0 | AD26: =IF($A26="","",IFERROR(Z26+AA26+AB26+AC26,"")) | AE26: =IF(ISNUMBER(AD26),AD26*Parametros!$B$12,"") | AF26: =IF(AND(ISNUMBER(Q26),K26<>""),IFERROR(1/(Q26*INDEX(Telas!$G$6:$G$105,MATCH(K26,Telas!$A$6:$A$105,0))),""),"") | AG26: =IF($A26="","",IF(ISNUMBER(AD26),IF(AND(N(Y26)>0,N(Parametros!$B$19)=0),"Lista, pero sin costo de impresión (Parametros)","Lista"),IF(Q26="","Consumo tela principal (Despiece o Mediciones). ","")&IF(COUNTIFS(Mediciones!$C$6:$C$305,$A26,Mediciones!$K$6:$K$305,"")>0,"Pesar 1 m de la tela medida (Telas, kg por metro). ","")&IF(T26="","Consumo Tela 2. ","")&IF(W26="","Consumo Tela 3. ","")&IF(K26="","Elegir tela principal. ",IF(ISERROR(INDEX(Telas!$I$6:$I$105,MATCH(K26,Telas!$A$6:$A$105,0))*1),"Precio o peso por metro de "&K26&". ",""))&IF(AND(N(T26)>0,L26=""),"Elegir Tela 2. ",IF(AND(N(T26)>0,ISERROR(INDEX(Telas!$I$6:$I$105,MATCH(L26,Telas!$A$6:$A$105,0))*1)),"Precio o peso por metro de "&L26&". ",""))&IF(Y26="","Metros impresos. ","")&IF(F26="","Tipo de confección. ",IF(AB26="","Precio de confección. ","")))) -> Consumo tela principal (Despiece o Mediciones). Elegir tela principal. Metros impresos. | AH26: Confección sugerida por el tipo de molde: confirmar. Falta ficha de corte.
A27: 22 · FUTHOMV02 | B27: Fútbol, raglán, cuello v | C27: Fútbol | D27: Camiseta | E27: Masculino | F27: Camiseta Futbol Molde 2026 (Raglan) | O27: =IF($A27="","",IF(COUNTIFS(Despiece!$A$6:$A$705,$A27,Despiece!$D$6:$D$705,"Tela principal",Despiece!$F$6:$F$705,">0")=0,"",SUMIFS(Despiece!$F$6:$F$705,Despiece!$A$6:$A$705,$A27,Despiece!$D$6:$D$705,"Tela principal"))) | P27: =IF($A27="","",IFERROR(AVERAGEIFS(Mediciones!$K$6:$K$305,Mediciones!$C$6:$C$305,$A27,Mediciones!$D$6:$D$305,"Tela principal"),"")) | Q27: =IF($A27="","",IF(N(IF($N27="Despiece",IF(ISNUMBER(O27),O27*(1+Parametros!$B$22),IF(COUNTIFS(Despiece!$A$6:$A$705,$A27,Despiece!$D$6:$D$705,"Tela principal")>0,"",0)),IF($N27="Medición real",IF(ISNUMBER(P27),P27,IF(COUNTIFS(Mediciones!$C$6:$C$305,$A27,Mediciones!$D$6:$D$305,"Tela principal")>0,"",0)),IF(ISNUMBER(P27),P27,IF(ISNUMBER(O27),O27*(1+Parametros!$B$22),IF(OR(COUNTIFS(Despiece!$A$6:$A$705,$A27,Despiece!$D$6:$D$705,"Tela principal")>0,COUNTIFS(Mediciones!$C$6:$C$305,$A27,Mediciones!$D$6:$D$305,"Tela principal")>0),"",0))))))=0,"",IF($N27="Despiece",IF(ISNUMBER(O27),O27*(1+Parametros!$B$22),IF(COUNTIFS(Despiece!$A$6:$A$705,$A27,Despiece!$D$6:$D$705,"Tela principal")>0,"",0)),IF($N27="Medición real",IF(ISNUMBER(P27),P27,IF(COUNTIFS(Mediciones!$C$6:$C$305,$A27,Mediciones!$D$6:$D$305,"Tela principal")>0,"",0)),IF(ISNUMBER(P27),P27,IF(ISNUMBER(O27),O27*(1+Parametros!$B$22),IF(OR(COUNTIFS(Despiece!$A$6:$A$705,$A27,Despiece!$D$6:$D$705,"Tela principal")>0,COUNTIFS(Mediciones!$C$6:$C$305,$A27,Mediciones!$D$6:$D$305,"Tela principal")>0),"",0))))))) | R27: =IF($A27="","",IF(COUNTIFS(Despiece!$A$6:$A$705,$A27,Despiece!$D$6:$D$705,"Tela 2",Despiece!$F$6:$F$705,">0")=0,"",SUMIFS(Despiece!$F$6:$F$705,Despiece!$A$6:$A$705,$A27,Despiece!$D$6:$D$705,"Tela 2"))) | S27: =IF($A27="","",IFERROR(AVERAGEIFS(Mediciones!$K$6:$K$305,Mediciones!$C$6:$C$305,$A27,Mediciones!$D$6:$D$305,"Tela 2"),"")) | T27: =IF($A27="","",IF($N27="Despiece",IF(ISNUMBER(R27),R27*(1+Parametros!$B$22),IF(COUNTIFS(Despiece!$A$6:$A$705,$A27,Despiece!$D$6:$D$705,"Tela 2")>0,"",0)),IF($N27="Medición real",IF(ISNUMBER(S27),S27,IF(COUNTIFS(Mediciones!$C$6:$C$305,$A27,Mediciones!$D$6:$D$305,"Tela 2")>0,"",0)),IF(ISNUMBER(S27),S27,IF(ISNUMBER(R27),R27*(1+Parametros!$B$22),IF(OR(COUNTIFS(Despiece!$A$6:$A$705,$A27,Despiece!$D$6:$D$705,"Tela 2")>0,COUNTIFS(Mediciones!$C$6:$C$305,$A27,Mediciones!$D$6:$D$305,"Tela 2")>0),"",0)))))) -> 0 | U27: =IF($A27="","",IF(COUNTIFS(Despiece!$A$6:$A$705,$A27,Despiece!$D$6:$D$705,"Tela 3",Despiece!$F$6:$F$705,">0")=0,"",SUMIFS(Despiece!$F$6:$F$705,Despiece!$A$6:$A$705,$A27,Despiece!$D$6:$D$705,"Tela 3"))) | V27: =IF($A27="","",IFERROR(AVERAGEIFS(Mediciones!$K$6:$K$305,Mediciones!$C$6:$C$305,$A27,Mediciones!$D$6:$D$305,"Tela 3"),"")) | W27: =IF($A27="","",IF($N27="Despiece",IF(ISNUMBER(U27),U27*(1+Parametros!$B$22),IF(COUNTIFS(Despiece!$A$6:$A$705,$A27,Despiece!$D$6:$D$705,"Tela 3")>0,"",0)),IF($N27="Medición real",IF(ISNUMBER(V27),V27,IF(COUNTIFS(Mediciones!$C$6:$C$305,$A27,Mediciones!$D$6:$D$305,"Tela 3")>0,"",0)),IF(ISNUMBER(V27),V27,IF(ISNUMBER(U27),U27*(1+Parametros!$B$22),IF(OR(COUNTIFS(Despiece!$A$6:$A$705,$A27,Despiece!$D$6:$D$705,"Tela 3")>0,COUNTIFS(Mediciones!$C$6:$C$305,$A27,Mediciones!$D$6:$D$305,"Tela 3")>0),"",0)))))) -> 0 | Y27: =IF($A27="","",IF(ISNUMBER(X27),X27,IF(COUNTIFS(Despiece!$A$6:$A$705,$A27,Despiece!$E$6:$E$705,"Sublimada",Despiece!$F$6:$F$705,">0")>0,SUMIFS(Despiece!$F$6:$F$705,Despiece!$A$6:$A$705,$A27,Despiece!$E$6:$E$705,"Sublimada")*(1+Parametros!$B$22),IF(COUNTIFS(Despiece!$A$6:$A$705,$A27,Despiece!$E$6:$E$705,"Sublimada")=0,0,"")))) | Z27: =IF($A27="","",IFERROR(IF(ISNUMBER(Q27),IF(Q27=0,0,Q27*INDEX(Telas!$I$6:$I$105,MATCH(K27,Telas!$A$6:$A$105,0))),NA())+IF(ISNUMBER(T27),IF(T27=0,0,T27*INDEX(Telas!$I$6:$I$105,MATCH(L27,Telas!$A$6:$A$105,0))),NA())+IF(ISNUMBER(W27),IF(W27=0,0,W27*INDEX(Telas!$I$6:$I$105,MATCH(IF(M27="",K27,M27),Telas!$A$6:$A$105,0))),NA()),"")) | AA27: =IF($A27="","",IF(ISNUMBER(Y27),Y27*Parametros!$B$19,"")) | AB27: =IF(OR($A27="",F27=""),"",IFERROR(INDEX(Confeccion!$B$6:$B$125,MATCH(F27,Confeccion!$A$6:$A$125,0)),"")) -> 2300 | AC27: =IF($A27="","",IFERROR(N(H27)*IF(G27="",0,INDEX(Avios!$C$6:$C$65,MATCH(G27,Avios!$A$6:$A$65,0)))+N(J27)*IF(I27="",0,INDEX(Avios!$C$6:$C$65,MATCH(I27,Avios!$A$6:$A$65,0))),"")) -> 0 | AD27: =IF($A27="","",IFERROR(Z27+AA27+AB27+AC27,"")) | AE27: =IF(ISNUMBER(AD27),AD27*Parametros!$B$12,"") | AF27: =IF(AND(ISNUMBER(Q27),K27<>""),IFERROR(1/(Q27*INDEX(Telas!$G$6:$G$105,MATCH(K27,Telas!$A$6:$A$105,0))),""),"") | AG27: =IF($A27="","",IF(ISNUMBER(AD27),IF(AND(N(Y27)>0,N(Parametros!$B$19)=0),"Lista, pero sin costo de impresión (Parametros)","Lista"),IF(Q27="","Consumo tela principal (Despiece o Mediciones). ","")&IF(COUNTIFS(Mediciones!$C$6:$C$305,$A27,Mediciones!$K$6:$K$305,"")>0,"Pesar 1 m de la tela medida (Telas, kg por metro). ","")&IF(T27="","Consumo Tela 2. ","")&IF(W27="","Consumo Tela 3. ","")&IF(K27="","Elegir tela principal. ",IF(ISERROR(INDEX(Telas!$I$6:$I$105,MATCH(K27,Telas!$A$6:$A$105,0))*1),"Precio o peso por metro de "&K27&". ",""))&IF(AND(N(T27)>0,L27=""),"Elegir Tela 2. ",IF(AND(N(T27)>0,ISERROR(INDEX(Telas!$I$6:$I$105,MATCH(L27,Telas!$A$6:$A$105,0))*1)),"Precio o peso por metro de "&L27&". ",""))&IF(Y27="","Metros impresos. ","")&IF(F27="","Tipo de confección. ",IF(AB27="","Precio de confección. ","")))) -> Consumo tela principal (Despiece o Mediciones). Elegir tela principal. Metros impresos. | AH27: Confección sugerida por el tipo de molde: confirmar. Falta ficha de corte.
A28: 23 · FUTINMUJV02 | B28: Fútbol infantil, raglán, cuello v | C28: Fútbol | D28: Camiseta | E28: Infantil Femenino | F28: Camiseta Futbol Molde 2026 (Raglan) | O28: =IF($A28="","",IF(COUNTIFS(Despiece!$A$6:$A$705,$A28,Despiece!$D$6:$D$705,"Tela principal",Despiece!$F$6:$F$705,">0")=0,"",SUMIFS(Despiece!$F$6:$F$705,Despiece!$A$6:$A$705,$A28,Despiece!$D$6:$D$705,"Tela principal"))) | P28: =IF($A28="","",IFERROR(AVERAGEIFS(Mediciones!$K$6:$K$305,Mediciones!$C$6:$C$305,$A28,Mediciones!$D$6:$D$305,"Tela principal"),"")) | Q28: =IF($A28="","",IF(N(IF($N28="Despiece",IF(ISNUMBER(O28),O28*(1+Parametros!$B$22),IF(COUNTIFS(Despiece!$A$6:$A$705,$A28,Despiece!$D$6:$D$705,"Tela principal")>0,"",0)),IF($N28="Medición real",IF(ISNUMBER(P28),P28,IF(COUNTIFS(Mediciones!$C$6:$C$305,$A28,Mediciones!$D$6:$D$305,"Tela principal")>0,"",0)),IF(ISNUMBER(P28),P28,IF(ISNUMBER(O28),O28*(1+Parametros!$B$22),IF(OR(COUNTIFS(Despiece!$A$6:$A$705,$A28,Despiece!$D$6:$D$705,"Tela principal")>0,COUNTIFS(Mediciones!$C$6:$C$305,$A28,Mediciones!$D$6:$D$305,"Tela principal")>0),"",0))))))=0,"",IF($N28="Despiece",IF(ISNUMBER(O28),O28*(1+Parametros!$B$22),IF(COUNTIFS(Despiece!$A$6:$A$705,$A28,Despiece!$D$6:$D$705,"Tela principal")>0,"",0)),IF($N28="Medición real",IF(ISNUMBER(P28),P28,IF(COUNTIFS(Mediciones!$C$6:$C$305,$A28,Mediciones!$D$6:$D$305,"Tela principal")>0,"",0)),IF(ISNUMBER(P28),P28,IF(ISNUMBER(O28),O28*(1+Parametros!$B$22),IF(OR(COUNTIFS(Despiece!$A$6:$A$705,$A28,Despiece!$D$6:$D$705,"Tela principal")>0,COUNTIFS(Mediciones!$C$6:$C$305,$A28,Mediciones!$D$6:$D$305,"Tela principal")>0),"",0))))))) | R28: =IF($A28="","",IF(COUNTIFS(Despiece!$A$6:$A$705,$A28,Despiece!$D$6:$D$705,"Tela 2",Despiece!$F$6:$F$705,">0")=0,"",SUMIFS(Despiece!$F$6:$F$705,Despiece!$A$6:$A$705,$A28,Despiece!$D$6:$D$705,"Tela 2"))) | S28: =IF($A28="","",IFERROR(AVERAGEIFS(Mediciones!$K$6:$K$305,Mediciones!$C$6:$C$305,$A28,Mediciones!$D$6:$D$305,"Tela 2"),"")) | T28: =IF($A28="","",IF($N28="Despiece",IF(ISNUMBER(R28),R28*(1+Parametros!$B$22),IF(COUNTIFS(Despiece!$A$6:$A$705,$A28,Despiece!$D$6:$D$705,"Tela 2")>0,"",0)),IF($N28="Medición real",IF(ISNUMBER(S28),S28,IF(COUNTIFS(Mediciones!$C$6:$C$305,$A28,Mediciones!$D$6:$D$305,"Tela 2")>0,"",0)),IF(ISNUMBER(S28),S28,IF(ISNUMBER(R28),R28*(1+Parametros!$B$22),IF(OR(COUNTIFS(Despiece!$A$6:$A$705,$A28,Despiece!$D$6:$D$705,"Tela 2")>0,COUNTIFS(Mediciones!$C$6:$C$305,$A28,Mediciones!$D$6:$D$305,"Tela 2")>0),"",0)))))) -> 0 | U28: =IF($A28="","",IF(COUNTIFS(Despiece!$A$6:$A$705,$A28,Despiece!$D$6:$D$705,"Tela 3",Despiece!$F$6:$F$705,">0")=0,"",SUMIFS(Despiece!$F$6:$F$705,Despiece!$A$6:$A$705,$A28,Despiece!$D$6:$D$705,"Tela 3"))) | V28: =IF($A28="","",IFERROR(AVERAGEIFS(Mediciones!$K$6:$K$305,Mediciones!$C$6:$C$305,$A28,Mediciones!$D$6:$D$305,"Tela 3"),"")) | W28: =IF($A28="","",IF($N28="Despiece",IF(ISNUMBER(U28),U28*(1+Parametros!$B$22),IF(COUNTIFS(Despiece!$A$6:$A$705,$A28,Despiece!$D$6:$D$705,"Tela 3")>0,"",0)),IF($N28="Medición real",IF(ISNUMBER(V28),V28,IF(COUNTIFS(Mediciones!$C$6:$C$305,$A28,Mediciones!$D$6:$D$305,"Tela 3")>0,"",0)),IF(ISNUMBER(V28),V28,IF(ISNUMBER(U28),U28*(1+Parametros!$B$22),IF(OR(COUNTIFS(Despiece!$A$6:$A$705,$A28,Despiece!$D$6:$D$705,"Tela 3")>0,COUNTIFS(Mediciones!$C$6:$C$305,$A28,Mediciones!$D$6:$D$305,"Tela 3")>0),"",0)))))) -> 0 | Y28: =IF($A28="","",IF(ISNUMBER(X28),X28,IF(COUNTIFS(Despiece!$A$6:$A$705,$A28,Despiece!$E$6:$E$705,"Sublimada",Despiece!$F$6:$F$705,">0")>0,SUMIFS(Despiece!$F$6:$F$705,Despiece!$A$6:$A$705,$A28,Despiece!$E$6:$E$705,"Sublimada")*(1+Parametros!$B$22),IF(COUNTIFS(Despiece!$A$6:$A$705,$A28,Despiece!$E$6:$E$705,"Sublimada")=0,0,"")))) | Z28: =IF($A28="","",IFERROR(IF(ISNUMBER(Q28),IF(Q28=0,0,Q28*INDEX(Telas!$I$6:$I$105,MATCH(K28,Telas!$A$6:$A$105,0))),NA())+IF(ISNUMBER(T28),IF(T28=0,0,T28*INDEX(Telas!$I$6:$I$105,MATCH(L28,Telas!$A$6:$A$105,0))),NA())+IF(ISNUMBER(W28),IF(W28=0,0,W28*INDEX(Telas!$I$6:$I$105,MATCH(IF(M28="",K28,M28),Telas!$A$6:$A$105,0))),NA()),"")) | AA28: =IF($A28="","",IF(ISNUMBER(Y28),Y28*Parametros!$B$19,"")) | AB28: =IF(OR($A28="",F28=""),"",IFERROR(INDEX(Confeccion!$B$6:$B$125,MATCH(F28,Confeccion!$A$6:$A$125,0)),"")) -> 2300 | AC28: =IF($A28="","",IFERROR(N(H28)*IF(G28="",0,INDEX(Avios!$C$6:$C$65,MATCH(G28,Avios!$A$6:$A$65,0)))+N(J28)*IF(I28="",0,INDEX(Avios!$C$6:$C$65,MATCH(I28,Avios!$A$6:$A$65,0))),"")) -> 0 | AD28: =IF($A28="","",IFERROR(Z28+AA28+AB28+AC28,"")) | AE28: =IF(ISNUMBER(AD28),AD28*Parametros!$B$12,"") | AF28: =IF(AND(ISNUMBER(Q28),K28<>""),IFERROR(1/(Q28*INDEX(Telas!$G$6:$G$105,MATCH(K28,Telas!$A$6:$A$105,0))),""),"") | AG28: =IF($A28="","",IF(ISNUMBER(AD28),IF(AND(N(Y28)>0,N(Parametros!$B$19)=0),"Lista, pero sin costo de impresión (Parametros)","Lista"),IF(Q28="","Consumo tela principal (Despiece o Mediciones). ","")&IF(COUNTIFS(Mediciones!$C$6:$C$305,$A28,Mediciones!$K$6:$K$305,"")>0,"Pesar 1 m de la tela medida (Telas, kg por metro). ","")&IF(T28="","Consumo Tela 2. ","")&IF(W28="","Consumo Tela 3. ","")&IF(K28="","Elegir tela principal. ",IF(ISERROR(INDEX(Telas!$I$6:$I$105,MATCH(K28,Telas!$A$6:$A$105,0))*1),"Precio o peso por metro de "&K28&". ",""))&IF(AND(N(T28)>0,L28=""),"Elegir Tela 2. ",IF(AND(N(T28)>0,ISERROR(INDEX(Telas!$I$6:$I$105,MATCH(L28,Telas!$A$6:$A$105,0))*1)),"Precio o peso por metro de "&L28&". ",""))&IF(Y28="","Metros impresos. ","")&IF(F28="","Tipo de confección. ",IF(AB28="","Precio de confección. ","")))) -> Consumo tela principal (Despiece o Mediciones). Elegir tela principal. Metros impresos. | AH28: Confección sugerida por el tipo de molde: confirmar. Falta ficha de corte.
A29: 24 · FUTINHOMV02 | B29: Fútbol infantil, raglán, cuello v | C29: Fútbol | D29: Camiseta | E29: Infantil Masculino | F29: Camiseta Futbol Molde 2026 (Raglan) | O29: =IF($A29="","",IF(COUNTIFS(Despiece!$A$6:$A$705,$A29,Despiece!$D$6:$D$705,"Tela principal",Despiece!$F$6:$F$705,">0")=0,"",SUMIFS(Despiece!$F$6:$F$705,Despiece!$A$6:$A$705,$A29,Despiece!$D$6:$D$705,"Tela principal"))) | P29: =IF($A29="","",IFERROR(AVERAGEIFS(Mediciones!$K$6:$K$305,Mediciones!$C$6:$C$305,$A29,Mediciones!$D$6:$D$305,"Tela principal"),"")) | Q29: =IF($A29="","",IF(N(IF($N29="Despiece",IF(ISNUMBER(O29),O29*(1+Parametros!$B$22),IF(COUNTIFS(Despiece!$A$6:$A$705,$A29,Despiece!$D$6:$D$705,"Tela principal")>0,"",0)),IF($N29="Medición real",IF(ISNUMBER(P29),P29,IF(COUNTIFS(Mediciones!$C$6:$C$305,$A29,Mediciones!$D$6:$D$305,"Tela principal")>0,"",0)),IF(ISNUMBER(P29),P29,IF(ISNUMBER(O29),O29*(1+Parametros!$B$22),IF(OR(COUNTIFS(Despiece!$A$6:$A$705,$A29,Despiece!$D$6:$D$705,"Tela principal")>0,COUNTIFS(Mediciones!$C$6:$C$305,$A29,Mediciones!$D$6:$D$305,"Tela principal")>0),"",0))))))=0,"",IF($N29="Despiece",IF(ISNUMBER(O29),O29*(1+Parametros!$B$22),IF(COUNTIFS(Despiece!$A$6:$A$705,$A29,Despiece!$D$6:$D$705,"Tela principal")>0,"",0)),IF($N29="Medición real",IF(ISNUMBER(P29),P29,IF(COUNTIFS(Mediciones!$C$6:$C$305,$A29,Mediciones!$D$6:$D$305,"Tela principal")>0,"",0)),IF(ISNUMBER(P29),P29,IF(ISNUMBER(O29),O29*(1+Parametros!$B$22),IF(OR(COUNTIFS(Despiece!$A$6:$A$705,$A29,Despiece!$D$6:$D$705,"Tela principal")>0,COUNTIFS(Mediciones!$C$6:$C$305,$A29,Mediciones!$D$6:$D$305,"Tela principal")>0),"",0))))))) | R29: =IF($A29="","",IF(COUNTIFS(Despiece!$A$6:$A$705,$A29,Despiece!$D$6:$D$705,"Tela 2",Despiece!$F$6:$F$705,">0")=0,"",SUMIFS(Despiece!$F$6:$F$705,Despiece!$A$6:$A$705,$A29,Despiece!$D$6:$D$705,"Tela 2"))) | S29: =IF($A29="","",IFERROR(AVERAGEIFS(Mediciones!$K$6:$K$305,Mediciones!$C$6:$C$305,$A29,Mediciones!$D$6:$D$305,"Tela 2"),"")) | T29: =IF($A29="","",IF($N29="Despiece",IF(ISNUMBER(R29),R29*(1+Parametros!$B$22),IF(COUNTIFS(Despiece!$A$6:$A$705,$A29,Despiece!$D$6:$D$705,"Tela 2")>0,"",0)),IF($N29="Medición real",IF(ISNUMBER(S29),S29,IF(COUNTIFS(Mediciones!$C$6:$C$305,$A29,Mediciones!$D$6:$D$305,"Tela 2")>0,"",0)),IF(ISNUMBER(S29),S29,IF(ISNUMBER(R29),R29*(1+Parametros!$B$22),IF(OR(COUNTIFS(Despiece!$A$6:$A$705,$A29,Despiece!$D$6:$D$705,"Tela 2")>0,COUNTIFS(Mediciones!$C$6:$C$305,$A29,Mediciones!$D$6:$D$305,"Tela 2")>0),"",0)))))) -> 0 | U29: =IF($A29="","",IF(COUNTIFS(Despiece!$A$6:$A$705,$A29,Despiece!$D$6:$D$705,"Tela 3",Despiece!$F$6:$F$705,">0")=0,"",SUMIFS(Despiece!$F$6:$F$705,Despiece!$A$6:$A$705,$A29,Despiece!$D$6:$D$705,"Tela 3"))) | V29: =IF($A29="","",IFERROR(AVERAGEIFS(Mediciones!$K$6:$K$305,Mediciones!$C$6:$C$305,$A29,Mediciones!$D$6:$D$305,"Tela 3"),"")) | W29: =IF($A29="","",IF($N29="Despiece",IF(ISNUMBER(U29),U29*(1+Parametros!$B$22),IF(COUNTIFS(Despiece!$A$6:$A$705,$A29,Despiece!$D$6:$D$705,"Tela 3")>0,"",0)),IF($N29="Medición real",IF(ISNUMBER(V29),V29,IF(COUNTIFS(Mediciones!$C$6:$C$305,$A29,Mediciones!$D$6:$D$305,"Tela 3")>0,"",0)),IF(ISNUMBER(V29),V29,IF(ISNUMBER(U29),U29*(1+Parametros!$B$22),IF(OR(COUNTIFS(Despiece!$A$6:$A$705,$A29,Despiece!$D$6:$D$705,"Tela 3")>0,COUNTIFS(Mediciones!$C$6:$C$305,$A29,Mediciones!$D$6:$D$305,"Tela 3")>0),"",0)))))) -> 0 | Y29: =IF($A29="","",IF(ISNUMBER(X29),X29,IF(COUNTIFS(Despiece!$A$6:$A$705,$A29,Despiece!$E$6:$E$705,"Sublimada",Despiece!$F$6:$F$705,">0")>0,SUMIFS(Despiece!$F$6:$F$705,Despiece!$A$6:$A$705,$A29,Despiece!$E$6:$E$705,"Sublimada")*(1+Parametros!$B$22),IF(COUNTIFS(Despiece!$A$6:$A$705,$A29,Despiece!$E$6:$E$705,"Sublimada")=0,0,"")))) | Z29: =IF($A29="","",IFERROR(IF(ISNUMBER(Q29),IF(Q29=0,0,Q29*INDEX(Telas!$I$6:$I$105,MATCH(K29,Telas!$A$6:$A$105,0))),NA())+IF(ISNUMBER(T29),IF(T29=0,0,T29*INDEX(Telas!$I$6:$I$105,MATCH(L29,Telas!$A$6:$A$105,0))),NA())+IF(ISNUMBER(W29),IF(W29=0,0,W29*INDEX(Telas!$I$6:$I$105,MATCH(IF(M29="",K29,M29),Telas!$A$6:$A$105,0))),NA()),"")) | AA29: =IF($A29="","",IF(ISNUMBER(Y29),Y29*Parametros!$B$19,"")) | AB29: =IF(OR($A29="",F29=""),"",IFERROR(INDEX(Confeccion!$B$6:$B$125,MATCH(F29,Confeccion!$A$6:$A$125,0)),"")) -> 2300 | AC29: =IF($A29="","",IFERROR(N(H29)*IF(G29="",0,INDEX(Avios!$C$6:$C$65,MATCH(G29,Avios!$A$6:$A$65,0)))+N(J29)*IF(I29="",0,INDEX(Avios!$C$6:$C$65,MATCH(I29,Avios!$A$6:$A$65,0))),"")) -> 0 | AD29: =IF($A29="","",IFERROR(Z29+AA29+AB29+AC29,"")) | AE29: =IF(ISNUMBER(AD29),AD29*Parametros!$B$12,"") | AF29: =IF(AND(ISNUMBER(Q29),K29<>""),IFERROR(1/(Q29*INDEX(Telas!$G$6:$G$105,MATCH(K29,Telas!$A$6:$A$105,0))),""),"") | AG29: =IF($A29="","",IF(ISNUMBER(AD29),IF(AND(N(Y29)>0,N(Parametros!$B$19)=0),"Lista, pero sin costo de impresión (Parametros)","Lista"),IF(Q29="","Consumo tela principal (Despiece o Mediciones). ","")&IF(COUNTIFS(Mediciones!$C$6:$C$305,$A29,Mediciones!$K$6:$K$305,"")>0,"Pesar 1 m de la tela medida (Telas, kg por metro). ","")&IF(T29="","Consumo Tela 2. ","")&IF(W29="","Consumo Tela 3. ","")&IF(K29="","Elegir tela principal. ",IF(ISERROR(INDEX(Telas!$I$6:$I$105,MATCH(K29,Telas!$A$6:$A$105,0))*1),"Precio o peso por metro de "&K29&". ",""))&IF(AND(N(T29)>0,L29=""),"Elegir Tela 2. ",IF(AND(N(T29)>0,ISERROR(INDEX(Telas!$I$6:$I$105,MATCH(L29,Telas!$A$6:$A$105,0))*1)),"Precio o peso por metro de "&L29&". ",""))&IF(Y29="","Metros impresos. ","")&IF(F29="","Tipo de confección. ",IF(AB29="","Precio de confección. ","")))) -> Consumo tela principal (Despiece o Mediciones). Elegir tela principal. Metros impresos. | AH29: Confección sugerida por el tipo de molde: confirmar. Falta ficha de corte.
A30: 25 · FUTMUJU02PRO | B30: Fútbol, raglán, pro, cuello redondo | C30: Fútbol | D30: Camiseta | E30: Femenino | F30: Camiseta Futbol Molde 2026 (Raglan) | O30: =IF($A30="","",IF(COUNTIFS(Despiece!$A$6:$A$705,$A30,Despiece!$D$6:$D$705,"Tela principal",Despiece!$F$6:$F$705,">0")=0,"",SUMIFS(Despiece!$F$6:$F$705,Despiece!$A$6:$A$705,$A30,Despiece!$D$6:$D$705,"Tela principal"))) | P30: =IF($A30="","",IFERROR(AVERAGEIFS(Mediciones!$K$6:$K$305,Mediciones!$C$6:$C$305,$A30,Mediciones!$D$6:$D$305,"Tela principal"),"")) | Q30: =IF($A30="","",IF(N(IF($N30="Despiece",IF(ISNUMBER(O30),O30*(1+Parametros!$B$22),IF(COUNTIFS(Despiece!$A$6:$A$705,$A30,Despiece!$D$6:$D$705,"Tela principal")>0,"",0)),IF($N30="Medición real",IF(ISNUMBER(P30),P30,IF(COUNTIFS(Mediciones!$C$6:$C$305,$A30,Mediciones!$D$6:$D$305,"Tela principal")>0,"",0)),IF(ISNUMBER(P30),P30,IF(ISNUMBER(O30),O30*(1+Parametros!$B$22),IF(OR(COUNTIFS(Despiece!$A$6:$A$705,$A30,Despiece!$D$6:$D$705,"Tela principal")>0,COUNTIFS(Mediciones!$C$6:$C$305,$A30,Mediciones!$D$6:$D$305,"Tela principal")>0),"",0))))))=0,"",IF($N30="Despiece",IF(ISNUMBER(O30),O30*(1+Parametros!$B$22),IF(COUNTIFS(Despiece!$A$6:$A$705,$A30,Despiece!$D$6:$D$705,"Tela principal")>0,"",0)),IF($N30="Medición real",IF(ISNUMBER(P30),P30,IF(COUNTIFS(Mediciones!$C$6:$C$305,$A30,Mediciones!$D$6:$D$305,"Tela principal")>0,"",0)),IF(ISNUMBER(P30),P30,IF(ISNUMBER(O30),O30*(1+Parametros!$B$22),IF(OR(COUNTIFS(Despiece!$A$6:$A$705,$A30,Despiece!$D$6:$D$705,"Tela principal")>0,COUNTIFS(Mediciones!$C$6:$C$305,$A30,Mediciones!$D$6:$D$305,"Tela principal")>0),"",0))))))) | R30: =IF($A30="","",IF(COUNTIFS(Despiece!$A$6:$A$705,$A30,Despiece!$D$6:$D$705,"Tela 2",Despiece!$F$6:$F$705,">0")=0,"",SUMIFS(Despiece!$F$6:$F$705,Despiece!$A$6:$A$705,$A30,Despiece!$D$6:$D$705,"Tela 2"))) | S30: =IF($A30="","",IFERROR(AVERAGEIFS(Mediciones!$K$6:$K$305,Mediciones!$C$6:$C$305,$A30,Mediciones!$D$6:$D$305,"Tela 2"),"")) | T30: =IF($A30="","",IF($N30="Despiece",IF(ISNUMBER(R30),R30*(1+Parametros!$B$22),IF(COUNTIFS(Despiece!$A$6:$A$705,$A30,Despiece!$D$6:$D$705,"Tela 2")>0,"",0)),IF($N30="Medición real",IF(ISNUMBER(S30),S30,IF(COUNTIFS(Mediciones!$C$6:$C$305,$A30,Mediciones!$D$6:$D$305,"Tela 2")>0,"",0)),IF(ISNUMBER(S30),S30,IF(ISNUMBER(R30),R30*(1+Parametros!$B$22),IF(OR(COUNTIFS(Despiece!$A$6:$A$705,$A30,Despiece!$D$6:$D$705,"Tela 2")>0,COUNTIFS(Mediciones!$C$6:$C$305,$A30,Mediciones!$D$6:$D$305,"Tela 2")>0),"",0)))))) | U30: =IF($A30="","",IF(COUNTIFS(Despiece!$A$6:$A$705,$A30,Despiece!$D$6:$D$705,"Tela 3",Despiece!$F$6:$F$705,">0")=0,"",SUMIFS(Despiece!$F$6:$F$705,Despiece!$A$6:$A$705,$A30,Despiece!$D$6:$D$705,"Tela 3"))) | V30: =IF($A30="","",IFERROR(AVERAGEIFS(Mediciones!$K$6:$K$305,Mediciones!$C$6:$C$305,$A30,Mediciones!$D$6:$D$305,"Tela 3"),"")) | W30: =IF($A30="","",IF($N30="Despiece",IF(ISNUMBER(U30),U30*(1+Parametros!$B$22),IF(COUNTIFS(Despiece!$A$6:$A$705,$A30,Despiece!$D$6:$D$705,"Tela 3")>0,"",0)),IF($N30="Medición real",IF(ISNUMBER(V30),V30,IF(COUNTIFS(Mediciones!$C$6:$C$305,$A30,Mediciones!$D$6:$D$305,"Tela 3")>0,"",0)),IF(ISNUMBER(V30),V30,IF(ISNUMBER(U30),U30*(1+Parametros!$B$22),IF(OR(COUNTIFS(Despiece!$A$6:$A$705,$A30,Despiece!$D$6:$D$705,"Tela 3")>0,COUNTIFS(Mediciones!$C$6:$C$305,$A30,Mediciones!$D$6:$D$305,"Tela 3")>0),"",0)))))) -> 0 | Y30: =IF($A30="","",IF(ISNUMBER(X30),X30,IF(COUNTIFS(Despiece!$A$6:$A$705,$A30,Despiece!$E$6:$E$705,"Sublimada",Despiece!$F$6:$F$705,">0")>0,SUMIFS(Despiece!$F$6:$F$705,Despiece!$A$6:$A$705,$A30,Despiece!$E$6:$E$705,"Sublimada")*(1+Parametros!$B$22),IF(COUNTIFS(Despiece!$A$6:$A$705,$A30,Despiece!$E$6:$E$705,"Sublimada")=0,0,"")))) | Z30: =IF($A30="","",IFERROR(IF(ISNUMBER(Q30),IF(Q30=0,0,Q30*INDEX(Telas!$I$6:$I$105,MATCH(K30,Telas!$A$6:$A$105,0))),NA())+IF(ISNUMBER(T30),IF(T30=0,0,T30*INDEX(Telas!$I$6:$I$105,MATCH(L30,Telas!$A$6:$A$105,0))),NA())+IF(ISNUMBER(W30),IF(W30=0,0,W30*INDEX(Telas!$I$6:$I$105,MATCH(IF(M30="",K30,M30),Telas!$A$6:$A$105,0))),NA()),"")) | AA30: =IF($A30="","",IF(ISNUMBER(Y30),Y30*Parametros!$B$19,"")) | AB30: =IF(OR($A30="",F30=""),"",IFERROR(INDEX(Confeccion!$B$6:$B$125,MATCH(F30,Confeccion!$A$6:$A$125,0)),"")) -> 2300 | AC30: =IF($A30="","",IFERROR(N(H30)*IF(G30="",0,INDEX(Avios!$C$6:$C$65,MATCH(G30,Avios!$A$6:$A$65,0)))+N(J30)*IF(I30="",0,INDEX(Avios!$C$6:$C$65,MATCH(I30,Avios!$A$6:$A$65,0))),"")) -> 0 | AD30: =IF($A30="","",IFERROR(Z30+AA30+AB30+AC30,"")) | AE30: =IF(ISNUMBER(AD30),AD30*Parametros!$B$12,"") | AF30: =IF(AND(ISNUMBER(Q30),K30<>""),IFERROR(1/(Q30*INDEX(Telas!$G$6:$G$105,MATCH(K30,Telas!$A$6:$A$105,0))),""),"") | AG30: =IF($A30="","",IF(ISNUMBER(AD30),IF(AND(N(Y30)>0,N(Parametros!$B$19)=0),"Lista, pero sin costo de impresión (Parametros)","Lista"),IF(Q30="","Consumo tela principal (Despiece o Mediciones). ","")&IF(COUNTIFS(Mediciones!$C$6:$C$305,$A30,Mediciones!$K$6:$K$305,"")>0,"Pesar 1 m de la tela medida (Telas, kg por metro). ","")&IF(T30="","Consumo Tela 2. ","")&IF(W30="","Consumo Tela 3. ","")&IF(K30="","Elegir tela principal. ",IF(ISERROR(INDEX(Telas!$I$6:$I$105,MATCH(K30,Telas!$A$6:$A$105,0))*1),"Precio o peso por metro de "&K30&". ",""))&IF(AND(N(T30)>0,L30=""),"Elegir Tela 2. ",IF(AND(N(T30)>0,ISERROR(INDEX(Telas!$I$6:$I$105,MATCH(L30,Telas!$A$6:$A$105,0))*1)),"Precio o peso por metro de "&L30&". ",""))&IF(Y30="","Metros impresos. ","")&IF(F30="","Tipo de confección. ",IF(AB30="","Precio de confección. ","")))) -> Consumo tela principal (Despiece o Mediciones). Consumo Tela 2. Elegir tela principal. Metros impresos. | AH30: Confección sugerida por el tipo de molde: confirmar. Falta ficha de corte.
A31: 26 · FUTHOMU02PRO | B31: Fútbol, raglán, pro, cuello redondo | C31: Fútbol | D31: Camiseta | E31: Masculino | F31: Camiseta Futbol Molde 2026 (Raglan) | O31: =IF($A31="","",IF(COUNTIFS(Despiece!$A$6:$A$705,$A31,Despiece!$D$6:$D$705,"Tela principal",Despiece!$F$6:$F$705,">0")=0,"",SUMIFS(Despiece!$F$6:$F$705,Despiece!$A$6:$A$705,$A31,Despiece!$D$6:$D$705,"Tela principal"))) | P31: =IF($A31="","",IFERROR(AVERAGEIFS(Mediciones!$K$6:$K$305,Mediciones!$C$6:$C$305,$A31,Mediciones!$D$6:$D$305,"Tela principal"),"")) | Q31: =IF($A31="","",IF(N(IF($N31="Despiece",IF(ISNUMBER(O31),O31*(1+Parametros!$B$22),IF(COUNTIFS(Despiece!$A$6:$A$705,$A31,Despiece!$D$6:$D$705,"Tela principal")>0,"",0)),IF($N31="Medición real",IF(ISNUMBER(P31),P31,IF(COUNTIFS(Mediciones!$C$6:$C$305,$A31,Mediciones!$D$6:$D$305,"Tela principal")>0,"",0)),IF(ISNUMBER(P31),P31,IF(ISNUMBER(O31),O31*(1+Parametros!$B$22),IF(OR(COUNTIFS(Despiece!$A$6:$A$705,$A31,Despiece!$D$6:$D$705,"Tela principal")>0,COUNTIFS(Mediciones!$C$6:$C$305,$A31,Mediciones!$D$6:$D$305,"Tela principal")>0),"",0))))))=0,"",IF($N31="Despiece",IF(ISNUMBER(O31),O31*(1+Parametros!$B$22),IF(COUNTIFS(Despiece!$A$6:$A$705,$A31,Despiece!$D$6:$D$705,"Tela principal")>0,"",0)),IF($N31="Medición real",IF(ISNUMBER(P31),P31,IF(COUNTIFS(Mediciones!$C$6:$C$305,$A31,Mediciones!$D$6:$D$305,"Tela principal")>0,"",0)),IF(ISNUMBER(P31),P31,IF(ISNUMBER(O31),O31*(1+Parametros!$B$22),IF(OR(COUNTIFS(Despiece!$A$6:$A$705,$A31,Despiece!$D$6:$D$705,"Tela principal")>0,COUNTIFS(Mediciones!$C$6:$C$305,$A31,Mediciones!$D$6:$D$305,"Tela principal")>0),"",0))))))) | R31: =IF($A31="","",IF(COUNTIFS(Despiece!$A$6:$A$705,$A31,Despiece!$D$6:$D$705,"Tela 2",Despiece!$F$6:$F$705,">0")=0,"",SUMIFS(Despiece!$F$6:$F$705,Despiece!$A$6:$A$705,$A31,Despiece!$D$6:$D$705,"Tela 2"))) | S31: =IF($A31="","",IFERROR(AVERAGEIFS(Mediciones!$K$6:$K$305,Mediciones!$C$6:$C$305,$A31,Mediciones!$D$6:$D$305,"Tela 2"),"")) | T31: =IF($A31="","",IF($N31="Despiece",IF(ISNUMBER(R31),R31*(1+Parametros!$B$22),IF(COUNTIFS(Despiece!$A$6:$A$705,$A31,Despiece!$D$6:$D$705,"Tela 2")>0,"",0)),IF($N31="Medición real",IF(ISNUMBER(S31),S31,IF(COUNTIFS(Mediciones!$C$6:$C$305,$A31,Mediciones!$D$6:$D$305,"Tela 2")>0,"",0)),IF(ISNUMBER(S31),S31,IF(ISNUMBER(R31),R31*(1+Parametros!$B$22),IF(OR(COUNTIFS(Despiece!$A$6:$A$705,$A31,Despiece!$D$6:$D$705,"Tela 2")>0,COUNTIFS(Mediciones!$C$6:$C$305,$A31,Mediciones!$D$6:$D$305,"Tela 2")>0),"",0)))))) | U31: =IF($A31="","",IF(COUNTIFS(Despiece!$A$6:$A$705,$A31,Despiece!$D$6:$D$705,"Tela 3",Despiece!$F$6:$F$705,">0")=0,"",SUMIFS(Despiece!$F$6:$F$705,Despiece!$A$6:$A$705,$A31,Despiece!$D$6:$D$705,"Tela 3"))) | V31: =IF($A31="","",IFERROR(AVERAGEIFS(Mediciones!$K$6:$K$305,Mediciones!$C$6:$C$305,$A31,Mediciones!$D$6:$D$305,"Tela 3"),"")) | W31: =IF($A31="","",IF($N31="Despiece",IF(ISNUMBER(U31),U31*(1+Parametros!$B$22),IF(COUNTIFS(Despiece!$A$6:$A$705,$A31,Despiece!$D$6:$D$705,"Tela 3")>0,"",0)),IF($N31="Medición real",IF(ISNUMBER(V31),V31,IF(COUNTIFS(Mediciones!$C$6:$C$305,$A31,Mediciones!$D$6:$D$305,"Tela 3")>0,"",0)),IF(ISNUMBER(V31),V31,IF(ISNUMBER(U31),U31*(1+Parametros!$B$22),IF(OR(COUNTIFS(Despiece!$A$6:$A$705,$A31,Despiece!$D$6:$D$705,"Tela 3")>0,COUNTIFS(Mediciones!$C$6:$C$305,$A31,Mediciones!$D$6:$D$305,"Tela 3")>0),"",0)))))) -> 0 | Y31: =IF($A31="","",IF(ISNUMBER(X31),X31,IF(COUNTIFS(Despiece!$A$6:$A$705,$A31,Despiece!$E$6:$E$705,"Sublimada",Despiece!$F$6:$F$705,">0")>0,SUMIFS(Despiece!$F$6:$F$705,Despiece!$A$6:$A$705,$A31,Despiece!$E$6:$E$705,"Sublimada")*(1+Parametros!$B$22),IF(COUNTIFS(Despiece!$A$6:$A$705,$A31,Despiece!$E$6:$E$705,"Sublimada")=0,0,"")))) | Z31: =IF($A31="","",IFERROR(IF(ISNUMBER(Q31),IF(Q31=0,0,Q31*INDEX(Telas!$I$6:$I$105,MATCH(K31,Telas!$A$6:$A$105,0))),NA())+IF(ISNUMBER(T31),IF(T31=0,0,T31*INDEX(Telas!$I$6:$I$105,MATCH(L31,Telas!$A$6:$A$105,0))),NA())+IF(ISNUMBER(W31),IF(W31=0,0,W31*INDEX(Telas!$I$6:$I$105,MATCH(IF(M31="",K31,M31),Telas!$A$6:$A$105,0))),NA()),"")) | AA31: =IF($A31="","",IF(ISNUMBER(Y31),Y31*Parametros!$B$19,"")) | AB31: =IF(OR($A31="",F31=""),"",IFERROR(INDEX(Confeccion!$B$6:$B$125,MATCH(F31,Confeccion!$A$6:$A$125,0)),"")) -> 2300 | AC31: =IF($A31="","",IFERROR(N(H31)*IF(G31="",0,INDEX(Avios!$C$6:$C$65,MATCH(G31,Avios!$A$6:$A$65,0)))+N(J31)*IF(I31="",0,INDEX(Avios!$C$6:$C$65,MATCH(I31,Avios!$A$6:$A$65,0))),"")) -> 0 | AD31: =IF($A31="","",IFERROR(Z31+AA31+AB31+AC31,"")) | AE31: =IF(ISNUMBER(AD31),AD31*Parametros!$B$12,"") | AF31: =IF(AND(ISNUMBER(Q31),K31<>""),IFERROR(1/(Q31*INDEX(Telas!$G$6:$G$105,MATCH(K31,Telas!$A$6:$A$105,0))),""),"") | AG31: =IF($A31="","",IF(ISNUMBER(AD31),IF(AND(N(Y31)>0,N(Parametros!$B$19)=0),"Lista, pero sin costo de impresión (Parametros)","Lista"),IF(Q31="","Consumo tela principal (Despiece o Mediciones). ","")&IF(COUNTIFS(Mediciones!$C$6:$C$305,$A31,Mediciones!$K$6:$K$305,"")>0,"Pesar 1 m de la tela medida (Telas, kg por metro). ","")&IF(T31="","Consumo Tela 2. ","")&IF(W31="","Consumo Tela 3. ","")&IF(K31="","Elegir tela principal. ",IF(ISERROR(INDEX(Telas!$I$6:$I$105,MATCH(K31,Telas!$A$6:$A$105,0))*1),"Precio o peso por metro de "&K31&". ",""))&IF(AND(N(T31)>0,L31=""),"Elegir Tela 2. ",IF(AND(N(T31)>0,ISERROR(INDEX(Telas!$I$6:$I$105,MATCH(L31,Telas!$A$6:$A$105,0))*1)),"Precio o peso por metro de "&L31&". ",""))&IF(Y31="","Metros impresos. ","")&IF(F31="","Tipo de confección. ",IF(AB31="","Precio de confección. ","")))) -> Consumo tela principal (Despiece o Mediciones). Consumo Tela 2. Elegir tela principal. Metros impresos. | AH31: Confección sugerida por el tipo de molde: confirmar. Falta ficha de corte.
... A34: 29 · BKMUJU03 | B34: Básquetbol, cuello redondo | C34: Básquetbol | D34: Camiseta | E34: Femenino | F34: Camiseta De Basket | O34: =IF($A34="","",IF(COUNTIFS(Despiece!$A$6:$A$705,$A34,Despiece!$D$6:$D$705,"Tela principal",Despiece!$F$6:$F$705,">0")=0,"",SUMIFS(Despiece!$F$6:$F$705,Despiece!$A$6:$A$705,$A34,Despiece!$D$6:$D$705,"Tela principal"))) | P34: =IF($A34="","",IFERROR(AVERAGEIFS(Mediciones!$K$6:$K$305,Mediciones!$C$6:$C$305,$A34,Mediciones!$D$6:$D$305,"Tela principal"),"")) | Q34: =IF($A34="","",IF(N(IF($N34="Despiece",IF(ISNUMBER(O34),O34*(1+Parametros!$B$22),IF(COUNTIFS(Despiece!$A$6:$A$705,$A34,Despiece!$D$6:$D$705,"Tela principal")>0,"",0)),IF($N34="Medición real",IF(ISNUMBER(P34),P34,IF(COUNTIFS(Mediciones!$C$6:$C$305,$A34,Mediciones!$D$6:$D$305,"Tela principal")>0,"",0)),IF(ISNUMBER(P34),P34,IF(ISNUMBER(O34),O34*(1+Parametros!$B$22),IF(OR(COUNTIFS(Despiece!$A$6:$A$705,$A34,Despiece!$D$6:$D$705,"Tela principal")>0,COUNTIFS(Mediciones!$C$6:$C$305,$A34,Mediciones!$D$6:$D$305,"Tela principal")>0),"",0))))))=0,"",IF($N34="Despiece",IF(ISNUMBER(O34),O34*(1+Parametros!$B$22),IF(COUNTIFS(Despiece!$A$6:$A$705,$A34,Despiece!$D$6:$D$705,"Tela principal")>0,"",0)),IF($N34="Medición real",IF(ISNUMBER(P34),P34,IF(COUNTIFS(Mediciones!$C$6:$C$305,$A34,Mediciones!$D$6:$D$305,"Tela principal")>0,"",0)),IF(ISNUMBER(P34),P34,IF(ISNUMBER(O34),O34*(1+Parametros!$B$22),IF(OR(COUNTIFS(Despiece!$A$6:$A$705,$A34,Despiece!$D$6:$D$705,"Tela principal")>0,COUNTIFS(Mediciones!$C$6:$C$305,$A34,Mediciones!$D$6:$D$305,"Tela principal")>0),"",0))))))) | R34: =IF($A34="","",IF(COUNTIFS(Despiece!$A$6:$A$705,$A34,Despiece!$D$6:$D$705,"Tela 2",Despiece!$F$6:$F$705,">0")=0,"",SUMIFS(Despiece!$F$6:$F$705,Despiece!$A$6:$A$705,$A34,Despiece!$D$6:$D$705,"Tela 2"))) | S34: =IF($A34="","",IFERROR(AVERAGEIFS(Mediciones!$K$6:$K$305,Mediciones!$C$6:$C$305,$A34,Mediciones!$D$6:$D$305,"Tela 2"),"")) | T34: =IF($A34="","",IF($N34="Despiece",IF(ISNUMBER(R34),R34*(1+Parametros!$B$22),IF(COUNTIFS(Despiece!$A$6:$A$705,$A34,Despiece!$D$6:$D$705,"Tela 2")>0,"",0)),IF($N34="Medición real",IF(ISNUMBER(S34),S34,IF(COUNTIFS(Mediciones!$C$6:$C$305,$A34,Mediciones!$D$6:$D$305,"Tela 2")>0,"",0)),IF(ISNUMBER(S34),S34,IF(ISNUMBER(R34),R34*(1+Parametros!$B$22),IF(OR(COUNTIFS(Despiece!$A$6:$A$705,$A34,Despiece!$D$6:$D$705,"Tela 2")>0,COUNTIFS(Mediciones!$C$6:$C$305,$A34,Mediciones!$D$6:$D$305,"Tela 2")>0),"",0)))))) -> 0 | U34: =IF($A34="","",IF(COUNTIFS(Despiece!$A$6:$A$705,$A34,Despiece!$D$6:$D$705,"Tela 3",Despiece!$F$6:$F$705,">0")=0,"",SUMIFS(Despiece!$F$6:$F$705,Despiece!$A$6:$A$705,$A34,Despiece!$D$6:$D$705,"Tela 3"))) | V34: =IF($A34="","",IFERROR(AVERAGEIFS(Mediciones!$K$6:$K$305,Mediciones!$C$6:$C$305,$A34,Mediciones!$D$6:$D$305,"Tela 3"),"")) | W34: =IF($A34="","",IF($N34="Despiece",IF(ISNUMBER(U34),U34*(1+Parametros!$B$22),IF(COUNTIFS(Despiece!$A$6:$A$705,$A34,Despiece!$D$6:$D$705,"Tela 3")>0,"",0)),IF($N34="Medición real",IF(ISNUMBER(V34),V34,IF(COUNTIFS(Mediciones!$C$6:$C$305,$A34,Mediciones!$D$6:$D$305,"Tela 3")>0,"",0)),IF(ISNUMBER(V34),V34,IF(ISNUMBER(U34),U34*(1+Parametros!$B$22),IF(OR(COUNTIFS(Despiece!$A$6:$A$705,$A34,Despiece!$D$6:$D$705,"Tela 3")>0,COUNTIFS(Mediciones!$C$6:$C$305,$A34,Mediciones!$D$6:$D$305,"Tela 3")>0),"",0)))))) -> 0 | Y34: =IF($A34="","",IF(ISNUMBER(X34),X34,IF(COUNTIFS(Despiece!$A$6:$A$705,$A34,Despiece!$E$6:$E$705,"Sublimada",Despiece!$F$6:$F$705,">0")>0,SUMIFS(Despiece!$F$6:$F$705,Despiece!$A$6:$A$705,$A34,Despiece!$E$6:$E$705,"Sublimada")*(1+Parametros!$B$22),IF(COUNTIFS(Despiece!$A$6:$A$705,$A34,Despiece!$E$6:$E$705,"Sublimada")=0,0,"")))) | Z34: =IF($A34="","",IFERROR(IF(ISNUMBER(Q34),IF(Q34=0,0,Q34*INDEX(Telas!$I$6:$I$105,MATCH(K34,Telas!$A$6:$A$105,0))),NA())+IF(ISNUMBER(T34),IF(T34=0,0,T34*INDEX(Telas!$I$6:$I$105,MATCH(L34,Telas!$A$6:$A$105,0))),NA())+IF(ISNUMBER(W34),IF(W34=0,0,W34*INDEX(Telas!$I$6:$I$105,MATCH(IF(M34="",K34,M34),Telas!$A$6:$A$105,0))),NA()),"")) | AA34: =IF($A34="","",IF(ISNUMBER(Y34),Y34*Parametros!$B$19,"")) | AB34: =IF(OR($A34="",F34=""),"",IFERROR(INDEX(Confeccion!$B$6:$B$125,MATCH(F34,Confeccion!$A$6:$A$125,0)),"")) -> 1900 | AC34: =IF($A34="","",IFERROR(N(H34)*IF(G34="",0,INDEX(Avios!$C$6:$C$65,MATCH(G34,Avios!$A$6:$A$65,0)))+N(J34)*IF(I34="",0,INDEX(Avios!$C$6:$C$65,MATCH(I34,Avios!$A$6:$A$65,0))),"")) -> 0 | AD34: =IF($A34="","",IFERROR(Z34+AA34+AB34+AC34,"")) | AE34: =IF(ISNUMBER(AD34),AD34*Parametros!$B$12,"") | AF34: =IF(AND(ISNUMBER(Q34),K34<>""),IFERROR(1/(Q34*INDEX(Telas!$G$6:$G$105,MATCH(K34,Telas!$A$6:$A$105,0))),""),"") | AG34: =IF($A34="","",IF(ISNUMBER(AD34),IF(AND(N(Y34)>0,N(Parametros!$B$19)=0),"Lista, pero sin costo de impresión (Parametros)","Lista"),IF(Q34="","Consumo tela principal (Despiece o Mediciones). ","")&IF(COUNTIFS(Mediciones!$C$6:$C$305,$A34,Mediciones!$K$6:$K$305,"")>0,"Pesar 1 m de la tela medida (Telas, kg por metro). ","")&IF(T34="","Consumo Tela 2. ","")&IF(W34="","Consumo Tela 3. ","")&IF(K34="","Elegir tela principal. ",IF(ISERROR(INDEX(Telas!$I$6:$I$105,MATCH(K34,Telas!$A$6:$A$105,0))*1),"Precio o peso por metro de "&K34&". ",""))&IF(AND(N(T34)>0,L34=""),"Elegir Tela 2. ",IF(AND(N(T34)>0,ISERROR(INDEX(Telas!$I$6:$I$105,MATCH(L34,Telas!$A$6:$A$105,0))*1)),"Precio o peso por metro de "&L34&". ",""))&IF(Y34="","Metros impresos. ","")&IF(F34="","Tipo de confección. ",IF(AB34="","Precio de confección. ","")))) -> Consumo tela principal (Despiece o Mediciones). Elegir tela principal. Metros impresos. | AH34: Confección sugerida por el tipo de molde: confirmar. Falta ficha de corte.
A35: 30 · BKHOMU03 | B35: Básquetbol, cuello redondo | C35: Básquetbol | D35: Camiseta | E35: Masculino | F35: Camiseta De Basket | K35: QUICKDRY | O35: =IF($A35="","",IF(COUNTIFS(Despiece!$A$6:$A$705,$A35,Despiece!$D$6:$D$705,"Tela principal",Despiece!$F$6:$F$705,">0")=0,"",SUMIFS(Despiece!$F$6:$F$705,Despiece!$A$6:$A$705,$A35,Despiece!$D$6:$D$705,"Tela principal"))) | P35: =IF($A35="","",IFERROR(AVERAGEIFS(Mediciones!$K$6:$K$305,Mediciones!$C$6:$C$305,$A35,Mediciones!$D$6:$D$305,"Tela principal"),"")) | Q35: =IF($A35="","",IF(N(IF($N35="Despiece",IF(ISNUMBER(O35),O35*(1+Parametros!$B$22),IF(COUNTIFS(Despiece!$A$6:$A$705,$A35,Despiece!$D$6:$D$705,"Tela principal")>0,"",0)),IF($N35="Medición real",IF(ISNUMBER(P35),P35,IF(COUNTIFS(Mediciones!$C$6:$C$305,$A35,Mediciones!$D$6:$D$305,"Tela principal")>0,"",0)),IF(ISNUMBER(P35),P35,IF(ISNUMBER(O35),O35*(1+Parametros!$B$22),IF(OR(COUNTIFS(Despiece!$A$6:$A$705,$A35,Despiece!$D$6:$D$705,"Tela principal")>0,COUNTIFS(Mediciones!$C$6:$C$305,$A35,Mediciones!$D$6:$D$305,"Tela principal")>0),"",0))))))=0,"",IF($N35="Despiece",IF(ISNUMBER(O35),O35*(1+Parametros!$B$22),IF(COUNTIFS(Despiece!$A$6:$A$705,$A35,Despiece!$D$6:$D$705,"Tela principal")>0,"",0)),IF($N35="Medición real",IF(ISNUMBER(P35),P35,IF(COUNTIFS(Mediciones!$C$6:$C$305,$A35,Mediciones!$D$6:$D$305,"Tela principal")>0,"",0)),IF(ISNUMBER(P35),P35,IF(ISNUMBER(O35),O35*(1+Parametros!$B$22),IF(OR(COUNTIFS(Despiece!$A$6:$A$705,$A35,Despiece!$D$6:$D$705,"Tela principal")>0,COUNTIFS(Mediciones!$C$6:$C$305,$A35,Mediciones!$D$6:$D$305,"Tela principal")>0),"",0))))))) | R35: =IF($A35="","",IF(COUNTIFS(Despiece!$A$6:$A$705,$A35,Despiece!$D$6:$D$705,"Tela 2",Despiece!$F$6:$F$705,">0")=0,"",SUMIFS(Despiece!$F$6:$F$705,Despiece!$A$6:$A$705,$A35,Despiece!$D$6:$D$705,"Tela 2"))) | S35: =IF($A35="","",IFERROR(AVERAGEIFS(Mediciones!$K$6:$K$305,Mediciones!$C$6:$C$305,$A35,Mediciones!$D$6:$D$305,"Tela 2"),"")) | T35: =IF($A35="","",IF($N35="Despiece",IF(ISNUMBER(R35),R35*(1+Parametros!$B$22),IF(COUNTIFS(Despiece!$A$6:$A$705,$A35,Despiece!$D$6:$D$705,"Tela 2")>0,"",0)),IF($N35="Medición real",IF(ISNUMBER(S35),S35,IF(COUNTIFS(Mediciones!$C$6:$C$305,$A35,Mediciones!$D$6:$D$305,"Tela 2")>0,"",0)),IF(ISNUMBER(S35),S35,IF(ISNUMBER(R35),R35*(1+Parametros!$B$22),IF(OR(COUNTIFS(Despiece!$A$6:$A$705,$A35,Despiece!$D$6:$D$705,"Tela 2")>0,COUNTIFS(Mediciones!$C$6:$C$305,$A35,Mediciones!$D$6:$D$305,"Tela 2")>0),"",0)))))) -> 0 | U35: =IF($A35="","",IF(COUNTIFS(Despiece!$A$6:$A$705,$A35,Despiece!$D$6:$D$705,"Tela 3",Despiece!$F$6:$F$705,">0")=0,"",SUMIFS(Despiece!$F$6:$F$705,Despiece!$A$6:$A$705,$A35,Despiece!$D$6:$D$705,"Tela 3"))) | V35: =IF($A35="","",IFERROR(AVERAGEIFS(Mediciones!$K$6:$K$305,Mediciones!$C$6:$C$305,$A35,Mediciones!$D$6:$D$305,"Tela 3"),"")) | W35: =IF($A35="","",IF($N35="Despiece",IF(ISNUMBER(U35),U35*(1+Parametros!$B$22),IF(COUNTIFS(Despiece!$A$6:$A$705,$A35,Despiece!$D$6:$D$705,"Tela 3")>0,"",0)),IF($N35="Medición real",IF(ISNUMBER(V35),V35,IF(COUNTIFS(Mediciones!$C$6:$C$305,$A35,Mediciones!$D$6:$D$305,"Tela 3")>0,"",0)),IF(ISNUMBER(V35),V35,IF(ISNUMBER(U35),U35*(1+Parametros!$B$22),IF(OR(COUNTIFS(Despiece!$A$6:$A$705,$A35,Despiece!$D$6:$D$705,"Tela 3")>0,COUNTIFS(Mediciones!$C$6:$C$305,$A35,Mediciones!$D$6:$D$305,"Tela 3")>0),"",0)))))) -> 0 | Y35: =IF($A35="","",IF(ISNUMBER(X35),X35,IF(COUNTIFS(Despiece!$A$6:$A$705,$A35,Despiece!$E$6:$E$705,"Sublimada",Despiece!$F$6:$F$705,">0")>0,SUMIFS(Despiece!$F$6:$F$705,Despiece!$A$6:$A$705,$A35,Despiece!$E$6:$E$705,"Sublimada")*(1+Parametros!$B$22),IF(COUNTIFS(Despiece!$A$6:$A$705,$A35,Despiece!$E$6:$E$705,"Sublimada")=0,0,"")))) | Z35: =IF($A35="","",IFERROR(IF(ISNUMBER(Q35),IF(Q35=0,0,Q35*INDEX(Telas!$I$6:$I$105,MATCH(K35,Telas!$A$6:$A$105,0))),NA())+IF(ISNUMBER(T35),IF(T35=0,0,T35*INDEX(Telas!$I$6:$I$105,MATCH(L35,Telas!$A$6:$A$105,0))),NA())+IF(ISNUMBER(W35),IF(W35=0,0,W35*INDEX(Telas!$I$6:$I$105,MATCH(IF(M35="",K35,M35),Telas!$A$6:$A$105,0))),NA()),"")) | AA35: =IF($A35="","",IF(ISNUMBER(Y35),Y35*Parametros!$B$19,"")) | AB35: =IF(OR($A35="",F35=""),"",IFERROR(INDEX(Confeccion!$B$6:$B$125,MATCH(F35,Confeccion!$A$6:$A$125,0)),"")) -> 1900 | AC35: =IF($A35="","",IFERROR(N(H35)*IF(G35="",0,INDEX(Avios!$C$6:$C$65,MATCH(G35,Avios!$A$6:$A$65,0)))+N(J35)*IF(I35="",0,INDEX(Avios!$C$6:$C$65,MATCH(I35,Avios!$A$6:$A$65,0))),"")) -> 0 | AD35: =IF($A35="","",IFERROR(Z35+AA35+AB35+AC35,"")) | AE35: =IF(ISNUMBER(AD35),AD35*Parametros!$B$12,"") | AF35: =IF(AND(ISNUMBER(Q35),K35<>""),IFERROR(1/(Q35*INDEX(Telas!$G$6:$G$105,MATCH(K35,Telas!$A$6:$A$105,0))),""),"") | AG35: =IF($A35="","",IF(ISNUMBER(AD35),IF(AND(N(Y35)>0,N(Parametros!$B$19)=0),"Lista, pero sin costo de impresión (Parametros)","Lista"),IF(Q35="","Consumo tela principal (Despiece o Mediciones). ","")&IF(COUNTIFS(Mediciones!$C$6:$C$305,$A35,Mediciones!$K$6:$K$305,"")>0,"Pesar 1 m de la tela medida (Telas, kg por metro). ","")&IF(T35="","Consumo Tela 2. ","")&IF(W35="","Consumo Tela 3. ","")&IF(K35="","Elegir tela principal. ",IF(ISERROR(INDEX(Telas!$I$6:$I$105,MATCH(K35,Telas!$A$6:$A$105,0))*1),"Precio o peso por metro de "&K35&". ",""))&IF(AND(N(T35)>0,L35=""),"Elegir Tela 2. ",IF(AND(N(T35)>0,ISERROR(INDEX(Telas!$I$6:$I$105,MATCH(L35,Telas!$A$6:$A$105,0))*1)),"Precio o peso por metro de "&L35&". ",""))&IF(Y35="","Metros impresos. ","")&IF(F35="","Tipo de confección. ",IF(AB35="","Precio de confección. ","")))) -> Consumo tela principal (Despiece o Mediciones). Pesar 1 m de la tela medida (Telas, kg por metro). Precio o peso por metro de QUICKDRY. Metros impresos. | AH35: Ficha OT 2425 (17 camisetas básquet). Falta metros impresos.
A36: 31 · BKINMUJU03 | B36: Básquetbol infantil, cuello redondo | C36: Básquetbol | D36: Camiseta | E36: Infantil Femenino | F36: Camiseta De Basket | O36: =IF($A36="","",IF(COUNTIFS(Despiece!$A$6:$A$705,$A36,Despiece!$D$6:$D$705,"Tela principal",Despiece!$F$6:$F$705,">0")=0,"",SUMIFS(Despiece!$F$6:$F$705,Despiece!$A$6:$A$705,$A36,Despiece!$D$6:$D$705,"Tela principal"))) | P36: =IF($A36="","",IFERROR(AVERAGEIFS(Mediciones!$K$6:$K$305,Mediciones!$C$6:$C$305,$A36,Mediciones!$D$6:$D$305,"Tela principal"),"")) | Q36: =IF($A36="","",IF(N(IF($N36="Despiece",IF(ISNUMBER(O36),O36*(1+Parametros!$B$22),IF(COUNTIFS(Despiece!$A$6:$A$705,$A36,Despiece!$D$6:$D$705,"Tela principal")>0,"",0)),IF($N36="Medición real",IF(ISNUMBER(P36),P36,IF(COUNTIFS(Mediciones!$C$6:$C$305,$A36,Mediciones!$D$6:$D$305,"Tela principal")>0,"",0)),IF(ISNUMBER(P36),P36,IF(ISNUMBER(O36),O36*(1+Parametros!$B$22),IF(OR(COUNTIFS(Despiece!$A$6:$A$705,$A36,Despiece!$D$6:$D$705,"Tela principal")>0,COUNTIFS(Mediciones!$C$6:$C$305,$A36,Mediciones!$D$6:$D$305,"Tela principal")>0),"",0))))))=0,"",IF($N36="Despiece",IF(ISNUMBER(O36),O36*(1+Parametros!$B$22),IF(COUNTIFS(Despiece!$A$6:$A$705,$A36,Despiece!$D$6:$D$705,"Tela principal")>0,"",0)),IF($N36="Medición real",IF(ISNUMBER(P36),P36,IF(COUNTIFS(Mediciones!$C$6:$C$305,$A36,Mediciones!$D$6:$D$305,"Tela principal")>0,"",0)),IF(ISNUMBER(P36),P36,IF(ISNUMBER(O36),O36*(1+Parametros!$B$22),IF(OR(COUNTIFS(Despiece!$A$6:$A$705,$A36,Despiece!$D$6:$D$705,"Tela principal")>0,COUNTIFS(Mediciones!$C$6:$C$305,$A36,Mediciones!$D$6:$D$305,"Tela principal")>0),"",0))))))) | R36: =IF($A36="","",IF(COUNTIFS(Despiece!$A$6:$A$705,$A36,Despiece!$D$6:$D$705,"Tela 2",Despiece!$F$6:$F$705,">0")=0,"",SUMIFS(Despiece!$F$6:$F$705,Despiece!$A$6:$A$705,$A36,Despiece!$D$6:$D$705,"Tela 2"))) | S36: =IF($A36="","",IFERROR(AVERAGEIFS(Mediciones!$K$6:$K$305,Mediciones!$C$6:$C$305,$A36,Mediciones!$D$6:$D$305,"Tela 2"),"")) | T36: =IF($A36="","",IF($N36="Despiece",IF(ISNUMBER(R36),R36*(1+Parametros!$B$22),IF(COUNTIFS(Despiece!$A$6:$A$705,$A36,Despiece!$D$6:$D$705,"Tela 2")>0,"",0)),IF($N36="Medición real",IF(ISNUMBER(S36),S36,IF(COUNTIFS(Mediciones!$C$6:$C$305,$A36,Mediciones!$D$6:$D$305,"Tela 2")>0,"",0)),IF(ISNUMBER(S36),S36,IF(ISNUMBER(R36),R36*(1+Parametros!$B$22),IF(OR(COUNTIFS(Despiece!$A$6:$A$705,$A36,Despiece!$D$6:$D$705,"Tela 2")>0,COUNTIFS(Mediciones!$C$6:$C$305,$A36,Mediciones!$D$6:$D$305,"Tela 2")>0),"",0)))))) -> 0 | U36: =IF($A36="","",IF(COUNTIFS(Despiece!$A$6:$A$705,$A36,Despiece!$D$6:$D$705,"Tela 3",Despiece!$F$6:$F$705,">0")=0,"",SUMIFS(Despiece!$F$6:$F$705,Despiece!$A$6:$A$705,$A36,Despiece!$D$6:$D$705,"Tela 3"))) | V36: =IF($A36="","",IFERROR(AVERAGEIFS(Mediciones!$K$6:$K$305,Mediciones!$C$6:$C$305,$A36,Mediciones!$D$6:$D$305,"Tela 3"),"")) | W36: =IF($A36="","",IF($N36="Despiece",IF(ISNUMBER(U36),U36*(1+Parametros!$B$22),IF(COUNTIFS(Despiece!$A$6:$A$705,$A36,Despiece!$D$6:$D$705,"Tela 3")>0,"",0)),IF($N36="Medición real",IF(ISNUMBER(V36),V36,IF(COUNTIFS(Mediciones!$C$6:$C$305,$A36,Mediciones!$D$6:$D$305,"Tela 3")>0,"",0)),IF(ISNUMBER(V36),V36,IF(ISNUMBER(U36),U36*(1+Parametros!$B$22),IF(OR(COUNTIFS(Despiece!$A$6:$A$705,$A36,Despiece!$D$6:$D$705,"Tela 3")>0,COUNTIFS(Mediciones!$C$6:$C$305,$A36,Mediciones!$D$6:$D$305,"Tela 3")>0),"",0)))))) -> 0 | Y36: =IF($A36="","",IF(ISNUMBER(X36),X36,IF(COUNTIFS(Despiece!$A$6:$A$705,$A36,Despiece!$E$6:$E$705,"Sublimada",Despiece!$F$6:$F$705,">0")>0,SUMIFS(Despiece!$F$6:$F$705,Despiece!$A$6:$A$705,$A36,Despiece!$E$6:$E$705,"Sublimada")*(1+Parametros!$B$22),IF(COUNTIFS(Despiece!$A$6:$A$705,$A36,Despiece!$E$6:$E$705,"Sublimada")=0,0,"")))) | Z36: =IF($A36="","",IFERROR(IF(ISNUMBER(Q36),IF(Q36=0,0,Q36*INDEX(Telas!$I$6:$I$105,MATCH(K36,Telas!$A$6:$A$105,0))),NA())+IF(ISNUMBER(T36),IF(T36=0,0,T36*INDEX(Telas!$I$6:$I$105,MATCH(L36,Telas!$A$6:$A$105,0))),NA())+IF(ISNUMBER(W36),IF(W36=0,0,W36*INDEX(Telas!$I$6:$I$105,MATCH(IF(M36="",K36,M36),Telas!$A$6:$A$105,0))),NA()),"")) | AA36: =IF($A36="","",IF(ISNUMBER(Y36),Y36*Parametros!$B$19,"")) | AB36: =IF(OR($A36="",F36=""),"",IFERROR(INDEX(Confeccion!$B$6:$B$125,MATCH(F36,Confeccion!$A$6:$A$125,0)),"")) -> 1900 | AC36: =IF($A36="","",IFERROR(N(H36)*IF(G36="",0,INDEX(Avios!$C$6:$C$65,MATCH(G36,Avios!$A$6:$A$65,0)))+N(J36)*IF(I36="",0,INDEX(Avios!$C$6:$C$65,MATCH(I36,Avios!$A$6:$A$65,0))),"")) -> 0 | AD36: =IF($A36="","",IFERROR(Z36+AA36+AB36+AC36,"")) | AE36: =IF(ISNUMBER(AD36),AD36*Parametros!$B$12,"") | AF36: =IF(AND(ISNUMBER(Q36),K36<>""),IFERROR(1/(Q36*INDEX(Telas!$G$6:$G$105,MATCH(K36,Telas!$A$6:$A$105,0))),""),"") | AG36: =IF($A36="","",IF(ISNUMBER(AD36),IF(AND(N(Y36)>0,N(Parametros!$B$19)=0),"Lista, pero sin costo de impresión (Parametros)","Lista"),IF(Q36="","Consumo tela principal (Despiece o Mediciones). ","")&IF(COUNTIFS(Mediciones!$C$6:$C$305,$A36,Mediciones!$K$6:$K$305,"")>0,"Pesar 1 m de la tela medida (Telas, kg por metro). ","")&IF(T36="","Consumo Tela 2. ","")&IF(W36="","Consumo Tela 3. ","")&IF(K36="","Elegir tela principal. ",IF(ISERROR(INDEX(Telas!$I$6:$I$105,MATCH(K36,Telas!$A$6:$A$105,0))*1),"Precio o peso por metro de "&K36&". ",""))&IF(AND(N(T36)>0,L36=""),"Elegir Tela 2. ",IF(AND(N(T36)>0,ISERROR(INDEX(Telas!$I$6:$I$105,MATCH(L36,Telas!$A$6:$A$105,0))*1)),"Precio o peso por metro de "&L36&". ",""))&IF(Y36="","Metros impresos. ","")&IF(F36="","Tipo de confección. ",IF(AB36="","Precio de confección. ","")))) -> Consumo tela principal (Despiece o Mediciones). Elegir tela principal. Metros impresos. | AH36: Confección sugerida por el tipo de molde: confirmar. Falta ficha de corte.
