Workbook

Sheet Como_usar
A1: RECETAS DE COSTO — PLAYMAKER (v2)
A2: Armado desde el Sistema de Costeo v2. Todo dato dice "Por confirmar" hasta que lo valides.
A4: QUÉ HACE
B5: Por cada producto calcula: COSTO DE PRODUCCIÓN + GASTOS FIJOS (como % del precio) = GANANCIA REAL, y el PRECIO MÍNIMO para no perder plata.
B6: Precio mínimo = costo de producción ÷ (1 − recargo − ganancia deseada).
A7: COLORES
B8: AZUL = lo escribes tú. GRIS = se calcula solo, no tocar. Semáforo: PIERDE (rojo) · BAJO META (amarillo) · OK (verde).
A9: LAS HOJAS
B10: Recetas — una fila por producto. Aquí ves la ganancia, el precio mínimo y qué datos faltan.
B11: Parametros — el recargo %, tu meta de ganancia y el costo de papel + tinta por metro.
B12: Gastos_Ventas — gastos fijos y ventas de los últimos 3 meses. De aquí sale el recargo.
B13: Precios — precio de cada tela y avío. Confeccion — lo que se paga al taller por prenda.
B14: Catalogo — todos los productos vendidos y cuáles ya tienen receta completa.
A15: PARA COMPLETAR UNA RECETA (en la hoja Recetas)
B16: 1) Elige la tela en la lista y escribe cuántos kg gasta una prenda (kg de la ficha de corte ÷ prendas cortadas). Si lleva malla u otra tela, usa "Tela 2".
B17: 2) Escribe los metros impresos por prenda (0 si no se sublima). 3) Elige el tipo de confección.
B18: 4) Si lleva avíos (cuello, cierre, elástico, etiqueta), suma su valor en "Otros avíos". 5) Cuando todo esté verificado, cambia el estado a "Confirmado".
B19: Para un producto nuevo, usa la primera fila vacía al final de la hoja.
A20: CADA TRIMESTRE (próximo: diciembre 2026)
B21: En Gastos_Ventas cambia los nombres de los meses y escribe los gastos y ventas de los 3 meses más recientes. El recargo y todas las recetas se actualizan solos.
A22: QUÉ CAMBIÓ RESPECTO DEL SISTEMA ANTERIOR (y del borrador v1)
B23: • Sueldos: ya no se cobran dentro de la receta y además en los gastos fijos (se contaban dos veces). Ahora todos los sueldos están en gastos de fábrica.
B24: • Camiseta Fútbol Playmaker (la más vendida): el consumo que tenía (0,161 kg) era del short. Queda en blanco hasta tener su ficha de corte.
B25: • Camiseta básquet: el consumo mezclaba camiseta y short. Ahora usa solo la camiseta (0,203 kg).
B26: • Camisetas Pro: ahora incluyen la malla (MESH) que aparece en la ficha de corte y antes no se cobraba.
B27: • Short Rugby: ahora usa la confección de short de rugby ($2.200) y no la de fútbol ($1.700).
B28: • Estampado ya no se cobra a todas las prendas por defecto.
A29: PENDIENTES QUE AFECTAN LOS RESULTADOS
B30: ="• Papel y tinta: "&IF(Parametros!$B$27=0,"SIN DATO → las prendas sublimadas salen más baratas de lo real.","ingresado ("&TEXT(Parametros!$B$27,"$#,##0")&" por metro).") -> • Papel y tinta: SIN DATO → las prendas sublimadas salen más baratas de lo real.
B31: ="• Recetas completas: "&COUNTIF(Catalogo!F6:F200,"Completa")&" · con datos faltantes: "&COUNTIF(Catalogo!F6:F200,"Faltan datos") -> • Recetas completas: 6 · con datos faltantes: 68
B32: ="• Precios por confirmar: "&(COUNTIF(Precios!E5:E200,"Por confirmar")+COUNTIF(Confeccion!D5:D200,"Por confirmar"))&" · telas sin precio: "&COUNTIF(Precios!E5:E200,"SIN PRECIO") -> • Precios por confirmar: 88 · telas sin precio: 1
B33: • Gastos: el archivo original trae un solo mes; se repitió en los 3 meses. Reemplazar con el gasto real.
B34: • Consumos de tela: casi todos vienen de 1 solo corte. Cada ficha de corte nueva los hace más confiables.

Sheet Recetas
A1: RECETAS — costo de producción, gastos y ganancia por prenda
A2: Una fila = un producto. Llena solo las columnas azules (E a M). Todo lo gris se calcula solo. Fuente de datos iniciales: Sistema de Costeo v2.
A3: ="Recargo usado: "&TEXT(Parametros!$B$14,"0.0%")&" del precio (fábrica "&TEXT(Parametros!$B$12,"0.0%")&" + comercial "&TEXT(Parametros!$B$13,"0.0%")&") · Meta de ganancia: "&TEXT(Parametros!$B$18,"0%")&" · Impresión: "&IF(Parametros!$B$27=0,"SIN COSTO (pendiente)",TEXT(Parametros!$B$27,"$#,##0")&" por metro") -> Recargo usado: 48.0% del precio (fábrica 35.3% + comercial 12.7%) · Meta de ganancia: 10% · Impresión: SIN COSTO (pendiente)
A4: PRODUCTO | E4: DATOS DE LA RECETA (los llenas tú) | O4: COSTO DE PRODUCCIÓN ($ por prenda) | T4: RESULTADO AL PRECIO ACTUAL
A5: Código | B5: Producto | C5: Tipo | D5: Unid. vendidas jun–sep | E5: Precio venta neto ($) | F5: Tela principal | G5: Kg tela por prenda | H5: Tela 2 (malla, etc.) | I5: Kg tela 2 por prenda | J5: Metros impresos por prenda | K5: Confección (tipo) | L5: Otros avíos ($ por prenda) | M5: Estado del dato | N5: Notas | O5: $ Telas | P5: $ Papel y tinta | Q5: $ Confección | R5: $ Avíos | S5: COSTO DE PRODUCCIÓN | T5: Gastos de fábrica | U5: Gastos comerciales | V5: GANANCIA ($) | W5: GANANCIA (%) | X5: Precio mínimo (sin perder) | Y5: Precio mínimo (con meta) | Z5: Semáforo | AA5: Qué falta
A6: FUTCSUBMC | B6: Camiseta Fútbol Playmaker, m/c | C6: Juego | D6: 198 | E6: 15994 | F6: CIRE BLANCO | K6: Camiseta De Futbol | M6: Por confirmar | N6: FALTA CONSUMO: el sistema anterior usaba 0,161 kg pero ese dato es del SHORT (OT 2547 y 2588). Hacer ficha de corte de camiseta adulto. | O6: =IF(B6="","",IFERROR(G6*INDEX(Precios!$D$5:$D$120,MATCH(F6,Precios!$A$5:$A$120,0)),0)+IF(H6="",0,IFERROR(I6*INDEX(Precios!$D$5:$D$120,MATCH(H6,Precios!$A$5:$A$120,0)),0))) -> 0 | P6: =IF(B6="","",N(J6)*Parametros!$B$27) -> 0 | Q6: =IF(B6="","",IFERROR(INDEX(Confeccion!$B$5:$B$100,MATCH(K6,Confeccion!$A$5:$A$100,0)),0)) -> 2000 | R6: =IF(B6="","",N(L6)) -> 0 | S6: =IF(B6="","",IF(AND(F6<>"",ISNUMBER(G6),ISNUMBER(IFERROR(INDEX(Precios!$D$5:$D$120,MATCH(F6,Precios!$A$5:$A$120,0)),"x")),OR(H6="",ISNUMBER(IFERROR(INDEX(Precios!$D$5:$D$120,MATCH(H6,Precios!$A$5:$A$120,0)),"x"))),J6<>"",K6<>"",Q6>0),SUM(O6:R6),"")) | T6: =IF(AND(S6<>"",ISNUMBER(E6)),E6*Parametros!$B$12,"") | U6: =IF(AND(S6<>"",ISNUMBER(E6)),E6*Parametros!$B$13,"") | V6: =IF(AND(S6<>"",ISNUMBER(E6)),E6-S6-T6-U6,"") | W6: =IF(AND(S6<>"",ISNUMBER(E6)),V6/E6,"") | X6: =IF(OR(S6="",Parametros!$B$14>=1),"",S6/(1-Parametros!$B$14)) | Y6: =IF(OR(S6="",Parametros!$B$14+Parametros!$B$18>=1),"",S6/(1-Parametros!$B$14-Parametros!$B$18)) | Z6: =IF(B6="","",IF(S6="","FALTAN DATOS",IF(NOT(ISNUMBER(E6)),"FALTA PRECIO",IF(V6<0,"PIERDE",IF(W6<Parametros!$B$18,"BAJO META","OK"))))) -> FALTAN DATOS | AA6: =IF(B6="","",IF(F6="","Tela. ","")&IF(NOT(ISNUMBER(G6)),"Kg de tela. ","")&IF(AND(F6<>"",NOT(ISNUMBER(IFERROR(INDEX(Precios!$D$5:$D$120,MATCH(F6,Precios!$A$5:$A$120,0)),"x")))),"Tela sin precio. ","")&IF(AND(H6<>"",NOT(ISNUMBER(IFERROR(INDEX(Precios!$D$5:$D$120,MATCH(H6,Precios!$A$5:$A$120,0)),"x")))),"Tela 2 sin precio. ","")&IF(J6="","Metros impresos. ","")&IF(AND(N(J6)>0,Parametros!$B$27=0),"Impresión sin costo. ","")&IF(K6="","Confección. ",IF(Q6=0,"Confección sin valor. ",""))&IF(NOT(ISNUMBER(E6)),"Precio de venta. ","")) -> Kg de tela. Metros impresos.
A7: FUTCSUBREDMC | B7: Camiseta Fútbol Playmaker Cuello Redondo m/c | C7: Juego | D7: 190 | E7: 16073 | F7: CIRE BLANCO | K7: Camiseta De Futbol | M7: Por confirmar | N7: FALTA CONSUMO (ver Camiseta Fútbol Playmaker m/c). | O7: =IF(B7="","",IFERROR(G7*INDEX(Precios!$D$5:$D$120,MATCH(F7,Precios!$A$5:$A$120,0)),0)+IF(H7="",0,IFERROR(I7*INDEX(Precios!$D$5:$D$120,MATCH(H7,Precios!$A$5:$A$120,0)),0))) -> 0 | P7: =IF(B7="","",N(J7)*Parametros!$B$27) -> 0 | Q7: =IF(B7="","",IFERROR(INDEX(Confeccion!$B$5:$B$100,MATCH(K7,Confeccion!$A$5:$A$100,0)),0)) -> 2000 | R7: =IF(B7="","",N(L7)) -> 0 | S7: =IF(B7="","",IF(AND(F7<>"",ISNUMBER(G7),ISNUMBER(IFERROR(INDEX(Precios!$D$5:$D$120,MATCH(F7,Precios!$A$5:$A$120,0)),"x")),OR(H7="",ISNUMBER(IFERROR(INDEX(Precios!$D$5:$D$120,MATCH(H7,Precios!$A$5:$A$120,0)),"x"))),J7<>"",K7<>"",Q7>0),SUM(O7:R7),"")) | T7: =IF(AND(S7<>"",ISNUMBER(E7)),E7*Parametros!$B$12,"") | U7: =IF(AND(S7<>"",ISNUMBER(E7)),E7*Parametros!$B$13,"") | V7: =IF(AND(S7<>"",ISNUMBER(E7)),E7-S7-T7-U7,"") | W7: =IF(AND(S7<>"",ISNUMBER(E7)),V7/E7,"") | X7: =IF(OR(S7="",Parametros!$B$14>=1),"",S7/(1-Parametros!$B$14)) | Y7: =IF(OR(S7="",Parametros!$B$14+Parametros!$B$18>=1),"",S7/(1-Parametros!$B$14-Parametros!$B$18)) | Z7: =IF(B7="","",IF(S7="","FALTAN DATOS",IF(NOT(ISNUMBER(E7)),"FALTA PRECIO",IF(V7<0,"PIERDE",IF(W7<Parametros!$B$18,"BAJO META","OK"))))) -> FALTAN DATOS | AA7: =IF(B7="","",IF(F7="","Tela. ","")&IF(NOT(ISNUMBER(G7)),"Kg de tela. ","")&IF(AND(F7<>"",NOT(ISNUMBER(IFERROR(INDEX(Precios!$D$5:$D$120,MATCH(F7,Precios!$A$5:$A$120,0)),"x")))),"Tela sin precio. ","")&IF(AND(H7<>"",NOT(ISNUMBER(IFERROR(INDEX(Precios!$D$5:$D$120,MATCH(H7,Precios!$A$5:$A$120,0)),"x")))),"Tela 2 sin precio. ","")&IF(J7="","Metros impresos. ","")&IF(AND(N(J7)>0,Parametros!$B$27=0),"Impresión sin costo. ","")&IF(K7="","Confección. ",IF(Q7=0,"Confección sin valor. ",""))&IF(NOT(ISNUMBER(E7)),"Precio de venta. ","")) -> Kg de tela. Metros impresos.
A8: FUTCSUBPROREDMC | B8: Camiseta Fútbol Pro Playmaker Cuello Redondo m/c | C8: Juego | D8: 160 | E8: 18403 | F8: MONTESIMONE TRAINING (fut pro) | G8: 0.12 | H8: MESH | I8: 0.0775 | J8: 1.9 | K8: Camiseta De Futbol | M8: Por confirmar | N8: Ficha OT 2547 (20 prendas masc.). Femenino dio 0,1225 kg (OT 2257). Metros: la ficha dice 1,9 (38 m / 20), la receta anterior 1,2 y la hoja de reprocesos 1,125 → confirmar. | O8: =IF(B8="","",IFERROR(G8*INDEX(Precios!$D$5:$D$120,MATCH(F8,Precios!$A$5:$A$120,0)),0)+IF(H8="",0,IFERROR(I8*INDEX(Precios!$D$5:$D$120,MATCH(H8,Precios!$A$5:$A$120,0)),0))) -> 1020.47 | P8: =IF(B8="","",N(J8)*Parametros!$B$27) -> 0 | Q8: =IF(B8="","",IFERROR(INDEX(Confeccion!$B$5:$B$100,MATCH(K8,Confeccion!$A$5:$A$100,0)),0)) -> 2000 | R8: =IF(B8="","",N(L8)) -> 0 | S8: =IF(B8="","",IF(AND(F8<>"",ISNUMBER(G8),ISNUMBER(IFERROR(INDEX(Precios!$D$5:$D$120,MATCH(F8,Precios!$A$5:$A$120,0)),"x")),OR(H8="",ISNUMBER(IFERROR(INDEX(Precios!$D$5:$D$120,MATCH(H8,Precios!$A$5:$A$120,0)),"x"))),J8<>"",K8<>"",Q8>0),SUM(O8:R8),"")) -> 3020.47 | T8: =IF(AND(S8<>"",ISNUMBER(E8)),E8*Parametros!$B$12,"") -> 6495.2752 | U8: =IF(AND(S8<>"",ISNUMBER(E8)),E8*Parametros!$B$13,"") -> 2331.5946 | V8: =IF(AND(S8<>"",ISNUMBER(E8)),E8-S8-T8-U8,"") -> 6555.6601 | W8: =IF(AND(S8<>"",ISNUMBER(E8)),V8/E8,"") -> 0.3562278 | X8: =IF(OR(S8="",Parametros!$B$14>=1),"",S8/(1-Parametros!$B$14)) -> 5804.6109 | Y8: =IF(OR(S8="",Parametros!$B$14+Parametros!$B$18>=1),"",S8/(1-Parametros!$B$14-Parametros!$B$18)) -> 7185.4873 | Z8: =IF(B8="","",IF(S8="","FALTAN DATOS",IF(NOT(ISNUMBER(E8)),"FALTA PRECIO",IF(V8<0,"PIERDE",IF(W8<Parametros!$B$18,"BAJO META","OK"))))) -> OK | AA8: =IF(B8="","",IF(F8="","Tela. ","")&IF(NOT(ISNUMBER(G8)),"Kg de tela. ","")&IF(AND(F8<>"",NOT(ISNUMBER(IFERROR(INDEX(Precios!$D$5:$D$120,MATCH(F8,Precios!$A$5:$A$120,0)),"x")))),"Tela sin precio. ","")&IF(AND(H8<>"",NOT(ISNUMBER(IFERROR(INDEX(Precios!$D$5:$D$120,MATCH(H8,Precios!$A$5:$A$120,0)),"x")))),"Tela 2 sin precio. ","")&IF(J8="","Metros impresos. ","")&IF(AND(N(J8)>0,Parametros!$B$27=0),"Impresión sin costo. ","")&IF(K8="","Confección. ",IF(Q8=0,"Confección sin valor. ",""))&IF(NOT(ISNUMBER(E8)),"Precio de venta. ","")) -> Impresión sin costo.
A9: VOLMASC-CSUB-V-MC | B9: Camiseta Voley fem Playmaker, V m/c | C9: Juego | D9: 139 | E9: 17563 | K9: Camiseta Voley | M9: Por confirmar | N9: Confección sugerida por el nombre: confirmar. | O9: =IF(B9="","",IFERROR(G9*INDEX(Precios!$D$5:$D$120,MATCH(F9,Precios!$A$5:$A$120,0)),0)+IF(H9="",0,IFERROR(I9*INDEX(Precios!$D$5:$D$120,MATCH(H9,Precios!$A$5:$A$120,0)),0))) -> 0 | P9: =IF(B9="","",N(J9)*Parametros!$B$27) -> 0 | Q9: =IF(B9="","",IFERROR(INDEX(Confeccion!$B$5:$B$100,MATCH(K9,Confeccion!$A$5:$A$100,0)),0)) -> 1700 | R9: =IF(B9="","",N(L9)) -> 0 | S9: =IF(B9="","",IF(AND(F9<>"",ISNUMBER(G9),ISNUMBER(IFERROR(INDEX(Precios!$D$5:$D$120,MATCH(F9,Precios!$A$5:$A$120,0)),"x")),OR(H9="",ISNUMBER(IFERROR(INDEX(Precios!$D$5:$D$120,MATCH(H9,Precios!$A$5:$A$120,0)),"x"))),J9<>"",K9<>"",Q9>0),SUM(O9:R9),"")) | T9: =IF(AND(S9<>"",ISNUMBER(E9)),E9*Parametros!$B$12,"") | U9: =IF(AND(S9<>"",ISNUMBER(E9)),E9*Parametros!$B$13,"") | V9: =IF(AND(S9<>"",ISNUMBER(E9)),E9-S9-T9-U9,"") | W9: =IF(AND(S9<>"",ISNUMBER(E9)),V9/E9,"") | X9: =IF(OR(S9="",Parametros!$B$14>=1),"",S9/(1-Parametros!$B$14)) | Y9: =IF(OR(S9="",Parametros!$B$14+Parametros!$B$18>=1),"",S9/(1-Parametros!$B$14-Parametros!$B$18)) | Z9: =IF(B9="","",IF(S9="","FALTAN DATOS",IF(NOT(ISNUMBER(E9)),"FALTA PRECIO",IF(V9<0,"PIERDE",IF(W9<Parametros!$B$18,"BAJO META","OK"))))) -> FALTAN DATOS | AA9: =IF(B9="","",IF(F9="","Tela. ","")&IF(NOT(ISNUMBER(G9)),"Kg de tela. ","")&IF(AND(F9<>"",NOT(ISNUMBER(IFERROR(INDEX(Precios!$D$5:$D$120,MATCH(F9,Precios!$A$5:$A$120,0)),"x")))),"Tela sin precio. ","")&IF(AND(H9<>"",NOT(ISNUMBER(IFERROR(INDEX(Precios!$D$5:$D$120,MATCH(H9,Precios!$A$5:$A$120,0)),"x")))),"Tela 2 sin precio. ","")&IF(J9="","Metros impresos. ","")&IF(AND(N(J9)>0,Parametros!$B$27=0),"Impresión sin costo. ","")&IF(K9="","Confección. ",IF(Q9=0,"Confección sin valor. ",""))&IF(NOT(ISNUMBER(E9)),"Precio de venta. ","")) -> Tela. Kg de tela. Metros impresos.
A10: FUTCSUBPROMC | B10: Camiseta Fútbol Pro Playmaker, m/c | C10: Juego | D10: 109 | E10: 18403 | F10: MONTESIMONE TRAINING (fut pro) | G10: 0.12 | H10: MESH | I10: 0.0775 | J10: 1.9 | K10: Camiseta De Futbol | M10: Por confirmar | N10: Igual que Pro cuello redondo (OT 2547). Confirmar metros impresos. | O10: =IF(B10="","",IFERROR(G10*INDEX(Precios!$D$5:$D$120,MATCH(F10,Precios!$A$5:$A$120,0)),0)+IF(H10="",0,IFERROR(I10*INDEX(Precios!$D$5:$D$120,MATCH(H10,Precios!$A$5:$A$120,0)),0))) -> 1020.47 | P10: =IF(B10="","",N(J10)*Parametros!$B$27) -> 0 | Q10: =IF(B10="","",IFERROR(INDEX(Confeccion!$B$5:$B$100,MATCH(K10,Confeccion!$A$5:$A$100,0)),0)) -> 2000 | R10: =IF(B10="","",N(L10)) -> 0 | S10: =IF(B10="","",IF(AND(F10<>"",ISNUMBER(G10),ISNUMBER(IFERROR(INDEX(Precios!$D$5:$D$120,MATCH(F10,Precios!$A$5:$A$120,0)),"x")),OR(H10="",ISNUMBER(IFERROR(INDEX(Precios!$D$5:$D$120,MATCH(H10,Precios!$A$5:$A$120,0)),"x"))),J10<>"",K10<>"",Q10>0),SUM(O10:R10),"")) -> 3020.47 | T10: =IF(AND(S10<>"",ISNUMBER(E10)),E10*Parametros!$B$12,"") -> 6495.2752 | U10: =IF(AND(S10<>"",ISNUMBER(E10)),E10*Parametros!$B$13,"") -> 2331.5946 | V10: =IF(AND(S10<>"",ISNUMBER(E10)),E10-S10-T10-U10,"") -> 6555.6601 | W10: =IF(AND(S10<>"",ISNUMBER(E10)),V10/E10,"") -> 0.3562278 | X10: =IF(OR(S10="",Parametros!$B$14>=1),"",S10/(1-Parametros!$B$14)) -> 5804.6109 | Y10: =IF(OR(S10="",Parametros!$B$14+Parametros!$B$18>=1),"",S10/(1-Parametros!$B$14-Parametros!$B$18)) -> 7185.4873 | Z10: =IF(B10="","",IF(S10="","FALTAN DATOS",IF(NOT(ISNUMBER(E10)),"FALTA PRECIO",IF(V10<0,"PIERDE",IF(W10<Parametros!$B$18,"BAJO META","OK"))))) -> OK | AA10: =IF(B10="","",IF(F10="","Tela. ","")&IF(NOT(ISNUMBER(G10)),"Kg de tela. ","")&IF(AND(F10<>"",NOT(ISNUMBER(IFERROR(INDEX(Precios!$D$5:$D$120,MATCH(F10,Precios!$A$5:$A$120,0)),"x")))),"Tela sin precio. ","")&IF(AND(H10<>"",NOT(ISNUMBER(IFERROR(INDEX(Precios!$D$5:$D$120,MATCH(H10,Precios!$A$5:$A$120,0)),"x")))),"Tela 2 sin precio. ","")&IF(J10="","Metros impresos. ","")&IF(AND(N(J10)>0,Parametros!$B$27=0),"Impresión sin costo. ","")&IF(K10="","Confección. ",IF(Q10=0,"Confección sin valor. ",""))&IF(NOT(ISNUMBER(E10)),"Precio de venta. ","")) -> Impresión sin costo.
A11: FUTCSUBMC-V | B11: Camiseta Fútbol Playmaker, V m/c | C11: Juego | D11: 109 | E11: 16589 | F11: CIRE BLANCO | K11: Camiseta De Futbol | M11: Por confirmar | N11: FALTA CONSUMO (ver Camiseta Fútbol Playmaker m/c). | O11: =IF(B11="","",IFERROR(G11*INDEX(Precios!$D$5:$D$120,MATCH(F11,Precios!$A$5:$A$120,0)),0)+IF(H11="",0,IFERROR(I11*INDEX(Precios!$D$5:$D$120,MATCH(H11,Precios!$A$5:$A$120,0)),0))) -> 0 | P11: =IF(B11="","",N(J11)*Parametros!$B$27) -> 0 | Q11: =IF(B11="","",IFERROR(INDEX(Confeccion!$B$5:$B$100,MATCH(K11,Confeccion!$A$5:$A$100,0)),0)) -> 2000 | R11: =IF(B11="","",N(L11)) -> 0 | S11: =IF(B11="","",IF(AND(F11<>"",ISNUMBER(G11),ISNUMBER(IFERROR(INDEX(Precios!$D$5:$D$120,MATCH(F11,Precios!$A$5:$A$120,0)),"x")),OR(H11="",ISNUMBER(IFERROR(INDEX(Precios!$D$5:$D$120,MATCH(H11,Precios!$A$5:$A$120,0)),"x"))),J11<>"",K11<>"",Q11>0),SUM(O11:R11),"")) | T11: =IF(AND(S11<>"",ISNUMBER(E11)),E11*Parametros!$B$12,"") | U11: =IF(AND(S11<>"",ISNUMBER(E11)),E11*Parametros!$B$13,"") | V11: =IF(AND(S11<>"",ISNUMBER(E11)),E11-S11-T11-U11,"") | W11: =IF(AND(S11<>"",ISNUMBER(E11)),V11/E11,"") | X11: =IF(OR(S11="",Parametros!$B$14>=1),"",S11/(1-Parametros!$B$14)) | Y11: =IF(OR(S11="",Parametros!$B$14+Parametros!$B$18>=1),"",S11/(1-Parametros!$B$14-Parametros!$B$18)) | Z11: =IF(B11="","",IF(S11="","FALTAN DATOS",IF(NOT(ISNUMBER(E11)),"FALTA PRECIO",IF(V11<0,"PIERDE",IF(W11<Parametros!$B$18,"BAJO META","OK"))))) -> FALTAN DATOS | AA11: =IF(B11="","",IF(F11="","Tela. ","")&IF(NOT(ISNUMBER(G11)),"Kg de tela. ","")&IF(AND(F11<>"",NOT(ISNUMBER(IFERROR(INDEX(Precios!$D$5:$D$120,MATCH(F11,Precios!$A$5:$A$120,0)),"x")))),"Tela sin precio. ","")&IF(AND(H11<>"",NOT(ISNUMBER(IFERROR(INDEX(Precios!$D$5:$D$120,MATCH(H11,Precios!$A$5:$A$120,0)),"x")))),"Tela 2 sin precio. ","")&IF(J11="","Metros impresos. ","")&IF(AND(N(J11)>0,Parametros!$B$27=0),"Impresión sin costo. ","")&IF(K11="","Confección. ",IF(Q11=0,"Confección sin valor. ",""))&IF(NOT(ISNUMBER(E11)),"Precio de venta. ","")) -> Kg de tela. Metros impresos.
A12: SALPOLPRESLISA | B12: Polera de Presentación Lisa | C12: Salida | D12: 109 | E12: 17004 | M12: Por confirmar | O12: =IF(B12="","",IFERROR(G12*INDEX(Precios!$D$5:$D$120,MATCH(F12,Precios!$A$5:$A$120,0)),0)+IF(H12="",0,IFERROR(I12*INDEX(Precios!$D$5:$D$120,MATCH(H12,Precios!$A$5:$A$120,0)),0))) -> 0 | P12: =IF(B12="","",N(J12)*Parametros!$B$27) -> 0 | Q12: =IF(B12="","",IFERROR(INDEX(Confeccion!$B$5:$B$100,MATCH(K12,Confeccion!$A$5:$A$100,0)),0)) -> 0 | R12: =IF(B12="","",N(L12)) -> 0 | S12: =IF(B12="","",IF(AND(F12<>"",ISNUMBER(G12),ISNUMBER(IFERROR(INDEX(Precios!$D$5:$D$120,MATCH(F12,Precios!$A$5:$A$120,0)),"x")),OR(H12="",ISNUMBER(IFERROR(INDEX(Precios!$D$5:$D$120,MATCH(H12,Precios!$A$5:$A$120,0)),"x"))),J12<>"",K12<>"",Q12>0),SUM(O12:R12),"")) | T12: =IF(AND(S12<>"",ISNUMBER(E12)),E12*Parametros!$B$12,"") | U12: =IF(AND(S12<>"",ISNUMBER(E12)),E12*Parametros!$B$13,"") | V12: =IF(AND(S12<>"",ISNUMBER(E12)),E12-S12-T12-U12,"") | W12: =IF(AND(S12<>"",ISNUMBER(E12)),V12/E12,"") | X12: =IF(OR(S12="",Parametros!$B$14>=1),"",S12/(1-Parametros!$B$14)) | Y12: =IF(OR(S12="",Parametros!$B$14+Parametros!$B$18>=1),"",S12/(1-Parametros!$B$14-Parametros!$B$18)) | Z12: =IF(B12="","",IF(S12="","FALTAN DATOS",IF(NOT(ISNUMBER(E12)),"FALTA PRECIO",IF(V12<0,"PIERDE",IF(W12<Parametros!$B$18,"BAJO META","OK"))))) -> FALTAN DATOS | AA12: =IF(B12="","",IF(F12="","Tela. ","")&IF(NOT(ISNUMBER(G12)),"Kg de tela. ","")&IF(AND(F12<>"",NOT(ISNUMBER(IFERROR(INDEX(Precios!$D$5:$D$120,MATCH(F12,Precios!$A$5:$A$120,0)),"x")))),"Tela sin precio. ","")&IF(AND(H12<>"",NOT(ISNUMBER(IFERROR(INDEX(Precios!$D$5:$D$120,MATCH(H12,Precios!$A$5:$A$120,0)),"x")))),"Tela 2 sin precio. ","")&IF(J12="","Metros impresos. ","")&IF(AND(N(J12)>0,Parametros!$B$27=0),"Impresión sin costo. ","")&IF(K12="","Confección. ",IF(Q12=0,"Confección sin valor. ",""))&IF(NOT(ISNUMBER(E12)),"Precio de venta. ","")) -> Tela. Kg de tela. Metros impresos. Confección.
A13: CSUBRUGSFROSA | B13: CAMISETA DE RUGBY STADE FRANCAIS ANIVERSARIO (ROSADA) | C13: Juego | D13: 100 | E13: 25714 | M13: Por confirmar | O13: =IF(B13="","",IFERROR(G13*INDEX(Precios!$D$5:$D$120,MATCH(F13,Precios!$A$5:$A$120,0)),0)+IF(H13="",0,IFERROR(I13*INDEX(Precios!$D$5:$D$120,MATCH(H13,Precios!$A$5:$A$120,0)),0))) -> 0 | P13: =IF(B13="","",N(J13)*Parametros!$B$27) -> 0 | Q13: =IF(B13="","",IFERROR(INDEX(Confeccion!$B$5:$B$100,MATCH(K13,Confeccion!$A$5:$A$100,0)),0)) -> 0 | R13: =IF(B13="","",N(L13)) -> 0 | S13: =IF(B13="","",IF(AND(F13<>"",ISNUMBER(G13),ISNUMBER(IFERROR(INDEX(Precios!$D$5:$D$120,MATCH(F13,Precios!$A$5:$A$120,0)),"x")),OR(H13="",ISNUMBER(IFERROR(INDEX(Precios!$D$5:$D$120,MATCH(H13,Precios!$A$5:$A$120,0)),"x"))),J13<>"",K13<>"",Q13>0),SUM(O13:R13),"")) | T13: =IF(AND(S13<>"",ISNUMBER(E13)),E13*Parametros!$B$12,"") | U13: =IF(AND(S13<>"",ISNUMBER(E13)),E13*Parametros!$B$13,"") | V13: =IF(AND(S13<>"",ISNUMBER(E13)),E13-S13-T13-U13,"") | W13: =IF(AND(S13<>"",ISNUMBER(E13)),V13/E13,"") | X13: =IF(OR(S13="",Parametros!$B$14>=1),"",S13/(1-Parametros!$B$14)) | Y13: =IF(OR(S13="",Parametros!$B$14+Parametros!$B$18>=1),"",S13/(1-Parametros!$B$14-Parametros!$B$18)) | Z13: =IF(B13="","",IF(S13="","FALTAN DATOS",IF(NOT(ISNUMBER(E13)),"FALTA PRECIO",IF(V13<0,"PIERDE",IF(W13<Parametros!$B$18,"BAJO META","OK"))))) -> FALTAN DATOS | AA13: =IF(B13="","",IF(F13="","Tela. ","")&IF(NOT(ISNUMBER(G13)),"Kg de tela. ","")&IF(AND(F13<>"",NOT(ISNUMBER(IFERROR(INDEX(Precios!$D$5:$D$120,MATCH(F13,Precios!$A$5:$A$120,0)),"x")))),"Tela sin precio. ","")&IF(AND(H13<>"",NOT(ISNUMBER(IFERROR(INDEX(Precios!$D$5:$D$120,MATCH(H13,Precios!$A$5:$A$120,0)),"x")))),"Tela 2 sin precio. ","")&IF(J13="","Metros impresos. ","")&IF(AND(N(J13)>0,Parametros!$B$27=0),"Impresión sin costo. ","")&IF(K13="","Confección. ",IF(Q13=0,"Confección sin valor. ",""))&IF(NOT(ISNUMBER(E13)),"Precio de venta. ","")) -> Tela. Kg de tela. Metros impresos. Confección.
A14: SAL-PLA-SUB-MC | B14: Polera de presentación Sublim m/c | C14: Salida | D14: 99 | E14: 18729 | M14: Por confirmar | O14: =IF(B14="","",IFERROR(G14*INDEX(Precios!$D$5:$D$120,MATCH(F14,Precios!$A$5:$A$120,0)),0)+IF(H14="",0,IFERROR(I14*INDEX(Precios!$D$5:$D$120,MATCH(H14,Precios!$A$5:$A$120,0)),0))) -> 0 | P14: =IF(B14="","",N(J14)*Parametros!$B$27) -> 0 | Q14: =IF(B14="","",IFERROR(INDEX(Confeccion!$B$5:$B$100,MATCH(K14,Confeccion!$A$5:$A$100,0)),0)) -> 0 | R14: =IF(B14="","",N(L14)) -> 0 | S14: =IF(B14="","",IF(AND(F14<>"",ISNUMBER(G14),ISNUMBER(IFERROR(INDEX(Precios!$D$5:$D$120,MATCH(F14,Precios!$A$5:$A$120,0)),"x")),OR(H14="",ISNUMBER(IFERROR(INDEX(Precios!$D$5:$D$120,MATCH(H14,Precios!$A$5:$A$120,0)),"x"))),J14<>"",K14<>"",Q14>0),SUM(O14:R14),"")) | T14: =IF(AND(S14<>"",ISNUMBER(E14)),E14*Parametros!$B$12,"") | U14: =IF(AND(S14<>"",ISNUMBER(E14)),E14*Parametros!$B$13,"") | V14: =IF(AND(S14<>"",ISNUMBER(E14)),E14-S14-T14-U14,"") | W14: =IF(AND(S14<>"",ISNUMBER(E14)),V14/E14,"") | X14: =IF(OR(S14="",Parametros!$B$14>=1),"",S14/(1-Parametros!$B$14)) | Y14: =IF(OR(S14="",Parametros!$B$14+Parametros!$B$18>=1),"",S14/(1-Parametros!$B$14-Parametros!$B$18)) | Z14: =IF(B14="","",IF(S14="","FALTAN DATOS",IF(NOT(ISNUMBER(E14)),"FALTA PRECIO",IF(V14<0,"PIERDE",IF(W14<Parametros!$B$18,"BAJO META","OK"))))) -> FALTAN DATOS | AA14: =IF(B14="","",IF(F14="","Tela. ","")&IF(NOT(ISNUMBER(G14)),"Kg de tela. ","")&IF(AND(F14<>"",NOT(ISNUMBER(IFERROR(INDEX(Precios!$D$5:$D$120,MATCH(F14,Precios!$A$5:$A$120,0)),"x")))),"Tela sin precio. ","")&IF(AND(H14<>"",NOT(ISNUMBER(IFERROR(INDEX(Precios!$D$5:$D$120,MATCH(H14,Precios!$A$5:$A$120,0)),"x")))),"Tela 2 sin precio. ","")&IF(J14="","Metros impresos. ","")&IF(AND(N(J14)>0,Parametros!$B$27=0),"Impresión sin costo. ","")&IF(K14="","Confección. ",IF(Q14=0,"Confección sin valor. ",""))&IF(NOT(ISNUMBER(E14)),"Precio de venta. ","")) -> Tela. Kg de tela. Metros impresos. Confección.
A15: POL-CSUB-POL-MC | B15: Polera Playmaker, Cuello Redondo m/c | C15: Juego | D15: 96 | E15: 15588 | M15: Por confirmar | O15: =IF(B15="","",IFERROR(G15*INDEX(Precios!$D$5:$D$120,MATCH(F15,Precios!$A$5:$A$120,0)),0)+IF(H15="",0,IFERROR(I15*INDEX(Precios!$D$5:$D$120,MATCH(H15,Precios!$A$5:$A$120,0)),0))) -> 0 | P15: =IF(B15="","",N(J15)*Parametros!$B$27) -> 0 | Q15: =IF(B15="","",IFERROR(INDEX(Confeccion!$B$5:$B$100,MATCH(K15,Confeccion!$A$5:$A$100,0)),0)) -> 0 | R15: =IF(B15="","",N(L15)) -> 0 | S15: =IF(B15="","",IF(AND(F15<>"",ISNUMBER(G15),ISNUMBER(IFERROR(INDEX(Precios!$D$5:$D$120,MATCH(F15,Precios!$A$5:$A$120,0)),"x")),OR(H15="",ISNUMBER(IFERROR(INDEX(Precios!$D$5:$D$120,MATCH(H15,Precios!$A$5:$A$120,0)),"x"))),J15<>"",K15<>"",Q15>0),SUM(O15:R15),"")) | T15: =IF(AND(S15<>"",ISNUMBER(E15)),E15*Parametros!$B$12,"") | U15: =IF(AND(S15<>"",ISNUMBER(E15)),E15*Parametros!$B$13,"") | V15: =IF(AND(S15<>"",ISNUMBER(E15)),E15-S15-T15-U15,"") | W15: =IF(AND(S15<>"",ISNUMBER(E15)),V15/E15,"") | X15: =IF(OR(S15="",Parametros!$B$14>=1),"",S15/(1-Parametros!$B$14)) | Y15: =IF(OR(S15="",Parametros!$B$14+Parametros!$B$18>=1),"",S15/(1-Parametros!$B$14-Parametros!$B$18)) | Z15: =IF(B15="","",IF(S15="","FALTAN DATOS",IF(NOT(ISNUMBER(E15)),"FALTA PRECIO",IF(V15<0,"PIERDE",IF(W15<Parametros!$B$18,"BAJO META","OK"))))) -> FALTAN DATOS | AA15: =IF(B15="","",IF(F15="","Tela. ","")&IF(NOT(ISNUMBER(G15)),"Kg de tela. ","")&IF(AND(F15<>"",NOT(ISNUMBER(IFERROR(INDEX(Precios!$D$5:$D$120,MATCH(F15,Precios!$A$5:$A$120,0)),"x")))),"Tela sin precio. ","")&IF(AND(H15<>"",NOT(ISNUMBER(IFERROR(INDEX(Precios!$D$5:$D$120,MATCH(H15,Precios!$A$5:$A$120,0)),"x")))),"Tela 2 sin precio. ","")&IF(J15="","Metros impresos. ","")&IF(AND(N(J15)>0,Parametros!$B$27=0),"Impresión sin costo. ","")&IF(K15="","Confección. ",IF(Q15=0,"Confección sin valor. ",""))&IF(NOT(ISNUMBER(E15)),"Precio de venta. ","")) -> Tela. Kg de tela. Metros impresos. Confección.
A16: RUGCSUBPRO | B16: Camiseta Rugby Pro Pmk | C16: Juego | D16: 93 | E16: 21765 | M16: Por confirmar | O16: =IF(B16="","",IFERROR(G16*INDEX(Precios!$D$5:$D$120,MATCH(F16,Precios!$A$5:$A$120,0)),0)+IF(H16="",0,IFERROR(I16*INDEX(Precios!$D$5:$D$120,MATCH(H16,Precios!$A$5:$A$120,0)),0))) -> 0 | P16: =IF(B16="","",N(J16)*Parametros!$B$27) -> 0 | Q16: =IF(B16="","",IFERROR(INDEX(Confeccion!$B$5:$B$100,MATCH(K16,Confeccion!$A$5:$A$100,0)),0)) -> 0 | R16: =IF(B16="","",N(L16)) -> 0 | S16: =IF(B16="","",IF(AND(F16<>"",ISNUMBER(G16),ISNUMBER(IFERROR(INDEX(Precios!$D$5:$D$120,MATCH(F16,Precios!$A$5:$A$120,0)),"x")),OR(H16="",ISNUMBER(IFERROR(INDEX(Precios!$D$5:$D$120,MATCH(H16,Precios!$A$5:$A$120,0)),"x"))),J16<>"",K16<>"",Q16>0),SUM(O16:R16),"")) | T16: =IF(AND(S16<>"",ISNUMBER(E16)),E16*Parametros!$B$12,"") | U16: =IF(AND(S16<>"",ISNUMBER(E16)),E16*Parametros!$B$13,"") | V16: =IF(AND(S16<>"",ISNUMBER(E16)),E16-S16-T16-U16,"") | W16: =IF(AND(S16<>"",ISNUMBER(E16)),V16/E16,"") | X16: =IF(OR(S16="",Parametros!$B$14>=1),"",S16/(1-Parametros!$B$14)) | Y16: =IF(OR(S16="",Parametros!$B$14+Parametros!$B$18>=1),"",S16/(1-Parametros!$B$14-Parametros!$B$18)) | Z16: =IF(B16="","",IF(S16="","FALTAN DATOS",IF(NOT(ISNUMBER(E16)),"FALTA PRECIO",IF(V16<0,"PIERDE",IF(W16<Parametros!$B$18,"BAJO META","OK"))))) -> FALTAN DATOS | AA16: =IF(B16="","",IF(F16="","Tela. ","")&IF(NOT(ISNUMBER(G16)),"Kg de tela. ","")&IF(AND(F16<>"",NOT(ISNUMBER(IFERROR(INDEX(Precios!$D$5:$D$120,MATCH(F16,Precios!$A$5:$A$120,0)),"x")))),"Tela sin precio. ","")&IF(AND(H16<>"",NOT(ISNUMBER(IFERROR(INDEX(Precios!$D$5:$D$120,MATCH(H16,Precios!$A$5:$A$120,0)),"x")))),"Tela 2 sin precio. ","")&IF(J16="","Metros impresos. ","")&IF(AND(N(J16)>0,Parametros!$B$27=0),"Impresión sin costo. ","")&IF(K16="","Confección. ",IF(Q16=0,"Confección sin valor. ",""))&IF(NOT(ISNUMBER(E16)),"Precio de venta. ","")) -> Tela. Kg de tela. Metros impresos. Confección.
A17: MDBZCOMENTPITSUB | B17: Conjunto Polerón de Entrenamiento + Buzo Pitillo Subl | C17: Salida | D17: 76 | E17: 44010 | M17: Por confirmar | N17: Son 2 prendas: armar como kit (polerón + pantalón). | O17: =IF(B17="","",IFERROR(G17*INDEX(Precios!$D$5:$D$120,MATCH(F17,Precios!$A$5:$A$120,0)),0)+IF(H17="",0,IFERROR(I17*INDEX(Precios!$D$5:$D$120,MATCH(H17,Precios!$A$5:$A$120,0)),0))) -> 0 | P17: =IF(B17="","",N(J17)*Parametros!$B$27) -> 0 | Q17: =IF(B17="","",IFERROR(INDEX(Confeccion!$B$5:$B$100,MATCH(K17,Confeccion!$A$5:$A$100,0)),0)) -> 0 | R17: =IF(B17="","",N(L17)) -> 0 | S17: =IF(B17="","",IF(AND(F17<>"",ISNUMBER(G17),ISNUMBER(IFERROR(INDEX(Precios!$D$5:$D$120,MATCH(F17,Precios!$A$5:$A$120,0)),"x")),OR(H17="",ISNUMBER(IFERROR(INDEX(Precios!$D$5:$D$120,MATCH(H17,Precios!$A$5:$A$120,0)),"x"))),J17<>"",K17<>"",Q17>0),SUM(O17:R17),"")) | T17: =IF(AND(S17<>"",ISNUMBER(E17)),E17*Parametros!$B$12,"") | U17: =IF(AND(S17<>"",ISNUMBER(E17)),E17*Parametros!$B$13,"") | V17: =IF(AND(S17<>"",ISNUMBER(E17)),E17-S17-T17-U17,"") | W17: =IF(AND(S17<>"",ISNUMBER(E17)),V17/E17,"") | X17: =IF(OR(S17="",Parametros!$B$14>=1),"",S17/(1-Parametros!$B$14)) | Y17: =IF(OR(S17="",Parametros!$B$14+Parametros!$B$18>=1),"",S17/(1-Parametros!$B$14-Parametros!$B$18)) | Z17: =IF(B17="","",IF(S17="","FALTAN DATOS",IF(NOT(ISNUMBER(E17)),"FALTA PRECIO",IF(V17<0,"PIERDE",IF(W17<Parametros!$B$18,"BAJO META","OK"))))) -> FALTAN DATOS | AA17: =IF(B17="","",IF(F17="","Tela. ","")&IF(NOT(ISNUMBER(G17)),"Kg de tela. ","")&IF(AND(F17<>"",NOT(ISNUMBER(IFERROR(INDEX(Precios!$D$5:$D$120,MATCH(F17,Precios!$A$5:$A$120,0)),"x")))),"Tela sin precio. ","")&IF(AND(H17<>"",NOT(ISNUMBER(IFERROR(INDEX(Precios!$D$5:$D$120,MATCH(H17,Precios!$A$5:$A$120,0)),"x")))),"Tela 2 sin precio. ","")&IF(J17="","Metros impresos. ","")&IF(AND(N(J17)>0,Parametros!$B$27=0),"Impresión sin costo. ","")&IF(K17="","Confección. ",IF(Q17=0,"Confección sin valor. ",""))&IF(NOT(ISNUMBER(E17)),"Precio de venta. ","")) -> Tela. Kg de tela. Metros impresos. Confección.
A18: FUTCSUBPROPIQMC | B18: Camiseta Fútbol Pro Playmaker, Piqué m/c | C18: Juego | D18: 66 | E18: 21554 | K18: Camiseta De Futbol | M18: Por confirmar | N18: Confección sugerida por el nombre: confirmar. | O18: =IF(B18="","",IFERROR(G18*INDEX(Precios!$D$5:$D$120,MATCH(F18,Precios!$A$5:$A$120,0)),0)+IF(H18="",0,IFERROR(I18*INDEX(Precios!$D$5:$D$120,MATCH(H18,Precios!$A$5:$A$120,0)),0))) -> 0 | P18: =IF(B18="","",N(J18)*Parametros!$B$27) -> 0 | Q18: =IF(B18="","",IFERROR(INDEX(Confeccion!$B$5:$B$100,MATCH(K18,Confeccion!$A$5:$A$100,0)),0)) -> 2000 | R18: =IF(B18="","",N(L18)) -> 0 | S18: =IF(B18="","",IF(AND(F18<>"",ISNUMBER(G18),ISNUMBER(IFERROR(INDEX(Precios!$D$5:$D$120,MATCH(F18,Precios!$A$5:$A$120,0)),"x")),OR(H18="",ISNUMBER(IFERROR(INDEX(Precios!$D$5:$D$120,MATCH(H18,Precios!$A$5:$A$120,0)),"x"))),J18<>"",K18<>"",Q18>0),SUM(O18:R18),"")) | T18: =IF(AND(S18<>"",ISNUMBER(E18)),E18*Parametros!$B$12,"") | U18: =IF(AND(S18<>"",ISNUMBER(E18)),E18*Parametros!$B$13,"") | V18: =IF(AND(S18<>"",ISNUMBER(E18)),E18-S18-T18-U18,"") | W18: =IF(AND(S18<>"",ISNUMBER(E18)),V18/E18,"") | X18: =IF(OR(S18="",Parametros!$B$14>=1),"",S18/(1-Parametros!$B$14)) | Y18: =IF(OR(S18="",Parametros!$B$14+Parametros!$B$18>=1),"",S18/(1-Parametros!$B$14-Parametros!$B$18)) | Z18: =IF(B18="","",IF(S18="","FALTAN DATOS",IF(NOT(ISNUMBER(E18)),"FALTA PRECIO",IF(V18<0,"PIERDE",IF(W18<Parametros!$B$18,"BAJO META","OK"))))) -> FALTAN DATOS | AA18: =IF(B18="","",IF(F18="","Tela. ","")&IF(NOT(ISNUMBER(G18)),"Kg de tela. ","")&IF(AND(F18<>"",NOT(ISNUMBER(IFERROR(INDEX(Precios!$D$5:$D$120,MATCH(F18,Precios!$A$5:$A$120,0)),"x")))),"Tela sin precio. ","")&IF(AND(H18<>"",NOT(ISNUMBER(IFERROR(INDEX(Precios!$D$5:$D$120,MATCH(H18,Precios!$A$5:$A$120,0)),"x")))),"Tela 2 sin precio. ","")&IF(J18="","Metros impresos. ","")&IF(AND(N(J18)>0,Parametros!$B$27=0),"Impresión sin costo. ","")&IF(K18="","Confección. ",IF(Q18=0,"Confección sin valor. ",""))&IF(NOT(ISNUMBER(E18)),"Precio de venta. ","")) -> Tela. Kg de tela. Metros impresos.
A19: RUNCSUBPROSM | B19: Camiseta Running Pro s/m | C19: Juego | D19: 65 | E19: 19244 | F19: 5K NACIONAL (running pro) | G19: 0.082 | J19: 1.2 | K19: Camiseta De Running | M19: Por confirmar | N19: Ficha OT 2223 (25 prendas). Metros 1,2 viene de la receta anterior, sin ficha: confirmar. | O19: =IF(B19="","",IFERROR(G19*INDEX(Precios!$D$5:$D$120,MATCH(F19,Precios!$A$5:$A$120,0)),0)+IF(H19="",0,IFERROR(I19*INDEX(Precios!$D$5:$D$120,MATCH(H19,Precios!$A$5:$A$120,0)),0))) -> 348.008 | P19: =IF(B19="","",N(J19)*Parametros!$B$27) -> 0 | Q19: =IF(B19="","",IFERROR(INDEX(Confeccion!$B$5:$B$100,MATCH(K19,Confeccion!$A$5:$A$100,0)),0)) -> 1800 | R19: =IF(B19="","",N(L19)) -> 0 | S19: =IF(B19="","",IF(AND(F19<>"",ISNUMBER(G19),ISNUMBER(IFERROR(INDEX(Precios!$D$5:$D$120,MATCH(F19,Precios!$A$5:$A$120,0)),"x")),OR(H19="",ISNUMBER(IFERROR(INDEX(Precios!$D$5:$D$120,MATCH(H19,Precios!$A$5:$A$120,0)),"x"))),J19<>"",K19<>"",Q19>0),SUM(O19:R19),"")) -> 2148.008 | T19: =IF(AND(S19<>"",ISNUMBER(E19)),E19*Parametros!$B$12,"") -> 6792.1033 | U19: =IF(AND(S19<>"",ISNUMBER(E19)),E19*Parametros!$B$13,"") -> 2438.1464 | V19: =IF(AND(S19<>"",ISNUMBER(E19)),E19-S19-T19-U19,"") -> 7865.7424 | W19: =IF(AND(S19<>"",ISNUMBER(E19)),V19/E19,"") -> 0.40873739 | X19: =IF(OR(S19="",Parametros!$B$14>=1),"",S19/(1-Parametros!$B$14)) -> 4127.9505 | Y19: =IF(OR(S19="",Parametros!$B$14+Parametros!$B$18>=1),"",S19/(1-Parametros!$B$14-Parametros!$B$18)) -> 5109.9611 | Z19: =IF(B19="","",IF(S19="","FALTAN DATOS",IF(NOT(ISNUMBER(E19)),"FALTA PRECIO",IF(V19<0,"PIERDE",IF(W19<Parametros!$B$18,"BAJO META","OK"))))) -> OK | AA19: =IF(B19="","",IF(F19="","Tela. ","")&IF(NOT(ISNUMBER(G19)),"Kg de tela. ","")&IF(AND(F19<>"",NOT(ISNUMBER(IFERROR(INDEX(Precios!$D$5:$D$120,MATCH(F19,Precios!$A$5:$A$120,0)),"x")))),"Tela sin precio. ","")&IF(AND(H19<>"",NOT(ISNUMBER(IFERROR(INDEX(Precios!$D$5:$D$120,MATCH(H19,Precios!$A$5:$A$120,0)),"x")))),"Tela 2 sin precio. ","")&IF(J19="","Metros impresos. ","")&IF(AND(N(J19)>0,Parametros!$B$27=0),"Impresión sin costo. ","")&IF(K19="","Confección. ",IF(Q19=0,"Confección sin valor. ",""))&IF(NOT(ISNUMBER(E19)),"Precio de venta. ","")) -> Impresión sin costo.
A20: SAL-CTV-SUB-SG | B20: CORTAVIENTO SUBLIMADO | C20: Salida | D20: 62 | E20: 36050 | M20: Por confirmar | O20: =IF(B20="","",IFERROR(G20*INDEX(Precios!$D$5:$D$120,MATCH(F20,Precios!$A$5:$A$120,0)),0)+IF(H20="",0,IFERROR(I20*INDEX(Precios!$D$5:$D$120,MATCH(H20,Precios!$A$5:$A$120,0)),0))) -> 0 | P20: =IF(B20="","",N(J20)*Parametros!$B$27) -> 0 | Q20: =IF(B20="","",IFERROR(INDEX(Confeccion!$B$5:$B$100,MATCH(K20,Confeccion!$A$5:$A$100,0)),0)) -> 0 | R20: =IF(B20="","",N(L20)) -> 0 | S20: =IF(B20="","",IF(AND(F20<>"",ISNUMBER(G20),ISNUMBER(IFERROR(INDEX(Precios!$D$5:$D$120,MATCH(F20,Precios!$A$5:$A$120,0)),"x")),OR(H20="",ISNUMBER(IFERROR(INDEX(Precios!$D$5:$D$120,MATCH(H20,Precios!$A$5:$A$120,0)),"x"))),J20<>"",K20<>"",Q20>0),SUM(O20:R20),"")) | T20: =IF(AND(S20<>"",ISNUMBER(E20)),E20*Parametros!$B$12,"") | U20: =IF(AND(S20<>"",ISNUMBER(E20)),E20*Parametros!$B$13,"") | V20: =IF(AND(S20<>"",ISNUMBER(E20)),E20-S20-T20-U20,"") | W20: =IF(AND(S20<>"",ISNUMBER(E20)),V20/E20,"") | X20: =IF(OR(S20="",Parametros!$B$14>=1),"",S20/(1-Parametros!$B$14)) | Y20: =IF(OR(S20="",Parametros!$B$14+Parametros!$B$18>=1),"",S20/(1-Parametros!$B$14-Parametros!$B$18)) | Z20: =IF(B20="","",IF(S20="","FALTAN DATOS",IF(NOT(ISNUMBER(E20)),"FALTA PRECIO",IF(V20<0,"PIERDE",IF(W20<Parametros!$B$18,"BAJO META","OK"))))) -> FALTAN DATOS | AA20: =IF(B20="","",IF(F20="","Tela. ","")&IF(NOT(ISNUMBER(G20)),"Kg de tela. ","")&IF(AND(F20<>"",NOT(ISNUMBER(IFERROR(INDEX(Precios!$D$5:$D$120,MATCH(F20,Precios!$A$5:$A$120,0)),"x")))),"Tela sin precio. ","")&IF(AND(H20<>"",NOT(ISNUMBER(IFERROR(INDEX(Precios!$D$5:$D$120,MATCH(H20,Precios!$A$5:$A$120,0)),"x")))),"Tela 2 sin precio. ","")&IF(J20="","Metros impresos. ","")&IF(AND(N(J20)>0,Parametros!$B$27=0),"Impresión sin costo. ","")&IF(K20="","Confección. ",IF(Q20=0,"Confección sin valor. ",""))&IF(NOT(ISNUMBER(E20)),"Precio de venta. ","")) -> Tela. Kg de tela. Metros impresos. Confección.
A21: RUG-SHO-BAS | B21: Short Rugby Basic | C21: Juego | D21: 61 | E21: 12507 | F21: GABARDINA | G21: 0.1842 | J21: 0 | K21: Short De Rugby | M21: Por confirmar | N21: Ficha OT 205 (19 prendas). El sistema anterior usaba confección de short de fútbol ($1.700); se cambió a Short De Rugby ($2.200). | O21: =IF(B21="","",IFERROR(G21*INDEX(Precios!$D$5:$D$120,MATCH(F21,Precios!$A$5:$A$120,0)),0)+IF(H21="",0,IFERROR(I21*INDEX(Precios!$D$5:$D$120,MATCH(H21,Precios!$A$5:$A$120,0)),0))) -> 506.55 | P21: =IF(B21="","",N(J21)*Parametros!$B$27) -> 0 | Q21: =IF(B21="","",IFERROR(INDEX(Confeccion!$B$5:$B$100,MATCH(K21,Confeccion!$A$5:$A$100,0)),0)) -> 2200 | R21: =IF(B21="","",N(L21)) -> 0 | S21: =IF(B21="","",IF(AND(F21<>"",ISNUMBER(G21),ISNUMBER(IFERROR(INDEX(Precios!$D$5:$D$120,MATCH(F21,Precios!$A$5:$A$120,0)),"x")),OR(H21="",ISNUMBER(IFERROR(INDEX(Precios!$D$5:$D$120,MATCH(H21,Precios!$A$5:$A$120,0)),"x"))),J21<>"",K21<>"",Q21>0),SUM(O21:R21),"")) -> 2706.55 | T21: =IF(AND(S21<>"",ISNUMBER(E21)),E21*Parametros!$B$12,"") -> 4414.3024 | U21: =IF(AND(S21<>"",ISNUMBER(E21)),E21*Parametros!$B$13,"") -> 1584.5924 | V21: =IF(AND(S21<>"",ISNUMBER(E21)),E21-S21-T21-U21,"") -> 3801.5552 | W21: =IF(AND(S21<>"",ISNUMBER(E21)),V21/E21,"") -> 0.3039542 | X21: =IF(OR(S21="",Parametros!$B$14>=1),"",S21/(1-Parametros!$B$14)) -> 5201.3328 | Y21: =IF(OR(S21="",Parametros!$B$14+Parametros!$B$18>=1),"",S21/(1-Parametros!$B$14-Parametros!$B$18)) -> 6438.6936 | Z21: =IF(B21="","",IF(S21="","FALTAN DATOS",IF(NOT(ISNUMBER(E21)),"FALTA PRECIO",IF(V21<0,"PIERDE",IF(W21<Parametros!$B$18,"BAJO META","OK"))))) -> OK | AA21: =IF(B21="","",IF(F21="","Tela. ","")&IF(NOT(ISNUMBER(G21)),"Kg de tela. ","")&IF(AND(F21<>"",NOT(ISNUMBER(IFERROR(INDEX(Precios!$D$5:$D$120,MATCH(F21,Precios!$A$5:$A$120,0)),"x")))),"Tela sin precio. ","")&IF(AND(H21<>"",NOT(ISNUMBER(IFERROR(INDEX(Precios!$D$5:$D$120,MATCH(H21,Precios!$A$5:$A$120,0)),"x")))),"Tela 2 sin precio. ","")&IF(J21="","Metros impresos. ","")&IF(AND(N(J21)>0,Parametros!$B$27=0),"Impresión sin costo. ","")&IF(K21="","Confección. ",IF(Q21=0,"Confección sin valor. ",""))&IF(NOT(ISNUMBER(E21)),"Precio de venta. ",""))
A22: SALPTPESUB | B22: Conjunto Polerón de Entrenamiento + Pitillo | C22: Salida | D22: 60 | E22: 41933 | M22: Por confirmar | N22: Son 2 prendas: armar como kit (polerón + pantalón). | O22: =IF(B22="","",IFERROR(G22*INDEX(Precios!$D$5:$D$120,MATCH(F22,Precios!$A$5:$A$120,0)),0)+IF(H22="",0,IFERROR(I22*INDEX(Precios!$D$5:$D$120,MATCH(H22,Precios!$A$5:$A$120,0)),0))) -> 0 | P22: =IF(B22="","",N(J22)*Parametros!$B$27) -> 0 | Q22: =IF(B22="","",IFERROR(INDEX(Confeccion!$B$5:$B$100,MATCH(K22,Confeccion!$A$5:$A$100,0)),0)) -> 0 | R22: =IF(B22="","",N(L22)) -> 0 | S22: =IF(B22="","",IF(AND(F22<>"",ISNUMBER(G22),ISNUMBER(IFERROR(INDEX(Precios!$D$5:$D$120,MATCH(F22,Precios!$A$5:$A$120,0)),"x")),OR(H22="",ISNUMBER(IFERROR(INDEX(Precios!$D$5:$D$120,MATCH(H22,Precios!$A$5:$A$120,0)),"x"))),J22<>"",K22<>"",Q22>0),SUM(O22:R22),"")) | T22: =IF(AND(S22<>"",ISNUMBER(E22)),E22*Parametros!$B$12,"") | U22: =IF(AND(S22<>"",ISNUMBER(E22)),E22*Parametros!$B$13,"") | V22: =IF(AND(S22<>"",ISNUMBER(E22)),E22-S22-T22-U22,"") | W22: =IF(AND(S22<>"",ISNUMBER(E22)),V22/E22,"") | X22: =IF(OR(S22="",Parametros!$B$14>=1),"",S22/(1-Parametros!$B$14)) | Y22: =IF(OR(S22="",Parametros!$B$14+Parametros!$B$18>=1),"",S22/(1-Parametros!$B$14-Parametros!$B$18)) | Z22: =IF(B22="","",IF(S22="","FALTAN DATOS",IF(NOT(ISNUMBER(E22)),"FALTA PRECIO",IF(V22<0,"PIERDE",IF(W22<Parametros!$B$18,"BAJO META","OK"))))) -> FALTAN DATOS | AA22: =IF(B22="","",IF(F22="","Tela. ","")&IF(NOT(ISNUMBER(G22)),"Kg de tela. ","")&IF(AND(F22<>"",NOT(ISNUMBER(IFERROR(INDEX(Precios!$D$5:$D$120,MATCH(F22,Precios!$A$5:$A$120,0)),"x")))),"Tela sin precio. ","")&IF(AND(H22<>"",NOT(ISNUMBER(IFERROR(INDEX(Precios!$D$5:$D$120,MATCH(H22,Precios!$A$5:$A$120,0)),"x")))),"Tela 2 sin precio. ","")&IF(J22="","Metros impresos. ","")&IF(AND(N(J22)>0,Parametros!$B$27=0),"Impresión sin costo. ","")&IF(K22="","Confección. ",IF(Q22=0,"Confección sin valor. ",""))&IF(NOT(ISNUMBER(E22)),"Precio de venta. ","")) -> Tela. Kg de tela. Metros impresos. Confección.
A23: FUTSHOLIS | B23: Short Fútbol Playmaker Liso | C23: Juego | D23: 55 | E23: 8059 | F23: CIRE BLANCO | G23: 0.1609 | J23: 0 | K23: Short De Futbol | M23: Por confirmar | N23: Promedio OT 2547 (0,175) y OT 2588 (0,138). Liso = sin impresión (0 m): confirmar. | O23: =IF(B23="","",IFERROR(G23*INDEX(Precios!$D$5:$D$120,MATCH(F23,Precios!$A$5:$A$120,0)),0)+IF(H23="",0,IFERROR(I23*INDEX(Precios!$D$5:$D$120,MATCH(H23,Precios!$A$5:$A$120,0)),0))) -> 901.04 | P23: =IF(B23="","",N(J23)*Parametros!$B$27) -> 0 | Q23: =IF(B23="","",IFERROR(INDEX(Confeccion!$B$5:$B$100,MATCH(K23,Confeccion!$A$5:$A$100,0)),0)) -> 1700 | R23: =IF(B23="","",N(L23)) -> 0 | S23: =IF(B23="","",IF(AND(F23<>"",ISNUMBER(G23),ISNUMBER(IFERROR(INDEX(Precios!$D$5:$D$120,MATCH(F23,Precios!$A$5:$A$120,0)),"x")),OR(H23="",ISNUMBER(IFERROR(INDEX(Precios!$D$5:$D$120,MATCH(H23,Precios!$A$5:$A$120,0)),"x"))),J23<>"",K23<>"",Q23>0),SUM(O23:R23),"")) -> 2601.04 | T23: =IF(AND(S23<>"",ISNUMBER(E23)),E23*Parametros!$B$12,"") -> 2844.3962 | U23: =IF(AND(S23<>"",ISNUMBER(E23)),E23*Parametros!$B$13,"") -> 1021.0466 | V23: =IF(AND(S23<>"",ISNUMBER(E23)),E23-S23-T23-U23,"") -> 1592.5172 | W23: =IF(AND(S23<>"",ISNUMBER(E23)),V23/E23,"") -> 0.19760729 | X23: =IF(OR(S23="",Parametros!$B$14>=1),"",S23/(1-Parametros!$B$14)) -> 4998.5682 | Y23: =IF(OR(S23="",Parametros!$B$14+Parametros!$B$18>=1),"",S23/(1-Parametros!$B$14-Parametros!$B$18)) -> 6187.6926 | Z23: =IF(B23="","",IF(S23="","FALTAN DATOS",IF(NOT(ISNUMBER(E23)),"FALTA PRECIO",IF(V23<0,"PIERDE",IF(W23<Parametros!$B$18,"BAJO META","OK"))))) -> OK | AA23: =IF(B23="","",IF(F23="","Tela. ","")&IF(NOT(ISNUMBER(G23)),"Kg de tela. ","")&IF(AND(F23<>"",NOT(ISNUMBER(IFERROR(INDEX(Precios!$D$5:$D$120,MATCH(F23,Precios!$A$5:$A$120,0)),"x")))),"Tela sin precio. ","")&IF(AND(H23<>"",NOT(ISNUMBER(IFERROR(INDEX(Precios!$D$5:$D$120,MATCH(H23,Precios!$A$5:$A$120,0)),"x")))),"Tela 2 sin precio. ","")&IF(J23="","Metros impresos. ","")&IF(AND(N(J23)>0,Parametros!$B$27=0),"Impresión sin costo. ","")&IF(K23="","Confección. ",IF(Q23=0,"Confección sin valor. ",""))&IF(NOT(ISNUMBER(E23)),"Precio de venta. ",""))
A24: VOLFEMCSUBPROV | B24: Camiseta Voley fem Pro Playmaker, V | C24: Juego | D24: 50 | E24: 19244 | K24: Camiseta Voley | M24: Por confirmar | N24: Confección sugerida por el nombre: confirmar. | O24: =IF(B24="","",IFERROR(G24*INDEX(Precios!$D$5:$D$120,MATCH(F24,Precios!$A$5:$A$120,0)),0)+IF(H24="",0,IFERROR(I24*INDEX(Precios!$D$5:$D$120,MATCH(H24,Precios!$A$5:$A$120,0)),0))) -> 0 | P24: =IF(B24="","",N(J24)*Parametros!$B$27) -> 0 | Q24: =IF(B24="","",IFERROR(INDEX(Confeccion!$B$5:$B$100,MATCH(K24,Confeccion!$A$5:$A$100,0)),0)) -> 1700 | R24: =IF(B24="","",N(L24)) -> 0 | S24: =IF(B24="","",IF(AND(F24<>"",ISNUMBER(G24),ISNUMBER(IFERROR(INDEX(Precios!$D$5:$D$120,MATCH(F24,Precios!$A$5:$A$120,0)),"x")),OR(H24="",ISNUMBER(IFERROR(INDEX(Precios!$D$5:$D$120,MATCH(H24,Precios!$A$5:$A$120,0)),"x"))),J24<>"",K24<>"",Q24>0),SUM(O24:R24),"")) | T24: =IF(AND(S24<>"",ISNUMBER(E24)),E24*Parametros!$B$12,"") | U24: =IF(AND(S24<>"",ISNUMBER(E24)),E24*Parametros!$B$13,"") | V24: =IF(AND(S24<>"",ISNUMBER(E24)),E24-S24-T24-U24,"") | W24: =IF(AND(S24<>"",ISNUMBER(E24)),V24/E24,"") | X24: =IF(OR(S24="",Parametros!$B$14>=1),"",S24/(1-Parametros!$B$14)) | Y24: =IF(OR(S24="",Parametros!$B$14+Parametros!$B$18>=1),"",S24/(1-Parametros!$B$14-Parametros!$B$18)) | Z24: =IF(B24="","",IF(S24="","FALTAN DATOS",IF(NOT(ISNUMBER(E24)),"FALTA PRECIO",IF(V24<0,"PIERDE",IF(W24<Parametros!$B$18,"BAJO META","OK"))))) -> FALTAN DATOS | AA24: =IF(B24="","",IF(F24="","Tela. ","")&IF(NOT(ISNUMBER(G24)),"Kg de tela. ","")&IF(AND(F24<>"",NOT(ISNUMBER(IFERROR(INDEX(Precios!$D$5:$D$120,MATCH(F24,Precios!$A$5:$A$120,0)),"x")))),"Tela sin precio. ","")&IF(AND(H24<>"",NOT(ISNUMBER(IFERROR(INDEX(Precios!$D$5:$D$120,MATCH(H24,Precios!$A$5:$A$120,0)),"x")))),"Tela 2 sin precio. ","")&IF(J24="","Metros impresos. ","")&IF(AND(N(J24)>0,Parametros!$B$27=0),"Impresión sin costo. ","")&IF(K24="","Confección. ",IF(Q24=0,"Confección sin valor. ",""))&IF(NOT(ISNUMBER(E24)),"Precio de venta. ","")) -> Tela. Kg de tela. Metros impresos.
A25: MDPTSUB | B25: PETO ENTRENAMIENTO SUB | C25: Juego | D25: 48 | E25: 8319 | K25: Peto Entrenamiento | M25: Por confirmar | N25: Confección sugerida por el nombre: confirmar. | O25: =IF(B25="","",IFERROR(G25*INDEX(Precios!$D$5:$D$120,MATCH(F25,Precios!$A$5:$A$120,0)),0)+IF(H25="",0,IFERROR(I25*INDEX(Precios!$D$5:$D$120,MATCH(H25,Precios!$A$5:$A$120,0)),0))) -> 0 | P25: =IF(B25="","",N(J25)*Parametros!$B$27) -> 0 | Q25: =IF(B25="","",IFERROR(INDEX(Confeccion!$B$5:$B$100,MATCH(K25,Confeccion!$A$5:$A$100,0)),0)) -> 1000 | R25: =IF(B25="","",N(L25)) -> 0 | S25: =IF(B25="","",IF(AND(F25<>"",ISNUMBER(G25),ISNUMBER(IFERROR(INDEX(Precios!$D$5:$D$120,MATCH(F25,Precios!$A$5:$A$120,0)),"x")),OR(H25="",ISNUMBER(IFERROR(INDEX(Precios!$D$5:$D$120,MATCH(H25,Precios!$A$5:$A$120,0)),"x"))),J25<>"",K25<>"",Q25>0),SUM(O25:R25),"")) | T25: =IF(AND(S25<>"",ISNUMBER(E25)),E25*Parametros!$B$12,"") | U25: =IF(AND(S25<>"",ISNUMBER(E25)),E25*Parametros!$B$13,"") | V25: =IF(AND(S25<>"",ISNUMBER(E25)),E25-S25-T25-U25,"") | W25: =IF(AND(S25<>"",ISNUMBER(E25)),V25/E25,"") | X25: =IF(OR(S25="",Parametros!$B$14>=1),"",S25/(1-Parametros!$B$14)) | Y25: =IF(OR(S25="",Parametros!$B$14+Parametros!$B$18>=1),"",S25/(1-Parametros!$B$14-Parametros!$B$18)) | Z25: =IF(B25="","",IF(S25="","FALTAN DATOS",IF(NOT(ISNUMBER(E25)),"FALTA PRECIO",IF(V25<0,"PIERDE",IF(W25<Parametros!$B$18,"BAJO META","OK"))))) -> FALTAN DATOS | AA25: =IF(B25="","",IF(F25="","Tela. ","")&IF(NOT(ISNUMBER(G25)),"Kg de tela. ","")&IF(AND(F25<>"",NOT(ISNUMBER(IFERROR(INDEX(Precios!$D$5:$D$120,MATCH(F25,Precios!$A$5:$A$120,0)),"x")))),"Tela sin precio. ","")&IF(AND(H25<>"",NOT(ISNUMBER(IFERROR(INDEX(Precios!$D$5:$D$120,MATCH(H25,Precios!$A$5:$A$120,0)),"x")))),"Tela 2 sin precio. ","")&IF(J25="","Metros impresos. ","")&IF(AND(N(J25)>0,Parametros!$B$27=0),"Impresión sin costo. ","")&IF(K25="","Confección. ",IF(Q25=0,"Confección sin valor. ",""))&IF(NOT(ISNUMBER(E25)),"Precio de venta. ","")) -> Tela. Kg de tela. Metros impresos.
A26: MDCSUBOVA | B26: Polera Playmaker, Cuello Oval s/mangas | C26: Juego | D26: 48 | E26: 16723 | M26: Por confirmar | O26: =IF(B26="","",IFERROR(G26*INDEX(Precios!$D$5:$D$120,MATCH(F26,Precios!$A$5:$A$120,0)),0)+IF(H26="",0,IFERROR(I26*INDEX(Precios!$D$5:$D$120,MATCH(H26,Precios!$A$5:$A$120,0)),0))) -> 0 | P26: =IF(B26="","",N(J26)*Parametros!$B$27) -> 0 | Q26: =IF(B26="","",IFERROR(INDEX(Confeccion!$B$5:$B$100,MATCH(K26,Confeccion!$A$5:$A$100,0)),0)) -> 0 | R26: =IF(B26="","",N(L26)) -> 0 | S26: =IF(B26="","",IF(AND(F26<>"",ISNUMBER(G26),ISNUMBER(IFERROR(INDEX(Precios!$D$5:$D$120,MATCH(F26,Precios!$A$5:$A$120,0)),"x")),OR(H26="",ISNUMBER(IFERROR(INDEX(Precios!$D$5:$D$120,MATCH(H26,Precios!$A$5:$A$120,0)),"x"))),J26<>"",K26<>"",Q26>0),SUM(O26:R26),"")) | T26: =IF(AND(S26<>"",ISNUMBER(E26)),E26*Parametros!$B$12,"") | U26: =IF(AND(S26<>"",ISNUMBER(E26)),E26*Parametros!$B$13,"") | V26: =IF(AND(S26<>"",ISNUMBER(E26)),E26-S26-T26-U26,"") | W26: =IF(AND(S26<>"",ISNUMBER(E26)),V26/E26,"") | X26: =IF(OR(S26="",Parametros!$B$14>=1),"",S26/(1-Parametros!$B$14)) | Y26: =IF(OR(S26="",Parametros!$B$14+Parametros!$B$18>=1),"",S26/(1-Parametros!$B$14-Parametros!$B$18)) | Z26: =IF(B26="","",IF(S26="","FALTAN DATOS",IF(NOT(ISNUMBER(E26)),"FALTA PRECIO",IF(V26<0,"PIERDE",IF(W26<Parametros!$B$18,"BAJO META","OK"))))) -> FALTAN DATOS | AA26: =IF(B26="","",IF(F26="","Tela. ","")&IF(NOT(ISNUMBER(G26)),"Kg de tela. ","")&IF(AND(F26<>"",NOT(ISNUMBER(IFERROR(INDEX(Precios!$D$5:$D$120,MATCH(F26,Precios!$A$5:$A$120,0)),"x")))),"Tela sin precio. ","")&IF(AND(H26<>"",NOT(ISNUMBER(IFERROR(INDEX(Precios!$D$5:$D$120,MATCH(H26,Precios!$A$5:$A$120,0)),"x")))),"Tela 2 sin precio. ","")&IF(J26="","Metros impresos. ","")&IF(AND(N(J26)>0,Parametros!$B$27=0),"Impresión sin costo. ","")&IF(K26="","Confección. ",IF(Q26=0,"Confección sin valor. ",""))&IF(NOT(ISNUMBER(E26)),"Precio de venta. ","")) -> Tela. Kg de tela. Metros impresos. Confección.
A27: SALHOOLIS | B27: Polerón Hoodie Playmaker liso | C27: Salida | D27: 47 | E27: 26134 | K27: Poleron Hoodie | M27: Por confirmar | N27: Confección sugerida por el nombre: confirmar. | O27: =IF(B27="","",IFERROR(G27*INDEX(Precios!$D$5:$D$120,MATCH(F27,Precios!$A$5:$A$120,0)),0)+IF(H27="",0,IFERROR(I27*INDEX(Precios!$D$5:$D$120,MATCH(H27,Precios!$A$5:$A$120,0)),0))) -> 0 | P27: =IF(B27="","",N(J27)*Parametros!$B$27) -> 0 | Q27: =IF(B27="","",IFERROR(INDEX(Confeccion!$B$5:$B$100,MATCH(K27,Confeccion!$A$5:$A$100,0)),0)) -> 3000 | R27: =IF(B27="","",N(L27)) -> 0 | S27: =IF(B27="","",IF(AND(F27<>"",ISNUMBER(G27),ISNUMBER(IFERROR(INDEX(Precios!$D$5:$D$120,MATCH(F27,Precios!$A$5:$A$120,0)),"x")),OR(H27="",ISNUMBER(IFERROR(INDEX(Precios!$D$5:$D$120,MATCH(H27,Precios!$A$5:$A$120,0)),"x"))),J27<>"",K27<>"",Q27>0),SUM(O27:R27),"")) | T27: =IF(AND(S27<>"",ISNUMBER(E27)),E27*Parametros!$B$12,"") | U27: =IF(AND(S27<>"",ISNUMBER(E27)),E27*Parametros!$B$13,"") | V27: =IF(AND(S27<>"",ISNUMBER(E27)),E27-S27-T27-U27,"") | W27: =IF(AND(S27<>"",ISNUMBER(E27)),V27/E27,"") | X27: =IF(OR(S27="",Parametros!$B$14>=1),"",S27/(1-Parametros!$B$14)) | Y27: =IF(OR(S27="",Parametros!$B$14+Parametros!$B$18>=1),"",S27/(1-Parametros!$B$14-Parametros!$B$18)) | Z27: =IF(B27="","",IF(S27="","FALTAN DATOS",IF(NOT(ISNUMBER(E27)),"FALTA PRECIO",IF(V27<0,"PIERDE",IF(W27<Parametros!$B$18,"BAJO META","OK"))))) -> FALTAN DATOS | AA27: =IF(B27="","",IF(F27="","Tela. ","")&IF(NOT(ISNUMBER(G27)),"Kg de tela. ","")&IF(AND(F27<>"",NOT(ISNUMBER(IFERROR(INDEX(Precios!$D$5:$D$120,MATCH(F27,Precios!$A$5:$A$120,0)),"x")))),"Tela sin precio. ","")&IF(AND(H27<>"",NOT(ISNUMBER(IFERROR(INDEX(Precios!$D$5:$D$120,MATCH(H27,Precios!$A$5:$A$120,0)),"x")))),"Tela 2 sin precio. ","")&IF(J27="","Metros impresos. ","")&IF(AND(N(J27)>0,Parametros!$B$27=0),"Impresión sin costo. ","")&IF(K27="","Confección. ",IF(Q27=0,"Confección sin valor. ",""))&IF(NOT(ISNUMBER(E27)),"Precio de venta. ","")) -> Tela. Kg de tela. Metros impresos.
A28: CSUBRUGSFBLANCA | B28: CAMISETA DE RUGBY STADE FRANCAIS ANIVERSARIO (BLANCA) | C28: Juego | D28: 44 | E28: 27605 | M28: Por confirmar | O28: =IF(B28="","",IFERROR(G28*INDEX(Precios!$D$5:$D$120,MATCH(F28,Precios!$A$5:$A$120,0)),0)+IF(H28="",0,IFERROR(I28*INDEX(Precios!$D$5:$D$120,MATCH(H28,Precios!$A$5:$A$120,0)),0))) -> 0 | P28: =IF(B28="","",N(J28)*Parametros!$B$27) -> 0 | Q28: =IF(B28="","",IFERROR(INDEX(Confeccion!$B$5:$B$100,MATCH(K28,Confeccion!$A$5:$A$100,0)),0)) -> 0 | R28: =IF(B28="","",N(L28)) -> 0 | S28: =IF(B28="","",IF(AND(F28<>"",ISNUMBER(G28),ISNUMBER(IFERROR(INDEX(Precios!$D$5:$D$120,MATCH(F28,Precios!$A$5:$A$120,0)),"x")),OR(H28="",ISNUMBER(IFERROR(INDEX(Precios!$D$5:$D$120,MATCH(H28,Precios!$A$5:$A$120,0)),"x"))),J28<>"",K28<>"",Q28>0),SUM(O28:R28),"")) | T28: =IF(AND(S28<>"",ISNUMBER(E28)),E28*Parametros!$B$12,"") | U28: =IF(AND(S28<>"",ISNUMBER(E28)),E28*Parametros!$B$13,"") | V28: =IF(AND(S28<>"",ISNUMBER(E28)),E28-S28-T28-U28,"") | W28: =IF(AND(S28<>"",ISNUMBER(E28)),V28/E28,"") | X28: =IF(OR(S28="",Parametros!$B$14>=1),"",S28/(1-Parametros!$B$14)) | Y28: =IF(OR(S28="",Parametros!$B$14+Parametros!$B$18>=1),"",S28/(1-Parametros!$B$14-Parametros!$B$18)) | Z28: =IF(B28="","",IF(S28="","FALTAN DATOS",IF(NOT(ISNUMBER(E28)),"FALTA PRECIO",IF(V28<0,"PIERDE",IF(W28<Parametros!$B$18,"BAJO META","OK"))))) -> FALTAN DATOS | AA28: =IF(B28="","",IF(F28="","Tela. ","")&IF(NOT(ISNUMBER(G28)),"Kg de tela. ","")&IF(AND(F28<>"",NOT(ISNUMBER(IFERROR(INDEX(Precios!$D$5:$D$120,MATCH(F28,Precios!$A$5:$A$120,0)),"x")))),"Tela sin precio. ","")&IF(AND(H28<>"",NOT(ISNUMBER(IFERROR(INDEX(Precios!$D$5:$D$120,MATCH(H28,Precios!$A$5:$A$120,0)),"x")))),"Tela 2 sin precio. ","")&IF(J28="","Metros impresos. ","")&IF(AND(N(J28)>0,Parametros!$B$27=0),"Impresión sin costo. ","")&IF(K28="","Confección. ",IF(Q28=0,"Confección sin valor. ",""))&IF(NOT(ISNUMBER(E28)),"Precio de venta. ","")) -> Tela. Kg de tela. Metros impresos. Confección.
A29: SAL-POL-3C | B29: Polerón 3C Playmaker Algodón Cierre | C29: Salida | D29: 40 | E29: 32689 | M29: Por confirmar | O29: =IF(B29="","",IFERROR(G29*INDEX(Precios!$D$5:$D$120,MATCH(F29,Precios!$A$5:$A$120,0)),0)+IF(H29="",0,IFERROR(I29*INDEX(Precios!$D$5:$D$120,MATCH(H29,Precios!$A$5:$A$120,0)),0))) -> 0 | P29: =IF(B29="","",N(J29)*Parametros!$B$27) -> 0 | Q29: =IF(B29="","",IFERROR(INDEX(Confeccion!$B$5:$B$100,MATCH(K29,Confeccion!$A$5:$A$100,0)),0)) -> 0 | R29: =IF(B29="","",N(L29)) -> 0 | S29: =IF(B29="","",IF(AND(F29<>"",ISNUMBER(G29),ISNUMBER(IFERROR(INDEX(Precios!$D$5:$D$120,MATCH(F29,Precios!$A$5:$A$120,0)),"x")),OR(H29="",ISNUMBER(IFERROR(INDEX(Precios!$D$5:$D$120,MATCH(H29,Precios!$A$5:$A$120,0)),"x"))),J29<>"",K29<>"",Q29>0),SUM(O29:R29),"")) | T29: =IF(AND(S29<>"",ISNUMBER(E29)),E29*Parametros!$B$12,"") | U29: =IF(AND(S29<>"",ISNUMBER(E29)),E29*Parametros!$B$13,"") | V29: =IF(AND(S29<>"",ISNUMBER(E29)),E29-S29-T29-U29,"") | W29: =IF(AND(S29<>"",ISNUMBER(E29)),V29/E29,"") | X29: =IF(OR(S29="",Parametros!$B$14>=1),"",S29/(1-Parametros!$B$14)) | Y29: =IF(OR(S29="",Parametros!$B$14+Parametros!$B$18>=1),"",S29/(1-Parametros!$B$14-Parametros!$B$18)) | Z29: =IF(B29="","",IF(S29="","FALTAN DATOS",IF(NOT(ISNUMBER(E29)),"FALTA PRECIO",IF(V29<0,"PIERDE",IF(W29<Parametros!$B$18,"BAJO META","OK"))))) -> FALTAN DATOS | AA29: =IF(B29="","",IF(F29="","Tela. ","")&IF(NOT(ISNUMBER(G29)),"Kg de tela. ","")&IF(AND(F29<>"",NOT(ISNUMBER(IFERROR(INDEX(Precios!$D$5:$D$120,MATCH(F29,Precios!$A$5:$A$120,0)),"x")))),"Tela sin precio. ","")&IF(AND(H29<>"",NOT(ISNUMBER(IFERROR(INDEX(Precios!$D$5:$D$120,MATCH(H29,Precios!$A$5:$A$120,0)),"x")))),"Tela 2 sin precio. ","")&IF(J29="","Metros impresos. ","")&IF(AND(N(J29)>0,Parametros!$B$27=0),"Impresión sin costo. ","")&IF(K29="","Confección. ",IF(Q29=0,"Confección sin valor. ",""))&IF(NOT(ISNUMBER(E29)),"Precio de venta. ","")) -> Tela. Kg de tela. Metros impresos. Confección.
A30: VOLMASC-CSUB-POL-CER | B30: Camiseta Voley masc Playmaker, Polo m/cero | C30: Juego | D30: 37 | E30: 17563 | K30: Camiseta Voley | M30: Por confirmar | N30: Confección sugerida por el nombre: confirmar. | O30: =IF(B30="","",IFERROR(G30*INDEX(Precios!$D$5:$D$120,MATCH(F30,Precios!$A$5:$A$120,0)),0)+IF(H30="",0,IFERROR(I30*INDEX(Precios!$D$5:$D$120,MATCH(H30,Precios!$A$5:$A$120,0)),0))) -> 0 | P30: =IF(B30="","",N(J30)*Parametros!$B$27) -> 0 | Q30: =IF(B30="","",IFERROR(INDEX(Confeccion!$B$5:$B$100,MATCH(K30,Confeccion!$A$5:$A$100,0)),0)) -> 1700 | R30: =IF(B30="","",N(L30)) -> 0 | S30: =IF(B30="","",IF(AND(F30<>"",ISNUMBER(G30),ISNUMBER(IFERROR(INDEX(Precios!$D$5:$D$120,MATCH(F30,Precios!$A$5:$A$120,0)),"x")),OR(H30="",ISNUMBER(IFERROR(INDEX(Precios!$D$5:$D$120,MATCH(H30,Precios!$A$5:$A$120,0)),"x"))),J30<>"",K30<>"",Q30>0),SUM(O30:R30),"")) | T30: =IF(AND(S30<>"",ISNUMBER(E30)),E30*Parametros!$B$12,"") | U30: =IF(AND(S30<>"",ISNUMBER(E30)),E30*Parametros!$B$13,"") | V30: =IF(AND(S30<>"",ISNUMBER(E30)),E30-S30-T30-U30,"") | W30: =IF(AND(S30<>"",ISNUMBER(E30)),V30/E30,"") | X30: =IF(OR(S30="",Parametros!$B$14>=1),"",S30/(1-Parametros!$B$14)) | Y30: =IF(OR(S30="",Parametros!$B$14+Parametros!$B$18>=1),"",S30/(1-Parametros!$B$14-Parametros!$B$18)) | Z30: =IF(B30="","",IF(S30="","FALTAN DATOS",IF(NOT(ISNUMBER(E30)),"FALTA PRECIO",IF(V30<0,"PIERDE",IF(W30<Parametros!$B$18,"BAJO META","OK"))))) -> FALTAN DATOS | AA30: =IF(B30="","",IF(F30="","Tela. ","")&IF(NOT(ISNUMBER(G30)),"Kg de tela. ","")&IF(AND(F30<>"",NOT(ISNUMBER(IFERROR(INDEX(Precios!$D$5:$D$120,MATCH(F30,Precios!$A$5:$A$120,0)),"x")))),"Tela sin precio. ","")&IF(AND(H30<>"",NOT(ISNUMBER(IFERROR(INDEX(Precios!$D$5:$D$120,MATCH(H30,Precios!$A$5:$A$120,0)),"x")))),"Tela 2 sin precio. ","")&IF(J30="","Metros impresos. ","")&IF(AND(N(J30)>0,Parametros!$B$27=0),"Impresión sin costo. ","")&IF(K30="","Confección. ",IF(Q30=0,"Confección sin valor. ",""))&IF(NOT(ISNUMBER(E30)),"Precio de venta. ","")) -> Tela. Kg de tela. Metros impresos.
A31: SALPRKLIS | B31: Parka Lisa Playmaker | C31: Salida | D31: 37 | E31: 54022 | M31: Por confirmar | O31: =IF(B31="","",IFERROR(G31*INDEX(Precios!$D$5:$D$120,MATCH(F31,Precios!$A$5:$A$120,0)),0)+IF(H31="",0,IFERROR(I31*INDEX(Precios!$D$5:$D$120,MATCH(H31,Precios!$A$5:$A$120,0)),0))) -> 0 | P31: =IF(B31="","",N(J31)*Parametros!$B$27) -> 0 | Q31: =IF(B31="","",IFERROR(INDEX(Confeccion!$B$5:$B$100,MATCH(K31,Confeccion!$A$5:$A$100,0)),0)) -> 0 | R31: =IF(B31="","",N(L31)) -> 0 | S31: =IF(B31="","",IF(AND(F31<>"",ISNUMBER(G31),ISNUMBER(IFERROR(INDEX(Precios!$D$5:$D$120,MATCH(F31,Precios!$A$5:$A$120,0)),"x")),OR(H31="",ISNUMBER(IFERROR(INDEX(Precios!$D$5:$D$120,MATCH(H31,Precios!$A$5:$A$120,0)),"x"))),J31<>"",K31<>"",Q31>0),SUM(O31:R31),"")) | T31: =IF(AND(S31<>"",ISNUMBER(E31)),E31*Parametros!$B$12,"") | U31: =IF(AND(S31<>"",ISNUMBER(E31)),E31*Parametros!$B$13,"") | V31: =IF(AND(S31<>"",ISNUMBER(E31)),E31-S31-T31-U31,"") | W31: =IF(AND(S31<>"",ISNUMBER(E31)),V31/E31,"") | X31: =IF(OR(S31="",Parametros!$B$14>=1),"",S31/(1-Parametros!$B$14)) | Y31: =IF(OR(S31="",Parametros!$B$14+Parametros!$B$18>=1),"",S31/(1-Parametros!$B$14-Parametros!$B$18)) | Z31: =IF(B31="","",IF(S31="","FALTAN DATOS",IF(NOT(ISNUMBER(E31)),"FALTA PRECIO",IF(V31<0,"PIERDE",IF(W31<Parametros!$B$18,"BAJO META","OK"))))) -> FALTAN DATOS | AA31: =IF(B31="","",IF(F31="","Tela. ","")&IF(NOT(ISNUMBER(G31)),"Kg de tela. ","")&IF(AND(F31<>"",NOT(ISNUMBER(IFERROR(INDEX(Precios!$D$5:$D$120,MATCH(F31,Precios!$A$5:$A$120,0)),"x")))),"Tela sin precio. ","")&IF(AND(H31<>"",NOT(ISNUMBER(IFERROR(INDEX(Precios!$D$5:$D$120,MATCH(H31,Precios!$A$5:$A$120,0)),"x")))),"Tela 2 sin precio. ","")&IF(J31="","Metros impresos. ","")&IF(AND(N(J31)>0,Parametros!$B$27=0),"Impresión sin costo. ","")&IF(K31="","Confección. ",IF(Q31=0,"Confección sin valor. ",""))&IF(NOT(ISNUMBER(E31)),"Precio de venta. ","")) -> Tela. Kg de tela. Metros impresos. Confección.
A32: RUG-SHO-PRO | B32: Short Rugby Pro | C32: Juego | D32: 35 | E32: 14202 | K32: Short De Rugby | M32: Por confirmar | N32: Confección sugerida por el nombre: confirmar. | O32: =IF(B32="","",IFERROR(G32*INDEX(Precios!$D$5:$D$120,MATCH(F32,Precios!$A$5:$A$120,0)),0)+IF(H32="",0,IFERROR(I32*INDEX(Precios!$D$5:$D$120,MATCH(H32,Precios!$A$5:$A$120,0)),0))) -> 0 | P32: =IF(B32="","",N(J32)*Parametros!$B$27) -> 0 | Q32: =IF(B32="","",IFERROR(INDEX(Confeccion!$B$5:$B$100,MATCH(K32,Confeccion!$A$5:$A$100,0)),0)) -> 2200 | R32: =IF(B32="","",N(L32)) -> 0 | S32: =IF(B32="","",IF(AND(F32<>"",ISNUMBER(G32),ISNUMBER(IFERROR(INDEX(Precios!$D$5:$D$120,MATCH(F32,Precios!$A$5:$A$120,0)),"x")),OR(H32="",ISNUMBER(IFERROR(INDEX(Precios!$D$5:$D$120,MATCH(H32,Precios!$A$5:$A$120,0)),"x"))),J32<>"",K32<>"",Q32>0),SUM(O32:R32),"")) | T32: =IF(AND(S32<>"",ISNUMBER(E32)),E32*Parametros!$B$12,"") | U32: =IF(AND(S32<>"",ISNUMBER(E32)),E32*Parametros!$B$13,"") | V32: =IF(AND(S32<>"",ISNUMBER(E32)),E32-S32-T32-U32,"") | W32: =IF(AND(S32<>"",ISNUMBER(E32)),V32/E32,"") | X32: =IF(OR(S32="",Parametros!$B$14>=1),"",S32/(1-Parametros!$B$14)) | Y32: =IF(OR(S32="",Parametros!$B$14+Parametros!$B$18>=1),"",S32/(1-Parametros!$B$14-Parametros!$B$18)) | Z32: =IF(B32="","",IF(S32="","FALTAN DATOS",IF(NOT(ISNUMBER(E32)),"FALTA PRECIO",IF(V32<0,"PIERDE",IF(W32<Parametros!$B$18,"BAJO META","OK"))))) -> FALTAN DATOS | AA32: =IF(B32="","",IF(F32="","Tela. ","")&IF(NOT(ISNUMBER(G32)),"Kg de tela. ","")&IF(AND(F32<>"",NOT(ISNUMBER(IFERROR(INDEX(Precios!$D$5:$D$120,MATCH(F32,Precios!$A$5:$A$120,0)),"x")))),"Tela sin precio. ","")&IF(AND(H32<>"",NOT(ISNUMBER(IFERROR(INDEX(Precios!$D$5:$D$120,MATCH(H32,Precios!$A$5:$A$120,0)),"x")))),"Tela 2 sin precio. ","")&IF(J32="","Metros impresos. ","")&IF(AND(N(J32)>0,Parametros!$B$27=0),"Impresión sin costo. ","")&IF(K32="","Confección. ",IF(Q32=0,"Confección sin valor. ",""))&IF(NOT(ISNUMBER(E32)),"Precio de venta. ","")) -> Tela. Kg de tela. Metros impresos.
A33: SAL-POL-SUB | B33: Polerón Entrenamiento Sublim | C33: Salida | D33: 35 | E33: 27647 | M33: Por confirmar | O33: =IF(B33="","",IFERROR(G33*INDEX(Precios!$D$5:$D$120,MATCH(F33,Precios!$A$5:$A$120,0)),0)+IF(H33="",0,IFERROR(I33*INDEX(Precios!$D$5:$D$120,MATCH(H33,Precios!$A$5:$A$120,0)),0))) -> 0 | P33: =IF(B33="","",N(J33)*Parametros!$B$27) -> 0 | Q33: =IF(B33="","",IFERROR(INDEX(Confeccion!$B$5:$B$100,MATCH(K33,Confeccion!$A$5:$A$100,0)),0)) -> 0 | R33: =IF(B33="","",N(L33)) -> 0 | S33: =IF(B33="","",IF(AND(F33<>"",ISNUMBER(G33),ISNUMBER(IFERROR(INDEX(Precios!$D$5:$D$120,MATCH(F33,Precios!$A$5:$A$120,0)),"x")),OR(H33="",ISNUMBER(IFERROR(INDEX(Precios!$D$5:$D$120,MATCH(H33,Precios!$A$5:$A$120,0)),"x"))),J33<>"",K33<>"",Q33>0),SUM(O33:R33),"")) | T33: =IF(AND(S33<>"",ISNUMBER(E33)),E33*Parametros!$B$12,"") | U33: =IF(AND(S33<>"",ISNUMBER(E33)),E33*Parametros!$B$13,"") | V33: =IF(AND(S33<>"",ISNUMBER(E33)),E33-S33-T33-U33,"") | W33: =IF(AND(S33<>"",ISNUMBER(E33)),V33/E33,"") | X33: =IF(OR(S33="",Parametros!$B$14>=1),"",S33/(1-Parametros!$B$14)) | Y33: =IF(OR(S33="",Parametros!$B$14+Parametros!$B$18>=1),"",S33/(1-Parametros!$B$14-Parametros!$B$18)) | Z33: =IF(B33="","",IF(S33="","FALTAN DATOS",IF(NOT(ISNUMBER(E33)),"FALTA PRECIO",IF(V33<0,"PIERDE",IF(W33<Parametros!$B$18,"BAJO META","OK"))))) -> FALTAN DATOS | AA33: =IF(B33="","",IF(F33="","Tela. ","")&IF(NOT(ISNUMBER(G33)),"Kg de tela. ","")&IF(AND(F33<>"",NOT(ISNUMBER(IFERROR(INDEX(Precios!$D$5:$D$120,MATCH(F33,Precios!$A$5:$A$120,0)),"x")))),"Tela sin precio. ","")&IF(AND(H33<>"",NOT(ISNUMBER(IFERROR(INDEX(Precios!$D$5:$D$120,MATCH(H33,Precios!$A$5:$A$120,0)),"x")))),"Tela 2 sin precio. ","")&IF(J33="","Metros impresos. ","")&IF(AND(N(J33)>0,Parametros!$B$27=0),"Impresión sin costo. ","")&IF(K33="","Confección. ",IF(Q33=0,"Confección sin valor. ",""))&IF(NOT(ISNUMBER(E33)),"Precio de venta. ","")) -> Tela. Kg de tela. Metros impresos. Confección.
A34: RUGCSUBPER | B34: Camiseta Rugby Performance Pmk | C34: Juego | D34: 34 | E34: 19664 | M34: Por confirmar | O34: =IF(B34="","",IFERROR(G34*INDEX(Precios!$D$5:$D$120,MATCH(F34,Precios!$A$5:$A$120,0)),0)+IF(H34="",0,IFERROR(I34*INDEX(Precios!$D$5:$D$120,MATCH(H34,Precios!$A$5:$A$120,0)),0))) -> 0 | P34: =IF(B34="","",N(J34)*Parametros!$B$27) -> 0 | Q34: =IF(B34="","",IFERROR(INDEX(Confeccion!$B$5:$B$100,MATCH(K34,Confeccion!$A$5:$A$100,0)),0)) -> 0 | R34: =IF(B34="","",N(L34)) -> 0 | S34: =IF(B34="","",IF(AND(F34<>"",ISNUMBER(G34),ISNUMBER(IFERROR(INDEX(Precios!$D$5:$D$120,MATCH(F34,Precios!$A$5:$A$120,0)),"x")),OR(H34="",ISNUMBER(IFERROR(INDEX(Precios!$D$5:$D$120,MATCH(H34,Precios!$A$5:$A$120,0)),"x"))),J34<>"",K34<>"",Q34>0),SUM(O34:R34),"")) | T34: =IF(AND(S34<>"",ISNUMBER(E34)),E34*Parametros!$B$12,"") | U34: =IF(AND(S34<>"",ISNUMBER(E34)),E34*Parametros!$B$13,"") | V34: =IF(AND(S34<>"",ISNUMBER(E34)),E34-S34-T34-U34,"") | W34: =IF(AND(S34<>"",ISNUMBER(E34)),V34/E34,"") | X34: =IF(OR(S34="",Parametros!$B$14>=1),"",S34/(1-Parametros!$B$14)) | Y34: =IF(OR(S34="",Parametros!$B$14+Parametros!$B$18>=1),"",S34/(1-Parametros!$B$14-Parametros!$B$18)) | Z34: =IF(B34="","",IF(S34="","FALTAN DATOS",IF(NOT(ISNUMBER(E34)),"FALTA PRECIO",IF(V34<0,"PIERDE",IF(W34<Parametros!$B$18,"BAJO META","OK"))))) -> FALTAN DATOS | AA34: =IF(B34="","",IF(F34="","Tela. ","")&IF(NOT(ISNUMBER(G34)),"Kg de tela. ","")&IF(AND(F34<>"",NOT(ISNUMBER(IFERROR(INDEX(Precios!$D$5:$D$120,MATCH(F34,Precios!$A$5:$A$120,0)),"x")))),"Tela sin precio. ","")&IF(AND(H34<>"",NOT(ISNUMBER(IFERROR(INDEX(Precios!$D$5:$D$120,MATCH(H34,Precios!$A$5:$A$120,0)),"x")))),"Tela 2 sin precio. ","")&IF(J34="","Metros impresos. ","")&IF(AND(N(J34)>0,Parametros!$B$27=0),"Impresión sin costo. ","")&IF(K34="","Confección. ",IF(Q34=0,"Confección sin valor. ",""))&IF(NOT(ISNUMBER(E34)),"Precio de venta. ","")) -> Tela. Kg de tela. Metros impresos. Confección.
A35: FUTCSUBML | B35: Camiseta Fútbol Playmaker, m/l | C35: Juego | D35: 34 | E35: 17563 | F35: CIRE BLANCO | K35: Camiseta De Futbol | M35: Por confirmar | N35: FALTA CONSUMO. Manga larga gasta más tela que m/c. | O35: =IF(B35="","",IFERROR(G35*INDEX(Precios!$D$5:$D$120,MATCH(F35,Precios!$A$5:$A$120,0)),0)+IF(H35="",0,IFERROR(I35*INDEX(Precios!$D$5:$D$120,MATCH(H35,Precios!$A$5:$A$120,0)),0))) -> 0 | P35: =IF(B35="","",N(J35)*Parametros!$B$27) -> 0 | Q35: =IF(B35="","",IFERROR(INDEX(Confeccion!$B$5:$B$100,MATCH(K35,Confeccion!$A$5:$A$100,0)),0)) -> 2000 | R35: =IF(B35="","",N(L35)) -> 0 | S35: =IF(B35="","",IF(AND(F35<>"",ISNUMBER(G35),ISNUMBER(IFERROR(INDEX(Precios!$D$5:$D$120,MATCH(F35,Precios!$A$5:$A$120,0)),"x")),OR(H35="",ISNUMBER(IFERROR(INDEX(Precios!$D$5:$D$120,MATCH(H35,Precios!$A$5:$A$120,0)),"x"))),J35<>"",K35<>"",Q35>0),SUM(O35:R35),"")) | T35: =IF(AND(S35<>"",ISNUMBER(E35)),E35*Parametros!$B$12,"") | U35: =IF(AND(S35<>"",ISNUMBER(E35)),E35*Parametros!$B$13,"") | V35: =IF(AND(S35<>"",ISNUMBER(E35)),E35-S35-T35-U35,"") | W35: =IF(AND(S35<>"",ISNUMBER(E35)),V35/E35,"") | X35: =IF(OR(S35="",Parametros!$B$14>=1),"",S35/(1-Parametros!$B$14)) | Y35: =IF(OR(S35="",Parametros!$B$14+Parametros!$B$18>=1),"",S35/(1-Parametros!$B$14-Parametros!$B$18)) | Z35: =IF(B35="","",IF(S35="","FALTAN DATOS",IF(NOT(ISNUMBER(E35)),"FALTA PRECIO",IF(V35<0,"PIERDE",IF(W35<Parametros!$B$18,"BAJO META","OK"))))) -> FALTAN DATOS | AA35: =IF(B35="","",IF(F35="","Tela. ","")&IF(NOT(ISNUMBER(G35)),"Kg de tela. ","")&IF(AND(F35<>"",NOT(ISNUMBER(IFERROR(INDEX(Precios!$D$5:$D$120,MATCH(F35,Precios!$A$5:$A$120,0)),"x")))),"Tela sin precio. ","")&IF(AND(H35<>"",NOT(ISNUMBER(IFERROR(INDEX(Precios!$D$5:$D$120,MATCH(H35,Precios!$A$5:$A$120,0)),"x")))),"Tela 2 sin precio. ","")&IF(J35="","Metros impresos. ","")&IF(AND(N(J35)>0,Parametros!$B$27=0),"Impresión sin costo. ","")&IF(K35="","Confección. ",IF(Q35=0,"Confección sin valor. ",""))&IF(NOT(ISNUMBER(E35)),"Precio de venta. ","")) -> Kg de tela. Metros impresos.
A36: SALALMLLISA | B36: Camiseta Algodón Manga Larga Lisa | C36: Juego | D36: 31 | E36: 12521 | M36: Por confirmar | O36: =IF(B36="","",IFERROR(G36*INDEX(Precios!$D$5:$D$120,MATCH(F36,Precios!$A$5:$A$120,0)),0)+IF(H36="",0,IFERROR(I36*INDEX(Precios!$D$5:$D$120,MATCH(H36,Precios!$A$5:$A$120,0)),0))) -> 0 | P36: =IF(B36="","",N(J36)*Parametros!$B$27) -> 0 | Q36: =IF(B36="","",IFERROR(INDEX(Confeccion!$B$5:$B$100,MATCH(K36,Confeccion!$A$5:$A$100,0)),0)) -> 0 | R36: =IF(B36="","",N(L36)) -> 0 | S36: =IF(B36="","",IF(AND(F36<>"",ISNUMBER(G36),ISNUMBER(IFERROR(INDEX(Precios!$D$5:$D$120,MATCH(F36,Precios!$A$5:$A$120,0)),"x")),OR(H36="",ISNUMBER(IFERROR(INDEX(Precios!$D$5:$D$120,MATCH(H36,Precios!$A$5:$A$120,0)),"x"))),J36<>"",K36<>"",Q36>0),SUM(O36:R36),"")) | T36: =IF(AND(S36<>"",ISNUMBER(E36)),E36*Parametros!$B$12,"") | U36: =IF(AND(S36<>"",ISNUMBER(E36)),E36*Parametros!$B$13,"") | V36: =IF(AND(S36<>"",ISNUMBER(E36)),E36-S36-T36-U36,"") | W36: =IF(AND(S36<>"",ISNUMBER(E36)),V36/E36,"") | X36: =IF(OR(S36="",Parametros!$B$14>=1),"",S36/(1-Parametros!$B$14)) | Y36: =IF(OR(S36="",Parametros!$B$14+Parametros!$B$18>=1),"",S36/(1-Parametros!$B$14-Parametros!$B$18)) | Z36: =IF(B36="","",IF(S36="","FALTAN DATOS",IF(NOT(ISNUMBER(E36)),"FALTA PRECIO",IF(V36<0,"PIERDE",IF(W36<Parametros!$B$18,"BAJO META","OK"))))) -> FALTAN DATOS | AA36: =IF(B36="","",IF(F36="","Tela. ","")&IF(NOT(ISNUMBER(G36)),"Kg de tela. ","")&IF(AND(F36<>"",NOT(ISNUMBER(IFERROR(INDEX(Precios!$D$5:$D$120,MATCH(F36,Precios!$A$5:$A$120,0)),"x")))),"Tela sin precio. ","")&IF(AND(H36<>"",NOT(ISNUMBER(IFERROR(INDEX(Precios!$D$5:$D$120,MATCH(H36,Precios!$A$5:$A$120,0)),"x")))),"Tela 2 sin precio. ","")&IF(J36="","Metros impresos. ","")&IF(AND(N(J36)>0,Parametros!$B$27=0),"Impresión sin costo. ","")&IF(K36="","Confección. ",IF(Q36=0,"Confección sin valor. ",""))&IF(NOT(ISNUMBER(E36)),"Precio de venta. ","")) -> Tela. Kg de tela. Metros impresos. Confección.
A37: RUG-CSUB-PIQ | B37: Camiseta Rugby Playmaker, Vintage | C37: Juego | D37: 29 | E37: 21204 | M37: Por confirmar | O37: =IF(B37="","",IFERROR(G37*INDEX(Precios!$D$5:$D$120,MATCH(F37,Precios!$A$5:$A$120,0)),0)+IF(H37="",0,IFERROR(I37*INDEX(Precios!$D$5:$D$120,MATCH(H37,Precios!$A$5:$A$120,0)),0))) -> 0 | P37: =IF(B37="","",N(J37)*Parametros!$B$27) -> 0 | Q37: =IF(B37="","",IFERROR(INDEX(Confeccion!$B$5:$B$100,MATCH(K37,Confeccion!$A$5:$A$100,0)),0)) -> 0 | R37: =IF(B37="","",N(L37)) -> 0 | S37: =IF(B37="","",IF(AND(F37<>"",ISNUMBER(G37),ISNUMBER(IFERROR(INDEX(Precios!$D$5:$D$120,MATCH(F37,Precios!$A$5:$A$120,0)),"x")),OR(H37="",ISNUMBER(IFERROR(INDEX(Precios!$D$5:$D$120,MATCH(H37,Precios!$A$5:$A$120,0)),"x"))),J37<>"",K37<>"",Q37>0),SUM(O37:R37),"")) | T37: =IF(AND(S37<>"",ISNUMBER(E37)),E37*Parametros!$B$12,"") | U37: =IF(AND(S37<>"",ISNUMBER(E37)),E37*Parametros!$B$13,"") | V37: =IF(AND(S37<>"",ISNUMBER(E37)),E37-S37-T37-U37,"") | W37: =IF(AND(S37<>"",ISNUMBER(E37)),V37/E37,"") | X37: =IF(OR(S37="",Parametros!$B$14>=1),"",S37/(1-Parametros!$B$14)) | Y37: =IF(OR(S37="",Parametros!$B$14+Parametros!$B$18>=1),"",S37/(1-Parametros!$B$14-Parametros!$B$18)) | Z37: =IF(B37="","",IF(S37="","FALTAN DATOS",IF(NOT(ISNUMBER(E37)),"FALTA PRECIO",IF(V37<0,"PIERDE",IF(W37<Parametros!$B$18,"BAJO META","OK"))))) -> FALTAN DATOS | AA37: =IF(B37="","",IF(F37="","Tela. ","")&IF(NOT(ISNUMBER(G37)),"Kg de tela. ","")&IF(AND(F37<>"",NOT(ISNUMBER(IFERROR(INDEX(Precios!$D$5:$D$120,MATCH(F37,Precios!$A$5:$A$120,0)),"x")))),"Tela sin precio. ","")&IF(AND(H37<>"",NOT(ISNUMBER(IFERROR(INDEX(Precios!$D$5:$D$120,MATCH(H37,Precios!$A$5:$A$120,0)),"x")))),"Tela 2 sin precio. ","")&IF(J37="","Metros impresos. ","")&IF(AND(N(J37)>0,Parametros!$B$27=0),"Impresión sin costo. ","")&IF(K37="","Confección. ",IF(Q37=0,"Confección sin valor. ",""))&IF(NOT(ISNUMBER(E37)),"Precio de venta. ","")) -> Tela. Kg de tela. Metros impresos. Confección.
A38: VOL-CSUB-SAL-MC | B38: Camiseta Salida de Cancha Voley m/c | C38: Salida | D38: 29 | E38: 22605 | K38: Camiseta Voley | M38: Por confirmar | N38: Confección sugerida por el nombre: confirmar. | O38: =IF(B38="","",IFERROR(G38*INDEX(Precios!$D$5:$D$120,MATCH(F38,Precios!$A$5:$A$120,0)),0)+IF(H38="",0,IFERROR(I38*INDEX(Precios!$D$5:$D$120,MATCH(H38,Precios!$A$5:$A$120,0)),0))) -> 0 | P38: =IF(B38="","",N(J38)*Parametros!$B$27) -> 0 | Q38: =IF(B38="","",IFERROR(INDEX(Confeccion!$B$5:$B$100,MATCH(K38,Confeccion!$A$5:$A$100,0)),0)) -> 1700 | R38: =IF(B38="","",N(L38)) -> 0 | S38: =IF(B38="","",IF(AND(F38<>"",ISNUMBER(G38),ISNUMBER(IFERROR(INDEX(Precios!$D$5:$D$120,MATCH(F38,Precios!$A$5:$A$120,0)),"x")),OR(H38="",ISNUMBER(IFERROR(INDEX(Precios!$D$5:$D$120,MATCH(H38,Precios!$A$5:$A$120,0)),"x"))),J38<>"",K38<>"",Q38>0),SUM(O38:R38),"")) | T38: =IF(AND(S38<>"",ISNUMBER(E38)),E38*Parametros!$B$12,"") | U38: =IF(AND(S38<>"",ISNUMBER(E38)),E38*Parametros!$B$13,"") | V38: =IF(AND(S38<>"",ISNUMBER(E38)),E38-S38-T38-U38,"") | W38: =IF(AND(S38<>"",ISNUMBER(E38)),V38/E38,"") | X38: =IF(OR(S38="",Parametros!$B$14>=1),"",S38/(1-Parametros!$B$14)) | Y38: =IF(OR(S38="",Parametros!$B$14+Parametros!$B$18>=1),"",S38/(1-Parametros!$B$14-Parametros!$B$18)) | Z38: =IF(B38="","",IF(S38="","FALTAN DATOS",IF(NOT(ISNUMBER(E38)),"FALTA PRECIO",IF(V38<0,"PIERDE",IF(W38<Parametros!$B$18,"BAJO META","OK"))))) -> FALTAN DATOS | AA38: =IF(B38="","",IF(F38="","Tela. ","")&IF(NOT(ISNUMBER(G38)),"Kg de tela. ","")&IF(AND(F38<>"",NOT(ISNUMBER(IFERROR(INDEX(Precios!$D$5:$D$120,MATCH(F38,Precios!$A$5:$A$120,0)),"x")))),"Tela sin precio. ","")&IF(AND(H38<>"",NOT(ISNUMBER(IFERROR(INDEX(Precios!$D$5:$D$120,MATCH(H38,Precios!$A$5:$A$120,0)),"x")))),"Tela 2 sin precio. ","")&IF(J38="","Metros impresos. ","")&IF(AND(N(J38)>0,Parametros!$B$27=0),"Impresión sin costo. ","")&IF(K38="","Confección. ",IF(Q38=0,"Confección sin valor. ",""))&IF(NOT(ISNUMBER(E38)),"Precio de venta. ","")) -> Tela. Kg de tela. Metros impresos.
A39: CSUBVOLFEMVSM | B39: CAMISETA VOLEY FEM V S/M PLAYMAKER | C39: Juego | D39: 29 | E39: 16723 | K39: Camiseta Voley | M39: Por confirmar | N39: Confección sugerida por el nombre: confirmar. | O39: =IF(B39="","",IFERROR(G39*INDEX(Precios!$D$5:$D$120,MATCH(F39,Precios!$A$5:$A$120,0)),0)+IF(H39="",0,IFERROR(I39*INDEX(Precios!$D$5:$D$120,MATCH(H39,Precios!$A$5:$A$120,0)),0))) -> 0 | P39: =IF(B39="","",N(J39)*Parametros!$B$27) -> 0 | Q39: =IF(B39="","",IFERROR(INDEX(Confeccion!$B$5:$B$100,MATCH(K39,Confeccion!$A$5:$A$100,0)),0)) -> 1700 | R39: =IF(B39="","",N(L39)) -> 0 | S39: =IF(B39="","",IF(AND(F39<>"",ISNUMBER(G39),ISNUMBER(IFERROR(INDEX(Precios!$D$5:$D$120,MATCH(F39,Precios!$A$5:$A$120,0)),"x")),OR(H39="",ISNUMBER(IFERROR(INDEX(Precios!$D$5:$D$120,MATCH(H39,Precios!$A$5:$A$120,0)),"x"))),J39<>"",K39<>"",Q39>0),SUM(O39:R39),"")) | T39: =IF(AND(S39<>"",ISNUMBER(E39)),E39*Parametros!$B$12,"") | U39: =IF(AND(S39<>"",ISNUMBER(E39)),E39*Parametros!$B$13,"") | V39: =IF(AND(S39<>"",ISNUMBER(E39)),E39-S39-T39-U39,"") | W39: =IF(AND(S39<>"",ISNUMBER(E39)),V39/E39,"") | X39: =IF(OR(S39="",Parametros!$B$14>=1),"",S39/(1-Parametros!$B$14)) | Y39: =IF(OR(S39="",Parametros!$B$14+Parametros!$B$18>=1),"",S39/(1-Parametros!$B$14-Parametros!$B$18)) | Z39: =IF(B39="","",IF(S39="","FALTAN DATOS",IF(NOT(ISNUMBER(E39)),"FALTA PRECIO",IF(V39<0,"PIERDE",IF(W39<Parametros!$B$18,"BAJO META","OK"))))) -> FALTAN DATOS | AA39: =IF(B39="","",IF(F39="","Tela. ","")&IF(NOT(ISNUMBER(G39)),"Kg de tela. ","")&IF(AND(F39<>"",NOT(ISNUMBER(IFERROR(INDEX(Precios!$D$5:$D$120,MATCH(F39,Precios!$A$5:$A$120,0)),"x")))),"Tela sin precio. ","")&IF(AND(H39<>"",NOT(ISNUMBER(IFERROR(INDEX(Precios!$D$5:$D$120,MATCH(H39,Precios!$A$5:$A$120,0)),"x")))),"Tela 2 sin precio. ","")&IF(J39="","Metros impresos. ","")&IF(AND(N(J39)>0,Parametros!$B$27=0),"Impresión sin costo. ","")&IF(K39="","Confección. ",IF(Q39=0,"Confección sin valor. ",""))&IF(NOT(ISNUMBER(E39)),"Precio de venta. ","")) -> Tela. Kg de tela. Metros impresos.
A40: RUG-CSUB-LIC | B40: Camiseta Rugby Playmaker, Low Profile | C40: Juego | D40: 26 | E40: 23488 | M40: Por confirmar | O40: =IF(B40="","",IFERROR(G40*INDEX(Precios!$D$5:$D$120,MATCH(F40,Precios!$A$5:$A$120,0)),0)+IF(H40="",0,IFERROR(I40*INDEX(Precios!$D$5:$D$120,MATCH(H40,Precios!$A$5:$A$120,0)),0))) -> 0 | P40: =IF(B40="","",N(J40)*Parametros!$B$27) -> 0 | Q40: =IF(B40="","",IFERROR(INDEX(Confeccion!$B$5:$B$100,MATCH(K40,Confeccion!$A$5:$A$100,0)),0)) -> 0 | R40: =IF(B40="","",N(L40)) -> 0 | S40: =IF(B40="","",IF(AND(F40<>"",ISNUMBER(G40),ISNUMBER(IFERROR(INDEX(Precios!$D$5:$D$120,MATCH(F40,Precios!$A$5:$A$120,0)),"x")),OR(H40="",ISNUMBER(IFERROR(INDEX(Precios!$D$5:$D$120,MATCH(H40,Precios!$A$5:$A$120,0)),"x"))),J40<>"",K40<>"",Q40>0),SUM(O40:R40),"")) | T40: =IF(AND(S40<>"",ISNUMBER(E40)),E40*Parametros!$B$12,"") | U40: =IF(AND(S40<>"",ISNUMBER(E40)),E40*Parametros!$B$13,"") | V40: =IF(AND(S40<>"",ISNUMBER(E40)),E40-S40-T40-U40,"") | W40: =IF(AND(S40<>"",ISNUMBER(E40)),V40/E40,"") | X40: =IF(OR(S40="",Parametros!$B$14>=1),"",S40/(1-Parametros!$B$14)) | Y40: =IF(OR(S40="",Parametros!$B$14+Parametros!$B$18>=1),"",S40/(1-Parametros!$B$14-Parametros!$B$18)) | Z40: =IF(B40="","",IF(S40="","FALTAN DATOS",IF(NOT(ISNUMBER(E40)),"FALTA PRECIO",IF(V40<0,"PIERDE",IF(W40<Parametros!$B$18,"BAJO META","OK"))))) -> FALTAN DATOS | AA40: =IF(B40="","",IF(F40="","Tela. ","")&IF(NOT(ISNUMBER(G40)),"Kg de tela. ","")&IF(AND(F40<>"",NOT(ISNUMBER(IFERROR(INDEX(Precios!$D$5:$D$120,MATCH(F40,Precios!$A$5:$A$120,0)),"x")))),"Tela sin precio. ","")&IF(AND(H40<>"",NOT(ISNUMBER(IFERROR(INDEX(Precios!$D$5:$D$120,MATCH(H40,Precios!$A$5:$A$120,0)),"x")))),"Tela 2 sin precio. ","")&IF(J40="","Metros impresos. ","")&IF(AND(N(J40)>0,Parametros!$B$27=0),"Impresión sin costo. ","")&IF(K40="","Confección. ",IF(Q40=0,"Confección sin valor. ",""))&IF(NOT(ISNUMBER(E40)),"Precio de venta. ","")) -> Tela. Kg de tela. Metros impresos. Confección.
A41: RUNCSUBPROMC | B41: Camiseta Running Pro m/c | C41: Juego | D41: 25 | E41: 19244 | F41: 5K NACIONAL (running pro) | K41: Camiseta Running Con Manga | M41: Por confirmar | N41: La ficha OT 2223 (0,082 kg) es s/m; con manga gasta más. Falta consumo. | O41: =IF(B41="","",IFERROR(G41*INDEX(Precios!$D$5:$D$120,MATCH(F41,Precios!$A$5:$A$120,0)),0)+IF(H41="",0,IFERROR(I41*INDEX(Precios!$D$5:$D$120,MATCH(H41,Precios!$A$5:$A$120,0)),0))) -> 0 | P41: =IF(B41="","",N(J41)*Parametros!$B$27) -> 0 | Q41: =IF(B41="","",IFERROR(INDEX(Confeccion!$B$5:$B$100,MATCH(K41,Confeccion!$A$5:$A$100,0)),0)) -> 2000 | R41: =IF(B41="","",N(L41)) -> 0 | S41: =IF(B41="","",IF(AND(F41<>"",ISNUMBER(G41),ISNUMBER(IFERROR(INDEX(Precios!$D$5:$D$120,MATCH(F41,Precios!$A$5:$A$120,0)),"x")),OR(H41="",ISNUMBER(IFERROR(INDEX(Precios!$D$5:$D$120,MATCH(H41,Precios!$A$5:$A$120,0)),"x"))),J41<>"",K41<>"",Q41>0),SUM(O41:R41),"")) | T41: =IF(AND(S41<>"",ISNUMBER(E41)),E41*Parametros!$B$12,"") | U41: =IF(AND(S41<>"",ISNUMBER(E41)),E41*Parametros!$B$13,"") | V41: =IF(AND(S41<>"",ISNUMBER(E41)),E41-S41-T41-U41,"") | W41: =IF(AND(S41<>"",ISNUMBER(E41)),V41/E41,"") | X41: =IF(OR(S41="",Parametros!$B$14>=1),"",S41/(1-Parametros!$B$14)) | Y41: =IF(OR(S41="",Parametros!$B$14+Parametros!$B$18>=1),"",S41/(1-Parametros!$B$14-Parametros!$B$18)) | Z41: =IF(B41="","",IF(S41="","FALTAN DATOS",IF(NOT(ISNUMBER(E41)),"FALTA PRECIO",IF(V41<0,"PIERDE",IF(W41<Parametros!$B$18,"BAJO META","OK"))))) -> FALTAN DATOS | AA41: =IF(B41="","",IF(F41="","Tela. ","")&IF(NOT(ISNUMBER(G41)),"Kg de tela. ","")&IF(AND(F41<>"",NOT(ISNUMBER(IFERROR(INDEX(Precios!$D$5:$D$120,MATCH(F41,Precios!$A$5:$A$120,0)),"x")))),"Tela sin precio. ","")&IF(AND(H41<>"",NOT(ISNUMBER(IFERROR(INDEX(Precios!$D$5:$D$120,MATCH(H41,Precios!$A$5:$A$120,0)),"x")))),"Tela 2 sin precio. ","")&IF(J41="","Metros impresos. ","")&IF(AND(N(J41)>0,Parametros!$B$27=0),"Impresión sin costo. ","")&IF(K41="","Confección. ",IF(Q41=0,"Confección sin valor. ",""))&IF(NOT(ISNUMBER(E41)),"Precio de venta. ","")) -> Kg de tela. Metros impresos.
A42: SAL-SHO-SUB | B42: SHORT SALIDA SUB | C42: Salida | D42: 25 | E42: 15882 | K42: Short De Salida | M42: Por confirmar | N42: Confección sugerida por el nombre: confirmar. | O42: =IF(B42="","",IFERROR(G42*INDEX(Precios!$D$5:$D$120,MATCH(F42,Precios!$A$5:$A$120,0)),0)+IF(H42="",0,IFERROR(I42*INDEX(Precios!$D$5:$D$120,MATCH(H42,Precios!$A$5:$A$120,0)),0))) -> 0 | P42: =IF(B42="","",N(J42)*Parametros!$B$27) -> 0 | Q42: =IF(B42="","",IFERROR(INDEX(Confeccion!$B$5:$B$100,MATCH(K42,Confeccion!$A$5:$A$100,0)),0)) -> 2200 | R42: =IF(B42="","",N(L42)) -> 0 | S42: =IF(B42="","",IF(AND(F42<>"",ISNUMBER(G42),ISNUMBER(IFERROR(INDEX(Precios!$D$5:$D$120,MATCH(F42,Precios!$A$5:$A$120,0)),"x")),OR(H42="",ISNUMBER(IFERROR(INDEX(Precios!$D$5:$D$120,MATCH(H42,Precios!$A$5:$A$120,0)),"x"))),J42<>"",K42<>"",Q42>0),SUM(O42:R42),"")) | T42: =IF(AND(S42<>"",ISNUMBER(E42)),E42*Parametros!$B$12,"") | U42: =IF(AND(S42<>"",ISNUMBER(E42)),E42*Parametros!$B$13,"") | V42: =IF(AND(S42<>"",ISNUMBER(E42)),E42-S42-T42-U42,"") | W42: =IF(AND(S42<>"",ISNUMBER(E42)),V42/E42,"") | X42: =IF(OR(S42="",Parametros!$B$14>=1),"",S42/(1-Parametros!$B$14)) | Y42: =IF(OR(S42="",Parametros!$B$14+Parametros!$B$18>=1),"",S42/(1-Parametros!$B$14-Parametros!$B$18)) | Z42: =IF(B42="","",IF(S42="","FALTAN DATOS",IF(NOT(ISNUMBER(E42)),"FALTA PRECIO",IF(V42<0,"PIERDE",IF(W42<Parametros!$B$18,"BAJO META","OK"))))) -> FALTAN DATOS | AA42: =IF(B42="","",IF(F42="","Tela. ","")&IF(NOT(ISNUMBER(G42)),"Kg de tela. ","")&IF(AND(F42<>"",NOT(ISNUMBER(IFERROR(INDEX(Precios!$D$5:$D$120,MATCH(F42,Precios!$A$5:$A$120,0)),"x")))),"Tela sin precio. ","")&IF(AND(H42<>"",NOT(ISNUMBER(IFERROR(INDEX(Precios!$D$5:$D$120,MATCH(H42,Precios!$A$5:$A$120,0)),"x")))),"Tela 2 sin precio. ","")&IF(J42="","Metros impresos. ","")&IF(AND(N(J42)>0,Parametros!$B$27=0),"Impresión sin costo. ","")&IF(K42="","Confección. ",IF(Q42=0,"Confección sin valor. ",""))&IF(NOT(ISNUMBER(E42)),"Precio de venta. ","")) -> Tela. Kg de tela. Metros impresos.
A43: FUTCSUBPIQMC | B43: Camiseta Fútbol Playmaker, Piqué m/c | C43: Juego | D43: 24 | E43: 18403 | K43: Camiseta De Futbol | M43: Por confirmar | N43: Confección sugerida por el nombre: confirmar. | O43: =IF(B43="","",IFERROR(G43*INDEX(Precios!$D$5:$D$120,MATCH(F43,Precios!$A$5:$A$120,0)),0)+IF(H43="",0,IFERROR(I43*INDEX(Precios!$D$5:$D$120,MATCH(H43,Precios!$A$5:$A$120,0)),0))) -> 0 | P43: =IF(B43="","",N(J43)*Parametros!$B$27) -> 0 | Q43: =IF(B43="","",IFERROR(INDEX(Confeccion!$B$5:$B$100,MATCH(K43,Confeccion!$A$5:$A$100,0)),0)) -> 2000 | R43: =IF(B43="","",N(L43)) -> 0 | S43: =IF(B43="","",IF(AND(F43<>"",ISNUMBER(G43),ISNUMBER(IFERROR(INDEX(Precios!$D$5:$D$120,MATCH(F43,Precios!$A$5:$A$120,0)),"x")),OR(H43="",ISNUMBER(IFERROR(INDEX(Precios!$D$5:$D$120,MATCH(H43,Precios!$A$5:$A$120,0)),"x"))),J43<>"",K43<>"",Q43>0),SUM(O43:R43),"")) | T43: =IF(AND(S43<>"",ISNUMBER(E43)),E43*Parametros!$B$12,"") | U43: =IF(AND(S43<>"",ISNUMBER(E43)),E43*Parametros!$B$13,"") | V43: =IF(AND(S43<>"",ISNUMBER(E43)),E43-S43-T43-U43,"") | W43: =IF(AND(S43<>"",ISNUMBER(E43)),V43/E43,"") | X43: =IF(OR(S43="",Parametros!$B$14>=1),"",S43/(1-Parametros!$B$14)) | Y43: =IF(OR(S43="",Parametros!$B$14+Parametros!$B$18>=1),"",S43/(1-Parametros!$B$14-Parametros!$B$18)) | Z43: =IF(B43="","",IF(S43="","FALTAN DATOS",IF(NOT(ISNUMBER(E43)),"FALTA PRECIO",IF(V43<0,"PIERDE",IF(W43<Parametros!$B$18,"BAJO META","OK"))))) -> FALTAN DATOS | AA43: =IF(B43="","",IF(F43="","Tela. ","")&IF(NOT(ISNUMBER(G43)),"Kg de tela. ","")&IF(AND(F43<>"",NOT(ISNUMBER(IFERROR(INDEX(Precios!$D$5:$D$120,MATCH(F43,Precios!$A$5:$A$120,0)),"x")))),"Tela sin precio. ","")&IF(AND(H43<>"",NOT(ISNUMBER(IFERROR(INDEX(Precios!$D$5:$D$120,MATCH(H43,Precios!$A$5:$A$120,0)),"x")))),"Tela 2 sin precio. ","")&IF(J43="","Metros impresos. ","")&IF(AND(N(J43)>0,Parametros!$B$27=0),"Impresión sin costo. ","")&IF(K43="","Confección. ",IF(Q43=0,"Confección sin valor. ",""))&IF(NOT(ISNUMBER(E43)),"Precio de venta. ","")) -> Tela. Kg de tela. Metros impresos.
A44: FUTCSUBPROMC-V | B44: Camiseta Fútbol Pro Playmaker, V m/c | C44: Juego | D44: 23 | E44: 19244 | F44: MONTESIMONE TRAINING (fut pro) | G44: 0.12 | H44: MESH | I44: 0.0775 | J44: 1.9 | K44: Camiseta De Futbol | M44: Por confirmar | N44: Igual que Pro cuello redondo (OT 2547). Cuello V puede variar. | O44: =IF(B44="","",IFERROR(G44*INDEX(Precios!$D$5:$D$120,MATCH(F44,Precios!$A$5:$A$120,0)),0)+IF(H44="",0,IFERROR(I44*INDEX(Precios!$D$5:$D$120,MATCH(H44,Precios!$A$5:$A$120,0)),0))) -> 1020.47 | P44: =IF(B44="","",N(J44)*Parametros!$B$27) -> 0 | Q44: =IF(B44="","",IFERROR(INDEX(Confeccion!$B$5:$B$100,MATCH(K44,Confeccion!$A$5:$A$100,0)),0)) -> 2000 | R44: =IF(B44="","",N(L44)) -> 0 | S44: =IF(B44="","",IF(AND(F44<>"",ISNUMBER(G44),ISNUMBER(IFERROR(INDEX(Precios!$D$5:$D$120,MATCH(F44,Precios!$A$5:$A$120,0)),"x")),OR(H44="",ISNUMBER(IFERROR(INDEX(Precios!$D$5:$D$120,MATCH(H44,Precios!$A$5:$A$120,0)),"x"))),J44<>"",K44<>"",Q44>0),SUM(O44:R44),"")) -> 3020.47 | T44: =IF(AND(S44<>"",ISNUMBER(E44)),E44*Parametros!$B$12,"") -> 6792.1033 | U44: =IF(AND(S44<>"",ISNUMBER(E44)),E44*Parametros!$B$13,"") -> 2438.1464 | V44: =IF(AND(S44<>"",ISNUMBER(E44)),E44-S44-T44-U44,"") -> 6993.2804 | W44: =IF(AND(S44<>"",ISNUMBER(E44)),V44/E44,"") -> 0.36340056 | X44: =IF(OR(S44="",Parametros!$B$14>=1),"",S44/(1-Parametros!$B$14)) -> 5804.6109 | Y44: =IF(OR(S44="",Parametros!$B$14+Parametros!$B$18>=1),"",S44/(1-Parametros!$B$14-Parametros!$B$18)) -> 7185.4873 | Z44: =IF(B44="","",IF(S44="","FALTAN DATOS",IF(NOT(ISNUMBER(E44)),"FALTA PRECIO",IF(V44<0,"PIERDE",IF(W44<Parametros!$B$18,"BAJO META","OK"))))) -> OK | AA44: =IF(B44="","",IF(F44="","Tela. ","")&IF(NOT(ISNUMBER(G44)),"Kg de tela. ","")&IF(AND(F44<>"",NOT(ISNUMBER(IFERROR(INDEX(Precios!$D$5:$D$120,MATCH(F44,Precios!$A$5:$A$120,0)),"x")))),"Tela sin precio. ","")&IF(AND(H44<>"",NOT(ISNUMBER(IFERROR(INDEX(Precios!$D$5:$D$120,MATCH(H44,Precios!$A$5:$A$120,0)),"x")))),"Tela 2 sin precio. ","")&IF(J44="","Metros impresos. ","")&IF(AND(N(J44)>0,Parametros!$B$27=0),"Impresión sin costo. ","")&IF(K44="","Confección. ",IF(Q44=0,"Confección sin valor. ",""))&IF(NOT(ISNUMBER(E44)),"Precio de venta. ","")) -> Impresión sin costo.
A45: BASCSUBPER | B45: Camiseta Básquetbol Performance | C45: Juego | D45: 21 | E45: 17563 | F45: QUICKDRY | G45: 0.2029 | K45: Camiseta De Basket | M45: Por confirmar | N45: Ficha OT 2425 solo camiseta (3,45 kg / 17). El sistema anterior mezclaba camiseta + short (0,178). Falta metros. | O45: =IF(B45="","",IFERROR(G45*INDEX(Precios!$D$5:$D$120,MATCH(F45,Precios!$A$5:$A$120,0)),0)+IF(H45="",0,IFERROR(I45*INDEX(Precios!$D$5:$D$120,MATCH(H45,Precios!$A$5:$A$120,0)),0))) -> 1419.4884 | P45: =IF(B45="","",N(J45)*Parametros!$B$27) -> 0 | Q45: =IF(B45="","",IFERROR(INDEX(Confeccion!$B$5:$B$100,MATCH(K45,Confeccion!$A$5:$A$100,0)),0)) -> 1900 | R45: =IF(B45="","",N(L45)) -> 0 | S45: =IF(B45="","",IF(AND(F45<>"",ISNUMBER(G45),ISNUMBER(IFERROR(INDEX(Precios!$D$5:$D$120,MATCH(F45,Precios!$A$5:$A$120,0)),"x")),OR(H45="",ISNUMBER(IFERROR(INDEX(Precios!$D$5:$D$120,MATCH(H45,Precios!$A$5:$A$120,0)),"x"))),J45<>"",K45<>"",Q45>0),SUM(O45:R45),"")) | T45: =IF(AND(S45<>"",ISNUMBER(E45)),E45*Parametros!$B$12,"") | U45: =IF(AND(S45<>"",ISNUMBER(E45)),E45*Parametros!$B$13,"") | V45: =IF(AND(S45<>"",ISNUMBER(E45)),E45-S45-T45-U45,"") | W45: =IF(AND(S45<>"",ISNUMBER(E45)),V45/E45,"") | X45: =IF(OR(S45="",Parametros!$B$14>=1),"",S45/(1-Parametros!$B$14)) | Y45: =IF(OR(S45="",Parametros!$B$14+Parametros!$B$18>=1),"",S45/(1-Parametros!$B$14-Parametros!$B$18)) | Z45: =IF(B45="","",IF(S45="","FALTAN DATOS",IF(NOT(ISNUMBER(E45)),"FALTA PRECIO",IF(V45<0,"PIERDE",IF(W45<Parametros!$B$18,"BAJO META","OK"))))) -> FALTAN DATOS | AA45: =IF(B45="","",IF(F45="","Tela. ","")&IF(NOT(ISNUMBER(G45)),"Kg de tela. ","")&IF(AND(F45<>"",NOT(ISNUMBER(IFERROR(INDEX(Precios!$D$5:$D$120,MATCH(F45,Precios!$A$5:$A$120,0)),"x")))),"Tela sin precio. ","")&IF(AND(H45<>"",NOT(ISNUMBER(IFERROR(INDEX(Precios!$D$5:$D$120,MATCH(H45,Precios!$A$5:$A$120,0)),"x")))),"Tela 2 sin precio. ","")&IF(J45="","Metros impresos. ","")&IF(AND(N(J45)>0,Parametros!$B$27=0),"Impresión sin costo. ","")&IF(K45="","Confección. ",IF(Q45=0,"Confección sin valor. ",""))&IF(NOT(ISNUMBER(E45)),"Precio de venta. ","")) -> Metros impresos.
A46: VOL-SHO-SUB | B46: Short Fútbol Playmaker Sublimado | C46: Juego | D46: 20 | E46: 12521 | F46: CIRE BLANCO | G46: 0.1609 | K46: Short De Futbol | M46: Por confirmar | N46: Consumo del short liso (OT 2547 y 2588). Falta metros impresos. | O46: =IF(B46="","",IFERROR(G46*INDEX(Precios!$D$5:$D$120,MATCH(F46,Precios!$A$5:$A$120,0)),0)+IF(H46="",0,IFERROR(I46*INDEX(Precios!$D$5:$D$120,MATCH(H46,Precios!$A$5:$A$120,0)),0))) -> 901.04 | P46: =IF(B46="","",N(J46)*Parametros!$B$27) -> 0 | Q46: =IF(B46="","",IFERROR(INDEX(Confeccion!$B$5:$B$100,MATCH(K46,Confeccion!$A$5:$A$100,0)),0)) -> 1700 | R46: =IF(B46="","",N(L46)) -> 0 | S46: =IF(B46="","",IF(AND(F46<>"",ISNUMBER(G46),ISNUMBER(IFERROR(INDEX(Precios!$D$5:$D$120,MATCH(F46,Precios!$A$5:$A$120,0)),"x")),OR(H46="",ISNUMBER(IFERROR(INDEX(Precios!$D$5:$D$120,MATCH(H46,Precios!$A$5:$A$120,0)),"x"))),J46<>"",K46<>"",Q46>0),SUM(O46:R46),"")) | T46: =IF(AND(S46<>"",ISNUMBER(E46)),E46*Parametros!$B$12,"") | U46: =IF(AND(S46<>"",ISNUMBER(E46)),E46*Parametros!$B$13,"") | V46: =IF(AND(S46<>"",ISNUMBER(E46)),E46-S46-T46-U46,"") | W46: =IF(AND(S46<>"",ISNUMBER(E46)),V46/E46,"") | X46: =IF(OR(S46="",Parametros!$B$14>=1),"",S46/(1-Parametros!$B$14)) | Y46: =IF(OR(S46="",Parametros!$B$14+Parametros!$B$18>=1),"",S46/(1-Parametros!$B$14-Parametros!$B$18)) | Z46: =IF(B46="","",IF(S46="","FALTAN DATOS",IF(NOT(ISNUMBER(E46)),"FALTA PRECIO",IF(V46<0,"PIERDE",IF(W46<Parametros!$B$18,"BAJO META","OK"))))) -> FALTAN DATOS | AA46: =IF(B46="","",IF(F46="","Tela. ","")&IF(NOT(ISNUMBER(G46)),"Kg de tela. ","")&IF(AND(F46<>"",NOT(ISNUMBER(IFERROR(INDEX(Precios!$D$5:$D$120,MATCH(F46,Precios!$A$5:$A$120,0)),"x")))),"Tela sin precio. ","")&IF(AND(H46<>"",NOT(ISNUMBER(IFERROR(INDEX(Precios!$D$5:$D$120,MATCH(H46,Precios!$A$5:$A$120,0)),"x")))),"Tela 2 sin precio. ","")&IF(J46="","Metros impresos. ","")&IF(AND(N(J46)>0,Parametros!$B$27=0),"Impresión sin costo. ","")&IF(K46="","Confección. ",IF(Q46=0,"Confección sin valor. ",""))&IF(NOT(ISNUMBER(E46)),"Precio de venta. ","")) -> Metros impresos.
A47: VOLFEM-CSUBPRO-POL | B47: Camiseta Voley fem Pro Playmaker, Polo | C47: Juego | D47: 20 | E47: 18403 | K47: Camiseta Voley | M47: Por confirmar | N47: Confección sugerida por el nombre: confirmar. | O47: =IF(B47="","",IFERROR(G47*INDEX(Precios!$D$5:$D$120,MATCH(F47,Precios!$A$5:$A$120,0)),0)+IF(H47="",0,IFERROR(I47*INDEX(Precios!$D$5:$D$120,MATCH(H47,Precios!$A$5:$A$120,0)),0))) -> 0 | P47: =IF(B47="","",N(J47)*Parametros!$B$27) -> 0 | Q47: =IF(B47="","",IFERROR(INDEX(Confeccion!$B$5:$B$100,MATCH(K47,Confeccion!$A$5:$A$100,0)),0)) -> 1700 | R47: =IF(B47="","",N(L47)) -> 0 | S47: =IF(B47="","",IF(AND(F47<>"",ISNUMBER(G47),ISNUMBER(IFERROR(INDEX(Precios!$D$5:$D$120,MATCH(F47,Precios!$A$5:$A$120,0)),"x")),OR(H47="",ISNUMBER(IFERROR(INDEX(Precios!$D$5:$D$120,MATCH(H47,Precios!$A$5:$A$120,0)),"x"))),J47<>"",K47<>"",Q47>0),SUM(O47:R47),"")) | T47: =IF(AND(S47<>"",ISNUMBER(E47)),E47*Parametros!$B$12,"") | U47: =IF(AND(S47<>"",ISNUMBER(E47)),E47*Parametros!$B$13,"") | V47: =IF(AND(S47<>"",ISNUMBER(E47)),E47-S47-T47-U47,"") | W47: =IF(AND(S47<>"",ISNUMBER(E47)),V47/E47,"") | X47: =IF(OR(S47="",Parametros!$B$14>=1),"",S47/(1-Parametros!$B$14)) | Y47: =IF(OR(S47="",Parametros!$B$14+Parametros!$B$18>=1),"",S47/(1-Parametros!$B$14-Parametros!$B$18)) | Z47: =IF(B47="","",IF(S47="","FALTAN DATOS",IF(NOT(ISNUMBER(E47)),"FALTA PRECIO",IF(V47<0,"PIERDE",IF(W47<Parametros!$B$18,"BAJO META","OK"))))) -> FALTAN DATOS | AA47: =IF(B47="","",IF(F47="","Tela. ","")&IF(NOT(ISNUMBER(G47)),"Kg de tela. ","")&IF(AND(F47<>"",NOT(ISNUMBER(IFERROR(INDEX(Precios!$D$5:$D$120,MATCH(F47,Precios!$A$5:$A$120,0)),"x")))),"Tela sin precio. ","")&IF(AND(H47<>"",NOT(ISNUMBER(IFERROR(INDEX(Precios!$D$5:$D$120,MATCH(H47,Precios!$A$5:$A$120,0)),"x")))),"Tela 2 sin precio. ","")&IF(J47="","Metros impresos. ","")&IF(AND(N(J47)>0,Parametros!$B$27=0),"Impresión sin costo. ","")&IF(K47="","Confección. ",IF(Q47=0,"Confección sin valor. ",""))&IF(NOT(ISNUMBER(E47)),"Precio de venta. ","")) -> Tela. Kg de tela. Metros impresos.
A48: CSUBRUGSFBLAZUL | B48: CAMISETA DE RUGBY STADE FRANCAIS ANIVERSARIO (AZUL) | C48: Juego | D48: 20 | E48: 30000 | M48: Por confirmar | O48: =IF(B48="","",IFERROR(G48*INDEX(Precios!$D$5:$D$120,MATCH(F48,Precios!$A$5:$A$120,0)),0)+IF(H48="",0,IFERROR(I48*INDEX(Precios!$D$5:$D$120,MATCH(H48,Precios!$A$5:$A$120,0)),0))) -> 0 | P48: =IF(B48="","",N(J48)*Parametros!$B$27) -> 0 | Q48: =IF(B48="","",IFERROR(INDEX(Confeccion!$B$5:$B$100,MATCH(K48,Confeccion!$A$5:$A$100,0)),0)) -> 0 | R48: =IF(B48="","",N(L48)) -> 0 | S48: =IF(B48="","",IF(AND(F48<>"",ISNUMBER(G48),ISNUMBER(IFERROR(INDEX(Precios!$D$5:$D$120,MATCH(F48,Precios!$A$5:$A$120,0)),"x")),OR(H48="",ISNUMBER(IFERROR(INDEX(Precios!$D$5:$D$120,MATCH(H48,Precios!$A$5:$A$120,0)),"x"))),J48<>"",K48<>"",Q48>0),SUM(O48:R48),"")) | T48: =IF(AND(S48<>"",ISNUMBER(E48)),E48*Parametros!$B$12,"") | U48: =IF(AND(S48<>"",ISNUMBER(E48)),E48*Parametros!$B$13,"") | V48: =IF(AND(S48<>"",ISNUMBER(E48)),E48-S48-T48-U48,"") | W48: =IF(AND(S48<>"",ISNUMBER(E48)),V48/E48,"") | X48: =IF(OR(S48="",Parametros!$B$14>=1),"",S48/(1-Parametros!$B$14)) | Y48: =IF(OR(S48="",Parametros!$B$14+Parametros!$B$18>=1),"",S48/(1-Parametros!$B$14-Parametros!$B$18)) | Z48: =IF(B48="","",IF(S48="","FALTAN DATOS",IF(NOT(ISNUMBER(E48)),"FALTA PRECIO",IF(V48<0,"PIERDE",IF(W48<Parametros!$B$18,"BAJO META","OK"))))) -> FALTAN DATOS | AA48: =IF(B48="","",IF(F48="","Tela. ","")&IF(NOT(ISNUMBER(G48)),"Kg de tela. ","")&IF(AND(F48<>"",NOT(ISNUMBER(IFERROR(INDEX(Precios!$D$5:$D$120,MATCH(F48,Precios!$A$5:$A$120,0)),"x")))),"Tela sin precio. ","")&IF(AND(H48<>"",NOT(ISNUMBER(IFERROR(INDEX(Precios!$D$5:$D$120,MATCH(H48,Precios!$A$5:$A$120,0)),"x")))),"Tela 2 sin precio. ","")&IF(J48="","Metros impresos. ","")&IF(AND(N(J48)>0,Parametros!$B$27=0),"Impresión sin costo. ","")&IF(K48="","Confección. ",IF(Q48=0,"Confección sin valor. ",""))&IF(NOT(ISNUMBER(E48)),"Precio de venta. ","")) -> Tela. Kg de tela. Metros impresos. Confección.
A49: MDPTLIS | B49: PETO ENTRENAMIENTO LISO | C49: Juego | D49: 20 | E49: 6000 | K49: Peto Entrenamiento | M49: Por confirmar | N49: Confección sugerida por el nombre: confirmar. | O49: =IF(B49="","",IFERROR(G49*INDEX(Precios!$D$5:$D$120,MATCH(F49,Precios!$A$5:$A$120,0)),0)+IF(H49="",0,IFERROR(I49*INDEX(Precios!$D$5:$D$120,MATCH(H49,Precios!$A$5:$A$120,0)),0))) -> 0 | P49: =IF(B49="","",N(J49)*Parametros!$B$27) -> 0 | Q49: =IF(B49="","",IFERROR(INDEX(Confeccion!$B$5:$B$100,MATCH(K49,Confeccion!$A$5:$A$100,0)),0)) -> 1000 | R49: =IF(B49="","",N(L49)) -> 0 | S49: =IF(B49="","",IF(AND(F49<>"",ISNUMBER(G49),ISNUMBER(IFERROR(INDEX(Precios!$D$5:$D$120,MATCH(F49,Precios!$A$5:$A$120,0)),"x")),OR(H49="",ISNUMBER(IFERROR(INDEX(Precios!$D$5:$D$120,MATCH(H49,Precios!$A$5:$A$120,0)),"x"))),J49<>"",K49<>"",Q49>0),SUM(O49:R49),"")) | T49: =IF(AND(S49<>"",ISNUMBER(E49)),E49*Parametros!$B$12,"") | U49: =IF(AND(S49<>"",ISNUMBER(E49)),E49*Parametros!$B$13,"") | V49: =IF(AND(S49<>"",ISNUMBER(E49)),E49-S49-T49-U49,"") | W49: =IF(AND(S49<>"",ISNUMBER(E49)),V49/E49,"") | X49: =IF(OR(S49="",Parametros!$B$14>=1),"",S49/(1-Parametros!$B$14)) | Y49: =IF(OR(S49="",Parametros!$B$14+Parametros!$B$18>=1),"",S49/(1-Parametros!$B$14-Parametros!$B$18)) | Z49: =IF(B49="","",IF(S49="","FALTAN DATOS",IF(NOT(ISNUMBER(E49)),"FALTA PRECIO",IF(V49<0,"PIERDE",IF(W49<Parametros!$B$18,"BAJO META","OK"))))) -> FALTAN DATOS | AA49: =IF(B49="","",IF(F49="","Tela. ","")&IF(NOT(ISNUMBER(G49)),"Kg de tela. ","")&IF(AND(F49<>"",NOT(ISNUMBER(IFERROR(INDEX(Precios!$D$5:$D$120,MATCH(F49,Precios!$A$5:$A$120,0)),"x")))),"Tela sin precio. ","")&IF(AND(H49<>"",NOT(ISNUMBER(IFERROR(INDEX(Precios!$D$5:$D$120,MATCH(H49,Precios!$A$5:$A$120,0)),"x")))),"Tela 2 sin precio. ","")&IF(J49="","Metros impresos. ","")&IF(AND(N(J49)>0,Parametros!$B$27=0),"Impresión sin costo. ","")&IF(K49="","Confección. ",IF(Q49=0,"Confección sin valor. ",""))&IF(NOT(ISNUMBER(E49)),"Precio de venta. ","")) -> Tela. Kg de tela. Metros impresos.
A50: RUNCSUBPERSM | B50: Camiseta Running Performance s/m | C50: Juego | D50: 19 | E50: 15882 | K50: Camiseta De Running | M50: Por confirmar | N50: Confección sugerida por el nombre: confirmar. | O50: =IF(B50="","",IFERROR(G50*INDEX(Precios!$D$5:$D$120,MATCH(F50,Precios!$A$5:$A$120,0)),0)+IF(H50="",0,IFERROR(I50*INDEX(Precios!$D$5:$D$120,MATCH(H50,Precios!$A$5:$A$120,0)),0))) -> 0 | P50: =IF(B50="","",N(J50)*Parametros!$B$27) -> 0 | Q50: =IF(B50="","",IFERROR(INDEX(Confeccion!$B$5:$B$100,MATCH(K50,Confeccion!$A$5:$A$100,0)),0)) -> 1800 | R50: =IF(B50="","",N(L50)) -> 0 | S50: =IF(B50="","",IF(AND(F50<>"",ISNUMBER(G50),ISNUMBER(IFERROR(INDEX(Precios!$D$5:$D$120,MATCH(F50,Precios!$A$5:$A$120,0)),"x")),OR(H50="",ISNUMBER(IFERROR(INDEX(Precios!$D$5:$D$120,MATCH(H50,Precios!$A$5:$A$120,0)),"x"))),J50<>"",K50<>"",Q50>0),SUM(O50:R50),"")) | T50: =IF(AND(S50<>"",ISNUMBER(E50)),E50*Parametros!$B$12,"") | U50: =IF(AND(S50<>"",ISNUMBER(E50)),E50*Parametros!$B$13,"") | V50: =IF(AND(S50<>"",ISNUMBER(E50)),E50-S50-T50-U50,"") | W50: =IF(AND(S50<>"",ISNUMBER(E50)),V50/E50,"") | X50: =IF(OR(S50="",Parametros!$B$14>=1),"",S50/(1-Parametros!$B$14)) | Y50: =IF(OR(S50="",Parametros!$B$14+Parametros!$B$18>=1),"",S50/(1-Parametros!$B$14-Parametros!$B$18)) | Z50: =IF(B50="","",IF(S50="","FALTAN DATOS",IF(NOT(ISNUMBER(E50)),"FALTA PRECIO",IF(V50<0,"PIERDE",IF(W50<Parametros!$B$18,"BAJO META","OK"))))) -> FALTAN DATOS | AA50: =IF(B50="","",IF(F50="","Tela. ","")&IF(NOT(ISNUMBER(G50)),"Kg de tela. ","")&IF(AND(F50<>"",NOT(ISNUMBER(IFERROR(INDEX(Precios!$D$5:$D$120,MATCH(F50,Precios!$A$5:$A$120,0)),"x")))),"Tela sin precio. ","")&IF(AND(H50<>"",NOT(ISNUMBER(IFERROR(INDEX(Precios!$D$5:$D$120,MATCH(H50,Precios!$A$5:$A$120,0)),"x")))),"Tela 2 sin precio. ","")&IF(J50="","Metros impresos. ","")&IF(AND(N(J50)>0,Parametros!$B$27=0),"Impresión sin costo. ","")&IF(K50="","Confección. ",IF(Q50=0,"Confección sin valor. ",""))&IF(NOT(ISNUMBER(E50)),"Precio de venta. ","")) -> Tela. Kg de tela. Metros impresos.
A51: SAL-BUZ-LIS-RT | B51: Pantalón Buzo Playmaker Liso Recto | C51: Salida | D51: 19 | E51: 15042 | K51: Pantalon No Pitillo | M51: Por confirmar | N51: Confección sugerida por el nombre: confirmar. | O51: =IF(B51="","",IFERROR(G51*INDEX(Precios!$D$5:$D$120,MATCH(F51,Precios!$A$5:$A$120,0)),0)+IF(H51="",0,IFERROR(I51*INDEX(Precios!$D$5:$D$120,MATCH(H51,Precios!$A$5:$A$120,0)),0))) -> 0 | P51: =IF(B51="","",N(J51)*Parametros!$B$27) -> 0 | Q51: =IF(B51="","",IFERROR(INDEX(Confeccion!$B$5:$B$100,MATCH(K51,Confeccion!$A$5:$A$100,0)),0)) -> 3200 | R51: =IF(B51="","",N(L51)) -> 0 | S51: =IF(B51="","",IF(AND(F51<>"",ISNUMBER(G51),ISNUMBER(IFERROR(INDEX(Precios!$D$5:$D$120,MATCH(F51,Precios!$A$5:$A$120,0)),"x")),OR(H51="",ISNUMBER(IFERROR(INDEX(Precios!$D$5:$D$120,MATCH(H51,Precios!$A$5:$A$120,0)),"x"))),J51<>"",K51<>"",Q51>0),SUM(O51:R51),"")) | T51: =IF(AND(S51<>"",ISNUMBER(E51)),E51*Parametros!$B$12,"") | U51: =IF(AND(S51<>"",ISNUMBER(E51)),E51*Parametros!$B$13,"") | V51: =IF(AND(S51<>"",ISNUMBER(E51)),E51-S51-T51-U51,"") | W51: =IF(AND(S51<>"",ISNUMBER(E51)),V51/E51,"") | X51: =IF(OR(S51="",Parametros!$B$14>=1),"",S51/(1-Parametros!$B$14)) | Y51: =IF(OR(S51="",Parametros!$B$14+Parametros!$B$18>=1),"",S51/(1-Parametros!$B$14-Parametros!$B$18)) | Z51: =IF(B51="","",IF(S51="","FALTAN DATOS",IF(NOT(ISNUMBER(E51)),"FALTA PRECIO",IF(V51<0,"PIERDE",IF(W51<Parametros!$B$18,"BAJO META","OK"))))) -> FALTAN DATOS | AA51: =IF(B51="","",IF(F51="","Tela. ","")&IF(NOT(ISNUMBER(G51)),"Kg de tela. ","")&IF(AND(F51<>"",NOT(ISNUMBER(IFERROR(INDEX(Precios!$D$5:$D$120,MATCH(F51,Precios!$A$5:$A$120,0)),"x")))),"Tela sin precio. ","")&IF(AND(H51<>"",NOT(ISNUMBER(IFERROR(INDEX(Precios!$D$5:$D$120,MATCH(H51,Precios!$A$5:$A$120,0)),"x")))),"Tela 2 sin precio. ","")&IF(J51="","Metros impresos. ","")&IF(AND(N(J51)>0,Parametros!$B$27=0),"Impresión sin costo. ","")&IF(K51="","Confección. ",IF(Q51=0,"Confección sin valor. ",""))&IF(NOT(ISNUMBER(E51)),"Precio de venta. ","")) -> Tela. Kg de tela. Metros impresos.
A52: SAL-BUZ-LIS | B52: Pantalón Buzo Playmaker Liso Pitillo | C52: Salida | D52: 17 | E52: 24328 | K52: Pantalon Pitillo | M52: Por confirmar | N52: Confección sugerida por el nombre: confirmar. | O52: =IF(B52="","",IFERROR(G52*INDEX(Precios!$D$5:$D$120,MATCH(F52,Precios!$A$5:$A$120,0)),0)+IF(H52="",0,IFERROR(I52*INDEX(Precios!$D$5:$D$120,MATCH(H52,Precios!$A$5:$A$120,0)),0))) -> 0 | P52: =IF(B52="","",N(J52)*Parametros!$B$27) -> 0 | Q52: =IF(B52="","",IFERROR(INDEX(Confeccion!$B$5:$B$100,MATCH(K52,Confeccion!$A$5:$A$100,0)),0)) -> 3500 | R52: =IF(B52="","",N(L52)) -> 0 | S52: =IF(B52="","",IF(AND(F52<>"",ISNUMBER(G52),ISNUMBER(IFERROR(INDEX(Precios!$D$5:$D$120,MATCH(F52,Precios!$A$5:$A$120,0)),"x")),OR(H52="",ISNUMBER(IFERROR(INDEX(Precios!$D$5:$D$120,MATCH(H52,Precios!$A$5:$A$120,0)),"x"))),J52<>"",K52<>"",Q52>0),SUM(O52:R52),"")) | T52: =IF(AND(S52<>"",ISNUMBER(E52)),E52*Parametros!$B$12,"") | U52: =IF(AND(S52<>"",ISNUMBER(E52)),E52*Parametros!$B$13,"") | V52: =IF(AND(S52<>"",ISNUMBER(E52)),E52-S52-T52-U52,"") | W52: =IF(AND(S52<>"",ISNUMBER(E52)),V52/E52,"") | X52: =IF(OR(S52="",Parametros!$B$14>=1),"",S52/(1-Parametros!$B$14)) | Y52: =IF(OR(S52="",Parametros!$B$14+Parametros!$B$18>=1),"",S52/(1-Parametros!$B$14-Parametros!$B$18)) | Z52: =IF(B52="","",IF(S52="","FALTAN DATOS",IF(NOT(ISNUMBER(E52)),"FALTA PRECIO",IF(V52<0,"PIERDE",IF(W52<Parametros!$B$18,"BAJO META","OK"))))) -> FALTAN DATOS | AA52: =IF(B52="","",IF(F52="","Tela. ","")&IF(NOT(ISNUMBER(G52)),"Kg de tela. ","")&IF(AND(F52<>"",NOT(ISNUMBER(IFERROR(INDEX(Precios!$D$5:$D$120,MATCH(F52,Precios!$A$5:$A$120,0)),"x")))),"Tela sin precio. ","")&IF(AND(H52<>"",NOT(ISNUMBER(IFERROR(INDEX(Precios!$D$5:$D$120,MATCH(H52,Precios!$A$5:$A$120,0)),"x")))),"Tela 2 sin precio. ","")&IF(J52="","Metros impresos. ","")&IF(AND(N(J52)>0,Parametros!$B$27=0),"Impresión sin costo. ","")&IF(K52="","Confección. ",IF(Q52=0,"Confección sin valor. ",""))&IF(NOT(ISNUMBER(E52)),"Precio de venta. ","")) -> Tela. Kg de tela. Metros impresos.
A53: RUNCSUBPERMC | B53: Camiseta Running Performance m/c | C53: Juego | D53: 16 | E53: 15882 | K53: Camiseta Running Con Manga | M53: Por confirmar | N53: Confección sugerida por el nombre: confirmar. | O53: =IF(B53="","",IFERROR(G53*INDEX(Precios!$D$5:$D$120,MATCH(F53,Precios!$A$5:$A$120,0)),0)+IF(H53="",0,IFERROR(I53*INDEX(Precios!$D$5:$D$120,MATCH(H53,Precios!$A$5:$A$120,0)),0))) -> 0 | P53: =IF(B53="","",N(J53)*Parametros!$B$27) -> 0 | Q53: =IF(B53="","",IFERROR(INDEX(Confeccion!$B$5:$B$100,MATCH(K53,Confeccion!$A$5:$A$100,0)),0)) -> 2000 | R53: =IF(B53="","",N(L53)) -> 0 | S53: =IF(B53="","",IF(AND(F53<>"",ISNUMBER(G53),ISNUMBER(IFERROR(INDEX(Precios!$D$5:$D$120,MATCH(F53,Precios!$A$5:$A$120,0)),"x")),OR(H53="",ISNUMBER(IFERROR(INDEX(Precios!$D$5:$D$120,MATCH(H53,Precios!$A$5:$A$120,0)),"x"))),J53<>"",K53<>"",Q53>0),SUM(O53:R53),"")) | T53: =IF(AND(S53<>"",ISNUMBER(E53)),E53*Parametros!$B$12,"") | U53: =IF(AND(S53<>"",ISNUMBER(E53)),E53*Parametros!$B$13,"") | V53: =IF(AND(S53<>"",ISNUMBER(E53)),E53-S53-T53-U53,"") | W53: =IF(AND(S53<>"",ISNUMBER(E53)),V53/E53,"") | X53: =IF(OR(S53="",Parametros!$B$14>=1),"",S53/(1-Parametros!$B$14)) | Y53: =IF(OR(S53="",Parametros!$B$14+Parametros!$B$18>=1),"",S53/(1-Parametros!$B$14-Parametros!$B$18)) | Z53: =IF(B53="","",IF(S53="","FALTAN DATOS",IF(NOT(ISNUMBER(E53)),"FALTA PRECIO",IF(V53<0,"PIERDE",IF(W53<Parametros!$B$18,"BAJO META","OK"))))) -> FALTAN DATOS | AA53: =IF(B53="","",IF(F53="","Tela. ","")&IF(NOT(ISNUMBER(G53)),"Kg de tela. ","")&IF(AND(F53<>"",NOT(ISNUMBER(IFERROR(INDEX(Precios!$D$5:$D$120,MATCH(F53,Precios!$A$5:$A$120,0)),"x")))),"Tela sin precio. ","")&IF(AND(H53<>"",NOT(ISNUMBER(IFERROR(INDEX(Precios!$D$5:$D$120,MATCH(H53,Precios!$A$5:$A$120,0)),"x")))),"Tela 2 sin precio. ","")&IF(J53="","Metros impresos. ","")&IF(AND(N(J53)>0,Parametros!$B$27=0),"Impresión sin costo. ","")&IF(K53="","Confección. ",IF(Q53=0,"Confección sin valor. ",""))&IF(NOT(ISNUMBER(E53)),"Precio de venta. ","")) -> Tela. Kg de tela. Metros impresos.
A54: HCKCSUBOVA | B54: Camiseta Hockey Playmaker, Cuello Ova s/mangas | C54: Juego | D54: 15 | E54: 17563 | K54: Camiseta De Hockey | M54: Por confirmar | N54: Confección sugerida por el nombre: confirmar. | O54: =IF(B54="","",IFERROR(G54*INDEX(Precios!$D$5:$D$120,MATCH(F54,Precios!$A$5:$A$120,0)),0)+IF(H54="",0,IFERROR(I54*INDEX(Precios!$D$5:$D$120,MATCH(H54,Precios!$A$5:$A$120,0)),0))) -> 0 | P54: =IF(B54="","",N(J54)*Parametros!$B$27) -> 0 | Q54: =IF(B54="","",IFERROR(INDEX(Confeccion!$B$5:$B$100,MATCH(K54,Confeccion!$A$5:$A$100,0)),0)) -> 1800 | R54: =IF(B54="","",N(L54)) -> 0 | S54: =IF(B54="","",IF(AND(F54<>"",ISNUMBER(G54),ISNUMBER(IFERROR(INDEX(Precios!$D$5:$D$120,MATCH(F54,Precios!$A$5:$A$120,0)),"x")),OR(H54="",ISNUMBER(IFERROR(INDEX(Precios!$D$5:$D$120,MATCH(H54,Precios!$A$5:$A$120,0)),"x"))),J54<>"",K54<>"",Q54>0),SUM(O54:R54),"")) | T54: =IF(AND(S54<>"",ISNUMBER(E54)),E54*Parametros!$B$12,"") | U54: =IF(AND(S54<>"",ISNUMBER(E54)),E54*Parametros!$B$13,"") | V54: =IF(AND(S54<>"",ISNUMBER(E54)),E54-S54-T54-U54,"") | W54: =IF(AND(S54<>"",ISNUMBER(E54)),V54/E54,"") | X54: =IF(OR(S54="",Parametros!$B$14>=1),"",S54/(1-Parametros!$B$14)) | Y54: =IF(OR(S54="",Parametros!$B$14+Parametros!$B$18>=1),"",S54/(1-Parametros!$B$14-Parametros!$B$18)) | Z54: =IF(B54="","",IF(S54="","FALTAN DATOS",IF(NOT(ISNUMBER(E54)),"FALTA PRECIO",IF(V54<0,"PIERDE",IF(W54<Parametros!$B$18,"BAJO META","OK"))))) -> FALTAN DATOS | AA54: =IF(B54="","",IF(F54="","Tela. ","")&IF(NOT(ISNUMBER(G54)),"Kg de tela. ","")&IF(AND(F54<>"",NOT(ISNUMBER(IFERROR(INDEX(Precios!$D$5:$D$120,MATCH(F54,Precios!$A$5:$A$120,0)),"x")))),"Tela sin precio. ","")&IF(AND(H54<>"",NOT(ISNUMBER(IFERROR(INDEX(Precios!$D$5:$D$120,MATCH(H54,Precios!$A$5:$A$120,0)),"x")))),"Tela 2 sin precio. ","")&IF(J54="","Metros impresos. ","")&IF(AND(N(J54)>0,Parametros!$B$27=0),"Impresión sin costo. ","")&IF(K54="","Confección. ",IF(Q54=0,"Confección sin valor. ",""))&IF(NOT(ISNUMBER(E54)),"Precio de venta. ","")) -> Tela. Kg de tela. Metros impresos.
A55: HCK-FAL-LIS | B55: Falda Short Hockey Playmaker lisa | C55: Juego | D55: 15 | E55: 14202 | K55: Camiseta De Hockey | M55: Por confirmar | N55: Confección sugerida por el nombre: confirmar. | O55: =IF(B55="","",IFERROR(G55*INDEX(Precios!$D$5:$D$120,MATCH(F55,Precios!$A$5:$A$120,0)),0)+IF(H55="",0,IFERROR(I55*INDEX(Precios!$D$5:$D$120,MATCH(H55,Precios!$A$5:$A$120,0)),0))) -> 0 | P55: =IF(B55="","",N(J55)*Parametros!$B$27) -> 0 | Q55: =IF(B55="","",IFERROR(INDEX(Confeccion!$B$5:$B$100,MATCH(K55,Confeccion!$A$5:$A$100,0)),0)) -> 1800 | R55: =IF(B55="","",N(L55)) -> 0 | S55: =IF(B55="","",IF(AND(F55<>"",ISNUMBER(G55),ISNUMBER(IFERROR(INDEX(Precios!$D$5:$D$120,MATCH(F55,Precios!$A$5:$A$120,0)),"x")),OR(H55="",ISNUMBER(IFERROR(INDEX(Precios!$D$5:$D$120,MATCH(H55,Precios!$A$5:$A$120,0)),"x"))),J55<>"",K55<>"",Q55>0),SUM(O55:R55),"")) | T55: =IF(AND(S55<>"",ISNUMBER(E55)),E55*Parametros!$B$12,"") | U55: =IF(AND(S55<>"",ISNUMBER(E55)),E55*Parametros!$B$13,"") | V55: =IF(AND(S55<>"",ISNUMBER(E55)),E55-S55-T55-U55,"") | W55: =IF(AND(S55<>"",ISNUMBER(E55)),V55/E55,"") | X55: =IF(OR(S55="",Parametros!$B$14>=1),"",S55/(1-Parametros!$B$14)) | Y55: =IF(OR(S55="",Parametros!$B$14+Parametros!$B$18>=1),"",S55/(1-Parametros!$B$14-Parametros!$B$18)) | Z55: =IF(B55="","",IF(S55="","FALTAN DATOS",IF(NOT(ISNUMBER(E55)),"FALTA PRECIO",IF(V55<0,"PIERDE",IF(W55<Parametros!$B$18,"BAJO META","OK"))))) -> FALTAN DATOS | AA55: =IF(B55="","",IF(F55="","Tela. ","")&IF(NOT(ISNUMBER(G55)),"Kg de tela. ","")&IF(AND(F55<>"",NOT(ISNUMBER(IFERROR(INDEX(Precios!$D$5:$D$120,MATCH(F55,Precios!$A$5:$A$120,0)),"x")))),"Tela sin precio. ","")&IF(AND(H55<>"",NOT(ISNUMBER(IFERROR(INDEX(Precios!$D$5:$D$120,MATCH(H55,Precios!$A$5:$A$120,0)),"x")))),"Tela 2 sin precio. ","")&IF(J55="","Metros impresos. ","")&IF(AND(N(J55)>0,Parametros!$B$27=0),"Impresión sin costo. ","")&IF(K55="","Confección. ",IF(Q55=0,"Confección sin valor. ",""))&IF(NOT(ISNUMBER(E55)),"Precio de venta. ","")) -> Tela. Kg de tela. Metros impresos.
A56: MDCALLARPMK | B56: Calza larga fem Playmaker | C56: Juego | D56: 14 | E56: 11681 | K56: Calza Larga | M56: Por confirmar | N56: Confección sugerida por el nombre: confirmar. | O56: =IF(B56="","",IFERROR(G56*INDEX(Precios!$D$5:$D$120,MATCH(F56,Precios!$A$5:$A$120,0)),0)+IF(H56="",0,IFERROR(I56*INDEX(Precios!$D$5:$D$120,MATCH(H56,Precios!$A$5:$A$120,0)),0))) -> 0 | P56: =IF(B56="","",N(J56)*Parametros!$B$27) -> 0 | Q56: =IF(B56="","",IFERROR(INDEX(Confeccion!$B$5:$B$100,MATCH(K56,Confeccion!$A$5:$A$100,0)),0)) -> 1800 | R56: =IF(B56="","",N(L56)) -> 0 | S56: =IF(B56="","",IF(AND(F56<>"",ISNUMBER(G56),ISNUMBER(IFERROR(INDEX(Precios!$D$5:$D$120,MATCH(F56,Precios!$A$5:$A$120,0)),"x")),OR(H56="",ISNUMBER(IFERROR(INDEX(Precios!$D$5:$D$120,MATCH(H56,Precios!$A$5:$A$120,0)),"x"))),J56<>"",K56<>"",Q56>0),SUM(O56:R56),"")) | T56: =IF(AND(S56<>"",ISNUMBER(E56)),E56*Parametros!$B$12,"") | U56: =IF(AND(S56<>"",ISNUMBER(E56)),E56*Parametros!$B$13,"") | V56: =IF(AND(S56<>"",ISNUMBER(E56)),E56-S56-T56-U56,"") | W56: =IF(AND(S56<>"",ISNUMBER(E56)),V56/E56,"") | X56: =IF(OR(S56="",Parametros!$B$14>=1),"",S56/(1-Parametros!$B$14)) | Y56: =IF(OR(S56="",Parametros!$B$14+Parametros!$B$18>=1),"",S56/(1-Parametros!$B$14-Parametros!$B$18)) | Z56: =IF(B56="","",IF(S56="","FALTAN DATOS",IF(NOT(ISNUMBER(E56)),"FALTA PRECIO",IF(V56<0,"PIERDE",IF(W56<Parametros!$B$18,"BAJO META","OK"))))) -> FALTAN DATOS | AA56: =IF(B56="","",IF(F56="","Tela. ","")&IF(NOT(ISNUMBER(G56)),"Kg de tela. ","")&IF(AND(F56<>"",NOT(ISNUMBER(IFERROR(INDEX(Precios!$D$5:$D$120,MATCH(F56,Precios!$A$5:$A$120,0)),"x")))),"Tela sin precio. ","")&IF(AND(H56<>"",NOT(ISNUMBER(IFERROR(INDEX(Precios!$D$5:$D$120,MATCH(H56,Precios!$A$5:$A$120,0)),"x")))),"Tela 2 sin precio. ","")&IF(J56="","Metros impresos. ","")&IF(AND(N(J56)>0,Parametros!$B$27=0),"Impresión sin costo. ","")&IF(K56="","Confección. ",IF(Q56=0,"Confección sin valor. ",""))&IF(NOT(ISNUMBER(E56)),"Precio de venta. ","")) -> Tela. Kg de tela. Metros impresos.
A57: SAL-HOO-APSUB | B57: Polerón Hoodie Aplicación Sublim | C57: Salida | D57: 14 | E57: 31092 | K57: Poleron Hoodie | M57: Por confirmar | N57: Confección sugerida por el nombre: confirmar. | O57: =IF(B57="","",IFERROR(G57*INDEX(Precios!$D$5:$D$120,MATCH(F57,Precios!$A$5:$A$120,0)),0)+IF(H57="",0,IFERROR(I57*INDEX(Precios!$D$5:$D$120,MATCH(H57,Precios!$A$5:$A$120,0)),0))) -> 0 | P57: =IF(B57="","",N(J57)*Parametros!$B$27) -> 0 | Q57: =IF(B57="","",IFERROR(INDEX(Confeccion!$B$5:$B$100,MATCH(K57,Confeccion!$A$5:$A$100,0)),0)) -> 3000 | R57: =IF(B57="","",N(L57)) -> 0 | S57: =IF(B57="","",IF(AND(F57<>"",ISNUMBER(G57),ISNUMBER(IFERROR(INDEX(Precios!$D$5:$D$120,MATCH(F57,Precios!$A$5:$A$120,0)),"x")),OR(H57="",ISNUMBER(IFERROR(INDEX(Precios!$D$5:$D$120,MATCH(H57,Precios!$A$5:$A$120,0)),"x"))),J57<>"",K57<>"",Q57>0),SUM(O57:R57),"")) | T57: =IF(AND(S57<>"",ISNUMBER(E57)),E57*Parametros!$B$12,"") | U57: =IF(AND(S57<>"",ISNUMBER(E57)),E57*Parametros!$B$13,"") | V57: =IF(AND(S57<>"",ISNUMBER(E57)),E57-S57-T57-U57,"") | W57: =IF(AND(S57<>"",ISNUMBER(E57)),V57/E57,"") | X57: =IF(OR(S57="",Parametros!$B$14>=1),"",S57/(1-Parametros!$B$14)) | Y57: =IF(OR(S57="",Parametros!$B$14+Parametros!$B$18>=1),"",S57/(1-Parametros!$B$14-Parametros!$B$18)) | Z57: =IF(B57="","",IF(S57="","FALTAN DATOS",IF(NOT(ISNUMBER(E57)),"FALTA PRECIO",IF(V57<0,"PIERDE",IF(W57<Parametros!$B$18,"BAJO META","OK"))))) -> FALTAN DATOS | AA57: =IF(B57="","",IF(F57="","Tela. ","")&IF(NOT(ISNUMBER(G57)),"Kg de tela. ","")&IF(AND(F57<>"",NOT(ISNUMBER(IFERROR(INDEX(Precios!$D$5:$D$120,MATCH(F57,Precios!$A$5:$A$120,0)),"x")))),"Tela sin precio. ","")&IF(AND(H57<>"",NOT(ISNUMBER(IFERROR(INDEX(Precios!$D$5:$D$120,MATCH(H57,Precios!$A$5:$A$120,0)),"x")))),"Tela 2 sin precio. ","")&IF(J57="","Metros impresos. ","")&IF(AND(N(J57)>0,Parametros!$B$27=0),"Impresión sin costo. ","")&IF(K57="","Confección. ",IF(Q57=0,"Confección sin valor. ",""))&IF(NOT(ISNUMBER(E57)),"Precio de venta. ","")) -> Tela. Kg de tela. Metros impresos.
A58: SAL-POL-BAS | B58: POLERON BASIC | C58: Salida | D58: 13 | E58: 17646 | M58: Por confirmar | O58: =IF(B58="","",IFERROR(G58*INDEX(Precios!$D$5:$D$120,MATCH(F58,Precios!$A$5:$A$120,0)),0)+IF(H58="",0,IFERROR(I58*INDEX(Precios!$D$5:$D$120,MATCH(H58,Precios!$A$5:$A$120,0)),0))) -> 0 | P58: =IF(B58="","",N(J58)*Parametros!$B$27) -> 0 | Q58: =IF(B58="","",IFERROR(INDEX(Confeccion!$B$5:$B$100,MATCH(K58,Confeccion!$A$5:$A$100,0)),0)) -> 0 | R58: =IF(B58="","",N(L58)) -> 0 | S58: =IF(B58="","",IF(AND(F58<>"",ISNUMBER(G58),ISNUMBER(IFERROR(INDEX(Precios!$D$5:$D$120,MATCH(F58,Precios!$A$5:$A$120,0)),"x")),OR(H58="",ISNUMBER(IFERROR(INDEX(Precios!$D$5:$D$120,MATCH(H58,Precios!$A$5:$A$120,0)),"x"))),J58<>"",K58<>"",Q58>0),SUM(O58:R58),"")) | T58: =IF(AND(S58<>"",ISNUMBER(E58)),E58*Parametros!$B$12,"") | U58: =IF(AND(S58<>"",ISNUMBER(E58)),E58*Parametros!$B$13,"") | V58: =IF(AND(S58<>"",ISNUMBER(E58)),E58-S58-T58-U58,"") | W58: =IF(AND(S58<>"",ISNUMBER(E58)),V58/E58,"") | X58: =IF(OR(S58="",Parametros!$B$14>=1),"",S58/(1-Parametros!$B$14)) | Y58: =IF(OR(S58="",Parametros!$B$14+Parametros!$B$18>=1),"",S58/(1-Parametros!$B$14-Parametros!$B$18)) | Z58: =IF(B58="","",IF(S58="","FALTAN DATOS",IF(NOT(ISNUMBER(E58)),"FALTA PRECIO",IF(V58<0,"PIERDE",IF(W58<Parametros!$B$18,"BAJO META","OK"))))) -> FALTAN DATOS | AA58: =IF(B58="","",IF(F58="","Tela. ","")&IF(NOT(ISNUMBER(G58)),"Kg de tela. ","")&IF(AND(F58<>"",NOT(ISNUMBER(IFERROR(INDEX(Precios!$D$5:$D$120,MATCH(F58,Precios!$A$5:$A$120,0)),"x")))),"Tela sin precio. ","")&IF(AND(H58<>"",NOT(ISNUMBER(IFERROR(INDEX(Precios!$D$5:$D$120,MATCH(H58,Precios!$A$5:$A$120,0)),"x")))),"Tela 2 sin precio. ","")&IF(J58="","Metros impresos. ","")&IF(AND(N(J58)>0,Parametros!$B$27=0),"Impresión sin costo. ","")&IF(K58="","Confección. ",IF(Q58=0,"Confección sin valor. ",""))&IF(NOT(ISNUMBER(E58)),"Precio de venta. ","")) -> Tela. Kg de tela. Metros impresos. Confección.
A59: CSUBVMC | B59: Polera Playmaker, Subl V m/c | C59: Juego | D59: 13 | E59: 16723 | M59: Por confirmar | O59: =IF(B59="","",IFERROR(G59*INDEX(Precios!$D$5:$D$120,MATCH(F59,Precios!$A$5:$A$120,0)),0)+IF(H59="",0,IFERROR(I59*INDEX(Precios!$D$5:$D$120,MATCH(H59,Precios!$A$5:$A$120,0)),0))) -> 0 | P59: =IF(B59="","",N(J59)*Parametros!$B$27) -> 0 | Q59: =IF(B59="","",IFERROR(INDEX(Confeccion!$B$5:$B$100,MATCH(K59,Confeccion!$A$5:$A$100,0)),0)) -> 0 | R59: =IF(B59="","",N(L59)) -> 0 | S59: =IF(B59="","",IF(AND(F59<>"",ISNUMBER(G59),ISNUMBER(IFERROR(INDEX(Precios!$D$5:$D$120,MATCH(F59,Precios!$A$5:$A$120,0)),"x")),OR(H59="",ISNUMBER(IFERROR(INDEX(Precios!$D$5:$D$120,MATCH(H59,Precios!$A$5:$A$120,0)),"x"))),J59<>"",K59<>"",Q59>0),SUM(O59:R59),"")) | T59: =IF(AND(S59<>"",ISNUMBER(E59)),E59*Parametros!$B$12,"") | U59: =IF(AND(S59<>"",ISNUMBER(E59)),E59*Parametros!$B$13,"") | V59: =IF(AND(S59<>"",ISNUMBER(E59)),E59-S59-T59-U59,"") | W59: =IF(AND(S59<>"",ISNUMBER(E59)),V59/E59,"") | X59: =IF(OR(S59="",Parametros!$B$14>=1),"",S59/(1-Parametros!$B$14)) | Y59: =IF(OR(S59="",Parametros!$B$14+Parametros!$B$18>=1),"",S59/(1-Parametros!$B$14-Parametros!$B$18)) | Z59: =IF(B59="","",IF(S59="","FALTAN DATOS",IF(NOT(ISNUMBER(E59)),"FALTA PRECIO",IF(V59<0,"PIERDE",IF(W59<Parametros!$B$18,"BAJO META","OK"))))) -> FALTAN DATOS | AA59: =IF(B59="","",IF(F59="","Tela. ","")&IF(NOT(ISNUMBER(G59)),"Kg de tela. ","")&IF(AND(F59<>"",NOT(ISNUMBER(IFERROR(INDEX(Precios!$D$5:$D$120,MATCH(F59,Precios!$A$5:$A$120,0)),"x")))),"Tela sin precio. ","")&IF(AND(H59<>"",NOT(ISNUMBER(IFERROR(INDEX(Precios!$D$5:$D$120,MATCH(H59,Precios!$A$5:$A$120,0)),"x")))),"Tela 2 sin precio. ","")&IF(J59="","Metros impresos. ","")&IF(AND(N(J59)>0,Parametros!$B$27=0),"Impresión sin costo. ","")&IF(K59="","Confección. ",IF(Q59=0,"Confección sin valor. ",""))&IF(NOT(ISNUMBER(E59)),"Precio de venta. ","")) -> Tela. Kg de tela. Metros impresos. Confección.
A60: BAS-CSUB-SAL-ML | B60: Camiseta Salida de Cancha Básquetbol m/l | C60: Salida | D60: 13 | E60: 17563 | M60: Por confirmar | O60: =IF(B60="","",IFERROR(G60*INDEX(Precios!$D$5:$D$120,MATCH(F60,Precios!$A$5:$A$120,0)),0)+IF(H60="",0,IFERROR(I60*INDEX(Precios!$D$5:$D$120,MATCH(H60,Precios!$A$5:$A$120,0)),0))) -> 0 | P60: =IF(B60="","",N(J60)*Parametros!$B$27) -> 0 | Q60: =IF(B60="","",IFERROR(INDEX(Confeccion!$B$5:$B$100,MATCH(K60,Confeccion!$A$5:$A$100,0)),0)) -> 0 | R60: =IF(B60="","",N(L60)) -> 0 | S60: =IF(B60="","",IF(AND(F60<>"",ISNUMBER(G60),ISNUMBER(IFERROR(INDEX(Precios!$D$5:$D$120,MATCH(F60,Precios!$A$5:$A$120,0)),"x")),OR(H60="",ISNUMBER(IFERROR(INDEX(Precios!$D$5:$D$120,MATCH(H60,Precios!$A$5:$A$120,0)),"x"))),J60<>"",K60<>"",Q60>0),SUM(O60:R60),"")) | T60: =IF(AND(S60<>"",ISNUMBER(E60)),E60*Parametros!$B$12,"") | U60: =IF(AND(S60<>"",ISNUMBER(E60)),E60*Parametros!$B$13,"") | V60: =IF(AND(S60<>"",ISNUMBER(E60)),E60-S60-T60-U60,"") | W60: =IF(AND(S60<>"",ISNUMBER(E60)),V60/E60,"") | X60: =IF(OR(S60="",Parametros!$B$14>=1),"",S60/(1-Parametros!$B$14)) | Y60: =IF(OR(S60="",Parametros!$B$14+Parametros!$B$18>=1),"",S60/(1-Parametros!$B$14-Parametros!$B$18)) | Z60: =IF(B60="","",IF(S60="","FALTAN DATOS",IF(NOT(ISNUMBER(E60)),"FALTA PRECIO",IF(V60<0,"PIERDE",IF(W60<Parametros!$B$18,"BAJO META","OK"))))) -> FALTAN DATOS | AA60: =IF(B60="","",IF(F60="","Tela. ","")&IF(NOT(ISNUMBER(G60)),"Kg de tela. ","")&IF(AND(F60<>"",NOT(ISNUMBER(IFERROR(INDEX(Precios!$D$5:$D$120,MATCH(F60,Precios!$A$5:$A$120,0)),"x")))),"Tela sin precio. ","")&IF(AND(H60<>"",NOT(ISNUMBER(IFERROR(INDEX(Precios!$D$5:$D$120,MATCH(H60,Precios!$A$5:$A$120,0)),"x")))),"Tela 2 sin precio. ","")&IF(J60="","Metros impresos. ","")&IF(AND(N(J60)>0,Parametros!$B$27=0),"Impresión sin costo. ","")&IF(K60="","Confección. ",IF(Q60=0,"Confección sin valor. ",""))&IF(NOT(ISNUMBER(E60)),"Precio de venta. ","")) -> Tela. Kg de tela. Metros impresos. Confección.
A61: VOLMASC-CSUB-POL-MC | B61: Camiseta Voley masc Playmaker, Polo m/c | C61: Juego | D61: 12 | E61: 16554 | K61: Camiseta Voley | M61: Por confirmar | N61: Confección sugerida por el nombre: confirmar. | O61: =IF(B61="","",IFERROR(G61*INDEX(Precios!$D$5:$D$120,MATCH(F61,Precios!$A$5:$A$120,0)),0)+IF(H61="",0,IFERROR(I61*INDEX(Precios!$D$5:$D$120,MATCH(H61,Precios!$A$5:$A$120,0)),0))) -> 0 | P61: =IF(B61="","",N(J61)*Parametros!$B$27) -> 0 | Q61: =IF(B61="","",IFERROR(INDEX(Confeccion!$B$5:$B$100,MATCH(K61,Confeccion!$A$5:$A$100,0)),0)) -> 1700 | R61: =IF(B61="","",N(L61)) -> 0 | S61: =IF(B61="","",IF(AND(F61<>"",ISNUMBER(G61),ISNUMBER(IFERROR(INDEX(Precios!$D$5:$D$120,MATCH(F61,Precios!$A$5:$A$120,0)),"x")),OR(H61="",ISNUMBER(IFERROR(INDEX(Precios!$D$5:$D$120,MATCH(H61,Precios!$A$5:$A$120,0)),"x"))),J61<>"",K61<>"",Q61>0),SUM(O61:R61),"")) | T61: =IF(AND(S61<>"",ISNUMBER(E61)),E61*Parametros!$B$12,"") | U61: =IF(AND(S61<>"",ISNUMBER(E61)),E61*Parametros!$B$13,"") | V61: =IF(AND(S61<>"",ISNUMBER(E61)),E61-S61-T61-U61,"") | W61: =IF(AND(S61<>"",ISNUMBER(E61)),V61/E61,"") | X61: =IF(OR(S61="",Parametros!$B$14>=1),"",S61/(1-Parametros!$B$14)) | Y61: =IF(OR(S61="",Parametros!$B$14+Parametros!$B$18>=1),"",S61/(1-Parametros!$B$14-Parametros!$B$18)) | Z61: =IF(B61="","",IF(S61="","FALTAN DATOS",IF(NOT(ISNUMBER(E61)),"FALTA PRECIO",IF(V61<0,"PIERDE",IF(W61<Parametros!$B$18,"BAJO META","OK"))))) -> FALTAN DATOS | AA61: =IF(B61="","",IF(F61="","Tela. ","")&IF(NOT(ISNUMBER(G61)),"Kg de tela. ","")&IF(AND(F61<>"",NOT(ISNUMBER(IFERROR(INDEX(Precios!$D$5:$D$120,MATCH(F61,Precios!$A$5:$A$120,0)),"x")))),"Tela sin precio. ","")&IF(AND(H61<>"",NOT(ISNUMBER(IFERROR(INDEX(Precios!$D$5:$D$120,MATCH(H61,Precios!$A$5:$A$120,0)),"x")))),"Tela 2 sin precio. ","")&IF(J61="","Metros impresos. ","")&IF(AND(N(J61)>0,Parametros!$B$27=0),"Impresión sin costo. ","")&IF(K61="","Confección. ",IF(Q61=0,"Confección sin valor. ",""))&IF(NOT(ISNUMBER(E61)),"Precio de venta. ","")) -> Tela. Kg de tela. Metros impresos.
A62: ENTPOLMANSUBL | B62: Polerón de Entrenamiento Mangas Sublimadas | C62: Salida | D62: 12 | E62: 30168 | M62: Por confirmar | O62: =IF(B62="","",IFERROR(G62*INDEX(Precios!$D$5:$D$120,MATCH(F62,Precios!$A$5:$A$120,0)),0)+IF(H62="",0,IFERROR(I62*INDEX(Precios!$D$5:$D$120,MATCH(H62,Precios!$A$5:$A$120,0)),0))) -> 0 | P62: =IF(B62="","",N(J62)*Parametros!$B$27) -> 0 | Q62: =IF(B62="","",IFERROR(INDEX(Confeccion!$B$5:$B$100,MATCH(K62,Confeccion!$A$5:$A$100,0)),0)) -> 0 | R62: =IF(B62="","",N(L62)) -> 0 | S62: =IF(B62="","",IF(AND(F62<>"",ISNUMBER(G62),ISNUMBER(IFERROR(INDEX(Precios!$D$5:$D$120,MATCH(F62,Precios!$A$5:$A$120,0)),"x")),OR(H62="",ISNUMBER(IFERROR(INDEX(Precios!$D$5:$D$120,MATCH(H62,Precios!$A$5:$A$120,0)),"x"))),J62<>"",K62<>"",Q62>0),SUM(O62:R62),"")) | T62: =IF(AND(S62<>"",ISNUMBER(E62)),E62*Parametros!$B$12,"") | U62: =IF(AND(S62<>"",ISNUMBER(E62)),E62*Parametros!$B$13,"") | V62: =IF(AND(S62<>"",ISNUMBER(E62)),E62-S62-T62-U62,"") | W62: =IF(AND(S62<>"",ISNUMBER(E62)),V62/E62,"") | X62: =IF(OR(S62="",Parametros!$B$14>=1),"",S62/(1-Parametros!$B$14)) | Y62: =IF(OR(S62="",Parametros!$B$14+Parametros!$B$18>=1),"",S62/(1-Parametros!$B$14-Parametros!$B$18)) | Z62: =IF(B62="","",IF(S62="","FALTAN DATOS",IF(NOT(ISNUMBER(E62)),"FALTA PRECIO",IF(V62<0,"PIERDE",IF(W62<Parametros!$B$18,"BAJO META","OK"))))) -> FALTAN DATOS | AA62: =IF(B62="","",IF(F62="","Tela. ","")&IF(NOT(ISNUMBER(G62)),"Kg de tela. ","")&IF(AND(F62<>"",NOT(ISNUMBER(IFERROR(INDEX(Precios!$D$5:$D$120,MATCH(F62,Precios!$A$5:$A$120,0)),"x")))),"Tela sin precio. ","")&IF(AND(H62<>"",NOT(ISNUMBER(IFERROR(INDEX(Precios!$D$5:$D$120,MATCH(H62,Precios!$A$5:$A$120,0)),"x")))),"Tela 2 sin precio. ","")&IF(J62="","Metros impresos. ","")&IF(AND(N(J62)>0,Parametros!$B$27=0),"Impresión sin costo. ","")&IF(K62="","Confección. ",IF(Q62=0,"Confección sin valor. ",""))&IF(NOT(ISNUMBER(E62)),"Precio de venta. ","")) -> Tela. Kg de tela. Metros impresos. Confección.
A63: POL-CSUB-POL-ML | B63: Polera Playmaker, Cuello Redondo m/l | C63: Juego | D63: 12 | E63: 17563 | M63: Por confirmar | O63: =IF(B63="","",IFERROR(G63*INDEX(Precios!$D$5:$D$120,MATCH(F63,Precios!$A$5:$A$120,0)),0)+IF(H63="",0,IFERROR(I63*INDEX(Precios!$D$5:$D$120,MATCH(H63,Precios!$A$5:$A$120,0)),0))) -> 0 | P63: =IF(B63="","",N(J63)*Parametros!$B$27) -> 0 | Q63: =IF(B63="","",IFERROR(INDEX(Confeccion!$B$5:$B$100,MATCH(K63,Confeccion!$A$5:$A$100,0)),0)) -> 0 | R63: =IF(B63="","",N(L63)) -> 0 | S63: =IF(B63="","",IF(AND(F63<>"",ISNUMBER(G63),ISNUMBER(IFERROR(INDEX(Precios!$D$5:$D$120,MATCH(F63,Precios!$A$5:$A$120,0)),"x")),OR(H63="",ISNUMBER(IFERROR(INDEX(Precios!$D$5:$D$120,MATCH(H63,Precios!$A$5:$A$120,0)),"x"))),J63<>"",K63<>"",Q63>0),SUM(O63:R63),"")) | T63: =IF(AND(S63<>"",ISNUMBER(E63)),E63*Parametros!$B$12,"") | U63: =IF(AND(S63<>"",ISNUMBER(E63)),E63*Parametros!$B$13,"") | V63: =IF(AND(S63<>"",ISNUMBER(E63)),E63-S63-T63-U63,"") | W63: =IF(AND(S63<>"",ISNUMBER(E63)),V63/E63,"") | X63: =IF(OR(S63="",Parametros!$B$14>=1),"",S63/(1-Parametros!$B$14)) | Y63: =IF(OR(S63="",Parametros!$B$14+Parametros!$B$18>=1),"",S63/(1-Parametros!$B$14-Parametros!$B$18)) | Z63: =IF(B63="","",IF(S63="","FALTAN DATOS",IF(NOT(ISNUMBER(E63)),"FALTA PRECIO",IF(V63<0,"PIERDE",IF(W63<Parametros!$B$18,"BAJO META","OK"))))) -> FALTAN DATOS | AA63: =IF(B63="","",IF(F63="","Tela. ","")&IF(NOT(ISNUMBER(G63)),"Kg de tela. ","")&IF(AND(F63<>"",NOT(ISNUMBER(IFERROR(INDEX(Precios!$D$5:$D$120,MATCH(F63,Precios!$A$5:$A$120,0)),"x")))),"Tela sin precio. ","")&IF(AND(H63<>"",NOT(ISNUMBER(IFERROR(INDEX(Precios!$D$5:$D$120,MATCH(H63,Precios!$A$5:$A$120,0)),"x")))),"Tela 2 sin precio. ","")&IF(J63="","Metros impresos. ","")&IF(AND(N(J63)>0,Parametros!$B$27=0),"Impresión sin costo. ","")&IF(K63="","Confección. ",IF(Q63=0,"Confección sin valor. ",""))&IF(NOT(ISNUMBER(E63)),"Precio de venta. ","")) -> Tela. Kg de tela. Metros impresos. Confección.
A64: RUGCSUSILV | B64: Camiseta Rugby Silver Pmk | C64: Juego | D64: 12 | E64: 19244 | M64: Por confirmar | O64: =IF(B64="","",IFERROR(G64*INDEX(Precios!$D$5:$D$120,MATCH(F64,Precios!$A$5:$A$120,0)),0)+IF(H64="",0,IFERROR(I64*INDEX(Precios!$D$5:$D$120,MATCH(H64,Precios!$A$5:$A$120,0)),0))) -> 0 | P64: =IF(B64="","",N(J64)*Parametros!$B$27) -> 0 | Q64: =IF(B64="","",IFERROR(INDEX(Confeccion!$B$5:$B$100,MATCH(K64,Confeccion!$A$5:$A$100,0)),0)) -> 0 | R64: =IF(B64="","",N(L64)) -> 0 | S64: =IF(B64="","",IF(AND(F64<>"",ISNUMBER(G64),ISNUMBER(IFERROR(INDEX(Precios!$D$5:$D$120,MATCH(F64,Precios!$A$5:$A$120,0)),"x")),OR(H64="",ISNUMBER(IFERROR(INDEX(Precios!$D$5:$D$120,MATCH(H64,Precios!$A$5:$A$120,0)),"x"))),J64<>"",K64<>"",Q64>0),SUM(O64:R64),"")) | T64: =IF(AND(S64<>"",ISNUMBER(E64)),E64*Parametros!$B$12,"") | U64: =IF(AND(S64<>"",ISNUMBER(E64)),E64*Parametros!$B$13,"") | V64: =IF(AND(S64<>"",ISNUMBER(E64)),E64-S64-T64-U64,"") | W64: =IF(AND(S64<>"",ISNUMBER(E64)),V64/E64,"") | X64: =IF(OR(S64="",Parametros!$B$14>=1),"",S64/(1-Parametros!$B$14)) | Y64: =IF(OR(S64="",Parametros!$B$14+Parametros!$B$18>=1),"",S64/(1-Parametros!$B$14-Parametros!$B$18)) | Z64: =IF(B64="","",IF(S64="","FALTAN DATOS",IF(NOT(ISNUMBER(E64)),"FALTA PRECIO",IF(V64<0,"PIERDE",IF(W64<Parametros!$B$18,"BAJO META","OK"))))) -> FALTAN DATOS | AA64: =IF(B64="","",IF(F64="","Tela. ","")&IF(NOT(ISNUMBER(G64)),"Kg de tela. ","")&IF(AND(F64<>"",NOT(ISNUMBER(IFERROR(INDEX(Precios!$D$5:$D$120,MATCH(F64,Precios!$A$5:$A$120,0)),"x")))),"Tela sin precio. ","")&IF(AND(H64<>"",NOT(ISNUMBER(IFERROR(INDEX(Precios!$D$5:$D$120,MATCH(H64,Precios!$A$5:$A$120,0)),"x")))),"Tela 2 sin precio. ","")&IF(J64="","Metros impresos. ","")&IF(AND(N(J64)>0,Parametros!$B$27=0),"Impresión sin costo. ","")&IF(K64="","Confección. ",IF(Q64=0,"Confección sin valor. ",""))&IF(NOT(ISNUMBER(E64)),"Precio de venta. ","")) -> Tela. Kg de tela. Metros impresos. Confección.
A65: SALPLASUB | B65: Polera de Presentación Sublim m/l | C65: Salida | D65: 11 | E65: 20084 | M65: Por confirmar | O65: =IF(B65="","",IFERROR(G65*INDEX(Precios!$D$5:$D$120,MATCH(F65,Precios!$A$5:$A$120,0)),0)+IF(H65="",0,IFERROR(I65*INDEX(Precios!$D$5:$D$120,MATCH(H65,Precios!$A$5:$A$120,0)),0))) -> 0 | P65: =IF(B65="","",N(J65)*Parametros!$B$27) -> 0 | Q65: =IF(B65="","",IFERROR(INDEX(Confeccion!$B$5:$B$100,MATCH(K65,Confeccion!$A$5:$A$100,0)),0)) -> 0 | R65: =IF(B65="","",N(L65)) -> 0 | S65: =IF(B65="","",IF(AND(F65<>"",ISNUMBER(G65),ISNUMBER(IFERROR(INDEX(Precios!$D$5:$D$120,MATCH(F65,Precios!$A$5:$A$120,0)),"x")),OR(H65="",ISNUMBER(IFERROR(INDEX(Precios!$D$5:$D$120,MATCH(H65,Precios!$A$5:$A$120,0)),"x"))),J65<>"",K65<>"",Q65>0),SUM(O65:R65),"")) | T65: =IF(AND(S65<>"",ISNUMBER(E65)),E65*Parametros!$B$12,"") | U65: =IF(AND(S65<>"",ISNUMBER(E65)),E65*Parametros!$B$13,"") | V65: =IF(AND(S65<>"",ISNUMBER(E65)),E65-S65-T65-U65,"") | W65: =IF(AND(S65<>"",ISNUMBER(E65)),V65/E65,"") | X65: =IF(OR(S65="",Parametros!$B$14>=1),"",S65/(1-Parametros!$B$14)) | Y65: =IF(OR(S65="",Parametros!$B$14+Parametros!$B$18>=1),"",S65/(1-Parametros!$B$14-Parametros!$B$18)) | Z65: =IF(B65="","",IF(S65="","FALTAN DATOS",IF(NOT(ISNUMBER(E65)),"FALTA PRECIO",IF(V65<0,"PIERDE",IF(W65<Parametros!$B$18,"BAJO META","OK"))))) -> FALTAN DATOS | AA65: =IF(B65="","",IF(F65="","Tela. ","")&IF(NOT(ISNUMBER(G65)),"Kg de tela. ","")&IF(AND(F65<>"",NOT(ISNUMBER(IFERROR(INDEX(Precios!$D$5:$D$120,MATCH(F65,Precios!$A$5:$A$120,0)),"x")))),"Tela sin precio. ","")&IF(AND(H65<>"",NOT(ISNUMBER(IFERROR(INDEX(Precios!$D$5:$D$120,MATCH(H65,Precios!$A$5:$A$120,0)),"x")))),"Tela 2 sin precio. ","")&IF(J65="","Metros impresos. ","")&IF(AND(N(J65)>0,Parametros!$B$27=0),"Impresión sin costo. ","")&IF(K65="","Confección. ",IF(Q65=0,"Confección sin valor. ",""))&IF(NOT(ISNUMBER(E65)),"Precio de venta. ","")) -> Tela. Kg de tela. Metros impresos. Confección.
A66: VOLFEMCSUBPOL | B66: Camiseta Voley fem Playmaker, Polo | C66: Juego | D66: 9 | E66: 17143 | K66: Camiseta Voley | M66: Por confirmar | N66: Confección sugerida por el nombre: confirmar. | O66: =IF(B66="","",IFERROR(G66*INDEX(Precios!$D$5:$D$120,MATCH(F66,Precios!$A$5:$A$120,0)),0)+IF(H66="",0,IFERROR(I66*INDEX(Precios!$D$5:$D$120,MATCH(H66,Precios!$A$5:$A$120,0)),0))) -> 0 | P66: =IF(B66="","",N(J66)*Parametros!$B$27) -> 0 | Q66: =IF(B66="","",IFERROR(INDEX(Confeccion!$B$5:$B$100,MATCH(K66,Confeccion!$A$5:$A$100,0)),0)) -> 1700 | R66: =IF(B66="","",N(L66)) -> 0 | S66: =IF(B66="","",IF(AND(F66<>"",ISNUMBER(G66),ISNUMBER(IFERROR(INDEX(Precios!$D$5:$D$120,MATCH(F66,Precios!$A$5:$A$120,0)),"x")),OR(H66="",ISNUMBER(IFERROR(INDEX(Precios!$D$5:$D$120,MATCH(H66,Precios!$A$5:$A$120,0)),"x"))),J66<>"",K66<>"",Q66>0),SUM(O66:R66),"")) | T66: =IF(AND(S66<>"",ISNUMBER(E66)),E66*Parametros!$B$12,"") | U66: =IF(AND(S66<>"",ISNUMBER(E66)),E66*Parametros!$B$13,"") | V66: =IF(AND(S66<>"",ISNUMBER(E66)),E66-S66-T66-U66,"") | W66: =IF(AND(S66<>"",ISNUMBER(E66)),V66/E66,"") | X66: =IF(OR(S66="",Parametros!$B$14>=1),"",S66/(1-Parametros!$B$14)) | Y66: =IF(OR(S66="",Parametros!$B$14+Parametros!$B$18>=1),"",S66/(1-Parametros!$B$14-Parametros!$B$18)) | Z66: =IF(B66="","",IF(S66="","FALTAN DATOS",IF(NOT(ISNUMBER(E66)),"FALTA PRECIO",IF(V66<0,"PIERDE",IF(W66<Parametros!$B$18,"BAJO META","OK"))))) -> FALTAN DATOS | AA66: =IF(B66="","",IF(F66="","Tela. ","")&IF(NOT(ISNUMBER(G66)),"Kg de tela. ","")&IF(AND(F66<>"",NOT(ISNUMBER(IFERROR(INDEX(Precios!$D$5:$D$120,MATCH(F66,Precios!$A$5:$A$120,0)),"x")))),"Tela sin precio. ","")&IF(AND(H66<>"",NOT(ISNUMBER(IFERROR(INDEX(Precios!$D$5:$D$120,MATCH(H66,Precios!$A$5:$A$120,0)),"x")))),"Tela 2 sin precio. ","")&IF(J66="","Metros impresos. ","")&IF(AND(N(J66)>0,Parametros!$B$27=0),"Impresión sin costo. ","")&IF(K66="","Confección. ",IF(Q66=0,"Confección sin valor. ",""))&IF(NOT(ISNUMBER(E66)),"Precio de venta. ","")) -> Tela. Kg de tela. Metros impresos.
A67: POLENTSUB | B67: POLERON DE ENTRENAMIENTO SUBLIMADO MEDIO CIERRE | C67: Salida | D67: 6 | E67: 32731 | M67: Por confirmar | O67: =IF(B67="","",IFERROR(G67*INDEX(Precios!$D$5:$D$120,MATCH(F67,Precios!$A$5:$A$120,0)),0)+IF(H67="",0,IFERROR(I67*INDEX(Precios!$D$5:$D$120,MATCH(H67,Precios!$A$5:$A$120,0)),0))) -> 0 | P67: =IF(B67="","",N(J67)*Parametros!$B$27) -> 0 | Q67: =IF(B67="","",IFERROR(INDEX(Confeccion!$B$5:$B$100,MATCH(K67,Confeccion!$A$5:$A$100,0)),0)) -> 0 | R67: =IF(B67="","",N(L67)) -> 0 | S67: =IF(B67="","",IF(AND(F67<>"",ISNUMBER(G67),ISNUMBER(IFERROR(INDEX(Precios!$D$5:$D$120,MATCH(F67,Precios!$A$5:$A$120,0)),"x")),OR(H67="",ISNUMBER(IFERROR(INDEX(Precios!$D$5:$D$120,MATCH(H67,Precios!$A$5:$A$120,0)),"x"))),J67<>"",K67<>"",Q67>0),SUM(O67:R67),"")) | T67: =IF(AND(S67<>"",ISNUMBER(E67)),E67*Parametros!$B$12,"") | U67: =IF(AND(S67<>"",ISNUMBER(E67)),E67*Parametros!$B$13,"") | V67: =IF(AND(S67<>"",ISNUMBER(E67)),E67-S67-T67-U67,"") | W67: =IF(AND(S67<>"",ISNUMBER(E67)),V67/E67,"") | X67: =IF(OR(S67="",Parametros!$B$14>=1),"",S67/(1-Parametros!$B$14)) | Y67: =IF(OR(S67="",Parametros!$B$14+Parametros!$B$18>=1),"",S67/(1-Parametros!$B$14-Parametros!$B$18)) | Z67: =IF(B67="","",IF(S67="","FALTAN DATOS",IF(NOT(ISNUMBER(E67)),"FALTA PRECIO",IF(V67<0,"PIERDE",IF(W67<Parametros!$B$18,"BAJO META","OK"))))) -> FALTAN DATOS | AA67: =IF(B67="","",IF(F67="","Tela. ","")&IF(NOT(ISNUMBER(G67)),"Kg de tela. ","")&IF(AND(F67<>"",NOT(ISNUMBER(IFERROR(INDEX(Precios!$D$5:$D$120,MATCH(F67,Precios!$A$5:$A$120,0)),"x")))),"Tela sin precio. ","")&IF(AND(H67<>"",NOT(ISNUMBER(IFERROR(INDEX(Precios!$D$5:$D$120,MATCH(H67,Precios!$A$5:$A$120,0)),"x")))),"Tela 2 sin precio. ","")&IF(J67="","Metros impresos. ","")&IF(AND(N(J67)>0,Parametros!$B$27=0),"Impresión sin costo. ","")&IF(K67="","Confección. ",IF(Q67=0,"Confección sin valor. ",""))&IF(NOT(ISNUMBER(E67)),"Precio de venta. ","")) -> Tela. Kg de tela. Metros impresos. Confección.
A68: POL-CSUB-V-MC | B68: Polera Playmaker, V m/c | C68: Juego | D68: 6 | E68: 16723 | M68: Por confirmar | O68: =IF(B68="","",IFERROR(G68*INDEX(Precios!$D$5:$D$120,MATCH(F68,Precios!$A$5:$A$120,0)),0)+IF(H68="",0,IFERROR(I68*INDEX(Precios!$D$5:$D$120,MATCH(H68,Precios!$A$5:$A$120,0)),0))) -> 0 | P68: =IF(B68="","",N(J68)*Parametros!$B$27) -> 0 | Q68: =IF(B68="","",IFERROR(INDEX(Confeccion!$B$5:$B$100,MATCH(K68,Confeccion!$A$5:$A$100,0)),0)) -> 0 | R68: =IF(B68="","",N(L68)) -> 0 | S68: =IF(B68="","",IF(AND(F68<>"",ISNUMBER(G68),ISNUMBER(IFERROR(INDEX(Precios!$D$5:$D$120,MATCH(F68,Precios!$A$5:$A$120,0)),"x")),OR(H68="",ISNUMBER(IFERROR(INDEX(Precios!$D$5:$D$120,MATCH(H68,Precios!$A$5:$A$120,0)),"x"))),J68<>"",K68<>"",Q68>0),SUM(O68:R68),"")) | T68: =IF(AND(S68<>"",ISNUMBER(E68)),E68*Parametros!$B$12,"") | U68: =IF(AND(S68<>"",ISNUMBER(E68)),E68*Parametros!$B$13,"") | V68: =IF(AND(S68<>"",ISNUMBER(E68)),E68-S68-T68-U68,"") | W68: =IF(AND(S68<>"",ISNUMBER(E68)),V68/E68,"") | X68: =IF(OR(S68="",Parametros!$B$14>=1),"",S68/(1-Parametros!$B$14)) | Y68: =IF(OR(S68="",Parametros!$B$14+Parametros!$B$18>=1),"",S68/(1-Parametros!$B$14-Parametros!$B$18)) | Z68: =IF(B68="","",IF(S68="","FALTAN DATOS",IF(NOT(ISNUMBER(E68)),"FALTA PRECIO",IF(V68<0,"PIERDE",IF(W68<Parametros!$B$18,"BAJO META","OK"))))) -> FALTAN DATOS | AA68: =IF(B68="","",IF(F68="","Tela. ","")&IF(NOT(ISNUMBER(G68)),"Kg de tela. ","")&IF(AND(F68<>"",NOT(ISNUMBER(IFERROR(INDEX(Precios!$D$5:$D$120,MATCH(F68,Precios!$A$5:$A$120,0)),"x")))),"Tela sin precio. ","")&IF(AND(H68<>"",NOT(ISNUMBER(IFERROR(INDEX(Precios!$D$5:$D$120,MATCH(H68,Precios!$A$5:$A$120,0)),"x")))),"Tela 2 sin precio. ","")&IF(J68="","Metros impresos. ","")&IF(AND(N(J68)>0,Parametros!$B$27=0),"Impresión sin costo. ","")&IF(K68="","Confección. ",IF(Q68=0,"Confección sin valor. ",""))&IF(NOT(ISNUMBER(E68)),"Precio de venta. ","")) -> Tela. Kg de tela. Metros impresos. Confección.
A69: RUGCSUBENTMC | B69: Camiseta de entrenamiento Rugby,m/c | C69: Juego | D69: 5 | E69: 15882 | M69: Por confirmar | O69: =IF(B69="","",IFERROR(G69*INDEX(Precios!$D$5:$D$120,MATCH(F69,Precios!$A$5:$A$120,0)),0)+IF(H69="",0,IFERROR(I69*INDEX(Precios!$D$5:$D$120,MATCH(H69,Precios!$A$5:$A$120,0)),0))) -> 0 | P69: =IF(B69="","",N(J69)*Parametros!$B$27) -> 0 | Q69: =IF(B69="","",IFERROR(INDEX(Confeccion!$B$5:$B$100,MATCH(K69,Confeccion!$A$5:$A$100,0)),0)) -> 0 | R69: =IF(B69="","",N(L69)) -> 0 | S69: =IF(B69="","",IF(AND(F69<>"",ISNUMBER(G69),ISNUMBER(IFERROR(INDEX(Precios!$D$5:$D$120,MATCH(F69,Precios!$A$5:$A$120,0)),"x")),OR(H69="",ISNUMBER(IFERROR(INDEX(Precios!$D$5:$D$120,MATCH(H69,Precios!$A$5:$A$120,0)),"x"))),J69<>"",K69<>"",Q69>0),SUM(O69:R69),"")) | T69: =IF(AND(S69<>"",ISNUMBER(E69)),E69*Parametros!$B$12,"") | U69: =IF(AND(S69<>"",ISNUMBER(E69)),E69*Parametros!$B$13,"") | V69: =IF(AND(S69<>"",ISNUMBER(E69)),E69-S69-T69-U69,"") | W69: =IF(AND(S69<>"",ISNUMBER(E69)),V69/E69,"") | X69: =IF(OR(S69="",Parametros!$B$14>=1),"",S69/(1-Parametros!$B$14)) | Y69: =IF(OR(S69="",Parametros!$B$14+Parametros!$B$18>=1),"",S69/(1-Parametros!$B$14-Parametros!$B$18)) | Z69: =IF(B69="","",IF(S69="","FALTAN DATOS",IF(NOT(ISNUMBER(E69)),"FALTA PRECIO",IF(V69<0,"PIERDE",IF(W69<Parametros!$B$18,"BAJO META","OK"))))) -> FALTAN DATOS | AA69: =IF(B69="","",IF(F69="","Tela. ","")&IF(NOT(ISNUMBER(G69)),"Kg de tela. ","")&IF(AND(F69<>"",NOT(ISNUMBER(IFERROR(INDEX(Precios!$D$5:$D$120,MATCH(F69,Precios!$A$5:$A$120,0)),"x")))),"Tela sin precio. ","")&IF(AND(H69<>"",NOT(ISNUMBER(IFERROR(INDEX(Precios!$D$5:$D$120,MATCH(H69,Precios!$A$5:$A$120,0)),"x")))),"Tela 2 sin precio. ","")&IF(J69="","Metros impresos. ","")&IF(AND(N(J69)>0,Parametros!$B$27=0),"Impresión sin costo. ","")&IF(K69="","Confección. ",IF(Q69=0,"Confección sin valor. ",""))&IF(NOT(ISNUMBER(E69)),"Precio de venta. ","")) -> Tela. Kg de tela. Metros impresos. Confección.
A70: MDCALCORPMK | B70: Calza corta fem Playmaker | C70: Juego | D70: 4 | E70: 12689 | F70: LYCRA | G70: 0.074 | J70: 0 | K70: Calza | M70: Por confirmar | N70: Ficha OT 2642 (5 calzas vóley). La Lycra no tiene precio todavía. | O70: =IF(B70="","",IFERROR(G70*INDEX(Precios!$D$5:$D$120,MATCH(F70,Precios!$A$5:$A$120,0)),0)+IF(H70="",0,IFERROR(I70*INDEX(Precios!$D$5:$D$120,MATCH(H70,Precios!$A$5:$A$120,0)),0))) -> 0 | P70: =IF(B70="","",N(J70)*Parametros!$B$27) -> 0 | Q70: =IF(B70="","",IFERROR(INDEX(Confeccion!$B$5:$B$100,MATCH(K70,Confeccion!$A$5:$A$100,0)),0)) -> 1200 | R70: =IF(B70="","",N(L70)) -> 0 | S70: =IF(B70="","",IF(AND(F70<>"",ISNUMBER(G70),ISNUMBER(IFERROR(INDEX(Precios!$D$5:$D$120,MATCH(F70,Precios!$A$5:$A$120,0)),"x")),OR(H70="",ISNUMBER(IFERROR(INDEX(Precios!$D$5:$D$120,MATCH(H70,Precios!$A$5:$A$120,0)),"x"))),J70<>"",K70<>"",Q70>0),SUM(O70:R70),"")) | T70: =IF(AND(S70<>"",ISNUMBER(E70)),E70*Parametros!$B$12,"") | U70: =IF(AND(S70<>"",ISNUMBER(E70)),E70*Parametros!$B$13,"") | V70: =IF(AND(S70<>"",ISNUMBER(E70)),E70-S70-T70-U70,"") | W70: =IF(AND(S70<>"",ISNUMBER(E70)),V70/E70,"") | X70: =IF(OR(S70="",Parametros!$B$14>=1),"",S70/(1-Parametros!$B$14)) | Y70: =IF(OR(S70="",Parametros!$B$14+Parametros!$B$18>=1),"",S70/(1-Parametros!$B$14-Parametros!$B$18)) | Z70: =IF(B70="","",IF(S70="","FALTAN DATOS",IF(NOT(ISNUMBER(E70)),"FALTA PRECIO",IF(V70<0,"PIERDE",IF(W70<Parametros!$B$18,"BAJO META","OK"))))) -> FALTAN DATOS | AA70: =IF(B70="","",IF(F70="","Tela. ","")&IF(NOT(ISNUMBER(G70)),"Kg de tela. ","")&IF(AND(F70<>"",NOT(ISNUMBER(IFERROR(INDEX(Precios!$D$5:$D$120,MATCH(F70,Precios!$A$5:$A$120,0)),"x")))),"Tela sin precio. ","")&IF(AND(H70<>"",NOT(ISNUMBER(IFERROR(INDEX(Precios!$D$5:$D$120,MATCH(H70,Precios!$A$5:$A$120,0)),"x")))),"Tela 2 sin precio. ","")&IF(J70="","Metros impresos. ","")&IF(AND(N(J70)>0,Parametros!$B$27=0),"Impresión sin costo. ","")&IF(K70="","Confección. ",IF(Q70=0,"Confección sin valor. ",""))&IF(NOT(ISNUMBER(E70)),"Precio de venta. ","")) -> Tela sin precio.
A71: SAL-SHO-LIS | B71: Short Salida con bolsillos | C71: Salida | D71: 4 | E71: 13445 | K71: Short De Salida | M71: Por confirmar | N71: Confección sugerida por el nombre: confirmar. | O71: =IF(B71="","",IFERROR(G71*INDEX(Precios!$D$5:$D$120,MATCH(F71,Precios!$A$5:$A$120,0)),0)+IF(H71="",0,IFERROR(I71*INDEX(Precios!$D$5:$D$120,MATCH(H71,Precios!$A$5:$A$120,0)),0))) -> 0 | P71: =IF(B71="","",N(J71)*Parametros!$B$27) -> 0 | Q71: =IF(B71="","",IFERROR(INDEX(Confeccion!$B$5:$B$100,MATCH(K71,Confeccion!$A$5:$A$100,0)),0)) -> 2200 | R71: =IF(B71="","",N(L71)) -> 0 | S71: =IF(B71="","",IF(AND(F71<>"",ISNUMBER(G71),ISNUMBER(IFERROR(INDEX(Precios!$D$5:$D$120,MATCH(F71,Precios!$A$5:$A$120,0)),"x")),OR(H71="",ISNUMBER(IFERROR(INDEX(Precios!$D$5:$D$120,MATCH(H71,Precios!$A$5:$A$120,0)),"x"))),J71<>"",K71<>"",Q71>0),SUM(O71:R71),"")) | T71: =IF(AND(S71<>"",ISNUMBER(E71)),E71*Parametros!$B$12,"") | U71: =IF(AND(S71<>"",ISNUMBER(E71)),E71*Parametros!$B$13,"") | V71: =IF(AND(S71<>"",ISNUMBER(E71)),E71-S71-T71-U71,"") | W71: =IF(AND(S71<>"",ISNUMBER(E71)),V71/E71,"") | X71: =IF(OR(S71="",Parametros!$B$14>=1),"",S71/(1-Parametros!$B$14)) | Y71: =IF(OR(S71="",Parametros!$B$14+Parametros!$B$18>=1),"",S71/(1-Parametros!$B$14-Parametros!$B$18)) | Z71: =IF(B71="","",IF(S71="","FALTAN DATOS",IF(NOT(ISNUMBER(E71)),"FALTA PRECIO",IF(V71<0,"PIERDE",IF(W71<Parametros!$B$18,"BAJO META","OK"))))) -> FALTAN DATOS | AA71: =IF(B71="","",IF(F71="","Tela. ","")&IF(NOT(ISNUMBER(G71)),"Kg de tela. ","")&IF(AND(F71<>"",NOT(ISNUMBER(IFERROR(INDEX(Precios!$D$5:$D$120,MATCH(F71,Precios!$A$5:$A$120,0)),"x")))),"Tela sin precio. ","")&IF(AND(H71<>"",NOT(ISNUMBER(IFERROR(INDEX(Precios!$D$5:$D$120,MATCH(H71,Precios!$A$5:$A$120,0)),"x")))),"Tela 2 sin precio. ","")&IF(J71="","Metros impresos. ","")&IF(AND(N(J71)>0,Parametros!$B$27=0),"Impresión sin costo. ","")&IF(K71="","Confección. ",IF(Q71=0,"Confección sin valor. ",""))&IF(NOT(ISNUMBER(E71)),"Precio de venta. ","")) -> Tela. Kg de tela. Metros impresos.
A72: ENT-POL-MANSUBL | B72: POLERON DE ENTRENAMIENTO MANGAS SUBLIMADAS MASC | C72: Salida | D72: 4 | E72: 30168 | M72: Por confirmar | O72: =IF(B72="","",IFERROR(G72*INDEX(Precios!$D$5:$D$120,MATCH(F72,Precios!$A$5:$A$120,0)),0)+IF(H72="",0,IFERROR(I72*INDEX(Precios!$D$5:$D$120,MATCH(H72,Precios!$A$5:$A$120,0)),0))) -> 0 | P72: =IF(B72="","",N(J72)*Parametros!$B$27) -> 0 | Q72: =IF(B72="","",IFERROR(INDEX(Confeccion!$B$5:$B$100,MATCH(K72,Confeccion!$A$5:$A$100,0)),0)) -> 0 | R72: =IF(B72="","",N(L72)) -> 0 | S72: =IF(B72="","",IF(AND(F72<>"",ISNUMBER(G72),ISNUMBER(IFERROR(INDEX(Precios!$D$5:$D$120,MATCH(F72,Precios!$A$5:$A$120,0)),"x")),OR(H72="",ISNUMBER(IFERROR(INDEX(Precios!$D$5:$D$120,MATCH(H72,Precios!$A$5:$A$120,0)),"x"))),J72<>"",K72<>"",Q72>0),SUM(O72:R72),"")) | T72: =IF(AND(S72<>"",ISNUMBER(E72)),E72*Parametros!$B$12,"") | U72: =IF(AND(S72<>"",ISNUMBER(E72)),E72*Parametros!$B$13,"") | V72: =IF(AND(S72<>"",ISNUMBER(E72)),E72-S72-T72-U72,"") | W72: =IF(AND(S72<>"",ISNUMBER(E72)),V72/E72,"") | X72: =IF(OR(S72="",Parametros!$B$14>=1),"",S72/(1-Parametros!$B$14)) | Y72: =IF(OR(S72="",Parametros!$B$14+Parametros!$B$18>=1),"",S72/(1-Parametros!$B$14-Parametros!$B$18)) | Z72: =IF(B72="","",IF(S72="","FALTAN DATOS",IF(NOT(ISNUMBER(E72)),"FALTA PRECIO",IF(V72<0,"PIERDE",IF(W72<Parametros!$B$18,"BAJO META","OK"))))) -> FALTAN DATOS | AA72: =IF(B72="","",IF(F72="","Tela. ","")&IF(NOT(ISNUMBER(G72)),"Kg de tela. ","")&IF(AND(F72<>"",NOT(ISNUMBER(IFERROR(INDEX(Precios!$D$5:$D$120,MATCH(F72,Precios!$A$5:$A$120,0)),"x")))),"Tela sin precio. ","")&IF(AND(H72<>"",NOT(ISNUMBER(IFERROR(INDEX(Precios!$D$5:$D$120,MATCH(H72,Precios!$A$5:$A$120,0)),"x")))),"Tela 2 sin precio. ","")&IF(J72="","Metros impresos. ","")&IF(AND(N(J72)>0,Parametros!$B$27=0),"Impresión sin costo. ","")&IF(K72="","Confección. ",IF(Q72=0,"Confección sin valor. ",""))&IF(NOT(ISNUMBER(E72)),"Precio de venta. ","")) -> Tela. Kg de tela. Metros impresos. Confección.
A73: VOLMASC-CSUB-V-CER | B73: Camiseta Voley masc Playmaker, V m/cero | C73: Juego | D73: 3 | E73: 16723 | K73: Camiseta Voley | M73: Por confirmar | N73: Confección sugerida por el nombre: confirmar. | O73: =IF(B73="","",IFERROR(G73*INDEX(Precios!$D$5:$D$120,MATCH(F73,Precios!$A$5:$A$120,0)),0)+IF(H73="",0,IFERROR(I73*INDEX(Precios!$D$5:$D$120,MATCH(H73,Precios!$A$5:$A$120,0)),0))) -> 0 | P73: =IF(B73="","",N(J73)*Parametros!$B$27) -> 0 | Q73: =IF(B73="","",IFERROR(INDEX(Confeccion!$B$5:$B$100,MATCH(K73,Confeccion!$A$5:$A$100,0)),0)) -> 1700 | R73: =IF(B73="","",N(L73)) -> 0 | S73: =IF(B73="","",IF(AND(F73<>"",ISNUMBER(G73),ISNUMBER(IFERROR(INDEX(Precios!$D$5:$D$120,MATCH(F73,Precios!$A$5:$A$120,0)),"x")),OR(H73="",ISNUMBER(IFERROR(INDEX(Precios!$D$5:$D$120,MATCH(H73,Precios!$A$5:$A$120,0)),"x"))),J73<>"",K73<>"",Q73>0),SUM(O73:R73),"")) | T73: =IF(AND(S73<>"",ISNUMBER(E73)),E73*Parametros!$B$12,"") | U73: =IF(AND(S73<>"",ISNUMBER(E73)),E73*Parametros!$B$13,"") | V73: =IF(AND(S73<>"",ISNUMBER(E73)),E73-S73-T73-U73,"") | W73: =IF(AND(S73<>"",ISNUMBER(E73)),V73/E73,"") | X73: =IF(OR(S73="",Parametros!$B$14>=1),"",S73/(1-Parametros!$B$14)) | Y73: =IF(OR(S73="",Parametros!$B$14+Parametros!$B$18>=1),"",S73/(1-Parametros!$B$14-Parametros!$B$18)) | Z73: =IF(B73="","",IF(S73="","FALTAN DATOS",IF(NOT(ISNUMBER(E73)),"FALTA PRECIO",IF(V73<0,"PIERDE",IF(W73<Parametros!$B$18,"BAJO META","OK"))))) -> FALTAN DATOS | AA73: =IF(B73="","",IF(F73="","Tela. ","")&IF(NOT(ISNUMBER(G73)),"Kg de tela. ","")&IF(AND(F73<>"",NOT(ISNUMBER(IFERROR(INDEX(Precios!$D$5:$D$120,MATCH(F73,Precios!$A$5:$A$120,0)),"x")))),"Tela sin precio. ","")&IF(AND(H73<>"",NOT(ISNUMBER(IFERROR(INDEX(Precios!$D$5:$D$120,MATCH(H73,Precios!$A$5:$A$120,0)),"x")))),"Tela 2 sin precio. ","")&IF(J73="","Metros impresos. ","")&IF(AND(N(J73)>0,Parametros!$B$27=0),"Impresión sin costo. ","")&IF(K73="","Confección. ",IF(Q73=0,"Confección sin valor. ",""))&IF(NOT(ISNUMBER(E73)),"Precio de venta. ","")) -> Tela. Kg de tela. Metros impresos.
A74: SAL-POL-MGSUB | B74: Polerón Entrenamiento liso con mangas Sublim | C74: Salida | D74: 2 | E74: 27647 | M74: Por confirmar | O74: =IF(B74="","",IFERROR(G74*INDEX(Precios!$D$5:$D$120,MATCH(F74,Precios!$A$5:$A$120,0)),0)+IF(H74="",0,IFERROR(I74*INDEX(Precios!$D$5:$D$120,MATCH(H74,Precios!$A$5:$A$120,0)),0))) -> 0 | P74: =IF(B74="","",N(J74)*Parametros!$B$27) -> 0 | Q74: =IF(B74="","",IFERROR(INDEX(Confeccion!$B$5:$B$100,MATCH(K74,Confeccion!$A$5:$A$100,0)),0)) -> 0 | R74: =IF(B74="","",N(L74)) -> 0 | S74: =IF(B74="","",IF(AND(F74<>"",ISNUMBER(G74),ISNUMBER(IFERROR(INDEX(Precios!$D$5:$D$120,MATCH(F74,Precios!$A$5:$A$120,0)),"x")),OR(H74="",ISNUMBER(IFERROR(INDEX(Precios!$D$5:$D$120,MATCH(H74,Precios!$A$5:$A$120,0)),"x"))),J74<>"",K74<>"",Q74>0),SUM(O74:R74),"")) | T74: =IF(AND(S74<>"",ISNUMBER(E74)),E74*Parametros!$B$12,"") | U74: =IF(AND(S74<>"",ISNUMBER(E74)),E74*Parametros!$B$13,"") | V74: =IF(AND(S74<>"",ISNUMBER(E74)),E74-S74-T74-U74,"") | W74: =IF(AND(S74<>"",ISNUMBER(E74)),V74/E74,"") | X74: =IF(OR(S74="",Parametros!$B$14>=1),"",S74/(1-Parametros!$B$14)) | Y74: =IF(OR(S74="",Parametros!$B$14+Parametros!$B$18>=1),"",S74/(1-Parametros!$B$14-Parametros!$B$18)) | Z74: =IF(B74="","",IF(S74="","FALTAN DATOS",IF(NOT(ISNUMBER(E74)),"FALTA PRECIO",IF(V74<0,"PIERDE",IF(W74<Parametros!$B$18,"BAJO META","OK"))))) -> FALTAN DATOS | AA74: =IF(B74="","",IF(F74="","Tela. ","")&IF(NOT(ISNUMBER(G74)),"Kg de tela. ","")&IF(AND(F74<>"",NOT(ISNUMBER(IFERROR(INDEX(Precios!$D$5:$D$120,MATCH(F74,Precios!$A$5:$A$120,0)),"x")))),"Tela sin precio. ","")&IF(AND(H74<>"",NOT(ISNUMBER(IFERROR(INDEX(Precios!$D$5:$D$120,MATCH(H74,Precios!$A$5:$A$120,0)),"x")))),"Tela 2 sin precio. ","")&IF(J74="","Metros impresos. ","")&IF(AND(N(J74)>0,Parametros!$B$27=0),"Impresión sin costo. ","")&IF(K74="","Confección. ",IF(Q74=0,"Confección sin valor. ",""))&IF(NOT(ISNUMBER(E74)),"Precio de venta. ","")) -> Tela. Kg de tela. Metros impresos. Confección.
A75: VOLMASC-CSUBPRO-V-MC | B75: Camiseta Voley masc Pro Playmaker, V m/c | C75: Juego | D75: 1 | E75: 19244 | K75: Camiseta Voley | M75: Por confirmar | N75: Confección sugerida por el nombre: confirmar. | O75: =IF(B75="","",IFERROR(G75*INDEX(Precios!$D$5:$D$120,MATCH(F75,Precios!$A$5:$A$120,0)),0)+IF(H75="",0,IFERROR(I75*INDEX(Precios!$D$5:$D$120,MATCH(H75,Precios!$A$5:$A$120,0)),0))) -> 0 | P75: =IF(B75="","",N(J75)*Parametros!$B$27) -> 0 | Q75: =IF(B75="","",IFERROR(INDEX(Confeccion!$B$5:$B$100,MATCH(K75,Confeccion!$A$5:$A$100,0)),0)) -> 1700 | R75: =IF(B75="","",N(L75)) -> 0 | S75: =IF(B75="","",IF(AND(F75<>"",ISNUMBER(G75),ISNUMBER(IFERROR(INDEX(Precios!$D$5:$D$120,MATCH(F75,Precios!$A$5:$A$120,0)),"x")),OR(H75="",ISNUMBER(IFERROR(INDEX(Precios!$D$5:$D$120,MATCH(H75,Precios!$A$5:$A$120,0)),"x"))),J75<>"",K75<>"",Q75>0),SUM(O75:R75),"")) | T75: =IF(AND(S75<>"",ISNUMBER(E75)),E75*Parametros!$B$12,"") | U75: =IF(AND(S75<>"",ISNUMBER(E75)),E75*Parametros!$B$13,"") | V75: =IF(AND(S75<>"",ISNUMBER(E75)),E75-S75-T75-U75,"") | W75: =IF(AND(S75<>"",ISNUMBER(E75)),V75/E75,"") | X75: =IF(OR(S75="",Parametros!$B$14>=1),"",S75/(1-Parametros!$B$14)) | Y75: =IF(OR(S75="",Parametros!$B$14+Parametros!$B$18>=1),"",S75/(1-Parametros!$B$14-Parametros!$B$18)) | Z75: =IF(B75="","",IF(S75="","FALTAN DATOS",IF(NOT(ISNUMBER(E75)),"FALTA PRECIO",IF(V75<0,"PIERDE",IF(W75<Parametros!$B$18,"BAJO META","OK"))))) -> FALTAN DATOS | AA75: =IF(B75="","",IF(F75="","Tela. ","")&IF(NOT(ISNUMBER(G75)),"Kg de tela. ","")&IF(AND(F75<>"",NOT(ISNUMBER(IFERROR(INDEX(Precios!$D$5:$D$120,MATCH(F75,Precios!$A$5:$A$120,0)),"x")))),"Tela sin precio. ","")&IF(AND(H75<>"",NOT(ISNUMBER(IFERROR(INDEX(Precios!$D$5:$D$120,MATCH(H75,Precios!$A$5:$A$120,0)),"x")))),"Tela 2 sin precio. ","")&IF(J75="","Metros impresos. ","")&IF(AND(N(J75)>0,Parametros!$B$27=0),"Impresión sin costo. ","")&IF(K75="","Confección. ",IF(Q75=0,"Confección sin valor. ",""))&IF(NOT(ISNUMBER(E75)),"Precio de venta. ","")) -> Tela. Kg de tela. Metros impresos.
A76: RUG-CSUB-POL | B76: Camiseta Rugby Playmaker, Polo | C76: Juego | D76: 1 | E76: 20084 | M76: Por confirmar | O76: =IF(B76="","",IFERROR(G76*INDEX(Precios!$D$5:$D$120,MATCH(F76,Precios!$A$5:$A$120,0)),0)+IF(H76="",0,IFERROR(I76*INDEX(Precios!$D$5:$D$120,MATCH(H76,Precios!$A$5:$A$120,0)),0))) -> 0 | P76: =IF(B76="","",N(J76)*Parametros!$B$27) -> 0 | Q76: =IF(B76="","",IFERROR(INDEX(Confeccion!$B$5:$B$100,MATCH(K76,Confeccion!$A$5:$A$100,0)),0)) -> 0 | R76: =IF(B76="","",N(L76)) -> 0 | S76: =IF(B76="","",IF(AND(F76<>"",ISNUMBER(G76),ISNUMBER(IFERROR(INDEX(Precios!$D$5:$D$120,MATCH(F76,Precios!$A$5:$A$120,0)),"x")),OR(H76="",ISNUMBER(IFERROR(INDEX(Precios!$D$5:$D$120,MATCH(H76,Precios!$A$5:$A$120,0)),"x"))),J76<>"",K76<>"",Q76>0),SUM(O76:R76),"")) | T76: =IF(AND(S76<>"",ISNUMBER(E76)),E76*Parametros!$B$12,"") | U76: =IF(AND(S76<>"",ISNUMBER(E76)),E76*Parametros!$B$13,"") | V76: =IF(AND(S76<>"",ISNUMBER(E76)),E76-S76-T76-U76,"") | W76: =IF(AND(S76<>"",ISNUMBER(E76)),V76/E76,"") | X76: =IF(OR(S76="",Parametros!$B$14>=1),"",S76/(1-Parametros!$B$14)) | Y76: =IF(OR(S76="",Parametros!$B$14+Parametros!$B$18>=1),"",S76/(1-Parametros!$B$14-Parametros!$B$18)) | Z76: =IF(B76="","",IF(S76="","FALTAN DATOS",IF(NOT(ISNUMBER(E76)),"FALTA PRECIO",IF(V76<0,"PIERDE",IF(W76<Parametros!$B$18,"BAJO META","OK"))))) -> FALTAN DATOS | AA76: =IF(B76="","",IF(F76="","Tela. ","")&IF(NOT(ISNUMBER(G76)),"Kg de tela. ","")&IF(AND(F76<>"",NOT(ISNUMBER(IFERROR(INDEX(Precios!$D$5:$D$120,MATCH(F76,Precios!$A$5:$A$120,0)),"x")))),"Tela sin precio. ","")&IF(AND(H76<>"",NOT(ISNUMBER(IFERROR(INDEX(Precios!$D$5:$D$120,MATCH(H76,Precios!$A$5:$A$120,0)),"x")))),"Tela 2 sin precio. ","")&IF(J76="","Metros impresos. ","")&IF(AND(N(J76)>0,Parametros!$B$27=0),"Impresión sin costo. ","")&IF(K76="","Confección. ",IF(Q76=0,"Confección sin valor. ",""))&IF(NOT(ISNUMBER(E76)),"Precio de venta. ","")) -> Tela. Kg de tela. Metros impresos. Confección.
A77: LZO-2 | B77: Lienzo 1.5x2 | C77: Juego | D77: 1 | E77: 21765 | K77: Lienzo | M77: Por confirmar | N77: Confección sugerida por el nombre: confirmar. | O77: =IF(B77="","",IFERROR(G77*INDEX(Precios!$D$5:$D$120,MATCH(F77,Precios!$A$5:$A$120,0)),0)+IF(H77="",0,IFERROR(I77*INDEX(Precios!$D$5:$D$120,MATCH(H77,Precios!$A$5:$A$120,0)),0))) -> 0 | P77: =IF(B77="","",N(J77)*Parametros!$B$27) -> 0 | Q77: =IF(B77="","",IFERROR(INDEX(Confeccion!$B$5:$B$100,MATCH(K77,Confeccion!$A$5:$A$100,0)),0)) -> 650 | R77: =IF(B77="","",N(L77)) -> 0 | S77: =IF(B77="","",IF(AND(F77<>"",ISNUMBER(G77),ISNUMBER(IFERROR(INDEX(Precios!$D$5:$D$120,MATCH(F77,Precios!$A$5:$A$120,0)),"x")),OR(H77="",ISNUMBER(IFERROR(INDEX(Precios!$D$5:$D$120,MATCH(H77,Precios!$A$5:$A$120,0)),"x"))),J77<>"",K77<>"",Q77>0),SUM(O77:R77),"")) | T77: =IF(AND(S77<>"",ISNUMBER(E77)),E77*Parametros!$B$12,"") | U77: =IF(AND(S77<>"",ISNUMBER(E77)),E77*Parametros!$B$13,"") | V77: =IF(AND(S77<>"",ISNUMBER(E77)),E77-S77-T77-U77,"") | W77: =IF(AND(S77<>"",ISNUMBER(E77)),V77/E77,"") | X77: =IF(OR(S77="",Parametros!$B$14>=1),"",S77/(1-Parametros!$B$14)) | Y77: =IF(OR(S77="",Parametros!$B$14+Parametros!$B$18>=1),"",S77/(1-Parametros!$B$14-Parametros!$B$18)) | Z77: =IF(B77="","",IF(S77="","FALTAN DATOS",IF(NOT(ISNUMBER(E77)),"FALTA PRECIO",IF(V77<0,"PIERDE",IF(W77<Parametros!$B$18,"BAJO META","OK"))))) -> FALTAN DATOS | AA77: =IF(B77="","",IF(F77="","Tela. ","")&IF(NOT(ISNUMBER(G77)),"Kg de tela. ","")&IF(AND(F77<>"",NOT(ISNUMBER(IFERROR(INDEX(Precios!$D$5:$D$120,MATCH(F77,Precios!$A$5:$A$120,0)),"x")))),"Tela sin precio. ","")&IF(AND(H77<>"",NOT(ISNUMBER(IFERROR(INDEX(Precios!$D$5:$D$120,MATCH(H77,Precios!$A$5:$A$120,0)),"x")))),"Tela 2 sin precio. ","")&IF(J77="","Metros impresos. ","")&IF(AND(N(J77)>0,Parametros!$B$27=0),"Impresión sin costo. ","")&IF(K77="","Confección. ",IF(Q77=0,"Confección sin valor. ",""))&IF(NOT(ISNUMBER(E77)),"Precio de venta. ","")) -> Tela. Kg de tela. Metros impresos.
A78: FUTJINSUB | B78: Jineta de Capitán Subl | C78: Juego | D78: 1 | E78: 11681 | M78: Por confirmar | O78: =IF(B78="","",IFERROR(G78*INDEX(Precios!$D$5:$D$120,MATCH(F78,Precios!$A$5:$A$120,0)),0)+IF(H78="",0,IFERROR(I78*INDEX(Precios!$D$5:$D$120,MATCH(H78,Precios!$A$5:$A$120,0)),0))) -> 0 | P78: =IF(B78="","",N(J78)*Parametros!$B$27) -> 0 | Q78: =IF(B78="","",IFERROR(INDEX(Confeccion!$B$5:$B$100,MATCH(K78,Confeccion!$A$5:$A$100,0)),0)) -> 0 | R78: =IF(B78="","",N(L78)) -> 0 | S78: =IF(B78="","",IF(AND(F78<>"",ISNUMBER(G78),ISNUMBER(IFERROR(INDEX(Precios!$D$5:$D$120,MATCH(F78,Precios!$A$5:$A$120,0)),"x")),OR(H78="",ISNUMBER(IFERROR(INDEX(Precios!$D$5:$D$120,MATCH(H78,Precios!$A$5:$A$120,0)),"x"))),J78<>"",K78<>"",Q78>0),SUM(O78:R78),"")) | T78: =IF(AND(S78<>"",ISNUMBER(E78)),E78*Parametros!$B$12,"") | U78: =IF(AND(S78<>"",ISNUMBER(E78)),E78*Parametros!$B$13,"") | V78: =IF(AND(S78<>"",ISNUMBER(E78)),E78-S78-T78-U78,"") | W78: =IF(AND(S78<>"",ISNUMBER(E78)),V78/E78,"") | X78: =IF(OR(S78="",Parametros!$B$14>=1),"",S78/(1-Parametros!$B$14)) | Y78: =IF(OR(S78="",Parametros!$B$14+Parametros!$B$18>=1),"",S78/(1-Parametros!$B$14-Parametros!$B$18)) | Z78: =IF(B78="","",IF(S78="","FALTAN DATOS",IF(NOT(ISNUMBER(E78)),"FALTA PRECIO",IF(V78<0,"PIERDE",IF(W78<Parametros!$B$18,"BAJO META","OK"))))) -> FALTAN DATOS | AA78: =IF(B78="","",IF(F78="","Tela. ","")&IF(NOT(ISNUMBER(G78)),"Kg de tela. ","")&IF(AND(F78<>"",NOT(ISNUMBER(IFERROR(INDEX(Precios!$D$5:$D$120,MATCH(F78,Precios!$A$5:$A$120,0)),"x")))),"Tela sin precio. ","")&IF(AND(H78<>"",NOT(ISNUMBER(IFERROR(INDEX(Precios!$D$5:$D$120,MATCH(H78,Precios!$A$5:$A$120,0)),"x")))),"Tela 2 sin precio. ","")&IF(J78="","Metros impresos. ","")&IF(AND(N(J78)>0,Parametros!$B$27=0),"Impresión sin costo. ","")&IF(K78="","Confección. ",IF(Q78=0,"Confección sin valor. ",""))&IF(NOT(ISNUMBER(E78)),"Precio de venta. ","")) -> Tela. Kg de tela. Metros impresos. Confección.
A79: SAL-POL-ALG-LIS | B79: POLERÓN ALGODÓN CON CAPUCHA PMK | C79: Salida | D79: 1 | E79: 21765 | M79: Por confirmar | O79: =IF(B79="","",IFERROR(G79*INDEX(Precios!$D$5:$D$120,MATCH(F79,Precios!$A$5:$A$120,0)),0)+IF(H79="",0,IFERROR(I79*INDEX(Precios!$D$5:$D$120,MATCH(H79,Precios!$A$5:$A$120,0)),0))) -> 0 | P79: =IF(B79="","",N(J79)*Parametros!$B$27) -> 0 | Q79: =IF(B79="","",IFERROR(INDEX(Confeccion!$B$5:$B$100,MATCH(K79,Confeccion!$A$5:$A$100,0)),0)) -> 0 | R79: =IF(B79="","",N(L79)) -> 0 | S79: =IF(B79="","",IF(AND(F79<>"",ISNUMBER(G79),ISNUMBER(IFERROR(INDEX(Precios!$D$5:$D$120,MATCH(F79,Precios!$A$5:$A$120,0)),"x")),OR(H79="",ISNUMBER(IFERROR(INDEX(Precios!$D$5:$D$120,MATCH(H79,Precios!$A$5:$A$120,0)),"x"))),J79<>"",K79<>"",Q79>0),SUM(O79:R79),"")) | T79: =IF(AND(S79<>"",ISNUMBER(E79)),E79*Parametros!$B$12,"") | U79: =IF(AND(S79<>"",ISNUMBER(E79)),E79*Parametros!$B$13,"") | V79: =IF(AND(S79<>"",ISNUMBER(E79)),E79-S79-T79-U79,"") | W79: =IF(AND(S79<>"",ISNUMBER(E79)),V79/E79,"") | X79: =IF(OR(S79="",Parametros!$B$14>=1),"",S79/(1-Parametros!$B$14)) | Y79: =IF(OR(S79="",Parametros!$B$14+Parametros!$B$18>=1),"",S79/(1-Parametros!$B$14-Parametros!$B$18)) | Z79: =IF(B79="","",IF(S79="","FALTAN DATOS",IF(NOT(ISNUMBER(E79)),"FALTA PRECIO",IF(V79<0,"PIERDE",IF(W79<Parametros!$B$18,"BAJO META","OK"))))) -> FALTAN DATOS | AA79: =IF(B79="","",IF(F79="","Tela. ","")&IF(NOT(ISNUMBER(G79)),"Kg de tela. ","")&IF(AND(F79<>"",NOT(ISNUMBER(IFERROR(INDEX(Precios!$D$5:$D$120,MATCH(F79,Precios!$A$5:$A$120,0)),"x")))),"Tela sin precio. ","")&IF(AND(H79<>"",NOT(ISNUMBER(IFERROR(INDEX(Precios!$D$5:$D$120,MATCH(H79,Precios!$A$5:$A$120,0)),"x")))),"Tela 2 sin precio. ","")&IF(J79="","Metros impresos. ","")&IF(AND(N(J79)>0,Parametros!$B$27=0),"Impresión sin costo. ","")&IF(K79="","Confección. ",IF(Q79=0,"Confección sin valor. ",""))&IF(NOT(ISNUMBER(E79)),"Precio de venta. ","")) -> Tela. Kg de tela. Metros impresos. Confección.
O80: =IF(B80="","",IFERROR(G80*INDEX(Precios!$D$5:$D$120,MATCH(F80,Precios!$A$5:$A$120,0)),0)+IF(H80="",0,IFERROR(I80*INDEX(Precios!$D$5:$D$120,MATCH(H80,Precios!$A$5:$A$120,0)),0))) | P80: =IF(B80="","",N(J80)*Parametros!$B$27) | Q80: =IF(B80="","",IFERROR(INDEX(Confeccion!$B$5:$B$100,MATCH(K80,Confeccion!$A$5:$A$100,0)),0)) | R80: =IF(B80="","",N(L80)) | S80: =IF(B80="","",IF(AND(F80<>"",ISNUMBER(G80),ISNUMBER(IFERROR(INDEX(Precios!$D$5:$D$120,MATCH(F80,Precios!$A$5:$A$120,0)),"x")),OR(H80="",ISNUMBER(IFERROR(INDEX(Precios!$D$5:$D$120,MATCH(H80,Precios!$A$5:$A$120,0)),"x"))),J80<>"",K80<>"",Q80>0),SUM(O80:R80),"")) | T80: =IF(AND(S80<>"",ISNUMBER(E80)),E80*Parametros!$B$12,"") | U80: =IF(AND(S80<>"",ISNUMBER(E80)),E80*Parametros!$B$13,"") | V80: =IF(AND(S80<>"",ISNUMBER(E80)),E80-S80-T80-U80,"") | W80: =IF(AND(S80<>"",ISNUMBER(E80)),V80/E80,"") | X80: =IF(OR(S80="",Parametros!$B$14>=1),"",S80/(1-Parametros!$B$14)) | Y80: =IF(OR(S80="",Parametros!$B$14+Parametros!$B$18>=1),"",S80/(1-Parametros!$B$14-Parametros!$B$18)) | Z80: =IF(B80="","",IF(S80="","FALTAN DATOS",IF(NOT(ISNUMBER(E80)),"FALTA PRECIO",IF(V80<0,"PIERDE",IF(W80<Parametros!$B$18,"BAJO META","OK"))))) | AA80: =IF(B80="","",IF(F80="","Tela. ","")&IF(NOT(ISNUMBER(G80)),"Kg de tela. ","")&IF(AND(F80<>"",NOT(ISNUMBER(IFERROR(INDEX(Precios!$D$5:$D$120,MATCH(F80,Precios!$A$5:$A$120,0)),"x")))),"Tela sin precio. ","")&IF(AND(H80<>"",NOT(ISNUMBER(IFERROR(INDEX(Precios!$D$5:$D$120,MATCH(H80,Precios!$A$5:$A$120,0)),"x")))),"Tela 2 sin precio. ","")&IF(J80="","Metros impresos. ","")&IF(AND(N(J80)>0,Parametros!$B$27=0),"Impresión sin costo. ","")&IF(K80="","Confección. ",IF(Q80=0,"Confección sin valor. ",""))&IF(NOT(ISNUMBER(E80)),"Precio de venta. ",""))
O81: =IF(B81="","",IFERROR(G81*INDEX(Precios!$D$5:$D$120,MATCH(F81,Precios!$A$5:$A$120,0)),0)+IF(H81="",0,IFERROR(I81*INDEX(Precios!$D$5:$D$120,MATCH(H81,Precios!$A$5:$A$120,0)),0))) | P81: =IF(B81="","",N(J81)*Parametros!$B$27) | Q81: =IF(B81="","",IFERROR(INDEX(Confeccion!$B$5:$B$100,MATCH(K81,Confeccion!$A$5:$A$100,0)),0)) | R81: =IF(B81="","",N(L81)) | S81: =IF(B81="","",IF(AND(F81<>"",ISNUMBER(G81),ISNUMBER(IFERROR(INDEX(Precios!$D$5:$D$120,MATCH(F81,Precios!$A$5:$A$120,0)),"x")),OR(H81="",ISNUMBER(IFERROR(INDEX(Precios!$D$5:$D$120,MATCH(H81,Precios!$A$5:$A$120,0)),"x"))),J81<>"",K81<>"",Q81>0),SUM(O81:R81),"")) | T81: =IF(AND(S81<>"",ISNUMBER(E81)),E81*Parametros!$B$12,"") | U81: =IF(AND(S81<>"",ISNUMBER(E81)),E81*Parametros!$B$13,"") | V81: =IF(AND(S81<>"",ISNUMBER(E81)),E81-S81-T81-U81,"") | W81: =IF(AND(S81<>"",ISNUMBER(E81)),V81/E81,"") | X81: =IF(OR(S81="",Parametros!$B$14>=1),"",S81/(1-Parametros!$B$14)) | Y81: =IF(OR(S81="",Parametros!$B$14+Parametros!$B$18>=1),"",S81/(1-Parametros!$B$14-Parametros!$B$18)) | Z81: =IF(B81="","",IF(S81="","FALTAN DATOS",IF(NOT(ISNUMBER(E81)),"FALTA PRECIO",IF(V81<0,"PIERDE",IF(W81<Parametros!$B$18,"BAJO META","OK"))))) | AA81: =IF(B81="","",IF(F81="","Tela. ","")&IF(NOT(ISNUMBER(G81)),"Kg de tela. ","")&IF(AND(F81<>"",NOT(ISNUMBER(IFERROR(INDEX(Precios!$D$5:$D$120,MATCH(F81,Precios!$A$5:$A$120,0)),"x")))),"Tela sin precio. ","")&IF(AND(H81<>"",NOT(ISNUMBER(IFERROR(INDEX(Precios!$D$5:$D$120,MATCH(H81,Precios!$A$5:$A$120,0)),"x")))),"Tela 2 sin precio. ","")&IF(J81="","Metros impresos. ","")&IF(AND(N(J81)>0,Parametros!$B$27=0),"Impresión sin costo. ","")&IF(K81="","Confección. ",IF(Q81=0,"Confección sin valor. ",""))&IF(NOT(ISNUMBER(E81)),"Precio de venta. ",""))
O82: =IF(B82="","",IFERROR(G82*INDEX(Precios!$D$5:$D$120,MATCH(F82,Precios!$A$5:$A$120,0)),0)+IF(H82="",0,IFERROR(I82*INDEX(Precios!$D$5:$D$120,MATCH(H82,Precios!$A$5:$A$120,0)),0))) | P82: =IF(B82="","",N(J82)*Parametros!$B$27) | Q82: =IF(B82="","",IFERROR(INDEX(Confeccion!$B$5:$B$100,MATCH(K82,Confeccion!$A$5:$A$100,0)),0)) | R82: =IF(B82="","",N(L82)) | S82: =IF(B82="","",IF(AND(F82<>"",ISNUMBER(G82),ISNUMBER(IFERROR(INDEX(Precios!$D$5:$D$120,MATCH(F82,Precios!$A$5:$A$120,0)),"x")),OR(H82="",ISNUMBER(IFERROR(INDEX(Precios!$D$5:$D$120,MATCH(H82,Precios!$A$5:$A$120,0)),"x"))),J82<>"",K82<>"",Q82>0),SUM(O82:R82),"")) | T82: =IF(AND(S82<>"",ISNUMBER(E82)),E82*Parametros!$B$12,"") | U82: =IF(AND(S82<>"",ISNUMBER(E82)),E82*Parametros!$B$13,"") | V82: =IF(AND(S82<>"",ISNUMBER(E82)),E82-S82-T82-U82,"") | W82: =IF(AND(S82<>"",ISNUMBER(E82)),V82/E82,"") | X82: =IF(OR(S82="",Parametros!$B$14>=1),"",S82/(1-Parametros!$B$14)) | Y82: =IF(OR(S82="",Parametros!$B$14+Parametros!$B$18>=1),"",S82/(1-Parametros!$B$14-Parametros!$B$18)) | Z82: =IF(B82="","",IF(S82="","FALTAN DATOS",IF(NOT(ISNUMBER(E82)),"FALTA PRECIO",IF(V82<0,"PIERDE",IF(W82<Parametros!$B$18,"BAJO META","OK"))))) | AA82: =IF(B82="","",IF(F82="","Tela. ","")&IF(NOT(ISNUMBER(G82)),"Kg de tela. ","")&IF(AND(F82<>"",NOT(ISNUMBER(IFERROR(INDEX(Precios!$D$5:$D$120,MATCH(F82,Precios!$A$5:$A$120,0)),"x")))),"Tela sin precio. ","")&IF(AND(H82<>"",NOT(ISNUMBER(IFERROR(INDEX(Precios!$D$5:$D$120,MATCH(H82,Precios!$A$5:$A$120,0)),"x")))),"Tela 2 sin precio. ","")&IF(J82="","Metros impresos. ","")&IF(AND(N(J82)>0,Parametros!$B$27=0),"Impresión sin costo. ","")&IF(K82="","Confección. ",IF(Q82=0,"Confección sin valor. ",""))&IF(NOT(ISNUMBER(E82)),"Precio de venta. ",""))
O83: =IF(B83="","",IFERROR(G83*INDEX(Precios!$D$5:$D$120,MATCH(F83,Precios!$A$5:$A$120,0)),0)+IF(H83="",0,IFERROR(I83*INDEX(Precios!$D$5:$D$120,MATCH(H83,Precios!$A$5:$A$120,0)),0))) | P83: =IF(B83="","",N(J83)*Parametros!$B$27) | Q83: =IF(B83="","",IFERROR(INDEX(Confeccion!$B$5:$B$100,MATCH(K83,Confeccion!$A$5:$A$100,0)),0)) | R83: =IF(B83="","",N(L83)) | S83: =IF(B83="","",IF(AND(F83<>"",ISNUMBER(G83),ISNUMBER(IFERROR(INDEX(Precios!$D$5:$D$120,MATCH(F83,Precios!$A$5:$A$120,0)),"x")),OR(H83="",ISNUMBER(IFERROR(INDEX(Precios!$D$5:$D$120,MATCH(H83,Precios!$A$5:$A$120,0)),"x"))),J83<>"",K83<>"",Q83>0),SUM(O83:R83),"")) | T83: =IF(AND(S83<>"",ISNUMBER(E83)),E83*Parametros!$B$12,"") | U83: =IF(AND(S83<>"",ISNUMBER(E83)),E83*Parametros!$B$13,"") | V83: =IF(AND(S83<>"",ISNUMBER(E83)),E83-S83-T83-U83,"") | W83: =IF(AND(S83<>"",ISNUMBER(E83)),V83/E83,"") | X83: =IF(OR(S83="",Parametros!$B$14>=1),"",S83/(1-Parametros!$B$14)) | Y83: =IF(OR(S83="",Parametros!$B$14+Parametros!$B$18>=1),"",S83/(1-Parametros!$B$14-Parametros!$B$18)) | Z83: =IF(B83="","",IF(S83="","FALTAN DATOS",IF(NOT(ISNUMBER(E83)),"FALTA PRECIO",IF(V83<0,"PIERDE",IF(W83<Parametros!$B$18,"BAJO META","OK"))))) | AA83: =IF(B83="","",IF(F83="","Tela. ","")&IF(NOT(ISNUMBER(G83)),"Kg de tela. ","")&IF(AND(F83<>"",NOT(ISNUMBER(IFERROR(INDEX(Precios!$D$5:$D$120,MATCH(F83,Precios!$A$5:$A$120,0)),"x")))),"Tela sin precio. ","")&IF(AND(H83<>"",NOT(ISNUMBER(IFERROR(INDEX(Precios!$D$5:$D$120,MATCH(H83,Precios!$A$5:$A$120,0)),"x")))),"Tela 2 sin precio. ","")&IF(J83="","Metros impresos. ","")&IF(AND(N(J83)>0,Parametros!$B$27=0),"Impresión sin costo. ","")&IF(K83="","Confección. ",IF(Q83=0,"Confección sin valor. ",""))&IF(NOT(ISNUMBER(E83)),"Precio de venta. ",""))
O84: =IF(B84="","",IFERROR(G84*INDEX(Precios!$D$5:$D$120,MATCH(F84,Precios!$A$5:$A$120,0)),0)+IF(H84="",0,IFERROR(I84*INDEX(Precios!$D$5:$D$120,MATCH(H84,Precios!$A$5:$A$120,0)),0))) | P84: =IF(B84="","",N(J84)*Parametros!$B$27) | Q84: =IF(B84="","",IFERROR(INDEX(Confeccion!$B$5:$B$100,MATCH(K84,Confeccion!$A$5:$A$100,0)),0)) | R84: =IF(B84="","",N(L84)) | S84: =IF(B84="","",IF(AND(F84<>"",ISNUMBER(G84),ISNUMBER(IFERROR(INDEX(Precios!$D$5:$D$120,MATCH(F84,Precios!$A$5:$A$120,0)),"x")),OR(H84="",ISNUMBER(IFERROR(INDEX(Precios!$D$5:$D$120,MATCH(H84,Precios!$A$5:$A$120,0)),"x"))),J84<>"",K84<>"",Q84>0),SUM(O84:R84),"")) | T84: =IF(AND(S84<>"",ISNUMBER(E84)),E84*Parametros!$B$12,"") | U84: =IF(AND(S84<>"",ISNUMBER(E84)),E84*Parametros!$B$13,"") | V84: =IF(AND(S84<>"",ISNUMBER(E84)),E84-S84-T84-U84,"") | W84: =IF(AND(S84<>"",ISNUMBER(E84)),V84/E84,"") | X84: =IF(OR(S84="",Parametros!$B$14>=1),"",S84/(1-Parametros!$B$14)) | Y84: =IF(OR(S84="",Parametros!$B$14+Parametros!$B$18>=1),"",S84/(1-Parametros!$B$14-Parametros!$B$18)) | Z84: =IF(B84="","",IF(S84="","FALTAN DATOS",IF(NOT(ISNUMBER(E84)),"FALTA PRECIO",IF(V84<0,"PIERDE",IF(W84<Parametros!$B$18,"BAJO META","OK"))))) | AA84: =IF(B84="","",IF(F84="","Tela. ","")&IF(NOT(ISNUMBER(G84)),"Kg de tela. ","")&IF(AND(F84<>"",NOT(ISNUMBER(IFERROR(INDEX(Precios!$D$5:$D$120,MATCH(F84,Precios!$A$5:$A$120,0)),"x")))),"Tela sin precio. ","")&IF(AND(H84<>"",NOT(ISNUMBER(IFERROR(INDEX(Precios!$D$5:$D$120,MATCH(H84,Precios!$A$5:$A$120,0)),"x")))),"Tela 2 sin precio. ","")&IF(J84="","Metros impresos. ","")&IF(AND(N(J84)>0,Parametros!$B$27=0),"Impresión sin costo. ","")&IF(K84="","Confección. ",IF(Q84=0,"Confección sin valor. ",""))&IF(NOT(ISNUMBER(E84)),"Precio de venta. ",""))
O85: =IF(B85="","",IFERROR(G85*INDEX(Precios!$D$5:$D$120,MATCH(F85,Precios!$A$5:$A$120,0)),0)+IF(H85="",0,IFERROR(I85*INDEX(Precios!$D$5:$D$120,MATCH(H85,Precios!$A$5:$A$120,0)),0))) | P85: =IF(B85="","",N(J85)*Parametros!$B$27) | Q85: =IF(B85="","",IFERROR(INDEX(Confeccion!$B$5:$B$100,MATCH(K85,Confeccion!$A$5:$A$100,0)),0)) | R85: =IF(B85="","",N(L85)) | S85: =IF(B85="","",IF(AND(F85<>"",ISNUMBER(G85),ISNUMBER(IFERROR(INDEX(Precios!$D$5:$D$120,MATCH(F85,Precios!$A$5:$A$120,0)),"x")),OR(H85="",ISNUMBER(IFERROR(INDEX(Precios!$D$5:$D$120,MATCH(H85,Precios!$A$5:$A$120,0)),"x"))),J85<>"",K85<>"",Q85>0),SUM(O85:R85),"")) | T85: =IF(AND(S85<>"",ISNUMBER(E85)),E85*Parametros!$B$12,"") | U85: =IF(AND(S85<>"",ISNUMBER(E85)),E85*Parametros!$B$13,"") | V85: =IF(AND(S85<>"",ISNUMBER(E85)),E85-S85-T85-U85,"") | W85: =IF(AND(S85<>"",ISNUMBER(E85)),V85/E85,"") | X85: =IF(OR(S85="",Parametros!$B$14>=1),"",S85/(1-Parametros!$B$14)) | Y85: =IF(OR(S85="",Parametros!$B$14+Parametros!$B$18>=1),"",S85/(1-Parametros!$B$14-Parametros!$B$18)) | Z85: =IF(B85="","",IF(S85="","FALTAN DATOS",IF(NOT(ISNUMBER(E85)),"FALTA PRECIO",IF(V85<0,"PIERDE",IF(W85<Parametros!$B$18,"BAJO META","OK"))))) | AA85: =IF(B85="","",IF(F85="","Tela. ","")&IF(NOT(ISNUMBER(G85)),"Kg de tela. ","")&IF(AND(F85<>"",NOT(ISNUMBER(IFERROR(INDEX(Precios!$D$5:$D$120,MATCH(F85,Precios!$A$5:$A$120,0)),"x")))),"Tela sin precio. ","")&IF(AND(H85<>"",NOT(ISNUMBER(IFERROR(INDEX(Precios!$D$5:$D$120,MATCH(H85,Precios!$A$5:$A$120,0)),"x")))),"Tela 2 sin precio. ","")&IF(J85="","Metros impresos. ","")&IF(AND(N(J85)>0,Parametros!$B$27=0),"Impresión sin costo. ","")&IF(K85="","Confección. ",IF(Q85=0,"Confección sin valor. ",""))&IF(NOT(ISNUMBER(E85)),"Precio de venta. ",""))
O86: =IF(B86="","",IFERROR(G86*INDEX(Precios!$D$5:$D$120,MATCH(F86,Precios!$A$5:$A$120,0)),0)+IF(H86="",0,IFERROR(I86*INDEX(Precios!$D$5:$D$120,MATCH(H86,Precios!$A$5:$A$120,0)),0))) | P86: =IF(B86="","",N(J86)*Parametros!$B$27) | Q86: =IF(B86="","",IFERROR(INDEX(Confeccion!$B$5:$B$100,MATCH(K86,Confeccion!$A$5:$A$100,0)),0)) | R86: =IF(B86="","",N(L86)) | S86: =IF(B86="","",IF(AND(F86<>"",ISNUMBER(G86),ISNUMBER(IFERROR(INDEX(Precios!$D$5:$D$120,MATCH(F86,Precios!$A$5:$A$120,0)),"x")),OR(H86="",ISNUMBER(IFERROR(INDEX(Precios!$D$5:$D$120,MATCH(H86,Precios!$A$5:$A$120,0)),"x"))),J86<>"",K86<>"",Q86>0),SUM(O86:R86),"")) | T86: =IF(AND(S86<>"",ISNUMBER(E86)),E86*Parametros!$B$12,"") | U86: =IF(AND(S86<>"",ISNUMBER(E86)),E86*Parametros!$B$13,"") | V86: =IF(AND(S86<>"",ISNUMBER(E86)),E86-S86-T86-U86,"") | W86: =IF(AND(S86<>"",ISNUMBER(E86)),V86/E86,"") | X86: =IF(OR(S86="",Parametros!$B$14>=1),"",S86/(1-Parametros!$B$14)) | Y86: =IF(OR(S86="",Parametros!$B$14+Parametros!$B$18>=1),"",S86/(1-Parametros!$B$14-Parametros!$B$18)) | Z86: =IF(B86="","",IF(S86="","FALTAN DATOS",IF(NOT(ISNUMBER(E86)),"FALTA PRECIO",IF(V86<0,"PIERDE",IF(W86<Parametros!$B$18,"BAJO META","OK"))))) | AA86: =IF(B86="","",IF(F86="","Tela. ","")&IF(NOT(ISNUMBER(G86)),"Kg de tela. ","")&IF(AND(F86<>"",NOT(ISNUMBER(IFERROR(INDEX(Precios!$D$5:$D$120,MATCH(F86,Precios!$A$5:$A$120,0)),"x")))),"Tela sin precio. ","")&IF(AND(H86<>"",NOT(ISNUMBER(IFERROR(INDEX(Precios!$D$5:$D$120,MATCH(H86,Precios!$A$5:$A$120,0)),"x")))),"Tela 2 sin precio. ","")&IF(J86="","Metros impresos. ","")&IF(AND(N(J86)>0,Parametros!$B$27=0),"Impresión sin costo. ","")&IF(K86="","Confección. ",IF(Q86=0,"Confección sin valor. ",""))&IF(NOT(ISNUMBER(E86)),"Precio de venta. ",""))
O87: =IF(B87="","",IFERROR(G87*INDEX(Precios!$D$5:$D$120,MATCH(F87,Precios!$A$5:$A$120,0)),0)+IF(H87="",0,IFERROR(I87*INDEX(Precios!$D$5:$D$120,MATCH(H87,Precios!$A$5:$A$120,0)),0))) | P87: =IF(B87="","",N(J87)*Parametros!$B$27) | Q87: =IF(B87="","",IFERROR(INDEX(Confeccion!$B$5:$B$100,MATCH(K87,Confeccion!$A$5:$A$100,0)),0)) | R87: =IF(B87="","",N(L87)) | S87: =IF(B87="","",IF(AND(F87<>"",ISNUMBER(G87),ISNUMBER(IFERROR(INDEX(Precios!$D$5:$D$120,MATCH(F87,Precios!$A$5:$A$120,0)),"x")),OR(H87="",ISNUMBER(IFERROR(INDEX(Precios!$D$5:$D$120,MATCH(H87,Precios!$A$5:$A$120,0)),"x"))),J87<>"",K87<>"",Q87>0),SUM(O87:R87),"")) | T87: =IF(AND(S87<>"",ISNUMBER(E87)),E87*Parametros!$B$12,"") | U87: =IF(AND(S87<>"",ISNUMBER(E87)),E87*Parametros!$B$13,"") | V87: =IF(AND(S87<>"",ISNUMBER(E87)),E87-S87-T87-U87,"") | W87: =IF(AND(S87<>"",ISNUMBER(E87)),V87/E87,"") | X87: =IF(OR(S87="",Parametros!$B$14>=1),"",S87/(1-Parametros!$B$14)) | Y87: =IF(OR(S87="",Parametros!$B$14+Parametros!$B$18>=1),"",S87/(1-Parametros!$B$14-Parametros!$B$18)) | Z87: =IF(B87="","",IF(S87="","FALTAN DATOS",IF(NOT(ISNUMBER(E87)),"FALTA PRECIO",IF(V87<0,"PIERDE",IF(W87<Parametros!$B$18,"BAJO META","OK"))))) | AA87: =IF(B87="","",IF(F87="","Tela. ","")&IF(NOT(ISNUMBER(G87)),"Kg de tela. ","")&IF(AND(F87<>"",NOT(ISNUMBER(IFERROR(INDEX(Precios!$D$5:$D$120,MATCH(F87,Precios!$A$5:$A$120,0)),"x")))),"Tela sin precio. ","")&IF(AND(H87<>"",NOT(ISNUMBER(IFERROR(INDEX(Precios!$D$5:$D$120,MATCH(H87,Precios!$A$5:$A$120,0)),"x")))),"Tela 2 sin precio. ","")&IF(J87="","Metros impresos. ","")&IF(AND(N(J87)>0,Parametros!$B$27=0),"Impresión sin costo. ","")&IF(K87="","Confección. ",IF(Q87=0,"Confección sin valor. ",""))&IF(NOT(ISNUMBER(E87)),"Precio de venta. ",""))
O88: =IF(B88="","",IFERROR(G88*INDEX(Precios!$D$5:$D$120,MATCH(F88,Precios!$A$5:$A$120,0)),0)+IF(H88="",0,IFERROR(I88*INDEX(Precios!$D$5:$D$120,MATCH(H88,Precios!$A$5:$A$120,0)),0))) | P88: =IF(B88="","",N(J88)*Parametros!$B$27) | Q88: =IF(B88="","",IFERROR(INDEX(Confeccion!$B$5:$B$100,MATCH(K88,Confeccion!$A$5:$A$100,0)),0)) | R88: =IF(B88="","",N(L88)) | S88: =IF(B88="","",IF(AND(F88<>"",ISNUMBER(G88),ISNUMBER(IFERROR(INDEX(Precios!$D$5:$D$120,MATCH(F88,Precios!$A$5:$A$120,0)),"x")),OR(H88="",ISNUMBER(IFERROR(INDEX(Precios!$D$5:$D$120,MATCH(H88,Precios!$A$5:$A$120,0)),"x"))),J88<>"",K88<>"",Q88>0),SUM(O88:R88),"")) | T88: =IF(AND(S88<>"",ISNUMBER(E88)),E88*Parametros!$B$12,"") | U88: =IF(AND(S88<>"",ISNUMBER(E88)),E88*Parametros!$B$13,"") | V88: =IF(AND(S88<>"",ISNUMBER(E88)),E88-S88-T88-U88,"") | W88: =IF(AND(S88<>"",ISNUMBER(E88)),V88/E88,"") | X88: =IF(OR(S88="",Parametros!$B$14>=1),"",S88/(1-Parametros!$B$14)) | Y88: =IF(OR(S88="",Parametros!$B$14+Parametros!$B$18>=1),"",S88/(1-Parametros!$B$14-Parametros!$B$18)) | Z88: =IF(B88="","",IF(S88="","FALTAN DATOS",IF(NOT(ISNUMBER(E88)),"FALTA PRECIO",IF(V88<0,"PIERDE",IF(W88<Parametros!$B$18,"BAJO META","OK"))))) | AA88: =IF(B88="","",IF(F88="","Tela. ","")&IF(NOT(ISNUMBER(G88)),"Kg de tela. ","")&IF(AND(F88<>"",NOT(ISNUMBER(IFERROR(INDEX(Precios!$D$5:$D$120,MATCH(F88,Precios!$A$5:$A$120,0)),"x")))),"Tela sin precio. ","")&IF(AND(H88<>"",NOT(ISNUMBER(IFERROR(INDEX(Precios!$D$5:$D$120,MATCH(H88,Precios!$A$5:$A$120,0)),"x")))),"Tela 2 sin precio. ","")&IF(J88="","Metros impresos. ","")&IF(AND(N(J88)>0,Parametros!$B$27=0),"Impresión sin costo. ","")&IF(K88="","Confección. ",IF(Q88=0,"Confección sin valor. ",""))&IF(NOT(ISNUMBER(E88)),"Precio de venta. ",""))
O89: =IF(B89="","",IFERROR(G89*INDEX(Precios!$D$5:$D$120,MATCH(F89,Precios!$A$5:$A$120,0)),0)+IF(H89="",0,IFERROR(I89*INDEX(Precios!$D$5:$D$120,MATCH(H89,Precios!$A$5:$A$120,0)),0))) | P89: =IF(B89="","",N(J89)*Parametros!$B$27) | Q89: =IF(B89="","",IFERROR(INDEX(Confeccion!$B$5:$B$100,MATCH(K89,Confeccion!$A$5:$A$100,0)),0)) | R89: =IF(B89="","",N(L89)) | S89: =IF(B89="","",IF(AND(F89<>"",ISNUMBER(G89),ISNUMBER(IFERROR(INDEX(Precios!$D$5:$D$120,MATCH(F89,Precios!$A$5:$A$120,0)),"x")),OR(H89="",ISNUMBER(IFERROR(INDEX(Precios!$D$5:$D$120,MATCH(H89,Precios!$A$5:$A$120,0)),"x"))),J89<>"",K89<>"",Q89>0),SUM(O89:R89),"")) | T89: =IF(AND(S89<>"",ISNUMBER(E89)),E89*Parametros!$B$12,"") | U89: =IF(AND(S89<>"",ISNUMBER(E89)),E89*Parametros!$B$13,"") | V89: =IF(AND(S89<>"",ISNUMBER(E89)),E89-S89-T89-U89,"") | W89: =IF(AND(S89<>"",ISNUMBER(E89)),V89/E89,"") | X89: =IF(OR(S89="",Parametros!$B$14>=1),"",S89/(1-Parametros!$B$14)) | Y89: =IF(OR(S89="",Parametros!$B$14+Parametros!$B$18>=1),"",S89/(1-Parametros!$B$14-Parametros!$B$18)) | Z89: =IF(B89="","",IF(S89="","FALTAN DATOS",IF(NOT(ISNUMBER(E89)),"FALTA PRECIO",IF(V89<0,"PIERDE",IF(W89<Parametros!$B$18,"BAJO META","OK"))))) | AA89: =IF(B89="","",IF(F89="","Tela. ","")&IF(NOT(ISNUMBER(G89)),"Kg de tela. ","")&IF(AND(F89<>"",NOT(ISNUMBER(IFERROR(INDEX(Precios!$D$5:$D$120,MATCH(F89,Precios!$A$5:$A$120,0)),"x")))),"Tela sin precio. ","")&IF(AND(H89<>"",NOT(ISNUMBER(IFERROR(INDEX(Precios!$D$5:$D$120,MATCH(H89,Precios!$A$5:$A$120,0)),"x")))),"Tela 2 sin precio. ","")&IF(J89="","Metros impresos. ","")&IF(AND(N(J89)>0,Parametros!$B$27=0),"Impresión sin costo. ","")&IF(K89="","Confección. ",IF(Q89=0,"Confección sin valor. ",""))&IF(NOT(ISNUMBER(E89)),"Precio de venta. ",""))
O90: =IF(B90="","",IFERROR(G90*INDEX(Precios!$D$5:$D$120,MATCH(F90,Precios!$A$5:$A$120,0)),0)+IF(H90="",0,IFERROR(I90*INDEX(Precios!$D$5:$D$120,MATCH(H90,Precios!$A$5:$A$120,0)),0))) | P90: =IF(B90="","",N(J90)*Parametros!$B$27) | Q90: =IF(B90="","",IFERROR(INDEX(Confeccion!$B$5:$B$100,MATCH(K90,Confeccion!$A$5:$A$100,0)),0)) | R90: =IF(B90="","",N(L90)) | S90: =IF(B90="","",IF(AND(F90<>"",ISNUMBER(G90),ISNUMBER(IFERROR(INDEX(Precios!$D$5:$D$120,MATCH(F90,Precios!$A$5:$A$120,0)),"x")),OR(H90="",ISNUMBER(IFERROR(INDEX(Precios!$D$5:$D$120,MATCH(H90,Precios!$A$5:$A$120,0)),"x"))),J90<>"",K90<>"",Q90>0),SUM(O90:R90),"")) | T90: =IF(AND(S90<>"",ISNUMBER(E90)),E90*Parametros!$B$12,"") | U90: =IF(AND(S90<>"",ISNUMBER(E90)),E90*Parametros!$B$13,"") | V90: =IF(AND(S90<>"",ISNUMBER(E90)),E90-S90-T90-U90,"") | W90: =IF(AND(S90<>"",ISNUMBER(E90)),V90/E90,"") | X90: =IF(OR(S90="",Parametros!$B$14>=1),"",S90/(1-Parametros!$B$14)) | Y90: =IF(OR(S90="",Parametros!$B$14+Parametros!$B$18>=1),"",S90/(1-Parametros!$B$14-Parametros!$B$18)) | Z90: =IF(B90="","",IF(S90="","FALTAN DATOS",IF(NOT(ISNUMBER(E90)),"FALTA PRECIO",IF(V90<0,"PIERDE",IF(W90<Parametros!$B$18,"BAJO META","OK"))))) | AA90: =IF(B90="","",IF(F90="","Tela. ","")&IF(NOT(ISNUMBER(G90)),"Kg de tela. ","")&IF(AND(F90<>"",NOT(ISNUMBER(IFERROR(INDEX(Precios!$D$5:$D$120,MATCH(F90,Precios!$A$5:$A$120,0)),"x")))),"Tela sin precio. ","")&IF(AND(H90<>"",NOT(ISNUMBER(IFERROR(INDEX(Precios!$D$5:$D$120,MATCH(H90,Precios!$A$5:$A$120,0)),"x")))),"Tela 2 sin precio. ","")&IF(J90="","Metros impresos. ","")&IF(AND(N(J90)>0,Parametros!$B$27=0),"Impresión sin costo. ","")&IF(K90="","Confección. ",IF(Q90=0,"Confección sin valor. ",""))&IF(NOT(ISNUMBER(E90)),"Precio de venta. ",""))
O91: =IF(B91="","",IFERROR(G91*INDEX(Precios!$D$5:$D$120,MATCH(F91,Precios!$A$5:$A$120,0)),0)+IF(H91="",0,IFERROR(I91*INDEX(Precios!$D$5:$D$120,MATCH(H91,Precios!$A$5:$A$120,0)),0))) | P91: =IF(B91="","",N(J91)*Parametros!$B$27) | Q91: =IF(B91="","",IFERROR(INDEX(Confeccion!$B$5:$B$100,MATCH(K91,Confeccion!$A$5:$A$100,0)),0)) | R91: =IF(B91="","",N(L91)) | S91: =IF(B91="","",IF(AND(F91<>"",ISNUMBER(G91),ISNUMBER(IFERROR(INDEX(Precios!$D$5:$D$120,MATCH(F91,Precios!$A$5:$A$120,0)),"x")),OR(H91="",ISNUMBER(IFERROR(INDEX(Precios!$D$5:$D$120,MATCH(H91,Precios!$A$5:$A$120,0)),"x"))),J91<>"",K91<>"",Q91>0),SUM(O91:R91),"")) | T91: =IF(AND(S91<>"",ISNUMBER(E91)),E91*Parametros!$B$12,"") | U91: =IF(AND(S91<>"",ISNUMBER(E91)),E91*Parametros!$B$13,"") | V91: =IF(AND(S91<>"",ISNUMBER(E91)),E91-S91-T91-U91,"") | W91: =IF(AND(S91<>"",ISNUMBER(E91)),V91/E91,"") | X91: =IF(OR(S91="",Parametros!$B$14>=1),"",S91/(1-Parametros!$B$14)) | Y91: =IF(OR(S91="",Parametros!$B$14+Parametros!$B$18>=1),"",S91/(1-Parametros!$B$14-Parametros!$B$18)) | Z91: =IF(B91="","",IF(S91="","FALTAN DATOS",IF(NOT(ISNUMBER(E91)),"FALTA PRECIO",IF(V91<0,"PIERDE",IF(W91<Parametros!$B$18,"BAJO META","OK"))))) | AA91: =IF(B91="","",IF(F91="","Tela. ","")&IF(NOT(ISNUMBER(G91)),"Kg de tela. ","")&IF(AND(F91<>"",NOT(ISNUMBER(IFERROR(INDEX(Precios!$D$5:$D$120,MATCH(F91,Precios!$A$5:$A$120,0)),"x")))),"Tela sin precio. ","")&IF(AND(H91<>"",NOT(ISNUMBER(IFERROR(INDEX(Precios!$D$5:$D$120,MATCH(H91,Precios!$A$5:$A$120,0)),"x")))),"Tela 2 sin precio. ","")&IF(J91="","Metros impresos. ","")&IF(AND(N(J91)>0,Parametros!$B$27=0),"Impresión sin costo. ","")&IF(K91="","Confección. ",IF(Q91=0,"Confección sin valor. ",""))&IF(NOT(ISNUMBER(E91)),"Precio de venta. ",""))
... O250: =IF(B250="","",IFERROR(G250*INDEX(Precios!$D$5:$D$120,MATCH(F250,Precios!$A$5:$A$120,0)),0)+IF(H250="",0,IFERROR(I250*INDEX(Precios!$D$5:$D$120,MATCH(H250,Precios!$A$5:$A$120,0)),0))) | P250: =IF(B250="","",N(J250)*Parametros!$B$27) | Q250: =IF(B250="","",IFERROR(INDEX(Confeccion!$B$5:$B$100,MATCH(K250,Confeccion!$A$5:$A$100,0)),0)) | R250: =IF(B250="","",N(L250)) | S250: =IF(B250="","",IF(AND(F250<>"",ISNUMBER(G250),ISNUMBER(IFERROR(INDEX(Precios!$D$5:$D$120,MATCH(F250,Precios!$A$5:$A$120,0)),"x")),OR(H250="",ISNUMBER(IFERROR(INDEX(Precios!$D$5:$D$120,MATCH(H250,Precios!$A$5:$A$120,0)),"x"))),J250<>"",K250<>"",Q250>0),SUM(O250:R250),"")) | T250: =IF(AND(S250<>"",ISNUMBER(E250)),E250*Parametros!$B$12,"") | U250: =IF(AND(S250<>"",ISNUMBER(E250)),E250*Parametros!$B$13,"") | V250: =IF(AND(S250<>"",ISNUMBER(E250)),E250-S250-T250-U250,"") | W250: =IF(AND(S250<>"",ISNUMBER(E250)),V250/E250,"") | X250: =IF(OR(S250="",Parametros!$B$14>=1),"",S250/(1-Parametros!$B$14)) | Y250: =IF(OR(S250="",Parametros!$B$14+Parametros!$B$18>=1),"",S250/(1-Parametros!$B$14-Parametros!$B$18)) | Z250: =IF(B250="","",IF(S250="","FALTAN DATOS",IF(NOT(ISNUMBER(E250)),"FALTA PRECIO",IF(V250<0,"PIERDE",IF(W250<Parametros!$B$18,"BAJO META","OK"))))) | AA250: =IF(B250="","",IF(F250="","Tela. ","")&IF(NOT(ISNUMBER(G250)),"Kg de tela. ","")&IF(AND(F250<>"",NOT(ISNUMBER(IFERROR(INDEX(Precios!$D$5:$D$120,MATCH(F250,Precios!$A$5:$A$120,0)),"x")))),"Tela sin precio. ","")&IF(AND(H250<>"",NOT(ISNUMBER(IFERROR(INDEX(Precios!$D$5:$D$120,MATCH(H250,Precios!$A$5:$A$120,0)),"x")))),"Tela 2 sin precio. ","")&IF(J250="","Metros impresos. ","")&IF(AND(N(J250)>0,Parametros!$B$27=0),"Impresión sin costo. ","")&IF(K250="","Confección. ",IF(Q250=0,"Confección sin valor. ",""))&IF(NOT(ISNUMBER(E250)),"Precio de venta. ",""))

Sheet Parametros
A1: PARÁMETROS — recargo, meta de ganancia y costo de impresión
A2: Azul = lo editas tú. Gris = se calcula solo.
A4: 1) RECARGO POR GASTOS FIJOS (promedio de los últimos 3 meses, se revisa cada trimestre)
A5: Gastos de fábrica — promedio mensual | B5: =Gastos_Ventas!F41 -> 12421897 | C5: Desde Gastos_Ventas
A6: Gastos comerciales — promedio mensual | B6: =Gastos_Ventas!F42 -> 4459061 | C6: Desde Gastos_Ventas
A7: Ventas netas — promedio mensual | B7: =Gastos_Ventas!F45 -> 35194840 | C7: Desde Gastos_Ventas
A8: Recargo de fábrica calculado | B8: =IFERROR(B5/B7,0) -> 0.35294654 | C8: Gastos de fábrica ÷ ventas
A9: Recargo comercial calculado | B9: =IFERROR(B6/B7,0) -> 0.12669644 | C9: Gastos comerciales ÷ ventas
A10: Recargo de fábrica fijado a mano (opcional) | C10: Vacío = usa el calculado. Escribe un % solo si quieres fijarlo.
A11: Recargo comercial fijado a mano (opcional) | C11: Vacío = usa el calculado.
A12: RECARGO DE FÁBRICA USADO | B12: =IF(ISNUMBER(B10),B10,B8) -> 0.35294654 | C12: Lo usan todas las recetas
A13: RECARGO COMERCIAL USADO | B13: =IF(ISNUMBER(B11),B11,B9) -> 0.12669644 | C13: Lo usan todas las recetas
A14: RECARGO TOTAL | B14: =B12+B13 -> 0.47964299 | C14: De cada $100 que vendes, este monto se va en pagar gastos fijos.
A15: Próxima revisión del recargo | B15: Diciembre 2026 | C15: Usar septiembre, octubre y noviembre.
A17: 2) META DE GANANCIA
A18: Ganancia deseada (% del precio de venta) | B18: 0.1 | C18: POR CONFIRMAR: 10% es solo un ejemplo. Define tu meta.
A20: 3) COSTO DE IMPRESIÓN (papel + tinta) por metro impreso
A21: Papel sublimación — precio del rollo ($) | B21: 50420 | C21: POR CONFIRMAR: en tu archivo dice $50.420 "por kg". ¿Es el precio del rollo?
A22: Papel — metros que rinde el rollo | C22: PENDIENTE: ¿cuántos metros trae el rollo?
A23: Tinta — precio por litro ($) | B23: 72119 | C23: POR CONFIRMAR: precio de la tinta magenta. ¿Los otros colores cuestan lo mismo?
A24: Tinta — ml que gasta 1 metro impreso | C24: PENDIENTE: litros gastados en el mes ÷ metros impresos (Control de Ploteo) × 1000.
A25: Papel por metro | B25: =IFERROR(B21/B22,0) -> 0 | C25: Se calcula solo
A26: Tinta por metro | B26: =B24*B23/1000 -> 0 | C26: Se calcula solo
A27: COSTO DE IMPRESIÓN POR METRO | B27: =B25+B26 -> 0 | C27: Mientras esté en $0, las prendas sublimadas salen más baratas de lo real.
A29: 4) POR QUÉ LOS SUELDOS NO VAN EN LA RECETA
A30: Los sueldos de ploteo, sublimación, corte y estampado se pagan completos cada mes, se produzca mucho o poco. Por eso van en "Gastos de fábrica" y llegan a cada prenda a través del recargo. Si además se cobraran dentro de la receta (como hacía el sistema anterior), se contarían dos veces. La receta solo lleva lo que se gasta por cada prenda: tela, papel y tinta, taller de confección y avíos.

Sheet Gastos_Ventas
A1: GASTOS FIJOS Y VENTAS — últimos 3 meses
A2: Cada trimestre escribe los 3 meses más recientes. El promedio y el recargo se recalculan solos.
A4: Concepto | B4: Grupo | C4: Jun-2026 | D4: Jul-2026 | E4: Ago-2026 | F4: Promedio 3 meses | G4: Nota
A5: Ploteo | B5: Fábrica | C5: 2400000 | D5: 2400000 | E5: 2400000 | F5: =AVERAGE(C5:E5) -> 2400000 | G5: Sueldo: se paga igual haya o no producción → va en gastos, no en la receta.
A6: Sublimación | B6: Fábrica | C6: 833000 | D6: 833000 | E6: 833000 | F6: =AVERAGE(C6:E6) -> 833000 | G6: Sueldo: se paga igual haya o no producción → va en gastos, no en la receta.
A7: Corte | B7: Fábrica | C7: 1666000 | D7: 1666000 | E7: 1666000 | F7: =AVERAGE(C7:E7) -> 1666000 | G7: Sueldo: se paga igual haya o no producción → va en gastos, no en la receta.
A8: Confección interna | B8: Fábrica | C8: 1105374 | D8: 1105374 | E8: 1105374 | F8: =AVERAGE(C8:E8) -> 1105374 | G8: Sueldo: se paga igual haya o no producción → va en gastos, no en la receta.
A9: Estampado | B9: Fábrica | C9: 720000 | D9: 720000 | E9: 720000 | F9: =AVERAGE(C9:E9) -> 720000 | G9: Sueldo: se paga igual haya o no producción → va en gastos, no en la receta.
A10: Luz | B10: Fábrica | C10: 638049 | D10: 638049 | E10: 638049 | F10: =AVERAGE(C10:E10) -> 638049
A11: Agua | B11: Fábrica | C11: 10630 | D11: 10630 | E11: 10630 | F11: =AVERAGE(C11:E11) -> 10630
A12: Telefonía | B12: Fábrica | C12: 95000 | D12: 95000 | E12: 95000 | F12: =AVERAGE(C12:E12) -> 95000
A13: Arriendo | B13: Fábrica | C13: 2163844 | D13: 2163844 | E13: 2163844 | F13: =AVERAGE(C13:E13) -> 2163844
A14: Internet | B14: Fábrica | C14: 49000 | D14: 49000 | E14: 49000 | F14: =AVERAGE(C14:E14) -> 49000
A15: Mantención de máquinas | B15: Fábrica | C15: 300000 | D15: 300000 | E15: 300000 | F15: =AVERAGE(C15:E15) -> 300000
A16: Seguridad | B16: Fábrica | C16: 50000 | D16: 50000 | E16: 50000 | F16: =AVERAGE(C16:E16) -> 50000
A17: Insumos de limpieza (aseo) | B17: Fábrica | C17: 100000 | D17: 100000 | E17: 100000 | F17: =AVERAGE(C17:E17) -> 100000
A18: Insumos de oficina | B18: Fábrica | C18: 100000 | D18: 100000 | E18: 100000 | F18: =AVERAGE(C18:E18) -> 100000
A19: Bencina | B19: Fábrica | C19: 300000 | D19: 300000 | E19: 300000 | F19: =AVERAGE(C19:E19) -> 300000
A20: Jefe de producción (sueldo) | B20: Fábrica | C20: 1071000 | D20: 1071000 | E20: 1071000 | F20: =AVERAGE(C20:E20) -> 1071000 | G20: Sueldo: se paga igual haya o no producción → va en gastos, no en la receta.
A21: Fichas técnicas (sueldo) | B21: Fábrica | C21: 400000 | D21: 400000 | E21: 400000 | F21: =AVERAGE(C21:E21) -> 400000 | G21: Sueldo: se paga igual haya o no producción → va en gastos, no en la receta.
A22: Apoyo producción (sueldo) | B22: Fábrica | C22: 120000 | D22: 120000 | E22: 120000 | F22: =AVERAGE(C22:E22) -> 120000 | G22: Sueldo: se paga igual haya o no producción → va en gastos, no en la receta.
A23: Personal aseo (sueldo) | B23: Fábrica | C23: 300000 | D23: 300000 | E23: 300000 | F23: =AVERAGE(C23:E23) -> 300000 | G23: Sueldo: se paga igual haya o no producción → va en gastos, no en la receta.
A24: CEO (sueldo) | B24: Comercial | C24: 0 | D24: 0 | E24: 0 | F24: =AVERAGE(C24:E24) -> 0 | G24: Sueldo: se paga igual haya o no producción → va en gastos, no en la receta.
A25: Administración (sueldo) | B25: Comercial | C25: 0 | D25: 0 | E25: 0 | F25: =AVERAGE(C25:E25) -> 0 | G25: Sueldo: se paga igual haya o no producción → va en gastos, no en la receta.
A26: Ventas (sueldo) | B26: Comercial | C26: 1680000 | D26: 1680000 | E26: 1680000 | F26: =AVERAGE(C26:E26) -> 1680000 | G26: Sueldo: se paga igual haya o no producción → va en gastos, no en la receta.
A27: Marketing (sueldo) | B27: Comercial | C27: 680000 | D27: 680000 | E27: 680000 | F27: =AVERAGE(C27:E27) -> 680000 | G27: Sueldo: se paga igual haya o no producción → va en gastos, no en la receta.
A28: Audiovisual / contenido (sueldo) | B28: Comercial | C28: 397000 | D28: 397000 | E28: 397000 | F28: =AVERAGE(C28:E28) -> 397000 | G28: Sueldo: se paga igual haya o no producción → va en gastos, no en la receta.
A29: Facebook / Instagram Ads | B29: Comercial | C29: 447861 | D29: 447861 | E29: 447861 | F29: =AVERAGE(C29:E29) -> 447861
A30: Google Ads | B30: Comercial | C30: 450000 | D30: 450000 | E30: 450000 | F30: =AVERAGE(C30:E30) -> 450000
A31: Agencia de marketing | B31: Comercial | C31: 214200 | D31: 214200 | E31: 214200 | F31: =AVERAGE(C31:E31) -> 214200
A32: Herramientas de IA | B32: Comercial | C32: 450000 | D32: 450000 | E32: 450000 | F32: =AVERAGE(C32:E32) -> 450000
A33: Software (Canva, Adobe, etc.) | B33: Comercial | C33: 60000 | D33: 60000 | E33: 60000 | F33: =AVERAGE(C33:E33) -> 60000
A34: Uber | B34: Comercial | C34: 80000 | D34: 80000 | E34: 80000 | F34: =AVERAGE(C34:E34) -> 80000
F35: =IF(COUNT(C35:E35)=0,0,AVERAGE(C35:E35)) -> 0 | G35: ← filas libres para agregar gastos
F36: =IF(COUNT(C36:E36)=0,0,AVERAGE(C36:E36)) -> 0
F37: =IF(COUNT(C37:E37)=0,0,AVERAGE(C37:E37)) -> 0
F38: =IF(COUNT(C38:E38)=0,0,AVERAGE(C38:E38)) -> 0
F39: =IF(COUNT(C39:E39)=0,0,AVERAGE(C39:E39)) -> 0
A41: TOTAL GASTOS DE FÁBRICA | C41: =SUMIF($B$5:$B$39,"Fábrica",C$5:C$39) -> 12421897 | D41: =SUMIF($B$5:$B$39,"Fábrica",D$5:D$39) -> 12421897 | E41: =SUMIF($B$5:$B$39,"Fábrica",E$5:E$39) -> 12421897 | F41: =SUMIF($B$5:$B$39,"Fábrica",F$5:F$39) -> 12421897
A42: TOTAL GASTOS COMERCIALES | C42: =SUMIF($B$5:$B$39,"Comercial",C$5:C$39) -> 4459061 | D42: =SUMIF($B$5:$B$39,"Comercial",D$5:D$39) -> 4459061 | E42: =SUMIF($B$5:$B$39,"Comercial",E$5:E$39) -> 4459061 | F42: =SUMIF($B$5:$B$39,"Comercial",F$5:F$39) -> 4459061
A43: TOTAL GASTOS FIJOS | C43: =C41+C42 -> 16880958 | D43: =D41+D42 -> 16880958 | E43: =E41+E42 -> 16880958 | F43: =F41+F42 -> 16880958
A45: VENTAS NETAS DEL MES ($) | C45: 32768213 | D45: 38874120 | E45: 33942186 | F45: =AVERAGE(C45:E45) -> 35194840 | G45: Fuente: hoja Proyectos_PMK (export Parrotfy), suma de Neto $ por mes. Septiembre no se usa: el export llega solo hasta el 5-sep.
A47: POR CONFIRMAR: el archivo original trae un solo mes de gastos; se repitió en los 3 meses. Reemplazar con el gasto real de cada mes.
A48: Fábrica = lo que cuesta tener la fábrica funcionando (arriendo, luz, todos los sueldos de producción). Comercial = vender (sueldos de ventas y marketing, publicidad). Puedes cambiar el grupo de cualquier línea.

Sheet Precios
A1: PRECIOS DE TELAS Y AVÍOS — neto, sin IVA
A2: Fuente: hoja 3_Insumos del Sistema de Costeo v2. Al cambiar un precio se actualizan todas las recetas. Cuando lo verifiques, cambia el estado a "Confirmado".
A4: Insumo | B4: Tipo | C4: Unidad | D4: Precio neto ($) | E4: Estado | F4: Nota
A5: MONTESIMONE TRAINING (fut pro) | B5: Tela | C5: kg | D5: 3531 | E5: Por confirmar
A6: LONDRES BLANCO | B6: Tela | C6: kg | D6: 5600 | E6: Por confirmar
A7: CIRE BLANCO | B7: Tela | C7: kg | D7: 5600 | E7: Por confirmar
A8: CIRE AZUL | B8: Tela | C8: kg | D8: 7500 | E8: Por confirmar
A9: MESH | B9: Tela | C9: kg | D9: 7700 | E9: Por confirmar
A10: FRANELA | B10: Tela | C10: kg | D10: 8000 | E10: Por confirmar
A11: PIQUE SELECCION | B11: Tela | C11: kg | D11: 7800 | E11: Por confirmar
A12: MICROFIBRA | B12: Tela | C12: kg | D12: 6900 | E12: Por confirmar
A13: CIRE MICROFIBRA AZUL REY | B13: Tela | C13: kg | D13: 7200 | E13: Por confirmar
A14: SCUBA | B14: Tela | C14: kg | D14: 7900 | E14: Por confirmar
A15: GLOBAL | B15: Tela | C15: kg | D15: 6800 | E15: Por confirmar
A16: PIQUE RUGBY | B16: Tela | C16: kg | D16: 5600 | E16: Por confirmar
... A33: JACQUARD BYTES | B33: Tela | C33: kg | D33: 4408 | E33: Por confirmar
A34: LYCRA | B34: Tela | C34: kg | E34: SIN PRECIO
A35: MALLA DEPORTIVA BLANCO | B35: Tela | C35: kg | D35: 6400 | E35: Por confirmar | F35: Estaba en avíos, pero se compra por kg como tela.
A36: NOVAK | B36: Tela | C36: kg | D36: 2975 | E36: Por confirmar | F36: Estaba en avíos, pero se compra por kg como tela.
A37: THERMAFLEECE | B37: Tela | C37: kg | D37: 8590 | E37: Por confirmar | F37: Estaba en avíos, pero se compra por kg como tela.
A38: Cuello | B38: Avío | C38: unidad | D38: 350 | E38: Por confirmar | F38: Precio marcado "estimado" en el archivo original.
A39: Puño | B39: Avío | C39: unidad | D39: 8500 | E39: Por confirmar | F39: $8.500 por unidad parece alto: ¿es por kg?
A40: Tapacuello | B40: Avío | C40: unidad | D40: 150 | E40: Por confirmar | F40: Precio marcado "estimado" en el archivo original.
A41: Hilo | B41: Avío | C41: unidad | D41: 80 | E41: Por confirmar | F41: Precio marcado "estimado" en el archivo original.
A42: Etiqueta | B42: Avío | C42: unidad | D42: 65 | E42: Por confirmar
A43: Cierre | B43: Avío | C43: unidad | D43: 600 | E43: Por confirmar | F43: Precio marcado "estimado" en el archivo original.
A44: Cordón | B44: Avío | C44: unidad | D44: 200 | E44: Por confirmar | F44: Precio marcado "estimado" en el archivo original.
A45: Elástico | B45: Avío | C45: unidad | D45: 5454 | E45: Por confirmar
A46: Forro | B46: Avío | C46: unidad | D46: 900 | E46: Por confirmar | F46: Precio marcado "estimado" en el archivo original.
A47: Cremallera bolsillo | B47: Avío | C47: unidad | D47: 400 | E47: Por confirmar | F47: Precio marcado "estimado" en el archivo original.

Sheet Confeccion
A1: CONFECCIÓN — valor que se paga al taller por prenda (neto, con planchado)
A2: Fuente: hoja Talleres_Confección del Sistema de Costeo v2. Agrega tipos nuevos al final.
A4: Tipo de prenda | B4: Valor con planchado ($) | C4: Sin planchado (ref.) | D4: Estado | E4: Nota
A5: Short De Futbol | B5: 1700 | C5: 1500 | D5: Por confirmar
A6: Camiseta De Futbol | B6: 2000 | C6: 1800 | D6: Por confirmar
A7: Camiseta De Futbol Retro | B7: 2200 | C7: 1900 | D7: Por confirmar
A8: Camiseta De Basket | B8: 1900 | C8: 1700 | D8: Por confirmar
A9: Camiseta De Basket Pro | B9: 2000 | C9: 1800 | D9: Por confirmar
A10: Short De Basket Pro | B10: 2200 | C10: 1700 | D10: Por confirmar
A11: Short De Basket | B11: 1900 | C11: 1700 | D11: Por confirmar
A12: Short De Basket Reversible | B12: 2400 | C12: 2000 | D12: Por confirmar
A13: Camiseta De Basket Reversible | B13: 2400 | C13: 2200 | D13: Por confirmar
A14: Camiseta De Rugby Básica | B14: 2200 | C14: 2000 | D14: Por confirmar
A15: Camiseta De Rugby Lycra | B15: 2600 | C15: 2300 | D15: Por confirmar
A16: Short De Rugby | B16: 2200 | C16: 2300 | D16: Por confirmar | E16: Ojo: sin planchado sale MÁS caro que con planchado. Revisar.
A17: Camiseta Futbol Molde 2026 (Raglan) | B17: 2300 | C17: 2000 | D17: Por confirmar
A18: Camiseta Futbol Fem Santiago Morning | B18: 2400 | C18: 2100 | D18: Por confirmar
A19: Short Fem Con Tajali | B19: 1800 | C19: 1700 | D19: Por confirmar
A20: Camiseta De Hockey | B20: 1800 | C20: 1600 | D20: Por confirmar
A21: Camiseta De Hockey Franja | B21: 2000 | C21: 1800 | D21: Por confirmar
A22: Calza-Falda | B22: 2600 | C22: 2300 | D22: Por confirmar
A23: Calza | B23: 1200 | C23: 1000 | D23: Por confirmar
A24: Pantalon Pitillo | B24: 3500 | C24: 3200 | D24: Por confirmar
A25: Poleron Entrenamiento Raglan | B25: 3200 | C25: 3000 | D25: Por confirmar
A26: Short De Salida | B26: 2200 | C26: 2000 | D26: Por confirmar
A27: Peto Entrenamiento | B27: 1000 | C27: 1000 | D27: Por confirmar
A28: Pantalon No Pitillo | B28: 3200 | C28: 3000 | D28: Por confirmar
... A50: Colett | B50: 500 | C50: 500 | D50: Por confirmar

Sheet Catalogo
A1: CATÁLOGO — qué productos ya tienen receta completa
A2: Todos los productos vendidos jun–sep 2026, de mayor a menor unidades (fuente: 2_Catálogo). Los kits se costean después sumando sus partes.
A3: ="Recetas completas: "&COUNTIF(F6:F200,"Completa")&" de "&COUNTA(A6:A200)&" productos · cubren el "&TEXT(SUMIF(F6:F200,"Completa",D6:D200)/SUM(D6:D200),"0%")&" de las unidades vendidas" -> Recetas completas: 6 de 132 productos · cubren el 7% de las unidades vendidas
A5: Código | B5: Producto | C5: Tipo | D5: Unidades vendidas | E5: Precio real prom. ($) | F5: Estado receta
A6: Código Histórico | B6: Producto | C6: Tipo | D6: Unidades | E6: Precio Real Prom. | F6: =IF(COUNTIF(Recetas!$A$6:$A$250,A6)=0,IF(C6="KIT/DÚO","Kit (después)","No está"),IF(COUNTIFS(Recetas!$A$6:$A$250,A6,Recetas!$S$6:$S$250,">0")>0,"Completa","Faltan datos")) -> No está
A7: DUODIAFUTB | B7: Dúo Pack Diamante Fútbol | C7: KIT/DÚO | D7: 496 | E7: 26379 | F7: =IF(COUNTIF(Recetas!$A$6:$A$250,A7)=0,IF(C7="KIT/DÚO","Kit (después)","No está"),IF(COUNTIFS(Recetas!$A$6:$A$250,A7,Recetas!$S$6:$S$250,">0")>0,"Completa","Faltan datos")) -> Kit (después)
A8: ESCDTF10 | B8: Escudo en DTF10cm | C8: ADICIONAL | D8: 387 | E8: 2094 | F8: =IF(COUNTIF(Recetas!$A$6:$A$250,A8)=0,IF(C8="KIT/DÚO","Kit (después)","No está"),IF(COUNTIFS(Recetas!$A$6:$A$250,A8,Recetas!$S$6:$S$250,">0")>0,"Completa","Faltan datos")) -> No está
A9: KITOROFUTB | B9: Kit Oro Fútbol | C9: KIT/DÚO | D9: 214 | E9: 29580 | F9: =IF(COUNTIF(Recetas!$A$6:$A$250,A9)=0,IF(C9="KIT/DÚO","Kit (después)","No está"),IF(COUNTIFS(Recetas!$A$6:$A$250,A9,Recetas!$S$6:$S$250,">0")>0,"Completa","Faltan datos")) -> Kit (después)
A10: ESCTEX10 | B10: Escudo Texturizado10cm | C10: ADICIONAL | D10: 214 | E10: 2941 | F10: =IF(COUNTIF(Recetas!$A$6:$A$250,A10)=0,IF(C10="KIT/DÚO","Kit (después)","No está"),IF(COUNTIFS(Recetas!$A$6:$A$250,A10,Recetas!$S$6:$S$250,">0")>0,"Completa","Faltan datos")) -> No está
A11: MEDPROPERCP | B11: Medias Pro Personalizadas PMK | C11: EXTERNO/REVENTA | D11: 209 | E11: 9734 | F11: =IF(COUNTIF(Recetas!$A$6:$A$250,A11)=0,IF(C11="KIT/DÚO","Kit (después)","No está"),IF(COUNTIFS(Recetas!$A$6:$A$250,A11,Recetas!$S$6:$S$250,">0")>0,"Completa","Faltan datos")) -> No está
A12: ESC-PRO-10CM | B12: ESCUDO PRO 10CM | C12: ADICIONAL | D12: 207 | E12: 2941 | F12: =IF(COUNTIF(Recetas!$A$6:$A$250,A12)=0,IF(C12="KIT/DÚO","Kit (después)","No está"),IF(COUNTIFS(Recetas!$A$6:$A$250,A12,Recetas!$S$6:$S$250,">0")>0,"Completa","Faltan datos")) -> No está
A13: FUTCSUBMC | B13: Camiseta Fútbol Playmaker, m/c | C13: JUEGO/COMPETENCIA | D13: 198 | E13: 15994 | F13: =IF(COUNTIF(Recetas!$A$6:$A$250,A13)=0,IF(C13="KIT/DÚO","Kit (después)","No está"),IF(COUNTIFS(Recetas!$A$6:$A$250,A13,Recetas!$S$6:$S$250,">0")>0,"Completa","Faltan datos")) -> Faltan datos
A14: FUTCSUBREDMC | B14: Camiseta Fútbol Playmaker Cuello Redondo m/c | C14: JUEGO/COMPETENCIA | D14: 190 | E14: 16073 | F14: =IF(COUNTIF(Recetas!$A$6:$A$250,A14)=0,IF(C14="KIT/DÚO","Kit (después)","No está"),IF(COUNTIFS(Recetas!$A$6:$A$250,A14,Recetas!$S$6:$S$250,">0")>0,"Completa","Faltan datos")) -> Faltan datos
A15: EXT-CUE-PIQ | B15: EXTRA CUELLO PIQUÉ | C15: ADICIONAL | D15: 161 | E15: 2521 | F15: =IF(COUNTIF(Recetas!$A$6:$A$250,A15)=0,IF(C15="KIT/DÚO","Kit (después)","No está"),IF(COUNTIFS(Recetas!$A$6:$A$250,A15,Recetas!$S$6:$S$250,">0")>0,"Completa","Faltan datos")) -> No está
A16: FUTCSUBPROREDMC | B16: Camiseta Fútbol Pro Playmaker Cuello Redondo m/c | C16: JUEGO/COMPETENCIA | D16: 160 | E16: 18403 | F16: =IF(COUNTIF(Recetas!$A$6:$A$250,A16)=0,IF(C16="KIT/DÚO","Kit (después)","No está"),IF(COUNTIFS(Recetas!$A$6:$A$250,A16,Recetas!$S$6:$S$250,">0")>0,"Completa","Faltan datos")) -> Completa
A17: KITDIAFUTB | B17: Kit Diamante Fútbol | C17: KIT/DÚO | D17: 148 | E17: 38898 | F17: =IF(COUNTIF(Recetas!$A$6:$A$250,A17)=0,IF(C17="KIT/DÚO","Kit (después)","No está"),IF(COUNTIFS(Recetas!$A$6:$A$250,A17,Recetas!$S$6:$S$250,">0")>0,"Completa","Faltan datos")) -> Kit (después)
A18: VOLMASC-CSUB-V-MC | B18: Camiseta Voley fem Playmaker, V m/c | C18: JUEGO/COMPETENCIA | D18: 139 | E18: 17563 | F18: =IF(COUNTIF(Recetas!$A$6:$A$250,A18)=0,IF(C18="KIT/DÚO","Kit (después)","No está"),IF(COUNTIFS(Recetas!$A$6:$A$250,A18,Recetas!$S$6:$S$250,">0")>0,"Completa","Faltan datos")) -> Faltan datos
... A114: VOLFEMCSUBPOL | B114: Camiseta Voley fem Playmaker, Polo | C114: JUEGO/COMPETENCIA | D114: 9 | E114: 17143 | F114: =IF(COUNTIF(Recetas!$A$6:$A$250,A114)=0,IF(C114="KIT/DÚO","Kit (después)","No está"),IF(COUNTIFS(Recetas!$A$6:$A$250,A114,Recetas!$S$6:$S$250,">0")>0,"Completa","Faltan datos")) -> Faltan datos
A115: REGBOLSUBPMK | B115: Bolso Sublimado Personalizado PMK de Regalo | C115: EXTERNO/REVENTA | D115: 8 | F115: =IF(COUNTIF(Recetas!$A$6:$A$250,A115)=0,IF(C115="KIT/DÚO","Kit (después)","No está"),IF(COUNTIFS(Recetas!$A$6:$A$250,A115,Recetas!$S$6:$S$250,">0")>0,"Completa","Faltan datos")) -> No está
A116: EXTTALESP | B116: EXTRA TALLA ESPECIAL | C116: ADICIONAL | D116: 8 | E116: 1260 | F116: =IF(COUNTIF(Recetas!$A$6:$A$250,A116)=0,IF(C116="KIT/DÚO","Kit (después)","No está"),IF(COUNTIFS(Recetas!$A$6:$A$250,A116,Recetas!$S$6:$S$250,">0")>0,"Completa","Faltan datos")) -> No está
A117: POLENTSUB | B117: POLERON DE ENTRENAMIENTO SUBLIMADO MEDIO CIERRE | C117: SALIDA/PRESENTACIÓN | D117: 6 | E117: 32731 | F117: =IF(COUNTIF(Recetas!$A$6:$A$250,A117)=0,IF(C117="KIT/DÚO","Kit (después)","No está"),IF(COUNTIFS(Recetas!$A$6:$A$250,A117,Recetas!$S$6:$S$250,">0")>0,"Completa","Faltan datos")) -> Faltan datos
A118: POL-CSUB-V-MC | B118: Polera Playmaker, V m/c | C118: JUEGO/COMPETENCIA | D118: 6 | E118: 16723 | F118: =IF(COUNTIF(Recetas!$A$6:$A$250,A118)=0,IF(C118="KIT/DÚO","Kit (después)","No está"),IF(COUNTIFS(Recetas!$A$6:$A$250,A118,Recetas!$S$6:$S$250,">0")>0,"Completa","Faltan datos")) -> Faltan datos
A119: RUGCSUBENTMC | B119: Camiseta de entrenamiento Rugby,m/c | C119: JUEGO/COMPETENCIA | D119: 5 | E119: 15882 | F119: =IF(COUNTIF(Recetas!$A$6:$A$250,A119)=0,IF(C119="KIT/DÚO","Kit (después)","No está"),IF(COUNTIFS(Recetas!$A$6:$A$250,A119,Recetas!$S$6:$S$250,">0")>0,"Completa","Faltan datos")) -> Faltan datos
A120: DESP | B120: DESPACHO | C120: JUEGO/COMPETENCIA | D120: 5 | E120: 13622 | F120: =IF(COUNTIF(Recetas!$A$6:$A$250,A120)=0,IF(C120="KIT/DÚO","Kit (después)","No está"),IF(COUNTIFS(Recetas!$A$6:$A$250,A120,Recetas!$S$6:$S$250,">0")>0,"Completa","Faltan datos")) -> No está
A121: BALFUTBA | B121: BALON DE FUTBOL | C121: EXTERNO/REVENTA | D121: 5 | E121: 29412 | F121: =IF(COUNTIF(Recetas!$A$6:$A$250,A121)=0,IF(C121="KIT/DÚO","Kit (después)","No está"),IF(COUNTIFS(Recetas!$A$6:$A$250,A121,Recetas!$S$6:$S$250,">0")>0,"Completa","Faltan datos")) -> No está
A122: MDCALCORPMK | B122: Calza corta fem Playmaker | C122: JUEGO/COMPETENCIA | D122: 4 | E122: 12689 | F122: =IF(COUNTIF(Recetas!$A$6:$A$250,A122)=0,IF(C122="KIT/DÚO","Kit (después)","No está"),IF(COUNTIFS(Recetas!$A$6:$A$250,A122,Recetas!$S$6:$S$250,">0")>0,"Completa","Faltan datos")) -> Faltan datos
A123: SAL-SHO-LIS | B123: Short Salida con bolsillos | C123: SALIDA/PRESENTACIÓN | D123: 4 | E123: 13445 | F123: =IF(COUNTIF(Recetas!$A$6:$A$250,A123)=0,IF(C123="KIT/DÚO","Kit (después)","No está"),IF(COUNTIFS(Recetas!$A$6:$A$250,A123,Recetas!$S$6:$S$250,">0")>0,"Completa","Faltan datos")) -> Faltan datos
A124: ENT-POL-MANSUBL | B124: POLERON DE ENTRENAMIENTO MANGAS SUBLIMADAS MASC | C124: SALIDA/PRESENTACIÓN | D124: 4 | E124: 30168 | F124: =IF(COUNTIF(Recetas!$A$6:$A$250,A124)=0,IF(C124="KIT/DÚO","Kit (después)","No está"),IF(COUNTIFS(Recetas!$A$6:$A$250,A124,Recetas!$S$6:$S$250,">0")>0,"Completa","Faltan datos")) -> Faltan datos
A125: BOLSUB | B125: BOLSO SUBLIMADO PERSONALIZADO | C125: EXTERNO/REVENTA | D125: 3 | E125: 21008 | F125: =IF(COUNTIF(Recetas!$A$6:$A$250,A125)=0,IF(C125="KIT/DÚO","Kit (después)","No está"),IF(COUNTIFS(Recetas!$A$6:$A$250,A125,Recetas!$S$6:$S$250,">0")>0,"Completa","Faltan datos")) -> No está
A126: VOLMASC-CSUB-V-CER | B126: Camiseta Voley masc Playmaker, V m/cero | C126: JUEGO/COMPETENCIA | D126: 3 | E126: 16723 | F126: =IF(COUNTIF(Recetas!$A$6:$A$250,A126)=0,IF(C126="KIT/DÚO","Kit (después)","No está"),IF(COUNTIFS(Recetas!$A$6:$A$250,A126,Recetas!$S$6:$S$250,">0")>0,"Completa","Faltan datos")) -> Faltan datos
A127: SAL-POL-MGSUB | B127: Polerón Entrenamiento liso con mangas Sublim | C127: SALIDA/PRESENTACIÓN | D127: 2 | E127: 27647 | F127: =IF(COUNTIF(Recetas!$A$6:$A$250,A127)=0,IF(C127="KIT/DÚO","Kit (después)","No está"),IF(COUNTIFS(Recetas!$A$6:$A$250,A127,Recetas!$S$6:$S$250,">0")>0,"Completa","Faltan datos")) -> Faltan datos
... A131: EXTML | B131: Exrta Manga Larga | C131: JUEGO/COMPETENCIA | D131: 2 | E131: 1681 | F131: =IF(COUNTIF(Recetas!$A$6:$A$250,A131)=0,IF(C131="KIT/DÚO","Kit (después)","No está"),IF(COUNTIFS(Recetas!$A$6:$A$250,A131,Recetas!$S$6:$S$250,">0")>0,"Completa","Faltan datos")) -> No está
A132: LZO2REG | B132: Lienzo 1.5x2mts Regalo | C132: JUEGO/COMPETENCIA | D132: 1 | F132: =IF(COUNTIF(Recetas!$A$6:$A$250,A132)=0,IF(C132="KIT/DÚO","Kit (después)","No está"),IF(COUNTIFS(Recetas!$A$6:$A$250,A132,Recetas!$S$6:$S$250,">0")>0,"Completa","Faltan datos")) -> No está
A133: VOLMASC-CSUBPRO-V-MC | B133: Camiseta Voley masc Pro Playmaker, V m/c | C133: JUEGO/COMPETENCIA | D133: 1 | E133: 19244 | F133: =IF(COUNTIF(Recetas!$A$6:$A$250,A133)=0,IF(C133="KIT/DÚO","Kit (después)","No está"),IF(COUNTIFS(Recetas!$A$6:$A$250,A133,Recetas!$S$6:$S$250,">0")>0,"Completa","Faltan datos")) -> Faltan datos
A134: RUG-CSUB-POL | B134: Camiseta Rugby Playmaker, Polo | C134: JUEGO/COMPETENCIA | D134: 1 | E134: 20084 | F134: =IF(COUNTIF(Recetas!$A$6:$A$250,A134)=0,IF(C134="KIT/DÚO","Kit (después)","No está"),IF(COUNTIFS(Recetas!$A$6:$A$250,A134,Recetas!$S$6:$S$250,">0")>0,"Completa","Faltan datos")) -> Faltan datos
A135: LZO-2 | B135: Lienzo 1.5x2 | C135: JUEGO/COMPETENCIA | D135: 1 | E135: 21765 | F135: =IF(COUNTIF(Recetas!$A$6:$A$250,A135)=0,IF(C135="KIT/DÚO","Kit (después)","No está"),IF(COUNTIFS(Recetas!$A$6:$A$250,A135,Recetas!$S$6:$S$250,">0")>0,"Completa","Faltan datos")) -> Faltan datos
A136: FUTJINSUB | B136: Jineta de Capitán Subl | C136: JUEGO/COMPETENCIA | D136: 1 | E136: 11681 | F136: =IF(COUNTIF(Recetas!$A$6:$A$250,A136)=0,IF(C136="KIT/DÚO","Kit (después)","No está"),IF(COUNTIFS(Recetas!$A$6:$A$250,A136,Recetas!$S$6:$S$250,">0")>0,"Completa","Faltan datos")) -> Faltan datos
A137: SAL-POL-ALG-LIS | B137: POLERÓN ALGODÓN CON CAPUCHA PMK | C137: SALIDA/PRESENTACIÓN | D137: 1 | E137: 21765 | F137: =IF(COUNTIF(Recetas!$A$6:$A$250,A137)=0,IF(C137="KIT/DÚO","Kit (después)","No está"),IF(COUNTIFS(Recetas!$A$6:$A$250,A137,Recetas!$S$6:$S$250,">0")>0,"Completa","Faltan datos")) -> Faltan datos
