Workbook

Sheet Como_usar
A1: RECETAS DE COSTO — PLAYMAKER (v5: consumos por molde, costo por tela y resultado mensual)
A2: La receta de un molde guarda solo CONSUMOS. El costo sale al elegir la tela de cada producto. Todo dato dice "Por confirmar" hasta que lo valides.
A4: LA IDEA
B5: Un mismo molde se puede producir en distintas telas: los CONSUMOS son los mismos (metros de tela, metros impresos, confección, avíos), pero el COSTO cambia según la tela.
B6: Por eso el consumo se mide en METROS (no en kg): los mismos metros pesan distinto en cada tela. Cada tela tiene su rendimiento (metros por kg) y de ahí sale su $ por metro.
A7: LAS HOJAS
B8: Recetas — una por molde del catálogo (54) + prendas sin molde. SOLO CONSUMOS. Si tu ficha de corte está en kg, escribe los kg y la tela con que se midió: se convierte solo a metros.
B9: Productos — lo que vendes: eliges el molde, la tela principal y la tela 2 (si lleva). Aquí se calcula el costo, la ganancia, el precio mínimo y el semáforo.
B10: Resultado_mensual — ventas, margen de contribución, gastos fijos, reprocesos, ganancia y punto de equilibrio de cada mes. La hoja para saber si el negocio está ganando.
B11: Precios — precio por kg y RENDIMIENTO (metros por kg) de cada tela → $ por metro. Avíos por unidad.
B12: Confeccion — valor del taller por tipo de prenda. Parametros / Gastos_Ventas — recargo de gastos fijos y meta. Catalogo — cobertura.
A13: CÓMO SACAR EL RENDIMIENTO DE UNA TELA (metros por kg)
B14: Toma un rollo: metros del rollo ÷ kg del rollo. Ej: rollo de 25 kg con 127 metros → 127 ÷ 25 = 5,08 m/kg. Muchas veces viene en la ficha del proveedor.
B15: Ojo: los metros por prenda se miden con el ancho de tela habitual. Si una tela es mucho más angosta o ancha, la tizada cambia: en ese caso conviene una receta aparte.
A16: CÓMO SACAR EL CONSUMO DE UN MOLDE
B17: De la ficha de corte: metros (o kg) de tela usados ÷ prendas cortadas. Si mides en metros, escríbelo en "Metros por prenda (directo)" y tiene prioridad sobre los kg.
A18: PENDIENTES QUE AFECTAN LOS RESULTADOS
B19: ="• Papel y tinta: "&IF(Parametros!$B$27=0,"SIN DATO → las prendas sublimadas salen más baratas de lo real.","ingresado ("&TEXT(Parametros!$B$27,"$#,##0")&" por metro).") -> • Papel y tinta: SIN DATO → las prendas sublimadas salen más baratas de lo real.
B20: ="• Telas con rendimiento cargado: "&COUNT(Precios!E5:E120)&" de "&COUNTIF(Precios!B5:B120,"Tela")&". Sin rendimiento, una tela no tiene $ por metro." -> • Telas con rendimiento cargado: 4 de 33. Sin rendimiento, una tela no tiene $ por metro.
B21: ="• Recetas (moldes) listas: "&COUNTIF(Recetas!T5:T84,"Lista")&" de "&COUNTA(Recetas!A5:A84) -> • Recetas (moldes) listas: 1 de 59
B22: ="• Productos con costo completo: "&COUNTIF(Catalogo!F6:F200,"Completa")&" · con datos faltantes: "&COUNTIF(Catalogo!F6:F200,"Faltan datos") -> • Productos con costo completo: 1 · con datos faltantes: 73
B23: • Gastos: el archivo original trae un solo mes; se repitió en los 3 meses. Reemplazar con el gasto real.

Sheet Resultado_mensual
A1: RESULTADO MENSUAL — ¿el negocio está ganando?
A2: Ventas − costo variable = margen de contribución. Margen − gastos fijos − reprocesos = ganancia del mes. Llena las celdas azules de cada mes.
A4: Concepto | B4: Jun-2026 | C4: Jul-2026 | D4: Ago-2026 | E4: Sep-2026 | F4: Oct-2026 | G4: Nov-2026 | H4: Dic-2026 | I4: Promedio (meses con ventas) | J4: De dónde sale
A5: Ventas netas ($) | B5: 32768213 | C5: 38874120 | D5: 33942186 | I5: =IFERROR(AVERAGEIF(B5:H5,">0",B5:H5),"") -> 35194840 | J5: Export de Parrotfy (Neto $). Septiembre: completar (el export llegaba solo hasta el día 5).
A6: Unidades vendidas | B6: 2176 | C6: 2037 | D6: 2034 | I6: =IFERROR(AVERAGEIF(B5:H5,">0",B6:H6),"") -> 2082.3333 | J6: Opcional. Jun–ago: líneas del export (incluye adicionales como escudos y cuellos).
A7: Costo variable REAL del mes ($) — opcional | I7: =IFERROR(AVERAGEIF(B5:H5,">0",B7:H7),"") | J7: Si sabes lo gastado en tela, papel, tinta, talleres y avíos del mes, escríbelo. Si no, se estima con el % de abajo.
A8: Costo variable usado ($) | B8: =IF(ISNUMBER(B7),B7,IF(AND(ISNUMBER(B5),ISNUMBER($B$24)),B5*$B$24,"")) | C8: =IF(ISNUMBER(C7),C7,IF(AND(ISNUMBER(C5),ISNUMBER($B$24)),C5*$B$24,"")) | D8: =IF(ISNUMBER(D7),D7,IF(AND(ISNUMBER(D5),ISNUMBER($B$24)),D5*$B$24,"")) | E8: =IF(ISNUMBER(E7),E7,IF(AND(ISNUMBER(E5),ISNUMBER($B$24)),E5*$B$24,"")) | F8: =IF(ISNUMBER(F7),F7,IF(AND(ISNUMBER(F5),ISNUMBER($B$24)),F5*$B$24,"")) | G8: =IF(ISNUMBER(G7),G7,IF(AND(ISNUMBER(G5),ISNUMBER($B$24)),G5*$B$24,"")) | H8: =IF(ISNUMBER(H7),H7,IF(AND(ISNUMBER(H5),ISNUMBER($B$24)),H5*$B$24,"")) | I8: =IFERROR(AVERAGEIF(B5:H5,">0",B8:H8),"") | J8: Real si lo escribiste; si no, ventas × costo variable promedio (fila 24). Vacío = todavía no hay un costo variable confiable.
A9: MARGEN DE CONTRIBUCIÓN ($) | B9: =IF(AND(ISNUMBER(B5),ISNUMBER(B8)),B5-B8,"") | C9: =IF(AND(ISNUMBER(C5),ISNUMBER(C8)),C5-C8,"") | D9: =IF(AND(ISNUMBER(D5),ISNUMBER(D8)),D5-D8,"") | E9: =IF(AND(ISNUMBER(E5),ISNUMBER(E8)),E5-E8,"") | F9: =IF(AND(ISNUMBER(F5),ISNUMBER(F8)),F5-F8,"") | G9: =IF(AND(ISNUMBER(G5),ISNUMBER(G8)),G5-G8,"") | H9: =IF(AND(ISNUMBER(H5),ISNUMBER(H8)),H5-H8,"") | I9: =IFERROR(AVERAGEIF(B5:H5,">0",B9:H9),"") | J9: Lo que dejan las ventas para pagar los gastos fijos.
A10: Margen de contribución (%) | B10: =IF(AND(N(B5)>0,ISNUMBER(B9)),B9/B5,"") | C10: =IF(AND(N(C5)>0,ISNUMBER(C9)),C9/C5,"") | D10: =IF(AND(N(D5)>0,ISNUMBER(D9)),D9/D5,"") | E10: =IF(AND(N(E5)>0,ISNUMBER(E9)),E9/E5,"") | F10: =IF(AND(N(F5)>0,ISNUMBER(F9)),F9/F5,"") | G10: =IF(AND(N(G5)>0,ISNUMBER(G9)),G9/G5,"") | H10: =IF(AND(N(H5)>0,ISNUMBER(H9)),H9/H5,"") | I10: =IFERROR(AVERAGEIF(B5:H5,">0",B10:H10),"")
A11: Gastos fijos del mes ($) | B11: 16880958 | C11: 16880958 | D11: 16880958 | I11: =IFERROR(AVERAGEIF(B5:H5,">0",B11:H11),"") -> 16880958 | J11: Jun–ago: hoja Gastos_Ventas (un solo mes repetido: reemplazar con el real). Desde septiembre: escribir el del mes.
A12: Reprocesos del mes ($) | B12: 1288500 | C12: 1723950 | D12: 1231200 | E12: 2304450 | I12: =IFERROR(AVERAGEIF(B5:H5,">0",B12:H12),"") -> 1414550 | J12: PMK_Maestro_2026, hoja Resumen_Mensual (costo estimado de reprocesos).
A13: Reprocesos (% de las ventas) | B13: =IF(AND(N(B5)>0,ISNUMBER(B12)),B12/B5,"") -> 0.039321644 | C13: =IF(AND(N(C5)>0,ISNUMBER(C12)),C12/C5,"") -> 0.044346985 | D13: =IF(AND(N(D5)>0,ISNUMBER(D12)),D12/D5,"") -> 0.036273444 | E13: =IF(AND(N(E5)>0,ISNUMBER(E12)),E12/E5,"") | F13: =IF(AND(N(F5)>0,ISNUMBER(F12)),F12/F5,"") | G13: =IF(AND(N(G5)>0,ISNUMBER(G12)),G12/G5,"") | H13: =IF(AND(N(H5)>0,ISNUMBER(H12)),H12/H5,"") | I13: =IFERROR(AVERAGEIF(B5:H5,">0",B13:H13),"") -> 0.039980691 | J13: Plata que se pierde por rehacer. Meta sugerida: bajo 2%.
A14: GANANCIA DEL MES ($) | B14: =IF(AND(ISNUMBER(B9),ISNUMBER(B11)),B9-B11-N(B12),"") | C14: =IF(AND(ISNUMBER(C9),ISNUMBER(C11)),C9-C11-N(C12),"") | D14: =IF(AND(ISNUMBER(D9),ISNUMBER(D11)),D9-D11-N(D12),"") | E14: =IF(AND(ISNUMBER(E9),ISNUMBER(E11)),E9-E11-N(E12),"") | F14: =IF(AND(ISNUMBER(F9),ISNUMBER(F11)),F9-F11-N(F12),"") | G14: =IF(AND(ISNUMBER(G9),ISNUMBER(G11)),G9-G11-N(G12),"") | H14: =IF(AND(ISNUMBER(H9),ISNUMBER(H11)),H9-H11-N(H12),"") | I14: =IFERROR(AVERAGEIF(B5:H5,">0",B14:H14),"") | J14: Margen de contribución − gastos fijos − reprocesos.
A15: Ganancia (% de las ventas) | B15: =IF(AND(N(B5)>0,ISNUMBER(B14)),B14/B5,"") | C15: =IF(AND(N(C5)>0,ISNUMBER(C14)),C14/C5,"") | D15: =IF(AND(N(D5)>0,ISNUMBER(D14)),D14/D5,"") | E15: =IF(AND(N(E5)>0,ISNUMBER(E14)),E14/E5,"") | F15: =IF(AND(N(F5)>0,ISNUMBER(F14)),F14/F5,"") | G15: =IF(AND(N(G5)>0,ISNUMBER(G14)),G14/G5,"") | H15: =IF(AND(N(H5)>0,ISNUMBER(H14)),H14/H5,"") | I15: =IFERROR(AVERAGEIF(B5:H5,">0",B15:H15),"")
A16: PUNTO DE EQUILIBRIO ($ de venta) | B16: =IF(AND(ISNUMBER(B11),ISNUMBER(B10)),IF(B10>0,(B11+N(B12))/B10,""),"") | C16: =IF(AND(ISNUMBER(C11),ISNUMBER(C10)),IF(C10>0,(C11+N(C12))/C10,""),"") | D16: =IF(AND(ISNUMBER(D11),ISNUMBER(D10)),IF(D10>0,(D11+N(D12))/D10,""),"") | E16: =IF(AND(ISNUMBER(E11),ISNUMBER(E10)),IF(E10>0,(E11+N(E12))/E10,""),"") | F16: =IF(AND(ISNUMBER(F11),ISNUMBER(F10)),IF(F10>0,(F11+N(F12))/F10,""),"") | G16: =IF(AND(ISNUMBER(G11),ISNUMBER(G10)),IF(G10>0,(G11+N(G12))/G10,""),"") | H16: =IF(AND(ISNUMBER(H11),ISNUMBER(H10)),IF(H10>0,(H11+N(H12))/H10,""),"") | I16: =IFERROR(AVERAGEIF(B5:H5,">0",B16:H16),"") | J16: Lo que hay que vender en el mes para no perder (gastos fijos + reprocesos ÷ margen %).
A17: Ventas sobre (o bajo) el equilibrio ($) | B17: =IF(AND(ISNUMBER(B5),ISNUMBER(B16)),B5-B16,"") | C17: =IF(AND(ISNUMBER(C5),ISNUMBER(C16)),C5-C16,"") | D17: =IF(AND(ISNUMBER(D5),ISNUMBER(D16)),D5-D16,"") | E17: =IF(AND(ISNUMBER(E5),ISNUMBER(E16)),E5-E16,"") | F17: =IF(AND(ISNUMBER(F5),ISNUMBER(F16)),F5-F16,"") | G17: =IF(AND(ISNUMBER(G5),ISNUMBER(G16)),G5-G16,"") | H17: =IF(AND(ISNUMBER(H5),ISNUMBER(H16)),H5-H16,"") | I17: =IFERROR(AVERAGEIF(B5:H5,">0",B17:H17),"") | J17: Positivo = vendiste más de lo necesario para cubrir todo.
A18: Resultado | B18: =IF(ISNUMBER(B14),IF(B14>=0,"GANA","PIERDE"),"") | C18: =IF(ISNUMBER(C14),IF(C14>=0,"GANA","PIERDE"),"") | D18: =IF(ISNUMBER(D14),IF(D14>=0,"GANA","PIERDE"),"") | E18: =IF(ISNUMBER(E14),IF(E14>=0,"GANA","PIERDE"),"") | F18: =IF(ISNUMBER(F14),IF(F14>=0,"GANA","PIERDE"),"") | G18: =IF(ISNUMBER(G14),IF(G14>=0,"GANA","PIERDE"),"") | H18: =IF(ISNUMBER(H14),IF(H14>=0,"GANA","PIERDE"),"") | I18: =IF(ISNUMBER(I14),IF(I14>=0,"GANA","PIERDE"),"")
A20: COSTO VARIABLE PROMEDIO (% de la venta) — se usa cuando no escribes el costo variable real del mes
A21: Calculado desde Productos | B21: =IFERROR(SUM(Productos!$Y$6:$Y$110)/SUM(Productos!$Z$6:$Z$110),"") -> 0.11161962 | C21: Costo de producción ÷ precio de venta, ponderado por unidades vendidas, de los productos que ya tienen costo completo.
A22: Unidades vendidas que cubre el cálculo | B22: =IFERROR(SUM(Productos!$AA$6:$AA$110)/SUM(Productos!$D$6:$D$110),0) -> 0.022011514 | C22: Mientras más alto, más confiable. Bajo 50% el promedio todavía no representa bien al negocio.
A23: Costo variable fijado a mano (opcional) | C23: Si tienes una estimación mejor (ej: 25%), escríbela aquí: tiene prioridad sobre el calculado.
A24: COSTO VARIABLE USADO (%) | B24: =IF(ISNUMBER(B23),B23,IF(AND(ISNUMBER(B21),B22>=0.5),B21,"")) | C24: =IF(ISNUMBER(B23),"Usando el valor fijado a mano.",IF(B22<0.5,"⚠ TODAVÍA NO HAY UN COSTO VARIABLE CONFIABLE: el cálculo cubre solo "&TEXT(B22,"0%")&" de las unidades vendidas (necesita 50%) y no incluye papel y tinta. Escribe el costo real del mes (fila 7) o una estimación (fila 23). Mientras, mira la tabla ¿Y si…? de abajo.","Calculado desde Productos (cubre "&TEXT(B22,"0%")&" de lo vendido).")) -> ⚠ TODAVÍA NO HAY UN COSTO VARIABLE CONFIABLE: el cálculo cubre solo 2% de las unidades vendidas (necesita 50%) y no incluye papel y tinta. Escribe el costo real del mes (fila 7) o una estimación (fila 23). Mientras, mira la tabla ¿Y si…? de abajo.
A26: ¿Y SI EL COSTO VARIABLE FUERA…? (mes promedio: ventas, gastos fijos y reprocesos de los meses con datos)
A27: Costo variable (% de la venta) | B27: Margen de contribución | C27: Ganancia del mes | D27: Ganancia (%) | E27: Punto de equilibrio
A28: 0.15 | B28: =IF(ISNUMBER($I$5),$I$5*(1-A28),"") -> 29915614 | C28: =IF(ISNUMBER($I$5),$I$5*(1-A28)-N($I$11)-N($I$12),"") -> 11620106 | D28: =IF(N($I$5)>0,C28/$I$5,"") -> 0.33016504 | E28: =IF(A28<1,(N($I$11)+N($I$12))/(1-A28),"") -> 21524127
A29: 0.2 | B29: =IF(ISNUMBER($I$5),$I$5*(1-A29),"") -> 28155872 | C29: =IF(ISNUMBER($I$5),$I$5*(1-A29)-N($I$11)-N($I$12),"") -> 9860363.7 | D29: =IF(N($I$5)>0,C29/$I$5,"") -> 0.28016504 | E29: =IF(A29<1,(N($I$11)+N($I$12))/(1-A29),"") -> 22869385
A30: 0.25 | B30: =IF(ISNUMBER($I$5),$I$5*(1-A30),"") -> 26396130 | C30: =IF(ISNUMBER($I$5),$I$5*(1-A30)-N($I$11)-N($I$12),"") -> 8100621.8 | D30: =IF(N($I$5)>0,C30/$I$5,"") -> 0.23016504 | E30: =IF(A30<1,(N($I$11)+N($I$12))/(1-A30),"") -> 24394011
A31: 0.3 | B31: =IF(ISNUMBER($I$5),$I$5*(1-A31),"") -> 24636388 | C31: =IF(ISNUMBER($I$5),$I$5*(1-A31)-N($I$11)-N($I$12),"") -> 6340879.8 | D31: =IF(N($I$5)>0,C31/$I$5,"") -> 0.18016504 | E31: =IF(A31<1,(N($I$11)+N($I$12))/(1-A31),"") -> 26136440
A32: 0.35 | B32: =IF(ISNUMBER($I$5),$I$5*(1-A32),"") -> 22876646 | C32: =IF(ISNUMBER($I$5),$I$5*(1-A32)-N($I$11)-N($I$12),"") -> 4581137.8 | D32: =IF(N($I$5)>0,C32/$I$5,"") -> 0.13016504 | E32: =IF(A32<1,(N($I$11)+N($I$12))/(1-A32),"") -> 28146935
A33: 0.4 | B33: =IF(ISNUMBER($I$5),$I$5*(1-A33),"") -> 21116904 | C33: =IF(ISNUMBER($I$5),$I$5*(1-A33)-N($I$11)-N($I$12),"") -> 2821395.8 | D33: =IF(N($I$5)>0,C33/$I$5,"") -> 0.080165042 | E33: =IF(A33<1,(N($I$11)+N($I$12))/(1-A33),"") -> 30492513
A34: 0.45 | B34: =IF(ISNUMBER($I$5),$I$5*(1-A34),"") -> 19357162 | C34: =IF(ISNUMBER($I$5),$I$5*(1-A34)-N($I$11)-N($I$12),"") -> 1061653.8 | D34: =IF(N($I$5)>0,C34/$I$5,"") -> 0.030165042 | E34: =IF(A34<1,(N($I$11)+N($I$12))/(1-A34),"") -> 33264560
A35: Puedes cambiar los % de la primera columna. Con las recetas completas (o el costo real del mes) sabrás en qué fila está el negocio.
A37: CÓMO LEER ESTA HOJA
A38: • MARGEN DE CONTRIBUCIÓN: lo que dejan las ventas después de pagar lo que se gasta por prenda (tela, papel, tinta, taller, avíos). Con él se pagan los gastos fijos.
A39: • PUNTO DE EQUILIBRIO: lo que necesitas vender en el mes para no perder. Si vendes más, el margen de lo que sobra es ganancia.
A40: • REPROCESOS: lo que cuesta rehacer prendas. Sale directo de la ganancia.
A41: • COSTO VARIABLE REAL DEL MES (fila 7): la forma más exacta es sumar las compras del mes de tela, papel, tinta y avíos, más lo pagado a los talleres de confección.
A42: • Para decidir un descuento: mientras el precio cubra el costo variable de la prenda y deje margen, el pedido ayuda a pagar los gastos fijos.

Sheet Productos
A1: PRODUCTOS — costo según el molde y la tela que elijas
A2: Cada producto toma los CONSUMOS de su molde (hoja Recetas) y los valoriza con la TELA que elijas aquí (precio por metro de la hoja Precios). Un mismo molde puede costar distinto según la tela.
A3: ="Recargo usado: "&TEXT(Parametros!$B$14,"0.0%")&" del precio (fábrica "&TEXT(Parametros!$B$12,"0.0%")&" + comercial "&TEXT(Parametros!$B$13,"0.0%")&") · Meta de ganancia: "&TEXT(Parametros!$B$18,"0%")&" · Impresión: "&IF(Parametros!$B$27=0,"SIN COSTO (pendiente)",TEXT(Parametros!$B$27,"$#,##0")&" por metro") -> Recargo usado: 48.0% del precio (fábrica 35.3% + comercial 12.7%) · Meta de ganancia: 10% · Impresión: SIN COSTO (pendiente)
A4: PRODUCTO | E4: LO ELIGES TÚ: molde, tela y precio | L4: COSTO DE PRODUCCIÓN ($ por prenda) | Q4: RESULTADO AL PRECIO ACTUAL
A5: Código | B5: Producto | C5: Tipo | D5: Unid. vendidas jun–sep | E5: Receta (molde) | F5: Tela principal | G5: Tela 2 (si el molde lleva) | H5: Extras ($ por prenda) | I5: Precio venta neto ($) | J5: Estado | K5: Notas | L5: $ Tela | M5: $ Papel y tinta | N5: $ Confección | O5: $ Avíos | P5: COSTO DE PRODUCCIÓN | Q5: Gastos de fábrica | R5: Gastos comerciales | S5: GANANCIA ($) | T5: GANANCIA (%) | U5: Precio mínimo (sin perder) | V5: Precio mínimo (con meta) | W5: Semáforo | X5: Qué falta | Y5: Aux: costo × unid. | Z5: Aux: venta × unid. | AA5: Aux: unid. con costo
A6: FUTCSUBMC | B6: Camiseta Fútbol Playmaker, m/c | C6: Juego | D6: 198 | E6: 02 · FUTHOMU01 | I6: 15994 | J6: Por confirmar | K6: Molde sugerido: fútbol masculino cuello redondo. Confirmar molde y elegir tela. | L6: =IF(OR(B6="",E6=""),"",IFERROR(INDEX(Recetas!$R$5:$R$84,MATCH($E6,Recetas!$A$5:$A$84,0))*IFERROR(INDEX(Precios!$F$5:$F$120,MATCH(F6,Precios!$A$5:$A$120,0)),"")+IF(N(INDEX(Recetas!$S$5:$S$84,MATCH($E6,Recetas!$A$5:$A$84,0)))=0,0,INDEX(Recetas!$S$5:$S$84,MATCH($E6,Recetas!$A$5:$A$84,0))*IFERROR(INDEX(Precios!$F$5:$F$120,MATCH(G6,Precios!$A$5:$A$120,0)),"")),"")) | M6: =IF(OR(B6="",E6=""),"",IFERROR(N(INDEX(Recetas!$L$5:$L$84,MATCH($E6,Recetas!$A$5:$A$84,0)))*Parametros!$B$27,"")) -> 0 | N6: =IF(OR(B6="",E6=""),"",IFERROR(INDEX(Confeccion!$B$5:$B$100,MATCH(INDEX(Recetas!$M$5:$M$84,MATCH($E6,Recetas!$A$5:$A$84,0)),Confeccion!$A$5:$A$100,0)),"")) -> 2000 | O6: =IF(OR(B6="",E6=""),"",IFERROR(N(INDEX(Recetas!$O$5:$O$84,MATCH($E6,Recetas!$A$5:$A$84,0)))*INDEX(Precios!$D$5:$D$120,MATCH(INDEX(Recetas!$N$5:$N$84,MATCH($E6,Recetas!$A$5:$A$84,0)),Precios!$A$5:$A$120,0)),0)) -> 0 | P6: =IF(OR(B6="",E6=""),"",IF(AND(IFERROR(INDEX(Recetas!$T$5:$T$84,MATCH($E6,Recetas!$A$5:$A$84,0))="Lista",FALSE()),ISNUMBER(L6),ISNUMBER(M6),ISNUMBER(N6),N(N6)>0),L6+M6+N6+N(O6)+N(H6),"")) | Q6: =IF(AND(ISNUMBER(P6),ISNUMBER(I6)),I6*Parametros!$B$12,"") | R6: =IF(AND(ISNUMBER(P6),ISNUMBER(I6)),I6*Parametros!$B$13,"") | S6: =IF(AND(ISNUMBER(P6),ISNUMBER(I6)),I6-P6-Q6-R6,"") | T6: =IF(AND(ISNUMBER(P6),ISNUMBER(I6)),S6/I6,"") | U6: =IF(OR(NOT(ISNUMBER(P6)),Parametros!$B$14>=1),"",P6/(1-Parametros!$B$14)) | V6: =IF(OR(NOT(ISNUMBER(P6)),Parametros!$B$14+Parametros!$B$18>=1),"",P6/(1-Parametros!$B$14-Parametros!$B$18)) | W6: =IF(B6="","",IF(E6="","SIN RECETA",IF(NOT(ISNUMBER(P6)),"FALTAN DATOS",IF(NOT(ISNUMBER(I6)),"FALTA PRECIO",IF(S6<0,"PIERDE",IF(T6<Parametros!$B$18,"BAJO META","OK")))))) -> FALTAN DATOS | X6: =IF(B6="","",IF(E6="","Elegir receta (molde). ",IF(ISNA(MATCH(E6,Recetas!$A$5:$A$84,0)),"La receta no existe. ",IF(IFERROR(INDEX(Recetas!$T$5:$T$84,MATCH($E6,Recetas!$A$5:$A$84,0))="Lista",FALSE()),"","Receta "&E6&": "&INDEX(Recetas!$T$5:$T$84,MATCH($E6,Recetas!$A$5:$A$84,0)))))&IF(F6="","Elegir tela. ",IF(IFERROR(INDEX(Precios!$F$5:$F$120,MATCH(F6,Precios!$A$5:$A$120,0)),"")="","Tela sin $/metro (falta rendimiento o precio). ",""))&IF(AND(E6<>"",N(IFERROR(INDEX(Recetas!$S$5:$S$84,MATCH($E6,Recetas!$A$5:$A$84,0)),0))>0,G6=""),"Elegir tela 2. ","")&IF(NOT(ISNUMBER(I6)),"Precio de venta.","")) -> Receta 02 · FUTHOMU01: Consumo de tela. Metros impresos. Elegir tela. | Y6: =IF(AND(ISNUMBER(P6),ISNUMBER(I6),ISNUMBER(D6)),P6*D6,0) -> 0 | Z6: =IF(AND(ISNUMBER(P6),ISNUMBER(I6),ISNUMBER(D6)),I6*D6,0) -> 0 | AA6: =IF(AND(ISNUMBER(P6),ISNUMBER(I6),ISNUMBER(D6)),D6,0) -> 0
A7: FUTCSUBREDMC | B7: Camiseta Fútbol Playmaker Cuello Redondo m/c | C7: Juego | D7: 190 | E7: 02 · FUTHOMU01 | I7: 16073 | J7: Por confirmar | K7: Molde sugerido. Elegir tela. | L7: =IF(OR(B7="",E7=""),"",IFERROR(INDEX(Recetas!$R$5:$R$84,MATCH($E7,Recetas!$A$5:$A$84,0))*IFERROR(INDEX(Precios!$F$5:$F$120,MATCH(F7,Precios!$A$5:$A$120,0)),"")+IF(N(INDEX(Recetas!$S$5:$S$84,MATCH($E7,Recetas!$A$5:$A$84,0)))=0,0,INDEX(Recetas!$S$5:$S$84,MATCH($E7,Recetas!$A$5:$A$84,0))*IFERROR(INDEX(Precios!$F$5:$F$120,MATCH(G7,Precios!$A$5:$A$120,0)),"")),"")) | M7: =IF(OR(B7="",E7=""),"",IFERROR(N(INDEX(Recetas!$L$5:$L$84,MATCH($E7,Recetas!$A$5:$A$84,0)))*Parametros!$B$27,"")) -> 0 | N7: =IF(OR(B7="",E7=""),"",IFERROR(INDEX(Confeccion!$B$5:$B$100,MATCH(INDEX(Recetas!$M$5:$M$84,MATCH($E7,Recetas!$A$5:$A$84,0)),Confeccion!$A$5:$A$100,0)),"")) -> 2000 | O7: =IF(OR(B7="",E7=""),"",IFERROR(N(INDEX(Recetas!$O$5:$O$84,MATCH($E7,Recetas!$A$5:$A$84,0)))*INDEX(Precios!$D$5:$D$120,MATCH(INDEX(Recetas!$N$5:$N$84,MATCH($E7,Recetas!$A$5:$A$84,0)),Precios!$A$5:$A$120,0)),0)) -> 0 | P7: =IF(OR(B7="",E7=""),"",IF(AND(IFERROR(INDEX(Recetas!$T$5:$T$84,MATCH($E7,Recetas!$A$5:$A$84,0))="Lista",FALSE()),ISNUMBER(L7),ISNUMBER(M7),ISNUMBER(N7),N(N7)>0),L7+M7+N7+N(O7)+N(H7),"")) | Q7: =IF(AND(ISNUMBER(P7),ISNUMBER(I7)),I7*Parametros!$B$12,"") | R7: =IF(AND(ISNUMBER(P7),ISNUMBER(I7)),I7*Parametros!$B$13,"") | S7: =IF(AND(ISNUMBER(P7),ISNUMBER(I7)),I7-P7-Q7-R7,"") | T7: =IF(AND(ISNUMBER(P7),ISNUMBER(I7)),S7/I7,"") | U7: =IF(OR(NOT(ISNUMBER(P7)),Parametros!$B$14>=1),"",P7/(1-Parametros!$B$14)) | V7: =IF(OR(NOT(ISNUMBER(P7)),Parametros!$B$14+Parametros!$B$18>=1),"",P7/(1-Parametros!$B$14-Parametros!$B$18)) | W7: =IF(B7="","",IF(E7="","SIN RECETA",IF(NOT(ISNUMBER(P7)),"FALTAN DATOS",IF(NOT(ISNUMBER(I7)),"FALTA PRECIO",IF(S7<0,"PIERDE",IF(T7<Parametros!$B$18,"BAJO META","OK")))))) -> FALTAN DATOS | X7: =IF(B7="","",IF(E7="","Elegir receta (molde). ",IF(ISNA(MATCH(E7,Recetas!$A$5:$A$84,0)),"La receta no existe. ",IF(IFERROR(INDEX(Recetas!$T$5:$T$84,MATCH($E7,Recetas!$A$5:$A$84,0))="Lista",FALSE()),"","Receta "&E7&": "&INDEX(Recetas!$T$5:$T$84,MATCH($E7,Recetas!$A$5:$A$84,0)))))&IF(F7="","Elegir tela. ",IF(IFERROR(INDEX(Precios!$F$5:$F$120,MATCH(F7,Precios!$A$5:$A$120,0)),"")="","Tela sin $/metro (falta rendimiento o precio). ",""))&IF(AND(E7<>"",N(IFERROR(INDEX(Recetas!$S$5:$S$84,MATCH($E7,Recetas!$A$5:$A$84,0)),0))>0,G7=""),"Elegir tela 2. ","")&IF(NOT(ISNUMBER(I7)),"Precio de venta.","")) -> Receta 02 · FUTHOMU01: Consumo de tela. Metros impresos. Elegir tela. | Y7: =IF(AND(ISNUMBER(P7),ISNUMBER(I7),ISNUMBER(D7)),P7*D7,0) -> 0 | Z7: =IF(AND(ISNUMBER(P7),ISNUMBER(I7),ISNUMBER(D7)),I7*D7,0) -> 0 | AA7: =IF(AND(ISNUMBER(P7),ISNUMBER(I7),ISNUMBER(D7)),D7,0) -> 0
A8: FUTCSUBPROREDMC | B8: Camiseta Fútbol Pro Playmaker Cuello Redondo m/c | C8: Juego | D8: 160 | E8: 14 · FUTHOMU01PRO | F8: MONTESIMONE TRAINING (fut pro) | G8: MESH | I8: 18403 | J8: Por confirmar | K8: Tela de la ficha OT 2547. | L8: =IF(OR(B8="",E8=""),"",IFERROR(INDEX(Recetas!$R$5:$R$84,MATCH($E8,Recetas!$A$5:$A$84,0))*IFERROR(INDEX(Precios!$F$5:$F$120,MATCH(F8,Precios!$A$5:$A$120,0)),"")+IF(N(INDEX(Recetas!$S$5:$S$84,MATCH($E8,Recetas!$A$5:$A$84,0)))=0,0,INDEX(Recetas!$S$5:$S$84,MATCH($E8,Recetas!$A$5:$A$84,0))*IFERROR(INDEX(Precios!$F$5:$F$120,MATCH(G8,Precios!$A$5:$A$120,0)),"")),"")) -> 423.72 | M8: =IF(OR(B8="",E8=""),"",IFERROR(N(INDEX(Recetas!$L$5:$L$84,MATCH($E8,Recetas!$A$5:$A$84,0)))*Parametros!$B$27,"")) -> 0 | N8: =IF(OR(B8="",E8=""),"",IFERROR(INDEX(Confeccion!$B$5:$B$100,MATCH(INDEX(Recetas!$M$5:$M$84,MATCH($E8,Recetas!$A$5:$A$84,0)),Confeccion!$A$5:$A$100,0)),"")) -> 2000 | O8: =IF(OR(B8="",E8=""),"",IFERROR(N(INDEX(Recetas!$O$5:$O$84,MATCH($E8,Recetas!$A$5:$A$84,0)))*INDEX(Precios!$D$5:$D$120,MATCH(INDEX(Recetas!$N$5:$N$84,MATCH($E8,Recetas!$A$5:$A$84,0)),Precios!$A$5:$A$120,0)),0)) -> 0 | P8: =IF(OR(B8="",E8=""),"",IF(AND(IFERROR(INDEX(Recetas!$T$5:$T$84,MATCH($E8,Recetas!$A$5:$A$84,0))="Lista",FALSE()),ISNUMBER(L8),ISNUMBER(M8),ISNUMBER(N8),N(N8)>0),L8+M8+N8+N(O8)+N(H8),"")) | Q8: =IF(AND(ISNUMBER(P8),ISNUMBER(I8)),I8*Parametros!$B$12,"") | R8: =IF(AND(ISNUMBER(P8),ISNUMBER(I8)),I8*Parametros!$B$13,"") | S8: =IF(AND(ISNUMBER(P8),ISNUMBER(I8)),I8-P8-Q8-R8,"") | T8: =IF(AND(ISNUMBER(P8),ISNUMBER(I8)),S8/I8,"") | U8: =IF(OR(NOT(ISNUMBER(P8)),Parametros!$B$14>=1),"",P8/(1-Parametros!$B$14)) | V8: =IF(OR(NOT(ISNUMBER(P8)),Parametros!$B$14+Parametros!$B$18>=1),"",P8/(1-Parametros!$B$14-Parametros!$B$18)) | W8: =IF(B8="","",IF(E8="","SIN RECETA",IF(NOT(ISNUMBER(P8)),"FALTAN DATOS",IF(NOT(ISNUMBER(I8)),"FALTA PRECIO",IF(S8<0,"PIERDE",IF(T8<Parametros!$B$18,"BAJO META","OK")))))) -> FALTAN DATOS | X8: =IF(B8="","",IF(E8="","Elegir receta (molde). ",IF(ISNA(MATCH(E8,Recetas!$A$5:$A$84,0)),"La receta no existe. ",IF(IFERROR(INDEX(Recetas!$T$5:$T$84,MATCH($E8,Recetas!$A$5:$A$84,0))="Lista",FALSE()),"","Receta "&E8&": "&INDEX(Recetas!$T$5:$T$84,MATCH($E8,Recetas!$A$5:$A$84,0)))))&IF(F8="","Elegir tela. ",IF(IFERROR(INDEX(Precios!$F$5:$F$120,MATCH(F8,Precios!$A$5:$A$120,0)),"")="","Tela sin $/metro (falta rendimiento o precio). ",""))&IF(AND(E8<>"",N(IFERROR(INDEX(Recetas!$S$5:$S$84,MATCH($E8,Recetas!$A$5:$A$84,0)),0))>0,G8=""),"Elegir tela 2. ","")&IF(NOT(ISNUMBER(I8)),"Precio de venta.","")) -> Receta 14 · FUTHOMU01PRO: Rendimiento de MESH (m/kg) en Precios. | Y8: =IF(AND(ISNUMBER(P8),ISNUMBER(I8),ISNUMBER(D8)),P8*D8,0) -> 0 | Z8: =IF(AND(ISNUMBER(P8),ISNUMBER(I8),ISNUMBER(D8)),I8*D8,0) -> 0 | AA8: =IF(AND(ISNUMBER(P8),ISNUMBER(I8),ISNUMBER(D8)),D8,0) -> 0
A9: VOLMASC-CSUB-V-MC | B9: Camiseta Voley fem Playmaker, V m/c | C9: Juego | D9: 139 | I9: 17563 | J9: Por confirmar | K9: Sin receta: elige el molde que usa (o crea su receta en "Recetas") y la tela. | L9: =IF(OR(B9="",E9=""),"",IFERROR(INDEX(Recetas!$R$5:$R$84,MATCH($E9,Recetas!$A$5:$A$84,0))*IFERROR(INDEX(Precios!$F$5:$F$120,MATCH(F9,Precios!$A$5:$A$120,0)),"")+IF(N(INDEX(Recetas!$S$5:$S$84,MATCH($E9,Recetas!$A$5:$A$84,0)))=0,0,INDEX(Recetas!$S$5:$S$84,MATCH($E9,Recetas!$A$5:$A$84,0))*IFERROR(INDEX(Precios!$F$5:$F$120,MATCH(G9,Precios!$A$5:$A$120,0)),"")),"")) | M9: =IF(OR(B9="",E9=""),"",IFERROR(N(INDEX(Recetas!$L$5:$L$84,MATCH($E9,Recetas!$A$5:$A$84,0)))*Parametros!$B$27,"")) | N9: =IF(OR(B9="",E9=""),"",IFERROR(INDEX(Confeccion!$B$5:$B$100,MATCH(INDEX(Recetas!$M$5:$M$84,MATCH($E9,Recetas!$A$5:$A$84,0)),Confeccion!$A$5:$A$100,0)),"")) | O9: =IF(OR(B9="",E9=""),"",IFERROR(N(INDEX(Recetas!$O$5:$O$84,MATCH($E9,Recetas!$A$5:$A$84,0)))*INDEX(Precios!$D$5:$D$120,MATCH(INDEX(Recetas!$N$5:$N$84,MATCH($E9,Recetas!$A$5:$A$84,0)),Precios!$A$5:$A$120,0)),0)) | P9: =IF(OR(B9="",E9=""),"",IF(AND(IFERROR(INDEX(Recetas!$T$5:$T$84,MATCH($E9,Recetas!$A$5:$A$84,0))="Lista",FALSE()),ISNUMBER(L9),ISNUMBER(M9),ISNUMBER(N9),N(N9)>0),L9+M9+N9+N(O9)+N(H9),"")) | Q9: =IF(AND(ISNUMBER(P9),ISNUMBER(I9)),I9*Parametros!$B$12,"") | R9: =IF(AND(ISNUMBER(P9),ISNUMBER(I9)),I9*Parametros!$B$13,"") | S9: =IF(AND(ISNUMBER(P9),ISNUMBER(I9)),I9-P9-Q9-R9,"") | T9: =IF(AND(ISNUMBER(P9),ISNUMBER(I9)),S9/I9,"") | U9: =IF(OR(NOT(ISNUMBER(P9)),Parametros!$B$14>=1),"",P9/(1-Parametros!$B$14)) | V9: =IF(OR(NOT(ISNUMBER(P9)),Parametros!$B$14+Parametros!$B$18>=1),"",P9/(1-Parametros!$B$14-Parametros!$B$18)) | W9: =IF(B9="","",IF(E9="","SIN RECETA",IF(NOT(ISNUMBER(P9)),"FALTAN DATOS",IF(NOT(ISNUMBER(I9)),"FALTA PRECIO",IF(S9<0,"PIERDE",IF(T9<Parametros!$B$18,"BAJO META","OK")))))) -> SIN RECETA | X9: =IF(B9="","",IF(E9="","Elegir receta (molde). ",IF(ISNA(MATCH(E9,Recetas!$A$5:$A$84,0)),"La receta no existe. ",IF(IFERROR(INDEX(Recetas!$T$5:$T$84,MATCH($E9,Recetas!$A$5:$A$84,0))="Lista",FALSE()),"","Receta "&E9&": "&INDEX(Recetas!$T$5:$T$84,MATCH($E9,Recetas!$A$5:$A$84,0)))))&IF(F9="","Elegir tela. ",IF(IFERROR(INDEX(Precios!$F$5:$F$120,MATCH(F9,Precios!$A$5:$A$120,0)),"")="","Tela sin $/metro (falta rendimiento o precio). ",""))&IF(AND(E9<>"",N(IFERROR(INDEX(Recetas!$S$5:$S$84,MATCH($E9,Recetas!$A$5:$A$84,0)),0))>0,G9=""),"Elegir tela 2. ","")&IF(NOT(ISNUMBER(I9)),"Precio de venta.","")) -> Elegir receta (molde). Elegir tela. | Y9: =IF(AND(ISNUMBER(P9),ISNUMBER(I9),ISNUMBER(D9)),P9*D9,0) -> 0 | Z9: =IF(AND(ISNUMBER(P9),ISNUMBER(I9),ISNUMBER(D9)),I9*D9,0) -> 0 | AA9: =IF(AND(ISNUMBER(P9),ISNUMBER(I9),ISNUMBER(D9)),D9,0) -> 0
A10: FUTCSUBPROMC | B10: Camiseta Fútbol Pro Playmaker, m/c | C10: Juego | D10: 109 | E10: 14 · FUTHOMU01PRO | F10: MONTESIMONE TRAINING (fut pro) | G10: MESH | I10: 18403 | J10: Por confirmar | K10: Molde Pro sugerido. Tela de la ficha OT 2547. | L10: =IF(OR(B10="",E10=""),"",IFERROR(INDEX(Recetas!$R$5:$R$84,MATCH($E10,Recetas!$A$5:$A$84,0))*IFERROR(INDEX(Precios!$F$5:$F$120,MATCH(F10,Precios!$A$5:$A$120,0)),"")+IF(N(INDEX(Recetas!$S$5:$S$84,MATCH($E10,Recetas!$A$5:$A$84,0)))=0,0,INDEX(Recetas!$S$5:$S$84,MATCH($E10,Recetas!$A$5:$A$84,0))*IFERROR(INDEX(Precios!$F$5:$F$120,MATCH(G10,Precios!$A$5:$A$120,0)),"")),"")) -> 423.72 | M10: =IF(OR(B10="",E10=""),"",IFERROR(N(INDEX(Recetas!$L$5:$L$84,MATCH($E10,Recetas!$A$5:$A$84,0)))*Parametros!$B$27,"")) -> 0 | N10: =IF(OR(B10="",E10=""),"",IFERROR(INDEX(Confeccion!$B$5:$B$100,MATCH(INDEX(Recetas!$M$5:$M$84,MATCH($E10,Recetas!$A$5:$A$84,0)),Confeccion!$A$5:$A$100,0)),"")) -> 2000 | O10: =IF(OR(B10="",E10=""),"",IFERROR(N(INDEX(Recetas!$O$5:$O$84,MATCH($E10,Recetas!$A$5:$A$84,0)))*INDEX(Precios!$D$5:$D$120,MATCH(INDEX(Recetas!$N$5:$N$84,MATCH($E10,Recetas!$A$5:$A$84,0)),Precios!$A$5:$A$120,0)),0)) -> 0 | P10: =IF(OR(B10="",E10=""),"",IF(AND(IFERROR(INDEX(Recetas!$T$5:$T$84,MATCH($E10,Recetas!$A$5:$A$84,0))="Lista",FALSE()),ISNUMBER(L10),ISNUMBER(M10),ISNUMBER(N10),N(N10)>0),L10+M10+N10+N(O10)+N(H10),"")) | Q10: =IF(AND(ISNUMBER(P10),ISNUMBER(I10)),I10*Parametros!$B$12,"") | R10: =IF(AND(ISNUMBER(P10),ISNUMBER(I10)),I10*Parametros!$B$13,"") | S10: =IF(AND(ISNUMBER(P10),ISNUMBER(I10)),I10-P10-Q10-R10,"") | T10: =IF(AND(ISNUMBER(P10),ISNUMBER(I10)),S10/I10,"") | U10: =IF(OR(NOT(ISNUMBER(P10)),Parametros!$B$14>=1),"",P10/(1-Parametros!$B$14)) | V10: =IF(OR(NOT(ISNUMBER(P10)),Parametros!$B$14+Parametros!$B$18>=1),"",P10/(1-Parametros!$B$14-Parametros!$B$18)) | W10: =IF(B10="","",IF(E10="","SIN RECETA",IF(NOT(ISNUMBER(P10)),"FALTAN DATOS",IF(NOT(ISNUMBER(I10)),"FALTA PRECIO",IF(S10<0,"PIERDE",IF(T10<Parametros!$B$18,"BAJO META","OK")))))) -> FALTAN DATOS | X10: =IF(B10="","",IF(E10="","Elegir receta (molde). ",IF(ISNA(MATCH(E10,Recetas!$A$5:$A$84,0)),"La receta no existe. ",IF(IFERROR(INDEX(Recetas!$T$5:$T$84,MATCH($E10,Recetas!$A$5:$A$84,0))="Lista",FALSE()),"","Receta "&E10&": "&INDEX(Recetas!$T$5:$T$84,MATCH($E10,Recetas!$A$5:$A$84,0)))))&IF(F10="","Elegir tela. ",IF(IFERROR(INDEX(Precios!$F$5:$F$120,MATCH(F10,Precios!$A$5:$A$120,0)),"")="","Tela sin $/metro (falta rendimiento o precio). ",""))&IF(AND(E10<>"",N(IFERROR(INDEX(Recetas!$S$5:$S$84,MATCH($E10,Recetas!$A$5:$A$84,0)),0))>0,G10=""),"Elegir tela 2. ","")&IF(NOT(ISNUMBER(I10)),"Precio de venta.","")) -> Receta 14 · FUTHOMU01PRO: Rendimiento de MESH (m/kg) en Precios. | Y10: =IF(AND(ISNUMBER(P10),ISNUMBER(I10),ISNUMBER(D10)),P10*D10,0) -> 0 | Z10: =IF(AND(ISNUMBER(P10),ISNUMBER(I10),ISNUMBER(D10)),I10*D10,0) -> 0 | AA10: =IF(AND(ISNUMBER(P10),ISNUMBER(I10),ISNUMBER(D10)),D10,0) -> 0
A11: FUTCSUBMC-V | B11: Camiseta Fútbol Playmaker, V m/c | C11: Juego | D11: 109 | E11: 06 · FUTHOMV01 | I11: 16589 | J11: Por confirmar | K11: Molde sugerido: cuello V. Elegir tela. | L11: =IF(OR(B11="",E11=""),"",IFERROR(INDEX(Recetas!$R$5:$R$84,MATCH($E11,Recetas!$A$5:$A$84,0))*IFERROR(INDEX(Precios!$F$5:$F$120,MATCH(F11,Precios!$A$5:$A$120,0)),"")+IF(N(INDEX(Recetas!$S$5:$S$84,MATCH($E11,Recetas!$A$5:$A$84,0)))=0,0,INDEX(Recetas!$S$5:$S$84,MATCH($E11,Recetas!$A$5:$A$84,0))*IFERROR(INDEX(Precios!$F$5:$F$120,MATCH(G11,Precios!$A$5:$A$120,0)),"")),"")) | M11: =IF(OR(B11="",E11=""),"",IFERROR(N(INDEX(Recetas!$L$5:$L$84,MATCH($E11,Recetas!$A$5:$A$84,0)))*Parametros!$B$27,"")) -> 0 | N11: =IF(OR(B11="",E11=""),"",IFERROR(INDEX(Confeccion!$B$5:$B$100,MATCH(INDEX(Recetas!$M$5:$M$84,MATCH($E11,Recetas!$A$5:$A$84,0)),Confeccion!$A$5:$A$100,0)),"")) -> 2000 | O11: =IF(OR(B11="",E11=""),"",IFERROR(N(INDEX(Recetas!$O$5:$O$84,MATCH($E11,Recetas!$A$5:$A$84,0)))*INDEX(Precios!$D$5:$D$120,MATCH(INDEX(Recetas!$N$5:$N$84,MATCH($E11,Recetas!$A$5:$A$84,0)),Precios!$A$5:$A$120,0)),0)) -> 0 | P11: =IF(OR(B11="",E11=""),"",IF(AND(IFERROR(INDEX(Recetas!$T$5:$T$84,MATCH($E11,Recetas!$A$5:$A$84,0))="Lista",FALSE()),ISNUMBER(L11),ISNUMBER(M11),ISNUMBER(N11),N(N11)>0),L11+M11+N11+N(O11)+N(H11),"")) | Q11: =IF(AND(ISNUMBER(P11),ISNUMBER(I11)),I11*Parametros!$B$12,"") | R11: =IF(AND(ISNUMBER(P11),ISNUMBER(I11)),I11*Parametros!$B$13,"") | S11: =IF(AND(ISNUMBER(P11),ISNUMBER(I11)),I11-P11-Q11-R11,"") | T11: =IF(AND(ISNUMBER(P11),ISNUMBER(I11)),S11/I11,"") | U11: =IF(OR(NOT(ISNUMBER(P11)),Parametros!$B$14>=1),"",P11/(1-Parametros!$B$14)) | V11: =IF(OR(NOT(ISNUMBER(P11)),Parametros!$B$14+Parametros!$B$18>=1),"",P11/(1-Parametros!$B$14-Parametros!$B$18)) | W11: =IF(B11="","",IF(E11="","SIN RECETA",IF(NOT(ISNUMBER(P11)),"FALTAN DATOS",IF(NOT(ISNUMBER(I11)),"FALTA PRECIO",IF(S11<0,"PIERDE",IF(T11<Parametros!$B$18,"BAJO META","OK")))))) -> FALTAN DATOS | X11: =IF(B11="","",IF(E11="","Elegir receta (molde). ",IF(ISNA(MATCH(E11,Recetas!$A$5:$A$84,0)),"La receta no existe. ",IF(IFERROR(INDEX(Recetas!$T$5:$T$84,MATCH($E11,Recetas!$A$5:$A$84,0))="Lista",FALSE()),"","Receta "&E11&": "&INDEX(Recetas!$T$5:$T$84,MATCH($E11,Recetas!$A$5:$A$84,0)))))&IF(F11="","Elegir tela. ",IF(IFERROR(INDEX(Precios!$F$5:$F$120,MATCH(F11,Precios!$A$5:$A$120,0)),"")="","Tela sin $/metro (falta rendimiento o precio). ",""))&IF(AND(E11<>"",N(IFERROR(INDEX(Recetas!$S$5:$S$84,MATCH($E11,Recetas!$A$5:$A$84,0)),0))>0,G11=""),"Elegir tela 2. ","")&IF(NOT(ISNUMBER(I11)),"Precio de venta.","")) -> Receta 06 · FUTHOMV01: Consumo de tela. Metros impresos. Elegir tela. | Y11: =IF(AND(ISNUMBER(P11),ISNUMBER(I11),ISNUMBER(D11)),P11*D11,0) -> 0 | Z11: =IF(AND(ISNUMBER(P11),ISNUMBER(I11),ISNUMBER(D11)),I11*D11,0) -> 0 | AA11: =IF(AND(ISNUMBER(P11),ISNUMBER(I11),ISNUMBER(D11)),D11,0) -> 0
A12: SALPOLPRESLISA | B12: Polera de Presentación Lisa | C12: Salida | D12: 109 | I12: 17004 | J12: Por confirmar | K12: Sin receta: elige el molde que usa (o crea su receta en "Recetas") y la tela. | L12: =IF(OR(B12="",E12=""),"",IFERROR(INDEX(Recetas!$R$5:$R$84,MATCH($E12,Recetas!$A$5:$A$84,0))*IFERROR(INDEX(Precios!$F$5:$F$120,MATCH(F12,Precios!$A$5:$A$120,0)),"")+IF(N(INDEX(Recetas!$S$5:$S$84,MATCH($E12,Recetas!$A$5:$A$84,0)))=0,0,INDEX(Recetas!$S$5:$S$84,MATCH($E12,Recetas!$A$5:$A$84,0))*IFERROR(INDEX(Precios!$F$5:$F$120,MATCH(G12,Precios!$A$5:$A$120,0)),"")),"")) | M12: =IF(OR(B12="",E12=""),"",IFERROR(N(INDEX(Recetas!$L$5:$L$84,MATCH($E12,Recetas!$A$5:$A$84,0)))*Parametros!$B$27,"")) | N12: =IF(OR(B12="",E12=""),"",IFERROR(INDEX(Confeccion!$B$5:$B$100,MATCH(INDEX(Recetas!$M$5:$M$84,MATCH($E12,Recetas!$A$5:$A$84,0)),Confeccion!$A$5:$A$100,0)),"")) | O12: =IF(OR(B12="",E12=""),"",IFERROR(N(INDEX(Recetas!$O$5:$O$84,MATCH($E12,Recetas!$A$5:$A$84,0)))*INDEX(Precios!$D$5:$D$120,MATCH(INDEX(Recetas!$N$5:$N$84,MATCH($E12,Recetas!$A$5:$A$84,0)),Precios!$A$5:$A$120,0)),0)) | P12: =IF(OR(B12="",E12=""),"",IF(AND(IFERROR(INDEX(Recetas!$T$5:$T$84,MATCH($E12,Recetas!$A$5:$A$84,0))="Lista",FALSE()),ISNUMBER(L12),ISNUMBER(M12),ISNUMBER(N12),N(N12)>0),L12+M12+N12+N(O12)+N(H12),"")) | Q12: =IF(AND(ISNUMBER(P12),ISNUMBER(I12)),I12*Parametros!$B$12,"") | R12: =IF(AND(ISNUMBER(P12),ISNUMBER(I12)),I12*Parametros!$B$13,"") | S12: =IF(AND(ISNUMBER(P12),ISNUMBER(I12)),I12-P12-Q12-R12,"") | T12: =IF(AND(ISNUMBER(P12),ISNUMBER(I12)),S12/I12,"") | U12: =IF(OR(NOT(ISNUMBER(P12)),Parametros!$B$14>=1),"",P12/(1-Parametros!$B$14)) | V12: =IF(OR(NOT(ISNUMBER(P12)),Parametros!$B$14+Parametros!$B$18>=1),"",P12/(1-Parametros!$B$14-Parametros!$B$18)) | W12: =IF(B12="","",IF(E12="","SIN RECETA",IF(NOT(ISNUMBER(P12)),"FALTAN DATOS",IF(NOT(ISNUMBER(I12)),"FALTA PRECIO",IF(S12<0,"PIERDE",IF(T12<Parametros!$B$18,"BAJO META","OK")))))) -> SIN RECETA | X12: =IF(B12="","",IF(E12="","Elegir receta (molde). ",IF(ISNA(MATCH(E12,Recetas!$A$5:$A$84,0)),"La receta no existe. ",IF(IFERROR(INDEX(Recetas!$T$5:$T$84,MATCH($E12,Recetas!$A$5:$A$84,0))="Lista",FALSE()),"","Receta "&E12&": "&INDEX(Recetas!$T$5:$T$84,MATCH($E12,Recetas!$A$5:$A$84,0)))))&IF(F12="","Elegir tela. ",IF(IFERROR(INDEX(Precios!$F$5:$F$120,MATCH(F12,Precios!$A$5:$A$120,0)),"")="","Tela sin $/metro (falta rendimiento o precio). ",""))&IF(AND(E12<>"",N(IFERROR(INDEX(Recetas!$S$5:$S$84,MATCH($E12,Recetas!$A$5:$A$84,0)),0))>0,G12=""),"Elegir tela 2. ","")&IF(NOT(ISNUMBER(I12)),"Precio de venta.","")) -> Elegir receta (molde). Elegir tela. | Y12: =IF(AND(ISNUMBER(P12),ISNUMBER(I12),ISNUMBER(D12)),P12*D12,0) -> 0 | Z12: =IF(AND(ISNUMBER(P12),ISNUMBER(I12),ISNUMBER(D12)),I12*D12,0) -> 0 | AA12: =IF(AND(ISNUMBER(P12),ISNUMBER(I12),ISNUMBER(D12)),D12,0) -> 0
A13: CSUBRUGSFROSA | B13: CAMISETA DE RUGBY STADE FRANCAIS ANIVERSARIO (ROSADA) | C13: Juego | D13: 100 | I13: 25714 | J13: Por confirmar | K13: Sin receta: elige el molde que usa (o crea su receta en "Recetas") y la tela. | L13: =IF(OR(B13="",E13=""),"",IFERROR(INDEX(Recetas!$R$5:$R$84,MATCH($E13,Recetas!$A$5:$A$84,0))*IFERROR(INDEX(Precios!$F$5:$F$120,MATCH(F13,Precios!$A$5:$A$120,0)),"")+IF(N(INDEX(Recetas!$S$5:$S$84,MATCH($E13,Recetas!$A$5:$A$84,0)))=0,0,INDEX(Recetas!$S$5:$S$84,MATCH($E13,Recetas!$A$5:$A$84,0))*IFERROR(INDEX(Precios!$F$5:$F$120,MATCH(G13,Precios!$A$5:$A$120,0)),"")),"")) | M13: =IF(OR(B13="",E13=""),"",IFERROR(N(INDEX(Recetas!$L$5:$L$84,MATCH($E13,Recetas!$A$5:$A$84,0)))*Parametros!$B$27,"")) | N13: =IF(OR(B13="",E13=""),"",IFERROR(INDEX(Confeccion!$B$5:$B$100,MATCH(INDEX(Recetas!$M$5:$M$84,MATCH($E13,Recetas!$A$5:$A$84,0)),Confeccion!$A$5:$A$100,0)),"")) | O13: =IF(OR(B13="",E13=""),"",IFERROR(N(INDEX(Recetas!$O$5:$O$84,MATCH($E13,Recetas!$A$5:$A$84,0)))*INDEX(Precios!$D$5:$D$120,MATCH(INDEX(Recetas!$N$5:$N$84,MATCH($E13,Recetas!$A$5:$A$84,0)),Precios!$A$5:$A$120,0)),0)) | P13: =IF(OR(B13="",E13=""),"",IF(AND(IFERROR(INDEX(Recetas!$T$5:$T$84,MATCH($E13,Recetas!$A$5:$A$84,0))="Lista",FALSE()),ISNUMBER(L13),ISNUMBER(M13),ISNUMBER(N13),N(N13)>0),L13+M13+N13+N(O13)+N(H13),"")) | Q13: =IF(AND(ISNUMBER(P13),ISNUMBER(I13)),I13*Parametros!$B$12,"") | R13: =IF(AND(ISNUMBER(P13),ISNUMBER(I13)),I13*Parametros!$B$13,"") | S13: =IF(AND(ISNUMBER(P13),ISNUMBER(I13)),I13-P13-Q13-R13,"") | T13: =IF(AND(ISNUMBER(P13),ISNUMBER(I13)),S13/I13,"") | U13: =IF(OR(NOT(ISNUMBER(P13)),Parametros!$B$14>=1),"",P13/(1-Parametros!$B$14)) | V13: =IF(OR(NOT(ISNUMBER(P13)),Parametros!$B$14+Parametros!$B$18>=1),"",P13/(1-Parametros!$B$14-Parametros!$B$18)) | W13: =IF(B13="","",IF(E13="","SIN RECETA",IF(NOT(ISNUMBER(P13)),"FALTAN DATOS",IF(NOT(ISNUMBER(I13)),"FALTA PRECIO",IF(S13<0,"PIERDE",IF(T13<Parametros!$B$18,"BAJO META","OK")))))) -> SIN RECETA | X13: =IF(B13="","",IF(E13="","Elegir receta (molde). ",IF(ISNA(MATCH(E13,Recetas!$A$5:$A$84,0)),"La receta no existe. ",IF(IFERROR(INDEX(Recetas!$T$5:$T$84,MATCH($E13,Recetas!$A$5:$A$84,0))="Lista",FALSE()),"","Receta "&E13&": "&INDEX(Recetas!$T$5:$T$84,MATCH($E13,Recetas!$A$5:$A$84,0)))))&IF(F13="","Elegir tela. ",IF(IFERROR(INDEX(Precios!$F$5:$F$120,MATCH(F13,Precios!$A$5:$A$120,0)),"")="","Tela sin $/metro (falta rendimiento o precio). ",""))&IF(AND(E13<>"",N(IFERROR(INDEX(Recetas!$S$5:$S$84,MATCH($E13,Recetas!$A$5:$A$84,0)),0))>0,G13=""),"Elegir tela 2. ","")&IF(NOT(ISNUMBER(I13)),"Precio de venta.","")) -> Elegir receta (molde). Elegir tela. | Y13: =IF(AND(ISNUMBER(P13),ISNUMBER(I13),ISNUMBER(D13)),P13*D13,0) -> 0 | Z13: =IF(AND(ISNUMBER(P13),ISNUMBER(I13),ISNUMBER(D13)),I13*D13,0) -> 0 | AA13: =IF(AND(ISNUMBER(P13),ISNUMBER(I13),ISNUMBER(D13)),D13,0) -> 0
A14: SAL-PLA-SUB-MC | B14: Polera de presentación Sublim m/c | C14: Salida | D14: 99 | I14: 18729 | J14: Por confirmar | K14: Sin receta: elige el molde que usa (o crea su receta en "Recetas") y la tela. | L14: =IF(OR(B14="",E14=""),"",IFERROR(INDEX(Recetas!$R$5:$R$84,MATCH($E14,Recetas!$A$5:$A$84,0))*IFERROR(INDEX(Precios!$F$5:$F$120,MATCH(F14,Precios!$A$5:$A$120,0)),"")+IF(N(INDEX(Recetas!$S$5:$S$84,MATCH($E14,Recetas!$A$5:$A$84,0)))=0,0,INDEX(Recetas!$S$5:$S$84,MATCH($E14,Recetas!$A$5:$A$84,0))*IFERROR(INDEX(Precios!$F$5:$F$120,MATCH(G14,Precios!$A$5:$A$120,0)),"")),"")) | M14: =IF(OR(B14="",E14=""),"",IFERROR(N(INDEX(Recetas!$L$5:$L$84,MATCH($E14,Recetas!$A$5:$A$84,0)))*Parametros!$B$27,"")) | N14: =IF(OR(B14="",E14=""),"",IFERROR(INDEX(Confeccion!$B$5:$B$100,MATCH(INDEX(Recetas!$M$5:$M$84,MATCH($E14,Recetas!$A$5:$A$84,0)),Confeccion!$A$5:$A$100,0)),"")) | O14: =IF(OR(B14="",E14=""),"",IFERROR(N(INDEX(Recetas!$O$5:$O$84,MATCH($E14,Recetas!$A$5:$A$84,0)))*INDEX(Precios!$D$5:$D$120,MATCH(INDEX(Recetas!$N$5:$N$84,MATCH($E14,Recetas!$A$5:$A$84,0)),Precios!$A$5:$A$120,0)),0)) | P14: =IF(OR(B14="",E14=""),"",IF(AND(IFERROR(INDEX(Recetas!$T$5:$T$84,MATCH($E14,Recetas!$A$5:$A$84,0))="Lista",FALSE()),ISNUMBER(L14),ISNUMBER(M14),ISNUMBER(N14),N(N14)>0),L14+M14+N14+N(O14)+N(H14),"")) | Q14: =IF(AND(ISNUMBER(P14),ISNUMBER(I14)),I14*Parametros!$B$12,"") | R14: =IF(AND(ISNUMBER(P14),ISNUMBER(I14)),I14*Parametros!$B$13,"") | S14: =IF(AND(ISNUMBER(P14),ISNUMBER(I14)),I14-P14-Q14-R14,"") | T14: =IF(AND(ISNUMBER(P14),ISNUMBER(I14)),S14/I14,"") | U14: =IF(OR(NOT(ISNUMBER(P14)),Parametros!$B$14>=1),"",P14/(1-Parametros!$B$14)) | V14: =IF(OR(NOT(ISNUMBER(P14)),Parametros!$B$14+Parametros!$B$18>=1),"",P14/(1-Parametros!$B$14-Parametros!$B$18)) | W14: =IF(B14="","",IF(E14="","SIN RECETA",IF(NOT(ISNUMBER(P14)),"FALTAN DATOS",IF(NOT(ISNUMBER(I14)),"FALTA PRECIO",IF(S14<0,"PIERDE",IF(T14<Parametros!$B$18,"BAJO META","OK")))))) -> SIN RECETA | X14: =IF(B14="","",IF(E14="","Elegir receta (molde). ",IF(ISNA(MATCH(E14,Recetas!$A$5:$A$84,0)),"La receta no existe. ",IF(IFERROR(INDEX(Recetas!$T$5:$T$84,MATCH($E14,Recetas!$A$5:$A$84,0))="Lista",FALSE()),"","Receta "&E14&": "&INDEX(Recetas!$T$5:$T$84,MATCH($E14,Recetas!$A$5:$A$84,0)))))&IF(F14="","Elegir tela. ",IF(IFERROR(INDEX(Precios!$F$5:$F$120,MATCH(F14,Precios!$A$5:$A$120,0)),"")="","Tela sin $/metro (falta rendimiento o precio). ",""))&IF(AND(E14<>"",N(IFERROR(INDEX(Recetas!$S$5:$S$84,MATCH($E14,Recetas!$A$5:$A$84,0)),0))>0,G14=""),"Elegir tela 2. ","")&IF(NOT(ISNUMBER(I14)),"Precio de venta.","")) -> Elegir receta (molde). Elegir tela. | Y14: =IF(AND(ISNUMBER(P14),ISNUMBER(I14),ISNUMBER(D14)),P14*D14,0) -> 0 | Z14: =IF(AND(ISNUMBER(P14),ISNUMBER(I14),ISNUMBER(D14)),I14*D14,0) -> 0 | AA14: =IF(AND(ISNUMBER(P14),ISNUMBER(I14),ISNUMBER(D14)),D14,0) -> 0
A15: POL-CSUB-POL-MC | B15: Polera Playmaker, Cuello Redondo m/c | C15: Juego | D15: 96 | I15: 15588 | J15: Por confirmar | K15: Sin receta: elige el molde que usa (o crea su receta en "Recetas") y la tela. | L15: =IF(OR(B15="",E15=""),"",IFERROR(INDEX(Recetas!$R$5:$R$84,MATCH($E15,Recetas!$A$5:$A$84,0))*IFERROR(INDEX(Precios!$F$5:$F$120,MATCH(F15,Precios!$A$5:$A$120,0)),"")+IF(N(INDEX(Recetas!$S$5:$S$84,MATCH($E15,Recetas!$A$5:$A$84,0)))=0,0,INDEX(Recetas!$S$5:$S$84,MATCH($E15,Recetas!$A$5:$A$84,0))*IFERROR(INDEX(Precios!$F$5:$F$120,MATCH(G15,Precios!$A$5:$A$120,0)),"")),"")) | M15: =IF(OR(B15="",E15=""),"",IFERROR(N(INDEX(Recetas!$L$5:$L$84,MATCH($E15,Recetas!$A$5:$A$84,0)))*Parametros!$B$27,"")) | N15: =IF(OR(B15="",E15=""),"",IFERROR(INDEX(Confeccion!$B$5:$B$100,MATCH(INDEX(Recetas!$M$5:$M$84,MATCH($E15,Recetas!$A$5:$A$84,0)),Confeccion!$A$5:$A$100,0)),"")) | O15: =IF(OR(B15="",E15=""),"",IFERROR(N(INDEX(Recetas!$O$5:$O$84,MATCH($E15,Recetas!$A$5:$A$84,0)))*INDEX(Precios!$D$5:$D$120,MATCH(INDEX(Recetas!$N$5:$N$84,MATCH($E15,Recetas!$A$5:$A$84,0)),Precios!$A$5:$A$120,0)),0)) | P15: =IF(OR(B15="",E15=""),"",IF(AND(IFERROR(INDEX(Recetas!$T$5:$T$84,MATCH($E15,Recetas!$A$5:$A$84,0))="Lista",FALSE()),ISNUMBER(L15),ISNUMBER(M15),ISNUMBER(N15),N(N15)>0),L15+M15+N15+N(O15)+N(H15),"")) | Q15: =IF(AND(ISNUMBER(P15),ISNUMBER(I15)),I15*Parametros!$B$12,"") | R15: =IF(AND(ISNUMBER(P15),ISNUMBER(I15)),I15*Parametros!$B$13,"") | S15: =IF(AND(ISNUMBER(P15),ISNUMBER(I15)),I15-P15-Q15-R15,"") | T15: =IF(AND(ISNUMBER(P15),ISNUMBER(I15)),S15/I15,"") | U15: =IF(OR(NOT(ISNUMBER(P15)),Parametros!$B$14>=1),"",P15/(1-Parametros!$B$14)) | V15: =IF(OR(NOT(ISNUMBER(P15)),Parametros!$B$14+Parametros!$B$18>=1),"",P15/(1-Parametros!$B$14-Parametros!$B$18)) | W15: =IF(B15="","",IF(E15="","SIN RECETA",IF(NOT(ISNUMBER(P15)),"FALTAN DATOS",IF(NOT(ISNUMBER(I15)),"FALTA PRECIO",IF(S15<0,"PIERDE",IF(T15<Parametros!$B$18,"BAJO META","OK")))))) -> SIN RECETA | X15: =IF(B15="","",IF(E15="","Elegir receta (molde). ",IF(ISNA(MATCH(E15,Recetas!$A$5:$A$84,0)),"La receta no existe. ",IF(IFERROR(INDEX(Recetas!$T$5:$T$84,MATCH($E15,Recetas!$A$5:$A$84,0))="Lista",FALSE()),"","Receta "&E15&": "&INDEX(Recetas!$T$5:$T$84,MATCH($E15,Recetas!$A$5:$A$84,0)))))&IF(F15="","Elegir tela. ",IF(IFERROR(INDEX(Precios!$F$5:$F$120,MATCH(F15,Precios!$A$5:$A$120,0)),"")="","Tela sin $/metro (falta rendimiento o precio). ",""))&IF(AND(E15<>"",N(IFERROR(INDEX(Recetas!$S$5:$S$84,MATCH($E15,Recetas!$A$5:$A$84,0)),0))>0,G15=""),"Elegir tela 2. ","")&IF(NOT(ISNUMBER(I15)),"Precio de venta.","")) -> Elegir receta (molde). Elegir tela. | Y15: =IF(AND(ISNUMBER(P15),ISNUMBER(I15),ISNUMBER(D15)),P15*D15,0) -> 0 | Z15: =IF(AND(ISNUMBER(P15),ISNUMBER(I15),ISNUMBER(D15)),I15*D15,0) -> 0 | AA15: =IF(AND(ISNUMBER(P15),ISNUMBER(I15),ISNUMBER(D15)),D15,0) -> 0
A16: RUGCSUBPRO | B16: Camiseta Rugby Pro Pmk | C16: Juego | D16: 93 | I16: 21765 | J16: Por confirmar | K16: Sin receta: elige el molde que usa (o crea su receta en "Recetas") y la tela. | L16: =IF(OR(B16="",E16=""),"",IFERROR(INDEX(Recetas!$R$5:$R$84,MATCH($E16,Recetas!$A$5:$A$84,0))*IFERROR(INDEX(Precios!$F$5:$F$120,MATCH(F16,Precios!$A$5:$A$120,0)),"")+IF(N(INDEX(Recetas!$S$5:$S$84,MATCH($E16,Recetas!$A$5:$A$84,0)))=0,0,INDEX(Recetas!$S$5:$S$84,MATCH($E16,Recetas!$A$5:$A$84,0))*IFERROR(INDEX(Precios!$F$5:$F$120,MATCH(G16,Precios!$A$5:$A$120,0)),"")),"")) | M16: =IF(OR(B16="",E16=""),"",IFERROR(N(INDEX(Recetas!$L$5:$L$84,MATCH($E16,Recetas!$A$5:$A$84,0)))*Parametros!$B$27,"")) | N16: =IF(OR(B16="",E16=""),"",IFERROR(INDEX(Confeccion!$B$5:$B$100,MATCH(INDEX(Recetas!$M$5:$M$84,MATCH($E16,Recetas!$A$5:$A$84,0)),Confeccion!$A$5:$A$100,0)),"")) | O16: =IF(OR(B16="",E16=""),"",IFERROR(N(INDEX(Recetas!$O$5:$O$84,MATCH($E16,Recetas!$A$5:$A$84,0)))*INDEX(Precios!$D$5:$D$120,MATCH(INDEX(Recetas!$N$5:$N$84,MATCH($E16,Recetas!$A$5:$A$84,0)),Precios!$A$5:$A$120,0)),0)) | P16: =IF(OR(B16="",E16=""),"",IF(AND(IFERROR(INDEX(Recetas!$T$5:$T$84,MATCH($E16,Recetas!$A$5:$A$84,0))="Lista",FALSE()),ISNUMBER(L16),ISNUMBER(M16),ISNUMBER(N16),N(N16)>0),L16+M16+N16+N(O16)+N(H16),"")) | Q16: =IF(AND(ISNUMBER(P16),ISNUMBER(I16)),I16*Parametros!$B$12,"") | R16: =IF(AND(ISNUMBER(P16),ISNUMBER(I16)),I16*Parametros!$B$13,"") | S16: =IF(AND(ISNUMBER(P16),ISNUMBER(I16)),I16-P16-Q16-R16,"") | T16: =IF(AND(ISNUMBER(P16),ISNUMBER(I16)),S16/I16,"") | U16: =IF(OR(NOT(ISNUMBER(P16)),Parametros!$B$14>=1),"",P16/(1-Parametros!$B$14)) | V16: =IF(OR(NOT(ISNUMBER(P16)),Parametros!$B$14+Parametros!$B$18>=1),"",P16/(1-Parametros!$B$14-Parametros!$B$18)) | W16: =IF(B16="","",IF(E16="","SIN RECETA",IF(NOT(ISNUMBER(P16)),"FALTAN DATOS",IF(NOT(ISNUMBER(I16)),"FALTA PRECIO",IF(S16<0,"PIERDE",IF(T16<Parametros!$B$18,"BAJO META","OK")))))) -> SIN RECETA | X16: =IF(B16="","",IF(E16="","Elegir receta (molde). ",IF(ISNA(MATCH(E16,Recetas!$A$5:$A$84,0)),"La receta no existe. ",IF(IFERROR(INDEX(Recetas!$T$5:$T$84,MATCH($E16,Recetas!$A$5:$A$84,0))="Lista",FALSE()),"","Receta "&E16&": "&INDEX(Recetas!$T$5:$T$84,MATCH($E16,Recetas!$A$5:$A$84,0)))))&IF(F16="","Elegir tela. ",IF(IFERROR(INDEX(Precios!$F$5:$F$120,MATCH(F16,Precios!$A$5:$A$120,0)),"")="","Tela sin $/metro (falta rendimiento o precio). ",""))&IF(AND(E16<>"",N(IFERROR(INDEX(Recetas!$S$5:$S$84,MATCH($E16,Recetas!$A$5:$A$84,0)),0))>0,G16=""),"Elegir tela 2. ","")&IF(NOT(ISNUMBER(I16)),"Precio de venta.","")) -> Elegir receta (molde). Elegir tela. | Y16: =IF(AND(ISNUMBER(P16),ISNUMBER(I16),ISNUMBER(D16)),P16*D16,0) -> 0 | Z16: =IF(AND(ISNUMBER(P16),ISNUMBER(I16),ISNUMBER(D16)),I16*D16,0) -> 0 | AA16: =IF(AND(ISNUMBER(P16),ISNUMBER(I16),ISNUMBER(D16)),D16,0) -> 0
A17: MDBZCOMENTPITSUB | B17: Conjunto Polerón de Entrenamiento + Buzo Pitillo Subl | C17: Salida | D17: 76 | I17: 44010 | J17: Por confirmar | K17: Sin receta: elige el molde que usa (o crea su receta en "Recetas") y la tela. | L17: =IF(OR(B17="",E17=""),"",IFERROR(INDEX(Recetas!$R$5:$R$84,MATCH($E17,Recetas!$A$5:$A$84,0))*IFERROR(INDEX(Precios!$F$5:$F$120,MATCH(F17,Precios!$A$5:$A$120,0)),"")+IF(N(INDEX(Recetas!$S$5:$S$84,MATCH($E17,Recetas!$A$5:$A$84,0)))=0,0,INDEX(Recetas!$S$5:$S$84,MATCH($E17,Recetas!$A$5:$A$84,0))*IFERROR(INDEX(Precios!$F$5:$F$120,MATCH(G17,Precios!$A$5:$A$120,0)),"")),"")) | M17: =IF(OR(B17="",E17=""),"",IFERROR(N(INDEX(Recetas!$L$5:$L$84,MATCH($E17,Recetas!$A$5:$A$84,0)))*Parametros!$B$27,"")) | N17: =IF(OR(B17="",E17=""),"",IFERROR(INDEX(Confeccion!$B$5:$B$100,MATCH(INDEX(Recetas!$M$5:$M$84,MATCH($E17,Recetas!$A$5:$A$84,0)),Confeccion!$A$5:$A$100,0)),"")) | O17: =IF(OR(B17="",E17=""),"",IFERROR(N(INDEX(Recetas!$O$5:$O$84,MATCH($E17,Recetas!$A$5:$A$84,0)))*INDEX(Precios!$D$5:$D$120,MATCH(INDEX(Recetas!$N$5:$N$84,MATCH($E17,Recetas!$A$5:$A$84,0)),Precios!$A$5:$A$120,0)),0)) | P17: =IF(OR(B17="",E17=""),"",IF(AND(IFERROR(INDEX(Recetas!$T$5:$T$84,MATCH($E17,Recetas!$A$5:$A$84,0))="Lista",FALSE()),ISNUMBER(L17),ISNUMBER(M17),ISNUMBER(N17),N(N17)>0),L17+M17+N17+N(O17)+N(H17),"")) | Q17: =IF(AND(ISNUMBER(P17),ISNUMBER(I17)),I17*Parametros!$B$12,"") | R17: =IF(AND(ISNUMBER(P17),ISNUMBER(I17)),I17*Parametros!$B$13,"") | S17: =IF(AND(ISNUMBER(P17),ISNUMBER(I17)),I17-P17-Q17-R17,"") | T17: =IF(AND(ISNUMBER(P17),ISNUMBER(I17)),S17/I17,"") | U17: =IF(OR(NOT(ISNUMBER(P17)),Parametros!$B$14>=1),"",P17/(1-Parametros!$B$14)) | V17: =IF(OR(NOT(ISNUMBER(P17)),Parametros!$B$14+Parametros!$B$18>=1),"",P17/(1-Parametros!$B$14-Parametros!$B$18)) | W17: =IF(B17="","",IF(E17="","SIN RECETA",IF(NOT(ISNUMBER(P17)),"FALTAN DATOS",IF(NOT(ISNUMBER(I17)),"FALTA PRECIO",IF(S17<0,"PIERDE",IF(T17<Parametros!$B$18,"BAJO META","OK")))))) -> SIN RECETA | X17: =IF(B17="","",IF(E17="","Elegir receta (molde). ",IF(ISNA(MATCH(E17,Recetas!$A$5:$A$84,0)),"La receta no existe. ",IF(IFERROR(INDEX(Recetas!$T$5:$T$84,MATCH($E17,Recetas!$A$5:$A$84,0))="Lista",FALSE()),"","Receta "&E17&": "&INDEX(Recetas!$T$5:$T$84,MATCH($E17,Recetas!$A$5:$A$84,0)))))&IF(F17="","Elegir tela. ",IF(IFERROR(INDEX(Precios!$F$5:$F$120,MATCH(F17,Precios!$A$5:$A$120,0)),"")="","Tela sin $/metro (falta rendimiento o precio). ",""))&IF(AND(E17<>"",N(IFERROR(INDEX(Recetas!$S$5:$S$84,MATCH($E17,Recetas!$A$5:$A$84,0)),0))>0,G17=""),"Elegir tela 2. ","")&IF(NOT(ISNUMBER(I17)),"Precio de venta.","")) -> Elegir receta (molde). Elegir tela. | Y17: =IF(AND(ISNUMBER(P17),ISNUMBER(I17),ISNUMBER(D17)),P17*D17,0) -> 0 | Z17: =IF(AND(ISNUMBER(P17),ISNUMBER(I17),ISNUMBER(D17)),I17*D17,0) -> 0 | AA17: =IF(AND(ISNUMBER(P17),ISNUMBER(I17),ISNUMBER(D17)),D17,0) -> 0
A18: FUTCSUBPROPIQMC | B18: Camiseta Fútbol Pro Playmaker, Piqué m/c | C18: Juego | D18: 66 | I18: 21554 | J18: Por confirmar | K18: Sin receta: elige el molde que usa (o crea su receta en "Recetas") y la tela. | L18: =IF(OR(B18="",E18=""),"",IFERROR(INDEX(Recetas!$R$5:$R$84,MATCH($E18,Recetas!$A$5:$A$84,0))*IFERROR(INDEX(Precios!$F$5:$F$120,MATCH(F18,Precios!$A$5:$A$120,0)),"")+IF(N(INDEX(Recetas!$S$5:$S$84,MATCH($E18,Recetas!$A$5:$A$84,0)))=0,0,INDEX(Recetas!$S$5:$S$84,MATCH($E18,Recetas!$A$5:$A$84,0))*IFERROR(INDEX(Precios!$F$5:$F$120,MATCH(G18,Precios!$A$5:$A$120,0)),"")),"")) | M18: =IF(OR(B18="",E18=""),"",IFERROR(N(INDEX(Recetas!$L$5:$L$84,MATCH($E18,Recetas!$A$5:$A$84,0)))*Parametros!$B$27,"")) | N18: =IF(OR(B18="",E18=""),"",IFERROR(INDEX(Confeccion!$B$5:$B$100,MATCH(INDEX(Recetas!$M$5:$M$84,MATCH($E18,Recetas!$A$5:$A$84,0)),Confeccion!$A$5:$A$100,0)),"")) | O18: =IF(OR(B18="",E18=""),"",IFERROR(N(INDEX(Recetas!$O$5:$O$84,MATCH($E18,Recetas!$A$5:$A$84,0)))*INDEX(Precios!$D$5:$D$120,MATCH(INDEX(Recetas!$N$5:$N$84,MATCH($E18,Recetas!$A$5:$A$84,0)),Precios!$A$5:$A$120,0)),0)) | P18: =IF(OR(B18="",E18=""),"",IF(AND(IFERROR(INDEX(Recetas!$T$5:$T$84,MATCH($E18,Recetas!$A$5:$A$84,0))="Lista",FALSE()),ISNUMBER(L18),ISNUMBER(M18),ISNUMBER(N18),N(N18)>0),L18+M18+N18+N(O18)+N(H18),"")) | Q18: =IF(AND(ISNUMBER(P18),ISNUMBER(I18)),I18*Parametros!$B$12,"") | R18: =IF(AND(ISNUMBER(P18),ISNUMBER(I18)),I18*Parametros!$B$13,"") | S18: =IF(AND(ISNUMBER(P18),ISNUMBER(I18)),I18-P18-Q18-R18,"") | T18: =IF(AND(ISNUMBER(P18),ISNUMBER(I18)),S18/I18,"") | U18: =IF(OR(NOT(ISNUMBER(P18)),Parametros!$B$14>=1),"",P18/(1-Parametros!$B$14)) | V18: =IF(OR(NOT(ISNUMBER(P18)),Parametros!$B$14+Parametros!$B$18>=1),"",P18/(1-Parametros!$B$14-Parametros!$B$18)) | W18: =IF(B18="","",IF(E18="","SIN RECETA",IF(NOT(ISNUMBER(P18)),"FALTAN DATOS",IF(NOT(ISNUMBER(I18)),"FALTA PRECIO",IF(S18<0,"PIERDE",IF(T18<Parametros!$B$18,"BAJO META","OK")))))) -> SIN RECETA | X18: =IF(B18="","",IF(E18="","Elegir receta (molde). ",IF(ISNA(MATCH(E18,Recetas!$A$5:$A$84,0)),"La receta no existe. ",IF(IFERROR(INDEX(Recetas!$T$5:$T$84,MATCH($E18,Recetas!$A$5:$A$84,0))="Lista",FALSE()),"","Receta "&E18&": "&INDEX(Recetas!$T$5:$T$84,MATCH($E18,Recetas!$A$5:$A$84,0)))))&IF(F18="","Elegir tela. ",IF(IFERROR(INDEX(Precios!$F$5:$F$120,MATCH(F18,Precios!$A$5:$A$120,0)),"")="","Tela sin $/metro (falta rendimiento o precio). ",""))&IF(AND(E18<>"",N(IFERROR(INDEX(Recetas!$S$5:$S$84,MATCH($E18,Recetas!$A$5:$A$84,0)),0))>0,G18=""),"Elegir tela 2. ","")&IF(NOT(ISNUMBER(I18)),"Precio de venta.","")) -> Elegir receta (molde). Elegir tela. | Y18: =IF(AND(ISNUMBER(P18),ISNUMBER(I18),ISNUMBER(D18)),P18*D18,0) -> 0 | Z18: =IF(AND(ISNUMBER(P18),ISNUMBER(I18),ISNUMBER(D18)),I18*D18,0) -> 0 | AA18: =IF(AND(ISNUMBER(P18),ISNUMBER(I18),ISNUMBER(D18)),D18,0) -> 0
A19: RUNCSUBPROSM | B19: Camiseta Running Pro s/m | C19: Juego | D19: 65 | E19: SM-03 · Camiseta Running s/m | F19: 5K NACIONAL (running pro) | I19: 19244 | J19: Por confirmar | L19: =IF(OR(B19="",E19=""),"",IFERROR(INDEX(Recetas!$R$5:$R$84,MATCH($E19,Recetas!$A$5:$A$84,0))*IFERROR(INDEX(Precios!$F$5:$F$120,MATCH(F19,Precios!$A$5:$A$120,0)),"")+IF(N(INDEX(Recetas!$S$5:$S$84,MATCH($E19,Recetas!$A$5:$A$84,0)))=0,0,INDEX(Recetas!$S$5:$S$84,MATCH($E19,Recetas!$A$5:$A$84,0))*IFERROR(INDEX(Precios!$F$5:$F$120,MATCH(G19,Precios!$A$5:$A$120,0)),"")),"")) -> 348.008 | M19: =IF(OR(B19="",E19=""),"",IFERROR(N(INDEX(Recetas!$L$5:$L$84,MATCH($E19,Recetas!$A$5:$A$84,0)))*Parametros!$B$27,"")) -> 0 | N19: =IF(OR(B19="",E19=""),"",IFERROR(INDEX(Confeccion!$B$5:$B$100,MATCH(INDEX(Recetas!$M$5:$M$84,MATCH($E19,Recetas!$A$5:$A$84,0)),Confeccion!$A$5:$A$100,0)),"")) -> 1800 | O19: =IF(OR(B19="",E19=""),"",IFERROR(N(INDEX(Recetas!$O$5:$O$84,MATCH($E19,Recetas!$A$5:$A$84,0)))*INDEX(Precios!$D$5:$D$120,MATCH(INDEX(Recetas!$N$5:$N$84,MATCH($E19,Recetas!$A$5:$A$84,0)),Precios!$A$5:$A$120,0)),0)) -> 0 | P19: =IF(OR(B19="",E19=""),"",IF(AND(IFERROR(INDEX(Recetas!$T$5:$T$84,MATCH($E19,Recetas!$A$5:$A$84,0))="Lista",FALSE()),ISNUMBER(L19),ISNUMBER(M19),ISNUMBER(N19),N(N19)>0),L19+M19+N19+N(O19)+N(H19),"")) -> 2148.008 | Q19: =IF(AND(ISNUMBER(P19),ISNUMBER(I19)),I19*Parametros!$B$12,"") -> 6792.1033 | R19: =IF(AND(ISNUMBER(P19),ISNUMBER(I19)),I19*Parametros!$B$13,"") -> 2438.1464 | S19: =IF(AND(ISNUMBER(P19),ISNUMBER(I19)),I19-P19-Q19-R19,"") -> 7865.7424 | T19: =IF(AND(ISNUMBER(P19),ISNUMBER(I19)),S19/I19,"") -> 0.40873739 | U19: =IF(OR(NOT(ISNUMBER(P19)),Parametros!$B$14>=1),"",P19/(1-Parametros!$B$14)) -> 4127.9505 | V19: =IF(OR(NOT(ISNUMBER(P19)),Parametros!$B$14+Parametros!$B$18>=1),"",P19/(1-Parametros!$B$14-Parametros!$B$18)) -> 5109.9611 | W19: =IF(B19="","",IF(E19="","SIN RECETA",IF(NOT(ISNUMBER(P19)),"FALTAN DATOS",IF(NOT(ISNUMBER(I19)),"FALTA PRECIO",IF(S19<0,"PIERDE",IF(T19<Parametros!$B$18,"BAJO META","OK")))))) -> OK | X19: =IF(B19="","",IF(E19="","Elegir receta (molde). ",IF(ISNA(MATCH(E19,Recetas!$A$5:$A$84,0)),"La receta no existe. ",IF(IFERROR(INDEX(Recetas!$T$5:$T$84,MATCH($E19,Recetas!$A$5:$A$84,0))="Lista",FALSE()),"","Receta "&E19&": "&INDEX(Recetas!$T$5:$T$84,MATCH($E19,Recetas!$A$5:$A$84,0)))))&IF(F19="","Elegir tela. ",IF(IFERROR(INDEX(Precios!$F$5:$F$120,MATCH(F19,Precios!$A$5:$A$120,0)),"")="","Tela sin $/metro (falta rendimiento o precio). ",""))&IF(AND(E19<>"",N(IFERROR(INDEX(Recetas!$S$5:$S$84,MATCH($E19,Recetas!$A$5:$A$84,0)),0))>0,G19=""),"Elegir tela 2. ","")&IF(NOT(ISNUMBER(I19)),"Precio de venta.","")) | Y19: =IF(AND(ISNUMBER(P19),ISNUMBER(I19),ISNUMBER(D19)),P19*D19,0) -> 139620.52 | Z19: =IF(AND(ISNUMBER(P19),ISNUMBER(I19),ISNUMBER(D19)),I19*D19,0) -> 1250860 | AA19: =IF(AND(ISNUMBER(P19),ISNUMBER(I19),ISNUMBER(D19)),D19,0) -> 65
A20: SAL-CTV-SUB-SG | B20: CORTAVIENTO SUBLIMADO | C20: Salida | D20: 62 | I20: 36050 | J20: Por confirmar | K20: Sin receta: elige el molde que usa (o crea su receta en "Recetas") y la tela. | L20: =IF(OR(B20="",E20=""),"",IFERROR(INDEX(Recetas!$R$5:$R$84,MATCH($E20,Recetas!$A$5:$A$84,0))*IFERROR(INDEX(Precios!$F$5:$F$120,MATCH(F20,Precios!$A$5:$A$120,0)),"")+IF(N(INDEX(Recetas!$S$5:$S$84,MATCH($E20,Recetas!$A$5:$A$84,0)))=0,0,INDEX(Recetas!$S$5:$S$84,MATCH($E20,Recetas!$A$5:$A$84,0))*IFERROR(INDEX(Precios!$F$5:$F$120,MATCH(G20,Precios!$A$5:$A$120,0)),"")),"")) | M20: =IF(OR(B20="",E20=""),"",IFERROR(N(INDEX(Recetas!$L$5:$L$84,MATCH($E20,Recetas!$A$5:$A$84,0)))*Parametros!$B$27,"")) | N20: =IF(OR(B20="",E20=""),"",IFERROR(INDEX(Confeccion!$B$5:$B$100,MATCH(INDEX(Recetas!$M$5:$M$84,MATCH($E20,Recetas!$A$5:$A$84,0)),Confeccion!$A$5:$A$100,0)),"")) | O20: =IF(OR(B20="",E20=""),"",IFERROR(N(INDEX(Recetas!$O$5:$O$84,MATCH($E20,Recetas!$A$5:$A$84,0)))*INDEX(Precios!$D$5:$D$120,MATCH(INDEX(Recetas!$N$5:$N$84,MATCH($E20,Recetas!$A$5:$A$84,0)),Precios!$A$5:$A$120,0)),0)) | P20: =IF(OR(B20="",E20=""),"",IF(AND(IFERROR(INDEX(Recetas!$T$5:$T$84,MATCH($E20,Recetas!$A$5:$A$84,0))="Lista",FALSE()),ISNUMBER(L20),ISNUMBER(M20),ISNUMBER(N20),N(N20)>0),L20+M20+N20+N(O20)+N(H20),"")) | Q20: =IF(AND(ISNUMBER(P20),ISNUMBER(I20)),I20*Parametros!$B$12,"") | R20: =IF(AND(ISNUMBER(P20),ISNUMBER(I20)),I20*Parametros!$B$13,"") | S20: =IF(AND(ISNUMBER(P20),ISNUMBER(I20)),I20-P20-Q20-R20,"") | T20: =IF(AND(ISNUMBER(P20),ISNUMBER(I20)),S20/I20,"") | U20: =IF(OR(NOT(ISNUMBER(P20)),Parametros!$B$14>=1),"",P20/(1-Parametros!$B$14)) | V20: =IF(OR(NOT(ISNUMBER(P20)),Parametros!$B$14+Parametros!$B$18>=1),"",P20/(1-Parametros!$B$14-Parametros!$B$18)) | W20: =IF(B20="","",IF(E20="","SIN RECETA",IF(NOT(ISNUMBER(P20)),"FALTAN DATOS",IF(NOT(ISNUMBER(I20)),"FALTA PRECIO",IF(S20<0,"PIERDE",IF(T20<Parametros!$B$18,"BAJO META","OK")))))) -> SIN RECETA | X20: =IF(B20="","",IF(E20="","Elegir receta (molde). ",IF(ISNA(MATCH(E20,Recetas!$A$5:$A$84,0)),"La receta no existe. ",IF(IFERROR(INDEX(Recetas!$T$5:$T$84,MATCH($E20,Recetas!$A$5:$A$84,0))="Lista",FALSE()),"","Receta "&E20&": "&INDEX(Recetas!$T$5:$T$84,MATCH($E20,Recetas!$A$5:$A$84,0)))))&IF(F20="","Elegir tela. ",IF(IFERROR(INDEX(Precios!$F$5:$F$120,MATCH(F20,Precios!$A$5:$A$120,0)),"")="","Tela sin $/metro (falta rendimiento o precio). ",""))&IF(AND(E20<>"",N(IFERROR(INDEX(Recetas!$S$5:$S$84,MATCH($E20,Recetas!$A$5:$A$84,0)),0))>0,G20=""),"Elegir tela 2. ","")&IF(NOT(ISNUMBER(I20)),"Precio de venta.","")) -> Elegir receta (molde). Elegir tela. | Y20: =IF(AND(ISNUMBER(P20),ISNUMBER(I20),ISNUMBER(D20)),P20*D20,0) -> 0 | Z20: =IF(AND(ISNUMBER(P20),ISNUMBER(I20),ISNUMBER(D20)),I20*D20,0) -> 0 | AA20: =IF(AND(ISNUMBER(P20),ISNUMBER(I20),ISNUMBER(D20)),D20,0) -> 0
A21: RUG-SHO-BAS | B21: Short Rugby Basic | C21: Juego | D21: 61 | E21: SM-02 · Short Rugby | F21: GABARDINA | I21: 12507 | J21: Por confirmar | L21: =IF(OR(B21="",E21=""),"",IFERROR(INDEX(Recetas!$R$5:$R$84,MATCH($E21,Recetas!$A$5:$A$84,0))*IFERROR(INDEX(Precios!$F$5:$F$120,MATCH(F21,Precios!$A$5:$A$120,0)),"")+IF(N(INDEX(Recetas!$S$5:$S$84,MATCH($E21,Recetas!$A$5:$A$84,0)))=0,0,INDEX(Recetas!$S$5:$S$84,MATCH($E21,Recetas!$A$5:$A$84,0))*IFERROR(INDEX(Precios!$F$5:$F$120,MATCH(G21,Precios!$A$5:$A$120,0)),"")),"")) | M21: =IF(OR(B21="",E21=""),"",IFERROR(N(INDEX(Recetas!$L$5:$L$84,MATCH($E21,Recetas!$A$5:$A$84,0)))*Parametros!$B$27,"")) -> 0 | N21: =IF(OR(B21="",E21=""),"",IFERROR(INDEX(Confeccion!$B$5:$B$100,MATCH(INDEX(Recetas!$M$5:$M$84,MATCH($E21,Recetas!$A$5:$A$84,0)),Confeccion!$A$5:$A$100,0)),"")) -> 2200 | O21: =IF(OR(B21="",E21=""),"",IFERROR(N(INDEX(Recetas!$O$5:$O$84,MATCH($E21,Recetas!$A$5:$A$84,0)))*INDEX(Precios!$D$5:$D$120,MATCH(INDEX(Recetas!$N$5:$N$84,MATCH($E21,Recetas!$A$5:$A$84,0)),Precios!$A$5:$A$120,0)),0)) -> 0 | P21: =IF(OR(B21="",E21=""),"",IF(AND(IFERROR(INDEX(Recetas!$T$5:$T$84,MATCH($E21,Recetas!$A$5:$A$84,0))="Lista",FALSE()),ISNUMBER(L21),ISNUMBER(M21),ISNUMBER(N21),N(N21)>0),L21+M21+N21+N(O21)+N(H21),"")) | Q21: =IF(AND(ISNUMBER(P21),ISNUMBER(I21)),I21*Parametros!$B$12,"") | R21: =IF(AND(ISNUMBER(P21),ISNUMBER(I21)),I21*Parametros!$B$13,"") | S21: =IF(AND(ISNUMBER(P21),ISNUMBER(I21)),I21-P21-Q21-R21,"") | T21: =IF(AND(ISNUMBER(P21),ISNUMBER(I21)),S21/I21,"") | U21: =IF(OR(NOT(ISNUMBER(P21)),Parametros!$B$14>=1),"",P21/(1-Parametros!$B$14)) | V21: =IF(OR(NOT(ISNUMBER(P21)),Parametros!$B$14+Parametros!$B$18>=1),"",P21/(1-Parametros!$B$14-Parametros!$B$18)) | W21: =IF(B21="","",IF(E21="","SIN RECETA",IF(NOT(ISNUMBER(P21)),"FALTAN DATOS",IF(NOT(ISNUMBER(I21)),"FALTA PRECIO",IF(S21<0,"PIERDE",IF(T21<Parametros!$B$18,"BAJO META","OK")))))) -> FALTAN DATOS | X21: =IF(B21="","",IF(E21="","Elegir receta (molde). ",IF(ISNA(MATCH(E21,Recetas!$A$5:$A$84,0)),"La receta no existe. ",IF(IFERROR(INDEX(Recetas!$T$5:$T$84,MATCH($E21,Recetas!$A$5:$A$84,0))="Lista",FALSE()),"","Receta "&E21&": "&INDEX(Recetas!$T$5:$T$84,MATCH($E21,Recetas!$A$5:$A$84,0)))))&IF(F21="","Elegir tela. ",IF(IFERROR(INDEX(Precios!$F$5:$F$120,MATCH(F21,Precios!$A$5:$A$120,0)),"")="","Tela sin $/metro (falta rendimiento o precio). ",""))&IF(AND(E21<>"",N(IFERROR(INDEX(Recetas!$S$5:$S$84,MATCH($E21,Recetas!$A$5:$A$84,0)),0))>0,G21=""),"Elegir tela 2. ","")&IF(NOT(ISNUMBER(I21)),"Precio de venta.","")) -> Receta SM-02 · Short Rugby: Rendimiento de GABARDINA (m/kg) en Precios. Tela sin $/metro (falta rendimiento o precio). | Y21: =IF(AND(ISNUMBER(P21),ISNUMBER(I21),ISNUMBER(D21)),P21*D21,0) -> 0 | Z21: =IF(AND(ISNUMBER(P21),ISNUMBER(I21),ISNUMBER(D21)),I21*D21,0) -> 0 | AA21: =IF(AND(ISNUMBER(P21),ISNUMBER(I21),ISNUMBER(D21)),D21,0) -> 0
A22: SALPTPESUB | B22: Conjunto Polerón de Entrenamiento + Pitillo | C22: Salida | D22: 60 | I22: 41933 | J22: Por confirmar | K22: Sin receta: elige el molde que usa (o crea su receta en "Recetas") y la tela. | L22: =IF(OR(B22="",E22=""),"",IFERROR(INDEX(Recetas!$R$5:$R$84,MATCH($E22,Recetas!$A$5:$A$84,0))*IFERROR(INDEX(Precios!$F$5:$F$120,MATCH(F22,Precios!$A$5:$A$120,0)),"")+IF(N(INDEX(Recetas!$S$5:$S$84,MATCH($E22,Recetas!$A$5:$A$84,0)))=0,0,INDEX(Recetas!$S$5:$S$84,MATCH($E22,Recetas!$A$5:$A$84,0))*IFERROR(INDEX(Precios!$F$5:$F$120,MATCH(G22,Precios!$A$5:$A$120,0)),"")),"")) | M22: =IF(OR(B22="",E22=""),"",IFERROR(N(INDEX(Recetas!$L$5:$L$84,MATCH($E22,Recetas!$A$5:$A$84,0)))*Parametros!$B$27,"")) | N22: =IF(OR(B22="",E22=""),"",IFERROR(INDEX(Confeccion!$B$5:$B$100,MATCH(INDEX(Recetas!$M$5:$M$84,MATCH($E22,Recetas!$A$5:$A$84,0)),Confeccion!$A$5:$A$100,0)),"")) | O22: =IF(OR(B22="",E22=""),"",IFERROR(N(INDEX(Recetas!$O$5:$O$84,MATCH($E22,Recetas!$A$5:$A$84,0)))*INDEX(Precios!$D$5:$D$120,MATCH(INDEX(Recetas!$N$5:$N$84,MATCH($E22,Recetas!$A$5:$A$84,0)),Precios!$A$5:$A$120,0)),0)) | P22: =IF(OR(B22="",E22=""),"",IF(AND(IFERROR(INDEX(Recetas!$T$5:$T$84,MATCH($E22,Recetas!$A$5:$A$84,0))="Lista",FALSE()),ISNUMBER(L22),ISNUMBER(M22),ISNUMBER(N22),N(N22)>0),L22+M22+N22+N(O22)+N(H22),"")) | Q22: =IF(AND(ISNUMBER(P22),ISNUMBER(I22)),I22*Parametros!$B$12,"") | R22: =IF(AND(ISNUMBER(P22),ISNUMBER(I22)),I22*Parametros!$B$13,"") | S22: =IF(AND(ISNUMBER(P22),ISNUMBER(I22)),I22-P22-Q22-R22,"") | T22: =IF(AND(ISNUMBER(P22),ISNUMBER(I22)),S22/I22,"") | U22: =IF(OR(NOT(ISNUMBER(P22)),Parametros!$B$14>=1),"",P22/(1-Parametros!$B$14)) | V22: =IF(OR(NOT(ISNUMBER(P22)),Parametros!$B$14+Parametros!$B$18>=1),"",P22/(1-Parametros!$B$14-Parametros!$B$18)) | W22: =IF(B22="","",IF(E22="","SIN RECETA",IF(NOT(ISNUMBER(P22)),"FALTAN DATOS",IF(NOT(ISNUMBER(I22)),"FALTA PRECIO",IF(S22<0,"PIERDE",IF(T22<Parametros!$B$18,"BAJO META","OK")))))) -> SIN RECETA | X22: =IF(B22="","",IF(E22="","Elegir receta (molde). ",IF(ISNA(MATCH(E22,Recetas!$A$5:$A$84,0)),"La receta no existe. ",IF(IFERROR(INDEX(Recetas!$T$5:$T$84,MATCH($E22,Recetas!$A$5:$A$84,0))="Lista",FALSE()),"","Receta "&E22&": "&INDEX(Recetas!$T$5:$T$84,MATCH($E22,Recetas!$A$5:$A$84,0)))))&IF(F22="","Elegir tela. ",IF(IFERROR(INDEX(Precios!$F$5:$F$120,MATCH(F22,Precios!$A$5:$A$120,0)),"")="","Tela sin $/metro (falta rendimiento o precio). ",""))&IF(AND(E22<>"",N(IFERROR(INDEX(Recetas!$S$5:$S$84,MATCH($E22,Recetas!$A$5:$A$84,0)),0))>0,G22=""),"Elegir tela 2. ","")&IF(NOT(ISNUMBER(I22)),"Precio de venta.","")) -> Elegir receta (molde). Elegir tela. | Y22: =IF(AND(ISNUMBER(P22),ISNUMBER(I22),ISNUMBER(D22)),P22*D22,0) -> 0 | Z22: =IF(AND(ISNUMBER(P22),ISNUMBER(I22),ISNUMBER(D22)),I22*D22,0) -> 0 | AA22: =IF(AND(ISNUMBER(P22),ISNUMBER(I22),ISNUMBER(D22)),D22,0) -> 0
A23: FUTSHOLIS | B23: Short Fútbol Playmaker Liso | C23: Juego | D23: 55 | E23: SM-01 · Short Fútbol | F23: CIRE BLANCO | I23: 8059 | J23: Por confirmar | K23: El short de fútbol aún no tiene molde en el catálogo. | L23: =IF(OR(B23="",E23=""),"",IFERROR(INDEX(Recetas!$R$5:$R$84,MATCH($E23,Recetas!$A$5:$A$84,0))*IFERROR(INDEX(Precios!$F$5:$F$120,MATCH(F23,Precios!$A$5:$A$120,0)),"")+IF(N(INDEX(Recetas!$S$5:$S$84,MATCH($E23,Recetas!$A$5:$A$84,0)))=0,0,INDEX(Recetas!$S$5:$S$84,MATCH($E23,Recetas!$A$5:$A$84,0))*IFERROR(INDEX(Precios!$F$5:$F$120,MATCH(G23,Precios!$A$5:$A$120,0)),"")),"")) | M23: =IF(OR(B23="",E23=""),"",IFERROR(N(INDEX(Recetas!$L$5:$L$84,MATCH($E23,Recetas!$A$5:$A$84,0)))*Parametros!$B$27,"")) -> 0 | N23: =IF(OR(B23="",E23=""),"",IFERROR(INDEX(Confeccion!$B$5:$B$100,MATCH(INDEX(Recetas!$M$5:$M$84,MATCH($E23,Recetas!$A$5:$A$84,0)),Confeccion!$A$5:$A$100,0)),"")) -> 1700 | O23: =IF(OR(B23="",E23=""),"",IFERROR(N(INDEX(Recetas!$O$5:$O$84,MATCH($E23,Recetas!$A$5:$A$84,0)))*INDEX(Precios!$D$5:$D$120,MATCH(INDEX(Recetas!$N$5:$N$84,MATCH($E23,Recetas!$A$5:$A$84,0)),Precios!$A$5:$A$120,0)),0)) -> 0 | P23: =IF(OR(B23="",E23=""),"",IF(AND(IFERROR(INDEX(Recetas!$T$5:$T$84,MATCH($E23,Recetas!$A$5:$A$84,0))="Lista",FALSE()),ISNUMBER(L23),ISNUMBER(M23),ISNUMBER(N23),N(N23)>0),L23+M23+N23+N(O23)+N(H23),"")) | Q23: =IF(AND(ISNUMBER(P23),ISNUMBER(I23)),I23*Parametros!$B$12,"") | R23: =IF(AND(ISNUMBER(P23),ISNUMBER(I23)),I23*Parametros!$B$13,"") | S23: =IF(AND(ISNUMBER(P23),ISNUMBER(I23)),I23-P23-Q23-R23,"") | T23: =IF(AND(ISNUMBER(P23),ISNUMBER(I23)),S23/I23,"") | U23: =IF(OR(NOT(ISNUMBER(P23)),Parametros!$B$14>=1),"",P23/(1-Parametros!$B$14)) | V23: =IF(OR(NOT(ISNUMBER(P23)),Parametros!$B$14+Parametros!$B$18>=1),"",P23/(1-Parametros!$B$14-Parametros!$B$18)) | W23: =IF(B23="","",IF(E23="","SIN RECETA",IF(NOT(ISNUMBER(P23)),"FALTAN DATOS",IF(NOT(ISNUMBER(I23)),"FALTA PRECIO",IF(S23<0,"PIERDE",IF(T23<Parametros!$B$18,"BAJO META","OK")))))) -> FALTAN DATOS | X23: =IF(B23="","",IF(E23="","Elegir receta (molde). ",IF(ISNA(MATCH(E23,Recetas!$A$5:$A$84,0)),"La receta no existe. ",IF(IFERROR(INDEX(Recetas!$T$5:$T$84,MATCH($E23,Recetas!$A$5:$A$84,0))="Lista",FALSE()),"","Receta "&E23&": "&INDEX(Recetas!$T$5:$T$84,MATCH($E23,Recetas!$A$5:$A$84,0)))))&IF(F23="","Elegir tela. ",IF(IFERROR(INDEX(Precios!$F$5:$F$120,MATCH(F23,Precios!$A$5:$A$120,0)),"")="","Tela sin $/metro (falta rendimiento o precio). ",""))&IF(AND(E23<>"",N(IFERROR(INDEX(Recetas!$S$5:$S$84,MATCH($E23,Recetas!$A$5:$A$84,0)),0))>0,G23=""),"Elegir tela 2. ","")&IF(NOT(ISNUMBER(I23)),"Precio de venta.","")) -> Receta SM-01 · Short Fútbol: Rendimiento de CIRE BLANCO (m/kg) en Precios. Tela sin $/metro (falta rendimiento o precio). | Y23: =IF(AND(ISNUMBER(P23),ISNUMBER(I23),ISNUMBER(D23)),P23*D23,0) -> 0 | Z23: =IF(AND(ISNUMBER(P23),ISNUMBER(I23),ISNUMBER(D23)),I23*D23,0) -> 0 | AA23: =IF(AND(ISNUMBER(P23),ISNUMBER(I23),ISNUMBER(D23)),D23,0) -> 0
A24: VOLFEMCSUBPROV | B24: Camiseta Voley fem Pro Playmaker, V | C24: Juego | D24: 50 | I24: 19244 | J24: Por confirmar | K24: Sin receta: elige el molde que usa (o crea su receta en "Recetas") y la tela. | L24: =IF(OR(B24="",E24=""),"",IFERROR(INDEX(Recetas!$R$5:$R$84,MATCH($E24,Recetas!$A$5:$A$84,0))*IFERROR(INDEX(Precios!$F$5:$F$120,MATCH(F24,Precios!$A$5:$A$120,0)),"")+IF(N(INDEX(Recetas!$S$5:$S$84,MATCH($E24,Recetas!$A$5:$A$84,0)))=0,0,INDEX(Recetas!$S$5:$S$84,MATCH($E24,Recetas!$A$5:$A$84,0))*IFERROR(INDEX(Precios!$F$5:$F$120,MATCH(G24,Precios!$A$5:$A$120,0)),"")),"")) | M24: =IF(OR(B24="",E24=""),"",IFERROR(N(INDEX(Recetas!$L$5:$L$84,MATCH($E24,Recetas!$A$5:$A$84,0)))*Parametros!$B$27,"")) | N24: =IF(OR(B24="",E24=""),"",IFERROR(INDEX(Confeccion!$B$5:$B$100,MATCH(INDEX(Recetas!$M$5:$M$84,MATCH($E24,Recetas!$A$5:$A$84,0)),Confeccion!$A$5:$A$100,0)),"")) | O24: =IF(OR(B24="",E24=""),"",IFERROR(N(INDEX(Recetas!$O$5:$O$84,MATCH($E24,Recetas!$A$5:$A$84,0)))*INDEX(Precios!$D$5:$D$120,MATCH(INDEX(Recetas!$N$5:$N$84,MATCH($E24,Recetas!$A$5:$A$84,0)),Precios!$A$5:$A$120,0)),0)) | P24: =IF(OR(B24="",E24=""),"",IF(AND(IFERROR(INDEX(Recetas!$T$5:$T$84,MATCH($E24,Recetas!$A$5:$A$84,0))="Lista",FALSE()),ISNUMBER(L24),ISNUMBER(M24),ISNUMBER(N24),N(N24)>0),L24+M24+N24+N(O24)+N(H24),"")) | Q24: =IF(AND(ISNUMBER(P24),ISNUMBER(I24)),I24*Parametros!$B$12,"") | R24: =IF(AND(ISNUMBER(P24),ISNUMBER(I24)),I24*Parametros!$B$13,"") | S24: =IF(AND(ISNUMBER(P24),ISNUMBER(I24)),I24-P24-Q24-R24,"") | T24: =IF(AND(ISNUMBER(P24),ISNUMBER(I24)),S24/I24,"") | U24: =IF(OR(NOT(ISNUMBER(P24)),Parametros!$B$14>=1),"",P24/(1-Parametros!$B$14)) | V24: =IF(OR(NOT(ISNUMBER(P24)),Parametros!$B$14+Parametros!$B$18>=1),"",P24/(1-Parametros!$B$14-Parametros!$B$18)) | W24: =IF(B24="","",IF(E24="","SIN RECETA",IF(NOT(ISNUMBER(P24)),"FALTAN DATOS",IF(NOT(ISNUMBER(I24)),"FALTA PRECIO",IF(S24<0,"PIERDE",IF(T24<Parametros!$B$18,"BAJO META","OK")))))) -> SIN RECETA | X24: =IF(B24="","",IF(E24="","Elegir receta (molde). ",IF(ISNA(MATCH(E24,Recetas!$A$5:$A$84,0)),"La receta no existe. ",IF(IFERROR(INDEX(Recetas!$T$5:$T$84,MATCH($E24,Recetas!$A$5:$A$84,0))="Lista",FALSE()),"","Receta "&E24&": "&INDEX(Recetas!$T$5:$T$84,MATCH($E24,Recetas!$A$5:$A$84,0)))))&IF(F24="","Elegir tela. ",IF(IFERROR(INDEX(Precios!$F$5:$F$120,MATCH(F24,Precios!$A$5:$A$120,0)),"")="","Tela sin $/metro (falta rendimiento o precio). ",""))&IF(AND(E24<>"",N(IFERROR(INDEX(Recetas!$S$5:$S$84,MATCH($E24,Recetas!$A$5:$A$84,0)),0))>0,G24=""),"Elegir tela 2. ","")&IF(NOT(ISNUMBER(I24)),"Precio de venta.","")) -> Elegir receta (molde). Elegir tela. | Y24: =IF(AND(ISNUMBER(P24),ISNUMBER(I24),ISNUMBER(D24)),P24*D24,0) -> 0 | Z24: =IF(AND(ISNUMBER(P24),ISNUMBER(I24),ISNUMBER(D24)),I24*D24,0) -> 0 | AA24: =IF(AND(ISNUMBER(P24),ISNUMBER(I24),ISNUMBER(D24)),D24,0) -> 0
A25: MDPTSUB | B25: PETO ENTRENAMIENTO SUB | C25: Juego | D25: 48 | I25: 8319 | J25: Por confirmar | K25: Sin receta: elige el molde que usa (o crea su receta en "Recetas") y la tela. | L25: =IF(OR(B25="",E25=""),"",IFERROR(INDEX(Recetas!$R$5:$R$84,MATCH($E25,Recetas!$A$5:$A$84,0))*IFERROR(INDEX(Precios!$F$5:$F$120,MATCH(F25,Precios!$A$5:$A$120,0)),"")+IF(N(INDEX(Recetas!$S$5:$S$84,MATCH($E25,Recetas!$A$5:$A$84,0)))=0,0,INDEX(Recetas!$S$5:$S$84,MATCH($E25,Recetas!$A$5:$A$84,0))*IFERROR(INDEX(Precios!$F$5:$F$120,MATCH(G25,Precios!$A$5:$A$120,0)),"")),"")) | M25: =IF(OR(B25="",E25=""),"",IFERROR(N(INDEX(Recetas!$L$5:$L$84,MATCH($E25,Recetas!$A$5:$A$84,0)))*Parametros!$B$27,"")) | N25: =IF(OR(B25="",E25=""),"",IFERROR(INDEX(Confeccion!$B$5:$B$100,MATCH(INDEX(Recetas!$M$5:$M$84,MATCH($E25,Recetas!$A$5:$A$84,0)),Confeccion!$A$5:$A$100,0)),"")) | O25: =IF(OR(B25="",E25=""),"",IFERROR(N(INDEX(Recetas!$O$5:$O$84,MATCH($E25,Recetas!$A$5:$A$84,0)))*INDEX(Precios!$D$5:$D$120,MATCH(INDEX(Recetas!$N$5:$N$84,MATCH($E25,Recetas!$A$5:$A$84,0)),Precios!$A$5:$A$120,0)),0)) | P25: =IF(OR(B25="",E25=""),"",IF(AND(IFERROR(INDEX(Recetas!$T$5:$T$84,MATCH($E25,Recetas!$A$5:$A$84,0))="Lista",FALSE()),ISNUMBER(L25),ISNUMBER(M25),ISNUMBER(N25),N(N25)>0),L25+M25+N25+N(O25)+N(H25),"")) | Q25: =IF(AND(ISNUMBER(P25),ISNUMBER(I25)),I25*Parametros!$B$12,"") | R25: =IF(AND(ISNUMBER(P25),ISNUMBER(I25)),I25*Parametros!$B$13,"") | S25: =IF(AND(ISNUMBER(P25),ISNUMBER(I25)),I25-P25-Q25-R25,"") | T25: =IF(AND(ISNUMBER(P25),ISNUMBER(I25)),S25/I25,"") | U25: =IF(OR(NOT(ISNUMBER(P25)),Parametros!$B$14>=1),"",P25/(1-Parametros!$B$14)) | V25: =IF(OR(NOT(ISNUMBER(P25)),Parametros!$B$14+Parametros!$B$18>=1),"",P25/(1-Parametros!$B$14-Parametros!$B$18)) | W25: =IF(B25="","",IF(E25="","SIN RECETA",IF(NOT(ISNUMBER(P25)),"FALTAN DATOS",IF(NOT(ISNUMBER(I25)),"FALTA PRECIO",IF(S25<0,"PIERDE",IF(T25<Parametros!$B$18,"BAJO META","OK")))))) -> SIN RECETA | X25: =IF(B25="","",IF(E25="","Elegir receta (molde). ",IF(ISNA(MATCH(E25,Recetas!$A$5:$A$84,0)),"La receta no existe. ",IF(IFERROR(INDEX(Recetas!$T$5:$T$84,MATCH($E25,Recetas!$A$5:$A$84,0))="Lista",FALSE()),"","Receta "&E25&": "&INDEX(Recetas!$T$5:$T$84,MATCH($E25,Recetas!$A$5:$A$84,0)))))&IF(F25="","Elegir tela. ",IF(IFERROR(INDEX(Precios!$F$5:$F$120,MATCH(F25,Precios!$A$5:$A$120,0)),"")="","Tela sin $/metro (falta rendimiento o precio). ",""))&IF(AND(E25<>"",N(IFERROR(INDEX(Recetas!$S$5:$S$84,MATCH($E25,Recetas!$A$5:$A$84,0)),0))>0,G25=""),"Elegir tela 2. ","")&IF(NOT(ISNUMBER(I25)),"Precio de venta.","")) -> Elegir receta (molde). Elegir tela. | Y25: =IF(AND(ISNUMBER(P25),ISNUMBER(I25),ISNUMBER(D25)),P25*D25,0) -> 0 | Z25: =IF(AND(ISNUMBER(P25),ISNUMBER(I25),ISNUMBER(D25)),I25*D25,0) -> 0 | AA25: =IF(AND(ISNUMBER(P25),ISNUMBER(I25),ISNUMBER(D25)),D25,0) -> 0
A26: MDCSUBOVA | B26: Polera Playmaker, Cuello Oval s/mangas | C26: Juego | D26: 48 | I26: 16723 | J26: Por confirmar | K26: Sin receta: elige el molde que usa (o crea su receta en "Recetas") y la tela. | L26: =IF(OR(B26="",E26=""),"",IFERROR(INDEX(Recetas!$R$5:$R$84,MATCH($E26,Recetas!$A$5:$A$84,0))*IFERROR(INDEX(Precios!$F$5:$F$120,MATCH(F26,Precios!$A$5:$A$120,0)),"")+IF(N(INDEX(Recetas!$S$5:$S$84,MATCH($E26,Recetas!$A$5:$A$84,0)))=0,0,INDEX(Recetas!$S$5:$S$84,MATCH($E26,Recetas!$A$5:$A$84,0))*IFERROR(INDEX(Precios!$F$5:$F$120,MATCH(G26,Precios!$A$5:$A$120,0)),"")),"")) | M26: =IF(OR(B26="",E26=""),"",IFERROR(N(INDEX(Recetas!$L$5:$L$84,MATCH($E26,Recetas!$A$5:$A$84,0)))*Parametros!$B$27,"")) | N26: =IF(OR(B26="",E26=""),"",IFERROR(INDEX(Confeccion!$B$5:$B$100,MATCH(INDEX(Recetas!$M$5:$M$84,MATCH($E26,Recetas!$A$5:$A$84,0)),Confeccion!$A$5:$A$100,0)),"")) | O26: =IF(OR(B26="",E26=""),"",IFERROR(N(INDEX(Recetas!$O$5:$O$84,MATCH($E26,Recetas!$A$5:$A$84,0)))*INDEX(Precios!$D$5:$D$120,MATCH(INDEX(Recetas!$N$5:$N$84,MATCH($E26,Recetas!$A$5:$A$84,0)),Precios!$A$5:$A$120,0)),0)) | P26: =IF(OR(B26="",E26=""),"",IF(AND(IFERROR(INDEX(Recetas!$T$5:$T$84,MATCH($E26,Recetas!$A$5:$A$84,0))="Lista",FALSE()),ISNUMBER(L26),ISNUMBER(M26),ISNUMBER(N26),N(N26)>0),L26+M26+N26+N(O26)+N(H26),"")) | Q26: =IF(AND(ISNUMBER(P26),ISNUMBER(I26)),I26*Parametros!$B$12,"") | R26: =IF(AND(ISNUMBER(P26),ISNUMBER(I26)),I26*Parametros!$B$13,"") | S26: =IF(AND(ISNUMBER(P26),ISNUMBER(I26)),I26-P26-Q26-R26,"") | T26: =IF(AND(ISNUMBER(P26),ISNUMBER(I26)),S26/I26,"") | U26: =IF(OR(NOT(ISNUMBER(P26)),Parametros!$B$14>=1),"",P26/(1-Parametros!$B$14)) | V26: =IF(OR(NOT(ISNUMBER(P26)),Parametros!$B$14+Parametros!$B$18>=1),"",P26/(1-Parametros!$B$14-Parametros!$B$18)) | W26: =IF(B26="","",IF(E26="","SIN RECETA",IF(NOT(ISNUMBER(P26)),"FALTAN DATOS",IF(NOT(ISNUMBER(I26)),"FALTA PRECIO",IF(S26<0,"PIERDE",IF(T26<Parametros!$B$18,"BAJO META","OK")))))) -> SIN RECETA | X26: =IF(B26="","",IF(E26="","Elegir receta (molde). ",IF(ISNA(MATCH(E26,Recetas!$A$5:$A$84,0)),"La receta no existe. ",IF(IFERROR(INDEX(Recetas!$T$5:$T$84,MATCH($E26,Recetas!$A$5:$A$84,0))="Lista",FALSE()),"","Receta "&E26&": "&INDEX(Recetas!$T$5:$T$84,MATCH($E26,Recetas!$A$5:$A$84,0)))))&IF(F26="","Elegir tela. ",IF(IFERROR(INDEX(Precios!$F$5:$F$120,MATCH(F26,Precios!$A$5:$A$120,0)),"")="","Tela sin $/metro (falta rendimiento o precio). ",""))&IF(AND(E26<>"",N(IFERROR(INDEX(Recetas!$S$5:$S$84,MATCH($E26,Recetas!$A$5:$A$84,0)),0))>0,G26=""),"Elegir tela 2. ","")&IF(NOT(ISNUMBER(I26)),"Precio de venta.","")) -> Elegir receta (molde). Elegir tela. | Y26: =IF(AND(ISNUMBER(P26),ISNUMBER(I26),ISNUMBER(D26)),P26*D26,0) -> 0 | Z26: =IF(AND(ISNUMBER(P26),ISNUMBER(I26),ISNUMBER(D26)),I26*D26,0) -> 0 | AA26: =IF(AND(ISNUMBER(P26),ISNUMBER(I26),ISNUMBER(D26)),D26,0) -> 0
A27: SALHOOLIS | B27: Polerón Hoodie Playmaker liso | C27: Salida | D27: 47 | I27: 26134 | J27: Por confirmar | K27: Sin receta: elige el molde que usa (o crea su receta en "Recetas") y la tela. | L27: =IF(OR(B27="",E27=""),"",IFERROR(INDEX(Recetas!$R$5:$R$84,MATCH($E27,Recetas!$A$5:$A$84,0))*IFERROR(INDEX(Precios!$F$5:$F$120,MATCH(F27,Precios!$A$5:$A$120,0)),"")+IF(N(INDEX(Recetas!$S$5:$S$84,MATCH($E27,Recetas!$A$5:$A$84,0)))=0,0,INDEX(Recetas!$S$5:$S$84,MATCH($E27,Recetas!$A$5:$A$84,0))*IFERROR(INDEX(Precios!$F$5:$F$120,MATCH(G27,Precios!$A$5:$A$120,0)),"")),"")) | M27: =IF(OR(B27="",E27=""),"",IFERROR(N(INDEX(Recetas!$L$5:$L$84,MATCH($E27,Recetas!$A$5:$A$84,0)))*Parametros!$B$27,"")) | N27: =IF(OR(B27="",E27=""),"",IFERROR(INDEX(Confeccion!$B$5:$B$100,MATCH(INDEX(Recetas!$M$5:$M$84,MATCH($E27,Recetas!$A$5:$A$84,0)),Confeccion!$A$5:$A$100,0)),"")) | O27: =IF(OR(B27="",E27=""),"",IFERROR(N(INDEX(Recetas!$O$5:$O$84,MATCH($E27,Recetas!$A$5:$A$84,0)))*INDEX(Precios!$D$5:$D$120,MATCH(INDEX(Recetas!$N$5:$N$84,MATCH($E27,Recetas!$A$5:$A$84,0)),Precios!$A$5:$A$120,0)),0)) | P27: =IF(OR(B27="",E27=""),"",IF(AND(IFERROR(INDEX(Recetas!$T$5:$T$84,MATCH($E27,Recetas!$A$5:$A$84,0))="Lista",FALSE()),ISNUMBER(L27),ISNUMBER(M27),ISNUMBER(N27),N(N27)>0),L27+M27+N27+N(O27)+N(H27),"")) | Q27: =IF(AND(ISNUMBER(P27),ISNUMBER(I27)),I27*Parametros!$B$12,"") | R27: =IF(AND(ISNUMBER(P27),ISNUMBER(I27)),I27*Parametros!$B$13,"") | S27: =IF(AND(ISNUMBER(P27),ISNUMBER(I27)),I27-P27-Q27-R27,"") | T27: =IF(AND(ISNUMBER(P27),ISNUMBER(I27)),S27/I27,"") | U27: =IF(OR(NOT(ISNUMBER(P27)),Parametros!$B$14>=1),"",P27/(1-Parametros!$B$14)) | V27: =IF(OR(NOT(ISNUMBER(P27)),Parametros!$B$14+Parametros!$B$18>=1),"",P27/(1-Parametros!$B$14-Parametros!$B$18)) | W27: =IF(B27="","",IF(E27="","SIN RECETA",IF(NOT(ISNUMBER(P27)),"FALTAN DATOS",IF(NOT(ISNUMBER(I27)),"FALTA PRECIO",IF(S27<0,"PIERDE",IF(T27<Parametros!$B$18,"BAJO META","OK")))))) -> SIN RECETA | X27: =IF(B27="","",IF(E27="","Elegir receta (molde). ",IF(ISNA(MATCH(E27,Recetas!$A$5:$A$84,0)),"La receta no existe. ",IF(IFERROR(INDEX(Recetas!$T$5:$T$84,MATCH($E27,Recetas!$A$5:$A$84,0))="Lista",FALSE()),"","Receta "&E27&": "&INDEX(Recetas!$T$5:$T$84,MATCH($E27,Recetas!$A$5:$A$84,0)))))&IF(F27="","Elegir tela. ",IF(IFERROR(INDEX(Precios!$F$5:$F$120,MATCH(F27,Precios!$A$5:$A$120,0)),"")="","Tela sin $/metro (falta rendimiento o precio). ",""))&IF(AND(E27<>"",N(IFERROR(INDEX(Recetas!$S$5:$S$84,MATCH($E27,Recetas!$A$5:$A$84,0)),0))>0,G27=""),"Elegir tela 2. ","")&IF(NOT(ISNUMBER(I27)),"Precio de venta.","")) -> Elegir receta (molde). Elegir tela. | Y27: =IF(AND(ISNUMBER(P27),ISNUMBER(I27),ISNUMBER(D27)),P27*D27,0) -> 0 | Z27: =IF(AND(ISNUMBER(P27),ISNUMBER(I27),ISNUMBER(D27)),I27*D27,0) -> 0 | AA27: =IF(AND(ISNUMBER(P27),ISNUMBER(I27),ISNUMBER(D27)),D27,0) -> 0
A28: CSUBRUGSFBLANCA | B28: CAMISETA DE RUGBY STADE FRANCAIS ANIVERSARIO (BLANCA) | C28: Juego | D28: 44 | I28: 27605 | J28: Por confirmar | K28: Sin receta: elige el molde que usa (o crea su receta en "Recetas") y la tela. | L28: =IF(OR(B28="",E28=""),"",IFERROR(INDEX(Recetas!$R$5:$R$84,MATCH($E28,Recetas!$A$5:$A$84,0))*IFERROR(INDEX(Precios!$F$5:$F$120,MATCH(F28,Precios!$A$5:$A$120,0)),"")+IF(N(INDEX(Recetas!$S$5:$S$84,MATCH($E28,Recetas!$A$5:$A$84,0)))=0,0,INDEX(Recetas!$S$5:$S$84,MATCH($E28,Recetas!$A$5:$A$84,0))*IFERROR(INDEX(Precios!$F$5:$F$120,MATCH(G28,Precios!$A$5:$A$120,0)),"")),"")) | M28: =IF(OR(B28="",E28=""),"",IFERROR(N(INDEX(Recetas!$L$5:$L$84,MATCH($E28,Recetas!$A$5:$A$84,0)))*Parametros!$B$27,"")) | N28: =IF(OR(B28="",E28=""),"",IFERROR(INDEX(Confeccion!$B$5:$B$100,MATCH(INDEX(Recetas!$M$5:$M$84,MATCH($E28,Recetas!$A$5:$A$84,0)),Confeccion!$A$5:$A$100,0)),"")) | O28: =IF(OR(B28="",E28=""),"",IFERROR(N(INDEX(Recetas!$O$5:$O$84,MATCH($E28,Recetas!$A$5:$A$84,0)))*INDEX(Precios!$D$5:$D$120,MATCH(INDEX(Recetas!$N$5:$N$84,MATCH($E28,Recetas!$A$5:$A$84,0)),Precios!$A$5:$A$120,0)),0)) | P28: =IF(OR(B28="",E28=""),"",IF(AND(IFERROR(INDEX(Recetas!$T$5:$T$84,MATCH($E28,Recetas!$A$5:$A$84,0))="Lista",FALSE()),ISNUMBER(L28),ISNUMBER(M28),ISNUMBER(N28),N(N28)>0),L28+M28+N28+N(O28)+N(H28),"")) | Q28: =IF(AND(ISNUMBER(P28),ISNUMBER(I28)),I28*Parametros!$B$12,"") | R28: =IF(AND(ISNUMBER(P28),ISNUMBER(I28)),I28*Parametros!$B$13,"") | S28: =IF(AND(ISNUMBER(P28),ISNUMBER(I28)),I28-P28-Q28-R28,"") | T28: =IF(AND(ISNUMBER(P28),ISNUMBER(I28)),S28/I28,"") | U28: =IF(OR(NOT(ISNUMBER(P28)),Parametros!$B$14>=1),"",P28/(1-Parametros!$B$14)) | V28: =IF(OR(NOT(ISNUMBER(P28)),Parametros!$B$14+Parametros!$B$18>=1),"",P28/(1-Parametros!$B$14-Parametros!$B$18)) | W28: =IF(B28="","",IF(E28="","SIN RECETA",IF(NOT(ISNUMBER(P28)),"FALTAN DATOS",IF(NOT(ISNUMBER(I28)),"FALTA PRECIO",IF(S28<0,"PIERDE",IF(T28<Parametros!$B$18,"BAJO META","OK")))))) -> SIN RECETA | X28: =IF(B28="","",IF(E28="","Elegir receta (molde). ",IF(ISNA(MATCH(E28,Recetas!$A$5:$A$84,0)),"La receta no existe. ",IF(IFERROR(INDEX(Recetas!$T$5:$T$84,MATCH($E28,Recetas!$A$5:$A$84,0))="Lista",FALSE()),"","Receta "&E28&": "&INDEX(Recetas!$T$5:$T$84,MATCH($E28,Recetas!$A$5:$A$84,0)))))&IF(F28="","Elegir tela. ",IF(IFERROR(INDEX(Precios!$F$5:$F$120,MATCH(F28,Precios!$A$5:$A$120,0)),"")="","Tela sin $/metro (falta rendimiento o precio). ",""))&IF(AND(E28<>"",N(IFERROR(INDEX(Recetas!$S$5:$S$84,MATCH($E28,Recetas!$A$5:$A$84,0)),0))>0,G28=""),"Elegir tela 2. ","")&IF(NOT(ISNUMBER(I28)),"Precio de venta.","")) -> Elegir receta (molde). Elegir tela. | Y28: =IF(AND(ISNUMBER(P28),ISNUMBER(I28),ISNUMBER(D28)),P28*D28,0) -> 0 | Z28: =IF(AND(ISNUMBER(P28),ISNUMBER(I28),ISNUMBER(D28)),I28*D28,0) -> 0 | AA28: =IF(AND(ISNUMBER(P28),ISNUMBER(I28),ISNUMBER(D28)),D28,0) -> 0
A29: SAL-POL-3C | B29: Polerón 3C Playmaker Algodón Cierre | C29: Salida | D29: 40 | I29: 32689 | J29: Por confirmar | K29: Sin receta: elige el molde que usa (o crea su receta en "Recetas") y la tela. | L29: =IF(OR(B29="",E29=""),"",IFERROR(INDEX(Recetas!$R$5:$R$84,MATCH($E29,Recetas!$A$5:$A$84,0))*IFERROR(INDEX(Precios!$F$5:$F$120,MATCH(F29,Precios!$A$5:$A$120,0)),"")+IF(N(INDEX(Recetas!$S$5:$S$84,MATCH($E29,Recetas!$A$5:$A$84,0)))=0,0,INDEX(Recetas!$S$5:$S$84,MATCH($E29,Recetas!$A$5:$A$84,0))*IFERROR(INDEX(Precios!$F$5:$F$120,MATCH(G29,Precios!$A$5:$A$120,0)),"")),"")) | M29: =IF(OR(B29="",E29=""),"",IFERROR(N(INDEX(Recetas!$L$5:$L$84,MATCH($E29,Recetas!$A$5:$A$84,0)))*Parametros!$B$27,"")) | N29: =IF(OR(B29="",E29=""),"",IFERROR(INDEX(Confeccion!$B$5:$B$100,MATCH(INDEX(Recetas!$M$5:$M$84,MATCH($E29,Recetas!$A$5:$A$84,0)),Confeccion!$A$5:$A$100,0)),"")) | O29: =IF(OR(B29="",E29=""),"",IFERROR(N(INDEX(Recetas!$O$5:$O$84,MATCH($E29,Recetas!$A$5:$A$84,0)))*INDEX(Precios!$D$5:$D$120,MATCH(INDEX(Recetas!$N$5:$N$84,MATCH($E29,Recetas!$A$5:$A$84,0)),Precios!$A$5:$A$120,0)),0)) | P29: =IF(OR(B29="",E29=""),"",IF(AND(IFERROR(INDEX(Recetas!$T$5:$T$84,MATCH($E29,Recetas!$A$5:$A$84,0))="Lista",FALSE()),ISNUMBER(L29),ISNUMBER(M29),ISNUMBER(N29),N(N29)>0),L29+M29+N29+N(O29)+N(H29),"")) | Q29: =IF(AND(ISNUMBER(P29),ISNUMBER(I29)),I29*Parametros!$B$12,"") | R29: =IF(AND(ISNUMBER(P29),ISNUMBER(I29)),I29*Parametros!$B$13,"") | S29: =IF(AND(ISNUMBER(P29),ISNUMBER(I29)),I29-P29-Q29-R29,"") | T29: =IF(AND(ISNUMBER(P29),ISNUMBER(I29)),S29/I29,"") | U29: =IF(OR(NOT(ISNUMBER(P29)),Parametros!$B$14>=1),"",P29/(1-Parametros!$B$14)) | V29: =IF(OR(NOT(ISNUMBER(P29)),Parametros!$B$14+Parametros!$B$18>=1),"",P29/(1-Parametros!$B$14-Parametros!$B$18)) | W29: =IF(B29="","",IF(E29="","SIN RECETA",IF(NOT(ISNUMBER(P29)),"FALTAN DATOS",IF(NOT(ISNUMBER(I29)),"FALTA PRECIO",IF(S29<0,"PIERDE",IF(T29<Parametros!$B$18,"BAJO META","OK")))))) -> SIN RECETA | X29: =IF(B29="","",IF(E29="","Elegir receta (molde). ",IF(ISNA(MATCH(E29,Recetas!$A$5:$A$84,0)),"La receta no existe. ",IF(IFERROR(INDEX(Recetas!$T$5:$T$84,MATCH($E29,Recetas!$A$5:$A$84,0))="Lista",FALSE()),"","Receta "&E29&": "&INDEX(Recetas!$T$5:$T$84,MATCH($E29,Recetas!$A$5:$A$84,0)))))&IF(F29="","Elegir tela. ",IF(IFERROR(INDEX(Precios!$F$5:$F$120,MATCH(F29,Precios!$A$5:$A$120,0)),"")="","Tela sin $/metro (falta rendimiento o precio). ",""))&IF(AND(E29<>"",N(IFERROR(INDEX(Recetas!$S$5:$S$84,MATCH($E29,Recetas!$A$5:$A$84,0)),0))>0,G29=""),"Elegir tela 2. ","")&IF(NOT(ISNUMBER(I29)),"Precio de venta.","")) -> Elegir receta (molde). Elegir tela. | Y29: =IF(AND(ISNUMBER(P29),ISNUMBER(I29),ISNUMBER(D29)),P29*D29,0) -> 0 | Z29: =IF(AND(ISNUMBER(P29),ISNUMBER(I29),ISNUMBER(D29)),I29*D29,0) -> 0 | AA29: =IF(AND(ISNUMBER(P29),ISNUMBER(I29),ISNUMBER(D29)),D29,0) -> 0
A30: VOLMASC-CSUB-POL-CER | B30: Camiseta Voley masc Playmaker, Polo m/cero | C30: Juego | D30: 37 | I30: 17563 | J30: Por confirmar | K30: Sin receta: elige el molde que usa (o crea su receta en "Recetas") y la tela. | L30: =IF(OR(B30="",E30=""),"",IFERROR(INDEX(Recetas!$R$5:$R$84,MATCH($E30,Recetas!$A$5:$A$84,0))*IFERROR(INDEX(Precios!$F$5:$F$120,MATCH(F30,Precios!$A$5:$A$120,0)),"")+IF(N(INDEX(Recetas!$S$5:$S$84,MATCH($E30,Recetas!$A$5:$A$84,0)))=0,0,INDEX(Recetas!$S$5:$S$84,MATCH($E30,Recetas!$A$5:$A$84,0))*IFERROR(INDEX(Precios!$F$5:$F$120,MATCH(G30,Precios!$A$5:$A$120,0)),"")),"")) | M30: =IF(OR(B30="",E30=""),"",IFERROR(N(INDEX(Recetas!$L$5:$L$84,MATCH($E30,Recetas!$A$5:$A$84,0)))*Parametros!$B$27,"")) | N30: =IF(OR(B30="",E30=""),"",IFERROR(INDEX(Confeccion!$B$5:$B$100,MATCH(INDEX(Recetas!$M$5:$M$84,MATCH($E30,Recetas!$A$5:$A$84,0)),Confeccion!$A$5:$A$100,0)),"")) | O30: =IF(OR(B30="",E30=""),"",IFERROR(N(INDEX(Recetas!$O$5:$O$84,MATCH($E30,Recetas!$A$5:$A$84,0)))*INDEX(Precios!$D$5:$D$120,MATCH(INDEX(Recetas!$N$5:$N$84,MATCH($E30,Recetas!$A$5:$A$84,0)),Precios!$A$5:$A$120,0)),0)) | P30: =IF(OR(B30="",E30=""),"",IF(AND(IFERROR(INDEX(Recetas!$T$5:$T$84,MATCH($E30,Recetas!$A$5:$A$84,0))="Lista",FALSE()),ISNUMBER(L30),ISNUMBER(M30),ISNUMBER(N30),N(N30)>0),L30+M30+N30+N(O30)+N(H30),"")) | Q30: =IF(AND(ISNUMBER(P30),ISNUMBER(I30)),I30*Parametros!$B$12,"") | R30: =IF(AND(ISNUMBER(P30),ISNUMBER(I30)),I30*Parametros!$B$13,"") | S30: =IF(AND(ISNUMBER(P30),ISNUMBER(I30)),I30-P30-Q30-R30,"") | T30: =IF(AND(ISNUMBER(P30),ISNUMBER(I30)),S30/I30,"") | U30: =IF(OR(NOT(ISNUMBER(P30)),Parametros!$B$14>=1),"",P30/(1-Parametros!$B$14)) | V30: =IF(OR(NOT(ISNUMBER(P30)),Parametros!$B$14+Parametros!$B$18>=1),"",P30/(1-Parametros!$B$14-Parametros!$B$18)) | W30: =IF(B30="","",IF(E30="","SIN RECETA",IF(NOT(ISNUMBER(P30)),"FALTAN DATOS",IF(NOT(ISNUMBER(I30)),"FALTA PRECIO",IF(S30<0,"PIERDE",IF(T30<Parametros!$B$18,"BAJO META","OK")))))) -> SIN RECETA | X30: =IF(B30="","",IF(E30="","Elegir receta (molde). ",IF(ISNA(MATCH(E30,Recetas!$A$5:$A$84,0)),"La receta no existe. ",IF(IFERROR(INDEX(Recetas!$T$5:$T$84,MATCH($E30,Recetas!$A$5:$A$84,0))="Lista",FALSE()),"","Receta "&E30&": "&INDEX(Recetas!$T$5:$T$84,MATCH($E30,Recetas!$A$5:$A$84,0)))))&IF(F30="","Elegir tela. ",IF(IFERROR(INDEX(Precios!$F$5:$F$120,MATCH(F30,Precios!$A$5:$A$120,0)),"")="","Tela sin $/metro (falta rendimiento o precio). ",""))&IF(AND(E30<>"",N(IFERROR(INDEX(Recetas!$S$5:$S$84,MATCH($E30,Recetas!$A$5:$A$84,0)),0))>0,G30=""),"Elegir tela 2. ","")&IF(NOT(ISNUMBER(I30)),"Precio de venta.","")) -> Elegir receta (molde). Elegir tela. | Y30: =IF(AND(ISNUMBER(P30),ISNUMBER(I30),ISNUMBER(D30)),P30*D30,0) -> 0 | Z30: =IF(AND(ISNUMBER(P30),ISNUMBER(I30),ISNUMBER(D30)),I30*D30,0) -> 0 | AA30: =IF(AND(ISNUMBER(P30),ISNUMBER(I30),ISNUMBER(D30)),D30,0) -> 0
A31: SALPRKLIS | B31: Parka Lisa Playmaker | C31: Salida | D31: 37 | I31: 54022 | J31: Por confirmar | K31: Sin receta: elige el molde que usa (o crea su receta en "Recetas") y la tela. | L31: =IF(OR(B31="",E31=""),"",IFERROR(INDEX(Recetas!$R$5:$R$84,MATCH($E31,Recetas!$A$5:$A$84,0))*IFERROR(INDEX(Precios!$F$5:$F$120,MATCH(F31,Precios!$A$5:$A$120,0)),"")+IF(N(INDEX(Recetas!$S$5:$S$84,MATCH($E31,Recetas!$A$5:$A$84,0)))=0,0,INDEX(Recetas!$S$5:$S$84,MATCH($E31,Recetas!$A$5:$A$84,0))*IFERROR(INDEX(Precios!$F$5:$F$120,MATCH(G31,Precios!$A$5:$A$120,0)),"")),"")) | M31: =IF(OR(B31="",E31=""),"",IFERROR(N(INDEX(Recetas!$L$5:$L$84,MATCH($E31,Recetas!$A$5:$A$84,0)))*Parametros!$B$27,"")) | N31: =IF(OR(B31="",E31=""),"",IFERROR(INDEX(Confeccion!$B$5:$B$100,MATCH(INDEX(Recetas!$M$5:$M$84,MATCH($E31,Recetas!$A$5:$A$84,0)),Confeccion!$A$5:$A$100,0)),"")) | O31: =IF(OR(B31="",E31=""),"",IFERROR(N(INDEX(Recetas!$O$5:$O$84,MATCH($E31,Recetas!$A$5:$A$84,0)))*INDEX(Precios!$D$5:$D$120,MATCH(INDEX(Recetas!$N$5:$N$84,MATCH($E31,Recetas!$A$5:$A$84,0)),Precios!$A$5:$A$120,0)),0)) | P31: =IF(OR(B31="",E31=""),"",IF(AND(IFERROR(INDEX(Recetas!$T$5:$T$84,MATCH($E31,Recetas!$A$5:$A$84,0))="Lista",FALSE()),ISNUMBER(L31),ISNUMBER(M31),ISNUMBER(N31),N(N31)>0),L31+M31+N31+N(O31)+N(H31),"")) | Q31: =IF(AND(ISNUMBER(P31),ISNUMBER(I31)),I31*Parametros!$B$12,"") | R31: =IF(AND(ISNUMBER(P31),ISNUMBER(I31)),I31*Parametros!$B$13,"") | S31: =IF(AND(ISNUMBER(P31),ISNUMBER(I31)),I31-P31-Q31-R31,"") | T31: =IF(AND(ISNUMBER(P31),ISNUMBER(I31)),S31/I31,"") | U31: =IF(OR(NOT(ISNUMBER(P31)),Parametros!$B$14>=1),"",P31/(1-Parametros!$B$14)) | V31: =IF(OR(NOT(ISNUMBER(P31)),Parametros!$B$14+Parametros!$B$18>=1),"",P31/(1-Parametros!$B$14-Parametros!$B$18)) | W31: =IF(B31="","",IF(E31="","SIN RECETA",IF(NOT(ISNUMBER(P31)),"FALTAN DATOS",IF(NOT(ISNUMBER(I31)),"FALTA PRECIO",IF(S31<0,"PIERDE",IF(T31<Parametros!$B$18,"BAJO META","OK")))))) -> SIN RECETA | X31: =IF(B31="","",IF(E31="","Elegir receta (molde). ",IF(ISNA(MATCH(E31,Recetas!$A$5:$A$84,0)),"La receta no existe. ",IF(IFERROR(INDEX(Recetas!$T$5:$T$84,MATCH($E31,Recetas!$A$5:$A$84,0))="Lista",FALSE()),"","Receta "&E31&": "&INDEX(Recetas!$T$5:$T$84,MATCH($E31,Recetas!$A$5:$A$84,0)))))&IF(F31="","Elegir tela. ",IF(IFERROR(INDEX(Precios!$F$5:$F$120,MATCH(F31,Precios!$A$5:$A$120,0)),"")="","Tela sin $/metro (falta rendimiento o precio). ",""))&IF(AND(E31<>"",N(IFERROR(INDEX(Recetas!$S$5:$S$84,MATCH($E31,Recetas!$A$5:$A$84,0)),0))>0,G31=""),"Elegir tela 2. ","")&IF(NOT(ISNUMBER(I31)),"Precio de venta.","")) -> Elegir receta (molde). Elegir tela. | Y31: =IF(AND(ISNUMBER(P31),ISNUMBER(I31),ISNUMBER(D31)),P31*D31,0) -> 0 | Z31: =IF(AND(ISNUMBER(P31),ISNUMBER(I31),ISNUMBER(D31)),I31*D31,0) -> 0 | AA31: =IF(AND(ISNUMBER(P31),ISNUMBER(I31),ISNUMBER(D31)),D31,0) -> 0
A32: RUG-SHO-PRO | B32: Short Rugby Pro | C32: Juego | D32: 35 | E32: SM-02 · Short Rugby | F32: GABARDINA | I32: 14202 | J32: Por confirmar | K32: Pro puede gastar distinto: confirmar. | L32: =IF(OR(B32="",E32=""),"",IFERROR(INDEX(Recetas!$R$5:$R$84,MATCH($E32,Recetas!$A$5:$A$84,0))*IFERROR(INDEX(Precios!$F$5:$F$120,MATCH(F32,Precios!$A$5:$A$120,0)),"")+IF(N(INDEX(Recetas!$S$5:$S$84,MATCH($E32,Recetas!$A$5:$A$84,0)))=0,0,INDEX(Recetas!$S$5:$S$84,MATCH($E32,Recetas!$A$5:$A$84,0))*IFERROR(INDEX(Precios!$F$5:$F$120,MATCH(G32,Precios!$A$5:$A$120,0)),"")),"")) | M32: =IF(OR(B32="",E32=""),"",IFERROR(N(INDEX(Recetas!$L$5:$L$84,MATCH($E32,Recetas!$A$5:$A$84,0)))*Parametros!$B$27,"")) -> 0 | N32: =IF(OR(B32="",E32=""),"",IFERROR(INDEX(Confeccion!$B$5:$B$100,MATCH(INDEX(Recetas!$M$5:$M$84,MATCH($E32,Recetas!$A$5:$A$84,0)),Confeccion!$A$5:$A$100,0)),"")) -> 2200 | O32: =IF(OR(B32="",E32=""),"",IFERROR(N(INDEX(Recetas!$O$5:$O$84,MATCH($E32,Recetas!$A$5:$A$84,0)))*INDEX(Precios!$D$5:$D$120,MATCH(INDEX(Recetas!$N$5:$N$84,MATCH($E32,Recetas!$A$5:$A$84,0)),Precios!$A$5:$A$120,0)),0)) -> 0 | P32: =IF(OR(B32="",E32=""),"",IF(AND(IFERROR(INDEX(Recetas!$T$5:$T$84,MATCH($E32,Recetas!$A$5:$A$84,0))="Lista",FALSE()),ISNUMBER(L32),ISNUMBER(M32),ISNUMBER(N32),N(N32)>0),L32+M32+N32+N(O32)+N(H32),"")) | Q32: =IF(AND(ISNUMBER(P32),ISNUMBER(I32)),I32*Parametros!$B$12,"") | R32: =IF(AND(ISNUMBER(P32),ISNUMBER(I32)),I32*Parametros!$B$13,"") | S32: =IF(AND(ISNUMBER(P32),ISNUMBER(I32)),I32-P32-Q32-R32,"") | T32: =IF(AND(ISNUMBER(P32),ISNUMBER(I32)),S32/I32,"") | U32: =IF(OR(NOT(ISNUMBER(P32)),Parametros!$B$14>=1),"",P32/(1-Parametros!$B$14)) | V32: =IF(OR(NOT(ISNUMBER(P32)),Parametros!$B$14+Parametros!$B$18>=1),"",P32/(1-Parametros!$B$14-Parametros!$B$18)) | W32: =IF(B32="","",IF(E32="","SIN RECETA",IF(NOT(ISNUMBER(P32)),"FALTAN DATOS",IF(NOT(ISNUMBER(I32)),"FALTA PRECIO",IF(S32<0,"PIERDE",IF(T32<Parametros!$B$18,"BAJO META","OK")))))) -> FALTAN DATOS | X32: =IF(B32="","",IF(E32="","Elegir receta (molde). ",IF(ISNA(MATCH(E32,Recetas!$A$5:$A$84,0)),"La receta no existe. ",IF(IFERROR(INDEX(Recetas!$T$5:$T$84,MATCH($E32,Recetas!$A$5:$A$84,0))="Lista",FALSE()),"","Receta "&E32&": "&INDEX(Recetas!$T$5:$T$84,MATCH($E32,Recetas!$A$5:$A$84,0)))))&IF(F32="","Elegir tela. ",IF(IFERROR(INDEX(Precios!$F$5:$F$120,MATCH(F32,Precios!$A$5:$A$120,0)),"")="","Tela sin $/metro (falta rendimiento o precio). ",""))&IF(AND(E32<>"",N(IFERROR(INDEX(Recetas!$S$5:$S$84,MATCH($E32,Recetas!$A$5:$A$84,0)),0))>0,G32=""),"Elegir tela 2. ","")&IF(NOT(ISNUMBER(I32)),"Precio de venta.","")) -> Receta SM-02 · Short Rugby: Rendimiento de GABARDINA (m/kg) en Precios. Tela sin $/metro (falta rendimiento o precio). | Y32: =IF(AND(ISNUMBER(P32),ISNUMBER(I32),ISNUMBER(D32)),P32*D32,0) -> 0 | Z32: =IF(AND(ISNUMBER(P32),ISNUMBER(I32),ISNUMBER(D32)),I32*D32,0) -> 0 | AA32: =IF(AND(ISNUMBER(P32),ISNUMBER(I32),ISNUMBER(D32)),D32,0) -> 0
A33: SAL-POL-SUB | B33: Polerón Entrenamiento Sublim | C33: Salida | D33: 35 | I33: 27647 | J33: Por confirmar | K33: Sin receta: elige el molde que usa (o crea su receta en "Recetas") y la tela. | L33: =IF(OR(B33="",E33=""),"",IFERROR(INDEX(Recetas!$R$5:$R$84,MATCH($E33,Recetas!$A$5:$A$84,0))*IFERROR(INDEX(Precios!$F$5:$F$120,MATCH(F33,Precios!$A$5:$A$120,0)),"")+IF(N(INDEX(Recetas!$S$5:$S$84,MATCH($E33,Recetas!$A$5:$A$84,0)))=0,0,INDEX(Recetas!$S$5:$S$84,MATCH($E33,Recetas!$A$5:$A$84,0))*IFERROR(INDEX(Precios!$F$5:$F$120,MATCH(G33,Precios!$A$5:$A$120,0)),"")),"")) | M33: =IF(OR(B33="",E33=""),"",IFERROR(N(INDEX(Recetas!$L$5:$L$84,MATCH($E33,Recetas!$A$5:$A$84,0)))*Parametros!$B$27,"")) | N33: =IF(OR(B33="",E33=""),"",IFERROR(INDEX(Confeccion!$B$5:$B$100,MATCH(INDEX(Recetas!$M$5:$M$84,MATCH($E33,Recetas!$A$5:$A$84,0)),Confeccion!$A$5:$A$100,0)),"")) | O33: =IF(OR(B33="",E33=""),"",IFERROR(N(INDEX(Recetas!$O$5:$O$84,MATCH($E33,Recetas!$A$5:$A$84,0)))*INDEX(Precios!$D$5:$D$120,MATCH(INDEX(Recetas!$N$5:$N$84,MATCH($E33,Recetas!$A$5:$A$84,0)),Precios!$A$5:$A$120,0)),0)) | P33: =IF(OR(B33="",E33=""),"",IF(AND(IFERROR(INDEX(Recetas!$T$5:$T$84,MATCH($E33,Recetas!$A$5:$A$84,0))="Lista",FALSE()),ISNUMBER(L33),ISNUMBER(M33),ISNUMBER(N33),N(N33)>0),L33+M33+N33+N(O33)+N(H33),"")) | Q33: =IF(AND(ISNUMBER(P33),ISNUMBER(I33)),I33*Parametros!$B$12,"") | R33: =IF(AND(ISNUMBER(P33),ISNUMBER(I33)),I33*Parametros!$B$13,"") | S33: =IF(AND(ISNUMBER(P33),ISNUMBER(I33)),I33-P33-Q33-R33,"") | T33: =IF(AND(ISNUMBER(P33),ISNUMBER(I33)),S33/I33,"") | U33: =IF(OR(NOT(ISNUMBER(P33)),Parametros!$B$14>=1),"",P33/(1-Parametros!$B$14)) | V33: =IF(OR(NOT(ISNUMBER(P33)),Parametros!$B$14+Parametros!$B$18>=1),"",P33/(1-Parametros!$B$14-Parametros!$B$18)) | W33: =IF(B33="","",IF(E33="","SIN RECETA",IF(NOT(ISNUMBER(P33)),"FALTAN DATOS",IF(NOT(ISNUMBER(I33)),"FALTA PRECIO",IF(S33<0,"PIERDE",IF(T33<Parametros!$B$18,"BAJO META","OK")))))) -> SIN RECETA | X33: =IF(B33="","",IF(E33="","Elegir receta (molde). ",IF(ISNA(MATCH(E33,Recetas!$A$5:$A$84,0)),"La receta no existe. ",IF(IFERROR(INDEX(Recetas!$T$5:$T$84,MATCH($E33,Recetas!$A$5:$A$84,0))="Lista",FALSE()),"","Receta "&E33&": "&INDEX(Recetas!$T$5:$T$84,MATCH($E33,Recetas!$A$5:$A$84,0)))))&IF(F33="","Elegir tela. ",IF(IFERROR(INDEX(Precios!$F$5:$F$120,MATCH(F33,Precios!$A$5:$A$120,0)),"")="","Tela sin $/metro (falta rendimiento o precio). ",""))&IF(AND(E33<>"",N(IFERROR(INDEX(Recetas!$S$5:$S$84,MATCH($E33,Recetas!$A$5:$A$84,0)),0))>0,G33=""),"Elegir tela 2. ","")&IF(NOT(ISNUMBER(I33)),"Precio de venta.","")) -> Elegir receta (molde). Elegir tela. | Y33: =IF(AND(ISNUMBER(P33),ISNUMBER(I33),ISNUMBER(D33)),P33*D33,0) -> 0 | Z33: =IF(AND(ISNUMBER(P33),ISNUMBER(I33),ISNUMBER(D33)),I33*D33,0) -> 0 | AA33: =IF(AND(ISNUMBER(P33),ISNUMBER(I33),ISNUMBER(D33)),D33,0) -> 0
A34: RUGCSUBPER | B34: Camiseta Rugby Performance Pmk | C34: Juego | D34: 34 | I34: 19664 | J34: Por confirmar | K34: Sin receta: elige el molde que usa (o crea su receta en "Recetas") y la tela. | L34: =IF(OR(B34="",E34=""),"",IFERROR(INDEX(Recetas!$R$5:$R$84,MATCH($E34,Recetas!$A$5:$A$84,0))*IFERROR(INDEX(Precios!$F$5:$F$120,MATCH(F34,Precios!$A$5:$A$120,0)),"")+IF(N(INDEX(Recetas!$S$5:$S$84,MATCH($E34,Recetas!$A$5:$A$84,0)))=0,0,INDEX(Recetas!$S$5:$S$84,MATCH($E34,Recetas!$A$5:$A$84,0))*IFERROR(INDEX(Precios!$F$5:$F$120,MATCH(G34,Precios!$A$5:$A$120,0)),"")),"")) | M34: =IF(OR(B34="",E34=""),"",IFERROR(N(INDEX(Recetas!$L$5:$L$84,MATCH($E34,Recetas!$A$5:$A$84,0)))*Parametros!$B$27,"")) | N34: =IF(OR(B34="",E34=""),"",IFERROR(INDEX(Confeccion!$B$5:$B$100,MATCH(INDEX(Recetas!$M$5:$M$84,MATCH($E34,Recetas!$A$5:$A$84,0)),Confeccion!$A$5:$A$100,0)),"")) | O34: =IF(OR(B34="",E34=""),"",IFERROR(N(INDEX(Recetas!$O$5:$O$84,MATCH($E34,Recetas!$A$5:$A$84,0)))*INDEX(Precios!$D$5:$D$120,MATCH(INDEX(Recetas!$N$5:$N$84,MATCH($E34,Recetas!$A$5:$A$84,0)),Precios!$A$5:$A$120,0)),0)) | P34: =IF(OR(B34="",E34=""),"",IF(AND(IFERROR(INDEX(Recetas!$T$5:$T$84,MATCH($E34,Recetas!$A$5:$A$84,0))="Lista",FALSE()),ISNUMBER(L34),ISNUMBER(M34),ISNUMBER(N34),N(N34)>0),L34+M34+N34+N(O34)+N(H34),"")) | Q34: =IF(AND(ISNUMBER(P34),ISNUMBER(I34)),I34*Parametros!$B$12,"") | R34: =IF(AND(ISNUMBER(P34),ISNUMBER(I34)),I34*Parametros!$B$13,"") | S34: =IF(AND(ISNUMBER(P34),ISNUMBER(I34)),I34-P34-Q34-R34,"") | T34: =IF(AND(ISNUMBER(P34),ISNUMBER(I34)),S34/I34,"") | U34: =IF(OR(NOT(ISNUMBER(P34)),Parametros!$B$14>=1),"",P34/(1-Parametros!$B$14)) | V34: =IF(OR(NOT(ISNUMBER(P34)),Parametros!$B$14+Parametros!$B$18>=1),"",P34/(1-Parametros!$B$14-Parametros!$B$18)) | W34: =IF(B34="","",IF(E34="","SIN RECETA",IF(NOT(ISNUMBER(P34)),"FALTAN DATOS",IF(NOT(ISNUMBER(I34)),"FALTA PRECIO",IF(S34<0,"PIERDE",IF(T34<Parametros!$B$18,"BAJO META","OK")))))) -> SIN RECETA | X34: =IF(B34="","",IF(E34="","Elegir receta (molde). ",IF(ISNA(MATCH(E34,Recetas!$A$5:$A$84,0)),"La receta no existe. ",IF(IFERROR(INDEX(Recetas!$T$5:$T$84,MATCH($E34,Recetas!$A$5:$A$84,0))="Lista",FALSE()),"","Receta "&E34&": "&INDEX(Recetas!$T$5:$T$84,MATCH($E34,Recetas!$A$5:$A$84,0)))))&IF(F34="","Elegir tela. ",IF(IFERROR(INDEX(Precios!$F$5:$F$120,MATCH(F34,Precios!$A$5:$A$120,0)),"")="","Tela sin $/metro (falta rendimiento o precio). ",""))&IF(AND(E34<>"",N(IFERROR(INDEX(Recetas!$S$5:$S$84,MATCH($E34,Recetas!$A$5:$A$84,0)),0))>0,G34=""),"Elegir tela 2. ","")&IF(NOT(ISNUMBER(I34)),"Precio de venta.","")) -> Elegir receta (molde). Elegir tela. | Y34: =IF(AND(ISNUMBER(P34),ISNUMBER(I34),ISNUMBER(D34)),P34*D34,0) -> 0 | Z34: =IF(AND(ISNUMBER(P34),ISNUMBER(I34),ISNUMBER(D34)),I34*D34,0) -> 0 | AA34: =IF(AND(ISNUMBER(P34),ISNUMBER(I34),ISNUMBER(D34)),D34,0) -> 0
A35: FUTCSUBML | B35: Camiseta Fútbol Playmaker, m/l | C35: Juego | D35: 34 | E35: 02 · FUTHOMU01 | I35: 17563 | J35: Por confirmar | K35: Manga larga: suma su costo extra en "Extras". Elegir tela. | L35: =IF(OR(B35="",E35=""),"",IFERROR(INDEX(Recetas!$R$5:$R$84,MATCH($E35,Recetas!$A$5:$A$84,0))*IFERROR(INDEX(Precios!$F$5:$F$120,MATCH(F35,Precios!$A$5:$A$120,0)),"")+IF(N(INDEX(Recetas!$S$5:$S$84,MATCH($E35,Recetas!$A$5:$A$84,0)))=0,0,INDEX(Recetas!$S$5:$S$84,MATCH($E35,Recetas!$A$5:$A$84,0))*IFERROR(INDEX(Precios!$F$5:$F$120,MATCH(G35,Precios!$A$5:$A$120,0)),"")),"")) | M35: =IF(OR(B35="",E35=""),"",IFERROR(N(INDEX(Recetas!$L$5:$L$84,MATCH($E35,Recetas!$A$5:$A$84,0)))*Parametros!$B$27,"")) -> 0 | N35: =IF(OR(B35="",E35=""),"",IFERROR(INDEX(Confeccion!$B$5:$B$100,MATCH(INDEX(Recetas!$M$5:$M$84,MATCH($E35,Recetas!$A$5:$A$84,0)),Confeccion!$A$5:$A$100,0)),"")) -> 2000 | O35: =IF(OR(B35="",E35=""),"",IFERROR(N(INDEX(Recetas!$O$5:$O$84,MATCH($E35,Recetas!$A$5:$A$84,0)))*INDEX(Precios!$D$5:$D$120,MATCH(INDEX(Recetas!$N$5:$N$84,MATCH($E35,Recetas!$A$5:$A$84,0)),Precios!$A$5:$A$120,0)),0)) -> 0 | P35: =IF(OR(B35="",E35=""),"",IF(AND(IFERROR(INDEX(Recetas!$T$5:$T$84,MATCH($E35,Recetas!$A$5:$A$84,0))="Lista",FALSE()),ISNUMBER(L35),ISNUMBER(M35),ISNUMBER(N35),N(N35)>0),L35+M35+N35+N(O35)+N(H35),"")) | Q35: =IF(AND(ISNUMBER(P35),ISNUMBER(I35)),I35*Parametros!$B$12,"") | R35: =IF(AND(ISNUMBER(P35),ISNUMBER(I35)),I35*Parametros!$B$13,"") | S35: =IF(AND(ISNUMBER(P35),ISNUMBER(I35)),I35-P35-Q35-R35,"") | T35: =IF(AND(ISNUMBER(P35),ISNUMBER(I35)),S35/I35,"") | U35: =IF(OR(NOT(ISNUMBER(P35)),Parametros!$B$14>=1),"",P35/(1-Parametros!$B$14)) | V35: =IF(OR(NOT(ISNUMBER(P35)),Parametros!$B$14+Parametros!$B$18>=1),"",P35/(1-Parametros!$B$14-Parametros!$B$18)) | W35: =IF(B35="","",IF(E35="","SIN RECETA",IF(NOT(ISNUMBER(P35)),"FALTAN DATOS",IF(NOT(ISNUMBER(I35)),"FALTA PRECIO",IF(S35<0,"PIERDE",IF(T35<Parametros!$B$18,"BAJO META","OK")))))) -> FALTAN DATOS | X35: =IF(B35="","",IF(E35="","Elegir receta (molde). ",IF(ISNA(MATCH(E35,Recetas!$A$5:$A$84,0)),"La receta no existe. ",IF(IFERROR(INDEX(Recetas!$T$5:$T$84,MATCH($E35,Recetas!$A$5:$A$84,0))="Lista",FALSE()),"","Receta "&E35&": "&INDEX(Recetas!$T$5:$T$84,MATCH($E35,Recetas!$A$5:$A$84,0)))))&IF(F35="","Elegir tela. ",IF(IFERROR(INDEX(Precios!$F$5:$F$120,MATCH(F35,Precios!$A$5:$A$120,0)),"")="","Tela sin $/metro (falta rendimiento o precio). ",""))&IF(AND(E35<>"",N(IFERROR(INDEX(Recetas!$S$5:$S$84,MATCH($E35,Recetas!$A$5:$A$84,0)),0))>0,G35=""),"Elegir tela 2. ","")&IF(NOT(ISNUMBER(I35)),"Precio de venta.","")) -> Receta 02 · FUTHOMU01: Consumo de tela. Metros impresos. Elegir tela. | Y35: =IF(AND(ISNUMBER(P35),ISNUMBER(I35),ISNUMBER(D35)),P35*D35,0) -> 0 | Z35: =IF(AND(ISNUMBER(P35),ISNUMBER(I35),ISNUMBER(D35)),I35*D35,0) -> 0 | AA35: =IF(AND(ISNUMBER(P35),ISNUMBER(I35),ISNUMBER(D35)),D35,0) -> 0
A36: SALALMLLISA | B36: Camiseta Algodón Manga Larga Lisa | C36: Juego | D36: 31 | I36: 12521 | J36: Por confirmar | K36: Sin receta: elige el molde que usa (o crea su receta en "Recetas") y la tela. | L36: =IF(OR(B36="",E36=""),"",IFERROR(INDEX(Recetas!$R$5:$R$84,MATCH($E36,Recetas!$A$5:$A$84,0))*IFERROR(INDEX(Precios!$F$5:$F$120,MATCH(F36,Precios!$A$5:$A$120,0)),"")+IF(N(INDEX(Recetas!$S$5:$S$84,MATCH($E36,Recetas!$A$5:$A$84,0)))=0,0,INDEX(Recetas!$S$5:$S$84,MATCH($E36,Recetas!$A$5:$A$84,0))*IFERROR(INDEX(Precios!$F$5:$F$120,MATCH(G36,Precios!$A$5:$A$120,0)),"")),"")) | M36: =IF(OR(B36="",E36=""),"",IFERROR(N(INDEX(Recetas!$L$5:$L$84,MATCH($E36,Recetas!$A$5:$A$84,0)))*Parametros!$B$27,"")) | N36: =IF(OR(B36="",E36=""),"",IFERROR(INDEX(Confeccion!$B$5:$B$100,MATCH(INDEX(Recetas!$M$5:$M$84,MATCH($E36,Recetas!$A$5:$A$84,0)),Confeccion!$A$5:$A$100,0)),"")) | O36: =IF(OR(B36="",E36=""),"",IFERROR(N(INDEX(Recetas!$O$5:$O$84,MATCH($E36,Recetas!$A$5:$A$84,0)))*INDEX(Precios!$D$5:$D$120,MATCH(INDEX(Recetas!$N$5:$N$84,MATCH($E36,Recetas!$A$5:$A$84,0)),Precios!$A$5:$A$120,0)),0)) | P36: =IF(OR(B36="",E36=""),"",IF(AND(IFERROR(INDEX(Recetas!$T$5:$T$84,MATCH($E36,Recetas!$A$5:$A$84,0))="Lista",FALSE()),ISNUMBER(L36),ISNUMBER(M36),ISNUMBER(N36),N(N36)>0),L36+M36+N36+N(O36)+N(H36),"")) | Q36: =IF(AND(ISNUMBER(P36),ISNUMBER(I36)),I36*Parametros!$B$12,"") | R36: =IF(AND(ISNUMBER(P36),ISNUMBER(I36)),I36*Parametros!$B$13,"") | S36: =IF(AND(ISNUMBER(P36),ISNUMBER(I36)),I36-P36-Q36-R36,"") | T36: =IF(AND(ISNUMBER(P36),ISNUMBER(I36)),S36/I36,"") | U36: =IF(OR(NOT(ISNUMBER(P36)),Parametros!$B$14>=1),"",P36/(1-Parametros!$B$14)) | V36: =IF(OR(NOT(ISNUMBER(P36)),Parametros!$B$14+Parametros!$B$18>=1),"",P36/(1-Parametros!$B$14-Parametros!$B$18)) | W36: =IF(B36="","",IF(E36="","SIN RECETA",IF(NOT(ISNUMBER(P36)),"FALTAN DATOS",IF(NOT(ISNUMBER(I36)),"FALTA PRECIO",IF(S36<0,"PIERDE",IF(T36<Parametros!$B$18,"BAJO META","OK")))))) -> SIN RECETA | X36: =IF(B36="","",IF(E36="","Elegir receta (molde). ",IF(ISNA(MATCH(E36,Recetas!$A$5:$A$84,0)),"La receta no existe. ",IF(IFERROR(INDEX(Recetas!$T$5:$T$84,MATCH($E36,Recetas!$A$5:$A$84,0))="Lista",FALSE()),"","Receta "&E36&": "&INDEX(Recetas!$T$5:$T$84,MATCH($E36,Recetas!$A$5:$A$84,0)))))&IF(F36="","Elegir tela. ",IF(IFERROR(INDEX(Precios!$F$5:$F$120,MATCH(F36,Precios!$A$5:$A$120,0)),"")="","Tela sin $/metro (falta rendimiento o precio). ",""))&IF(AND(E36<>"",N(IFERROR(INDEX(Recetas!$S$5:$S$84,MATCH($E36,Recetas!$A$5:$A$84,0)),0))>0,G36=""),"Elegir tela 2. ","")&IF(NOT(ISNUMBER(I36)),"Precio de venta.","")) -> Elegir receta (molde). Elegir tela. | Y36: =IF(AND(ISNUMBER(P36),ISNUMBER(I36),ISNUMBER(D36)),P36*D36,0) -> 0 | Z36: =IF(AND(ISNUMBER(P36),ISNUMBER(I36),ISNUMBER(D36)),I36*D36,0) -> 0 | AA36: =IF(AND(ISNUMBER(P36),ISNUMBER(I36),ISNUMBER(D36)),D36,0) -> 0
A37: RUG-CSUB-PIQ | B37: Camiseta Rugby Playmaker, Vintage | C37: Juego | D37: 29 | I37: 21204 | J37: Por confirmar | K37: Sin receta: elige el molde que usa (o crea su receta en "Recetas") y la tela. | L37: =IF(OR(B37="",E37=""),"",IFERROR(INDEX(Recetas!$R$5:$R$84,MATCH($E37,Recetas!$A$5:$A$84,0))*IFERROR(INDEX(Precios!$F$5:$F$120,MATCH(F37,Precios!$A$5:$A$120,0)),"")+IF(N(INDEX(Recetas!$S$5:$S$84,MATCH($E37,Recetas!$A$5:$A$84,0)))=0,0,INDEX(Recetas!$S$5:$S$84,MATCH($E37,Recetas!$A$5:$A$84,0))*IFERROR(INDEX(Precios!$F$5:$F$120,MATCH(G37,Precios!$A$5:$A$120,0)),"")),"")) | M37: =IF(OR(B37="",E37=""),"",IFERROR(N(INDEX(Recetas!$L$5:$L$84,MATCH($E37,Recetas!$A$5:$A$84,0)))*Parametros!$B$27,"")) | N37: =IF(OR(B37="",E37=""),"",IFERROR(INDEX(Confeccion!$B$5:$B$100,MATCH(INDEX(Recetas!$M$5:$M$84,MATCH($E37,Recetas!$A$5:$A$84,0)),Confeccion!$A$5:$A$100,0)),"")) | O37: =IF(OR(B37="",E37=""),"",IFERROR(N(INDEX(Recetas!$O$5:$O$84,MATCH($E37,Recetas!$A$5:$A$84,0)))*INDEX(Precios!$D$5:$D$120,MATCH(INDEX(Recetas!$N$5:$N$84,MATCH($E37,Recetas!$A$5:$A$84,0)),Precios!$A$5:$A$120,0)),0)) | P37: =IF(OR(B37="",E37=""),"",IF(AND(IFERROR(INDEX(Recetas!$T$5:$T$84,MATCH($E37,Recetas!$A$5:$A$84,0))="Lista",FALSE()),ISNUMBER(L37),ISNUMBER(M37),ISNUMBER(N37),N(N37)>0),L37+M37+N37+N(O37)+N(H37),"")) | Q37: =IF(AND(ISNUMBER(P37),ISNUMBER(I37)),I37*Parametros!$B$12,"") | R37: =IF(AND(ISNUMBER(P37),ISNUMBER(I37)),I37*Parametros!$B$13,"") | S37: =IF(AND(ISNUMBER(P37),ISNUMBER(I37)),I37-P37-Q37-R37,"") | T37: =IF(AND(ISNUMBER(P37),ISNUMBER(I37)),S37/I37,"") | U37: =IF(OR(NOT(ISNUMBER(P37)),Parametros!$B$14>=1),"",P37/(1-Parametros!$B$14)) | V37: =IF(OR(NOT(ISNUMBER(P37)),Parametros!$B$14+Parametros!$B$18>=1),"",P37/(1-Parametros!$B$14-Parametros!$B$18)) | W37: =IF(B37="","",IF(E37="","SIN RECETA",IF(NOT(ISNUMBER(P37)),"FALTAN DATOS",IF(NOT(ISNUMBER(I37)),"FALTA PRECIO",IF(S37<0,"PIERDE",IF(T37<Parametros!$B$18,"BAJO META","OK")))))) -> SIN RECETA | X37: =IF(B37="","",IF(E37="","Elegir receta (molde). ",IF(ISNA(MATCH(E37,Recetas!$A$5:$A$84,0)),"La receta no existe. ",IF(IFERROR(INDEX(Recetas!$T$5:$T$84,MATCH($E37,Recetas!$A$5:$A$84,0))="Lista",FALSE()),"","Receta "&E37&": "&INDEX(Recetas!$T$5:$T$84,MATCH($E37,Recetas!$A$5:$A$84,0)))))&IF(F37="","Elegir tela. ",IF(IFERROR(INDEX(Precios!$F$5:$F$120,MATCH(F37,Precios!$A$5:$A$120,0)),"")="","Tela sin $/metro (falta rendimiento o precio). ",""))&IF(AND(E37<>"",N(IFERROR(INDEX(Recetas!$S$5:$S$84,MATCH($E37,Recetas!$A$5:$A$84,0)),0))>0,G37=""),"Elegir tela 2. ","")&IF(NOT(ISNUMBER(I37)),"Precio de venta.","")) -> Elegir receta (molde). Elegir tela. | Y37: =IF(AND(ISNUMBER(P37),ISNUMBER(I37),ISNUMBER(D37)),P37*D37,0) -> 0 | Z37: =IF(AND(ISNUMBER(P37),ISNUMBER(I37),ISNUMBER(D37)),I37*D37,0) -> 0 | AA37: =IF(AND(ISNUMBER(P37),ISNUMBER(I37),ISNUMBER(D37)),D37,0) -> 0
A38: VOL-CSUB-SAL-MC | B38: Camiseta Salida de Cancha Voley m/c | C38: Salida | D38: 29 | I38: 22605 | J38: Por confirmar | K38: Sin receta: elige el molde que usa (o crea su receta en "Recetas") y la tela. | L38: =IF(OR(B38="",E38=""),"",IFERROR(INDEX(Recetas!$R$5:$R$84,MATCH($E38,Recetas!$A$5:$A$84,0))*IFERROR(INDEX(Precios!$F$5:$F$120,MATCH(F38,Precios!$A$5:$A$120,0)),"")+IF(N(INDEX(Recetas!$S$5:$S$84,MATCH($E38,Recetas!$A$5:$A$84,0)))=0,0,INDEX(Recetas!$S$5:$S$84,MATCH($E38,Recetas!$A$5:$A$84,0))*IFERROR(INDEX(Precios!$F$5:$F$120,MATCH(G38,Precios!$A$5:$A$120,0)),"")),"")) | M38: =IF(OR(B38="",E38=""),"",IFERROR(N(INDEX(Recetas!$L$5:$L$84,MATCH($E38,Recetas!$A$5:$A$84,0)))*Parametros!$B$27,"")) | N38: =IF(OR(B38="",E38=""),"",IFERROR(INDEX(Confeccion!$B$5:$B$100,MATCH(INDEX(Recetas!$M$5:$M$84,MATCH($E38,Recetas!$A$5:$A$84,0)),Confeccion!$A$5:$A$100,0)),"")) | O38: =IF(OR(B38="",E38=""),"",IFERROR(N(INDEX(Recetas!$O$5:$O$84,MATCH($E38,Recetas!$A$5:$A$84,0)))*INDEX(Precios!$D$5:$D$120,MATCH(INDEX(Recetas!$N$5:$N$84,MATCH($E38,Recetas!$A$5:$A$84,0)),Precios!$A$5:$A$120,0)),0)) | P38: =IF(OR(B38="",E38=""),"",IF(AND(IFERROR(INDEX(Recetas!$T$5:$T$84,MATCH($E38,Recetas!$A$5:$A$84,0))="Lista",FALSE()),ISNUMBER(L38),ISNUMBER(M38),ISNUMBER(N38),N(N38)>0),L38+M38+N38+N(O38)+N(H38),"")) | Q38: =IF(AND(ISNUMBER(P38),ISNUMBER(I38)),I38*Parametros!$B$12,"") | R38: =IF(AND(ISNUMBER(P38),ISNUMBER(I38)),I38*Parametros!$B$13,"") | S38: =IF(AND(ISNUMBER(P38),ISNUMBER(I38)),I38-P38-Q38-R38,"") | T38: =IF(AND(ISNUMBER(P38),ISNUMBER(I38)),S38/I38,"") | U38: =IF(OR(NOT(ISNUMBER(P38)),Parametros!$B$14>=1),"",P38/(1-Parametros!$B$14)) | V38: =IF(OR(NOT(ISNUMBER(P38)),Parametros!$B$14+Parametros!$B$18>=1),"",P38/(1-Parametros!$B$14-Parametros!$B$18)) | W38: =IF(B38="","",IF(E38="","SIN RECETA",IF(NOT(ISNUMBER(P38)),"FALTAN DATOS",IF(NOT(ISNUMBER(I38)),"FALTA PRECIO",IF(S38<0,"PIERDE",IF(T38<Parametros!$B$18,"BAJO META","OK")))))) -> SIN RECETA | X38: =IF(B38="","",IF(E38="","Elegir receta (molde). ",IF(ISNA(MATCH(E38,Recetas!$A$5:$A$84,0)),"La receta no existe. ",IF(IFERROR(INDEX(Recetas!$T$5:$T$84,MATCH($E38,Recetas!$A$5:$A$84,0))="Lista",FALSE()),"","Receta "&E38&": "&INDEX(Recetas!$T$5:$T$84,MATCH($E38,Recetas!$A$5:$A$84,0)))))&IF(F38="","Elegir tela. ",IF(IFERROR(INDEX(Precios!$F$5:$F$120,MATCH(F38,Precios!$A$5:$A$120,0)),"")="","Tela sin $/metro (falta rendimiento o precio). ",""))&IF(AND(E38<>"",N(IFERROR(INDEX(Recetas!$S$5:$S$84,MATCH($E38,Recetas!$A$5:$A$84,0)),0))>0,G38=""),"Elegir tela 2. ","")&IF(NOT(ISNUMBER(I38)),"Precio de venta.","")) -> Elegir receta (molde). Elegir tela. | Y38: =IF(AND(ISNUMBER(P38),ISNUMBER(I38),ISNUMBER(D38)),P38*D38,0) -> 0 | Z38: =IF(AND(ISNUMBER(P38),ISNUMBER(I38),ISNUMBER(D38)),I38*D38,0) -> 0 | AA38: =IF(AND(ISNUMBER(P38),ISNUMBER(I38),ISNUMBER(D38)),D38,0) -> 0
A39: CSUBVOLFEMVSM | B39: CAMISETA VOLEY FEM V S/M PLAYMAKER | C39: Juego | D39: 29 | I39: 16723 | J39: Por confirmar | K39: Sin receta: elige el molde que usa (o crea su receta en "Recetas") y la tela. | L39: =IF(OR(B39="",E39=""),"",IFERROR(INDEX(Recetas!$R$5:$R$84,MATCH($E39,Recetas!$A$5:$A$84,0))*IFERROR(INDEX(Precios!$F$5:$F$120,MATCH(F39,Precios!$A$5:$A$120,0)),"")+IF(N(INDEX(Recetas!$S$5:$S$84,MATCH($E39,Recetas!$A$5:$A$84,0)))=0,0,INDEX(Recetas!$S$5:$S$84,MATCH($E39,Recetas!$A$5:$A$84,0))*IFERROR(INDEX(Precios!$F$5:$F$120,MATCH(G39,Precios!$A$5:$A$120,0)),"")),"")) | M39: =IF(OR(B39="",E39=""),"",IFERROR(N(INDEX(Recetas!$L$5:$L$84,MATCH($E39,Recetas!$A$5:$A$84,0)))*Parametros!$B$27,"")) | N39: =IF(OR(B39="",E39=""),"",IFERROR(INDEX(Confeccion!$B$5:$B$100,MATCH(INDEX(Recetas!$M$5:$M$84,MATCH($E39,Recetas!$A$5:$A$84,0)),Confeccion!$A$5:$A$100,0)),"")) | O39: =IF(OR(B39="",E39=""),"",IFERROR(N(INDEX(Recetas!$O$5:$O$84,MATCH($E39,Recetas!$A$5:$A$84,0)))*INDEX(Precios!$D$5:$D$120,MATCH(INDEX(Recetas!$N$5:$N$84,MATCH($E39,Recetas!$A$5:$A$84,0)),Precios!$A$5:$A$120,0)),0)) | P39: =IF(OR(B39="",E39=""),"",IF(AND(IFERROR(INDEX(Recetas!$T$5:$T$84,MATCH($E39,Recetas!$A$5:$A$84,0))="Lista",FALSE()),ISNUMBER(L39),ISNUMBER(M39),ISNUMBER(N39),N(N39)>0),L39+M39+N39+N(O39)+N(H39),"")) | Q39: =IF(AND(ISNUMBER(P39),ISNUMBER(I39)),I39*Parametros!$B$12,"") | R39: =IF(AND(ISNUMBER(P39),ISNUMBER(I39)),I39*Parametros!$B$13,"") | S39: =IF(AND(ISNUMBER(P39),ISNUMBER(I39)),I39-P39-Q39-R39,"") | T39: =IF(AND(ISNUMBER(P39),ISNUMBER(I39)),S39/I39,"") | U39: =IF(OR(NOT(ISNUMBER(P39)),Parametros!$B$14>=1),"",P39/(1-Parametros!$B$14)) | V39: =IF(OR(NOT(ISNUMBER(P39)),Parametros!$B$14+Parametros!$B$18>=1),"",P39/(1-Parametros!$B$14-Parametros!$B$18)) | W39: =IF(B39="","",IF(E39="","SIN RECETA",IF(NOT(ISNUMBER(P39)),"FALTAN DATOS",IF(NOT(ISNUMBER(I39)),"FALTA PRECIO",IF(S39<0,"PIERDE",IF(T39<Parametros!$B$18,"BAJO META","OK")))))) -> SIN RECETA | X39: =IF(B39="","",IF(E39="","Elegir receta (molde). ",IF(ISNA(MATCH(E39,Recetas!$A$5:$A$84,0)),"La receta no existe. ",IF(IFERROR(INDEX(Recetas!$T$5:$T$84,MATCH($E39,Recetas!$A$5:$A$84,0))="Lista",FALSE()),"","Receta "&E39&": "&INDEX(Recetas!$T$5:$T$84,MATCH($E39,Recetas!$A$5:$A$84,0)))))&IF(F39="","Elegir tela. ",IF(IFERROR(INDEX(Precios!$F$5:$F$120,MATCH(F39,Precios!$A$5:$A$120,0)),"")="","Tela sin $/metro (falta rendimiento o precio). ",""))&IF(AND(E39<>"",N(IFERROR(INDEX(Recetas!$S$5:$S$84,MATCH($E39,Recetas!$A$5:$A$84,0)),0))>0,G39=""),"Elegir tela 2. ","")&IF(NOT(ISNUMBER(I39)),"Precio de venta.","")) -> Elegir receta (molde). Elegir tela. | Y39: =IF(AND(ISNUMBER(P39),ISNUMBER(I39),ISNUMBER(D39)),P39*D39,0) -> 0 | Z39: =IF(AND(ISNUMBER(P39),ISNUMBER(I39),ISNUMBER(D39)),I39*D39,0) -> 0 | AA39: =IF(AND(ISNUMBER(P39),ISNUMBER(I39),ISNUMBER(D39)),D39,0) -> 0
A40: RUG-CSUB-LIC | B40: Camiseta Rugby Playmaker, Low Profile | C40: Juego | D40: 26 | I40: 23488 | J40: Por confirmar | K40: Sin receta: elige el molde que usa (o crea su receta en "Recetas") y la tela. | L40: =IF(OR(B40="",E40=""),"",IFERROR(INDEX(Recetas!$R$5:$R$84,MATCH($E40,Recetas!$A$5:$A$84,0))*IFERROR(INDEX(Precios!$F$5:$F$120,MATCH(F40,Precios!$A$5:$A$120,0)),"")+IF(N(INDEX(Recetas!$S$5:$S$84,MATCH($E40,Recetas!$A$5:$A$84,0)))=0,0,INDEX(Recetas!$S$5:$S$84,MATCH($E40,Recetas!$A$5:$A$84,0))*IFERROR(INDEX(Precios!$F$5:$F$120,MATCH(G40,Precios!$A$5:$A$120,0)),"")),"")) | M40: =IF(OR(B40="",E40=""),"",IFERROR(N(INDEX(Recetas!$L$5:$L$84,MATCH($E40,Recetas!$A$5:$A$84,0)))*Parametros!$B$27,"")) | N40: =IF(OR(B40="",E40=""),"",IFERROR(INDEX(Confeccion!$B$5:$B$100,MATCH(INDEX(Recetas!$M$5:$M$84,MATCH($E40,Recetas!$A$5:$A$84,0)),Confeccion!$A$5:$A$100,0)),"")) | O40: =IF(OR(B40="",E40=""),"",IFERROR(N(INDEX(Recetas!$O$5:$O$84,MATCH($E40,Recetas!$A$5:$A$84,0)))*INDEX(Precios!$D$5:$D$120,MATCH(INDEX(Recetas!$N$5:$N$84,MATCH($E40,Recetas!$A$5:$A$84,0)),Precios!$A$5:$A$120,0)),0)) | P40: =IF(OR(B40="",E40=""),"",IF(AND(IFERROR(INDEX(Recetas!$T$5:$T$84,MATCH($E40,Recetas!$A$5:$A$84,0))="Lista",FALSE()),ISNUMBER(L40),ISNUMBER(M40),ISNUMBER(N40),N(N40)>0),L40+M40+N40+N(O40)+N(H40),"")) | Q40: =IF(AND(ISNUMBER(P40),ISNUMBER(I40)),I40*Parametros!$B$12,"") | R40: =IF(AND(ISNUMBER(P40),ISNUMBER(I40)),I40*Parametros!$B$13,"") | S40: =IF(AND(ISNUMBER(P40),ISNUMBER(I40)),I40-P40-Q40-R40,"") | T40: =IF(AND(ISNUMBER(P40),ISNUMBER(I40)),S40/I40,"") | U40: =IF(OR(NOT(ISNUMBER(P40)),Parametros!$B$14>=1),"",P40/(1-Parametros!$B$14)) | V40: =IF(OR(NOT(ISNUMBER(P40)),Parametros!$B$14+Parametros!$B$18>=1),"",P40/(1-Parametros!$B$14-Parametros!$B$18)) | W40: =IF(B40="","",IF(E40="","SIN RECETA",IF(NOT(ISNUMBER(P40)),"FALTAN DATOS",IF(NOT(ISNUMBER(I40)),"FALTA PRECIO",IF(S40<0,"PIERDE",IF(T40<Parametros!$B$18,"BAJO META","OK")))))) -> SIN RECETA | X40: =IF(B40="","",IF(E40="","Elegir receta (molde). ",IF(ISNA(MATCH(E40,Recetas!$A$5:$A$84,0)),"La receta no existe. ",IF(IFERROR(INDEX(Recetas!$T$5:$T$84,MATCH($E40,Recetas!$A$5:$A$84,0))="Lista",FALSE()),"","Receta "&E40&": "&INDEX(Recetas!$T$5:$T$84,MATCH($E40,Recetas!$A$5:$A$84,0)))))&IF(F40="","Elegir tela. ",IF(IFERROR(INDEX(Precios!$F$5:$F$120,MATCH(F40,Precios!$A$5:$A$120,0)),"")="","Tela sin $/metro (falta rendimiento o precio). ",""))&IF(AND(E40<>"",N(IFERROR(INDEX(Recetas!$S$5:$S$84,MATCH($E40,Recetas!$A$5:$A$84,0)),0))>0,G40=""),"Elegir tela 2. ","")&IF(NOT(ISNUMBER(I40)),"Precio de venta.","")) -> Elegir receta (molde). Elegir tela. | Y40: =IF(AND(ISNUMBER(P40),ISNUMBER(I40),ISNUMBER(D40)),P40*D40,0) -> 0 | Z40: =IF(AND(ISNUMBER(P40),ISNUMBER(I40),ISNUMBER(D40)),I40*D40,0) -> 0 | AA40: =IF(AND(ISNUMBER(P40),ISNUMBER(I40),ISNUMBER(D40)),D40,0) -> 0
A41: RUNCSUBPROMC | B41: Camiseta Running Pro m/c | C41: Juego | D41: 25 | I41: 19244 | J41: Por confirmar | K41: Sin receta: elige el molde que usa (o crea su receta en "Recetas") y la tela. | L41: =IF(OR(B41="",E41=""),"",IFERROR(INDEX(Recetas!$R$5:$R$84,MATCH($E41,Recetas!$A$5:$A$84,0))*IFERROR(INDEX(Precios!$F$5:$F$120,MATCH(F41,Precios!$A$5:$A$120,0)),"")+IF(N(INDEX(Recetas!$S$5:$S$84,MATCH($E41,Recetas!$A$5:$A$84,0)))=0,0,INDEX(Recetas!$S$5:$S$84,MATCH($E41,Recetas!$A$5:$A$84,0))*IFERROR(INDEX(Precios!$F$5:$F$120,MATCH(G41,Precios!$A$5:$A$120,0)),"")),"")) | M41: =IF(OR(B41="",E41=""),"",IFERROR(N(INDEX(Recetas!$L$5:$L$84,MATCH($E41,Recetas!$A$5:$A$84,0)))*Parametros!$B$27,"")) | N41: =IF(OR(B41="",E41=""),"",IFERROR(INDEX(Confeccion!$B$5:$B$100,MATCH(INDEX(Recetas!$M$5:$M$84,MATCH($E41,Recetas!$A$5:$A$84,0)),Confeccion!$A$5:$A$100,0)),"")) | O41: =IF(OR(B41="",E41=""),"",IFERROR(N(INDEX(Recetas!$O$5:$O$84,MATCH($E41,Recetas!$A$5:$A$84,0)))*INDEX(Precios!$D$5:$D$120,MATCH(INDEX(Recetas!$N$5:$N$84,MATCH($E41,Recetas!$A$5:$A$84,0)),Precios!$A$5:$A$120,0)),0)) | P41: =IF(OR(B41="",E41=""),"",IF(AND(IFERROR(INDEX(Recetas!$T$5:$T$84,MATCH($E41,Recetas!$A$5:$A$84,0))="Lista",FALSE()),ISNUMBER(L41),ISNUMBER(M41),ISNUMBER(N41),N(N41)>0),L41+M41+N41+N(O41)+N(H41),"")) | Q41: =IF(AND(ISNUMBER(P41),ISNUMBER(I41)),I41*Parametros!$B$12,"") | R41: =IF(AND(ISNUMBER(P41),ISNUMBER(I41)),I41*Parametros!$B$13,"") | S41: =IF(AND(ISNUMBER(P41),ISNUMBER(I41)),I41-P41-Q41-R41,"") | T41: =IF(AND(ISNUMBER(P41),ISNUMBER(I41)),S41/I41,"") | U41: =IF(OR(NOT(ISNUMBER(P41)),Parametros!$B$14>=1),"",P41/(1-Parametros!$B$14)) | V41: =IF(OR(NOT(ISNUMBER(P41)),Parametros!$B$14+Parametros!$B$18>=1),"",P41/(1-Parametros!$B$14-Parametros!$B$18)) | W41: =IF(B41="","",IF(E41="","SIN RECETA",IF(NOT(ISNUMBER(P41)),"FALTAN DATOS",IF(NOT(ISNUMBER(I41)),"FALTA PRECIO",IF(S41<0,"PIERDE",IF(T41<Parametros!$B$18,"BAJO META","OK")))))) -> SIN RECETA | X41: =IF(B41="","",IF(E41="","Elegir receta (molde). ",IF(ISNA(MATCH(E41,Recetas!$A$5:$A$84,0)),"La receta no existe. ",IF(IFERROR(INDEX(Recetas!$T$5:$T$84,MATCH($E41,Recetas!$A$5:$A$84,0))="Lista",FALSE()),"","Receta "&E41&": "&INDEX(Recetas!$T$5:$T$84,MATCH($E41,Recetas!$A$5:$A$84,0)))))&IF(F41="","Elegir tela. ",IF(IFERROR(INDEX(Precios!$F$5:$F$120,MATCH(F41,Precios!$A$5:$A$120,0)),"")="","Tela sin $/metro (falta rendimiento o precio). ",""))&IF(AND(E41<>"",N(IFERROR(INDEX(Recetas!$S$5:$S$84,MATCH($E41,Recetas!$A$5:$A$84,0)),0))>0,G41=""),"Elegir tela 2. ","")&IF(NOT(ISNUMBER(I41)),"Precio de venta.","")) -> Elegir receta (molde). Elegir tela. | Y41: =IF(AND(ISNUMBER(P41),ISNUMBER(I41),ISNUMBER(D41)),P41*D41,0) -> 0 | Z41: =IF(AND(ISNUMBER(P41),ISNUMBER(I41),ISNUMBER(D41)),I41*D41,0) -> 0 | AA41: =IF(AND(ISNUMBER(P41),ISNUMBER(I41),ISNUMBER(D41)),D41,0) -> 0
A42: SAL-SHO-SUB | B42: SHORT SALIDA SUB | C42: Salida | D42: 25 | I42: 15882 | J42: Por confirmar | K42: Sin receta: elige el molde que usa (o crea su receta en "Recetas") y la tela. | L42: =IF(OR(B42="",E42=""),"",IFERROR(INDEX(Recetas!$R$5:$R$84,MATCH($E42,Recetas!$A$5:$A$84,0))*IFERROR(INDEX(Precios!$F$5:$F$120,MATCH(F42,Precios!$A$5:$A$120,0)),"")+IF(N(INDEX(Recetas!$S$5:$S$84,MATCH($E42,Recetas!$A$5:$A$84,0)))=0,0,INDEX(Recetas!$S$5:$S$84,MATCH($E42,Recetas!$A$5:$A$84,0))*IFERROR(INDEX(Precios!$F$5:$F$120,MATCH(G42,Precios!$A$5:$A$120,0)),"")),"")) | M42: =IF(OR(B42="",E42=""),"",IFERROR(N(INDEX(Recetas!$L$5:$L$84,MATCH($E42,Recetas!$A$5:$A$84,0)))*Parametros!$B$27,"")) | N42: =IF(OR(B42="",E42=""),"",IFERROR(INDEX(Confeccion!$B$5:$B$100,MATCH(INDEX(Recetas!$M$5:$M$84,MATCH($E42,Recetas!$A$5:$A$84,0)),Confeccion!$A$5:$A$100,0)),"")) | O42: =IF(OR(B42="",E42=""),"",IFERROR(N(INDEX(Recetas!$O$5:$O$84,MATCH($E42,Recetas!$A$5:$A$84,0)))*INDEX(Precios!$D$5:$D$120,MATCH(INDEX(Recetas!$N$5:$N$84,MATCH($E42,Recetas!$A$5:$A$84,0)),Precios!$A$5:$A$120,0)),0)) | P42: =IF(OR(B42="",E42=""),"",IF(AND(IFERROR(INDEX(Recetas!$T$5:$T$84,MATCH($E42,Recetas!$A$5:$A$84,0))="Lista",FALSE()),ISNUMBER(L42),ISNUMBER(M42),ISNUMBER(N42),N(N42)>0),L42+M42+N42+N(O42)+N(H42),"")) | Q42: =IF(AND(ISNUMBER(P42),ISNUMBER(I42)),I42*Parametros!$B$12,"") | R42: =IF(AND(ISNUMBER(P42),ISNUMBER(I42)),I42*Parametros!$B$13,"") | S42: =IF(AND(ISNUMBER(P42),ISNUMBER(I42)),I42-P42-Q42-R42,"") | T42: =IF(AND(ISNUMBER(P42),ISNUMBER(I42)),S42/I42,"") | U42: =IF(OR(NOT(ISNUMBER(P42)),Parametros!$B$14>=1),"",P42/(1-Parametros!$B$14)) | V42: =IF(OR(NOT(ISNUMBER(P42)),Parametros!$B$14+Parametros!$B$18>=1),"",P42/(1-Parametros!$B$14-Parametros!$B$18)) | W42: =IF(B42="","",IF(E42="","SIN RECETA",IF(NOT(ISNUMBER(P42)),"FALTAN DATOS",IF(NOT(ISNUMBER(I42)),"FALTA PRECIO",IF(S42<0,"PIERDE",IF(T42<Parametros!$B$18,"BAJO META","OK")))))) -> SIN RECETA | X42: =IF(B42="","",IF(E42="","Elegir receta (molde). ",IF(ISNA(MATCH(E42,Recetas!$A$5:$A$84,0)),"La receta no existe. ",IF(IFERROR(INDEX(Recetas!$T$5:$T$84,MATCH($E42,Recetas!$A$5:$A$84,0))="Lista",FALSE()),"","Receta "&E42&": "&INDEX(Recetas!$T$5:$T$84,MATCH($E42,Recetas!$A$5:$A$84,0)))))&IF(F42="","Elegir tela. ",IF(IFERROR(INDEX(Precios!$F$5:$F$120,MATCH(F42,Precios!$A$5:$A$120,0)),"")="","Tela sin $/metro (falta rendimiento o precio). ",""))&IF(AND(E42<>"",N(IFERROR(INDEX(Recetas!$S$5:$S$84,MATCH($E42,Recetas!$A$5:$A$84,0)),0))>0,G42=""),"Elegir tela 2. ","")&IF(NOT(ISNUMBER(I42)),"Precio de venta.","")) -> Elegir receta (molde). Elegir tela. | Y42: =IF(AND(ISNUMBER(P42),ISNUMBER(I42),ISNUMBER(D42)),P42*D42,0) -> 0 | Z42: =IF(AND(ISNUMBER(P42),ISNUMBER(I42),ISNUMBER(D42)),I42*D42,0) -> 0 | AA42: =IF(AND(ISNUMBER(P42),ISNUMBER(I42),ISNUMBER(D42)),D42,0) -> 0
A43: FUTCSUBPIQMC | B43: Camiseta Fútbol Playmaker, Piqué m/c | C43: Juego | D43: 24 | E43: 10 · FUTHOMCC01 | I43: 18403 | J43: Por confirmar | K43: ¿Piqué = cuello camisero? Confirmar molde y tela. | L43: =IF(OR(B43="",E43=""),"",IFERROR(INDEX(Recetas!$R$5:$R$84,MATCH($E43,Recetas!$A$5:$A$84,0))*IFERROR(INDEX(Precios!$F$5:$F$120,MATCH(F43,Precios!$A$5:$A$120,0)),"")+IF(N(INDEX(Recetas!$S$5:$S$84,MATCH($E43,Recetas!$A$5:$A$84,0)))=0,0,INDEX(Recetas!$S$5:$S$84,MATCH($E43,Recetas!$A$5:$A$84,0))*IFERROR(INDEX(Precios!$F$5:$F$120,MATCH(G43,Precios!$A$5:$A$120,0)),"")),"")) | M43: =IF(OR(B43="",E43=""),"",IFERROR(N(INDEX(Recetas!$L$5:$L$84,MATCH($E43,Recetas!$A$5:$A$84,0)))*Parametros!$B$27,"")) -> 0 | N43: =IF(OR(B43="",E43=""),"",IFERROR(INDEX(Confeccion!$B$5:$B$100,MATCH(INDEX(Recetas!$M$5:$M$84,MATCH($E43,Recetas!$A$5:$A$84,0)),Confeccion!$A$5:$A$100,0)),"")) -> 2000 | O43: =IF(OR(B43="",E43=""),"",IFERROR(N(INDEX(Recetas!$O$5:$O$84,MATCH($E43,Recetas!$A$5:$A$84,0)))*INDEX(Precios!$D$5:$D$120,MATCH(INDEX(Recetas!$N$5:$N$84,MATCH($E43,Recetas!$A$5:$A$84,0)),Precios!$A$5:$A$120,0)),0)) -> 0 | P43: =IF(OR(B43="",E43=""),"",IF(AND(IFERROR(INDEX(Recetas!$T$5:$T$84,MATCH($E43,Recetas!$A$5:$A$84,0))="Lista",FALSE()),ISNUMBER(L43),ISNUMBER(M43),ISNUMBER(N43),N(N43)>0),L43+M43+N43+N(O43)+N(H43),"")) | Q43: =IF(AND(ISNUMBER(P43),ISNUMBER(I43)),I43*Parametros!$B$12,"") | R43: =IF(AND(ISNUMBER(P43),ISNUMBER(I43)),I43*Parametros!$B$13,"") | S43: =IF(AND(ISNUMBER(P43),ISNUMBER(I43)),I43-P43-Q43-R43,"") | T43: =IF(AND(ISNUMBER(P43),ISNUMBER(I43)),S43/I43,"") | U43: =IF(OR(NOT(ISNUMBER(P43)),Parametros!$B$14>=1),"",P43/(1-Parametros!$B$14)) | V43: =IF(OR(NOT(ISNUMBER(P43)),Parametros!$B$14+Parametros!$B$18>=1),"",P43/(1-Parametros!$B$14-Parametros!$B$18)) | W43: =IF(B43="","",IF(E43="","SIN RECETA",IF(NOT(ISNUMBER(P43)),"FALTAN DATOS",IF(NOT(ISNUMBER(I43)),"FALTA PRECIO",IF(S43<0,"PIERDE",IF(T43<Parametros!$B$18,"BAJO META","OK")))))) -> FALTAN DATOS | X43: =IF(B43="","",IF(E43="","Elegir receta (molde). ",IF(ISNA(MATCH(E43,Recetas!$A$5:$A$84,0)),"La receta no existe. ",IF(IFERROR(INDEX(Recetas!$T$5:$T$84,MATCH($E43,Recetas!$A$5:$A$84,0))="Lista",FALSE()),"","Receta "&E43&": "&INDEX(Recetas!$T$5:$T$84,MATCH($E43,Recetas!$A$5:$A$84,0)))))&IF(F43="","Elegir tela. ",IF(IFERROR(INDEX(Precios!$F$5:$F$120,MATCH(F43,Precios!$A$5:$A$120,0)),"")="","Tela sin $/metro (falta rendimiento o precio). ",""))&IF(AND(E43<>"",N(IFERROR(INDEX(Recetas!$S$5:$S$84,MATCH($E43,Recetas!$A$5:$A$84,0)),0))>0,G43=""),"Elegir tela 2. ","")&IF(NOT(ISNUMBER(I43)),"Precio de venta.","")) -> Receta 10 · FUTHOMCC01: Consumo de tela. Metros impresos. Elegir tela. | Y43: =IF(AND(ISNUMBER(P43),ISNUMBER(I43),ISNUMBER(D43)),P43*D43,0) -> 0 | Z43: =IF(AND(ISNUMBER(P43),ISNUMBER(I43),ISNUMBER(D43)),I43*D43,0) -> 0 | AA43: =IF(AND(ISNUMBER(P43),ISNUMBER(I43),ISNUMBER(D43)),D43,0) -> 0
A44: FUTCSUBPROMC-V | B44: Camiseta Fútbol Pro Playmaker, V m/c | C44: Juego | D44: 23 | E44: 16 · FUTHOMV01PRO | F44: MONTESIMONE TRAINING (fut pro) | G44: MESH | I44: 19244 | J44: Por confirmar | K44: Molde Pro cuello V. Tela como la Pro cuello redondo: confirmar. | L44: =IF(OR(B44="",E44=""),"",IFERROR(INDEX(Recetas!$R$5:$R$84,MATCH($E44,Recetas!$A$5:$A$84,0))*IFERROR(INDEX(Precios!$F$5:$F$120,MATCH(F44,Precios!$A$5:$A$120,0)),"")+IF(N(INDEX(Recetas!$S$5:$S$84,MATCH($E44,Recetas!$A$5:$A$84,0)))=0,0,INDEX(Recetas!$S$5:$S$84,MATCH($E44,Recetas!$A$5:$A$84,0))*IFERROR(INDEX(Precios!$F$5:$F$120,MATCH(G44,Precios!$A$5:$A$120,0)),"")),"")) | M44: =IF(OR(B44="",E44=""),"",IFERROR(N(INDEX(Recetas!$L$5:$L$84,MATCH($E44,Recetas!$A$5:$A$84,0)))*Parametros!$B$27,"")) -> 0 | N44: =IF(OR(B44="",E44=""),"",IFERROR(INDEX(Confeccion!$B$5:$B$100,MATCH(INDEX(Recetas!$M$5:$M$84,MATCH($E44,Recetas!$A$5:$A$84,0)),Confeccion!$A$5:$A$100,0)),"")) -> 2000 | O44: =IF(OR(B44="",E44=""),"",IFERROR(N(INDEX(Recetas!$O$5:$O$84,MATCH($E44,Recetas!$A$5:$A$84,0)))*INDEX(Precios!$D$5:$D$120,MATCH(INDEX(Recetas!$N$5:$N$84,MATCH($E44,Recetas!$A$5:$A$84,0)),Precios!$A$5:$A$120,0)),0)) -> 0 | P44: =IF(OR(B44="",E44=""),"",IF(AND(IFERROR(INDEX(Recetas!$T$5:$T$84,MATCH($E44,Recetas!$A$5:$A$84,0))="Lista",FALSE()),ISNUMBER(L44),ISNUMBER(M44),ISNUMBER(N44),N(N44)>0),L44+M44+N44+N(O44)+N(H44),"")) | Q44: =IF(AND(ISNUMBER(P44),ISNUMBER(I44)),I44*Parametros!$B$12,"") | R44: =IF(AND(ISNUMBER(P44),ISNUMBER(I44)),I44*Parametros!$B$13,"") | S44: =IF(AND(ISNUMBER(P44),ISNUMBER(I44)),I44-P44-Q44-R44,"") | T44: =IF(AND(ISNUMBER(P44),ISNUMBER(I44)),S44/I44,"") | U44: =IF(OR(NOT(ISNUMBER(P44)),Parametros!$B$14>=1),"",P44/(1-Parametros!$B$14)) | V44: =IF(OR(NOT(ISNUMBER(P44)),Parametros!$B$14+Parametros!$B$18>=1),"",P44/(1-Parametros!$B$14-Parametros!$B$18)) | W44: =IF(B44="","",IF(E44="","SIN RECETA",IF(NOT(ISNUMBER(P44)),"FALTAN DATOS",IF(NOT(ISNUMBER(I44)),"FALTA PRECIO",IF(S44<0,"PIERDE",IF(T44<Parametros!$B$18,"BAJO META","OK")))))) -> FALTAN DATOS | X44: =IF(B44="","",IF(E44="","Elegir receta (molde). ",IF(ISNA(MATCH(E44,Recetas!$A$5:$A$84,0)),"La receta no existe. ",IF(IFERROR(INDEX(Recetas!$T$5:$T$84,MATCH($E44,Recetas!$A$5:$A$84,0))="Lista",FALSE()),"","Receta "&E44&": "&INDEX(Recetas!$T$5:$T$84,MATCH($E44,Recetas!$A$5:$A$84,0)))))&IF(F44="","Elegir tela. ",IF(IFERROR(INDEX(Precios!$F$5:$F$120,MATCH(F44,Precios!$A$5:$A$120,0)),"")="","Tela sin $/metro (falta rendimiento o precio). ",""))&IF(AND(E44<>"",N(IFERROR(INDEX(Recetas!$S$5:$S$84,MATCH($E44,Recetas!$A$5:$A$84,0)),0))>0,G44=""),"Elegir tela 2. ","")&IF(NOT(ISNUMBER(I44)),"Precio de venta.","")) -> Receta 16 · FUTHOMV01PRO: Consumo de tela. Metros impresos. | Y44: =IF(AND(ISNUMBER(P44),ISNUMBER(I44),ISNUMBER(D44)),P44*D44,0) -> 0 | Z44: =IF(AND(ISNUMBER(P44),ISNUMBER(I44),ISNUMBER(D44)),I44*D44,0) -> 0 | AA44: =IF(AND(ISNUMBER(P44),ISNUMBER(I44),ISNUMBER(D44)),D44,0) -> 0
A45: BASCSUBPER | B45: Camiseta Básquetbol Performance | C45: Juego | D45: 21 | E45: 30 · BKHOMU03 | F45: QUICKDRY | I45: 17563 | J45: Por confirmar | K45: Molde sugerido: básquet masculino cuello redondo. | L45: =IF(OR(B45="",E45=""),"",IFERROR(INDEX(Recetas!$R$5:$R$84,MATCH($E45,Recetas!$A$5:$A$84,0))*IFERROR(INDEX(Precios!$F$5:$F$120,MATCH(F45,Precios!$A$5:$A$120,0)),"")+IF(N(INDEX(Recetas!$S$5:$S$84,MATCH($E45,Recetas!$A$5:$A$84,0)))=0,0,INDEX(Recetas!$S$5:$S$84,MATCH($E45,Recetas!$A$5:$A$84,0))*IFERROR(INDEX(Precios!$F$5:$F$120,MATCH(G45,Precios!$A$5:$A$120,0)),"")),"")) | M45: =IF(OR(B45="",E45=""),"",IFERROR(N(INDEX(Recetas!$L$5:$L$84,MATCH($E45,Recetas!$A$5:$A$84,0)))*Parametros!$B$27,"")) -> 0 | N45: =IF(OR(B45="",E45=""),"",IFERROR(INDEX(Confeccion!$B$5:$B$100,MATCH(INDEX(Recetas!$M$5:$M$84,MATCH($E45,Recetas!$A$5:$A$84,0)),Confeccion!$A$5:$A$100,0)),"")) -> 1900 | O45: =IF(OR(B45="",E45=""),"",IFERROR(N(INDEX(Recetas!$O$5:$O$84,MATCH($E45,Recetas!$A$5:$A$84,0)))*INDEX(Precios!$D$5:$D$120,MATCH(INDEX(Recetas!$N$5:$N$84,MATCH($E45,Recetas!$A$5:$A$84,0)),Precios!$A$5:$A$120,0)),0)) -> 0 | P45: =IF(OR(B45="",E45=""),"",IF(AND(IFERROR(INDEX(Recetas!$T$5:$T$84,MATCH($E45,Recetas!$A$5:$A$84,0))="Lista",FALSE()),ISNUMBER(L45),ISNUMBER(M45),ISNUMBER(N45),N(N45)>0),L45+M45+N45+N(O45)+N(H45),"")) | Q45: =IF(AND(ISNUMBER(P45),ISNUMBER(I45)),I45*Parametros!$B$12,"") | R45: =IF(AND(ISNUMBER(P45),ISNUMBER(I45)),I45*Parametros!$B$13,"") | S45: =IF(AND(ISNUMBER(P45),ISNUMBER(I45)),I45-P45-Q45-R45,"") | T45: =IF(AND(ISNUMBER(P45),ISNUMBER(I45)),S45/I45,"") | U45: =IF(OR(NOT(ISNUMBER(P45)),Parametros!$B$14>=1),"",P45/(1-Parametros!$B$14)) | V45: =IF(OR(NOT(ISNUMBER(P45)),Parametros!$B$14+Parametros!$B$18>=1),"",P45/(1-Parametros!$B$14-Parametros!$B$18)) | W45: =IF(B45="","",IF(E45="","SIN RECETA",IF(NOT(ISNUMBER(P45)),"FALTAN DATOS",IF(NOT(ISNUMBER(I45)),"FALTA PRECIO",IF(S45<0,"PIERDE",IF(T45<Parametros!$B$18,"BAJO META","OK")))))) -> FALTAN DATOS | X45: =IF(B45="","",IF(E45="","Elegir receta (molde). ",IF(ISNA(MATCH(E45,Recetas!$A$5:$A$84,0)),"La receta no existe. ",IF(IFERROR(INDEX(Recetas!$T$5:$T$84,MATCH($E45,Recetas!$A$5:$A$84,0))="Lista",FALSE()),"","Receta "&E45&": "&INDEX(Recetas!$T$5:$T$84,MATCH($E45,Recetas!$A$5:$A$84,0)))))&IF(F45="","Elegir tela. ",IF(IFERROR(INDEX(Precios!$F$5:$F$120,MATCH(F45,Precios!$A$5:$A$120,0)),"")="","Tela sin $/metro (falta rendimiento o precio). ",""))&IF(AND(E45<>"",N(IFERROR(INDEX(Recetas!$S$5:$S$84,MATCH($E45,Recetas!$A$5:$A$84,0)),0))>0,G45=""),"Elegir tela 2. ","")&IF(NOT(ISNUMBER(I45)),"Precio de venta.","")) -> Receta 30 · BKHOMU03: Rendimiento de QUICKDRY (m/kg) en Precios. Metros impresos. Tela sin $/metro (falta rendimiento o precio). | Y45: =IF(AND(ISNUMBER(P45),ISNUMBER(I45),ISNUMBER(D45)),P45*D45,0) -> 0 | Z45: =IF(AND(ISNUMBER(P45),ISNUMBER(I45),ISNUMBER(D45)),I45*D45,0) -> 0 | AA45: =IF(AND(ISNUMBER(P45),ISNUMBER(I45),ISNUMBER(D45)),D45,0) -> 0
A46: VOL-SHO-SUB | B46: Short Fútbol Playmaker Sublimado | C46: Juego | D46: 20 | E46: SM-01 · Short Fútbol | F46: CIRE BLANCO | I46: 12521 | J46: Por confirmar | K46: Short sublimado: completar metros impresos en su receta. | L46: =IF(OR(B46="",E46=""),"",IFERROR(INDEX(Recetas!$R$5:$R$84,MATCH($E46,Recetas!$A$5:$A$84,0))*IFERROR(INDEX(Precios!$F$5:$F$120,MATCH(F46,Precios!$A$5:$A$120,0)),"")+IF(N(INDEX(Recetas!$S$5:$S$84,MATCH($E46,Recetas!$A$5:$A$84,0)))=0,0,INDEX(Recetas!$S$5:$S$84,MATCH($E46,Recetas!$A$5:$A$84,0))*IFERROR(INDEX(Precios!$F$5:$F$120,MATCH(G46,Precios!$A$5:$A$120,0)),"")),"")) | M46: =IF(OR(B46="",E46=""),"",IFERROR(N(INDEX(Recetas!$L$5:$L$84,MATCH($E46,Recetas!$A$5:$A$84,0)))*Parametros!$B$27,"")) -> 0 | N46: =IF(OR(B46="",E46=""),"",IFERROR(INDEX(Confeccion!$B$5:$B$100,MATCH(INDEX(Recetas!$M$5:$M$84,MATCH($E46,Recetas!$A$5:$A$84,0)),Confeccion!$A$5:$A$100,0)),"")) -> 1700 | O46: =IF(OR(B46="",E46=""),"",IFERROR(N(INDEX(Recetas!$O$5:$O$84,MATCH($E46,Recetas!$A$5:$A$84,0)))*INDEX(Precios!$D$5:$D$120,MATCH(INDEX(Recetas!$N$5:$N$84,MATCH($E46,Recetas!$A$5:$A$84,0)),Precios!$A$5:$A$120,0)),0)) -> 0 | P46: =IF(OR(B46="",E46=""),"",IF(AND(IFERROR(INDEX(Recetas!$T$5:$T$84,MATCH($E46,Recetas!$A$5:$A$84,0))="Lista",FALSE()),ISNUMBER(L46),ISNUMBER(M46),ISNUMBER(N46),N(N46)>0),L46+M46+N46+N(O46)+N(H46),"")) | Q46: =IF(AND(ISNUMBER(P46),ISNUMBER(I46)),I46*Parametros!$B$12,"") | R46: =IF(AND(ISNUMBER(P46),ISNUMBER(I46)),I46*Parametros!$B$13,"") | S46: =IF(AND(ISNUMBER(P46),ISNUMBER(I46)),I46-P46-Q46-R46,"") | T46: =IF(AND(ISNUMBER(P46),ISNUMBER(I46)),S46/I46,"") | U46: =IF(OR(NOT(ISNUMBER(P46)),Parametros!$B$14>=1),"",P46/(1-Parametros!$B$14)) | V46: =IF(OR(NOT(ISNUMBER(P46)),Parametros!$B$14+Parametros!$B$18>=1),"",P46/(1-Parametros!$B$14-Parametros!$B$18)) | W46: =IF(B46="","",IF(E46="","SIN RECETA",IF(NOT(ISNUMBER(P46)),"FALTAN DATOS",IF(NOT(ISNUMBER(I46)),"FALTA PRECIO",IF(S46<0,"PIERDE",IF(T46<Parametros!$B$18,"BAJO META","OK")))))) -> FALTAN DATOS | X46: =IF(B46="","",IF(E46="","Elegir receta (molde). ",IF(ISNA(MATCH(E46,Recetas!$A$5:$A$84,0)),"La receta no existe. ",IF(IFERROR(INDEX(Recetas!$T$5:$T$84,MATCH($E46,Recetas!$A$5:$A$84,0))="Lista",FALSE()),"","Receta "&E46&": "&INDEX(Recetas!$T$5:$T$84,MATCH($E46,Recetas!$A$5:$A$84,0)))))&IF(F46="","Elegir tela. ",IF(IFERROR(INDEX(Precios!$F$5:$F$120,MATCH(F46,Precios!$A$5:$A$120,0)),"")="","Tela sin $/metro (falta rendimiento o precio). ",""))&IF(AND(E46<>"",N(IFERROR(INDEX(Recetas!$S$5:$S$84,MATCH($E46,Recetas!$A$5:$A$84,0)),0))>0,G46=""),"Elegir tela 2. ","")&IF(NOT(ISNUMBER(I46)),"Precio de venta.","")) -> Receta SM-01 · Short Fútbol: Rendimiento de CIRE BLANCO (m/kg) en Precios. Tela sin $/metro (falta rendimiento o precio). | Y46: =IF(AND(ISNUMBER(P46),ISNUMBER(I46),ISNUMBER(D46)),P46*D46,0) -> 0 | Z46: =IF(AND(ISNUMBER(P46),ISNUMBER(I46),ISNUMBER(D46)),I46*D46,0) -> 0 | AA46: =IF(AND(ISNUMBER(P46),ISNUMBER(I46),ISNUMBER(D46)),D46,0) -> 0
A47: VOLFEM-CSUBPRO-POL | B47: Camiseta Voley fem Pro Playmaker, Polo | C47: Juego | D47: 20 | I47: 18403 | J47: Por confirmar | K47: Sin receta: elige el molde que usa (o crea su receta en "Recetas") y la tela. | L47: =IF(OR(B47="",E47=""),"",IFERROR(INDEX(Recetas!$R$5:$R$84,MATCH($E47,Recetas!$A$5:$A$84,0))*IFERROR(INDEX(Precios!$F$5:$F$120,MATCH(F47,Precios!$A$5:$A$120,0)),"")+IF(N(INDEX(Recetas!$S$5:$S$84,MATCH($E47,Recetas!$A$5:$A$84,0)))=0,0,INDEX(Recetas!$S$5:$S$84,MATCH($E47,Recetas!$A$5:$A$84,0))*IFERROR(INDEX(Precios!$F$5:$F$120,MATCH(G47,Precios!$A$5:$A$120,0)),"")),"")) | M47: =IF(OR(B47="",E47=""),"",IFERROR(N(INDEX(Recetas!$L$5:$L$84,MATCH($E47,Recetas!$A$5:$A$84,0)))*Parametros!$B$27,"")) | N47: =IF(OR(B47="",E47=""),"",IFERROR(INDEX(Confeccion!$B$5:$B$100,MATCH(INDEX(Recetas!$M$5:$M$84,MATCH($E47,Recetas!$A$5:$A$84,0)),Confeccion!$A$5:$A$100,0)),"")) | O47: =IF(OR(B47="",E47=""),"",IFERROR(N(INDEX(Recetas!$O$5:$O$84,MATCH($E47,Recetas!$A$5:$A$84,0)))*INDEX(Precios!$D$5:$D$120,MATCH(INDEX(Recetas!$N$5:$N$84,MATCH($E47,Recetas!$A$5:$A$84,0)),Precios!$A$5:$A$120,0)),0)) | P47: =IF(OR(B47="",E47=""),"",IF(AND(IFERROR(INDEX(Recetas!$T$5:$T$84,MATCH($E47,Recetas!$A$5:$A$84,0))="Lista",FALSE()),ISNUMBER(L47),ISNUMBER(M47),ISNUMBER(N47),N(N47)>0),L47+M47+N47+N(O47)+N(H47),"")) | Q47: =IF(AND(ISNUMBER(P47),ISNUMBER(I47)),I47*Parametros!$B$12,"") | R47: =IF(AND(ISNUMBER(P47),ISNUMBER(I47)),I47*Parametros!$B$13,"") | S47: =IF(AND(ISNUMBER(P47),ISNUMBER(I47)),I47-P47-Q47-R47,"") | T47: =IF(AND(ISNUMBER(P47),ISNUMBER(I47)),S47/I47,"") | U47: =IF(OR(NOT(ISNUMBER(P47)),Parametros!$B$14>=1),"",P47/(1-Parametros!$B$14)) | V47: =IF(OR(NOT(ISNUMBER(P47)),Parametros!$B$14+Parametros!$B$18>=1),"",P47/(1-Parametros!$B$14-Parametros!$B$18)) | W47: =IF(B47="","",IF(E47="","SIN RECETA",IF(NOT(ISNUMBER(P47)),"FALTAN DATOS",IF(NOT(ISNUMBER(I47)),"FALTA PRECIO",IF(S47<0,"PIERDE",IF(T47<Parametros!$B$18,"BAJO META","OK")))))) -> SIN RECETA | X47: =IF(B47="","",IF(E47="","Elegir receta (molde). ",IF(ISNA(MATCH(E47,Recetas!$A$5:$A$84,0)),"La receta no existe. ",IF(IFERROR(INDEX(Recetas!$T$5:$T$84,MATCH($E47,Recetas!$A$5:$A$84,0))="Lista",FALSE()),"","Receta "&E47&": "&INDEX(Recetas!$T$5:$T$84,MATCH($E47,Recetas!$A$5:$A$84,0)))))&IF(F47="","Elegir tela. ",IF(IFERROR(INDEX(Precios!$F$5:$F$120,MATCH(F47,Precios!$A$5:$A$120,0)),"")="","Tela sin $/metro (falta rendimiento o precio). ",""))&IF(AND(E47<>"",N(IFERROR(INDEX(Recetas!$S$5:$S$84,MATCH($E47,Recetas!$A$5:$A$84,0)),0))>0,G47=""),"Elegir tela 2. ","")&IF(NOT(ISNUMBER(I47)),"Precio de venta.","")) -> Elegir receta (molde). Elegir tela. | Y47: =IF(AND(ISNUMBER(P47),ISNUMBER(I47),ISNUMBER(D47)),P47*D47,0) -> 0 | Z47: =IF(AND(ISNUMBER(P47),ISNUMBER(I47),ISNUMBER(D47)),I47*D47,0) -> 0 | AA47: =IF(AND(ISNUMBER(P47),ISNUMBER(I47),ISNUMBER(D47)),D47,0) -> 0
A48: CSUBRUGSFBLAZUL | B48: CAMISETA DE RUGBY STADE FRANCAIS ANIVERSARIO (AZUL) | C48: Juego | D48: 20 | I48: 30000 | J48: Por confirmar | K48: Sin receta: elige el molde que usa (o crea su receta en "Recetas") y la tela. | L48: =IF(OR(B48="",E48=""),"",IFERROR(INDEX(Recetas!$R$5:$R$84,MATCH($E48,Recetas!$A$5:$A$84,0))*IFERROR(INDEX(Precios!$F$5:$F$120,MATCH(F48,Precios!$A$5:$A$120,0)),"")+IF(N(INDEX(Recetas!$S$5:$S$84,MATCH($E48,Recetas!$A$5:$A$84,0)))=0,0,INDEX(Recetas!$S$5:$S$84,MATCH($E48,Recetas!$A$5:$A$84,0))*IFERROR(INDEX(Precios!$F$5:$F$120,MATCH(G48,Precios!$A$5:$A$120,0)),"")),"")) | M48: =IF(OR(B48="",E48=""),"",IFERROR(N(INDEX(Recetas!$L$5:$L$84,MATCH($E48,Recetas!$A$5:$A$84,0)))*Parametros!$B$27,"")) | N48: =IF(OR(B48="",E48=""),"",IFERROR(INDEX(Confeccion!$B$5:$B$100,MATCH(INDEX(Recetas!$M$5:$M$84,MATCH($E48,Recetas!$A$5:$A$84,0)),Confeccion!$A$5:$A$100,0)),"")) | O48: =IF(OR(B48="",E48=""),"",IFERROR(N(INDEX(Recetas!$O$5:$O$84,MATCH($E48,Recetas!$A$5:$A$84,0)))*INDEX(Precios!$D$5:$D$120,MATCH(INDEX(Recetas!$N$5:$N$84,MATCH($E48,Recetas!$A$5:$A$84,0)),Precios!$A$5:$A$120,0)),0)) | P48: =IF(OR(B48="",E48=""),"",IF(AND(IFERROR(INDEX(Recetas!$T$5:$T$84,MATCH($E48,Recetas!$A$5:$A$84,0))="Lista",FALSE()),ISNUMBER(L48),ISNUMBER(M48),ISNUMBER(N48),N(N48)>0),L48+M48+N48+N(O48)+N(H48),"")) | Q48: =IF(AND(ISNUMBER(P48),ISNUMBER(I48)),I48*Parametros!$B$12,"") | R48: =IF(AND(ISNUMBER(P48),ISNUMBER(I48)),I48*Parametros!$B$13,"") | S48: =IF(AND(ISNUMBER(P48),ISNUMBER(I48)),I48-P48-Q48-R48,"") | T48: =IF(AND(ISNUMBER(P48),ISNUMBER(I48)),S48/I48,"") | U48: =IF(OR(NOT(ISNUMBER(P48)),Parametros!$B$14>=1),"",P48/(1-Parametros!$B$14)) | V48: =IF(OR(NOT(ISNUMBER(P48)),Parametros!$B$14+Parametros!$B$18>=1),"",P48/(1-Parametros!$B$14-Parametros!$B$18)) | W48: =IF(B48="","",IF(E48="","SIN RECETA",IF(NOT(ISNUMBER(P48)),"FALTAN DATOS",IF(NOT(ISNUMBER(I48)),"FALTA PRECIO",IF(S48<0,"PIERDE",IF(T48<Parametros!$B$18,"BAJO META","OK")))))) -> SIN RECETA | X48: =IF(B48="","",IF(E48="","Elegir receta (molde). ",IF(ISNA(MATCH(E48,Recetas!$A$5:$A$84,0)),"La receta no existe. ",IF(IFERROR(INDEX(Recetas!$T$5:$T$84,MATCH($E48,Recetas!$A$5:$A$84,0))="Lista",FALSE()),"","Receta "&E48&": "&INDEX(Recetas!$T$5:$T$84,MATCH($E48,Recetas!$A$5:$A$84,0)))))&IF(F48="","Elegir tela. ",IF(IFERROR(INDEX(Precios!$F$5:$F$120,MATCH(F48,Precios!$A$5:$A$120,0)),"")="","Tela sin $/metro (falta rendimiento o precio). ",""))&IF(AND(E48<>"",N(IFERROR(INDEX(Recetas!$S$5:$S$84,MATCH($E48,Recetas!$A$5:$A$84,0)),0))>0,G48=""),"Elegir tela 2. ","")&IF(NOT(ISNUMBER(I48)),"Precio de venta.","")) -> Elegir receta (molde). Elegir tela. | Y48: =IF(AND(ISNUMBER(P48),ISNUMBER(I48),ISNUMBER(D48)),P48*D48,0) -> 0 | Z48: =IF(AND(ISNUMBER(P48),ISNUMBER(I48),ISNUMBER(D48)),I48*D48,0) -> 0 | AA48: =IF(AND(ISNUMBER(P48),ISNUMBER(I48),ISNUMBER(D48)),D48,0) -> 0
A49: MDPTLIS | B49: PETO ENTRENAMIENTO LISO | C49: Juego | D49: 20 | I49: 6000 | J49: Por confirmar | K49: Sin receta: elige el molde que usa (o crea su receta en "Recetas") y la tela. | L49: =IF(OR(B49="",E49=""),"",IFERROR(INDEX(Recetas!$R$5:$R$84,MATCH($E49,Recetas!$A$5:$A$84,0))*IFERROR(INDEX(Precios!$F$5:$F$120,MATCH(F49,Precios!$A$5:$A$120,0)),"")+IF(N(INDEX(Recetas!$S$5:$S$84,MATCH($E49,Recetas!$A$5:$A$84,0)))=0,0,INDEX(Recetas!$S$5:$S$84,MATCH($E49,Recetas!$A$5:$A$84,0))*IFERROR(INDEX(Precios!$F$5:$F$120,MATCH(G49,Precios!$A$5:$A$120,0)),"")),"")) | M49: =IF(OR(B49="",E49=""),"",IFERROR(N(INDEX(Recetas!$L$5:$L$84,MATCH($E49,Recetas!$A$5:$A$84,0)))*Parametros!$B$27,"")) | N49: =IF(OR(B49="",E49=""),"",IFERROR(INDEX(Confeccion!$B$5:$B$100,MATCH(INDEX(Recetas!$M$5:$M$84,MATCH($E49,Recetas!$A$5:$A$84,0)),Confeccion!$A$5:$A$100,0)),"")) | O49: =IF(OR(B49="",E49=""),"",IFERROR(N(INDEX(Recetas!$O$5:$O$84,MATCH($E49,Recetas!$A$5:$A$84,0)))*INDEX(Precios!$D$5:$D$120,MATCH(INDEX(Recetas!$N$5:$N$84,MATCH($E49,Recetas!$A$5:$A$84,0)),Precios!$A$5:$A$120,0)),0)) | P49: =IF(OR(B49="",E49=""),"",IF(AND(IFERROR(INDEX(Recetas!$T$5:$T$84,MATCH($E49,Recetas!$A$5:$A$84,0))="Lista",FALSE()),ISNUMBER(L49),ISNUMBER(M49),ISNUMBER(N49),N(N49)>0),L49+M49+N49+N(O49)+N(H49),"")) | Q49: =IF(AND(ISNUMBER(P49),ISNUMBER(I49)),I49*Parametros!$B$12,"") | R49: =IF(AND(ISNUMBER(P49),ISNUMBER(I49)),I49*Parametros!$B$13,"") | S49: =IF(AND(ISNUMBER(P49),ISNUMBER(I49)),I49-P49-Q49-R49,"") | T49: =IF(AND(ISNUMBER(P49),ISNUMBER(I49)),S49/I49,"") | U49: =IF(OR(NOT(ISNUMBER(P49)),Parametros!$B$14>=1),"",P49/(1-Parametros!$B$14)) | V49: =IF(OR(NOT(ISNUMBER(P49)),Parametros!$B$14+Parametros!$B$18>=1),"",P49/(1-Parametros!$B$14-Parametros!$B$18)) | W49: =IF(B49="","",IF(E49="","SIN RECETA",IF(NOT(ISNUMBER(P49)),"FALTAN DATOS",IF(NOT(ISNUMBER(I49)),"FALTA PRECIO",IF(S49<0,"PIERDE",IF(T49<Parametros!$B$18,"BAJO META","OK")))))) -> SIN RECETA | X49: =IF(B49="","",IF(E49="","Elegir receta (molde). ",IF(ISNA(MATCH(E49,Recetas!$A$5:$A$84,0)),"La receta no existe. ",IF(IFERROR(INDEX(Recetas!$T$5:$T$84,MATCH($E49,Recetas!$A$5:$A$84,0))="Lista",FALSE()),"","Receta "&E49&": "&INDEX(Recetas!$T$5:$T$84,MATCH($E49,Recetas!$A$5:$A$84,0)))))&IF(F49="","Elegir tela. ",IF(IFERROR(INDEX(Precios!$F$5:$F$120,MATCH(F49,Precios!$A$5:$A$120,0)),"")="","Tela sin $/metro (falta rendimiento o precio). ",""))&IF(AND(E49<>"",N(IFERROR(INDEX(Recetas!$S$5:$S$84,MATCH($E49,Recetas!$A$5:$A$84,0)),0))>0,G49=""),"Elegir tela 2. ","")&IF(NOT(ISNUMBER(I49)),"Precio de venta.","")) -> Elegir receta (molde). Elegir tela. | Y49: =IF(AND(ISNUMBER(P49),ISNUMBER(I49),ISNUMBER(D49)),P49*D49,0) -> 0 | Z49: =IF(AND(ISNUMBER(P49),ISNUMBER(I49),ISNUMBER(D49)),I49*D49,0) -> 0 | AA49: =IF(AND(ISNUMBER(P49),ISNUMBER(I49),ISNUMBER(D49)),D49,0) -> 0
A50: RUNCSUBPERSM | B50: Camiseta Running Performance s/m | C50: Juego | D50: 19 | I50: 15882 | J50: Por confirmar | K50: Sin receta: elige el molde que usa (o crea su receta en "Recetas") y la tela. | L50: =IF(OR(B50="",E50=""),"",IFERROR(INDEX(Recetas!$R$5:$R$84,MATCH($E50,Recetas!$A$5:$A$84,0))*IFERROR(INDEX(Precios!$F$5:$F$120,MATCH(F50,Precios!$A$5:$A$120,0)),"")+IF(N(INDEX(Recetas!$S$5:$S$84,MATCH($E50,Recetas!$A$5:$A$84,0)))=0,0,INDEX(Recetas!$S$5:$S$84,MATCH($E50,Recetas!$A$5:$A$84,0))*IFERROR(INDEX(Precios!$F$5:$F$120,MATCH(G50,Precios!$A$5:$A$120,0)),"")),"")) | M50: =IF(OR(B50="",E50=""),"",IFERROR(N(INDEX(Recetas!$L$5:$L$84,MATCH($E50,Recetas!$A$5:$A$84,0)))*Parametros!$B$27,"")) | N50: =IF(OR(B50="",E50=""),"",IFERROR(INDEX(Confeccion!$B$5:$B$100,MATCH(INDEX(Recetas!$M$5:$M$84,MATCH($E50,Recetas!$A$5:$A$84,0)),Confeccion!$A$5:$A$100,0)),"")) | O50: =IF(OR(B50="",E50=""),"",IFERROR(N(INDEX(Recetas!$O$5:$O$84,MATCH($E50,Recetas!$A$5:$A$84,0)))*INDEX(Precios!$D$5:$D$120,MATCH(INDEX(Recetas!$N$5:$N$84,MATCH($E50,Recetas!$A$5:$A$84,0)),Precios!$A$5:$A$120,0)),0)) | P50: =IF(OR(B50="",E50=""),"",IF(AND(IFERROR(INDEX(Recetas!$T$5:$T$84,MATCH($E50,Recetas!$A$5:$A$84,0))="Lista",FALSE()),ISNUMBER(L50),ISNUMBER(M50),ISNUMBER(N50),N(N50)>0),L50+M50+N50+N(O50)+N(H50),"")) | Q50: =IF(AND(ISNUMBER(P50),ISNUMBER(I50)),I50*Parametros!$B$12,"") | R50: =IF(AND(ISNUMBER(P50),ISNUMBER(I50)),I50*Parametros!$B$13,"") | S50: =IF(AND(ISNUMBER(P50),ISNUMBER(I50)),I50-P50-Q50-R50,"") | T50: =IF(AND(ISNUMBER(P50),ISNUMBER(I50)),S50/I50,"") | U50: =IF(OR(NOT(ISNUMBER(P50)),Parametros!$B$14>=1),"",P50/(1-Parametros!$B$14)) | V50: =IF(OR(NOT(ISNUMBER(P50)),Parametros!$B$14+Parametros!$B$18>=1),"",P50/(1-Parametros!$B$14-Parametros!$B$18)) | W50: =IF(B50="","",IF(E50="","SIN RECETA",IF(NOT(ISNUMBER(P50)),"FALTAN DATOS",IF(NOT(ISNUMBER(I50)),"FALTA PRECIO",IF(S50<0,"PIERDE",IF(T50<Parametros!$B$18,"BAJO META","OK")))))) -> SIN RECETA | X50: =IF(B50="","",IF(E50="","Elegir receta (molde). ",IF(ISNA(MATCH(E50,Recetas!$A$5:$A$84,0)),"La receta no existe. ",IF(IFERROR(INDEX(Recetas!$T$5:$T$84,MATCH($E50,Recetas!$A$5:$A$84,0))="Lista",FALSE()),"","Receta "&E50&": "&INDEX(Recetas!$T$5:$T$84,MATCH($E50,Recetas!$A$5:$A$84,0)))))&IF(F50="","Elegir tela. ",IF(IFERROR(INDEX(Precios!$F$5:$F$120,MATCH(F50,Precios!$A$5:$A$120,0)),"")="","Tela sin $/metro (falta rendimiento o precio). ",""))&IF(AND(E50<>"",N(IFERROR(INDEX(Recetas!$S$5:$S$84,MATCH($E50,Recetas!$A$5:$A$84,0)),0))>0,G50=""),"Elegir tela 2. ","")&IF(NOT(ISNUMBER(I50)),"Precio de venta.","")) -> Elegir receta (molde). Elegir tela. | Y50: =IF(AND(ISNUMBER(P50),ISNUMBER(I50),ISNUMBER(D50)),P50*D50,0) -> 0 | Z50: =IF(AND(ISNUMBER(P50),ISNUMBER(I50),ISNUMBER(D50)),I50*D50,0) -> 0 | AA50: =IF(AND(ISNUMBER(P50),ISNUMBER(I50),ISNUMBER(D50)),D50,0) -> 0
A51: SAL-BUZ-LIS-RT | B51: Pantalón Buzo Playmaker Liso Recto | C51: Salida | D51: 19 | I51: 15042 | J51: Por confirmar | K51: Sin receta: elige el molde que usa (o crea su receta en "Recetas") y la tela. | L51: =IF(OR(B51="",E51=""),"",IFERROR(INDEX(Recetas!$R$5:$R$84,MATCH($E51,Recetas!$A$5:$A$84,0))*IFERROR(INDEX(Precios!$F$5:$F$120,MATCH(F51,Precios!$A$5:$A$120,0)),"")+IF(N(INDEX(Recetas!$S$5:$S$84,MATCH($E51,Recetas!$A$5:$A$84,0)))=0,0,INDEX(Recetas!$S$5:$S$84,MATCH($E51,Recetas!$A$5:$A$84,0))*IFERROR(INDEX(Precios!$F$5:$F$120,MATCH(G51,Precios!$A$5:$A$120,0)),"")),"")) | M51: =IF(OR(B51="",E51=""),"",IFERROR(N(INDEX(Recetas!$L$5:$L$84,MATCH($E51,Recetas!$A$5:$A$84,0)))*Parametros!$B$27,"")) | N51: =IF(OR(B51="",E51=""),"",IFERROR(INDEX(Confeccion!$B$5:$B$100,MATCH(INDEX(Recetas!$M$5:$M$84,MATCH($E51,Recetas!$A$5:$A$84,0)),Confeccion!$A$5:$A$100,0)),"")) | O51: =IF(OR(B51="",E51=""),"",IFERROR(N(INDEX(Recetas!$O$5:$O$84,MATCH($E51,Recetas!$A$5:$A$84,0)))*INDEX(Precios!$D$5:$D$120,MATCH(INDEX(Recetas!$N$5:$N$84,MATCH($E51,Recetas!$A$5:$A$84,0)),Precios!$A$5:$A$120,0)),0)) | P51: =IF(OR(B51="",E51=""),"",IF(AND(IFERROR(INDEX(Recetas!$T$5:$T$84,MATCH($E51,Recetas!$A$5:$A$84,0))="Lista",FALSE()),ISNUMBER(L51),ISNUMBER(M51),ISNUMBER(N51),N(N51)>0),L51+M51+N51+N(O51)+N(H51),"")) | Q51: =IF(AND(ISNUMBER(P51),ISNUMBER(I51)),I51*Parametros!$B$12,"") | R51: =IF(AND(ISNUMBER(P51),ISNUMBER(I51)),I51*Parametros!$B$13,"") | S51: =IF(AND(ISNUMBER(P51),ISNUMBER(I51)),I51-P51-Q51-R51,"") | T51: =IF(AND(ISNUMBER(P51),ISNUMBER(I51)),S51/I51,"") | U51: =IF(OR(NOT(ISNUMBER(P51)),Parametros!$B$14>=1),"",P51/(1-Parametros!$B$14)) | V51: =IF(OR(NOT(ISNUMBER(P51)),Parametros!$B$14+Parametros!$B$18>=1),"",P51/(1-Parametros!$B$14-Parametros!$B$18)) | W51: =IF(B51="","",IF(E51="","SIN RECETA",IF(NOT(ISNUMBER(P51)),"FALTAN DATOS",IF(NOT(ISNUMBER(I51)),"FALTA PRECIO",IF(S51<0,"PIERDE",IF(T51<Parametros!$B$18,"BAJO META","OK")))))) -> SIN RECETA | X51: =IF(B51="","",IF(E51="","Elegir receta (molde). ",IF(ISNA(MATCH(E51,Recetas!$A$5:$A$84,0)),"La receta no existe. ",IF(IFERROR(INDEX(Recetas!$T$5:$T$84,MATCH($E51,Recetas!$A$5:$A$84,0))="Lista",FALSE()),"","Receta "&E51&": "&INDEX(Recetas!$T$5:$T$84,MATCH($E51,Recetas!$A$5:$A$84,0)))))&IF(F51="","Elegir tela. ",IF(IFERROR(INDEX(Precios!$F$5:$F$120,MATCH(F51,Precios!$A$5:$A$120,0)),"")="","Tela sin $/metro (falta rendimiento o precio). ",""))&IF(AND(E51<>"",N(IFERROR(INDEX(Recetas!$S$5:$S$84,MATCH($E51,Recetas!$A$5:$A$84,0)),0))>0,G51=""),"Elegir tela 2. ","")&IF(NOT(ISNUMBER(I51)),"Precio de venta.","")) -> Elegir receta (molde). Elegir tela. | Y51: =IF(AND(ISNUMBER(P51),ISNUMBER(I51),ISNUMBER(D51)),P51*D51,0) -> 0 | Z51: =IF(AND(ISNUMBER(P51),ISNUMBER(I51),ISNUMBER(D51)),I51*D51,0) -> 0 | AA51: =IF(AND(ISNUMBER(P51),ISNUMBER(I51),ISNUMBER(D51)),D51,0) -> 0
A52: SAL-BUZ-LIS | B52: Pantalón Buzo Playmaker Liso Pitillo | C52: Salida | D52: 17 | I52: 24328 | J52: Por confirmar | K52: Sin receta: elige el molde que usa (o crea su receta en "Recetas") y la tela. | L52: =IF(OR(B52="",E52=""),"",IFERROR(INDEX(Recetas!$R$5:$R$84,MATCH($E52,Recetas!$A$5:$A$84,0))*IFERROR(INDEX(Precios!$F$5:$F$120,MATCH(F52,Precios!$A$5:$A$120,0)),"")+IF(N(INDEX(Recetas!$S$5:$S$84,MATCH($E52,Recetas!$A$5:$A$84,0)))=0,0,INDEX(Recetas!$S$5:$S$84,MATCH($E52,Recetas!$A$5:$A$84,0))*IFERROR(INDEX(Precios!$F$5:$F$120,MATCH(G52,Precios!$A$5:$A$120,0)),"")),"")) | M52: =IF(OR(B52="",E52=""),"",IFERROR(N(INDEX(Recetas!$L$5:$L$84,MATCH($E52,Recetas!$A$5:$A$84,0)))*Parametros!$B$27,"")) | N52: =IF(OR(B52="",E52=""),"",IFERROR(INDEX(Confeccion!$B$5:$B$100,MATCH(INDEX(Recetas!$M$5:$M$84,MATCH($E52,Recetas!$A$5:$A$84,0)),Confeccion!$A$5:$A$100,0)),"")) | O52: =IF(OR(B52="",E52=""),"",IFERROR(N(INDEX(Recetas!$O$5:$O$84,MATCH($E52,Recetas!$A$5:$A$84,0)))*INDEX(Precios!$D$5:$D$120,MATCH(INDEX(Recetas!$N$5:$N$84,MATCH($E52,Recetas!$A$5:$A$84,0)),Precios!$A$5:$A$120,0)),0)) | P52: =IF(OR(B52="",E52=""),"",IF(AND(IFERROR(INDEX(Recetas!$T$5:$T$84,MATCH($E52,Recetas!$A$5:$A$84,0))="Lista",FALSE()),ISNUMBER(L52),ISNUMBER(M52),ISNUMBER(N52),N(N52)>0),L52+M52+N52+N(O52)+N(H52),"")) | Q52: =IF(AND(ISNUMBER(P52),ISNUMBER(I52)),I52*Parametros!$B$12,"") | R52: =IF(AND(ISNUMBER(P52),ISNUMBER(I52)),I52*Parametros!$B$13,"") | S52: =IF(AND(ISNUMBER(P52),ISNUMBER(I52)),I52-P52-Q52-R52,"") | T52: =IF(AND(ISNUMBER(P52),ISNUMBER(I52)),S52/I52,"") | U52: =IF(OR(NOT(ISNUMBER(P52)),Parametros!$B$14>=1),"",P52/(1-Parametros!$B$14)) | V52: =IF(OR(NOT(ISNUMBER(P52)),Parametros!$B$14+Parametros!$B$18>=1),"",P52/(1-Parametros!$B$14-Parametros!$B$18)) | W52: =IF(B52="","",IF(E52="","SIN RECETA",IF(NOT(ISNUMBER(P52)),"FALTAN DATOS",IF(NOT(ISNUMBER(I52)),"FALTA PRECIO",IF(S52<0,"PIERDE",IF(T52<Parametros!$B$18,"BAJO META","OK")))))) -> SIN RECETA | X52: =IF(B52="","",IF(E52="","Elegir receta (molde). ",IF(ISNA(MATCH(E52,Recetas!$A$5:$A$84,0)),"La receta no existe. ",IF(IFERROR(INDEX(Recetas!$T$5:$T$84,MATCH($E52,Recetas!$A$5:$A$84,0))="Lista",FALSE()),"","Receta "&E52&": "&INDEX(Recetas!$T$5:$T$84,MATCH($E52,Recetas!$A$5:$A$84,0)))))&IF(F52="","Elegir tela. ",IF(IFERROR(INDEX(Precios!$F$5:$F$120,MATCH(F52,Precios!$A$5:$A$120,0)),"")="","Tela sin $/metro (falta rendimiento o precio). ",""))&IF(AND(E52<>"",N(IFERROR(INDEX(Recetas!$S$5:$S$84,MATCH($E52,Recetas!$A$5:$A$84,0)),0))>0,G52=""),"Elegir tela 2. ","")&IF(NOT(ISNUMBER(I52)),"Precio de venta.","")) -> Elegir receta (molde). Elegir tela. | Y52: =IF(AND(ISNUMBER(P52),ISNUMBER(I52),ISNUMBER(D52)),P52*D52,0) -> 0 | Z52: =IF(AND(ISNUMBER(P52),ISNUMBER(I52),ISNUMBER(D52)),I52*D52,0) -> 0 | AA52: =IF(AND(ISNUMBER(P52),ISNUMBER(I52),ISNUMBER(D52)),D52,0) -> 0
A53: RUNCSUBPERMC | B53: Camiseta Running Performance m/c | C53: Juego | D53: 16 | I53: 15882 | J53: Por confirmar | K53: Sin receta: elige el molde que usa (o crea su receta en "Recetas") y la tela. | L53: =IF(OR(B53="",E53=""),"",IFERROR(INDEX(Recetas!$R$5:$R$84,MATCH($E53,Recetas!$A$5:$A$84,0))*IFERROR(INDEX(Precios!$F$5:$F$120,MATCH(F53,Precios!$A$5:$A$120,0)),"")+IF(N(INDEX(Recetas!$S$5:$S$84,MATCH($E53,Recetas!$A$5:$A$84,0)))=0,0,INDEX(Recetas!$S$5:$S$84,MATCH($E53,Recetas!$A$5:$A$84,0))*IFERROR(INDEX(Precios!$F$5:$F$120,MATCH(G53,Precios!$A$5:$A$120,0)),"")),"")) | M53: =IF(OR(B53="",E53=""),"",IFERROR(N(INDEX(Recetas!$L$5:$L$84,MATCH($E53,Recetas!$A$5:$A$84,0)))*Parametros!$B$27,"")) | N53: =IF(OR(B53="",E53=""),"",IFERROR(INDEX(Confeccion!$B$5:$B$100,MATCH(INDEX(Recetas!$M$5:$M$84,MATCH($E53,Recetas!$A$5:$A$84,0)),Confeccion!$A$5:$A$100,0)),"")) | O53: =IF(OR(B53="",E53=""),"",IFERROR(N(INDEX(Recetas!$O$5:$O$84,MATCH($E53,Recetas!$A$5:$A$84,0)))*INDEX(Precios!$D$5:$D$120,MATCH(INDEX(Recetas!$N$5:$N$84,MATCH($E53,Recetas!$A$5:$A$84,0)),Precios!$A$5:$A$120,0)),0)) | P53: =IF(OR(B53="",E53=""),"",IF(AND(IFERROR(INDEX(Recetas!$T$5:$T$84,MATCH($E53,Recetas!$A$5:$A$84,0))="Lista",FALSE()),ISNUMBER(L53),ISNUMBER(M53),ISNUMBER(N53),N(N53)>0),L53+M53+N53+N(O53)+N(H53),"")) | Q53: =IF(AND(ISNUMBER(P53),ISNUMBER(I53)),I53*Parametros!$B$12,"") | R53: =IF(AND(ISNUMBER(P53),ISNUMBER(I53)),I53*Parametros!$B$13,"") | S53: =IF(AND(ISNUMBER(P53),ISNUMBER(I53)),I53-P53-Q53-R53,"") | T53: =IF(AND(ISNUMBER(P53),ISNUMBER(I53)),S53/I53,"") | U53: =IF(OR(NOT(ISNUMBER(P53)),Parametros!$B$14>=1),"",P53/(1-Parametros!$B$14)) | V53: =IF(OR(NOT(ISNUMBER(P53)),Parametros!$B$14+Parametros!$B$18>=1),"",P53/(1-Parametros!$B$14-Parametros!$B$18)) | W53: =IF(B53="","",IF(E53="","SIN RECETA",IF(NOT(ISNUMBER(P53)),"FALTAN DATOS",IF(NOT(ISNUMBER(I53)),"FALTA PRECIO",IF(S53<0,"PIERDE",IF(T53<Parametros!$B$18,"BAJO META","OK")))))) -> SIN RECETA | X53: =IF(B53="","",IF(E53="","Elegir receta (molde). ",IF(ISNA(MATCH(E53,Recetas!$A$5:$A$84,0)),"La receta no existe. ",IF(IFERROR(INDEX(Recetas!$T$5:$T$84,MATCH($E53,Recetas!$A$5:$A$84,0))="Lista",FALSE()),"","Receta "&E53&": "&INDEX(Recetas!$T$5:$T$84,MATCH($E53,Recetas!$A$5:$A$84,0)))))&IF(F53="","Elegir tela. ",IF(IFERROR(INDEX(Precios!$F$5:$F$120,MATCH(F53,Precios!$A$5:$A$120,0)),"")="","Tela sin $/metro (falta rendimiento o precio). ",""))&IF(AND(E53<>"",N(IFERROR(INDEX(Recetas!$S$5:$S$84,MATCH($E53,Recetas!$A$5:$A$84,0)),0))>0,G53=""),"Elegir tela 2. ","")&IF(NOT(ISNUMBER(I53)),"Precio de venta.","")) -> Elegir receta (molde). Elegir tela. | Y53: =IF(AND(ISNUMBER(P53),ISNUMBER(I53),ISNUMBER(D53)),P53*D53,0) -> 0 | Z53: =IF(AND(ISNUMBER(P53),ISNUMBER(I53),ISNUMBER(D53)),I53*D53,0) -> 0 | AA53: =IF(AND(ISNUMBER(P53),ISNUMBER(I53),ISNUMBER(D53)),D53,0) -> 0
A54: HCKCSUBOVA | B54: Camiseta Hockey Playmaker, Cuello Ova s/mangas | C54: Juego | D54: 15 | I54: 17563 | J54: Por confirmar | K54: Sin receta: elige el molde que usa (o crea su receta en "Recetas") y la tela. | L54: =IF(OR(B54="",E54=""),"",IFERROR(INDEX(Recetas!$R$5:$R$84,MATCH($E54,Recetas!$A$5:$A$84,0))*IFERROR(INDEX(Precios!$F$5:$F$120,MATCH(F54,Precios!$A$5:$A$120,0)),"")+IF(N(INDEX(Recetas!$S$5:$S$84,MATCH($E54,Recetas!$A$5:$A$84,0)))=0,0,INDEX(Recetas!$S$5:$S$84,MATCH($E54,Recetas!$A$5:$A$84,0))*IFERROR(INDEX(Precios!$F$5:$F$120,MATCH(G54,Precios!$A$5:$A$120,0)),"")),"")) | M54: =IF(OR(B54="",E54=""),"",IFERROR(N(INDEX(Recetas!$L$5:$L$84,MATCH($E54,Recetas!$A$5:$A$84,0)))*Parametros!$B$27,"")) | N54: =IF(OR(B54="",E54=""),"",IFERROR(INDEX(Confeccion!$B$5:$B$100,MATCH(INDEX(Recetas!$M$5:$M$84,MATCH($E54,Recetas!$A$5:$A$84,0)),Confeccion!$A$5:$A$100,0)),"")) | O54: =IF(OR(B54="",E54=""),"",IFERROR(N(INDEX(Recetas!$O$5:$O$84,MATCH($E54,Recetas!$A$5:$A$84,0)))*INDEX(Precios!$D$5:$D$120,MATCH(INDEX(Recetas!$N$5:$N$84,MATCH($E54,Recetas!$A$5:$A$84,0)),Precios!$A$5:$A$120,0)),0)) | P54: =IF(OR(B54="",E54=""),"",IF(AND(IFERROR(INDEX(Recetas!$T$5:$T$84,MATCH($E54,Recetas!$A$5:$A$84,0))="Lista",FALSE()),ISNUMBER(L54),ISNUMBER(M54),ISNUMBER(N54),N(N54)>0),L54+M54+N54+N(O54)+N(H54),"")) | Q54: =IF(AND(ISNUMBER(P54),ISNUMBER(I54)),I54*Parametros!$B$12,"") | R54: =IF(AND(ISNUMBER(P54),ISNUMBER(I54)),I54*Parametros!$B$13,"") | S54: =IF(AND(ISNUMBER(P54),ISNUMBER(I54)),I54-P54-Q54-R54,"") | T54: =IF(AND(ISNUMBER(P54),ISNUMBER(I54)),S54/I54,"") | U54: =IF(OR(NOT(ISNUMBER(P54)),Parametros!$B$14>=1),"",P54/(1-Parametros!$B$14)) | V54: =IF(OR(NOT(ISNUMBER(P54)),Parametros!$B$14+Parametros!$B$18>=1),"",P54/(1-Parametros!$B$14-Parametros!$B$18)) | W54: =IF(B54="","",IF(E54="","SIN RECETA",IF(NOT(ISNUMBER(P54)),"FALTAN DATOS",IF(NOT(ISNUMBER(I54)),"FALTA PRECIO",IF(S54<0,"PIERDE",IF(T54<Parametros!$B$18,"BAJO META","OK")))))) -> SIN RECETA | X54: =IF(B54="","",IF(E54="","Elegir receta (molde). ",IF(ISNA(MATCH(E54,Recetas!$A$5:$A$84,0)),"La receta no existe. ",IF(IFERROR(INDEX(Recetas!$T$5:$T$84,MATCH($E54,Recetas!$A$5:$A$84,0))="Lista",FALSE()),"","Receta "&E54&": "&INDEX(Recetas!$T$5:$T$84,MATCH($E54,Recetas!$A$5:$A$84,0)))))&IF(F54="","Elegir tela. ",IF(IFERROR(INDEX(Precios!$F$5:$F$120,MATCH(F54,Precios!$A$5:$A$120,0)),"")="","Tela sin $/metro (falta rendimiento o precio). ",""))&IF(AND(E54<>"",N(IFERROR(INDEX(Recetas!$S$5:$S$84,MATCH($E54,Recetas!$A$5:$A$84,0)),0))>0,G54=""),"Elegir tela 2. ","")&IF(NOT(ISNUMBER(I54)),"Precio de venta.","")) -> Elegir receta (molde). Elegir tela. | Y54: =IF(AND(ISNUMBER(P54),ISNUMBER(I54),ISNUMBER(D54)),P54*D54,0) -> 0 | Z54: =IF(AND(ISNUMBER(P54),ISNUMBER(I54),ISNUMBER(D54)),I54*D54,0) -> 0 | AA54: =IF(AND(ISNUMBER(P54),ISNUMBER(I54),ISNUMBER(D54)),D54,0) -> 0
A55: HCK-FAL-LIS | B55: Falda Short Hockey Playmaker lisa | C55: Juego | D55: 15 | I55: 14202 | J55: Por confirmar | K55: Sin receta: elige el molde que usa (o crea su receta en "Recetas") y la tela. | L55: =IF(OR(B55="",E55=""),"",IFERROR(INDEX(Recetas!$R$5:$R$84,MATCH($E55,Recetas!$A$5:$A$84,0))*IFERROR(INDEX(Precios!$F$5:$F$120,MATCH(F55,Precios!$A$5:$A$120,0)),"")+IF(N(INDEX(Recetas!$S$5:$S$84,MATCH($E55,Recetas!$A$5:$A$84,0)))=0,0,INDEX(Recetas!$S$5:$S$84,MATCH($E55,Recetas!$A$5:$A$84,0))*IFERROR(INDEX(Precios!$F$5:$F$120,MATCH(G55,Precios!$A$5:$A$120,0)),"")),"")) | M55: =IF(OR(B55="",E55=""),"",IFERROR(N(INDEX(Recetas!$L$5:$L$84,MATCH($E55,Recetas!$A$5:$A$84,0)))*Parametros!$B$27,"")) | N55: =IF(OR(B55="",E55=""),"",IFERROR(INDEX(Confeccion!$B$5:$B$100,MATCH(INDEX(Recetas!$M$5:$M$84,MATCH($E55,Recetas!$A$5:$A$84,0)),Confeccion!$A$5:$A$100,0)),"")) | O55: =IF(OR(B55="",E55=""),"",IFERROR(N(INDEX(Recetas!$O$5:$O$84,MATCH($E55,Recetas!$A$5:$A$84,0)))*INDEX(Precios!$D$5:$D$120,MATCH(INDEX(Recetas!$N$5:$N$84,MATCH($E55,Recetas!$A$5:$A$84,0)),Precios!$A$5:$A$120,0)),0)) | P55: =IF(OR(B55="",E55=""),"",IF(AND(IFERROR(INDEX(Recetas!$T$5:$T$84,MATCH($E55,Recetas!$A$5:$A$84,0))="Lista",FALSE()),ISNUMBER(L55),ISNUMBER(M55),ISNUMBER(N55),N(N55)>0),L55+M55+N55+N(O55)+N(H55),"")) | Q55: =IF(AND(ISNUMBER(P55),ISNUMBER(I55)),I55*Parametros!$B$12,"") | R55: =IF(AND(ISNUMBER(P55),ISNUMBER(I55)),I55*Parametros!$B$13,"") | S55: =IF(AND(ISNUMBER(P55),ISNUMBER(I55)),I55-P55-Q55-R55,"") | T55: =IF(AND(ISNUMBER(P55),ISNUMBER(I55)),S55/I55,"") | U55: =IF(OR(NOT(ISNUMBER(P55)),Parametros!$B$14>=1),"",P55/(1-Parametros!$B$14)) | V55: =IF(OR(NOT(ISNUMBER(P55)),Parametros!$B$14+Parametros!$B$18>=1),"",P55/(1-Parametros!$B$14-Parametros!$B$18)) | W55: =IF(B55="","",IF(E55="","SIN RECETA",IF(NOT(ISNUMBER(P55)),"FALTAN DATOS",IF(NOT(ISNUMBER(I55)),"FALTA PRECIO",IF(S55<0,"PIERDE",IF(T55<Parametros!$B$18,"BAJO META","OK")))))) -> SIN RECETA | X55: =IF(B55="","",IF(E55="","Elegir receta (molde). ",IF(ISNA(MATCH(E55,Recetas!$A$5:$A$84,0)),"La receta no existe. ",IF(IFERROR(INDEX(Recetas!$T$5:$T$84,MATCH($E55,Recetas!$A$5:$A$84,0))="Lista",FALSE()),"","Receta "&E55&": "&INDEX(Recetas!$T$5:$T$84,MATCH($E55,Recetas!$A$5:$A$84,0)))))&IF(F55="","Elegir tela. ",IF(IFERROR(INDEX(Precios!$F$5:$F$120,MATCH(F55,Precios!$A$5:$A$120,0)),"")="","Tela sin $/metro (falta rendimiento o precio). ",""))&IF(AND(E55<>"",N(IFERROR(INDEX(Recetas!$S$5:$S$84,MATCH($E55,Recetas!$A$5:$A$84,0)),0))>0,G55=""),"Elegir tela 2. ","")&IF(NOT(ISNUMBER(I55)),"Precio de venta.","")) -> Elegir receta (molde). Elegir tela. | Y55: =IF(AND(ISNUMBER(P55),ISNUMBER(I55),ISNUMBER(D55)),P55*D55,0) -> 0 | Z55: =IF(AND(ISNUMBER(P55),ISNUMBER(I55),ISNUMBER(D55)),I55*D55,0) -> 0 | AA55: =IF(AND(ISNUMBER(P55),ISNUMBER(I55),ISNUMBER(D55)),D55,0) -> 0
A56: MDCALLARPMK | B56: Calza larga fem Playmaker | C56: Juego | D56: 14 | I56: 11681 | J56: Por confirmar | K56: Sin receta: elige el molde que usa (o crea su receta en "Recetas") y la tela. | L56: =IF(OR(B56="",E56=""),"",IFERROR(INDEX(Recetas!$R$5:$R$84,MATCH($E56,Recetas!$A$5:$A$84,0))*IFERROR(INDEX(Precios!$F$5:$F$120,MATCH(F56,Precios!$A$5:$A$120,0)),"")+IF(N(INDEX(Recetas!$S$5:$S$84,MATCH($E56,Recetas!$A$5:$A$84,0)))=0,0,INDEX(Recetas!$S$5:$S$84,MATCH($E56,Recetas!$A$5:$A$84,0))*IFERROR(INDEX(Precios!$F$5:$F$120,MATCH(G56,Precios!$A$5:$A$120,0)),"")),"")) | M56: =IF(OR(B56="",E56=""),"",IFERROR(N(INDEX(Recetas!$L$5:$L$84,MATCH($E56,Recetas!$A$5:$A$84,0)))*Parametros!$B$27,"")) | N56: =IF(OR(B56="",E56=""),"",IFERROR(INDEX(Confeccion!$B$5:$B$100,MATCH(INDEX(Recetas!$M$5:$M$84,MATCH($E56,Recetas!$A$5:$A$84,0)),Confeccion!$A$5:$A$100,0)),"")) | O56: =IF(OR(B56="",E56=""),"",IFERROR(N(INDEX(Recetas!$O$5:$O$84,MATCH($E56,Recetas!$A$5:$A$84,0)))*INDEX(Precios!$D$5:$D$120,MATCH(INDEX(Recetas!$N$5:$N$84,MATCH($E56,Recetas!$A$5:$A$84,0)),Precios!$A$5:$A$120,0)),0)) | P56: =IF(OR(B56="",E56=""),"",IF(AND(IFERROR(INDEX(Recetas!$T$5:$T$84,MATCH($E56,Recetas!$A$5:$A$84,0))="Lista",FALSE()),ISNUMBER(L56),ISNUMBER(M56),ISNUMBER(N56),N(N56)>0),L56+M56+N56+N(O56)+N(H56),"")) | Q56: =IF(AND(ISNUMBER(P56),ISNUMBER(I56)),I56*Parametros!$B$12,"") | R56: =IF(AND(ISNUMBER(P56),ISNUMBER(I56)),I56*Parametros!$B$13,"") | S56: =IF(AND(ISNUMBER(P56),ISNUMBER(I56)),I56-P56-Q56-R56,"") | T56: =IF(AND(ISNUMBER(P56),ISNUMBER(I56)),S56/I56,"") | U56: =IF(OR(NOT(ISNUMBER(P56)),Parametros!$B$14>=1),"",P56/(1-Parametros!$B$14)) | V56: =IF(OR(NOT(ISNUMBER(P56)),Parametros!$B$14+Parametros!$B$18>=1),"",P56/(1-Parametros!$B$14-Parametros!$B$18)) | W56: =IF(B56="","",IF(E56="","SIN RECETA",IF(NOT(ISNUMBER(P56)),"FALTAN DATOS",IF(NOT(ISNUMBER(I56)),"FALTA PRECIO",IF(S56<0,"PIERDE",IF(T56<Parametros!$B$18,"BAJO META","OK")))))) -> SIN RECETA | X56: =IF(B56="","",IF(E56="","Elegir receta (molde). ",IF(ISNA(MATCH(E56,Recetas!$A$5:$A$84,0)),"La receta no existe. ",IF(IFERROR(INDEX(Recetas!$T$5:$T$84,MATCH($E56,Recetas!$A$5:$A$84,0))="Lista",FALSE()),"","Receta "&E56&": "&INDEX(Recetas!$T$5:$T$84,MATCH($E56,Recetas!$A$5:$A$84,0)))))&IF(F56="","Elegir tela. ",IF(IFERROR(INDEX(Precios!$F$5:$F$120,MATCH(F56,Precios!$A$5:$A$120,0)),"")="","Tela sin $/metro (falta rendimiento o precio). ",""))&IF(AND(E56<>"",N(IFERROR(INDEX(Recetas!$S$5:$S$84,MATCH($E56,Recetas!$A$5:$A$84,0)),0))>0,G56=""),"Elegir tela 2. ","")&IF(NOT(ISNUMBER(I56)),"Precio de venta.","")) -> Elegir receta (molde). Elegir tela. | Y56: =IF(AND(ISNUMBER(P56),ISNUMBER(I56),ISNUMBER(D56)),P56*D56,0) -> 0 | Z56: =IF(AND(ISNUMBER(P56),ISNUMBER(I56),ISNUMBER(D56)),I56*D56,0) -> 0 | AA56: =IF(AND(ISNUMBER(P56),ISNUMBER(I56),ISNUMBER(D56)),D56,0) -> 0
A57: SAL-HOO-APSUB | B57: Polerón Hoodie Aplicación Sublim | C57: Salida | D57: 14 | I57: 31092 | J57: Por confirmar | K57: Sin receta: elige el molde que usa (o crea su receta en "Recetas") y la tela. | L57: =IF(OR(B57="",E57=""),"",IFERROR(INDEX(Recetas!$R$5:$R$84,MATCH($E57,Recetas!$A$5:$A$84,0))*IFERROR(INDEX(Precios!$F$5:$F$120,MATCH(F57,Precios!$A$5:$A$120,0)),"")+IF(N(INDEX(Recetas!$S$5:$S$84,MATCH($E57,Recetas!$A$5:$A$84,0)))=0,0,INDEX(Recetas!$S$5:$S$84,MATCH($E57,Recetas!$A$5:$A$84,0))*IFERROR(INDEX(Precios!$F$5:$F$120,MATCH(G57,Precios!$A$5:$A$120,0)),"")),"")) | M57: =IF(OR(B57="",E57=""),"",IFERROR(N(INDEX(Recetas!$L$5:$L$84,MATCH($E57,Recetas!$A$5:$A$84,0)))*Parametros!$B$27,"")) | N57: =IF(OR(B57="",E57=""),"",IFERROR(INDEX(Confeccion!$B$5:$B$100,MATCH(INDEX(Recetas!$M$5:$M$84,MATCH($E57,Recetas!$A$5:$A$84,0)),Confeccion!$A$5:$A$100,0)),"")) | O57: =IF(OR(B57="",E57=""),"",IFERROR(N(INDEX(Recetas!$O$5:$O$84,MATCH($E57,Recetas!$A$5:$A$84,0)))*INDEX(Precios!$D$5:$D$120,MATCH(INDEX(Recetas!$N$5:$N$84,MATCH($E57,Recetas!$A$5:$A$84,0)),Precios!$A$5:$A$120,0)),0)) | P57: =IF(OR(B57="",E57=""),"",IF(AND(IFERROR(INDEX(Recetas!$T$5:$T$84,MATCH($E57,Recetas!$A$5:$A$84,0))="Lista",FALSE()),ISNUMBER(L57),ISNUMBER(M57),ISNUMBER(N57),N(N57)>0),L57+M57+N57+N(O57)+N(H57),"")) | Q57: =IF(AND(ISNUMBER(P57),ISNUMBER(I57)),I57*Parametros!$B$12,"") | R57: =IF(AND(ISNUMBER(P57),ISNUMBER(I57)),I57*Parametros!$B$13,"") | S57: =IF(AND(ISNUMBER(P57),ISNUMBER(I57)),I57-P57-Q57-R57,"") | T57: =IF(AND(ISNUMBER(P57),ISNUMBER(I57)),S57/I57,"") | U57: =IF(OR(NOT(ISNUMBER(P57)),Parametros!$B$14>=1),"",P57/(1-Parametros!$B$14)) | V57: =IF(OR(NOT(ISNUMBER(P57)),Parametros!$B$14+Parametros!$B$18>=1),"",P57/(1-Parametros!$B$14-Parametros!$B$18)) | W57: =IF(B57="","",IF(E57="","SIN RECETA",IF(NOT(ISNUMBER(P57)),"FALTAN DATOS",IF(NOT(ISNUMBER(I57)),"FALTA PRECIO",IF(S57<0,"PIERDE",IF(T57<Parametros!$B$18,"BAJO META","OK")))))) -> SIN RECETA | X57: =IF(B57="","",IF(E57="","Elegir receta (molde). ",IF(ISNA(MATCH(E57,Recetas!$A$5:$A$84,0)),"La receta no existe. ",IF(IFERROR(INDEX(Recetas!$T$5:$T$84,MATCH($E57,Recetas!$A$5:$A$84,0))="Lista",FALSE()),"","Receta "&E57&": "&INDEX(Recetas!$T$5:$T$84,MATCH($E57,Recetas!$A$5:$A$84,0)))))&IF(F57="","Elegir tela. ",IF(IFERROR(INDEX(Precios!$F$5:$F$120,MATCH(F57,Precios!$A$5:$A$120,0)),"")="","Tela sin $/metro (falta rendimiento o precio). ",""))&IF(AND(E57<>"",N(IFERROR(INDEX(Recetas!$S$5:$S$84,MATCH($E57,Recetas!$A$5:$A$84,0)),0))>0,G57=""),"Elegir tela 2. ","")&IF(NOT(ISNUMBER(I57)),"Precio de venta.","")) -> Elegir receta (molde). Elegir tela. | Y57: =IF(AND(ISNUMBER(P57),ISNUMBER(I57),ISNUMBER(D57)),P57*D57,0) -> 0 | Z57: =IF(AND(ISNUMBER(P57),ISNUMBER(I57),ISNUMBER(D57)),I57*D57,0) -> 0 | AA57: =IF(AND(ISNUMBER(P57),ISNUMBER(I57),ISNUMBER(D57)),D57,0) -> 0
A58: SAL-POL-BAS | B58: POLERON BASIC | C58: Salida | D58: 13 | I58: 17646 | J58: Por confirmar | K58: Sin receta: elige el molde que usa (o crea su receta en "Recetas") y la tela. | L58: =IF(OR(B58="",E58=""),"",IFERROR(INDEX(Recetas!$R$5:$R$84,MATCH($E58,Recetas!$A$5:$A$84,0))*IFERROR(INDEX(Precios!$F$5:$F$120,MATCH(F58,Precios!$A$5:$A$120,0)),"")+IF(N(INDEX(Recetas!$S$5:$S$84,MATCH($E58,Recetas!$A$5:$A$84,0)))=0,0,INDEX(Recetas!$S$5:$S$84,MATCH($E58,Recetas!$A$5:$A$84,0))*IFERROR(INDEX(Precios!$F$5:$F$120,MATCH(G58,Precios!$A$5:$A$120,0)),"")),"")) | M58: =IF(OR(B58="",E58=""),"",IFERROR(N(INDEX(Recetas!$L$5:$L$84,MATCH($E58,Recetas!$A$5:$A$84,0)))*Parametros!$B$27,"")) | N58: =IF(OR(B58="",E58=""),"",IFERROR(INDEX(Confeccion!$B$5:$B$100,MATCH(INDEX(Recetas!$M$5:$M$84,MATCH($E58,Recetas!$A$5:$A$84,0)),Confeccion!$A$5:$A$100,0)),"")) | O58: =IF(OR(B58="",E58=""),"",IFERROR(N(INDEX(Recetas!$O$5:$O$84,MATCH($E58,Recetas!$A$5:$A$84,0)))*INDEX(Precios!$D$5:$D$120,MATCH(INDEX(Recetas!$N$5:$N$84,MATCH($E58,Recetas!$A$5:$A$84,0)),Precios!$A$5:$A$120,0)),0)) | P58: =IF(OR(B58="",E58=""),"",IF(AND(IFERROR(INDEX(Recetas!$T$5:$T$84,MATCH($E58,Recetas!$A$5:$A$84,0))="Lista",FALSE()),ISNUMBER(L58),ISNUMBER(M58),ISNUMBER(N58),N(N58)>0),L58+M58+N58+N(O58)+N(H58),"")) | Q58: =IF(AND(ISNUMBER(P58),ISNUMBER(I58)),I58*Parametros!$B$12,"") | R58: =IF(AND(ISNUMBER(P58),ISNUMBER(I58)),I58*Parametros!$B$13,"") | S58: =IF(AND(ISNUMBER(P58),ISNUMBER(I58)),I58-P58-Q58-R58,"") | T58: =IF(AND(ISNUMBER(P58),ISNUMBER(I58)),S58/I58,"") | U58: =IF(OR(NOT(ISNUMBER(P58)),Parametros!$B$14>=1),"",P58/(1-Parametros!$B$14)) | V58: =IF(OR(NOT(ISNUMBER(P58)),Parametros!$B$14+Parametros!$B$18>=1),"",P58/(1-Parametros!$B$14-Parametros!$B$18)) | W58: =IF(B58="","",IF(E58="","SIN RECETA",IF(NOT(ISNUMBER(P58)),"FALTAN DATOS",IF(NOT(ISNUMBER(I58)),"FALTA PRECIO",IF(S58<0,"PIERDE",IF(T58<Parametros!$B$18,"BAJO META","OK")))))) -> SIN RECETA | X58: =IF(B58="","",IF(E58="","Elegir receta (molde). ",IF(ISNA(MATCH(E58,Recetas!$A$5:$A$84,0)),"La receta no existe. ",IF(IFERROR(INDEX(Recetas!$T$5:$T$84,MATCH($E58,Recetas!$A$5:$A$84,0))="Lista",FALSE()),"","Receta "&E58&": "&INDEX(Recetas!$T$5:$T$84,MATCH($E58,Recetas!$A$5:$A$84,0)))))&IF(F58="","Elegir tela. ",IF(IFERROR(INDEX(Precios!$F$5:$F$120,MATCH(F58,Precios!$A$5:$A$120,0)),"")="","Tela sin $/metro (falta rendimiento o precio). ",""))&IF(AND(E58<>"",N(IFERROR(INDEX(Recetas!$S$5:$S$84,MATCH($E58,Recetas!$A$5:$A$84,0)),0))>0,G58=""),"Elegir tela 2. ","")&IF(NOT(ISNUMBER(I58)),"Precio de venta.","")) -> Elegir receta (molde). Elegir tela. | Y58: =IF(AND(ISNUMBER(P58),ISNUMBER(I58),ISNUMBER(D58)),P58*D58,0) -> 0 | Z58: =IF(AND(ISNUMBER(P58),ISNUMBER(I58),ISNUMBER(D58)),I58*D58,0) -> 0 | AA58: =IF(AND(ISNUMBER(P58),ISNUMBER(I58),ISNUMBER(D58)),D58,0) -> 0
... A69: RUGCSUBENTMC | B69: Camiseta de entrenamiento Rugby,m/c | C69: Juego | D69: 5 | I69: 15882 | J69: Por confirmar | K69: Sin receta: elige el molde que usa (o crea su receta en "Recetas") y la tela. | L69: =IF(OR(B69="",E69=""),"",IFERROR(INDEX(Recetas!$R$5:$R$84,MATCH($E69,Recetas!$A$5:$A$84,0))*IFERROR(INDEX(Precios!$F$5:$F$120,MATCH(F69,Precios!$A$5:$A$120,0)),"")+IF(N(INDEX(Recetas!$S$5:$S$84,MATCH($E69,Recetas!$A$5:$A$84,0)))=0,0,INDEX(Recetas!$S$5:$S$84,MATCH($E69,Recetas!$A$5:$A$84,0))*IFERROR(INDEX(Precios!$F$5:$F$120,MATCH(G69,Precios!$A$5:$A$120,0)),"")),"")) | M69: =IF(OR(B69="",E69=""),"",IFERROR(N(INDEX(Recetas!$L$5:$L$84,MATCH($E69,Recetas!$A$5:$A$84,0)))*Parametros!$B$27,"")) | N69: =IF(OR(B69="",E69=""),"",IFERROR(INDEX(Confeccion!$B$5:$B$100,MATCH(INDEX(Recetas!$M$5:$M$84,MATCH($E69,Recetas!$A$5:$A$84,0)),Confeccion!$A$5:$A$100,0)),"")) | O69: =IF(OR(B69="",E69=""),"",IFERROR(N(INDEX(Recetas!$O$5:$O$84,MATCH($E69,Recetas!$A$5:$A$84,0)))*INDEX(Precios!$D$5:$D$120,MATCH(INDEX(Recetas!$N$5:$N$84,MATCH($E69,Recetas!$A$5:$A$84,0)),Precios!$A$5:$A$120,0)),0)) | P69: =IF(OR(B69="",E69=""),"",IF(AND(IFERROR(INDEX(Recetas!$T$5:$T$84,MATCH($E69,Recetas!$A$5:$A$84,0))="Lista",FALSE()),ISNUMBER(L69),ISNUMBER(M69),ISNUMBER(N69),N(N69)>0),L69+M69+N69+N(O69)+N(H69),"")) | Q69: =IF(AND(ISNUMBER(P69),ISNUMBER(I69)),I69*Parametros!$B$12,"") | R69: =IF(AND(ISNUMBER(P69),ISNUMBER(I69)),I69*Parametros!$B$13,"") | S69: =IF(AND(ISNUMBER(P69),ISNUMBER(I69)),I69-P69-Q69-R69,"") | T69: =IF(AND(ISNUMBER(P69),ISNUMBER(I69)),S69/I69,"") | U69: =IF(OR(NOT(ISNUMBER(P69)),Parametros!$B$14>=1),"",P69/(1-Parametros!$B$14)) | V69: =IF(OR(NOT(ISNUMBER(P69)),Parametros!$B$14+Parametros!$B$18>=1),"",P69/(1-Parametros!$B$14-Parametros!$B$18)) | W69: =IF(B69="","",IF(E69="","SIN RECETA",IF(NOT(ISNUMBER(P69)),"FALTAN DATOS",IF(NOT(ISNUMBER(I69)),"FALTA PRECIO",IF(S69<0,"PIERDE",IF(T69<Parametros!$B$18,"BAJO META","OK")))))) -> SIN RECETA | X69: =IF(B69="","",IF(E69="","Elegir receta (molde). ",IF(ISNA(MATCH(E69,Recetas!$A$5:$A$84,0)),"La receta no existe. ",IF(IFERROR(INDEX(Recetas!$T$5:$T$84,MATCH($E69,Recetas!$A$5:$A$84,0))="Lista",FALSE()),"","Receta "&E69&": "&INDEX(Recetas!$T$5:$T$84,MATCH($E69,Recetas!$A$5:$A$84,0)))))&IF(F69="","Elegir tela. ",IF(IFERROR(INDEX(Precios!$F$5:$F$120,MATCH(F69,Precios!$A$5:$A$120,0)),"")="","Tela sin $/metro (falta rendimiento o precio). ",""))&IF(AND(E69<>"",N(IFERROR(INDEX(Recetas!$S$5:$S$84,MATCH($E69,Recetas!$A$5:$A$84,0)),0))>0,G69=""),"Elegir tela 2. ","")&IF(NOT(ISNUMBER(I69)),"Precio de venta.","")) -> Elegir receta (molde). Elegir tela. | Y69: =IF(AND(ISNUMBER(P69),ISNUMBER(I69),ISNUMBER(D69)),P69*D69,0) -> 0 | Z69: =IF(AND(ISNUMBER(P69),ISNUMBER(I69),ISNUMBER(D69)),I69*D69,0) -> 0 | AA69: =IF(AND(ISNUMBER(P69),ISNUMBER(I69),ISNUMBER(D69)),D69,0) -> 0
A70: MDCALCORPMK | B70: Calza corta fem Playmaker | C70: Juego | D70: 4 | E70: SM-04 · Calza Vóley | F70: LYCRA | I70: 12689 | J70: Por confirmar | L70: =IF(OR(B70="",E70=""),"",IFERROR(INDEX(Recetas!$R$5:$R$84,MATCH($E70,Recetas!$A$5:$A$84,0))*IFERROR(INDEX(Precios!$F$5:$F$120,MATCH(F70,Precios!$A$5:$A$120,0)),"")+IF(N(INDEX(Recetas!$S$5:$S$84,MATCH($E70,Recetas!$A$5:$A$84,0)))=0,0,INDEX(Recetas!$S$5:$S$84,MATCH($E70,Recetas!$A$5:$A$84,0))*IFERROR(INDEX(Precios!$F$5:$F$120,MATCH(G70,Precios!$A$5:$A$120,0)),"")),"")) | M70: =IF(OR(B70="",E70=""),"",IFERROR(N(INDEX(Recetas!$L$5:$L$84,MATCH($E70,Recetas!$A$5:$A$84,0)))*Parametros!$B$27,"")) -> 0 | N70: =IF(OR(B70="",E70=""),"",IFERROR(INDEX(Confeccion!$B$5:$B$100,MATCH(INDEX(Recetas!$M$5:$M$84,MATCH($E70,Recetas!$A$5:$A$84,0)),Confeccion!$A$5:$A$100,0)),"")) -> 1200 | O70: =IF(OR(B70="",E70=""),"",IFERROR(N(INDEX(Recetas!$O$5:$O$84,MATCH($E70,Recetas!$A$5:$A$84,0)))*INDEX(Precios!$D$5:$D$120,MATCH(INDEX(Recetas!$N$5:$N$84,MATCH($E70,Recetas!$A$5:$A$84,0)),Precios!$A$5:$A$120,0)),0)) -> 0 | P70: =IF(OR(B70="",E70=""),"",IF(AND(IFERROR(INDEX(Recetas!$T$5:$T$84,MATCH($E70,Recetas!$A$5:$A$84,0))="Lista",FALSE()),ISNUMBER(L70),ISNUMBER(M70),ISNUMBER(N70),N(N70)>0),L70+M70+N70+N(O70)+N(H70),"")) | Q70: =IF(AND(ISNUMBER(P70),ISNUMBER(I70)),I70*Parametros!$B$12,"") | R70: =IF(AND(ISNUMBER(P70),ISNUMBER(I70)),I70*Parametros!$B$13,"") | S70: =IF(AND(ISNUMBER(P70),ISNUMBER(I70)),I70-P70-Q70-R70,"") | T70: =IF(AND(ISNUMBER(P70),ISNUMBER(I70)),S70/I70,"") | U70: =IF(OR(NOT(ISNUMBER(P70)),Parametros!$B$14>=1),"",P70/(1-Parametros!$B$14)) | V70: =IF(OR(NOT(ISNUMBER(P70)),Parametros!$B$14+Parametros!$B$18>=1),"",P70/(1-Parametros!$B$14-Parametros!$B$18)) | W70: =IF(B70="","",IF(E70="","SIN RECETA",IF(NOT(ISNUMBER(P70)),"FALTAN DATOS",IF(NOT(ISNUMBER(I70)),"FALTA PRECIO",IF(S70<0,"PIERDE",IF(T70<Parametros!$B$18,"BAJO META","OK")))))) -> FALTAN DATOS | X70: =IF(B70="","",IF(E70="","Elegir receta (molde). ",IF(ISNA(MATCH(E70,Recetas!$A$5:$A$84,0)),"La receta no existe. ",IF(IFERROR(INDEX(Recetas!$T$5:$T$84,MATCH($E70,Recetas!$A$5:$A$84,0))="Lista",FALSE()),"","Receta "&E70&": "&INDEX(Recetas!$T$5:$T$84,MATCH($E70,Recetas!$A$5:$A$84,0)))))&IF(F70="","Elegir tela. ",IF(IFERROR(INDEX(Precios!$F$5:$F$120,MATCH(F70,Precios!$A$5:$A$120,0)),"")="","Tela sin $/metro (falta rendimiento o precio). ",""))&IF(AND(E70<>"",N(IFERROR(INDEX(Recetas!$S$5:$S$84,MATCH($E70,Recetas!$A$5:$A$84,0)),0))>0,G70=""),"Elegir tela 2. ","")&IF(NOT(ISNUMBER(I70)),"Precio de venta.","")) -> Receta SM-04 · Calza Vóley: Rendimiento de LYCRA (m/kg) en Precios. Tela sin $/metro (falta rendimiento o precio). | Y70: =IF(AND(ISNUMBER(P70),ISNUMBER(I70),ISNUMBER(D70)),P70*D70,0) -> 0 | Z70: =IF(AND(ISNUMBER(P70),ISNUMBER(I70),ISNUMBER(D70)),I70*D70,0) -> 0 | AA70: =IF(AND(ISNUMBER(P70),ISNUMBER(I70),ISNUMBER(D70)),D70,0) -> 0
A71: SAL-SHO-LIS | B71: Short Salida con bolsillos | C71: Salida | D71: 4 | I71: 13445 | J71: Por confirmar | K71: Sin receta: elige el molde que usa (o crea su receta en "Recetas") y la tela. | L71: =IF(OR(B71="",E71=""),"",IFERROR(INDEX(Recetas!$R$5:$R$84,MATCH($E71,Recetas!$A$5:$A$84,0))*IFERROR(INDEX(Precios!$F$5:$F$120,MATCH(F71,Precios!$A$5:$A$120,0)),"")+IF(N(INDEX(Recetas!$S$5:$S$84,MATCH($E71,Recetas!$A$5:$A$84,0)))=0,0,INDEX(Recetas!$S$5:$S$84,MATCH($E71,Recetas!$A$5:$A$84,0))*IFERROR(INDEX(Precios!$F$5:$F$120,MATCH(G71,Precios!$A$5:$A$120,0)),"")),"")) | M71: =IF(OR(B71="",E71=""),"",IFERROR(N(INDEX(Recetas!$L$5:$L$84,MATCH($E71,Recetas!$A$5:$A$84,0)))*Parametros!$B$27,"")) | N71: =IF(OR(B71="",E71=""),"",IFERROR(INDEX(Confeccion!$B$5:$B$100,MATCH(INDEX(Recetas!$M$5:$M$84,MATCH($E71,Recetas!$A$5:$A$84,0)),Confeccion!$A$5:$A$100,0)),"")) | O71: =IF(OR(B71="",E71=""),"",IFERROR(N(INDEX(Recetas!$O$5:$O$84,MATCH($E71,Recetas!$A$5:$A$84,0)))*INDEX(Precios!$D$5:$D$120,MATCH(INDEX(Recetas!$N$5:$N$84,MATCH($E71,Recetas!$A$5:$A$84,0)),Precios!$A$5:$A$120,0)),0)) | P71: =IF(OR(B71="",E71=""),"",IF(AND(IFERROR(INDEX(Recetas!$T$5:$T$84,MATCH($E71,Recetas!$A$5:$A$84,0))="Lista",FALSE()),ISNUMBER(L71),ISNUMBER(M71),ISNUMBER(N71),N(N71)>0),L71+M71+N71+N(O71)+N(H71),"")) | Q71: =IF(AND(ISNUMBER(P71),ISNUMBER(I71)),I71*Parametros!$B$12,"") | R71: =IF(AND(ISNUMBER(P71),ISNUMBER(I71)),I71*Parametros!$B$13,"") | S71: =IF(AND(ISNUMBER(P71),ISNUMBER(I71)),I71-P71-Q71-R71,"") | T71: =IF(AND(ISNUMBER(P71),ISNUMBER(I71)),S71/I71,"") | U71: =IF(OR(NOT(ISNUMBER(P71)),Parametros!$B$14>=1),"",P71/(1-Parametros!$B$14)) | V71: =IF(OR(NOT(ISNUMBER(P71)),Parametros!$B$14+Parametros!$B$18>=1),"",P71/(1-Parametros!$B$14-Parametros!$B$18)) | W71: =IF(B71="","",IF(E71="","SIN RECETA",IF(NOT(ISNUMBER(P71)),"FALTAN DATOS",IF(NOT(ISNUMBER(I71)),"FALTA PRECIO",IF(S71<0,"PIERDE",IF(T71<Parametros!$B$18,"BAJO META","OK")))))) -> SIN RECETA | X71: =IF(B71="","",IF(E71="","Elegir receta (molde). ",IF(ISNA(MATCH(E71,Recetas!$A$5:$A$84,0)),"La receta no existe. ",IF(IFERROR(INDEX(Recetas!$T$5:$T$84,MATCH($E71,Recetas!$A$5:$A$84,0))="Lista",FALSE()),"","Receta "&E71&": "&INDEX(Recetas!$T$5:$T$84,MATCH($E71,Recetas!$A$5:$A$84,0)))))&IF(F71="","Elegir tela. ",IF(IFERROR(INDEX(Precios!$F$5:$F$120,MATCH(F71,Precios!$A$5:$A$120,0)),"")="","Tela sin $/metro (falta rendimiento o precio). ",""))&IF(AND(E71<>"",N(IFERROR(INDEX(Recetas!$S$5:$S$84,MATCH($E71,Recetas!$A$5:$A$84,0)),0))>0,G71=""),"Elegir tela 2. ","")&IF(NOT(ISNUMBER(I71)),"Precio de venta.","")) -> Elegir receta (molde). Elegir tela. | Y71: =IF(AND(ISNUMBER(P71),ISNUMBER(I71),ISNUMBER(D71)),P71*D71,0) -> 0 | Z71: =IF(AND(ISNUMBER(P71),ISNUMBER(I71),ISNUMBER(D71)),I71*D71,0) -> 0 | AA71: =IF(AND(ISNUMBER(P71),ISNUMBER(I71),ISNUMBER(D71)),D71,0) -> 0
A72: ENT-POL-MANSUBL | B72: POLERON DE ENTRENAMIENTO MANGAS SUBLIMADAS MASC | C72: Salida | D72: 4 | I72: 30168 | J72: Por confirmar | K72: Sin receta: elige el molde que usa (o crea su receta en "Recetas") y la tela. | L72: =IF(OR(B72="",E72=""),"",IFERROR(INDEX(Recetas!$R$5:$R$84,MATCH($E72,Recetas!$A$5:$A$84,0))*IFERROR(INDEX(Precios!$F$5:$F$120,MATCH(F72,Precios!$A$5:$A$120,0)),"")+IF(N(INDEX(Recetas!$S$5:$S$84,MATCH($E72,Recetas!$A$5:$A$84,0)))=0,0,INDEX(Recetas!$S$5:$S$84,MATCH($E72,Recetas!$A$5:$A$84,0))*IFERROR(INDEX(Precios!$F$5:$F$120,MATCH(G72,Precios!$A$5:$A$120,0)),"")),"")) | M72: =IF(OR(B72="",E72=""),"",IFERROR(N(INDEX(Recetas!$L$5:$L$84,MATCH($E72,Recetas!$A$5:$A$84,0)))*Parametros!$B$27,"")) | N72: =IF(OR(B72="",E72=""),"",IFERROR(INDEX(Confeccion!$B$5:$B$100,MATCH(INDEX(Recetas!$M$5:$M$84,MATCH($E72,Recetas!$A$5:$A$84,0)),Confeccion!$A$5:$A$100,0)),"")) | O72: =IF(OR(B72="",E72=""),"",IFERROR(N(INDEX(Recetas!$O$5:$O$84,MATCH($E72,Recetas!$A$5:$A$84,0)))*INDEX(Precios!$D$5:$D$120,MATCH(INDEX(Recetas!$N$5:$N$84,MATCH($E72,Recetas!$A$5:$A$84,0)),Precios!$A$5:$A$120,0)),0)) | P72: =IF(OR(B72="",E72=""),"",IF(AND(IFERROR(INDEX(Recetas!$T$5:$T$84,MATCH($E72,Recetas!$A$5:$A$84,0))="Lista",FALSE()),ISNUMBER(L72),ISNUMBER(M72),ISNUMBER(N72),N(N72)>0),L72+M72+N72+N(O72)+N(H72),"")) | Q72: =IF(AND(ISNUMBER(P72),ISNUMBER(I72)),I72*Parametros!$B$12,"") | R72: =IF(AND(ISNUMBER(P72),ISNUMBER(I72)),I72*Parametros!$B$13,"") | S72: =IF(AND(ISNUMBER(P72),ISNUMBER(I72)),I72-P72-Q72-R72,"") | T72: =IF(AND(ISNUMBER(P72),ISNUMBER(I72)),S72/I72,"") | U72: =IF(OR(NOT(ISNUMBER(P72)),Parametros!$B$14>=1),"",P72/(1-Parametros!$B$14)) | V72: =IF(OR(NOT(ISNUMBER(P72)),Parametros!$B$14+Parametros!$B$18>=1),"",P72/(1-Parametros!$B$14-Parametros!$B$18)) | W72: =IF(B72="","",IF(E72="","SIN RECETA",IF(NOT(ISNUMBER(P72)),"FALTAN DATOS",IF(NOT(ISNUMBER(I72)),"FALTA PRECIO",IF(S72<0,"PIERDE",IF(T72<Parametros!$B$18,"BAJO META","OK")))))) -> SIN RECETA | X72: =IF(B72="","",IF(E72="","Elegir receta (molde). ",IF(ISNA(MATCH(E72,Recetas!$A$5:$A$84,0)),"La receta no existe. ",IF(IFERROR(INDEX(Recetas!$T$5:$T$84,MATCH($E72,Recetas!$A$5:$A$84,0))="Lista",FALSE()),"","Receta "&E72&": "&INDEX(Recetas!$T$5:$T$84,MATCH($E72,Recetas!$A$5:$A$84,0)))))&IF(F72="","Elegir tela. ",IF(IFERROR(INDEX(Precios!$F$5:$F$120,MATCH(F72,Precios!$A$5:$A$120,0)),"")="","Tela sin $/metro (falta rendimiento o precio). ",""))&IF(AND(E72<>"",N(IFERROR(INDEX(Recetas!$S$5:$S$84,MATCH($E72,Recetas!$A$5:$A$84,0)),0))>0,G72=""),"Elegir tela 2. ","")&IF(NOT(ISNUMBER(I72)),"Precio de venta.","")) -> Elegir receta (molde). Elegir tela. | Y72: =IF(AND(ISNUMBER(P72),ISNUMBER(I72),ISNUMBER(D72)),P72*D72,0) -> 0 | Z72: =IF(AND(ISNUMBER(P72),ISNUMBER(I72),ISNUMBER(D72)),I72*D72,0) -> 0 | AA72: =IF(AND(ISNUMBER(P72),ISNUMBER(I72),ISNUMBER(D72)),D72,0) -> 0
A73: VOLMASC-CSUB-V-CER | B73: Camiseta Voley masc Playmaker, V m/cero | C73: Juego | D73: 3 | I73: 16723 | J73: Por confirmar | K73: Sin receta: elige el molde que usa (o crea su receta en "Recetas") y la tela. | L73: =IF(OR(B73="",E73=""),"",IFERROR(INDEX(Recetas!$R$5:$R$84,MATCH($E73,Recetas!$A$5:$A$84,0))*IFERROR(INDEX(Precios!$F$5:$F$120,MATCH(F73,Precios!$A$5:$A$120,0)),"")+IF(N(INDEX(Recetas!$S$5:$S$84,MATCH($E73,Recetas!$A$5:$A$84,0)))=0,0,INDEX(Recetas!$S$5:$S$84,MATCH($E73,Recetas!$A$5:$A$84,0))*IFERROR(INDEX(Precios!$F$5:$F$120,MATCH(G73,Precios!$A$5:$A$120,0)),"")),"")) | M73: =IF(OR(B73="",E73=""),"",IFERROR(N(INDEX(Recetas!$L$5:$L$84,MATCH($E73,Recetas!$A$5:$A$84,0)))*Parametros!$B$27,"")) | N73: =IF(OR(B73="",E73=""),"",IFERROR(INDEX(Confeccion!$B$5:$B$100,MATCH(INDEX(Recetas!$M$5:$M$84,MATCH($E73,Recetas!$A$5:$A$84,0)),Confeccion!$A$5:$A$100,0)),"")) | O73: =IF(OR(B73="",E73=""),"",IFERROR(N(INDEX(Recetas!$O$5:$O$84,MATCH($E73,Recetas!$A$5:$A$84,0)))*INDEX(Precios!$D$5:$D$120,MATCH(INDEX(Recetas!$N$5:$N$84,MATCH($E73,Recetas!$A$5:$A$84,0)),Precios!$A$5:$A$120,0)),0)) | P73: =IF(OR(B73="",E73=""),"",IF(AND(IFERROR(INDEX(Recetas!$T$5:$T$84,MATCH($E73,Recetas!$A$5:$A$84,0))="Lista",FALSE()),ISNUMBER(L73),ISNUMBER(M73),ISNUMBER(N73),N(N73)>0),L73+M73+N73+N(O73)+N(H73),"")) | Q73: =IF(AND(ISNUMBER(P73),ISNUMBER(I73)),I73*Parametros!$B$12,"") | R73: =IF(AND(ISNUMBER(P73),ISNUMBER(I73)),I73*Parametros!$B$13,"") | S73: =IF(AND(ISNUMBER(P73),ISNUMBER(I73)),I73-P73-Q73-R73,"") | T73: =IF(AND(ISNUMBER(P73),ISNUMBER(I73)),S73/I73,"") | U73: =IF(OR(NOT(ISNUMBER(P73)),Parametros!$B$14>=1),"",P73/(1-Parametros!$B$14)) | V73: =IF(OR(NOT(ISNUMBER(P73)),Parametros!$B$14+Parametros!$B$18>=1),"",P73/(1-Parametros!$B$14-Parametros!$B$18)) | W73: =IF(B73="","",IF(E73="","SIN RECETA",IF(NOT(ISNUMBER(P73)),"FALTAN DATOS",IF(NOT(ISNUMBER(I73)),"FALTA PRECIO",IF(S73<0,"PIERDE",IF(T73<Parametros!$B$18,"BAJO META","OK")))))) -> SIN RECETA | X73: =IF(B73="","",IF(E73="","Elegir receta (molde). ",IF(ISNA(MATCH(E73,Recetas!$A$5:$A$84,0)),"La receta no existe. ",IF(IFERROR(INDEX(Recetas!$T$5:$T$84,MATCH($E73,Recetas!$A$5:$A$84,0))="Lista",FALSE()),"","Receta "&E73&": "&INDEX(Recetas!$T$5:$T$84,MATCH($E73,Recetas!$A$5:$A$84,0)))))&IF(F73="","Elegir tela. ",IF(IFERROR(INDEX(Precios!$F$5:$F$120,MATCH(F73,Precios!$A$5:$A$120,0)),"")="","Tela sin $/metro (falta rendimiento o precio). ",""))&IF(AND(E73<>"",N(IFERROR(INDEX(Recetas!$S$5:$S$84,MATCH($E73,Recetas!$A$5:$A$84,0)),0))>0,G73=""),"Elegir tela 2. ","")&IF(NOT(ISNUMBER(I73)),"Precio de venta.","")) -> Elegir receta (molde). Elegir tela. | Y73: =IF(AND(ISNUMBER(P73),ISNUMBER(I73),ISNUMBER(D73)),P73*D73,0) -> 0 | Z73: =IF(AND(ISNUMBER(P73),ISNUMBER(I73),ISNUMBER(D73)),I73*D73,0) -> 0 | AA73: =IF(AND(ISNUMBER(P73),ISNUMBER(I73),ISNUMBER(D73)),D73,0) -> 0
A74: SAL-POL-MGSUB | B74: Polerón Entrenamiento liso con mangas Sublim | C74: Salida | D74: 2 | I74: 27647 | J74: Por confirmar | K74: Sin receta: elige el molde que usa (o crea su receta en "Recetas") y la tela. | L74: =IF(OR(B74="",E74=""),"",IFERROR(INDEX(Recetas!$R$5:$R$84,MATCH($E74,Recetas!$A$5:$A$84,0))*IFERROR(INDEX(Precios!$F$5:$F$120,MATCH(F74,Precios!$A$5:$A$120,0)),"")+IF(N(INDEX(Recetas!$S$5:$S$84,MATCH($E74,Recetas!$A$5:$A$84,0)))=0,0,INDEX(Recetas!$S$5:$S$84,MATCH($E74,Recetas!$A$5:$A$84,0))*IFERROR(INDEX(Precios!$F$5:$F$120,MATCH(G74,Precios!$A$5:$A$120,0)),"")),"")) | M74: =IF(OR(B74="",E74=""),"",IFERROR(N(INDEX(Recetas!$L$5:$L$84,MATCH($E74,Recetas!$A$5:$A$84,0)))*Parametros!$B$27,"")) | N74: =IF(OR(B74="",E74=""),"",IFERROR(INDEX(Confeccion!$B$5:$B$100,MATCH(INDEX(Recetas!$M$5:$M$84,MATCH($E74,Recetas!$A$5:$A$84,0)),Confeccion!$A$5:$A$100,0)),"")) | O74: =IF(OR(B74="",E74=""),"",IFERROR(N(INDEX(Recetas!$O$5:$O$84,MATCH($E74,Recetas!$A$5:$A$84,0)))*INDEX(Precios!$D$5:$D$120,MATCH(INDEX(Recetas!$N$5:$N$84,MATCH($E74,Recetas!$A$5:$A$84,0)),Precios!$A$5:$A$120,0)),0)) | P74: =IF(OR(B74="",E74=""),"",IF(AND(IFERROR(INDEX(Recetas!$T$5:$T$84,MATCH($E74,Recetas!$A$5:$A$84,0))="Lista",FALSE()),ISNUMBER(L74),ISNUMBER(M74),ISNUMBER(N74),N(N74)>0),L74+M74+N74+N(O74)+N(H74),"")) | Q74: =IF(AND(ISNUMBER(P74),ISNUMBER(I74)),I74*Parametros!$B$12,"") | R74: =IF(AND(ISNUMBER(P74),ISNUMBER(I74)),I74*Parametros!$B$13,"") | S74: =IF(AND(ISNUMBER(P74),ISNUMBER(I74)),I74-P74-Q74-R74,"") | T74: =IF(AND(ISNUMBER(P74),ISNUMBER(I74)),S74/I74,"") | U74: =IF(OR(NOT(ISNUMBER(P74)),Parametros!$B$14>=1),"",P74/(1-Parametros!$B$14)) | V74: =IF(OR(NOT(ISNUMBER(P74)),Parametros!$B$14+Parametros!$B$18>=1),"",P74/(1-Parametros!$B$14-Parametros!$B$18)) | W74: =IF(B74="","",IF(E74="","SIN RECETA",IF(NOT(ISNUMBER(P74)),"FALTAN DATOS",IF(NOT(ISNUMBER(I74)),"FALTA PRECIO",IF(S74<0,"PIERDE",IF(T74<Parametros!$B$18,"BAJO META","OK")))))) -> SIN RECETA | X74: =IF(B74="","",IF(E74="","Elegir receta (molde). ",IF(ISNA(MATCH(E74,Recetas!$A$5:$A$84,0)),"La receta no existe. ",IF(IFERROR(INDEX(Recetas!$T$5:$T$84,MATCH($E74,Recetas!$A$5:$A$84,0))="Lista",FALSE()),"","Receta "&E74&": "&INDEX(Recetas!$T$5:$T$84,MATCH($E74,Recetas!$A$5:$A$84,0)))))&IF(F74="","Elegir tela. ",IF(IFERROR(INDEX(Precios!$F$5:$F$120,MATCH(F74,Precios!$A$5:$A$120,0)),"")="","Tela sin $/metro (falta rendimiento o precio). ",""))&IF(AND(E74<>"",N(IFERROR(INDEX(Recetas!$S$5:$S$84,MATCH($E74,Recetas!$A$5:$A$84,0)),0))>0,G74=""),"Elegir tela 2. ","")&IF(NOT(ISNUMBER(I74)),"Precio de venta.","")) -> Elegir receta (molde). Elegir tela. | Y74: =IF(AND(ISNUMBER(P74),ISNUMBER(I74),ISNUMBER(D74)),P74*D74,0) -> 0 | Z74: =IF(AND(ISNUMBER(P74),ISNUMBER(I74),ISNUMBER(D74)),I74*D74,0) -> 0 | AA74: =IF(AND(ISNUMBER(P74),ISNUMBER(I74),ISNUMBER(D74)),D74,0) -> 0
A75: VOLMASC-CSUBPRO-V-MC | B75: Camiseta Voley masc Pro Playmaker, V m/c | C75: Juego | D75: 1 | I75: 19244 | J75: Por confirmar | K75: Sin receta: elige el molde que usa (o crea su receta en "Recetas") y la tela. | L75: =IF(OR(B75="",E75=""),"",IFERROR(INDEX(Recetas!$R$5:$R$84,MATCH($E75,Recetas!$A$5:$A$84,0))*IFERROR(INDEX(Precios!$F$5:$F$120,MATCH(F75,Precios!$A$5:$A$120,0)),"")+IF(N(INDEX(Recetas!$S$5:$S$84,MATCH($E75,Recetas!$A$5:$A$84,0)))=0,0,INDEX(Recetas!$S$5:$S$84,MATCH($E75,Recetas!$A$5:$A$84,0))*IFERROR(INDEX(Precios!$F$5:$F$120,MATCH(G75,Precios!$A$5:$A$120,0)),"")),"")) | M75: =IF(OR(B75="",E75=""),"",IFERROR(N(INDEX(Recetas!$L$5:$L$84,MATCH($E75,Recetas!$A$5:$A$84,0)))*Parametros!$B$27,"")) | N75: =IF(OR(B75="",E75=""),"",IFERROR(INDEX(Confeccion!$B$5:$B$100,MATCH(INDEX(Recetas!$M$5:$M$84,MATCH($E75,Recetas!$A$5:$A$84,0)),Confeccion!$A$5:$A$100,0)),"")) | O75: =IF(OR(B75="",E75=""),"",IFERROR(N(INDEX(Recetas!$O$5:$O$84,MATCH($E75,Recetas!$A$5:$A$84,0)))*INDEX(Precios!$D$5:$D$120,MATCH(INDEX(Recetas!$N$5:$N$84,MATCH($E75,Recetas!$A$5:$A$84,0)),Precios!$A$5:$A$120,0)),0)) | P75: =IF(OR(B75="",E75=""),"",IF(AND(IFERROR(INDEX(Recetas!$T$5:$T$84,MATCH($E75,Recetas!$A$5:$A$84,0))="Lista",FALSE()),ISNUMBER(L75),ISNUMBER(M75),ISNUMBER(N75),N(N75)>0),L75+M75+N75+N(O75)+N(H75),"")) | Q75: =IF(AND(ISNUMBER(P75),ISNUMBER(I75)),I75*Parametros!$B$12,"") | R75: =IF(AND(ISNUMBER(P75),ISNUMBER(I75)),I75*Parametros!$B$13,"") | S75: =IF(AND(ISNUMBER(P75),ISNUMBER(I75)),I75-P75-Q75-R75,"") | T75: =IF(AND(ISNUMBER(P75),ISNUMBER(I75)),S75/I75,"") | U75: =IF(OR(NOT(ISNUMBER(P75)),Parametros!$B$14>=1),"",P75/(1-Parametros!$B$14)) | V75: =IF(OR(NOT(ISNUMBER(P75)),Parametros!$B$14+Parametros!$B$18>=1),"",P75/(1-Parametros!$B$14-Parametros!$B$18)) | W75: =IF(B75="","",IF(E75="","SIN RECETA",IF(NOT(ISNUMBER(P75)),"FALTAN DATOS",IF(NOT(ISNUMBER(I75)),"FALTA PRECIO",IF(S75<0,"PIERDE",IF(T75<Parametros!$B$18,"BAJO META","OK")))))) -> SIN RECETA | X75: =IF(B75="","",IF(E75="","Elegir receta (molde). ",IF(ISNA(MATCH(E75,Recetas!$A$5:$A$84,0)),"La receta no existe. ",IF(IFERROR(INDEX(Recetas!$T$5:$T$84,MATCH($E75,Recetas!$A$5:$A$84,0))="Lista",FALSE()),"","Receta "&E75&": "&INDEX(Recetas!$T$5:$T$84,MATCH($E75,Recetas!$A$5:$A$84,0)))))&IF(F75="","Elegir tela. ",IF(IFERROR(INDEX(Precios!$F$5:$F$120,MATCH(F75,Precios!$A$5:$A$120,0)),"")="","Tela sin $/metro (falta rendimiento o precio). ",""))&IF(AND(E75<>"",N(IFERROR(INDEX(Recetas!$S$5:$S$84,MATCH($E75,Recetas!$A$5:$A$84,0)),0))>0,G75=""),"Elegir tela 2. ","")&IF(NOT(ISNUMBER(I75)),"Precio de venta.","")) -> Elegir receta (molde). Elegir tela. | Y75: =IF(AND(ISNUMBER(P75),ISNUMBER(I75),ISNUMBER(D75)),P75*D75,0) -> 0 | Z75: =IF(AND(ISNUMBER(P75),ISNUMBER(I75),ISNUMBER(D75)),I75*D75,0) -> 0 | AA75: =IF(AND(ISNUMBER(P75),ISNUMBER(I75),ISNUMBER(D75)),D75,0) -> 0
A76: RUG-CSUB-POL | B76: Camiseta Rugby Playmaker, Polo | C76: Juego | D76: 1 | I76: 20084 | J76: Por confirmar | K76: Sin receta: elige el molde que usa (o crea su receta en "Recetas") y la tela. | L76: =IF(OR(B76="",E76=""),"",IFERROR(INDEX(Recetas!$R$5:$R$84,MATCH($E76,Recetas!$A$5:$A$84,0))*IFERROR(INDEX(Precios!$F$5:$F$120,MATCH(F76,Precios!$A$5:$A$120,0)),"")+IF(N(INDEX(Recetas!$S$5:$S$84,MATCH($E76,Recetas!$A$5:$A$84,0)))=0,0,INDEX(Recetas!$S$5:$S$84,MATCH($E76,Recetas!$A$5:$A$84,0))*IFERROR(INDEX(Precios!$F$5:$F$120,MATCH(G76,Precios!$A$5:$A$120,0)),"")),"")) | M76: =IF(OR(B76="",E76=""),"",IFERROR(N(INDEX(Recetas!$L$5:$L$84,MATCH($E76,Recetas!$A$5:$A$84,0)))*Parametros!$B$27,"")) | N76: =IF(OR(B76="",E76=""),"",IFERROR(INDEX(Confeccion!$B$5:$B$100,MATCH(INDEX(Recetas!$M$5:$M$84,MATCH($E76,Recetas!$A$5:$A$84,0)),Confeccion!$A$5:$A$100,0)),"")) | O76: =IF(OR(B76="",E76=""),"",IFERROR(N(INDEX(Recetas!$O$5:$O$84,MATCH($E76,Recetas!$A$5:$A$84,0)))*INDEX(Precios!$D$5:$D$120,MATCH(INDEX(Recetas!$N$5:$N$84,MATCH($E76,Recetas!$A$5:$A$84,0)),Precios!$A$5:$A$120,0)),0)) | P76: =IF(OR(B76="",E76=""),"",IF(AND(IFERROR(INDEX(Recetas!$T$5:$T$84,MATCH($E76,Recetas!$A$5:$A$84,0))="Lista",FALSE()),ISNUMBER(L76),ISNUMBER(M76),ISNUMBER(N76),N(N76)>0),L76+M76+N76+N(O76)+N(H76),"")) | Q76: =IF(AND(ISNUMBER(P76),ISNUMBER(I76)),I76*Parametros!$B$12,"") | R76: =IF(AND(ISNUMBER(P76),ISNUMBER(I76)),I76*Parametros!$B$13,"") | S76: =IF(AND(ISNUMBER(P76),ISNUMBER(I76)),I76-P76-Q76-R76,"") | T76: =IF(AND(ISNUMBER(P76),ISNUMBER(I76)),S76/I76,"") | U76: =IF(OR(NOT(ISNUMBER(P76)),Parametros!$B$14>=1),"",P76/(1-Parametros!$B$14)) | V76: =IF(OR(NOT(ISNUMBER(P76)),Parametros!$B$14+Parametros!$B$18>=1),"",P76/(1-Parametros!$B$14-Parametros!$B$18)) | W76: =IF(B76="","",IF(E76="","SIN RECETA",IF(NOT(ISNUMBER(P76)),"FALTAN DATOS",IF(NOT(ISNUMBER(I76)),"FALTA PRECIO",IF(S76<0,"PIERDE",IF(T76<Parametros!$B$18,"BAJO META","OK")))))) -> SIN RECETA | X76: =IF(B76="","",IF(E76="","Elegir receta (molde). ",IF(ISNA(MATCH(E76,Recetas!$A$5:$A$84,0)),"La receta no existe. ",IF(IFERROR(INDEX(Recetas!$T$5:$T$84,MATCH($E76,Recetas!$A$5:$A$84,0))="Lista",FALSE()),"","Receta "&E76&": "&INDEX(Recetas!$T$5:$T$84,MATCH($E76,Recetas!$A$5:$A$84,0)))))&IF(F76="","Elegir tela. ",IF(IFERROR(INDEX(Precios!$F$5:$F$120,MATCH(F76,Precios!$A$5:$A$120,0)),"")="","Tela sin $/metro (falta rendimiento o precio). ",""))&IF(AND(E76<>"",N(IFERROR(INDEX(Recetas!$S$5:$S$84,MATCH($E76,Recetas!$A$5:$A$84,0)),0))>0,G76=""),"Elegir tela 2. ","")&IF(NOT(ISNUMBER(I76)),"Precio de venta.","")) -> Elegir receta (molde). Elegir tela. | Y76: =IF(AND(ISNUMBER(P76),ISNUMBER(I76),ISNUMBER(D76)),P76*D76,0) -> 0 | Z76: =IF(AND(ISNUMBER(P76),ISNUMBER(I76),ISNUMBER(D76)),I76*D76,0) -> 0 | AA76: =IF(AND(ISNUMBER(P76),ISNUMBER(I76),ISNUMBER(D76)),D76,0) -> 0
A77: LZO-2 | B77: Lienzo 1.5x2 | C77: Juego | D77: 1 | I77: 21765 | J77: Por confirmar | K77: Sin receta: elige el molde que usa (o crea su receta en "Recetas") y la tela. | L77: =IF(OR(B77="",E77=""),"",IFERROR(INDEX(Recetas!$R$5:$R$84,MATCH($E77,Recetas!$A$5:$A$84,0))*IFERROR(INDEX(Precios!$F$5:$F$120,MATCH(F77,Precios!$A$5:$A$120,0)),"")+IF(N(INDEX(Recetas!$S$5:$S$84,MATCH($E77,Recetas!$A$5:$A$84,0)))=0,0,INDEX(Recetas!$S$5:$S$84,MATCH($E77,Recetas!$A$5:$A$84,0))*IFERROR(INDEX(Precios!$F$5:$F$120,MATCH(G77,Precios!$A$5:$A$120,0)),"")),"")) | M77: =IF(OR(B77="",E77=""),"",IFERROR(N(INDEX(Recetas!$L$5:$L$84,MATCH($E77,Recetas!$A$5:$A$84,0)))*Parametros!$B$27,"")) | N77: =IF(OR(B77="",E77=""),"",IFERROR(INDEX(Confeccion!$B$5:$B$100,MATCH(INDEX(Recetas!$M$5:$M$84,MATCH($E77,Recetas!$A$5:$A$84,0)),Confeccion!$A$5:$A$100,0)),"")) | O77: =IF(OR(B77="",E77=""),"",IFERROR(N(INDEX(Recetas!$O$5:$O$84,MATCH($E77,Recetas!$A$5:$A$84,0)))*INDEX(Precios!$D$5:$D$120,MATCH(INDEX(Recetas!$N$5:$N$84,MATCH($E77,Recetas!$A$5:$A$84,0)),Precios!$A$5:$A$120,0)),0)) | P77: =IF(OR(B77="",E77=""),"",IF(AND(IFERROR(INDEX(Recetas!$T$5:$T$84,MATCH($E77,Recetas!$A$5:$A$84,0))="Lista",FALSE()),ISNUMBER(L77),ISNUMBER(M77),ISNUMBER(N77),N(N77)>0),L77+M77+N77+N(O77)+N(H77),"")) | Q77: =IF(AND(ISNUMBER(P77),ISNUMBER(I77)),I77*Parametros!$B$12,"") | R77: =IF(AND(ISNUMBER(P77),ISNUMBER(I77)),I77*Parametros!$B$13,"") | S77: =IF(AND(ISNUMBER(P77),ISNUMBER(I77)),I77-P77-Q77-R77,"") | T77: =IF(AND(ISNUMBER(P77),ISNUMBER(I77)),S77/I77,"") | U77: =IF(OR(NOT(ISNUMBER(P77)),Parametros!$B$14>=1),"",P77/(1-Parametros!$B$14)) | V77: =IF(OR(NOT(ISNUMBER(P77)),Parametros!$B$14+Parametros!$B$18>=1),"",P77/(1-Parametros!$B$14-Parametros!$B$18)) | W77: =IF(B77="","",IF(E77="","SIN RECETA",IF(NOT(ISNUMBER(P77)),"FALTAN DATOS",IF(NOT(ISNUMBER(I77)),"FALTA PRECIO",IF(S77<0,"PIERDE",IF(T77<Parametros!$B$18,"BAJO META","OK")))))) -> SIN RECETA | X77: =IF(B77="","",IF(E77="","Elegir receta (molde). ",IF(ISNA(MATCH(E77,Recetas!$A$5:$A$84,0)),"La receta no existe. ",IF(IFERROR(INDEX(Recetas!$T$5:$T$84,MATCH($E77,Recetas!$A$5:$A$84,0))="Lista",FALSE()),"","Receta "&E77&": "&INDEX(Recetas!$T$5:$T$84,MATCH($E77,Recetas!$A$5:$A$84,0)))))&IF(F77="","Elegir tela. ",IF(IFERROR(INDEX(Precios!$F$5:$F$120,MATCH(F77,Precios!$A$5:$A$120,0)),"")="","Tela sin $/metro (falta rendimiento o precio). ",""))&IF(AND(E77<>"",N(IFERROR(INDEX(Recetas!$S$5:$S$84,MATCH($E77,Recetas!$A$5:$A$84,0)),0))>0,G77=""),"Elegir tela 2. ","")&IF(NOT(ISNUMBER(I77)),"Precio de venta.","")) -> Elegir receta (molde). Elegir tela. | Y77: =IF(AND(ISNUMBER(P77),ISNUMBER(I77),ISNUMBER(D77)),P77*D77,0) -> 0 | Z77: =IF(AND(ISNUMBER(P77),ISNUMBER(I77),ISNUMBER(D77)),I77*D77,0) -> 0 | AA77: =IF(AND(ISNUMBER(P77),ISNUMBER(I77),ISNUMBER(D77)),D77,0) -> 0
A78: FUTJINSUB | B78: Jineta de Capitán Subl | C78: Juego | D78: 1 | I78: 11681 | J78: Por confirmar | K78: Sin receta: elige el molde que usa (o crea su receta en "Recetas") y la tela. | L78: =IF(OR(B78="",E78=""),"",IFERROR(INDEX(Recetas!$R$5:$R$84,MATCH($E78,Recetas!$A$5:$A$84,0))*IFERROR(INDEX(Precios!$F$5:$F$120,MATCH(F78,Precios!$A$5:$A$120,0)),"")+IF(N(INDEX(Recetas!$S$5:$S$84,MATCH($E78,Recetas!$A$5:$A$84,0)))=0,0,INDEX(Recetas!$S$5:$S$84,MATCH($E78,Recetas!$A$5:$A$84,0))*IFERROR(INDEX(Precios!$F$5:$F$120,MATCH(G78,Precios!$A$5:$A$120,0)),"")),"")) | M78: =IF(OR(B78="",E78=""),"",IFERROR(N(INDEX(Recetas!$L$5:$L$84,MATCH($E78,Recetas!$A$5:$A$84,0)))*Parametros!$B$27,"")) | N78: =IF(OR(B78="",E78=""),"",IFERROR(INDEX(Confeccion!$B$5:$B$100,MATCH(INDEX(Recetas!$M$5:$M$84,MATCH($E78,Recetas!$A$5:$A$84,0)),Confeccion!$A$5:$A$100,0)),"")) | O78: =IF(OR(B78="",E78=""),"",IFERROR(N(INDEX(Recetas!$O$5:$O$84,MATCH($E78,Recetas!$A$5:$A$84,0)))*INDEX(Precios!$D$5:$D$120,MATCH(INDEX(Recetas!$N$5:$N$84,MATCH($E78,Recetas!$A$5:$A$84,0)),Precios!$A$5:$A$120,0)),0)) | P78: =IF(OR(B78="",E78=""),"",IF(AND(IFERROR(INDEX(Recetas!$T$5:$T$84,MATCH($E78,Recetas!$A$5:$A$84,0))="Lista",FALSE()),ISNUMBER(L78),ISNUMBER(M78),ISNUMBER(N78),N(N78)>0),L78+M78+N78+N(O78)+N(H78),"")) | Q78: =IF(AND(ISNUMBER(P78),ISNUMBER(I78)),I78*Parametros!$B$12,"") | R78: =IF(AND(ISNUMBER(P78),ISNUMBER(I78)),I78*Parametros!$B$13,"") | S78: =IF(AND(ISNUMBER(P78),ISNUMBER(I78)),I78-P78-Q78-R78,"") | T78: =IF(AND(ISNUMBER(P78),ISNUMBER(I78)),S78/I78,"") | U78: =IF(OR(NOT(ISNUMBER(P78)),Parametros!$B$14>=1),"",P78/(1-Parametros!$B$14)) | V78: =IF(OR(NOT(ISNUMBER(P78)),Parametros!$B$14+Parametros!$B$18>=1),"",P78/(1-Parametros!$B$14-Parametros!$B$18)) | W78: =IF(B78="","",IF(E78="","SIN RECETA",IF(NOT(ISNUMBER(P78)),"FALTAN DATOS",IF(NOT(ISNUMBER(I78)),"FALTA PRECIO",IF(S78<0,"PIERDE",IF(T78<Parametros!$B$18,"BAJO META","OK")))))) -> SIN RECETA | X78: =IF(B78="","",IF(E78="","Elegir receta (molde). ",IF(ISNA(MATCH(E78,Recetas!$A$5:$A$84,0)),"La receta no existe. ",IF(IFERROR(INDEX(Recetas!$T$5:$T$84,MATCH($E78,Recetas!$A$5:$A$84,0))="Lista",FALSE()),"","Receta "&E78&": "&INDEX(Recetas!$T$5:$T$84,MATCH($E78,Recetas!$A$5:$A$84,0)))))&IF(F78="","Elegir tela. ",IF(IFERROR(INDEX(Precios!$F$5:$F$120,MATCH(F78,Precios!$A$5:$A$120,0)),"")="","Tela sin $/metro (falta rendimiento o precio). ",""))&IF(AND(E78<>"",N(IFERROR(INDEX(Recetas!$S$5:$S$84,MATCH($E78,Recetas!$A$5:$A$84,0)),0))>0,G78=""),"Elegir tela 2. ","")&IF(NOT(ISNUMBER(I78)),"Precio de venta.","")) -> Elegir receta (molde). Elegir tela. | Y78: =IF(AND(ISNUMBER(P78),ISNUMBER(I78),ISNUMBER(D78)),P78*D78,0) -> 0 | Z78: =IF(AND(ISNUMBER(P78),ISNUMBER(I78),ISNUMBER(D78)),I78*D78,0) -> 0 | AA78: =IF(AND(ISNUMBER(P78),ISNUMBER(I78),ISNUMBER(D78)),D78,0) -> 0
A79: SAL-POL-ALG-LIS | B79: POLERÓN ALGODÓN CON CAPUCHA PMK | C79: Salida | D79: 1 | I79: 21765 | J79: Por confirmar | K79: Sin receta: elige el molde que usa (o crea su receta en "Recetas") y la tela. | L79: =IF(OR(B79="",E79=""),"",IFERROR(INDEX(Recetas!$R$5:$R$84,MATCH($E79,Recetas!$A$5:$A$84,0))*IFERROR(INDEX(Precios!$F$5:$F$120,MATCH(F79,Precios!$A$5:$A$120,0)),"")+IF(N(INDEX(Recetas!$S$5:$S$84,MATCH($E79,Recetas!$A$5:$A$84,0)))=0,0,INDEX(Recetas!$S$5:$S$84,MATCH($E79,Recetas!$A$5:$A$84,0))*IFERROR(INDEX(Precios!$F$5:$F$120,MATCH(G79,Precios!$A$5:$A$120,0)),"")),"")) | M79: =IF(OR(B79="",E79=""),"",IFERROR(N(INDEX(Recetas!$L$5:$L$84,MATCH($E79,Recetas!$A$5:$A$84,0)))*Parametros!$B$27,"")) | N79: =IF(OR(B79="",E79=""),"",IFERROR(INDEX(Confeccion!$B$5:$B$100,MATCH(INDEX(Recetas!$M$5:$M$84,MATCH($E79,Recetas!$A$5:$A$84,0)),Confeccion!$A$5:$A$100,0)),"")) | O79: =IF(OR(B79="",E79=""),"",IFERROR(N(INDEX(Recetas!$O$5:$O$84,MATCH($E79,Recetas!$A$5:$A$84,0)))*INDEX(Precios!$D$5:$D$120,MATCH(INDEX(Recetas!$N$5:$N$84,MATCH($E79,Recetas!$A$5:$A$84,0)),Precios!$A$5:$A$120,0)),0)) | P79: =IF(OR(B79="",E79=""),"",IF(AND(IFERROR(INDEX(Recetas!$T$5:$T$84,MATCH($E79,Recetas!$A$5:$A$84,0))="Lista",FALSE()),ISNUMBER(L79),ISNUMBER(M79),ISNUMBER(N79),N(N79)>0),L79+M79+N79+N(O79)+N(H79),"")) | Q79: =IF(AND(ISNUMBER(P79),ISNUMBER(I79)),I79*Parametros!$B$12,"") | R79: =IF(AND(ISNUMBER(P79),ISNUMBER(I79)),I79*Parametros!$B$13,"") | S79: =IF(AND(ISNUMBER(P79),ISNUMBER(I79)),I79-P79-Q79-R79,"") | T79: =IF(AND(ISNUMBER(P79),ISNUMBER(I79)),S79/I79,"") | U79: =IF(OR(NOT(ISNUMBER(P79)),Parametros!$B$14>=1),"",P79/(1-Parametros!$B$14)) | V79: =IF(OR(NOT(ISNUMBER(P79)),Parametros!$B$14+Parametros!$B$18>=1),"",P79/(1-Parametros!$B$14-Parametros!$B$18)) | W79: =IF(B79="","",IF(E79="","SIN RECETA",IF(NOT(ISNUMBER(P79)),"FALTAN DATOS",IF(NOT(ISNUMBER(I79)),"FALTA PRECIO",IF(S79<0,"PIERDE",IF(T79<Parametros!$B$18,"BAJO META","OK")))))) -> SIN RECETA | X79: =IF(B79="","",IF(E79="","Elegir receta (molde). ",IF(ISNA(MATCH(E79,Recetas!$A$5:$A$84,0)),"La receta no existe. ",IF(IFERROR(INDEX(Recetas!$T$5:$T$84,MATCH($E79,Recetas!$A$5:$A$84,0))="Lista",FALSE()),"","Receta "&E79&": "&INDEX(Recetas!$T$5:$T$84,MATCH($E79,Recetas!$A$5:$A$84,0)))))&IF(F79="","Elegir tela. ",IF(IFERROR(INDEX(Precios!$F$5:$F$120,MATCH(F79,Precios!$A$5:$A$120,0)),"")="","Tela sin $/metro (falta rendimiento o precio). ",""))&IF(AND(E79<>"",N(IFERROR(INDEX(Recetas!$S$5:$S$84,MATCH($E79,Recetas!$A$5:$A$84,0)),0))>0,G79=""),"Elegir tela 2. ","")&IF(NOT(ISNUMBER(I79)),"Precio de venta.","")) -> Elegir receta (molde). Elegir tela. | Y79: =IF(AND(ISNUMBER(P79),ISNUMBER(I79),ISNUMBER(D79)),P79*D79,0) -> 0 | Z79: =IF(AND(ISNUMBER(P79),ISNUMBER(I79),ISNUMBER(D79)),I79*D79,0) -> 0 | AA79: =IF(AND(ISNUMBER(P79),ISNUMBER(I79),ISNUMBER(D79)),D79,0) -> 0
L80: =IF(OR(B80="",E80=""),"",IFERROR(INDEX(Recetas!$R$5:$R$84,MATCH($E80,Recetas!$A$5:$A$84,0))*IFERROR(INDEX(Precios!$F$5:$F$120,MATCH(F80,Precios!$A$5:$A$120,0)),"")+IF(N(INDEX(Recetas!$S$5:$S$84,MATCH($E80,Recetas!$A$5:$A$84,0)))=0,0,INDEX(Recetas!$S$5:$S$84,MATCH($E80,Recetas!$A$5:$A$84,0))*IFERROR(INDEX(Precios!$F$5:$F$120,MATCH(G80,Precios!$A$5:$A$120,0)),"")),"")) | M80: =IF(OR(B80="",E80=""),"",IFERROR(N(INDEX(Recetas!$L$5:$L$84,MATCH($E80,Recetas!$A$5:$A$84,0)))*Parametros!$B$27,"")) | N80: =IF(OR(B80="",E80=""),"",IFERROR(INDEX(Confeccion!$B$5:$B$100,MATCH(INDEX(Recetas!$M$5:$M$84,MATCH($E80,Recetas!$A$5:$A$84,0)),Confeccion!$A$5:$A$100,0)),"")) | O80: =IF(OR(B80="",E80=""),"",IFERROR(N(INDEX(Recetas!$O$5:$O$84,MATCH($E80,Recetas!$A$5:$A$84,0)))*INDEX(Precios!$D$5:$D$120,MATCH(INDEX(Recetas!$N$5:$N$84,MATCH($E80,Recetas!$A$5:$A$84,0)),Precios!$A$5:$A$120,0)),0)) | P80: =IF(OR(B80="",E80=""),"",IF(AND(IFERROR(INDEX(Recetas!$T$5:$T$84,MATCH($E80,Recetas!$A$5:$A$84,0))="Lista",FALSE()),ISNUMBER(L80),ISNUMBER(M80),ISNUMBER(N80),N(N80)>0),L80+M80+N80+N(O80)+N(H80),"")) | Q80: =IF(AND(ISNUMBER(P80),ISNUMBER(I80)),I80*Parametros!$B$12,"") | R80: =IF(AND(ISNUMBER(P80),ISNUMBER(I80)),I80*Parametros!$B$13,"") | S80: =IF(AND(ISNUMBER(P80),ISNUMBER(I80)),I80-P80-Q80-R80,"") | T80: =IF(AND(ISNUMBER(P80),ISNUMBER(I80)),S80/I80,"") | U80: =IF(OR(NOT(ISNUMBER(P80)),Parametros!$B$14>=1),"",P80/(1-Parametros!$B$14)) | V80: =IF(OR(NOT(ISNUMBER(P80)),Parametros!$B$14+Parametros!$B$18>=1),"",P80/(1-Parametros!$B$14-Parametros!$B$18)) | W80: =IF(B80="","",IF(E80="","SIN RECETA",IF(NOT(ISNUMBER(P80)),"FALTAN DATOS",IF(NOT(ISNUMBER(I80)),"FALTA PRECIO",IF(S80<0,"PIERDE",IF(T80<Parametros!$B$18,"BAJO META","OK")))))) | X80: =IF(B80="","",IF(E80="","Elegir receta (molde). ",IF(ISNA(MATCH(E80,Recetas!$A$5:$A$84,0)),"La receta no existe. ",IF(IFERROR(INDEX(Recetas!$T$5:$T$84,MATCH($E80,Recetas!$A$5:$A$84,0))="Lista",FALSE()),"","Receta "&E80&": "&INDEX(Recetas!$T$5:$T$84,MATCH($E80,Recetas!$A$5:$A$84,0)))))&IF(F80="","Elegir tela. ",IF(IFERROR(INDEX(Precios!$F$5:$F$120,MATCH(F80,Precios!$A$5:$A$120,0)),"")="","Tela sin $/metro (falta rendimiento o precio). ",""))&IF(AND(E80<>"",N(IFERROR(INDEX(Recetas!$S$5:$S$84,MATCH($E80,Recetas!$A$5:$A$84,0)),0))>0,G80=""),"Elegir tela 2. ","")&IF(NOT(ISNUMBER(I80)),"Precio de venta.","")) | Y80: =IF(AND(ISNUMBER(P80),ISNUMBER(I80),ISNUMBER(D80)),P80*D80,0) -> 0 | Z80: =IF(AND(ISNUMBER(P80),ISNUMBER(I80),ISNUMBER(D80)),I80*D80,0) -> 0 | AA80: =IF(AND(ISNUMBER(P80),ISNUMBER(I80),ISNUMBER(D80)),D80,0) -> 0
