Workbook

Sheet LEEME
A1: RECETAS DE COSTO — PLAYMAKER
A2: Versión 1 · armada desde el Sistema de Costeo v2. Todo dato figura "Por confirmar" hasta que lo valides.
A4: QUÉ HACE
B5: Por cada producto calcula: costo de producción + gastos de fábrica + gastos comerciales = ganancia real, y el precio mínimo para no perder.
B6: Fórmula del precio mínimo: costo de producción ÷ (1 − recargo − ganancia deseada).
A7: COLORES
B8: AMARILLO con letra azul = lo escribes tú. GRIS = se calcula solo, no tocar. VERDE = viene de otra hoja.
A9: HOJAS
B10: Recetas: una fila por producto. Aquí está el resultado (ganancia, precio mínimo, semáforo).
B11: Parametros: recargo %, meta de ganancia, tinta/papel y costo de ploteo, sublimación, corte y estampado.
B12: Gastos_Fijos: gastos y ventas de los últimos 3 meses. De aquí sale el recargo.
B13: Insumos: precio de cada tela, avío y consumible. Confeccion: lo que se paga al taller por prenda.
B14: Catalogo: los 131 productos vendidos y cuáles ya tienen receta.
A15: PARA AGREGAR UN PRODUCTO (4 pasos)
B16: 1) En Recetas, usa la primera fila vacía y elige el producto del catálogo (columna A).
B17: 2) Elige tela y confección en las listas. Escribe los kg de tela por prenda y los metros de ploteo y sublimación.
B18: 3) Escribe el precio de venta neto. 4) Revisa el semáforo y las alertas de la derecha.
A19: CADA TRIMESTRE (reajuste)
B20: En Gastos_Fijos: reemplaza los nombres de mes y los montos de gastos y ventas de los últimos 3 meses. El recargo se recalcula solo.
B21: Revisa en Insumos y Confeccion si cambiaron precios de tela o valores de taller.
A22: SEMÁFORO
B23: PIERDE = el precio no cubre costo + gastos. BAJO META = gana, pero menos que tu ganancia deseada. OK = cumple la meta.
A24: PENDIENTES IMPORTANTES (afectan los resultados)
B25: ="• Tinta y papel de sublimación: "&IF(Parametros!B17=0,"SIN DATO — los costos están subestimados.","ingresado.")
B26: ="• Datos de precio por confirmar: "&(COUNTIF(Insumos!E6:E200,"Por confirmar")+COUNTIF(Confeccion!D5:D200,"Por confirmar")+COUNTIF(Parametros!J21:J24,"Por confirmar"))&" (insumos, confección y procesos). Cambia el estado a Confirmado al verificar."
B27: ="• Precios de insumos PENDIENTES (sin precio): "&COUNTIF(Insumos!E6:E200,"PENDIENTE")
B28: • Avíos (hilo, etiqueta, cuello, etc.) no estaban en las recetas originales: usa la columna "Otros avíos" para incluirlos.
B29: • Gastos de los 3 meses: el archivo original solo traía un mes, repetido en los tres. Reemplazar con datos reales.
B30: • Consumos de tela: la mayoría viene de 1 o 2 proyectos (estado Observado/Preliminar). Mejoran al sumar más cortes.

Sheet Recetas
A1: RECETAS — costo de producción, gastos y ganancia por prenda
A2: Una fila = un producto. Solo llenas las columnas amarillas (A a L). Todo lo demás se calcula solo.
A3: ="Recargo usado: "&TEXT(Parametros!B15,"0.0%")&" del precio (fábrica "&TEXT(Parametros!B13,"0.0%")&" + comercial "&TEXT(Parametros!B14,"0.0%")&") · Meta de ganancia: "&TEXT(Parametros!B16,"0%")
A4: DATOS DEL PRODUCTO (los llenas tú) | M4: COSTO DE PRODUCCIÓN ($ por prenda) | U4: RESULTADO COMERCIAL
A5: Producto (catálogo) | B5: Variante / segmento | C5: Tela | D5: Consumo tela (kg por prenda) | E5: Metros ploteo | F5: Metros sublimación | G5: Confección (tipo) | H5: Estampado (1 = sí, 0 = no) | I5: Otros avíos ($ por prenda) | J5: Precio venta neto ($) | K5: Estado del dato | L5: Notas | M5: Tela | N5: Ploteo | O5: Sublimación | P5: Tinta y papel | Q5: Corte | R5: Estampado | S5: Confección | T5: COSTO DE PRODUCCIÓN | U5: Gastos de fábrica | V5: Gastos comerciales | W5: GANANCIA ($) | X5: GANANCIA (%) | Y5: Precio de equilibrio | Z5: Precio mínimo con meta | AA5: Semáforo | AB5: Alertas de datos
A6: Camiseta Fútbol Pro Playmaker, m/c | B6: Pro Masculino | C6: MONTESIMONE TRAINING (fut pro) | D6: 0.12 | E6: 1.2 | F6: 1.9 | G6: Camiseta De Futbol | H6: 1 | I6: 0 | J6: 18403 | K6: Observado | L6: Consumo basado en 1 proyecto (20 prendas) | M6: =IF($A6="","",IFERROR(D6*INDEX(Insumos!$D$6:$D$98,MATCH(C6,Insumos!$A$6:$A$98,0)),0)) | N6: =IF($A6="","",E6*Parametros!$H$21) | O6: =IF($A6="","",F6*Parametros!$H$22) | P6: =IF($A6="","",F6*Parametros!$B$17) | Q6: =IF($A6="","",D6*Parametros!$H$23) | R6: =IF($A6="","",H6*Parametros!$H$24) | S6: =IF($A6="","",IFERROR(INDEX(Confeccion!$B$5:$B$80,MATCH(G6,Confeccion!$A$5:$A$80,0)),0)) | T6: =IF($A6="","",SUM(M6:S6)+I6) | U6: =IF($A6="","",IF(J6="","",J6*Parametros!$B$13)) | V6: =IF($A6="","",IF(J6="","",J6*Parametros!$B$14)) | W6: =IF($A6="","",IF(J6="","",J6-T6-U6-V6)) | X6: =IF($A6="","",IF(J6="","",W6/J6)) | Y6: =IF($A6="","",IF(Parametros!$B$15>=1,"",T6/(1-Parametros!$B$15))) | Z6: =IF($A6="","",IF(Parametros!$B$15+Parametros!$B$16>=1,"",T6/(1-Parametros!$B$15-Parametros!$B$16))) | AA6: =IF($A6="","",IF(J6="","Falta precio",IF(W6<0,"PIERDE",IF(X6<Parametros!$B$16,"BAJO META","OK")))) | AB6: =IF($A6="","",IF(OR(C6="",D6=""),"Falta tela o consumo. ","")&IF(AND(C6<>"",M6=0),"Tela sin precio. ","")&IF(S6=0,"Confección sin valor. ","")&IF(J6="","Falta precio de venta. ",""))
A7: Camiseta Fútbol Pro Playmaker, m/c | B7: Pro Femenino | C7: MONTESIMONE TRAINING (fut pro) | D7: 0.1225 | E7: 1.2 | F7: 1.9 | G7: Camiseta De Futbol | H7: 1 | I7: 0 | J7: 18403 | K7: Observado | L7: Consumo basado en 1 proyecto (20 prendas) | M7: =IF($A7="","",IFERROR(D7*INDEX(Insumos!$D$6:$D$98,MATCH(C7,Insumos!$A$6:$A$98,0)),0)) | N7: =IF($A7="","",E7*Parametros!$H$21) | O7: =IF($A7="","",F7*Parametros!$H$22) | P7: =IF($A7="","",F7*Parametros!$B$17) | Q7: =IF($A7="","",D7*Parametros!$H$23) | R7: =IF($A7="","",H7*Parametros!$H$24) | S7: =IF($A7="","",IFERROR(INDEX(Confeccion!$B$5:$B$80,MATCH(G7,Confeccion!$A$5:$A$80,0)),0)) | T7: =IF($A7="","",SUM(M7:S7)+I7) | U7: =IF($A7="","",IF(J7="","",J7*Parametros!$B$13)) | V7: =IF($A7="","",IF(J7="","",J7*Parametros!$B$14)) | W7: =IF($A7="","",IF(J7="","",J7-T7-U7-V7)) | X7: =IF($A7="","",IF(J7="","",W7/J7)) | Y7: =IF($A7="","",IF(Parametros!$B$15>=1,"",T7/(1-Parametros!$B$15))) | Z7: =IF($A7="","",IF(Parametros!$B$15+Parametros!$B$16>=1,"",T7/(1-Parametros!$B$15-Parametros!$B$16))) | AA7: =IF($A7="","",IF(J7="","Falta precio",IF(W7<0,"PIERDE",IF(X7<Parametros!$B$16,"BAJO META","OK")))) | AB7: =IF($A7="","",IF(OR(C7="",D7=""),"Falta tela o consumo. ","")&IF(AND(C7<>"",M7=0),"Tela sin precio. ","")&IF(S7=0,"Confección sin valor. ","")&IF(J7="","Falta precio de venta. ",""))
A8: Camiseta Fútbol Playmaker, m/c | B8: Nacional Infantil | C8: CIRE BLANCO | D8: 0.0375 | E8: 1.2 | F8: 1.2 | G8: Camiseta De Futbol | H8: 1 | I8: 0 | J8: 15994 | K8: Observado | L8: Consumo basado en 1 proyecto (48 prendas) | M8: =IF($A8="","",IFERROR(D8*INDEX(Insumos!$D$6:$D$98,MATCH(C8,Insumos!$A$6:$A$98,0)),0)) | N8: =IF($A8="","",E8*Parametros!$H$21) | O8: =IF($A8="","",F8*Parametros!$H$22) | P8: =IF($A8="","",F8*Parametros!$B$17) | Q8: =IF($A8="","",D8*Parametros!$H$23) | R8: =IF($A8="","",H8*Parametros!$H$24) | S8: =IF($A8="","",IFERROR(INDEX(Confeccion!$B$5:$B$80,MATCH(G8,Confeccion!$A$5:$A$80,0)),0)) | T8: =IF($A8="","",SUM(M8:S8)+I8) | U8: =IF($A8="","",IF(J8="","",J8*Parametros!$B$13)) | V8: =IF($A8="","",IF(J8="","",J8*Parametros!$B$14)) | W8: =IF($A8="","",IF(J8="","",J8-T8-U8-V8)) | X8: =IF($A8="","",IF(J8="","",W8/J8)) | Y8: =IF($A8="","",IF(Parametros!$B$15>=1,"",T8/(1-Parametros!$B$15))) | Z8: =IF($A8="","",IF(Parametros!$B$15+Parametros!$B$16>=1,"",T8/(1-Parametros!$B$15-Parametros!$B$16))) | AA8: =IF($A8="","",IF(J8="","Falta precio",IF(W8<0,"PIERDE",IF(X8<Parametros!$B$16,"BAJO META","OK")))) | AB8: =IF($A8="","",IF(OR(C8="",D8=""),"Falta tela o consumo. ","")&IF(AND(C8<>"",M8=0),"Tela sin precio. ","")&IF(S8=0,"Confección sin valor. ","")&IF(J8="","Falta precio de venta. ",""))
A9: Camiseta Fútbol Playmaker, m/c | B9: Nacional Masculino | C9: CIRE BLANCO | D9: 0.1609375 | E9: 1.2 | F9: 1.2 | G9: Camiseta De Futbol | H9: 1 | I9: 0 | J9: 15994 | K9: Preliminar | L9: Consumo promedio de 2 proyectos (32 prendas) | M9: =IF($A9="","",IFERROR(D9*INDEX(Insumos!$D$6:$D$98,MATCH(C9,Insumos!$A$6:$A$98,0)),0)) | N9: =IF($A9="","",E9*Parametros!$H$21) | O9: =IF($A9="","",F9*Parametros!$H$22) | P9: =IF($A9="","",F9*Parametros!$B$17) | Q9: =IF($A9="","",D9*Parametros!$H$23) | R9: =IF($A9="","",H9*Parametros!$H$24) | S9: =IF($A9="","",IFERROR(INDEX(Confeccion!$B$5:$B$80,MATCH(G9,Confeccion!$A$5:$A$80,0)),0)) | T9: =IF($A9="","",SUM(M9:S9)+I9) | U9: =IF($A9="","",IF(J9="","",J9*Parametros!$B$13)) | V9: =IF($A9="","",IF(J9="","",J9*Parametros!$B$14)) | W9: =IF($A9="","",IF(J9="","",J9-T9-U9-V9)) | X9: =IF($A9="","",IF(J9="","",W9/J9)) | Y9: =IF($A9="","",IF(Parametros!$B$15>=1,"",T9/(1-Parametros!$B$15))) | Z9: =IF($A9="","",IF(Parametros!$B$15+Parametros!$B$16>=1,"",T9/(1-Parametros!$B$15-Parametros!$B$16))) | AA9: =IF($A9="","",IF(J9="","Falta precio",IF(W9<0,"PIERDE",IF(X9<Parametros!$B$16,"BAJO META","OK")))) | AB9: =IF($A9="","",IF(OR(C9="",D9=""),"Falta tela o consumo. ","")&IF(AND(C9<>"",M9=0),"Tela sin precio. ","")&IF(S9=0,"Confección sin valor. ","")&IF(J9="","Falta precio de venta. ",""))
A10: Camiseta Básquet Nacional s/m | B10: Nacional Masculino | C10: QUICKDRY | D10: 0.1779412 | E10: 1.2 | F10: 1.2 | G10: Camiseta De Basket | H10: 1 | I10: 0 | K10: Preliminar | L10: No hay ítem de camiseta de básquet en el catálogo: ingresar precio de venta | M10: =IF($A10="","",IFERROR(D10*INDEX(Insumos!$D$6:$D$98,MATCH(C10,Insumos!$A$6:$A$98,0)),0)) | N10: =IF($A10="","",E10*Parametros!$H$21) | O10: =IF($A10="","",F10*Parametros!$H$22) | P10: =IF($A10="","",F10*Parametros!$B$17) | Q10: =IF($A10="","",D10*Parametros!$H$23) | R10: =IF($A10="","",H10*Parametros!$H$24) | S10: =IF($A10="","",IFERROR(INDEX(Confeccion!$B$5:$B$80,MATCH(G10,Confeccion!$A$5:$A$80,0)),0)) | T10: =IF($A10="","",SUM(M10:S10)+I10) | U10: =IF($A10="","",IF(J10="","",J10*Parametros!$B$13)) | V10: =IF($A10="","",IF(J10="","",J10*Parametros!$B$14)) | W10: =IF($A10="","",IF(J10="","",J10-T10-U10-V10)) | X10: =IF($A10="","",IF(J10="","",W10/J10)) | Y10: =IF($A10="","",IF(Parametros!$B$15>=1,"",T10/(1-Parametros!$B$15))) | Z10: =IF($A10="","",IF(Parametros!$B$15+Parametros!$B$16>=1,"",T10/(1-Parametros!$B$15-Parametros!$B$16))) | AA10: =IF($A10="","",IF(J10="","Falta precio",IF(W10<0,"PIERDE",IF(X10<Parametros!$B$16,"BAJO META","OK")))) | AB10: =IF($A10="","",IF(OR(C10="",D10=""),"Falta tela o consumo. ","")&IF(AND(C10<>"",M10=0),"Tela sin precio. ","")&IF(S10=0,"Confección sin valor. ","")&IF(J10="","Falta precio de venta. ",""))
A11: Camiseta Running Pro m/c | B11: Pro Masculino | C11: 5K NACIONAL (running pro) | D11: 0.082 | E11: 1.2 | F11: 1.2 | G11: Camiseta De Running | H11: 1 | I11: 0 | J11: 19244 | K11: Observado | L11: Consumo basado en 1 proyecto (25 prendas) | M11: =IF($A11="","",IFERROR(D11*INDEX(Insumos!$D$6:$D$98,MATCH(C11,Insumos!$A$6:$A$98,0)),0)) | N11: =IF($A11="","",E11*Parametros!$H$21) | O11: =IF($A11="","",F11*Parametros!$H$22) | P11: =IF($A11="","",F11*Parametros!$B$17) | Q11: =IF($A11="","",D11*Parametros!$H$23) | R11: =IF($A11="","",H11*Parametros!$H$24) | S11: =IF($A11="","",IFERROR(INDEX(Confeccion!$B$5:$B$80,MATCH(G11,Confeccion!$A$5:$A$80,0)),0)) | T11: =IF($A11="","",SUM(M11:S11)+I11) | U11: =IF($A11="","",IF(J11="","",J11*Parametros!$B$13)) | V11: =IF($A11="","",IF(J11="","",J11*Parametros!$B$14)) | W11: =IF($A11="","",IF(J11="","",J11-T11-U11-V11)) | X11: =IF($A11="","",IF(J11="","",W11/J11)) | Y11: =IF($A11="","",IF(Parametros!$B$15>=1,"",T11/(1-Parametros!$B$15))) | Z11: =IF($A11="","",IF(Parametros!$B$15+Parametros!$B$16>=1,"",T11/(1-Parametros!$B$15-Parametros!$B$16))) | AA11: =IF($A11="","",IF(J11="","Falta precio",IF(W11<0,"PIERDE",IF(X11<Parametros!$B$16,"BAJO META","OK")))) | AB11: =IF($A11="","",IF(OR(C11="",D11=""),"Falta tela o consumo. ","")&IF(AND(C11<>"",M11=0),"Tela sin precio. ","")&IF(S11=0,"Confección sin valor. ","")&IF(J11="","Falta precio de venta. ",""))
A12: Short Fútbol Playmaker Liso | B12: Nacional Masculino | C12: CIRE BLANCO | D12: 0.1609375 | E12: 0 | F12: 1.2 | G12: Short De Futbol | H12: 1 | I12: 0 | J12: 8059 | K12: Preliminar | L12: Ploteo en 0 metros viene así del archivo original: confirmar | M12: =IF($A12="","",IFERROR(D12*INDEX(Insumos!$D$6:$D$98,MATCH(C12,Insumos!$A$6:$A$98,0)),0)) | N12: =IF($A12="","",E12*Parametros!$H$21) | O12: =IF($A12="","",F12*Parametros!$H$22) | P12: =IF($A12="","",F12*Parametros!$B$17) | Q12: =IF($A12="","",D12*Parametros!$H$23) | R12: =IF($A12="","",H12*Parametros!$H$24) | S12: =IF($A12="","",IFERROR(INDEX(Confeccion!$B$5:$B$80,MATCH(G12,Confeccion!$A$5:$A$80,0)),0)) | T12: =IF($A12="","",SUM(M12:S12)+I12) | U12: =IF($A12="","",IF(J12="","",J12*Parametros!$B$13)) | V12: =IF($A12="","",IF(J12="","",J12*Parametros!$B$14)) | W12: =IF($A12="","",IF(J12="","",J12-T12-U12-V12)) | X12: =IF($A12="","",IF(J12="","",W12/J12)) | Y12: =IF($A12="","",IF(Parametros!$B$15>=1,"",T12/(1-Parametros!$B$15))) | Z12: =IF($A12="","",IF(Parametros!$B$15+Parametros!$B$16>=1,"",T12/(1-Parametros!$B$15-Parametros!$B$16))) | AA12: =IF($A12="","",IF(J12="","Falta precio",IF(W12<0,"PIERDE",IF(X12<Parametros!$B$16,"BAJO META","OK")))) | AB12: =IF($A12="","",IF(OR(C12="",D12=""),"Falta tela o consumo. ","")&IF(AND(C12<>"",M12=0),"Tela sin precio. ","")&IF(S12=0,"Confección sin valor. ","")&IF(J12="","Falta precio de venta. ",""))
A13: Short Rugby Basic | B13: Nacional Masculino | C13: GABARDINA | D13: 0.1842105 | E13: 0 | F13: 1.2 | G13: Short De Futbol | H13: 1 | I13: 0 | J13: 12507 | K13: Observado | L13: Confirmar: usa confección "Short De Futbol" ($1.700); existe "Short De Rugby" ($2.200). Ploteo en 0 viene del original | M13: =IF($A13="","",IFERROR(D13*INDEX(Insumos!$D$6:$D$98,MATCH(C13,Insumos!$A$6:$A$98,0)),0)) | N13: =IF($A13="","",E13*Parametros!$H$21) | O13: =IF($A13="","",F13*Parametros!$H$22) | P13: =IF($A13="","",F13*Parametros!$B$17) | Q13: =IF($A13="","",D13*Parametros!$H$23) | R13: =IF($A13="","",H13*Parametros!$H$24) | S13: =IF($A13="","",IFERROR(INDEX(Confeccion!$B$5:$B$80,MATCH(G13,Confeccion!$A$5:$A$80,0)),0)) | T13: =IF($A13="","",SUM(M13:S13)+I13) | U13: =IF($A13="","",IF(J13="","",J13*Parametros!$B$13)) | V13: =IF($A13="","",IF(J13="","",J13*Parametros!$B$14)) | W13: =IF($A13="","",IF(J13="","",J13-T13-U13-V13)) | X13: =IF($A13="","",IF(J13="","",W13/J13)) | Y13: =IF($A13="","",IF(Parametros!$B$15>=1,"",T13/(1-Parametros!$B$15))) | Z13: =IF($A13="","",IF(Parametros!$B$15+Parametros!$B$16>=1,"",T13/(1-Parametros!$B$15-Parametros!$B$16))) | AA13: =IF($A13="","",IF(J13="","Falta precio",IF(W13<0,"PIERDE",IF(X13<Parametros!$B$16,"BAJO META","OK")))) | AB13: =IF($A13="","",IF(OR(C13="",D13=""),"Falta tela o consumo. ","")&IF(AND(C13<>"",M13=0),"Tela sin precio. ","")&IF(S13=0,"Confección sin valor. ","")&IF(J13="","Falta precio de venta. ",""))
A14: Calza Vóley Femenino | B14: Nacional Femenino | C14: LYCRA | D14: 0.074 | E14: 0 | F14: 1.2 | G14: Calza | H14: 1 | I14: 0 | K14: Observado | L14: Falta precio de la Lycra y precio de venta; confirmar a qué ítem del catálogo corresponde | M14: =IF($A14="","",IFERROR(D14*INDEX(Insumos!$D$6:$D$98,MATCH(C14,Insumos!$A$6:$A$98,0)),0)) | N14: =IF($A14="","",E14*Parametros!$H$21) | O14: =IF($A14="","",F14*Parametros!$H$22) | P14: =IF($A14="","",F14*Parametros!$B$17) | Q14: =IF($A14="","",D14*Parametros!$H$23) | R14: =IF($A14="","",H14*Parametros!$H$24) | S14: =IF($A14="","",IFERROR(INDEX(Confeccion!$B$5:$B$80,MATCH(G14,Confeccion!$A$5:$A$80,0)),0)) | T14: =IF($A14="","",SUM(M14:S14)+I14) | U14: =IF($A14="","",IF(J14="","",J14*Parametros!$B$13)) | V14: =IF($A14="","",IF(J14="","",J14*Parametros!$B$14)) | W14: =IF($A14="","",IF(J14="","",J14-T14-U14-V14)) | X14: =IF($A14="","",IF(J14="","",W14/J14)) | Y14: =IF($A14="","",IF(Parametros!$B$15>=1,"",T14/(1-Parametros!$B$15))) | Z14: =IF($A14="","",IF(Parametros!$B$15+Parametros!$B$16>=1,"",T14/(1-Parametros!$B$15-Parametros!$B$16))) | AA14: =IF($A14="","",IF(J14="","Falta precio",IF(W14<0,"PIERDE",IF(X14<Parametros!$B$16,"BAJO META","OK")))) | AB14: =IF($A14="","",IF(OR(C14="",D14=""),"Falta tela o consumo. ","")&IF(AND(C14<>"",M14=0),"Tela sin precio. ","")&IF(S14=0,"Confección sin valor. ","")&IF(J14="","Falta precio de venta. ",""))
M15: =IF($A15="","",IFERROR(D15*INDEX(Insumos!$D$6:$D$98,MATCH(C15,Insumos!$A$6:$A$98,0)),0)) | N15: =IF($A15="","",E15*Parametros!$H$21) | O15: =IF($A15="","",F15*Parametros!$H$22) | P15: =IF($A15="","",F15*Parametros!$B$17) | Q15: =IF($A15="","",D15*Parametros!$H$23) | R15: =IF($A15="","",H15*Parametros!$H$24) | S15: =IF($A15="","",IFERROR(INDEX(Confeccion!$B$5:$B$80,MATCH(G15,Confeccion!$A$5:$A$80,0)),0)) | T15: =IF($A15="","",SUM(M15:S15)+I15) | U15: =IF($A15="","",IF(J15="","",J15*Parametros!$B$13)) | V15: =IF($A15="","",IF(J15="","",J15*Parametros!$B$14)) | W15: =IF($A15="","",IF(J15="","",J15-T15-U15-V15)) | X15: =IF($A15="","",IF(J15="","",W15/J15)) | Y15: =IF($A15="","",IF(Parametros!$B$15>=1,"",T15/(1-Parametros!$B$15))) | Z15: =IF($A15="","",IF(Parametros!$B$15+Parametros!$B$16>=1,"",T15/(1-Parametros!$B$15-Parametros!$B$16))) | AA15: =IF($A15="","",IF(J15="","Falta precio",IF(W15<0,"PIERDE",IF(X15<Parametros!$B$16,"BAJO META","OK")))) | AB15: =IF($A15="","",IF(OR(C15="",D15=""),"Falta tela o consumo. ","")&IF(AND(C15<>"",M15=0),"Tela sin precio. ","")&IF(S15=0,"Confección sin valor. ","")&IF(J15="","Falta precio de venta. ",""))
M16: =IF($A16="","",IFERROR(D16*INDEX(Insumos!$D$6:$D$98,MATCH(C16,Insumos!$A$6:$A$98,0)),0)) | N16: =IF($A16="","",E16*Parametros!$H$21) | O16: =IF($A16="","",F16*Parametros!$H$22) | P16: =IF($A16="","",F16*Parametros!$B$17) | Q16: =IF($A16="","",D16*Parametros!$H$23) | R16: =IF($A16="","",H16*Parametros!$H$24) | S16: =IF($A16="","",IFERROR(INDEX(Confeccion!$B$5:$B$80,MATCH(G16,Confeccion!$A$5:$A$80,0)),0)) | T16: =IF($A16="","",SUM(M16:S16)+I16) | U16: =IF($A16="","",IF(J16="","",J16*Parametros!$B$13)) | V16: =IF($A16="","",IF(J16="","",J16*Parametros!$B$14)) | W16: =IF($A16="","",IF(J16="","",J16-T16-U16-V16)) | X16: =IF($A16="","",IF(J16="","",W16/J16)) | Y16: =IF($A16="","",IF(Parametros!$B$15>=1,"",T16/(1-Parametros!$B$15))) | Z16: =IF($A16="","",IF(Parametros!$B$15+Parametros!$B$16>=1,"",T16/(1-Parametros!$B$15-Parametros!$B$16))) | AA16: =IF($A16="","",IF(J16="","Falta precio",IF(W16<0,"PIERDE",IF(X16<Parametros!$B$16,"BAJO META","OK")))) | AB16: =IF($A16="","",IF(OR(C16="",D16=""),"Falta tela o consumo. ","")&IF(AND(C16<>"",M16=0),"Tela sin precio. ","")&IF(S16=0,"Confección sin valor. ","")&IF(J16="","Falta precio de venta. ",""))
M17: =IF($A17="","",IFERROR(D17*INDEX(Insumos!$D$6:$D$98,MATCH(C17,Insumos!$A$6:$A$98,0)),0)) | N17: =IF($A17="","",E17*Parametros!$H$21) | O17: =IF($A17="","",F17*Parametros!$H$22) | P17: =IF($A17="","",F17*Parametros!$B$17) | Q17: =IF($A17="","",D17*Parametros!$H$23) | R17: =IF($A17="","",H17*Parametros!$H$24) | S17: =IF($A17="","",IFERROR(INDEX(Confeccion!$B$5:$B$80,MATCH(G17,Confeccion!$A$5:$A$80,0)),0)) | T17: =IF($A17="","",SUM(M17:S17)+I17) | U17: =IF($A17="","",IF(J17="","",J17*Parametros!$B$13)) | V17: =IF($A17="","",IF(J17="","",J17*Parametros!$B$14)) | W17: =IF($A17="","",IF(J17="","",J17-T17-U17-V17)) | X17: =IF($A17="","",IF(J17="","",W17/J17)) | Y17: =IF($A17="","",IF(Parametros!$B$15>=1,"",T17/(1-Parametros!$B$15))) | Z17: =IF($A17="","",IF(Parametros!$B$15+Parametros!$B$16>=1,"",T17/(1-Parametros!$B$15-Parametros!$B$16))) | AA17: =IF($A17="","",IF(J17="","Falta precio",IF(W17<0,"PIERDE",IF(X17<Parametros!$B$16,"BAJO META","OK")))) | AB17: =IF($A17="","",IF(OR(C17="",D17=""),"Falta tela o consumo. ","")&IF(AND(C17<>"",M17=0),"Tela sin precio. ","")&IF(S17=0,"Confección sin valor. ","")&IF(J17="","Falta precio de venta. ",""))
M18: =IF($A18="","",IFERROR(D18*INDEX(Insumos!$D$6:$D$98,MATCH(C18,Insumos!$A$6:$A$98,0)),0)) | N18: =IF($A18="","",E18*Parametros!$H$21) | O18: =IF($A18="","",F18*Parametros!$H$22) | P18: =IF($A18="","",F18*Parametros!$B$17) | Q18: =IF($A18="","",D18*Parametros!$H$23) | R18: =IF($A18="","",H18*Parametros!$H$24) | S18: =IF($A18="","",IFERROR(INDEX(Confeccion!$B$5:$B$80,MATCH(G18,Confeccion!$A$5:$A$80,0)),0)) | T18: =IF($A18="","",SUM(M18:S18)+I18) | U18: =IF($A18="","",IF(J18="","",J18*Parametros!$B$13)) | V18: =IF($A18="","",IF(J18="","",J18*Parametros!$B$14)) | W18: =IF($A18="","",IF(J18="","",J18-T18-U18-V18)) | X18: =IF($A18="","",IF(J18="","",W18/J18)) | Y18: =IF($A18="","",IF(Parametros!$B$15>=1,"",T18/(1-Parametros!$B$15))) | Z18: =IF($A18="","",IF(Parametros!$B$15+Parametros!$B$16>=1,"",T18/(1-Parametros!$B$15-Parametros!$B$16))) | AA18: =IF($A18="","",IF(J18="","Falta precio",IF(W18<0,"PIERDE",IF(X18<Parametros!$B$16,"BAJO META","OK")))) | AB18: =IF($A18="","",IF(OR(C18="",D18=""),"Falta tela o consumo. ","")&IF(AND(C18<>"",M18=0),"Tela sin precio. ","")&IF(S18=0,"Confección sin valor. ","")&IF(J18="","Falta precio de venta. ",""))
M19: =IF($A19="","",IFERROR(D19*INDEX(Insumos!$D$6:$D$98,MATCH(C19,Insumos!$A$6:$A$98,0)),0)) | N19: =IF($A19="","",E19*Parametros!$H$21) | O19: =IF($A19="","",F19*Parametros!$H$22) | P19: =IF($A19="","",F19*Parametros!$B$17) | Q19: =IF($A19="","",D19*Parametros!$H$23) | R19: =IF($A19="","",H19*Parametros!$H$24) | S19: =IF($A19="","",IFERROR(INDEX(Confeccion!$B$5:$B$80,MATCH(G19,Confeccion!$A$5:$A$80,0)),0)) | T19: =IF($A19="","",SUM(M19:S19)+I19) | U19: =IF($A19="","",IF(J19="","",J19*Parametros!$B$13)) | V19: =IF($A19="","",IF(J19="","",J19*Parametros!$B$14)) | W19: =IF($A19="","",IF(J19="","",J19-T19-U19-V19)) | X19: =IF($A19="","",IF(J19="","",W19/J19)) | Y19: =IF($A19="","",IF(Parametros!$B$15>=1,"",T19/(1-Parametros!$B$15))) | Z19: =IF($A19="","",IF(Parametros!$B$15+Parametros!$B$16>=1,"",T19/(1-Parametros!$B$15-Parametros!$B$16))) | AA19: =IF($A19="","",IF(J19="","Falta precio",IF(W19<0,"PIERDE",IF(X19<Parametros!$B$16,"BAJO META","OK")))) | AB19: =IF($A19="","",IF(OR(C19="",D19=""),"Falta tela o consumo. ","")&IF(AND(C19<>"",M19=0),"Tela sin precio. ","")&IF(S19=0,"Confección sin valor. ","")&IF(J19="","Falta precio de venta. ",""))
M20: =IF($A20="","",IFERROR(D20*INDEX(Insumos!$D$6:$D$98,MATCH(C20,Insumos!$A$6:$A$98,0)),0)) | N20: =IF($A20="","",E20*Parametros!$H$21) | O20: =IF($A20="","",F20*Parametros!$H$22) | P20: =IF($A20="","",F20*Parametros!$B$17) | Q20: =IF($A20="","",D20*Parametros!$H$23) | R20: =IF($A20="","",H20*Parametros!$H$24) | S20: =IF($A20="","",IFERROR(INDEX(Confeccion!$B$5:$B$80,MATCH(G20,Confeccion!$A$5:$A$80,0)),0)) | T20: =IF($A20="","",SUM(M20:S20)+I20) | U20: =IF($A20="","",IF(J20="","",J20*Parametros!$B$13)) | V20: =IF($A20="","",IF(J20="","",J20*Parametros!$B$14)) | W20: =IF($A20="","",IF(J20="","",J20-T20-U20-V20)) | X20: =IF($A20="","",IF(J20="","",W20/J20)) | Y20: =IF($A20="","",IF(Parametros!$B$15>=1,"",T20/(1-Parametros!$B$15))) | Z20: =IF($A20="","",IF(Parametros!$B$15+Parametros!$B$16>=1,"",T20/(1-Parametros!$B$15-Parametros!$B$16))) | AA20: =IF($A20="","",IF(J20="","Falta precio",IF(W20<0,"PIERDE",IF(X20<Parametros!$B$16,"BAJO META","OK")))) | AB20: =IF($A20="","",IF(OR(C20="",D20=""),"Falta tela o consumo. ","")&IF(AND(C20<>"",M20=0),"Tela sin precio. ","")&IF(S20=0,"Confección sin valor. ","")&IF(J20="","Falta precio de venta. ",""))
M21: =IF($A21="","",IFERROR(D21*INDEX(Insumos!$D$6:$D$98,MATCH(C21,Insumos!$A$6:$A$98,0)),0)) | N21: =IF($A21="","",E21*Parametros!$H$21) | O21: =IF($A21="","",F21*Parametros!$H$22) | P21: =IF($A21="","",F21*Parametros!$B$17) | Q21: =IF($A21="","",D21*Parametros!$H$23) | R21: =IF($A21="","",H21*Parametros!$H$24) | S21: =IF($A21="","",IFERROR(INDEX(Confeccion!$B$5:$B$80,MATCH(G21,Confeccion!$A$5:$A$80,0)),0)) | T21: =IF($A21="","",SUM(M21:S21)+I21) | U21: =IF($A21="","",IF(J21="","",J21*Parametros!$B$13)) | V21: =IF($A21="","",IF(J21="","",J21*Parametros!$B$14)) | W21: =IF($A21="","",IF(J21="","",J21-T21-U21-V21)) | X21: =IF($A21="","",IF(J21="","",W21/J21)) | Y21: =IF($A21="","",IF(Parametros!$B$15>=1,"",T21/(1-Parametros!$B$15))) | Z21: =IF($A21="","",IF(Parametros!$B$15+Parametros!$B$16>=1,"",T21/(1-Parametros!$B$15-Parametros!$B$16))) | AA21: =IF($A21="","",IF(J21="","Falta precio",IF(W21<0,"PIERDE",IF(X21<Parametros!$B$16,"BAJO META","OK")))) | AB21: =IF($A21="","",IF(OR(C21="",D21=""),"Falta tela o consumo. ","")&IF(AND(C21<>"",M21=0),"Tela sin precio. ","")&IF(S21=0,"Confección sin valor. ","")&IF(J21="","Falta precio de venta. ",""))
M22: =IF($A22="","",IFERROR(D22*INDEX(Insumos!$D$6:$D$98,MATCH(C22,Insumos!$A$6:$A$98,0)),0)) | N22: =IF($A22="","",E22*Parametros!$H$21) | O22: =IF($A22="","",F22*Parametros!$H$22) | P22: =IF($A22="","",F22*Parametros!$B$17) | Q22: =IF($A22="","",D22*Parametros!$H$23) | R22: =IF($A22="","",H22*Parametros!$H$24) | S22: =IF($A22="","",IFERROR(INDEX(Confeccion!$B$5:$B$80,MATCH(G22,Confeccion!$A$5:$A$80,0)),0)) | T22: =IF($A22="","",SUM(M22:S22)+I22) | U22: =IF($A22="","",IF(J22="","",J22*Parametros!$B$13)) | V22: =IF($A22="","",IF(J22="","",J22*Parametros!$B$14)) | W22: =IF($A22="","",IF(J22="","",J22-T22-U22-V22)) | X22: =IF($A22="","",IF(J22="","",W22/J22)) | Y22: =IF($A22="","",IF(Parametros!$B$15>=1,"",T22/(1-Parametros!$B$15))) | Z22: =IF($A22="","",IF(Parametros!$B$15+Parametros!$B$16>=1,"",T22/(1-Parametros!$B$15-Parametros!$B$16))) | AA22: =IF($A22="","",IF(J22="","Falta precio",IF(W22<0,"PIERDE",IF(X22<Parametros!$B$16,"BAJO META","OK")))) | AB22: =IF($A22="","",IF(OR(C22="",D22=""),"Falta tela o consumo. ","")&IF(AND(C22<>"",M22=0),"Tela sin precio. ","")&IF(S22=0,"Confección sin valor. ","")&IF(J22="","Falta precio de venta. ",""))
M23: =IF($A23="","",IFERROR(D23*INDEX(Insumos!$D$6:$D$98,MATCH(C23,Insumos!$A$6:$A$98,0)),0)) | N23: =IF($A23="","",E23*Parametros!$H$21) | O23: =IF($A23="","",F23*Parametros!$H$22) | P23: =IF($A23="","",F23*Parametros!$B$17) | Q23: =IF($A23="","",D23*Parametros!$H$23) | R23: =IF($A23="","",H23*Parametros!$H$24) | S23: =IF($A23="","",IFERROR(INDEX(Confeccion!$B$5:$B$80,MATCH(G23,Confeccion!$A$5:$A$80,0)),0)) | T23: =IF($A23="","",SUM(M23:S23)+I23) | U23: =IF($A23="","",IF(J23="","",J23*Parametros!$B$13)) | V23: =IF($A23="","",IF(J23="","",J23*Parametros!$B$14)) | W23: =IF($A23="","",IF(J23="","",J23-T23-U23-V23)) | X23: =IF($A23="","",IF(J23="","",W23/J23)) | Y23: =IF($A23="","",IF(Parametros!$B$15>=1,"",T23/(1-Parametros!$B$15))) | Z23: =IF($A23="","",IF(Parametros!$B$15+Parametros!$B$16>=1,"",T23/(1-Parametros!$B$15-Parametros!$B$16))) | AA23: =IF($A23="","",IF(J23="","Falta precio",IF(W23<0,"PIERDE",IF(X23<Parametros!$B$16,"BAJO META","OK")))) | AB23: =IF($A23="","",IF(OR(C23="",D23=""),"Falta tela o consumo. ","")&IF(AND(C23<>"",M23=0),"Tela sin precio. ","")&IF(S23=0,"Confección sin valor. ","")&IF(J23="","Falta precio de venta. ",""))
M24: =IF($A24="","",IFERROR(D24*INDEX(Insumos!$D$6:$D$98,MATCH(C24,Insumos!$A$6:$A$98,0)),0)) | N24: =IF($A24="","",E24*Parametros!$H$21) | O24: =IF($A24="","",F24*Parametros!$H$22) | P24: =IF($A24="","",F24*Parametros!$B$17) | Q24: =IF($A24="","",D24*Parametros!$H$23) | R24: =IF($A24="","",H24*Parametros!$H$24) | S24: =IF($A24="","",IFERROR(INDEX(Confeccion!$B$5:$B$80,MATCH(G24,Confeccion!$A$5:$A$80,0)),0)) | T24: =IF($A24="","",SUM(M24:S24)+I24) | U24: =IF($A24="","",IF(J24="","",J24*Parametros!$B$13)) | V24: =IF($A24="","",IF(J24="","",J24*Parametros!$B$14)) | W24: =IF($A24="","",IF(J24="","",J24-T24-U24-V24)) | X24: =IF($A24="","",IF(J24="","",W24/J24)) | Y24: =IF($A24="","",IF(Parametros!$B$15>=1,"",T24/(1-Parametros!$B$15))) | Z24: =IF($A24="","",IF(Parametros!$B$15+Parametros!$B$16>=1,"",T24/(1-Parametros!$B$15-Parametros!$B$16))) | AA24: =IF($A24="","",IF(J24="","Falta precio",IF(W24<0,"PIERDE",IF(X24<Parametros!$B$16,"BAJO META","OK")))) | AB24: =IF($A24="","",IF(OR(C24="",D24=""),"Falta tela o consumo. ","")&IF(AND(C24<>"",M24=0),"Tela sin precio. ","")&IF(S24=0,"Confección sin valor. ","")&IF(J24="","Falta precio de venta. ",""))
M25: =IF($A25="","",IFERROR(D25*INDEX(Insumos!$D$6:$D$98,MATCH(C25,Insumos!$A$6:$A$98,0)),0)) | N25: =IF($A25="","",E25*Parametros!$H$21) | O25: =IF($A25="","",F25*Parametros!$H$22) | P25: =IF($A25="","",F25*Parametros!$B$17) | Q25: =IF($A25="","",D25*Parametros!$H$23) | R25: =IF($A25="","",H25*Parametros!$H$24) | S25: =IF($A25="","",IFERROR(INDEX(Confeccion!$B$5:$B$80,MATCH(G25,Confeccion!$A$5:$A$80,0)),0)) | T25: =IF($A25="","",SUM(M25:S25)+I25) | U25: =IF($A25="","",IF(J25="","",J25*Parametros!$B$13)) | V25: =IF($A25="","",IF(J25="","",J25*Parametros!$B$14)) | W25: =IF($A25="","",IF(J25="","",J25-T25-U25-V25)) | X25: =IF($A25="","",IF(J25="","",W25/J25)) | Y25: =IF($A25="","",IF(Parametros!$B$15>=1,"",T25/(1-Parametros!$B$15))) | Z25: =IF($A25="","",IF(Parametros!$B$15+Parametros!$B$16>=1,"",T25/(1-Parametros!$B$15-Parametros!$B$16))) | AA25: =IF($A25="","",IF(J25="","Falta precio",IF(W25<0,"PIERDE",IF(X25<Parametros!$B$16,"BAJO META","OK")))) | AB25: =IF($A25="","",IF(OR(C25="",D25=""),"Falta tela o consumo. ","")&IF(AND(C25<>"",M25=0),"Tela sin precio. ","")&IF(S25=0,"Confección sin valor. ","")&IF(J25="","Falta precio de venta. ",""))
M26: =IF($A26="","",IFERROR(D26*INDEX(Insumos!$D$6:$D$98,MATCH(C26,Insumos!$A$6:$A$98,0)),0)) | N26: =IF($A26="","",E26*Parametros!$H$21) | O26: =IF($A26="","",F26*Parametros!$H$22) | P26: =IF($A26="","",F26*Parametros!$B$17) | Q26: =IF($A26="","",D26*Parametros!$H$23) | R26: =IF($A26="","",H26*Parametros!$H$24) | S26: =IF($A26="","",IFERROR(INDEX(Confeccion!$B$5:$B$80,MATCH(G26,Confeccion!$A$5:$A$80,0)),0)) | T26: =IF($A26="","",SUM(M26:S26)+I26) | U26: =IF($A26="","",IF(J26="","",J26*Parametros!$B$13)) | V26: =IF($A26="","",IF(J26="","",J26*Parametros!$B$14)) | W26: =IF($A26="","",IF(J26="","",J26-T26-U26-V26)) | X26: =IF($A26="","",IF(J26="","",W26/J26)) | Y26: =IF($A26="","",IF(Parametros!$B$15>=1,"",T26/(1-Parametros!$B$15))) | Z26: =IF($A26="","",IF(Parametros!$B$15+Parametros!$B$16>=1,"",T26/(1-Parametros!$B$15-Parametros!$B$16))) | AA26: =IF($A26="","",IF(J26="","Falta precio",IF(W26<0,"PIERDE",IF(X26<Parametros!$B$16,"BAJO META","OK")))) | AB26: =IF($A26="","",IF(OR(C26="",D26=""),"Falta tela o consumo. ","")&IF(AND(C26<>"",M26=0),"Tela sin precio. ","")&IF(S26=0,"Confección sin valor. ","")&IF(J26="","Falta precio de venta. ",""))
... M205: =IF($A205="","",IFERROR(D205*INDEX(Insumos!$D$6:$D$98,MATCH(C205,Insumos!$A$6:$A$98,0)),0)) | N205: =IF($A205="","",E205*Parametros!$H$21) | O205: =IF($A205="","",F205*Parametros!$H$22) | P205: =IF($A205="","",F205*Parametros!$B$17) | Q205: =IF($A205="","",D205*Parametros!$H$23) | R205: =IF($A205="","",H205*Parametros!$H$24) | S205: =IF($A205="","",IFERROR(INDEX(Confeccion!$B$5:$B$80,MATCH(G205,Confeccion!$A$5:$A$80,0)),0)) | T205: =IF($A205="","",SUM(M205:S205)+I205) | U205: =IF($A205="","",IF(J205="","",J205*Parametros!$B$13)) | V205: =IF($A205="","",IF(J205="","",J205*Parametros!$B$14)) | W205: =IF($A205="","",IF(J205="","",J205-T205-U205-V205)) | X205: =IF($A205="","",IF(J205="","",W205/J205)) | Y205: =IF($A205="","",IF(Parametros!$B$15>=1,"",T205/(1-Parametros!$B$15))) | Z205: =IF($A205="","",IF(Parametros!$B$15+Parametros!$B$16>=1,"",T205/(1-Parametros!$B$15-Parametros!$B$16))) | AA205: =IF($A205="","",IF(J205="","Falta precio",IF(W205<0,"PIERDE",IF(X205<Parametros!$B$16,"BAJO META","OK")))) | AB205: =IF($A205="","",IF(OR(C205="",D205=""),"Falta tela o consumo. ","")&IF(AND(C205<>"",M205=0),"Tela sin precio. ","")&IF(S205=0,"Confección sin valor. ","")&IF(J205="","Falta precio de venta. ",""))

Sheet Parametros
A1: PARÁMETROS — recargo, meta de ganancia y costo de procesos
A2: Amarillo con letra azul = lo editas tú. Gris = se calcula solo. Verde = viene de otra hoja.
A4: 1) RECARGO POR GASTOS FIJOS Y COMERCIALES
A5: Concepto | B5: Valor | C5: Cómo se calcula
A6: Gastos de fábrica — promedio 3 meses | B6: =Gastos_Fijos!$F$38 | C6: Desde Gastos_Fijos
A7: Gastos comerciales — promedio 3 meses | B7: =Gastos_Fijos!$F$39 | C7: Desde Gastos_Fijos
A8: Ventas netas — promedio 3 meses | B8: =Gastos_Fijos!$F$42 | C8: Desde Gastos_Fijos
A9: Recargo de fábrica calculado | B9: =IFERROR(B6/B8,0) | C9: Gastos de fábrica ÷ ventas
A10: Recargo comercial calculado | B10: =IFERROR(B7/B8,0) | C10: Gastos comerciales ÷ ventas
A11: Recargo de fábrica manual (opcional) | C11: Déjalo vacío para usar el calculado. Escribe un % para fijarlo.
A12: Recargo comercial manual (opcional) | C12: Déjalo vacío para usar el calculado. Escribe un % para fijarlo.
A13: RECARGO DE FÁBRICA USADO | B13: =IF(ISNUMBER(B11),B11,B9) | C13: Es el que usan las recetas
A14: RECARGO COMERCIAL USADO | B14: =IF(ISNUMBER(B12),B12,B10) | C14: Es el que usan las recetas
A15: RECARGO TOTAL USADO | B15: =B13+B14 | C15: De cada $100 vendidos, este % se reserva para pagar los gastos
A16: Ganancia deseada | B16: 0.1 | C16: POR CONFIRMAR: meta de ganancia sobre el precio de venta (10% es un ejemplo)
A17: Tinta + papel de sublimación ($ por metro sublimado) | B17: 0 | C17: PENDIENTE: hoy no está en ningún costo. Ingresar cuando tengas el dato.
A19: 2) COSTO DE PROCESOS (sueldo ÷ horas ÷ operarios ÷ rendimiento)
A20: Proceso | B20: Sueldo mensual | C20: Horas/mes | D20: N° operarios | E20: Valor hora | F20: Rendimiento | G20: Unidad rend. | H20: COSTO | I20: Se cobra por | J20: Estado
A21: Ploteo | B21: =Gastos_Fijos!$F$6 | C21: 168 | D21: 3 | E21: =IFERROR(B21/C21/D21,0) | F21: 53.9 | G21: m/h | H21: =IFERROR(E21/F21,0) | I21: metro | J21: Por confirmar
A22: Sublimación | B22: =Gastos_Fijos!$F$7 | C22: 168 | D22: 1 | E22: =IFERROR(B22/C22/D22,0) | F22: 38.8 | G22: m/h | H22: =IFERROR(E22/F22,0) | I22: metro | J22: Por confirmar
A23: Corte | B23: =Gastos_Fijos!$F$8 | C23: 168 | D23: 2 | E23: =IFERROR(B23/C23/D23,0) | G23: kg/h | H23: 3943 | I23: kg de tela | J23: Por confirmar
A24: Estampado | B24: =Gastos_Fijos!$F$10 | C24: 168 | D24: 1 | E24: =IFERROR(B24/C24/D24,0) | F24: 48 | G24: prendas/h | H24: =IFERROR(E24/F24,0) | I24: prenda | J24: Por confirmar
A26: Corte: $3.943 por kg es un valor fijo del archivo original (no tenía rendimiento kg/h). Por confirmar.
A27: Rendimientos (m/h, prendas/h) vienen del archivo original: ploteo de 544 registros, sublimación de solo 3 proyectos, estampado de 1 observación.

Sheet Gastos_Fijos
A1: GASTOS FIJOS Y VENTAS — últimos 3 meses
A2: Cada trimestre: escribe los 3 meses más recientes (amarillo). El sistema promedia y recalcula el recargo solo.
A5: Concepto | B5: Grupo | C5: Jun-2026 | D5: Jul-2026 | E5: Ago-2026 | F5: Promedio 3 meses | G5: Nota
A6: Ploteo | B6: Fábrica | C6: 2400000 | D6: 2400000 | E6: 2400000 | F6: =AVERAGE(C6:E6) | G6: Sueldo del área (viene del archivo original)
A7: Sublimación | B7: Fábrica | C7: 833000 | D7: 833000 | E7: 833000 | F7: =AVERAGE(C7:E7) | G7: Sueldo del área (viene del archivo original)
A8: Corte | B8: Fábrica | C8: 1666000 | D8: 1666000 | E8: 1666000 | F8: =AVERAGE(C8:E8) | G8: Sueldo del área (viene del archivo original)
A9: Confección interna | B9: Fábrica | C9: 1105374 | D9: 1105374 | E9: 1105374 | F9: =AVERAGE(C9:E9) | G9: Sueldo del área (viene del archivo original)
A10: Estampado | B10: Fábrica | C10: 720000 | D10: 720000 | E10: 720000 | F10: =AVERAGE(C10:E10) | G10: Sueldo del área (viene del archivo original)
A11: Luz | B11: Fábrica | C11: 638049 | D11: 638049 | E11: 638049 | F11: =AVERAGE(C11:E11) | G11: Gasto de fábrica
A12: Agua | B12: Fábrica | C12: 10630 | D12: 10630 | E12: 10630 | F12: =AVERAGE(C12:E12) | G12: Gasto de fábrica
A13: Telefonía | B13: Fábrica | C13: 95000 | D13: 95000 | E13: 95000 | F13: =AVERAGE(C13:E13) | G13: Gasto de fábrica
A14: Arriendo | B14: Fábrica | C14: 2163844 | D14: 2163844 | E14: 2163844 | F14: =AVERAGE(C14:E14) | G14: Gasto de fábrica
A15: Internet | B15: Fábrica | C15: 49000 | D15: 49000 | E15: 49000 | F15: =AVERAGE(C15:E15) | G15: Gasto de fábrica
A16: Mantención de máquinas | B16: Fábrica | C16: 300000 | D16: 300000 | E16: 300000 | F16: =AVERAGE(C16:E16) | G16: Gasto de fábrica
A17: Seguridad | B17: Fábrica | C17: 50000 | D17: 50000 | E17: 50000 | F17: =AVERAGE(C17:E17) | G17: Gasto de fábrica
... A36: Descuento: sueldos ya cobrados dentro de las recetas (ingresar en negativo) | B36: Fábrica | C36: 0 | D36: 0 | E36: 0 | F36: =AVERAGE(C36:E36) | G36: Dejar en 0 salvo que quieras evitar contar dos veces parte del sueldo de ploteo/sublimación/corte
A38: TOTAL GASTOS DE FÁBRICA | C38: =SUMIF($B$6:$B$36,"Fábrica",C$6:C$36) | D38: =SUMIF($B$6:$B$36,"Fábrica",D$6:D$36) | E38: =SUMIF($B$6:$B$36,"Fábrica",E$6:E$36) | F38: =SUMIF($B$6:$B$36,"Fábrica",F$6:F$36)
A39: TOTAL GASTOS COMERCIALES | C39: =SUMIF($B$6:$B$36,"Comercial",C$6:C$36) | D39: =SUMIF($B$6:$B$36,"Comercial",D$6:D$36) | E39: =SUMIF($B$6:$B$36,"Comercial",E$6:E$36) | F39: =SUMIF($B$6:$B$36,"Comercial",F$6:F$36)
A40: TOTAL GASTOS FIJOS | C40: =C38+C39 | D40: =D38+D39 | E40: =E38+E39 | F40: =F38+F39
A42: VENTAS NETAS DEL MES ($) | C42: 32768213 | D42: 38874120 | E42: 33942186 | F42: =AVERAGE(C42:E42) | G42: Fuente: hoja Proyectos_PMK del archivo original (suma Neto $ jun, jul, ago 2026)
A44: POR CONFIRMAR: los 3 meses de gastos tienen el mismo monto (el archivo original solo trae un mes). Reemplazar con el gasto real de cada mes.
A45: Grupo "Fábrica" = cuesta producir (arriendo, luz, sueldos de producción). Grupo "Comercial" = ventas y marketing. Puedes cambiar el grupo de cualquier línea.
A46: Los sueldos de ploteo/sublimación/corte/estampado están en "Fábrica": las recetas cobran solo el tiempo usado, el resto del sueldo sigue siendo costo de la empresa.

Sheet Insumos
A1: INSUMOS — precios netos (sin IVA)
A2: Cambiar un precio aquí actualiza todas las recetas. Cuando verifiques un precio, cambia el estado a "Confirmado".
A5: Insumo | B5: Tipo | C5: Unidad | D5: Precio neto ($) | E5: Estado | F5: Nota
A6: MONTESIMONE TRAINING (fut pro) | B6: Tela | C6: kg | D6: 3531 | E6: Por confirmar
A7: LONDRES BLANCO | B7: Tela | C7: kg | D7: 5600 | E7: Por confirmar
A8: CIRE BLANCO | B8: Tela | C8: kg | D8: 5600 | E8: Por confirmar
A9: CIRE AZUL | B9: Tela | C9: kg | D9: 7500 | E9: Por confirmar
A10: MESH | B10: Tela | C10: kg | D10: 7700 | E10: Por confirmar
A11: FRANELA | B11: Tela | C11: kg | D11: 8000 | E11: Por confirmar
A12: PIQUE SELECCION | B12: Tela | C12: kg | D12: 7800 | E12: Por confirmar
A13: MICROFIBRA | B13: Tela | C13: kg | D13: 6900 | E13: Por confirmar
A14: CIRE MICROFIBRA AZUL REY | B14: Tela | C14: kg | D14: 7200 | E14: Por confirmar
A15: SCUBA | B15: Tela | C15: kg | D15: 7900 | E15: Por confirmar
A16: GLOBAL | B16: Tela | C16: kg | D16: 6800 | E16: Por confirmar
A17: PIQUE RUGBY | B17: Tela | C17: kg | D17: 5600 | E17: Por confirmar
... A34: JACQUARD BYTES | B34: Tela | C34: kg | D34: 4408 | E34: Por confirmar
A35: LYCRA | B35: Tela | C35: kg | E35: PENDIENTE
A36: Insumo | B36: Consumible | C36: Unidad | E36: PENDIENTE
A37: ETIQUETAS | B37: Consumible | C37: kg | D37: 63.343669 | E37: Por confirmar | F37: Unidad dudosa (kg): confirmar si es por kg o por unidad
A38: PUÑO ELASTICO | B38: Consumible | C38: kg | D38: 8500 | E38: Por confirmar | F38: Unidad dudosa (kg): confirmar si es por kg o por unidad
A39: MEDIAS PERSONALIZADAS | B39: Consumible | C39: kg | D39: 4000 | E39: Por confirmar | F39: Unidad dudosa (kg): confirmar si es por kg o por unidad
A40: MEDIAS BASICAS | B40: Consumible | C40: kg | D40: 2500 | E40: Por confirmar | F40: Unidad dudosa (kg): confirmar si es por kg o por unidad
A41: MALLA DEPORTIVA BLANCO | B41: Consumible | C41: kg | D41: 6400 | E41: Por confirmar
A42: NOVAK | B42: Consumible | C42: kg | D42: 2975 | E42: Por confirmar
A43: THERMAFLEECE | B43: Consumible | C43: kg | D43: 8590 | E43: Por confirmar
A44: TINTAS MAGENTA | B44: Consumible | C44: litro | D44: 72119 | E44: Por confirmar
A45: FLUSHING LIQUID | B45: Consumible | C45: kg | D45: 45000 | E45: Por confirmar
A46: PAPEL PROTECT KRAFT | B46: Consumible | C46: kg | D46: 100840 | E46: Por confirmar
A47: PAPEL SUBLIMACION | B47: Consumible | C47: kg | D47: 50420 | E47: Por confirmar
A48: PAPEL DE PROTECCION KRAFT | B48: Consumible | C48: kg | D48: 94500 | E48: Por confirmar
A49: Cuello | B49: Avío | C49: unidad | D49: 350 | E49: Por confirmar | F49: Era "estimado" en el archivo original
A50: Puño | B50: Avío | C50: unidad | D50: 8500 | E50: Por confirmar
A51: Tapacuello | B51: Avío | C51: unidad | D51: 150 | E51: Por confirmar | F51: Era "estimado" en el archivo original
A52: Hilo | B52: Avío | C52: unidad | D52: 80 | E52: Por confirmar | F52: Era "estimado" en el archivo original
A53: Etiqueta | B53: Avío | C53: unidad | D53: 65 | E53: Por confirmar
A54: Cierre | B54: Avío | C54: unidad | D54: 600 | E54: Por confirmar | F54: Era "estimado" en el archivo original
A55: Cordón | B55: Avío | C55: unidad | D55: 200 | E55: Por confirmar | F55: Era "estimado" en el archivo original
A56: Elástico | B56: Avío | C56: unidad | D56: 5454 | E56: Por confirmar
A57: Forro | B57: Avío | C57: unidad | D57: 900 | E57: Por confirmar | F57: Era "estimado" en el archivo original
A58: Cremallera bolsillo | B58: Avío | C58: unidad | D58: 400 | E58: Por confirmar | F58: Era "estimado" en el archivo original

Sheet Confeccion
A1: CONFECCIÓN — valor por prenda pagado a taller (neto, con planchado)
A2: Se paga por prenda terminada. Agrega nuevos tipos de prenda al final de la lista.
A4: Tipo de prenda | B4: Valor con planchado ($) | C4: Sin planchado (ref.) | D4: Estado
A5: Short De Futbol | B5: 1700 | C5: 1500 | D5: Por confirmar
A6: Camiseta De Futbol | B6: 2000 | C6: 1800 | D6: Por confirmar
A7: Camiseta De Futbol Retro | B7: 2200 | C7: 1900 | D7: Por confirmar
A8: Camiseta De Basket | B8: 1900 | C8: 1700 | D8: Por confirmar
A9: Camiseta De Basket Pro | B9: 2000 | C9: 1800 | D9: Por confirmar
A10: Short De Basket Pro | B10: 2200 | C10: 1700 | D10: Por confirmar
A11: Short De Basket | B11: 1900 | C11: 1700 | D11: Por confirmar
A12: Short De Basket Reversible | B12: 2400 | C12: 2000 | D12: Por confirmar
A13: Camiseta De Basket Reversible | B13: 2400 | C13: 2200 | D13: Por confirmar
A14: Camiseta De Rugby Básica | B14: 2200 | C14: 2000 | D14: Por confirmar
A15: Camiseta De Rugby Lycra | B15: 2600 | C15: 2300 | D15: Por confirmar
A16: Short De Rugby | B16: 2200 | C16: 2300 | D16: Por confirmar
... A50: Colett | B50: 500 | C50: 500 | D50: Por confirmar

Sheet Catalogo
A1: CATÁLOGO — qué productos ya tienen receta
A2: Ordenado por unidades vendidas (jun–sep 2026). Haz las recetas de arriba hacia abajo.
A3: ="Con receta: "&COUNTIF(F5:F142,"Sí")&" de "&COUNTA(A5:A142)&" productos · "&TEXT(SUMIF(F5:F142,"Sí",C5:C142)/SUM(C5:C142),"0%")&" de las unidades vendidas"
A4: Producto | B4: Tipo | C4: Unidades vendidas | D4: Venta neta ($) | E4: Precio real promedio ($) | F4: ¿Tiene receta?
A5: Dúo Pack Diamante Fútbol | B5: KIT/DÚO | C5: 496 | D5: 12634203 | E5: 26379 | F5: =IF(COUNTIF(Recetas!$A$6:$A$205,A5)>0,"Sí","falta")
A6: Escudo en DTF10cm | B6: ADICIONAL | C6: 387 | D6: 810449 | E6: 2094 | F6: =IF(COUNTIF(Recetas!$A$6:$A$205,A6)>0,"Sí","falta")
A7: Kit Oro Fútbol | B7: KIT/DÚO | C7: 214 | D7: 6158556 | E7: 29580 | F7: =IF(COUNTIF(Recetas!$A$6:$A$205,A7)>0,"Sí","falta")
A8: Escudo Texturizado10cm | B8: ADICIONAL | C8: 214 | D8: 570554 | E8: 2941 | F8: =IF(COUNTIF(Recetas!$A$6:$A$205,A8)>0,"Sí","falta")
A9: Medias Pro Personalizadas PMK | B9: EXTERNO/REVENTA | C9: 209 | D9: 1903429 | E9: 9734 | F9: =IF(COUNTIF(Recetas!$A$6:$A$205,A9)>0,"Sí","falta")
A10: ESCUDO PRO 10CM | B10: ADICIONAL | C10: 207 | D10: 608787 | E10: 2941 | F10: =IF(COUNTIF(Recetas!$A$6:$A$205,A10)>0,"Sí","falta")
A11: Camiseta Fútbol Playmaker, m/c | B11: JUEGO/COMPETENCIA | C11: 198 | D11: 3166996 | E11: 15994 | F11: =IF(COUNTIF(Recetas!$A$6:$A$205,A11)>0,"Sí","falta")
A12: Camiseta Fútbol Playmaker Cuello Redondo m/c | B12: JUEGO/COMPETENCIA | C12: 190 | D12: 3023801 | E12: 16073 | F12: =IF(COUNTIF(Recetas!$A$6:$A$205,A12)>0,"Sí","falta")
A13: EXTRA CUELLO PIQUÉ | B13: ADICIONAL | C13: 161 | D13: 357100 | E13: 2521 | F13: =IF(COUNTIF(Recetas!$A$6:$A$205,A13)>0,"Sí","falta")
A14: Camiseta Fútbol Pro Playmaker Cuello Redondo m/c | B14: JUEGO/COMPETENCIA | C14: 160 | D14: 2907674 | E14: 18403 | F14: =IF(COUNTIF(Recetas!$A$6:$A$205,A14)>0,"Sí","falta")
A15: Kit Diamante Fútbol | B15: KIT/DÚO | C15: 148 | D15: 4786004 | E15: 38898 | F15: =IF(COUNTIF(Recetas!$A$6:$A$205,A15)>0,"Sí","falta")
A16: Camiseta Voley fem Playmaker, V m/c | B16: JUEGO/COMPETENCIA | C16: 139 | D16: 2336461 | E16: 17563 | F16: =IF(COUNTIF(Recetas!$A$6:$A$205,A16)>0,"Sí","falta")
... A114: Camiseta Voley fem Playmaker, Polo | B114: JUEGO/COMPETENCIA | C114: 9 | D114: 153023 | E114: 17143 | F114: =IF(COUNTIF(Recetas!$A$6:$A$205,A114)>0,"Sí","falta")
A115: Bolso Sublimado Personalizado PMK de Regalo | B115: EXTERNO/REVENTA | C115: 8 | D115: 0 | F115: =IF(COUNTIF(Recetas!$A$6:$A$205,A115)>0,"Sí","falta")
A116: EXTRA TALLA ESPECIAL | B116: ADICIONAL | C116: 8 | D116: 9242 | E116: 1260 | F116: =IF(COUNTIF(Recetas!$A$6:$A$205,A116)>0,"Sí","falta")
A117: POLERON DE ENTRENAMIENTO SUBLIMADO MEDIO CIERRE | B117: SALIDA/PRESENTACIÓN | C117: 6 | D117: 196302 | E117: 32731 | F117: =IF(COUNTIF(Recetas!$A$6:$A$205,A117)>0,"Sí","falta")
A118: Polera Playmaker, V m/c | B118: JUEGO/COMPETENCIA | C118: 6 | D118: 100338 | E118: 16723 | F118: =IF(COUNTIF(Recetas!$A$6:$A$205,A118)>0,"Sí","falta")
A119: Camiseta de entrenamiento Rugby,m/c | B119: JUEGO/COMPETENCIA | C119: 5 | D119: 79410 | E119: 15882 | F119: =IF(COUNTIF(Recetas!$A$6:$A$205,A119)>0,"Sí","falta")
A120: DESPACHO | B120: JUEGO/COMPETENCIA | C120: 5 | D120: 89679 | E120: 13622 | F120: =IF(COUNTIF(Recetas!$A$6:$A$205,A120)>0,"Sí","falta")
A121: BALON DE FUTBOL | B121: EXTERNO/REVENTA | C121: 5 | D121: 147060 | E121: 29412 | F121: =IF(COUNTIF(Recetas!$A$6:$A$205,A121)>0,"Sí","falta")
A122: Camiseta Playmaker Running manga/L | B122: JUEGO/COMPETENCIA | C122: 5 | D122: 92015 | E122: 18403 | F122: =IF(COUNTIF(Recetas!$A$6:$A$205,A122)>0,"Sí","falta")
A123: Calza corta fem Playmaker | B123: JUEGO/COMPETENCIA | C123: 4 | D123: 50588 | E123: 12689 | F123: =IF(COUNTIF(Recetas!$A$6:$A$205,A123)>0,"Sí","falta")
A124: PARKA LISA PLAYMAKER BOSTON WEB | B124: SALIDA/PRESENTACIÓN | C124: 4 | D124: 151260 | E124: 50420 | F124: =IF(COUNTIF(Recetas!$A$6:$A$205,A124)>0,"Sí","falta")
A125: Short Salida con bolsillos | B125: SALIDA/PRESENTACIÓN | C125: 4 | D125: 53780 | E125: 13445 | F125: =IF(COUNTIF(Recetas!$A$6:$A$205,A125)>0,"Sí","falta")
A126: POLERON DE ENTRENAMIENTO MANGAS SUBLIMADAS MASC | B126: SALIDA/PRESENTACIÓN | C126: 4 | D126: 120672 | E126: 30168 | F126: =IF(COUNTIF(Recetas!$A$6:$A$205,A126)>0,"Sí","falta")
A127: BOLSO SUBLIMADO PERSONALIZADO | B127: EXTERNO/REVENTA | C127: 3 | D127: 42016 | E127: 21008 | F127: =IF(COUNTIF(Recetas!$A$6:$A$205,A127)>0,"Sí","falta")
... A134: MEDIAS PRO RUGBY | B134: EXTERNO/REVENTA | C134: 2 | D134: 22186 | E134: 11093 | F134: =IF(COUNTIF(Recetas!$A$6:$A$205,A134)>0,"Sí","falta")
A135: GUANTES ARQUERO | B135: JUEGO/COMPETENCIA | C135: 2 | D135: 0 | F135: =IF(COUNTIF(Recetas!$A$6:$A$205,A135)>0,"Sí","falta")
A136: Exrta Manga Larga | B136: JUEGO/COMPETENCIA | C136: 2 | D136: 3362 | E136: 1681 | F136: =IF(COUNTIF(Recetas!$A$6:$A$205,A136)>0,"Sí","falta")
A137: Lienzo 1.5x2mts Regalo | B137: JUEGO/COMPETENCIA | C137: 1 | D137: 0 | F137: =IF(COUNTIF(Recetas!$A$6:$A$205,A137)>0,"Sí","falta")
A138: Camiseta Voley masc Pro Playmaker, V m/c | B138: JUEGO/COMPETENCIA | C138: 1 | D138: 19244 | E138: 19244 | F138: =IF(COUNTIF(Recetas!$A$6:$A$205,A138)>0,"Sí","falta")
A139: Camiseta Rugby Playmaker, Polo | B139: JUEGO/COMPETENCIA | C139: 1 | D139: 20084 | E139: 20084 | F139: =IF(COUNTIF(Recetas!$A$6:$A$205,A139)>0,"Sí","falta")
A140: Lienzo 1.5x2 | B140: JUEGO/COMPETENCIA | C140: 1 | D140: 21765 | E140: 21765 | F140: =IF(COUNTIF(Recetas!$A$6:$A$205,A140)>0,"Sí","falta")
A141: Jineta de Capitán Subl | B141: JUEGO/COMPETENCIA | C141: 1 | D141: 11681 | E141: 11681 | F141: =IF(COUNTIF(Recetas!$A$6:$A$205,A141)>0,"Sí","falta")
A142: POLERÓN ALGODÓN CON CAPUCHA PMK | B142: SALIDA/PRESENTACIÓN | C142: 1 | D142: 21765 | E142: 21765 | F142: =IF(COUNTIF(Recetas!$A$6:$A$205,A142)>0,"Sí","falta")
