Workbook

Sheet Proyección
A1: PREVENTA OFICIAL GAUCHOS — PROYECCIÓN DE ROYALTY PARA EL CLUB
A2: Escribe en las celdas amarillas cuántas unidades se venderían de cada producto en la temporada. El resto se calcula solo. Valores en pesos chilenos.
A4: Código | B4: Producto | C4: Precio socio (con IVA) | D4: Precio neto (sin IVA) | E4: Unidades proyectadas | F4: Venta neta | H4: PARÁMETROS
A5: GAU-01 | B5: Camiseta de juego — Local OP1 | C5: 29900 | D5: =ROUND(C5/(1+$I$5),0) -> 25126 | E5: 10 | F5: =D5*E5 -> 251260 | H5: IVA | I5: 0.19
A6: GAU-02 | B6: Camiseta de juego — Local 02 | C6: 29900 | D6: =ROUND(C6/(1+$I$5),0) -> 25126 | E6: 10 | F6: =D6*E6 -> 251260 | H6: Bono si el royalty se recibe en productos | I6: 0.3
A7: GAU-03 | B7: Camiseta de juego — Visita 01 | C7: 29900 | D7: =ROUND(C7/(1+$I$5),0) -> 25126 | E7: 10 | F7: =D7*E7 -> 251260
A8: GAU-04 | B8: Camiseta de juego — Visita 02 | C8: 29900 | D8: =ROUND(C8/(1+$I$5),0) -> 25126 | E8: 10 | F8: =D8*E8 -> 251260 | H8: TRAMOS DE ROYALTY
A9: GAU-05 | B9: Short de juego | C9: 19900 | D9: =ROUND(C9/(1+$I$5),0) -> 16723 | E9: 10 | F9: =D9*E9 -> 167230 | H9: Unidades en la temporada | I9: Royalty | J9: Desde
A10: GAU-06 | B10: Medias de juego | C10: 10900 | D10: =ROUND(C10/(1+$I$5),0) -> 9160 | E10: 10 | F10: =D10*E10 -> 91600 | H10: Hasta 100 | I10: 0.11 | J10: 0
A11: GAU-07 | B11: Match Day Shirt | C11: 21900 | D11: =ROUND(C11/(1+$I$5),0) -> 18403 | E11: 10 | F11: =D11*E11 -> 184030 | H11: 101 a 200 | I11: 0.12 | J11: 101
A12: GAU-08 | B12: Camiseta de entrenamiento | C12: 22900 | D12: =ROUND(C12/(1+$I$5),0) -> 19244 | E12: 10 | F12: =D12*E12 -> 192440 | H12: 201 a 350 | I12: 0.13 | J12: 201
A13: GAU-09 | B13: Polerón medio cierre | C13: 34900 | D13: =ROUND(C13/(1+$I$5),0) -> 29328 | E13: 10 | F13: =D13*E13 -> 293280 | H13: 351 a 500 | I13: 0.14 | J13: 351
A14: GAU-10 | B14: Buzo de contacto manga larga | C14: 28900 | D14: =ROUND(C14/(1+$I$5),0) -> 24286 | E14: 10 | F14: =D14*E14 -> 242860 | H14: Más de 500 | I14: 0.15 | J14: 501
A15: GAU-11 | B15: Camiseta sin mangas | C15: 21900 | D15: =ROUND(C15/(1+$I$5),0) -> 18403 | E15: 10 | F15: =D15*E15 -> 184030 | H15: El tramo alcanzado se aplica a todas las unidades de la temporada. Si cambias un límite, ajusta también su columna Desde.
A16: GAU-12 | B16: Short tipo básquet | C16: 19900 | D16: =ROUND(C16/(1+$I$5),0) -> 16723 | E16: 10 | F16: =D16*E16 -> 167230
A17: GAU-13 | B17: Polo piqué | C17: 23900 | D17: =ROUND(C17/(1+$I$5),0) -> 20084 | E17: 10 | F17: =D17*E17 -> 200840 | H17: RESULTADO DE LA TEMPORADA
A18: GAU-14 | B18: Chaqueta cierre completo | C18: 37900 | D18: =ROUND(C18/(1+$I$5),0) -> 31849 | E18: 10 | F18: =D18*E18 -> 318490 | H18: Unidades vendidas | I18: =E27 -> 220
A19: GAU-15 | B19: Cortaviento con capucha | C19: 40900 | D19: =ROUND(C19/(1+$I$5),0) -> 34370 | E19: 10 | F19: =D19*E19 -> 343700 | H19: Venta total a socios (con IVA) | I19: =SUMPRODUCT(C5:C26,E5:E26) -> 6518000
A20: GAU-16 | B20: Polerón cuello redondo | C20: 22900 | D20: =ROUND(C20/(1+$I$5),0) -> 19244 | E20: 10 | F20: =D20*E20 -> 192440 | H20: Venta neta (sin IVA) | I20: =F27 -> 5477330
A21: GAU-17 | B21: Hoodie | C21: 31900 | D21: =ROUND(C21/(1+$I$5),0) -> 26807 | E21: 10 | F21: =D21*E21 -> 268070 | H21: Tramo alcanzado | I21: =IF(I18=0,0,INDEX($I$10:$I$14,MATCH(I18,$J$10:$J$14,1))) -> 0.13
A22: GAU-18 | B22: Chaqueta varsity | C22: 47900 | D22: =ROUND(C22/(1+$I$5),0) -> 40252 | E22: 10 | F22: =D22*E22 -> 402520 | H22: Royalty para el club (efectivo) | I22: =ROUND(I20*I21,0) -> 712053
A23: GAU-19 | B23: Polera de algodón | C23: 17900 | D23: =ROUND(C23/(1+$I$5),0) -> 15042 | E23: 10 | F23: =D23*E23 -> 150420 | H23: Royalty si se recibe en productos | I23: =ROUND(I22*(1+I6),0) -> 925669
A24: GAU-20 | B24: Bermuda deportiva | C24: 21900 | D24: =ROUND(C24/(1+$I$5),0) -> 18403 | E24: 10 | F24: =D24*E24 -> 184030 | H24: Royalty promedio por unidad | I24: =IF(I18=0,0,ROUND(I22/I18,0)) -> 3237
A25: GAU-21 | B25: Pantalón pitillo | C25: 25900 | D25: =ROUND(C25/(1+$I$5),0) -> 21765 | E25: 10 | F25: =D25*E25 -> 217650
A26: GAU-22 | B26: Parka larga | C26: 79900 | D26: =ROUND(C26/(1+$I$5),0) -> 67143 | E26: 10 | F26: =D26*E26 -> 671430
B27: TOTAL | E27: =SUM(E5:E26) -> 220 | F27: =SUM(F5:F26) -> 5477330

Sheet Escenarios
A1: ESCENARIOS: ¿CUÁNTO RECIBE EL CLUB SEGÚN LO QUE SE VENDA?
A2: Royalty de la temporada según el total de unidades vendidas a socios. Usa el precio neto promedio de la hoja Proyección (ponderado por las unidades que escribiste ahí).
A4: Precio neto promedio por unidad | D4: =IF(Proyección!I18>0,Proyección!I20/Proyección!I18,AVERAGE(Proyección!D5:D26)) -> 24896.955
A5: Precio promedio con IVA | D5: =IF(Proyección!I18>0,Proyección!I19/Proyección!I18,AVERAGE(Proyección!C5:C26)) -> 29627.273
A7: Unidades vendidas en la temporada | B7: Tramo | C7: Venta a socios (con IVA) | D7: Venta neta (sin IVA) | E7: Royalty para el club (efectivo) | F7: Royalty si se recibe en productos (+bono) | G7: Royalty promedio por unidad
A8: 50 | B8: =IF(A8=0,0,INDEX(Proyección!$I$10:$I$14,MATCH(A8,Proyección!$J$10:$J$14,1))) -> 0.11 | C8: =ROUND(A8*$D$5,0) -> 1481364 | D8: =ROUND(A8*$D$4,0) -> 1244848 | E8: =ROUND(D8*B8,0) -> 136933 | F8: =ROUND(E8*(1+Proyección!$I$6),0) -> 178013 | G8: =IF(A8=0,0,ROUND(E8/A8,0)) -> 2739
A9: 100 | B9: =IF(A9=0,0,INDEX(Proyección!$I$10:$I$14,MATCH(A9,Proyección!$J$10:$J$14,1))) -> 0.11 | C9: =ROUND(A9*$D$5,0) -> 2962727 | D9: =ROUND(A9*$D$4,0) -> 2489695 | E9: =ROUND(D9*B9,0) -> 273866 | F9: =ROUND(E9*(1+Proyección!$I$6),0) -> 356026 | G9: =IF(A9=0,0,ROUND(E9/A9,0)) -> 2739
A10: 150 | B10: =IF(A10=0,0,INDEX(Proyección!$I$10:$I$14,MATCH(A10,Proyección!$J$10:$J$14,1))) -> 0.12 | C10: =ROUND(A10*$D$5,0) -> 4444091 | D10: =ROUND(A10*$D$4,0) -> 3734543 | E10: =ROUND(D10*B10,0) -> 448145 | F10: =ROUND(E10*(1+Proyección!$I$6),0) -> 582589 | G10: =IF(A10=0,0,ROUND(E10/A10,0)) -> 2988
A11: 200 | B11: =IF(A11=0,0,INDEX(Proyección!$I$10:$I$14,MATCH(A11,Proyección!$J$10:$J$14,1))) -> 0.12 | C11: =ROUND(A11*$D$5,0) -> 5925455 | D11: =ROUND(A11*$D$4,0) -> 4979391 | E11: =ROUND(D11*B11,0) -> 597527 | F11: =ROUND(E11*(1+Proyección!$I$6),0) -> 776785 | G11: =IF(A11=0,0,ROUND(E11/A11,0)) -> 2988
A12: 250 | B12: =IF(A12=0,0,INDEX(Proyección!$I$10:$I$14,MATCH(A12,Proyección!$J$10:$J$14,1))) -> 0.13 | C12: =ROUND(A12*$D$5,0) -> 7406818 | D12: =ROUND(A12*$D$4,0) -> 6224239 | E12: =ROUND(D12*B12,0) -> 809151 | F12: =ROUND(E12*(1+Proyección!$I$6),0) -> 1051896 | G12: =IF(A12=0,0,ROUND(E12/A12,0)) -> 3237
A13: 300 | B13: =IF(A13=0,0,INDEX(Proyección!$I$10:$I$14,MATCH(A13,Proyección!$J$10:$J$14,1))) -> 0.13 | C13: =ROUND(A13*$D$5,0) -> 8888182 | D13: =ROUND(A13*$D$4,0) -> 7469086 | E13: =ROUND(D13*B13,0) -> 970981 | F13: =ROUND(E13*(1+Proyección!$I$6),0) -> 1262275 | G13: =IF(A13=0,0,ROUND(E13/A13,0)) -> 3237
A14: 350 | B14: =IF(A14=0,0,INDEX(Proyección!$I$10:$I$14,MATCH(A14,Proyección!$J$10:$J$14,1))) -> 0.13 | C14: =ROUND(A14*$D$5,0) -> 10369545 | D14: =ROUND(A14*$D$4,0) -> 8713934 | E14: =ROUND(D14*B14,0) -> 1132811 | F14: =ROUND(E14*(1+Proyección!$I$6),0) -> 1472654 | G14: =IF(A14=0,0,ROUND(E14/A14,0)) -> 3237
A15: 400 | B15: =IF(A15=0,0,INDEX(Proyección!$I$10:$I$14,MATCH(A15,Proyección!$J$10:$J$14,1))) -> 0.14 | C15: =ROUND(A15*$D$5,0) -> 11850909 | D15: =ROUND(A15*$D$4,0) -> 9958782 | E15: =ROUND(D15*B15,0) -> 1394229 | F15: =ROUND(E15*(1+Proyección!$I$6),0) -> 1812498 | G15: =IF(A15=0,0,ROUND(E15/A15,0)) -> 3486
A16: 500 | B16: =IF(A16=0,0,INDEX(Proyección!$I$10:$I$14,MATCH(A16,Proyección!$J$10:$J$14,1))) -> 0.14 | C16: =ROUND(A16*$D$5,0) -> 14813636 | D16: =ROUND(A16*$D$4,0) -> 12448477 | E16: =ROUND(D16*B16,0) -> 1742787 | F16: =ROUND(E16*(1+Proyección!$I$6),0) -> 2265623 | G16: =IF(A16=0,0,ROUND(E16/A16,0)) -> 3486
A17: 600 | B17: =IF(A17=0,0,INDEX(Proyección!$I$10:$I$14,MATCH(A17,Proyección!$J$10:$J$14,1))) -> 0.15 | C17: =ROUND(A17*$D$5,0) -> 17776364 | D17: =ROUND(A17*$D$4,0) -> 14938173 | E17: =ROUND(D17*B17,0) -> 2240726 | F17: =ROUND(E17*(1+Proyección!$I$6),0) -> 2912944 | G17: =IF(A17=0,0,ROUND(E17/A17,0)) -> 3735
A18: 750 | B18: =IF(A18=0,0,INDEX(Proyección!$I$10:$I$14,MATCH(A18,Proyección!$J$10:$J$14,1))) -> 0.15 | C18: =ROUND(A18*$D$5,0) -> 22220455 | D18: =ROUND(A18*$D$4,0) -> 18672716 | E18: =ROUND(D18*B18,0) -> 2800907 | F18: =ROUND(E18*(1+Proyección!$I$6),0) -> 3641179 | G18: =IF(A18=0,0,ROUND(E18/A18,0)) -> 3735
A19: 1000 | B19: =IF(A19=0,0,INDEX(Proyección!$I$10:$I$14,MATCH(A19,Proyección!$J$10:$J$14,1))) -> 0.15 | C19: =ROUND(A19*$D$5,0) -> 29627273 | D19: =ROUND(A19*$D$4,0) -> 24896955 | E19: =ROUND(D19*B19,0) -> 3734543 | F19: =ROUND(E19*(1+Proyección!$I$6),0) -> 4854906 | G19: =IF(A19=0,0,ROUND(E19/A19,0)) -> 3735
A21: CÓMO FUNCIONAN LOS TRAMOS
A22: 1. Se suman las unidades vendidas a socios en toda la temporada (todas las preventas juntas).
A23: 2. Ese total define el tramo: hasta 100 unidades 11%, de 101 a 200 12%, de 201 a 350 13%, de 351 a 500 14% y más de 500 15%.
A24: 3. El porcentaje del tramo alcanzado se aplica a TODAS las unidades de la temporada, no solo a las que superan el límite.
A25: 4. El royalty se calcula sobre la venta neta (sin IVA y sin devoluciones). Si el club lo recibe en productos, se suma el bono.
A26: Ejemplo: con 220 unidades la temporada queda en el tramo de 13%, y ese 13% se aplica a las 220.
